Workbook
Name _Hlk211416489: 'RELACION DE PAGOS EMITIDOS'!#REF!

Sheet RELACION DE PAGOS EMITIDOS
A5: DIRECCION DE FISCALIZACION Y CONTROL
A6: RELACION DE PAGOS EMITIDOS DURANTE EL MES DE NOVIEMBRE 2025
A7: ESTABLECIMIENTO: HOSPITAL MATERNO INFANTIL SAN LORENZO DE LOS MINA
A9: PAGOS CORRESPONDIENTES AL MES : NOVIEMBRE 2025
A10: FECHA | B10: LIBRAMIENTO | C10: TRANSFERENCIA | D10: CHEQUE | E10: BENEFICIARIO | F10: NO.FACTURAS | G10: VALOR DE FACTURA | H10: VALOR PAGADO
A11: 45964 | C11: 372 | E11: P&D RECYCLING SRL | F11: PAGO NCF B1500000320 SERVICIO DE RECOGIDA DE DESECHOS BIOMEDICOS SEGÚN O/C HSLM-2025-01044. | G11: 720000 | H11: 684000
A12: 45965 | C12: 373 | E12: CARLOS RAFAEL DE PAULA ROSSO | F12: PAGO NCF B1500000071 REPARACION DE CUARTO FRIO AREA DE COCINA DE 4 TONELADAS SEGÚN O/C HSLM-2025-01099 | G12: 361378.54 | H12: 346065.89
A13: 45967 | C13: 379 | E13: LUZ ESTHER BATISTA PEREZ | F13: PAGO NCF B1500001309, ADQUISICION DE FUNDAS PLASTICAS SEGÚN O/C HSLM-2025-01031. | G13: 158061 | H13: 151363.5
A14: 45974 | C14: 380 | E14: PLANETA AZUL S.A | F14: PAGO NCF E45000013058 ADQUISICION DE BOTELLAS DE AGUA SEGÚN O/C HSLM-2025-00322. | G14: 15000 | H14: 15000
A15: 45974 | C15: 381 | E15: PLANETA AZUL S.A | F15: PAGO NCF E450000012562 ADQUISICION DE BOTELLAS DE AGUA SEGÚN O/C HSLM-2025-01004 | G15: 14000 | H15: 14000
A16: 45974 | C16: 382 | E16: SUPER LAPTOP BROWSING SRL | F16: PAGO NCF B1500000184 ADQUISICION DE UPS SEGÚN O/C HSLM-2025-01090 | G16: 413000 | H16: 395500
A17: 45974 | C17: 383 | E17: BAAM & ASOCIADOS SRL | F17: PAGO NCF B1500000096 ADQUISICION E INSTALACION DE CONTROL DE SALIDA PUERTA PRINCIPAL SEGÚN O/C HSLM-2025-01038 | G17: 175173.19 | H17: 166414.53
A18: 45974 | C18: 384 | E18: BAAM & ASOCIADOS SRL | F18: PAGO NCF B1500000197 ADQUISICION BARRERAS DE CONTROL EN LAS ENTRADAS PRINCIPALES DE LOS PARQUEOS SEGÚN O/C HSLM-2025-01037 | G18: 244226.81 | H18: 233878.22
A19: 45974 | C19: 385 | E19: G&M GELMAT COMERCIAL SRL | F19: PAGO NCF B1500000199 ADQUISICION DE CAJAS PARA EQUIPO ELECTRICO SEGÚN O/C HSLM-2025-01071. | G19: 41819.2 | H19: 40047.2
A20: 45974 | C20: 386 | E20: NULO | F20: NULO | G20: 0 | H20: 0
A21: 45974 | C21: 387 | E21: IV BIODESINFECCION SRL | F21: PAGO NCF B1500000305 SERVICIO DE DESINFECION SEGÚN O/C HSLM-2025-01089 | G21: 185260 | H21: 177410
A22: 45974 | C22: 388 | E22: TROPIGAS DOMINICANA SRL | F22: PAGO NCF E45000000005518 POR ADQUISICION DE GAS LICUADO DE PETROLEO SEGÚN O/ C HSLM-2025-00730 | G22: 21952 | H22: 21952
... A35: 45989 | C35: 401 | E35: TONER DEPOT MULTISERVICIOS EORG SRL | F35: PAGO NCF E450000000424, POR SERVICIO DE IMPRESIÓN EN EL MES DE OCTUBRE 2025 SEGÚN O/C HSLM-2025-00725 | G35: 298561.92 | H35: 272247.99
A36: 45989 | C36: =+C35+1 -> 402 | E36: OFITOP, SRL | F36: PAGO DE FACT NCF NO. B1500000024, POR ADQUISICION DE MUEBLES DE OFICINA PARA SER UTILIZADO EN LA READECUACION DEL CONSULTORIO DE OFTALMOLOGIA, SEGÚN ORDEN DE COMPRA HSLM-2025-01042 | G36: 182234.7 | H36: 174512.67
A37: 45989 | C37: =+C36+1 -> 403 | E37: OFITOP, SRL | F37: PAGO DE FACT NCF NO. B1500000021, POR ELABORCION DE LETRERO TIPO SEÑALIZACION EN ACRILICO ROTULADO EN VINIL 30X30, SEGÚN ORDEN DE COMPRA HSLM-2025-01026 | G37: 221258.85 | H37: 211883.48
A38: 45989 | C38: =+C37+1 -> 404 | E38: OFITOP, SRL | F38: PAGO DE FACT NCF NO. B1500000019, POR ADQUISICION DE MOBILIARIOS, SEGÚN ORDEN DE COMPRA HSLM-2025-01041 | G38: 260210.02 | H38: 249184.17
A39: 45989 | C39: 405 | E39: FARMACO QUIMICA NACIONAL, | F39: ADQUISICION DE VALCULA HIDROCEFALICA, | G39: 30444 | H39: 30444
A40: 45989 | C40: 406 | E40: HOSPAL MEDICA SRL | F40: ADQUISICION DE VALCULA HIDROCEFALICA, ORDEN DE SEVICIO 2025-01222 | G40: 34220 | H40: 34220
A41: 45989 | C41: 407 | E41: Suplimed, SRL | F41: PAGO FACTURA NCF B1500000127 | G41: 195000 | H41: 195000
A42: 45989 | C42: 408 | E42: COMISION NACIONAL DE ENERGIA | F42: SERVICIO DE LICENCIA OPERACIONAL RADIODIAGNOSTICA PARA EL HOSPITAL | G42: 13260 | H42: 13260
A43: 45972 | D43: 37317 | E43: NULO | F43: NULO | G43: 0 | H43: 0
A44: 45981 | D44: 37318 | E44: DELMIRA GARCIA | F44: REPOSICION DEL FONDO DE CAJA CHICA DESDE RECIBO 40668 HASTA EL RECIBO 40702 | G44: 56945.15 | H44: 56945.15
A45: 45981 | D45: 37319 | E45: RUDDY SEGURA | F45: PAGO NCF B1100000080 SERVICIO DE LIMPIEZA Y CLORIFICACION DE CISTERNA DE ESTE HOSPITAL | G45: 21673.47 | H45: 18000
A46: 45981 | D46: 37320 | E46: ALEXANDER MENDEZ CONTRERAS | F46: PAGO NCF B1100000081 SERVICIO DE JARDINERIA PARA AREAS VERDES DE ESTE HOSPITAL. | G46: 18061.22 | H46: 15000
A47: 45981 | D47: 37321 | E47: NELSON YNFANTE VELAZQUEZ | F47: PAGO NCF B1100000082 SERVICIO DE PINTURA DE LAS AREAS DE EMERGENCIA Y PEDIATRIA DE ESTE HOSPITAL | G47: 18061.22 | H47: 15000
A48: 45981 | D48: 37322 | E48: FREDDY OSCAR RODRIGUEZ RIVAS | F48: COLABORACION DE CAVACION DE HOYO Y CERTIFICACION DE ACTAS EN EL MES DE NOVIEMBRE 2025 | G48: 3600 | H48: 3600
A49: 45982 | D49: 37323 | E49: OVIDIO DE JESUS DURAN CLEMENTE | F49: PAGO POR SERVICIO DE TRANSPORTE DE LA AMBULANCIA CORRESPONDIENTE AL MES DE NOVIEMBRE 2025 | G49: 20000 | H49: 20000
A50: 45991 | E50: COMISIONES BANCARIAS | F50: COMISIONES BANCARIAS | G50: 14087.24 | H50: 14087.24
A51: 03/11/2025 | B51: 4930 | E51: Grupo Xeron Medic SRL | F51: PAGO FACTURA NCF B1500000303 POR ADQUISICION DE UTIL MEDICO SEGUN O/C HSLM-2025-01062. | G51: 272108
A52: 03/11/2025 | B52: 4934 | E52: Grupo Xeron Medic SRL | F52: PAGO FACTURA NCF B1500000310 POR ADQUISICION DE UTIL MEDICO SEGUN O/C HSLM-2025-01082. | G52: 252331.2
A53: 03/11/2025 | B53: 4938 | E53: Grupo Xeron Medic SRL | F53: PAGO FACTURA NCF B1500000312 POR ADQUISICION DE UTIL MEDICO SEGUN O/C HSLM-2025-01095. | G53: 224294.4
A54: 03/11/2025 | B54: 4942 | E54: Bio Nuclear, SA | F54: PAGO DE FACT NCF NO. E450000008409 Y E450000008443, POR ADQUISICION DE CONTROLES EQAS, SEGUN ORDEN DE COMPRA HSLM-2025-01021 | G54: 17504.5
A55: 03/11/2025 | B55: 4953 | E55: PAPELERIA E IMPRESOS CRISHOAN, SRL | F55: PAGO DE FACT NCF NO B1500001792, POR ADQUISICION DE IMPRESOS, SEGUN ORDEN DE COMPRA HSLM-2025-01097 | G55: 271695
A56: 03/11/2025 | B56: 4960 | E56: Farmaco Internacional, SRL | F56: PAGO DE FACT NCF NO. E450000000118, POR ADQUISICION DE UTIL MEDICO, SEGUN ORDEN DE COMPRA HSLM-2025-00894 | G56: 138591
A57: 03/11/2025 | B57: 4961 | E57: Destreza Comercial, SRL | F57: PAGO DE FACT NCF B1500000079 POR ADQUISICION DE MEDICAMENTOS SEGUN O/C HSLM-2025-01083. | G57: 71400
A58: 03/11/2025 | B58: 4965 | E58: Dumas Pharmaceuticals, S.R.L. | F58: PAGO DE FACT NCF NO. B1500001442, POR ADQUISICION DE UTIL MEDICO, SEGUN ORDEN DE COMPRA HSLM-2025-00946 | G58: 255284.8
A59: 03/11/2025 | B59: 4969 | E59: Farnasa, SRL | F59: PAGO DE FACT NCF B1500000957 POR ADQUISICION DE MEDICAMENTOS SEGUN O/C HSLM-2025-01074. | G59: 87500
A60: 03/11/2025 | B60: 4974 | E60: Corporacion Medica A.G., SRL | F60: PAGO DE FACT NCF B1500000146 POR ADQUISICION DE UTILES MEDICOS SEGUN O/C HSLM-2025-01086. | G60: 247800
A61: 03/11/2025 | B61: 4977 | E61: Farmaco Internacional, SRL | F61: PAGO DE FACT NCF NO. E450000000122, POR ADQUISICION DE UTIL MEDICO, SEGUN ORDEN DE COMPRA HSLM-2025-01105 | G61: 101786
A62: 03/11/2025 | B62: 4981 | E62: Farmaco Internacional, SRL | F62: PAGO DE FACT NCF NO. E450000000120, POR ADQUISICION DE UTIL MEDICO, SEGUN ORDEN DE COMPRA HSLM-2025-00894 | G62: 138591
... A127: 27/11/2025 | B127: 5355 | E127: Abrias Novo Group SRL | F127: PAGO DE FACT NCF B1500000166 POR ADQUISICION DE PUERTA POLIMETAL BLANCA SEGUN O/C HSLM-2025-01076. | G127: 15340
A128: Total | G128: =SUM(G11:G127) -> 1.644549e+08 | H128: =SUM(H12:H113) -> 6039289.7
A130: RESUMEN DE GASTOS
A131: PAGOS A PROVEEDORES | C131: 30561659
A132: CAJA CHICA | C132: =+G44 -> 56945.15
A133: NOMINA | C133: =+G105+G104+G103+G97+G96+G94+G95+G93+G82+G81 -> 1.3374081e+08
A134: OTROS GASTOS | C134: =+G43+G45+G46+G47+G48+G49+G50 -> 95483.15
A135: TOTAL GENERAL | C135: =+C131+C132+C133+C134 -> 1.644549e+08

Sheet RELACION ORDENES DE COMPRAS
A4: SERVICIO NACIONAL DE SALUD
A5: DIRECCION DE FISCALIZACION
A6: RELACIÓN DE ORDENES DE COMPRAS DE BIENES Y SERVICIOS EFECTUADAS.
A7: ESTABLECIMIENTO: HOSPITAL MATERNO INFANTIL SAN LORENZO DE LOS MINA REGION OZAMA
A8: 45962 | J8: EN PROCESO POR EL AREA DE COMPRAS
A9: Fecha | B9: # Orden de Compra o Servicios | C9: # DE EXPEDIENTE(PROCESO CELEBRADO) | D9: No. De Factura Fiscal NCF | E9: Fuente. Financ (FR-VS) | F9: Beneficiario | G9: Rubro | H9: No. Cta. Objetal del Gasto | I9: Valor | J9: Status del proceso | K9: solo observar cuando se presentas esos procesos

Sheet CONS. FUENTES FINAN
A1: Form. No.6 SRS
A3: Servicio Nacional de Salud
A4: Dirección de Fizcalización
A5: Consolidado de Ingresos y Gastos por Fuente de Financiamiento
A6: HOSPITAL MATERNO INFANTIL SAN LORENZO DE LOS MINA
A7: OCTUBRE 2025
C8: Ingresos Generales:
E9: 1.- Balance Inicial / Fuente:
E10: Anticipo Financiero | H10: Otros Aportes | L10: Contraseña: 0001
E11: Transferencias Corrientes
E12: Venta de Servicios | G12: 5363379
E13: 2.- Ingresos por Fuente / Cuenta
E14: Anticipo Financiero | H14: Otros Aportes | L14: OBJETAL | M14: FR | N14: VS
E15: Transferencias Corrientes | G15: =+'INGR SEGUN ORIGEN'!E12 -> 1.5626822e+08 | H15: Aportes Nomina SNS | L15: 2.1 | M15: =G26 -> 1.3374081e+08 | N15: =H26 -> 0
E16: Venta de Servicios | G16: =+'INGR SEGUN ORIGEN'!E35+'INGR SEGUN ORIGEN'!E42 -> 9309369.1 | L16: 2.2 | M16: =G87 -> 1896797.1 | N16: =H87 -> 2083820.5
H17: TOTAL INGRESOS RDS | I17: =+G10+G11+G12+I10+G14+G15+G16+I14+I15 -> 1.7094097e+08 | L17: 2.3 | M17: ='CONS. FUENTES FINAN'!G212 -> 13779851 | N17: ='CONS. FUENTES FINAN'!H212 -> 2184325.9
L18: 2.4 | M18: =G330 -> 0 | N18: =H330 -> 3600
L19: 2.6 | M19: =G336 -> 8010447.3 | N19: =H336 -> 2755244.7
L20: 2.7 | M20: ='CONS. FUENTES FINAN'!G463 -> 0 | N20: ='CONS. FUENTES FINAN'!H463 -> 0
A21: 1 | F21: 2 | G21: 3 | I21: 4 | J21: 5
A22: Código Presupuestario | F22: Descripción Gasto por Cuenta | G22: Distribución del Gasto por Fuente de Financiamiento | I22: TOTAL | J22: %
A23: Tipo | B23: Objeto | C23: Cuenta | D23: Sub-Cuenta | E23: Auxiliar | G23: Fondo 100 | H23: Venta de Servicios/ Otros Aportes
A25: 2 | F25: Gastos | G25: =+G26+G87+G212+G330+G336+G463 -> 157427908 | H25: =+H26+H87+H212+H330+H336+H463 -> 7026991.1 | I25: =SUM(G25:H25) -> 1.644549e+08 | J25: =+J26+J87+J212+J330+J336+J463 -> 1
A26: 2 | B26: 1 | F26: Servicios Personales | G26: =+G27+G51+G64+G71+G78 -> 1.3374081e+08 | H26: =+H27+H51+H64+H71+H78 -> 0 | I26: =SUM(G26:H26) -> 1.3374081e+08 | J26: =I26/$I$25 -> 0.81323702
A27: 2 | B27: 1 | C27: 1 | F27: Remuneraciones | G27: =+G28+G35+G42+G44+G46 -> 1.2113301e+08 | H27: =+H28+H35+H42+H44+H46 -> 0 | I27: =SUM(G27:H27) -> 1.2113301e+08
A28: 2 | B28: 1 | C28: 1 | D28: 1 | F28: Remuneraciones al personal fijo | G28: =SUM(G29:G34) -> 59046800 | H28: =SUM(H29:H34) -> 0 | I28: =SUM(G28:H28) -> 59046800
A29: 2 | B29: 1 | C29: 1 | D29: 1 | E29: 01 | F29: Sueldos a empleados fijos | G29: ='CUENTA T FONDO 100'!A97 -> 59046800 | H29: ='CUENTA T VS'!A75 -> 0 | I29: =SUM(G29:H29) -> 59046800 | J29: =I29/$I$25 -> 0.35904555
A30: 2 | B30: 1 | C30: 1 | D30: 1 | E30: 02 | F30: Sueldos a médicos | G30: ='CUENTA T FONDO 100'!B97 -> 0 | H30: ='CUENTA T VS'!B75 -> 0 | I30: =SUM(G30:H30) -> 0 | J30: =I30/$I$25 -> 0
A31: 2 | B31: 1 | C31: 1 | D31: 1 | E31: 03 | F31: Ascensos a militares | G31: ='CUENTA T FONDO 100'!C97 -> 0 | H31: ='CUENTA T VS'!C75 -> 0 | I31: =SUM(G31:H31) -> 0 | J31: =I31/$I$25 -> 0
A32: 2 | B32: 1 | C32: 1 | D32: 1 | E32: 04 | F32: Nuevas plazas maestros | G32: ='CUENTA T FONDO 100'!D97 -> 0 | H32: ='CUENTA T VS'!D75 -> 0 | I32: =SUM(G32:H32) -> 0 | J32: =I32/$I$25 -> 0
A33: 2 | B33: 1 | C33: 1 | D33: 1 | E33: 05 | F33: Incentivos y escalafón | G33: ='CUENTA T FONDO 100'!E97 -> 0 | H33: ='CUENTA T VS'!E75 -> 0 | I33: =SUM(G33:H33) -> 0 | J33: =I33/$I$25 -> 0
A34: 2 | B34: 1 | C34: 1 | D34: 1 | E34: 06 | F34: Nuevas plazas a médicos | G34: ='CUENTA T FONDO 100'!F97 -> 0 | H34: ='CUENTA T VS'!F75 -> 0 | I34: =SUM(G34:H34) -> 0 | J34: =I34/$I$25 -> 0
A35: 2 | B35: 1 | C35: 1 | D35: 2 | F35: Remuneraciones al personal con carácter transitorio | G35: =SUM(G36:G41) -> 1342531 | H35: =SUM(H36:H41) -> 0 | I35: =SUM(G35:H35) -> 1342531
A36: 2 | B36: 1 | C36: 1 | D36: 2 | E36: 03 | F36: Suplencias | G36: ='CUENTA T FONDO 100'!G97 -> 0 | H36: ='CUENTA T VS'!G75 -> 0 | I36: =SUM(G36:H36) -> 0 | J36: =I36/$I$25 -> 0
A37: 2 | B37: 1 | C37: 1 | D37: 2 | E37: 05 | F37: Sueldo al personal nominal en período probatorio | G37: ='CUENTA T FONDO 100'!H97 -> 0 | H37: ='CUENTA T VS'!H75 -> 0 | I37: =SUM(G37:H37) -> 0 | J37: =I37/$I$25 -> 0
A38: 2 | B38: 1 | C38: 1 | D38: 2 | E38: 06 | F38: Jornales | G38: ='CUENTA T FONDO 100'!I97 -> 0 | H38: ='CUENTA T VS'!I75 -> 0 | I38: =SUM(G38:H38) -> 0 | J38: =I38/$I$25 -> 0
A39: 2 | B39: 1 | C39: 1 | D39: 2 | E39: 08 | F39: Empleados temporales | G39: ='CUENTA T FONDO 100'!J97 -> 1342531 | H39: ='CUENTA T VS'!J75 -> 0 | I39: =SUM(G39:H39) -> 1342531 | J39: =I39/$I$25 -> 0.008163521
A40: 2 | B40: 1 | C40: 1 | D40: 2 | E40: 09 | F40: Personal de carácter eventual | G40: ='CUENTA T FONDO 100'!K97 -> 0 | H40: ='CUENTA T VS'!K75 -> 0 | I40: =SUM(G40:H40) -> 0 | J40: =I40/$I$25 -> 0
A41: 2 | B41: 1 | C41: 1 | D41: 2 | E41: 11 | F41: Interinato | G41: ='CUENTA T FONDO 100'!L97 -> 0 | H41: ='CUENTA T VS'!L75 -> 0 | I41: =SUM(G41:H41) -> 0 | J41: =I41/$I$25 -> 0
A42: 2 | B42: 1 | C42: 1 | D42: 3 | F42: Sueldos al personal fijo en trámite de pensiones | G42: =SUM(G43) -> 0 | H42: =SUM(H43) -> 0 | I42: =SUM(G42:H42) -> 0
A43: 2 | B43: 1 | C43: 1 | D43: 3 | E43: 01 | F43: Sueldos al personal fijo en trámite de pensiones | G43: ='CUENTA T FONDO 100'!M97 -> 0 | H43: ='CUENTA T VS'!M75 -> 0 | I43: =SUM(G43:H43) -> 0 | J43: =I43/$I$25 -> 0
A44: 2 | B44: 1 | C44: 1 | D44: 4 | F44: Sueldo anual no. 13 | G44: =SUM(G45) -> 60212859 | H44: =SUM(H45) -> 0 | I44: =SUM(G44:H44) -> 60212859
A45: 2 | B45: 1 | C45: 1 | D45: 4 | E45: 01 | F45: Sueldo anual no. 13 | G45: ='CUENTA T FONDO 100'!N97 -> 60212859 | H45: ='CUENTA T VS'!N75 -> 0 | I45: =SUM(G45:H45) -> 60212859 | J45: =I45/$I$25 -> 0.366136
A46: 2 | B46: 1 | C46: 1 | D46: 5 | F46: Prestaciones económinas | G46: =SUM(G47:G50) -> 530819.29 | H46: =SUM(H47:H50) -> 0 | I46: =SUM(G46:H46) -> 530819.29
A47: 2 | B47: 1 | C47: 1 | D47: 5 | E47: 01 | F47: Prestaciones económinas | G47: ='CUENTA T FONDO 100'!O97 -> 0 | H47: ='CUENTA T VS'!O75 -> 0 | I47: =SUM(G47:H47) -> 0 | J47: =I47/$I$25 -> 0
A48: 2 | B48: 1 | C48: 1 | D48: 5 | E48: 02 | F48: Pago de porcentaje por desvinculación de cargo | G48: ='CUENTA T FONDO 100'!P97 -> 0 | H48: ='CUENTA T VS'!P75 -> 0 | I48: =SUM(G48:H48) -> 0 | J48: =I48/$I$25 -> 0
A49: 2 | B49: 1 | C49: 1 | D49: 5 | E49: 03 | F49: Prestación laboral por desvinculación | G49: ='CUENTA T FONDO 100'!Q97 -> 51000 | H49: ='CUENTA T VS'!Q75 -> 0 | I49: =SUM(G49:H49) -> 51000 | J49: =I49/$I$25 -> 0.00031011542
A50: 2 | B50: 1 | C50: 1 | D50: 5 | E50: 04 | F50: Proporción de vacaciones no disfrutadas | G50: ='CUENTA T FONDO 100'!R97 -> 479819.29 | H50: ='CUENTA T VS'!R75 -> 0 | I50: =SUM(G50:H50) -> 479819.29 | J50: =I50/$I$25 -> 0.0029176345
A51: 2 | B51: 1 | C51: 2 | F51: Sobresueldos | G51: =+G52+G54 -> 3315450.2 | H51: =+H52+H54 -> 0 | I51: =SUM(G51:H51) -> 3315450.2
A52: 2 | B52: 1 | C52: 2 | D52: 1 | F52: Primas por antigüedad | G52: =SUM(G53) -> 2652914.7 | H52: =SUM(H53) -> 0 | I52: =SUM(G52:H52) -> 2652914.7
A53: 2 | B53: 1 | C53: 2 | D53: 1 | E53: 01 | F53: Primas por antigüedad | G53: ='CUENTA T FONDO 100'!S97 -> 2652914.7 | H53: ='CUENTA T VS'!S75 -> 0 | I53: =SUM(G53:H53) -> 2652914.7 | J53: =I53/$I$25 -> 0.016131564
A54: 2 | B54: 1 | C54: 2 | D54: 2 | F54: Compensación | G54: =SUM(G55:G63) -> 662535.52 | H54: =SUM(H55:H63) -> 0 | I54: =SUM(G54:H54) -> 662535.52
A55: 2 | B55: 1 | C55: 2 | D55: 2 | E55: 01 | F55: Compensación por gastos de alimentación | G55: ='CUENTA T FONDO 100'!T97 -> 0 | H55: ='CUENTA T VS'!T75 -> 0 | I55: =SUM(G55:H55) -> 0 | J55: =I55/$I$25 -> 0
A56: 2 | B56: 1 | C56: 2 | D56: 2 | E56: 03 | F56: Pago de horas extraordinarias | G56: ='CUENTA T FONDO 100'!U97 -> 0 | H56: ='CUENTA T VS'!U75 -> 0 | I56: =SUM(G56:H56) -> 0 | J56: =I56/$I$25 -> 0
A57: 2 | B57: 1 | C57: 2 | D57: 2 | E57: 04 | F57: Prima de transporte | G57: ='CUENTA T FONDO 100'!V97 -> 0 | H57: ='CUENTA T VS'!V75 -> 0 | I57: =SUM(G57:H57) -> 0 | J57: =I57/$I$25 -> 0
A58: 2 | B58: 1 | C58: 2 | D58: 2 | E58: 05 | F58: Compensación servicios de Seguridad | G58: ='CUENTA T FONDO 100'!W97 -> 75000 | H58: ='CUENTA T VS'!W75 -> 0 | I58: =SUM(G58:H58) -> 75000 | J58: =I58/$I$25 -> 0.00045605209
A59: 2 | B59: 1 | C59: 2 | D59: 2 | E59: 06 | F59: Incentivo por Rendimieto Individual | G59: ='CUENTA T FONDO 100'!X97 -> 0 | H59: ='CUENTA T VS'!X75 -> 0 | I59: =SUM(G59:H59) -> 0 | J59: =I59/$I$25 -> 0
A60: 2 | B60: 1 | C60: 2 | D60: 2 | E60: 07 | F60: Compensación por distancia | G60: ='CUENTA T FONDO 100'!Y97 -> 0 | H60: ='CUENTA T VS'!Y75 -> 0 | I60: =SUM(G60:H60) -> 0 | J60: =I60/$I$25 -> 0
A61: 2 | B61: 1 | C61: 2 | D61: 2 | E61: 08 | F61: Compensaciones especiales | G61: ='CUENTA T FONDO 100'!Z97 -> 317800 | H61: ='CUENTA T VS'!Z75 -> 0 | I61: =SUM(G61:H61) -> 317800 | J61: =I61/$I$25 -> 0.0019324447
A62: 2 | B62: 1 | C62: 2 | D62: 2 | E62: 09 | F62: Bono por desempeño a servidores de carrera | G62: ='CUENTA T FONDO 100'!AA97 -> 0 | H62: ='CUENTA T VS'!AA75 -> 0 | I62: =SUM(G62:H62) -> 0 | J62: =I62/$I$25 -> 0
A63: 2 | B63: 1 | C63: 2 | D63: 2 | E63: 10 | F63: Compensacion por cumplimiento de indicadores | G63: ='CUENTA T FONDO 100'!AB97 -> 269735.52 | H63: ='CUENTA T VS'!AB75 -> 0 | I63: =SUM(G63:H63) -> 269735.52 | J63: =I63/$I$25 -> 0.0016401793
A64: 2 | B64: 1 | C64: 3 | F64: Dietas y Gastos de Representación | G64: =+G65+G68 -> 0 | H64: =+H65+H68 -> 0 | I64: =SUM(G64:H64) -> 0
A65: 2 | B65: 1 | C65: 3 | D65: 1 | F65: Dietas | G65: =SUM(G66:G67) -> 0 | H65: =SUM(H66:H67) -> 0 | I65: =SUM(G65:H65) -> 0
A66: 2 | B66: 1 | C66: 3 | D66: 1 | E66: 01 | F66: Dietas en el país | G66: ='CUENTA T FONDO 100'!AC97 -> 0 | H66: ='CUENTA T VS'!AC75 -> 0 | I66: =SUM(G66:H66) -> 0 | J66: =I66/$I$25 -> 0
A67: 2 | B67: 1 | C67: 3 | D67: 1 | E67: 02 | F67: Dietas en el exterior | G67: ='CUENTA T FONDO 100'!AD97 -> 0 | H67: ='CUENTA T VS'!AD75 -> 0 | I67: =SUM(G67:H67) -> 0 | J67: =I67/$I$25 -> 0
A68: 2 | B68: 1 | C68: 3 | D68: 2 | F68: Gastos de representación | G68: =SUM(G69:G70) -> 0 | H68: =SUM(H69:H70) -> 0 | I68: =SUM(G68:H68) -> 0
A69: 2 | B69: 1 | C69: 3 | D69: 2 | E69: 01 | F69: Gastos de representación en el país | G69: ='CUENTA T FONDO 100'!AE97 -> 0 | H69: ='CUENTA T VS'!AE75 -> 0 | I69: =SUM(G69:H69) -> 0 | J69: =I69/$I$25 -> 0
A70: 2 | B70: 1 | C70: 3 | D70: 2 | E70: 02 | F70: Gastos de representación en el exterior | G70: ='CUENTA T FONDO 100'!AF97 -> 0 | H70: ='CUENTA T VS'!AF75 -> 0 | I70: =SUM(G70:H70) -> 0 | J70: =I70/$I$25 -> 0
A71: 2 | B71: 1 | C71: 4 | F71: Gratificaciones y Bonificaciones | G71: =+G72+G74 -> 0 | H71: =+H72+H74 -> 0 | I71: =SUM(G71:H71) -> 0
A72: 2 | B72: 1 | C72: 4 | D72: 1 | F72: Bonificaciones | G72: =SUM(G73) -> 0 | H72: =SUM(H73) -> 0 | I72: =SUM(G72:H72) -> 0
A73: 2 | B73: 1 | C73: 4 | D73: 1 | E73: 01 | F73: Bonificaciones | G73: ='CUENTA T FONDO 100'!AG97 -> 0 | H73: ='CUENTA T VS'!AG75 -> 0 | I73: =SUM(G73:H73) -> 0 | J73: =I73/$I$25 -> 0
A74: 2 | B74: 1 | C74: 4 | D74: 2 | F74: Otras Gratificaciones y Bonificaciones | G74: =SUM(G75:G77) -> 0 | H74: =SUM(H75:H77) -> 0 | I74: =SUM(G74:H74) -> 0
A75: 2 | B75: 1 | C75: 4 | D75: 2 | E75: 01 | F75: Bono escolar | G75: ='CUENTA T FONDO 100'!AH97 -> 0 | H75: ='CUENTA T VS'!AH75 -> 0 | I75: =SUM(G75:H75) -> 0 | J75: =I75/$I$25 -> 0
A76: 2 | B76: 1 | C76: 4 | D76: 2 | E76: 02 | F76: Gratificaciones por pasantías | G76: ='CUENTA T FONDO 100'!AI97 -> 0 | H76: ='CUENTA T VS'!AI75 -> 0 | I76: =SUM(G76:H76) -> 0 | J76: =I76/$I$25 -> 0
A77: 2 | B77: 1 | C77: 4 | D77: 2 | E77: 03 | F77: Gratificaciones por aniversario de institución | G77: ='CUENTA T FONDO 100'!AJ97 -> 0 | H77: ='CUENTA T VS'!AJ75 -> 0 | I77: =SUM(G77:H77) -> 0 | J77: =I77/$I$25 -> 0
A78: 2 | B78: 1 | C78: 5 | F78: Contribuciones a la Seguridad Social y Riesgo Laboral | G78: =+G79+G81+G83+G85 -> 9292352.7 | H78: =+H79+H81+H83+H85 -> 0 | I78: =SUM(G78:H78) -> 9292352.7
A79: 2 | B79: 1 | C79: 5 | D79: 1 | F79: Contribuciones al seguro de salud | G79: =SUM(G80) -> 4281604.4 | H79: =SUM(H80) -> 0 | I79: =SUM(G79:H79) -> 4281604.4
A80: 2 | B80: 1 | C80: 5 | D80: 1 | E80: 01 | F80: Contribuciones al seguro de salud | G80: ='CUENTA T FONDO 100'!AK97 -> 4281604.4 | H80: ='CUENTA T VS'!AK75 -> 0 | I80: =SUM(G80:H80) -> 4281604.4 | J80: =I80/$I$25 -> 0.026035128
A81: 2 | B81: 1 | C81: 5 | D81: 2 | F81: Contribuciones al seguro de pensiones | G81: =SUM(G82) -> 4287644.2 | H81: =SUM(H82) -> 0 | I81: =SUM(G81:H81) -> 4287644.2
A82: 2 | B82: 1 | C82: 5 | D82: 2 | E82: 01 | F82: Contribuciones al seguro de pensiones | G82: ='CUENTA T FONDO 100'!AL97 -> 4287644.2 | H82: ='CUENTA T VS'!AL75 -> 0 | I82: =SUM(G82:H82) -> 4287644.2 | J82: =I82/$I$25 -> 0.026071855
A83: 2 | B83: 1 | C83: 5 | D83: 3 | F83: Contribuciones al seguro de riesgo laboral | G83: =SUM(G84) -> 723104.06 | H83: =SUM(H84) -> 0 | I83: =SUM(G83:H83) -> 723104.06
A84: 2 | B84: 1 | C84: 5 | D84: 3 | E84: 01 | F84: Contribuciones al seguro de riesgo laboral | G84: ='CUENTA T FONDO 100'!AM97 -> 723104.06 | H84: ='CUENTA T VS'!AM75 -> 0 | I84: =SUM(G84:H84) -> 723104.06 | J84: =I84/$I$25 -> 0.0043969749
A85: 2 | B85: 1 | C85: 5 | D85: 4 | F85: Contribuciones al plan de retiro complementario | G85: =SUM(G86) -> 0 | H85: =SUM(H86) -> 0 | I85: =SUM(G85:H85) -> 0
A86: 2 | B86: 1 | C86: 5 | D86: 4 | E86: 01 | F86: Contribuciones al plan de retiro complementario | G86: ='CUENTA T FONDO 100'!AN97 -> 0 | H86: ='CUENTA T VS'!AN75 -> 0 | I86: =SUM(G86:H86) -> 0 | J86: =I86/$I$25 -> 0
A87: 2 | B87: 2 | F87: Servicios No Personales | G87: =G88+G106+G111+G116+G125+G148+G157+G179+G208 -> 1896797.1 | H87: =H88+H106+H111+H116+H125+H148+H157+H179+H208 -> 2083820.5 | I87: =SUM(G87:H87) -> 3980617.7 | J87: =I87/$I$25 -> 0.02420492
A88: 2 | B88: 2 | C88: 1 | F88: Servicios Básicos | G88: =+G89+G91+G93+G95+G97+G99+G102+G104 -> 60535 | H88: =+H89+H91+H93+H95+H97+H99+H102+H104 -> 745000 | I88: =SUM(G88:H88) -> 805535
A89: 2 | B89: 2 | C89: 1 | D89: 1 | F89: Radiocomunicación | G89: =SUM(G90) -> 0 | H89: =SUM(H90) -> 0 | I89: =SUM(G89:H89) -> 0
A90: 2 | B90: 2 | C90: 1 | D90: 1 | E90: 01 | F90: Radiocomunicación | G90: ='CUENTA T FONDO 100'!AO97 -> 0 | H90: ='CUENTA T VS'!AO75 -> 0 | I90: =SUM(G90:H90) -> 0 | J90: =I90/$I$25 -> 0
A91: 2 | B91: 2 | C91: 1 | D91: 2 | F91: Servicios telefónico de larga distancia | G91: =SUM(G92) -> 0 | H91: =SUM(H92) -> 0 | I91: =SUM(G91:H91) -> 0
A92: 2 | B92: 2 | C92: 1 | D92: 2 | E92: 01 | F92: Servicios telefónico de larga distancia | G92: ='CUENTA T FONDO 100'!AP97 -> 0 | H92: ='CUENTA T VS'!AP75 -> 0 | I92: =SUM(G92:H92) -> 0 | J92: =I92/$I$25 -> 0
A93: 2 | B93: 2 | C93: 1 | D93: 3 | F93: Teléfono local | G93: =SUM(G94) -> 0 | H93: =SUM(H94) -> 0 | I93: =SUM(G93:H93) -> 0
A94: 2 | B94: 2 | C94: 1 | D94: 3 | E94: 01 | F94: Teléfono local | G94: ='CUENTA T FONDO 100'!AQ97 -> 0 | H94: ='CUENTA T VS'!AQ75 -> 0 | I94: =SUM(G94:H94) -> 0 | J94: =I94/$I$25 -> 0
A95: 2 | B95: 2 | C95: 1 | D95: 4 | F95: Telefax y correos | G95: =SUM(G96) -> 0 | H95: =SUM(H96) -> 0 | I95: =SUM(G95:H95) -> 0
A96: 2 | B96: 2 | C96: 1 | D96: 4 | E96: 01 | F96: Telefax y correos | G96: ='CUENTA T FONDO 100'!AR97 -> 0 | H96: ='CUENTA T VS'!AR75 -> 0 | I96: =SUM(G96:H96) -> 0 | J96: =I96/$I$25 -> 0
A97: 2 | B97: 2 | C97: 1 | D97: 5 | F97: Servicio de Internet y televisión por cable | G97: =SUM(G98) -> 0 | H97: =SUM(H98) -> 0 | I97: =SUM(G97:H97) -> 0
A98: 2 | B98: 2 | C98: 1 | D98: 5 | E98: 01 | F98: Servicio de Internet y televisión por cable | G98: ='CUENTA T FONDO 100'!AS97 -> 0 | H98: ='CUENTA T VS'!AS75 -> 0 | I98: =SUM(G98:H98) -> 0 | J98: =I98/$I$25 -> 0
A99: 2 | B99: 2 | C99: 1 | D99: 6 | F99: Electricidad | G99: =SUM(G100:G101) -> 0 | H99: =SUM(H100:H101) -> 0 | I99: =SUM(G99:H99) -> 0
A100: 2 | B100: 2 | C100: 1 | D100: 6 | E100: 01 | F100: Energía eléctrica | G100: ='CUENTA T FONDO 100'!AT97 -> 0 | H100: ='CUENTA T VS'!AT75 -> 0 | I100: =SUM(G100:H100) -> 0 | J100: =I100/$I$25 -> 0
A101: 2 | B101: 2 | C101: 1 | D101: 6 | E101: 02 | F101: Electricidad no cortable | G101: ='CUENTA T FONDO 100'!AU97 -> 0 | H101: ='CUENTA T VS'!AU75 -> 0 | I101: =SUM(G101:H101) -> 0 | J101: =I101/$I$25 -> 0
A102: 2 | B102: 2 | C102: 1 | D102: 7 | F102: Agua | G102: =SUM(G103) -> 60535 | H102: =SUM(H103) -> 0 | I102: =SUM(G102:H102) -> 60535
...

Sheet CUENTA T FONDO 100
A1: D E S G L O S E D E L A S C U E N T A S
A2: 211101 | B2: 211102 | C2: 211103 | D2: 211104 | E2: 211105 | F2: 211106 | G2: 211203 | H2: 211205 | I2: 211206 | J2: 211208 | K2: 211209 | L2: 211211 | M2: 211301 | N2: 211401 | O2: 211501 | P2: 211502 | Q2: 211503 | R2: 211504 | S2: 212101 | T2: 212201 | U2: 212203 | V2: 212204 | W2: 212205 | X2: 212206 | Y2: 212207 | Z2: 212208 | AA2: 212209 | AB2: 212210 | AC2: 213101 | AD2: 213102 | AE2: 213201 | AF2: 213202 | AG2: 214101 | AH2: 214201 | AI2: 214202 | AJ2: 214203 | AK2: 215101 | AL2: 215201 | AM2: 215301 | AN2: 215401 | AO2: 221101 | AP2: 221201 | AQ2: 221301 | AR2: 221401 | AS2: 221501 | AT2: 221601 | AU2: 221602 | AV2: 221701 | AW2: 221801 | AX2: 222101 | AY2: 222201 | AZ2: 223101 | BA2: 223201 | BB2: 224101 | BC2: 224201 | BD2: 224301 | BE2: 224401 | BF2: 225101 | BG2: 225201 | BH2: 225301 | BI2: 225302 | BJ2: 225303 | BK2: 225304 | BL2: 225305 | BM2: 225401 | BN2: 225501 | BO2: 225601 | BP2: 225701 | BQ2: 225801 | BR2: 225901 | BS2: 226101 | BT2: 226201 | BU2: 226301 | BV2: 226401 | BW2: 227101 | BX2: 227102 | BY2: 227103 | BZ2: 227104 | CA2: 227105 | CB2: 227106 | CC2: 227107 | CD2: 227199 | CE2: 227201 | CF2: 227202 | CG2: 227203 | CH2: 227204 | CI2: 227205 | CJ2: 227206 | CK2: 227207 | CL2: 227208 | CM2: 227299 | CN2: 227301 | CO2: 228101 | CP2: 228201 | CQ2: 228301 | CR2: 228401 | CS2: 228501 | CT2: 228502 | CU2: 228503 | CV2: 228601 | CW2: 228602 | CX2: 228603 | CY2: 228604 | CZ2: 228701 | DA2: 228702 | DB2: 228703 | DC2: 228704 | DD2: 228705 | DE2: 228706 | DF2: 228801 | DG2: 228802 | DH2: 228803 | DI2: 229201 | DJ2: 229203 | DK2: 231101 | DL2: 231102 | DM2: 231201 | DN2: 231301 | DO2: 231302 | DP2: 231303 | DQ2: 231401 | DR2: 232101 | DS2: 232201 | DT2: 232301 | DU2: 233101 | DV2: 233201 | DW2: 233301 | DX2: 233401 | DY2: 233501 | DZ2: 233601 | EA2: 234101 | EB2: 234201 | EC2: 235101 | ED2: 235201 | EE2: 235301 | EF2: 235401 | EG2: 235501 | EH2: 236101 | EI2: 236102 | EJ2: 236103 | EK2: 236104 | EL2: 236105 | EM2: 236201 | EN2: 236202 | EO2: 236203 | EP2: 236304 | EQ2: 236305 | ER2: 236306 | ES2: 236401 | ET2: 236402 | EU2: 236403 | EV2: 236404 | EW2: 236405 | EX2: 236406 | EY2: 236407 | EZ2: 236901 | FA2: 237101 | FB2: 237102 | FC2: 237103 | FD2: 237104 | FE2: 237105 | FF2: 237106 | FG2: 237107 | FH2: 237201 | FI2: 237202 | FJ2: 237203 | FK2: 237204 | FL2: 237205 | FM2: 237206 | FN2: 237299 | FO2: 238101 | FP2: 238201 | FQ2: 239101 | FR2: 239102 | FS2: 239201 | FT2: 239301 | FU2: 239401 | FV2: 239501 | FW2: 239601 | FX2: 239701 | FY2: 239801 | FZ2: 239802 | GA2: 239901 | GB2: 239904 | GC2: 241201 | GD2: 241202 | GE2: 241203 | GF2: 241204 | GG2: 241205 | GH2: 261101 | GI2: 261201 | GJ2: 261301 | GK2: 261401 | GL2: 261901 | GM2: 262101 | GN2: 262201 | GO2: 262301 | GP2: 262401 | GQ2: 263101 | GR2: 263201 | GS2: 263301 | GT2: 263401 | GU2: 264101 | GV2: 264201 | GW2: 264301 | GX2: 264401 | GY2: 264501 | GZ2: 264601 | HA2: 264701 | HB2: 264801 | HC2: 265101 | HD2: 265201 | HE2: 265301 | HF2: 265401 | HG2: 265501 | HH2: 265601 | HI2: 265701 | HJ2: 265801 | HK2: 266101 | HL2: 266201 | HM2: 267101 | HN2: 267201 | HO2: 267301 | HP2: 267401 | HQ2: 267501 | HR2: 267601 | HS2: 267701 | HT2: 267801 | HU2: 267901 | HV2: 268101 | HW2: 268201 | HX2: 268301 | HY2: 268302 | HZ2: 268401 | IA2: 268501 | IB2: 268601 | IC2: 268701 | ID2: 268802 | IE2: 268803 | IF2: 268804 | IG2: 268901 | IH2: 269101 | II2: 269102 | IJ2: 269201 | IK2: 269202 | IL2: 269301 | IM2: 269401 | IN2: 269501 | IO2: 269502 | IP2: 269503 | IQ2: 2269901 | IR2: 271101 | IS2: 271201 | IT2: 271301 | IU2: 271401 | IV2: 272101 | IW2: 272201 | IX2: 272301 | IY2: 272401 | IZ2: 272501 | JA2: 272601 | JB2: 272701 | JC2: 272801 | JD2: 272901 | JE2: 273101 | JF2: 273201 | JG2: 274101 | JH2: 274201 | JI2: Totales | JJ2: TRANSF NO. | JK2: VALOR | JL2: RETENCION | JM2: AÑOS ANTERIORES | JN2: 2022 | JO2: Total | JP2: Proveedor Informal
FT3: 272108 | JI3: =SUM(A3:JH3) -> 272108 | JJ3: 4930 | JO3: =+JM3+JN3 -> 0
FT4: 252331.2 | JI4: =SUM(A4:JH4) -> 252331.2 | JJ4: 4934
FT5: 224294.4 | JI5: =SUM(A5:JH5) -> 224294.4 | JJ5: 4938
FJ6: 17504.5 | JI6: =SUM(A6:JH6) -> 17504.5 | JJ6: 4942
DW7: 271695 | JI7: =SUM(A7:JH7) -> 271695 | JJ7: 4953
FT8: 138591 | JI8: =SUM(A8:JH8) -> 138591 | JJ8: 4960
EA9: 71400 | JI9: =SUM(A9:JH9) -> 71400 | JJ9: 4961
FT10: 255284.8 | JI10: =SUM(A10:JH10) -> 255284.8 | JJ10: 4965
EA11: 87500 | JI11: =SUM(A11:JH11) -> 87500 | JJ11: 4969
FT12: 247800 | JI12: =SUM(A12:JH12) -> 247800 | JJ12: 4974
FT13: 101786 | JI13: =SUM(A13:JH13) -> 101786 | JJ13: 4977
FT14: 138591 | JI14: =SUM(A14:JH14) -> 138591 | JJ14: 4981
EA15: 97435 | JI15: =SUM(A15:JH15) -> 97435 | JJ15: 4988
FT16: 1513350 | JI16: =SUM(A16:JH16) -> 1513350 | JJ16: 4989
FT17: 96946.88 | JI17: =SUM(A17:JH17) -> 96946.88 | JJ17: 4993
FJ18: 80000 | JI18: =SUM(A18:JH18) -> 80000 | JJ18: 4997
FJ19: 249166 | FT19: 23128 | JI19: =SUM(A19:JH19) -> 272294 | JJ19: 5001
BX20: 30861.53 | EG20: 18154.65 | JI20: =SUM(A20:JH20) -> 49016.18 | JJ20: 5014
EA21: 260000 | JI21: =SUM(A21:JH21) -> 260000 | JJ21: 5016
GH22: 31507.02 | JI22: =SUM(A22:JH22) -> 31507.02 | JJ22: 5021
GQ23: 1791000 | JI23: =SUM(A23:JH23) -> 1791000 | JJ23: 5026
HF24: 42057.86 | JI24: =SUM(A24:JH24) -> 42057.86 | JJ24: 5031
FT25: 247800 | JI25: =SUM(A25:JH25) -> 247800 | JJ25: 5032
HI26: 22585.2 | JI26: =SUM(A26:JH26) -> 22585.2 | JJ26: 5040
GR27: 59000 | JI27: =SUM(A27:JH27) -> 59000 | JJ27: 5041
FS28: 225498 | JI28: =SUM(A28:JH28) -> 225498 | JJ28: 5045
EA29: 192000 | JI29: =SUM(A29:JH29) -> 192000 | JJ29: 5049
FT30: 54000 | JI30: =SUM(A30:JH30) -> 54000 | JJ30: 5054
EA31: 33000 | FT31: 15599.6 | JI31: =SUM(A31:JH31) -> 48599.6 | JJ31: 5058
GH32: 58174 | GK32: 38940 | JI32: =SUM(A32:JH32) -> 97114 | JJ32: 5072
Q33: 51000 | JI33: =SUM(A33:JH33) -> 51000 | JJ33: 5074
R34: 479819.29 | JI34: =SUM(A34:JH34) -> 479819.29 | JJ34: 5076
FT35: 102987.84 | JI35: =SUM(A35:JH35) -> 102987.84 | JJ35: 5082
FQ36: 1207966 | JI36: =SUM(A36:JH36) -> 1207966 | JJ36: 5086
DK37: 292565.2 | JI37: =SUM(A37:JH37) -> 292565.2 | JJ37: 5090
GQ38: 1500000.7 | JI38: =SUM(A38:JH38) -> 1500000.7 | JJ38: 5101
DR39: 557734.03 | JI39: =SUM(A39:JH39) -> 557734.03 | JJ39: 5105
CH40: 5691.23 | JI40: =SUM(A40:JH40) -> 5691.23 | JJ40: 5125
AV41: 60535 | JI41: =SUM(A41:JH41) -> 60535 | JJ41: 5145
EA42: 1155000 | JI42: =SUM(A42:JH42) -> 1155000 | JJ42: 5149
GQ43: 191750 | JI43: =SUM(A43:JH43) -> 191750 | JJ43: 5158
FJ44: 753004.12 | FQ44: 86005 | JI44: =SUM(A44:JH44) -> 839009.12 | JJ44: 5162
N45: 9000 | JI45: =SUM(A45:JH45) -> 9000 | JJ45: 5170
N46: 1132781 | JI46: =SUM(A46:JH46) -> 1132781 | JJ46: 5172
N47: 1229710.5 | JI47: =SUM(A47:JH47) -> 1229710.5 | JJ47: 5174
N48: 57796367 | JI48: =SUM(A48:JH48) -> 57796367 | JJ48: 5176
N49: 45000 | JI49: =SUM(A49:JH49) -> 45000 | JJ49: 5178
EA50: 240000 | JI50: =SUM(A50:JH50) -> 240000 | JJ50: 5184
BW51: 1575209.4 | JI51: =SUM(A51:JH51) -> 1575209.4 | JJ51: 5190
DV52: 224790 | JI52: =SUM(A52:JH52) -> 224790 | JJ52: 5197
DV53: 221958 | JI53: =SUM(A53:JH53) -> 221958 | JJ53: 5201
DW54: 196470 | JI54: =SUM(A54:JH54) -> 196470 | JJ54: 5205
W55: 75000 | JI55: =SUM(A55:JH55) -> 75000 | JJ55: 5215
J56: 1342531 | AK56: 95185.45 | AL56: 95319.7 | AM56: 15830.76 | JI56: =SUM(A56:JH56) -> 1548866.9 | JJ56: 5217
A57: 59046800 | S57: 2652914.7 | Z57: 317800 | AB57: =101150.82+168584.7 -> 269735.52 | AK57: 4186418.9 | AL57: 4192324.5 | AM57: 707273.3 | JI57: =SUM(A57:JH57) -> 71373267 | JJ57: 5219
EA58: 33000 | FT58: 34314.4 | JI58: =SUM(A58:JH58) -> 67314.4 | JJ58: 5223
GB59: 66552 | JI59: =SUM(A59:JH59) -> 66552 | JJ59: 5227
EA60: 250000 | JI60: =SUM(A60:JH60) -> 250000 | JJ60: 5231
FT61: 240720 | JI61: =SUM(A61:JH61) -> 240720 | JJ61: 5235
GQ62: 134639.3 | JI62: =SUM(A62:JH62) -> 134639.3 | JJ62: 5247
DV63: 220070 | JI63: =SUM(A63:JH63) -> 220070 | JJ63: 5258
FQ64: 79650 | JI64: =SUM(A64:JH64) -> 79650 | JJ64: 5262
EA65: 1155000 | JI65: =SUM(A65:JH65) -> 1155000 | JJ65: 5282
FJ66: 239138.55 | JI66: =SUM(A66:JH66) -> 239138.55 | JJ66: 5290
DW67: 269040 | JI67: =SUM(A67:JH67) -> 269040 | JJ67: 5295
GQ68: 784700 | JI68: =SUM(A68:JH68) -> 784700 | JJ68: 5301
FJ69: 190680 | JI69: =SUM(A69:JH69) -> 190680 | JJ69: 5309
CQ70: 224500 | JI70: =SUM(A70:JH70) -> 224500 | JJ70: 5313
FJ71: 188482 | JI71: =SUM(A71:JH71) -> 188482 | JJ71: 5317
GT72: 1456293.2 | JI72: =SUM(A72:JH72) -> 1456293.2 | JJ72: 5323
FT73: 51448 | JI73: =SUM(A73:JH73) -> 51448 | JJ73: 5327
GQ74: 1899800 | JI74: =SUM(A74:JH74) -> 1899800 | JJ74: 5333
FT75: 17700 | JI75: =SUM(A75:JH75) -> 17700 | JJ75: 5339
FJ76: 88560 | JI76: =SUM(A76:JH76) -> 88560 | JJ76: 5343
FJ77: 165195.2 | JI77: =SUM(A77:JH77) -> 165195.2 | JJ77: 5347
DV78: 251517 | JI78: =SUM(A78:JH78) -> 251517 | JJ78: 5351
FZ79: 15340 | JI79: =SUM(A79:JH79) -> 15340 | JJ79: 5355
A80: =SUM(A3:A79) -> 59046800 | B80: =SUM(B3:B79) -> 0 | C80: =SUM(C3:C79) -> 0 | D80: =SUM(D3:D79) -> 0 | E80: =SUM(E3:E79) -> 0 | F80: =SUM(F3:F79) -> 0 | G80: =SUM(G3:G79) -> 0 | H80: =SUM(H3:H79) -> 0 | ... JI80: =SUM(JI3:JI79) -> 157427908 | JN80: =SUM(JN3:JN56) -> 0 | JO80: =SUM(JO3:JO56) -> 0 | JP80: =SUM(JP3:JP56) -> 0
A81: 211101 | B81: 211102 | C81: 211103 | D81: 211104 | E81: 211105 | F81: 211106 | G81: 211203 | H81: 211205 | I81: 211206 | J81: 211208 | K81: 211209 | L81: 211211 | M81: 211301 | N81: 211401 | O81: 211501 | P81: 211502 | Q81: 211503 | R81: 211504 | S81: 212101 | T81: 212201 | U81: 212203 | V81: 212204 | W81: 212205 | X81: 212206 | Y81: 212207 | Z81: 212208 | AA81: 212209 | AB81: 212210 | AC81: 213101 | AD81: 213102 | AE81: 213201 | AF81: 213202 | AG81: 214101 | AH81: 214201 | AI81: 214202 | AJ81: 214203 | AK81: 215101 | AL81: 215201 | AM81: 215301 | AN81: 215401 | AO81: 221101 | AP81: 221201 | AQ81: 221301 | AR81: 221401 | AS81: 221501 | AT81: 221601 | AU81: 221602 | AV81: 221701 | AW81: 221801 | AX81: 222101 | AY81: 222201 | AZ81: 223101 | BA81: 223201 | BB81: 224101 | BC81: 224201 | BD81: 224301 | BE81: 224401 | BF81: 225101 | BG81: 225201 | BH81: 225301 | BI81: 225302 | BJ81: 225303 | BK81: 225304 | BL81: 225305 | BM81: 225401 | BN81: 225501 | BO81: 225601 | BP81: 225701 | BQ81: 225801 | BR81: 225901 | BS81: 226101 | BT81: 226201 | BU81: 226301 | BV81: 226401 | BW81: 227101 | BX81: 227102 | BY81: 227103 | BZ81: 227104 | CA81: 227105 | CB81: 227106 | CC81: 227107 | CD81: 227199 | CE81: 227201 | CF81: 227202 | CG81: 227203 | CH81: 227204 | CI81: 227205 | CJ81: 227206 | CK81: 227207 | CL81: 227208 | CM81: 227299 | CN81: 227301 | CO81: 228101 | CP81: 228201 | CQ81: 228301 | CR81: 228401 | CS81: 228501 | CT81: 228502 | CU81: 228503 | CV81: 228601 | CW81: 228602 | CX81: 228603 | CY81: 228604 | CZ81: 228701 | DA81: 228702 | DB81: 228703 | DC81: 228704 | DD81: 228705 | DE81: 228706 | DF81: 228801 | DG81: 228802 | DH81: 228803 | DI81: 229201 | DJ81: 229203 | DK81: 231101 | DL81: 231102 | DM81: 231201 | DN81: 231301 | DO81: 231302 | DP81: 231303 | DQ81: 231401 | DR81: 232101 | DS81: 232201 | DT81: 232301 | DU81: 233101 | DV81: 233201 | DW81: 233301 | DX81: 233401 | DY81: 233501 | DZ81: 233601 | EA81: 234101 | EB81: 234201 | EC81: 235101 | ED81: 235201 | EE81: 235301 | EF81: 235401 | EG81: 235501 | EH81: 236101 | EI81: 236102 | EJ81: 236103 | EK81: 236104 | EL81: 236105 | EM81: 236201 | EN81: 236202 | EO81: 236203 | EP81: 236304 | EQ81: 236305 | ER81: 236306 | ES81: 236401 | ET81: 236402 | EU81: 236403 | EV81: 236404 | EW81: 236405 | EX81: 236406 | EY81: 236407 | EZ81: 236901 | FA81: 237101 | FB81: 237102 | FC81: 237103 | FD81: 237104 | FE81: 237105 | FF81: 237106 | FG81: 237107 | FH81: 237201 | FI81: 237202 | FJ81: 237203 | FK81: 237204 | FL81: 237205 | FM81: 237206 | FN81: 237299 | FO81: 238101 | FP81: 238201 | FQ81: 239101 | FR81: 239102 | FS81: 239201 | FT81: 239301 | FU81: 239401 | FV81: 239501 | FW81: 239601 | FX81: 239701 | FY81: 239801 | FZ81: 239802 | GA81: 239901 | GB81: 239904 | GC81: 241201 | GD81: 241202 | GE81: 241203 | GF81: 241204 | GG81: 241205 | GH81: 261101 | GI81: 261201 | GJ81: 261301 | GK81: 261401 | GL81: 261901 | GM81: 262101 | GN81: 262201 | GO81: 262301 | GP81: 262401 | GQ81: 263101 | GR81: 263201 | GS81: 263301 | GT81: 263401 | GU81: 264101 | GV81: 264201 | GW81: 264301 | GX81: 264401 | GY81: 264501 | GZ81: 264601 | HA81: 264701 | HB81: 264801 | HC81: 265101 | HD81: 265201 | HE81: 265301 | HF81: 265401 | HG81: 265501 | HH81: 265601 | HI81: 265701 | HJ81: 265801 | HK81: 266101 | HL81: 266201 | HM81: 267101 | HN81: 267201 | HO81: 267301 | HP81: 267401 | HQ81: 267501 | HR81: 267601 | HS81: 267701 | HT81: 267801 | HU81: 267901 | HV81: 268101 | HW81: 268201 | HX81: 268301 | HY81: 268302 | HZ81: 268401 | IA81: 268501 | IB81: 268601 | IC81: 268701 | ID81: 268802 | IE81: 268803 | IF81: 268804 | IG81: 268901 | IH81: 269101 | II81: 269102 | IJ81: 269201 | IK81: 269202 | IL81: 269301 | IM81: 269401 | IN81: 269501 | IO81: 269502 | IP81: 269503 | IQ81: 2269901 | IR81: 271101 | IS81: 271201 | IT81: 271301 | IU81: 271401 | IV81: 272101 | IW81: 272201 | IX81: 272301 | IY81: 272401 | IZ81: 272501 | JA81: 272601 | JB81: 272701 | JC81: 272801 | JD81: 272901 | JE81: 273101 | JF81: 273201 | JG81: 274101 | JH81: 274201 | JI81: Totales | JK81: =SUM(JK3:JK57) -> 0 | JL81: =SUM(JL3:JL57) -> 0 | JM81: =SUM(JM3:JM57) -> 0
JI82: =SUM(A82:JH82) -> 0
JI83: =SUM(A83:JH83) -> 0
JI84: =SUM(A84:JH84) -> 0
JI85: =SUM(A85:JH85) -> 0
JI86: =SUM(A86:JH86) -> 0
JI87: =SUM(A87:JH87) -> 0
JI88: =SUM(A88:JH88) -> 0
JI89: =SUM(A89:JH89) -> 0
JI90: =SUM(A90:JH90) -> 0
JI91: =SUM(A91:JH91) -> 0
JI92: =SUM(A92:JH92) -> 0
JI93: =SUM(A93:JH93) -> 0
... JI95: =SUM(A95:JH95) -> 0
A96: =SUM(A82:A95) -> 0 | B96: =SUM(B82:B95) -> 0 | C96: =SUM(C82:C95) -> 0 | D96: =SUM(D82:D95) -> 0 | E96: =SUM(E82:E95) -> 0 | F96: =SUM(F82:F95) -> 0 | G96: =SUM(G82:G95) -> 0 | H96: =SUM(H82:H95) -> 0 | ... JI96: =SUM(JI82:JI95) -> 0
A97: =A80+A96 -> 59046800 | B97: =B80+B96 -> 0 | C97: =C80+C96 -> 0 | D97: =D80+D96 -> 0 | E97: =E80+E96 -> 0 | F97: =F80+F96 -> 0 | G97: =G80+G96 -> 0 | H97: =H80+H96 -> 0 | ... JI97: =JI80+JI96 -> 157427908

Sheet CUENTA T VS
A1: D E S G L O S E D E L A S C U E N T A S
A2: 211101 | B2: 211102 | C2: 211103 | D2: 211104 | E2: 211105 | F2: 211106 | G2: 211203 | H2: 211205 | I2: 211206 | J2: 211208 | K2: 211209 | L2: 211211 | M2: 211301 | N2: 211401 | O2: 211501 | P2: 211502 | Q2: 211503 | R2: 211504 | S2: 212101 | T2: 212201 | U2: 212203 | V2: 212204 | W2: 212205 | X2: 212206 | Y2: 212207 | Z2: 212208 | AA2: 212209 | AB2: 212210 | AC2: 213101 | AD2: 213102 | AE2: 213201 | AF2: 213202 | AG2: 214101 | AH2: 214201 | AI2: 214202 | AJ2: 214203 | AK2: 215101 | AL2: 215201 | AM2: 215301 | AN2: 215401 | AO2: 221101 | AP2: 221201 | AQ2: 221301 | AR2: 221401 | AS2: 221501 | AT2: 221601 | AU2: 221602 | AV2: 221701 | AW2: 221801 | AX2: 222101 | AY2: 222201 | AZ2: 223101 | BA2: 223201 | BB2: 224101 | BC2: 224201 | BD2: 224301 | BE2: 224401 | BF2: 225101 | BG2: 225201 | BH2: 225301 | BI2: 225302 | BJ2: 225303 | BK2: 225304 | BL2: 225305 | BM2: 225401 | BN2: 225501 | BO2: 225601 | BP2: 225701 | BQ2: 225801 | BR2: 225901 | BS2: 226101 | BT2: 226201 | BU2: 226301 | BV2: 226401 | BW2: 227101 | BX2: 227102 | BY2: 227103 | BZ2: 227104 | CA2: 227105 | CB2: 227106 | CC2: 227107 | CD2: 227199 | CE2: 227201 | CF2: 227202 | CG2: 227203 | CH2: 227204 | CI2: 227205 | CJ2: 227206 | CK2: 227207 | CL2: 227208 | CM2: 227299 | CN2: 227301 | CO2: 228101 | CP2: 228201 | CQ2: 228301 | CR2: 228401 | CS2: 228501 | CT2: 228502 | CU2: 228503 | CV2: 228601 | CW2: 228602 | CX2: 228603 | CY2: 228604 | CZ2: 228701 | DA2: 228702 | DB2: 228703 | DC2: 228704 | DD2: 228705 | DE2: 228706 | DF2: 228801 | DG2: 228802 | DH2: 228803 | DI2: 229201 | DJ2: 229203 | DK2: 231101 | DL2: 231102 | DM2: 231201 | DN2: 231301 | DO2: 231302 | DP2: 231303 | DQ2: 231401 | DR2: 232101 | DS2: 232201 | DT2: 232301 | DU2: 233101 | DV2: 233201 | DW2: 233301 | DX2: 233401 | DY2: 233501 | DZ2: 233601 | EA2: 234101 | EB2: 234201 | EC2: 235101 | ED2: 235201 | EE2: 235301 | EF2: 235401 | EG2: 235501 | EH2: 236101 | EI2: 236102 | EJ2: 236103 | EK2: 236104 | EL2: 236105 | EM2: 236201 | EN2: 236202 | EO2: 236203 | EP2: 236304 | EQ2: 236305 | ER2: 236306 | ES2: 236401 | ET2: 236402 | EU2: 236403 | EV2: 236404 | EW2: 236405 | EX2: 236406 | EY2: 236407 | EZ2: 236901 | FA2: 237101 | FB2: 237102 | FC2: 237103 | FD2: 237104 | FE2: 237105 | FF2: 237106 | FG2: 237107 | FH2: 237201 | FI2: 237202 | FJ2: 237203 | FK2: 237204 | FL2: 237205 | FM2: 237206 | FN2: 237299 | FO2: 238101 | FP2: 238201 | FQ2: 239101 | FR2: 239102 | FS2: 239201 | FT2: 239301 | FU2: 239401 | FV2: 239501 | FW2: 239601 | FX2: 239701 | FY2: 239801 | FZ2: 239802 | GA2: 239901 | GB2: 239904 | GC2: 241201 | GD2: 241202 | GE2: 241203 | GF2: 241204 | GG2: 241205 | GH2: 261101 | GI2: 261201 | GJ2: 261301 | GK2: 261401 | GL2: 261901 | GM2: 262101 | GN2: 262201 | GO2: 262301 | GP2: 262401 | GQ2: 263101 | GR2: 263201 | GS2: 263301 | GT2: 263401 | GU2: 264101 | GV2: 264201 | GW2: 264301 | GX2: 264401 | GY2: 264501 | GZ2: 264601 | HA2: 264701 | HB2: 264801 | HC2: 265101 | HD2: 265201 | HE2: 265301 | HF2: 265401 | HG2: 265501 | HH2: 265601 | HI2: 265701 | HJ2: 265801 | HK2: 266101 | HL2: 266201 | HM2: 267101 | HN2: 267201 | HO2: 267301 | HP2: 267401 | HQ2: 267501 | HR2: 267601 | HS2: 267701 | HT2: 267801 | HU2: 267901 | HV2: 268101 | HW2: 268201 | HX2: 268301 | HY2: 268302 | HZ2: 268401 | IA2: 268501 | IB2: 268601 | IC2: 268701 | ID2: 268802 | IE2: 268803 | IF2: 268804 | IG2: 268901 | IH2: 269101 | II2: 269102 | IJ2: 269201 | IK2: 269202 | IL2: 269301 | IM2: 269401 | IN2: 269501 | IO2: 269502 | IP2: 269503 | IQ2: 2269901 | IR2: 271101 | IS2: 271201 | IT2: 271301 | IU2: 271401 | IV2: 272101 | IW2: 272201 | IX2: 272301 | IY2: 272401 | IZ2: 272501 | JA2: 272601 | JB2: 272701 | JC2: 272801 | JD2: 272901 | JE2: 273101 | JF2: 273201 | JG2: 274101 | JH2: 274201 | JI2: Totales | JJ2: TRANSF NO. | JK2: VALOR | JL2: RETENCION | JM2: AÑOS ANTERIORES | JN2: 2022 | JO2: Total | JP2: Proveedor Informal
AW3: 720000 | JI3: =SUM(A3:JH3) -> 720000 | JJ3: 372 | JK3: 684000 | JL3: =+JI3-JK3 -> 36000
CL4: 361378.54 | JI4: =SUM(A4:JH4) -> 361378.54 | JJ4: 373 | JK4: 346065.89 | JL4: =+JI4-JK4 -> 15312.65
FQ5: 158061 | JI5: =SUM(A5:JH5) -> 158061 | JJ5: 379 | JK5: 151363.5 | JL5: =+JI5-JK5 -> 6697.5
DK6: 15000 | JI6: =SUM(A6:JH6) -> 15000 | JJ6: 380 | JK6: 15000 | JL6: =+JI6-JK6 -> 0
DK7: 14000 | JI7: =SUM(A7:JH7) -> 14000 | JJ7: 381 | JK7: 14000 | JL7: =+JI7-JK7 -> 0
HH8: 413000 | JI8: =SUM(A8:JH8) -> 413000 | JJ8: 382 | JK8: 395500 | JL8: =+JI8-JK8 -> 17500
GB9: 175173.19 | JI9: =SUM(A9:JH9) -> 175173.19 | JJ9: 383 | JK9: 166414.53 | JL9: =+JI9-JK9 -> 8758.66
GB10: 244226.81 | JI10: =SUM(A10:JH10) -> 244226.81 | JJ10: 384 | JK10: 233878.22 | JL10: =+JI10-JK10 -> 10348.59
FW11: 41819.2 | JI11: =SUM(A11:JH11) -> 41819.2 | JJ11: 385 | JK11: 40047.2 | JL11: =+JI11-JK11 -> 1772
JI12: =SUM(A12:JH12) -> 0 | JJ12: 386 | JK12: 0 | JL12: =+JI12-JK12 -> 0
CU13: 185260 | JI13: =SUM(A13:JH13) -> 185260 | JJ13: 387 | JK13: 177410 | JL13: =+JI13-JK13 -> 7850
FD14: 21952 | JI14: =SUM(A14:JH14) -> 21952 | JJ14: 388 | JK14: 21952 | JL14: =+JI14-JK14 -> 0
AW15: 25000 | JI15: =SUM(A15:JH15) -> 25000 | JJ15: 389 | JK15: 25000 | JL15: =+JI15-JK15 -> 0
DD16: 244260 | JI16: =SUM(A16:JH16) -> 244260 | JJ16: 390 | JK16: 233910 | JL16: =+JI16-JK16 -> 10350
FN17: 140797.6 | JI17: =SUM(A17:JH17) -> 140797.6 | JJ17: 391 | JK17: 134831.6 | JL17: =+JI17-JK17 -> 5966
GR18: 1899800 | JI18: =SUM(A18:JH18) -> 1899800 | JJ18: 392 | JK18: 1819300 | JL18: =+JI18-JK18 -> 80500
DE19: 16520 | JI19: =SUM(A19:JH19) -> 16520 | JJ19: 393 | JK19: 16520 | JL19: =+JI19-JK19 -> 0
DK20: 41400 | JI20: =SUM(A20:JH20) -> 41400 | JJ20: 394 | JK20: 41400 | JL20: =+JI20-JK20 -> 0
EA21: 270000 | JI21: =SUM(A21:JH21) -> 270000 | JJ21: 395 | JK21: 256500 | JL21: =+JI21-JK21 -> 13500
FQ22: 262500 | JI22: =SUM(A22:JH22) -> 262500 | JJ22: 396 | JK22: 249375 | JL22: =+JI22-JK22 -> 13125
FA23: 172000 | JI23: =SUM(A23:JH23) -> 172000 | JJ23: 397 | JK23: 170573.26 | JL23: =+JI23-JK23 -> 1426.74
DK24: 92925 | JI24: =SUM(A24:JH24) -> 92925 | JJ24: 398 | JK24: 88278.75 | JL24: =+JI24-JK24 -> 4646.25
DE25: 10000 | JI25: =SUM(A25:JH25) -> 10000 | JJ25: 399 | JK25: 10000 | JL25: =+JI25-JK25 -> 0
EA26: 114300 | JI26: =SUM(A26:JH26) -> 114300 | JJ26: 400 | JK26: 108585 | JL26: =+JI26-JK26 -> 5715
EE27: 298561.92 | JI27: =SUM(A27:JH27) -> 298561.92 | JJ27: 401 | JK27: 272247.99 | JL27: =+JI27-JK27 -> 26313.93
GH28: 182234.7 | JI28: =SUM(A28:JH28) -> 182234.7 | JJ28: 402 | JK28: 174512.67 | JL28: =+JI28-JK28 -> 7722.03
AX29: 221258.85 | JI29: =SUM(A29:JH29) -> 221258.85 | JJ29: 403 | JK29: 211883.48 | JL29: =+JI29-JK29 -> 9375.37
GH30: 260210.02 | JI30: =SUM(A30:JH30) -> 260210.02 | JJ30: 404 | JK30: 249184.17 | JL30: =+JI30-JK30 -> 11025.85
FT31: 30444 | JI31: =SUM(A31:JH31) -> 30444 | JJ31: 405 | JK31: 30444 | JL31: =+JI31-JK31 -> 0
FT32: 34220 | JI32: =SUM(A32:JH32) -> 34220 | JJ32: 406 | JK32: 34220 | JL32: =+JI32-JK32 -> 0
DE33: 195000 | JI33: =SUM(A33:JH33) -> 195000 | JJ33: 407 | JK33: 195000 | JL33: =+JI33-JK33 -> 0
DE34: 13260 | JI34: =SUM(A34:JH34) -> 13260 | JJ34: 408 | JK34: 13260 | JL34: =+JI34-JK34 -> 0
JI35: =SUM(A35:JH35) -> 0 | JJ35: 37317 | JK35: 0 | JL35: =+JI35-JK35 -> 0
GA36: 56945.15 | JI36: =SUM(A36:JH36) -> 56945.15 | JJ36: 37318 | JK36: 56945.15 | JL36: =+JI36-JK36 -> 0
BW37: 21673.47 | JI37: =SUM(A37:JH37) -> 21673.47 | JJ37: 37319 | JK37: 18000 | JL37: =+JI37-JK37 -> 3673.47
BW38: 18061.22 | JI38: =SUM(A38:JH38) -> 18061.22 | JJ38: 37320 | JK38: 15000 | JL38: =+JI38-JK38 -> 3061.22
BW39: 18061.22 | JI39: =SUM(A39:JH39) -> 18061.22 | JJ39: 37321 | JK39: 15000 | JL39: =+JI39-JK39 -> 3061.22
GC40: 3600 | JI40: =SUM(A40:JH40) -> 3600 | JJ40: 37322 | JK40: 3600 | JL40: =+JI40-JK40 -> 0
BB41: 20000 | JI41: =SUM(A41:JH41) -> 20000 | JJ41: 37323 | JK41: 20000 | JL41: =+JI41-JK41 -> 0
DF42: 14087.24 | JI42: =SUM(A42:JH42) -> 14087.24 | JK42: 14087.24 | JL42: =+JI42-JK42 -> 0
JI43: =SUM(A43:JH43) -> 0 | JL43: =+JI43-JK43 -> 0
JI44: =SUM(A44:JH44) -> 0 | JL44: =+JI44-JK44 -> 0
JI45: =SUM(A45:JH45) -> 0 | JL45: =+JI45-JK45 -> 0
JI46: =SUM(A46:JH46) -> 0 | JL46: =+JI46-JK46 -> 0
JI47: =SUM(A47:JH47) -> 0 | JL47: =+JI47-JK47 -> 0
JI48: =SUM(A48:JH48) -> 0 | JL48: =+JI48-JK48 -> 0
JI49: =SUM(A49:JH49) -> 0 | JL49: =+JI49-JK49 -> 0
JI50: =SUM(A50:JH50) -> 0 | JL50: =+JI50-JK50 -> 0
JI51: =SUM(A51:JH51) -> 0 | JL51: =+JI51-JK51 -> 0
JI52: =SUM(A52:JH52) -> 0 | JL52: =+JI52-JK52 -> 0
JI53: =SUM(A53:JH53) -> 0 | JL53: =+JI53-JK53 -> 0
JI54: =SUM(A54:JH54) -> 0 | JL54: =+JI54-JK54 -> 0
... JI57: =SUM(A57:JH57) -> 0 | JL57: =+JI57-JK57 -> 0
A58: =SUM(A3:A57) -> 0 | B58: =SUM(B3:B57) -> 0 | C58: =SUM(C3:C57) -> 0 | D58: =SUM(D3:D57) -> 0 | E58: =SUM(E3:E57) -> 0 | F58: =SUM(F3:F57) -> 0 | G58: =SUM(G3:G57) -> 0 | H58: =SUM(H3:H57) -> 0 | ... JI58: =SUM(JI3:JI57) -> 7026991.1 | JK58: =SUM(JK3:JK57) -> 6723289.7 | JL58: =SUM(JL3:JL57) -> 303701.48 | JM58: =SUM(JM3:JM57) -> 0 | JN58: =SUM(JN3:JN57) -> 0 | JO58: =SUM(JO3:JO57) -> 0 | JP58: =SUM(JP3:JP57) -> 0
A59: 211101 | B59: 211102 | C59: 211103 | D59: 211104 | E59: 211105 | F59: 211106 | G59: 211203 | H59: 211205 | I59: 211206 | J59: 211208 | K59: 211209 | L59: 211211 | M59: 211301 | N59: 211401 | O59: 211501 | P59: 211502 | Q59: 211503 | R59: 211504 | S59: 212101 | T59: 212201 | U59: 212203 | V59: 212204 | W59: 212205 | X59: 212206 | Y59: 212207 | Z59: 212208 | AA59: 212209 | AB59: 212210 | AC59: 213101 | AD59: 213102 | AE59: 213201 | AF59: 213202 | AG59: 214101 | AH59: 214201 | AI59: 214202 | AJ59: 214203 | AK59: 215101 | AL59: 215201 | AM59: 215301 | AN59: 215401 | AO59: 221101 | AP59: 221201 | AQ59: 221301 | AR59: 221401 | AS59: 221501 | AT59: 221601 | AU59: 221602 | AV59: 221701 | AW59: 221801 | AX59: 222101 | AY59: 222201 | AZ59: 223101 | BA59: 223201 | BB59: 224101 | BC59: 224201 | BD59: 224301 | BE59: 224401 | BF59: 225101 | BG59: 225201 | BH59: 225301 | BI59: 225302 | BJ59: 225303 | BK59: 225304 | BL59: 225305 | BM59: 225401 | BN59: 225501 | BO59: 225601 | BP59: 225701 | BQ59: 225801 | BR59: 225901 | BS59: 226101 | BT59: 226201 | BU59: 226301 | BV59: 226401 | BW59: 227101 | BX59: 227102 | BY59: 227103 | BZ59: 227104 | CA59: 227105 | CB59: 227106 | CC59: 227107 | CD59: 227199 | CE59: 227201 | CF59: 227202 | CG59: 227203 | CH59: 227204 | CI59: 227205 | CJ59: 227206 | CK59: 227207 | CL59: 227208 | CM59: 227299 | CN59: 227301 | CO59: 228101 | CP59: 228201 | CQ59: 228301 | CR59: 228401 | CS59: 228501 | CT59: 228502 | CU59: 228503 | CV59: 228601 | CW59: 228602 | CX59: 228603 | CY59: 228604 | CZ59: 228701 | DA59: 228702 | DB59: 228703 | DC59: 228704 | DD59: 228705 | DE59: 228706 | DF59: 228801 | DG59: 228802 | DH59: 228803 | DI59: 229201 | DJ59: 229203 | DK59: 231101 | DL59: 231102 | DM59: 231201 | DN59: 231301 | DO59: 231302 | DP59: 231303 | DQ59: 231401 | DR59: 232101 | DS59: 232201 | DT59: 232301 | DU59: 233101 | DV59: 233201 | DW59: 233301 | DX59: 233401 | DY59: 233501 | DZ59: 233601 | EA59: 234101 | EB59: 234201 | EC59: 235101 | ED59: 235201 | EE59: 235301 | EF59: 235401 | EG59: 235501 | EH59: 236101 | EI59: 236102 | EJ59: 236103 | EK59: 236104 | EL59: 236105 | EM59: 236201 | EN59: 236202 | EO59: 236203 | EP59: 236304 | EQ59: 236305 | ER59: 236306 | ES59: 236401 | ET59: 236402 | EU59: 236403 | EV59: 236404 | EW59: 236405 | EX59: 236406 | EY59: 236407 | EZ59: 236901 | FA59: 237101 | FB59: 237102 | FC59: 237103 | FD59: 237104 | FE59: 237105 | FF59: 237106 | FG59: 237107 | FH59: 237201 | FI59: 237202 | FJ59: 237203 | FK59: 237204 | FL59: 237205 | FM59: 237206 | FN59: 237299 | FO59: 238101 | FP59: 238201 | FQ59: 239101 | FR59: 239102 | FS59: 239201 | FT59: 239301 | FU59: 239401 | FV59: 239501 | FW59: 239601 | FX59: 239701 | FY59: 239801 | FZ59: 239802 | GA59: 239901 | GB59: 239904 | GC59: 241201 | GD59: 241202 | GE59: 241203 | GF59: 241204 | GG59: 241205 | GH59: 261101 | GI59: 261201 | GJ59: 261301 | GK59: 261401 | GL59: 261901 | GM59: 262101 | GN59: 262201 | GO59: 262301 | GP59: 262401 | GQ59: 263101 | GR59: 263201 | GS59: 263301 | GT59: 263401 | GU59: 264101 | GV59: 264201 | GW59: 264301 | GX59: 264401 | GY59: 264501 | GZ59: 264601 | HA59: 264701 | HB59: 264801 | HC59: 265101 | HD59: 265201 | HE59: 265301 | HF59: 265401 | HG59: 265501 | HH59: 265601 | HI59: 265701 | HJ59: 265801 | HK59: 266101 | HL59: 266201 | HM59: 267101 | HN59: 267201 | HO59: 267301 | HP59: 267401 | HQ59: 267501 | HR59: 267601 | HS59: 267701 | HT59: 267801 | HU59: 267901 | HV59: 268101 | HW59: 268201 | HX59: 268301 | HY59: 268302 | HZ59: 268401 | IA59: 268501 | IB59: 268601 | IC59: 268701 | ID59: 268802 | IE59: 268803 | IF59: 268804 | IG59: 268901 | IH59: 269101 | II59: 269102 | IJ59: 269201 | IK59: 269202 | IL59: 269301 | IM59: 269401 | IN59: 269501 | IO59: 269502 | IP59: 269503 | IQ59: 2269901 | IR59: 271101 | IS59: 271201 | IT59: 271301 | IU59: 271401 | IV59: 272101 | IW59: 272201 | IX59: 272301 | IY59: 272401 | IZ59: 272501 | JA59: 272601 | JB59: 272701 | JC59: 272801 | JD59: 272901 | JE59: 273101 | JF59: 273201 | JG59: 274101 | JH59: 274201
JI60: =SUM(A60:JH60) -> 0
JI61: =SUM(A61:JH61) -> 0
JI62: =SUM(A62:JH62) -> 0
JI63: =SUM(A63:JH63) -> 0
JI64: =SUM(A64:JH64) -> 0
JI65: =SUM(A65:JH65) -> 0
JI66: =SUM(A66:JH66) -> 0
JI67: =SUM(A67:JH67) -> 0
JI68: =SUM(A68:JH68) -> 0
JI69: =SUM(A69:JH69) -> 0
JI70: =SUM(A70:JH70) -> 0
JI71: =SUM(A71:JH71) -> 0
... JI73: =SUM(A73:JH73) -> 0
A74: =SUM(A60:A73) -> 0 | B74: =SUM(B60:B73) -> 0 | C74: =SUM(C60:C73) -> 0 | D74: =SUM(D60:D73) -> 0 | E74: =SUM(E60:E73) -> 0 | F74: =SUM(F60:F73) -> 0 | G74: =SUM(G60:G73) -> 0 | H74: =SUM(H60:H73) -> 0 | ... JH74: =SUM(JH60:JH73) -> 0 | JI74: =SUM(A74:JH74) -> 0
A75: =A58+A74 -> 0 | B75: =B58+B74 -> 0 | C75: =C58+C74 -> 0 | D75: =D58+D74 -> 0 | E75: =E58+E74 -> 0 | F75: =F58+F74 -> 0 | G75: =G58+G74 -> 0 | H75: =H58+H74 -> 0 | ... JH75: =JH58+JH74 -> 0 | JI75: =SUM(A75:JH75) -> 7026991.1

Sheet GASTOS X ATENCION
A1: SERVICIO NACIONAL DE SALUD
A2: ='CONS. FUENTES FINAN'!A6 -> HOSPITAL MATERNO INFANTIL SAN LORENZO DE LOS MINA
A3: RESUMEN COMPARATIVO DE GASTOS ESPECIFICOS FONDO 100 Y VENTA DE SERVICIOS
A6: DETALLE | B6: FONDO 100 | C6: VENTA SERVICIOS | D6: TOTAL | E6: %
A8: Atención Directa
A9: Medicamentos e Insumos Médicos | B9: ='CONS. FUENTES FINAN'!G245+'CONS. FUENTES FINAN'!G315 -> 7603116.1 | C9: ='CONS. FUENTES FINAN'!H245+'CONS. FUENTES FINAN'!H315 -> 448964 | D9: =SUM(B9:C9) -> 8052080.1 | E9: =+D9/D12 -> 0.79216828
A10: Oxigeno | B10: ='CONS. FUENTES FINAN'!G302 -> 0 | C10: ='CONS. FUENTES FINAN'!H302 -> 140797.6 | D10: =SUM(B10:C10) -> 140797.6 | E10: =+D10/D12 -> 0.013851749
A11: Reactivos e Insumos de Laboratorio | B11: ='CONS. FUENTES FINAN'!G296+'CONS. FUENTES FINAN'!G297+'CONS. FUENTES FINAN'!G298 -> 1971730.4 | C11: ='CONS. FUENTES FINAN'!H296+'CONS. FUENTES FINAN'!H297+'CONS. FUENTES FINAN'!H298 -> 0 | D11: =SUM(B11:C11) -> 1971730.4 | E11: =+D11/D12 -> 0.19397997
A12: Total | B12: =SUM(B9:B11) -> 9574846.5 | C12: =SUM(C9:C11) -> 589761.6 | D12: =SUM(D9:D11) -> 10164608 | E12: =+D12/D39 -> 0.061807876
A13: Mantenimiento de Equipos
A14: Reparación y Mantenimiento Maquinaria y Eq. | B14: ='CONS. FUENTES FINAN'!G157+'CONS. FUENTES FINAN'!G188+'CONS. FUENTES FINAN'!G223+'CONS. FUENTES FINAN'!G252+'CONS. FUENTES FINAN'!G254+'CONS. FUENTES FINAN'!G256+'CONS. FUENTES FINAN'!G258+'CONS. FUENTES FINAN'!G261+'CONS. FUENTES FINAN'!G292+'CONS. FUENTES FINAN'!G293+'CONS. FUENTES FINAN'!G299+'CONS. FUENTES FINAN'!G300+'CONS. FUENTES FINAN'!G301+'CONS. FUENTES FINAN'!G324 -> 1627102.1 | C14: ='CONS. FUENTES FINAN'!H157+'CONS. FUENTES FINAN'!H188+'CONS. FUENTES FINAN'!H223+'CONS. FUENTES FINAN'!H252+'CONS. FUENTES FINAN'!H254+'CONS. FUENTES FINAN'!H256+'CONS. FUENTES FINAN'!H258+'CONS. FUENTES FINAN'!H261+'CONS. FUENTES FINAN'!H292+'CONS. FUENTES FINAN'!H293+'CONS. FUENTES FINAN'!H299+'CONS. FUENTES FINAN'!H300+'CONS. FUENTES FINAN'!H301+'CONS. FUENTES FINAN'!H324 -> 902996.37 | D14: =SUM(B14:C14) -> 2530098.5 | E14: =+D14/D16 -> 0.98374007
A15: Productos Eléctricos y Afines | B15: ='CONS. FUENTES FINAN'!G320 -> 0 | C15: ='CONS. FUENTES FINAN'!H320 -> 41819.2 | D15: =SUM(B15:C15) -> 41819.2 | E15: =+D15/D16 -> 0.016259929
A16: Total | B16: =SUM(B14:B15) -> 1627102.1 | C16: =SUM(C14:C15) -> 944815.57 | D16: =SUM(D14:D15) -> 2571917.7 | E16: =+D16/D39 -> 0.015639046
A17: Gastos Administrativos
A18: Servicios Personales | B18: ='CONS. FUENTES FINAN'!G26 -> 1.3374081e+08 | C18: ='CONS. FUENTES FINAN'!H26 -> 0 | D18: =SUM(B18:C18) -> 1.3374081e+08 | E18: =+D18/D34 -> 0.94883482
A19: Servicio Telefónico | B19: ='CONS. FUENTES FINAN'!G91+'CONS. FUENTES FINAN'!G93+'CONS. FUENTES FINAN'!G95+'CONS. FUENTES FINAN'!G97 -> 0 | C19: ='CONS. FUENTES FINAN'!H91+'CONS. FUENTES FINAN'!H93+'CONS. FUENTES FINAN'!H95+'CONS. FUENTES FINAN'!H97 -> 0 | D19: =SUM(B19:C19) -> 0 | E19: =+D19/D34 -> 0
A20: Servicios Basicos (electricidad, agua y residuos solidos) | B20: ='CONS. FUENTES FINAN'!G99+'CONS. FUENTES FINAN'!G102+'CONS. FUENTES FINAN'!G104 -> 60535 | C20: ='CONS. FUENTES FINAN'!H99+'CONS. FUENTES FINAN'!H102+'CONS. FUENTES FINAN'!H104 -> 745000 | D20: =SUM(B20:C20) -> 805535 | E20: =+D20/D34 -> 0.0057149321
A21: Viáticos | B21: ='CONS. FUENTES FINAN'!G111 -> 0 | C21: ='CONS. FUENTES FINAN'!H111 -> 0 | D21: =SUM(B21:C21) -> 0 | E21: =+D21/D34 -> 0
A22: Transporte y almacenaje | B22: ='CONS. FUENTES FINAN'!G116 -> 0 | C22: ='CONS. FUENTES FINAN'!H116 -> 20000 | D22: =SUM(B22:C22) -> 20000 | E22: =+D22/D34 -> 0.00014189159
A23: Alquileres | B23: ='CONS. FUENTES FINAN'!G125 -> 0 | C23: ='CONS. FUENTES FINAN'!H125 -> 0 | D23: =SUM(B23:C23) -> 0 | E23: =+D23/D34 -> 0
A24: Comisiones y Gastos Bancarios | B24: ='CONS. FUENTES FINAN'!G182 -> 0 | C24: ='CONS. FUENTES FINAN'!H182 -> 0 | D24: =SUM(B24:C24) -> 0 | E24: =+D24/D34 -> 0
A25: Materiales de Oficina, Impresión y Encuadernación | B25: ='CONS. FUENTES FINAN'!G109+'CONS. FUENTES FINAN'!G312 -> 225498 | C25: ='CONS. FUENTES FINAN'!H109+'CONS. FUENTES FINAN'!H312 -> 0 | D25: =SUM(B25:C25) -> 225498 | E25: =+D25/D34 -> 0.0015998135
A26: Alimentos y Bebidas para Personas | B26: ='CONS. FUENTES FINAN'!G208+'CONS. FUENTES FINAN'!G214+'CONS. FUENTES FINAN'!G217+'CONS. FUENTES FINAN'!G219 -> 292565.2 | C26: ='CONS. FUENTES FINAN'!H208+'CONS. FUENTES FINAN'!H214+'CONS. FUENTES FINAN'!H217+'CONS. FUENTES FINAN'!H219 -> 163325 | D26: =SUM(B26:C26) -> 455890.2 | E26: =+D26/D34 -> 0.0032343493
A27: Productos de papel, carton e impesos | B27: ='CONS. FUENTES FINAN'!G232 -> 1655540 | C27: ='CONS. FUENTES FINAN'!H232 -> 0 | D27: =SUM(B27:C27) -> 1655540 | E27: =+D27/D34 -> 0.01174536
A28: Articulos de Plasticos | B28: ='CONS. FUENTES FINAN'!G259 -> 18154.65 | C28: ='CONS. FUENTES FINAN'!H259 -> 0 | D28: =SUM(B28:C28) -> 18154.65 | E28: =+D28/D34 -> 0.00012879961
A29: Gasolina | B29: ='CONS. FUENTES FINAN'!G288 -> 0 | C29: ='CONS. FUENTES FINAN'!H288 -> 172000 | D29: =SUM(B29:C29) -> 172000 | E29: =+D29/D34 -> 0.0012202677
A30: Gasoil | B30: ='CONS. FUENTES FINAN'!G289+'CONS. FUENTES FINAN'!G290 -> 0 | C30: ='CONS. FUENTES FINAN'!H289+'CONS. FUENTES FINAN'!H290 -> 0 | D30: =SUM(B30:C30) -> 0 | E30: =+D30/D34 -> 0
A31: GLP | B31: ='CONS. FUENTES FINAN'!G291+'CONS. FUENTES FINAN'!G294 -> 0 | C31: ='CONS. FUENTES FINAN'!H291+'CONS. FUENTES FINAN'!H294 -> 21952 | D31: =SUM(B31:C31) -> 21952 | E31: =+D31/D34 -> 0.00015574021
A32: Materiales de Limpieza e Higiene | B32: ='CONS. FUENTES FINAN'!G309 -> 1373621 | C32: ='CONS. FUENTES FINAN'!H309 -> 420561 | D32: =SUM(B32:C32) -> 1794182 | E32: =+D32/D34 -> 0.012728967
A33: Otros Egresos y Gastos | B33: ='CONS. FUENTES FINAN'!G89+'CONS. FUENTES FINAN'!G107+'CONS. FUENTES FINAN'!G148+'CONS. FUENTES FINAN'!G180+'CONS. FUENTES FINAN'!G184+'CONS. FUENTES FINAN'!G186+'CONS. FUENTES FINAN'!G192+'CONS. FUENTES FINAN'!G197+'CONS. FUENTES FINAN'!G204+'CONS. FUENTES FINAN'!G225+'CONS. FUENTES FINAN'!G303+'CONS. FUENTES FINAN'!G316+'CONS. FUENTES FINAN'!G318+'CONS. FUENTES FINAN'!G322+'CONS. FUENTES FINAN'!G327+'CONS. FUENTES FINAN'!G330 -> 848786.03 | C33: ='CONS. FUENTES FINAN'!H89+'CONS. FUENTES FINAN'!H107+'CONS. FUENTES FINAN'!H148+'CONS. FUENTES FINAN'!H180+'CONS. FUENTES FINAN'!H184+'CONS. FUENTES FINAN'!H186+'CONS. FUENTES FINAN'!H192+'CONS. FUENTES FINAN'!H197+'CONS. FUENTES FINAN'!H204+'CONS. FUENTES FINAN'!H225+'CONS. FUENTES FINAN'!H303+'CONS. FUENTES FINAN'!H316+'CONS. FUENTES FINAN'!H318+'CONS. FUENTES FINAN'!H322+'CONS. FUENTES FINAN'!H327+'CONS. FUENTES FINAN'!H330 -> 1194331.2 | D33: =SUM(B33:C33) -> 2043117.3 | E33: =+D33/D34 -> 0.014495058
A34: Total | B34: =SUM(B17:B33) -> 1.3821551e+08 | C34: =SUM(C17:C33) -> 2737169.2 | D34: =SUM(D17:D33) -> 1.4095268e+08 | E34: =+D34/D39 -> 0.85709019
A35: Gastos Inversion y Capital
A36: Bienes Muebles, Inmuebles e Intangibles | B36: ='CONS. FUENTES FINAN'!G336 -> 8010447.3 | C36: ='CONS. FUENTES FINAN'!H336 -> 2755244.7 | D36: =SUM(B36:C36) -> 10765692 | E36: =+D36/D38 -> 1
A37: Obras | B37: ='CONS. FUENTES FINAN'!G463 -> 0 | C37: ='CONS. FUENTES FINAN'!H463 -> 0 | D37: =SUM(B37:C37) -> 0 | E37: =+D37/D38 -> 0
A38: Total | B38: =SUM(B36:B37) -> 8010447.3 | C38: =SUM(C36:C37) -> 2755244.7 | D38: =SUM(D36:D37) -> 10765692 | E38: =+D38/D39 -> 0.065462884
A39: Total General | B39: =+B12+B16+B34+B38 -> 157427908 | C39: =+C12+C16+C34+C38 -> 7026991.1 | D39: =+D12+D16+D34+D38 -> 1.644549e+08 | E39: =+E12+E16+E34+E38 -> 1
A40: Porciento | B40: =+B39/D39 -> 0.95727101 | C40: =+C39/D39 -> 0.042728986 | D40: =+B40+C40 -> 1

Sheet PLANTILLA PRESUPUESTO
A1: SERVICIO NACIONAL DE SALUD
A2: NOMBRE DEL ESTABLECIMIENTO
A3: CONSOLIDADO GASTOS EJECUCION FINANCIERA 2025
A4: En RD$
A6: Detalle | B6: FONDO REPONIBLE | G6: VENTA SEVICIOS/OTROS APORTES | L6: TOTAL
A7: 2 - GASTOS | B7: 1ro | C7: 2do | D7: 3ro | E7: 4to | G7: 1ro | H7: 2do | I7: 3ro | J7: 4to | L7: 1ro | M7: 2do | N7: 3ro | O7: 4to
A8: 2.1 - REMUNERACIONES Y CONTRIBUCIONES | B8: =SUM(B9:B13) -> 1.9856074e+08 | C8: =SUM(C9:C13) -> 1.9977032e+08 | D8: =SUM(D9:D13) -> 2.1475844e+08 | E8: =SUM(E9:E13) -> 2.0672766e+08 | G8: =SUM(G9:G13) -> 5231553.6 | H8: =SUM(H9:H13) -> 0 | I8: =SUM(I9:I13) -> 4413127.6 | J8: =SUM(J9:J13) -> 0 | L8: =SUM(B8+G8) -> 2.0379229e+08 | M8: =SUM(C8+H8) -> 1.9977032e+08 | N8: =SUM(D8+I8) -> 2.1917157e+08 | O8: =SUM(E8+J8) -> 2.0672766e+08
A9: 2.1.1 - REMUNERACIONES | B9: =SUM('TRANSFERENCIA CORRIENTE'!C10:E10) -> 1.639452e+08 | C9: =SUM('TRANSFERENCIA CORRIENTE'!F10:H10) -> 1.6408478e+08 | D9: =SUM('TRANSFERENCIA CORRIENTE'!I10:K10) -> 1.775012e+08 | E9: =SUM('TRANSFERENCIA CORRIENTE'!L10:N10) -> 1.8153111e+08 | G9: =SUM(VS!C10:E10) -> 0 | H9: =SUM(VS!F10:H10) -> 0 | I9: =SUM(VS!I10:K10) -> 0 | J9: =SUM(VS!L10:N10) -> 0 | L9: =SUM(B9+G9) -> 1.639452e+08 | M9: =SUM(C9+H9) -> 1.6408478e+08 | N9: =SUM(D9+I9) -> 1.775012e+08 | O9: =SUM(E9+J9) -> 1.8153111e+08
A10: 2.1.2 - SOBRESUELDOS | B10: =SUM('TRANSFERENCIA CORRIENTE'!C11:E11) -> 9594398.8 | C10: =SUM('TRANSFERENCIA CORRIENTE'!F11:H11) -> 10535799 | D10: =SUM('TRANSFERENCIA CORRIENTE'!I11:K11) -> 10034891 | E10: =SUM('TRANSFERENCIA CORRIENTE'!L11:N11) -> 6610497.3 | G10: =SUM(VS!C11:E11) -> 5231553.6 | H10: =SUM(VS!F11:H11) -> 0 | I10: =SUM(VS!I11:K11) -> 4413127.6 | J10: =SUM(VS!L11:N11) -> 0 | L10: =SUM(B10+G10) -> 14825952 | M10: =SUM(C10+H10) -> 10535799 | N10: =SUM(D10+I10) -> 14448019 | O10: =SUM(E10+J10) -> 6610497.3
A11: 2.1.3 - DIETAS Y GASTOS DE REPRESENTACIÓN | B11: =SUM('TRANSFERENCIA CORRIENTE'!C12:E12) -> 0 | C11: =SUM('TRANSFERENCIA CORRIENTE'!F12:H12) -> 0 | D11: =SUM('TRANSFERENCIA CORRIENTE'!I12:K12) -> 0 | E11: =SUM('TRANSFERENCIA CORRIENTE'!L12:N12) -> 0 | G11: =SUM(VS!C12:E12) -> 0 | H11: =SUM(VS!F12:H12) -> 0 | I11: =SUM(VS!I12:K12) -> 0 | J11: =SUM(VS!L12:N12) -> 0 | L11: =SUM(B11+G11) -> 0 | M11: =SUM(C11+H11) -> 0 | N11: =SUM(D11+I11) -> 0 | O11: =SUM(E11+J11) -> 0
A12: 2.1.4 - GRATIFICACIONES Y BONIFICACIONES | B12: =SUM('TRANSFERENCIA CORRIENTE'!C13:E13) -> 0 | C12: =SUM('TRANSFERENCIA CORRIENTE'!F13:H13) -> 0 | D12: =SUM('TRANSFERENCIA CORRIENTE'!I13:K13) -> 0 | E12: =SUM('TRANSFERENCIA CORRIENTE'!L13:N13) -> 0 | G12: =SUM(VS!C13:E13) -> 0 | H12: =SUM(VS!F13:H13) -> 0 | I12: =SUM(VS!I13:K13) -> 0 | J12: =SUM(VS!L13:N13) -> 0 | L12: =SUM(B12+G12) -> 0 | M12: =SUM(C12+H12) -> 0 | N12: =SUM(D12+I12) -> 0 | O12: =SUM(E12+J12) -> 0
A13: 2.1.5 - CONTRIBUCIONES A LA SEGURIDAD SOCIAL | B13: =SUM('TRANSFERENCIA CORRIENTE'!C14:E14) -> 25021132 | C13: =SUM('TRANSFERENCIA CORRIENTE'!F14:H14) -> 25149742 | D13: =SUM('TRANSFERENCIA CORRIENTE'!I14:K14) -> 27222347 | E13: =SUM('TRANSFERENCIA CORRIENTE'!L14:N14) -> 18586055 | G13: =SUM(VS!C14:E14) -> 0 | H13: =SUM(VS!F14:H14) -> 0 | I13: =SUM(VS!I14:K14) -> 0 | J13: =SUM(VS!L14:N14) -> 0 | L13: =SUM(B13+G13) -> 25021132 | M13: =SUM(C13+H13) -> 25149742 | N13: =SUM(D13+I13) -> 27222347 | O13: =SUM(E13+J13) -> 18586055
A14: 2.2 - CONTRATACIÓN DE SERVICIOS | B14: =SUM(B15:B23) -> 9308364.9 | C14: =SUM(C15:C23) -> 10131818 | D14: =SUM(D15:D23) -> 11703690 | E14: =SUM(E15:E23) -> 2689695.2 | G14: =SUM(G15:G23) -> 8306683.8 | H14: =SUM(H15:H23) -> 7239413.8 | I14: =SUM(I15:I23) -> 10378416 | J14: =SUM(J15:J23) -> 4048661.9 | L14: =SUM(B14+G14) -> 17615049 | M14: =SUM(C14+H14) -> 17371232 | N14: =SUM(D14+I14) -> 22082105 | O14: =SUM(E14+J14) -> 6738357.1
A15: 2.2.1 - SERVICIOS BÁSICOS | B15: =SUM('TRANSFERENCIA CORRIENTE'!C16:E16) -> 2020024.3 | C15: =SUM('TRANSFERENCIA CORRIENTE'!F16:H16) -> 181605 | D15: =SUM('TRANSFERENCIA CORRIENTE'!J16:L16) -> 181605 | E15: =SUM('TRANSFERENCIA CORRIENTE'!L16:N16) -> 121070 | G15: =SUM(VS!C16:E16) -> 2341561.9 | H15: =SUM(VS!F16:H16) -> 2348580.7 | I15: =SUM(VS!I16:K16) -> 2876937.6 | J15: =SUM(VS!L16:N16) -> 1913099.9 | L15: =SUM(B15+G15) -> 4361586.2 | M15: =SUM(C15+H15) -> 2530185.7 | N15: =SUM(D15+I15) -> 3058542.6 | O15: =SUM(E15+J15) -> 2034169.9
A16: 2.2.2 - PUBLICIDAD, IMPRESIÓN Y ENCUADERNACIÓN | B16: =SUM('TRANSFERENCIA CORRIENTE'!C17:E17) -> 324206.83 | C16: =SUM('TRANSFERENCIA CORRIENTE'!F17:H17) -> 351993.83 | D16: =SUM('TRANSFERENCIA CORRIENTE'!J17:L17) -> 190472.3 | E16: =SUM('TRANSFERENCIA CORRIENTE'!L17:N17) -> 54044 | G16: =SUM(VS!C17:E17) -> 0 | H16: =SUM(VS!F17:H17) -> 310139.4 | I16: =SUM(VS!I17:K17) -> 1187725.2 | J16: =SUM(VS!L17:N17) -> 221258.85 | L16: =SUM(B16+G16) -> 324206.83 | M16: =SUM(C16+H16) -> 662133.23 | N16: =SUM(D16+I16) -> 1378197.5 | O16: =SUM(E16+J16) -> 275302.85
A17: 2.2.3 - VIÁTICOS | B17: =SUM('TRANSFERENCIA CORRIENTE'!C18:E18) -> 0 | C17: =SUM('TRANSFERENCIA CORRIENTE'!F18:H18) -> 0 | D17: =SUM('TRANSFERENCIA CORRIENTE'!J18:L18) -> 0 | E17: =SUM('TRANSFERENCIA CORRIENTE'!L18:N18) -> 0 | G17: =SUM(VS!C18:E18) -> 0 | H17: =SUM(VS!F18:H18) -> 0 | I17: =SUM(VS!I18:K18) -> 0 | J17: =SUM(VS!L18:N18) -> 40000 | L17: =SUM(B17+G17) -> 0 | M17: =SUM(C17+H17) -> 0 | N17: =SUM(D17+I17) -> 0 | O17: =SUM(E17+J17) -> 40000
A18: 2.2.4 - TRANSPORTE Y ALMACENAJE | B18: =SUM('TRANSFERENCIA CORRIENTE'!C19:E19) -> 0 | C18: =SUM('TRANSFERENCIA CORRIENTE'!F19:H19) -> 0 | D18: =SUM('TRANSFERENCIA CORRIENTE'!J19:L19) -> 0 | E18: =SUM('TRANSFERENCIA CORRIENTE'!L19:N19) -> 0 | G18: =SUM(VS!C19:E19) -> 56000 | H18: =SUM(VS!F19:H19) -> 96000 | I18: =SUM(VS!I19:K19) -> 76000 | J18: =SUM(VS!L19:N19) -> 20000 | L18: =SUM(B18+G18) -> 56000 | M18: =SUM(C18+H18) -> 96000 | N18: =SUM(D18+I18) -> 76000 | O18: =SUM(E18+J18) -> 20000
A19: 2.2.5 - ALQUILERES Y RENTAS | B19: =SUM('TRANSFERENCIA CORRIENTE'!C20:E20) -> 0 | C19: =SUM('TRANSFERENCIA CORRIENTE'!F20:H20) -> 150000 | D19: =SUM('TRANSFERENCIA CORRIENTE'!J20:L20) -> 448561.92 | E19: =SUM('TRANSFERENCIA CORRIENTE'!L20:N20) -> 298561.92 | G19: =SUM(VS!C20:E20) -> 519625.15 | H19: =SUM(VS!F20:H20) -> 759170.42 | I19: =SUM(VS!I20:K20) -> 927025.64 | J19: =SUM(VS!L20:N20) -> 298143.38 | L19: =SUM(B19+G19) -> 519625.15 | M19: =SUM(C19+H19) -> 909170.42 | N19: =SUM(D19+I19) -> 1375587.6 | O19: =SUM(E19+J19) -> 596705.3
A20: 2.2.6 - SEGUROS | B20: =SUM('TRANSFERENCIA CORRIENTE'!C21:E21) -> 0 | C20: =SUM('TRANSFERENCIA CORRIENTE'!F21:H21) -> 0 | D20: =SUM('TRANSFERENCIA CORRIENTE'!J21:L21) -> 0 | E20: =SUM('TRANSFERENCIA CORRIENTE'!L21:N21) -> 0 | G20: =SUM(VS!C21:E21) -> 0 | H20: =SUM(VS!F21:H21) -> 0 | I20: =SUM(VS!I21:K21) -> 0 | J20: =SUM(VS!L21:N21) -> 3449.08 | L20: =SUM(B20+G20) -> 0 | M20: =SUM(C20+H20) -> 0 | N20: =SUM(D20+I20) -> 0 | O20: =SUM(E20+J20) -> 3449.08
A21: 2.2.7 - SERVICIOS DE CONSERVACIÓN, REPARACIONES MENORES E INSTALACIONES TEMPORALES | B21: =SUM('TRANSFERENCIA CORRIENTE'!C22:E22) -> 6474433.8 | C21: =SUM('TRANSFERENCIA CORRIENTE'!F22:H22) -> 5611474.3 | D21: =SUM('TRANSFERENCIA CORRIENTE'!J22:L22) -> 4467039.5 | E21: =SUM('TRANSFERENCIA CORRIENTE'!L22:N22) -> 1669019.3 | G21: =SUM(VS!C22:E22) -> 4556850.1 | H21: =SUM(VS!F22:H22) -> 1040817.6 | I21: =SUM(VS!I22:K22) -> 3360268.8 | J21: =SUM(VS!L22:N22) -> 425674.45 | L21: =SUM(B21+G21) -> 11031284 | M21: =SUM(C21+H21) -> 6652291.9 | N21: =SUM(D21+I21) -> 7827308.2 | O21: =SUM(E21+J21) -> 2094693.7
A22: 2.2.8 - OTROS SERVICIOS NO INCLUIDOS EN CONCEPTOS ANTERIORES | B22: =SUM('TRANSFERENCIA CORRIENTE'!C23:E23) -> 489700 | C22: =SUM('TRANSFERENCIA CORRIENTE'!F23:H23) -> 413000 | D22: =SUM('TRANSFERENCIA CORRIENTE'!J23:L23) -> 4101500 | E22: =SUM('TRANSFERENCIA CORRIENTE'!L23:N23) -> 547000 | G22: =SUM(VS!C23:E23) -> 832646.66 | H22: =SUM(VS!F23:H23) -> 1774418.3 | I22: =SUM(VS!I23:K23) -> 1400729.1 | J22: =SUM(VS!L23:N23) -> 1127036.2 | L22: =SUM(B22+G22) -> 1322346.7 | M22: =SUM(C22+H22) -> 2187418.3 | N22: =SUM(D22+I22) -> 5502229.1 | O22: =SUM(E22+J22) -> 1674036.2
A23: 2.2.9 - OTRAS CONTRATACIONES DE SERVICIOS | B23: =SUM('TRANSFERENCIA CORRIENTE'!C24:E24) -> 0 | C23: =SUM('TRANSFERENCIA CORRIENTE'!F24:H24) -> 3423745 | D23: =SUM('TRANSFERENCIA CORRIENTE'!J24:L24) -> 2314511 | E23: =SUM('TRANSFERENCIA CORRIENTE'!L24:N24) -> 0 | G23: =SUM(VS!C24:E24) -> 0 | H23: =SUM(VS!F24:H24) -> 910287.4 | I23: =SUM(VS!I24:K24) -> 549729.55 | J23: =SUM(VS!L24:N24) -> 0 | L23: =SUM(B23+G23) -> 0 | M23: =SUM(C23+H23) -> 4334032.4 | N23: =SUM(D23+I23) -> 2864240.5 | O23: =SUM(E23+J23) -> 0
A24: 2.3 - MATERIALES Y SUMINISTROS | B24: =SUM(B25:B33) -> 46153283 | C24: =SUM(C25:C33) -> 52385651 | D24: =SUM(D25:D33) -> 1.0378694e+08 | E24: =SUM(E25:E33) -> 45676288 | G24: =SUM(G25:G33) -> 7292547.3 | H24: =SUM(H25:H33) -> 6552680.6 | I24: =SUM(I25:I33) -> 9091857.1 | J24: =SUM(J25:J33) -> 8069838.1 | L24: =SUM(B24+G24) -> 53445831 | M24: =SUM(C24+H24) -> 58938331 | N24: =SUM(D24+I24) -> 1.128788e+08 | O24: =SUM(E24+J24) -> 53746126
A25: 2.3.1 - ALIMENTOS Y PRODUCTOS AGROFORESTALES | B25: =SUM('TRANSFERENCIA CORRIENTE'!C26:E26) -> 3713897.2 | C25: =SUM('TRANSFERENCIA CORRIENTE'!F26:H26) -> 4866999.2 | D25: =SUM('TRANSFERENCIA CORRIENTE'!I23:K23) -> 3779000 | E25: =SUM('TRANSFERENCIA CORRIENTE'!L26:N26) -> 1904370.2 | G25: =SUM(VS!C26:E26) -> 1500755.8 | H25: =SUM(VS!F26:H26) -> 663230 | I25: =SUM(VS!I26:K26) -> 1574425.7 | J25: =SUM(VS!L26:N26) -> 448552 | L25: =SUM(B25+G25) -> 5214653 | M25: =SUM(C25+H25) -> 5530229.2 | N25: =SUM(D25+I25) -> 5353425.7 | O25: =SUM(E25+J25) -> 2352922.2
A26: 2.3.2 - TEXTILES Y VESTUARIOS | B26: =SUM('TRANSFERENCIA CORRIENTE'!C27:E27) -> 61630.73 | C26: =SUM('TRANSFERENCIA CORRIENTE'!F27:H27) -> 2375399.4 | D26: =SUM('TRANSFERENCIA CORRIENTE'!I24:K24) -> 2314511 | E26: =SUM('TRANSFERENCIA CORRIENTE'!L27:N27) -> 624994.03 | G26: =SUM(VS!C27:E27) -> 0 | H26: =SUM(VS!F27:H27) -> 346306.4 | I26: =SUM(VS!I27:K27) -> 0 | J26: =SUM(VS!L27:N27) -> 0 | L26: =SUM(B26+G26) -> 61630.73 | M26: =SUM(C26+H26) -> 2721705.8 | N26: =SUM(D26+I26) -> 2314511 | O26: =SUM(E26+J26) -> 624994.03
A27: 2.3.3 - PRODUCTOS DE PAPEL, CARTÓN E IMPRESOS | B27: =SUM('TRANSFERENCIA CORRIENTE'!C28:E28) -> 1826911.8 | C27: =SUM('TRANSFERENCIA CORRIENTE'!F28:H28) -> 2991695.7 | D27: =SUM('TRANSFERENCIA CORRIENTE'!I25:K25) -> 65609607 | E27: =SUM('TRANSFERENCIA CORRIENTE'!L28:N28) -> 2540026 | G27: =SUM(VS!C28:E28) -> 251163 | H27: =SUM(VS!F28:H28) -> 803989 | I27: =SUM(VS!I28:K28) -> 734332.03 | J27: =SUM(VS!L28:N28) -> 0 | L27: =SUM(B27+G27) -> 2078074.8 | M27: =SUM(C27+H27) -> 3795684.7 | N27: =SUM(D27+I27) -> 66343939 | O27: =SUM(E27+J27) -> 2540026
A28: 2.3.4 - PRODUCTOS FARMACÉUTICOS | B28: =SUM('TRANSFERENCIA CORRIENTE'!C29:E29) -> 10797336 | C28: =SUM('TRANSFERENCIA CORRIENTE'!F29:H29) -> 12009357 | D28: =SUM('TRANSFERENCIA CORRIENTE'!I26:K26) -> 6044845.1 | E28: =SUM('TRANSFERENCIA CORRIENTE'!L29:N29) -> 6533049.3 | G28: =SUM(VS!C29:E29) -> 558000 | H28: =SUM(VS!F29:H29) -> 402220.76 | I28: =SUM(VS!I29:K29) -> 496000 | J28: =SUM(VS!L29:N29) -> 2567560 | L28: =SUM(B28+G28) -> 11355336 | M28: =SUM(C28+H28) -> 12411577 | N28: =SUM(D28+I28) -> 6540845.1 | O28: =SUM(E28+J28) -> 9100609.3
A29: 2.3.5 - PRODUCTOS DE CUERO, CAUCHO Y PLÁSTICO | B29: =SUM('TRANSFERENCIA CORRIENTE'!C30:E30) -> 334708.95 | C29: =SUM('TRANSFERENCIA CORRIENTE'!F30:H30) -> 1024240.4 | D29: =SUM('TRANSFERENCIA CORRIENTE'!I27:K27) -> 3015806.8 | E29: =SUM('TRANSFERENCIA CORRIENTE'!L30:N30) -> 641356.08 | G29: =SUM(VS!C30:E30) -> 567494.87 | H29: =SUM(VS!F30:H30) -> 0 | I29: =SUM(VS!I30:K30) -> 140314.78 | J29: =SUM(VS!L30:N30) -> 298561.92 | L29: =SUM(B29+G29) -> 902203.82 | M29: =SUM(C29+H29) -> 1024240.4 | N29: =SUM(D29+I29) -> 3156121.5 | O29: =SUM(E29+J29) -> 939918
A30: 2.3.6 - PRODUCTOS DE MINERALES, METÁLICOS Y NO METÁLICOS | B30: =SUM('TRANSFERENCIA CORRIENTE'!C31:E31) -> 11630.98 | C30: =SUM('TRANSFERENCIA CORRIENTE'!F31:H31) -> 667620.59 | D30: =SUM('TRANSFERENCIA CORRIENTE'!I28:K28) -> 2859834.4 | E30: =SUM('TRANSFERENCIA CORRIENTE'!L31:N31) -> 236465.7 | G30: =SUM(VS!C31:E31) -> 293957.3 | H30: =SUM(VS!F31:H31) -> 0 | I30: =SUM(VS!I31:K31) -> 211552.06 | J30: =SUM(VS!L31:N31) -> 875.01 | L30: =SUM(B30+G30) -> 305588.28 | M30: =SUM(C30+H30) -> 667620.59 | N30: =SUM(D30+I30) -> 3071386.4 | O30: =SUM(E30+J30) -> 237340.71
A31: 2.3.7 - COMBUSTIBLES, LUBRICANTES, PRODUCTOS QUÍMICOS Y CONEXOS | B31: =SUM('TRANSFERENCIA CORRIENTE'!C32:E32) -> 8910102 | C31: =SUM('TRANSFERENCIA CORRIENTE'!F32:H32) -> 10068979 | D31: =SUM('TRANSFERENCIA CORRIENTE'!I29:K29) -> 19203378 | E31: =SUM('TRANSFERENCIA CORRIENTE'!L32:N32) -> 21413947 | G31: =SUM(VS!C32:E32) -> 1660334.6 | H31: =SUM(VS!F32:H32) -> 1500202 | I31: =SUM(VS!I32:K32) -> 2324461 | J31: =SUM(VS!L32:N32) -> 1113655 | L31: =SUM(B31+G31) -> 10570437 | M31: =SUM(C31+H31) -> 11569181 | N31: =SUM(D31+I31) -> 21527839 | O31: =SUM(E31+J31) -> 22527602
A32: 2.3.8 - GASTOS QUE SE ASIGNARÁN DURANTE EL EJERCICIO (ART. 32 Y 33 LEY 423-06) | B32: =SUM('TRANSFERENCIA CORRIENTE'!C33:E33) -> 0 | C32: =SUM('TRANSFERENCIA CORRIENTE'!F33:H33) -> 0 | D32: =SUM('TRANSFERENCIA CORRIENTE'!I30:K30) -> 673453.82 | E32: =SUM('TRANSFERENCIA CORRIENTE'!L33:N33) -> 0 | G32: =SUM(VS!C33:E33) -> 0 | H32: =SUM(VS!F33:H33) -> 0 | I32: =SUM(VS!I33:K33) -> 0 | J32: =SUM(VS!L33:N33) -> 0 | L32: =SUM(B32+G32) -> 0 | M32: =SUM(C32+H32) -> 0 | N32: =SUM(D32+I32) -> 673453.82 | O32: =SUM(E32+J32) -> 0
A33: 2.3.9 - PRODUCTOS Y ÚTILES VARIOS | B33: =SUM('TRANSFERENCIA CORRIENTE'!C34:E34) -> 20497066 | C33: =SUM('TRANSFERENCIA CORRIENTE'!F34:H34) -> 18381359 | D33: =SUM('TRANSFERENCIA CORRIENTE'!I31:K31) -> 286504 | E33: =SUM('TRANSFERENCIA CORRIENTE'!L34:N34) -> 11782079 | G33: =SUM(VS!C34:E34) -> 2460841.8 | H33: =SUM(VS!F34:H34) -> 2836732.4 | I33: =SUM(VS!I34:K34) -> 3610771.5 | J33: =SUM(VS!L34:N34) -> 3640634.2 | L33: =SUM(B33+G33) -> 22957908 | M33: =SUM(C33+H33) -> 21218092 | N33: =SUM(D33+I33) -> 3897275.5 | O33: =SUM(E33+J33) -> 15422714
A34: 2.4 - TRANSFERENCIAS CORRIENTES | B34: =SUM(B35:B41) -> 0 | C34: =SUM(C35:C41) -> 0 | D34: =SUM(D35:D41) -> 0 | E34: =SUM(E35:E41) -> 0 | G34: =SUM(G35:G41) -> 287786.7 | H34: =SUM(H35:H41) -> 1223981 | I34: =SUM(I35:I41) -> 122771 | J34: =SUM(J35:J41) -> 3600 | L34: =SUM(B34+G34) -> 287786.7 | M34: =SUM(C34+H34) -> 1223981 | N34: =SUM(D34+I34) -> 122771 | O34: =SUM(E34+J34) -> 3600
A35: 2.4.1 - TRANSFERENCIAS CORRIENTES AL SECTOR PRIVADO | B35: =SUM('TRANSFERENCIA CORRIENTE'!C36:E36) -> 0 | C35: =SUM('TRANSFERENCIA CORRIENTE'!F36:H36) -> 0 | D35: =SUM('TRANSFERENCIA CORRIENTE'!I36:K36) -> 0 | E35: =SUM('TRANSFERENCIA CORRIENTE'!L36:N36) -> 0 | G35: =SUM(VS!C36:E36) -> 287786.7 | H35: =SUM(VS!F36:H36) -> 1223981 | I35: =SUM(VS!I36:K36) -> 122771 | J35: =SUM(VS!L36:N36) -> 3600 | L35: =SUM(B35+G35) -> 287786.7 | M35: =SUM(C35+H35) -> 1223981 | N35: =SUM(D35+I35) -> 122771 | O35: =SUM(E35+J35) -> 3600
A36: 2.4.2 - TRANSFERENCIAS CORRIENTES AL GOBIERNO GENERAL NACIONAL | B36: =SUM('TRANSFERENCIA CORRIENTE'!C37:E37) -> 0 | C36: =SUM('TRANSFERENCIA CORRIENTE'!F37:H37) -> 0 | D36: =SUM('TRANSFERENCIA CORRIENTE'!I37:K37) -> 0 | E36: =SUM('TRANSFERENCIA CORRIENTE'!L37:N37) -> 0 | G36: =SUM(VS!C37:E37) -> 0 | H36: =SUM(VS!F37:H37) -> 0 | I36: =SUM(VS!I37:K37) -> 0 | J36: =SUM(VS!L37:N37) -> 0 | L36: =SUM(B36+G36) -> 0 | M36: =SUM(C36+H36) -> 0 | N36: =SUM(D36+I36) -> 0 | O36: =SUM(E36+J36) -> 0
A37: 2.4.3 - TRANSFERENCIAS CORRIENTES A GOBIERNOS GENERALES LOCALES | B37: =SUM('TRANSFERENCIA CORRIENTE'!C38:E38) -> 0 | C37: =SUM('TRANSFERENCIA CORRIENTE'!F38:H38) -> 0 | D37: =SUM('TRANSFERENCIA CORRIENTE'!I38:K38) -> 0 | E37: =SUM('TRANSFERENCIA CORRIENTE'!L38:N38) -> 0 | G37: =SUM(VS!C38:E38) -> 0 | H37: =SUM(VS!F38:H38) -> 0 | I37: =SUM(VS!I38:K38) -> 0 | J37: =SUM(VS!L38:N38) -> 0 | L37: =SUM(B37+G37) -> 0 | M37: =SUM(C37+H37) -> 0 | N37: =SUM(D37+I37) -> 0 | O37: =SUM(E37+J37) -> 0
A38: 2.4.4 - TRANSFERENCIAS CORRIENTES A EMPRESAS PÚBLICAS NO FINANCIERAS | B38: =SUM('TRANSFERENCIA CORRIENTE'!C39:E39) -> 0 | C38: =SUM('TRANSFERENCIA CORRIENTE'!F39:H39) -> 0 | D38: =SUM('TRANSFERENCIA CORRIENTE'!I39:K39) -> 0 | E38: =SUM('TRANSFERENCIA CORRIENTE'!L39:N39) -> 0 | G38: =SUM(VS!C39:E39) -> 0 | H38: =SUM(VS!F39:H39) -> 0 | I38: =SUM(VS!I39:K39) -> 0 | J38: =SUM(VS!L39:N39) -> 0 | L38: =SUM(B38+G38) -> 0 | M38: =SUM(C38+H38) -> 0 | N38: =SUM(D38+I38) -> 0 | O38: =SUM(E38+J38) -> 0
A39: 2.4.5 - TRANSFERENCIAS CORRIENTES A INSTITUCIONES PÚBLICAS FINANCIERAS | B39: =SUM('TRANSFERENCIA CORRIENTE'!C40:E40) -> 0 | C39: =SUM('TRANSFERENCIA CORRIENTE'!F40:H40) -> 0 | D39: =SUM('TRANSFERENCIA CORRIENTE'!I40:K40) -> 0 | E39: =SUM('TRANSFERENCIA CORRIENTE'!L40:N40) -> 0 | G39: =SUM(VS!C40:E40) -> 0 | H39: =SUM(VS!F40:H40) -> 0 | I39: =SUM(VS!I40:K40) -> 0 | J39: =SUM(VS!L40:N40) -> 0 | L39: =SUM(B39+G39) -> 0 | M39: =SUM(C39+H39) -> 0 | N39: =SUM(D39+I39) -> 0 | O39: =SUM(E39+J39) -> 0
A40: 2.4.7 - TRANSFERENCIAS CORRIENTES AL SECTOR EXTERNO | B40: =SUM('TRANSFERENCIA CORRIENTE'!C41:E41) -> 0 | C40: =SUM('TRANSFERENCIA CORRIENTE'!F41:H41) -> 0 | D40: =SUM('TRANSFERENCIA CORRIENTE'!I41:K41) -> 0 | E40: =SUM('TRANSFERENCIA CORRIENTE'!L41:N41) -> 0 | G40: =SUM(VS!C41:E41) -> 0 | H40: =SUM(VS!F41:H41) -> 0 | I40: =SUM(VS!I41:K41) -> 0 | J40: =SUM(VS!L41:N41) -> 0 | L40: =SUM(B40+G40) -> 0 | M40: =SUM(C40+H40) -> 0 | N40: =SUM(D40+I40) -> 0 | O40: =SUM(E40+J40) -> 0
A41: 2.4.9 - TRANSFERENCIAS CORRIENTES A OTRAS INSTITUCIONES PÚBLICAS | B41: =SUM('TRANSFERENCIA CORRIENTE'!C42:E42) -> 0 | C41: =SUM('TRANSFERENCIA CORRIENTE'!F42:H42) -> 0 | D41: =SUM('TRANSFERENCIA CORRIENTE'!I42:K42) -> 0 | E41: =SUM('TRANSFERENCIA CORRIENTE'!L42:N42) -> 0 | G41: =SUM(VS!C42:E42) -> 0 | H41: =SUM(VS!F42:H42) -> 0 | I41: =SUM(VS!I42:K42) -> 0 | J41: =SUM(VS!L42:N42) -> 0 | L41: =SUM(B41+G41) -> 0 | M41: =SUM(C41+H41) -> 0 | N41: =SUM(D41+I41) -> 0 | O41: =SUM(E41+J41) -> 0
A42: 2.5 - TRANSFERENCIAS DE CAPITAL | B42: =SUM(B43:B49) -> 0 | C42: =SUM(C43:C49) -> 0 | D42: =SUM(D43:D49) -> 0 | E42: =SUM(E43:E49) -> 0 | G42: =SUM(G43:G49) -> 0 | H42: =SUM(H43:H49) -> 0 | I42: =SUM(I43:I49) -> 0 | J42: =SUM(J43:J49) -> 0 | L42: =SUM(B42+G42) -> 0 | M42: =SUM(C42+H42) -> 0 | N42: =SUM(D42+I42) -> 0 | O42: =SUM(E42+J42) -> 0
A43: 2.5.1 - TRANSFERENCIAS DE CAPITAL AL SECTOR PRIVADO | B43: =SUM('TRANSFERENCIA CORRIENTE'!C44:E44) -> 0 | C43: =SUM('TRANSFERENCIA CORRIENTE'!F44:H44) -> 0 | D43: =SUM('TRANSFERENCIA CORRIENTE'!I44:K44) -> 0 | E43: =SUM('TRANSFERENCIA CORRIENTE'!L44:N44) -> 0 | G43: =SUM(VS!C44:E44) -> 0 | H43: =SUM(VS!F44:H44) -> 0 | I43: =SUM(VS!I44:K44) -> 0 | J43: =SUM(VS!L44:N44) -> 0 | L43: =SUM(B43+G43) -> 0 | M43: =SUM(C43+H43) -> 0 | N43: =SUM(D43+I43) -> 0 | O43: =SUM(E43+J43) -> 0
A44: 2.5.2 - TRANSFERENCIAS DE CAPITAL AL GOBIERNO GENERAL NACIONAL | B44: =SUM('TRANSFERENCIA CORRIENTE'!C45:E45) -> 0 | C44: =SUM('TRANSFERENCIA CORRIENTE'!F45:H45) -> 0 | D44: =SUM('TRANSFERENCIA CORRIENTE'!I45:K45) -> 0 | E44: =SUM('TRANSFERENCIA CORRIENTE'!L45:N45) -> 0 | G44: =SUM(VS!C45:E45) -> 0 | H44: =SUM(VS!F45:H45) -> 0 | I44: =SUM(VS!I45:K45) -> 0 | J44: =SUM(VS!L45:N45) -> 0 | L44: =SUM(B44+G44) -> 0 | M44: =SUM(C44+H44) -> 0 | N44: =SUM(D44+I44) -> 0 | O44: =SUM(E44+J44) -> 0
A45: 2.5.3 - TRANSFERENCIAS DE CAPITAL A GOBIERNOS GENERALES LOCALES | B45: =SUM('TRANSFERENCIA CORRIENTE'!C46:E46) -> 0 | C45: =SUM('TRANSFERENCIA CORRIENTE'!F46:H46) -> 0 | D45: =SUM('TRANSFERENCIA CORRIENTE'!I46:K46) -> 0 | E45: =SUM('TRANSFERENCIA CORRIENTE'!L46:N46) -> 0 | G45: =SUM(VS!C46:E46) -> 0 | H45: =SUM(VS!F46:H46) -> 0 | I45: =SUM(VS!I46:K46) -> 0 | J45: =SUM(VS!L46:N46) -> 0 | L45: =SUM(B45+G45) -> 0 | M45: =SUM(C45+H45) -> 0 | N45: =SUM(D45+I45) -> 0 | O45: =SUM(E45+J45) -> 0
A46: 2.5.4 - TRANSFERENCIAS DE CAPITAL A EMPRESAS PÚBLICAS NO FINANCIERAS | B46: =SUM('TRANSFERENCIA CORRIENTE'!C47:E47) -> 0 | C46: =SUM('TRANSFERENCIA CORRIENTE'!F47:H47) -> 0 | D46: =SUM('TRANSFERENCIA CORRIENTE'!I47:K47) -> 0 | E46: =SUM('TRANSFERENCIA CORRIENTE'!L47:N47) -> 0 | G46: =SUM(VS!C47:E47) -> 0 | H46: =SUM(VS!F47:H47) -> 0 | I46: =SUM(VS!I47:K47) -> 0 | J46: =SUM(VS!L47:N47) -> 0 | L46: =SUM(B46+G46) -> 0 | M46: =SUM(C46+H46) -> 0 | N46: =SUM(D46+I46) -> 0 | O46: =SUM(E46+J46) -> 0
A47: 2.5.5 - TRANSFERENCIAS DE CAPITAL A INSTITUCIONES PÚBLICAS FINANCIERAS | B47: =SUM('TRANSFERENCIA CORRIENTE'!C48:E48) -> 0 | C47: =SUM('TRANSFERENCIA CORRIENTE'!F48:H48) -> 0 | D47: =SUM('TRANSFERENCIA CORRIENTE'!I48:K48) -> 0 | E47: =SUM('TRANSFERENCIA CORRIENTE'!L48:N48) -> 0 | G47: =SUM(VS!C48:E48) -> 0 | H47: =SUM(VS!F48:H48) -> 0 | I47: =SUM(VS!I48:K48) -> 0 | J47: =SUM(VS!L48:N48) -> 0 | L47: =SUM(B47+G47) -> 0 | M47: =SUM(C47+H47) -> 0 | N47: =SUM(D47+I47) -> 0 | O47: =SUM(E47+J47) -> 0
A48: 2.5.6 - TRANSFERENCIAS DE CAPITAL AL SECTOR EXTERNO | B48: =SUM('TRANSFERENCIA CORRIENTE'!C49:E49) -> 0 | C48: =SUM('TRANSFERENCIA CORRIENTE'!F49:H49) -> 0 | D48: =SUM('TRANSFERENCIA CORRIENTE'!I49:K49) -> 0 | E48: =SUM('TRANSFERENCIA CORRIENTE'!L49:N49) -> 0 | G48: =SUM(VS!C49:E49) -> 0 | H48: =SUM(VS!F49:H49) -> 0 | I48: =SUM(VS!I49:K49) -> 0 | J48: =SUM(VS!L49:N49) -> 0 | L48: =SUM(B48+G48) -> 0 | M48: =SUM(C48+H48) -> 0 | N48: =SUM(D48+I48) -> 0 | O48: =SUM(E48+J48) -> 0
A49: 2.5.9 - TRANSFERENCIAS DE CAPITAL A OTRAS INSTITUCIONES PÚBLICAS | B49: =SUM('TRANSFERENCIA CORRIENTE'!C50:E50) -> 0 | C49: =SUM('TRANSFERENCIA CORRIENTE'!F50:H50) -> 0 | D49: =SUM('TRANSFERENCIA CORRIENTE'!I50:K50) -> 0 | E49: =SUM('TRANSFERENCIA CORRIENTE'!L50:N50) -> 0 | G49: =SUM(VS!C50:E50) -> 0 | H49: =SUM(VS!F50:H50) -> 0 | I49: =SUM(VS!I50:K50) -> 0 | J49: =SUM(VS!L50:N50) -> 0 | L49: =SUM(B49+G49) -> 0 | M49: =SUM(C49+H49) -> 0 | N49: =SUM(D49+I49) -> 0 | O49: =SUM(E49+J49) -> 0
A50: 2.6 - BIENES MUEBLES, INMUEBLES E INTANGIBLES | B50: =SUM(B51:B59) -> 17857867 | C50: =SUM(C51:C59) -> 14943855 | D50: =SUM(D51:D59) -> 25711105 | E50: =SUM(E51:E59) -> 11447712 | G50: =SUM(G51:G59) -> 5076044.2 | H50: =SUM(H51:H59) -> 5383431.2 | I50: =SUM(I51:I59) -> 5370952.4 | J50: =SUM(J51:J59) -> 3065952.1 | L50: =SUM(B50+G50) -> 22933911 | M50: =SUM(C50+H50) -> 20327286 | N50: =SUM(D50+I50) -> 31082057 | O50: =SUM(E50+J50) -> 14513664
A51: 2.6.1 - MOBILIARIO Y EQUIPO | B51: =SUM('TRANSFERENCIA CORRIENTE'!C52:E52) -> 1110625.9 | C51: =SUM('TRANSFERENCIA CORRIENTE'!F52:H52) -> 3586435.1 | D51: =SUM('TRANSFERENCIA CORRIENTE'!I52:K52) -> 6119237.3 | E51: =SUM('TRANSFERENCIA CORRIENTE'!L52:N52) -> 1243565.2 | G51: =SUM(VS!C52:E52) -> 0 | H51: =SUM(VS!F52:H52) -> 7995.01 | I51: =SUM(VS!I52:K52) -> 2929998 | J51: =SUM(VS!L52:N52) -> 450430.96 | L51: =SUM(B51+G51) -> 1110625.9 | M51: =SUM(C51+H51) -> 3594430.1 | N51: =SUM(D51+I51) -> 9049235.3 | O51: =SUM(E51+J51) -> 1693996.2
A52: 2.6.2 - MOBILIARIO Y EQUIPO EDUCACIONAL Y RECREATIVO | B52: =SUM('TRANSFERENCIA CORRIENTE'!C53:E53) -> 0 | C52: =SUM('TRANSFERENCIA CORRIENTE'!F53:H53) -> 182926.74 | D52: =SUM('TRANSFERENCIA CORRIENTE'!I53:K53) -> 0 | E52: =SUM('TRANSFERENCIA CORRIENTE'!L53:N53) -> 0 | G52: =SUM(VS!C53:E53) -> 0 | H52: =SUM(VS!F53:H53) -> 1399834 | I52: =SUM(VS!I53:K53) -> 389046 | J52: =SUM(VS!L53:N53) -> 0 | L52: =SUM(B52+G52) -> 0 | M52: =SUM(C52+H52) -> 1582760.7 | N52: =SUM(D52+I52) -> 389046 | O52: =SUM(E52+J52) -> 0
A53: 2.6.3 - EQUIPO E INSTRUMENTAL, CIENTÍFICO Y LABORATORIO | B53: =SUM('TRANSFERENCIA CORRIENTE'!C54:E54) -> 16744041 | C53: =SUM('TRANSFERENCIA CORRIENTE'!F54:H54) -> 6663622.6 | D53: =SUM('TRANSFERENCIA CORRIENTE'!I54:K54) -> 10518535 | E53: =SUM('TRANSFERENCIA CORRIENTE'!L54:N54) -> 9135364.7 | G53: =SUM(VS!C54:E54) -> 2963024.8 | H53: =SUM(VS!F54:H54) -> 3975602.1 | I53: =SUM(VS!I54:K54) -> 1710444.5 | J53: =SUM(VS!L54:N54) -> 2012071.1 | L53: =SUM(B53+G53) -> 19707066 | M53: =SUM(C53+H53) -> 10639225 | N53: =SUM(D53+I53) -> 12228980 | O53: =SUM(E53+J53) -> 11147436
A54: 2.6.4 - VEHÍCULOS Y EQUIPO DE TRANSPORTE, TRACCIÓN Y ELEVACIÓN | B54: =SUM('TRANSFERENCIA CORRIENTE'!C55:E55) -> 0 | C54: =SUM('TRANSFERENCIA CORRIENTE'!F55:H55) -> 0 | D54: =SUM('TRANSFERENCIA CORRIENTE'!I55:K55) -> 0 | E54: =SUM('TRANSFERENCIA CORRIENTE'!L55:N55) -> 0 | G54: =SUM(VS!C55:E55) -> 107609.37 | H54: =SUM(VS!F55:H55) -> 0 | I54: =SUM(VS!I55:K55) -> 0 | J54: =SUM(VS!L55:N55) -> 0 | L54: =SUM(B54+G54) -> 107609.37 | M54: =SUM(C54+H54) -> 0 | N54: =SUM(D54+I54) -> 0 | O54: =SUM(E54+J54) -> 0
A55: 2.6.5 - MAQUINARIA, OTROS EQUIPOS Y HERRAMIENTAS | B55: =SUM('TRANSFERENCIA CORRIENTE'!C56:E56) -> 3199.97 | C55: =SUM('TRANSFERENCIA CORRIENTE'!F56:H56) -> 4165309.5 | D55: =SUM('TRANSFERENCIA CORRIENTE'!I56:K56) -> 9007252.2 | E55: =SUM('TRANSFERENCIA CORRIENTE'!L56:N56) -> 1068781.9 | G55: =SUM(VS!C56:E56) -> 2005410 | H55: =SUM(VS!F56:H56) -> 0 | I55: =SUM(VS!I56:K56) -> 282700.01 | J55: =SUM(VS!L56:N56) -> 603450.01 | L55: =SUM(B55+G55) -> 2008610 | M55: =SUM(C55+H55) -> 4165309.5 | N55: =SUM(D55+I55) -> 9289952.3 | O55: =SUM(E55+J55) -> 1672231.9
A56: 2.6.6 - EQUIPOS DE DEFENSA Y SEGURIDAD | B56: =SUM('TRANSFERENCIA CORRIENTE'!C57:E57) -> 0 | C56: =SUM('TRANSFERENCIA CORRIENTE'!F57:H57) -> 0 | D56: =SUM('TRANSFERENCIA CORRIENTE'!I57:K57) -> 66080 | E56: =SUM('TRANSFERENCIA CORRIENTE'!L57:N57) -> 0 | G56: =SUM(VS!C57:E57) -> 0 | H56: =SUM(VS!F57:H57) -> 0 | I56: =SUM(VS!I57:K57) -> 58764 | J56: =SUM(VS!L57:N57) -> 0 | L56: =SUM(B56+G56) -> 0 | M56: =SUM(C56+H56) -> 0 | N56: =SUM(D56+I56) -> 124844 | O56: =SUM(E56+J56) -> 0
A57: 2.6.7 - ACTIVOS BIÓLOGICOS CULTIVABLES | B57: =SUM('TRANSFERENCIA CORRIENTE'!C58:E58) -> 0 | C57: =SUM('TRANSFERENCIA CORRIENTE'!F58:H58) -> 0 | D57: =SUM('TRANSFERENCIA CORRIENTE'!I58:K58) -> 0 | E57: =SUM('TRANSFERENCIA CORRIENTE'!L58:N58) -> 0 | G57: =SUM(VS!C58:E58) -> 0 | H57: =SUM(VS!F58:H58) -> 0 | I57: =SUM(VS!I58:K58) -> 0 | J57: =SUM(VS!L58:N58) -> 0 | L57: =SUM(B57+G57) -> 0 | M57: =SUM(C57+H57) -> 0 | N57: =SUM(D57+I57) -> 0 | O57: =SUM(E57+J57) -> 0
A58: 2.6.8 - BIENES INTANGIBLES | B58: =SUM('TRANSFERENCIA CORRIENTE'!C59:E59) -> 0 | C58: =SUM('TRANSFERENCIA CORRIENTE'!F59:H59) -> 0 | D58: =SUM('TRANSFERENCIA CORRIENTE'!I59:K59) -> 0 | E58: =SUM('TRANSFERENCIA CORRIENTE'!L59:N59) -> 0 | G58: =SUM(VS!C59:E59) -> 0 | H58: =SUM(VS!F59:H59) -> 0 | I58: =SUM(VS!I59:K59) -> 0 | J58: =SUM(VS!L59:N59) -> 0 | L58: =SUM(B58+G58) -> 0 | M58: =SUM(C58+H58) -> 0 | N58: =SUM(D58+I58) -> 0 | O58: =SUM(E58+J58) -> 0
A59: 2.6.9 - EDIFICIOS, ESTRUCTURAS, TIERRAS, TERRENOS Y OBJETOS DE VALOR | B59: =SUM('TRANSFERENCIA CORRIENTE'!C60:E60) -> 0 | C59: =SUM('TRANSFERENCIA CORRIENTE'!F60:H60) -> 345560.94 | D59: =SUM('TRANSFERENCIA CORRIENTE'!I60:K60) -> 0 | E59: =SUM('TRANSFERENCIA CORRIENTE'!L60:N60) -> 0 | G59: =SUM(VS!C60:E60) -> 0 | H59: =SUM(VS!F60:H60) -> 0 | I59: =SUM(VS!I60:K60) -> 0 | J59: =SUM(VS!L60:N60) -> 0 | L59: =SUM(B59+G59) -> 0 | M59: =SUM(C59+H59) -> 345560.94 | N59: =SUM(D59+I59) -> 0 | O59: =SUM(E59+J59) -> 0
A60: 2.7 - OBRAS | B60: =SUM(B61:B64) -> 0 | C60: =SUM(C61:C64) -> 0 | D60: =SUM(D61:D64) -> 0 | E60: =SUM(E61:E64) -> 0 | G60: =SUM(G61:G64) -> 0 | H60: =SUM(H61:H64) -> 0 | I60: =SUM(I61:I64) -> 0 | J60: =SUM(J61:J64) -> 0 | L60: =SUM(B60+G60) -> 0 | M60: =SUM(C60+H60) -> 0 | N60: =SUM(D60+I60) -> 0 | O60: =SUM(E60+J60) -> 0
A61: 2.7.1 - OBRAS EN EDIFICACIONES | B61: =SUM('TRANSFERENCIA CORRIENTE'!C62:E62) -> 0 | C61: =SUM('TRANSFERENCIA CORRIENTE'!F62:H62) -> 0 | D61: =SUM('TRANSFERENCIA CORRIENTE'!I62:K62) -> 0 | E61: =SUM('TRANSFERENCIA CORRIENTE'!L62:N62) -> 0 | G61: =SUM(VS!C62:E62) -> 0 | H61: =SUM(VS!F62:H62) -> 0 | I61: =SUM(VS!I62:K62) -> 0 | J61: =SUM(VS!L62:N62) -> 0 | L61: =SUM(B61+G61) -> 0 | M61: =SUM(C61+H61) -> 0 | N61: =SUM(D61+I61) -> 0 | O61: =SUM(E61+J61) -> 0
A62: 2.7.2 - INFRAESTRUCTURA | B62: =SUM('TRANSFERENCIA CORRIENTE'!C63:E63) -> 0 | C62: =SUM('TRANSFERENCIA CORRIENTE'!F63:H63) -> 0 | D62: =SUM('TRANSFERENCIA CORRIENTE'!I63:K63) -> 0 | E62: =SUM('TRANSFERENCIA CORRIENTE'!L63:N63) -> 0 | G62: =SUM(VS!C63:E63) -> 0 | H62: =SUM(VS!F63:H63) -> 0 | I62: =SUM(VS!I63:K63) -> 0 | J62: =SUM(VS!L63:N63) -> 0 | L62: =SUM(B62+G62) -> 0 | M62: =SUM(C62+H62) -> 0 | N62: =SUM(D62+I62) -> 0 | O62: =SUM(E62+J62) -> 0
A63: 2.7.3 - CONSTRUCCIONES EN BIENES CONCESIONADOS | B63: =SUM('TRANSFERENCIA CORRIENTE'!C64:E64) -> 0 | C63: =SUM('TRANSFERENCIA CORRIENTE'!F64:H64) -> 0 | D63: =SUM('TRANSFERENCIA CORRIENTE'!I64:K64) -> 0 | E63: =SUM('TRANSFERENCIA CORRIENTE'!L64:N64) -> 0 | G63: =SUM(VS!C64:E64) -> 0 | H63: =SUM(VS!F64:H64) -> 0 | I63: =SUM(VS!I64:K64) -> 0 | J63: =SUM(VS!L64:N64) -> 0 | L63: =SUM(B63+G63) -> 0 | M63: =SUM(C63+H63) -> 0 | N63: =SUM(D63+I63) -> 0 | O63: =SUM(E63+J63) -> 0
A64: 2.7.4 - GASTOS QUE SE ASIGNARÁN DURANTE EL EJERCICIO PARA INVERSIÓN (ART. 32 Y 33 LEY 423-06) | B64: =SUM('TRANSFERENCIA CORRIENTE'!C65:E65) -> 0 | C64: =SUM('TRANSFERENCIA CORRIENTE'!F65:H65) -> 0 | D64: =SUM('TRANSFERENCIA CORRIENTE'!I65:K65) -> 0 | E64: =SUM('TRANSFERENCIA CORRIENTE'!L65:N65) -> 0 | G64: =SUM(VS!C65:E65) -> 0 | H64: =SUM(VS!F65:H65) -> 0 | I64: =SUM(VS!I65:K65) -> 0 | J64: =SUM(VS!L65:N65) -> 0 | L64: =SUM(B64+G64) -> 0 | M64: =SUM(C64+H64) -> 0 | N64: =SUM(D64+I64) -> 0 | O64: =SUM(E64+J64) -> 0
A65: 2.8 - ADQUISICION DE ACTIVOS FINANCIEROS CON FINES DE POLÍTICA | B65: =SUM(B66:B67) -> 0 | C65: =SUM(C66:C67) -> 0 | D65: =SUM(D66:D67) -> 0 | E65: =SUM(E66:E67) -> 0 | G65: =SUM(G66:G67) -> 0 | H65: =SUM(H66:H67) -> 0 | I65: =SUM(I66:I67) -> 0 | J65: =SUM(J66:J67) -> 0 | L65: =SUM(B65+G65) -> 0 | M65: =SUM(C65+H65) -> 0 | N65: =SUM(D65+I65) -> 0 | O65: =SUM(E65+J65) -> 0
A66: 2.8.1 - CONCESIÓN DE PRESTAMOS | B66: =SUM('TRANSFERENCIA CORRIENTE'!C67:E67) -> 0 | C66: =SUM('TRANSFERENCIA CORRIENTE'!F67:H67) -> 0 | D66: =SUM('TRANSFERENCIA CORRIENTE'!I67:K67) -> 0 | E66: =SUM('TRANSFERENCIA CORRIENTE'!L67:N67) -> 0 | G66: =SUM(VS!C67:E67) -> 0 | H66: =SUM(VS!F67:H67) -> 0 | I66: =SUM(VS!I67:K67) -> 0 | J66: =SUM(VS!L67:N67) -> 0 | L66: =SUM(B66+G66) -> 0 | M66: =SUM(C66+H66) -> 0 | N66: =SUM(D66+I66) -> 0 | O66: =SUM(E66+J66) -> 0
A67: 2.8.2 - ADQUISICIÓN DE TÍTULOS VALORES REPRESENTATIVOS DE DEUDA | B67: =SUM('TRANSFERENCIA CORRIENTE'!C68:E68) -> 0 | C67: =SUM('TRANSFERENCIA CORRIENTE'!F68:H68) -> 0 | D67: =SUM('TRANSFERENCIA CORRIENTE'!I68:K68) -> 0 | E67: =SUM('TRANSFERENCIA CORRIENTE'!L68:N68) -> 0 | G67: =SUM(VS!C68:E68) -> 0 | H67: =SUM(VS!F68:H68) -> 0 | I67: =SUM(VS!I68:K68) -> 0 | J67: =SUM(VS!L68:N68) -> 0 | L67: =SUM(B67+G67) -> 0 | M67: =SUM(C67+H67) -> 0 | N67: =SUM(D67+I67) -> 0 | O67: =SUM(E67+J67) -> 0
A68: 2.9 - GASTOS FINANCIEROS | B68: =SUM(B69:B71) -> 0 | C68: =SUM(C69:C71) -> 0 | D68: =SUM(D69:D71) -> 0 | E68: =SUM(E69:E71) -> 0 | G68: =SUM(G69:G71) -> 0 | H68: =SUM(H69:H71) -> 0 | I68: =SUM(I69:I71) -> 0 | J68: =SUM(J69:J71) -> 0 | L68: =SUM(B68+G68) -> 0 | M68: =SUM(C68+H68) -> 0 | N68: =SUM(D68+I68) -> 0 | O68: =SUM(E68+J68) -> 0
A69: 2.9.1 - INTERESES DE LA DEUDA PÚBLICA INTERNA | B69: =SUM('TRANSFERENCIA CORRIENTE'!C70:E70) -> 0 | C69: =SUM('TRANSFERENCIA CORRIENTE'!F70:H70) -> 0 | D69: =SUM('TRANSFERENCIA CORRIENTE'!I70:K70) -> 0 | E69: =SUM('TRANSFERENCIA CORRIENTE'!L70:N70) -> 0 | G69: =SUM(VS!C70:E70) -> 0 | H69: =SUM(VS!F70:H70) -> 0 | I69: =SUM(VS!I70:K70) -> 0 | J69: =SUM(VS!L70:N70) -> 0 | L69: =SUM(B69+G69) -> 0 | M69: =SUM(C69+H69) -> 0 | N69: =SUM(D69+I69) -> 0 | O69: =SUM(E69+J69) -> 0
A70: 2.9.2 - INTERESES DE LA DEUDA PUBLICA EXTERNA | B70: =SUM('TRANSFERENCIA CORRIENTE'!C71:E71) -> 0 | C70: =SUM('TRANSFERENCIA CORRIENTE'!F71:H71) -> 0 | D70: =SUM('TRANSFERENCIA CORRIENTE'!I71:K71) -> 0 | E70: =SUM('TRANSFERENCIA CORRIENTE'!L71:N71) -> 0 | G70: =SUM(VS!C71:E71) -> 0 | H70: =SUM(VS!F71:H71) -> 0 | I70: =SUM(VS!I71:K71) -> 0 | J70: =SUM(VS!L71:N71) -> 0 | L70: =SUM(B70+G70) -> 0 | M70: =SUM(C70+H70) -> 0 | N70: =SUM(D70+I70) -> 0 | O70: =SUM(E70+J70) -> 0
A71: 2.9.4 - COMISIONES Y OTROS GASTOS BANCARIOS DE LA DEUDA PÚBLICA | B71: =SUM('TRANSFERENCIA CORRIENTE'!C72:E72) -> 0 | C71: =SUM('TRANSFERENCIA CORRIENTE'!F72:H72) -> 0 | D71: =SUM('TRANSFERENCIA CORRIENTE'!I72:K72) -> 0 | E71: =SUM('TRANSFERENCIA CORRIENTE'!L72:N72) -> 0 | H71: =SUM(VS!F72:H72) -> 0 | I71: =SUM(VS!I72:K72) -> 0 | J71: =SUM(VS!L72:N72) -> 0 | L71: =SUM(B71+G71) -> 0 | M71: =SUM(C71+H71) -> 0 | N71: =SUM(D71+I71) -> 0 | O71: =SUM(E71+J71) -> 0
A72: Total Gastos | B72: =+B8+B14+B24+B34+B42+B50+B60+B65+B68 -> 2.7188025e+08 | C72: =+C8+C14+C24+C34+C42+C50+C60+C65+C68 -> 2.7723165e+08 | D72: =+D8+D14+D24+D34+D42+D50+D60+D65+D68 -> 3.5596018e+08 | E72: =+E8+E14+E24+E34+E42+E50+E60+E65+E68 -> 2.6654135e+08 | G72: =+G8+G14+G24+G34+G42+G50+G60+G65+G68 -> 26194616 | H72: =+H8+H14+H24+H34+H42+H50+H60+H65+H68 -> 20399507 | I72: =+I8+I14+I24+I34+I42+I50+I60+I65+I68 -> 29377124 | J72: =+J8+J14+J24+J34+J42+J50+J60+J65+J68 -> 15188052 | L72: =SUM(B72+G72) -> 2.9807487e+08 | M72: =SUM(C72+H72) -> 2.9763115e+08 | N72: =SUM(D72+I72) -> 3.853373e+08 | O72: =SUM(E72+J72) -> 2.8172941e+08
A73: 4 - APLICACIONES FINANCIERAS | B73: =SUM('TRANSFERENCIA CORRIENTE'!C74:E74) -> 0 | C73: =SUM('TRANSFERENCIA CORRIENTE'!F74:H74) -> 0 | D73: =SUM('TRANSFERENCIA CORRIENTE'!I74:K74) -> 0 | E73: =SUM('TRANSFERENCIA CORRIENTE'!L74:N74) -> 0 | G73: =SUM(VS!C74:E74) -> 0 | H73: =SUM(VS!F74:H74) -> 0 | I73: =SUM(VS!I74:K74) -> 0 | J73: =SUM(VS!L74:N74) -> 0 | L73: =SUM(B73+G73) -> 0 | M73: =SUM(C73+H73) -> 0 | N73: =SUM(D73+I73) -> 0 | O73: =SUM(E73+J73) -> 0
A74: 4.1 - INCREMENTO DE ACTIVOS FINANCIEROS | B74: =SUM('TRANSFERENCIA CORRIENTE'!C75:E75) -> 0 | C74: =SUM('TRANSFERENCIA CORRIENTE'!F75:H75) -> 0 | D74: =SUM('TRANSFERENCIA CORRIENTE'!I75:K75) -> 0 | E74: =SUM('TRANSFERENCIA CORRIENTE'!L75:N75) -> 0 | G74: =SUM(VS!C75:E75) -> 0 | H74: =SUM(VS!F75:H75) -> 0 | I74: =SUM(VS!I75:K75) -> 0 | J74: =SUM(VS!L75:N75) -> 0 | L74: =SUM(B74+G74) -> 0 | M74: =SUM(C74+H74) -> 0 | N74: =SUM(D74+I74) -> 0 | O74: =SUM(E74+J74) -> 0
A75: 4.1.1 - INCREMENTO DE ACTIVOS FINANCIEROS CORRIENTES | B75: =SUM('TRANSFERENCIA CORRIENTE'!C76:E76) -> 0 | C75: =SUM('TRANSFERENCIA CORRIENTE'!F76:H76) -> 0 | D75: =SUM('TRANSFERENCIA CORRIENTE'!I76:K76) -> 0 | E75: =SUM('TRANSFERENCIA CORRIENTE'!L76:N76) -> 0 | G75: =SUM(VS!C76:E76) -> 0 | H75: =SUM(VS!F76:H76) -> 0 | I75: =SUM(VS!I76:K76) -> 0 | J75: =SUM(VS!L76:N76) -> 0 | L75: =SUM(B75+G75) -> 0 | M75: =SUM(C75+H75) -> 0 | N75: =SUM(D75+I75) -> 0 | O75: =SUM(E75+J75) -> 0
A76: 4.1.2 - INCREMENTO DE ACTIVOS FINANCIEROS NO CORRIENTES | B76: =SUM('TRANSFERENCIA CORRIENTE'!C77:E77) -> 0 | C76: =SUM('TRANSFERENCIA CORRIENTE'!F77:H77) -> 0 | D76: =SUM('TRANSFERENCIA CORRIENTE'!I77:K77) -> 0 | E76: =SUM('TRANSFERENCIA CORRIENTE'!L77:N77) -> 0 | G76: =SUM(VS!C77:E77) -> 0 | H76: =SUM(VS!F77:H77) -> 0 | I76: =SUM(VS!I77:K77) -> 0 | J76: =SUM(VS!L77:N77) -> 0 | L76: =SUM(B76+G76) -> 0 | M76: =SUM(C76+H76) -> 0 | N76: =SUM(D76+I76) -> 0 | O76: =SUM(E76+J76) -> 0
A77: 4.2 - DISMINUCIÓN DE PASIVOS | B77: =SUM('TRANSFERENCIA CORRIENTE'!C78:E78) -> 0 | C77: =SUM('TRANSFERENCIA CORRIENTE'!F78:H78) -> 0 | D77: =SUM('TRANSFERENCIA CORRIENTE'!I78:K78) -> 0 | E77: =SUM('TRANSFERENCIA CORRIENTE'!L78:N78) -> 0 | G77: =SUM(VS!C78:E78) -> 0 | H77: =SUM(VS!F78:H78) -> 0 | I77: =SUM(VS!I78:K78) -> 0 | J77: =SUM(VS!L78:N78) -> 0 | L77: =SUM(B77+G77) -> 0 | M77: =SUM(C77+H77) -> 0 | N77: =SUM(D77+I77) -> 0 | O77: =SUM(E77+J77) -> 0
A78: 4.2.1 - DISMINUCIÓN DE PASIVOS CORRIENTES | B78: =SUM('TRANSFERENCIA CORRIENTE'!C79:E79) -> 0 | C78: =SUM('TRANSFERENCIA CORRIENTE'!F79:H79) -> 0 | D78: =SUM('TRANSFERENCIA CORRIENTE'!I79:K79) -> 0 | E78: =SUM('TRANSFERENCIA CORRIENTE'!L79:N79) -> 0 | G78: =SUM(VS!C79:E79) -> 0 | H78: =SUM(VS!F79:H79) -> 0 | I78: =SUM(VS!I79:K79) -> 0 | J78: =SUM(VS!L79:N79) -> 0 | L78: =SUM(B78+G78) -> 0 | M78: =SUM(C78+H78) -> 0 | N78: =SUM(D78+I78) -> 0 | O78: =SUM(E78+J78) -> 0
A79: 4.2.2 - DISMINUCIÓN DE PASIVOS NO CORRIENTES | B79: =SUM('TRANSFERENCIA CORRIENTE'!C80:E80) -> 0 | C79: =SUM('TRANSFERENCIA CORRIENTE'!F80:H80) -> 0 | D79: =SUM('TRANSFERENCIA CORRIENTE'!I80:K80) -> 0 | E79: =SUM('TRANSFERENCIA CORRIENTE'!L80:N80) -> 0 | G79: =SUM(VS!C80:E80) -> 0 | H79: =SUM(VS!F80:H80) -> 0 | I79: =SUM(VS!I80:K80) -> 0 | J79: =SUM(VS!L80:N80) -> 0 | L79: =SUM(B79+G79) -> 0 | M79: =SUM(C79+H79) -> 0 | N79: =SUM(D79+I79) -> 0 | O79: =SUM(E79+J79) -> 0
A80: 4.3 - DISMINUCIÓN DE FONDOS DE TERCEROS | B80: =SUM('TRANSFERENCIA CORRIENTE'!C81:E81) -> 0 | C80: =SUM('TRANSFERENCIA CORRIENTE'!F81:H81) -> 0 | D80: =SUM('TRANSFERENCIA CORRIENTE'!I81:K81) -> 0 | E80: =SUM('TRANSFERENCIA CORRIENTE'!L81:N81) -> 0 | G80: =SUM(VS!C81:E81) -> 0 | H80: =SUM(VS!F81:H81) -> 0 | I80: =SUM(VS!I81:K81) -> 0 | J80: =SUM(VS!L81:N81) -> 0 | L80: =SUM(B80+G80) -> 0 | M80: =SUM(C80+H80) -> 0 | N80: =SUM(D80+I80) -> 0 | O80: =SUM(E80+J80) -> 0
A81: 4.3.5 - DISMINUCIÓN DEPÓSITOS FONDOS DE TERCEROS | B81: =SUM('TRANSFERENCIA CORRIENTE'!C82:E82) -> 0 | C81: =SUM('TRANSFERENCIA CORRIENTE'!F82:H82) -> 0 | D81: =SUM('TRANSFERENCIA CORRIENTE'!I82:K82) -> 0 | E81: =SUM('TRANSFERENCIA CORRIENTE'!L82:N82) -> 0 | G81: =SUM(VS!C82:E82) -> 0 | H81: =SUM(VS!F82:H82) -> 0 | I81: =SUM(VS!I82:K82) -> 0 | J81: =SUM(VS!L82:N82) -> 0 | L81: =SUM(B81+G81) -> 0 | M81: =SUM(C81+H81) -> 0 | N81: =SUM(D81+I81) -> 0 | O81: =SUM(E81+J81) -> 0
A82: TOTAL APLICACIONES FINANCIERAS | B82: =SUM(B83) -> 2.7188025e+08 | C82: =SUM(C83) -> 2.7723165e+08 | D82: =SUM(D83) -> 3.2049951e+08 | E82: =SUM(E83) -> 2.6654135e+08 | G82: =SUM(G83) -> 26194616 | H82: =SUM(H83) -> 20399507 | I82: =SUM(I83) -> 29377124 | J82: =SUM(J83) -> 15188052 | L82: =SUM(B82+G82) -> 2.9807487e+08 | M82: =SUM(C82+H82) -> 2.9763115e+08 | N82: =SUM(D82+I82) -> 3.4987663e+08 | O82: =SUM(E82+J82) -> 2.8172941e+08
A83: TOTAL GASTOS Y APLICACIONES FINANCIERAS | B83: =SUM('TRANSFERENCIA CORRIENTE'!C85:E85) -> 2.7188025e+08 | C83: =SUM('TRANSFERENCIA CORRIENTE'!F85:H85) -> 2.7723165e+08 | D83: =SUM('TRANSFERENCIA CORRIENTE'!I85:K85) -> 3.2049951e+08 | E83: =SUM('TRANSFERENCIA CORRIENTE'!L85:N85) -> 2.6654135e+08 | G83: =SUM(VS!C85:E85) -> 26194616 | H83: =SUM(VS!F85:H85) -> 20399507 | I83: =SUM(VS!I85:K85) -> 29377124 | J83: =SUM(VS!L85:N85) -> 15188052 | L83: =SUM(B83+G83) -> 2.9807487e+08 | M83: =SUM(C83+H83) -> 2.9763115e+08 | N83: =SUM(D83+I83) -> 3.4987663e+08 | O83: =SUM(E83+J83) -> 2.8172941e+08

Sheet Sheet2

Sheet TRANSFERENCIA CORRIENTE
A1: SERVICIO NACIONAL DE SALUD
A2: HOSPITAL MATERNO INFANTIL SAN LORENZO DE LOS MINA
A3: REGION
A4: Ejecución de Gastos Fondo (100) 2025
A5: En RD$
A7: Detalle | B7: Total | C7: Enero | D7: Febrero | E7: Marzo | F7: Abril | G7: Mayo | H7: Junio | I7: Julio | J7: Agosto | K7: Septiembre | L7: Octubre | M7: Noviembre | N7: Diciembre
A8: 2 - GASTOS
A9: 2.1 - REMUNERACIONES Y CONTRIBUCIONES | B9: =SUM(B10:B14) -> 8.1981716e+08 | C9: 65091180 | D9: 67131936 | E9: 66337620 | F9: 66556156 | G9: 66630551 | H9: 66583615 | I9: 71335676 | J9: 71831261 | K9: =SUM(K10:K14) -> 71591504 | L9: =SUM(L10:L14) -> 72986847 | M9: =SUM(M10:M14) -> 1.3374081e+08 | N9: 0
A10: 2.1.1 - REMUNERACIONES | B10: =SUM(C10:N10) -> 6.870623e+08 | C10: 53640339 | D10: 55586129 | E10: 54718737 | F10: 54771097 | G10: 54445140 | H10: 54868543 | I10: 58925421 | J10: 59410356 | K10: 59165425 | L10: 60398098 | M10: 1.2113301e+08
A11: 2.1.2 - SOBRESUELDOS | B11: =SUM(C11:N11) -> 36775586 | C11: 3196999.6 | D11: 3197999.6 | E11: 3199399.6 | F11: 3384964.5 | G11: 3807608.3 | H11: 3343226.2 | I11: 3344880.2 | J11: 3368105.6 | K11: 3321905.6 | L11: 3295047.1 | M11: 3315450.2
A12: 2.1.3 - DIETAS Y GASTOS DE REPRESENTACIÓN | B12: =SUM(C12:N12) -> 0
A13: 2.1.4 - GRATIFICACIONES Y BONIFICACIONES | B13: =SUM(C13:N13) -> 0
A14: 2.1.5 - CONTRIBUCIONES A LA SEGURIDAD SOCIAL | B14: =SUM(C14:N14) -> 95979276 | C14: 8253841.6 | D14: 8347807.5 | E14: 8419483.2 | F14: 8400093.9 | G14: 8377802.1 | H14: 8371846.2 | I14: 9065374.6 | J14: 9052799.4 | K14: 9104173.4 | L14: 9293701.9 | M14: 9292352.7
A15: 2.2 - CONTRATACIÓN DE SERVICIOS | B15: =SUM(C15:N15) -> 36550236 | C15: 0 | D15: 1336968.6 | E15: 7971396.2 | F15: 210535 | G15: 1680824.8 | H15: 8240458.4 | I15: 3509565.8 | J15: 3128332.8 | K15: =SUM(K16:K24) -> 7782458.8 | L15: =SUM(L16:L24) -> 792898.06 | M15: =SUM(M16:M24) -> 1896797.1 | N15: 0
A16: 2.2.1 - SERVICIOS BÁSICOS | B16: =SUM(C16:N16) -> 2504304.3 | E16: 2020024.3 | F16: 60535 | G16: 60535 | H16: 60535 | I16: 60535 | J16: 60535 | K16: 60535 | L16: 60535 | M16: 60535
A17: 2.2.2 - PUBLICIDAD, IMPRESIÓN Y ENCUADERNACIÓN | B17: =SUM(C17:N17) -> 866672.96 | D17: 324206.83 | G17: 32889.84 | H17: 319103.99 | J17: 88795 | K17: 47633.3 | L17: 54044
A18: 2.2.3 - VIÁTICOS | B18: =SUM(C18:N18) -> 0
A19: 2.2.4 - TRANSPORTE Y ALMACENAJE | B19: =SUM(C19:N19) -> 0
A20: 2.2.5 - ALQUILERES Y RENTAS | B20: =SUM(C20:N20) -> 598561.92 | F20: 150000 | J20: 150000 | L20: 298561.92
A21: 2.2.6 - SEGUROS | B21: =SUM(C21:N21) -> 0
A22: 2.2.7 - SERVICIOS DE CONSERVACIÓN, REPARACIONES MENORES E INSTALACIONES TEMPORALES | B22: =SUM(C22:N22) -> 21613740 | D22: 523061.81 | E22: 5951371.9 | G22: 1174400 | H22: 4437074.3 | I22: 3449030.8 | J22: 2829002.8 | K22: 1580779.5 | L22: 57257.14 | M22: 1611762.1
A23: 2.2.8 - OTROS SERVICIOS NO INCLUIDOS EN CONCEPTOS ANTERIORES | B23: =SUM(C23:N23) -> 5228700 | D23: 489700 | G23: 413000 | K23: 3779000 | L23: 322500 | M23: 224500
A24: 2.2.9 - OTRAS CONTRATACIONES DE SERVICIOS | B24: =SUM(C24:N24) -> 5738256 | H24: 3423745 | K24: 2314511
A25: 2.3 - MATERIALES Y SUMINISTROS | B25: =SUM(B26:B34) -> 2.0982483e+08 | C25: =SUM(C26:C34) -> 4970600.4 | D25: =SUM(D26:D34) -> 14433131 | E25: =SUM(E26:E34) -> 26749552 | F25: =SUM(F26:F34) -> 20368607 | G25: =SUM(G26:G34) -> 16608513 | H25: =SUM(H26:H34) -> 15408530 | I25: =SUM(I26:I34) -> 26146220 | ... N25: =SUM(N26:N34) -> 0
A26: 2.3.1 - ALIMENTOS Y PRODUCTOS AGROFORESTALES | B26: =SUM(C26:N26) -> 16530112 | D26: 591460.4 | E26: 3122436.8 | F26: 812515 | G26: 1657538 | H26: 2396946.2 | I26: 1787251.8 | J26: 2077230.7 | K26: 2180362.6 | L26: 1611805 | M26: 292565.2
A27: 2.3.2 - TEXTILES Y VESTUARIOS | B27: =SUM(C27:N27) -> 6077830.9 | D27: 61630.73 | F27: 1562980.5 | H27: 812418.96 | I27: 1577150.7 | J27: 180540 | K27: 1258116.1 | L27: 67260 | M27: 557734.03
A28: 2.3.3 - PRODUCTOS DE PAPEL, CARTÓN E IMPRESOS | B28: =SUM(C28:N28) -> 10218468 | D28: 352366.67 | E28: 1474545.2 | F28: 1510942.2 | G28: 765138.96 | H28: 715614.54 | I28: 1579886.7 | J28: 912967.7 | K28: 366980 | L28: 884486 | M28: 1655540
A29: 2.3.4 - PRODUCTOS FARMACÉUTICOS | B29: =SUM(C29:N29) -> 48543120 | C29: 1862880 | D29: 2014526.8 | E29: 6919929 | F29: 6349109 | G29: 2637285.6 | H29: 3022962 | I29: 6806505 | J29: 2962573 | K29: 9434300 | L29: 2958714.3 | M29: 3574335
A30: 2.3.5 - PRODUCTOS DE CUERO, CAUCHO Y PLÁSTICO | B30: =SUM(C30:N30) -> 2673759.3 | E30: 334708.95 | F30: 506546.35 | G30: 384413.08 | H30: 133281 | I30: 655140.22 | J30: 18313.6 | L30: 623201.43 | M30: 18154.65
A31: 2.3.6 - PRODUCTOS DE MINERALES, METÁLICOS Y NO METÁLICOS | B31: =SUM(C31:N31) -> 1202221.3 | D31: 11630.98 | F31: 351015.88 | G31: 215177.81 | H31: 101426.9 | J31: 286504 | L31: 236465.7
A32: 2.3.7 - COMBUSTIBLES, LUBRICANTES, PRODUCTOS QUÍMICOS Y CONEXOS | B32: =SUM(C32:N32) -> 51823570 | C32: 1844663.4 | D32: 3902915.5 | E32: 3162523 | F32: 2759191.9 | G32: 4409677.5 | H32: 2900109.8 | I32: 4028536.8 | J32: 2398944 | K32: 5003060.2 | L32: 19442217 | M32: 1971730.4
A33: 2.3.8 - GASTOS QUE SE ASIGNARÁN DURANTE EL EJERCICIO (ART. 32 Y 33 LEY 423-06) | B33: =SUM(C33:N33) -> 0
A34: 2.3.9 - PRODUCTOS Y ÚTILES VARIOS | B34: =SUM(C34:N34) -> 72755749 | C34: 1263057 | D34: 7498600.4 | E34: 11735409 | F34: 6516306.6 | G34: 6539281.9 | H34: 5325771 | I34: 9711748.4 | J34: 5484666.6 | K34: 6898829.2 | L34: 6072287.3 | M34: 5709792.1
A35: 2.4 - TRANSFERENCIAS CORRIENTES | B35: 0 | C35: 0 | D35: 0 | E35: 0 | F35: 0 | G35: 0 | H35: 0 | I35: 0 | J35: 0 | K35: =SUM(K36:K42) -> 0 | L35: 0 | M35: 0 | N35: 0
A36: 2.4.1 - TRANSFERENCIAS CORRIENTES AL SECTOR PRIVADO | B36: 0
A37: 2.4.2 - TRANSFERENCIAS CORRIENTES AL GOBIERNO GENERAL NACIONAL | B37: 0
A38: 2.4.3 - TRANSFERENCIAS CORRIENTES A GOBIERNOS GENERALES LOCALES | B38: 0
A39: 2.4.4 - TRANSFERENCIAS CORRIENTES A EMPRESAS PÚBLICAS NO FINANCIERAS | B39: 0
A40: 2.4.5 - TRANSFERENCIAS CORRIENTES A INSTITUCIONES PÚBLICAS FINANCIERAS | B40: 0
A41: 2.4.7 - TRANSFERENCIAS CORRIENTES AL SECTOR EXTERNO | B41: 0
A42: 2.4.9 - TRANSFERENCIAS CORRIENTES A OTRAS INSTITUCIONES PÚBLICAS | B42: 0
A43: 2.5 - TRANSFERENCIAS DE CAPITAL | B43: 0 | C43: 0 | D43: 0 | E43: 0 | F43: 0 | G43: 0 | H43: 0 | I43: 0 | J43: 0 | K43: =SUM(K44:K50) -> 0 | L43: 0 | M43: 0 | N43: 0
A44: 2.5.1 - TRANSFERENCIAS DE CAPITAL AL SECTOR PRIVADO | B44: 0
A45: 2.5.2 - TRANSFERENCIAS DE CAPITAL AL GOBIERNO GENERAL NACIONAL | B45: 0
A46: 2.5.3 - TRANSFERENCIAS DE CAPITAL A GOBIERNOS GENERALES LOCALES | B46: 0
A47: 2.5.4 - TRANSFERENCIAS DE CAPITAL A EMPRESAS PÚBLICAS NO FINANCIERAS | B47: 0
A48: 2.5.5 - TRANSFERENCIAS DE CAPITAL A INSTITUCIONES PÚBLICAS FINANCIERAS | B48: 0
A49: 2.5.6 - TRANSFERENCIAS DE CAPITAL AL SECTOR EXTERNO | B49: 0
A50: 2.5.9 - TRANSFERENCIAS DE CAPITAL A OTRAS INSTITUCIONES PÚBLICAS | B50: 0
A51: 2.6 - BIENES MUEBLES, INMUEBLES E INTANGIBLES | B51: =SUM(C51:N51) -> 69960538 | C51: 0 | D51: =SUM(D52:D60) -> 6461017.3 | E51: =SUM(E52:E60) -> 11396849 | F51: =SUM(F52:F60) -> 4665041.4 | G51: =SUM(G52:G60) -> 6580673.1 | H51: =SUM(H52:H60) -> 3698140.3 | I51: =SUM(I52:I60) -> 9300722.7 | J51: =SUM(J52:J60) -> 10590779 | K51: =SUM(K52:K60) -> 5819603.3 | ... N51: =SUM(N52:N60) -> 0
A52: 2.6.1 - MOBILIARIO Y EQUIPO | B52: =SUM(C52:N52) -> 12059863 | D52: 432420.86 | E52: 678205 | F52: 1812434.5 | G52: 231484.25 | H52: 1542516.3 | I52: 2268904.4 | J52: 2704062.9 | K52: 1146270 | L52: 1114944.2 | M52: 128621.02
A53: 2.6.2 - MOBILIARIO Y EQUIPO EDUCACIONAL Y RECREATIVO | B53: =SUM(C53:N53) -> 182926.74 | G53: 182926.74
A54: 2.6.3 - EQUIPO E INSTRUMENTAL, CIENTÍFICO Y LABORATORIO | B54: =SUM(C54:N54) -> 43061563 | D54: 6028596.4 | E54: 10715444 | F54: 2635786.9 | G54: 2285211.7 | H54: 1742624 | I54: 5025506.7 | J54: 1295400.2 | K54: 4197628.2 | L54: 1318181.5 | M54: 7817183.2
A55: 2.6.4 - VEHÍCULOS Y EQUIPO DE TRANSPORTE, TRACCIÓN Y ELEVACIÓN | B55: =SUM(C55:N55) -> 0
A56: 2.6.5 - MAQUINARIA, OTROS EQUIPOS Y HERRAMIENTAS | B56: =SUM(C56:N56) -> 14244544 | E56: 3199.97 | F56: 216820 | G56: 3535489.5 | H56: 413000 | I56: 2006311.6 | J56: 6591315.4 | K56: 409625.2 | L56: 1004138.8 | M56: 64643.06
A57: 2.6.6 - EQUIPOS DE DEFENSA Y SEGURIDAD | B57: =SUM(C57:N57) -> 66080 | K57: 66080
A58: 2.6.7 - ACTIVOS BIÓLOGICOS CULTIVABLES | B58: =SUM(C58:N58) -> 0
A59: 2.6.8 - BIENES INTANGIBLES | B59: =SUM(C59:N59) -> 0
A60: 2.6.9 - EDIFICIOS, ESTRUCTURAS, TIERRAS, TERRENOS Y OBJETOS DE VALOR | B60: =SUM(C60:N60) -> 345560.94 | G60: 345560.94
A61: 2.7 - OBRAS | B61: 0 | C61: 0 | D61: 0 | E61: 0 | F61: 0 | G61: 0 | H61: 0 | I61: 0 | J61: 0 | K61: 0 | L61: 0 | M61: 0 | N61: 0
A62: 2.7.1 - OBRAS EN EDIFICACIONES | B62: 0
A63: 2.7.2 - INFRAESTRUCTURA | B63: 0
A64: 2.7.3 - CONSTRUCCIONES EN BIENES CONCESIONADOS | B64: 0
A65: 2.7.4 - GASTOS QUE SE ASIGNARÁN DURANTE EL EJERCICIO PARA INVERSIÓN (ART. 32 Y 33 LEY 423-06) | B65: 0
A66: 2.8 - ADQUISICION DE ACTIVOS FINANCIEROS CON FINES DE POLÍTICA | B66: 0 | C66: 0 | D66: 0 | E66: 0 | F66: 0 | G66: 0 | H66: 0 | I66: 0 | J66: 0 | K66: 0 | L66: 0 | M66: 0 | N66: 0
A67: 2.8.1 - CONCESIÓN DE PRESTAMOS | B67: 0
A68: 2.8.2 - ADQUISICIÓN DE TÍTULOS VALORES REPRESENTATIVOS DE DEUDA | B68: 0
A69: 2.9 - GASTOS FINANCIEROS | B69: 0 | C69: 0 | D69: 0 | E69: 0 | F69: 0 | G69: 0 | H69: 0 | I69: 0 | J69: 0 | K69: 0 | L69: 0 | M69: 0 | N69: 0
A70: 2.9.1 - INTERESES DE LA DEUDA PÚBLICA INTERNA | B70: 0
A71: 2.9.2 - INTERESES DE LA DEUDA PUBLICA EXTERNA | B71: 0
A72: 2.9.4 - COMISIONES Y OTROS GASTOS BANCARIOS DE LA DEUDA PÚBLICA | B72: 0
A73: Total Gastos | B73: =+B51+B43+B35+B25+B15+B9 -> 1.1361528e+09 | C73: =+C51+C43+C35+C25+C15+C9 -> 70061780 | D73: =+D51+D43+D35+D25+D15+D9 -> 89363053 | E73: =+E51+E43+E35+E25+E15+E9 -> 1.1245542e+08 | F73: =+F51+F43+F35+F25+F15+F9 -> 91800340 | G73: =+G51+G43+G35+G25+G15+G9 -> 91500562 | H73: =+H51+H43+H35+H25+H15+H9 -> 93930744 | I73: =+I51+I43+I35+I25+I15+I9 -> 1.1029218e+08 | ... N73: =+N51+N43+N35+N25+N15+N9 -> 0
A74: 4 - APLICACIONES FINANCIERAS
A75: 4.1 - INCREMENTO DE ACTIVOS FINANCIEROS
A76: 4.1.1 - INCREMENTO DE ACTIVOS FINANCIEROS CORRIENTES
A77: 4.1.2 - INCREMENTO DE ACTIVOS FINANCIEROS NO CORRIENTES
A78: 4.2 - DISMINUCIÓN DE PASIVOS
A79: 4.2.1 - DISMINUCIÓN DE PASIVOS CORRIENTES
A80: 4.2.2 - DISMINUCIÓN DE PASIVOS NO CORRIENTES
A81: 4.3 - DISMINUCIÓN DE FONDOS DE TERCEROS
A82: 4.3.5 - DISMINUCIÓN DEPÓSITOS FONDOS DE TERCEROS
A83: TOTAL APLICACIONES FINANCIERAS
A85: TOTAL GASTOS Y APLICACIONES FINANCIERAS | B85: =+B73 -> 1.1361528e+09 | C85: =+C73 -> 70061780 | D85: =+D73 -> 89363053 | E85: =+E73 -> 1.1245542e+08 | F85: =+F73 -> 91800340 | G85: =+G73 -> 91500562 | H85: =+H73 -> 93930744 | I85: =+I73 -> 1.1029218e+08 | ... N85: =+N73 -> 0
A86: Fuente: [fuente]
A87: Fecha de registro: hasta el [01] de [01] del [2025]
A88: Fecha de imputación: hasta el [30] de [11] del [2025]

Sheet VS
A1: SERVICIO NACIONAL DE SALUD
A2: HOSPITAL MATERNO INFANTIL SAN LORENZO DE LOS MINA
A3: REGION
A4: Ejecución de Gastos VENTA SERVICIOS 2025
A5: En RD$
A7: Detalle | B7: Total | C7: Enero | D7: Febrero | E7: Marzo | F7: Abril | G7: Mayo | H7: Junio | I7: Julio | J7: Agosto | K7: Septiembre | L7: Octubre | M7: Noviembre | N7: Diciembre
A8: 2 - GASTOS
A9: 2.1 - REMUNERACIONES Y CONTRIBUCIONES | B9: =SUM(C9:N9) -> 9644681.1 | C9: 0 | D9: 0 | E9: 5231553.6 | F9: 0 | G9: 0 | H9: 0 | I9: 0 | J9: 0 | K9: =SUM(K10:K14) -> 4413127.6 | L9: 0 | M9: =SUM(M10:M14) -> 0 | N9: 0
A10: 2.1.1 - REMUNERACIONES | B10: =SUM(C10:N10) -> 0
A11: 2.1.2 - SOBRESUELDOS | B11: =SUM(C11:N11) -> 9644681.1 | E11: 5231553.6 | K11: 4413127.6
A12: 2.1.3 - DIETAS Y GASTOS DE REPRESENTACIÓN | B12: =SUM(C12:N12) -> 0
A13: 2.1.4 - GRATIFICACIONES Y BONIFICACIONES | B13: =SUM(C13:N13) -> 0
A14: 2.1.5 - CONTRIBUCIONES A LA SEGURIDAD SOCIAL | B14: =SUM(C14:N14) -> 0
A15: 2.2 - CONTRATACIÓN DE SERVICIOS | B15: =SUM(C15:N15) -> 29973175 | C15: 2733844.3 | D15: 1213383.4 | E15: 4359456.2 | F15: 1256712.1 | G15: 2044062.6 | H15: 3938639.1 | I15: 5012155.8 | J15: 3808523.8 | K15: =SUM(K16:K24) -> 1557736.2 | L15: =SUM(L16:L24) -> 1964841.4 | M15: =SUM(M16:M24) -> 2083820.5 | N15: 0
A16: 2.2.1 - SERVICIOS BÁSICOS | B16: =SUM(C16:N16) -> 9480180.1 | C16: 351316.33 | D16: 259054.4 | E16: 1731191.2 | F16: 285608.3 | G16: 1098463.4 | H16: 964509 | I16: 1781904.1 | J16: 933611.83 | K16: 161421.68 | L16: 1168099.9 | M16: 745000
A17: 2.2.2 - PUBLICIDAD, IMPRESIÓN Y ENCUADERNACIÓN | B17: =SUM(C17:N17) -> 1719123.4 | H17: 310139.4 | I17: 581445 | J17: 336559.6 | K17: 269720.57 | M17: 221258.85
A18: 2.2.3 - VIÁTICOS | B18: =SUM(C18:N18) -> 40000 | L18: 40000
A19: 2.2.4 - TRANSPORTE Y ALMACENAJE | B19: =SUM(C19:N19) -> 248000 | D19: 24000 | E19: 32000 | G19: 76000 | H19: 20000 | I19: 8000 | K19: 68000 | M19: 20000
A20: 2.2.5 - ALQUILERES Y RENTAS | B20: =SUM(C20:N20) -> 2503964.6 | C20: 266664.25 | D20: 252960.9 | F20: 229519.78 | G20: 529650.64 | I20: 298861.54 | J20: 628164.1 | L20: 298143.38
A21: 2.2.6 - SEGUROS | B21: =SUM(C21:N21) -> 3449.08 | L21: 3449.08
A22: 2.2.7 - SERVICIOS DE CONSERVACIÓN, REPARACIONES MENORES E INSTALACIONES TEMPORALES | B22: =SUM(C22:N22) -> 9383610.9 | C22: 2064518.4 | D22: 472756.61 | E22: 2019575.2 | F22: 199877.53 | G22: 205899.14 | H22: 635040.9 | I22: 1632573.3 | J22: 925675.21 | K22: 802020.26 | L22: 6500 | M22: 419174.45
A23: 2.2.8 - OTROS SERVICIOS NO INCLUIDOS EN CONCEPTOS ANTERIORES | B23: =SUM(C23:N23) -> 5134830.3 | C23: 51345.35 | D23: 204611.44 | E23: 576689.87 | F23: 541706.48 | G23: 134049.4 | H23: 1098662.4 | I23: 709371.88 | J23: 524832.27 | K23: 166524.93 | L23: 448649 | M23: 678387.24
A24: 2.2.9 - OTRAS CONTRATACIONES DE SERVICIOS | B24: =SUM(C24:N24) -> 1460016.9 | H24: 910287.4 | J24: 459680.8 | K24: 90048.75
A25: 2.3 - MATERIALES Y SUMINISTROS | B25: =SUM(B26:B34) -> 31006923 | C25: =SUM(C26:C34) -> 3062630.7 | D25: =SUM(D26:D34) -> 2432378.3 | E25: =SUM(E26:E34) -> 1797538.3 | F25: =SUM(F26:F34) -> 2995765.2 | G25: =SUM(G26:G34) -> 2557401.6 | H25: =SUM(H26:H34) -> 999513.81 | I25: =SUM(I26:I34) -> 3444623.9 | ... M25: =SUM(M26:M34) -> 2184325.9 | N25: 0
A26: 2.3.1 - ALIMENTOS Y PRODUCTOS AGROFORESTALES | B26: =SUM(C26:N26) -> 4186963.5 | C26: 541265 | D26: 300691.8 | E26: 658799 | F26: 94850 | G26: 355075 | H26: 213305 | I26: 360730 | J26: 166750 | K26: 1046945.7 | L26: 285227 | M26: 163325
A27: 2.3.2 - TEXTILES Y VESTUARIOS | B27: =SUM(C27:N27) -> 346306.4 | G27: 141128 | H27: 205178.4
A28: 2.3.3 - PRODUCTOS DE PAPEL, CARTÓN E IMPRESOS | B28: =SUM(C28:N28) -> 1789484 | C28: 85550 | D28: 107616 | E28: 57997 | F28: 196824 | G28: 607165 | I28: 26550 | J28: 690182 | K28: 17600.03
A29: 2.3.4 - PRODUCTOS FARMACÉUTICOS | B29: =SUM(C29:N29) -> 4023780.8 | C29: 308000 | E29: 250000 | F29: 92000 | G29: 130100 | H29: 180120.76 | I29: 152800 | J29: 269200 | K29: 74000 | L29: 2183260 | M29: 384300
A30: 2.3.5 - PRODUCTOS DE CUERO, CAUCHO Y PLÁSTICO | B30: =SUM(C30:N30) -> 1006371.6 | D30: 249831.2 | E30: 317663.67 | I30: 77390.01 | J30: 62924.77 | M30: 298561.92
A31: 2.3.6 - PRODUCTOS DE MINERALES, METÁLICOS Y NO METÁLICOS | B31: =SUM(C31:N31) -> 506384.37 | D31: 183732.33 | E31: 110224.97 | I31: 24157.95 | J31: 187394.11 | L31: 875.01
A32: 2.3.7 - COMBUSTIBLES, LUBRICANTES, PRODUCTOS QUÍMICOS Y CONEXOS | B32: =SUM(C32:N32) -> 6598652.6 | C32: 228412.84 | D32: 1114592.7 | E32: 317328.99 | F32: 226537 | G32: 1065923 | H32: 207742 | I32: 1044515 | J32: 250850.02 | K32: 1029096 | L32: 778905.4 | M32: 334749.6
A33: 2.3.8 - GASTOS QUE SE ASIGNARÁN DURANTE EL EJERCICIO (ART. 32 Y 33 LEY 423-06) | B33: =SUM(C33:N33) -> 0
A34: 2.3.9 - PRODUCTOS Y ÚTILES VARIOS | B34: =SUM(C34:N34) -> 12548980 | C34: 1899402.8 | D34: 475914.23 | E34: 85524.69 | F34: 2385554.2 | G34: 258010.6 | H34: 193167.65 | I34: 1758480.9 | J34: 851056.62 | K34: 1001234 | L34: 2637244.9 | M34: 1003389.3
A35: 2.4 - TRANSFERENCIAS CORRIENTES | B35: =SUM(B36:B42) -> 1638138.7 | C35: =SUM(C36:C42) -> 136966.7 | D35: =SUM(D36:D42) -> 23400 | E35: =SUM(E36:E42) -> 127420 | F35: =SUM(F36:F42) -> 624573 | G35: =SUM(G36:G42) -> 480808 | H35: =SUM(H36:H42) -> 118600 | I35: =SUM(I36:I42) -> 67571 | ... N35: =SUM(N36:N42) -> 0
A36: 2.4.1 - TRANSFERENCIAS CORRIENTES AL SECTOR PRIVADO | B36: =SUM(C36:N36) -> 1638138.7 | C36: 136966.7 | D36: 23400 | E36: 127420 | F36: 624573 | G36: 480808 | H36: 118600 | I36: 67571 | J36: 33600 | K36: 21600 | M36: 3600
A37: 2.4.2 - TRANSFERENCIAS CORRIENTES AL GOBIERNO GENERAL NACIONAL | B37: =SUM(C37:N37) -> 0
A38: 2.4.3 - TRANSFERENCIAS CORRIENTES A GOBIERNOS GENERALES LOCALES | B38: =SUM(C38:N38) -> 0
A39: 2.4.4 - TRANSFERENCIAS CORRIENTES A EMPRESAS PÚBLICAS NO FINANCIERAS | B39: =SUM(C39:N39) -> 0
A40: 2.4.5 - TRANSFERENCIAS CORRIENTES A INSTITUCIONES PÚBLICAS FINANCIERAS | B40: =SUM(C40:N40) -> 0
A41: 2.4.7 - TRANSFERENCIAS CORRIENTES AL SECTOR EXTERNO | B41: =SUM(C41:N41) -> 0
A42: 2.4.9 - TRANSFERENCIAS CORRIENTES A OTRAS INSTITUCIONES PÚBLICAS | B42: =SUM(C42:N42) -> 0
A43: 2.5 - TRANSFERENCIAS DE CAPITAL | B43: =SUM(C43:N43) -> 0 | C43: 0 | D43: 0 | E43: 0 | F43: 0 | G43: 0 | H43: 0 | I43: 0 | J43: 0 | K43: =SUM(K44:K50) -> 0 | L43: 0 | M43: 0 | N43: 0
A44: 2.5.1 - TRANSFERENCIAS DE CAPITAL AL SECTOR PRIVADO | B44: =SUM(C44:N44) -> 0
A45: 2.5.2 - TRANSFERENCIAS DE CAPITAL AL GOBIERNO GENERAL NACIONAL | B45: =SUM(C45:N45) -> 0
A46: 2.5.3 - TRANSFERENCIAS DE CAPITAL A GOBIERNOS GENERALES LOCALES | B46: =SUM(C46:N46) -> 0
A47: 2.5.4 - TRANSFERENCIAS DE CAPITAL A EMPRESAS PÚBLICAS NO FINANCIERAS | B47: =SUM(C47:N47) -> 0
A48: 2.5.5 - TRANSFERENCIAS DE CAPITAL A INSTITUCIONES PÚBLICAS FINANCIERAS | B48: =SUM(C48:N48) -> 0
A49: 2.5.6 - TRANSFERENCIAS DE CAPITAL AL SECTOR EXTERNO | B49: =SUM(C49:N49) -> 0
A50: 2.5.9 - TRANSFERENCIAS DE CAPITAL A OTRAS INSTITUCIONES PÚBLICAS | B50: =SUM(C50:N50) -> 0
A51: 2.6 - BIENES MUEBLES, INMUEBLES E INTANGIBLES | B51: =SUM(B52:B60) -> 18896380 | C51: =SUM(C52:C60) -> 887994.84 | D51: =SUM(D52:D60) -> 3887510 | E51: =SUM(E52:E60) -> 300539.37 | F51: =SUM(F52:F60) -> 0 | G51: =SUM(G52:G60) -> 3927042.2 | H51: =SUM(H52:H60) -> 1456389 | I51: =SUM(I52:I60) -> 730510.01 | ... N51: =SUM(N52:N60) -> 0
A52: 2.6.1 - MOBILIARIO Y EQUIPO | B52: =SUM(C52:N52) -> 3388423.9 | H52: 7995.01 | J52: 684631.95 | K52: 2245366 | L52: 7986.24 | M52: 442444.72
A53: 2.6.2 - MOBILIARIO Y EQUIPO EDUCACIONAL Y RECREATIVO | B53: =SUM(C53:N53) -> 1788880 | H53: 1399834 | I53: 389046
A54: 2.6.3 - EQUIPO E INSTRUMENTAL, CIENTÍFICO Y LABORATORIO | B54: =SUM(C54:N54) -> 10661143 | C54: 887994.84 | D54: 2075030 | G54: 3927042.2 | H54: 48559.95 | J54: 1710444.5 | L54: 112271.1 | M54: 1899800
A55: 2.6.4 - VEHÍCULOS Y EQUIPO DE TRANSPORTE, TRACCIÓN Y ELEVACIÓN | B55: =SUM(C55:N55) -> 107609.37 | E55: 107609.37
A56: 2.6.5 - MAQUINARIA, OTROS EQUIPOS Y HERRAMIENTAS | B56: =SUM(C56:N56) -> 2891560 | D56: 1812480 | E56: 192930 | I56: 282700.01 | L56: 190450.01 | M56: 413000
A57: 2.6.6 - EQUIPOS DE DEFENSA Y SEGURIDAD | B57: =SUM(C57:N57) -> 58764 | I57: 58764
A58: 2.6.7 - ACTIVOS BIÓLOGICOS CULTIVABLES | B58: =SUM(C58:N58) -> 0
A59: 2.6.8 - BIENES INTANGIBLES | B59: =SUM(C59:N59) -> 0
A60: 2.6.9 - EDIFICIOS, ESTRUCTURAS, TIERRAS, TERRENOS Y OBJETOS DE VALOR | B60: =SUM(C60:N60) -> 0
A61: 2.7 - OBRAS | B61: =SUM(C61:N61) -> 0 | C61: 0 | D61: 0 | E61: 0 | F61: 0 | G61: 0 | H61: 0 | I61: 0 | J61: 0 | K61: =SUM(K62:K65) -> 0 | L61: 0 | M61: =SUM(M62:M65) -> 0 | N61: 0
A62: 2.7.1 - OBRAS EN EDIFICACIONES | B62: =SUM(C62:N62) -> 0
A63: 2.7.2 - INFRAESTRUCTURA | B63: =SUM(C63:N63) -> 0
A64: 2.7.3 - CONSTRUCCIONES EN BIENES CONCESIONADOS | B64: =SUM(C64:N64) -> 0
A65: 2.7.4 - GASTOS QUE SE ASIGNARÁN DURANTE EL EJERCICIO PARA INVERSIÓN (ART. 32 Y 33 LEY 423-06) | B65: =SUM(C65:N65) -> 0
A66: 2.8 - ADQUISICION DE ACTIVOS FINANCIEROS CON FINES DE POLÍTICA | B66: =SUM(C66:N66) -> 0 | C66: 0 | D66: 0 | E66: 0 | F66: 0 | G66: 0 | H66: 0 | I66: 0 | J66: 0 | K66: 0 | L66: 0 | M66: =SUM(M67:M68) -> 0 | N66: 0
A67: 2.8.1 - CONCESIÓN DE PRESTAMOS | B67: =SUM(C67:N67) -> 0
A68: 2.8.2 - ADQUISICIÓN DE TÍTULOS VALORES REPRESENTATIVOS DE DEUDA | B68: =SUM(C68:N68) -> 0
A69: 2.9 - GASTOS FINANCIEROS | B69: =SUM(C69:N69) -> 0 | C69: 0 | D69: 0 | E69: 0 | F69: 0 | G69: 0 | H69: 0 | I69: 0 | J69: 0 | K69: 0 | L69: 0 | M69: =SUM(M70:M72) -> 0 | N69: 0
A70: 2.9.1 - INTERESES DE LA DEUDA PÚBLICA INTERNA | B70: =SUM(C70:N70) -> 0
A71: 2.9.2 - INTERESES DE LA DEUDA PUBLICA EXTERNA | B71: =SUM(C71:N71) -> 0
A72: 2.9.4 - COMISIONES Y OTROS GASTOS BANCARIOS DE LA DEUDA PÚBLICA | B72: =SUM(C72:N72) -> 0
A73: Total Gastos | B73: =+B9+B15+B25+B35+B43+B51+B61+B66+B69 -> 91159298 | C73: =+C9+C15+C25+C35+C43+C51+C61+C66+C69 -> 6821436.5 | D73: =+D9+D15+D25+D35+D43+D51+D61+D66+D69 -> 7556671.6 | E73: =+E9+E15+E25+E35+E43+E51+E61+E66+E69 -> 11816507 | F73: =+F9+F15+F25+F35+F43+F51+F61+F66+F69 -> 4877050.3 | G73: =+G9+G15+G25+G35+G43+G51+G61+G66+G69 -> 9009314.4 | H73: =+H9+H15+H25+H35+H43+H51+H61+H66+H69 -> 6513141.9 | I73: =+I9+I15+I25+I35+I43+I51+I61+I66+I69 -> 9254860.6 | ... N73: =+N9+N15+N25+N35+N43+N51+N61+N66+N69 -> 0
A74: 4 - APLICACIONES FINANCIERAS | B74: =SUM(C74:N74) -> 0
A75: 4.1 - INCREMENTO DE ACTIVOS FINANCIEROS | B75: =SUM(C75:N75) -> 0
A76: 4.1.1 - INCREMENTO DE ACTIVOS FINANCIEROS CORRIENTES | B76: =SUM(C76:N76) -> 0
A77: 4.1.2 - INCREMENTO DE ACTIVOS FINANCIEROS NO CORRIENTES | B77: =SUM(C77:N77) -> 0
A78: 4.2 - DISMINUCIÓN DE PASIVOS | B78: =SUM(C78:N78) -> 0
A79: 4.2.1 - DISMINUCIÓN DE PASIVOS CORRIENTES | B79: =SUM(C79:N79) -> 0
A80: 4.2.2 - DISMINUCIÓN DE PASIVOS NO CORRIENTES | B80: =SUM(C80:N80) -> 0
A81: 4.3 - DISMINUCIÓN DE FONDOS DE TERCEROS | B81: =SUM(C81:N81) -> 0
A82: 4.3.5 - DISMINUCIÓN DEPÓSITOS FONDOS DE TERCEROS | B82: =SUM(C82:N82) -> 0
A83: TOTAL APLICACIONES FINANCIERAS | B83: =SUM(C83:N83) -> 0
B84: =SUM(C84:N84) -> 0
A85: TOTAL GASTOS Y APLICACIONES FINANCIERAS | B85: =+B83+B73 -> 91159298 | C85: =+C83+C73 -> 6821436.5 | D85: =+D83+D73 -> 7556671.6 | E85: =+E83+E73 -> 11816507 | F85: =+F83+F73 -> 4877050.3 | G85: =+G83+G73 -> 9009314.4 | H85: =+H83+H73 -> 6513141.9 | I85: =+I83+I73 -> 9254860.6 | ... N85: =+N83+N73 -> 0
A86: Fuente: [fuente]
A87: Fecha de registro: hasta el [01] de [01] del [2025]
A88: Fecha de imputación: hasta el [30] de [11] del [2025]

Sheet OBLIGACIONES PENDIENTES
A4: SERVICIO REGIONAL DE SALUD
A5: DIRECCIÓN DE FISCALIZACIÓN Y CONTROL
A6: DETALLE OBLIGACIONES CONTRAÍDAS PENDIENTES AL 30 DE NOVIEMBRE 2025
A7: HOSPITAL MATERNO INFANTIL SAN LORENZO DE LOS MINA
A8: A | B8: B | D8: C | E8: D | F8: E | G8: F
A9: TIPO | B9: PERÍODO | E9: STATUS PRESTAMO
B10: DESDE | C10: HASTA | D10: MONTO | E10: MONTO ORIGEN | F10: MONTO AMORTIZADO | G10: BALANCE PENDIENTE
A11: PROMESE CAL
A12: RETENCIONES DE IMPUESTOS (DGII) | B12: 44470 | C12: 45991 | D12: =13514741.06+303701.48 -> 13818443
A13: APROVISIONAMIENTOS DE INCENTIVOS | B13: 45505 | C13: 45991 | D13: =4817972.08-4413127.55+1227716.05+745396.13+892519.41 -> 3270476.1
A14: SEGURIDAD SOCIAL
A15: APROVISIONAMIENTO DE REGALIA PASCUAL
A16: PRESTACIONES LABORALES
A17: VIATICOS
A18: PRÉSTAMOS Y/O ANTICIPOS FINANCIEROS OTORGADOS POR SENASA
A19: TOTAL | D19: 18332713
A21: Nota. En el caso de las columnas D, E y F, solo aplican para llenado de los préstamos otogados por SENASA.
A25: Preparado por: | D25: Revisado por:
A34: ___________________________________________

Sheet INGR SEGUN ORIGEN
A3: Servicio Nacional de Salud
A4: Dirección de Fiscalización
A6: Comportamiento de Ingresos percibidos Segregados según Origen
A7: Establecimiento: HOSPITAL MATERNO INFANTIL SAN LORENZO DE LOS MINA Mes: NOVIEMBRE . Año: 2025 SRS: I
A8: origen | B8: ARS | C8: Fecha deposito | D8: No. De Documento de referencia | E8: valor de Transferencia o Cheque
A9: INGRESOS | B9: FONDO 100(2.1) | E9: =89977894.99+50197656.33 -> 1.4017555e+08
B10: FONDO 100 (2.3) | E10: 12923035
B11: FONDO 100 (2.6) | E11: 3169632.1
A12: Sub-Total | E12: =SUM(E9:E11) -> 1.5626822e+08
A13: Venta de Servicio | B13: SUBSIDIADO | C13: 45964 | E13: 3879690.4
B14: SUBSIDIADO (odontologia) | C14: 45965 | E14: 50000
B15: SUBSIDIADO (odontologia) | C15: 45966 | E15: 50000
B16: SUBSIDIADO | C16: 45972 | E16: 500
B17: SEMMA | C17: 45974 | E17: 12492.5
B18: SUBSIDIADO | C18: 45975 | E18: 6000
B19: ARS RENACER | C19: 45979 | E19: 310138.92
B20: CONTRIBUTIVO | C20: 45979 | E20: 2110440.8
B21: ARS SENASA PENSIONADO | C21: 45979 | E21: 18188.8
B22: ARS PRIMERA HUMANO | C22: 45980 | E22: 848860.46
B23: ARS HUMANO | C23: 45980 | E23: 70034.89
B24: ARS MAPHRE | C24: 45981 | E24: 6044.93
B25: ARS MAPHRE | C25: 45981 | E25: 67416
... B34: ARS FUTURO | C34: 45989 | E34: 802889.48
A35: Sub-Total INGR. POR FACT DE SERV. DE INSTITUCIONES | E35: =SUM(E13:E34) -> 8925194.1
B36: Cafetería | E36: 0
B37: Odontologia (facturacion servicios no contemplado en Plan Basico) | C37: DEL 01 AL 30 DE NOVIEMBRE 2025 | E37: 168425
B38: Alquiler de espacios internos a terceros
B39: Aportes provenientes de convenios Institucionales | C39: DEL 01 AL 30 DE NOVIEMBRE 2025 | E39: 30000
B40: INGRESOS POR SERVICIOS PACIENTES PRIVADOS Y DIFERENCIAS POR SEGUROS MEDICOS
B41: Otros (INGRESOS EXTRANJEROS ) | C41: DEL 01 AL 30 DE NOVIEMBRE 2025 | E41: 185750
A42: Sub-Total | E42: =+E37+E41+E36+E39 -> 384175
A43: Total General | E43: =+E42+E35+E12 -> 1.6557759e+08
A46: Bajo las funciones que nos asisten certificamos que el valor de los ingresos percibidos al 30/11/2025 correspondieron a un monto de RD$165,577,587.02
A49: Dado a los 30 dias del mes de noviembre del año 2025
A51: Cuenta Núm. | B51: Balance en libro | C51: Balance en Banco | D51: Balance Conciliado
A52: 010-390450-6 | B52: 2685939.8 | C52: 3066800.8 | D52: 2685939.8
A53: 010-026900-0 | B53: 1.6989873e+08 | C53: 1.6989873e+08 | D53: 1.6989873e+08
A54: 602-500900-0 | B54: 3768456.6 | C54: 3768456.6 | D54: 3768456.6
A55: 999-510700-0 | B55: 4423428.7 | C55: 4423428.7 | D55: 4423428.7
B56: =SUM(B52:B55) -> 1.8077656e+08 | C56: =SUM(C52:C55) -> 1.8115742e+08 | D56: =SUM(D52:D55) -> 1.8077656e+08
A60: Preparado por: | D60: Revisado por:
B61: ____________________________________ | D61: ___________________________________
A62: Aprobado por:
B63: ________________________________

Sheet Sheet1
A1: 7800 | B1: 11000 | D1: 11000
A2: 5100 | B2: 45000 | D2: 45000
A3: 900 | B3: 13100 | D3: 13100
A4: 5100 | B4: 74050 | D4: 74050
A5: 11400 | B5: 42900 | D5: 42900
A6: 11500 | B6: 43800 | D6: 43800
A7: 4600 | B7: 57000 | D7: 57000
A8: 5000 | B8: 12200
A9: 13200 | B9: 4500
A10: 5300
A11: 1400
A12: 3300
A13: 4700
A14: 7300
A15: 2750
A16: 5400
A17: 5000
A18: 4500
A19: 5300
A20: 5450
A21: 8800
... A30: 3200
A31: =SUM(A1:A30) -> 185750 | B31: =SUM(B1:B30) -> 303550
A32: 191950
A33: =+A31-A32 -> -6200

Sheet DEUDA
A1: Deuda Autogestion
A2: Reporte clasificacion de deuda por proveedor y por periodos.
A3: Nombre del Establecimiento: HOSPITAL MATERNO INFANTIL SAN LORENZO DE LOS MINA
A4: No. | B4: Proveedor | E4: PERIODOS
C5: Concepto de Compras | D5: Fuente Financiamiento | E5: ≤2014 | F5: 2015-2019 | G5: 2020 | H5: 2021 | I5: 2022 | J5: 2023 | K5: 2024 | L5: 31 DE ENERO 2025 | M5: 28 DE FEBRERO 2025 | N5: 31 DE MARZO 2025 | O5: 30 DE ABRIL 2025 | P5: 31 DE MAYO 2025 | Q5: 30 DE JUNIO 2025 | R5: 31 DE JULIO 2025 | S5: 31 DE AGOSTO 2025 | T5: 30 DE SEPTIEMBRE 2025 | U5: 31 DE OCTUBRE 2025 | V5: 30 DE NOVIEMBRE 2025 | W5: Total | X5: OBSERVACIONES
A6: 1 | B6: GA INTERPRISE IMPORT, SRL | D6: VS/FG | J6: 287920 | W6: =SUM(J6:V6) -> 287920 | X6: IMPUESTOS
A7: 2 | B7: D, CORA INDUSTRIAL, S.R.L | D7: VS/FG | J7: 220483.05 | W7: =SUM(J7:V7) -> 220483.05 | X7: IMPUESTOS
A8: 3 | B8: Bio Nuclear, SA | D8: VS/FG | J8: 4182 | W8: =SUM(J8:V8) -> 4182 | X8: PROBLEMAS CON EL COMPROBANTE, EN ESPERA DEL PROVEEDOR PARA EL CAMBIO DE NCF
A9: 4 | B9: Insocorp, S.R.L. | D9: VS/FG | K9: 162462.4 | W9: =SUM(J9:V9) -> 162462.4 | X9: PROBLEMAS CON EL COMPROBANTE, EN ESPERA DEL PROVEEDOR PARA EL CAMBIO DE NCF
A10: 5 | B10: J. JIREH EQUIPOS MEDICOS SRL | D10: VS/FG | K10: 16520 | W10: =SUM(J10:V10) -> 16520 | X10: IMPUESTOS
A11: 6 | B11: Ciencia Tecnología y Consultas, SRL (CIENTEC) | D11: VS/FG | L11: 5691.23 | W11: =SUM(J11:V11) -> 5691.23 | X11: PROBLEMAS CON EL COMPROBANTE, EN ESPERA DEL PROVEEDOR PARA EL CAMBIO DE NCF
A12: 7 | B12: Agua Planeta Azul, SA | D12: VS/FG | N12: 9500 | W12: =SUM(J12:V12) -> 9500 | X12: PROBLEMAS CON EL COMPROBANTE, EN ESPERA DEL PROVEEDOR PARA EL CAMBIO DE NCF
A13: 8 | B13: FARMACIA RUTH | D13: VS/FG | O13: 13900 | W13: =SUM(J13:V13) -> 13900 | X13: PROBLEMAS CON LA ORDEN
A14: 9 | B14: FARMACIA RUTH | D14: VS/FG | P14: 18500 | W14: =SUM(J14:V14) -> 18500 | X14: PROBLEMAS CON LA ORDEN
A15: 10 | B15: FARMACIA RUTH | D15: VS/FG | Q15: 23625 | W15: =SUM(J15:V15) -> 23625 | X15: PROBLEMAS CON LA ORDEN
A16: 11 | B16: Agua Planeta Azul, SA | D16: VS/FG | Q16: 2700 | W16: =SUM(J16:V16) -> 2700 | X16: PROBLEMAS CON EL COMPROBANTE, EN ESPERA DEL PROVEEDOR PARA EL CAMBIO DE NCF
A17: 12 | B17: Agua Planeta Azul, SA | D17: VS/FG | Q17: 15750 | W17: =SUM(J17:V17) -> 15750 | X17: PROBLEMAS CON EL COMPROBANTE, EN ESPERA DEL PROVEEDOR PARA EL CAMBIO DE NCF
A18: 13 | B18: Agua Planeta Azul, SA | D18: VS/FG | R18: 12660 | W18: =SUM(J18:V18) -> 12660 | X18: PROBLEMAS CON EL COMPROBANTE, EN ESPERA DEL PROVEEDOR PARA EL CAMBIO DE NCF
A19: 14 | B19: FARMACIA RUTH | D19: VS/FG | R19: 16100 | W19: =SUM(J19:V19) -> 16100 | X19: PROBLEMAS CON LA ORDEN
A20: 15 | B20: CEM CARIBBEAN EQUIPMENT MEDICAL | D20: VS/FG | S20: 10792.8 | W20: =SUM(J20:V20) -> 10792.8 | X20: PROBLEMAS CON LA ORDEN
A21: =+A20+1 -> 16 | B21: FARMACIA RUTH | D21: VS/FG | S21: 950 | W21: =SUM(J21:V21) -> 950 | X21: PROBLEMAS CON LA ORDEN
A22: =+A21+1 -> 17 | B22: Gestiones Sanitarias & Ambientales, SRL (GSA) | D22: VS/FG | S22: 16520 | W22: =SUM(J22:V22) -> 16520 | X22: PROBLEMAS CON LA ORDEN
A23: =+A22+1 -> 18 | B23: FARMACIA RUTH | D23: VS/FG | U23: 17150 | W23: =SUM(J23:V23) -> 17150 | X23: PROBLEMAS CON LA ORDEN
A24: =+A23+1 -> 19 | B24: SUPLIMED,SRL | D24: VS/FG | U24: 73546.12 | W24: =SUM(J24:V24) -> 73546.12 | X24: EN ESPERA DE MODIFICACION PRESUPUESTARIA
A25: =+A24+1 -> 20 | B25: FARMACIA RUTH | D25: VS/FG | V25: 39250 | W25: =SUM(J25:V25) -> 39250 | X25: EN ESPERA DE MODIFICACION PRESUPUESTARIA
A26: =+A25+1 -> 21 | B26: Hospifar, SRL | D26: VS/FG | V26: 472000 | W26: =SUM(J26:V26) -> 472000 | X26: EN ESPERA DE MODIFICACION PRESUPUESTARIA
A27: =+A26+1 -> 22 | B27: Adler Amicis Valdez Marmolejos | D27: VS/FG | V27: 30680 | W27: =SUM(J27:V27) -> 30680 | X27: EN ESPERA DE MODIFICACION PRESUPUESTARIA
A28: =+A27+1 -> 23 | B28: Air Liquide Dominicana, SAS | D28: VS/FG | V28: 7861.63 | W28: =SUM(J28:V28) -> 7861.63 | X28: EN ESPERA DE MODIFICACION PRESUPUESTARIA
A29: =+A28+1 -> 24 | B29: Bio Nuclear, SA | D29: VS/FG | V29: 533138 | W29: =SUM(J29:V29) -> 533138 | X29: EN ESPERA DE MODIFICACION PRESUPUESTARIA
A30: =+A29+1 -> 25 | B30: Lambda Diagnósticos, SRL | D30: VS/FG | V30: 556517.39 | W30: =SUM(J30:V30) -> 556517.39 | X30: EN ESPERA DE MODIFICACION PRESUPUESTARIA
A31: =+A30+1 -> 26 | B31: Macrotech Farmacéutica, SRL | D31: VS/FG | V31: 525496.48 | W31: =SUM(J31:V31) -> 525496.48 | X31: EN ESPERA DE MODIFICACION PRESUPUESTARIA
A32: =+A31+1 -> 27 | B32: Bio Nova, SRL | D32: VS/FG | V32: 193848 | W32: =SUM(J32:V32) -> 193848 | X32: EN ESPERA DE MODIFICACION PRESUPUESTARIA
A33: =+A32+1 -> 28 | B33: Bio Nuclear, SA | D33: VS/FG | V33: 21564 | W33: =SUM(J33:V33) -> 21564 | X33: EN ESPERA DE MODIFICACION PRESUPUESTARIA
A34: =+A33+1 -> 29 | B34: Bello-Lab, SRL | D34: VS/FG | V34: 147671.4 | W34: =SUM(J34:V34) -> 147671.4 | X34: EN ESPERA DE MODIFICACION PRESUPUESTARIA
A35: =+A34+1 -> 30 | B35: A&S Importadora Medicas, SRL | D35: VS/FG | V35: 183810 | W35: =SUM(J35:V35) -> 183810 | X35: EN ESPERA DE MODIFICACION PRESUPUESTARIA
A36: =+A35+1 -> 31 | B36: VANGUARDIA SALUD SRL | D36: VS/FG | V36: 112214 | W36: =SUM(J36:V36) -> 112214 | X36: EN ESPERA DE MODIFICACION PRESUPUESTARIA
... A42: =+A41+1 -> 37 | B42: LINAMED SRL | D42: VS/FG | V42: 271400 | W42: =SUM(J42:V42) -> 271400 | X42: EN ESPERA DE MODIFICACION PRESUPUESTARIA
A43: =+A42+1 -> 38 | B43: Agua Planeta Azul, SA | D43: VS/FG | Q43: 3900 | W43: =SUM(J43:V43) -> 3900 | X43: PROBLEMAS CON EL COMPROBANTE, EN ESPERA DEL PROVEEDOR PARA EL CAMBIO DE NCF
A44: =+A43+1 -> 39 | B44: Agua Planeta Azul, SA | D44: VS/FG | Q44: 9060 | W44: =SUM(J44:V44) -> 9060 | X44: PROBLEMAS CON EL COMPROBANTE, EN ESPERA DEL PROVEEDOR PARA EL CAMBIO DE NCF
A45: =+A44+1 -> 40 | B45: Agua Planeta Azul, SA | D45: VS/FG | Q45: 9120 | W45: =SUM(J45:V45) -> 9120 | X45: PROBLEMAS CON EL COMPROBANTE, EN ESPERA DEL PROVEEDOR PARA EL CAMBIO DE NCF
E46: =SUM(E6:E25) -> 0 | F46: =SUM(F6:F25) -> 0 | G46: =SUM(G6:G25) -> 0 | H46: =SUM(H6:H25) -> 0 | I46: =SUM(I6:I25) -> 0 | J46: =SUM(J6:J45) -> 512585.05 | K46: =SUM(K6:K45) -> 178982.4 | L46: =SUM(L6:L45) -> 5691.23 | M46: =SUM(M6:M45) -> 0 | N46: =SUM(N6:N45) -> 9500 | O46: =SUM(O6:O45) -> 13900 | P46: =SUM(P6:P45) -> 18500 | Q46: =SUM(Q6:Q45) -> 64155 | ... W46: =SUM(W6:W45) -> 5000426.5
A47: Total General | W47: =+W46 -> 5000426.5
Q48: B

Sheet INGRESOS POR A.R.S
A2: Servicio Nacional De Salud
A3: Dirección de Fiscalizacion
A4: Ingresos Por Facturación ARS
A6: Establecimiento: | B6: HOSPITAL MATERNO INFANTIL SAN LORENZO DE LOS MINA
A8: ARS | C8: ENERO | E8: FEBRERO | G8: MARZO | I8: ABRIL | K8: MAYO | M8: JUNIO | O8: JULIO | Q8: AGOSTO | S8: SEPTIEMBRE | U8: OCTUBRE | W8: NOVIEMBRE | Y8: DICIEMBRE
C9: Facturado | D9: Recibido | E9: Facturado | F9: Recibido | G9: Facturado | H9: Recibido | I9: Facturado | J9: Recibido | K9: Facturado | L9: Recibido | M9: Facturado | N9: Recibido | O9: Facturado | P9: Recibido | Q9: Facturado | R9: Recibido | S9: Facturado | T9: Recibido | U9: Facturado | V9: Recibido | W9: Facturado | X9: Recibido | Y9: Facturado | Z9: Recibido
A10: 1 | B10: SENASA SUBSIDIADO | C10: 4027257.3 | D10: 4833111.5 | E10: 4840265.3 | F10: 5841673.2 | G10: 3159909.7 | H10: 4645181.4 | I10: 1946482.7 | J10: 3053880 | K10: 3199661.2 | L10: 3249661.2 | M10: 5356651.5 | O10: 4812753.5 | P10: 5346295.1 | Q10: 7413343.7 | R10: 4903253.5 | S10: 5095748.9 | T10: 7386343.7 | U10: 3962152.9 | V10: 2015276.3 | W10: 7112050.8 | X10: =3879690.42+50000+50000+6000+500 -> 3986190.4
A11: 2 | B11: SENASA CONTRIBUTIVO | C11: 1094583.8 | E11: 2417181.1 | F11: 2152926.5 | G11: 2645113.9 | H11: 1041144.3 | I11: 3267715.2 | J11: 2326715 | K11: 2490193.7 | L11: 2588374.1 | M11: 1240459.9 | N11: 2927464.4 | O11: 2661675 | P11: 2432528 | Q11: 2570895.8 | R11: 1219321.4 | S11: 2390951.2 | T11: =2528895.81+50000 -> 2578895.8 | U11: 2495962.6 | V11: 2521542.4 | W11: 1571156.8 | X11: 2110440.8
A12: 3 | B12: SENASA JUB. Y PENS. | C12: 0 | D12: 0 | E12: 10985.64 | G12: 0 | K12: 2134.86 | L12: 13000 | M12: 30812.76 | O12: 21145.63 | Q12: 30463.1 | R12: 30468.55 | S12: 18188.8 | U12: 13049.24 | W12: 16090.03 | X12: 18188.8
A13: 4 | B13: SENASA LARIMAR | M13: 2580 | R13: 2580
A14: Total SeNaSa | C14: 5121841.1 | D14: 4833111.5 | E14: 7268432.1 | F14: 7994599.7 | G14: 5805023.6 | H14: 5686325.7 | I14: 5214198 | J14: 5380594.9 | K14: 5691989.8 | L14: 5851035.3 | M14: 6630504.1 | N14: 2927464.4 | O14: 7495574.1 | P14: 7778823.1 | Q14: 10014703 | R14: 6153043.4 | S14: =SUM(S10:S13) -> 7504888.9 | T14: =SUM(T10:T13) -> 9965239.6 | U14: =SUM(U10:U13) -> 6471164.7 | V14: =SUM(V10:V13) -> 4536818.7 | W14: =SUM(W10:W13) -> 8699297.6 | X14: =SUM(X10:X13) -> 6114820 | Y14: =SUM(Y10:Y13) -> 0 | Z14: =SUM(Z10:Z13) -> 0
A15: 5 | B15: PALIC SALUD | C15: 211714.57 | D15: 206908.45 | E15: 389860 | G15: 189915.48 | H15: 606511.88 | I15: 448858.04 | J15: 187591.6 | K15: 173257.12 | L15: 442756.63 | M15: 274846.74 | O15: 265950.63 | P15: 441505.67 | Q15: 142766.48 | R15: 130717.94 | S15: =80190.4+6545.23+196009.12 -> 282744.75 | T15: =87151.82+48471.2+133968.58+5754 -> 275345.6 | U15: =67416+3960.5+295194.04 -> 366570.54 | W15: =87744.4+14022.84+407190.87 -> 508958.11 | X15: =6044.93+67416+3248.15+80190.4+156815.27+293688.85+38223.05 -> 645626.65
A16: 6 | B16: ARL
A17: 7 | B17: RENACER | C17: 275352.44 | D17: 156983.55 | E17: 222716.34 | F17: 272552.44 | G17: 73918.68 | H17: 222620.34 | J17: 73057.08 | M17: 443337.56 | P17: 417359.58 | Q17: 378719.69 | S17: 356377.87 | T17: 372910.21 | W17: 628535.91
A18: 8 | B18: YUNEN | C18: 7848.94 | D18: 55135.74 | E18: 14338.35 | F18: 7848.94 | G18: 162551.53 | H18: 14338.35 | I18: 37897.65 | J18: 19489.76 | K18: 45390.42 | L18: 155606.87 | M18: 166835.63 | N18: 79214.03 | O18: 19360.44 | P18: 86993.18 | Q18: 13119.97 | R18: 77589.09 | S18: 66096.6 | T18: 19188.28 | U18: 19865.35 | W18: 50524.35
A19: 9 | B19: UNIVERSAL
A20: 10 | B20: ARS HUMANO | C20: 44770.98 | E20: 16720.82 | F20: 97648.3 | G20: 83376.61 | H20: 34117.68 | I20: 77617.28 | J20: 97704.2 | K20: 29761.8 | M20: 50732.77 | N20: 102719.16 | O20: 38168.82 | P20: 48385.69 | Q20: 45135.37 | R20: 38168.82 | S20: 37253.63 | U20: 87793.49 | V20: 31403.87 | W20: 60465.44
A21: 11 | B21: ARS PLANSALUD BANCO CENTRAL
A22: 12 | B22: SEMMA | C22: 7193.05 | D22: 15993.02 | E22: 28868.13 | F22: 9531.6 | G22: 10657.5 | H22: 77169.4 | I22: 27941.11 | J22: 35261.18 | K22: 99169.27 | M22: 36644.9 | N22: 8860.1 | O22: 19740.54 | Q22: 13301.87 | R22: 26210.35 | S22: 72979.17 | T22: 36338.96 | U22: 21293.38 | V22: 18494.98 | W22: 57553.05
A23: 13 | B23: FUTURO | C23: 269639.73 | D23: 234503.89 | E23: 617068.65 | G23: 366095.18 | H23: 356314.76 | I23: 395799.78 | J23: 388735.9 | K23: 525599.56 | L23: 493974.92 | M23: 236054.2 | N23: 213364.69 | O23: 651828.66 | P23: 649331.98 | Q23: 389838.41 | S23: 1040980.3 | T23: 1062055.6 | U23: 1209329.2 | V23: 1183974.5 | W23: 807581.85 | X23: 802889.48
A24: 14 | B24: APS | C24: 69588.33 | E24: 122630.62 | F24: 8262.07 | G24: 43770.8 | H24: 212345.21 | I24: 55860.67 | K24: 109234.31 | M24: 229878 | O24: 216887.67 | Q24: 178852.56 | S24: 246860.42 | T24: 201903.47 | U24: 148382.76 | V24: =642600.65+329212.9 -> 971813.55 | W24: 329823.23
A25: 15 | B25: SALUD SEGURA
A26: 16 | B26: CONSTITUCION
A27: 17 | B27: META SALUD | C27: 1396 | E27: 20821.36 | F27: 31949.94 | G27: 80842.17 | H27: 1396 | I27: 32922.74 | K27: 3500 | L27: 32863.84 | M27: 41032.92 | O27: 11961.97 | Q27: 12148 | R27: 12030.35 | S27: 22455.91 | U27: 37260.88 | V27: 7000 | W27: 5000 | X27: 37260.48
A28: 18 | B28: ASEMAP | C28: 4869.52 | D28: 6475.14 | E28: 102975.46 | F28: 4869.52 | G28: 6619.63 | H28: 102672.34 | I28: 12257.4 | J28: 6619.63 | K28: 111906.17 | L28: 12182.4 | M28: 7768.47 | O28: 11676.13 | P28: 118687.31 | Q28: 28902.56 | R28: 7768.46 | S28: 7856.59 | T28: 28902.56 | U28: 22304.52 | V28: =7586.59+9610.03 -> 17196.62 | W28: 84258.25
A29: 19 | B29: GMA | C29: 76159.34 | E29: 186957.88 | G29: 136798.59 | I29: 83229.31 | K29: 9976.34 | M29: 108970.25 | O29: 49885.59 | P29: 444038.71 | Q29: 26648.23 | S29: 12927.61 | U29: 71868.65 | W29: 125975.2 | X29: 22069.48
A30: 20 | B30: MONUMENTAL | C30: 75131.09 | D30: 71992.2 | E30: 146560.32 | G30: 85258.31 | H30: 237322.18 | I30: 119188.62 | J30: 146560.32 | K30: 58287.88 | L30: 84594.85 | M30: 97214.78 | O30: 108900.79 | P30: 125937.38 | Q30: 40745.74 | S30: 105146.53 | U30: 55818.18 | V30: 40245.74 | W30: 106828.8
A31: 21 | B31: CMD | C31: 273646.7 | D31: 273646.7 | E31: 41285.9 | F31: 41071.9 | G31: 22435.77 | H31: 11220.43 | I31: 61608.05 | J31: 22435.77 | K31: 31245 | L31: 61607.99 | M31: 237194.17 | N31: 31240 | O31: 63128.33 | P31: 300322.5 | Q31: 88200.19 | S31: 282288.73 | T31: 88060.19 | U31: 61039.21 | V31: 281564.03 | W31: 148817.44 | X31: 61001.21
A32: 22 | B32: RESERVAS | C32: 48081.02 | D32: 48081.02 | E32: 217047.26 | G32: 79962.77 | I32: 61346.15 | K32: 57351.74 | L32: 79987.57 | M32: 10000 | O32: 18399.99 | P32: 36534.85 | Q32: 38168.7 | R32: 38168.7 | S32: 165161.13 | U32: 8284.72 | V32: 8284.72 | W32: 71332.28
A33: 23 | B33: SIMAG | C33: 28637.51 | E33: 92478.63 | G33: 2821.24 | I33: 1604 | K33: 3360 | M33: 3319.22 | O33: 4368.41 | P33: 181158.69 | Q33: 54351.55 | S33: 2500 | T33: 11667.45 | U33: 2544.72 | W33: 6279.36
A34: 24 | B34: SEMUNASED
A35: 25 | B35: SERVICIOS MEDICOS UASD
A36: 26 | B36: PRIMERA ARS HUMANO | C36: 259154.57 | E36: 439967.13 | F36: 870590.25 | G36: 404678.83 | H36: 262926.38 | I36: 432554.37 | J36: 534014.43 | K36: 317521.34 | L36: 304098.74 | M36: 374483.12 | N36: 268649.03 | O36: 442825.83 | P36: 313059.93 | Q36: 399800.36 | R36: 401045.51 | S36: 634790.11 | U36: 317086.49 | V36: 357164.54 | W36: 444335.13
B37: EXTRANJEROS | K37: 80323.32 | M37: 436800 | N37: 423700 | U37: 311200 | W37: 218750 | X37: 185750
A38: Total ARS PRIVADAS | C38: 1653183.8 | D38: 1069719.7 | E38: 2660296.9 | F38: 1344325 | G38: 1749703.1 | H38: 2138955 | I38: 1848685.2 | J38: 1511469.9 | K38: 1655884.3 | L38: 1667673.8 | M38: 2755112.7 | N38: 1127747 | O38: 1923083.8 | P38: 3163315.5 | Q38: 1850699.7 | R38: 731699.22 | S38: =SUM(S15:S36) -> 3336419.4 | T38: =SUM(T15:T36) -> 2096372.3 | U38: =SUM(U15:U37) -> 2740642.1 | V38: =SUM(V15:V36) -> 2917142.5 | W38: =SUM(W15:W37) -> 3655018.4 | X38: =SUM(X15:X37) -> 1754597.3 | Y38: =SUM(Y15:Y36) -> 0 | Z38: =SUM(Z15:Z36) -> 0
A39: TOTAL | C39: 6775024.9 | D39: 5902831.2 | E39: 9928728.9 | F39: 9338924.6 | G39: 7554726.7 | H39: 7825280.6 | I39: 7062883.1 | J39: 6892064.8 | K39: 7347874.1 | L39: 7518709.1 | M39: 9385616.8 | N39: 4055211.4 | O39: 9418657.9 | P39: 10942139 | Q39: 11865402 | R39: 6884742.7 | S39: =+S38+S14 -> 10841308 | T39: =+T38+T14 -> 12061612 | U39: =+U38+U14 -> 9211806.8 | V39: =+V38+V14 -> 7453961.3 | W39: =+W38+W14 -> 12354316 | X39: =+X38+X14 -> 7869417.3 | Y39: =+Y38+Y14 -> 0 | Z39: =+Z38+Z14 -> 0

Sheet GLOSA
A1: Servicio Nacional de Salud
A2: Dirección de Fiscalización
A3: Glosa /mes
A4: Establecimientos | B4: Facturado | C4: Recibido | D4: Glosado | E4: %
A5: Enero | B5: 6775024.9 | C5: 5902831.2 | D5: 102835 | E5: =+D5/B5 -> 0.015178542
A6: Febrero | B6: 9928728.9 | C6: 9338924.6 | D6: 221056.08 | E6: =+D6/B6 -> 0.022264288
A7: Marzo | B7: 7643032.2 | C7: 7825280.7 | D7: 99442.51 | E7: =+D7/B7 -> 0.013010871
A8: Abril | B8: 6994829.1 | C8: 6892064.8 | D8: 68054 | E8: =+D8/B8 -> 0.0097291869
A9: Mayo | B9: 7347874.1 | C9: 7518709.1 | D9: 116253.22 | E9: =+D9/B9 -> 0.015821341
A10: Junio | B10: 9385616.4 | C10: 4055211.4 | D10: 67756.32 | E10: =+D10/B10 -> 0.0072191657
A11: Julio | B11: 9418657.9 | C11: 10942139 | D11: 116253.22 | E11: =+D11/B11 -> 0.012342865
A12: Agosto | B12: 11865402 | C12: 6884742.7 | D12: 36950 | E12: =+D12/B12 -> 0.0031140958
A13: Septiembre | B13: 11178188 | C13: 12061612 | D13: 88793.31 | E13: =+D13/B13 -> 0.0079434438
A14: Octubre | B14: 9211806.8 | C14: 7453961.2 | D14: 102915.12 | E14: =+D14/B14 -> 0.011172088
A15: Noviembre | B15: 12354316 | C15: 7869417.3 | D15: 145495.75 | E15: =+D15/B15 -> 0.011776917 | H15: .
A16: Diciembre
A17: Total | B17: =SUM(B5:B16) -> 1.0210348e+08 | C17: =SUM(C5:C16) -> 86744894 | D17: =SUM(D5:D16) -> 1165804.5 | E17: =+D17/B17 -> 0.011417873
A19: Preparado por:
A20: Licda.
