Workbook

Sheet RELACION DE PAGOS EMITIDOS
A5: DIRECCION DE FISCALIZACION Y CONTROL
A6: RELACION DE PAGOS EMITIDOS DURANTE EL MES
A7: ESTABLECIMIENTO:HOSPITAL MATERNO INFANTIL SAN LORENZO DE LOS MINA
A9: PAGOS CORRESPONDIENTES AL MES : ABRIL 2025
A10: FECHA | B10: LIBRAMIENTO | C10: TRANSFERENCIA | D10: CHEQUE | E10: BENEFICIARIO | F10: NO.FACTURAS | G10: VALOR DE FACTURA | H10: VALOR PAGADO
A11: 45778 | C11: 130 | E11: TONER DEPOT MULTISERVICIOS EORG, SRL | F11: PAGO NCF B1500008503 SERVCIO DE IMPRESIÓN EN EL MES DE ABRIL 2025 SEGÚN O/C HSLM-2025-00147. | G11: 247030.86 | H11: 236563.45
A12: 45778 | C12: =+C11+1 -> 131 | E12: P&D RECYCLING, SRL | F12: PAGO DE FACT NCF NO. B1500000308, POR SERVICIO DE RECOGIDA DE DESECHOS SOLIDOS, SEGÚN ORDEN DE COMPRA HSLM-2025-00344 | G12: 760000 | H12: 722000
A13: 45779 | C13: =+C12+1 -> 132 | E13: ALTICE DOMINICANA, SA | F13: PAGO DE FACT NCF NO. E4500000014550 | G13: 104532.2 | H13: 104532.2
A14: 45779 | C14: =+C13+1 -> 133 | E14: COLEGIO DOMINICANO DE PROFESIONALES DE ENFERMERIA | F14: APORTE ECONOMICO PARA PERSONAL DE ENFERMERIA PARA EL XVIII CONGRESO NACIONAL Y X INTERNACIONAL DE ENFERMERIA QUE SERA CELEBRADO DEL 08 AL 11 DE MARZO 2025 | G14: 200000 | H14: 200000
A15: 45779 | C15: =+C14+1 -> 134 | E15: ALTICE DOMINICANA, SA | F15: PAGO DE FACT E4500000014347, POR SERVICIO DE COMUNICACIÓN PERIODO FACTURADO 23/03/2025 AL 22/04/2025, CUENTA 2666630 | G15: 104427.01 | H15: 104427.01
C16: =+C15+1 -> 135 | E16: UTILIZADA EN ABRIL 2025 | F16: UTILIZADA EN ABRIL 2025 | G16: 0 | H16: 0
C17: =+C16+1 -> 136 | E17: UTILIZADA EN ABRIL 2026 | F17: UTILIZADA EN ABRIL 2026 | G17: 0 | H17: 0
C18: =+C17+1 -> 137 | E18: FARMACO QUIMICA NACIONAL S.A | G18: 26821.4 | H18: 25684
C19: =+C18+1 -> 138 | E19: FARMACO QUIMICA NACIONAL S.A | G19: 26821.4 | H19: 25684
A20: 45784 | C20: =+C19+1 -> 139 | E20: DELIA JOSEFINA TATIS PERDOMO | F20: PAGO DE FACT NCF NO. B1500000524, POR ALQUILER DE CARPA 6*6 EJECUTIVA POR 15 DIAS CALENDARIO, PARA SER UTILIZADA EN EL AREA DE PARQUEO, SEGÚN ORDEN DE COMPRA HSLM-2024-00706 | G20: 53100 | H20: 50850
C21: =+C20+1 -> 140 | E21: WEPA TOURS, SRL | F21: COLABORACION PARA LA JORNADA EDUCATIVA DEDICADA AL DIA DE LAS ENFERMERAS, A REALIZARSE DESDE EL 14 AL 16 DE MAYO 2025 | G21: 70800 | H21: 70800
A22: 45784 | C22: =+C21+1 -> 141 | E22: LILIAN YOMAYRA ENCARNACION DE MATOS | F22: PAGO DE REGENCIA EN PERMISO DE DROGAS Y FARMACIA, PERTENECIENTE AL MES DE ABRIL 2025 | G22: 10000 | H22: 10000
C23: =+C22+1 -> 142 | E23: TURINTER | G23: 50958 | H23: 50958
A24: 45789 | C24: =+C23+1 -> 143 | E24: HOSPITRONICA, SRL | F24: PAGO DE FACT NCF B1500000145, POR ADQUISICION DE CARRO DE TRANSPORTE PARA AUTOCLAVE DE VAPOR, SEGÚN ORDEN DE COMPRA HSLM-2025-00308 | G24: 621205.1 | H24: 594882.85
C25: =+C24+1 -> 144 | E25: INVERSIONES FH SRL | F25: PAGO NCF B15000001495 ADQUISICION DE TICKETS DE COMBUSTIBLE SEGÚN O/C HSLM-2025-00423 | G25: 172000 | H25: 170573.26
A26: 45790 | C26: =+C25+1 -> 145 | E26: CEM CARIBBEAN EQUIPMENT MEDICAL, SRL | F26: PAGO DE FACT NCF NO. B1500001345, POR ADQUISICION DE KIT DE CONTROL DE GASES ARTERIALES, SEGÚN ORDEN DE COMPRA HSLM-2025-00167 | G26: 846850 | H26: 804507.5
A27: 45790 | C27: =+C26+1 -> 146 | E27: ADLER AMICIS VALDEZ MARMOLEJOS | F27: PAGO DE FACT NCF NO. B1500000029, ADQUISICION DE MATERIALES IMPRESOS, SEGÚN ORDEN DE COMPRA HSLM-2025-00320 | G27: 108265 | H27: 103677.5
A28: 45790 | C28: =+C27+1 -> 147 | E28: TROPIGAS DOMINICANA, SRL | F28: PAGO DE FACT E450000005419, POR ADQUISICION DE GAS LICUADO DE PETROLEO, SEGÚN ORDEN DE COMPRA HSLM-2025-00066 | G28: 23868 | H28: 23868
A29: 45790 | C29: =+C28+1 -> 148 | E29: JESUS FERMIN MARTINEZ LOPEZ | F29: PAGO DE FACT NCF NO. B1500000432, POR SERVICIO DE TRANSPORTE SEGÚN ORDEN DE COMPRA HSLM-2025-000068 | G29: 32000 | H29: 30400
A30: 45790 | C30: =+C29+1 -> 149 | E30: LEHAIM SUMINISTROS | F30: PAGO DE FACT NCF NO. B1500000014, POR ADQUISICION DE SERVILLETA, SEGÚN ORDEN DE COMPRA HSLM-2025-00143 | G30: 227500 | H30: 216125
A31: 45790 | C31: =+C30+1 -> 150 | E31: LEHAIM SUMINISTROS | F31: PAGO DE FACT NO. B1500000013, POR ADQUISICION DE PAPEL HIGIENICO | G31: 271400 | H31: 259900
A32: 45790 | C32: =+C31+1 -> 151 | E32: CEM CARIBBEAN EQUIPMENT MEDICAL, SRL | F32: PAGO DE FACT NCF NO. B1500001356, POR ADQUISICION DE VENTILADOR PEDIATRICO NEONATAL, SEGÚN ORDEN DE COMPRA HSLM-2025-0271 | G32: 1590510.2 | H32: 1523115.7
A33: 45791 | C33: =+C32+1 -> 152 | E33: GESTIONES SANITARIAS & AMBIENTALES, SRL | F33: PAGO DE FACT NCF NO B1500000447, POR SERVICIO DDE ANALISIS MICROBIOLOGICO, DE AGUA POTABLE, HSLM-CD-2024-0007 | G33: 39530 | H33: 37855
A34: 45791 | C34: =+C33+1 -> 153 | E34: PRODUCTOS CANO | F34: PAGO DE FACT NCF NO, B1500001319 POR ADQUISICION DE PAN MES DE ABRIL 2025 | G34: 91875 | H34: 87281.25
A35: 45791 | C35: =+C34+1 -> 154 | E35: CABOD, EIRL | F35: PAGO DE FACT NCF NO B1500001758, POR ADQUISICION DE MATERIALES DE LIMPIEZA SEGÚN ORDEN DE COMPRA HSLM-2025-00318 | G35: 98506.4 | H35: 94332.4
A36: 45791 | C36: =+C35+1 -> 155 | E36: JF2H SUPLIDORES DIVERSOS | F36: PAGO NCF B150000104 ADQUISICION DE TELA PARA FABRICAR COLCHAS, SEGÚN ORDEN DE COMPRA HSLM-2025-00412 | G36: 141128 | H36: 135148
C37: =+C36+1 -> 156 | E37: SANDRY GOMEZ RODRIGUEZ | F37: PAGO DE FACT NCF NO. B1500000560, POR ADQUISICION DE ALIMENTOS, SEGÚN ORDEN DE COMPRA HSLM-2025-00310 | G37: 263200 | H37: 250040
C38: =+C37+1 -> 157 | E38: SINDICATO NACIONAL DE TRABAJADORES DE ENFERMERIA | F38: SALDO COLABORACION PARA ACTIVIDAD DEL DIA DEL ENFERMERO | G38: 70000 | H38: 70000
C39: =+C38+1 -> 158 | E39: DESTREZA COMERCIAL SRL | F39: PAGO NCF B1500000060 ADQUISCION DE MEDICAMENTOS SEGÚN O/C HSLM-2025-00414. | G39: 42000 | H39: 39900
C40: =+C39+1 -> 159 | E40: IV BIODESINFECCION SRL | F40: PAGO NCF B1500000285 SERVICIO DE DESINFECCION AREA DE QUIROFANO DE INFECTOLOGIA, UCI DE ADULTOS 3ERA PLANTA Y AREA DE HOSPITALIZACION SEGÚN O/C HSLM-2025-00407. | G40: 37996 | H40: 36386
C41: =+C40+1 -> 160 | E41: IV BIODESINFECCION SRL | F41: PAGO NCF B1500000286 SERVICIO DE DESINFECCION AREA DE UCIN 1 SEGÚN O/C HSLM-2025-00418 | G41: 9912 | H41: 9492
C42: =+C41+1 -> 161 | E42: ANTARES PHARMA SRL | F42: PAGO NCF B1500000001 UTILES MEDICOS E INSPIROMETRO SEGÚN O/C HSLM-2025-00379. | G42: 65468.29 | H42: 62694.21
C43: =+C42+1 -> 162 | E43: FARMACIA RUTH SRL | F43: PAGO NCF B1500000278 ADQUISICION DE MEDICAMENTOS SEGÚN O/C 1896 | G43: 88100 | H43: 83695
C44: =+C43+1 -> 163 | E44: NULO | F44: NULO | G44: 0 | H44: 0
C45: =+C44+1 -> 164 | E45: NULO | F45: NULO | G45: 0 | H45: 0
C46: =+C45+1 -> 165 | E46: ALTICE DOMINICANA S.A | F46: PAGO NCF E450000015174 SERVICIO TELEFONICO PERIODO FACTURADO 23/04/2025 AL 22/05/2025 CUENTA 2666630 | G46: 104504.21 | H46: 104504.21
C47: =+C46+1 -> 166 | E47: LABORATORIO CLINICO LICDA PATRIA M RIVAS SRL | F47: PAGO NCF E450000000023 SERVICIO DE ESTUDIOS ESPECIALIZADOS SEGÚN O/C HSLM-2025-00312 | G47: 17033 | H47: 17033
C48: =+C47+1 -> 167 | E48: AYUNTAMIENTO SANTO DOMINGO ESTE | F48: PAGO NCF B1500055810 SERVICIO DE RECOGIDA DE DESECHOS SOLIDOS EN EL MES DE MAYO 2025. | G48: 25000 | H48: 25000
... C54: =+C53+1 -> 173 | E54: COLEGIO MEDICO DOMINICANO | F54: COLABORACION PARA EL REFRIGERIO DE LA NOCHE INAUGURAL DE LA VIII JORNADA CIENTIFICA, EVIDENCIA E INNOVACION PARA LA SALUD MATERNA INFANTIL, QUE SE REALIZARA EN EL COLEGIO MEDICO DOMINICANO, EL MIERCOLES 28/05/2025, SEGÚN DOCUMENTACION ANEXA | G54: 50000 | H54: 50000
B55: 1778 | E55: Ciencia Tecnología y Consultas, SRL | F55: PAGO DE FACT NCF B1500007637 POR ADQUISICION DE REACTIVOS MAGLUMI E INSUMOS DE LABORATORIO SEGUN O/C HSLM-2025-00275. | G55: 675748.48
B56: 1781 | E56: Eligium, EIRL | F56: Pago de Fact NO B1500000003, por mantenimiento del area de comedor del 2do piso, segun orden de compra HSLM-2024-00282 | G56: 1649337.3
B57: 1785 | E57: Ciencia Tecnología y Consultas, SRL | F57: PAGO DE FACT NCF B1500007671 POR ADQUISICION DE REACTIVOS MAGLUMI E INSUMOS DE LABORATORIO SEGUN O/C HSLM-2025-00381. | G57: 817323.12
B58: 1790 | E58: CABOD, EIRL | F58: PAGO FACTURA NCF B1500001749 POR ADQUISICION DE MATERIALES DE LIMPIEZA SEGUN O/C HSLM-2025-00318 | G58: 247068.4
B59: 1801 | E59: Khris Aus Pharmacy, S.R.L | F59: PAGO FACTURA NCF B1500000151 POR AQUISICION DE UTIL MEDICO SEGUN O/C HSLM-2025-00383. | G59: 270102
B60: 1805 | E60: SSP Servisalud Premium, SRL | F60: PAGO FACTURA E450000000040 POR ADQUISICION DE PINZAS QUIRURGICAS SEGUN O/C HSLM-2024-01209. | G60: 939471.75
B61: 1809 | E61: Ropharma, SRL | F61: PAGO FACTURA NCF B1500001308 POR ADQUISICION DE MEDICAMENTOS SEGUN O/C HSLM-2025-00382. | G61: 210000
B62: 1813 | E62: Khris Aus Pharmacy, S.R.L | F62: PAGO FACTURA NCF B1500000152 POR ADQUISICION DE UTIL MEDICO SEGUN O/C HSLM-2025-00384. | G62: 270102
B63: 1820 | E63: Xavier Vargas, Ingeniería Electromecánica, EIRL | F63: PAGO FACTURA NCF B1500000243 POR ADQUISICION DE SUMINISTRO E INSTALACION DE AIRES ACONDICIONADOS SEGUN O/C HSLM-2025-00377. | G63: 91569.9
B64: 1835 | E64: Farmaco Internacional, SRL | F64: PAGO FACTURA NCF B1500001036 POR ADQUISICION DE UTILES MEDICOS SEGUN O/C HSLM-2025-00239. | G64: 1937560
B65: 1839 | E65: Farmaco Internacional, SRL | F65: PAGO FACTURA NCF E45000000004 POR ADQUISICION DE UTILES MEDICOS SEGUN O/C HSLM-2025-00345. | G65: 276519
B66: 1841 | E66: HOSPITAL MATERNO INFANTIL SAN LORENZO DE LOS MINAS | F66: HOSANLORE.NOMINA PAGO BONO POR DESEMPEÑO CORRESPONDIENTE AL AÑO 2024 | G66: 443970.11
... B106: 2024 | E106: HOSPITAL MATERNO INFANTIL SAN LORENZO DE LOS MINAS | F106: HOSANLORE.NOMINA SUELDO FIJO MAYO 2025 | G106: 64837161
B107: 2028 | E107: Macrotech Farmacéutica, SRL | F107: PAGO DE FACT NCF E450000000834 POR ADQUISICION DE UTILES MEDICOS SEGUN O/C HSLM-2025-00387. | G107: 216441.5
B108: 2030 | E108: Abrias Novo Group SRL | F108: PAGO DE FACT NCF B1500000123 POR SERVICIO DE ROTACION FULL COLOR Y ADQUISICION DE KIT DE INTERCOM SEGUN O/C HSLM-2025-00328. | G108: 71293.48
B109: 2034 | E109: Abrias Novo Group SRL | F109: PAGO DE FACT NCF B1500000119 POR ADQUISICION DE ETIQUETAS DE LABEL SEGUN O/C HSLM-2025-00317. | G109: 7590.76
B110: 2038 | E110: Abrias Novo Group SRL | F110: PAGO DE FACT NCF B1500000119 POR ADQUISICION DE SILLON RECLINABLE, SELLADORA E IMPRESORA DE ETIQUETAS ZEBRA SEGUN O/C HSLM-2025-00317. | G110: 192260.63
B111: 2042 | E111: MIGUELINA VASQUEZ CASTILLO | F111: PAGO DE FACT NCF B1500000508 POR ADQUISICION DE INSUMOS FERRETEROS SEGUN O/C HSLM-2025-00243. | G111: 164190.82
B112: 2046 | E112: MIGUELINA VASQUEZ CASTILLO | F112: PAGO DE FACT NCF B1500000508 POR ADQUISICION DE EXTRACTOR DE AIRE, PULIDORA, ESCALERA, TALADRO Y ABANICO SEGUN O/C HSLM-2025-00243. | G112: 65254.99
B113: 2052 | E113: Xavier Vargas, Ingeniería Electromecánica, EIRL | F113: PAGO DE FACT NCF B1500000247 POR ADQUISICION DE AIRE ACONDICIONADO GREEN INVERTER 24K SEGUN O/C HSLM-2025-00444. | G113: 70279.62
B114: 2056 | E114: CORPORACION DEL ACUEDUCTO Y ALCANTARILLADO DE SANTO DOMINGO | F114: PAGO DE FACT E450000006913 POR SERVICIO DE AGUA CORRESPONDIENTE AL MES DE MAYO 2025. | G114: 60535
B115: 2063 | E115: BIO NOVA, SRL | F115: PAGO DE FACT NCF B1500016743 POR ADQUISICION DE LISADOR Y DILUENTES SEGUN O/C HSLM-2025-00374. | G115: 90528
B116: 2067 | E116: Dumas Pharmaceuticals, S.R.L. | F116: PAGO DE FACT NCF B1500001130 POR ADQUISICION DE JABON LIQUIDO ANTISEPTICO Y MEROPENEM 1G SEGUN O/C HSLM-2025-00425. | G116: 77000
B117: 2071 | E117: Xavier Vargas, Ingeniería Electromecánica, EIRL | F117: PAGO DE FACT NCF B1500000244 POR ADQUISICION DE CHILLER MODULAR SAMSUNG 15 TON SEGUN O/C HSLM-2025-00409. | G117: 1575867.5
B118: 2075 | E118: Xavier Vargas, Ingeniería Electromecánica, EIRL | F118: PAGO DE FACT NCF B1500000246 POR ADQUISICION DE CHILLER MODULAR SAMSUNG DE15 TON, SEGUN O/C HSLM-2025-00396. | G118: 1652000
... B139: 2179 | E139: Farmaco Internacional, SRL | F139: PAGO DE FACT NCF E450000000012 POR ADQUISICION DE UTILES MEDICOS Y MEDICAMENTOS SEGUN O/C HSLM-2025-00449. | G139: 214259.64
A140: 45778 | D140: 37223 | E140: WELINTHON PEREZ RAMIREZ | F140: PAGO ESTUDIOS A PACIENTE INTERNO DARIANNY PEREZ | G140: 10650 | H140: 10650
A141: 45779 | D141: 37224 | E141: RAMON DE LEON REYES | F141: PAGO POR SERVICIO DE REPARACION DE PUERTA ENROLLABLE DE PARILLA DE DESAGUE DEL HOSPITAL | G141: 54184.86 | H141: 45000
A142: 45779 | D142: 37225 | E142: FRANKELY MOREL FROMETA | F142: PAGO POR SERVICIO DE TRANSPORTE DE LA AMBULANCIA | G142: 15000 | H142: 15000
A143: 45779 | D143: 37226 | E143: FREDDY OSCAR RODRIGUEZ RIVAS | F143: COLABORACION PARA CAVAR HOYO Y CERTIFICACION DE ACTAS DE DEFUNCION | G143: 3400 | H143: 3400
A144: 45789 | D144: 37227 | E144: RAMON EUCLIDES ALVAREZ VILLILO | F144: COLABORACION PARA EL ALQUILER DE CRANEOTOMO CON DOS PUNTAS, PARA EL PACIENTE ROSENDI LUIS POR TRAUMATISMO CRANEONCEFALICO SEVERO | G144: 25000 | H144: 25000
D145: =+D144+1 -> 37228 | E145: RAMON DE LEON REYES | F145: PAGO NCF B1100000037 FABRICACION DE MESA PARA SOPORTE DE EQUIPO DE PATOLOGIA. | G145: 12040.81 | H145: 10000
D146: =+D145+1 -> 37229 | E146: DELMIRA GARCIA | F146: REPOSCION DE CAJA CHICA SEGÚN RECIBOS 40342 AL 40401. | G146: 50620 | H146: 50620
D147: =+D146+1 -> 37230 | E147: NELSON YNFANTE VELAZQUEZ | F147: PAGO POR EL SERVICIO DE PINTADO DE LAS DIFERENTES AREAS DEL HOSPITAL. | G147: 18061.22 | H147: 15000
D148: =+D147+1 -> 37231 | E148: RUDDY SEGURA | F148: PAGO POR EL SERVICIO DE LIMPIEZA Y CLORIFICACION DE LAS CISTERNAS DE ESTE HOSPITAL | G148: 21673.47 | H148: 18000
D149: =+D148+1 -> 37232 | E149: ALEXANDER MENDEZ CONTRERAS | F149: PAGO POR EL SERVICIO DE JARDINERIA Y MANTENIMIENTO DE AREAS VERDES DE ESTE HOSPITAL | G149: 18061.22 | H149: 15000
D150: =+D149+1 -> 37233 | E150: OLEGARIO GUERRERO | F150: PAGO DE FACT NCF B1100000042 POR SERVICIO DE PINTURAS DE COLUMNAS Y PAREDES EXTERIOR DE ESTE HOSPITAL. | G150: 9632.66 | H150: 8000
D151: =+D150+1 -> 37234 | E151: OVIDIO DE JESUS DURAN CLEMENTE | F151: PAGO POR SERVICIO DE TRANSPORTE DE LA AMBULANCIA CORRESPONDIENTE AL MES DE MAYO 2025 | G151: 20000 | H151: 20000
D152: =+D151+1 -> 37235 | E152: MICHEL ALEXANDER MELO | F152: PAGO POR SERVICIO DE CAMBIO E INSTALACION DE PLAFONES DE DIFERENTES AREAS DE ESTE HOSPITAL, SEGÚN ORDEN DE COMPRA 0023 | G152: 72244.9 | H152: 60000
A154: Total | G154: =SUM(G11:G152) -> 1.0050988e+08 | H154: =SUM(H11:H152) -> 8712553.8
A158: RESUMEN
A159: PAGO PROVEEDORES | C159: 33295114
A160: CAJA CHICA | C160: 50620
A161: NOMINA | C161: =+G99+G100+G106+G66 -> 66630551
A162: OTROS | C162: =+G144+G143+G142+G141+G140+G14+G145+G147+G148+G149+G150+G151+G152 -> 479949.14
A163: TOTAL GENERAL | C163: =SUM(C159:C162) -> 1.0045623e+08

Sheet RELACION ORDENES DE COMPRAS
A4: SERVICIO NACIONAL DE SALUD
A5: DIRECCION DE FISCALIZACION
A6: RELACIÓN DE ORDENES DE COMPRAS DE BIENES Y SERVICIOS EFECTUADAS.
A7: ESTABLECIMIENTO: HOSPITAL MATERNO INFANTIL SAN LORENZO DE LOS MINA REGION_0 MES DE MAYO 2025
A8: Fecha | B8: # Orden de Compra o Servicios | C8: # DE EXPEDIENTE(PROCESO CELEBRADO) | D8: No. De Factura Fiscal NCF | E8: Fuente. Financ (FR-VS) | F8: Beneficiario | G8: Rubro | H8: No. Cta. Objetal del Gasto | I8: Valor | J8: Status del proceso | K8: solo observar cuando se presentas esos procesos
A9: 45778.502 | B9: HSML-2025-00421 | C9: HSLM-DAF-CD-2025-0339 | E9: VS/FG | F9: Diucam Group SRL | G9: 44120000 | H9: 2.2.7.1.01 | I9: 272005.91 | J9: Adjudicado
A10: 45778.502 | B10: Analisis de oferta | C10: HSLM-DAF-CM-2025-0108 | E10: VS/FG | G10: 42290000 | J10: Evaluación
A11: 45778.502 | B11: Analisis de oferta | C11: HSLM-DAF-CM-2025-0109 | E11: VS/FG | G11: 42290000 | H11: 2.2.7.1.01 | J11: Evaluación
A12: 45779.459 | B12: HSML-2025-00422 | C12: HSLM-DAF-CD-2025-0340 | E12: VS/FG | F12: Baucomer, SRL | G12: 51160000 | H12: 2.6.3.2.01 | I12: 199620 | J12: Adjudicado
A13: 45779.479 | B13: HSML-2025-00447 | C13: HSLM-DAF-CM-2025-0110 | E13: VS/FG | F13: BAAM & Asociados, SRL | G13: 30170000 | H13: 2.2.7.1.01 | I13: 883372.39 | J13: Adjudicado
A14: 45779.576 | B14: HSML-2025-00423 | C14: HSLM-DAF-CD-2025-0341 | E14: VS/FG | F14: INVERSIONES FH, SRL | G14: 15100000 | H14: 2.2.7.1.01 | I14: 172000 | J14: Adjudicado
A15: 45783.521 | B15: HSML-2025-00425 | C15: HSLM-DAF-CD-2025-0342 | E15: VS/FG | F15: Dumas Pharmaceuticals, SRL | G15: 51100000 | H15: 2.6.1.1.01 | I15: 77000 | J15: Adjudicado
A16: 45783.569 | B16: HSML-2025-00452 | C16: HSLM-DAF-CM-2025-0111 | E16: VS/FG | F16: P&D Recycling, SRL | G16: 76120000 | H16: 2.6.3.1.01 | I16: 760000 | J16: Adjudicado
A17: 45784.465 | B17: HSML-2025-00429 | C17: HSLM-DAF-CD-2025-0343 | E17: VS/FG | F17: Baucomer, SRL | G17: 42140000 | H17: 2.3.1.1.01 | I17: 242945 | J17: Adjudicado
A18: 45784.502 | B18: HSML-2025-00430 | C18: HSLM-DAF-CD-2025-0344 | E18: VS/FG | F18: Diucam Group SRL | G18: 90100000 | H18: 2.3.7.1.01 | I18: 57938 | J18: Adjudicado
A19: 45784.584 | B19: HSML-2025-00431 | C19: HSLM-DAF-CD-2025-0346 | E19: VS/FG | F19: Grupo Xeron Medic SRL | G19: 51140000 | H19: 2.3.1.1.01 | I19: 251945 | J19: Adjudicado
A20: 45784.626 | B20: HSML-2025-00469 | C20: HSLM-DAF-CD-2025-0345 | E20: VS/FG | F20: osorio integraciones | G20: 46170000 | H20: 2.3.1.1.01 | I20: 58764 | J20: Adjudicado
A21: 45784.709 | B21: HSML-2025-00433 | C21: HSLM-DAF-CD-2025-0348 | E21: VS/FG | F21: Farmaco Internacional, SRL | G21: 42180000 | H21: 2.3.9.3.01 | I21: 26821.4 | J21: Adjudicado
A22: 45784.709 | B22: HSML-2025-00432 | C22: HSLM-DAF-CD-2025-0347 | E22: VS/FG | F22: Grupo Xeron Medic SRL | G22: 42170000 | H22: 2.2.1.8.01 | I22: 160159.96 | J22: Adjudicado
A23: 45785.465 | B23: HSML-2025-00435 | C23: HSLM-DAF-CD-2025-0349 | E23: VS/FG | F23: Farmaco Internacional, SRL | G23: 42180000 | H23: 2.6.1.3.01 | I23: 26821.4 | J23: Adjudicado
... A61: 45792.502 | B61: HSML-2025-00494 | C61: HSLM-DAF-CM-2025-0122 | E61: VS/FG | F61: Ciencia Tecnología y Consultas, SRL | G61: 41100000 | H61: 2.3.4.1.01 | I61: 778983.4 | J61: Adjudicado
A62: 45792.502 | B62: HSML-2025-00501 | C62: HSLM-DAF-CD-2025-0378 | E62: VS/FG | F62: Farmaceutica Dalmasi (FARMADAL), SRL | G62: 41110000 | I62: 34021.44 | J62: Adjudicado
A63: 45792.542 | B63: HSML-2025-00497 | C63: HSLM-DAF-CM-2025-0125 | E63: VS/FG | F63: Bello-Lab, SRL | G63: 41100000 | H63: 2.3.9.3.01 | I63: 329391 | J63: Adjudicado
A64: 45792.542 | B64: HSML-2025-00481 | C64: HSLM-DAF-CD-2025-0379 | E64: VS/FG | F64: CEM Caribbean Equipment Medical, SRL | G64: 41110000 | H64: 2.3.9.3.01 | I64: 174238 | J64: Adjudicado
A65: 45792.573 | B65: HSML-2025-00470 | C65: HSLM-DAF-CD-2025-0382 | E65: VS/FG | F65: Farmaco Internacional, SRL | G65: 41100000 | H65: 2.3.4.1.01 | I65: 6289.04 | J65: Adjudicado
A66: 45792.584 | B66: HSML-2025-00473 | C66: HSLM-DAF-CD-2025-0381 | E66: VS/FG | F66: Papelería E. Impresos Crishoan, SRL | G66: 82120000 | H66: 2.2.7.2.08 | I66: 266326 | J66: Adjudicado
A67: 45792.584 | B67: HSML-2025-00498 | C67: HSLM-DAF-CM-2025-0123 | E67: VS/FG | F67: Sued & Fargesa, SRL | G67: 41110000 | H67: 2.3.9.1.01 | I67: 573395 | J67: Adjudicado
A68: 45792.585 | B68: HSML-2025-00471 | C68: HSLM-DAF-CD-2025-0380 | E68: VS/FG | F68: Q&Q Medical RD, SRL | G68: 41100000 | H68: 2.3.4.1.01 | I68: 226240.22 | J68: Adjudicado
A69: 45792.611 | B69: HSML-2025-00499 | C69: HSLM-DAF-CM-2025-0124 | E69: VS/FG | F69: CEM Caribbean Equipment Medical, SRL | G69: 41110000 | H69: 2.3.9.3.01 | I69: 668000 | J69: Adjudicado
A70: 45793.438 | B70: HSML-2025-00480 | C70: HSLM-DAF-CD-2025-0383 | E70: VS/FG | F70: Global Multi-Pharma Dominicana THM, SRL | G70: 42310000 | H70: 2.3.4.1.01 | I70: 264000 | J70: Adjudicado
A71: 45793.46 | B71: HSML-2025-00479 | C71: HSLM-DAF-CD-2025-0384 | E71: VS/FG | F71: Global Multi-Pharma Dominicana THM, SRL | G71: 42180000 | H71: 2.3.7.2.03 | I71: 57820 | J71: Adjudicado
A72: 45793.502 | B72: HSML-2025-00495 | C72: HSLM-DAF-CM-2025-0126 | E72: VS/FG | F72: G & M Gelmat Comercial, SRL | G72: 42180000 | H72: 2.3.9.3.01 | I72: 674774 | J72: Adjudicado
A73: 45793.503 | B73: cancelado | C73: HSLM-DAF-CD-2025-0385 | E73: VS/FG | G73: 52150000 | H73: 2.3.4.1.01 | J73: Cancelado
A74: 45793.542 | B74: HSML-2025-00475 | C74: HSLM-DAF-CD-2025-0388 | E74: VS/FG | F74: Gestoria Administrativa Ynuñez S.R.L | G74: 41100000 | H74: 2.3.7.2.03 | I74: 270007.6 | J74: Adjudicado
A75: 45793.542 | B75: HSML-2025-00474 | C75: HSLM-DAF-CD-2025-0387 | E75: VS/FG | F75: Dumas Pharmaceuticals, SRL | G75: 51120000 | H75: 2.6.1.1.01 | I75: 45000 | J75: Adjudicado
A76: 45793.542 | B76: Analisis de oferta | C76: HSLM-DAF-CM-2025-0127 | E76: VS/FG | G76: 42200000 | H76: 2.6.3.4.01 | J76: Evaluación
A77: 45793.542 | B77: HSML-2025-00478 | C77: HSLM-DAF-CD-2025-0386 | E77: VS/FG | F77: Bello-Lab, SRL | G77: 41110000 | H77: 2.3.4.1.01 | I77: 247123.9 | J77: Adjudicado
A78: 45793.542 | B78: HSML-2025-00477 | C78: HSLM-DAF-CD-2025-0389 | E78: VS/FG | F78: JM Distribución, SRL | G78: 52150000 | H78: 2.3.9.3.01 | I78: 72900.01 | J78: Adjudicado
A79: 45793.584 | B79: HSML-2025-00476 | C79: HSLM-DAF-CD-2025-0390 | E79: VS/FG | F79: Grupo Xeron Medic SRL | G79: 42270000 | H79: 2.2.9.1.01 | I79: 163902 | J79: Adjudicado
A80: 45796.479 | B80: HSML-2025-00482 | C80: HSLM-DAF-CD-2025-0391 | E80: VS/FG | F80: Xavier Vargas, Ingeniería Electromecánica, EIRL | G80: 40100000 | H80: 2.6.5.4.02 | I80: 232932 | J80: Adjudicado
A81: 45796.502 | B81: Analisis de oferta | C81: HSLM-DAF-CD-2025-0392 | E81: VS/FG | G81: 41110000 | H81: 2.6.5.4.02 | J81: Evaluación
A82: 45797.361 | B82: HSML-2025-00486 | C82: HSLM-DAF-CD-2025-0393 | E82: VS/FG | F82: Gapiezo SRL | G82: 30170000 | H82: 2.3.9.3.01 | I82: 80125.36 | J82: Adjudicado
A83: 45797.49 | B83: HSML-2025-00514 | C83: HSLM-DAF-CM-2025-0130 | E83: VS/FG | F83: Capegar, SRL | G83: 39100000 | H83: 2.6.3.1.01 | I83: 484500.04 | J83: Adjudicado
A84: 45797.502 | B84: HSML-2025-00507 | C84: HSLM-DAF-CM-2025-0128 | E84: VS/FG | F84: Osorio Integraciones, S.R.L | G84: 52160000 | H84: 2.6.3.2.01 | I84: 429289 | J84: Adjudicado
A85: 45797.502 | B85: HSML-2025-00508 | C85: HSLM-DAF-CM-2025-0129 | E85: VS/FG | F85: Osorio Integraciones, S.R.L | G85: 52160000 | H85: 2.3.4.1.01 | I85: 389046 | J85: Adjudicado
A86: 45797.502 | B86: HSML-2025-00487 | C86: HSLM-DAF-CD-2025-0394 | E86: VS/FG | F86: Abrias Novo Group SRL | G86: 52100000 | H86: 2.3.9.3.01 | I86: 189862 | J86: Adjudicado
A87: 45797.584 | B87: HSML-2025-00488 | C87: HSLM-DAF-CD-2025-0395 | E87: VS/FG | F87: Adler Amicis Valdez Marmolejos | G87: 82120000 | H87: 2.3.9.3.01 | I87: 53100 | J87: Adjudicado
A88: 45798.459 | B88: HSML-2025-00491 | C88: HSLM-DAF-CD-2025-0396 | E88: VS/FG | F88: Abrias Novo Group SRL | G88: 52130000 | H88: 2.3.9.3.01 | I88: 248012.09 | J88: Adjudicado
A89: 45798.46 | B89: HSML-2025-00492 | C89: HSLM-DAF-CD-2025-0397 | E89: VS/FG | F89: CEM Caribbean Equipment Medical, SRL | G89: 14110000 | H89: 2.3.7.2.03 | I89: 9487.2 | J89: Adjudicado
A90: 45798.465 | B90: HSML-2025-00493 | C90: HSLM-DAF-CD-2025-0398 | E90: VS/FG | F90: Farmaco Internacional, SRL | G90: 42290000 | I90: 55960.32 | J90: Adjudicado
A91: 45798.503 | B91: Analisis de oferta | C91: HSLM-DAF-CM-2025-0131 | E91: VS/FG | G91: 52120000 | H91: 2.3.9.3.01 | J91: Abierto
A92: 45798.503 | B92: HSML-2025-00509 | C92: HSLM-DAF-CM-2025-0132 | E92: VS/FG | F92: Tu Amigo, SRL | G92: 15100000 | H92: 2.3.7.2.03 | I92: 664800 | J92: Adjudicado
A93: 45798.563 | B93: HSML-2025-00496 | C93: HSLM-DAF-CD-2025-0399 | E93: VS/FG | F93: Baucomer, SRL | G93: 51110000 | H93: 2.6.5.2.01 | I93: 234000 | J93: Adjudicado
A94: 45799.502 | B94: HSML-2025-00515 | C94: HSLM-DAF-CM-2025-0133 | E94: VS/FG | F94: Abrias Novo Group SRL | G94: 90100000 | H94: 2.6.5.4.02 | I94: 1639492 | J94: Adjudicado
A95: 45799.627 | B95: Analisis de oferta | C95: HSLM-DAF-CD-2025-0400 | E95: VS/FG | G95: 41110000 | H95: 2.3.2.3.01 | J95: Evaluación
A96: 45800.502 | B96: HSML-2025-00503 | C96: HSLM-DAF-CD-2025-0401 | E96: VS/FG | F96: Papelería E. Impresos Crishoan, SRL | G96: 60120000 | H96: 2.2.7.1.01 | I96: 233640 | J96: Adjudicado
A97: 45803.376 | B97: HSML-2025-00513 | C97: HSLM-DAF-CD-2025-0402 | E97: VS/FG | F97: I.V. Biodesinfección, SRL | G97: 76100000 | H97: 2.3.2.2.01 | I97: 197673.6 | J97: Adjudicado
A98: 45803.418 | B98: HSML-2025-00530 | C98: HSLM-DAF-CM-2025-0134 | E98: VS/FG | F98: Sandry Gomez Rodriguez | G98: 50110000 | H98: 2.2.7.1.01 | I98: 521100 | J98: Adjudicado
A99: 45803.418 | B99: HSML-2025-00504 | C99: HSLM-DAF-CD-2025-0403 | E99: VS/FG | F99: Antares Pharma, SRL | G99: 42270000 | H99: 2.6.1.3.01 | I99: 180003.01 | J99: Adjudicado
A100: 45803.459 | B100: HSML-2025-00531 | C100: HSLM-DAF-CM-2025-0136 | E100: VS/FG | F100: Sandry Gomez Rodriguez | G100: 50130000 | H100: 2.6.1.9.01 | I100: 275330 | J100: Adjudicado
A101: 45803.46 | B101: HSML-2025-00506 | C101: HSLM-DAF-CD-2025-0404 | E101: VS/FG | F101: Antares Pharma, SRL | G101: 51190000 | I101: 108142.5 | J101: Adjudicado
A102: 45803.502 | B102: HSML-2025-00523 | C102: HSLM-DAF-CM-2025-0135 | E102: VS/FG | F102: Abrias Novo Group SRL | G102: 90100000 | H102: 2.6.1.1.01 | I102: 910287.4 | J102: Adjudicado
A103: 45803.502 | B103: HSML-2025-00533 | C103: HSLM-DAF-CM-2025-0137 | E103: VS/FG | F103: Sandry Gomez Rodriguez | G103: 50100000 | H103: 2.2.8.5.03 | I103: 374360 | J103: Adjudicado
A104: 45803.626 | B104: HSML-2025-00510 | C104: HSLM-DAF-CD-2025-0405 | E104: VS/FG | F104: Adler Amicis Valdez Marmolejos | G104: 82120000 | H104: 2.3.4.1.01 | I104: 88889 | J104: Adjudicado
A105: 45804.459 | B105: HSML-2025-00511 | C105: HSLM-DAF-CD-2025-0406 | E105: VS/FG | F105: Bio Nova, SRL | G105: 41110000 | H105: 2.3.9.3.01 | I105: 137145 | J105: Adjudicado
A106: 45804.503 | B106: Analisis de oferta | C106: HSLM-DAF-CM-2025-0138 | E106: VS/FG | G106: 50190000 | J106: Publicado
A107: 45804.542 | B107: HSML-2025-00512 | C107: HSLM-DAF-CD-2025-0407 | E107: VS/FG | F107: Ropharma, SRL | G107: 51190000 | H107: 2.6.3.2.01 | I107: 253500 | J107: Adjudicado
A108: 45805.46 | B108: HSML-2025-00516 | C108: HSLM-DAF-CD-2025-0409 | E108: VS/FG | F108: RYS SOLUCIONES E INVERSIONES INTEGRALES, SRL | G108: 14110000 | H108: 2.3.2.1.01 | I108: 177000 | J108: Adjudicado
A109: 45805.503 | B109: HSML-2025-00517 | C109: HSLM-DAF-CD-2025-0408 | E109: VS/FG | F109: Abrias Novo Group SRL | G109: 82120000 | H109: 2.6.3.1.01 | I109: 71591.43 | J109: Adjudicado
A110: 45805.503 | B110: HSML-2025-00528 | C110: HSLM-DAF-CD-2025-0410 | E110: VS/FG | F110: Servicio de Biomedicina Médico SERBIOMED, SRL | G110: 85160000 | H110: 2.3.1.1.01 | I110: 212400 | J110: Adjudicado
A111: 45805.503 | B111: HSML-2025-00526 | C111: HSLM-DAF-CD-2025-0411 | E111: VS/FG | F111: Servicio de Biomedicina Médico SERBIOMED, SRL | G111: 85160000 | H111: 2.3.1.1.01 | I111: 247800 | J111: Adjudicado
A112: 45805.563 | B112: HSML-2025-00518 | C112: HSLM-DAF-CD-2025-0412 | E112: VS/FG | F112: INVERSIONES FH, SRL | G112: 15100000 | H112: 2.3.1.1.01 | I112: 172000 | J112: Adjudicado
A113: 45805.628 | B113: Analisis de oferta | C113: HSLM-DAF-CM-2025-0139 | E113: VS/FG | G113: 81110000 | H113: 2.3.4.1.01 | J113: Evaluación
A114: 45806.465 | B114: HSML-2025-00520 | C114: HSLM-DAF-CD-2025-0413 | E114: VS/FG | F114: Grupo Xeron Medic SRL | G114: 51150000 | H114: 2.2.2.2.01 | I114: 210000 | J114: Adjudicado
A115: 45806.502 | B115: HSML-2025-00522 | C115: HSLM-DAF-CD-2025-0414 | E115: VS/FG | F115: Osiris & Co, SA | G115: 42130000 | H115: 2.2.8.5.03 | I115: 257004 | J115: Adjudicado
A116: 45806.503 | B116: Analisis de oferta | C116: HSLM-DAF-CM-2025-0140 | E116: VS/FG | G116: 43210000 | J116: Evaluación
A117: 45806.521 | B117: HSML-2025-00519 | C117: HSLM-DAF-CD-2025-0415 | E117: VS/FG | F117: Grupo Xeron Medic SRL | G117: 51100000 | H117: 2.3.9.9.05 | I117: 151260 | J117: Adjudicado
A118: 45806.543 | B118: HSML-2025-00521 | C118: HSLM-DAF-CD-2025-0416 | E118: VS/FG | F118: Adler Amicis Valdez Marmolejos | G118: 53100000 | H118: 2.2.8.3.01 | I118: 223020 | J118: Adjudicado
A119: 45807.419 | B119: HSML-2025-00524 | C119: HSLM-DAF-CD-2025-0417 | E119: VS/FG | F119: RYS SOLUCIONES E INVERSIONES INTEGRALES, SRL | G119: 82120000 | H119: 2.3.9.3.01 | I119: 264320 | J119: Adjudicado
A120: 45807.419 | B120: HSML-2025-00525 | C120: HSLM-DAF-CD-2025-0418 | E120: VS/FG | F120: Corporacion Medica A.G., SRL | G120: 42140000 | I120: 177000 | J120: Adjudicado
A121: 45807.459 | B121: HSML-2025-00532 | C121: HSLM-DAF-CD-2025-0419 | E121: VS/FG | F121: Gta Elevators, S.R.L | G121: 72100000 | I121: 106200 | J121: Adjudicado
D122: vs | F122: Sub-Total Compras RD$ | I122: =SUM(I9:I121) -> 30151207
A125: RESUMEN DE COMPRAS o SERVICIOS POR CUENTAS: | F125: RESUMEN DE PROCESO SEGÚN MODALIDAD:
A127: CUENTAS No. | B127: CANTIDAD | C127: MONTO | F127: TIPO | G127: CANTIDAD | H127: MONTO
F128: Compra Directa
F129: Compra Menor
F130: Comparacion de precio
F131: TOTAL COMPRAS | G131: =SUM(G128:G130) -> 0 | H131: =+H123 -> 0
E139: CERTIFICO CORRECTO:
E141: __________________________
E142: DIRECTOR
E144: __________________________
E145: ADMINISTRADOR:
E148: ENC. DE COMPRAS:__________________________
A169: TOTAL RESUMEN | C169: =SUM(C128:C168) -> 0

Sheet CUENTA T VS
A1: D E S G L O S E D E L A S C U E N T A S
A2: 211101 | B2: 211102 | C2: 211103 | D2: 211104 | E2: 211105 | F2: 211106 | G2: 211203 | H2: 211205 | I2: 211206 | J2: 211208 | K2: 211209 | L2: 211211 | M2: 211301 | N2: 211401 | O2: 211501 | P2: 211502 | Q2: 211503 | R2: 211504 | S2: 212101 | T2: 212201 | U2: 212203 | V2: 212204 | W2: 212205 | X2: 212206 | Y2: 212207 | Z2: 212208 | AA2: 212209 | AB2: 212210 | AC2: 213101 | AD2: 213102 | AE2: 213201 | AF2: 213202 | AG2: 214101 | AH2: 214201 | AI2: 214202 | AJ2: 214203 | AK2: 215101 | AL2: 215201 | AM2: 215301 | AN2: 215401 | AO2: 221101 | AP2: 221201 | AQ2: 221301 | AR2: 221401 | AS2: 221501 | AT2: 221601 | AU2: 221602 | AV2: 221701 | AW2: 221801 | AX2: 222101 | AY2: 222201 | AZ2: 223101 | BA2: 223201 | BB2: 224101 | BC2: 224201 | BD2: 224301 | BE2: 224401 | BF2: 225101 | BG2: 225201 | BH2: 225301 | BI2: 225302 | BJ2: 225303 | BK2: 225304 | BL2: 225305 | BM2: 225401 | BN2: 225501 | BO2: 225601 | BP2: 225701 | BQ2: 225801 | BR2: 225901 | BS2: 226101 | BT2: 226201 | BU2: 226301 | BV2: 226401 | BW2: 227101 | BX2: 227102 | BY2: 227103 | BZ2: 227104 | CA2: 227105 | CB2: 227106 | CC2: 227107 | CD2: 227199 | CE2: 227201 | CF2: 227202 | CG2: 227203 | CH2: 227204 | CI2: 227205 | CJ2: 227206 | CK2: 227207 | CL2: 227208 | CM2: 227299 | CN2: 227301 | CO2: 228101 | CP2: 228201 | CQ2: 228301 | CR2: 228401 | CS2: 228501 | CT2: 228502 | CU2: 228503 | CV2: 228601 | CW2: 228602 | CX2: 228603 | CY2: 228604 | CZ2: 228701 | DA2: 228702 | DB2: 228703 | DC2: 228704 | DD2: 228705 | DE2: 228706 | DF2: 228801 | DG2: 228802 | DH2: 228803 | DI2: 229201 | DJ2: 229203 | DK2: 231101 | DL2: 231102 | DM2: 231201 | DN2: 231301 | DO2: 231302 | DP2: 231303 | DQ2: 231401 | DR2: 232101 | DS2: 232201 | DT2: 232301 | DU2: 233101 | DV2: 233201 | DW2: 233301 | DX2: 233401 | DY2: 233501 | DZ2: 233601 | EA2: 234101 | EB2: 234201 | EC2: 235101 | ED2: 235201 | EE2: 235301 | EF2: 235401 | EG2: 235501 | EH2: 236101 | EI2: 236102 | EJ2: 236103 | EK2: 236104 | EL2: 236105 | EM2: 236201 | EN2: 236202 | EO2: 236203 | EP2: 236304 | EQ2: 236305 | ER2: 236306 | ES2: 236401 | ET2: 236402 | EU2: 236403 | EV2: 236404 | EW2: 236405 | EX2: 236406 | EY2: 236407 | EZ2: 236901 | FA2: 237101 | FB2: 237102 | FC2: 237103 | FD2: 237104 | FE2: 237105 | FF2: 237106 | FG2: 237107 | FH2: 237201 | FI2: 237202 | FJ2: 237203 | FK2: 237204 | FL2: 237205 | FM2: 237206 | FN2: 237299 | FO2: 238101 | FP2: 238201 | FQ2: 239101 | FR2: 239102 | FS2: 239201 | FT2: 239301 | FU2: 239401 | FV2: 239501 | FW2: 239601 | FX2: 239701 | FY2: 239801 | FZ2: 239802 | GA2: 239901 | GB2: 239904 | GC2: 241201 | GD2: 241202 | GE2: 241203 | GF2: 241204 | GG2: 241205 | GH2: 261101 | GI2: 261201 | GJ2: 261301 | GK2: 261401 | GL2: 261901 | GM2: 262101 | GN2: 262201 | GO2: 262301 | GP2: 262401 | GQ2: 263101 | GR2: 263201 | GS2: 263301 | GT2: 263401 | GU2: 264101 | GV2: 264201 | GW2: 264301 | GX2: 264401 | GY2: 264501 | GZ2: 264601 | HA2: 264701 | HB2: 264801 | HC2: 265101 | HD2: 265201 | HE2: 265301 | HF2: 265401 | HG2: 265501 | HH2: 265601 | HI2: 265701 | HJ2: 265801 | HK2: 266101 | HL2: 266201 | HM2: 267101 | HN2: 267201 | HO2: 267301 | HP2: 267401 | HQ2: 267501 | HR2: 267601 | HS2: 267701 | HT2: 267801 | HU2: 267901 | HV2: 268101 | HW2: 268201 | HX2: 268301 | HY2: 268302 | HZ2: 268401 | IA2: 268501 | IB2: 268601 | IC2: 268701 | ID2: 268802 | IE2: 268803 | IF2: 268804 | IG2: 268901 | IH2: 269101 | II2: 269102 | IJ2: 269201 | IK2: 269202 | IL2: 269301 | IM2: 269401 | IN2: 269501 | IO2: 269502 | IP2: 269503 | IQ2: 2269901 | IR2: 271101 | IS2: 271201 | IT2: 271301 | IU2: 271401 | IV2: 272101 | IW2: 272201 | IX2: 272301 | IY2: 272401 | IZ2: 272501 | JA2: 272601 | JB2: 272701 | JC2: 272801 | JD2: 272901 | JE2: 273101 | JF2: 273201 | JG2: 274101 | JH2: 274201 | JI2: Totales | JJ2: TRANSF NO. | JK2: VALOR | JL2: RETENCION | JM2: AÑOS ANTERIORES | JN2: 2022 | JO2: Total | JP2: Proveedor Informal
BI3: 247030.86 | JI3: =SUM(A3:JH3) -> 247030.86 | JJ3: 130
AW4: 760000 | JI4: =SUM(A4:JH4) -> 760000 | JJ4: 131
AQ5: 104532.2 | JI5: =SUM(A5:JH5) -> 104532.2 | JJ5: 132
GD6: 200000 | JI6: =SUM(A6:JH6) -> 200000 | JJ6: 133
AS7: 104427.01 | JI7: =SUM(A7:JH7) -> 104427.01 | JJ7: 134
JI8: =SUM(A8:JH8) -> 0 | JJ8: 135
JI9: =SUM(A9:JH9) -> 0 | JJ9: 136
FT10: 26821.4 | JI10: =SUM(A10:JH10) -> 26821.4 | JJ10: 137
FT11: 26821.4 | JI11: =SUM(A11:JH11) -> 26821.4 | JJ11: 138
BQ12: 53100 | JI12: =SUM(A12:JH12) -> 53100 | JJ12: 139
GD13: 70800 | JI13: =SUM(A13:JH13) -> 70800 | JJ13: 140
DE14: 10000 | JI14: =SUM(A14:JH14) -> 10000 | JJ14: 141
GD15: 50958 | JI15: =SUM(A15:JH15) -> 50958 | JJ15: 142
GR16: 621205.1 | JI16: =SUM(A16:JH16) -> 621205.1 | JJ16: 143
FA17: 172000 | JI17: =SUM(A17:JH17) -> 172000 | JJ17: 144
FJ18: 846850 | JI18: =SUM(A18:JH18) -> 846850 | JJ18: 145
DW19: 108265 | JI19: =SUM(A19:JH19) -> 108265 | JJ19: 146
FD20: 23868 | JI20: =SUM(A20:JH20) -> 23868 | JJ20: 147
BC21: 32000 | JI21: =SUM(A21:JH21) -> 32000 | JJ21: 148
DV22: 227500 | JI22: =SUM(A22:JH22) -> 227500 | JJ22: 149
DV23: 271400 | JI23: =SUM(A23:JH23) -> 271400 | JJ23: 150
GR24: 1590510.2 | JI24: =SUM(A24:JH24) -> 1590510.2 | JJ24: 151
CU25: 39530 | JI25: =SUM(A25:JH25) -> 39530 | JJ25: 152
DK26: 91875 | JI26: =SUM(A26:JH26) -> 91875 | JJ26: 153
FQ27: 98506.4 | JI27: =SUM(A27:JH27) -> 98506.4 | JJ27: 154
DR28: 141128 | JI28: =SUM(A28:JH28) -> 141128 | JJ28: 155
DK29: 263200 | JI29: =SUM(A29:JH29) -> 263200 | JJ29: 156
GD30: 70000 | JI30: =SUM(A30:JH30) -> 70000 | JJ30: =+JJ29+1 -> 157
EA31: 42000 | JI31: =SUM(A31:JH31) -> 42000 | JJ31: =+JJ30+1 -> 158
CU32: 37996 | JI32: =SUM(A32:JH32) -> 37996 | JJ32: =+JJ31+1 -> 159
CU33: 9912 | JI33: =SUM(A33:JH33) -> 9912 | JJ33: =+JJ32+1 -> 160
FT34: 55241.4 | GR34: 10226.89 | JI34: =SUM(A34:JH34) -> 65468.29 | JJ34: =+JJ33+1 -> 161
EA35: 88100 | JI35: =SUM(A35:JH35) -> 88100 | JJ35: =+JJ34+1 -> 162
JI36: =SUM(A36:JH36) -> 0 | JJ36: =+JJ35+1 -> 163
JI37: =SUM(A37:JH37) -> 0 | JJ37: =+JJ36+1 -> 164
AQ38: 104504.21 | JI38: =SUM(A38:JH38) -> 104504.21 | JJ38: =+JJ37+1 -> 165
DE39: 17033 | JI39: =SUM(A39:JH39) -> 17033 | JJ39: =+JJ38+1 -> 166
AW40: 25000 | JI40: =SUM(A40:JH40) -> 25000 | JJ40: =+JJ39+1 -> 167
BC41: 24000 | JI41: =SUM(A41:JH41) -> 24000 | JJ41: =+JJ40+1 -> 168
BI42: 229519.78 | JI42: =SUM(A42:JH42) -> 229519.78 | JJ42: =+JJ41+1 -> 169
FD43: 23205 | JI43: =SUM(A43:JH43) -> 23205 | JJ43: =+JJ42+1 -> 170
CU44: 4578.4 | JI44: =SUM(A44:JH44) -> 4578.4 | JJ44: =+JJ43+1 -> 171
GT45: 1705100 | JI45: =SUM(A45:JH45) -> 1705100 | JJ45: =+JJ44+1 -> 172
GD46: 50000 | JI46: =SUM(A46:JH46) -> 50000 | JJ46: =+JJ45+1 -> 173
GD47: 10650 | JI47: =SUM(A47:JH47) -> 10650 | JJ47: 37223
CL48: 54184.86 | JI48: =SUM(A48:JH48) -> 54184.86 | JJ48: 37224
DE49: 15000 | JI49: =SUM(A49:JH49) -> 15000 | JJ49: 37225
GD50: 3400 | JI50: =SUM(A50:JH50) -> 3400 | JJ50: 37226
GD51: 25000 | JI51: =SUM(A51:JH51) -> 25000 | JJ51: 37227
CL52: 12040.81 | JI52: =SUM(A52:JH52) -> 12040.81 | JJ52: 37228
GA53: 50620 | JI53: =SUM(A53:JH53) -> 50620 | JJ53: 37229
CL54: 18061.22 | JI54: =SUM(A54:JH54) -> 18061.22 | JJ54: 37230
CL55: 21673.47 | JI55: =SUM(A55:JH55) -> 21673.47 | JJ55: 37231
CL56: 18061.22 | JI56: =SUM(A56:JH56) -> 18061.22 | JJ56: 37232
CL57: 9632.66 | JI57: =SUM(A57:JH57) -> 9632.66 | JJ57: 37233
BB58: 20000 | JI58: =SUM(A58:JH58) -> 20000 | JJ58: 37234
CL59: 72244.9 | JI59: =SUM(A59:JH59) -> 72244.9 | JJ59: 37235
JI60: =SUM(A60:JH60) -> 0
JI61: =SUM(A61:JH61) -> 0
JI62: =SUM(A62:JH62) -> 0
JI63: =SUM(A63:JH63) -> 0
JI64: =SUM(A64:JH64) -> 0
JI65: =SUM(A65:JH65) -> 0
JI66: =SUM(A66:JH66) -> 0
JI67: =SUM(A67:JH67) -> 0
JI68: =SUM(A68:JH68) -> 0
JI69: =SUM(A69:JH69) -> 0
JI70: =SUM(A70:JH70) -> 0
JI71: =SUM(A71:JH71) -> 0
... JI86: =SUM(A86:JH86) -> 0
JI87: =SUM(A87:JH87) -> 0 | JL87: =+JI87-JK87 -> 0
JI88: =SUM(A88:JH88) -> 0 | JL88: =+JI88-JK88 -> 0
A89: =SUM(A3:A88) -> 0 | B89: =SUM(B3:B88) -> 0 | C89: =SUM(C3:C88) -> 0 | D89: =SUM(D3:D88) -> 0 | E89: =SUM(E3:E88) -> 0 | F89: =SUM(F3:F88) -> 0 | G89: =SUM(G3:G88) -> 0 | H89: =SUM(H3:H88) -> 0 | ... JH89: =SUM(JH3:JH88) -> 0 | JI89: =SUM(A89:JH89) -> 9009314.4 | JL89: =SUM(JL3:JL88) -> 0 | JM89: =SUM(JM3:JM88) -> 0 | JN89: =SUM(JN3:JN88) -> 0 | JO89: =SUM(JO3:JO88) -> 0 | JP89: =SUM(JP3:JP88) -> 0
A90: 211101 | B90: 211102 | C90: 211103 | D90: 211104 | E90: 211105 | F90: 211106 | G90: 211203 | H90: 211205 | I90: 211206 | J90: 211208 | K90: 211209 | L90: 211211 | M90: 211301 | N90: 211401 | O90: 211501 | P90: 211502 | Q90: 211503 | R90: 211504 | S90: 212101 | T90: 212201 | U90: 212203 | V90: 212204 | W90: 212205 | X90: 212206 | Y90: 212207 | Z90: 212208 | AA90: 212209 | AB90: 212210 | AC90: 213101 | AD90: 213102 | AE90: 213201 | AF90: 213202 | AG90: 214101 | AH90: 214201 | AI90: 214202 | AJ90: 214203 | AK90: 215101 | AL90: 215201 | AM90: 215301 | AN90: 215401 | AO90: 221101 | AP90: 221201 | AQ90: 221301 | AR90: 221401 | AS90: 221501 | AT90: 221601 | AU90: 221602 | AV90: 221701 | AW90: 221801 | AX90: 222101 | AY90: 222201 | AZ90: 223101 | BA90: 223201 | BB90: 224101 | BC90: 224201 | BD90: 224301 | BE90: 224401 | BF90: 225101 | BG90: 225201 | BH90: 225301 | BI90: 225302 | BJ90: 225303 | BK90: 225304 | BL90: 225305 | BM90: 225401 | BN90: 225501 | BO90: 225601 | BP90: 225701 | BQ90: 225801 | BR90: 225901 | BS90: 226101 | BT90: 226201 | BU90: 226301
JI91: =SUM(A91:JH91) -> 0
JI92: =SUM(A92:JH92) -> 0
JI93: =SUM(A93:JH93) -> 0
JI94: =SUM(A94:JH94) -> 0
JI95: =SUM(A95:JH95) -> 0
JI96: =SUM(A96:JH96) -> 0
JI97: =SUM(A97:JH97) -> 0
JI98: =SUM(A98:JH98) -> 0
JI99: =SUM(A99:JH99) -> 0
JI100: =SUM(A100:JH100) -> 0
JI101: =SUM(A101:JH101) -> 0
JI102: =SUM(A102:JH102) -> 0
... JI104: =SUM(A104:JH104) -> 0
A105: =SUM(A91:A104) -> 0 | B105: =SUM(B91:B104) -> 0 | C105: =SUM(C91:C104) -> 0 | D105: =SUM(D91:D104) -> 0 | E105: =SUM(E91:E104) -> 0 | F105: =SUM(F91:F104) -> 0 | G105: =SUM(G91:G104) -> 0 | H105: =SUM(H91:H104) -> 0 | ... JI105: =SUM(JI91:JI104) -> 0
A106: =A89+A105 -> 0 | B106: =B89+B105 -> 0 | C106: =C89+C105 -> 0 | D106: =D89+D105 -> 0 | E106: =E89+E105 -> 0 | F106: =F89+F105 -> 0 | G106: =G89+G105 -> 0 | H106: =H89+H105 -> 0 | ... JI106: =JI89+JI105 -> 9009314.4

Sheet CUENTA T FONDO 100
A1: D E S G L O S E D E L A S C U E N T A S
A2: 211101 | B2: 211102 | C2: 211103 | D2: 211104 | E2: 211105 | F2: 211106 | G2: 211203 | H2: 211205 | I2: 211206 | J2: 211208 | K2: 211209 | L2: 211211 | M2: 211301 | N2: 211401 | O2: 211501 | P2: 211502 | Q2: 211503 | R2: 211504 | S2: 212101 | T2: 212201 | U2: 212203 | V2: 212204 | W2: 212205 | X2: 212206 | Y2: 212207 | Z2: 212208 | AA2: 212209 | AB2: 212210 | AC2: 213101 | AD2: 213102 | AE2: 213201 | AF2: 213202 | AG2: 214101 | AH2: 214201 | AI2: 214202 | AJ2: 214203 | AK2: 215101 | AL2: 215201 | AM2: 215301 | AN2: 215401 | AO2: 221101 | AP2: 221201 | AQ2: 221301 | AR2: 221401 | AS2: 221501 | AT2: 221601 | AU2: 221602 | AV2: 221701 | AW2: 221801 | AX2: 222101 | AY2: 222201 | AZ2: 223101 | BA2: 223201 | BB2: 224101 | BC2: 224201 | BD2: 224301 | BE2: 224401 | BF2: 225101 | BG2: 225201 | BH2: 225301 | BI2: 225302 | BJ2: 225303 | BK2: 225304 | BL2: 225305 | BM2: 225401 | BN2: 225501 | BO2: 225601 | BP2: 225701 | BQ2: 225801 | BR2: 225901 | BS2: 226101 | BT2: 226201 | BU2: 226301 | BV2: 226401 | BW2: 227101 | BX2: 227102 | BY2: 227103 | BZ2: 227104 | CA2: 227105 | CB2: 227106 | CC2: 227107 | CD2: 227199 | CE2: 227201 | CF2: 227202 | CG2: 227203 | CH2: 227204 | CI2: 227205 | CJ2: 227206 | CK2: 227207 | CL2: 227208 | CM2: 227299 | CN2: 227301 | CO2: 228101 | CP2: 228201 | CQ2: 228301 | CR2: 228401 | CS2: 228501 | CT2: 228502 | CU2: 228503 | CV2: 228601 | CW2: 228602 | CX2: 228603 | CY2: 228604 | CZ2: 228701 | DA2: 228702 | DB2: 228703 | DC2: 228704 | DD2: 228705 | DE2: 228706 | DF2: 228801 | DG2: 228802 | DH2: 228803 | DI2: 229201 | DJ2: 229203 | DK2: 231101 | DL2: 231102 | DM2: 231201 | DN2: 231301 | DO2: 231302 | DP2: 231303 | DQ2: 231401 | DR2: 232101 | DS2: 232201 | DT2: 232301 | DU2: 233101 | DV2: 233201 | DW2: 233301 | DX2: 233401 | DY2: 233501 | DZ2: 233601 | EA2: 234101 | EB2: 234201 | EC2: 235101 | ED2: 235201 | EE2: 235301 | EF2: 235401 | EG2: 235501 | EH2: 236101 | EI2: 236102 | EJ2: 236103 | EK2: 236104 | EL2: 236105 | EM2: 236201 | EN2: 236202 | EO2: 236203 | EP2: 236304 | EQ2: 236305 | ER2: 236306 | ES2: 236401 | ET2: 236402 | EU2: 236403 | EV2: 236404 | EW2: 236405 | EX2: 236406 | EY2: 236407 | EZ2: 236901 | FA2: 237101 | FB2: 237102 | FC2: 237103 | FD2: 237104 | FE2: 237105 | FF2: 237106 | FG2: 237107 | FH2: 237201 | FI2: 237202 | FJ2: 237203 | FK2: 237204 | FL2: 237205 | FM2: 237206 | FN2: 237299 | FO2: 238101 | FP2: 238201 | FQ2: 239101 | FR2: 239102 | FS2: 239201 | FT2: 239301 | FU2: 239401 | FV2: 239501 | FW2: 239601 | FX2: 239701 | FY2: 239801 | FZ2: 239802 | GA2: 239901 | GB2: 239904 | GC2: 241201 | GD2: 241202 | GE2: 241203 | GF2: 241204 | GG2: 241205 | GH2: 261101 | GI2: 261201 | GJ2: 261301 | GK2: 261401 | GL2: 261901 | GM2: 262101 | GN2: 262201 | GO2: 262301 | GP2: 262401 | GQ2: 263101 | GR2: 263201 | GS2: 263301 | GT2: 263401 | GU2: 264101 | GV2: 264201 | GW2: 264301 | GX2: 264401 | GY2: 264501 | GZ2: 264601 | HA2: 264701 | HB2: 264801 | HC2: 265101 | HD2: 265201 | HE2: 265301 | HF2: 265401 | HG2: 265501 | HH2: 265601 | HI2: 265701 | HJ2: 265801 | HK2: 266101 | HL2: 266201 | HM2: 267101 | HN2: 267201 | HO2: 267301 | HP2: 267401 | HQ2: 267501 | HR2: 267601 | HS2: 267701 | HT2: 267801 | HU2: 267901 | HV2: 268101 | HW2: 268201 | HX2: 268301 | HY2: 268302 | HZ2: 268401 | IA2: 268501 | IB2: 268601 | IC2: 268701 | ID2: 268802 | IE2: 268803 | IF2: 268804 | IG2: 268901 | IH2: 269101 | II2: 269102 | IJ2: 269201 | IK2: 269202 | IL2: 269301 | IM2: 269401 | IN2: 269501 | IO2: 269502 | IP2: 269503 | IQ2: 2269901 | IR2: 271101 | IS2: 271201 | IT2: 271301 | IU2: 271401 | IV2: 272101 | IW2: 272201 | IX2: 272301 | IY2: 272401 | IZ2: 272501 | JA2: 272601 | JB2: 272701 | JC2: 272801 | JD2: 272901 | JE2: 273101 | JF2: 273201 | JG2: 274101 | JH2: 274201 | JI2: Totales | JJ2: LIBRAMIENTO | JK2: VALOR | JL2: RETENCION | JM2: AÑOS ANTERIORES | JN2: 2024 | JO2: Total | JP2: Proveedor Informal
FJ3: 622991.58 | FQ3: 52756.9 | JI3: =SUM(A3:JH3) -> 675748.48 | JJ3: 1778 | JL3: =+JI3-JK3 -> 675748.48 | JO3: =+JM3+JN3 -> 0
FA4: 1649337.3 | JI4: =SUM(A4:JH4) -> 1649337.3 | JJ4: 1781 | JL4: =+JI4-JK4 -> 1649337.3
FJ5: 645614.72 | FN5: 9976 | FQ5: 161732.4 | JI5: =SUM(A5:JH5) -> 817323.12 | JJ5: 1785 | JL5: =+JI5-JK5 -> 817323.12
FQ6: 247068.4 | JI6: =SUM(A6:JH6) -> 247068.4 | JJ6: 1790 | JL6: =+JI6-JK6 -> 247068.4
FT7: 270102 | JI7: =SUM(A7:JH7) -> 270102 | JJ7: 1801 | JL7: =+JI7-JK7 -> 270102
GR8: 939471.75 | JI8: =SUM(A8:JH8) -> 939471.75 | JJ8: 1805 | JL8: =+JI8-JK8 -> 939471.75
EA9: 210000 | JI9: =SUM(A9:JH9) -> 210000 | JJ9: 1809 | JL9: =+JI9-JK9 -> 210000
FT10: 270102 | JI10: =SUM(A10:JH10) -> 270102 | JJ10: 1813 | JL10: =+JI10-JK10 -> 270102
HF11: 91569.9 | JI11: =SUM(A11:JH11) -> 91569.9 | JJ11: 1820 | JL11: =+JI11-JK11 -> 91569.9
FT12: 1937560 | JI12: =SUM(A12:JH12) -> 1937560 | JJ12: 1835 | JL12: =+JI12-JK12 -> 1937560
FT13: 276519 | JI13: =SUM(A13:JH13) -> 276519 | JJ13: 1839 | JL13: =+JI13-JK13 -> 276519
AA14: 443970.11 | JI14: =SUM(A14:JH14) -> 443970.11 | JJ14: 1841 | JL14: =+JI14-JK14 -> 443970.11
EA15: 17133.6 | FT15: 36875 | JI15: =SUM(A15:JH15) -> 54008.6 | JJ15: 1845 | JL15: =+JI15-JK15 -> 54008.6
EA16: 152500 | JI16: =SUM(A16:JH16) -> 152500 | JJ16: 1849 | JL16: =+JI16-JK16 -> 152500
DK17: 698555.7 | JI17: =SUM(A17:JH17) -> 698555.7 | JJ17: 1853 | JL17: =+JI17-JK17 -> 698555.7
FT18: 271400 | JI18: =SUM(A18:JH18) -> 271400 | JJ18: 1857 | JL18: =+JI18-JK18 -> 271400
GQ19: 508060.8 | JI19: =SUM(A19:JH19) -> 508060.8 | JJ19: 1861 | JL19: =+JI19-JK19 -> 508060.8
FT20: 177000 | JI20: =SUM(A20:JH20) -> 177000 | JJ20: 1865 | JL20: =+JI20-JK20 -> 177000
EG21: 57151.44 | JI21: =SUM(A21:JH21) -> 57151.44 | JJ21: 1873 | JL21: =+JI21-JK21 -> 57151.44
FT22: 129520 | JI22: =SUM(A22:JH22) -> 129520 | JJ22: 1875 | JL22: =+JI22-JK22 -> 129520
FT23: 179360 | JI23: =SUM(A23:JH23) -> 179360 | JJ23: 1879 | JL23: =+JI23-JK23 -> 179360
EA24: 199620 | JI24: =SUM(A24:JH24) -> 199620 | JJ24: 1890 | JL24: =+JI24-JK24 -> 199620
FT25: 242945 | JI25: =SUM(A25:JH25) -> 242945 | JJ25: 1897 | JL25: =+JI25-JK25 -> 242945
FT26: 270000 | JI26: =SUM(A26:JH26) -> 270000 | JJ26: 1900 | JL26: =+JI26-JK26 -> 270000
EA27: 44000 | JI27: =SUM(A27:JH27) -> 44000 | JJ27: 1902 | JL27: =+JI27-JK27 -> 44000
DV28: 209745 | JI28: =SUM(A28:JH28) -> 209745 | JJ28: 1910 | JL28: =+JI28-JK28 -> 209745
DW29: 271990 | JI29: =SUM(A29:JH29) -> 271990 | JJ29: 1917 | JL29: =+JI29-JK29 -> 271990
FJ30: 64960 | FT30: 47500 | JI30: =SUM(A30:JH30) -> 112460 | JJ30: 1920 | JL30: =+JI30-JK30 -> 112460
EA31: 205342 | JI31: =SUM(A31:JH31) -> 205342 | JJ31: 1923 | JL31: =+JI31-JK31 -> 205342
DK32: 269657.5 | JI32: =SUM(A32:JH32) -> 269657.5 | JJ32: 1927 | JL32: =+JI32-JK32 -> 269657.5
EA33: 190315 | JI33: =SUM(A33:JH33) -> 190315 | JJ33: 1931 | JL33: =+JI33-JK33 -> 190315
EA34: 250000 | JI34: =SUM(A34:JH34) -> 250000 | JJ34: 1936 | JL34: =+JI34-JK34 -> 250000
DK35: 436930 | JI35: =SUM(A35:JH35) -> 436930 | JJ35: 1940 | JL35: =+JI35-JK35 -> 436930
EA36: 263750 | JI36: =SUM(A36:JH36) -> 263750 | JJ36: 1944 | JL36: =+JI36-JK36 -> 263750
EP37: 160008 | FN37: 5616.8 | JI37: =SUM(A37:JH37) -> 165624.8 | JJ37: 1956 | JL37: =+JI37-JK37 -> 165624.8
FT38: 115050 | JI38: =SUM(A38:JH38) -> 115050 | JJ38: 1961 | JL38: =+JI38-JK38 -> 115050
HJ39: 97704 | JI39: =SUM(A39:JH39) -> 97704 | JJ39: 1968 | JL39: =+JI39-JK39 -> 97704
EA40: 251945 | JI40: =SUM(A40:JH40) -> 251945 | JJ40: 1969 | JL40: =+JI40-JK40 -> 251945
FT41: 132257.5 | JI41: =SUM(A41:JH41) -> 132257.5 | JJ41: 1975 | JL41: =+JI41-JK41 -> 132257.5
FB42: 664800 | JI42: =SUM(A42:JH42) -> 664800 | JJ42: 1977 | JL42: =+JI42-JK42 -> 664800
EA43: 270000 | JI43: =SUM(A43:JH43) -> 270000 | JJ43: 1982 | JL43: =+JI43-JK43 -> 270000
DK44: 234200 | JI44: =SUM(A44:JH44) -> 234200 | JJ44: 1988 | JL44: =+JI44-JK44 -> 234200
GR45: 666086.4 | JI45: =SUM(A45:JH45) -> 666086.4 | JJ45: 1989 | JL45: =+JI45-JK45 -> 666086.4
GK46: 85044.26 | GM46: 47202.36 | JI46: =SUM(A46:JH46) -> 132246.62 | JJ46: 1995 | JL46: =+JI46-JK46 -> 132246.62
W47: 45000 | JI47: =SUM(A47:JH47) -> 45000 | JJ47: 1997 | JL47: =+JI47-JK47 -> 45000
J48: 1130531 | AK48: 80154.65 | AL48: 80267.7 | AM48: 13466.76 | JI48: =SUM(A48:JH48) -> 1304420.1 | JJ48: 1999 | JL48: =+JI48-JK48 -> 1304420.1
EP49: 42480 | FM49: 144668 | FN49: 18000 | JI49: =SUM(A49:JH49) -> 205148 | JJ49: 2003 | JL49: =+JI49-JK49 -> 205148
CZ50: 413000 | JI50: =SUM(A50:JH50) -> 413000 | JJ50: 2007 | JL50: =+JI50-JK50 -> 413000
BW51: 17999.98 | JI51: =SUM(A51:JH51) -> 17999.98 | JJ51: 2011 | JL51: =+JI51-JK51 -> 17999.98
GL52: 72717.26 | IP52: 345560.94 | JI52: =SUM(A52:JH52) -> 418278.2 | JJ52: 2015 | JL52: =+JI52-JK52 -> 418278.2
CL53: 1156400 | JI53: =SUM(A53:JH53) -> 1156400 | JJ53: 2022 | JL53: =+JI53-JK53 -> 1156400
A54: 53314609 | S54: 2723298.2 | Z54: 334800 | AB54: =91955.28+168584.68 -> 260539.96 | AK54: 3780008.1 | AL54: 3785337.7 | AM54: 638567.16 | JI54: =SUM(A54:JH54) -> 64837161 | JJ54: 2024 | JL54: =+JI54-JK54 -> 64837161
FT55: 216441.5 | JI55: =SUM(A55:JH55) -> 216441.5 | JJ55: 2028 | JL55: =+JI55-JK55 -> 216441.5
AY56: 32889.84 | GB56: 38403.64 | JI56: =SUM(A56:JH56) -> 71293.48 | JJ56: 2030 | JL56: =+JI56-JK56 -> 71293.48
DV57: 7590.76 | JI57: =SUM(A57:JH57) -> 7590.76 | JJ57: 2034 | JL57: =+JI57-JK57 -> 7590.76
GJ58: 40572.73 | GP58: 135724.38 | HD58: 15963.52 | JI58: =SUM(A58:JH58) -> 192260.63 | JJ58: 2038 | JL58: =+JI58-JK58 -> 192260.63
EG59: 2699.98 | ER59: 12689.81 | FW59: 148801.03 | JI59: =SUM(A59:JH59) -> 164190.82 | JJ59: 2042 | JL59: =+JI59-JK59 -> 164190.82
GK60: 33150 | HI60: 32104.99 | JI60: =SUM(A60:JH60) -> 65254.99 | JJ60: 2046 | JL60: =+JI60-JK60 -> 65254.99
HF61: 70279.62 | JI61: =SUM(A61:JH61) -> 70279.62 | JJ61: 2052 | JL61: =+JI61-JK61 -> 70279.62
AV62: 60535 | JI62: =SUM(A62:JH62) -> 60535 | JJ62: 2056 | JL62: =+JI62-JK62 -> 60535
FJ63: 90528 | JI63: =SUM(A63:JH63) -> 90528 | JJ63: 2063 | JL63: =+JI63-JK63 -> 90528
EA64: 77000 | JI64: =SUM(A64:JH64) -> 77000 | JJ64: 2067 | JL64: =+JI64-JK64 -> 77000
HF65: 1575867.5 | JI65: =SUM(A65:JH65) -> 1575867.5 | JJ65: 2071 | JL65: =+JI65-JK65 -> 1575867.5
HF66: 1652000 | JI66: =SUM(A66:JH66) -> 1652000 | JJ66: 2075 | JL66: =+JI66-JK66 -> 1652000
GQ67: 171592.71 | JI67: =SUM(A67:JH67) -> 171592.71 | JJ67: 2080 | JL67: =+JI67-JK67 -> 171592.71
FQ68: 73089.2 | JI68: =SUM(A68:JH68) -> 73089.2 | JJ68: 2084 | JL68: =+JI68-JK68 -> 73089.2
DK69: 18195.6 | FT69: 5900 | JI69: =SUM(A69:JH69) -> 24095.6 | JJ69: 2088 | JL69: =+JI69-JK69 -> 24095.6
DW70: 266326 | JI70: =SUM(A70:JH70) -> 266326 | JJ70: 2106 | JL70: =+JI70-JK70 -> 266326
FN71: 80363.9 | JI71: =SUM(A71:JH71) -> 80363.9 | JJ71: 2110 | JL71: =+JI71-JK71 -> 80363.9
EG72: 7894.2 | FQ72: 127591.39 | JI72: =SUM(A72:JH72) -> 135485.59 | JJ72: 2115 | JL72: =+JI72-JK72 -> 135485.59
FJ73: 229790 | FS73: 7363.2 | FT73: 21948 | JI73: =SUM(A73:JH73) -> 259101.2 | JJ73: 2119 | JL73: =+JI73-JK73 -> 259101.2
EG74: 130748.55 | JI74: =SUM(A74:JH74) -> 130748.55 | JJ74: 2125 | JL74: =+JI74-JK74 -> 130748.55
EG75: 185918.91 | JI75: =SUM(A75:JH75) -> 185918.91 | JJ75: 2129 | JL75: =+JI75-JK75 -> 185918.91
DU76: 9487.2 | JI76: =SUM(A76:JH76) -> 9487.2 | JJ76: 2133 | JL76: =+JI76-JK76 -> 9487.2
EA77: 234000 | JI77: =SUM(A77:JH77) -> 234000 | JJ77: 2137 | JL77: =+JI77-JK77 -> 234000
EA78: 219000 | JI78: =SUM(A78:JH78) -> 219000 | JJ78: 2141 | JL78: =+JI78-JK78 -> 219000
FT79: 247998.24 | JI79: =SUM(A79:JH79) -> 247998.24 | JJ79: 2147 | JL79: =+JI79-JK79 -> 247998.24
FT80: 269040 | JI80: =SUM(A80:JH80) -> 269040 | JJ80: 2151 | JL80: =+JI80-JK80 -> 269040
FT81: 129664 | JI81: =SUM(A81:JH81) -> 129664 | JJ81: 2155 | JL81: =+JI81-JK81 -> 129664
FT82: 55960.32 | JI82: =SUM(A82:JH82) -> 55960.32 | JJ82: 2159 | JL82: =+JI82-JK82 -> 55960.32
EA83: 45000 | JI83: =SUM(A83:JH83) -> 45000 | JJ83: 2163 | JL83: =+JI83-JK83 -> 45000
FT84: 6289.04 | JI84: =SUM(A84:JH84) -> 6289.04 | JJ84: 2167 | JL84: =+JI84-JK84 -> 6289.04
FM85: 183031.16 | GB85: 2562.49 | JI85: =SUM(A85:JH85) -> 185593.65 | JJ85: 2171 | JL85: =+JI85-JK85 -> 185593.65
FT86: 163902 | JI86: =SUM(A86:JH86) -> 163902 | JJ86: 2175 | JL86: =+JI86-JK86 -> 163902
EA87: 7680 | FT87: 206579.64 | JI87: =SUM(A87:JH87) -> 214259.64 | JJ87: 2179 | JL87: =+JI87-JK87 -> 214259.64
JI88: =SUM(A88:JH88) -> 0 | JL88: =+JI88-JK88 -> 0
JI89: =SUM(A89:JH89) -> 0 | JL89: =+JI89-JK89 -> 0
JI90: =SUM(A90:JH90) -> 0 | JL90: =+JI90-JK90 -> 0
JI91: =SUM(A91:JH91) -> 0 | JL91: =+JI91-JK91 -> 0
JI92: =SUM(A92:JH92) -> 0 | JL92: =+JI92-JK92 -> 0
JI93: =SUM(A93:JH93) -> 0 | JL93: =+JI93-JK93 -> 0
JI94: =SUM(A94:JH94) -> 0 | JL94: =+JI94-JK94 -> 0
JI95: =SUM(A95:JH95) -> 0 | JL95: =+JI95-JK95 -> 0
JI96: =SUM(A96:JH96) -> 0 | JL96: =+JI96-JK96 -> 0
JI97: =SUM(A97:JH97) -> 0 | JL97: =+JI97-JK97 -> 0
JI98: =SUM(A98:JH98) -> 0 | JL98: =+JI98-JK98 -> 0
JI99: =SUM(A99:JH99) -> 0 | JL99: =+JI99-JK99 -> 0
... JI123: =SUM(A123:JH123) -> 0 | JL123: =+JI123-JK123 -> 0
...

Sheet CONS. FUENTES FINAN
A1: Form. No.6 SRS
A3: Servicio Nacional de Salud
A4: Dirección de Fizcalización
A5: Consolidado de Ingresos y Gastos por Fuente de Financiamiento
A6: HOSPITAL MATERNO INFANTIL SAN LORENZO DE LOS MINA
A7: MAYO 2025
C8: Ingresos Generales:
E9: 1.- Balance Inicial / Fuente:
E10: Anticipo Financiero | H10: Otros Aportes | L10: Contraseña: 0001
E11: Transferencias Corrientes
E12: Venta de Servicios | G12: 1731116.6
E13: 2.- Ingresos por Fuente / Cuenta
E14: Anticipo Financiero | G14: 0 | H14: Otros Aportes | I14: =+'INGR SEGUN ORIGEN'!E37 -> 574300 | L14: OBJETAL | M14: FR | N14: VS
E15: Transferencias Corrientes | G15: =+'INGR SEGUN ORIGEN'!E12 -> 1.003168e+08 | H15: Aportes Nomina SNS | I15: 0 | L15: 2.1 | M15: =G26 -> 66630551 | N15: =H26 -> 0
E16: Venta de Servicios | G16: =+'INGR SEGUN ORIGEN'!E29 -> 7518709.1 | L16: 2.2 | M16: =G87 -> 1680824.8 | N16: =H87 -> 2044062.6
H17: TOTAL INGRESOS RDS | I17: =+G10+G11+G12+I10+G14+G15+G16+I14+I15 -> 1.1014092e+08 | L17: 2.3 | M17: ='CONS. FUENTES FINAN'!G212 -> 16608514 | N17: ='CONS. FUENTES FINAN'!H212 -> 2557401.6
L18: 2.4 | M18: =G330 -> 0 | N18: =H330 -> 480808
L19: 2.6 | M19: =G336 -> 6580673.1 | N19: =H336 -> 3927042.2
L20: 2.7 | M20: ='CONS. FUENTES FINAN'!G463 -> 0 | N20: ='CONS. FUENTES FINAN'!H463 -> 0
A21: 1 | F21: 2 | G21: 3 | I21: 4 | J21: 5
A22: Código Presupuestario | F22: Descripción Gasto por Cuenta | G22: Distribución del Gasto por Fuente de Financiamiento | I22: TOTAL | J22: %
A23: Tipo | B23: Objeto | C23: Cuenta | D23: Sub-Cuenta | E23: Auxiliar | G23: Fondo 100 | H23: Venta de Servicios/ Otros Aportes
A25: 2 | F25: Gastos | G25: =+G26+G87+G212+G330+G336+G463 -> 91500562 | H25: =+H26+H87+H212+H330+H336+H463 -> 9009314.4 | I25: =SUM(G25:H25) -> 1.0050988e+08 | J25: =+J26+J87+J212+J330+J336+J463 -> 1
A26: 2 | B26: 1 | F26: Servicios Personales | G26: =+G27+G51+G64+G71+G78 -> 66630551 | H26: =+H27+H51+H64+H71+H78 -> 0 | I26: =SUM(G26:H26) -> 66630551 | J26: =I26/$I$25 -> 0.66292541
A27: 2 | B27: 1 | C27: 1 | F27: Remuneraciones | G27: =+G28+G35+G42+G44+G46 -> 54445140 | H27: =+H28+H35+H42+H44+H46 -> 0 | I27: =SUM(G27:H27) -> 54445140 | J27: =I27/$I$25 -> 0.54168946
A28: 2 | B28: 1 | C28: 1 | D28: 1 | F28: Remuneraciones al personal fijo | G28: =SUM(G29:G34) -> 53314609 | H28: =SUM(H29:H34) -> 0 | I28: =SUM(G28:H28) -> 53314609 | J28: =I28/$I$25 -> 0.5304415
A29: 2 | B29: 1 | C29: 1 | D29: 1 | E29: 01 | F29: Sueldos a empleados fijos | G29: ='CUENTA T FONDO 100'!A126 -> 53314609 | H29: ='CUENTA T VS'!A106 -> 0 | I29: =SUM(G29:H29) -> 53314609 | J29: =I29/$I$25 -> 0.5304415
A30: 2 | B30: 1 | C30: 1 | D30: 1 | E30: 02 | F30: Sueldos a médicos | G30: ='CUENTA T FONDO 100'!B126 -> 0 | H30: ='CUENTA T VS'!B106 -> 0 | I30: =SUM(G30:H30) -> 0 | J30: =I30/$I$25 -> 0
A31: 2 | B31: 1 | C31: 1 | D31: 1 | E31: 03 | F31: Ascensos a militares | G31: ='CUENTA T FONDO 100'!C126 -> 0 | H31: ='CUENTA T VS'!C106 -> 0 | I31: =SUM(G31:H31) -> 0 | J31: =I31/$I$25 -> 0
A32: 2 | B32: 1 | C32: 1 | D32: 1 | E32: 04 | F32: Nuevas plazas maestros | G32: ='CUENTA T FONDO 100'!D126 -> 0 | H32: ='CUENTA T VS'!D106 -> 0 | I32: =SUM(G32:H32) -> 0 | J32: =I32/$I$25 -> 0
A33: 2 | B33: 1 | C33: 1 | D33: 1 | E33: 05 | F33: Incentivos y escalafón | G33: ='CUENTA T FONDO 100'!E126 -> 0 | H33: ='CUENTA T VS'!E106 -> 0 | I33: =SUM(G33:H33) -> 0 | J33: =I33/$I$25 -> 0
A34: 2 | B34: 1 | C34: 1 | D34: 1 | E34: 06 | F34: Nuevas plazas a médicos | G34: ='CUENTA T FONDO 100'!F126 -> 0 | H34: ='CUENTA T VS'!F106 -> 0 | I34: =SUM(G34:H34) -> 0 | J34: =I34/$I$25 -> 0
A35: 2 | B35: 1 | C35: 1 | D35: 2 | F35: Remuneraciones al personal con carácter transitorio | G35: =SUM(G36:G41) -> 1130531 | H35: =SUM(H36:H41) -> 0 | I35: =SUM(G35:H35) -> 1130531
A36: 2 | B36: 1 | C36: 1 | D36: 2 | E36: 03 | F36: Suplencias | G36: ='CUENTA T FONDO 100'!G126 -> 0 | H36: ='CUENTA T VS'!G106 -> 0 | I36: =SUM(G36:H36) -> 0 | J36: =I36/$I$25 -> 0
A37: 2 | B37: 1 | C37: 1 | D37: 2 | E37: 05 | F37: Sueldo al personal nominal en período probatorio | G37: ='CUENTA T FONDO 100'!H126 -> 0 | H37: ='CUENTA T VS'!H106 -> 0 | I37: =SUM(G37:H37) -> 0 | J37: =I37/$I$25 -> 0
A38: 2 | B38: 1 | C38: 1 | D38: 2 | E38: 06 | F38: Jornales | G38: ='CUENTA T FONDO 100'!I126 -> 0 | H38: ='CUENTA T VS'!I106 -> 0 | I38: =SUM(G38:H38) -> 0 | J38: =I38/$I$25 -> 0
A39: 2 | B39: 1 | C39: 1 | D39: 2 | E39: 08 | F39: Empleados temporales | G39: ='CUENTA T FONDO 100'!J126 -> 1130531 | H39: ='CUENTA T VS'!J106 -> 0 | I39: =SUM(G39:H39) -> 1130531 | J39: =I39/$I$25 -> 0.01124796
A40: 2 | B40: 1 | C40: 1 | D40: 2 | E40: 09 | F40: Personal de carácter eventual | G40: ='CUENTA T FONDO 100'!K126 -> 0 | H40: ='CUENTA T VS'!K106 -> 0 | I40: =SUM(G40:H40) -> 0 | J40: =I40/$I$25 -> 0
A41: 2 | B41: 1 | C41: 1 | D41: 2 | E41: 11 | F41: Interinato | G41: ='CUENTA T FONDO 100'!L126 -> 0 | H41: ='CUENTA T VS'!L106 -> 0 | I41: =SUM(G41:H41) -> 0 | J41: =I41/$I$25 -> 0
A42: 2 | B42: 1 | C42: 1 | D42: 3 | F42: Sueldos al personal fijo en trámite de pensiones | G42: =SUM(G43) -> 0 | H42: =SUM(H43) -> 0 | I42: =SUM(G42:H42) -> 0
A43: 2 | B43: 1 | C43: 1 | D43: 3 | E43: 01 | F43: Sueldos al personal fijo en trámite de pensiones | G43: ='CUENTA T FONDO 100'!M126 -> 0 | H43: ='CUENTA T VS'!M106 -> 0 | I43: =SUM(G43:H43) -> 0 | J43: =I43/$I$25 -> 0
A44: 2 | B44: 1 | C44: 1 | D44: 4 | F44: Sueldo anual no. 13 | G44: =SUM(G45) -> 0 | H44: =SUM(H45) -> 0 | I44: =SUM(G44:H44) -> 0
A45: 2 | B45: 1 | C45: 1 | D45: 4 | E45: 01 | F45: Sueldo anual no. 13 | G45: ='CUENTA T FONDO 100'!N126 -> 0 | H45: ='CUENTA T VS'!N106 -> 0 | I45: =SUM(G45:H45) -> 0 | J45: =I45/$I$25 -> 0
A46: 2 | B46: 1 | C46: 1 | D46: 5 | F46: Prestaciones económinas | G46: =SUM(G47:G50) -> 0 | H46: =SUM(H47:H50) -> 0 | I46: =SUM(G46:H46) -> 0
A47: 2 | B47: 1 | C47: 1 | D47: 5 | E47: 01 | F47: Prestaciones económinas | G47: ='CUENTA T FONDO 100'!O126 -> 0 | H47: ='CUENTA T VS'!O106 -> 0 | I47: =SUM(G47:H47) -> 0 | J47: =I47/$I$25 -> 0
A48: 2 | B48: 1 | C48: 1 | D48: 5 | E48: 02 | F48: Pago de porcentaje por desvinculación de cargo | G48: ='CUENTA T FONDO 100'!P126 -> 0 | H48: ='CUENTA T VS'!P106 -> 0 | I48: =SUM(G48:H48) -> 0 | J48: =I48/$I$25 -> 0
A49: 2 | B49: 1 | C49: 1 | D49: 5 | E49: 03 | F49: Prestación laboral por desvinculación | G49: ='CUENTA T FONDO 100'!Q126 -> 0 | H49: ='CUENTA T VS'!Q106 -> 0 | I49: =SUM(G49:H49) -> 0 | J49: =I49/$I$25 -> 0
A50: 2 | B50: 1 | C50: 1 | D50: 5 | E50: 04 | F50: Proporción de vacaciones no disfrutadas | G50: ='CUENTA T FONDO 100'!R126 -> 0 | H50: ='CUENTA T VS'!R106 -> 0 | I50: =SUM(G50:H50) -> 0 | J50: =I50/$I$25 -> 0
A51: 2 | B51: 1 | C51: 2 | F51: Sobresueldos | G51: =+G52+G54 -> 3807608.3 | H51: =+H52+H54 -> 0 | I51: =SUM(G51:H51) -> 3807608.3
A52: 2 | B52: 1 | C52: 2 | D52: 1 | F52: Primas por antigüedad | G52: =SUM(G53) -> 2723298.2 | H52: =SUM(H53) -> 0 | I52: =SUM(G52:H52) -> 2723298.2
A53: 2 | B53: 1 | C53: 2 | D53: 1 | E53: 01 | F53: Primas por antigüedad | G53: ='CUENTA T FONDO 100'!S126 -> 2723298.2 | H53: ='CUENTA T VS'!S106 -> 0 | I53: =SUM(G53:H53) -> 2723298.2 | J53: =I53/$I$25 -> 0.027094832
A54: 2 | B54: 1 | C54: 2 | D54: 2 | F54: Compensación | G54: =SUM(G55:G63) -> 1084310.1 | H54: =SUM(H55:H63) -> 0 | I54: =SUM(G54:H54) -> 1084310.1
A55: 2 | B55: 1 | C55: 2 | D55: 2 | E55: 01 | F55: Compensación por gastos de alimentación | G55: ='CUENTA T FONDO 100'!T126 -> 0 | H55: ='CUENTA T VS'!T106 -> 0 | I55: =SUM(G55:H55) -> 0 | J55: =I55/$I$25 -> 0
A56: 2 | B56: 1 | C56: 2 | D56: 2 | E56: 03 | F56: Pago de horas extraordinarias | G56: ='CUENTA T FONDO 100'!U126 -> 0 | H56: ='CUENTA T VS'!U106 -> 0 | I56: =SUM(G56:H56) -> 0 | J56: =I56/$I$25 -> 0
A57: 2 | B57: 1 | C57: 2 | D57: 2 | E57: 04 | F57: Prima de transporte | G57: ='CUENTA T FONDO 100'!V126 -> 0 | H57: ='CUENTA T VS'!V106 -> 0 | I57: =SUM(G57:H57) -> 0 | J57: =I57/$I$25 -> 0
A58: 2 | B58: 1 | C58: 2 | D58: 2 | E58: 05 | F58: Compensación servicios de Seguridad | G58: ='CUENTA T FONDO 100'!W126 -> 45000 | H58: ='CUENTA T VS'!W106 -> 0 | I58: =SUM(G58:H58) -> 45000 | J58: =I58/$I$25 -> 0.00044771719
A59: 2 | B59: 1 | C59: 2 | D59: 2 | E59: 06 | F59: Incentivo por Rendimieto Individual | G59: ='CUENTA T FONDO 100'!X126 -> 0 | H59: ='CUENTA T VS'!X106 -> 0 | I59: =SUM(G59:H59) -> 0 | J59: =I59/$I$25 -> 0
A60: 2 | B60: 1 | C60: 2 | D60: 2 | E60: 07 | F60: Compensación por distancia | G60: ='CUENTA T FONDO 100'!Y126 -> 0 | H60: ='CUENTA T VS'!Y106 -> 0 | I60: =SUM(G60:H60) -> 0 | J60: =I60/$I$25 -> 0
A61: 2 | B61: 1 | C61: 2 | D61: 2 | E61: 08 | F61: Compensaciones especiales | G61: ='CUENTA T FONDO 100'!Z126 -> 334800 | H61: ='CUENTA T VS'!Z106 -> 0 | I61: =SUM(G61:H61) -> 334800 | J61: =I61/$I$25 -> 0.0033310159
A62: 2 | B62: 1 | C62: 2 | D62: 2 | E62: 09 | F62: Bono por desempeño a servidores de carrera | G62: ='CUENTA T FONDO 100'!AA126 -> 443970.11 | H62: ='CUENTA T VS'!AA106 -> 0 | I62: =SUM(G62:H62) -> 443970.11 | J62: =I62/$I$25 -> 0.0044171789
A63: 2 | B63: 1 | C63: 2 | D63: 2 | E63: 10 | F63: Compensacion por cumplimiento de indicadores | G63: ='CUENTA T FONDO 100'!AB126 -> 260539.96 | H63: ='CUENTA T VS'!AB106 -> 0 | I63: =SUM(G63:H63) -> 260539.96 | J63: =I63/$I$25 -> 0.0025921827
A64: 2 | B64: 1 | C64: 3 | F64: Dietas y Gastos de Representación | G64: =+G65+G68 -> 0 | H64: =+H65+H68 -> 0 | I64: =SUM(G64:H64) -> 0
A65: 2 | B65: 1 | C65: 3 | D65: 1 | F65: Dietas | G65: =SUM(G66:G67) -> 0 | H65: =SUM(H66:H67) -> 0 | I65: =SUM(G65:H65) -> 0
A66: 2 | B66: 1 | C66: 3 | D66: 1 | E66: 01 | F66: Dietas en el país | G66: ='CUENTA T FONDO 100'!AC126 -> 0 | H66: ='CUENTA T VS'!AC106 -> 0 | I66: =SUM(G66:H66) -> 0 | J66: =I66/$I$25 -> 0
A67: 2 | B67: 1 | C67: 3 | D67: 1 | E67: 02 | F67: Dietas en el exterior | G67: ='CUENTA T FONDO 100'!AD126 -> 0 | H67: ='CUENTA T VS'!AD106 -> 0 | I67: =SUM(G67:H67) -> 0 | J67: =I67/$I$25 -> 0
A68: 2 | B68: 1 | C68: 3 | D68: 2 | F68: Gastos de representación | G68: =SUM(G69:G70) -> 0 | H68: =SUM(H69:H70) -> 0 | I68: =SUM(G68:H68) -> 0
A69: 2 | B69: 1 | C69: 3 | D69: 2 | E69: 01 | F69: Gastos de representación en el país | G69: ='CUENTA T FONDO 100'!AE126 -> 0 | H69: ='CUENTA T VS'!AE106 -> 0 | I69: =SUM(G69:H69) -> 0 | J69: =I69/$I$25 -> 0
A70: 2 | B70: 1 | C70: 3 | D70: 2 | E70: 02 | F70: Gastos de representación en el exterior | G70: ='CUENTA T FONDO 100'!AF126 -> 0 | H70: ='CUENTA T VS'!AF106 -> 0 | I70: =SUM(G70:H70) -> 0 | J70: =I70/$I$25 -> 0
A71: 2 | B71: 1 | C71: 4 | F71: Gratificaciones y Bonificaciones | G71: =+G72+G74 -> 0 | H71: =+H72+H74 -> 0 | I71: =SUM(G71:H71) -> 0
A72: 2 | B72: 1 | C72: 4 | D72: 1 | F72: Bonificaciones | G72: =SUM(G73) -> 0 | H72: =SUM(H73) -> 0 | I72: =SUM(G72:H72) -> 0
A73: 2 | B73: 1 | C73: 4 | D73: 1 | E73: 01 | F73: Bonificaciones | G73: ='CUENTA T FONDO 100'!AG126 -> 0 | H73: ='CUENTA T VS'!AG106 -> 0 | I73: =SUM(G73:H73) -> 0 | J73: =I73/$I$25 -> 0
A74: 2 | B74: 1 | C74: 4 | D74: 2 | F74: Otras Gratificaciones y Bonificaciones | G74: =SUM(G75:G77) -> 0 | H74: =SUM(H75:H77) -> 0 | I74: =SUM(G74:H74) -> 0
A75: 2 | B75: 1 | C75: 4 | D75: 2 | E75: 01 | F75: Bono escolar | G75: ='CUENTA T FONDO 100'!AH126 -> 0 | H75: ='CUENTA T VS'!AH106 -> 0 | I75: =SUM(G75:H75) -> 0 | J75: =I75/$I$25 -> 0
A76: 2 | B76: 1 | C76: 4 | D76: 2 | E76: 02 | F76: Gratificaciones por pasantías | G76: ='CUENTA T FONDO 100'!AI126 -> 0 | H76: ='CUENTA T VS'!AI106 -> 0 | I76: =SUM(G76:H76) -> 0 | J76: =I76/$I$25 -> 0
A77: 2 | B77: 1 | C77: 4 | D77: 2 | E77: 03 | F77: Gratificaciones por aniversario de institución | G77: ='CUENTA T FONDO 100'!AJ126 -> 0 | H77: ='CUENTA T VS'!AJ106 -> 0 | I77: =SUM(G77:H77) -> 0 | J77: =I77/$I$25 -> 0
A78: 2 | B78: 1 | C78: 5 | F78: Contribuciones a la Seguridad Social y Riesgo Laboral | G78: =+G79+G81+G83+G85 -> 8377802.1 | H78: =+H79+H81+H83+H85 -> 0 | I78: =SUM(G78:H78) -> 8377802.1
A79: 2 | B79: 1 | C79: 5 | D79: 1 | F79: Contribuciones al seguro de salud | G79: =SUM(G80) -> 3860162.8 | H79: =SUM(H80) -> 0 | I79: =SUM(G79:H79) -> 3860162.8
A80: 2 | B80: 1 | C80: 5 | D80: 1 | E80: 01 | F80: Contribuciones al seguro de salud | G80: ='CUENTA T FONDO 100'!AK126 -> 3860162.8 | H80: ='CUENTA T VS'!AK106 -> 0 | I80: =SUM(G80:H80) -> 3860162.8 | J80: =I80/$I$25 -> 0.038405805
A81: 2 | B81: 1 | C81: 5 | D81: 2 | F81: Contribuciones al seguro de pensiones | G81: =SUM(G82) -> 3865605.4 | H81: =SUM(H82) -> 0 | I81: =SUM(G81:H81) -> 3865605.4
A82: 2 | B82: 1 | C82: 5 | D82: 2 | E82: 01 | F82: Contribuciones al seguro de pensiones | G82: ='CUENTA T FONDO 100'!AL126 -> 3865605.4 | H82: ='CUENTA T VS'!AL106 -> 0 | I82: =SUM(G82:H82) -> 3865605.4 | J82: =I82/$I$25 -> 0.038459956
A83: 2 | B83: 1 | C83: 5 | D83: 3 | F83: Contribuciones al seguro de riesgo laboral | G83: =SUM(G84) -> 652033.92 | H83: =SUM(H84) -> 0 | I83: =SUM(G83:H83) -> 652033.92
A84: 2 | B84: 1 | C84: 5 | D84: 3 | E84: 01 | F84: Contribuciones al seguro de riesgo laboral | G84: ='CUENTA T FONDO 100'!AM126 -> 652033.92 | H84: ='CUENTA T VS'!AM106 -> 0 | I84: =SUM(G84:H84) -> 652033.92 | J84: =I84/$I$25 -> 0.0064872622
A85: 2 | B85: 1 | C85: 5 | D85: 4 | F85: Contribuciones al plan de retiro complementario | G85: =SUM(G86) -> 0 | H85: =SUM(H86) -> 0 | I85: =SUM(G85:H85) -> 0
A86: 2 | B86: 1 | C86: 5 | D86: 4 | E86: 01 | F86: Contribuciones al plan de retiro complementario | G86: ='CUENTA T FONDO 100'!AN126 -> 0 | H86: ='CUENTA T VS'!AN106 -> 0 | I86: =SUM(G86:H86) -> 0 | J86: =I86/$I$25 -> 0
A87: 2 | B87: 2 | F87: Servicios No Personales | G87: =G88+G106+G111+G116+G125+G148+G157+G179+G208 -> 1680824.8 | H87: =H88+H106+H111+H116+H125+H148+H157+H179+H208 -> 2044062.6 | I87: =SUM(G87:H87) -> 3724887.4 | J87: =I87/$I$25 -> 0.037059914
A88: 2 | B88: 2 | C88: 1 | F88: Servicios Básicos | G88: =+G89+G91+G93+G95+G97+G99+G102+G104 -> 60535 | H88: =+H89+H91+H93+H95+H97+H99+H102+H104 -> 1098463.4 | I88: =SUM(G88:H88) -> 1158998.4
A89: 2 | B89: 2 | C89: 1 | D89: 1 | F89: Radiocomunicación | G89: =SUM(G90) -> 0 | H89: =SUM(H90) -> 0 | I89: =SUM(G89:H89) -> 0
A90: 2 | B90: 2 | C90: 1 | D90: 1 | E90: 01 | F90: Radiocomunicación | G90: ='CUENTA T FONDO 100'!AO126 -> 0 | H90: ='CUENTA T VS'!AO106 -> 0 | I90: =SUM(G90:H90) -> 0 | J90: =I90/$I$25 -> 0
A91: 2 | B91: 2 | C91: 1 | D91: 2 | F91: Servicios telefónico de larga distancia | G91: =SUM(G92) -> 0 | H91: =SUM(H92) -> 0 | I91: =SUM(G91:H91) -> 0
A92: 2 | B92: 2 | C92: 1 | D92: 2 | E92: 01 | F92: Servicios telefónico de larga distancia | G92: ='CUENTA T FONDO 100'!AP126 -> 0 | H92: ='CUENTA T VS'!AP106 -> 0 | I92: =SUM(G92:H92) -> 0 | J92: =I92/$I$25 -> 0
A93: 2 | B93: 2 | C93: 1 | D93: 3 | F93: Teléfono local | G93: =SUM(G94) -> 0 | H93: =SUM(H94) -> 209036.41 | I93: =SUM(G93:H93) -> 209036.41
A94: 2 | B94: 2 | C94: 1 | D94: 3 | E94: 01 | F94: Teléfono local | G94: ='CUENTA T FONDO 100'!AQ126 -> 0 | H94: ='CUENTA T VS'!AQ106 -> 209036.41 | I94: =SUM(G94:H94) -> 209036.41 | J94: =I94/$I$25 -> 0.0020797599
A95: 2 | B95: 2 | C95: 1 | D95: 4 | F95: Telefax y correos | G95: =SUM(G96) -> 0 | H95: =SUM(H96) -> 0 | I95: =SUM(G95:H95) -> 0
A96: 2 | B96: 2 | C96: 1 | D96: 4 | E96: 01 | F96: Telefax y correos | G96: ='CUENTA T FONDO 100'!AR126 -> 0 | H96: ='CUENTA T VS'!AR106 -> 0 | I96: =SUM(G96:H96) -> 0 | J96: =I96/$I$25 -> 0
A97: 2 | B97: 2 | C97: 1 | D97: 5 | F97: Servicio de Internet y televisión por cable | G97: =SUM(G98) -> 0 | H97: =SUM(H98) -> 104427.01 | I97: =SUM(G97:H97) -> 104427.01
A98: 2 | B98: 2 | C98: 1 | D98: 5 | E98: 01 | F98: Servicio de Internet y televisión por cable | G98: ='CUENTA T FONDO 100'!AS126 -> 0 | H98: ='CUENTA T VS'!AS106 -> 104427.01 | I98: =SUM(G98:H98) -> 104427.01 | J98: =I98/$I$25 -> 0.0010389726
A99: 2 | B99: 2 | C99: 1 | D99: 6 | F99: Electricidad | G99: =SUM(G100:G101) -> 0 | H99: =SUM(H100:H101) -> 0 | I99: =SUM(G99:H99) -> 0
A100: 2 | B100: 2 | C100: 1 | D100: 6 | E100: 01 | F100: Energía eléctrica | G100: ='CUENTA T FONDO 100'!AT126 -> 0 | H100: ='CUENTA T VS'!AT106 -> 0 | I100: =SUM(G100:H100) -> 0 | J100: =I100/$I$25 -> 0
A101: 2 | B101: 2 | C101: 1 | D101: 6 | E101: 02 | F101: Electricidad no cortable | G101: ='CUENTA T FONDO 100'!AU126 -> 0 | H101: ='CUENTA T VS'!AU106 -> 0 | I101: =SUM(G101:H101) -> 0 | J101: =I101/$I$25 -> 0
A102: 2 | B102: 2 | C102: 1 | D102: 7 | F102: Agua | G102: =SUM(G103) -> 60535 | H102: =SUM(H103) -> 0 | I102: =SUM(G102:H102) -> 60535
...

Sheet GASTOS X ATENCION
A1: SERVICIO NACIONAL DE SALUD
A2: ='CONS. FUENTES FINAN'!A6 -> HOSPITAL MATERNO INFANTIL SAN LORENZO DE LOS MINA
A3: RESUMEN COMPARATIVO DE GASTOS ESPECIFICOS FONDO 100 Y VENTA DE SERVICIOS
A6: DETALLE | B6: FONDO 100 | C6: VENTA SERVICIOS | D6: TOTAL | E6: %
A8: Atención Directa
A9: Medicamentos e Insumos Médicos | B9: ='CONS. FUENTES FINAN'!G245+'CONS. FUENTES FINAN'!G315 -> 8317198.8 | C9: ='CONS. FUENTES FINAN'!H245+'CONS. FUENTES FINAN'!H315 -> 238984.2 | D9: =SUM(B9:C9) -> 8556183 | E9: =+D9/D12 -> 0.76593676
A10: Oxigeno | B10: ='CONS. FUENTES FINAN'!G302 -> 113956.7 | C10: ='CONS. FUENTES FINAN'!H302 -> 0 | D10: =SUM(B10:C10) -> 113956.7 | E10: =+D10/D12 -> 0.010201234
A11: Reactivos e Insumos de Laboratorio | B11: ='CONS. FUENTES FINAN'!G296+'CONS. FUENTES FINAN'!G297+'CONS. FUENTES FINAN'!G298 -> 1653884.3 | C11: ='CONS. FUENTES FINAN'!H296+'CONS. FUENTES FINAN'!H297+'CONS. FUENTES FINAN'!H298 -> 846850 | D11: =SUM(B11:C11) -> 2500734.3 | E11: =+D11/D12 -> 0.22386201
A12: Total | B12: =SUM(B9:B11) -> 10085040 | C12: =SUM(C9:C11) -> 1085834.2 | D12: =SUM(D9:D11) -> 11170874 | E12: =+D12/D39 -> 0.11114205
A13: Mantenimiento de Equipos
A14: Reparación y Mantenimiento Maquinaria y Eq. | B14: ='CONS. FUENTES FINAN'!G157+'CONS. FUENTES FINAN'!G188+'CONS. FUENTES FINAN'!G223+'CONS. FUENTES FINAN'!G252+'CONS. FUENTES FINAN'!G254+'CONS. FUENTES FINAN'!G256+'CONS. FUENTES FINAN'!G258+'CONS. FUENTES FINAN'!G261+'CONS. FUENTES FINAN'!G292+'CONS. FUENTES FINAN'!G293+'CONS. FUENTES FINAN'!G299+'CONS. FUENTES FINAN'!G300+'CONS. FUENTES FINAN'!G301+'CONS. FUENTES FINAN'!G324 -> 1717277 | C14: ='CONS. FUENTES FINAN'!H157+'CONS. FUENTES FINAN'!H188+'CONS. FUENTES FINAN'!H223+'CONS. FUENTES FINAN'!H252+'CONS. FUENTES FINAN'!H254+'CONS. FUENTES FINAN'!H256+'CONS. FUENTES FINAN'!H258+'CONS. FUENTES FINAN'!H261+'CONS. FUENTES FINAN'!H292+'CONS. FUENTES FINAN'!H293+'CONS. FUENTES FINAN'!H299+'CONS. FUENTES FINAN'!H300+'CONS. FUENTES FINAN'!H301+'CONS. FUENTES FINAN'!H324 -> 297915.54 | D14: =SUM(B14:C14) -> 2015192.5 | E14: =+D14/D16 -> 0.93123777
A15: Productos Eléctricos y Afines | B15: ='CONS. FUENTES FINAN'!G320 -> 148801.03 | C15: ='CONS. FUENTES FINAN'!H320 -> 0 | D15: =SUM(B15:C15) -> 148801.03 | E15: =+D15/D16 -> 0.068762235
A16: Total | B16: =SUM(B14:B15) -> 1866078 | C16: =SUM(C14:C15) -> 297915.54 | D16: =SUM(D14:D15) -> 2163993.5 | E16: =+D16/D39 -> 0.021530158
A17: Gastos Administrativos
A18: Servicios Personales | B18: ='CONS. FUENTES FINAN'!G26 -> 66630551 | C18: ='CONS. FUENTES FINAN'!H26 -> 0 | D18: =SUM(B18:C18) -> 66630551 | E18: =+D18/D34 -> 0.86908703
A19: Servicio Telefónico | B19: ='CONS. FUENTES FINAN'!G91+'CONS. FUENTES FINAN'!G93+'CONS. FUENTES FINAN'!G95+'CONS. FUENTES FINAN'!G97 -> 0 | C19: ='CONS. FUENTES FINAN'!H91+'CONS. FUENTES FINAN'!H93+'CONS. FUENTES FINAN'!H95+'CONS. FUENTES FINAN'!H97 -> 313463.42 | D19: =SUM(B19:C19) -> 313463.42 | E19: =+D19/D34 -> 0.0040886199
A20: Servicios Basicos (electricidad, agua y residuos solidos) | B20: ='CONS. FUENTES FINAN'!G99+'CONS. FUENTES FINAN'!G102+'CONS. FUENTES FINAN'!G104 -> 60535 | C20: ='CONS. FUENTES FINAN'!H99+'CONS. FUENTES FINAN'!H102+'CONS. FUENTES FINAN'!H104 -> 785000 | D20: =SUM(B20:C20) -> 845535 | E20: =+D20/D34 -> 0.011028627
A21: Viáticos | B21: ='CONS. FUENTES FINAN'!G111 -> 0 | C21: ='CONS. FUENTES FINAN'!H111 -> 0 | D21: =SUM(B21:C21) -> 0 | E21: =+D21/D34 -> 0
A22: Transporte y almacenaje | B22: ='CONS. FUENTES FINAN'!G116 -> 0 | C22: ='CONS. FUENTES FINAN'!H116 -> 76000 | D22: =SUM(B22:C22) -> 76000 | E22: =+D22/D34 -> 0.00099129624
A23: Alquileres | B23: ='CONS. FUENTES FINAN'!G125 -> 0 | C23: ='CONS. FUENTES FINAN'!H125 -> 529650.64 | D23: =SUM(B23:C23) -> 529650.64 | E23: =+D23/D34 -> 0.0069084301
A24: Comisiones y Gastos Bancarios | B24: ='CONS. FUENTES FINAN'!G182 -> 0 | C24: ='CONS. FUENTES FINAN'!H182 -> 0 | D24: =SUM(B24:C24) -> 0 | E24: =+D24/D34 -> 0
A25: Materiales de Oficina, Impresión y Encuadernación | B25: ='CONS. FUENTES FINAN'!G109+'CONS. FUENTES FINAN'!G312 -> 40253.04 | C25: ='CONS. FUENTES FINAN'!H109+'CONS. FUENTES FINAN'!H312 -> 0 | D25: =SUM(B25:C25) -> 40253.04 | E25: =+D25/D34 -> 0.00052503536
A26: Alimentos y Bebidas para Personas | B26: ='CONS. FUENTES FINAN'!G208+'CONS. FUENTES FINAN'!G214+'CONS. FUENTES FINAN'!G217+'CONS. FUENTES FINAN'!G219 -> 1657538.8 | C26: ='CONS. FUENTES FINAN'!H208+'CONS. FUENTES FINAN'!H214+'CONS. FUENTES FINAN'!H217+'CONS. FUENTES FINAN'!H219 -> 355075 | D26: =SUM(B26:C26) -> 2012613.8 | E26: =+D26/D34 -> 0.02625127
A27: Productos de papel, carton e impesos | B27: ='CONS. FUENTES FINAN'!G232 -> 765138.96 | C27: ='CONS. FUENTES FINAN'!H232 -> 607165 | D27: =SUM(B27:C27) -> 1372304 | E27: =+D27/D34 -> 0.01789947
A28: Articulos de Plasticos | B28: ='CONS. FUENTES FINAN'!G259 -> 384413.08 | C28: ='CONS. FUENTES FINAN'!H259 -> 0 | D28: =SUM(B28:C28) -> 384413.08 | E28: =+D28/D34 -> 0.0050140426
A29: Gasolina | B29: ='CONS. FUENTES FINAN'!G288 -> 1649337.3 | C29: ='CONS. FUENTES FINAN'!H288 -> 172000 | D29: =SUM(B29:C29) -> 1821337.3 | E29: =+D29/D34 -> 0.023756379
A30: Gasoil | B30: ='CONS. FUENTES FINAN'!G289+'CONS. FUENTES FINAN'!G290 -> 664800 | C30: ='CONS. FUENTES FINAN'!H289+'CONS. FUENTES FINAN'!H290 -> 0 | D30: =SUM(B30:C30) -> 664800 | E30: =+D30/D34 -> 0.0086712334
A31: GLP | B31: ='CONS. FUENTES FINAN'!G291+'CONS. FUENTES FINAN'!G294 -> 0 | C31: ='CONS. FUENTES FINAN'!H291+'CONS. FUENTES FINAN'!H294 -> 47073 | D31: =SUM(B31:C31) -> 47073 | E31: =+D31/D34 -> 0.00061399063
A32: Materiales de Limpieza e Higiene | B32: ='CONS. FUENTES FINAN'!G309 -> 662238.29 | C32: ='CONS. FUENTES FINAN'!H309 -> 98506.4 | D32: =SUM(B32:C32) -> 760744.69 | E32: =+D32/D34 -> 0.0099226756
A33: Otros Egresos y Gastos | B33: ='CONS. FUENTES FINAN'!G89+'CONS. FUENTES FINAN'!G107+'CONS. FUENTES FINAN'!G148+'CONS. FUENTES FINAN'!G180+'CONS. FUENTES FINAN'!G184+'CONS. FUENTES FINAN'!G186+'CONS. FUENTES FINAN'!G192+'CONS. FUENTES FINAN'!G197+'CONS. FUENTES FINAN'!G204+'CONS. FUENTES FINAN'!G225+'CONS. FUENTES FINAN'!G303+'CONS. FUENTES FINAN'!G316+'CONS. FUENTES FINAN'!G318+'CONS. FUENTES FINAN'!G322+'CONS. FUENTES FINAN'!G327+'CONS. FUENTES FINAN'!G330 -> 453966.13 | C33: ='CONS. FUENTES FINAN'!H89+'CONS. FUENTES FINAN'!H107+'CONS. FUENTES FINAN'!H148+'CONS. FUENTES FINAN'!H180+'CONS. FUENTES FINAN'!H184+'CONS. FUENTES FINAN'!H186+'CONS. FUENTES FINAN'!H192+'CONS. FUENTES FINAN'!H197+'CONS. FUENTES FINAN'!H204+'CONS. FUENTES FINAN'!H225+'CONS. FUENTES FINAN'!H303+'CONS. FUENTES FINAN'!H316+'CONS. FUENTES FINAN'!H318+'CONS. FUENTES FINAN'!H322+'CONS. FUENTES FINAN'!H327+'CONS. FUENTES FINAN'!H330 -> 714589 | D33: =SUM(B33:C33) -> 1168555.1 | E33: =+D33/D34 -> 0.015241899
A34: Total | B34: =SUM(B17:B33) -> 72968771 | C34: =SUM(C17:C33) -> 3698522.5 | D34: =SUM(D17:D33) -> 76667294 | E34: =+D34/D39 -> 0.76278368
A35: Gastos Inversion y Capital
A36: Bienes Muebles, Inmuebles e Intangibles | B36: ='CONS. FUENTES FINAN'!G336 -> 6580673.1 | C36: ='CONS. FUENTES FINAN'!H336 -> 3927042.2 | D36: =SUM(B36:C36) -> 10507715 | E36: =+D36/D38 -> 1
A37: Obras | B37: ='CONS. FUENTES FINAN'!G463 -> 0 | C37: ='CONS. FUENTES FINAN'!H463 -> 0 | D37: =SUM(B37:C37) -> 0 | E37: =+D37/D38 -> 0
A38: Total | B38: =SUM(B36:B37) -> 6580673.1 | C38: =SUM(C36:C37) -> 3927042.2 | D38: =SUM(D36:D37) -> 10507715 | E38: =+D38/D39 -> 0.10454411
A39: Total General | B39: =+B12+B16+B34+B38 -> 91500562 | C39: =+C12+C16+C34+C38 -> 9009314.4 | D39: =+D12+D16+D34+D38 -> 1.0050988e+08 | E39: =+E12+E16+E34+E38 -> 1
A40: Porciento | B40: =+B39/D39 -> 0.91036389 | C40: =+C39/D39 -> 0.08963611 | D40: =+B40+C40 -> 1

Sheet PLANTILLA PRESUPUESTO
A1: SERVICIO NACIONAL DE SALUD
A2: HOSPITAL MATERNO INFANTIL SAN LORENZO DE LOS MINA
A3: CONSOLIDADO GASTOS EJECUCION FINANCIERA 2025
A4: En RD$
A6: Detalle | B6: FONDO REPONIBLE | G6: VENTA SEVICIOS/OTROS APORTES | L6: TOTAL
A7: 2 - GASTOS | B7: 1ro | C7: 2do | D7: 3ro | E7: 4to | G7: 1ro | H7: 2do | I7: 3ro | J7: 4to | L7: 1ro | M7: 2do | N7: 3ro | O7: 4to
A8: 2.1 - REMUNERACIONES Y CONTRIBUCIONES | B8: =SUM(B9:B13) -> 1.9856074e+08 | C8: =SUM(C9:C13) -> 1.3318671e+08 | D8: =SUM(D9:D13) -> 0 | E8: =SUM(E9:E13) -> 0 | G8: =SUM(G9:G13) -> 5231553.6 | H8: =SUM(H9:H13) -> 0 | I8: =SUM(I9:I13) -> 0 | J8: =SUM(J9:J13) -> 0 | L8: =SUM(B8+G8) -> 2.0379229e+08 | M8: =SUM(C8+H8) -> 1.3318671e+08 | N8: =SUM(D8+I8) -> 0 | O8: =SUM(E8+J8) -> 0
A9: 2.1.1 - REMUNERACIONES | B9: =SUM('TRANSFERENCIA CORRIENTE'!C10:E10) -> 1.639452e+08 | C9: =SUM('TRANSFERENCIA CORRIENTE'!F10:H10) -> 1.0921624e+08 | D9: =SUM('TRANSFERENCIA CORRIENTE'!I10:K10) -> 0 | E9: =SUM('TRANSFERENCIA CORRIENTE'!L10:N10) -> 0 | G9: =SUM(VS!C10:E10) -> 0 | H9: =SUM(VS!F10:H10) -> 0 | I9: =SUM(VS!I10:K10) -> 0 | J9: =SUM(VS!L10:N10) -> 0 | L9: =SUM(B9+G9) -> 1.639452e+08 | M9: =SUM(C9+H9) -> 1.0921624e+08 | N9: =SUM(D9+I9) -> 0 | O9: =SUM(E9+J9) -> 0
A10: 2.1.2 - SOBRESUELDOS | B10: =SUM('TRANSFERENCIA CORRIENTE'!C11:E11) -> 9594398.8 | C10: =SUM('TRANSFERENCIA CORRIENTE'!F11:H11) -> 7192572.8 | D10: =SUM('TRANSFERENCIA CORRIENTE'!I11:K11) -> 0 | E10: =SUM('TRANSFERENCIA CORRIENTE'!L11:N11) -> 0 | G10: =SUM(VS!C11:E11) -> 5231553.6 | H10: =SUM(VS!F11:H11) -> 0 | I10: =SUM(VS!I11:K11) -> 0 | J10: =SUM(VS!L11:N11) -> 0 | L10: =SUM(B10+G10) -> 14825952 | M10: =SUM(C10+H10) -> 7192572.8 | N10: =SUM(D10+I10) -> 0 | O10: =SUM(E10+J10) -> 0
A11: 2.1.3 - DIETAS Y GASTOS DE REPRESENTACIÓN | B11: =SUM('TRANSFERENCIA CORRIENTE'!C12:E12) -> 0 | C11: =SUM('TRANSFERENCIA CORRIENTE'!F12:H12) -> 0 | D11: =SUM('TRANSFERENCIA CORRIENTE'!I12:K12) -> 0 | E11: =SUM('TRANSFERENCIA CORRIENTE'!L12:N12) -> 0 | G11: =SUM(VS!C12:E12) -> 0 | H11: =SUM(VS!F12:H12) -> 0 | I11: =SUM(VS!I12:K12) -> 0 | J11: =SUM(VS!L12:N12) -> 0 | L11: =SUM(B11+G11) -> 0 | M11: =SUM(C11+H11) -> 0 | N11: =SUM(D11+I11) -> 0 | O11: =SUM(E11+J11) -> 0
A12: 2.1.4 - GRATIFICACIONES Y BONIFICACIONES | B12: =SUM('TRANSFERENCIA CORRIENTE'!C13:E13) -> 0 | C12: =SUM('TRANSFERENCIA CORRIENTE'!F13:H13) -> 0 | D12: =SUM('TRANSFERENCIA CORRIENTE'!I13:K13) -> 0 | E12: =SUM('TRANSFERENCIA CORRIENTE'!L13:N13) -> 0 | G12: =SUM(VS!C13:E13) -> 0 | H12: =SUM(VS!F13:H13) -> 0 | I12: =SUM(VS!I13:K13) -> 0 | J12: =SUM(VS!L13:N13) -> 0 | L12: =SUM(B12+G12) -> 0 | M12: =SUM(C12+H12) -> 0 | N12: =SUM(D12+I12) -> 0 | O12: =SUM(E12+J12) -> 0
A13: 2.1.5 - CONTRIBUCIONES A LA SEGURIDAD SOCIAL | B13: =SUM('TRANSFERENCIA CORRIENTE'!C14:E14) -> 25021132 | C13: =SUM('TRANSFERENCIA CORRIENTE'!F14:H14) -> 16777896 | D13: =SUM('TRANSFERENCIA CORRIENTE'!I14:K14) -> 0 | E13: =SUM('TRANSFERENCIA CORRIENTE'!L14:N14) -> 0 | G13: =SUM(VS!C14:E14) -> 0 | H13: =SUM(VS!F14:H14) -> 0 | I13: =SUM(VS!I14:K14) -> 0 | J13: =SUM(VS!L14:N14) -> 0 | L13: =SUM(B13+G13) -> 25021132 | M13: =SUM(C13+H13) -> 16777896 | N13: =SUM(D13+I13) -> 0 | O13: =SUM(E13+J13) -> 0
A14: 2.2 - CONTRATACIÓN DE SERVICIOS | B14: =SUM(B15:B23) -> 9308364.9 | C14: =SUM(C15:C23) -> 1891359.8 | D14: =SUM(D15:D23) -> 0 | E14: =SUM(E15:E23) -> 0 | G14: =SUM(G15:G23) -> 8306683.8 | H14: =SUM(H15:H23) -> 3300774.7 | I14: =SUM(I15:I23) -> 0 | J14: =SUM(J15:J23) -> 0 | L14: =SUM(B14+G14) -> 17615049 | M14: =SUM(C14+H14) -> 5192134.5 | N14: =SUM(D14+I14) -> 0 | O14: =SUM(E14+J14) -> 0
A15: 2.2.1 - SERVICIOS BÁSICOS | B15: =SUM('TRANSFERENCIA CORRIENTE'!C16:E16) -> 2020024.3 | C15: =SUM('TRANSFERENCIA CORRIENTE'!F16:H16) -> 121070 | D15: =SUM('TRANSFERENCIA CORRIENTE'!J16:L16) -> 0 | E15: =SUM('TRANSFERENCIA CORRIENTE'!L16:N16) -> 0 | G15: =SUM(VS!C16:E16) -> 2341561.9 | H15: =SUM(VS!F16:H16) -> 1384071.7 | I15: =SUM(VS!I16:K16) -> 0 | J15: =SUM(VS!L16:N16) -> 0 | L15: =SUM(B15+G15) -> 4361586.2 | M15: =SUM(C15+H15) -> 1505141.7 | N15: =SUM(D15+I15) -> 0 | O15: =SUM(E15+J15) -> 0
A16: 2.2.2 - PUBLICIDAD, IMPRESIÓN Y ENCUADERNACIÓN | B16: =SUM('TRANSFERENCIA CORRIENTE'!C17:E17) -> 324206.83 | C16: =SUM('TRANSFERENCIA CORRIENTE'!F17:H17) -> 32889.84 | D16: =SUM('TRANSFERENCIA CORRIENTE'!J17:L17) -> 0 | E16: =SUM('TRANSFERENCIA CORRIENTE'!L17:N17) -> 0 | G16: =SUM(VS!C17:E17) -> 0 | H16: =SUM(VS!F17:H17) -> 0 | I16: =SUM(VS!I17:K17) -> 0 | J16: =SUM(VS!L17:N17) -> 0 | L16: =SUM(B16+G16) -> 324206.83 | M16: =SUM(C16+H16) -> 32889.84 | N16: =SUM(D16+I16) -> 0 | O16: =SUM(E16+J16) -> 0
A17: 2.2.3 - VIÁTICOS | B17: =SUM('TRANSFERENCIA CORRIENTE'!C18:E18) -> 0 | C17: =SUM('TRANSFERENCIA CORRIENTE'!F18:H18) -> 0 | D17: =SUM('TRANSFERENCIA CORRIENTE'!J18:L18) -> 0 | E17: =SUM('TRANSFERENCIA CORRIENTE'!L18:N18) -> 0 | G17: =SUM(VS!C18:E18) -> 0 | H17: =SUM(VS!F18:H18) -> 0 | I17: =SUM(VS!I18:K18) -> 0 | J17: =SUM(VS!L18:N18) -> 0 | L17: =SUM(B17+G17) -> 0 | M17: =SUM(C17+H17) -> 0 | N17: =SUM(D17+I17) -> 0 | O17: =SUM(E17+J17) -> 0
A18: 2.2.4 - TRANSPORTE Y ALMACENAJE | B18: =SUM('TRANSFERENCIA CORRIENTE'!C19:E19) -> 0 | C18: =SUM('TRANSFERENCIA CORRIENTE'!F19:H19) -> 0 | D18: =SUM('TRANSFERENCIA CORRIENTE'!J19:L19) -> 0 | E18: =SUM('TRANSFERENCIA CORRIENTE'!L19:N19) -> 0 | G18: =SUM(VS!C19:E19) -> 56000 | H18: =SUM(VS!F19:H19) -> 76000 | I18: =SUM(VS!I19:K19) -> 0 | J18: =SUM(VS!L19:N19) -> 0 | L18: =SUM(B18+G18) -> 56000 | M18: =SUM(C18+H18) -> 76000 | N18: =SUM(D18+I18) -> 0 | O18: =SUM(E18+J18) -> 0
A19: 2.2.5 - ALQUILERES Y RENTAS | B19: =SUM('TRANSFERENCIA CORRIENTE'!C20:E20) -> 0 | C19: =SUM('TRANSFERENCIA CORRIENTE'!F20:H20) -> 150000 | D19: =SUM('TRANSFERENCIA CORRIENTE'!J20:L20) -> 0 | E19: =SUM('TRANSFERENCIA CORRIENTE'!L20:N20) -> 0 | G19: =SUM(VS!C20:E20) -> 519625.15 | H19: =SUM(VS!F20:H20) -> 759170.42 | I19: =SUM(VS!I20:K20) -> 0 | J19: =SUM(VS!L20:N20) -> 0 | L19: =SUM(B19+G19) -> 519625.15 | M19: =SUM(C19+H19) -> 909170.42 | N19: =SUM(D19+I19) -> 0 | O19: =SUM(E19+J19) -> 0
A20: 2.2.6 - SEGUROS | B20: =SUM('TRANSFERENCIA CORRIENTE'!C21:E21) -> 0 | C20: =SUM('TRANSFERENCIA CORRIENTE'!F21:H21) -> 0 | D20: =SUM('TRANSFERENCIA CORRIENTE'!J21:L21) -> 0 | E20: =SUM('TRANSFERENCIA CORRIENTE'!L21:N21) -> 0 | G20: =SUM(VS!C21:E21) -> 0 | H20: =SUM(VS!F21:H21) -> 0 | I20: =SUM(VS!I21:K21) -> 0 | J20: =SUM(VS!L21:N21) -> 0 | L20: =SUM(B20+G20) -> 0 | M20: =SUM(C20+H20) -> 0 | N20: =SUM(D20+I20) -> 0 | O20: =SUM(E20+J20) -> 0
A21: 2.2.7 - SERVICIOS DE CONSERVACIÓN, REPARACIONES MENORES E INSTALACIONES TEMPORALES | B21: =SUM('TRANSFERENCIA CORRIENTE'!C22:E22) -> 6474433.8 | C21: =SUM('TRANSFERENCIA CORRIENTE'!F22:H22) -> 1174400 | D21: =SUM('TRANSFERENCIA CORRIENTE'!J22:L22) -> 0 | E21: =SUM('TRANSFERENCIA CORRIENTE'!L22:N22) -> 0 | G21: =SUM(VS!C22:E22) -> 4556850.1 | H21: =SUM(VS!F22:H22) -> 405776.67 | I21: =SUM(VS!I22:K22) -> 0 | J21: =SUM(VS!L22:N22) -> 0 | L21: =SUM(B21+G21) -> 11031284 | M21: =SUM(C21+H21) -> 1580176.6 | N21: =SUM(D21+I21) -> 0 | O21: =SUM(E21+J21) -> 0
A22: 2.2.8 - OTROS SERVICIOS NO INCLUIDOS EN CONCEPTOS ANTERIORES | B22: =SUM('TRANSFERENCIA CORRIENTE'!C23:E23) -> 489700 | C22: =SUM('TRANSFERENCIA CORRIENTE'!F23:H23) -> 413000 | D22: =SUM('TRANSFERENCIA CORRIENTE'!J23:L23) -> 0 | E22: =SUM('TRANSFERENCIA CORRIENTE'!L23:N23) -> 0 | G22: =SUM(VS!C23:E23) -> 832646.66 | H22: =SUM(VS!F23:H23) -> 675755.88 | I22: =SUM(VS!I23:K23) -> 0 | J22: =SUM(VS!L23:N23) -> 0 | L22: =SUM(B22+G22) -> 1322346.7 | M22: =SUM(C22+H22) -> 1088755.9 | N22: =SUM(D22+I22) -> 0 | O22: =SUM(E22+J22) -> 0
A23: 2.2.9 - OTRAS CONTRATACIONES DE SERVICIOS | B23: =SUM('TRANSFERENCIA CORRIENTE'!C24:E24) -> 0 | C23: =SUM('TRANSFERENCIA CORRIENTE'!F24:H24) -> 0 | D23: =SUM('TRANSFERENCIA CORRIENTE'!J24:L24) -> 0 | E23: =SUM('TRANSFERENCIA CORRIENTE'!L24:N24) -> 0 | G23: =SUM(VS!C24:E24) -> 0 | H23: =SUM(VS!F24:H24) -> 0 | I23: =SUM(VS!I24:K24) -> 0 | J23: =SUM(VS!L24:N24) -> 0 | L23: =SUM(B23+G23) -> 0 | M23: =SUM(C23+H23) -> 0 | N23: =SUM(D23+I23) -> 0 | O23: =SUM(E23+J23) -> 0
A24: 2.3 - MATERIALES Y SUMINISTROS | B24: =SUM(B25:B33) -> 46153283 | C24: =SUM(C25:C33) -> 36977120 | D24: =SUM(D25:D33) -> 0 | E24: =SUM(E25:E33) -> 0 | G24: =SUM(G25:G33) -> 7292547.3 | H24: =SUM(H25:H33) -> 5553166.8 | I24: =SUM(I25:I33) -> 0 | J24: =SUM(J25:J33) -> 0 | L24: =SUM(B24+G24) -> 53445831 | M24: =SUM(C24+H24) -> 42530287 | N24: =SUM(D24+I24) -> 0 | O24: =SUM(E24+J24) -> 0
A25: 2.3.1 - ALIMENTOS Y PRODUCTOS AGROFORESTALES | B25: =SUM('TRANSFERENCIA CORRIENTE'!C26:E26) -> 3713897.2 | C25: =SUM('TRANSFERENCIA CORRIENTE'!F26:H26) -> 2470053 | D25: =SUM('TRANSFERENCIA CORRIENTE'!I23:K23) -> 0 | E25: =SUM('TRANSFERENCIA CORRIENTE'!L26:N26) -> 0 | G25: =SUM(VS!C26:E26) -> 1500755.8 | H25: =SUM(VS!F26:H26) -> 449925 | I25: =SUM(VS!I26:K26) -> 0 | J25: =SUM(VS!L26:N26) -> 0 | L25: =SUM(B25+G25) -> 5214653 | M25: =SUM(C25+H25) -> 2919978 | N25: =SUM(D25+I25) -> 0 | O25: =SUM(E25+J25) -> 0
A26: 2.3.2 - TEXTILES Y VESTUARIOS | B26: =SUM('TRANSFERENCIA CORRIENTE'!C27:E27) -> 61630.73 | C26: =SUM('TRANSFERENCIA CORRIENTE'!F27:H27) -> 1562980.5 | D26: =SUM('TRANSFERENCIA CORRIENTE'!I24:K24) -> 0 | E26: =SUM('TRANSFERENCIA CORRIENTE'!L27:N27) -> 0 | G26: =SUM(VS!C27:E27) -> 0 | H26: =SUM(VS!F27:H27) -> 141128 | I26: =SUM(VS!I27:K27) -> 0 | J26: =SUM(VS!L27:N27) -> 0 | L26: =SUM(B26+G26) -> 61630.73 | M26: =SUM(C26+H26) -> 1704108.5 | N26: =SUM(D26+I26) -> 0 | O26: =SUM(E26+J26) -> 0
A27: 2.3.3 - PRODUCTOS DE PAPEL, CARTÓN E IMPRESOS | B27: =SUM('TRANSFERENCIA CORRIENTE'!C28:E28) -> 1826911.8 | C27: =SUM('TRANSFERENCIA CORRIENTE'!F28:H28) -> 2276081.2 | D27: =SUM('TRANSFERENCIA CORRIENTE'!I25:K25) -> 0 | E27: =SUM('TRANSFERENCIA CORRIENTE'!L28:N28) -> 0 | G27: =SUM(VS!C28:E28) -> 251163 | H27: =SUM(VS!F28:H28) -> 803989 | I27: =SUM(VS!I28:K28) -> 0 | J27: =SUM(VS!L28:N28) -> 0 | L27: =SUM(B27+G27) -> 2078074.8 | M27: =SUM(C27+H27) -> 3080070.2 | N27: =SUM(D27+I27) -> 0 | O27: =SUM(E27+J27) -> 0
A28: 2.3.4 - PRODUCTOS FARMACÉUTICOS | B28: =SUM('TRANSFERENCIA CORRIENTE'!C29:E29) -> 10797336 | C28: =SUM('TRANSFERENCIA CORRIENTE'!F29:H29) -> 8986394.6 | D28: =SUM('TRANSFERENCIA CORRIENTE'!I26:K26) -> 0 | E28: =SUM('TRANSFERENCIA CORRIENTE'!L29:N29) -> 0 | G28: =SUM(VS!C29:E29) -> 558000 | H28: =SUM(VS!F29:H29) -> 222100 | I28: =SUM(VS!I29:K29) -> 0 | J28: =SUM(VS!L29:N29) -> 0 | L28: =SUM(B28+G28) -> 11355336 | M28: =SUM(C28+H28) -> 9208494.6 | N28: =SUM(D28+I28) -> 0 | O28: =SUM(E28+J28) -> 0
A29: 2.3.5 - PRODUCTOS DE CUERO, CAUCHO Y PLÁSTICO | B29: =SUM('TRANSFERENCIA CORRIENTE'!C30:E30) -> 334708.95 | C29: =SUM('TRANSFERENCIA CORRIENTE'!F30:H30) -> 890959.43 | D29: =SUM('TRANSFERENCIA CORRIENTE'!I27:K27) -> 0 | E29: =SUM('TRANSFERENCIA CORRIENTE'!L30:N30) -> 0 | G29: =SUM(VS!C30:E30) -> 567494.87 | H29: =SUM(VS!F30:H30) -> 0 | I29: =SUM(VS!I30:K30) -> 0 | J29: =SUM(VS!L30:N30) -> 0 | L29: =SUM(B29+G29) -> 902203.82 | M29: =SUM(C29+H29) -> 890959.43 | N29: =SUM(D29+I29) -> 0 | O29: =SUM(E29+J29) -> 0
A30: 2.3.6 - PRODUCTOS DE MINERALES, METÁLICOS Y NO METÁLICOS | B30: =SUM('TRANSFERENCIA CORRIENTE'!C31:E31) -> 11630.98 | C30: =SUM('TRANSFERENCIA CORRIENTE'!F31:H31) -> 566193.69 | D30: =SUM('TRANSFERENCIA CORRIENTE'!I28:K28) -> 0 | E30: =SUM('TRANSFERENCIA CORRIENTE'!L31:N31) -> 0 | G30: =SUM(VS!C31:E31) -> 293957.3 | H30: =SUM(VS!F31:H31) -> 0 | I30: =SUM(VS!I31:K31) -> 0 | J30: =SUM(VS!L31:N31) -> 0 | L30: =SUM(B30+G30) -> 305588.28 | M30: =SUM(C30+H30) -> 566193.69 | N30: =SUM(D30+I30) -> 0 | O30: =SUM(E30+J30) -> 0
A31: 2.3.7 - COMBUSTIBLES, LUBRICANTES, PRODUCTOS QUÍMICOS Y CONEXOS | B31: =SUM('TRANSFERENCIA CORRIENTE'!C32:E32) -> 8910102 | C31: =SUM('TRANSFERENCIA CORRIENTE'!F32:H32) -> 7168869.4 | D31: =SUM('TRANSFERENCIA CORRIENTE'!I29:K29) -> 0 | E31: =SUM('TRANSFERENCIA CORRIENTE'!L32:N32) -> 0 | G31: =SUM(VS!C32:E32) -> 1660334.6 | H31: =SUM(VS!F32:H32) -> 1292460 | I31: =SUM(VS!I32:K32) -> 0 | J31: =SUM(VS!L32:N32) -> 0 | L31: =SUM(B31+G31) -> 10570437 | M31: =SUM(C31+H31) -> 8461329.4 | N31: =SUM(D31+I31) -> 0 | O31: =SUM(E31+J31) -> 0
A32: 2.3.8 - GASTOS QUE SE ASIGNARÁN DURANTE EL EJERCICIO (ART. 32 Y 33 LEY 423-06) | B32: =SUM('TRANSFERENCIA CORRIENTE'!C33:E33) -> 0 | C32: =SUM('TRANSFERENCIA CORRIENTE'!F33:H33) -> 0 | D32: =SUM('TRANSFERENCIA CORRIENTE'!I30:K30) -> 0 | E32: =SUM('TRANSFERENCIA CORRIENTE'!L33:N33) -> 0 | G32: =SUM(VS!C33:E33) -> 0 | H32: =SUM(VS!F33:H33) -> 0 | I32: =SUM(VS!I33:K33) -> 0 | J32: =SUM(VS!L33:N33) -> 0 | L32: =SUM(B32+G32) -> 0 | M32: =SUM(C32+H32) -> 0 | N32: =SUM(D32+I32) -> 0 | O32: =SUM(E32+J32) -> 0
A33: 2.3.9 - PRODUCTOS Y ÚTILES VARIOS | B33: =SUM('TRANSFERENCIA CORRIENTE'!C34:E34) -> 20497066 | C33: =SUM('TRANSFERENCIA CORRIENTE'!F34:H34) -> 13055589 | D33: =SUM('TRANSFERENCIA CORRIENTE'!I31:K31) -> 0 | E33: =SUM('TRANSFERENCIA CORRIENTE'!L34:N34) -> 0 | G33: =SUM(VS!C34:E34) -> 2460841.8 | H33: =SUM(VS!F34:H34) -> 2643564.8 | I33: =SUM(VS!I34:K34) -> 0 | J33: =SUM(VS!L34:N34) -> 0 | L33: =SUM(B33+G33) -> 22957908 | M33: =SUM(C33+H33) -> 15699153 | N33: =SUM(D33+I33) -> 0 | O33: =SUM(E33+J33) -> 0
A34: 2.4 - TRANSFERENCIAS CORRIENTES | B34: =SUM(B35:B41) -> 0 | C34: =SUM(C35:C41) -> 0 | D34: =SUM(D35:D41) -> 0 | E34: =SUM(E35:E41) -> 0 | G34: =SUM(G35:G41) -> 287786.7 | H34: =SUM(H35:H41) -> 1105381 | I34: =SUM(I35:I41) -> 0 | J34: =SUM(J35:J41) -> 0 | L34: =SUM(B34+G34) -> 287786.7 | M34: =SUM(C34+H34) -> 1105381 | N34: =SUM(D34+I34) -> 0 | O34: =SUM(E34+J34) -> 0
A35: 2.4.1 - TRANSFERENCIAS CORRIENTES AL SECTOR PRIVADO | B35: =SUM('TRANSFERENCIA CORRIENTE'!C36:E36) -> 0 | C35: =SUM('TRANSFERENCIA CORRIENTE'!F36:H36) -> 0 | D35: =SUM('TRANSFERENCIA CORRIENTE'!I36:K36) -> 0 | E35: =SUM('TRANSFERENCIA CORRIENTE'!L36:N36) -> 0 | G35: =SUM(VS!C36:E36) -> 287786.7 | H35: =SUM(VS!F36:H36) -> 1105381 | I35: =SUM(VS!I36:K36) -> 0 | J35: =SUM(VS!L36:N36) -> 0 | L35: =SUM(B35+G35) -> 287786.7 | M35: =SUM(C35+H35) -> 1105381 | N35: =SUM(D35+I35) -> 0 | O35: =SUM(E35+J35) -> 0
A36: 2.4.2 - TRANSFERENCIAS CORRIENTES AL GOBIERNO GENERAL NACIONAL | B36: =SUM('TRANSFERENCIA CORRIENTE'!C37:E37) -> 0 | C36: =SUM('TRANSFERENCIA CORRIENTE'!F37:H37) -> 0 | D36: =SUM('TRANSFERENCIA CORRIENTE'!I37:K37) -> 0 | E36: =SUM('TRANSFERENCIA CORRIENTE'!L37:N37) -> 0 | G36: =SUM(VS!C37:E37) -> 0 | H36: =SUM(VS!F37:H37) -> 0 | I36: =SUM(VS!I37:K37) -> 0 | J36: =SUM(VS!L37:N37) -> 0 | L36: =SUM(B36+G36) -> 0 | M36: =SUM(C36+H36) -> 0 | N36: =SUM(D36+I36) -> 0 | O36: =SUM(E36+J36) -> 0
A37: 2.4.3 - TRANSFERENCIAS CORRIENTES A GOBIERNOS GENERALES LOCALES | B37: =SUM('TRANSFERENCIA CORRIENTE'!C38:E38) -> 0 | C37: =SUM('TRANSFERENCIA CORRIENTE'!F38:H38) -> 0 | D37: =SUM('TRANSFERENCIA CORRIENTE'!I38:K38) -> 0 | E37: =SUM('TRANSFERENCIA CORRIENTE'!L38:N38) -> 0 | G37: =SUM(VS!C38:E38) -> 0 | H37: =SUM(VS!F38:H38) -> 0 | I37: =SUM(VS!I38:K38) -> 0 | J37: =SUM(VS!L38:N38) -> 0 | L37: =SUM(B37+G37) -> 0 | M37: =SUM(C37+H37) -> 0 | N37: =SUM(D37+I37) -> 0 | O37: =SUM(E37+J37) -> 0
A38: 2.4.4 - TRANSFERENCIAS CORRIENTES A EMPRESAS PÚBLICAS NO FINANCIERAS | B38: =SUM('TRANSFERENCIA CORRIENTE'!C39:E39) -> 0 | C38: =SUM('TRANSFERENCIA CORRIENTE'!F39:H39) -> 0 | D38: =SUM('TRANSFERENCIA CORRIENTE'!I39:K39) -> 0 | E38: =SUM('TRANSFERENCIA CORRIENTE'!L39:N39) -> 0 | G38: =SUM(VS!C39:E39) -> 0 | H38: =SUM(VS!F39:H39) -> 0 | I38: =SUM(VS!I39:K39) -> 0 | J38: =SUM(VS!L39:N39) -> 0 | L38: =SUM(B38+G38) -> 0 | M38: =SUM(C38+H38) -> 0 | N38: =SUM(D38+I38) -> 0 | O38: =SUM(E38+J38) -> 0
A39: 2.4.5 - TRANSFERENCIAS CORRIENTES A INSTITUCIONES PÚBLICAS FINANCIERAS | B39: =SUM('TRANSFERENCIA CORRIENTE'!C40:E40) -> 0 | C39: =SUM('TRANSFERENCIA CORRIENTE'!F40:H40) -> 0 | D39: =SUM('TRANSFERENCIA CORRIENTE'!I40:K40) -> 0 | E39: =SUM('TRANSFERENCIA CORRIENTE'!L40:N40) -> 0 | G39: =SUM(VS!C40:E40) -> 0 | H39: =SUM(VS!F40:H40) -> 0 | I39: =SUM(VS!I40:K40) -> 0 | J39: =SUM(VS!L40:N40) -> 0 | L39: =SUM(B39+G39) -> 0 | M39: =SUM(C39+H39) -> 0 | N39: =SUM(D39+I39) -> 0 | O39: =SUM(E39+J39) -> 0
A40: 2.4.7 - TRANSFERENCIAS CORRIENTES AL SECTOR EXTERNO | B40: =SUM('TRANSFERENCIA CORRIENTE'!C41:E41) -> 0 | C40: =SUM('TRANSFERENCIA CORRIENTE'!F41:H41) -> 0 | D40: =SUM('TRANSFERENCIA CORRIENTE'!I41:K41) -> 0 | E40: =SUM('TRANSFERENCIA CORRIENTE'!L41:N41) -> 0 | G40: =SUM(VS!C41:E41) -> 0 | H40: =SUM(VS!F41:H41) -> 0 | I40: =SUM(VS!I41:K41) -> 0 | J40: =SUM(VS!L41:N41) -> 0 | L40: =SUM(B40+G40) -> 0 | M40: =SUM(C40+H40) -> 0 | N40: =SUM(D40+I40) -> 0 | O40: =SUM(E40+J40) -> 0
A41: 2.4.9 - TRANSFERENCIAS CORRIENTES A OTRAS INSTITUCIONES PÚBLICAS | B41: =SUM('TRANSFERENCIA CORRIENTE'!C42:E42) -> 0 | C41: =SUM('TRANSFERENCIA CORRIENTE'!F42:H42) -> 0 | D41: =SUM('TRANSFERENCIA CORRIENTE'!I42:K42) -> 0 | E41: =SUM('TRANSFERENCIA CORRIENTE'!L42:N42) -> 0 | G41: =SUM(VS!C42:E42) -> 0 | H41: =SUM(VS!F42:H42) -> 0 | I41: =SUM(VS!I42:K42) -> 0 | J41: =SUM(VS!L42:N42) -> 0 | L41: =SUM(B41+G41) -> 0 | M41: =SUM(C41+H41) -> 0 | N41: =SUM(D41+I41) -> 0 | O41: =SUM(E41+J41) -> 0
A42: 2.5 - TRANSFERENCIAS DE CAPITAL | B42: =SUM(B43:B49) -> 0 | C42: =SUM(C43:C49) -> 0 | D42: =SUM(D43:D49) -> 0 | E42: =SUM(E43:E49) -> 0 | G42: =SUM(G43:G49) -> 0 | H42: =SUM(H43:H49) -> 0 | I42: =SUM(I43:I49) -> 0 | J42: =SUM(J43:J49) -> 0 | L42: =SUM(B42+G42) -> 0 | M42: =SUM(C42+H42) -> 0 | N42: =SUM(D42+I42) -> 0 | O42: =SUM(E42+J42) -> 0
A43: 2.5.1 - TRANSFERENCIAS DE CAPITAL AL SECTOR PRIVADO | B43: =SUM('TRANSFERENCIA CORRIENTE'!C44:E44) -> 0 | C43: =SUM('TRANSFERENCIA CORRIENTE'!F44:H44) -> 0 | D43: =SUM('TRANSFERENCIA CORRIENTE'!I44:K44) -> 0 | E43: =SUM('TRANSFERENCIA CORRIENTE'!L44:N44) -> 0 | G43: =SUM(VS!C44:E44) -> 0 | H43: =SUM(VS!F44:H44) -> 0 | I43: =SUM(VS!I44:K44) -> 0 | J43: =SUM(VS!L44:N44) -> 0 | L43: =SUM(B43+G43) -> 0 | M43: =SUM(C43+H43) -> 0 | N43: =SUM(D43+I43) -> 0 | O43: =SUM(E43+J43) -> 0
A44: 2.5.2 - TRANSFERENCIAS DE CAPITAL AL GOBIERNO GENERAL NACIONAL | B44: =SUM('TRANSFERENCIA CORRIENTE'!C45:E45) -> 0 | C44: =SUM('TRANSFERENCIA CORRIENTE'!F45:H45) -> 0 | D44: =SUM('TRANSFERENCIA CORRIENTE'!I45:K45) -> 0 | E44: =SUM('TRANSFERENCIA CORRIENTE'!L45:N45) -> 0 | G44: =SUM(VS!C45:E45) -> 0 | H44: =SUM(VS!F45:H45) -> 0 | I44: =SUM(VS!I45:K45) -> 0 | J44: =SUM(VS!L45:N45) -> 0 | L44: =SUM(B44+G44) -> 0 | M44: =SUM(C44+H44) -> 0 | N44: =SUM(D44+I44) -> 0 | O44: =SUM(E44+J44) -> 0
A45: 2.5.3 - TRANSFERENCIAS DE CAPITAL A GOBIERNOS GENERALES LOCALES | B45: =SUM('TRANSFERENCIA CORRIENTE'!C46:E46) -> 0 | C45: =SUM('TRANSFERENCIA CORRIENTE'!F46:H46) -> 0 | D45: =SUM('TRANSFERENCIA CORRIENTE'!I46:K46) -> 0 | E45: =SUM('TRANSFERENCIA CORRIENTE'!L46:N46) -> 0 | G45: =SUM(VS!C46:E46) -> 0 | H45: =SUM(VS!F46:H46) -> 0 | I45: =SUM(VS!I46:K46) -> 0 | J45: =SUM(VS!L46:N46) -> 0 | L45: =SUM(B45+G45) -> 0 | M45: =SUM(C45+H45) -> 0 | N45: =SUM(D45+I45) -> 0 | O45: =SUM(E45+J45) -> 0
A46: 2.5.4 - TRANSFERENCIAS DE CAPITAL A EMPRESAS PÚBLICAS NO FINANCIERAS | B46: =SUM('TRANSFERENCIA CORRIENTE'!C47:E47) -> 0 | C46: =SUM('TRANSFERENCIA CORRIENTE'!F47:H47) -> 0 | D46: =SUM('TRANSFERENCIA CORRIENTE'!I47:K47) -> 0 | E46: =SUM('TRANSFERENCIA CORRIENTE'!L47:N47) -> 0 | G46: =SUM(VS!C47:E47) -> 0 | H46: =SUM(VS!F47:H47) -> 0 | I46: =SUM(VS!I47:K47) -> 0 | J46: =SUM(VS!L47:N47) -> 0 | L46: =SUM(B46+G46) -> 0 | M46: =SUM(C46+H46) -> 0 | N46: =SUM(D46+I46) -> 0 | O46: =SUM(E46+J46) -> 0
A47: 2.5.5 - TRANSFERENCIAS DE CAPITAL A INSTITUCIONES PÚBLICAS FINANCIERAS | B47: =SUM('TRANSFERENCIA CORRIENTE'!C48:E48) -> 0 | C47: =SUM('TRANSFERENCIA CORRIENTE'!F48:H48) -> 0 | D47: =SUM('TRANSFERENCIA CORRIENTE'!I48:K48) -> 0 | E47: =SUM('TRANSFERENCIA CORRIENTE'!L48:N48) -> 0 | G47: =SUM(VS!C48:E48) -> 0 | H47: =SUM(VS!F48:H48) -> 0 | I47: =SUM(VS!I48:K48) -> 0 | J47: =SUM(VS!L48:N48) -> 0 | L47: =SUM(B47+G47) -> 0 | M47: =SUM(C47+H47) -> 0 | N47: =SUM(D47+I47) -> 0 | O47: =SUM(E47+J47) -> 0
A48: 2.5.6 - TRANSFERENCIAS DE CAPITAL AL SECTOR EXTERNO | B48: =SUM('TRANSFERENCIA CORRIENTE'!C49:E49) -> 0 | C48: =SUM('TRANSFERENCIA CORRIENTE'!F49:H49) -> 0 | D48: =SUM('TRANSFERENCIA CORRIENTE'!I49:K49) -> 0 | E48: =SUM('TRANSFERENCIA CORRIENTE'!L49:N49) -> 0 | G48: =SUM(VS!C49:E49) -> 0 | H48: =SUM(VS!F49:H49) -> 0 | I48: =SUM(VS!I49:K49) -> 0 | J48: =SUM(VS!L49:N49) -> 0 | L48: =SUM(B48+G48) -> 0 | M48: =SUM(C48+H48) -> 0 | N48: =SUM(D48+I48) -> 0 | O48: =SUM(E48+J48) -> 0
A49: 2.5.9 - TRANSFERENCIAS DE CAPITAL A OTRAS INSTITUCIONES PÚBLICAS | B49: =SUM('TRANSFERENCIA CORRIENTE'!C50:E50) -> 0 | C49: =SUM('TRANSFERENCIA CORRIENTE'!F50:H50) -> 0 | D49: =SUM('TRANSFERENCIA CORRIENTE'!I50:K50) -> 0 | E49: =SUM('TRANSFERENCIA CORRIENTE'!L50:N50) -> 0 | G49: =SUM(VS!C50:E50) -> 0 | H49: =SUM(VS!F50:H50) -> 0 | I49: =SUM(VS!I50:K50) -> 0 | J49: =SUM(VS!L50:N50) -> 0 | L49: =SUM(B49+G49) -> 0 | M49: =SUM(C49+H49) -> 0 | N49: =SUM(D49+I49) -> 0 | O49: =SUM(E49+J49) -> 0
A50: 2.6 - BIENES MUEBLES, INMUEBLES E INTANGIBLES | B50: =SUM(B51:B59) -> 17857867 | C50: =SUM(C51:C59) -> 11245715 | D50: =SUM(D51:D59) -> 0 | E50: =SUM(E51:E59) -> 0 | G50: =SUM(G51:G59) -> 5076044.2 | H50: =SUM(H51:H59) -> 3927042.2 | I50: =SUM(I51:I59) -> 0 | J50: =SUM(J51:J59) -> 0 | L50: =SUM(B50+G50) -> 22933911 | M50: =SUM(C50+H50) -> 15172757 | N50: =SUM(D50+I50) -> 0 | O50: =SUM(E50+J50) -> 0
A51: 2.6.1 - MOBILIARIO Y EQUIPO | B51: =SUM('TRANSFERENCIA CORRIENTE'!C52:E52) -> 1110625.9 | C51: =SUM('TRANSFERENCIA CORRIENTE'!F52:H52) -> 2043918.7 | D51: =SUM('TRANSFERENCIA CORRIENTE'!I52:K52) -> 0 | E51: =SUM('TRANSFERENCIA CORRIENTE'!L52:N52) -> 0 | G51: =SUM(VS!C52:E52) -> 0 | H51: =SUM(VS!F52:H52) -> 0 | I51: =SUM(VS!I52:K52) -> 0 | J51: =SUM(VS!L52:N52) -> 0 | L51: =SUM(B51+G51) -> 1110625.9 | M51: =SUM(C51+H51) -> 2043918.7 | N51: =SUM(D51+I51) -> 0 | O51: =SUM(E51+J51) -> 0
A52: 2.6.2 - MOBILIARIO Y EQUIPO EDUCACIONAL Y RECREATIVO | B52: =SUM('TRANSFERENCIA CORRIENTE'!C53:E53) -> 0 | C52: =SUM('TRANSFERENCIA CORRIENTE'!F53:H53) -> 182926.74 | D52: =SUM('TRANSFERENCIA CORRIENTE'!I53:K53) -> 0 | E52: =SUM('TRANSFERENCIA CORRIENTE'!L53:N53) -> 0 | G52: =SUM(VS!C53:E53) -> 0 | H52: =SUM(VS!F53:H53) -> 0 | I52: =SUM(VS!I53:K53) -> 0 | J52: =SUM(VS!L53:N53) -> 0 | L52: =SUM(B52+G52) -> 0 | M52: =SUM(C52+H52) -> 182926.74 | N52: =SUM(D52+I52) -> 0 | O52: =SUM(E52+J52) -> 0
A53: 2.6.3 - EQUIPO E INSTRUMENTAL, CIENTÍFICO Y LABORATORIO | B53: =SUM('TRANSFERENCIA CORRIENTE'!C54:E54) -> 16744041 | C53: =SUM('TRANSFERENCIA CORRIENTE'!F54:H54) -> 4920998.6 | D53: =SUM('TRANSFERENCIA CORRIENTE'!I54:K54) -> 0 | E53: =SUM('TRANSFERENCIA CORRIENTE'!L54:N54) -> 0 | G53: =SUM(VS!C54:E54) -> 2963024.8 | H53: =SUM(VS!F54:H54) -> 3927042.2 | I53: =SUM(VS!I54:K54) -> 0 | J53: =SUM(VS!L54:N54) -> 0 | L53: =SUM(B53+G53) -> 19707066 | M53: =SUM(C53+H53) -> 8848040.8 | N53: =SUM(D53+I53) -> 0 | O53: =SUM(E53+J53) -> 0
A54: 2.6.4 - VEHÍCULOS Y EQUIPO DE TRANSPORTE, TRACCIÓN Y ELEVACIÓN | B54: =SUM('TRANSFERENCIA CORRIENTE'!C55:E55) -> 0 | C54: =SUM('TRANSFERENCIA CORRIENTE'!F55:H55) -> 0 | D54: =SUM('TRANSFERENCIA CORRIENTE'!I55:K55) -> 0 | E54: =SUM('TRANSFERENCIA CORRIENTE'!L55:N55) -> 0 | G54: =SUM(VS!C55:E55) -> 107609.37 | H54: =SUM(VS!F55:H55) -> 0 | I54: =SUM(VS!I55:K55) -> 0 | J54: =SUM(VS!L55:N55) -> 0 | L54: =SUM(B54+G54) -> 107609.37 | M54: =SUM(C54+H54) -> 0 | N54: =SUM(D54+I54) -> 0 | O54: =SUM(E54+J54) -> 0
A55: 2.6.5 - MAQUINARIA, OTROS EQUIPOS Y HERRAMIENTAS | B55: =SUM('TRANSFERENCIA CORRIENTE'!C56:E56) -> 3199.97 | C55: =SUM('TRANSFERENCIA CORRIENTE'!F56:H56) -> 3752309.5 | D55: =SUM('TRANSFERENCIA CORRIENTE'!I56:K56) -> 0 | E55: =SUM('TRANSFERENCIA CORRIENTE'!L56:N56) -> 0 | G55: =SUM(VS!C56:E56) -> 2005410 | H55: =SUM(VS!F56:H56) -> 0 | I55: =SUM(VS!I56:K56) -> 0 | J55: =SUM(VS!L56:N56) -> 0 | L55: =SUM(B55+G55) -> 2008610 | M55: =SUM(C55+H55) -> 3752309.5 | N55: =SUM(D55+I55) -> 0 | O55: =SUM(E55+J55) -> 0
A56: 2.6.6 - EQUIPOS DE DEFENSA Y SEGURIDAD | B56: =SUM('TRANSFERENCIA CORRIENTE'!C57:E57) -> 0 | C56: =SUM('TRANSFERENCIA CORRIENTE'!F57:H57) -> 0 | D56: =SUM('TRANSFERENCIA CORRIENTE'!I57:K57) -> 0 | E56: =SUM('TRANSFERENCIA CORRIENTE'!L57:N57) -> 0 | G56: =SUM(VS!C57:E57) -> 0 | H56: =SUM(VS!F57:H57) -> 0 | I56: =SUM(VS!I57:K57) -> 0 | J56: =SUM(VS!L57:N57) -> 0 | L56: =SUM(B56+G56) -> 0 | M56: =SUM(C56+H56) -> 0 | N56: =SUM(D56+I56) -> 0 | O56: =SUM(E56+J56) -> 0
A57: 2.6.7 - ACTIVOS BIÓLOGICOS CULTIVABLES | B57: =SUM('TRANSFERENCIA CORRIENTE'!C58:E58) -> 0 | C57: =SUM('TRANSFERENCIA CORRIENTE'!F58:H58) -> 0 | D57: =SUM('TRANSFERENCIA CORRIENTE'!I58:K58) -> 0 | E57: =SUM('TRANSFERENCIA CORRIENTE'!L58:N58) -> 0 | G57: =SUM(VS!C58:E58) -> 0 | H57: =SUM(VS!F58:H58) -> 0 | I57: =SUM(VS!I58:K58) -> 0 | J57: =SUM(VS!L58:N58) -> 0 | L57: =SUM(B57+G57) -> 0 | M57: =SUM(C57+H57) -> 0 | N57: =SUM(D57+I57) -> 0 | O57: =SUM(E57+J57) -> 0
A58: 2.6.8 - BIENES INTANGIBLES | B58: =SUM('TRANSFERENCIA CORRIENTE'!C59:E59) -> 0 | C58: =SUM('TRANSFERENCIA CORRIENTE'!F59:H59) -> 0 | D58: =SUM('TRANSFERENCIA CORRIENTE'!I59:K59) -> 0 | E58: =SUM('TRANSFERENCIA CORRIENTE'!L59:N59) -> 0 | G58: =SUM(VS!C59:E59) -> 0 | H58: =SUM(VS!F59:H59) -> 0 | I58: =SUM(VS!I59:K59) -> 0 | J58: =SUM(VS!L59:N59) -> 0 | L58: =SUM(B58+G58) -> 0 | M58: =SUM(C58+H58) -> 0 | N58: =SUM(D58+I58) -> 0 | O58: =SUM(E58+J58) -> 0
A59: 2.6.9 - EDIFICIOS, ESTRUCTURAS, TIERRAS, TERRENOS Y OBJETOS DE VALOR | B59: =SUM('TRANSFERENCIA CORRIENTE'!C60:E60) -> 0 | C59: =SUM('TRANSFERENCIA CORRIENTE'!F60:H60) -> 345560.94 | D59: =SUM('TRANSFERENCIA CORRIENTE'!I60:K60) -> 0 | E59: =SUM('TRANSFERENCIA CORRIENTE'!L60:N60) -> 0 | G59: =SUM(VS!C60:E60) -> 0 | H59: =SUM(VS!F60:H60) -> 0 | I59: =SUM(VS!I60:K60) -> 0 | J59: =SUM(VS!L60:N60) -> 0 | L59: =SUM(B59+G59) -> 0 | M59: =SUM(C59+H59) -> 345560.94 | N59: =SUM(D59+I59) -> 0 | O59: =SUM(E59+J59) -> 0
A60: 2.7 - OBRAS | B60: =SUM(B61:B64) -> 0 | C60: =SUM(C61:C64) -> 0 | D60: =SUM(D61:D64) -> 0 | E60: =SUM(E61:E64) -> 0 | G60: =SUM(G61:G64) -> 0 | H60: =SUM(H61:H64) -> 0 | I60: =SUM(I61:I64) -> 0 | J60: =SUM(J61:J64) -> 0 | L60: =SUM(B60+G60) -> 0 | M60: =SUM(C60+H60) -> 0 | N60: =SUM(D60+I60) -> 0 | O60: =SUM(E60+J60) -> 0
A61: 2.7.1 - OBRAS EN EDIFICACIONES | B61: =SUM('TRANSFERENCIA CORRIENTE'!C62:E62) -> 0 | C61: =SUM('TRANSFERENCIA CORRIENTE'!F62:H62) -> 0 | D61: =SUM('TRANSFERENCIA CORRIENTE'!I62:K62) -> 0 | E61: =SUM('TRANSFERENCIA CORRIENTE'!L62:N62) -> 0 | G61: =SUM(VS!C62:E62) -> 0 | H61: =SUM(VS!F62:H62) -> 0 | I61: =SUM(VS!I62:K62) -> 0 | J61: =SUM(VS!L62:N62) -> 0 | L61: =SUM(B61+G61) -> 0 | M61: =SUM(C61+H61) -> 0 | N61: =SUM(D61+I61) -> 0 | O61: =SUM(E61+J61) -> 0
A62: 2.7.2 - INFRAESTRUCTURA | B62: =SUM('TRANSFERENCIA CORRIENTE'!C63:E63) -> 0 | C62: =SUM('TRANSFERENCIA CORRIENTE'!F63:H63) -> 0 | D62: =SUM('TRANSFERENCIA CORRIENTE'!I63:K63) -> 0 | E62: =SUM('TRANSFERENCIA CORRIENTE'!L63:N63) -> 0 | G62: =SUM(VS!C63:E63) -> 0 | H62: =SUM(VS!F63:H63) -> 0 | I62: =SUM(VS!I63:K63) -> 0 | J62: =SUM(VS!L63:N63) -> 0 | L62: =SUM(B62+G62) -> 0 | M62: =SUM(C62+H62) -> 0 | N62: =SUM(D62+I62) -> 0 | O62: =SUM(E62+J62) -> 0
A63: 2.7.3 - CONSTRUCCIONES EN BIENES CONCESIONADOS | B63: =SUM('TRANSFERENCIA CORRIENTE'!C64:E64) -> 0 | C63: =SUM('TRANSFERENCIA CORRIENTE'!F64:H64) -> 0 | D63: =SUM('TRANSFERENCIA CORRIENTE'!I64:K64) -> 0 | E63: =SUM('TRANSFERENCIA CORRIENTE'!L64:N64) -> 0 | G63: =SUM(VS!C64:E64) -> 0 | H63: =SUM(VS!F64:H64) -> 0 | I63: =SUM(VS!I64:K64) -> 0 | J63: =SUM(VS!L64:N64) -> 0 | L63: =SUM(B63+G63) -> 0 | M63: =SUM(C63+H63) -> 0 | N63: =SUM(D63+I63) -> 0 | O63: =SUM(E63+J63) -> 0
A64: 2.7.4 - GASTOS QUE SE ASIGNARÁN DURANTE EL EJERCICIO PARA INVERSIÓN (ART. 32 Y 33 LEY 423-06) | B64: =SUM('TRANSFERENCIA CORRIENTE'!C65:E65) -> 0 | C64: =SUM('TRANSFERENCIA CORRIENTE'!F65:H65) -> 0 | D64: =SUM('TRANSFERENCIA CORRIENTE'!I65:K65) -> 0 | E64: =SUM('TRANSFERENCIA CORRIENTE'!L65:N65) -> 0 | G64: =SUM(VS!C65:E65) -> 0 | H64: =SUM(VS!F65:H65) -> 0 | I64: =SUM(VS!I65:K65) -> 0 | J64: =SUM(VS!L65:N65) -> 0 | L64: =SUM(B64+G64) -> 0 | M64: =SUM(C64+H64) -> 0 | N64: =SUM(D64+I64) -> 0 | O64: =SUM(E64+J64) -> 0
A65: 2.8 - ADQUISICION DE ACTIVOS FINANCIEROS CON FINES DE POLÍTICA | B65: =SUM(B66:B67) -> 0 | C65: =SUM(C66:C67) -> 0 | D65: =SUM(D66:D67) -> 0 | E65: =SUM(E66:E67) -> 0 | G65: =SUM(G66:G67) -> 0 | H65: =SUM(H66:H67) -> 0 | I65: =SUM(I66:I67) -> 0 | J65: =SUM(J66:J67) -> 0 | L65: =SUM(B65+G65) -> 0 | M65: =SUM(C65+H65) -> 0 | N65: =SUM(D65+I65) -> 0 | O65: =SUM(E65+J65) -> 0
A66: 2.8.1 - CONCESIÓN DE PRESTAMOS | B66: =SUM('TRANSFERENCIA CORRIENTE'!C67:E67) -> 0 | C66: =SUM('TRANSFERENCIA CORRIENTE'!F67:H67) -> 0 | D66: =SUM('TRANSFERENCIA CORRIENTE'!I67:K67) -> 0 | E66: =SUM('TRANSFERENCIA CORRIENTE'!L67:N67) -> 0 | G66: =SUM(VS!C67:E67) -> 0 | H66: =SUM(VS!F67:H67) -> 0 | I66: =SUM(VS!I67:K67) -> 0 | J66: =SUM(VS!L67:N67) -> 0 | L66: =SUM(B66+G66) -> 0 | M66: =SUM(C66+H66) -> 0 | N66: =SUM(D66+I66) -> 0 | O66: =SUM(E66+J66) -> 0
A67: 2.8.2 - ADQUISICIÓN DE TÍTULOS VALORES REPRESENTATIVOS DE DEUDA | B67: =SUM('TRANSFERENCIA CORRIENTE'!C68:E68) -> 0 | C67: =SUM('TRANSFERENCIA CORRIENTE'!F68:H68) -> 0 | D67: =SUM('TRANSFERENCIA CORRIENTE'!I68:K68) -> 0 | E67: =SUM('TRANSFERENCIA CORRIENTE'!L68:N68) -> 0 | G67: =SUM(VS!C68:E68) -> 0 | H67: =SUM(VS!F68:H68) -> 0 | I67: =SUM(VS!I68:K68) -> 0 | J67: =SUM(VS!L68:N68) -> 0 | L67: =SUM(B67+G67) -> 0 | M67: =SUM(C67+H67) -> 0 | N67: =SUM(D67+I67) -> 0 | O67: =SUM(E67+J67) -> 0
A68: 2.9 - GASTOS FINANCIEROS | B68: =SUM(B69:B71) -> 0 | C68: =SUM(C69:C71) -> 0 | D68: =SUM(D69:D71) -> 0 | E68: =SUM(E69:E71) -> 0 | G68: =SUM(G69:G71) -> 0 | H68: =SUM(H69:H71) -> 0 | I68: =SUM(I69:I71) -> 0 | J68: =SUM(J69:J71) -> 0 | L68: =SUM(B68+G68) -> 0 | M68: =SUM(C68+H68) -> 0 | N68: =SUM(D68+I68) -> 0 | O68: =SUM(E68+J68) -> 0
A69: 2.9.1 - INTERESES DE LA DEUDA PÚBLICA INTERNA | B69: =SUM('TRANSFERENCIA CORRIENTE'!C70:E70) -> 0 | C69: =SUM('TRANSFERENCIA CORRIENTE'!F70:H70) -> 0 | D69: =SUM('TRANSFERENCIA CORRIENTE'!I70:K70) -> 0 | E69: =SUM('TRANSFERENCIA CORRIENTE'!L70:N70) -> 0 | G69: =SUM(VS!C70:E70) -> 0 | H69: =SUM(VS!F70:H70) -> 0 | I69: =SUM(VS!I70:K70) -> 0 | J69: =SUM(VS!L70:N70) -> 0 | L69: =SUM(B69+G69) -> 0 | M69: =SUM(C69+H69) -> 0 | N69: =SUM(D69+I69) -> 0 | O69: =SUM(E69+J69) -> 0
A70: 2.9.2 - INTERESES DE LA DEUDA PUBLICA EXTERNA | B70: =SUM('TRANSFERENCIA CORRIENTE'!C71:E71) -> 0 | C70: =SUM('TRANSFERENCIA CORRIENTE'!F71:H71) -> 0 | D70: =SUM('TRANSFERENCIA CORRIENTE'!I71:K71) -> 0 | E70: =SUM('TRANSFERENCIA CORRIENTE'!L71:N71) -> 0 | G70: =SUM(VS!C71:E71) -> 0 | H70: =SUM(VS!F71:H71) -> 0 | I70: =SUM(VS!I71:K71) -> 0 | J70: =SUM(VS!L71:N71) -> 0 | L70: =SUM(B70+G70) -> 0 | M70: =SUM(C70+H70) -> 0 | N70: =SUM(D70+I70) -> 0 | O70: =SUM(E70+J70) -> 0
A71: 2.9.4 - COMISIONES Y OTROS GASTOS BANCARIOS DE LA DEUDA PÚBLICA | B71: =SUM('TRANSFERENCIA CORRIENTE'!C72:E72) -> 0 | C71: =SUM('TRANSFERENCIA CORRIENTE'!F72:H72) -> 0 | D71: =SUM('TRANSFERENCIA CORRIENTE'!I72:K72) -> 0 | E71: =SUM('TRANSFERENCIA CORRIENTE'!L72:N72) -> 0 | H71: =SUM(VS!F72:H72) -> 0 | I71: =SUM(VS!I72:K72) -> 0 | J71: =SUM(VS!L72:N72) -> 0 | L71: =SUM(B71+G71) -> 0 | M71: =SUM(C71+H71) -> 0 | N71: =SUM(D71+I71) -> 0 | O71: =SUM(E71+J71) -> 0
A72: Total Gastos | B72: =+B8+B14+B24+B34+B42+B50+B60+B65+B68 -> 2.7188025e+08 | C72: =+C8+C14+C24+C34+C42+C50+C60+C65+C68 -> 1.833009e+08 | D72: =+D8+D14+D24+D34+D42+D50+D60+D65+D68 -> 0 | E72: =+E8+E14+E24+E34+E42+E50+E60+E65+E68 -> 0 | G72: =+G8+G14+G24+G34+G42+G50+G60+G65+G68 -> 26194616 | H72: =+H8+H14+H24+H34+H42+H50+H60+H65+H68 -> 13886365 | I72: =+I8+I14+I24+I34+I42+I50+I60+I65+I68 -> 0 | J72: =+J8+J14+J24+J34+J42+J50+J60+J65+J68 -> 0 | L72: =SUM(B72+G72) -> 2.9807487e+08 | M72: =SUM(C72+H72) -> 1.9718727e+08 | N72: =SUM(D72+I72) -> 0 | O72: =SUM(E72+J72) -> 0
A73: 4 - APLICACIONES FINANCIERAS | B73: =SUM('TRANSFERENCIA CORRIENTE'!C74:E74) -> 0 | C73: =SUM('TRANSFERENCIA CORRIENTE'!F74:H74) -> 0 | D73: =SUM('TRANSFERENCIA CORRIENTE'!I74:K74) -> 0 | E73: =SUM('TRANSFERENCIA CORRIENTE'!L74:N74) -> 0 | G73: =SUM(VS!C74:E74) -> 0 | H73: =SUM(VS!F74:H74) -> 0 | I73: =SUM(VS!I74:K74) -> 0 | J73: =SUM(VS!L74:N74) -> 0 | L73: =SUM(B73+G73) -> 0 | M73: =SUM(C73+H73) -> 0 | N73: =SUM(D73+I73) -> 0 | O73: =SUM(E73+J73) -> 0
A74: 4.1 - INCREMENTO DE ACTIVOS FINANCIEROS | B74: =SUM('TRANSFERENCIA CORRIENTE'!C75:E75) -> 0 | C74: =SUM('TRANSFERENCIA CORRIENTE'!F75:H75) -> 0 | D74: =SUM('TRANSFERENCIA CORRIENTE'!I75:K75) -> 0 | E74: =SUM('TRANSFERENCIA CORRIENTE'!L75:N75) -> 0 | G74: =SUM(VS!C75:E75) -> 0 | H74: =SUM(VS!F75:H75) -> 0 | I74: =SUM(VS!I75:K75) -> 0 | J74: =SUM(VS!L75:N75) -> 0 | L74: =SUM(B74+G74) -> 0 | M74: =SUM(C74+H74) -> 0 | N74: =SUM(D74+I74) -> 0 | O74: =SUM(E74+J74) -> 0
A75: 4.1.1 - INCREMENTO DE ACTIVOS FINANCIEROS CORRIENTES | B75: =SUM('TRANSFERENCIA CORRIENTE'!C76:E76) -> 0 | C75: =SUM('TRANSFERENCIA CORRIENTE'!F76:H76) -> 0 | D75: =SUM('TRANSFERENCIA CORRIENTE'!I76:K76) -> 0 | E75: =SUM('TRANSFERENCIA CORRIENTE'!L76:N76) -> 0 | G75: =SUM(VS!C76:E76) -> 0 | H75: =SUM(VS!F76:H76) -> 0 | I75: =SUM(VS!I76:K76) -> 0 | J75: =SUM(VS!L76:N76) -> 0 | L75: =SUM(B75+G75) -> 0 | M75: =SUM(C75+H75) -> 0 | N75: =SUM(D75+I75) -> 0 | O75: =SUM(E75+J75) -> 0
A76: 4.1.2 - INCREMENTO DE ACTIVOS FINANCIEROS NO CORRIENTES | B76: =SUM('TRANSFERENCIA CORRIENTE'!C77:E77) -> 0 | C76: =SUM('TRANSFERENCIA CORRIENTE'!F77:H77) -> 0 | D76: =SUM('TRANSFERENCIA CORRIENTE'!I77:K77) -> 0 | E76: =SUM('TRANSFERENCIA CORRIENTE'!L77:N77) -> 0 | G76: =SUM(VS!C77:E77) -> 0 | H76: =SUM(VS!F77:H77) -> 0 | I76: =SUM(VS!I77:K77) -> 0 | J76: =SUM(VS!L77:N77) -> 0 | L76: =SUM(B76+G76) -> 0 | M76: =SUM(C76+H76) -> 0 | N76: =SUM(D76+I76) -> 0 | O76: =SUM(E76+J76) -> 0
A77: 4.2 - DISMINUCIÓN DE PASIVOS | B77: =SUM('TRANSFERENCIA CORRIENTE'!C78:E78) -> 0 | C77: =SUM('TRANSFERENCIA CORRIENTE'!F78:H78) -> 0 | D77: =SUM('TRANSFERENCIA CORRIENTE'!I78:K78) -> 0 | E77: =SUM('TRANSFERENCIA CORRIENTE'!L78:N78) -> 0 | G77: =SUM(VS!C78:E78) -> 0 | H77: =SUM(VS!F78:H78) -> 0 | I77: =SUM(VS!I78:K78) -> 0 | J77: =SUM(VS!L78:N78) -> 0 | L77: =SUM(B77+G77) -> 0 | M77: =SUM(C77+H77) -> 0 | N77: =SUM(D77+I77) -> 0 | O77: =SUM(E77+J77) -> 0
A78: 4.2.1 - DISMINUCIÓN DE PASIVOS CORRIENTES | B78: =SUM('TRANSFERENCIA CORRIENTE'!C79:E79) -> 0 | C78: =SUM('TRANSFERENCIA CORRIENTE'!F79:H79) -> 0 | D78: =SUM('TRANSFERENCIA CORRIENTE'!I79:K79) -> 0 | E78: =SUM('TRANSFERENCIA CORRIENTE'!L79:N79) -> 0 | G78: =SUM(VS!C79:E79) -> 0 | H78: =SUM(VS!F79:H79) -> 0 | I78: =SUM(VS!I79:K79) -> 0 | J78: =SUM(VS!L79:N79) -> 0 | L78: =SUM(B78+G78) -> 0 | M78: =SUM(C78+H78) -> 0 | N78: =SUM(D78+I78) -> 0 | O78: =SUM(E78+J78) -> 0
A79: 4.2.2 - DISMINUCIÓN DE PASIVOS NO CORRIENTES | B79: =SUM('TRANSFERENCIA CORRIENTE'!C80:E80) -> 0 | C79: =SUM('TRANSFERENCIA CORRIENTE'!F80:H80) -> 0 | D79: =SUM('TRANSFERENCIA CORRIENTE'!I80:K80) -> 0 | E79: =SUM('TRANSFERENCIA CORRIENTE'!L80:N80) -> 0 | G79: =SUM(VS!C80:E80) -> 0 | H79: =SUM(VS!F80:H80) -> 0 | I79: =SUM(VS!I80:K80) -> 0 | J79: =SUM(VS!L80:N80) -> 0 | L79: =SUM(B79+G79) -> 0 | M79: =SUM(C79+H79) -> 0 | N79: =SUM(D79+I79) -> 0 | O79: =SUM(E79+J79) -> 0
A80: 4.3 - DISMINUCIÓN DE FONDOS DE TERCEROS | B80: =SUM('TRANSFERENCIA CORRIENTE'!C81:E81) -> 0 | C80: =SUM('TRANSFERENCIA CORRIENTE'!F81:H81) -> 0 | D80: =SUM('TRANSFERENCIA CORRIENTE'!I81:K81) -> 0 | E80: =SUM('TRANSFERENCIA CORRIENTE'!L81:N81) -> 0 | G80: =SUM(VS!C81:E81) -> 0 | H80: =SUM(VS!F81:H81) -> 0 | I80: =SUM(VS!I81:K81) -> 0 | J80: =SUM(VS!L81:N81) -> 0 | L80: =SUM(B80+G80) -> 0 | M80: =SUM(C80+H80) -> 0 | N80: =SUM(D80+I80) -> 0 | O80: =SUM(E80+J80) -> 0
A81: 4.3.5 - DISMINUCIÓN DEPÓSITOS FONDOS DE TERCEROS | B81: =SUM('TRANSFERENCIA CORRIENTE'!C82:E82) -> 0 | C81: =SUM('TRANSFERENCIA CORRIENTE'!F82:H82) -> 0 | D81: =SUM('TRANSFERENCIA CORRIENTE'!I82:K82) -> 0 | E81: =SUM('TRANSFERENCIA CORRIENTE'!L82:N82) -> 0 | G81: =SUM(VS!C82:E82) -> 0 | H81: =SUM(VS!F82:H82) -> 0 | I81: =SUM(VS!I82:K82) -> 0 | J81: =SUM(VS!L82:N82) -> 0 | L81: =SUM(B81+G81) -> 0 | M81: =SUM(C81+H81) -> 0 | N81: =SUM(D81+I81) -> 0 | O81: =SUM(E81+J81) -> 0
A82: TOTAL APLICACIONES FINANCIERAS | B82: =SUM(B83) -> 2.7188025e+08 | C82: =SUM(C83) -> 1.833009e+08 | D82: =SUM(D83) -> 0 | E82: =SUM(E83) -> 0 | G82: =SUM(G83) -> 26194616 | H82: =SUM(H83) -> 13886365 | I82: =SUM(I83) -> 0 | J82: =SUM(J83) -> 0 | L82: =SUM(B82+G82) -> 2.9807487e+08 | M82: =SUM(C82+H82) -> 1.9718727e+08 | N82: =SUM(D82+I82) -> 0 | O82: =SUM(E82+J82) -> 0
A83: TOTAL GASTOS Y APLICACIONES FINANCIERAS | B83: =SUM('TRANSFERENCIA CORRIENTE'!C85:E85) -> 2.7188025e+08 | C83: =SUM('TRANSFERENCIA CORRIENTE'!F85:H85) -> 1.833009e+08 | D83: =SUM('TRANSFERENCIA CORRIENTE'!I85:K85) -> 0 | E83: =SUM('TRANSFERENCIA CORRIENTE'!L85:N85) -> 0 | G83: =SUM(VS!C85:E85) -> 26194616 | H83: =SUM(VS!F85:H85) -> 13886365 | I83: =SUM(VS!I85:K85) -> 0 | J83: =SUM(VS!L85:N85) -> 0 | L83: =SUM(B83+G83) -> 2.9807487e+08 | M83: =SUM(C83+H83) -> 1.9718727e+08 | N83: =SUM(D83+I83) -> 0 | O83: =SUM(E83+J83) -> 0

Sheet TRANSFERENCIA CORRIENTE
A1: SERVICIO NACIONAL DE SALUD
A2: HOSPITAL MATERNO INFANTIL SAN LORENZO DE LOS MINA
A3: REGION
A4: Ejecución de Gastos Fondo (100) 2025
A5: En RD$
A7: Detalle | B7: Total | C7: Enero | D7: Febrero | E7: Marzo | F7: Abril | G7: Mayo | H7: Junio | I7: Julio | J7: Agosto | K7: Septiembre | L7: Octubre | M7: Noviembre | N7: Diciembre
A8: 2 - GASTOS
A9: 2.1 - REMUNERACIONES Y CONTRIBUCIONES | B9: =SUM(C9:N9) -> 3.3174744e+08 | C9: =SUM(C10:C14) -> 65091180 | D9: =SUM(D10:D14) -> 67131936 | E9: =SUM(E10:E14) -> 66337620 | F9: =SUM(F10:F14) -> 66556156 | G9: =SUM(G10:G14) -> 66630551 | H9: =SUM(H10:H14) -> 0 | I9: =SUM(I10:I14) -> 0 | J9: =SUM(J10:J14) -> 0 | ... N9: =SUM(N10:N14) -> 0
A10: 2.1.1 - REMUNERACIONES | B10: =SUM(C10:N10) -> 2.7316144e+08 | C10: 53640339 | D10: 55586129 | E10: 54718737 | F10: 54771097 | G10: 54445140
A11: 2.1.2 - SOBRESUELDOS | B11: =SUM(C11:N11) -> 16786972 | C11: 3196999.6 | D11: 3197999.6 | E11: 3199399.6 | F11: 3384964.5 | G11: 3807608.3
A12: 2.1.3 - DIETAS Y GASTOS DE REPRESENTACIÓN | B12: =SUM(C12:N12) -> 0
A13: 2.1.4 - GRATIFICACIONES Y BONIFICACIONES | B13: =SUM(C13:N13) -> 0
A14: 2.1.5 - CONTRIBUCIONES A LA SEGURIDAD SOCIAL | B14: =SUM(C14:N14) -> 41799028 | C14: 8253841.6 | D14: 8347807.5 | E14: 8419483.2 | F14: 8400093.9 | G14: 8377802.1
A15: 2.2 - CONTRATACIÓN DE SERVICIOS | B15: =SUM(C15:N15) -> 11199725 | C15: =SUM(C16:C24) -> 0 | D15: =SUM(D16:D24) -> 1336968.6 | E15: =SUM(E16:E24) -> 7971396.2 | F15: =SUM(F16:F24) -> 210535 | G15: =SUM(G16:G24) -> 1680824.8 | H15: =SUM(H16:H24) -> 0 | I15: =SUM(I16:I24) -> 0 | J15: =SUM(J16:J24) -> 0 | ... N15: =SUM(N16:N24) -> 0
A16: 2.2.1 - SERVICIOS BÁSICOS | B16: =SUM(C16:N16) -> 2141094.3 | E16: 2020024.3 | F16: 60535 | G16: 60535
A17: 2.2.2 - PUBLICIDAD, IMPRESIÓN Y ENCUADERNACIÓN | B17: =SUM(C17:N17) -> 357096.67 | D17: 324206.83 | G17: 32889.84
A18: 2.2.3 - VIÁTICOS | B18: =SUM(C18:N18) -> 0
A19: 2.2.4 - TRANSPORTE Y ALMACENAJE | B19: =SUM(C19:N19) -> 0
A20: 2.2.5 - ALQUILERES Y RENTAS | B20: =SUM(C20:N20) -> 150000 | F20: 150000
A21: 2.2.6 - SEGUROS | B21: =SUM(C21:N21) -> 0
A22: 2.2.7 - SERVICIOS DE CONSERVACIÓN, REPARACIONES MENORES E INSTALACIONES TEMPORALES | B22: =SUM(C22:N22) -> 7648833.7 | D22: 523061.81 | E22: 5951371.9 | G22: 1174400
A23: 2.2.8 - OTROS SERVICIOS NO INCLUIDOS EN CONCEPTOS ANTERIORES | B23: =SUM(C23:N23) -> 902700 | D23: 489700 | G23: 413000
A24: 2.2.9 - OTRAS CONTRATACIONES DE SERVICIOS | B24: =SUM(C24:N24) -> 0
A25: 2.3 - MATERIALES Y SUMINISTROS | B25: =SUM(C25:N25) -> 83130404 | C25: =SUM(C26:C34) -> 4970600.4 | D25: =SUM(D26:D34) -> 14433131 | E25: =SUM(E26:E34) -> 26749552 | F25: =SUM(F26:F34) -> 20368607 | G25: =SUM(G26:G34) -> 16608513 | H25: =SUM(H26:H34) -> 0 | I25: =SUM(I26:I34) -> 0 | J25: =SUM(J26:J34) -> 0 | ... N25: =SUM(N26:N34) -> 0
A26: 2.3.1 - ALIMENTOS Y PRODUCTOS AGROFORESTALES | D26: 591460.4 | E26: 3122436.8 | F26: 812515 | G26: 1657538
A27: 2.3.2 - TEXTILES Y VESTUARIOS | D27: 61630.73 | F27: 1562980.5
A28: 2.3.3 - PRODUCTOS DE PAPEL, CARTÓN E IMPRESOS | D28: 352366.67 | E28: 1474545.2 | F28: 1510942.2 | G28: 765138.96
A29: 2.3.4 - PRODUCTOS FARMACÉUTICOS | C29: 1862880 | D29: 2014526.8 | E29: 6919929 | F29: 6349109 | G29: 2637285.6
A30: 2.3.5 - PRODUCTOS DE CUERO, CAUCHO Y PLÁSTICO | E30: 334708.95 | F30: 506546.35 | G30: 384413.08
A31: 2.3.6 - PRODUCTOS DE MINERALES, METÁLICOS Y NO METÁLICOS | D31: 11630.98 | F31: 351015.88 | G31: 215177.81
A32: 2.3.7 - COMBUSTIBLES, LUBRICANTES, PRODUCTOS QUÍMICOS Y CONEXOS | C32: 1844663.4 | D32: 3902915.5 | E32: 3162523 | F32: 2759191.9 | G32: 4409677.5
A33: 2.3.8 - GASTOS QUE SE ASIGNARÁN DURANTE EL EJERCICIO (ART. 32 Y 33 LEY 423-06)
A34: 2.3.9 - PRODUCTOS Y ÚTILES VARIOS | C34: 1263057 | D34: 7498600.4 | E34: 11735409 | F34: 6516306.6 | G34: 6539281.9
A35: 2.4 - TRANSFERENCIAS CORRIENTES | B35: =SUM(C35:N35) -> 0 | C35: =SUM(C36:C42) -> 0 | D35: =SUM(D36:D42) -> 0 | E35: =SUM(E36:E42) -> 0 | F35: =SUM(F36:F42) -> 0 | G35: =SUM(G36:G42) -> 0 | H35: =SUM(H36:H42) -> 0 | I35: =SUM(I36:I42) -> 0 | J35: =SUM(J36:J42) -> 0 | ... N35: =SUM(N36:N42) -> 0
A36: 2.4.1 - TRANSFERENCIAS CORRIENTES AL SECTOR PRIVADO | B36: =SUM(C36:N36) -> 0
A37: 2.4.2 - TRANSFERENCIAS CORRIENTES AL GOBIERNO GENERAL NACIONAL | B37: =SUM(C37:N37) -> 0
A38: 2.4.3 - TRANSFERENCIAS CORRIENTES A GOBIERNOS GENERALES LOCALES | B38: =SUM(C38:N38) -> 0
A39: 2.4.4 - TRANSFERENCIAS CORRIENTES A EMPRESAS PÚBLICAS NO FINANCIERAS | B39: =SUM(C39:N39) -> 0
A40: 2.4.5 - TRANSFERENCIAS CORRIENTES A INSTITUCIONES PÚBLICAS FINANCIERAS | B40: =SUM(C40:N40) -> 0
A41: 2.4.7 - TRANSFERENCIAS CORRIENTES AL SECTOR EXTERNO | B41: =SUM(C41:N41) -> 0
A42: 2.4.9 - TRANSFERENCIAS CORRIENTES A OTRAS INSTITUCIONES PÚBLICAS | B42: =SUM(C42:N42) -> 0
A43: 2.5 - TRANSFERENCIAS DE CAPITAL | B43: =SUM(C43:N43) -> 0 | C43: =SUM(C44:C50) -> 0 | D43: =SUM(D44:D50) -> 0 | E43: =SUM(E44:E50) -> 0 | F43: =SUM(F44:F50) -> 0 | G43: =SUM(G44:G50) -> 0 | H43: =SUM(H44:H50) -> 0 | I43: =SUM(I44:I50) -> 0 | J43: =SUM(J44:J50) -> 0 | ... N43: =SUM(N44:N50) -> 0
A44: 2.5.1 - TRANSFERENCIAS DE CAPITAL AL SECTOR PRIVADO | B44: =SUM(C44:N44) -> 0
A45: 2.5.2 - TRANSFERENCIAS DE CAPITAL AL GOBIERNO GENERAL NACIONAL | B45: =SUM(C45:N45) -> 0
A46: 2.5.3 - TRANSFERENCIAS DE CAPITAL A GOBIERNOS GENERALES LOCALES | B46: =SUM(C46:N46) -> 0
A47: 2.5.4 - TRANSFERENCIAS DE CAPITAL A EMPRESAS PÚBLICAS NO FINANCIERAS | B47: =SUM(C47:N47) -> 0
A48: 2.5.5 - TRANSFERENCIAS DE CAPITAL A INSTITUCIONES PÚBLICAS FINANCIERAS | B48: =SUM(C48:N48) -> 0
A49: 2.5.6 - TRANSFERENCIAS DE CAPITAL AL SECTOR EXTERNO | B49: =SUM(C49:N49) -> 0
A50: 2.5.9 - TRANSFERENCIAS DE CAPITAL A OTRAS INSTITUCIONES PÚBLICAS | B50: =SUM(C50:N50) -> 0
A51: 2.6 - BIENES MUEBLES, INMUEBLES E INTANGIBLES | B51: =SUM(C51:N51) -> 29103581 | C51: =SUM(C52:C60) -> 0 | D51: =SUM(D52:D60) -> 6461017.3 | E51: =SUM(E52:E60) -> 11396849 | F51: =SUM(F52:F60) -> 4665041.4 | G51: =SUM(G52:G60) -> 6580673.1 | H51: =SUM(H52:H60) -> 0 | I51: =SUM(I52:I60) -> 0 | J51: =SUM(J52:J60) -> 0 | ... N51: =SUM(N52:N60) -> 0
A52: 2.6.1 - MOBILIARIO Y EQUIPO | B52: =SUM(C52:N52) -> 3154544.6 | D52: 432420.86 | E52: 678205 | F52: 1812434.5 | G52: 231484.25
A53: 2.6.2 - MOBILIARIO Y EQUIPO EDUCACIONAL Y RECREATIVO | B53: =SUM(C53:N53) -> 182926.74 | G53: 182926.74
A54: 2.6.3 - EQUIPO E INSTRUMENTAL, CIENTÍFICO Y LABORATORIO | B54: =SUM(C54:N54) -> 21665039 | D54: 6028596.4 | E54: 10715444 | F54: 2635786.9 | G54: 2285211.7
A55: 2.6.4 - VEHÍCULOS Y EQUIPO DE TRANSPORTE, TRACCIÓN Y ELEVACIÓN | B55: =SUM(C55:N55) -> 0
A56: 2.6.5 - MAQUINARIA, OTROS EQUIPOS Y HERRAMIENTAS | B56: =SUM(C56:N56) -> 3755509.5 | E56: 3199.97 | F56: 216820 | G56: 3535489.5
A57: 2.6.6 - EQUIPOS DE DEFENSA Y SEGURIDAD | B57: =SUM(C57:N57) -> 0
A58: 2.6.7 - ACTIVOS BIÓLOGICOS CULTIVABLES | B58: =SUM(C58:N58) -> 0
A59: 2.6.8 - BIENES INTANGIBLES | B59: =SUM(C59:N59) -> 0
A60: 2.6.9 - EDIFICIOS, ESTRUCTURAS, TIERRAS, TERRENOS Y OBJETOS DE VALOR | B60: =SUM(C60:N60) -> 345560.94 | G60: 345560.94
A61: 2.7 - OBRAS | B61: =SUM(C61:N61) -> 0 | C61: =SUM(C62:C65) -> 0 | D61: =SUM(D62:D65) -> 0 | E61: =SUM(E62:E65) -> 0 | F61: =SUM(F62:F65) -> 0 | G61: =SUM(G62:G65) -> 0 | H61: =SUM(H62:H65) -> 0 | I61: =SUM(I62:I65) -> 0 | J61: =SUM(J62:J65) -> 0 | ... N61: =SUM(N62:N65) -> 0
A62: 2.7.1 - OBRAS EN EDIFICACIONES | B62: =SUM(C62:N62) -> 0
A63: 2.7.2 - INFRAESTRUCTURA | B63: =SUM(C63:N63) -> 0
A64: 2.7.3 - CONSTRUCCIONES EN BIENES CONCESIONADOS | B64: =SUM(C64:N64) -> 0
A65: 2.7.4 - GASTOS QUE SE ASIGNARÁN DURANTE EL EJERCICIO PARA INVERSIÓN (ART. 32 Y 33 LEY 423-06) | B65: =SUM(C65:N65) -> 0
A66: 2.8 - ADQUISICION DE ACTIVOS FINANCIEROS CON FINES DE POLÍTICA | B66: =SUM(C66:N66) -> 0 | C66: =SUM(C67:C68) -> 0 | D66: =SUM(D67:D68) -> 0 | E66: =SUM(E67:E68) -> 0 | F66: =SUM(F67:F68) -> 0 | G66: =SUM(G67:G68) -> 0 | H66: =SUM(H67:H68) -> 0 | I66: =SUM(I67:I68) -> 0 | J66: =SUM(J67:J68) -> 0 | ... N66: =SUM(N67:N68) -> 0
A67: 2.8.1 - CONCESIÓN DE PRESTAMOS | B67: =SUM(C67:N67) -> 0
A68: 2.8.2 - ADQUISICIÓN DE TÍTULOS VALORES REPRESENTATIVOS DE DEUDA | B68: =SUM(C68:N68) -> 0
A69: 2.9 - GASTOS FINANCIEROS | B69: =SUM(C69:N69) -> 0 | C69: =SUM(C70:C72) -> 0 | D69: =SUM(D70:D72) -> 0 | E69: =SUM(E70:E72) -> 0 | F69: =SUM(F70:F72) -> 0 | G69: =SUM(G70:G72) -> 0 | H69: =SUM(H70:H72) -> 0 | I69: =SUM(I70:I72) -> 0 | J69: =SUM(J70:J72) -> 0 | ... N69: =SUM(N70:N72) -> 0
A70: 2.9.1 - INTERESES DE LA DEUDA PÚBLICA INTERNA | B70: =SUM(C70:N70) -> 0
A71: 2.9.2 - INTERESES DE LA DEUDA PUBLICA EXTERNA | B71: =SUM(C71:N71) -> 0
A72: 2.9.4 - COMISIONES Y OTROS GASTOS BANCARIOS DE LA DEUDA PÚBLICA | B72: =SUM(C72:N72) -> 0
A73: Total Gastos | B73: =B9+B15+B25+B35+B43+B51+B61+B66+B69 -> 4.5518115e+08 | C73: =C9+C15+C25+C35+C43+C51+C61+C66+C69 -> 70061780 | D73: =D9+D15+D25+D35+D43+D51+D61+D66+D69 -> 89363053 | E73: =E9+E15+E25+E35+E43+E51+E61+E66+E69 -> 1.1245542e+08 | F73: =F9+F15+F25+F35+F43+F51+F61+F66+F69 -> 91800340 | G73: =G9+G15+G25+G35+G43+G51+G61+G66+G69 -> 91500562 | H73: =H9+H15+H25+H35+H43+H51+H61+H66+H69 -> 0 | I73: =I9+I15+I25+I35+I43+I51+I61+I66+I69 -> 0 | ... N73: =N9+N15+N25+N35+N43+N51+N61+N66+N69 -> 0
A74: 4 - APLICACIONES FINANCIERAS
A75: 4.1 - INCREMENTO DE ACTIVOS FINANCIEROS
A76: 4.1.1 - INCREMENTO DE ACTIVOS FINANCIEROS CORRIENTES
A77: 4.1.2 - INCREMENTO DE ACTIVOS FINANCIEROS NO CORRIENTES
A78: 4.2 - DISMINUCIÓN DE PASIVOS
A79: 4.2.1 - DISMINUCIÓN DE PASIVOS CORRIENTES
A80: 4.2.2 - DISMINUCIÓN DE PASIVOS NO CORRIENTES
A81: 4.3 - DISMINUCIÓN DE FONDOS DE TERCEROS
A82: 4.3.5 - DISMINUCIÓN DEPÓSITOS FONDOS DE TERCEROS
A83: TOTAL APLICACIONES FINANCIERAS
A85: TOTAL GASTOS Y APLICACIONES FINANCIERAS | B85: =+B83+B73 -> 4.5518115e+08 | C85: =+C83+C73 -> 70061780 | D85: =+D83+D73 -> 89363053 | E85: =+E83+E73 -> 1.1245542e+08 | F85: =+F83+F73 -> 91800340 | G85: =+G83+G73 -> 91500562 | H85: =+H83+H73 -> 0 | I85: =+I83+I73 -> 0 | ... N85: =+N83+N73 -> 0
A86: Fuente: [fuente]
A87: Fecha de registro: hasta el [día] de [mes] del [año]
A88: Fecha de imputación: hasta el [día] de [mes] del [año]

Sheet VS
A1: SERVICIO NACIONAL DE SALUD
A2: HOSPITAL MATERNO INFANTIL SAN LORENZO DE LOS MINA
A3: REGION
A4: Ejecución de Gastos VENTA SERVICIOS 2025
A5: En RD$
A7: Detalle | B7: Total | C7: Enero | D7: Febrero | E7: Marzo | F7: Abril | G7: Mayo | H7: Junio | I7: Julio | J7: Agosto | K7: Septiembre | L7: Octubre | M7: Noviembre | N7: Diciembre
A8: 2 - GASTOS
A9: 2.1 - REMUNERACIONES Y CONTRIBUCIONES | B9: =SUM(C9:N9) -> 5231553.6 | C9: =SUM(C10:C14) -> 0 | D9: =SUM(D10:D14) -> 0 | E9: =SUM(E10:E14) -> 5231553.6 | F9: =SUM(F10:F14) -> 0 | G9: =SUM(G10:G14) -> 0 | H9: =SUM(H10:H14) -> 0 | I9: =SUM(I10:I14) -> 0 | J9: =SUM(J10:J14) -> 0 | ... N9: =SUM(N10:N14) -> 0
A10: 2.1.1 - REMUNERACIONES | B10: =SUM(C10:N10) -> 0
A11: 2.1.2 - SOBRESUELDOS | B11: =SUM(C11:N11) -> 5231553.6 | E11: 5231553.6
A12: 2.1.3 - DIETAS Y GASTOS DE REPRESENTACIÓN | B12: =SUM(C12:N12) -> 0
A13: 2.1.4 - GRATIFICACIONES Y BONIFICACIONES | B13: =SUM(C13:N13) -> 0
A14: 2.1.5 - CONTRIBUCIONES A LA SEGURIDAD SOCIAL | B14: =SUM(C14:N14) -> 0
A15: 2.2 - CONTRATACIÓN DE SERVICIOS | B15: =SUM(C15:N15) -> 11607459 | C15: =SUM(C16:C24) -> 2733844.3 | D15: =SUM(D16:D24) -> 1213383.4 | E15: =SUM(E16:E24) -> 4359456.2 | F15: =SUM(F16:F24) -> 1256712.1 | G15: =SUM(G16:G24) -> 2044062.6 | H15: =SUM(H16:H24) -> 0 | I15: =SUM(I16:I24) -> 0 | J15: =SUM(J16:J24) -> 0 | ... N15: =SUM(N16:N24) -> 0
A16: 2.2.1 - SERVICIOS BÁSICOS | B16: =SUM(C16:N16) -> 3725633.6 | C16: 351316.33 | D16: 259054.4 | E16: 1731191.2 | F16: 285608.3 | G16: 1098463.4
A17: 2.2.2 - PUBLICIDAD, IMPRESIÓN Y ENCUADERNACIÓN | B17: =SUM(C17:N17) -> 0
A18: 2.2.3 - VIÁTICOS | B18: =SUM(C18:N18) -> 0
A19: 2.2.4 - TRANSPORTE Y ALMACENAJE | B19: =SUM(C19:N19) -> 132000 | D19: 24000 | E19: 32000 | G19: 76000
A20: 2.2.5 - ALQUILERES Y RENTAS | B20: =SUM(C20:N20) -> 1278795.6 | C20: 266664.25 | D20: 252960.9 | F20: 229519.78 | G20: 529650.64
A21: 2.2.6 - SEGUROS | B21: =SUM(C21:N21) -> 0
A22: 2.2.7 - SERVICIOS DE CONSERVACIÓN, REPARACIONES MENORES E INSTALACIONES TEMPORALES | B22: =SUM(C22:N22) -> 4962626.8 | C22: 2064518.4 | D22: =215685.19+42142.86+18061.22+33714.29+21673.47+18061.22+115591.83+7826.53 -> 472756.61 | E22: 2019575.2 | F22: 199877.53 | G22: 205899.14
A23: 2.2.8 - OTROS SERVICIOS NO INCLUIDOS EN CONCEPTOS ANTERIORES | B23: =SUM(C23:N23) -> 1508402.5 | C23: 51345.35 | D23: =193432+11179.44 -> 204611.44 | E23: 576689.87 | F23: =524513+17193.48 -> 541706.48 | G23: 134049.4
A24: 2.2.9 - OTRAS CONTRATACIONES DE SERVICIOS | B24: =SUM(C24:N24) -> 0
A25: 2.3 - MATERIALES Y SUMINISTROS | B25: =SUM(C25:N25) -> 12845714 | C25: =SUM(C26:C34) -> 3062630.7 | D25: =SUM(D26:D34) -> 2432378.3 | E25: =SUM(E26:E34) -> 1797538.3 | F25: =SUM(F26:F34) -> 2995765.2 | G25: =SUM(G26:G34) -> 2557401.6 | H25: =SUM(H26:H34) -> 0 | I25: =SUM(I26:I34) -> 0 | J25: =SUM(J26:J34) -> 0 | ... N25: =SUM(N26:N34) -> 0
A26: 2.3.1 - ALIMENTOS Y PRODUCTOS AGROFORESTALES | B26: =SUM(C26:N26) -> 1950680.8 | C26: 541265 | D26: 300691.8 | E26: 658799 | F26: 94850 | G26: 355075
A27: 2.3.2 - TEXTILES Y VESTUARIOS | B27: =SUM(C27:N27) -> 141128 | G27: 141128
A28: 2.3.3 - PRODUCTOS DE PAPEL, CARTÓN E IMPRESOS | B28: =SUM(C28:N28) -> 1055152 | C28: 85550 | D28: 107616 | E28: 57997 | F28: 196824 | G28: 607165
A29: 2.3.4 - PRODUCTOS FARMACÉUTICOS | B29: =SUM(C29:N29) -> 780100 | C29: 308000 | E29: 250000 | F29: 92000 | G29: 130100
A30: 2.3.5 - PRODUCTOS DE CUERO, CAUCHO Y PLÁSTICO | B30: =SUM(C30:N30) -> 567494.87 | D30: 249831.2 | E30: 317663.67
A31: 2.3.6 - PRODUCTOS DE MINERALES, METÁLICOS Y NO METÁLICOS | B31: =SUM(C31:N31) -> 293957.3 | D31: 183732.33 | E31: 110224.97
A32: 2.3.7 - COMBUSTIBLES, LUBRICANTES, PRODUCTOS QUÍMICOS Y CONEXOS | B32: =SUM(C32:N32) -> 2952794.6 | C32: 228412.84 | D32: 1114592.7 | E32: 317328.99 | F32: 226537 | G32: 1065923
A33: 2.3.8 - GASTOS QUE SE ASIGNARÁN DURANTE EL EJERCICIO (ART. 32 Y 33 LEY 423-06) | B33: =SUM(C33:N33) -> 0
A34: 2.3.9 - PRODUCTOS Y ÚTILES VARIOS | B34: =SUM(C34:N34) -> 5104406.5 | C34: 1899402.8 | D34: =423850.01+52064.22 -> 475914.23 | E34: 85524.69 | F34: =2330135.61+55418.59 -> 2385554.2 | G34: 258010.6
A35: 2.4 - TRANSFERENCIAS CORRIENTES | B35: =SUM(C35:N35) -> 1393167.7 | C35: =SUM(C36:C42) -> 136966.7 | D35: =SUM(D36:D42) -> 23400 | E35: =SUM(E36:E42) -> 127420 | F35: =SUM(F36:F42) -> 624573 | G35: =SUM(G36:G42) -> 480808 | H35: =SUM(H36:H42) -> 0 | I35: =SUM(I36:I42) -> 0 | J35: =SUM(J36:J42) -> 0 | ... N35: =SUM(N36:N42) -> 0
A36: 2.4.1 - TRANSFERENCIAS CORRIENTES AL SECTOR PRIVADO | B36: =SUM(C36:N36) -> 1393167.7 | C36: 136966.7 | D36: 23400 | E36: 127420 | F36: 624573 | G36: 480808
A37: 2.4.2 - TRANSFERENCIAS CORRIENTES AL GOBIERNO GENERAL NACIONAL | B37: =SUM(C37:N37) -> 0
A38: 2.4.3 - TRANSFERENCIAS CORRIENTES A GOBIERNOS GENERALES LOCALES | B38: =SUM(C38:N38) -> 0
A39: 2.4.4 - TRANSFERENCIAS CORRIENTES A EMPRESAS PÚBLICAS NO FINANCIERAS | B39: =SUM(C39:N39) -> 0
A40: 2.4.5 - TRANSFERENCIAS CORRIENTES A INSTITUCIONES PÚBLICAS FINANCIERAS | B40: =SUM(C40:N40) -> 0
A41: 2.4.7 - TRANSFERENCIAS CORRIENTES AL SECTOR EXTERNO | B41: =SUM(C41:N41) -> 0
A42: 2.4.9 - TRANSFERENCIAS CORRIENTES A OTRAS INSTITUCIONES PÚBLICAS | B42: =SUM(C42:N42) -> 0
A43: 2.5 - TRANSFERENCIAS DE CAPITAL | B43: =SUM(C43:N43) -> 0 | C43: =SUM(C44:C50) -> 0 | D43: =SUM(D44:D50) -> 0 | E43: =SUM(E44:E50) -> 0 | F43: =SUM(F44:F50) -> 0 | G43: =SUM(G44:G50) -> 0 | H43: =SUM(H44:H50) -> 0 | I43: =SUM(I44:I50) -> 0 | J43: =SUM(J44:J50) -> 0 | ... N43: =SUM(N44:N50) -> 0
A44: 2.5.1 - TRANSFERENCIAS DE CAPITAL AL SECTOR PRIVADO | B44: =SUM(C44:N44) -> 0
A45: 2.5.2 - TRANSFERENCIAS DE CAPITAL AL GOBIERNO GENERAL NACIONAL | B45: =SUM(C45:N45) -> 0
A46: 2.5.3 - TRANSFERENCIAS DE CAPITAL A GOBIERNOS GENERALES LOCALES | B46: =SUM(C46:N46) -> 0
A47: 2.5.4 - TRANSFERENCIAS DE CAPITAL A EMPRESAS PÚBLICAS NO FINANCIERAS | B47: =SUM(C47:N47) -> 0
A48: 2.5.5 - TRANSFERENCIAS DE CAPITAL A INSTITUCIONES PÚBLICAS FINANCIERAS | B48: =SUM(C48:N48) -> 0
A49: 2.5.6 - TRANSFERENCIAS DE CAPITAL AL SECTOR EXTERNO | B49: =SUM(C49:N49) -> 0
A50: 2.5.9 - TRANSFERENCIAS DE CAPITAL A OTRAS INSTITUCIONES PÚBLICAS | B50: =SUM(C50:N50) -> 0
A51: 2.6 - BIENES MUEBLES, INMUEBLES E INTANGIBLES | B51: =SUM(C51:N51) -> 9003086.4 | C51: =SUM(C52:C60) -> 887994.84 | D51: =SUM(D52:D60) -> 3887510 | E51: =SUM(E52:E60) -> 300539.37 | F51: =SUM(F52:F60) -> 0 | G51: =SUM(G52:G60) -> 3927042.2 | H51: =SUM(H52:H60) -> 0 | I51: =SUM(I52:I60) -> 0 | J51: =SUM(J52:J60) -> 0 | ... N51: =SUM(N52:N60) -> 0
A52: 2.6.1 - MOBILIARIO Y EQUIPO | B52: =SUM(C52:N52) -> 0
A53: 2.6.2 - MOBILIARIO Y EQUIPO EDUCACIONAL Y RECREATIVO | B53: =SUM(C53:N53) -> 0
A54: 2.6.3 - EQUIPO E INSTRUMENTAL, CIENTÍFICO Y LABORATORIO | B54: =SUM(C54:N54) -> 6890067 | C54: 887994.84 | D54: 2075030 | G54: 3927042.2
A55: 2.6.4 - VEHÍCULOS Y EQUIPO DE TRANSPORTE, TRACCIÓN Y ELEVACIÓN | B55: =SUM(C55:N55) -> 107609.37 | E55: 107609.37
A56: 2.6.5 - MAQUINARIA, OTROS EQUIPOS Y HERRAMIENTAS | B56: =SUM(C56:N56) -> 2005410 | D56: 1812480 | E56: 192930
A57: 2.6.6 - EQUIPOS DE DEFENSA Y SEGURIDAD | B57: =SUM(C57:N57) -> 0
A58: 2.6.7 - ACTIVOS BIÓLOGICOS CULTIVABLES | B58: =SUM(C58:N58) -> 0
A59: 2.6.8 - BIENES INTANGIBLES | B59: =SUM(C59:N59) -> 0
A60: 2.6.9 - EDIFICIOS, ESTRUCTURAS, TIERRAS, TERRENOS Y OBJETOS DE VALOR | B60: =SUM(C60:N60) -> 0
A61: 2.7 - OBRAS | B61: =SUM(C61:N61) -> 0 | C61: =SUM(C62:C65) -> 0 | D61: =SUM(D62:D65) -> 0 | E61: =SUM(E62:E65) -> 0 | F61: =SUM(F62:F65) -> 0 | G61: =SUM(G62:G65) -> 0 | H61: =SUM(H62:H65) -> 0 | I61: =SUM(I62:I65) -> 0 | J61: =SUM(J62:J65) -> 0 | ... N61: =SUM(N62:N65) -> 0
A62: 2.7.1 - OBRAS EN EDIFICACIONES | B62: =SUM(C62:N62) -> 0
A63: 2.7.2 - INFRAESTRUCTURA | B63: =SUM(C63:N63) -> 0
A64: 2.7.3 - CONSTRUCCIONES EN BIENES CONCESIONADOS | B64: =SUM(C64:N64) -> 0
A65: 2.7.4 - GASTOS QUE SE ASIGNARÁN DURANTE EL EJERCICIO PARA INVERSIÓN (ART. 32 Y 33 LEY 423-06) | B65: =SUM(C65:N65) -> 0
A66: 2.8 - ADQUISICION DE ACTIVOS FINANCIEROS CON FINES DE POLÍTICA | B66: =SUM(C66:N66) -> 0 | C66: =SUM(C67:C68) -> 0 | D66: =SUM(D67:D68) -> 0 | E66: =SUM(E67:E68) -> 0 | F66: =SUM(F67:F68) -> 0 | G66: =SUM(G67:G68) -> 0 | H66: =SUM(H67:H68) -> 0 | I66: =SUM(I67:I68) -> 0 | J66: =SUM(J67:J68) -> 0 | ... N66: =SUM(N67:N68) -> 0
A67: 2.8.1 - CONCESIÓN DE PRESTAMOS | B67: =SUM(C67:N67) -> 0
A68: 2.8.2 - ADQUISICIÓN DE TÍTULOS VALORES REPRESENTATIVOS DE DEUDA | B68: =SUM(C68:N68) -> 0
A69: 2.9 - GASTOS FINANCIEROS | B69: =SUM(C69:N69) -> 0 | C69: =SUM(C70:C72) -> 0 | D69: =SUM(D70:D72) -> 0 | E69: =SUM(E70:E72) -> 0 | F69: =SUM(F70:F72) -> 0 | G69: =SUM(G70:G72) -> 0 | H69: =SUM(H70:H72) -> 0 | I69: =SUM(I70:I72) -> 0 | J69: =SUM(J70:J72) -> 0 | ... N69: =SUM(N70:N72) -> 0
A70: 2.9.1 - INTERESES DE LA DEUDA PÚBLICA INTERNA | B70: =SUM(C70:N70) -> 0
A71: 2.9.2 - INTERESES DE LA DEUDA PUBLICA EXTERNA | B71: =SUM(C71:N71) -> 0
A72: 2.9.4 - COMISIONES Y OTROS GASTOS BANCARIOS DE LA DEUDA PÚBLICA | B72: =SUM(C72:N72) -> 0
A73: Total Gastos | B73: =B9+B15+B25+B35+B43+B51+B61+B66+B69 -> 40080980 | C73: =C9+C15+C25+C35+C43+C51+C61+C66+C69 -> 6821436.5 | D73: =D9+D15+D25+D35+D43+D51+D61+D66+D69 -> 7556671.6 | E73: =E9+E15+E25+E35+E43+E51+E61+E66+E69 -> 11816507 | F73: =F9+F15+F25+F35+F43+F51+F61+F66+F69 -> 4877050.3 | G73: =G9+G15+G25+G35+G43+G51+G61+G66+G69 -> 9009314.4 | H73: =H9+H15+H25+H35+H43+H51+H61+H66+H69 -> 0 | I73: =I9+I15+I25+I35+I43+I51+I61+I66+I69 -> 0 | ... N73: =N9+N15+N25+N35+N43+N51+N61+N66+N69 -> 0
A74: 4 - APLICACIONES FINANCIERAS
A75: 4.1 - INCREMENTO DE ACTIVOS FINANCIEROS
A76: 4.1.1 - INCREMENTO DE ACTIVOS FINANCIEROS CORRIENTES
A77: 4.1.2 - INCREMENTO DE ACTIVOS FINANCIEROS NO CORRIENTES
A78: 4.2 - DISMINUCIÓN DE PASIVOS
A79: 4.2.1 - DISMINUCIÓN DE PASIVOS CORRIENTES
A80: 4.2.2 - DISMINUCIÓN DE PASIVOS NO CORRIENTES
A81: 4.3 - DISMINUCIÓN DE FONDOS DE TERCEROS
A82: 4.3.5 - DISMINUCIÓN DEPÓSITOS FONDOS DE TERCEROS
A83: TOTAL APLICACIONES FINANCIERAS
A85: TOTAL GASTOS Y APLICACIONES FINANCIERAS | B85: =+B83+B73 -> 40080980 | C85: =+C83+C73 -> 6821436.5 | D85: =+D83+D73 -> 7556671.6 | E85: =+E83+E73 -> 11816507 | F85: =+F83+F73 -> 4877050.3 | G85: =+G83+G73 -> 9009314.4
A86: Fuente: [fuente]
A87: Fecha de registro: hasta el [día] de [mes] del [año]
A88: Fecha de imputación: hasta el [día] de [mes] del [año]

Sheet OBLIGACIONES PENDIENTES
B4: SERVICIO REGIONAL DE SALUD
B5: DIRECCIÓN DE FISCALIZACIÓN Y CONTROL
B6: DETALLE OBLIGACIONES CONTRAÍDAS PENDIENTES AL 31 DE MAYO 2025
B7: HOSPITAL MATERNO INFANTIL SAN LORENZO DE LOS MINA
B8: A | C8: B | E8: C | F8: D | G8: E | H8: F
B9: TIPO | C9: PERÍODO | F9: STATUS PRESTAMO
C10: DESDE | D10: HASTA | E10: MONTO | F10: MONTO ORIGEN | G10: MONTO AMORTIZADO | H10: BALANCE PENDIENTE
B11: PROMESE CAL
B12: RETENCIONES DE IMPUESTOS (DGII) | C12: 44470 | D12: 45808 | E12: =6455721.37+191917.63+545919.42+146780.59+231604.06+289366.65+335354.64+387110.47+660164.03+254405.37+295100.71+268154.84+476725.77+301006.83+418780.67+471731.75+276884.63+183994.68+296760.59 -> 12487485
B13: APROVISIONAMIENTOS DE INCENTIVOS | C13: 45505 | D13: 45808 | E13: =4432093.625+933892.46+332731.24+782528.07-5231553.59+751870.91 -> 2001562.7
B14: SEGURIDAD SOCIAL
B15: APROVISIONAMIENTO DE REGALIA PASCUAL
B16: PRESTACIONES LABORALES
B17: VIATICOS
B18: PRÉSTAMOS Y/O ANTICIPOS FINANCIEROS OTORGADOS POR SENASA
B19: TOTAL | E19: =SUM(E12:E18)+E11 -> 14489047
B21: Nota. En el caso de las columnas D, E y F, solo aplican para llenado de los préstamos otogados por SENASA.
B25: Preparado por: | E25: Revisado por:

Sheet INGR SEGUN ORIGEN
A3: Servicio Nacional de Salud
A4: Dirección de Fiscalización
A6: Comportamiento de Ingresos percibidos Segregados según Origen
A7: Establecimiento: HOSPITAL MATERNO INFANTIL SAN LORENZO DE LOS MINA Mes: MAYO . Año: 2025 SRS: I
A8: . | B8: ARS | C8: Fecha deposito | D8: No. De Documento de referencia | E8: valor de Transferencia o Cheque
A9: INGRESOS | B9: FONDO 100(2.1) | E9: =79621891.83+4931430 -> 84553322
B10: FONDO 100(2.3) | E10: 12593841
B11: FONDO 100(2.6) | E11: 3169632.1
A12: Sub-Total | E12: =SUM(E9:E11) -> 1.003168e+08
B13: ARS YUNEN | C13: 45778 | E13: 155606.87
B14: ARS SENASA SUBSIDIADO | C14: 45783 | E14: 3199661.2
B15: SENASA(POR ATENCION ODONTOGICA) | C15: 45783 | E15: 50000
B16: ASEMAP | C16: 45784 | E16: 12182.4
B17: ARS MONUMENTAL | C17: 45785 | E17: 84594.85
B18: ARS SENASA PENSIONADO | C18: 45790 | E18: 13000
B19: ARS RESERVAS | C19: 45792 | E19: 79987.57
B20: SENASA CONTRIBUTIVO | C20: 45793 | E20: 2588374.1
B21: ARS CMD | C21: 45796 | E21: 61607.99
B22: ARS MAPHRE | C22: 45797 | E22: 54068.8
B23: ARS MAPHRE | C23: 45797 | E23: 12721.54
B24: ARS MAPHRE | C24: 45797 | E24: 375966.29
... B27: ARS FUTURO | C27: 45807 | E27: 493974.92
B28: INGR. POR FACT DE SERV. DE INSTITUCIONES
A29: Sub-Total | E29: =SUM(E13:E28) -> 7518709.1
A30: OTROS APORTES | B30: Cafetería | E30: 150000
B31: Odontologia (facturacion servicios no contemplado en Plan Basico) | C31: 01-05-2025 AL 31-05-2025 | E31: 284450
B32: Alquiler de espacios internos a terceros
B33: Aportes provenientes de convenios Institucionales | C33: DESDE FEBRERO- ABRIL 2025 | E33: 15000
B34: INGRESOS POR SERVICIOS PACIENTES PRIVADOS Y DIFERENCIAS POR SEGUROS MEDICOS
B35: Atenciones a Pacientes Extranjeros | C35: 01-05-2025 AL 31-05-2025 | E35: 124850
B36: Otros (Identificar Fuente )
A37: Sub-Total | E37: =SUM(E30:E35) -> 574300
A38: Total General | E38: =E29+E37+E12 -> 1.084098e+08
A41: Bajo las funciones que nos asisten certificamos que el valor de los ingresos percibidos durante el mes de marzo de 2025, correspondieron a un monto de RD$108,409,804.19
A44: Dado a los 31/05/2025
A46: Cuenta Núm. | B46: Balance en libro | C46: Balance en Banco | D46: Balance Conciliado
A47: 010-390450-6 | B47: 1377881.2 | C47: 3821033.6 | D47: 1731116.6
A53: Preparado por: | D53: Revisado por:
B54: ____________________________________ | D54: ___________________________________
A55: Aprobado por:
B56: ________________________________

Sheet DEUDA
A1: Servicio Nacional de Salud
A2: DIRECCION DE FISCALIZACION
A3: RELACION DEUDA
A4: ESTABLECIMIENTO: | B4: HOSPITAL MATERNO INFANTIL SAN LORENZO DE LOS MINA | D4: CUENTAS POR PAGAR A: | E4: 45778
A6: NO | B6: NOMBRES PROVEEDOR | C6: CONCEPTO | D6: FUENTE FINANCIMIENTO | E6: Años anteriores 2020 | F6: AL 31 DICIEMBRE 2021 | G6: AL 31 DICIEMBRE 2022 | H6: AL 31 DICIEMBRE 2023 | I6: Al 31 DICIEMBRE 2024 | J6: AL 31 DE ENERO 2025 | K6: AL 28 DE FEBRERO 2025 | L6: 31 DE MARZO 2025 | M6: 30 DE ABRIL 2025 | N6: 31 DE MAYO 2025 | O6: TOTAL ADEUDA
A7: 1 | B7: Hospifar, SRL | C7: 44963 | D7: VS/FG | H7: 11375 | O7: =SUM(E7:N7) -> 11375
A8: =+A7+1 -> 2 | B8: Hospifar, SRL | C8: 44963 | D8: VS/FG | H8: 94965 | O8: =SUM(E8:N8) -> 94965
A9: =+A8+1 -> 3 | B9: Ventas Diversas Farmaceuticas, SRL (VENDIFAR) | C9: 45042 | D9: VS/FG | H9: 224775 | O9: =SUM(E9:N9) -> 224775
A10: =+A9+1 -> 4 | B10: GA INTERPRISE IMPORT, SRL | C10: 45055 | D10: VS/FG | H10: 287920 | O10: =SUM(E10:N10) -> 287920
A11: =+A10+1 -> 5 | B11: D, CORA INDUSTRIAL, S.R.L | C11: 45083 | D11: VS/FG | H11: 220483.05 | O11: =SUM(E11:N11) -> 220483.05
A12: =+A11+1 -> 6 | B12: Bio Nuclear, SA | C12: 45092 | D12: VS/FG | H12: 4182 | O12: =SUM(E12:N12) -> 4182
A13: =+A12+1 -> 7 | B13: VARA, SRL. | C13: 45092 | D13: VS/FG | H13: 58382.86 | O13: =SUM(E13:N13) -> 58382.86
A14: =+A13+1 -> 8 | B14: Morami, SRL | C14: 45135 | D14: VS/FG | H14: 213260 | O14: =SUM(E14:N14) -> 213260
A15: =+A14+1 -> 9 | B15: Leromed Pharma, SRL | C15: 45155 | D15: VS/FG | H15: 167208 | O15: =SUM(E15:N15) -> 167208
A16: =+A15+1 -> 10 | B16: Caribbean Integrated Solutions, SRL | C16: 45184 | D16: VS/FG | H16: 400 | O16: =SUM(E16:N16) -> 400
A17: =+A16+1 -> 11 | B17: SLYKING GROUP, SRL | C17: 45292 | D17: VS/FG | I17: 39361.26 | O17: =SUM(E17:N17) -> 39361.26
A18: =+A17+1 -> 12 | B18: LE.F.P CONSULTORES SRL | C18: 45327 | D18: VS/FG | I18: 48852 | O18: =SUM(E18:N18) -> 48852
A19: =+A18+1 -> 13 | B19: LE.F.P CONSULTORES SRL | C19: 45327 | D19: VS/FG | I19: 48852 | O19: =SUM(E19:N19) -> 48852
A20: =+A19+1 -> 14 | B20: Bio Nova, SRL | C20: 45352 | D20: VS/FG | I20: 94341 | O20: =SUM(E20:N20) -> 94341
A21: =+A20+1 -> 15 | B21: FARMACIA RUTH | C21: 45385 | D21: VS/FG | I21: 3450 | O21: =SUM(E21:N21) -> 3450
A22: =+A21+1 -> 16 | B22: Insocorp, S.R.L. | C22: 45394 | D22: VS/FG | I22: 162462.4 | O22: =SUM(E22:N22) -> 162462.4
A23: =+A22+1 -> 17 | B23: SLYKING GROUP, SRL | C23: 45446 | D23: VS/FG | I23: 240720 | O23: =SUM(E23:N23) -> 240720
A24: =+A23+1 -> 18 | B24: LE.F.P CONSULTORES SRL | C24: 45476 | D24: VS/FG | I24: 48852 | O24: =SUM(E24:N24) -> 48852
A25: =+A24+1 -> 19 | B25: LE.F.P CONSULTORES SRL | C25: 45476 | D25: VS/FG | I25: 48852 | O25: =SUM(E25:N25) -> 48852
A26: =+A25+1 -> 20 | B26: UNIQUE REPRESENTACIONES, S.R.L | C26: 45503 | D26: VS/FG | I26: 112271.1 | O26: =SUM(E26:N26) -> 112271.1
A27: =+A26+1 -> 21 | B27: Delia Josefina Tatis Perdomo | C27: 45506 | D27: VS/FG | I27: 56168 | O27: =SUM(E27:N27) -> 56168
A28: =+A27+1 -> 22 | B28: J. JIREH EQUIPOS MEDICOS SRL | C28: 45593 | D28: VS/FG | I28: 16520 | O28: =SUM(E28:N28) -> 16520
... A30: =+A29+1 -> 24 | B30: FARMACIA RUTH | C30: 45625 | D30: VS/FG | I30: 77150 | O30: =SUM(E30:N30) -> 77150
A31: =+A30+1 -> 25 | B31: Insocorp, S.R.L. | C31: 45667 | D31: VS/FG | J31: 20060 | O31: =SUM(E31:N31) -> 20060
A32: =+A31+1 -> 26 | B32: Insocorp, S.R.L. | C32: 45702 | D32: VS/FG | K32: 137691.84 | O32: =SUM(E32:N32) -> 137691.84
A33: =+A32+1 -> 27 | B33: Super Latop Browsing SRL | C33: 45719 | D33: VS/FG | L33: 413000 | O33: =SUM(E33:N33) -> 413000
A34: =+A33+1 -> 28 | B34: JBW LEGER INGENIEROS SRL | C34: 45719 | D34: VS/FG | L34: 1361145 | O34: =SUM(E34:N34) -> 1361145
A35: =+A34+1 -> 29 | B35: FARMACIA RUTH | C35: 45720 | D35: VS/FG | L35: 7250 | O35: =SUM(E35:N35) -> 7250
A36: =+A35+1 -> 30 | B36: PATRIA RIVAS LABORATORIO CLINICO | C36: 45724 | D36: VS/FG | L36: 3500 | O36: =SUM(E36:N36) -> 3500
A37: =+A36+1 -> 31 | B37: Bio Nova, SRL | C37: 45738 | D37: VS/FG | L37: 107989.6 | O37: =SUM(E37:N37) -> 107989.6
A38: =+A37+1 -> 32 | B38: Agua Planeta Azul, SA | C38: 45740 | D38: VS/FG | L38: 9500 | O38: =SUM(E38:N38) -> 9500
A39: =+A38+1 -> 33 | B39: Abrias Novo Group SRL | C39: 45742 | D39: VS/FG | L39: 216333.29 | O39: =SUM(E39:N39) -> 216333.29
A40: =+A39+1 -> 34 | B40: REGULATORY | C40: 45744 | D40: VS/FG | L40: 1475000 | O40: =SUM(E40:N40) -> 1475000
A41: =+A40+1 -> 35 | B41: FARMACIA RUTH | C41: 45748 | D41: VS/FG | M41: 13900 | O41: =SUM(E41:N41) -> 13900
A42: =+A41+1 -> 36 | B42: FARMACIA RUTH | C42: 45748 | D42: VS/FG | M42: 13900 | O42: =SUM(E42:N42) -> 13900
A43: =+A42+1 -> 37 | B43: Agua Planeta Azul, SA | C43: 45749 | D43: VS/FG | M43: 9480 | O43: =SUM(E43:N43) -> 9480
A44: =+A43+1 -> 38 | B44: Bio Win, SRL | C44: 45750 | D44: VS/FG | M44: 2400 | O44: =SUM(E44:N44) -> 2400
A45: =+A44+1 -> 39 | B45: Bio Win, SRL | C45: 45750 | D45: VS/FG | M45: 2400 | O45: =SUM(E45:N45) -> 2400
A46: =+A45+1 -> 40 | B46: PATRIA RIVAS LABORATORIO CLINICO | C46: 45750 | D46: VS/FG | M46: 44763 | O46: =SUM(E46:N46) -> 44763
A47: =+A46+1 -> 41 | B47: Bio Nuclear, SA | C47: 45754 | D47: VS/FG | M47: 49106.2 | O47: =SUM(E47:N47) -> 49106.2
A48: =+A47+1 -> 42 | B48: Agua Planeta Azul, SA | C48: 45756 | D48: VS/FG | M48: 9360 | O48: =SUM(E48:N48) -> 9360
A49: =+A48+1 -> 43 | B49: CAPEGAR SRL | C49: 45761 | D49: VS/FG | M49: 781979.39 | O49: =SUM(E49:N49) -> 781979.39
A50: =+A49+1 -> 44 | B50: Agua Planeta Azul, SA | C50: 45762 | D50: VS/FG | M50: 8160 | O50: =SUM(E50:N50) -> 8160
A51: =+A50+1 -> 45 | B51: Abrias Novo Group SRL | C51: 45763 | D51: VS/FG | M51: 148119.29 | O51: =SUM(E51:N51) -> 148119.29
A52: =+A51+1 -> 46 | B52: Papelería E. Impresos Crishoan, SRL | C52: 45763 | D52: VS/FG | M52: 271282 | O52: =SUM(E52:N52) -> 271282
... A57: =+A56+1 -> 51 | B57: Centro de la Sangre y Especialidades, SRL | C57: 45777 | D57: VS/FG | M57: 24000 | O57: =SUM(E57:N57) -> 24000
A58: =+A57+1 -> 52 | B58: FARMACIA RUTH | C58: 45778 | D58: VS/FG | N58: 18500 | O58: =SUM(E58:N58) -> 18500
A59: =+A58+1 -> 53 | B59: JT Investdent, SRL | C59: 45778 | D59: VS/FG | N59: 174761.32 | O59: =SUM(E59:N59) -> 174761.32
A60: =+A59+1 -> 54 | B60: JT Investdent, SRL | C60: 45779 | D60: VS/FG | N60: 271990 | O60: =SUM(E60:N60) -> 271990
A61: =+A60+1 -> 55 | B61: Xavier Vargas, Ingeniería Electromecánica, EIRL | C61: 45783 | D61: VS/FG | N61: 1726315 | O61: =SUM(E61:N61) -> 1726315
A62: =+A61+1 -> 56 | B62: Abrias Novo Group SRL | C62: 45784 | D62: VS/FG | N62: 254532.85 | O62: =SUM(E62:N62) -> 254532.85
A63: =+A62+1 -> 57 | B63: Abrias Novo Group SRL | C63: 45784 | D63: VS/FG | N63: 259599.95 | O63: =SUM(E63:N63) -> 259599.95
A64: =+A63+1 -> 58 | B64: Abrias Novo Group SRL | C64: 45784 | D64: VS/FG | N64: 262738.81 | O64: =SUM(E64:N64) -> 262738.81
A65: =+A64+1 -> 59 | B65: DIUCAM GROUP SRL | C65: 45784 | D65: VS/FG | N65: 272005.91 | O65: =SUM(E65:N65) -> 272005.91
A66: =+A65+1 -> 60 | B66: Farmaco Internacional, SRL | C66: 45790 | D66: VS/FG | N66: 214259.64 | O66: =SUM(E66:N66) -> 214259.64
A67: =+A66+1 -> 61 | B67: ROPHARMA, SRL | C67: 45792 | D67: VS/FG | N67: 42000 | O67: =SUM(E67:N67) -> 42000
A68: =+A67+1 -> 62 | B68: ROPHARMA, SRL | C68: 45792 | D68: VS/FG | N68: 170000 | O68: =SUM(E68:N68) -> 170000
A69: =+A68+1 -> 63 | B69: Empresa Rotricomercial, SRL | C69: 45792 | D69: VS/FG | N69: 194700 | O69: =SUM(E69:N69) -> 194700
... A76: =+A75+1 -> 70 | B76: Global Multi-Pharma Dominicana THM, SRL | C76: 45796 | D76: VS/FG | N76: 264000 | O76: =SUM(E76:N76) -> 264000
A77: 1 | B77: Abrias Novo Group SRL | C77: 45798 | D77: VS/FG | N77: 40275.82 | O77: =SUM(E77:N77) -> 40275.82
A78: =+A77+1 -> 2 | B78: Abrias Novo Group SRL | C78: 45798 | D78: VS/FG | N78: 196877.8 | O78: =SUM(E78:N78) -> 196877.8
A79: =+A78+1 -> 3 | B79: SUPLIMED,SRL | C79: 45799 | D79: VS/FG | N79: 220500 | O79: =SUM(E79:N79) -> 220500
A80: =+A79+1 -> 4 | B80: SUPLIMED,SRL | C80: 45799 | D80: VS/FG | N80: 220500 | O80: =SUM(E80:N80) -> 220500
A81: =+A80+1 -> 5 | B81: CEM CARIBBEAN EQUIPMENT MEDICAL | C81: 45800 | D81: VS/FG | N81: 668000 | O81: =SUM(E81:N81) -> 668000
A82: =+A81+1 -> 6 | B82: WILSON FRIAS | C82: 45803 | D82: VS/FG | N82: 181999.13 | O82: =SUM(E82:N82) -> 181999.13
A83: TOTAL GENERAL | E83: =SUM(E7:E82) -> 0 | G83: =SUM(G7:G82) -> 0 | H83: =SUM(H7:H82) -> 1282950.9 | I83: =SUM(I7:I82) -> 1008626.8 | J83: =SUM(J7:J82) -> 20060 | K83: =SUM(K7:K82) -> 137691.84 | L83: =SUM(L7:L82) -> 3593717.9 | M83: =SUM(M7:M82) -> 1898698.6 | N83: =SUM(N7:N82) -> 8623546.6 | O83: =SUM(O7:O82) -> 16565293

Sheet Hoja1
D1: 11550 | E1: INGRESOS POR EXTRANJEROS
A2: 155606.87 | B2: ARS YUNEN | D2: 3000 | E2: INGRESOS POR EXTRANJEROS | G2: 150000 | H2: CAFETERIA
A3: 3199661.2 | B3: ARS SENASA SUBSIDIADO | D3: 4000 | E3: INGRESOS POR EXTRANJEROS | G3: 15000 | H3: FEBRERO, MARZO Y ABRIL 2025, UCE
A4: 50000 | B4: ARS SENASA SUBSIDIADO | D4: 4000 | E4: INGRESOS POR EXTRANJEROS | G4: =SUM(G2:G3) -> 165000
A5: 12182.4 | B5: ASEMAP | D5: 4000 | E5: INGRESOS POR EXTRANJEROS
A6: 84594.85 | B6: ARS MONUMENTAL | D6: 8000 | E6: INGRESOS POR EXTRANJEROS
A7: 13000 | B7: SENASA PENSIONADO | D7: 3200 | E7: INGRESOS POR EXTRANJEROS
A8: 79987.57 | B8: ARS RESERVAS | D8: 4000 | E8: INGRESOS POR EXTRANJEROS
A9: 2588374.1 | B9: ARS SENASA CONTRIBUTIVO | D9: 4000 | E9: INGRESOS POR EXTRANJEROS
A10: 61607.99 | B10: CMD | D10: 3500 | E10: INGRESOS POR EXTRANJEROS
A11: 54068.8 | B11: ARS MAPHRE | D11: 2100 | E11: INGRESOS POR EXTRANJEROS
A12: 12721.54 | B12: ARS MAPHRE | D12: 3500 | E12: INGRESOS POR EXTRANJEROS
A13: 375966.29 | B13: ARS MAPHRE | D13: 4000 | E13: INGRESOS POR EXTRANJEROS
A14: 304098.74 | B14: ARS PRIMERA | D14: 4000 | E14: INGRESOS POR EXTRANJEROS
A15: 32863.84 | B15: ARS META SALUD | D15: 7100 | E15: INGRESOS POR EXTRANJEROS
A16: 493974.92 | B16: ARS FUTURO | D16: 23600 | E16: INGRESOS POR EXTRANJEROS
A17: =SUM(A2:A16) -> 7518709.1 | D17: 31300 | E17: INGRESOS POR EXTRANJEROS
D18: 22000
D19: 13900
D20: =SUM(D1:D19) -> 160750
D22: 1000 | E22: ODONTOLOGIA
D23: 1500
D24: 1800 | E24: ODONTOLOGIA
D25: 2000
D26: 2000
D27: 2000
D28: 2000
D29: 2000
D30: 2000
D31: 2000
D32: 2000
D33: 2000
D34: 2000
D35: 2000
D36: 2000
D37: 2500
D38: 2500 | E38: ODONTOLOGIA
D39: 2800 | E39: ODONTOLOGIA
D40: 2900 | E40: ODONTOLOGIA
D41: 3000
D42: 3000
D43: 3000
D44: 3000
D45: 3000
D46: 3000
D47: 3000
D48: 3100 | E48: ODONTOLOGIA
D49: 3500
D50: 3500
D51: 3700 | E51: ODONTOLOGIA
D52: 3700 | E52: ODONTOLOGIA
D53: 4100 | E53: ODONTOLOGIA
D54: 4400 | E54: ODONTOLOGIA
D55: 4600 | E55: ODONTOLOGIA
D56: 4600 | E56: ODONTOLOGIA
D57: 4700 | E57: ODONTOLOGIA
D58: 4900 | E58: ODONTOLOGIA
D59: 5000
D60: 5400 | E60: ODONTOLOGIA
D61: 5400 | E61: ODONTOLOGIA
D62: 5500 | E62: ODONTOLOGIA
D63: 5600 | E63: ODONTOLOGIA
D64: 5750 | E64: ODONTOLOGIA
D65: 5800 | E65: ODONTOLOGIA
D66: 5800
D67: 6000 | E67: ODONTOLOGIA
D68: 6200 | E68: ODONTOLOGIA
D69: 7000
D70: 7100 | E70: ODONTOLOGIA
D71: 7500 | E71: ODONTOLOGIA
D72: 8800 | E72: ODONTOLOGIA
D73: 9100 | E73: ODONTOLOGIA
D74: 10100 | E74: ODONTOLOGIA
D75: 11600 | E75: ODONTOLOGIA
D76: 11900 | E76: ODONTOLOGIA
D77: 14200 | E77: ODONTOLOGIA
D80: =SUM(D22:D79) -> 248550
D81: =+D80+D20 -> 409300
D82: =+D80+D20+A17+G4 -> 8093009.1
D83: 8093009.1
D84: =+D82-D83 -> 0

Sheet INGRESOS POR A.R.S
A2: Servicio Nacional De Salud
A3: Dirección de Fiscalizacion
A4: Ingresos Por Facturación ARS
A6: Establecimiento: | C6: HOSPITAL MATERNO INFANTIL SAN LORENZO DE LOS MINA
A8: ARS | C8: ENERO | E8: FEBRERO | G8: MARZO | I8: ABRIL | K8: MAYO | M8: JUNIO | O8: JULIO | Q8: AGOSTO | S8: SEPTIEMBRE | U8: OCTUBRE | W8: NOVIEMBRE | Y8: DICIEMBRE
C9: Facturado | D9: Recibido | E9: Facturado | F9: Recibido | G9: Facturado | H9: Recibido | I9: Facturado | J9: Recibido | K9: Facturado | L9: Recibido | M9: Facturado | N9: Recibido | O9: Facturado | P9: Recibido | Q9: Facturado | R9: Recibido | S9: Facturado | T9: Recibido | U9: Facturado | V9: Recibido | W9: Facturado | X9: Recibido | Y9: Facturado | Z9: Recibido
A10: 1 | B10: SENASA SUBSIDIADO | C10: 4027257.3 | D10: 4833111.5 | E10: 4840265.3 | F10: 5841673.2 | G10: =13000+3146909.72 -> 3159909.7 | H10: =4595181.39+50000 -> 4645181.4 | I10: =6959.16+1939523.55 -> 1946482.7 | J10: =100000+2942930.33+10949.64 -> 3053880 | K10: 3199661.2 | L10: =3199661.24+50000 -> 3249661.2
A11: 2 | B11: SENASA CONTRIBUTIVO | C11: 1094583.8 | E11: 2417181.1 | F11: 2152926.5 | G11: 2645113.9 | H11: 1041144.3 | I11: 3267715.2 | J11: 2326715 | K11: 2490193.7 | L11: 2588374.1
B12: SENASA JUB. Y PENS. | C12: 0 | D12: 0 | E12: 10985.64 | G12: 0 | K12: 2134.86 | L12: 13000
A13: Total SeNaSa | C13: =SUM(C10:C12) -> 5121841.1 | D13: =SUM(D10:D12) -> 4833111.5 | E13: =SUM(E10:E12) -> 7268432.1 | F13: =SUM(F10:F12) -> 7994599.7 | G13: =SUM(G10:G12) -> 5805023.6 | H13: =SUM(H10:H12) -> 5686325.7 | I13: =SUM(I10:I12) -> 5214198 | J13: =SUM(J10:J12) -> 5380594.9 | ... Z13: =SUM(Z10:Z12) -> 0
A14: 3 | B14: PALIC SALUD | C14: 211714.57 | D14: 206908.45 | E14: =65463.45+12918.96+311477.59 -> 389860 | G14: =53140.7+6743.06+130031.72 -> 189915.48 | H14: =16298.76+15397.47+30434.4+65463.45+12863.4+155572.92+309977.48+504 -> 606511.88 | I14: =54068.8+12721.58+382067.66 -> 448858.04 | J14: =51140.7+129754.16+6696.74 -> 187591.6 | K14: =47703.2+8425.36+117128.56 -> 173257.12 | L14: =54068.8+12721.54+375966.29 -> 442756.63
A15: 4 | B15: ARL
A16: 5 | B16: RENACER | C16: 275352.44 | D16: 156983.55 | E16: 222716.34 | F16: 272552.44 | G16: 73918.68 | H16: 222620.34 | J16: 73057.08
A17: 6 | B17: YUNEN | C17: 7848.94 | D17: 55135.74 | E17: 14338.35 | F17: 7848.94 | G17: 162551.53 | H17: 14338.35 | I17: 37897.65 | J17: 19489.76 | K17: 45390.42 | L17: 155606.87
A18: 7 | B18: UNIVERSAL
A19: 8 | B19: ARS HUMANO | C19: 44770.98 | E19: 16720.82 | F19: 97648.3 | G19: 83376.61 | H19: 34117.68 | I19: 77617.28 | J19: 97704.2 | K19: 29761.8
A20: 9 | B20: ARS PLANSALUD BANCO CENTRAL
A21: 10 | B21: SEMMA | C21: 7193.05 | D21: 15993.02 | E21: 28868.13 | F21: 9531.6 | G21: 10657.5 | H21: 77169.4 | I21: 27941.11 | J21: =28868.13+6393.05 -> 35261.18 | K21: 99169.27
A22: 11 | B22: FUTURO | C22: 269639.73 | D22: 234503.89 | E22: 617068.65 | G22: 366095.18 | H22: 356314.76 | I22: 395799.78 | J22: 388735.9 | K22: 525599.56 | L22: 493974.92
A23: 12 | B23: APS | C23: 69588.33 | E23: 122630.62 | F23: 8262.07 | G23: 43770.8 | H23: 212345.21 | I23: 55860.67 | K23: 109234.31
A24: 13 | B24: SALUD SEGURA
A25: 14 | B25: CONSTITUCION
A26: 15 | B26: META SALUD | C26: 1396 | E26: 20821.36 | F26: 31949.94 | G26: 80842.17 | H26: 1396 | I26: 32922.74 | K26: 3500 | L26: 32863.84
A27: 16 | B27: ASEMAP | C27: 4869.52 | D27: 6475.14 | E27: 102975.46 | F27: 4869.52 | G27: 6619.63 | H27: 102672.34 | I27: 12257.4 | J27: 6619.63 | K27: 111906.17 | L27: 12182.4
A28: 17 | B28: GMA | C28: 76159.34 | E28: 186957.88 | G28: 136798.59 | I28: 83229.31 | K28: 9976.34
A29: 18 | B29: MONUMENTAL | C29: 75131.09 | D29: 71992.2 | E29: 146560.32 | G29: 85258.31 | H29: 237322.18 | I29: 119188.62 | J29: 146560.32 | K29: 58287.88 | L29: 84594.85
A30: 19 | B30: CMD | C30: 273646.7 | D30: 273646.7 | E30: 41285.9 | F30: 41071.9 | G30: 22435.77 | H30: 11220.43 | I30: 61608.05 | J30: 22435.77 | K30: 31245 | L30: 61607.99
A31: 20 | B31: RESERVAS | C31: 48081.02 | D31: 48081.02 | E31: 217047.26 | G31: 79962.77 | I31: 61346.15 | K31: 57351.74 | L31: 79987.57
A32: 21 | B32: SIMAG | C32: 28637.51 | E32: 92478.63 | G32: 2821.24 | I32: 1604 | K32: 3360
A33: 22 | B33: SEMUNASED
A34: 23 | B34: SERVICIOS MEDICOS UASD
A35: 24 | B35: PRIMERA ARS HUMANO | C35: 259154.57 | E35: 439967.13 | F35: 870590.25 | G35: 404678.83 | H35: 262926.38 | I35: 432554.37 | J35: 534014.43 | K35: 317521.34 | L35: 304098.74
B36: EXTRANJEROS | K36: 80323.32
A37: Total ARS PRIVADAS | C37: =SUM(C14:C35) -> 1653183.8 | D37: =SUM(D14:D35) -> 1069719.7 | E37: =SUM(E14:E35) -> 2660296.9 | F37: =SUM(F14:F35) -> 1344325 | G37: =SUM(G14:G35) -> 1749703.1 | H37: =SUM(H14:H35) -> 2138955 | I37: =SUM(I14:I35) -> 1848685.2 | J37: =SUM(J14:J35) -> 1511469.9 | K37: =SUM(K14:K36) -> 1655884.3 | L37: =SUM(L14:L35) -> 1667673.8 | M37: =SUM(M14:M35) -> 0 | N37: =SUM(N14:N35) -> 0 | O37: =SUM(O14:O35) -> 0 | P37: =SUM(P14:P35) -> 0 | Q37: =SUM(Q14:Q35) -> 0 | R37: =SUM(R14:R35) -> 0 | S37: =SUM(S14:S35) -> 0 | ... Z37: =SUM(Z14:Z35) -> 0
A38: TOTAL | C38: =C13+C37 -> 6775024.9 | D38: =D13+D37 -> 5902831.2 | E38: =E13+E37 -> 9928728.9 | F38: =F13+F37 -> 9338924.6 | G38: =G13+G37 -> 7554726.7 | H38: =H13+H37 -> 7825280.6 | I38: =I13+I37 -> 7062883.1 | J38: =J13+J37 -> 6892064.8 | ... Z38: =Z13+Z37 -> 0
A40: Preparado por:
A41: Licda.

Sheet GLOSA
A1: Servicio Nacional de Salud
A2: Dirección de Fiscalización
A3: Glosa /mes
A4: Establecimientos | B4: Facturado | C4: Recibido | D4: Glosado | E4: %
A5: Enero | B5: 6775024.9 | C5: 5902831.2 | D5: 102835 | E5: =+D5/C5 -> 0.017421301
A6: Febrero | B6: 9928728.9 | C6: 9338924.6 | D6: =147829.22+68679.07+4547.79 -> 221056.08 | E6: =+D6/C6 -> 0.0236704
A7: Marzo | B7: 7643032.2 | C7: 7825280.7 | D7: 99442.51 | E7: =+D7/C7 -> 0.012707852
A8: Abril | B8: 6994829.1 | C8: 6892064.8 | D8: 68054 | E8: =+D8/C8 -> 0.0098742542
A9: Mayo | B9: 7347874.1 | C9: 7518709.1 | D9: =47721.02+68532.2 -> 116253.22 | E9: =+D9/C9 -> 0.015461859
A10: Junio
A11: Julio
A12: Agosto
A13: Septiembre
A14: Octubre
A15: Noviembre
A16: Diciembre
A17: Total | B17: =SUM(B5:B13) -> 38689489 | C17: =SUM(C5:C13) -> 37477810 | D17: =SUM(D5:D13) -> 607640.81 | E17: =+D17/C17 -> 0.016213349
A19: Preparado por:
A20: Licda.
