Workbook

Sheet RELACION DE PAGOS EMITIDOS
A5: DIRECCION DE FISCALIZACION Y CONTROL
A6: RELACION DE PAGOS EMITIDOS DURANTE EL MES
A7: ESTABLECIMIENTO: HOSPITAL MATERNO INFANTIL SAN LORENZO DE LOS MINA
A9: PAGOS CORRESPONDIENTES AL MES : SEPTIEMBRE 2025
A10: FECHA | B10: LIBRAMIENTO | C10: TRANSFERENCIA | D10: CHEQUE | E10: BENEFICIARIO | F10: NO.FACTURAS | G10: VALOR DE FACTURA | H10: VALOR PAGADO
A11: 45697 | C11: 290 | E11: LORA & ALMONTE REPARACIONES, SRL | F11: PAGO DE FACT NCF NO. B1500000209 POR ADQUISICION DE TANQUE DE AGUA DE 120 GL, PARA SER UTILIZADOS EN EL CUARTO DE BOMBA ESTE HOSPITAL, SEGÚN ORDEN DE COMPRA HSLM-2025-00862 | G11: 177799.99 | H11: 170266.1
A12: 45786 | C12: 291 | E12: CABOD, SRL | F12: PAGO DE FACTS NCFS NOS, B1500001833 y B1500001837, POR ADQUISICION DE DETERGENTE PARA LAVANDERIA, SEGÚN ORDEN DE COMPRA HSLM-2025-00615 (SALDO DE LA ORDEN) | G12: 155677.4 | H12: 149080.9
A13: 45786 | C13: 292 | E13: PRODUCTOS CANO SRL | F13: PAGO NCF B1500001400, POR ADQUISICION DE PAN SEGÚN O/C HSLM-2025-00118. | G13: 90600 | H13: 86070
A14: 45786 | C14: 293 | E14: BIO-WIN | F14: PAGO DE FACT NCF NO. B1500002583, B1500002591, POR ADQUISICION DE SANGRE DE CARNERO, SEGÚN ORDEN DE COMPRA HSLM-2025-00669 | G14: 4800 | H14: 4560
A15: 45786 | C15: 294 | E15: PLANETA AZUL | F15: PAGO DE FACT NCF E4500000014324, POR ADQUISICION DE BOTELLAS DE AGUA 16.9 ONZ,, SEGÚN ORDEN DE COMPRA 2025-00649 | G15: 14000 | H15: 14000
A16: 45786 | C16: 295 | E16: PLANETA AZUL, SA | F16: PAGO DE FACT NCF E4500000017083, E4500000017078 Y E4500000017088 POR ADQUISICION DE BOTELLONES DE AGUA, SEGÚN ORDEN DE COMPRA 2025-00587 | G16: 30060 | H16: 30060
A17: 45786 | C17: 296 | E17: PLANETA AZUL, SA | F17: PAGO DE FACT NCF E4500000009906, POR ADQUISICION DE BOTELLITAS DE AGUA DE 16.9 OZ, SEGÚN ORDEN DE COMPRA 2025-00323 | G17: 7000 | H17: 7000
A18: 45786 | C18: 297 | E18: AIR LIQUIDE DOMINICANA, SAS | F18: PAGO DE FACT NCF E4500000003124, POR ADQUISICION DE SERVICIOS DE INSTALACION Y MANTENIMIENTO DE LA RED DE OXIGENO DEL HOSPITAL, SEGÚN ORDEN DE COMPRA HSLM-2025-00860 | G18: 132966.46 | H18: 132966.46
A19: 45786 | C19: 298 | E19: JESUS FERMIN MARTINEZ | F19: PAGO DE FACT NCF NO B1500000459, POR SERVICIO DE TRANSPORTE, SEGÚN ORDEN DE COMPRA HSLM-2025-00709 | G19: 16000 | H19: 15200
A20: 45786 | C20: 299 | E20: AYUNTAMIENTO SANTO DOMINGO ESTE | F20: PAGO NCF NO B1500056270, POR SERVICIO DE RECOGIDA DE DESECHOS SOLIDOS EN EL MES DE AGOSTO 2025 | G20: 25000 | H20: 25000
A21: 45786 | C21: 300 | E21: ALTICE DOMINICANA S,A | F21: PAGO NCF E450000017823, POR SERVICIO DE COMUNICACIÓN PERIODO FACTURADO 01/09/2025 CUENTA 12843802 | G21: 111421.68 | H21: 111421.68
A22: 45786 | C22: 301 | E22: Lilian Yomayra Encarnación de Matos | F22: pago de regencia y renovación del permiso de drogas y farmacia del hospital, perteneciente al mes de agosto 2025 | G22: 25000 | H22: 25000
... A27: 46000 | C27: 306 | E27: INVERSIONES FH, SRL | F27: PAGO NCF B1500001543 ADQUISICION DE TICKETS DE COMBUSTIBLE SEGÚN O/C HSLM-2025-00912 | G27: 172000 | H27: 170573.26
A28: 17/09/2025 | C28: 307 | E28: FARMACO QUIMICA NACIONAL, SA | F28: ADQUISICION DE VALVULA HIDROCEFALICA, SEGÚN ORDEN DE COMPRA HSLM-2025-00943 | G28: 27704.04 | H28: 26530.14
A29: 18/09/2025 | C29: 308 | E29: TROPIGAS DOMINICANA, SRL | F29: PAGO DE FACT NCF NO. E450000005486, POR ADQUISICION DE GAS LICUADO DE PETROLEO SEGÚN ORDEN DE COMPRA HSLM-2025-00730 | G29: 22638 | H29: 22638
A30: 18/09/2025 | C30: 309 | E30: CENTRO DE LA SANGRE Y ESPECIALIDADES Y ESPECIALIDADES SRL | F30: PAGO NCF B1500000413, SERVICIO DE SANGRE PARA PACIENTES INTERNOS SEGÚN O/C HSLM-2025-00428. | G30: 74000 | H30: 70300
A31: 18/09/2025 | C31: 310 | E31: AYUNTAMIENTO SANTO DOMINGO ESTE | F31: PAGO NCF NO B1500056466, POR SERVICIO DE RECOGIDA DE DESECHOS SOLIDOS EN EL MES DE SEPTIEMBRE 2025 | G31: 25000 | H31: 25000
A32: 18/9/2025 | C32: 311 | E32: LABORATORIO CLINICO LCDA PATRIA M RIVAS SRL | F32: PAGO NCF NO E4500000000115 Y E4500000000098, POR SERVICIO DE ESTUDIOS ESPECIALIZADOS SEGÚN ORDEN DE COMPRA HSLM-2025-00312 | G32: 76045 | H32: 76045
A33: 18/09/2025 | C33: 312 | E33: CENTRO DE ESTUDIOS MEDICOS Y DIAGNOSTICOS POR IMÁGENES, SRL | F33: PAGO DE FACT NCF B1500000407, POR SERVICIOS DE ESTUDIOS ESPECIALIZADOS A PACIENTES INTERNOS SEGÚN O/C HSLM-2025-00311 | G33: 44300 | H33: 42085
A34: 18/09/2025 | C34: 313 | E34: WILSON HUMBERTO CIRINEO DE LA CRUZ | F34: PAGO DE FACT NCF B1500000002, POR INSTALACION DE CUBICULO Y DIVISION DE OFICINA, SEGÚN ORDEN DE COMPRA HSLM-2025-00839 | G34: 180568 | H34: 173003
A35: 18/09/2025 | C35: 314 | E35: OFITOP, SRL | F35: PAGO DE FACT NCF NO. B1500000013, POR ADQUISICION DE LETRERO TIPO SEÑALIZACION EN ACRILICO ROTULADO EN VINYL, SEGÚN ORDEN DE COMPRA HSLM-2025-00767 | G35: 136880 | H35: 131080
A36: 18/09/2025 | C36: 315 | E36: CARLOS RAFAEL DE PAULA ROSSO | F36: PAGO DE FACT NCF NO. B1500000070, POR ADQUISICION DE REPARACION DE AIRE ACONDICIONADO, SEGÚN ORDEN DE COMPRA HSLM-2025-00915 | G36: 396975.6 | H36: 380154.6
A37: 18/09/2025 | C37: 316 | E37: OFITOP, SRL | F37: PAGO DE FACT NCF NO. B1500000012, POR ADQUISICION DE NEVERA EJECUTIVA Y MOBILIARIO, SEGÚN ORDEN DE COMPRA HSLM-2025-00879 | G37: 248301.03 | H37: 237779.8
A38: 18/9/2025 | C38: 317 | E38: OFITOP, SRL | F38: PAGO DE FACT NCF NO. B1500000011, POR ADQUISICION DE LAMINADOS EN VINIL ADHESIVO, SEGÚN ORDEN DE COMPRA HSLM-2025-00816 | G38: 132840.57 | H38: 127211.73
A39: 22/09/2025 | C39: 318 | E39: PRODUCTOS TECNOLOGICOS E INDUSTRIALES JARDIN DEL EDEN, E.I.R.L | F39: PAGO DE FACT NCF NO. B1500000090, POR ADQUISICION DE DETERGENTE PARA LA LAVANDERIA, SEGÚN ORDEN DE COMPRA HSLM-2025-00918 | G39: 365139.2 | H39: 349667.2
... A43: 26/09/2025 | C43: 322 | E43: OSCAR A RENTA NEGRON, SA | F43: ADQUISICION DE MEDICAMENTOS, | G43: 34270.4 | H43: 34270.4
A44: 29/9/2025 | C44: 322-A | E44: NOMINA INCENTIVOS | F44: PAGO NOMINA INCENTIVO SENASA ENERO-JULIO 2025 | G44: 4413127.6 | H44: 4413127.6
A45: 03/09/2025 | B45: 3911 | E45: Insocorp, SRL | F45: PAGO DE FACT NCF B1500000231 POR ADQUISICION DE ASPIRADORES DE SECRECIONES ELECTRICAS SEGUN O/C HSLM- 2025-00724. | G45: 1945820
A46: 03/09/2025 | B46: 3915 | E46: Insocorp, SRL | F46: PAGO DE FACT NCF B1500000226 POR ADQUISICION DE LENTE DE LAPAROSCOPIA SEGUN O/C HSLM-2025-00857. | G46: 271000
A47: 03/09/2025 | B47: 3919 | E47: Corporacion Medica A.G., SRL | F47: PAGO DE FACT NCF B1500000128 POR ADQUISICION DE PAPEL GRADO MEDICO SEGUN O/C HSLM-2025-00858. | G47: 260780
A48: 03/09/2025 | B48: 3923 | E48: Tu Amigo, SRL | F48: PAGO DE FACT NCF B1500000312 POR ADQUISICION DE GASOIL REGULAR SEGUN O/C HSLM-2025-00842. | G48: 337200
A49: 03/09/2025 | B49: 3927 | E49: Ofitop, S.R.L | F49: PAGO DE FACT NCF B1500000007 POR ADQUISICION DE SILLA CAJERO, SILLON SEMI EJECUTIVO Y SILLA DE VISITA SEGUN O/C HSLM-2025-00795. | G49: 260443.67
A50: 03/09/2025 | B50: 3932 | E50: Ofitop, S.R.L | F50: PAGO DE FACT NCF B1500000008 POR ADQUISICION DE SILLA CAJERO SEGUN O/C HSLM-2025-00798. | G50: 45366.46
A51: 04/09/2025 | B51: 3936 | E51: Abrias Novo Group SRL | F51: PAGO DE FACT NCF B1500000157 POR ADQUISICION DE COCTEL SIN ALCOHOL PARA 500 PERSONAS SEGUN O/C HSLM-2025-00821. | G51: 242313
A52: 04/09/2025 | B52: 3940 | E52: Lambda Diagnósticos, SRL | F52: PAGO DE FACT NCF B1500002206 POR ADQUISICION DE REACTIVOS Y UTILES MEDICOS SEGUN O/C HSLM-2024-01177. | G52: 163477.94
A53: 04/09/2025 | B53: 3944 | E53: Copem Hospiclinic, SRL | F53: PAGO DE FACT NCF B1500003181 POR ADQUISICION DE MEDICAMENTOS SEGUN O/C HSLM-2024-00997. | G53: 75000
A54: 04/09/2025 | B54: 3948 | E54: Farmaco Internacional, SRL | F54: PAGO DE FACT NCF E450000000074 POR ADQUISICION DE UTILES MEDICOS SEGUN O/C HSLM-2025-00828. | G54: 259328
A55: 04/09/2025 | B55: 3952 | E55: Empresa Rotricomercial, SRL | F55: PAGO DE FACT NCF B1500000391 POR ADQUISICION DE MEDICAMENTOS SEGUN O/C HSLM-2025-00829. | G55: 271700
A56: 05/09/2025 | B56: 3963 | E56: Ropharma, SRL | F56: PAGO DE FACT NCF B1500001427 POR ADQUISICION DE MEDICAMENTOS SEGUN O/C HSLM-2025-00826. | G56: 180000
... A148: 30/09/2025 | B148: 4463 | E148: A&S Importadora Medicas, SRL | F148: PAGO DE FACT NCF NO. B1500002450, POR ADQUISICION DE UTIL MEDICO Y MEDICAMENTO, SEGUN ORDEN DE COMPRA HSLM-2025-00955 | G148: 221736
A149: 45697 | D149: 37290 | E149: ELVIS EMMANUEL DE LA ROSA NUÑEZ | F149: PAGO POR SERVICIO DE MANTENIMIENTO MECANICO PARA LA AMBULANCIA DE ESTE HOSPITAL, SEGÚN ORDEN DE SERVICIO 0044 | G149: 33714.29 | H149: 28000
A150: 45878 | D150: 37291 | E150: DELMIRA GARCIA | F150: REPOSICION DEL FONDO DE CAJA CHICA | G150: 55617.91 | H150: 55617.91
A151: 18/09/2025 | D151: 37292 | E151: FREDY OSCAR RODRIGUEZ RIVAS | F151: COLABORACION PARA CAVAR HOYO Y CERTIFICACION DE ACTAS DE DEFUNCION | G151: 3600 | H151: 3600
A152: 22/9/2025 | D152: 37293 | E152: NULO | F152: NULO | G152: 0 | H152: 0
A153: 22/9/2025 | D153: 37294 | E153: NULO | F153: NULO | G153: 0 | H153: 0
A154: 22/9/2025 | D154: 37295 | E154: DELMIRA GARCIA | F154: REPOSICION DEL FONDO DE CAJA CHICA | G154: 56472.04 | H154: 56472.04
A155: 26/09/2025 | D155: 37296 | E155: NULO | F155: NULO | G155: 0 | H155: 0
A156: 26/09/2025 | D156: 37297 | E156: SANTIAGO RUDECINTO SORIANO | F156: COLABORACION PARA REALIZAR EL ESTUDIO DE GAMMAGRAFIA HEPATUBILIAR, PARA DESCARTAR SINDROME COLESTASICO EN ESTUDIO, ATRESIA BILIAR | G156: 18000 | H156: 18000
A157: 26/9/2025 | D157: 37298 | E157: RUDDY SEGURA | F157: PAGO POR EL SERVICIO DE LIMPIEZA Y CLORIFICACION DE LAS CISTERNAS DE ESTE HOSPITAL, SEGÚN ORDEN HSLM-CD-2025-0054. | G157: 21673.47 | H157: 18000
A158: 26/09/2025 | D158: 37299 | E158: NELSON YNFANTE VELAZQUEZ | F158: SERVICIO DE PINTURA PARA EL PRIMER NIVEL DE ESTE HOSPITAL, SEGÚN ORDEN DE SERVICIO HSLM-CD-2025-0056 | G158: 18061.22 | H158: 15000
A159: 26/09/2025 | D159: 37300 | E159: ALEXANDER MENDEZ CONTRERAS | F159: PAGO POR EL SERVICIO DE JARDINERIA Y MANTENIMIENTO DE AREAS VERDES DE ESTE HOSPITAL, SEGÚN ORDEN HSLM-CD-2025-0055. | G159: 18061.22 | H159: 15000
A160: 26/09/2025 | D160: 37301 | E160: OVIDIO DE JESUS DURAN CLEMENTE | F160: PAGO POR SERVICIO DE TRANSPORTE DE LA AMBULANCIA CORRESPONDIENTE AL MES DE SEPTIEMBRE 2025. | G160: 20000 | H160: 20000
A161: 30/09/2025 | E161: COMISIONES BANCARIAS | F161: PAGO POR COMISION BANCARIA | G161: 21179.93 | H161: 21179.93
A162: Total | G162: =SUM(G11:G161) -> 1.2174192e+08 | H162: =SUM(H11:H161) -> 11126440
A164: RESUMEN DE GASTOS
A165: PAGOS A PROVEEDORES | C165: =+G162-C166-C168-C167 -> 41078960
A166: CAJA CHICA | C166: =+G154+G150 -> 112089.95
A167: NOMINA | C167: =+G81+G68+G67+G44+G44 -> 80417759
A168: OTROS GASTOS | C168: =+G160+G159+G157+G158+G156+G155+G153+G153+G152+G151+G149 -> 133110.2
A169: TOTAL GENERAL | C169: =+C165+C166+C167+C168 -> 1.2174192e+08

Sheet RELACION ORDENES DE COMPRAS
A4: SERVICIO NACIONAL DE SALUD
A5: DIRECCION DE FISCALIZACION
A6: RELACIÓN DE ORDENES DE COMPRAS DE BIENES Y SERVICIOS EFECTUADAS MES DE SEPTIEMBRE 2025
A7: ESTABLECIMIENTO: HOSPITAL MATERNO INFANTIL SAN LORENZO DE LOS MINA REGION OZAMA
A8: Fecha | B8: # Orden de Compra o Servicios | C8: # DE EXPEDIENTE(PROCESO CELEBRADO) | D8: No. De Factura Fiscal NCF | E8: Fuente. Financ (FR-VS) | F8: Beneficiario | G8: Rubro | H8: No. Cta. Objetal del Gasto | I8: Valor | J8: Status del proceso | K8: solo observar cuando se presentas esos procesos
A9: 45901.419 | B9: HSML-2025-00698 | C9: HSLM-DAF-CD-2025-0698 | F9: Margayu, SRL | G9: 50110000 | H9: Productos de carne y aves de corral | I9: 227500 | J9: Adjudicado
A10: 45901.459 | B10: HSML-2025-00882 | C10: HSLM-DAF-CD-2025-0699 | F10: Farmacia Ruth, SRL | G10: 85120000 | H10: Práctica médica | I10: 270000 | J10: Adjudicado
A11: 45901.459 | B11: HSML-2025-00880 | C11: HSLM-DAF-CD-2025-0700 | F11: Corporacion Medica A.G., SRL | G11: 42280000 | H11: Productos para la esterilización médica | I11: 260780 | J11: Adjudicado
A12: 45901.626 | B12: HSML-2025-00885 | C12: HSLM-DAF-CD-2025-0701 | F12: Farmaco Internacional, SRL | G12: 42220000 | H12: Productos para administración intravenosa y arterial | I12: 216825 | J12: Adjudicado
A13: 45901.626 | B13: HSML-2025-00884 | C13: HSLM-DAF-CD-2025-0702 | F13: Empresa Rotricomercial, SRL | G13: 51190000 | H13: Agentes que afectan el agua y los electrolitos | I13: 240000 | J13: Adjudicado
A14: 45902.42 | B14: HSML-2025-00886 | C14: HSLM-DAF-CD-2025-0703 | F14: Dumas Pharmaceuticals, SRL | G14: 42200000 | H14: Productos de hacer imágenes diagnósticas médicas y de medicina nuclear | I14: 197768 | J14: Adjudicado
A15: 45902.46 | B15: HSML-2025-00910 | C15: HSLM-DAF-CM-2025-0220 | F15: INSOCORP, SRL | G15: 42290000 | H15: Productos quirúrgicos | I15: 708000 | J15: Adjudicado
A16: 45902.503 | B16: HSML-2025-00909 | C16: HSLM-DAF-CM-2025-0221 | F16: INSOCORP, SRL | G16: 42290000 | H16: Productos quirúrgicos | I16: 354815 | J16: Adjudicado
A17: 45902.507 | B17: HSML-2025-00808 | C17: HSLM-DAF-CD-2025-0704 | F17: INSOCORP, SRL | G17: 41100000 | H17: Equipo de laboratorio y científico | I17: 26550 | J17: Adjudicado
A18: 45902.542 | B18: HSML-2025-00902 | C18: HSLM-DAF-CD-2025-0705 | F18: Jhonathan Del Rosario Franco | G18: 80120000 | H18: Servicios legales | I18: 17700 | J18: Adjudicado
A19: 45902.585 | B19: HSML-2025-00901 | C19: HSLM-DAF-CD-2025-0706 | F19: Diucam Group SRL | G19: 47130000 | H19: Suministros de aseo y limpieza | I19: 212400 | J19: Adjudicado
A20: 45903.419 | B20: HSML-2025-00897 | C20: HSLM-DAF-CD-2025-0707 | F20: Sermetic, SRL | G20: 71120000 | H20: Servicios de construcción y perforación de pozos | I20: 90049 | J20: Adjudicado
... A66: 45915.418 | B66: HSML-2025-00937 | C66: HSLM-DAF-CD-2025-0739 | F66: Diucam Group SRL | G66: 47130000 | H66: Suministros de aseo y limpieza | I66: 264674 | J66: Adjudicado
A67: 45915.459 | B67: Analisis de oferta | C67: HSLM-DAF-CD-2025-0741 | G67: 50200000 | H67: Bebidas | J67: Evaluación
A68: 45915.459 | B68: HSML-2025-00938 | C68: HSLM-DAF-CD-2025-0740 | F68: Papelería E. Impresos Crishoan, SRL | G68: 44120000 | H68: Suministros de oficina | I68: 271072 | J68: Adjudicado
A69: 45915.503 | B69: HSML-2025-00940 | C69: HSLM-DAF-CD-2025-0742 | F69: Bello-Lab, SRL | G69: 42290000 | H69: Productos quirúrgicos | I69: 206175 | J69: Adjudicado
A70: 45916.419 | B70: HSML-2025-00941 | C70: HSLM-DAF-CD-2025-0743 | F70: Diucam Group SRL | G70: 47130000 | H70: Suministros de aseo y limpieza | I70: 256532 | J70: Adjudicado
A71: 45916.431 | B71: HSML-2025-00943 | C71: HSLM-DAF-CD-2025-0744 | F71: Farmaco Quimica Nacional, SA | G71: 42180000 | H71: Productos de examen y control del paciente | I71: 27704 | J71: Adjudicado
A72: 45916.502 | B72: HSML-2025-00975 | C72: HSLM-DAF-CM-2025-0237 | F72: Negocios Suheidy Rodriguez, SRL | G72: 24110000 | H72: Recipientes y almacenamiento | I72: 858450 | J72: Adjudicado
A73: 45916.543 | B73: HSML-2025-00946 | C73: HSLM-DAF-CD-2025-0745 | F73: Dumas Pharmaceuticals, SRL | G73: 51180000 | H73: Hormonas y antagonistas hormonales | I73: 26900 | J73: Adjudicado
A74: 45916.569 | B74: HSML-2025-00947 | C74: HSLM-DAF-CD-2025-0746 | F74: Oficclin Comercial, SRL | G74: 51120000 | H74: Medicamentos cardiovasculares | I74: 145220 | J74: Adjudicado
A75: 45917.334 | B75: HSML-2025-00992 | C75: HSLM-DAF-CM-2025-0238 | F75: Khris Aus Pharmacy, S.R.L | G75: 51100000 | H75: Medicamentos antiinfecciosos | I75: 1200000 | J75: Adjudicado
A76: 45917.424 | B76: HSML-2025-00951 | C76: HSLM-DAF-CD-2025-0747 | F76: CEM Caribbean Equipment Medical, SRL | G76: 14110000 | H76: Productos de papel | I76: 28462 | J76: Adjudicado
A77: 45917.469 | B77: HSML-2025-00953 | C77: HSLM-DAF-CD-2025-0748 | F77: Osiris & Co, SA | G77: 42240000 | H77: Productos medicinales de deportes y ortopédicos y prótesis | I77: 212738 | J77: Adjudicado
A78: 45917.507 | B78: HSML-2025-00950 | C78: HSLM-DAF-CD-2025-0749 | F78: Antares Pharma, SRL | G78: 51100000 | H78: Medicamentos antiinfecciosos | I78: 225000 | J78: Adjudicado
A79: 45917.585 | B79: HSML-2025-00952 | C79: HSLM-DAF-CD-2025-0750 | F79: G & M Gelmat Comercial, SRL | G79: 51150000 | H79: Medicamentos para el sistema nervioso autónomo | I79: 144000 | J79: Adjudicado
... A97: 45922.514 | B97: HSML-2025-00974 | C97: HSLM-DAF-CD-2025-0767 | F97: Medequip, SRL | G97: 47120000 | H97: Equipo de aseo | I97: 168003 | J97: Adjudicado
A98: 45922.626 | B98: Analisis de oferta | C98: HSLM-DAF-CM-2025-0240 | G98: 50100000 | H98: Frutos secos | J98: Evaluación
A99: 45922.708 | B99: HSML-2025-00979 | C99: HSLM-DAF-CD-2025-0768 | F99: Grupo Irmaceli Services, S.R.L. | G99: 46190000 | H99: Protección contra incendios | I99: 135936 | J99: Adjudicado
A100: 45923.419 | B100: Analisis de oferta | C100: HSLM-DAF-CM-2025-0241 | G100: 50110000 | H100: Productos de carne y aves de corral | J100: Evaluación
A101: 45923.461 | B101: HSML-2025-00978 | C101: HSLM-DAF-CD-2025-0769 | F101: Suplimed, SRL | G101: 42310000 | H101: Productos para el cuidado de heridas | I101: 172643 | J101: Adjudicado
A102: 45923.502 | B102: HSML-2025-00976 | C102: HSLM-DAF-CD-2025-0772 | F102: Hauspital, SRL | G102: 42270000 | H102: Productos de resucitación, anestesia y respiratorio | I102: 159300 | J102: Adjudicado
A103: 45923.503 | B103: Analisis de oferta | C103: HSLM-DAF-CM-2025-0242 | G103: 50110000 | H103: Productos de carne y aves de corral | J103: Evaluación
A104: 45923.503 | B104: HSML-2025-00977 | C104: HSLM-DAF-CD-2025-0771 | F104: Hauspital, SRL | G104: 51190000 | H104: Agentes que afectan el agua y los electrolitos | I104: 117000 | J104: Adjudicado
A105: 45923.503 | B105: HSML-2025-00980 | C105: HSLM-DAF-CD-2025-0770 | F105: Bello-Lab, SRL | G105: 41110000 | H105: Instrumentos de medida, observación y ensayo | I105: 272294 | J105: Adjudicado
A106: 45925.438 | B106: HSML-2025-00981 | C106: HSLM-DAF-CD-2025-0773 | F106: Destreza Comercial, SRL | G106: 42270000 | H106: Productos de resucitación, anestesia y respiratorio | I106: 272595 | J106: Adjudicado
A107: 45925.479 | B107: Analisis de oferta | C107: HSLM-DAF-CM-2025-0244 | G107: 52130000 | H107: Tratamientos de ventanas | J107: Publicado
A108: 45925.503 | B108: HSML-2025-00982 | C108: HSLM-DAF-CD-2025-0774 | F108: Diucam Group SRL | G108: 43210000 | H108: Equipo informático y accesorios | I108: 75520 | J108: Adjudicado
A109: 45925.503 | B109: Analisis de oferta | C109: HSLM-DAF-CM-2025-0243 | G109: 50190000 | H109: Alimentos preparados y conservados | J109: Publicado
A110: 45925.507 | B110: HSML-2025-00983 | C110: HSLM-DAF-CD-2025-0776 | F110: Morami, SRL | G110: 51100000 | H110: Medicamentos antiinfecciosos | I110: 119000 | J110: Adjudicado
A111: 45925.543 | B111: cancelado | C111: HSLM-DAF-CD-2025-0775 | G111: 56100000 | H111: Muebles de alojamiento | J111: Cancelado
A112: 45925.543 | B112: HSML-2025-00984 | C112: HSLM-DAF-CD-2025-0777 | F112: Morami, SRL | G112: 42230000 | H112: Nutrición clínica | I112: 177885 | J112: Adjudicado
A113: 45925.585 | B113: Analisis de oferta | C113: HSLM-DAF-CD-2025-0778 | G113: 27110000 | H113: Herramientas de mano | J113: Evaluación
A114: 45925.604 | B114: HSML-2025-00986 | C114: HSLM-DAF-CD-2025-0780 | F114: Antares Pharma, SRL | G114: 51100000 | H114: Medicamentos antiinfecciosos | I114: 225000 | J114: Adjudicado
A115: 45925.604 | B115: HSML-2025-00985 | C115: HSLM-DAF-CD-2025-0779 | F115: Abrias Novo Group SRL | G115: 56100000 | H115: Muebles de alojamiento | I115: 252409 | J115: Adjudicado
A116: 45929.354 | B116: HSML-2025-00987 | C116: HSLM-DAF-CD-2025-0781 | F116: Sandry Gomez Rodriguez | G116: 50100000 | H116: Frutos secos | I116: 138645 | J116: Adjudicado
A117: 45929.396 | B117: HSML-2025-00988 | C117: HSLM-DAF-CD-2025-0782 | F117: Baucomer, SRL | G117: 51160000 | H117: Medicamentos que afectan al sistema respiratorio | I117: 140000 | J117: Adjudicado
A118: 45929.479 | B118: HSML-2025-00990 | C118: HSLM-DAF-CD-2025-0783 | F118: Mantenergia Electrica y Abastecimientos, SRL | G118: 26110000 | H118: Baterías y generadores y transmisión de energía cinética | I118: 125930 | J118: Adjudicado
A119: 45929.502 | B119: HSML-2025-00991 | C119: HSLM-DAF-CD-2025-0784 | F119: Osiris & Co, SA | G119: 42190000 | H119: Productos de centro médico | I119: 229805 | J119: Adjudicado
A120: 45929.626 | B120: Analisis de oferta | C120: HSLM-DAF-CM-2025-0245 | G120: 42220000 | H120: Productos para administración intravenosa y arterial | J120: Publicado
A121: 45929.626 | B121: Analisis de oferta | C121: HSLM-DAF-CD-2025-0785 | G121: 51150000 | H121: Medicamentos para el sistema nervioso autónomo | J121: Evaluación
D122: vs | F122: Sub-Total Compras RD$ | I122: =SUM(I9:I121) -> 28785488
A125: RESUMEN DE COMPRAS o SERVICIOS POR CUENTAS: | F125: RESUMEN DE PROCESO SEGÚN MODALIDAD:
A127: CUENTAS No. | B127: CANTIDAD | C127: MONTO | F127: TIPO | G127: CANTIDAD | H127: MONTO
F128: Compra Directa
F129: Compra Menor
F130: Comparacion de precio
F131: TOTAL COMPRAS | G131: =SUM(G128:G130) -> 0 | H131: =+H123 -> 0
E139: CERTIFICO CORRECTO:
E141: __________________________
E142: DIRECTOR
E144: __________________________
E145: ADMINISTRADOR:
E148: ENC. DE COMPRAS:__________________________
A169: TOTAL RESUMEN | C169: =SUM(C128:C168) -> 0

Sheet CONS. FUENTES FINAN
A1: Form. No.6 SRS
A3: Servicio Nacional de Salud
A4: Dirección de Fizcalización
A5: Consolidado de Ingresos y Gastos por Fuente de Financiamiento
A6: HOSPITAL MATERNO INFANTIL SAN LORENZO DE LOS MINA
A7: SEPTIEMBRE 2025
C8: Ingresos Generales:
E9: 1.- Balance Inicial / Fuente:
E10: Anticipo Financiero | H10: Otros Aportes | L10: Contraseña: 0001
E11: Transferencias Corrientes
E12: Venta de Servicios | G12: 209079.81
E13: 2.- Ingresos por Fuente / Cuenta
E14: Anticipo Financiero | H14: Otros Aportes | I14: =+'INGR SEGUN ORIGEN'!E38 -> 489300 | L14: OBJETAL | M14: FR | N14: VS
E15: Transferencias Corrientes | G15: =+'INGR SEGUN ORIGEN'!E12 -> 1.0574137e+08 | H15: Aportes Nomina SNS | L15: 2.1 | M15: =G26 -> 71591504 | N15: =H26 -> 4413127.6
E16: Venta de Servicios | G16: =+'INGR SEGUN ORIGEN'!E30 -> 12277160 | L16: 2.2 | M16: =G87 -> 7782458.8 | N16: =H87 -> 1557736.2
H17: TOTAL INGRESOS RDS | I17: =+G10+G11+G12+I10+G14+G15+G16+I14+I15 -> 1.1871691e+08 | L17: 2.3 | M17: ='CONS. FUENTES FINAN'!G212 -> 25141648 | N17: ='CONS. FUENTES FINAN'!H212 -> 3168875.7
L18: 2.4 | M18: =G330 -> 0 | N18: =H330 -> 21600
L19: 2.6 | M19: =G336 -> 5819603.3 | N19: =H336 -> 2245366
L20: 2.7 | M20: ='CONS. FUENTES FINAN'!G463 -> 0 | N20: ='CONS. FUENTES FINAN'!H463 -> 0
A21: 1 | F21: 2 | G21: 3 | I21: 4 | J21: 5
A22: Código Presupuestario | F22: Descripción Gasto por Cuenta | G22: Distribución del Gasto por Fuente de Financiamiento | I22: TOTAL | J22: %
A23: Tipo | B23: Objeto | C23: Cuenta | D23: Sub-Cuenta | E23: Auxiliar | G23: Fondo 100 | H23: Venta de Servicios/ Otros Aportes
A25: 2 | F25: Gastos | G25: =+G26+G87+G212+G330+G336+G463 -> 1.1033521e+08 | H25: =+H26+H87+H212+H330+H336+H463 -> 11406705 | I25: =SUM(G25:H25) -> 1.2174192e+08 | J25: =+J26+J87+J212+J330+J336+J463 -> 1
A26: 2 | B26: 1 | F26: Servicios Personales | G26: =+G27+G51+G64+G71+G78 -> 71591504 | H26: =+H27+H51+H64+H71+H78 -> 4413127.6 | I26: =SUM(G26:H26) -> 76004631 | J26: =I26/$I$25 -> 0.62430945
A27: 2 | B27: 1 | C27: 1 | F27: Remuneraciones | G27: =+G28+G35+G42+G44+G46 -> 59165425 | H27: =+H28+H35+H42+H44+H46 -> 0 | I27: =SUM(G27:H27) -> 59165425
A28: 2 | B28: 1 | C28: 1 | D28: 1 | F28: Remuneraciones al personal fijo | G28: =SUM(G29:G34) -> 58052894 | H28: =SUM(H29:H34) -> 0 | I28: =SUM(G28:H28) -> 58052894
A29: 2 | B29: 1 | C29: 1 | D29: 1 | E29: 01 | F29: Sueldos a empleados fijos | G29: ='CUENTA T FONDO 100'!A126 -> 58052894 | H29: ='CUENTA T VS'!A75 -> 0 | I29: =SUM(G29:H29) -> 58052894 | J29: =I29/$I$25 -> 0.47685213
A30: 2 | B30: 1 | C30: 1 | D30: 1 | E30: 02 | F30: Sueldos a médicos | G30: ='CUENTA T FONDO 100'!B126 -> 0 | H30: ='CUENTA T VS'!B75 -> 0 | I30: =SUM(G30:H30) -> 0 | J30: =I30/$I$25 -> 0
A31: 2 | B31: 1 | C31: 1 | D31: 1 | E31: 03 | F31: Ascensos a militares | G31: ='CUENTA T FONDO 100'!C126 -> 0 | H31: ='CUENTA T VS'!C75 -> 0 | I31: =SUM(G31:H31) -> 0 | J31: =I31/$I$25 -> 0
A32: 2 | B32: 1 | C32: 1 | D32: 1 | E32: 04 | F32: Nuevas plazas maestros | G32: ='CUENTA T FONDO 100'!D126 -> 0 | H32: ='CUENTA T VS'!D75 -> 0 | I32: =SUM(G32:H32) -> 0 | J32: =I32/$I$25 -> 0
A33: 2 | B33: 1 | C33: 1 | D33: 1 | E33: 05 | F33: Incentivos y escalafón | G33: ='CUENTA T FONDO 100'!E126 -> 0 | H33: ='CUENTA T VS'!E75 -> 0 | I33: =SUM(G33:H33) -> 0 | J33: =I33/$I$25 -> 0
A34: 2 | B34: 1 | C34: 1 | D34: 1 | E34: 06 | F34: Nuevas plazas a médicos | G34: ='CUENTA T FONDO 100'!F126 -> 0 | H34: ='CUENTA T VS'!F75 -> 0 | I34: =SUM(G34:H34) -> 0 | J34: =I34/$I$25 -> 0
A35: 2 | B35: 1 | C35: 1 | D35: 2 | F35: Remuneraciones al personal con carácter transitorio | G35: =SUM(G36:G41) -> 1112531 | H35: =SUM(H36:H41) -> 0 | I35: =SUM(G35:H35) -> 1112531
A36: 2 | B36: 1 | C36: 1 | D36: 2 | E36: 03 | F36: Suplencias | G36: ='CUENTA T FONDO 100'!G126 -> 0 | H36: ='CUENTA T VS'!G75 -> 0 | I36: =SUM(G36:H36) -> 0 | J36: =I36/$I$25 -> 0
A37: 2 | B37: 1 | C37: 1 | D37: 2 | E37: 05 | F37: Sueldo al personal nominal en período probatorio | G37: ='CUENTA T FONDO 100'!H126 -> 0 | H37: ='CUENTA T VS'!H75 -> 0 | I37: =SUM(G37:H37) -> 0 | J37: =I37/$I$25 -> 0
A38: 2 | B38: 1 | C38: 1 | D38: 2 | E38: 06 | F38: Jornales | G38: ='CUENTA T FONDO 100'!I126 -> 0 | H38: ='CUENTA T VS'!I75 -> 0 | I38: =SUM(G38:H38) -> 0 | J38: =I38/$I$25 -> 0
A39: 2 | B39: 1 | C39: 1 | D39: 2 | E39: 08 | F39: Empleados temporales | G39: ='CUENTA T FONDO 100'!J126 -> 1112531 | H39: ='CUENTA T VS'!J75 -> 0 | I39: =SUM(G39:H39) -> 1112531 | J39: =I39/$I$25 -> 0.0091384384
A40: 2 | B40: 1 | C40: 1 | D40: 2 | E40: 09 | F40: Personal de carácter eventual | G40: ='CUENTA T FONDO 100'!K126 -> 0 | H40: ='CUENTA T VS'!K75 -> 0 | I40: =SUM(G40:H40) -> 0 | J40: =I40/$I$25 -> 0
A41: 2 | B41: 1 | C41: 1 | D41: 2 | E41: 11 | F41: Interinato | G41: ='CUENTA T FONDO 100'!L126 -> 0 | H41: ='CUENTA T VS'!L75 -> 0 | I41: =SUM(G41:H41) -> 0 | J41: =I41/$I$25 -> 0
A42: 2 | B42: 1 | C42: 1 | D42: 3 | F42: Sueldos al personal fijo en trámite de pensiones | G42: =SUM(G43) -> 0 | H42: =SUM(H43) -> 0 | I42: =SUM(G42:H42) -> 0
A43: 2 | B43: 1 | C43: 1 | D43: 3 | E43: 01 | F43: Sueldos al personal fijo en trámite de pensiones | G43: ='CUENTA T FONDO 100'!M126 -> 0 | H43: ='CUENTA T VS'!M75 -> 0 | I43: =SUM(G43:H43) -> 0 | J43: =I43/$I$25 -> 0
A44: 2 | B44: 1 | C44: 1 | D44: 4 | F44: Sueldo anual no. 13 | G44: =SUM(G45) -> 0 | H44: =SUM(H45) -> 0 | I44: =SUM(G44:H44) -> 0
A45: 2 | B45: 1 | C45: 1 | D45: 4 | E45: 01 | F45: Sueldo anual no. 13 | G45: ='CUENTA T FONDO 100'!N126 -> 0 | H45: ='CUENTA T VS'!N75 -> 0 | I45: =SUM(G45:H45) -> 0 | J45: =I45/$I$25 -> 0
A46: 2 | B46: 1 | C46: 1 | D46: 5 | F46: Prestaciones económinas | G46: =SUM(G47:G50) -> 0 | H46: =SUM(H47:H50) -> 0 | I46: =SUM(G46:H46) -> 0
A47: 2 | B47: 1 | C47: 1 | D47: 5 | E47: 01 | F47: Prestaciones económinas | G47: ='CUENTA T FONDO 100'!O126 -> 0 | H47: ='CUENTA T VS'!O75 -> 0 | I47: =SUM(G47:H47) -> 0 | J47: =I47/$I$25 -> 0
A48: 2 | B48: 1 | C48: 1 | D48: 5 | E48: 02 | F48: Pago de porcentaje por desvinculación de cargo | G48: ='CUENTA T FONDO 100'!P126 -> 0 | H48: ='CUENTA T VS'!P75 -> 0 | I48: =SUM(G48:H48) -> 0 | J48: =I48/$I$25 -> 0
A49: 2 | B49: 1 | C49: 1 | D49: 5 | E49: 03 | F49: Prestación laboral por desvinculación | G49: ='CUENTA T FONDO 100'!Q126 -> 0 | H49: ='CUENTA T VS'!Q75 -> 0 | I49: =SUM(G49:H49) -> 0 | J49: =I49/$I$25 -> 0
A50: 2 | B50: 1 | C50: 1 | D50: 5 | E50: 04 | F50: Proporción de vacaciones no disfrutadas | G50: ='CUENTA T FONDO 100'!R126 -> 0 | H50: ='CUENTA T VS'!R75 -> 0 | I50: =SUM(G50:H50) -> 0 | J50: =I50/$I$25 -> 0
A51: 2 | B51: 1 | C51: 2 | F51: Sobresueldos | G51: =+G52+G54 -> 3321905.6 | H51: =+H52+H54 -> 4413127.6 | I51: =SUM(G51:H51) -> 7735033.2
A52: 2 | B52: 1 | C52: 2 | D52: 1 | F52: Primas por antigüedad | G52: =SUM(G53) -> 2702311.6 | H52: =SUM(H53) -> 0 | I52: =SUM(G52:H52) -> 2702311.6
A53: 2 | B53: 1 | C53: 2 | D53: 1 | E53: 01 | F53: Primas por antigüedad | G53: ='CUENTA T FONDO 100'!S126 -> 2702311.6 | H53: ='CUENTA T VS'!S75 -> 0 | I53: =SUM(G53:H53) -> 2702311.6 | J53: =I53/$I$25 -> 0.022197051
A54: 2 | B54: 1 | C54: 2 | D54: 2 | F54: Compensación | G54: =SUM(G55:G63) -> 619593.99 | H54: =SUM(H55:H63) -> 4413127.6 | I54: =SUM(G54:H54) -> 5032721.5
A55: 2 | B55: 1 | C55: 2 | D55: 2 | E55: 01 | F55: Compensación por gastos de alimentación | G55: ='CUENTA T FONDO 100'!T126 -> 0 | H55: ='CUENTA T VS'!T75 -> 0 | I55: =SUM(G55:H55) -> 0 | J55: =I55/$I$25 -> 0
A56: 2 | B56: 1 | C56: 2 | D56: 2 | E56: 03 | F56: Pago de horas extraordinarias | G56: ='CUENTA T FONDO 100'!U126 -> 0 | H56: ='CUENTA T VS'!U75 -> 0 | I56: =SUM(G56:H56) -> 0 | J56: =I56/$I$25 -> 0
A57: 2 | B57: 1 | C57: 2 | D57: 2 | E57: 04 | F57: Prima de transporte | G57: ='CUENTA T FONDO 100'!V126 -> 0 | H57: ='CUENTA T VS'!V75 -> 0 | I57: =SUM(G57:H57) -> 0 | J57: =I57/$I$25 -> 0
A58: 2 | B58: 1 | C58: 2 | D58: 2 | E58: 05 | F58: Compensación servicios de Seguridad | G58: ='CUENTA T FONDO 100'!W126 -> 45000 | H58: ='CUENTA T VS'!W75 -> 0 | I58: =SUM(G58:H58) -> 45000 | J58: =I58/$I$25 -> 0.00036963439
A59: 2 | B59: 1 | C59: 2 | D59: 2 | E59: 06 | F59: Incentivo por Rendimieto Individual | G59: ='CUENTA T FONDO 100'!X126 -> 0 | H59: ='CUENTA T VS'!X75 -> 4413127.6 | I59: =SUM(G59:H59) -> 4413127.6 | J59: =I59/$I$25 -> 0.03624986
A60: 2 | B60: 1 | C60: 2 | D60: 2 | E60: 07 | F60: Compensación por distancia | G60: ='CUENTA T FONDO 100'!Y126 -> 0 | H60: ='CUENTA T VS'!Y75 -> 0 | I60: =SUM(G60:H60) -> 0 | J60: =I60/$I$25 -> 0
A61: 2 | B61: 1 | C61: 2 | D61: 2 | E61: 08 | F61: Compensaciones especiales | G61: ='CUENTA T FONDO 100'!Z126 -> 288000 | H61: ='CUENTA T VS'!Z75 -> 0 | I61: =SUM(G61:H61) -> 288000 | J61: =I61/$I$25 -> 0.0023656601
A62: 2 | B62: 1 | C62: 2 | D62: 2 | E62: 09 | F62: Bono por desempeño a servidores de carrera | G62: ='CUENTA T FONDO 100'!AA126 -> 0 | H62: ='CUENTA T VS'!AA75 -> 0 | I62: =SUM(G62:H62) -> 0 | J62: =I62/$I$25 -> 0
A63: 2 | B63: 1 | C63: 2 | D63: 2 | E63: 10 | F63: Compensacion por cumplimiento de indicadores | G63: ='CUENTA T FONDO 100'!AB126 -> 286593.99 | H63: ='CUENTA T VS'!AB75 -> 0 | I63: =SUM(G63:H63) -> 286593.99 | J63: =I63/$I$25 -> 0.002354111
A64: 2 | B64: 1 | C64: 3 | F64: Dietas y Gastos de Representación | G64: =+G65+G68 -> 0 | H64: =+H65+H68 -> 0 | I64: =SUM(G64:H64) -> 0
A65: 2 | B65: 1 | C65: 3 | D65: 1 | F65: Dietas | G65: =SUM(G66:G67) -> 0 | H65: =SUM(H66:H67) -> 0 | I65: =SUM(G65:H65) -> 0
A66: 2 | B66: 1 | C66: 3 | D66: 1 | E66: 01 | F66: Dietas en el país | G66: ='CUENTA T FONDO 100'!AC126 -> 0 | H66: ='CUENTA T VS'!AC75 -> 0 | I66: =SUM(G66:H66) -> 0 | J66: =I66/$I$25 -> 0
A67: 2 | B67: 1 | C67: 3 | D67: 1 | E67: 02 | F67: Dietas en el exterior | G67: ='CUENTA T FONDO 100'!AD126 -> 0 | H67: ='CUENTA T VS'!AD75 -> 0 | I67: =SUM(G67:H67) -> 0 | J67: =I67/$I$25 -> 0
A68: 2 | B68: 1 | C68: 3 | D68: 2 | F68: Gastos de representación | G68: =SUM(G69:G70) -> 0 | H68: =SUM(H69:H70) -> 0 | I68: =SUM(G68:H68) -> 0
A69: 2 | B69: 1 | C69: 3 | D69: 2 | E69: 01 | F69: Gastos de representación en el país | G69: ='CUENTA T FONDO 100'!AE126 -> 0 | H69: ='CUENTA T VS'!AE75 -> 0 | I69: =SUM(G69:H69) -> 0 | J69: =I69/$I$25 -> 0
A70: 2 | B70: 1 | C70: 3 | D70: 2 | E70: 02 | F70: Gastos de representación en el exterior | G70: ='CUENTA T FONDO 100'!AF126 -> 0 | H70: ='CUENTA T VS'!AF75 -> 0 | I70: =SUM(G70:H70) -> 0 | J70: =I70/$I$25 -> 0
A71: 2 | B71: 1 | C71: 4 | F71: Gratificaciones y Bonificaciones | G71: =+G72+G74 -> 0 | H71: =+H72+H74 -> 0 | I71: =SUM(G71:H71) -> 0
A72: 2 | B72: 1 | C72: 4 | D72: 1 | F72: Bonificaciones | G72: =SUM(G73) -> 0 | H72: =SUM(H73) -> 0 | I72: =SUM(G72:H72) -> 0
A73: 2 | B73: 1 | C73: 4 | D73: 1 | E73: 01 | F73: Bonificaciones | G73: ='CUENTA T FONDO 100'!AG126 -> 0 | H73: ='CUENTA T VS'!AG75 -> 0 | I73: =SUM(G73:H73) -> 0 | J73: =I73/$I$25 -> 0
A74: 2 | B74: 1 | C74: 4 | D74: 2 | F74: Otras Gratificaciones y Bonificaciones | G74: =SUM(G75:G77) -> 0 | H74: =SUM(H75:H77) -> 0 | I74: =SUM(G74:H74) -> 0
A75: 2 | B75: 1 | C75: 4 | D75: 2 | E75: 01 | F75: Bono escolar | G75: ='CUENTA T FONDO 100'!AH126 -> 0 | H75: ='CUENTA T VS'!AH75 -> 0 | I75: =SUM(G75:H75) -> 0 | J75: =I75/$I$25 -> 0
A76: 2 | B76: 1 | C76: 4 | D76: 2 | E76: 02 | F76: Gratificaciones por pasantías | G76: ='CUENTA T FONDO 100'!AI126 -> 0 | H76: ='CUENTA T VS'!AI75 -> 0 | I76: =SUM(G76:H76) -> 0 | J76: =I76/$I$25 -> 0
A77: 2 | B77: 1 | C77: 4 | D77: 2 | E77: 03 | F77: Gratificaciones por aniversario de institución | G77: ='CUENTA T FONDO 100'!AJ126 -> 0 | H77: ='CUENTA T VS'!AJ75 -> 0 | I77: =SUM(G77:H77) -> 0 | J77: =I77/$I$25 -> 0
A78: 2 | B78: 1 | C78: 5 | F78: Contribuciones a la Seguridad Social y Riesgo Laboral | G78: =+G79+G81+G83+G85 -> 9104173.4 | H78: =+H79+H81+H83+H85 -> 0 | I78: =SUM(G78:H78) -> 9104173.4
A79: 2 | B79: 1 | C79: 5 | D79: 1 | F79: Contribuciones al seguro de salud | G79: =SUM(G80) -> 4194829.4 | H79: =SUM(H80) -> 0 | I79: =SUM(G79:H79) -> 4194829.4
A80: 2 | B80: 1 | C80: 5 | D80: 1 | E80: 01 | F80: Contribuciones al seguro de salud | G80: ='CUENTA T FONDO 100'!AK126 -> 4194829.4 | H80: ='CUENTA T VS'!AK75 -> 0 | I80: =SUM(G80:H80) -> 4194829.4 | J80: =I80/$I$25 -> 0.034456738
A81: 2 | B81: 1 | C81: 5 | D81: 2 | F81: Contribuciones al seguro de pensiones | G81: =SUM(G82) -> 4200746.8 | H81: =SUM(H82) -> 0 | I81: =SUM(G81:H81) -> 4200746.8
A82: 2 | B82: 1 | C82: 5 | D82: 2 | E82: 01 | F82: Contribuciones al seguro de pensiones | G82: ='CUENTA T FONDO 100'!AL126 -> 4200746.8 | H82: ='CUENTA T VS'!AL75 -> 0 | I82: =SUM(G82:H82) -> 4200746.8 | J82: =I82/$I$25 -> 0.034505344
A83: 2 | B83: 1 | C83: 5 | D83: 3 | F83: Contribuciones al seguro de riesgo laboral | G83: =SUM(G84) -> 708597.18 | H83: =SUM(H84) -> 0 | I83: =SUM(G83:H83) -> 708597.18
A84: 2 | B84: 1 | C84: 5 | D84: 3 | E84: 01 | F84: Contribuciones al seguro de riesgo laboral | G84: ='CUENTA T FONDO 100'!AM126 -> 708597.18 | H84: ='CUENTA T VS'!AM75 -> 0 | I84: =SUM(G84:H84) -> 708597.18 | J84: =I84/$I$25 -> 0.0058204863
A85: 2 | B85: 1 | C85: 5 | D85: 4 | F85: Contribuciones al plan de retiro complementario | G85: =SUM(G86) -> 0 | H85: =SUM(H86) -> 0 | I85: =SUM(G85:H85) -> 0
A86: 2 | B86: 1 | C86: 5 | D86: 4 | E86: 01 | F86: Contribuciones al plan de retiro complementario | G86: ='CUENTA T FONDO 100'!AN126 -> 0 | H86: ='CUENTA T VS'!AN75 -> 0 | I86: =SUM(G86:H86) -> 0 | J86: =I86/$I$25 -> 0
A87: 2 | B87: 2 | F87: Servicios No Personales | G87: =G88+G106+G111+G116+G125+G148+G157+G179+G208 -> 7782458.8 | H87: =H88+H106+H111+H116+H125+H148+H157+H179+H208 -> 1557736.2 | I87: =SUM(G87:H87) -> 9340195 | J87: =I87/$I$25 -> 0.076721273
A88: 2 | B88: 2 | C88: 1 | F88: Servicios Básicos | G88: =+G89+G91+G93+G95+G97+G99+G102+G104 -> 60535 | H88: =+H89+H91+H93+H95+H97+H99+H102+H104 -> 161421.68 | I88: =SUM(G88:H88) -> 221956.68
A89: 2 | B89: 2 | C89: 1 | D89: 1 | F89: Radiocomunicación | G89: =SUM(G90) -> 0 | H89: =SUM(H90) -> 0 | I89: =SUM(G89:H89) -> 0
A90: 2 | B90: 2 | C90: 1 | D90: 1 | E90: 01 | F90: Radiocomunicación | G90: ='CUENTA T FONDO 100'!AO126 -> 0 | H90: ='CUENTA T VS'!AO75 -> 0 | I90: =SUM(G90:H90) -> 0 | J90: =I90/$I$25 -> 0
A91: 2 | B91: 2 | C91: 1 | D91: 2 | F91: Servicios telefónico de larga distancia | G91: =SUM(G92) -> 0 | H91: =SUM(H92) -> 0 | I91: =SUM(G91:H91) -> 0
A92: 2 | B92: 2 | C92: 1 | D92: 2 | E92: 01 | F92: Servicios telefónico de larga distancia | G92: ='CUENTA T FONDO 100'!AP126 -> 0 | H92: ='CUENTA T VS'!AP75 -> 0 | I92: =SUM(G92:H92) -> 0 | J92: =I92/$I$25 -> 0
A93: 2 | B93: 2 | C93: 1 | D93: 3 | F93: Teléfono local | G93: =SUM(G94) -> 0 | H93: =SUM(H94) -> 111421.68 | I93: =SUM(G93:H93) -> 111421.68
A94: 2 | B94: 2 | C94: 1 | D94: 3 | E94: 01 | F94: Teléfono local | G94: ='CUENTA T FONDO 100'!AQ126 -> 0 | H94: ='CUENTA T VS'!AQ75 -> 111421.68 | I94: =SUM(G94:H94) -> 111421.68 | J94: =I94/$I$25 -> 0.00091522855
A95: 2 | B95: 2 | C95: 1 | D95: 4 | F95: Telefax y correos | G95: =SUM(G96) -> 0 | H95: =SUM(H96) -> 0 | I95: =SUM(G95:H95) -> 0
A96: 2 | B96: 2 | C96: 1 | D96: 4 | E96: 01 | F96: Telefax y correos | G96: ='CUENTA T FONDO 100'!AR126 -> 0 | H96: ='CUENTA T VS'!AR75 -> 0 | I96: =SUM(G96:H96) -> 0 | J96: =I96/$I$25 -> 0
A97: 2 | B97: 2 | C97: 1 | D97: 5 | F97: Servicio de Internet y televisión por cable | G97: =SUM(G98) -> 0 | H97: =SUM(H98) -> 0 | I97: =SUM(G97:H97) -> 0
A98: 2 | B98: 2 | C98: 1 | D98: 5 | E98: 01 | F98: Servicio de Internet y televisión por cable | G98: ='CUENTA T FONDO 100'!AS126 -> 0 | H98: ='CUENTA T VS'!AS75 -> 0 | I98: =SUM(G98:H98) -> 0 | J98: =I98/$I$25 -> 0
A99: 2 | B99: 2 | C99: 1 | D99: 6 | F99: Electricidad | G99: =SUM(G100:G101) -> 0 | H99: =SUM(H100:H101) -> 0 | I99: =SUM(G99:H99) -> 0
A100: 2 | B100: 2 | C100: 1 | D100: 6 | E100: 01 | F100: Energía eléctrica | G100: ='CUENTA T FONDO 100'!AT126 -> 0 | H100: ='CUENTA T VS'!AT75 -> 0 | I100: =SUM(G100:H100) -> 0 | J100: =I100/$I$25 -> 0
A101: 2 | B101: 2 | C101: 1 | D101: 6 | E101: 02 | F101: Electricidad no cortable | G101: ='CUENTA T FONDO 100'!AU126 -> 0 | H101: ='CUENTA T VS'!AU75 -> 0 | I101: =SUM(G101:H101) -> 0 | J101: =I101/$I$25 -> 0
A102: 2 | B102: 2 | C102: 1 | D102: 7 | F102: Agua | G102: =SUM(G103) -> 60535 | H102: =SUM(H103) -> 0 | I102: =SUM(G102:H102) -> 60535
...

Sheet CUENTA T FONDO 100
A1: D E S G L O S E D E L A S C U E N T A S
A2: 211101 | B2: 211102 | C2: 211103 | D2: 211104 | E2: 211105 | F2: 211106 | G2: 211203 | H2: 211205 | I2: 211206 | J2: 211208 | K2: 211209 | L2: 211211 | M2: 211301 | N2: 211401 | O2: 211501 | P2: 211502 | Q2: 211503 | R2: 211504 | S2: 212101 | T2: 212201 | U2: 212203 | V2: 212204 | W2: 212205 | X2: 212206 | Y2: 212207 | Z2: 212208 | AA2: 212209 | AB2: 212210 | AC2: 213101 | AD2: 213102 | AE2: 213201 | AF2: 213202 | AG2: 214101 | AH2: 214201 | AI2: 214202 | AJ2: 214203 | AK2: 215101 | AL2: 215201 | AM2: 215301 | AN2: 215401 | AO2: 221101 | AP2: 221201 | AQ2: 221301 | AR2: 221401 | AS2: 221501 | AT2: 221601 | AU2: 221602 | AV2: 221701 | AW2: 221801 | AX2: 222101 | AY2: 222201 | AZ2: 223101 | BA2: 223201 | BB2: 224101 | BC2: 224201 | BD2: 224301 | BE2: 224401 | BF2: 225101 | BG2: 225201 | BH2: 225301 | BI2: 225302 | BJ2: 225303 | BK2: 225304 | BL2: 225305 | BM2: 225401 | BN2: 225501 | BO2: 225601 | BP2: 225701 | BQ2: 225801 | BR2: 225901 | BS2: 226101 | BT2: 226201 | BU2: 226301 | BV2: 226401 | BW2: 227101 | BX2: 227102 | BY2: 227103 | BZ2: 227104 | CA2: 227105 | CB2: 227106 | CC2: 227107 | CD2: 227199 | CE2: 227201 | CF2: 227202 | CG2: 227203 | CH2: 227204 | CI2: 227205 | CJ2: 227206 | CK2: 227207 | CL2: 227208 | CM2: 227299 | CN2: 227301 | CO2: 228101 | CP2: 228201 | CQ2: 228301 | CR2: 228401 | CS2: 228501 | CT2: 228502 | CU2: 228503 | CV2: 228601 | CW2: 228602 | CX2: 228603 | CY2: 228604 | CZ2: 228701 | DA2: 228702 | DB2: 228703 | DC2: 228704 | DD2: 228705 | DE2: 228706 | DF2: 228801 | DG2: 228802 | DH2: 228803 | DI2: 229201 | DJ2: 229203 | DK2: 231101 | DL2: 231102 | DM2: 231201 | DN2: 231301 | DO2: 231302 | DP2: 231303 | DQ2: 231401 | DR2: 232101 | DS2: 232201 | DT2: 232301 | DU2: 233101 | DV2: 233201 | DW2: 233301 | DX2: 233401 | DY2: 233501 | DZ2: 233601 | EA2: 234101 | EB2: 234201 | EC2: 235101 | ED2: 235201 | EE2: 235301 | EF2: 235401 | EG2: 235501 | EH2: 236101 | EI2: 236102 | EJ2: 236103 | EK2: 236104 | EL2: 236105 | EM2: 236201 | EN2: 236202 | EO2: 236203 | EP2: 236304 | EQ2: 236305 | ER2: 236306 | ES2: 236401 | ET2: 236402 | EU2: 236403 | EV2: 236404 | EW2: 236405 | EX2: 236406 | EY2: 236407 | EZ2: 236901 | FA2: 237101 | FB2: 237102 | FC2: 237103 | FD2: 237104 | FE2: 237105 | FF2: 237106 | FG2: 237107 | FH2: 237201 | FI2: 237202 | FJ2: 237203 | FK2: 237204 | FL2: 237205 | FM2: 237206 | FN2: 237299 | FO2: 238101 | FP2: 238201 | FQ2: 239101 | FR2: 239102 | FS2: 239201 | FT2: 239301 | FU2: 239401 | FV2: 239501 | FW2: 239601 | FX2: 239701 | FY2: 239801 | FZ2: 239802 | GA2: 239901 | GB2: 239904 | GC2: 241201 | GD2: 241202 | GE2: 241203 | GF2: 241204 | GG2: 241205 | GH2: 261101 | GI2: 261201 | GJ2: 261301 | GK2: 261401 | GL2: 261901 | GM2: 262101 | GN2: 262201 | GO2: 262301 | GP2: 262401 | GQ2: 263101 | GR2: 263201 | GS2: 263301 | GT2: 263401 | GU2: 264101 | GV2: 264201 | GW2: 264301 | GX2: 264401 | GY2: 264501 | GZ2: 264601 | HA2: 264701 | HB2: 264801 | HC2: 265101 | HD2: 265201 | HE2: 265301 | HF2: 265401 | HG2: 265501 | HH2: 265601 | HI2: 265701 | HJ2: 265801 | HK2: 266101 | HL2: 266201 | HM2: 267101 | HN2: 267201 | HO2: 267301 | HP2: 267401 | HQ2: 267501 | HR2: 267601 | HS2: 267701 | HT2: 267801 | HU2: 267901 | HV2: 268101 | HW2: 268201 | HX2: 268301 | HY2: 268302 | HZ2: 268401 | IA2: 268501 | IB2: 268601 | IC2: 268701 | ID2: 268802 | IE2: 268803 | IF2: 268804 | IG2: 268901 | IH2: 269101 | II2: 269102 | IJ2: 269201 | IK2: 269202 | IL2: 269301 | IM2: 269401 | IN2: 269501 | IO2: 269502 | IP2: 269503 | IQ2: 2269901 | IR2: 271101 | IS2: 271201 | IT2: 271301 | IU2: 271401 | IV2: 272101 | IW2: 272201 | IX2: 272301 | IY2: 272401 | IZ2: 272501 | JA2: 272601 | JB2: 272701 | JC2: 272801 | JD2: 272901 | JE2: 273101 | JF2: 273201 | JG2: 274101 | JH2: 274201 | JI2: Totales | JJ2: TRANSF NO. | JK2: VALOR | JL2: RETENCION | JM2: AÑOS ANTERIORES | JN2: 2022 | JO2: Total | JP2: Proveedor Informal
GQ3: 1945820 | JI3: =SUM(A3:JH3) -> 1945820 | JJ3: 3911 | JO3: =+JM3+JN3 -> 0
FT4: 271000 | JI4: =SUM(A4:JH4) -> 271000 | JJ4: 3915
FT5: 260780 | JI5: =SUM(A5:JH5) -> 260780 | JJ5: 3919
FB6: 337200 | JI6: =SUM(A6:JH6) -> 337200 | JJ6: 3923
GH7: 260443.67 | JI7: =SUM(A7:JH7) -> 260443.67 | JJ7: 3927
GH8: 45366.46 | JI8: =SUM(A8:JH8) -> 45366.46 | JJ8: 3932
DK9: 242313 | JI9: =SUM(A9:JH9) -> 242313 | JJ9: 3936
FJ10: 120000 | FT10: 43477.94 | JI10: =SUM(A10:JH10) -> 163477.94 | JJ10: 3940
EA11: 75000 | JI11: =SUM(A11:JH11) -> 75000 | JJ11: 3944
FT12: 259328 | JI12: =SUM(A12:JH12) -> 259328 | JJ12: 3948
EA13: 271700 | JI13: =SUM(A13:JH13) -> 271700 | JJ13: 3952
EA14: 180000 | JI14: =SUM(A14:JH14) -> 180000 | JJ14: 3963
FT15: 177000 | JI15: =SUM(A15:JH15) -> 177000 | JJ15: 4016
EA16: 78000 | JI16: =SUM(A16:JH16) -> 78000 | JJ16: 4020
DK17: 166220 | JI17: =SUM(A17:JH17) -> 166220 | JJ17: 4029
FT18: 144019 | JI18: =SUM(A18:JH18) -> 144019 | JJ18: 4033
FT19: 188800 | JI19: =SUM(A19:JH19) -> 188800 | JJ19: 4037
EA20: 230000 | JI20: =SUM(A20:JH20) -> 230000 | JJ20: 4044
EA21: 193640 | FT21: 39936 | JI21: =SUM(A21:JH21) -> 233576 | JJ21: 4045
FT22: 259234.2 | JI22: =SUM(A22:JH22) -> 259234.2 | JJ22: 4049
EA23: 92500 | JI23: =SUM(A23:JH23) -> 92500 | JJ23: 4056
AV24: 60535 | JI24: =SUM(A24:JH24) -> 60535 | JJ24: 4060
W25: 45000 | JI25: =SUM(A25:JH25) -> 45000 | JJ25: 4067
J26: 1112531 | AK26: 78878.45 | AL26: 78989.7 | AM26: 13250.76 | JI26: =SUM(A26:JH26) -> 1283649.9 | JJ26: 4069
FQ27: 112690 | JI27: =SUM(A27:JH27) -> 112690 | JJ27: 4074
FT28: 247800 | JI28: =SUM(A28:JH28) -> 247800 | JJ28: 4078
EA29: 79600 | JI29: =SUM(A29:JH29) -> 79600 | JJ29: 4083
CH30: 13039 | JI30: =SUM(A30:JH30) -> 13039 | JJ30: 4095
FT31: 368160 | JI31: =SUM(A31:JH31) -> 368160 | JJ31: 4099
EA32: 735000 | JI32: =SUM(A32:JH32) -> 735000 | JJ32: 4104
EA33: 1875000 | JI33: =SUM(A33:JH33) -> 1875000 | JJ33: 4108
DJ34: 1095158 | JI34: =SUM(A34:JH34) -> 1095158 | JJ34: 4115
DJ35: 1144423 | JI35: =SUM(A35:JH35) -> 1144423 | JJ35: 4119
GK36: 111510 | JI36: =SUM(A36:JH36) -> 111510 | JJ36: 4126
DV37: 97940 | JI37: =SUM(A37:JH37) -> 97940 | JJ37: 4132
GJ38: 99049.2 | JI38: =SUM(A38:JH38) -> 99049.2 | JJ38: 4133
A39: 58052894 | S39: 2702311.6 | Z39: 288000 | AB39: =101150.82+185443.17 -> 286593.99 | AK39: 4115950.9 | AL39: 4121757.1 | AM39: 695346.42 | JI39: =SUM(A39:JH39) -> 70262854 | JJ39: 4135
FY40: 80124.36 | JI40: =SUM(A40:JH40) -> 80124.36 | JJ40: 4139
GQ41: 140999.99 | JI41: =SUM(A41:JH41) -> 140999.99 | JJ41: 4143
GH42: 49560 | HL42: 66080 | JI42: =SUM(A42:JH42) -> 115640 | JJ42: 4147
EA43: 1325000 | JI43: =SUM(A43:JH43) -> 1325000 | JJ43: 4151
GJ44: 295000 | JI44: =SUM(A44:JH44) -> 295000 | JJ44: 4155
FT45: 271253.68 | JI45: =SUM(A45:JH45) -> 271253.68 | JJ45: 4159
EA46: 442500 | JI46: =SUM(A46:JH46) -> 442500 | JJ46: 4163
EA47: 120000 | FT47: 147500 | JI47: =SUM(A47:JH47) -> 267500 | JJ47: 4171
DK48: 735773.58 | DV48: 26668 | JI48: =SUM(A48:JH48) -> 762441.58 | JJ48: 4176
DK49: 628550 | JI49: =SUM(A49:JH49) -> 628550 | JJ49: 4180
DS50: 788476.06 | JI50: =SUM(A50:JH50) -> 788476.06 | JJ50: 4186
DK51: 407506 | JI51: =SUM(A51:JH51) -> 407506 | JJ51: 4190
GQ52: 692448.19 | JI52: =SUM(A52:JH52) -> 692448.19 | JJ52: 4195
HJ53: 30444 | JI53: =SUM(A53:JH53) -> 30444 | JJ53: 4205
EA54: 60000 | FT54: 140243 | JI54: =SUM(A54:JH54) -> 200243 | JJ54: 4209
EA55: 199000 | JI55: =SUM(A55:JH55) -> 199000 | JJ55: 4213
FT56: 208500 | JI56: =SUM(A56:JH56) -> 208500 | JJ56: 4217
FT57: 269040 | JI57: =SUM(A57:JH57) -> 269040 | JJ57: 4223
HJ58: 101480 | JI58: =SUM(A58:JH58) -> 101480 | JJ58: 4231
GQ59: 47200 | JI59: =SUM(A59:JH59) -> 47200 | JJ59: 4232
GQ60: 271400 | JI60: =SUM(A60:JH60) -> 271400 | JJ60: 4237
GJ61: 74356.64 | JI61: =SUM(A61:JH61) -> 74356.64 | JJ61: 4241
AY62: 47633.3 | JI62: =SUM(A62:JH62) -> 47633.3 | JJ62: 4245
EA63: 23000 | JI63: =SUM(A63:JH63) -> 23000 | JJ63: 4260
FY64: 26550 | JI64: =SUM(A64:JH64) -> 26550 | JJ64: 4264
DD65: 1829000 | JI65: =SUM(A65:JH65) -> 1829000 | JJ65: 4271
GQ66: 1099760 | JI66: =SUM(A66:JH66) -> 1099760 | JJ66: 4272
EA67: 140000 | JI67: =SUM(A67:JH67) -> 140000 | JJ67: 4276
HH68: 277701.2 | JI68: =SUM(A68:JH68) -> 277701.2 | JJ68: 4280
EA69: 240000 | JI69: =SUM(A69:JH69) -> 240000 | JJ69: 4284
FT70: 197768 | JI70: =SUM(A70:JH70) -> 197768 | JJ70: 4288
FT71: 216825 | JI71: =SUM(A71:JH71) -> 216825 | JJ71: 4292
FJ72: 588545.72 | FQ72: 73419.6 | JI72: =SUM(A72:JH72) -> 661965.32 | JJ72: 4296
FJ73: 637538.02 | JI73: =SUM(A73:JH73) -> 637538.02 | JJ73: 4300
DW74: 242372 | JI74: =SUM(A74:JH74) -> 242372 | JJ74: 4305
GH75: 148680 | JI75: =SUM(A75:JH75) -> 148680 | JJ75: 4309
FQ76: 212400 | JI76: =SUM(A76:JH76) -> 212400 | JJ76: 4313
GH77: 62304 | JI77: =SUM(A77:JH77) -> 62304 | JJ77: 4317
FT78: 211210 | JI78: =SUM(A78:JH78) -> 211210 | JJ78: 4321
DD79: 1950000 | JI79: =SUM(A79:JH79) -> 1950000 | JJ79: 4326
BW80: 1567740.5 | JI80: =SUM(A80:JH80) -> 1567740.5 | JJ80: 4330
DS81: 469640 | JI81: =SUM(A81:JH81) -> 469640 | JJ81: 4334
FQ82: 4101.09 | JI82: =SUM(A82:JH82) -> 4101.09 | JJ82: 4339
FT83: 8673 | JI83: =SUM(A83:JH83) -> 8673 | JJ83: 4346
FT84: 28461.6 | JI84: =SUM(A84:JH84) -> 28461.6 | JJ84: 4352
EA85: 145220 | JI85: =SUM(A85:JH85) -> 145220 | JJ85: 4356
FS86: 271071.5 | JI86: =SUM(A86:JH86) -> 271071.5 | JJ86: 4360
EA87: 144000 | JI87: =SUM(A87:JH87) -> 144000 | JJ87: 4364
FT88: 172642.97 | JI88: =SUM(A88:JH88) -> 172642.97 | JJ88: 4368
EA89: 195000 | JI89: =SUM(A89:JH89) -> 195000 | JJ89: 4390
DJ90: 74930 | JI90: =SUM(A90:JH90) -> 74930 | JJ90: 4396
EA91: 112000 | JI91: =SUM(A91:JH91) -> 112000 | JJ91: 4399
FJ92: 313804 | JI92: =SUM(A92:JH92) -> 313804 | JJ92: 4403
EA93: 1612500 | JI93: =SUM(A93:JH93) -> 1612500 | JJ93: 4406
FJ94: 605972.48 | JI94: =SUM(A94:JH94) -> 605972.48 | JJ94: 4411
FQ95: 196918.4 | JI95: =SUM(A95:JH95) -> 196918.4 | JJ95: 4415
FJ96: 1800000 | JI96: =SUM(A96:JH96) -> 1800000 | JJ96: 4419
EA97: 48580 | FT97: 155053.12 | JI97: =SUM(A97:JH97) -> 203633.12 | JJ97: 4425
EA98: 225000 | JI98: =SUM(A98:JH98) -> 225000 | JJ98: 4431
FT99: 1050993 | JI99: =SUM(A99:JH99) -> 1050993 | JJ99: 4432
EA100: 117000 | JI100: =SUM(A100:JH100) -> 117000 | JJ100: 4436
...

Sheet CUENTA T VS
A1: D E S G L O S E D E L A S C U E N T A S
A2: 211101 | B2: 211102 | C2: 211103 | D2: 211104 | E2: 211105 | F2: 211106 | G2: 211203 | H2: 211205 | I2: 211206 | J2: 211208 | K2: 211209 | L2: 211211 | M2: 211301 | N2: 211401 | O2: 211501 | P2: 211502 | Q2: 211503 | R2: 211504 | S2: 212101 | T2: 212201 | U2: 212203 | V2: 212204 | W2: 212205 | X2: 212206 | Y2: 212207 | Z2: 212208 | AA2: 212209 | AB2: 212210 | AC2: 213101 | AD2: 213102 | AE2: 213201 | AF2: 213202 | AG2: 214101 | AH2: 214201 | AI2: 214202 | AJ2: 214203 | AK2: 215101 | AL2: 215201 | AM2: 215301 | AN2: 215401 | AO2: 221101 | AP2: 221201 | AQ2: 221301 | AR2: 221401 | AS2: 221501 | AT2: 221601 | AU2: 221602 | AV2: 221701 | AW2: 221801 | AX2: 222101 | AY2: 222201 | AZ2: 223101 | BA2: 223201 | BB2: 224101 | BC2: 224201 | BD2: 224301 | BE2: 224401 | BF2: 225101 | BG2: 225201 | BH2: 225301 | BI2: 225302 | BJ2: 225303 | BK2: 225304 | BL2: 225305 | BM2: 225401 | BN2: 225501 | BO2: 225601 | BP2: 225701 | BQ2: 225801 | BR2: 225901 | BS2: 226101 | BT2: 226201 | BU2: 226301 | BV2: 226401 | BW2: 227101 | BX2: 227102 | BY2: 227103 | BZ2: 227104 | CA2: 227105 | CB2: 227106 | CC2: 227107 | CD2: 227199 | CE2: 227201 | CF2: 227202 | CG2: 227203 | CH2: 227204 | CI2: 227205 | CJ2: 227206 | CK2: 227207 | CL2: 227208 | CM2: 227299 | CN2: 227301 | CO2: 228101 | CP2: 228201 | CQ2: 228301 | CR2: 228401 | CS2: 228501 | CT2: 228502 | CU2: 228503 | CV2: 228601 | CW2: 228602 | CX2: 228603 | CY2: 228604 | CZ2: 228701 | DA2: 228702 | DB2: 228703 | DC2: 228704 | DD2: 228705 | DE2: 228706 | DF2: 228801 | DG2: 228802 | DH2: 228803 | DI2: 229201 | DJ2: 229203 | DK2: 231101 | DL2: 231102 | DM2: 231201 | DN2: 231301 | DO2: 231302 | DP2: 231303 | DQ2: 231401 | DR2: 232101 | DS2: 232201 | DT2: 232301 | DU2: 233101 | DV2: 233201 | DW2: 233301 | DX2: 233401 | DY2: 233501 | DZ2: 233601 | EA2: 234101 | EB2: 234201 | EC2: 235101 | ED2: 235201 | EE2: 235301 | EF2: 235401 | EG2: 235501 | EH2: 236101 | EI2: 236102 | EJ2: 236103 | EK2: 236104 | EL2: 236105 | EM2: 236201 | EN2: 236202 | EO2: 236203 | EP2: 236304 | EQ2: 236305 | ER2: 236306 | ES2: 236401 | ET2: 236402 | EU2: 236403 | EV2: 236404 | EW2: 236405 | EX2: 236406 | EY2: 236407 | EZ2: 236901 | FA2: 237101 | FB2: 237102 | FC2: 237103 | FD2: 237104 | FE2: 237105 | FF2: 237106 | FG2: 237107 | FH2: 237201 | FI2: 237202 | FJ2: 237203 | FK2: 237204 | FL2: 237205 | FM2: 237206 | FN2: 237299 | FO2: 238101 | FP2: 238201 | FQ2: 239101 | FR2: 239102 | FS2: 239201 | FT2: 239301 | FU2: 239401 | FV2: 239501 | FW2: 239601 | FX2: 239701 | FY2: 239801 | FZ2: 239802 | GA2: 239901 | GB2: 239904 | GC2: 241201 | GD2: 241202 | GE2: 241203 | GF2: 241204 | GG2: 241205 | GH2: 261101 | GI2: 261201 | GJ2: 261301 | GK2: 261401 | GL2: 261901 | GM2: 262101 | GN2: 262201 | GO2: 262301 | GP2: 262401 | GQ2: 263101 | GR2: 263201 | GS2: 263301 | GT2: 263401 | GU2: 264101 | GV2: 264201 | GW2: 264301 | GX2: 264401 | GY2: 264501 | GZ2: 264601 | HA2: 264701 | HB2: 264801 | HC2: 265101 | HD2: 265201 | HE2: 265301 | HF2: 265401 | HG2: 265501 | HH2: 265601 | HI2: 265701 | HJ2: 265801 | HK2: 266101 | HL2: 266201 | HM2: 267101 | HN2: 267201 | HO2: 267301 | HP2: 267401 | HQ2: 267501 | HR2: 267601 | HS2: 267701 | HT2: 267801 | HU2: 267901 | HV2: 268101 | HW2: 268201 | HX2: 268301 | HY2: 268302 | HZ2: 268401 | IA2: 268501 | IB2: 268601 | IC2: 268701 | ID2: 268802 | IE2: 268803 | IF2: 268804 | IG2: 268901 | IH2: 269101 | II2: 269102 | IJ2: 269201 | IK2: 269202 | IL2: 269301 | IM2: 269401 | IN2: 269501 | IO2: 269502 | IP2: 269503 | IQ2: 2269901 | IR2: 271101 | IS2: 271201 | IT2: 271301 | IU2: 271401 | IV2: 272101 | IW2: 272201 | IX2: 272301 | IY2: 272401 | IZ2: 272501 | JA2: 272601 | JB2: 272701 | JC2: 272801 | JD2: 272901 | JE2: 273101 | JF2: 273201 | JG2: 274101 | JH2: 274201 | JI2: Totales | JJ2: TRANSF NO. | JK2: VALOR | JL2: RETENCION | JM2: AÑOS ANTERIORES | JN2: 2022 | JO2: Total | JP2: Proveedor Informal
GL4: 177799.99 | JI4: =SUM(A4:JH4) -> 177799.99 | JJ4: 290 | JK4: 177799.99 | JL4: =+JI4-JK4 -> 0
FN5: 155677.4 | JI5: =SUM(A5:JH5) -> 155677.4 | JJ5: 291 | JK5: 155677.4 | JL5: =+JI5-JK5 -> 0
DK6: 90600 | JI6: =SUM(A6:JH6) -> 90600 | JJ6: 292 | JK6: 90600 | JL6: =+JI6-JK6 -> 0
FJ7: 4800 | JI7: =SUM(A7:JH7) -> 4800 | JJ7: 293 | JK7: 4800 | JL7: =+JI7-JK7 -> 0
DK8: 14000 | JI8: =SUM(A8:JH8) -> 14000 | JJ8: 294 | JK8: 14000 | JL8: =+JI8-JK8 -> 0
DK9: 30060 | JI9: =SUM(A9:JH9) -> 30060 | JJ9: 295 | JK9: 30060 | JL9: =+JI9-JK9 -> 0
DK10: 7000 | JI10: =SUM(A10:JH10) -> 7000 | JJ10: 296 | JK10: 7000 | JL10: =+JI10-JK10 -> 0
CH11: 132966.46 | JI11: =SUM(A11:JH11) -> 132966.46 | JJ11: 297 | JK11: 132966.46 | JL11: =+JI11-JK11 -> 0
BC12: 16000 | JI12: =SUM(A12:JH12) -> 16000 | JJ12: 298 | JK12: 16000 | JL12: =+JI12-JK12 -> 0
AW13: 25000 | JI13: =SUM(A13:JH13) -> 25000 | JJ13: 299 | JK13: 25000 | JL13: =+JI13-JK13 -> 0
AQ14: 111421.68 | JI14: =SUM(A14:JH14) -> 111421.68 | JJ14: 300 | JK14: 111421.68 | JL14: =+JI14-JK14 -> 0
DE15: 25000 | JI15: =SUM(A15:JH15) -> 25000 | JJ15: 301 | JK15: 25000 | JL15: =+JI15-JK15 -> 0
GJ16: 1819265 | JI16: =SUM(A16:JH16) -> 1819265 | JJ16: 302 | JK16: 1819265 | JL16: =+JI16-JK16 -> 0
DK17: 633345.26 | DV17: 17600.03 | FV17: 2900 | JI17: =SUM(A17:JH17) -> 653845.29 | JJ17: 303 | JK17: 653845.29 | JL17: =+JI17-JK17 -> 0
DK18: 237670 | JI18: =SUM(A18:JH18) -> 237670 | JJ18: 304 | JK18: 237670 | JL18: =+JI18-JK18 -> 0
DI19: 90048.75 | JI19: =SUM(A19:JH19) -> 90048.75 | JJ19: 305 | JK19: 90048.75 | JL19: =+JI19-JK19 -> 0
FA20: 172000 | JI20: =SUM(A20:JH20) -> 172000 | JJ20: 306 | JK20: 172000 | JL20: =+JI20-JK20 -> 0
FT21: 27704.04 | JI21: =SUM(A21:JH21) -> 27704.04 | JJ21: 307 | JK21: 27704.04 | JL21: =+JI21-JK21 -> 0
FD22: 22638 | JI22: =SUM(A22:JH22) -> 22638 | JJ22: 308 | JK22: 22638 | JL22: =+JI22-JK22 -> 0
EA23: 74000 | JI23: =SUM(A23:JH23) -> 74000 | JJ23: 309 | JK23: 74000 | JL23: =+JI23-JK23 -> 0
AW24: 25000 | JI24: =SUM(A24:JH24) -> 25000 | JJ24: 310 | JK24: 25000 | JL24: =+JI24-JK24 -> 0
DE25: 76045 | JI25: =SUM(A25:JH25) -> 76045 | JJ25: 311 | JK25: 76045 | JL25: =+JI25-JK25 -> 0
DE26: 44300 | JI26: =SUM(A26:JH26) -> 44300 | JJ26: 312 | JK26: 44300 | JL26: =+JI26-JK26 -> 0
CL27: 180568 | JI27: =SUM(A27:JH27) -> 180568 | JJ27: 313 | JK27: 180568 | JL27: =+JI27-JK27 -> 0
AY28: 136880 | JI28: =SUM(A28:JH28) -> 136880 | JJ28: 314 | JK28: 136880 | JL28: =+JI28-JK28 -> 0
CL29: 396975.6 | JI29: =SUM(A29:JH29) -> 396975.6 | JJ29: 315 | JK29: 396975.6 | JL29: =+JI29-JK29 -> 0
GH30: 162142.87 | GK30: 26658.16 | GL30: 59500 | JI30: =SUM(A30:JH30) -> 248301.03 | JJ30: 316 | JK30: 248301.03 | JL30: =+JI30-JK30 -> 0
AY31: 132840.57 | JI31: =SUM(A31:JH31) -> 132840.57 | JJ31: 317 | JK31: 132840.57 | JL31: =+JI31-JK31 -> 0
FN32: 365139.2 | JI32: =SUM(A32:JH32) -> 365139.2 | JJ32: 318 | JK32: 365139.2 | JL32: =+JI32-JK32 -> 0
FN33: 308841.4 | JI33: =SUM(A33:JH33) -> 308841.4 | JJ33: 319 | JK33: 308841.4 | JL33: =+JI33-JK33 -> 0
BC34: 32000 | JI34: =SUM(A34:JH34) -> 32000 | JJ34: 320 | JK34: 32000 | JL34: =+JI34-JK34 -> 0
FV35: 858540 | JI35: =SUM(A35:JH35) -> 858540 | JJ35: 321 | JK35: 858540 | JL35: =+JI35-JK35 -> 0
DK36: 34270.4 | JI36: =SUM(A36:JH36) -> 34270.4 | JJ36: 322 | JK36: 34270.4 | JL36: =+JI36-JK36 -> 0
CJ37: 33714.29 | JI37: =SUM(A37:JH37) -> 33714.29 | JJ37: 37290 | JL37: =+JI37-JK37 -> 33714.29
GA38: 55617.91 | JI38: =SUM(A38:JH38) -> 55617.91 | JJ38: =+JJ37+1 -> 37291 | JL38: =+JI38-JK38 -> 55617.91
GC39: 3600 | JI39: =SUM(A39:JH39) -> 3600 | JJ39: =+JJ38+1 -> 37292 | JL39: =+JI39-JK39 -> 3600
JI40: =SUM(A40:JH40) -> 0 | JJ40: =+JJ39+1 -> 37293 | JL40: =+JI40-JK40 -> 0
JI41: =SUM(A41:JH41) -> 0 | JJ41: =+JJ40+1 -> 37294 | JL41: =+JI41-JK41 -> 0
GA42: 56472.04 | JI42: =SUM(A42:JH42) -> 56472.04 | JJ42: =+JJ41+1 -> 37295 | JL42: =+JI42-JK42 -> 56472.04
JI43: =SUM(A43:JH43) -> 0 | JJ43: =+JJ42+1 -> 37296 | JL43: =+JI43-JK43 -> 0
GC44: 18000 | JI44: =SUM(A44:JH44) -> 18000 | JJ44: =+JJ43+1 -> 37297 | JL44: =+JI44-JK44 -> 18000
CL45: 21673.47 | JI45: =SUM(A45:JH45) -> 21673.47 | JJ45: =+JJ44+1 -> 37298 | JL45: =+JI45-JK45 -> 21673.47
CL46: 18061.22 | JI46: =SUM(A46:JH46) -> 18061.22 | JJ46: =+JJ45+1 -> 37299 | JL46: =+JI46-JK46 -> 18061.22
CL47: 18061.22 | JI47: =SUM(A47:JH47) -> 18061.22 | JJ47: =+JJ46+1 -> 37300 | JL47: =+JI47-JK47 -> 18061.22
BC48: 20000 | JI48: =SUM(A48:JH48) -> 20000 | JJ48: =+JJ47+1 -> 37301 | JL48: =+JI48-JK48 -> 20000
X49: 4413127.6 | JI49: =SUM(A49:JH49) -> 4413127.6 | JJ49: 322-A | JL49: =+JI49-JK49 -> 4413127.6
JI50: =SUM(A50:JH50) -> 0 | JL50: =+JI50-JK50 -> 0
JI51: =SUM(A51:JH51) -> 0 | JL51: =+JI51-JK51 -> 0
JI52: =SUM(A52:JH52) -> 0 | JL52: =+JI52-JK52 -> 0
JI53: =SUM(A53:JH53) -> 0 | JL53: =+JI53-JK53 -> 0
JI54: =SUM(A54:JH54) -> 0 | JL54: =+JI54-JK54 -> 0
JI55: =SUM(A55:JH55) -> 0 | JL55: =+JI55-JK55 -> 0
CP56: 21179.93 | JI56: =SUM(A56:JH56) -> 21179.93 | JL56: =+JI56-JK56 -> 21179.93
JI57: =SUM(A57:JH57) -> 0 | JL57: =+JI57-JK57 -> 0
A58: =SUM(A3:A57) -> 0 | B58: =SUM(B3:B57) -> 0 | C58: =SUM(C3:C57) -> 0 | D58: =SUM(D3:D57) -> 0 | E58: =SUM(E3:E57) -> 0 | F58: =SUM(F3:F57) -> 0 | G58: =SUM(G3:G57) -> 0 | H58: =SUM(H3:H57) -> 0 | ... JI58: =SUM(JI3:JI57) -> 11406705 | JK58: =SUM(JK3:JK57) -> 6727197.8 | JL58: =SUM(JL3:JL57) -> 4679507.6 | JM58: =SUM(JM3:JM57) -> 0 | JN58: =SUM(JN3:JN57) -> 0 | JO58: =SUM(JO3:JO57) -> 0 | JP58: =SUM(JP3:JP57) -> 0
A59: 211101 | B59: 211102 | C59: 211103 | D59: 211104 | E59: 211105 | F59: 211106 | G59: 211203 | H59: 211205 | I59: 211206 | J59: 211208 | K59: 211209 | L59: 211211 | M59: 211301 | N59: 211401 | O59: 211501 | P59: 211502 | Q59: 211503 | R59: 211504 | S59: 212101 | T59: 212201 | U59: 212203 | V59: 212204 | W59: 212205 | X59: 212206 | Y59: 212207 | Z59: 212208 | AA59: 212209 | AB59: 212210 | AC59: 213101 | AD59: 213102 | AE59: 213201 | AF59: 213202 | AG59: 214101 | AH59: 214201 | AI59: 214202 | AJ59: 214203 | AK59: 215101 | AL59: 215201 | AM59: 215301 | AN59: 215401 | AO59: 221101 | AP59: 221201 | AQ59: 221301 | AR59: 221401 | AS59: 221501 | AT59: 221601 | AU59: 221602 | AV59: 221701 | AW59: 221801 | AX59: 222101 | AY59: 222201 | AZ59: 223101 | BA59: 223201 | BB59: 224101 | BC59: 224201 | BD59: 224301 | BE59: 224401 | BF59: 225101 | BG59: 225201 | BH59: 225301 | BI59: 225302 | BJ59: 225303 | BK59: 225304 | BL59: 225305 | BM59: 225401 | BN59: 225501 | BO59: 225601 | BP59: 225701 | BQ59: 225801 | BR59: 225901 | BS59: 226101 | BT59: 226201 | BU59: 226301 | BV59: 226401 | BW59: 227101 | BX59: 227102 | BY59: 227103 | BZ59: 227104 | CA59: 227105 | CB59: 227106 | CC59: 227107 | CD59: 227199 | CE59: 227201 | CF59: 227202 | CG59: 227203 | CH59: 227204 | CI59: 227205 | CJ59: 227206 | CK59: 227207 | CL59: 227208 | CM59: 227299 | CN59: 227301 | CO59: 228101 | CP59: 228201 | CQ59: 228301 | CR59: 228401 | CS59: 228501 | CT59: 228502 | CU59: 228503 | CV59: 228601 | CW59: 228602 | CX59: 228603 | CY59: 228604 | CZ59: 228701 | DA59: 228702 | DB59: 228703 | DC59: 228704 | DD59: 228705 | DE59: 228706 | DF59: 228801 | DG59: 228802 | DH59: 228803 | DI59: 229201 | DJ59: 229203 | DK59: 231101 | DL59: 231102 | DM59: 231201 | DN59: 231301 | DO59: 231302 | DP59: 231303 | DQ59: 231401 | DR59: 232101 | DS59: 232201 | DT59: 232301 | DU59: 233101 | DV59: 233201 | DW59: 233301 | DX59: 233401 | DY59: 233501 | DZ59: 233601 | EA59: 234101 | EB59: 234201 | EC59: 235101 | ED59: 235201 | EE59: 235301 | EF59: 235401 | EG59: 235501 | EH59: 236101 | EI59: 236102 | EJ59: 236103 | EK59: 236104 | EL59: 236105 | EM59: 236201 | EN59: 236202 | EO59: 236203 | EP59: 236304 | EQ59: 236305 | ER59: 236306 | ES59: 236401 | ET59: 236402 | EU59: 236403 | EV59: 236404 | EW59: 236405 | EX59: 236406 | EY59: 236407 | EZ59: 236901 | FA59: 237101 | FB59: 237102 | FC59: 237103 | FD59: 237104 | FE59: 237105 | FF59: 237106 | FG59: 237107 | FH59: 237201 | FI59: 237202 | FJ59: 237203 | FK59: 237204 | FL59: 237205 | FM59: 237206 | FN59: 237299 | FO59: 238101 | FP59: 238201 | FQ59: 239101 | FR59: 239102 | FS59: 239201 | FT59: 239301 | FU59: 239401 | FV59: 239501 | FW59: 239601 | FX59: 239701 | FY59: 239801 | FZ59: 239802 | GA59: 239901 | GB59: 239904 | GC59: 241201 | GD59: 241202 | GE59: 241203 | GF59: 241204 | GG59: 241205 | GH59: 261101 | GI59: 261201 | GJ59: 261301 | GK59: 261401 | GL59: 261901 | GM59: 262101 | GN59: 262201 | GO59: 262301 | GP59: 262401 | GQ59: 263101 | GR59: 263201 | GS59: 263301 | GT59: 263401 | GU59: 264101 | GV59: 264201 | GW59: 264301 | GX59: 264401 | GY59: 264501 | GZ59: 264601 | HA59: 264701 | HB59: 264801 | HC59: 265101 | HD59: 265201 | HE59: 265301 | HF59: 265401 | HG59: 265501 | HH59: 265601 | HI59: 265701 | HJ59: 265801 | HK59: 266101 | HL59: 266201 | HM59: 267101 | HN59: 267201 | HO59: 267301 | HP59: 267401 | HQ59: 267501 | HR59: 267601 | HS59: 267701 | HT59: 267801 | HU59: 267901 | HV59: 268101 | HW59: 268201 | HX59: 268301 | HY59: 268302 | HZ59: 268401 | IA59: 268501 | IB59: 268601 | IC59: 268701 | ID59: 268802 | IE59: 268803 | IF59: 268804 | IG59: 268901 | IH59: 269101 | II59: 269102 | IJ59: 269201 | IK59: 269202 | IL59: 269301 | IM59: 269401 | IN59: 269501 | IO59: 269502 | IP59: 269503 | IQ59: 2269901 | IR59: 271101 | IS59: 271201 | IT59: 271301 | IU59: 271401 | IV59: 272101 | IW59: 272201 | IX59: 272301 | IY59: 272401 | IZ59: 272501 | JA59: 272601 | JB59: 272701 | JC59: 272801 | JD59: 272901 | JE59: 273101 | JF59: 273201 | JG59: 274101 | JH59: 274201 | JI59: Totales
JI60: =SUM(A60:JH60) -> 0
JI61: =SUM(A61:JH61) -> 0
JI62: =SUM(A62:JH62) -> 0
JI63: =SUM(A63:JH63) -> 0
JI64: =SUM(A64:JH64) -> 0
JI65: =SUM(A65:JH65) -> 0
JI66: =SUM(A66:JH66) -> 0
JI67: =SUM(A67:JH67) -> 0
JI68: =SUM(A68:JH68) -> 0
JI69: =SUM(A69:JH69) -> 0
JI70: =SUM(A70:JH70) -> 0
JI71: =SUM(A71:JH71) -> 0
... JI73: =SUM(A73:JH73) -> 0
A74: =SUM(A60:A73) -> 0 | B74: =SUM(B60:B73) -> 0 | C74: =SUM(C60:C73) -> 0 | D74: =SUM(D60:D73) -> 0 | E74: =SUM(E60:E73) -> 0 | F74: =SUM(F60:F73) -> 0 | G74: =SUM(G60:G73) -> 0 | H74: =SUM(H60:H73) -> 0 | ... JI74: =SUM(JI60:JI73) -> 0
A75: =A58+A74 -> 0 | B75: =B58+B74 -> 0 | C75: =C58+C74 -> 0 | D75: =D58+D74 -> 0 | E75: =E58+E74 -> 0 | F75: =F58+F74 -> 0 | G75: =G58+G74 -> 0 | H75: =H58+H74 -> 0 | ... JI75: =JI58+JI74 -> 11406705

Sheet GASTOS X ATENCION
A1: SERVICIO NACIONAL DE SALUD
A2: ='CONS. FUENTES FINAN'!A6 -> HOSPITAL MATERNO INFANTIL SAN LORENZO DE LOS MINA
A3: RESUMEN COMPARATIVO DE GASTOS ESPECIFICOS FONDO 100 Y VENTA DE SERVICIOS
A6: DETALLE | B6: FONDO 100 | C6: VENTA SERVICIOS | D6: TOTAL | E6: %
A8: Atención Directa
A9: Medicamentos e Insumos Médicos | B9: ='CONS. FUENTES FINAN'!G245+'CONS. FUENTES FINAN'!G315 -> 15355854 | C9: ='CONS. FUENTES FINAN'!H245+'CONS. FUENTES FINAN'!H315 -> 101704.04 | D9: =SUM(B9:C9) -> 15457558 | E9: =+D9/D12 -> 0.73755365
A10: Oxigeno | B10: ='CONS. FUENTES FINAN'!G302 -> 0 | C10: ='CONS. FUENTES FINAN'!H302 -> 829658 | D10: =SUM(B10:C10) -> 829658 | E10: =+D10/D12 -> 0.03958693
A11: Reactivos e Insumos de Laboratorio | B11: ='CONS. FUENTES FINAN'!G296+'CONS. FUENTES FINAN'!G297+'CONS. FUENTES FINAN'!G298 -> 4665860.2 | C11: ='CONS. FUENTES FINAN'!H296+'CONS. FUENTES FINAN'!H297+'CONS. FUENTES FINAN'!H298 -> 4800 | D11: =SUM(B11:C11) -> 4670660.2 | E11: =+D11/D12 -> 0.22285942
A12: Total | B12: =SUM(B9:B11) -> 20021714 | C12: =SUM(C9:C11) -> 936162.04 | D12: =SUM(D9:D11) -> 20957877 | E12: =+D12/D39 -> 0.17215004
A13: Mantenimiento de Equipos
A14: Reparación y Mantenimiento Maquinaria y Eq. | B14: ='CONS. FUENTES FINAN'!G157+'CONS. FUENTES FINAN'!G188+'CONS. FUENTES FINAN'!G223+'CONS. FUENTES FINAN'!G252+'CONS. FUENTES FINAN'!G254+'CONS. FUENTES FINAN'!G256+'CONS. FUENTES FINAN'!G258+'CONS. FUENTES FINAN'!G261+'CONS. FUENTES FINAN'!G292+'CONS. FUENTES FINAN'!G293+'CONS. FUENTES FINAN'!G299+'CONS. FUENTES FINAN'!G300+'CONS. FUENTES FINAN'!G301+'CONS. FUENTES FINAN'!G324 -> 1687453.9 | C14: ='CONS. FUENTES FINAN'!H157+'CONS. FUENTES FINAN'!H188+'CONS. FUENTES FINAN'!H223+'CONS. FUENTES FINAN'!H252+'CONS. FUENTES FINAN'!H254+'CONS. FUENTES FINAN'!H256+'CONS. FUENTES FINAN'!H258+'CONS. FUENTES FINAN'!H261+'CONS. FUENTES FINAN'!H292+'CONS. FUENTES FINAN'!H293+'CONS. FUENTES FINAN'!H299+'CONS. FUENTES FINAN'!H300+'CONS. FUENTES FINAN'!H301+'CONS. FUENTES FINAN'!H324 -> 802020.26 | D14: =SUM(B14:C14) -> 2489474.1 | E14: =+D14/D16 -> 1
A15: Productos Eléctricos y Afines | B15: ='CONS. FUENTES FINAN'!G320 -> 0 | C15: ='CONS. FUENTES FINAN'!H320 -> 0 | D15: =SUM(B15:C15) -> 0 | E15: =+D15/D16 -> 0
A16: Total | B16: =SUM(B14:B15) -> 1687453.9 | C16: =SUM(C14:C15) -> 802020.26 | D16: =SUM(D14:D15) -> 2489474.1 | E16: =+D16/D39 -> 0.020448783
A17: Gastos Administrativos
A18: Servicios Personales | B18: ='CONS. FUENTES FINAN'!G26 -> 71591504 | C18: ='CONS. FUENTES FINAN'!H26 -> 4413127.6 | D18: =SUM(B18:C18) -> 76004631 | E18: =+D18/D34 -> 0.84234699
A19: Servicio Telefónico | B19: ='CONS. FUENTES FINAN'!G91+'CONS. FUENTES FINAN'!G93+'CONS. FUENTES FINAN'!G95+'CONS. FUENTES FINAN'!G97 -> 0 | C19: ='CONS. FUENTES FINAN'!H91+'CONS. FUENTES FINAN'!H93+'CONS. FUENTES FINAN'!H95+'CONS. FUENTES FINAN'!H97 -> 111421.68 | D19: =SUM(B19:C19) -> 111421.68 | E19: =+D19/D34 -> 0.0012348684
A20: Servicios Basicos (electricidad, agua y residuos solidos) | B20: ='CONS. FUENTES FINAN'!G99+'CONS. FUENTES FINAN'!G102+'CONS. FUENTES FINAN'!G104 -> 60535 | C20: ='CONS. FUENTES FINAN'!H99+'CONS. FUENTES FINAN'!H102+'CONS. FUENTES FINAN'!H104 -> 50000 | D20: =SUM(B20:C20) -> 110535 | E20: =+D20/D34 -> 0.0012250415
A21: Viáticos | B21: ='CONS. FUENTES FINAN'!G111 -> 0 | C21: ='CONS. FUENTES FINAN'!H111 -> 0 | D21: =SUM(B21:C21) -> 0 | E21: =+D21/D34 -> 0
A22: Transporte y almacenaje | B22: ='CONS. FUENTES FINAN'!G116 -> 0 | C22: ='CONS. FUENTES FINAN'!H116 -> 68000 | D22: =SUM(B22:C22) -> 68000 | E22: =+D22/D34 -> 0.00075363296
A23: Alquileres | B23: ='CONS. FUENTES FINAN'!G125 -> 0 | C23: ='CONS. FUENTES FINAN'!H125 -> 0 | D23: =SUM(B23:C23) -> 0 | E23: =+D23/D34 -> 0
A24: Comisiones y Gastos Bancarios | B24: ='CONS. FUENTES FINAN'!G182 -> 0 | C24: ='CONS. FUENTES FINAN'!H182 -> 21179.93 | D24: =SUM(B24:C24) -> 21179.93 | E24: =+D24/D34 -> 0.00023473372
A25: Materiales de Oficina, Impresión y Encuadernación | B25: ='CONS. FUENTES FINAN'!G109+'CONS. FUENTES FINAN'!G312 -> 318704.8 | C25: ='CONS. FUENTES FINAN'!H109+'CONS. FUENTES FINAN'!H312 -> 269720.57 | D25: =SUM(B25:C25) -> 588425.37 | E25: =+D25/D34 -> 0.0065214228
A26: Alimentos y Bebidas para Personas | B26: ='CONS. FUENTES FINAN'!G208+'CONS. FUENTES FINAN'!G214+'CONS. FUENTES FINAN'!G217+'CONS. FUENTES FINAN'!G219 -> 4494873.6 | C26: ='CONS. FUENTES FINAN'!H208+'CONS. FUENTES FINAN'!H214+'CONS. FUENTES FINAN'!H217+'CONS. FUENTES FINAN'!H219 -> 1136994.4 | D26: =SUM(B26:C26) -> 5631868 | E26: =+D26/D34 -> 0.062417078
A27: Productos de papel, carton e impesos | B27: ='CONS. FUENTES FINAN'!G232 -> 366980 | C27: ='CONS. FUENTES FINAN'!H232 -> 17600.03 | D27: =SUM(B27:C27) -> 384580.03 | E27: =+D27/D34 -> 0.004262238
A28: Articulos de Plasticos | B28: ='CONS. FUENTES FINAN'!G259 -> 0 | C28: ='CONS. FUENTES FINAN'!H259 -> 0 | D28: =SUM(B28:C28) -> 0 | E28: =+D28/D34 -> 0
A29: Gasolina | B29: ='CONS. FUENTES FINAN'!G288 -> 0 | C29: ='CONS. FUENTES FINAN'!H288 -> 172000 | D29: =SUM(B29:C29) -> 172000 | E29: =+D29/D34 -> 0.0019062481
A30: Gasoil | B30: ='CONS. FUENTES FINAN'!G289+'CONS. FUENTES FINAN'!G290 -> 337200 | C30: ='CONS. FUENTES FINAN'!H289+'CONS. FUENTES FINAN'!H290 -> 0 | D30: =SUM(B30:C30) -> 337200 | E30: =+D30/D34 -> 0.0037371328
A31: GLP | B31: ='CONS. FUENTES FINAN'!G291+'CONS. FUENTES FINAN'!G294 -> 0 | C31: ='CONS. FUENTES FINAN'!H291+'CONS. FUENTES FINAN'!H294 -> 22638 | D31: =SUM(B31:C31) -> 22638 | E31: =+D31/D34 -> 0.00025089328
A32: Materiales de Limpieza e Higiene | B32: ='CONS. FUENTES FINAN'!G309 -> 599529.09 | C32: ='CONS. FUENTES FINAN'!H309 -> 0 | D32: =SUM(B32:C32) -> 599529.09 | E32: =+D32/D34 -> 0.0066444836
A33: Otros Egresos y Gastos | B33: ='CONS. FUENTES FINAN'!G89+'CONS. FUENTES FINAN'!G107+'CONS. FUENTES FINAN'!G148+'CONS. FUENTES FINAN'!G180+'CONS. FUENTES FINAN'!G184+'CONS. FUENTES FINAN'!G186+'CONS. FUENTES FINAN'!G192+'CONS. FUENTES FINAN'!G197+'CONS. FUENTES FINAN'!G204+'CONS. FUENTES FINAN'!G225+'CONS. FUENTES FINAN'!G303+'CONS. FUENTES FINAN'!G316+'CONS. FUENTES FINAN'!G318+'CONS. FUENTES FINAN'!G322+'CONS. FUENTES FINAN'!G327+'CONS. FUENTES FINAN'!G330 -> 5037116.1 | C33: ='CONS. FUENTES FINAN'!H89+'CONS. FUENTES FINAN'!H107+'CONS. FUENTES FINAN'!H148+'CONS. FUENTES FINAN'!H180+'CONS. FUENTES FINAN'!H184+'CONS. FUENTES FINAN'!H186+'CONS. FUENTES FINAN'!H192+'CONS. FUENTES FINAN'!H197+'CONS. FUENTES FINAN'!H204+'CONS. FUENTES FINAN'!H225+'CONS. FUENTES FINAN'!H303+'CONS. FUENTES FINAN'!H316+'CONS. FUENTES FINAN'!H318+'CONS. FUENTES FINAN'!H322+'CONS. FUENTES FINAN'!H327+'CONS. FUENTES FINAN'!H330 -> 1140474.9 | D33: =SUM(B33:C33) -> 6177591 | E33: =+D33/D34 -> 0.068465238
A34: Total | B34: =SUM(B17:B33) -> 82806442 | C34: =SUM(C17:C33) -> 7423157.1 | D34: =SUM(D17:D33) -> 90229600 | E34: =+D34/D39 -> 0.74115473
A35: Gastos Inversion y Capital
A36: Bienes Muebles, Inmuebles e Intangibles | B36: ='CONS. FUENTES FINAN'!G336 -> 5819603.3 | C36: ='CONS. FUENTES FINAN'!H336 -> 2245366 | D36: =SUM(B36:C36) -> 8064969.4 | E36: =+D36/D38 -> 1
A37: Obras | B37: ='CONS. FUENTES FINAN'!G463 -> 0 | C37: ='CONS. FUENTES FINAN'!H463 -> 0 | D37: =SUM(B37:C37) -> 0 | E37: =+D37/D38 -> 0
A38: Total | B38: =SUM(B36:B37) -> 5819603.3 | C38: =SUM(C36:C37) -> 2245366 | D38: =SUM(D36:D37) -> 8064969.4 | E38: =+D38/D39 -> 0.066246445
A39: Total General | B39: =+B12+B16+B34+B38 -> 1.1033521e+08 | C39: =+C12+C16+C34+C38 -> 11406705 | D39: =+D12+D16+D34+D38 -> 1.2174192e+08 | E39: =+E12+E16+E34+E38 -> 1
A40: Porciento | B40: =+B39/D39 -> 0.90630421 | C40: =+C39/D39 -> 0.093695791 | D40: =+B40+C40 -> 1

Sheet PLANTILLA PRESUPUESTO
A1: SERVICIO NACIONAL DE SALUD
A2: NOMBRE DEL ESTABLECIMIENTO
A3: CONSOLIDADO GASTOS EJECUCION FINANCIERA 2025
A4: En RD$
A6: Detalle | B6: FONDO REPONIBLE | G6: VENTA SEVICIOS/OTROS APORTES | L6: TOTAL
A7: 2 - GASTOS | B7: 1ro | C7: 2do | D7: 3ro | E7: 4to | G7: 1ro | H7: 2do | I7: 3ro | J7: 4to | L7: 1ro | M7: 2do | N7: 3ro | O7: 4to
A8: 2.1 - REMUNERACIONES Y CONTRIBUCIONES | B8: =SUM(B9:B13) -> 1.9856074e+08 | C8: =SUM(C9:C13) -> 1.9977032e+08 | D8: =SUM(D9:D13) -> 2.1475844e+08 | E8: =SUM(E9:E13) -> 0 | G8: =SUM(G9:G13) -> 5231553.6 | H8: =SUM(H9:H13) -> 0 | I8: =SUM(I9:I13) -> 4413127.6 | J8: =SUM(J9:J13) -> 0 | L8: =SUM(B8+G8) -> 2.0379229e+08 | M8: =SUM(C8+H8) -> 1.9977032e+08 | N8: =SUM(D8+I8) -> 2.1917157e+08 | O8: =SUM(E8+J8) -> 0
A9: 2.1.1 - REMUNERACIONES | B9: =SUM('TRANSFERENCIA CORRIENTE'!C10:E10) -> 1.639452e+08 | C9: =SUM('TRANSFERENCIA CORRIENTE'!F10:H10) -> 1.6408478e+08 | D9: =SUM('TRANSFERENCIA CORRIENTE'!I10:K10) -> 1.775012e+08 | E9: =SUM('TRANSFERENCIA CORRIENTE'!L10:N10) -> 0 | G9: =SUM(VS!C10:E10) -> 0 | H9: =SUM(VS!F10:H10) -> 0 | I9: =SUM(VS!I10:K10) -> 0 | J9: =SUM(VS!L10:N10) -> 0 | L9: =SUM(B9+G9) -> 1.639452e+08 | M9: =SUM(C9+H9) -> 1.6408478e+08 | N9: =SUM(D9+I9) -> 1.775012e+08 | O9: =SUM(E9+J9) -> 0
A10: 2.1.2 - SOBRESUELDOS | B10: =SUM('TRANSFERENCIA CORRIENTE'!C11:E11) -> 9594398.8 | C10: =SUM('TRANSFERENCIA CORRIENTE'!F11:H11) -> 10535799 | D10: =SUM('TRANSFERENCIA CORRIENTE'!I11:K11) -> 10034891 | E10: =SUM('TRANSFERENCIA CORRIENTE'!L11:N11) -> 0 | G10: =SUM(VS!C11:E11) -> 5231553.6 | H10: =SUM(VS!F11:H11) -> 0 | I10: =SUM(VS!I11:K11) -> 4413127.6 | J10: =SUM(VS!L11:N11) -> 0 | L10: =SUM(B10+G10) -> 14825952 | M10: =SUM(C10+H10) -> 10535799 | N10: =SUM(D10+I10) -> 14448019 | O10: =SUM(E10+J10) -> 0
A11: 2.1.3 - DIETAS Y GASTOS DE REPRESENTACIÓN | B11: =SUM('TRANSFERENCIA CORRIENTE'!C12:E12) -> 0 | C11: =SUM('TRANSFERENCIA CORRIENTE'!F12:H12) -> 0 | D11: =SUM('TRANSFERENCIA CORRIENTE'!I12:K12) -> 0 | E11: =SUM('TRANSFERENCIA CORRIENTE'!L12:N12) -> 0 | G11: =SUM(VS!C12:E12) -> 0 | H11: =SUM(VS!F12:H12) -> 0 | I11: =SUM(VS!I12:K12) -> 0 | J11: =SUM(VS!L12:N12) -> 0 | L11: =SUM(B11+G11) -> 0 | M11: =SUM(C11+H11) -> 0 | N11: =SUM(D11+I11) -> 0 | O11: =SUM(E11+J11) -> 0
A12: 2.1.4 - GRATIFICACIONES Y BONIFICACIONES | B12: =SUM('TRANSFERENCIA CORRIENTE'!C13:E13) -> 0 | C12: =SUM('TRANSFERENCIA CORRIENTE'!F13:H13) -> 0 | D12: =SUM('TRANSFERENCIA CORRIENTE'!I13:K13) -> 0 | E12: =SUM('TRANSFERENCIA CORRIENTE'!L13:N13) -> 0 | G12: =SUM(VS!C13:E13) -> 0 | H12: =SUM(VS!F13:H13) -> 0 | I12: =SUM(VS!I13:K13) -> 0 | J12: =SUM(VS!L13:N13) -> 0 | L12: =SUM(B12+G12) -> 0 | M12: =SUM(C12+H12) -> 0 | N12: =SUM(D12+I12) -> 0 | O12: =SUM(E12+J12) -> 0
A13: 2.1.5 - CONTRIBUCIONES A LA SEGURIDAD SOCIAL | B13: =SUM('TRANSFERENCIA CORRIENTE'!C14:E14) -> 25021132 | C13: =SUM('TRANSFERENCIA CORRIENTE'!F14:H14) -> 25149742 | D13: =SUM('TRANSFERENCIA CORRIENTE'!I14:K14) -> 27222347 | E13: =SUM('TRANSFERENCIA CORRIENTE'!L14:N14) -> 0 | G13: =SUM(VS!C14:E14) -> 0 | H13: =SUM(VS!F14:H14) -> 0 | I13: =SUM(VS!I14:K14) -> 0 | J13: =SUM(VS!L14:N14) -> 0 | L13: =SUM(B13+G13) -> 25021132 | M13: =SUM(C13+H13) -> 25149742 | N13: =SUM(D13+I13) -> 27222347 | O13: =SUM(E13+J13) -> 0
A14: 2.2 - CONTRATACIÓN DE SERVICIOS | B14: =SUM(B15:B23) -> 9308364.9 | C14: =SUM(C15:C23) -> 10131818 | D14: =SUM(D15:D23) -> 10910792 | E14: =SUM(E15:E23) -> 0 | G14: =SUM(G15:G23) -> 8306683.8 | H14: =SUM(H15:H23) -> 7239413.8 | I14: =SUM(I15:I23) -> 10378416 | J14: =SUM(J15:J23) -> 0 | L14: =SUM(B14+G14) -> 17615049 | M14: =SUM(C14+H14) -> 17371232 | N14: =SUM(D14+I14) -> 21289207 | O14: =SUM(E14+J14) -> 0
A15: 2.2.1 - SERVICIOS BÁSICOS | B15: =SUM('TRANSFERENCIA CORRIENTE'!C16:E16) -> 2020024.3 | C15: =SUM('TRANSFERENCIA CORRIENTE'!F16:H16) -> 181605 | D15: =SUM('TRANSFERENCIA CORRIENTE'!J16:L16) -> 121070 | E15: =SUM('TRANSFERENCIA CORRIENTE'!L16:N16) -> 0 | G15: =SUM(VS!C16:E16) -> 2341561.9 | H15: =SUM(VS!F16:H16) -> 2348580.7 | I15: =SUM(VS!I16:K16) -> 2876937.6 | J15: =SUM(VS!L16:N16) -> 0 | L15: =SUM(B15+G15) -> 4361586.2 | M15: =SUM(C15+H15) -> 2530185.7 | N15: =SUM(D15+I15) -> 2998007.6 | O15: =SUM(E15+J15) -> 0
A16: 2.2.2 - PUBLICIDAD, IMPRESIÓN Y ENCUADERNACIÓN | B16: =SUM('TRANSFERENCIA CORRIENTE'!C17:E17) -> 324206.83 | C16: =SUM('TRANSFERENCIA CORRIENTE'!F17:H17) -> 351993.83 | D16: =SUM('TRANSFERENCIA CORRIENTE'!J17:L17) -> 136428.3 | E16: =SUM('TRANSFERENCIA CORRIENTE'!L17:N17) -> 0 | G16: =SUM(VS!C17:E17) -> 0 | H16: =SUM(VS!F17:H17) -> 310139.4 | I16: =SUM(VS!I17:K17) -> 1187725.2 | J16: =SUM(VS!L17:N17) -> 0 | L16: =SUM(B16+G16) -> 324206.83 | M16: =SUM(C16+H16) -> 662133.23 | N16: =SUM(D16+I16) -> 1324153.5 | O16: =SUM(E16+J16) -> 0
A17: 2.2.3 - VIÁTICOS | B17: =SUM('TRANSFERENCIA CORRIENTE'!C18:E18) -> 0 | C17: =SUM('TRANSFERENCIA CORRIENTE'!F18:H18) -> 0 | D17: =SUM('TRANSFERENCIA CORRIENTE'!J18:L18) -> 0 | E17: =SUM('TRANSFERENCIA CORRIENTE'!L18:N18) -> 0 | G17: =SUM(VS!C18:E18) -> 0 | H17: =SUM(VS!F18:H18) -> 0 | I17: =SUM(VS!I18:K18) -> 0 | J17: =SUM(VS!L18:N18) -> 0 | L17: =SUM(B17+G17) -> 0 | M17: =SUM(C17+H17) -> 0 | N17: =SUM(D17+I17) -> 0 | O17: =SUM(E17+J17) -> 0
A18: 2.2.4 - TRANSPORTE Y ALMACENAJE | B18: =SUM('TRANSFERENCIA CORRIENTE'!C19:E19) -> 0 | C18: =SUM('TRANSFERENCIA CORRIENTE'!F19:H19) -> 0 | D18: =SUM('TRANSFERENCIA CORRIENTE'!J19:L19) -> 0 | E18: =SUM('TRANSFERENCIA CORRIENTE'!L19:N19) -> 0 | G18: =SUM(VS!C19:E19) -> 56000 | H18: =SUM(VS!F19:H19) -> 96000 | I18: =SUM(VS!I19:K19) -> 76000 | J18: =SUM(VS!L19:N19) -> 0 | L18: =SUM(B18+G18) -> 56000 | M18: =SUM(C18+H18) -> 96000 | N18: =SUM(D18+I18) -> 76000 | O18: =SUM(E18+J18) -> 0
A19: 2.2.5 - ALQUILERES Y RENTAS | B19: =SUM('TRANSFERENCIA CORRIENTE'!C20:E20) -> 0 | C19: =SUM('TRANSFERENCIA CORRIENTE'!F20:H20) -> 150000 | D19: =SUM('TRANSFERENCIA CORRIENTE'!J20:L20) -> 150000 | E19: =SUM('TRANSFERENCIA CORRIENTE'!L20:N20) -> 0 | G19: =SUM(VS!C20:E20) -> 519625.15 | H19: =SUM(VS!F20:H20) -> 759170.42 | I19: =SUM(VS!I20:K20) -> 927025.64 | J19: =SUM(VS!L20:N20) -> 0 | L19: =SUM(B19+G19) -> 519625.15 | M19: =SUM(C19+H19) -> 909170.42 | N19: =SUM(D19+I19) -> 1077025.6 | O19: =SUM(E19+J19) -> 0
A20: 2.2.6 - SEGUROS | B20: =SUM('TRANSFERENCIA CORRIENTE'!C21:E21) -> 0 | C20: =SUM('TRANSFERENCIA CORRIENTE'!F21:H21) -> 0 | D20: =SUM('TRANSFERENCIA CORRIENTE'!J21:L21) -> 0 | E20: =SUM('TRANSFERENCIA CORRIENTE'!L21:N21) -> 0 | G20: =SUM(VS!C21:E21) -> 0 | H20: =SUM(VS!F21:H21) -> 0 | I20: =SUM(VS!I21:K21) -> 0 | J20: =SUM(VS!L21:N21) -> 0 | L20: =SUM(B20+G20) -> 0 | M20: =SUM(C20+H20) -> 0 | N20: =SUM(D20+I20) -> 0 | O20: =SUM(E20+J20) -> 0
A21: 2.2.7 - SERVICIOS DE CONSERVACIÓN, REPARACIONES MENORES E INSTALACIONES TEMPORALES | B21: =SUM('TRANSFERENCIA CORRIENTE'!C22:E22) -> 6474433.8 | C21: =SUM('TRANSFERENCIA CORRIENTE'!F22:H22) -> 5611474.3 | D21: =SUM('TRANSFERENCIA CORRIENTE'!J22:L22) -> 4409782.3 | E21: =SUM('TRANSFERENCIA CORRIENTE'!L22:N22) -> 0 | G21: =SUM(VS!C22:E22) -> 4556850.1 | H21: =SUM(VS!F22:H22) -> 1040817.6 | I21: =SUM(VS!I22:K22) -> 3360268.8 | J21: =SUM(VS!L22:N22) -> 0 | L21: =SUM(B21+G21) -> 11031284 | M21: =SUM(C21+H21) -> 6652291.9 | N21: =SUM(D21+I21) -> 7770051.1 | O21: =SUM(E21+J21) -> 0
A22: 2.2.8 - OTROS SERVICIOS NO INCLUIDOS EN CONCEPTOS ANTERIORES | B22: =SUM('TRANSFERENCIA CORRIENTE'!C23:E23) -> 489700 | C22: =SUM('TRANSFERENCIA CORRIENTE'!F23:H23) -> 413000 | D22: =SUM('TRANSFERENCIA CORRIENTE'!J23:L23) -> 3779000 | E22: =SUM('TRANSFERENCIA CORRIENTE'!L23:N23) -> 0 | G22: =SUM(VS!C23:E23) -> 832646.66 | H22: =SUM(VS!F23:H23) -> 1774418.3 | I22: =SUM(VS!I23:K23) -> 1400729.1 | J22: =SUM(VS!L23:N23) -> 0 | L22: =SUM(B22+G22) -> 1322346.7 | M22: =SUM(C22+H22) -> 2187418.3 | N22: =SUM(D22+I22) -> 5179729.1 | O22: =SUM(E22+J22) -> 0
A23: 2.2.9 - OTRAS CONTRATACIONES DE SERVICIOS | B23: =SUM('TRANSFERENCIA CORRIENTE'!C24:E24) -> 0 | C23: =SUM('TRANSFERENCIA CORRIENTE'!F24:H24) -> 3423745 | D23: =SUM('TRANSFERENCIA CORRIENTE'!J24:L24) -> 2314511 | E23: =SUM('TRANSFERENCIA CORRIENTE'!L24:N24) -> 0 | G23: =SUM(VS!C24:E24) -> 0 | H23: =SUM(VS!F24:H24) -> 910287.4 | I23: =SUM(VS!I24:K24) -> 549729.55 | J23: =SUM(VS!L24:N24) -> 0 | L23: =SUM(B23+G23) -> 0 | M23: =SUM(C23+H23) -> 4334032.4 | N23: =SUM(D23+I23) -> 2864240.5 | O23: =SUM(E23+J23) -> 0
A24: 2.3 - MATERIALES Y SUMINISTROS | B24: =SUM(B25:B33) -> 46153283 | C24: =SUM(C25:C33) -> 52385651 | D24: =SUM(D25:D33) -> 1.0378694e+08 | E24: =SUM(E25:E33) -> 0 | G24: =SUM(G25:G33) -> 7292547.3 | H24: =SUM(H25:H33) -> 6552680.6 | I24: =SUM(I25:I33) -> 9091857.1 | J24: =SUM(J25:J33) -> 0 | L24: =SUM(B24+G24) -> 53445831 | M24: =SUM(C24+H24) -> 58938331 | N24: =SUM(D24+I24) -> 1.128788e+08 | O24: =SUM(E24+J24) -> 0
A25: 2.3.1 - ALIMENTOS Y PRODUCTOS AGROFORESTALES | B25: =SUM('TRANSFERENCIA CORRIENTE'!C26:E26) -> 3713897.2 | C25: =SUM('TRANSFERENCIA CORRIENTE'!F26:H26) -> 4866999.2 | D25: =SUM('TRANSFERENCIA CORRIENTE'!I23:K23) -> 3779000 | E25: =SUM('TRANSFERENCIA CORRIENTE'!L26:N26) -> 0 | G25: =SUM(VS!C26:E26) -> 1500755.8 | H25: =SUM(VS!F26:H26) -> 663230 | I25: =SUM(VS!I26:K26) -> 1574425.7 | J25: =SUM(VS!L26:N26) -> 0 | L25: =SUM(B25+G25) -> 5214653 | M25: =SUM(C25+H25) -> 5530229.2 | N25: =SUM(D25+I25) -> 5353425.7 | O25: =SUM(E25+J25) -> 0
A26: 2.3.2 - TEXTILES Y VESTUARIOS | B26: =SUM('TRANSFERENCIA CORRIENTE'!C27:E27) -> 61630.73 | C26: =SUM('TRANSFERENCIA CORRIENTE'!F27:H27) -> 2375399.4 | D26: =SUM('TRANSFERENCIA CORRIENTE'!I24:K24) -> 2314511 | E26: =SUM('TRANSFERENCIA CORRIENTE'!L27:N27) -> 0 | G26: =SUM(VS!C27:E27) -> 0 | H26: =SUM(VS!F27:H27) -> 346306.4 | I26: =SUM(VS!I27:K27) -> 0 | J26: =SUM(VS!L27:N27) -> 0 | L26: =SUM(B26+G26) -> 61630.73 | M26: =SUM(C26+H26) -> 2721705.8 | N26: =SUM(D26+I26) -> 2314511 | O26: =SUM(E26+J26) -> 0
A27: 2.3.3 - PRODUCTOS DE PAPEL, CARTÓN E IMPRESOS | B27: =SUM('TRANSFERENCIA CORRIENTE'!C28:E28) -> 1826911.8 | C27: =SUM('TRANSFERENCIA CORRIENTE'!F28:H28) -> 2991695.7 | D27: =SUM('TRANSFERENCIA CORRIENTE'!I25:K25) -> 65609607 | E27: =SUM('TRANSFERENCIA CORRIENTE'!L28:N28) -> 0 | G27: =SUM(VS!C28:E28) -> 251163 | H27: =SUM(VS!F28:H28) -> 803989 | I27: =SUM(VS!I28:K28) -> 734332.03 | J27: =SUM(VS!L28:N28) -> 0 | L27: =SUM(B27+G27) -> 2078074.8 | M27: =SUM(C27+H27) -> 3795684.7 | N27: =SUM(D27+I27) -> 66343939 | O27: =SUM(E27+J27) -> 0
A28: 2.3.4 - PRODUCTOS FARMACÉUTICOS | B28: =SUM('TRANSFERENCIA CORRIENTE'!C29:E29) -> 10797336 | C28: =SUM('TRANSFERENCIA CORRIENTE'!F29:H29) -> 12009357 | D28: =SUM('TRANSFERENCIA CORRIENTE'!I26:K26) -> 6044845.1 | E28: =SUM('TRANSFERENCIA CORRIENTE'!L29:N29) -> 0 | G28: =SUM(VS!C29:E29) -> 558000 | H28: =SUM(VS!F29:H29) -> 402220.76 | I28: =SUM(VS!I29:K29) -> 496000 | J28: =SUM(VS!L29:N29) -> 0 | L28: =SUM(B28+G28) -> 11355336 | M28: =SUM(C28+H28) -> 12411577 | N28: =SUM(D28+I28) -> 6540845.1 | O28: =SUM(E28+J28) -> 0
A29: 2.3.5 - PRODUCTOS DE CUERO, CAUCHO Y PLÁSTICO | B29: =SUM('TRANSFERENCIA CORRIENTE'!C30:E30) -> 334708.95 | C29: =SUM('TRANSFERENCIA CORRIENTE'!F30:H30) -> 1024240.4 | D29: =SUM('TRANSFERENCIA CORRIENTE'!I27:K27) -> 3015806.8 | E29: =SUM('TRANSFERENCIA CORRIENTE'!L30:N30) -> 0 | G29: =SUM(VS!C30:E30) -> 567494.87 | H29: =SUM(VS!F30:H30) -> 0 | I29: =SUM(VS!I30:K30) -> 140314.78 | J29: =SUM(VS!L30:N30) -> 0 | L29: =SUM(B29+G29) -> 902203.82 | M29: =SUM(C29+H29) -> 1024240.4 | N29: =SUM(D29+I29) -> 3156121.5 | O29: =SUM(E29+J29) -> 0
A30: 2.3.6 - PRODUCTOS DE MINERALES, METÁLICOS Y NO METÁLICOS | B30: =SUM('TRANSFERENCIA CORRIENTE'!C31:E31) -> 11630.98 | C30: =SUM('TRANSFERENCIA CORRIENTE'!F31:H31) -> 667620.59 | D30: =SUM('TRANSFERENCIA CORRIENTE'!I28:K28) -> 2859834.4 | E30: =SUM('TRANSFERENCIA CORRIENTE'!L31:N31) -> 0 | G30: =SUM(VS!C31:E31) -> 293957.3 | H30: =SUM(VS!F31:H31) -> 0 | I30: =SUM(VS!I31:K31) -> 211552.06 | J30: =SUM(VS!L31:N31) -> 0 | L30: =SUM(B30+G30) -> 305588.28 | M30: =SUM(C30+H30) -> 667620.59 | N30: =SUM(D30+I30) -> 3071386.4 | O30: =SUM(E30+J30) -> 0
A31: 2.3.7 - COMBUSTIBLES, LUBRICANTES, PRODUCTOS QUÍMICOS Y CONEXOS | B31: =SUM('TRANSFERENCIA CORRIENTE'!C32:E32) -> 8910102 | C31: =SUM('TRANSFERENCIA CORRIENTE'!F32:H32) -> 10068979 | D31: =SUM('TRANSFERENCIA CORRIENTE'!I29:K29) -> 19203378 | E31: =SUM('TRANSFERENCIA CORRIENTE'!L32:N32) -> 0 | G31: =SUM(VS!C32:E32) -> 1660334.6 | H31: =SUM(VS!F32:H32) -> 1500202 | I31: =SUM(VS!I32:K32) -> 2324461 | J31: =SUM(VS!L32:N32) -> 0 | L31: =SUM(B31+G31) -> 10570437 | M31: =SUM(C31+H31) -> 11569181 | N31: =SUM(D31+I31) -> 21527839 | O31: =SUM(E31+J31) -> 0
A32: 2.3.8 - GASTOS QUE SE ASIGNARÁN DURANTE EL EJERCICIO (ART. 32 Y 33 LEY 423-06) | B32: =SUM('TRANSFERENCIA CORRIENTE'!C33:E33) -> 0 | C32: =SUM('TRANSFERENCIA CORRIENTE'!F33:H33) -> 0 | D32: =SUM('TRANSFERENCIA CORRIENTE'!I30:K30) -> 673453.82 | E32: =SUM('TRANSFERENCIA CORRIENTE'!L33:N33) -> 0 | G32: =SUM(VS!C33:E33) -> 0 | H32: =SUM(VS!F33:H33) -> 0 | I32: =SUM(VS!I33:K33) -> 0 | J32: =SUM(VS!L33:N33) -> 0 | L32: =SUM(B32+G32) -> 0 | M32: =SUM(C32+H32) -> 0 | N32: =SUM(D32+I32) -> 673453.82 | O32: =SUM(E32+J32) -> 0
A33: 2.3.9 - PRODUCTOS Y ÚTILES VARIOS | B33: =SUM('TRANSFERENCIA CORRIENTE'!C34:E34) -> 20497066 | C33: =SUM('TRANSFERENCIA CORRIENTE'!F34:H34) -> 18381359 | D33: =SUM('TRANSFERENCIA CORRIENTE'!I31:K31) -> 286504 | E33: =SUM('TRANSFERENCIA CORRIENTE'!L34:N34) -> 0 | G33: =SUM(VS!C34:E34) -> 2460841.8 | H33: =SUM(VS!F34:H34) -> 2836732.4 | I33: =SUM(VS!I34:K34) -> 3610771.5 | J33: =SUM(VS!L34:N34) -> 0 | L33: =SUM(B33+G33) -> 22957908 | M33: =SUM(C33+H33) -> 21218092 | N33: =SUM(D33+I33) -> 3897275.5 | O33: =SUM(E33+J33) -> 0
A34: 2.4 - TRANSFERENCIAS CORRIENTES | B34: =SUM(B35:B41) -> 0 | C34: =SUM(C35:C41) -> 0 | D34: =SUM(D35:D41) -> 0 | E34: =SUM(E35:E41) -> 0 | G34: =SUM(G35:G41) -> 287786.7 | H34: =SUM(H35:H41) -> 1223981 | I34: =SUM(I35:I41) -> 122771 | J34: =SUM(J35:J41) -> 0 | L34: =SUM(B34+G34) -> 287786.7 | M34: =SUM(C34+H34) -> 1223981 | N34: =SUM(D34+I34) -> 122771 | O34: =SUM(E34+J34) -> 0
A35: 2.4.1 - TRANSFERENCIAS CORRIENTES AL SECTOR PRIVADO | B35: =SUM('TRANSFERENCIA CORRIENTE'!C36:E36) -> 0 | C35: =SUM('TRANSFERENCIA CORRIENTE'!F36:H36) -> 0 | D35: =SUM('TRANSFERENCIA CORRIENTE'!I36:K36) -> 0 | E35: =SUM('TRANSFERENCIA CORRIENTE'!L36:N36) -> 0 | G35: =SUM(VS!C36:E36) -> 287786.7 | H35: =SUM(VS!F36:H36) -> 1223981 | I35: =SUM(VS!I36:K36) -> 122771 | J35: =SUM(VS!L36:N36) -> 0 | L35: =SUM(B35+G35) -> 287786.7 | M35: =SUM(C35+H35) -> 1223981 | N35: =SUM(D35+I35) -> 122771 | O35: =SUM(E35+J35) -> 0
A36: 2.4.2 - TRANSFERENCIAS CORRIENTES AL GOBIERNO GENERAL NACIONAL | B36: =SUM('TRANSFERENCIA CORRIENTE'!C37:E37) -> 0 | C36: =SUM('TRANSFERENCIA CORRIENTE'!F37:H37) -> 0 | D36: =SUM('TRANSFERENCIA CORRIENTE'!I37:K37) -> 0 | E36: =SUM('TRANSFERENCIA CORRIENTE'!L37:N37) -> 0 | G36: =SUM(VS!C37:E37) -> 0 | H36: =SUM(VS!F37:H37) -> 0 | I36: =SUM(VS!I37:K37) -> 0 | J36: =SUM(VS!L37:N37) -> 0 | L36: =SUM(B36+G36) -> 0 | M36: =SUM(C36+H36) -> 0 | N36: =SUM(D36+I36) -> 0 | O36: =SUM(E36+J36) -> 0
A37: 2.4.3 - TRANSFERENCIAS CORRIENTES A GOBIERNOS GENERALES LOCALES | B37: =SUM('TRANSFERENCIA CORRIENTE'!C38:E38) -> 0 | C37: =SUM('TRANSFERENCIA CORRIENTE'!F38:H38) -> 0 | D37: =SUM('TRANSFERENCIA CORRIENTE'!I38:K38) -> 0 | E37: =SUM('TRANSFERENCIA CORRIENTE'!L38:N38) -> 0 | G37: =SUM(VS!C38:E38) -> 0 | H37: =SUM(VS!F38:H38) -> 0 | I37: =SUM(VS!I38:K38) -> 0 | J37: =SUM(VS!L38:N38) -> 0 | L37: =SUM(B37+G37) -> 0 | M37: =SUM(C37+H37) -> 0 | N37: =SUM(D37+I37) -> 0 | O37: =SUM(E37+J37) -> 0
A38: 2.4.4 - TRANSFERENCIAS CORRIENTES A EMPRESAS PÚBLICAS NO FINANCIERAS | B38: =SUM('TRANSFERENCIA CORRIENTE'!C39:E39) -> 0 | C38: =SUM('TRANSFERENCIA CORRIENTE'!F39:H39) -> 0 | D38: =SUM('TRANSFERENCIA CORRIENTE'!I39:K39) -> 0 | E38: =SUM('TRANSFERENCIA CORRIENTE'!L39:N39) -> 0 | G38: =SUM(VS!C39:E39) -> 0 | H38: =SUM(VS!F39:H39) -> 0 | I38: =SUM(VS!I39:K39) -> 0 | J38: =SUM(VS!L39:N39) -> 0 | L38: =SUM(B38+G38) -> 0 | M38: =SUM(C38+H38) -> 0 | N38: =SUM(D38+I38) -> 0 | O38: =SUM(E38+J38) -> 0
A39: 2.4.5 - TRANSFERENCIAS CORRIENTES A INSTITUCIONES PÚBLICAS FINANCIERAS | B39: =SUM('TRANSFERENCIA CORRIENTE'!C40:E40) -> 0 | C39: =SUM('TRANSFERENCIA CORRIENTE'!F40:H40) -> 0 | D39: =SUM('TRANSFERENCIA CORRIENTE'!I40:K40) -> 0 | E39: =SUM('TRANSFERENCIA CORRIENTE'!L40:N40) -> 0 | G39: =SUM(VS!C40:E40) -> 0 | H39: =SUM(VS!F40:H40) -> 0 | I39: =SUM(VS!I40:K40) -> 0 | J39: =SUM(VS!L40:N40) -> 0 | L39: =SUM(B39+G39) -> 0 | M39: =SUM(C39+H39) -> 0 | N39: =SUM(D39+I39) -> 0 | O39: =SUM(E39+J39) -> 0
A40: 2.4.7 - TRANSFERENCIAS CORRIENTES AL SECTOR EXTERNO | B40: =SUM('TRANSFERENCIA CORRIENTE'!C41:E41) -> 0 | C40: =SUM('TRANSFERENCIA CORRIENTE'!F41:H41) -> 0 | D40: =SUM('TRANSFERENCIA CORRIENTE'!I41:K41) -> 0 | E40: =SUM('TRANSFERENCIA CORRIENTE'!L41:N41) -> 0 | G40: =SUM(VS!C41:E41) -> 0 | H40: =SUM(VS!F41:H41) -> 0 | I40: =SUM(VS!I41:K41) -> 0 | J40: =SUM(VS!L41:N41) -> 0 | L40: =SUM(B40+G40) -> 0 | M40: =SUM(C40+H40) -> 0 | N40: =SUM(D40+I40) -> 0 | O40: =SUM(E40+J40) -> 0
A41: 2.4.9 - TRANSFERENCIAS CORRIENTES A OTRAS INSTITUCIONES PÚBLICAS | B41: =SUM('TRANSFERENCIA CORRIENTE'!C42:E42) -> 0 | C41: =SUM('TRANSFERENCIA CORRIENTE'!F42:H42) -> 0 | D41: =SUM('TRANSFERENCIA CORRIENTE'!I42:K42) -> 0 | E41: =SUM('TRANSFERENCIA CORRIENTE'!L42:N42) -> 0 | G41: =SUM(VS!C42:E42) -> 0 | H41: =SUM(VS!F42:H42) -> 0 | I41: =SUM(VS!I42:K42) -> 0 | J41: =SUM(VS!L42:N42) -> 0 | L41: =SUM(B41+G41) -> 0 | M41: =SUM(C41+H41) -> 0 | N41: =SUM(D41+I41) -> 0 | O41: =SUM(E41+J41) -> 0
A42: 2.5 - TRANSFERENCIAS DE CAPITAL | B42: =SUM(B43:B49) -> 0 | C42: =SUM(C43:C49) -> 0 | D42: =SUM(D43:D49) -> 0 | E42: =SUM(E43:E49) -> 0 | G42: =SUM(G43:G49) -> 0 | H42: =SUM(H43:H49) -> 0 | I42: =SUM(I43:I49) -> 0 | J42: =SUM(J43:J49) -> 0 | L42: =SUM(B42+G42) -> 0 | M42: =SUM(C42+H42) -> 0 | N42: =SUM(D42+I42) -> 0 | O42: =SUM(E42+J42) -> 0
A43: 2.5.1 - TRANSFERENCIAS DE CAPITAL AL SECTOR PRIVADO | B43: =SUM('TRANSFERENCIA CORRIENTE'!C44:E44) -> 0 | C43: =SUM('TRANSFERENCIA CORRIENTE'!F44:H44) -> 0 | D43: =SUM('TRANSFERENCIA CORRIENTE'!I44:K44) -> 0 | E43: =SUM('TRANSFERENCIA CORRIENTE'!L44:N44) -> 0 | G43: =SUM(VS!C44:E44) -> 0 | H43: =SUM(VS!F44:H44) -> 0 | I43: =SUM(VS!I44:K44) -> 0 | J43: =SUM(VS!L44:N44) -> 0 | L43: =SUM(B43+G43) -> 0 | M43: =SUM(C43+H43) -> 0 | N43: =SUM(D43+I43) -> 0 | O43: =SUM(E43+J43) -> 0
A44: 2.5.2 - TRANSFERENCIAS DE CAPITAL AL GOBIERNO GENERAL NACIONAL | B44: =SUM('TRANSFERENCIA CORRIENTE'!C45:E45) -> 0 | C44: =SUM('TRANSFERENCIA CORRIENTE'!F45:H45) -> 0 | D44: =SUM('TRANSFERENCIA CORRIENTE'!I45:K45) -> 0 | E44: =SUM('TRANSFERENCIA CORRIENTE'!L45:N45) -> 0 | G44: =SUM(VS!C45:E45) -> 0 | H44: =SUM(VS!F45:H45) -> 0 | I44: =SUM(VS!I45:K45) -> 0 | J44: =SUM(VS!L45:N45) -> 0 | L44: =SUM(B44+G44) -> 0 | M44: =SUM(C44+H44) -> 0 | N44: =SUM(D44+I44) -> 0 | O44: =SUM(E44+J44) -> 0
A45: 2.5.3 - TRANSFERENCIAS DE CAPITAL A GOBIERNOS GENERALES LOCALES | B45: =SUM('TRANSFERENCIA CORRIENTE'!C46:E46) -> 0 | C45: =SUM('TRANSFERENCIA CORRIENTE'!F46:H46) -> 0 | D45: =SUM('TRANSFERENCIA CORRIENTE'!I46:K46) -> 0 | E45: =SUM('TRANSFERENCIA CORRIENTE'!L46:N46) -> 0 | G45: =SUM(VS!C46:E46) -> 0 | H45: =SUM(VS!F46:H46) -> 0 | I45: =SUM(VS!I46:K46) -> 0 | J45: =SUM(VS!L46:N46) -> 0 | L45: =SUM(B45+G45) -> 0 | M45: =SUM(C45+H45) -> 0 | N45: =SUM(D45+I45) -> 0 | O45: =SUM(E45+J45) -> 0
A46: 2.5.4 - TRANSFERENCIAS DE CAPITAL A EMPRESAS PÚBLICAS NO FINANCIERAS | B46: =SUM('TRANSFERENCIA CORRIENTE'!C47:E47) -> 0 | C46: =SUM('TRANSFERENCIA CORRIENTE'!F47:H47) -> 0 | D46: =SUM('TRANSFERENCIA CORRIENTE'!I47:K47) -> 0 | E46: =SUM('TRANSFERENCIA CORRIENTE'!L47:N47) -> 0 | G46: =SUM(VS!C47:E47) -> 0 | H46: =SUM(VS!F47:H47) -> 0 | I46: =SUM(VS!I47:K47) -> 0 | J46: =SUM(VS!L47:N47) -> 0 | L46: =SUM(B46+G46) -> 0 | M46: =SUM(C46+H46) -> 0 | N46: =SUM(D46+I46) -> 0 | O46: =SUM(E46+J46) -> 0
A47: 2.5.5 - TRANSFERENCIAS DE CAPITAL A INSTITUCIONES PÚBLICAS FINANCIERAS | B47: =SUM('TRANSFERENCIA CORRIENTE'!C48:E48) -> 0 | C47: =SUM('TRANSFERENCIA CORRIENTE'!F48:H48) -> 0 | D47: =SUM('TRANSFERENCIA CORRIENTE'!I48:K48) -> 0 | E47: =SUM('TRANSFERENCIA CORRIENTE'!L48:N48) -> 0 | G47: =SUM(VS!C48:E48) -> 0 | H47: =SUM(VS!F48:H48) -> 0 | I47: =SUM(VS!I48:K48) -> 0 | J47: =SUM(VS!L48:N48) -> 0 | L47: =SUM(B47+G47) -> 0 | M47: =SUM(C47+H47) -> 0 | N47: =SUM(D47+I47) -> 0 | O47: =SUM(E47+J47) -> 0
A48: 2.5.6 - TRANSFERENCIAS DE CAPITAL AL SECTOR EXTERNO | B48: =SUM('TRANSFERENCIA CORRIENTE'!C49:E49) -> 0 | C48: =SUM('TRANSFERENCIA CORRIENTE'!F49:H49) -> 0 | D48: =SUM('TRANSFERENCIA CORRIENTE'!I49:K49) -> 0 | E48: =SUM('TRANSFERENCIA CORRIENTE'!L49:N49) -> 0 | G48: =SUM(VS!C49:E49) -> 0 | H48: =SUM(VS!F49:H49) -> 0 | I48: =SUM(VS!I49:K49) -> 0 | J48: =SUM(VS!L49:N49) -> 0 | L48: =SUM(B48+G48) -> 0 | M48: =SUM(C48+H48) -> 0 | N48: =SUM(D48+I48) -> 0 | O48: =SUM(E48+J48) -> 0
A49: 2.5.9 - TRANSFERENCIAS DE CAPITAL A OTRAS INSTITUCIONES PÚBLICAS | B49: =SUM('TRANSFERENCIA CORRIENTE'!C50:E50) -> 0 | C49: =SUM('TRANSFERENCIA CORRIENTE'!F50:H50) -> 0 | D49: =SUM('TRANSFERENCIA CORRIENTE'!I50:K50) -> 0 | E49: =SUM('TRANSFERENCIA CORRIENTE'!L50:N50) -> 0 | G49: =SUM(VS!C50:E50) -> 0 | H49: =SUM(VS!F50:H50) -> 0 | I49: =SUM(VS!I50:K50) -> 0 | J49: =SUM(VS!L50:N50) -> 0 | L49: =SUM(B49+G49) -> 0 | M49: =SUM(C49+H49) -> 0 | N49: =SUM(D49+I49) -> 0 | O49: =SUM(E49+J49) -> 0
A50: 2.6 - BIENES MUEBLES, INMUEBLES E INTANGIBLES | B50: =SUM(B51:B59) -> 17857867 | C50: =SUM(C51:C59) -> 14943855 | D50: =SUM(D51:D59) -> 25711105 | E50: =SUM(E51:E59) -> 0 | G50: =SUM(G51:G59) -> 5076044.2 | H50: =SUM(H51:H59) -> 5383431.2 | I50: =SUM(I51:I59) -> 5370952.4 | J50: =SUM(J51:J59) -> 0 | L50: =SUM(B50+G50) -> 22933911 | M50: =SUM(C50+H50) -> 20327286 | N50: =SUM(D50+I50) -> 31082057 | O50: =SUM(E50+J50) -> 0
A51: 2.6.1 - MOBILIARIO Y EQUIPO | B51: =SUM('TRANSFERENCIA CORRIENTE'!C52:E52) -> 1110625.9 | C51: =SUM('TRANSFERENCIA CORRIENTE'!F52:H52) -> 3586435.1 | D51: =SUM('TRANSFERENCIA CORRIENTE'!I52:K52) -> 6119237.3 | E51: =SUM('TRANSFERENCIA CORRIENTE'!L52:N52) -> 0 | G51: =SUM(VS!C52:E52) -> 0 | H51: =SUM(VS!F52:H52) -> 7995.01 | I51: =SUM(VS!I52:K52) -> 2929998 | J51: =SUM(VS!L52:N52) -> 0 | L51: =SUM(B51+G51) -> 1110625.9 | M51: =SUM(C51+H51) -> 3594430.1 | N51: =SUM(D51+I51) -> 9049235.3 | O51: =SUM(E51+J51) -> 0
A52: 2.6.2 - MOBILIARIO Y EQUIPO EDUCACIONAL Y RECREATIVO | B52: =SUM('TRANSFERENCIA CORRIENTE'!C53:E53) -> 0 | C52: =SUM('TRANSFERENCIA CORRIENTE'!F53:H53) -> 182926.74 | D52: =SUM('TRANSFERENCIA CORRIENTE'!I53:K53) -> 0 | E52: =SUM('TRANSFERENCIA CORRIENTE'!L53:N53) -> 0 | G52: =SUM(VS!C53:E53) -> 0 | H52: =SUM(VS!F53:H53) -> 1399834 | I52: =SUM(VS!I53:K53) -> 389046 | J52: =SUM(VS!L53:N53) -> 0 | L52: =SUM(B52+G52) -> 0 | M52: =SUM(C52+H52) -> 1582760.7 | N52: =SUM(D52+I52) -> 389046 | O52: =SUM(E52+J52) -> 0
A53: 2.6.3 - EQUIPO E INSTRUMENTAL, CIENTÍFICO Y LABORATORIO | B53: =SUM('TRANSFERENCIA CORRIENTE'!C54:E54) -> 16744041 | C53: =SUM('TRANSFERENCIA CORRIENTE'!F54:H54) -> 6663622.6 | D53: =SUM('TRANSFERENCIA CORRIENTE'!I54:K54) -> 10518535 | E53: =SUM('TRANSFERENCIA CORRIENTE'!L54:N54) -> 0 | G53: =SUM(VS!C54:E54) -> 2963024.8 | H53: =SUM(VS!F54:H54) -> 3975602.1 | I53: =SUM(VS!I54:K54) -> 1710444.5 | J53: =SUM(VS!L54:N54) -> 0 | L53: =SUM(B53+G53) -> 19707066 | M53: =SUM(C53+H53) -> 10639225 | N53: =SUM(D53+I53) -> 12228980 | O53: =SUM(E53+J53) -> 0
A54: 2.6.4 - VEHÍCULOS Y EQUIPO DE TRANSPORTE, TRACCIÓN Y ELEVACIÓN | B54: =SUM('TRANSFERENCIA CORRIENTE'!C55:E55) -> 0 | C54: =SUM('TRANSFERENCIA CORRIENTE'!F55:H55) -> 0 | D54: =SUM('TRANSFERENCIA CORRIENTE'!I55:K55) -> 0 | E54: =SUM('TRANSFERENCIA CORRIENTE'!L55:N55) -> 0 | G54: =SUM(VS!C55:E55) -> 107609.37 | H54: =SUM(VS!F55:H55) -> 0 | I54: =SUM(VS!I55:K55) -> 0 | J54: =SUM(VS!L55:N55) -> 0 | L54: =SUM(B54+G54) -> 107609.37 | M54: =SUM(C54+H54) -> 0 | N54: =SUM(D54+I54) -> 0 | O54: =SUM(E54+J54) -> 0
A55: 2.6.5 - MAQUINARIA, OTROS EQUIPOS Y HERRAMIENTAS | B55: =SUM('TRANSFERENCIA CORRIENTE'!C56:E56) -> 3199.97 | C55: =SUM('TRANSFERENCIA CORRIENTE'!F56:H56) -> 4165309.5 | D55: =SUM('TRANSFERENCIA CORRIENTE'!I56:K56) -> 9007252.2 | E55: =SUM('TRANSFERENCIA CORRIENTE'!L56:N56) -> 0 | G55: =SUM(VS!C56:E56) -> 2005410 | H55: =SUM(VS!F56:H56) -> 0 | I55: =SUM(VS!I56:K56) -> 282700.01 | J55: =SUM(VS!L56:N56) -> 0 | L55: =SUM(B55+G55) -> 2008610 | M55: =SUM(C55+H55) -> 4165309.5 | N55: =SUM(D55+I55) -> 9289952.3 | O55: =SUM(E55+J55) -> 0
A56: 2.6.6 - EQUIPOS DE DEFENSA Y SEGURIDAD | B56: =SUM('TRANSFERENCIA CORRIENTE'!C57:E57) -> 0 | C56: =SUM('TRANSFERENCIA CORRIENTE'!F57:H57) -> 0 | D56: =SUM('TRANSFERENCIA CORRIENTE'!I57:K57) -> 66080 | E56: =SUM('TRANSFERENCIA CORRIENTE'!L57:N57) -> 0 | G56: =SUM(VS!C57:E57) -> 0 | H56: =SUM(VS!F57:H57) -> 0 | I56: =SUM(VS!I57:K57) -> 58764 | J56: =SUM(VS!L57:N57) -> 0 | L56: =SUM(B56+G56) -> 0 | M56: =SUM(C56+H56) -> 0 | N56: =SUM(D56+I56) -> 124844 | O56: =SUM(E56+J56) -> 0
A57: 2.6.7 - ACTIVOS BIÓLOGICOS CULTIVABLES | B57: =SUM('TRANSFERENCIA CORRIENTE'!C58:E58) -> 0 | C57: =SUM('TRANSFERENCIA CORRIENTE'!F58:H58) -> 0 | D57: =SUM('TRANSFERENCIA CORRIENTE'!I58:K58) -> 0 | E57: =SUM('TRANSFERENCIA CORRIENTE'!L58:N58) -> 0 | G57: =SUM(VS!C58:E58) -> 0 | H57: =SUM(VS!F58:H58) -> 0 | I57: =SUM(VS!I58:K58) -> 0 | J57: =SUM(VS!L58:N58) -> 0 | L57: =SUM(B57+G57) -> 0 | M57: =SUM(C57+H57) -> 0 | N57: =SUM(D57+I57) -> 0 | O57: =SUM(E57+J57) -> 0
A58: 2.6.8 - BIENES INTANGIBLES | B58: =SUM('TRANSFERENCIA CORRIENTE'!C59:E59) -> 0 | C58: =SUM('TRANSFERENCIA CORRIENTE'!F59:H59) -> 0 | D58: =SUM('TRANSFERENCIA CORRIENTE'!I59:K59) -> 0 | E58: =SUM('TRANSFERENCIA CORRIENTE'!L59:N59) -> 0 | G58: =SUM(VS!C59:E59) -> 0 | H58: =SUM(VS!F59:H59) -> 0 | I58: =SUM(VS!I59:K59) -> 0 | J58: =SUM(VS!L59:N59) -> 0 | L58: =SUM(B58+G58) -> 0 | M58: =SUM(C58+H58) -> 0 | N58: =SUM(D58+I58) -> 0 | O58: =SUM(E58+J58) -> 0
A59: 2.6.9 - EDIFICIOS, ESTRUCTURAS, TIERRAS, TERRENOS Y OBJETOS DE VALOR | B59: =SUM('TRANSFERENCIA CORRIENTE'!C60:E60) -> 0 | C59: =SUM('TRANSFERENCIA CORRIENTE'!F60:H60) -> 345560.94 | D59: =SUM('TRANSFERENCIA CORRIENTE'!I60:K60) -> 0 | E59: =SUM('TRANSFERENCIA CORRIENTE'!L60:N60) -> 0 | G59: =SUM(VS!C60:E60) -> 0 | H59: =SUM(VS!F60:H60) -> 0 | I59: =SUM(VS!I60:K60) -> 0 | J59: =SUM(VS!L60:N60) -> 0 | L59: =SUM(B59+G59) -> 0 | M59: =SUM(C59+H59) -> 345560.94 | N59: =SUM(D59+I59) -> 0 | O59: =SUM(E59+J59) -> 0
A60: 2.7 - OBRAS | B60: =SUM(B61:B64) -> 0 | C60: =SUM(C61:C64) -> 0 | D60: =SUM(D61:D64) -> 0 | E60: =SUM(E61:E64) -> 0 | G60: =SUM(G61:G64) -> 0 | H60: =SUM(H61:H64) -> 0 | I60: =SUM(I61:I64) -> 0 | J60: =SUM(J61:J64) -> 0 | L60: =SUM(B60+G60) -> 0 | M60: =SUM(C60+H60) -> 0 | N60: =SUM(D60+I60) -> 0 | O60: =SUM(E60+J60) -> 0
A61: 2.7.1 - OBRAS EN EDIFICACIONES | B61: =SUM('TRANSFERENCIA CORRIENTE'!C62:E62) -> 0 | C61: =SUM('TRANSFERENCIA CORRIENTE'!F62:H62) -> 0 | D61: =SUM('TRANSFERENCIA CORRIENTE'!I62:K62) -> 0 | E61: =SUM('TRANSFERENCIA CORRIENTE'!L62:N62) -> 0 | G61: =SUM(VS!C62:E62) -> 0 | H61: =SUM(VS!F62:H62) -> 0 | I61: =SUM(VS!I62:K62) -> 0 | J61: =SUM(VS!L62:N62) -> 0 | L61: =SUM(B61+G61) -> 0 | M61: =SUM(C61+H61) -> 0 | N61: =SUM(D61+I61) -> 0 | O61: =SUM(E61+J61) -> 0
A62: 2.7.2 - INFRAESTRUCTURA | B62: =SUM('TRANSFERENCIA CORRIENTE'!C63:E63) -> 0 | C62: =SUM('TRANSFERENCIA CORRIENTE'!F63:H63) -> 0 | D62: =SUM('TRANSFERENCIA CORRIENTE'!I63:K63) -> 0 | E62: =SUM('TRANSFERENCIA CORRIENTE'!L63:N63) -> 0 | G62: =SUM(VS!C63:E63) -> 0 | H62: =SUM(VS!F63:H63) -> 0 | I62: =SUM(VS!I63:K63) -> 0 | J62: =SUM(VS!L63:N63) -> 0 | L62: =SUM(B62+G62) -> 0 | M62: =SUM(C62+H62) -> 0 | N62: =SUM(D62+I62) -> 0 | O62: =SUM(E62+J62) -> 0
A63: 2.7.3 - CONSTRUCCIONES EN BIENES CONCESIONADOS | B63: =SUM('TRANSFERENCIA CORRIENTE'!C64:E64) -> 0 | C63: =SUM('TRANSFERENCIA CORRIENTE'!F64:H64) -> 0 | D63: =SUM('TRANSFERENCIA CORRIENTE'!I64:K64) -> 0 | E63: =SUM('TRANSFERENCIA CORRIENTE'!L64:N64) -> 0 | G63: =SUM(VS!C64:E64) -> 0 | H63: =SUM(VS!F64:H64) -> 0 | I63: =SUM(VS!I64:K64) -> 0 | J63: =SUM(VS!L64:N64) -> 0 | L63: =SUM(B63+G63) -> 0 | M63: =SUM(C63+H63) -> 0 | N63: =SUM(D63+I63) -> 0 | O63: =SUM(E63+J63) -> 0
A64: 2.7.4 - GASTOS QUE SE ASIGNARÁN DURANTE EL EJERCICIO PARA INVERSIÓN (ART. 32 Y 33 LEY 423-06) | B64: =SUM('TRANSFERENCIA CORRIENTE'!C65:E65) -> 0 | C64: =SUM('TRANSFERENCIA CORRIENTE'!F65:H65) -> 0 | D64: =SUM('TRANSFERENCIA CORRIENTE'!I65:K65) -> 0 | E64: =SUM('TRANSFERENCIA CORRIENTE'!L65:N65) -> 0 | G64: =SUM(VS!C65:E65) -> 0 | H64: =SUM(VS!F65:H65) -> 0 | I64: =SUM(VS!I65:K65) -> 0 | J64: =SUM(VS!L65:N65) -> 0 | L64: =SUM(B64+G64) -> 0 | M64: =SUM(C64+H64) -> 0 | N64: =SUM(D64+I64) -> 0 | O64: =SUM(E64+J64) -> 0
A65: 2.8 - ADQUISICION DE ACTIVOS FINANCIEROS CON FINES DE POLÍTICA | B65: =SUM(B66:B67) -> 0 | C65: =SUM(C66:C67) -> 0 | D65: =SUM(D66:D67) -> 0 | E65: =SUM(E66:E67) -> 0 | G65: =SUM(G66:G67) -> 0 | H65: =SUM(H66:H67) -> 0 | I65: =SUM(I66:I67) -> 0 | J65: =SUM(J66:J67) -> 0 | L65: =SUM(B65+G65) -> 0 | M65: =SUM(C65+H65) -> 0 | N65: =SUM(D65+I65) -> 0 | O65: =SUM(E65+J65) -> 0
A66: 2.8.1 - CONCESIÓN DE PRESTAMOS | B66: =SUM('TRANSFERENCIA CORRIENTE'!C67:E67) -> 0 | C66: =SUM('TRANSFERENCIA CORRIENTE'!F67:H67) -> 0 | D66: =SUM('TRANSFERENCIA CORRIENTE'!I67:K67) -> 0 | E66: =SUM('TRANSFERENCIA CORRIENTE'!L67:N67) -> 0 | G66: =SUM(VS!C67:E67) -> 0 | H66: =SUM(VS!F67:H67) -> 0 | I66: =SUM(VS!I67:K67) -> 0 | J66: =SUM(VS!L67:N67) -> 0 | L66: =SUM(B66+G66) -> 0 | M66: =SUM(C66+H66) -> 0 | N66: =SUM(D66+I66) -> 0 | O66: =SUM(E66+J66) -> 0
A67: 2.8.2 - ADQUISICIÓN DE TÍTULOS VALORES REPRESENTATIVOS DE DEUDA | B67: =SUM('TRANSFERENCIA CORRIENTE'!C68:E68) -> 0 | C67: =SUM('TRANSFERENCIA CORRIENTE'!F68:H68) -> 0 | D67: =SUM('TRANSFERENCIA CORRIENTE'!I68:K68) -> 0 | E67: =SUM('TRANSFERENCIA CORRIENTE'!L68:N68) -> 0 | G67: =SUM(VS!C68:E68) -> 0 | H67: =SUM(VS!F68:H68) -> 0 | I67: =SUM(VS!I68:K68) -> 0 | J67: =SUM(VS!L68:N68) -> 0 | L67: =SUM(B67+G67) -> 0 | M67: =SUM(C67+H67) -> 0 | N67: =SUM(D67+I67) -> 0 | O67: =SUM(E67+J67) -> 0
A68: 2.9 - GASTOS FINANCIEROS | B68: =SUM(B69:B71) -> 0 | C68: =SUM(C69:C71) -> 0 | D68: =SUM(D69:D71) -> 0 | E68: =SUM(E69:E71) -> 0 | G68: =SUM(G69:G71) -> 0 | H68: =SUM(H69:H71) -> 0 | I68: =SUM(I69:I71) -> 0 | J68: =SUM(J69:J71) -> 0 | L68: =SUM(B68+G68) -> 0 | M68: =SUM(C68+H68) -> 0 | N68: =SUM(D68+I68) -> 0 | O68: =SUM(E68+J68) -> 0
A69: 2.9.1 - INTERESES DE LA DEUDA PÚBLICA INTERNA | B69: =SUM('TRANSFERENCIA CORRIENTE'!C70:E70) -> 0 | C69: =SUM('TRANSFERENCIA CORRIENTE'!F70:H70) -> 0 | D69: =SUM('TRANSFERENCIA CORRIENTE'!I70:K70) -> 0 | E69: =SUM('TRANSFERENCIA CORRIENTE'!L70:N70) -> 0 | G69: =SUM(VS!C70:E70) -> 0 | H69: =SUM(VS!F70:H70) -> 0 | I69: =SUM(VS!I70:K70) -> 0 | J69: =SUM(VS!L70:N70) -> 0 | L69: =SUM(B69+G69) -> 0 | M69: =SUM(C69+H69) -> 0 | N69: =SUM(D69+I69) -> 0 | O69: =SUM(E69+J69) -> 0
A70: 2.9.2 - INTERESES DE LA DEUDA PUBLICA EXTERNA | B70: =SUM('TRANSFERENCIA CORRIENTE'!C71:E71) -> 0 | C70: =SUM('TRANSFERENCIA CORRIENTE'!F71:H71) -> 0 | D70: =SUM('TRANSFERENCIA CORRIENTE'!I71:K71) -> 0 | E70: =SUM('TRANSFERENCIA CORRIENTE'!L71:N71) -> 0 | G70: =SUM(VS!C71:E71) -> 0 | H70: =SUM(VS!F71:H71) -> 0 | I70: =SUM(VS!I71:K71) -> 0 | J70: =SUM(VS!L71:N71) -> 0 | L70: =SUM(B70+G70) -> 0 | M70: =SUM(C70+H70) -> 0 | N70: =SUM(D70+I70) -> 0 | O70: =SUM(E70+J70) -> 0
A71: 2.9.4 - COMISIONES Y OTROS GASTOS BANCARIOS DE LA DEUDA PÚBLICA | B71: =SUM('TRANSFERENCIA CORRIENTE'!C72:E72) -> 0 | C71: =SUM('TRANSFERENCIA CORRIENTE'!F72:H72) -> 0 | D71: =SUM('TRANSFERENCIA CORRIENTE'!I72:K72) -> 0 | E71: =SUM('TRANSFERENCIA CORRIENTE'!L72:N72) -> 0 | H71: =SUM(VS!F72:H72) -> 0 | I71: =SUM(VS!I72:K72) -> 0 | J71: =SUM(VS!L72:N72) -> 0 | L71: =SUM(B71+G71) -> 0 | M71: =SUM(C71+H71) -> 0 | N71: =SUM(D71+I71) -> 0 | O71: =SUM(E71+J71) -> 0
A72: Total Gastos | B72: =+B8+B14+B24+B34+B42+B50+B60+B65+B68 -> 2.7188025e+08 | C72: =+C8+C14+C24+C34+C42+C50+C60+C65+C68 -> 2.7723165e+08 | D72: =+D8+D14+D24+D34+D42+D50+D60+D65+D68 -> 3.5516728e+08 | E72: =+E8+E14+E24+E34+E42+E50+E60+E65+E68 -> 0 | G72: =+G8+G14+G24+G34+G42+G50+G60+G65+G68 -> 26194616 | H72: =+H8+H14+H24+H34+H42+H50+H60+H65+H68 -> 20399507 | I72: =+I8+I14+I24+I34+I42+I50+I60+I65+I68 -> 29377124 | J72: =+J8+J14+J24+J34+J42+J50+J60+J65+J68 -> 0 | L72: =SUM(B72+G72) -> 2.9807487e+08 | M72: =SUM(C72+H72) -> 2.9763115e+08 | N72: =SUM(D72+I72) -> 3.845444e+08 | O72: =SUM(E72+J72) -> 0
A73: 4 - APLICACIONES FINANCIERAS | B73: =SUM('TRANSFERENCIA CORRIENTE'!C74:E74) -> 0 | C73: =SUM('TRANSFERENCIA CORRIENTE'!F74:H74) -> 0 | D73: =SUM('TRANSFERENCIA CORRIENTE'!I74:K74) -> 0 | E73: =SUM('TRANSFERENCIA CORRIENTE'!L74:N74) -> 0 | G73: =SUM(VS!C74:E74) -> 0 | H73: =SUM(VS!F74:H74) -> 0 | I73: =SUM(VS!I74:K74) -> 0 | J73: =SUM(VS!L74:N74) -> 0 | L73: =SUM(B73+G73) -> 0 | M73: =SUM(C73+H73) -> 0 | N73: =SUM(D73+I73) -> 0 | O73: =SUM(E73+J73) -> 0
A74: 4.1 - INCREMENTO DE ACTIVOS FINANCIEROS | B74: =SUM('TRANSFERENCIA CORRIENTE'!C75:E75) -> 0 | C74: =SUM('TRANSFERENCIA CORRIENTE'!F75:H75) -> 0 | D74: =SUM('TRANSFERENCIA CORRIENTE'!I75:K75) -> 0 | E74: =SUM('TRANSFERENCIA CORRIENTE'!L75:N75) -> 0 | G74: =SUM(VS!C75:E75) -> 0 | H74: =SUM(VS!F75:H75) -> 0 | I74: =SUM(VS!I75:K75) -> 0 | J74: =SUM(VS!L75:N75) -> 0 | L74: =SUM(B74+G74) -> 0 | M74: =SUM(C74+H74) -> 0 | N74: =SUM(D74+I74) -> 0 | O74: =SUM(E74+J74) -> 0
A75: 4.1.1 - INCREMENTO DE ACTIVOS FINANCIEROS CORRIENTES | B75: =SUM('TRANSFERENCIA CORRIENTE'!C76:E76) -> 0 | C75: =SUM('TRANSFERENCIA CORRIENTE'!F76:H76) -> 0 | D75: =SUM('TRANSFERENCIA CORRIENTE'!I76:K76) -> 0 | E75: =SUM('TRANSFERENCIA CORRIENTE'!L76:N76) -> 0 | G75: =SUM(VS!C76:E76) -> 0 | H75: =SUM(VS!F76:H76) -> 0 | I75: =SUM(VS!I76:K76) -> 0 | J75: =SUM(VS!L76:N76) -> 0 | L75: =SUM(B75+G75) -> 0 | M75: =SUM(C75+H75) -> 0 | N75: =SUM(D75+I75) -> 0 | O75: =SUM(E75+J75) -> 0
A76: 4.1.2 - INCREMENTO DE ACTIVOS FINANCIEROS NO CORRIENTES | B76: =SUM('TRANSFERENCIA CORRIENTE'!C77:E77) -> 0 | C76: =SUM('TRANSFERENCIA CORRIENTE'!F77:H77) -> 0 | D76: =SUM('TRANSFERENCIA CORRIENTE'!I77:K77) -> 0 | E76: =SUM('TRANSFERENCIA CORRIENTE'!L77:N77) -> 0 | G76: =SUM(VS!C77:E77) -> 0 | H76: =SUM(VS!F77:H77) -> 0 | I76: =SUM(VS!I77:K77) -> 0 | J76: =SUM(VS!L77:N77) -> 0 | L76: =SUM(B76+G76) -> 0 | M76: =SUM(C76+H76) -> 0 | N76: =SUM(D76+I76) -> 0 | O76: =SUM(E76+J76) -> 0
A77: 4.2 - DISMINUCIÓN DE PASIVOS | B77: =SUM('TRANSFERENCIA CORRIENTE'!C78:E78) -> 0 | C77: =SUM('TRANSFERENCIA CORRIENTE'!F78:H78) -> 0 | D77: =SUM('TRANSFERENCIA CORRIENTE'!I78:K78) -> 0 | E77: =SUM('TRANSFERENCIA CORRIENTE'!L78:N78) -> 0 | G77: =SUM(VS!C78:E78) -> 0 | H77: =SUM(VS!F78:H78) -> 0 | I77: =SUM(VS!I78:K78) -> 0 | J77: =SUM(VS!L78:N78) -> 0 | L77: =SUM(B77+G77) -> 0 | M77: =SUM(C77+H77) -> 0 | N77: =SUM(D77+I77) -> 0 | O77: =SUM(E77+J77) -> 0
A78: 4.2.1 - DISMINUCIÓN DE PASIVOS CORRIENTES | B78: =SUM('TRANSFERENCIA CORRIENTE'!C79:E79) -> 0 | C78: =SUM('TRANSFERENCIA CORRIENTE'!F79:H79) -> 0 | D78: =SUM('TRANSFERENCIA CORRIENTE'!I79:K79) -> 0 | E78: =SUM('TRANSFERENCIA CORRIENTE'!L79:N79) -> 0 | G78: =SUM(VS!C79:E79) -> 0 | H78: =SUM(VS!F79:H79) -> 0 | I78: =SUM(VS!I79:K79) -> 0 | J78: =SUM(VS!L79:N79) -> 0 | L78: =SUM(B78+G78) -> 0 | M78: =SUM(C78+H78) -> 0 | N78: =SUM(D78+I78) -> 0 | O78: =SUM(E78+J78) -> 0
A79: 4.2.2 - DISMINUCIÓN DE PASIVOS NO CORRIENTES | B79: =SUM('TRANSFERENCIA CORRIENTE'!C80:E80) -> 0 | C79: =SUM('TRANSFERENCIA CORRIENTE'!F80:H80) -> 0 | D79: =SUM('TRANSFERENCIA CORRIENTE'!I80:K80) -> 0 | E79: =SUM('TRANSFERENCIA CORRIENTE'!L80:N80) -> 0 | G79: =SUM(VS!C80:E80) -> 0 | H79: =SUM(VS!F80:H80) -> 0 | I79: =SUM(VS!I80:K80) -> 0 | J79: =SUM(VS!L80:N80) -> 0 | L79: =SUM(B79+G79) -> 0 | M79: =SUM(C79+H79) -> 0 | N79: =SUM(D79+I79) -> 0 | O79: =SUM(E79+J79) -> 0
A80: 4.3 - DISMINUCIÓN DE FONDOS DE TERCEROS | B80: =SUM('TRANSFERENCIA CORRIENTE'!C81:E81) -> 0 | C80: =SUM('TRANSFERENCIA CORRIENTE'!F81:H81) -> 0 | D80: =SUM('TRANSFERENCIA CORRIENTE'!I81:K81) -> 0 | E80: =SUM('TRANSFERENCIA CORRIENTE'!L81:N81) -> 0 | G80: =SUM(VS!C81:E81) -> 0 | H80: =SUM(VS!F81:H81) -> 0 | I80: =SUM(VS!I81:K81) -> 0 | J80: =SUM(VS!L81:N81) -> 0 | L80: =SUM(B80+G80) -> 0 | M80: =SUM(C80+H80) -> 0 | N80: =SUM(D80+I80) -> 0 | O80: =SUM(E80+J80) -> 0
A81: 4.3.5 - DISMINUCIÓN DEPÓSITOS FONDOS DE TERCEROS | B81: =SUM('TRANSFERENCIA CORRIENTE'!C82:E82) -> 0 | C81: =SUM('TRANSFERENCIA CORRIENTE'!F82:H82) -> 0 | D81: =SUM('TRANSFERENCIA CORRIENTE'!I82:K82) -> 0 | E81: =SUM('TRANSFERENCIA CORRIENTE'!L82:N82) -> 0 | G81: =SUM(VS!C82:E82) -> 0 | H81: =SUM(VS!F82:H82) -> 0 | I81: =SUM(VS!I82:K82) -> 0 | J81: =SUM(VS!L82:N82) -> 0 | L81: =SUM(B81+G81) -> 0 | M81: =SUM(C81+H81) -> 0 | N81: =SUM(D81+I81) -> 0 | O81: =SUM(E81+J81) -> 0
A82: TOTAL APLICACIONES FINANCIERAS | B82: =SUM(B83) -> 2.7188025e+08 | C82: =SUM(C83) -> 2.7723165e+08 | D82: =SUM(D83) -> 3.1003641e+08 | E82: =SUM(E83) -> 2.9961634e+08 | G82: =SUM(G83) -> 26194616 | H82: =SUM(H83) -> 20399507 | I82: =SUM(I83) -> 29377124 | J82: =SUM(J83) -> 0 | L82: =SUM(B82+G82) -> 2.9807487e+08 | M82: =SUM(C82+H82) -> 2.9763115e+08 | N82: =SUM(D82+I82) -> 3.3941353e+08 | O82: =SUM(E82+J82) -> 2.9961634e+08
A83: TOTAL GASTOS Y APLICACIONES FINANCIERAS | B83: =SUM('TRANSFERENCIA CORRIENTE'!C85:E85) -> 2.7188025e+08 | C83: =SUM('TRANSFERENCIA CORRIENTE'!F85:H85) -> 2.7723165e+08 | D83: =SUM('TRANSFERENCIA CORRIENTE'!I85:K85) -> 3.1003641e+08 | E83: =SUM('TRANSFERENCIA CORRIENTE'!L85:N85) -> 2.9961634e+08 | G83: =SUM(VS!C85:E85) -> 26194616 | H83: =SUM(VS!F85:H85) -> 20399507 | I83: =SUM(VS!I85:K85) -> 29377124 | J83: =SUM(VS!L85:N85) -> 0 | L83: =SUM(B83+G83) -> 2.9807487e+08 | M83: =SUM(C83+H83) -> 2.9763115e+08 | N83: =SUM(D83+I83) -> 3.3941353e+08 | O83: =SUM(E83+J83) -> 2.9961634e+08

Sheet Sheet2

Sheet TRANSFERENCIA CORRIENTE
A1: SERVICIO NACIONAL DE SALUD
A2: HOSPITAL MATERNO INFANTIL SAN LORENZO DE LOS MINA
A3: REGION
A4: Ejecución de Gastos Fondo (100) 2025
A5: En RD$
A7: Detalle | B7: Total | C7: Enero | D7: Febrero | E7: Marzo | F7: Abril | G7: Mayo | H7: Junio | I7: Julio | J7: Agosto | K7: Septiembre | L7: Octubre | M7: Noviembre | N7: Diciembre
A8: 2 - GASTOS
A9: 2.1 - REMUNERACIONES Y CONTRIBUCIONES | B9: 5.4149799e+08 | C9: 65091180 | D9: 67131936 | E9: 66337620 | F9: 66556156 | G9: 66630551 | H9: 66583615 | I9: 71335676 | J9: 71831261 | K9: =SUM(K10:K14) -> 71591504 | L9: 0 | M9: 0 | N9: 0
A10: 2.1.1 - REMUNERACIONES | B10: 4.4636576e+08 | C10: 53640339 | D10: 55586129 | E10: 54718737 | F10: 54771097 | G10: 54445140 | H10: 54868543 | I10: 58925421 | J10: 59410356 | K10: 59165425
A11: 2.1.2 - SOBRESUELDOS | B11: 26843184 | C11: 3196999.6 | D11: 3197999.6 | E11: 3199399.6 | F11: 3384964.5 | G11: 3807608.3 | H11: 3343226.2 | I11: 3344880.2 | J11: 3368105.6 | K11: 3321905.6
A12: 2.1.3 - DIETAS Y GASTOS DE REPRESENTACIÓN | B12: 0
A13: 2.1.4 - GRATIFICACIONES Y BONIFICACIONES | B13: 0
A14: 2.1.5 - CONTRIBUCIONES A LA SEGURIDAD SOCIAL | B14: 68289048 | C14: 8253841.6 | D14: 8347807.5 | E14: 8419483.2 | F14: 8400093.9 | G14: 8377802.1 | H14: 8371846.2 | I14: 9065374.6 | J14: 9052799.4 | K14: 9104173.4
A15: 2.2 - CONTRATACIÓN DE SERVICIOS | B15: 26078082 | C15: 0 | D15: 1336968.6 | E15: 7971396.2 | F15: 210535 | G15: 1680824.8 | H15: 8240458.4 | I15: 3509565.8 | J15: 3128332.8 | K15: =SUM(K16:K24) -> 7782458.8 | L15: 0 | M15: 0 | N15: 0
A16: 2.2.1 - SERVICIOS BÁSICOS | B16: 2322699.3 | E16: 2020024.3 | F16: 60535 | G16: 60535 | H16: 60535 | I16: 60535 | J16: 60535 | K16: 60535
A17: 2.2.2 - PUBLICIDAD, IMPRESIÓN Y ENCUADERNACIÓN | B17: 764995.66 | D17: 324206.83 | G17: 32889.84 | H17: 319103.99 | J17: 88795 | K17: 47633.3
A18: 2.2.3 - VIÁTICOS | B18: 0
A19: 2.2.4 - TRANSPORTE Y ALMACENAJE | B19: 0
A20: 2.2.5 - ALQUILERES Y RENTAS | B20: 300000 | F20: 150000 | J20: 150000
A21: 2.2.6 - SEGUROS | B21: 0
A22: 2.2.7 - SERVICIOS DE CONSERVACIÓN, REPARACIONES MENORES E INSTALACIONES TEMPORALES | B22: 18363942 | D22: 523061.81 | E22: 5951371.9 | G22: 1174400 | H22: 4437074.3 | I22: 3449030.8 | J22: 2829002.8 | K22: 1580779.5
A23: 2.2.8 - OTROS SERVICIOS NO INCLUIDOS EN CONCEPTOS ANTERIORES | B23: 902700 | D23: 489700 | G23: 413000 | K23: 3779000
A24: 2.2.9 - OTRAS CONTRATACIONES DE SERVICIOS | B24: 3423745 | H24: 3423745 | K24: 2314511
A25: 2.3 - MATERIALES Y SUMINISTROS | B25: 1.3900689e+08 | C25: 4970600.4 | D25: 14433131 | E25: 26749552 | F25: 20368607 | G25: 16608513 | H25: 15408530 | I25: 26146220 | J25: 14321740 | K25: =SUM(K26:K34) -> 25141648 | L25: 0 | M25: 0 | N25: 0
A26: 2.3.1 - ALIMENTOS Y PRODUCTOS AGROFORESTALES | D26: 591460.4 | E26: 3122436.8 | F26: 812515 | G26: 1657538 | H26: 2396946.2 | I26: 1787251.8 | J26: 2077230.7 | K26: 2180362.6
A27: 2.3.2 - TEXTILES Y VESTUARIOS | D27: 61630.73 | F27: 1562980.5 | H27: 812418.96 | I27: 1577150.7 | J27: 180540 | K27: 1258116.1
A28: 2.3.3 - PRODUCTOS DE PAPEL, CARTÓN E IMPRESOS | D28: 352366.67 | E28: 1474545.2 | F28: 1510942.2 | G28: 765138.96 | H28: 715614.54 | I28: 1579886.7 | J28: 912967.7 | K28: 366980
A29: 2.3.4 - PRODUCTOS FARMACÉUTICOS | C29: 1862880 | D29: 2014526.8 | E29: 6919929 | F29: 6349109 | G29: 2637285.6 | H29: 3022962 | I29: 6806505 | J29: 2962573 | K29: 9434300
A30: 2.3.5 - PRODUCTOS DE CUERO, CAUCHO Y PLÁSTICO | E30: 334708.95 | F30: 506546.35 | G30: 384413.08 | H30: 133281 | I30: 655140.22 | J30: 18313.6
A31: 2.3.6 - PRODUCTOS DE MINERALES, METÁLICOS Y NO METÁLICOS | D31: 11630.98 | F31: 351015.88 | G31: 215177.81 | H31: 101426.9 | J31: 286504
A32: 2.3.7 - COMBUSTIBLES, LUBRICANTES, PRODUCTOS QUÍMICOS Y CONEXOS | C32: 1844663.4 | D32: 3902915.5 | E32: 3162523 | F32: 2759191.9 | G32: 4409677.5 | H32: 2900109.8 | I32: 4028536.8 | J32: 2398944 | K32: 5003060.2
A33: 2.3.8 - GASTOS QUE SE ASIGNARÁN DURANTE EL EJERCICIO (ART. 32 Y 33 LEY 423-06)
A34: 2.3.9 - PRODUCTOS Y ÚTILES VARIOS | C34: 1263057 | D34: 7498600.4 | E34: 11735409 | F34: 6516306.6 | G34: 6539281.9 | H34: 5325771 | I34: 9711748.4 | J34: 5484666.6 | K34: 6898829.2
A35: 2.4 - TRANSFERENCIAS CORRIENTES | B35: 0 | C35: 0 | D35: 0 | E35: 0 | F35: 0 | G35: 0 | H35: 0 | I35: 0 | J35: 0 | K35: =SUM(K36:K42) -> 0 | L35: 0 | M35: 0 | N35: 0
A36: 2.4.1 - TRANSFERENCIAS CORRIENTES AL SECTOR PRIVADO | B36: 0
A37: 2.4.2 - TRANSFERENCIAS CORRIENTES AL GOBIERNO GENERAL NACIONAL | B37: 0
A38: 2.4.3 - TRANSFERENCIAS CORRIENTES A GOBIERNOS GENERALES LOCALES | B38: 0
A39: 2.4.4 - TRANSFERENCIAS CORRIENTES A EMPRESAS PÚBLICAS NO FINANCIERAS | B39: 0
A40: 2.4.5 - TRANSFERENCIAS CORRIENTES A INSTITUCIONES PÚBLICAS FINANCIERAS | B40: 0
A41: 2.4.7 - TRANSFERENCIAS CORRIENTES AL SECTOR EXTERNO | B41: 0
A42: 2.4.9 - TRANSFERENCIAS CORRIENTES A OTRAS INSTITUCIONES PÚBLICAS | B42: 0
A43: 2.5 - TRANSFERENCIAS DE CAPITAL | B43: 0 | C43: 0 | D43: 0 | E43: 0 | F43: 0 | G43: 0 | H43: 0 | I43: 0 | J43: 0 | K43: =SUM(K44:K50) -> 0 | L43: 0 | M43: 0 | N43: 0
A44: 2.5.1 - TRANSFERENCIAS DE CAPITAL AL SECTOR PRIVADO | B44: 0
A45: 2.5.2 - TRANSFERENCIAS DE CAPITAL AL GOBIERNO GENERAL NACIONAL | B45: 0
A46: 2.5.3 - TRANSFERENCIAS DE CAPITAL A GOBIERNOS GENERALES LOCALES | B46: 0
A47: 2.5.4 - TRANSFERENCIAS DE CAPITAL A EMPRESAS PÚBLICAS NO FINANCIERAS | B47: 0
A48: 2.5.5 - TRANSFERENCIAS DE CAPITAL A INSTITUCIONES PÚBLICAS FINANCIERAS | B48: 0
A49: 2.5.6 - TRANSFERENCIAS DE CAPITAL AL SECTOR EXTERNO | B49: 0
A50: 2.5.9 - TRANSFERENCIAS DE CAPITAL A OTRAS INSTITUCIONES PÚBLICAS | B50: 0
A51: 2.6 - BIENES MUEBLES, INMUEBLES E INTANGIBLES | B51: 52693223 | C51: 0 | D51: 6461017.3 | E51: 11396849 | F51: 4665041.4 | G51: 6580673.1 | H51: 3698140.3 | I51: 9300722.7 | J51: 10590779 | K51: =SUM(K52:K60) -> 5819603.3 | L51: 0 | M51: 0 | N51: 0
A52: 2.6.1 - MOBILIARIO Y EQUIPO | B52: 9670028.3 | D52: 432420.86 | E52: 678205 | F52: 1812434.5 | G52: 231484.25 | H52: 1542516.3 | I52: 2268904.4 | J52: 2704062.9 | K52: 1146270
A53: 2.6.2 - MOBILIARIO Y EQUIPO EDUCACIONAL Y RECREATIVO | B53: 182926.74 | G53: 182926.74
A54: 2.6.3 - EQUIPO E INSTRUMENTAL, CIENTÍFICO Y LABORATORIO | B54: 29728570 | D54: 6028596.4 | E54: 10715444 | F54: 2635786.9 | G54: 2285211.7 | H54: 1742624 | I54: 5025506.7 | J54: 1295400.2 | K54: 4197628.2
A55: 2.6.4 - VEHÍCULOS Y EQUIPO DE TRANSPORTE, TRACCIÓN Y ELEVACIÓN | B55: 0
A56: 2.6.5 - MAQUINARIA, OTROS EQUIPOS Y HERRAMIENTAS | B56: 12766137 | E56: 3199.97 | F56: 216820 | G56: 3535489.5 | H56: 413000 | I56: 2006311.6 | J56: 6591315.4 | K56: 409625.2
A57: 2.6.6 - EQUIPOS DE DEFENSA Y SEGURIDAD | B57: 0 | K57: 66080
A58: 2.6.7 - ACTIVOS BIÓLOGICOS CULTIVABLES | B58: 0
A59: 2.6.8 - BIENES INTANGIBLES | B59: 0
A60: 2.6.9 - EDIFICIOS, ESTRUCTURAS, TIERRAS, TERRENOS Y OBJETOS DE VALOR | B60: 345560.94 | G60: 345560.94
A61: 2.7 - OBRAS | B61: 0 | C61: 0 | D61: 0 | E61: 0 | F61: 0 | G61: 0 | H61: 0 | I61: 0 | J61: 0 | K61: 0 | L61: 0 | M61: 0 | N61: 0
A62: 2.7.1 - OBRAS EN EDIFICACIONES | B62: 0
A63: 2.7.2 - INFRAESTRUCTURA | B63: 0
A64: 2.7.3 - CONSTRUCCIONES EN BIENES CONCESIONADOS | B64: 0
A65: 2.7.4 - GASTOS QUE SE ASIGNARÁN DURANTE EL EJERCICIO PARA INVERSIÓN (ART. 32 Y 33 LEY 423-06) | B65: 0
A66: 2.8 - ADQUISICION DE ACTIVOS FINANCIEROS CON FINES DE POLÍTICA | B66: 0 | C66: 0 | D66: 0 | E66: 0 | F66: 0 | G66: 0 | H66: 0 | I66: 0 | J66: 0 | K66: 0 | L66: 0 | M66: 0 | N66: 0
A67: 2.8.1 - CONCESIÓN DE PRESTAMOS | B67: 0
A68: 2.8.2 - ADQUISICIÓN DE TÍTULOS VALORES REPRESENTATIVOS DE DEUDA | B68: 0
A69: 2.9 - GASTOS FINANCIEROS | B69: 0 | C69: 0 | D69: 0 | E69: 0 | F69: 0 | G69: 0 | H69: 0 | I69: 0 | J69: 0 | K69: 0 | L69: 0 | M69: 0 | N69: 0
A70: 2.9.1 - INTERESES DE LA DEUDA PÚBLICA INTERNA | B70: 0
A71: 2.9.2 - INTERESES DE LA DEUDA PUBLICA EXTERNA | B71: 0
A72: 2.9.4 - COMISIONES Y OTROS GASTOS BANCARIOS DE LA DEUDA PÚBLICA | B72: 0
A73: Total Gastos | B73: 7.5927619e+08 | C73: 70061780 | D73: 89363053 | E73: 1.1245542e+08 | F73: 91800340 | G73: 91500562 | H73: 93930744 | I73: 1.1029218e+08 | J73: =+J69+J66+J61+J51+J43+J35+J25+J15+J9 -> 99872112 | K73: =+K69+K66+K61+K51+K43+K35+K25+K15+K9 -> 1.1033521e+08 | N73: 0
A74: 4 - APLICACIONES FINANCIERAS
A75: 4.1 - INCREMENTO DE ACTIVOS FINANCIEROS
A76: 4.1.1 - INCREMENTO DE ACTIVOS FINANCIEROS CORRIENTES
A77: 4.1.2 - INCREMENTO DE ACTIVOS FINANCIEROS NO CORRIENTES
A78: 4.2 - DISMINUCIÓN DE PASIVOS
A79: 4.2.1 - DISMINUCIÓN DE PASIVOS CORRIENTES
A80: 4.2.2 - DISMINUCIÓN DE PASIVOS NO CORRIENTES
A81: 4.3 - DISMINUCIÓN DE FONDOS DE TERCEROS
A82: 4.3.5 - DISMINUCIÓN DEPÓSITOS FONDOS DE TERCEROS
A83: TOTAL APLICACIONES FINANCIERAS
A85: TOTAL GASTOS Y APLICACIONES FINANCIERAS | B85: 7.5927619e+08 | C85: 70061780 | D85: 89363053 | E85: 1.1245542e+08 | F85: 91800340 | G85: 91500562 | H85: 93930744 | I85: 1.1029218e+08 | J85: 99872112 | K85: 99872112 | L85: 99872112 | M85: 99872112 | N85: 99872112
A86: Fuente: [fuente]
A87: Fecha de registro: hasta el [01] de [01] del [2025]
A88: Fecha de imputación: hasta el [30] de [09] del [2025]

Sheet VS
A1: SERVICIO NACIONAL DE SALUD
A2: HOSPITAL MATERNO INFANTIL SAN LORENZO DE LOS MINA
A3: REGION
A4: Ejecución de Gastos VENTA SERVICIOS 2025
A5: En RD$
A7: Detalle | B7: Total | C7: Enero | D7: Febrero | E7: Marzo | F7: Abril | G7: Mayo | H7: Junio | I7: Julio | J7: Agosto | K7: Septiembre | L7: Octubre | M7: Noviembre | N7: Diciembre
A8: 2 - GASTOS
A9: 2.1 - REMUNERACIONES Y CONTRIBUCIONES | B9: =SUM(C9:N9) -> 9644681.1 | C9: 0 | D9: 0 | E9: 5231553.6 | F9: 0 | G9: 0 | H9: 0 | I9: 0 | J9: 0 | K9: =SUM(K10:K14) -> 4413127.6 | L9: 0 | M9: 0 | N9: 0
A10: 2.1.1 - REMUNERACIONES | B10: =SUM(C10:N10) -> 0
A11: 2.1.2 - SOBRESUELDOS | B11: =SUM(C11:N11) -> 9644681.1 | E11: 5231553.6 | K11: 4413127.6
A12: 2.1.3 - DIETAS Y GASTOS DE REPRESENTACIÓN | B12: =SUM(C12:N12) -> 0
A13: 2.1.4 - GRATIFICACIONES Y BONIFICACIONES | B13: =SUM(C13:N13) -> 0
A14: 2.1.5 - CONTRIBUCIONES A LA SEGURIDAD SOCIAL | B14: =SUM(C14:N14) -> 0
A15: 2.2 - CONTRATACIÓN DE SERVICIOS | B15: =SUM(C15:N15) -> 25924513 | C15: 2733844.3 | D15: 1213383.4 | E15: 4359456.2 | F15: 1256712.1 | G15: 2044062.6 | H15: 3938639.1 | I15: 5012155.8 | J15: 3808523.8 | K15: =SUM(K16:K24) -> 1557736.2 | L15: 0 | M15: 0 | N15: 0
A16: 2.2.1 - SERVICIOS BÁSICOS | B16: =SUM(C16:N16) -> 7567080.2 | C16: 351316.33 | D16: 259054.4 | E16: 1731191.2 | F16: 285608.3 | G16: 1098463.4 | H16: 964509 | I16: 1781904.1 | J16: 933611.83 | K16: 161421.68
A17: 2.2.2 - PUBLICIDAD, IMPRESIÓN Y ENCUADERNACIÓN | B17: =SUM(C17:N17) -> 1497864.6 | H17: 310139.4 | I17: 581445 | J17: 336559.6 | K17: 269720.57
A18: 2.2.3 - VIÁTICOS | B18: =SUM(C18:N18) -> 0
A19: 2.2.4 - TRANSPORTE Y ALMACENAJE | B19: =SUM(C19:N19) -> 228000 | D19: 24000 | E19: 32000 | G19: 76000 | H19: 20000 | I19: 8000 | K19: 68000
A20: 2.2.5 - ALQUILERES Y RENTAS | B20: =SUM(C20:N20) -> 2205821.2 | C20: 266664.25 | D20: 252960.9 | F20: 229519.78 | G20: 529650.64 | I20: 298861.54 | J20: 628164.1
A21: 2.2.6 - SEGUROS | B21: =SUM(C21:N21) -> 0
A22: 2.2.7 - SERVICIOS DE CONSERVACIÓN, REPARACIONES MENORES E INSTALACIONES TEMPORALES | B22: =SUM(C22:N22) -> 8957936.4 | C22: 2064518.4 | D22: 472756.61 | E22: 2019575.2 | F22: 199877.53 | G22: 205899.14 | H22: 635040.9 | I22: 1632573.3 | J22: 925675.21 | K22: 802020.26
A23: 2.2.8 - OTROS SERVICIOS NO INCLUIDOS EN CONCEPTOS ANTERIORES | B23: =SUM(C23:N23) -> 4007794 | C23: 51345.35 | D23: 204611.44 | E23: 576689.87 | F23: 541706.48 | G23: 134049.4 | H23: 1098662.4 | I23: 709371.88 | J23: 524832.27 | K23: 166524.93
A24: 2.2.9 - OTRAS CONTRATACIONES DE SERVICIOS | B24: =SUM(C24:N24) -> 1460016.9 | H24: 910287.4 | J24: 459680.8 | K24: 90048.75
A25: 2.3 - MATERIALES Y SUMINISTROS | B25: =SUM(C25:N25) -> 22937085 | C25: 3062630.7 | D25: 2432378.3 | E25: 1797538.3 | F25: 2995765.2 | G25: 2557401.6 | H25: 999513.81 | I25: 3444623.9 | J25: 2478357.5 | K25: =SUM(K26:K34) -> 3168875.7 | L25: 0 | M25: 0 | N25: 0
A26: 2.3.1 - ALIMENTOS Y PRODUCTOS AGROFORESTALES | B26: =SUM(C26:N26) -> 3738411.5 | C26: 541265 | D26: 300691.8 | E26: 658799 | F26: 94850 | G26: 355075 | H26: 213305 | I26: 360730 | J26: 166750 | K26: 1046945.7
A27: 2.3.2 - TEXTILES Y VESTUARIOS | B27: =SUM(C27:N27) -> 346306.4 | G27: 141128 | H27: 205178.4
A28: 2.3.3 - PRODUCTOS DE PAPEL, CARTÓN E IMPRESOS | B28: =SUM(C28:N28) -> 1789484 | C28: 85550 | D28: 107616 | E28: 57997 | F28: 196824 | G28: 607165 | I28: 26550 | J28: 690182 | K28: 17600.03
A29: 2.3.4 - PRODUCTOS FARMACÉUTICOS | B29: =SUM(C29:N29) -> 1456220.8 | C29: 308000 | E29: 250000 | F29: 92000 | G29: 130100 | H29: 180120.76 | I29: 152800 | J29: 269200 | K29: 74000
A30: 2.3.5 - PRODUCTOS DE CUERO, CAUCHO Y PLÁSTICO | B30: =SUM(C30:N30) -> 707809.65 | D30: 249831.2 | E30: 317663.67 | I30: 77390.01 | J30: 62924.77
A31: 2.3.6 - PRODUCTOS DE MINERALES, METÁLICOS Y NO METÁLICOS | B31: =SUM(C31:N31) -> 505509.36 | D31: 183732.33 | E31: 110224.97 | I31: 24157.95 | J31: 187394.11
A32: 2.3.7 - COMBUSTIBLES, LUBRICANTES, PRODUCTOS QUÍMICOS Y CONEXOS | B32: =SUM(C32:N32) -> 5484997.6 | C32: 228412.84 | D32: 1114592.7 | E32: 317328.99 | F32: 226537 | G32: 1065923 | H32: 207742 | I32: 1044515 | J32: 250850.02 | K32: 1029096
A33: 2.3.8 - GASTOS QUE SE ASIGNARÁN DURANTE EL EJERCICIO (ART. 32 Y 33 LEY 423-06) | B33: =SUM(C33:N33) -> 0
A34: 2.3.9 - PRODUCTOS Y ÚTILES VARIOS | B34: =SUM(C34:N34) -> 8908345.7 | C34: 1899402.8 | D34: 475914.23 | E34: 85524.69 | F34: 2385554.2 | G34: 258010.6 | H34: 193167.65 | I34: 1758480.9 | J34: 851056.62 | K34: 1001234
A35: 2.4 - TRANSFERENCIAS CORRIENTES | B35: =SUM(C35:N35) -> 1634538.7 | C35: 136966.7 | D35: 23400 | E35: 127420 | F35: 624573 | G35: 480808 | H35: 118600 | I35: 67571 | J35: =SUM(J36) -> 33600 | K35: =SUM(K36:K42) -> 21600 | L35: 0 | M35: 0 | N35: 0
A36: 2.4.1 - TRANSFERENCIAS CORRIENTES AL SECTOR PRIVADO | B36: =SUM(C36:N36) -> 1634538.7 | C36: 136966.7 | D36: 23400 | E36: 127420 | F36: 624573 | G36: 480808 | H36: 118600 | I36: 67571 | J36: 33600 | K36: 21600
A37: 2.4.2 - TRANSFERENCIAS CORRIENTES AL GOBIERNO GENERAL NACIONAL | B37: =SUM(C37:N37) -> 0
A38: 2.4.3 - TRANSFERENCIAS CORRIENTES A GOBIERNOS GENERALES LOCALES | B38: =SUM(C38:N38) -> 0
A39: 2.4.4 - TRANSFERENCIAS CORRIENTES A EMPRESAS PÚBLICAS NO FINANCIERAS | B39: =SUM(C39:N39) -> 0
A40: 2.4.5 - TRANSFERENCIAS CORRIENTES A INSTITUCIONES PÚBLICAS FINANCIERAS | B40: =SUM(C40:N40) -> 0
A41: 2.4.7 - TRANSFERENCIAS CORRIENTES AL SECTOR EXTERNO | B41: =SUM(C41:N41) -> 0
A42: 2.4.9 - TRANSFERENCIAS CORRIENTES A OTRAS INSTITUCIONES PÚBLICAS | B42: =SUM(C42:N42) -> 0
A43: 2.5 - TRANSFERENCIAS DE CAPITAL | B43: =SUM(C43:N43) -> 0 | C43: 0 | D43: 0 | E43: 0 | F43: 0 | G43: 0 | H43: 0 | I43: 0 | J43: 0 | K43: =SUM(K44:K50) -> 0 | L43: 0 | M43: 0 | N43: 0
A44: 2.5.1 - TRANSFERENCIAS DE CAPITAL AL SECTOR PRIVADO | B44: =SUM(C44:N44) -> 0
A45: 2.5.2 - TRANSFERENCIAS DE CAPITAL AL GOBIERNO GENERAL NACIONAL | B45: =SUM(C45:N45) -> 0
A46: 2.5.3 - TRANSFERENCIAS DE CAPITAL A GOBIERNOS GENERALES LOCALES | B46: =SUM(C46:N46) -> 0
A47: 2.5.4 - TRANSFERENCIAS DE CAPITAL A EMPRESAS PÚBLICAS NO FINANCIERAS | B47: =SUM(C47:N47) -> 0
A48: 2.5.5 - TRANSFERENCIAS DE CAPITAL A INSTITUCIONES PÚBLICAS FINANCIERAS | B48: =SUM(C48:N48) -> 0
A49: 2.5.6 - TRANSFERENCIAS DE CAPITAL AL SECTOR EXTERNO | B49: =SUM(C49:N49) -> 0
A50: 2.5.9 - TRANSFERENCIAS DE CAPITAL A OTRAS INSTITUCIONES PÚBLICAS | B50: =SUM(C50:N50) -> 0
A51: 2.6 - BIENES MUEBLES, INMUEBLES E INTANGIBLES | B51: =SUM(C51:N51) -> 15830428 | C51: 887994.84 | D51: 3887510 | E51: 300539.37 | F51: 0 | G51: 3927042.2 | H51: 1456389 | I51: 730510.01 | J51: 2395076.4 | K51: =SUM(K52:K60) -> 2245366 | L51: 0 | M51: 0 | N51: 0
A52: 2.6.1 - MOBILIARIO Y EQUIPO | B52: =SUM(C52:N52) -> 2937993 | H52: 7995.01 | J52: 684631.95 | K52: 2245366
A53: 2.6.2 - MOBILIARIO Y EQUIPO EDUCACIONAL Y RECREATIVO | B53: =SUM(C53:N53) -> 1788880 | H53: 1399834 | I53: 389046
A54: 2.6.3 - EQUIPO E INSTRUMENTAL, CIENTÍFICO Y LABORATORIO | B54: =SUM(C54:N54) -> 8649071.4 | C54: 887994.84 | D54: 2075030 | G54: 3927042.2 | H54: 48559.95 | J54: 1710444.5
A55: 2.6.4 - VEHÍCULOS Y EQUIPO DE TRANSPORTE, TRACCIÓN Y ELEVACIÓN | B55: =SUM(C55:N55) -> 107609.37 | E55: 107609.37
A56: 2.6.5 - MAQUINARIA, OTROS EQUIPOS Y HERRAMIENTAS | B56: =SUM(C56:N56) -> 2288110 | D56: 1812480 | E56: 192930 | I56: 282700.01
A57: 2.6.6 - EQUIPOS DE DEFENSA Y SEGURIDAD | B57: =SUM(C57:N57) -> 58764 | I57: 58764
A58: 2.6.7 - ACTIVOS BIÓLOGICOS CULTIVABLES | B58: =SUM(C58:N58) -> 0
A59: 2.6.8 - BIENES INTANGIBLES | B59: =SUM(C59:N59) -> 0
A60: 2.6.9 - EDIFICIOS, ESTRUCTURAS, TIERRAS, TERRENOS Y OBJETOS DE VALOR | B60: =SUM(C60:N60) -> 0
A61: 2.7 - OBRAS | B61: =SUM(C61:N61) -> 0 | C61: 0 | D61: 0 | E61: 0 | F61: 0 | G61: 0 | H61: 0 | I61: 0 | J61: 0 | K61: =SUM(K62:K65) -> 0 | L61: 0 | M61: 0 | N61: 0
A62: 2.7.1 - OBRAS EN EDIFICACIONES | B62: =SUM(C62:N62) -> 0
A63: 2.7.2 - INFRAESTRUCTURA | B63: =SUM(C63:N63) -> 0
A64: 2.7.3 - CONSTRUCCIONES EN BIENES CONCESIONADOS | B64: =SUM(C64:N64) -> 0
A65: 2.7.4 - GASTOS QUE SE ASIGNARÁN DURANTE EL EJERCICIO PARA INVERSIÓN (ART. 32 Y 33 LEY 423-06) | B65: =SUM(C65:N65) -> 0
A66: 2.8 - ADQUISICION DE ACTIVOS FINANCIEROS CON FINES DE POLÍTICA | B66: =SUM(C66:N66) -> 0 | C66: 0 | D66: 0 | E66: 0 | F66: 0 | G66: 0 | H66: 0 | I66: 0 | J66: 0 | K66: 0 | L66: 0 | M66: 0 | N66: 0
A67: 2.8.1 - CONCESIÓN DE PRESTAMOS | B67: =SUM(C67:N67) -> 0
A68: 2.8.2 - ADQUISICIÓN DE TÍTULOS VALORES REPRESENTATIVOS DE DEUDA | B68: =SUM(C68:N68) -> 0
A69: 2.9 - GASTOS FINANCIEROS | B69: =SUM(C69:N69) -> 0 | C69: 0 | D69: 0 | E69: 0 | F69: 0 | G69: 0 | H69: 0 | I69: 0 | J69: 0 | K69: 0 | L69: 0 | M69: 0 | N69: 0
A70: 2.9.1 - INTERESES DE LA DEUDA PÚBLICA INTERNA | B70: =SUM(C70:N70) -> 0
A71: 2.9.2 - INTERESES DE LA DEUDA PUBLICA EXTERNA | B71: =SUM(C71:N71) -> 0
A72: 2.9.4 - COMISIONES Y OTROS GASTOS BANCARIOS DE LA DEUDA PÚBLICA | B72: =SUM(C72:N72) -> 0
A73: Total Gastos | B73: =+B69+B66+B61+B51+B43+B35+B25+B15+B9 -> 75971246 | C73: =+C69+C66+C61+C51+C43+C35+C25+C15+C9 -> 6821436.5 | D73: =+D69+D66+D61+D51+D43+D35+D25+D15+D9 -> 7556671.6 | E73: =+E69+E66+E61+E51+E43+E35+E25+E15+E9 -> 11816508 | F73: =+F69+F66+F61+F51+F43+F35+F25+F15+F9 -> 4877050.3 | G73: =+G69+G66+G61+G51+G43+G35+G25+G15+G9 -> 9009314.4 | H73: =+H69+H66+H61+H51+H43+H35+H25+H15+H9 -> 6513141.9 | I73: =+I69+I66+I61+I51+I43+I35+I25+I15+I9 -> 9254860.6 | ... N73: =+N69+N66+N61+N51+N43+N35+N25+N15+N9 -> 0
A74: 4 - APLICACIONES FINANCIERAS | B74: =SUM(C74:N74) -> 0
A75: 4.1 - INCREMENTO DE ACTIVOS FINANCIEROS | B75: =SUM(C75:N75) -> 0
A76: 4.1.1 - INCREMENTO DE ACTIVOS FINANCIEROS CORRIENTES | B76: =SUM(C76:N76) -> 0
A77: 4.1.2 - INCREMENTO DE ACTIVOS FINANCIEROS NO CORRIENTES | B77: =SUM(C77:N77) -> 0
A78: 4.2 - DISMINUCIÓN DE PASIVOS | B78: =SUM(C78:N78) -> 0
A79: 4.2.1 - DISMINUCIÓN DE PASIVOS CORRIENTES | B79: =SUM(C79:N79) -> 0
A80: 4.2.2 - DISMINUCIÓN DE PASIVOS NO CORRIENTES | B80: =SUM(C80:N80) -> 0
A81: 4.3 - DISMINUCIÓN DE FONDOS DE TERCEROS | B81: =SUM(C81:N81) -> 0
A82: 4.3.5 - DISMINUCIÓN DEPÓSITOS FONDOS DE TERCEROS | B82: =SUM(C82:N82) -> 0
A83: TOTAL APLICACIONES FINANCIERAS | B83: =SUM(C83:N83) -> 0
B84: =SUM(C84:N84) -> 0
A85: TOTAL GASTOS Y APLICACIONES FINANCIERAS | B85: =+B83+B73 -> 75971246 | C85: =+C83+C73 -> 6821436.5 | D85: =+D83+D73 -> 7556671.6 | E85: =+E83+E73 -> 11816508 | F85: =+F83+F73 -> 4877050.3 | G85: =+G83+G73 -> 9009314.4 | H85: =+H83+H73 -> 6513141.9 | I85: =+I83+I73 -> 9254860.6 | ... K85: =+K83+K73 -> 11406705
A86: Fuente: [fuente]
A87: Fecha de registro: hasta el [01] de [01] del [2025]
A88: Fecha de imputación: hasta el [30] de [09] del [2025]

Sheet OBLIGACIONES PENDIENTES
A4: SERVICIO REGIONAL DE SALUD
A5: DIRECCIÓN DE FISCALIZACIÓN Y CONTROL
A6: DETALLE OBLIGACIONES CONTRAÍDAS PENDIENTES AL 30 DE SEPTIEMBRE 2025
A7: HOSPITAL MATERNO INFANTIL SAN LORENZO DE LOS MINA
A8: A | B8: B | D8: C | E8: D | F8: E | G8: F
A9: TIPO | B9: PERÍODO | E9: STATUS PRESTAMO
B10: DESDE | C10: HASTA | D10: MONTO | E10: MONTO ORIGEN | F10: MONTO AMORTIZADO | G10: BALANCE PENDIENTE
A11: PROMESE CAL
A12: RETENCIONES DE IMPUESTOS (DGII) | B12: 44470 | C12: 30/9/2025 | D12: 13514741
A13: APROVISIONAMIENTOS DE INCENTIVOS | B13: 45505 | C13: 30/9/2025 | D13: =4817972.08-4413127.55+1227716.05 -> 1632560.6
A14: SEGURIDAD SOCIAL
A15: APROVISIONAMIENTO DE REGALIA PASCUAL
A16: PRESTACIONES LABORALES
A17: VIATICOS
A18: PRÉSTAMOS Y/O ANTICIPOS FINANCIEROS OTORGADOS POR SENASA
A19: TOTAL | D19: 18332713
A21: Nota. En el caso de las columnas D, E y F, solo aplican para llenado de los préstamos otogados por SENASA.
A25: Preparado por: | D25: Revisado por:
A34: ___________________________________________

Sheet INGR SEGUN ORIGEN
A3: Servicio Nacional de Salud
A4: Dirección de Fiscalización
A6: Comportamiento de Ingresos percibidos Segregados según Origen
A7: Establecimiento: HOSPITAL MATERNO INFANTIL SAN LORENZO DE LOS MINA Mes: SEPTIEMBRE . Año: 2025 SRS: I
A8: origen | B8: ARS | C8: Fecha deposito | D8: No. De Documento de referencia | E8: valor de Transferencia o Cheque
A9: INGRESOS | B9: FONDO 100(2.1) | E9: =5424573.16+84553321.83 -> 89977895
B10: FONDO 100 (2.3) | E10: 12593841
B11: FONDO 100 (2.6) | E11: 3169632.1
A12: Sub-Total | E12: =SUM(E9:E11) -> 1.0574137e+08
A13: Venta de Servicio | B13: SUBSIDIADO | C13: 45666 | E13: 7386343.7
B14: CONTRIBUTIDO | C14: 45970 | E14: 2528895.8
B15: SENASA(POR ATENCION ODONTOGICA) | C15: 45666 | E15: 50000
B16: ARS RENACER | C16: 45909 | E16: 372910.21
C17: 46000 | E17: 203400.6
B18: APS | C18: 17/09/2025 | E18: 201903.47
B19: SIMAG | C19: 18/09/2025 | E19: 11667.45
B20: ARS MAPHRE | C20: 19/09/2025 | E20: 87151.82
B21: ARS MAPHRE | C21: 19/09/2025 | E21: 48471.2
B22: ARS MAPHRE | C22: 19/09/2025 | E22: 133968.58
B23: ARS MAPHRE | C23: 19/09/2025 | E23: 5754
B24: ARS ASEMAP | C24: 22/09/2025 | E24: 28902.56
B25: ARS CMD | C25: 23/09/2025 | E25: 88060.19
C26: 25/09/2025 | E26: 12148
B27: ARS SEMMA | C27: 29/09/2025 | E27: 36338.96
B28: ARS FUTURO | C28: 30/09/2025 | E28: 1062055.6
B29: ARS YUNEN | C29: 45666 | E29: 19188.28
B30: INGR. POR FACT DE SERV. DE INSTITUCIONES | E30: =SUM(E13:E29) -> 12277160
A31: Sub-Total
B32: Cafetería
B33: Odontologia (facturacion servicios no contemplado en Plan Basico) | C33: DEL 01 AL 30 DE SEPTIEMBRE 2025 | E33: 185750
B34: Alquiler de espacios internos a terceros
B35: Aportes provenientes de convenios Institucionales
B36: INGRESOS POR SERVICIOS PACIENTES PRIVADOS Y DIFERENCIAS POR SEGUROS MEDICOS | C36: DEL 01 AL 30 DE SEPTIEMBRE 2025
B37: Otros (INGRESOS EXTRANJEROS ) | E37: 303550
A38: Sub-Total | E38: =+E33+E37 -> 489300
A39: Total General | E39: =+E12+E30+E38 -> 1.1850783e+08
A42: Bajo las funciones que nos asisten certificamos que el valor de los ingresos percibidos al 30/09/2025 correspondieron a un monto de RD$118,507,828.69
A45: Dado a los 30 dias del mes de 09 del año 2025
A47: Cuenta Núm. | B47: Balance en libro | C47: Balance en Banco | D47: Balance Conciliado
A48: 010-390450-6 | B48: 209079.81 | C48: 557413.1 | D48: 209079.81
A49: 010-026900-0 | B49: 3.2218202e+08 | C49: 3.4255447e+08 | D49: =342554473.85-20372450.95 -> 3.2218202e+08
A50: 602-500900-0 | B50: -474137.18 | C50: 2274478.5 | D50: =2274478.47-2748615.65 -> -474137.18
A51: 999-510700-0 | B51: 4178472.9 | C51: 4178472.9 | D51: 4178472.9
B52: =SUM(B48:B51) -> 3.2609544e+08 | C52: =SUM(C48:C51) -> 3.4956484e+08 | D52: =SUM(D48:D51) -> 3.2609544e+08
A56: Preparado por: | D56: Revisado por:
B57: ____________________________________ | D57: ___________________________________
A58: Aprobado por:
B59: ________________________________

Sheet Sheet1
A1: 7800 | B1: 11000 | D1: 11000
A2: 5100 | B2: 45000 | D2: 45000
A3: 900 | B3: 13100 | D3: 13100
A4: 5100 | B4: 74050 | D4: 74050
A5: 11400 | B5: 42900 | D5: 42900
A6: 11500 | B6: 43800 | D6: 43800
A7: 4600 | B7: 57000 | D7: 57000
A8: 5000 | B8: 12200
A9: 13200 | B9: 4500
A10: 5300
A11: 1400
A12: 3300
A13: 4700
A14: 7300
A15: 2750
A16: 5400
A17: 5000
A18: 4500
A19: 5300
A20: 5450
A21: 8800
... A30: 3200
A31: =SUM(A1:A30) -> 185750 | B31: =SUM(B1:B30) -> 303550
A32: 191950
A33: =+A31-A32 -> -6200

Sheet DEUDA
A1: Servicio Nacional de Salud
A2: DIRECCION DE FISCALIZACION
A3: RELACION DEUDA
A4: ESTABLECIMIENTO: HOSPITAL MATERNO INFANTIL SAN LORENZO DE LOS MINA
A5: MES DE SEPTIEMBRE 2025
A6: NO | B6: NOMBRES PROVEEDOR | C6: CONCEPTO DE COMPRA | D6: FUENTE DE FINANCIAMIENTO | E6: Años anteriores 2020 | F6: AL 31 DICIEMBRE 2021 | G6: AL 31 DICIEMBRE 2022 | H6: AL 31 DICIEMBRE 2023 | I6: Al 31 DICIEMBRE 2024 | J6: 31 ENERO 2025 | K6: 28 DE FEBRERO 2025 | L6: 31 DE MARZO 2025 | M6: 30 DE ABRIL 2025 | N6: 31 DE MAYO 2025 | O6: 30 DE JUNIO 2025 | P6: 31 DE JULIO 2025 | Q6: 31 DE AGOSTO 2025 | R6: 30 DE SEPTIEMBRE 2025 | S6: TOTAL ADEUDA
A7: 1 | B7: Hospifar, SRL | D7: VS/FG | H7: 94965 | S7: =SUM(E7:R7) -> 94965
A8: 2 | B8: Hospifar, SRL | D8: VS/FG | H8: 11375 | S8: =SUM(E8:R8) -> 11375
A9: 3 | B9: GA INTERPRISE IMPORT, SRL | D9: VS/FG | H9: 287920 | S9: =SUM(E9:R9) -> 287920
A10: 4 | B10: D, CORA INDUSTRIAL, S.R.L | D10: VS/FG | H10: 220483.05 | S10: =SUM(E10:R10) -> 220483.05
A11: 5 | B11: VARA, SRL. | D11: VS/FG | H11: 58382.86 | S11: =SUM(E11:R11) -> 58382.86
A12: 6 | B12: Bio Nuclear, SA | D12: VS/FG | H12: 4182 | S12: =SUM(E12:R12) -> 4182
A13: 7 | B13: Morami, SRL | D13: VS/FG | H13: 213260 | S13: =SUM(E13:R13) -> 213260
A14: 8 | B14: LE.F.P CONSULTORES SRL | D14: VS/FG | I14: 48852 | S14: =SUM(E14:R14) -> 48852
A15: 9 | B15: LE.F.P CONSULTORES SRL | D15: VS/FG | I15: 48852 | S15: =SUM(E15:R15) -> 48852
A16: 10 | B16: LE.F.P CONSULTORES SRL | D16: VS/FG | I16: 48852 | S16: =SUM(E16:R16) -> 48852
A17: 11 | B17: LE.F.P CONSULTORES SRL | D17: VS/FG | I17: 48852 | S17: =SUM(E17:R17) -> 48852
A18: 12 | B18: UNIQUE REPRESENTACIONES, S.R.L | D18: VS/FG | I18: 112271.1 | S18: =SUM(E18:R18) -> 112271.1
A19: 13 | B19: J. JIREH EQUIPOS MEDICOS SRL | D19: VS/FG | I19: 16520 | S19: =SUM(E19:R19) -> 16520
A20: 14 | B20: FARMACIA RUTH | D20: VS/FG | J20: 23625 | S20: =SUM(E20:R20) -> 23625
A21: 15 | B21: Ciencia Tecnología y Consultas, SRL (CIENTEC) | D21: VS/FG | J21: 5691.23 | S21: =SUM(E21:R21) -> 5691.23
A22: 16 | B22: Insocorp, S.R.L. | D22: VS/FG | K22: 137691.84 | S22: =SUM(E22:R22) -> 137691.84
A23: 17 | B23: Agua Planeta Azul, SA | D23: VS/FG | L23: 9500 | S23: =SUM(E23:R23) -> 9500
A24: 18 | B24: Agua Planeta Azul, SA | D24: VS/FG | L24: 9060 | S24: =SUM(E24:R24) -> 9060
A25: 19 | B25: Agua Planeta Azul, SA | D25: VS/FG | L25: 9120 | S25: =SUM(E25:R25) -> 9120
A26: 20 | B26: FARMACIA RUTH | D26: VS/FG | M26: 13900 | S26: =SUM(E26:R26) -> 13900
A27: 21 | B27: FARMACIA RUTH | D27: VS/FG | N27: 18500 | S27: =SUM(E27:R27) -> 18500
A28: 22 | B28: Agua Planeta Azul, SA | D28: VS/FG | O28: 15750 | S28: =SUM(E28:R28) -> 15750
A29: 23 | B29: Agua Planeta Azul, SA | D29: VS/FG | O29: 2700 | S29: =SUM(E29:R29) -> 2700
A30: 24 | B30: SUPLIMED,SRL | D30: VS/FG | O30: 165375 | S30: =SUM(E30:R30) -> 165375
A31: 25 | B31: Agua Planeta Azul, SA | D31: VS/FG | P31: 12660 | S31: =SUM(E31:R31) -> 12660
A32: 26 | B32: FARMACIA RUTH | D32: VS/FG | P32: 16100 | S32: =SUM(E32:R32) -> 16100
A33: 27 | B33: Insocorp, S.R.L. | D33: VS/FG | P33: 199998.2 | S33: =SUM(E33:R33) -> 199998.2
A34: 28 | B34: FARMACIA RUTH | D34: VS/FG | Q34: 950 | S34: =SUM(E34:R34) -> 950
A35: 29 | B35: Gestiones Sanitarias & Ambientales, SRL (GSA) | D35: VS/FG | Q35: 16520 | S35: =SUM(E35:R35) -> 16520
A36: 30 | B36: Lora & Almore Reparaciones SRL | D36: VS/FG | R36: 23681.25 | S36: =SUM(E36:R36) -> 23681.25
A37: 31 | B37: DIALISIS NET SRL | D37: VS/FG | R37: 15000 | S37: =SUM(E37:R37) -> 15000
A38: 32 | B38: Agua Planeta Azul, SA | D38: VS/FG | L38: 3900 | S38: =SUM(E38:R38) -> 3900
A39: TOTAL GENERAL | E39: =SUM(E7:E38) -> 0 | F39: =SUM(F7:F38) -> 0 | G39: =SUM(G7:G38) -> 0 | H39: =SUM(H7:H38) -> 890567.91 | I39: =SUM(I7:I38) -> 324199.1 | J39: =SUM(J7:J38) -> 29316.23 | K39: =SUM(K7:K38) -> 137691.84 | L39: =SUM(L7:L38) -> 31580 | ... S39: =SUM(S7:S38) -> 1914489.5

Sheet INGRESOS POR A.R.S
A2: Servicio Nacional De Salud
A3: Dirección de Fiscalizacion
A4: Ingresos Por Facturación ARS
A6: Establecimiento: | B6: HOSPITAL MATERNO INFANTIL SAN LORENZO DE LOS MINA | C6: HOSPITAL MATERNO INFANTIL SAN LORENZO DE LOS MINA
A8: ARS | C8: ENERO | E8: FEBRERO | G8: MARZO | I8: ABRIL | K8: MAYO | M8: JUNIO | O8: JULIO | Q8: AGOSTO | S8: SEPTIEMBRE | U8: OCTUBRE | W8: NOVIEMBRE | Y8: DICIEMBRE
C9: Facturado | D9: Recibido | E9: Facturado | F9: Recibido | G9: Facturado | H9: Recibido | I9: Facturado | J9: Recibido | K9: Facturado | L9: Recibido | M9: Facturado | N9: Recibido | O9: Facturado | P9: Recibido | Q9: Facturado | R9: Recibido | S9: Facturado | T9: Recibido | U9: Facturado | V9: Recibido | W9: Facturado | X9: Recibido | Y9: Facturado | Z9: Recibido
A10: 1 | B10: SENASA SUBSIDIADO | C10: 4027257.3 | D10: 4833111.5 | E10: 4840265.3 | F10: 5841673.2 | G10: 3159909.7 | H10: 4645181.4 | I10: 1946482.7 | J10: 3053880 | K10: 3199661.2 | L10: 3249661.2 | M10: 5356651.5 | O10: 4812753.5 | P10: 5346295.1 | Q10: 7413343.7 | R10: 4903253.5 | S10: 5095748.9 | T10: 7386343.7
A11: 2 | B11: SENASA CONTRIBUTIVO | C11: 1094583.8 | E11: 2417181.1 | F11: 2152926.5 | G11: 2645113.9 | H11: 1041144.3 | I11: 3267715.2 | J11: 2326715 | K11: 2490193.7 | L11: 2588374.1 | M11: 1240459.9 | N11: 2927464.4 | O11: 2661675 | P11: 2432528 | Q11: 2570895.8 | R11: 1219321.4 | S11: 2390951.2 | T11: =2528895.81+50000 -> 2578895.8
A12: 3 | B12: SENASA JUB. Y PENS. | C12: 0 | D12: 0 | E12: 10985.64 | G12: 0 | K12: 2134.86 | L12: 13000 | M12: 30812.76 | O12: 21145.63 | Q12: 30463.1 | R12: 30468.55 | S12: 18188.8
A13: 4 | B13: SENASA LARIMAR | M13: 2580 | R13: 2580
A14: Total SeNaSa | C14: 5121841.1 | D14: 4833111.5 | E14: 7268432.1 | F14: 7994599.7 | G14: 5805023.6 | H14: 5686325.7 | I14: 5214198 | J14: 5380594.9 | K14: 5691989.8 | L14: 5851035.3 | M14: 6630504.1 | N14: 2927464.4 | O14: 7495574.1 | P14: 7778823.1 | Q14: 10014703 | R14: 6153043.4 | S14: =SUM(S10:S13) -> 7504888.9 | T14: =SUM(T10:T13) -> 9965239.6 | U14: =SUM(U10:U13) -> 0 | V14: =SUM(V10:V13) -> 0 | W14: =SUM(W10:W13) -> 0 | X14: =SUM(X10:X13) -> 0 | Y14: =SUM(Y10:Y13) -> 0 | Z14: =SUM(Z10:Z13) -> 0
A15: 5 | B15: PALIC SALUD | C15: 211714.57 | D15: 206908.45 | E15: 389860 | G15: 189915.48 | H15: 606511.88 | I15: 448858.04 | J15: 187591.6 | K15: 173257.12 | L15: 442756.63 | M15: 274846.74 | O15: 265950.63 | P15: 441505.67 | Q15: 142766.48 | R15: 130717.94 | S15: =80190.4+6545.23+196009.12 -> 282744.75 | T15: =87151.82+48471.2+133968.58+5754 -> 275345.6
A16: 6 | B16: ARL
A17: 7 | B17: RENACER | C17: 275352.44 | D17: 156983.55 | E17: 222716.34 | F17: 272552.44 | G17: 73918.68 | H17: 222620.34 | J17: 73057.08 | M17: 443337.56 | P17: 417359.58 | Q17: 378719.69 | S17: 356377.87 | T17: 372910.21
A18: 8 | B18: YUNEN | C18: 7848.94 | D18: 55135.74 | E18: 14338.35 | F18: 7848.94 | G18: 162551.53 | H18: 14338.35 | I18: 37897.65 | J18: 19489.76 | K18: 45390.42 | L18: 155606.87 | M18: 166835.63 | N18: 79214.03 | O18: 19360.44 | P18: 86993.18 | Q18: 13119.97 | R18: 77589.09 | S18: 66096.6 | T18: 19188.28
A19: 9 | B19: UNIVERSAL
A20: 10 | B20: ARS HUMANO | C20: 44770.98 | E20: 16720.82 | F20: 97648.3 | G20: 83376.61 | H20: 34117.68 | I20: 77617.28 | J20: 97704.2 | K20: 29761.8 | M20: 50732.77 | N20: 102719.16 | O20: 38168.82 | P20: 48385.69 | Q20: 45135.37 | R20: 38168.82 | S20: 37253.63
A21: 11 | B21: ARS PLANSALUD BANCO CENTRAL
A22: 12 | B22: SEMMA | C22: 7193.05 | D22: 15993.02 | E22: 28868.13 | F22: 9531.6 | G22: 10657.5 | H22: 77169.4 | I22: 27941.11 | J22: 35261.18 | K22: 99169.27 | M22: 36644.9 | N22: 8860.1 | O22: 19740.54 | Q22: 13301.87 | R22: 26210.35 | S22: 72979.17 | T22: 36338.96
A23: 13 | B23: FUTURO | C23: 269639.73 | D23: 234503.89 | E23: 617068.65 | G23: 366095.18 | H23: 356314.76 | I23: 395799.78 | J23: 388735.9 | K23: 525599.56 | L23: 493974.92 | M23: 236054.2 | N23: 213364.69 | O23: 651828.66 | P23: 649331.98 | Q23: 389838.41 | S23: 1040980.3 | T23: 1062055.6
A24: 14 | B24: APS | C24: 69588.33 | E24: 122630.62 | F24: 8262.07 | G24: 43770.8 | H24: 212345.21 | I24: 55860.67 | K24: 109234.31 | M24: 229878 | O24: 216887.67 | Q24: 178852.56 | S24: 246860.42 | T24: 201903.47
A25: 15 | B25: SALUD SEGURA
A26: 16 | B26: CONSTITUCION
A27: 17 | B27: META SALUD | C27: 1396 | E27: 20821.36 | F27: 31949.94 | G27: 80842.17 | H27: 1396 | I27: 32922.74 | K27: 3500 | L27: 32863.84 | M27: 41032.92 | O27: 11961.97 | Q27: 12148 | R27: 12030.35 | S27: 22455.91
A28: 18 | B28: ASEMAP | C28: 4869.52 | D28: 6475.14 | E28: 102975.46 | F28: 4869.52 | G28: 6619.63 | H28: 102672.34 | I28: 12257.4 | J28: 6619.63 | K28: 111906.17 | L28: 12182.4 | M28: 7768.47 | O28: 11676.13 | P28: 118687.31 | Q28: 28902.56 | R28: 7768.46 | S28: 7856.59 | T28: 28902.56
A29: 19 | B29: GMA | C29: 76159.34 | E29: 186957.88 | G29: 136798.59 | I29: 83229.31 | K29: 9976.34 | M29: 108970.25 | O29: 49885.59 | P29: 444038.71 | Q29: 26648.23 | S29: 12927.61
A30: 20 | B30: MONUMENTAL | C30: 75131.09 | D30: 71992.2 | E30: 146560.32 | G30: 85258.31 | H30: 237322.18 | I30: 119188.62 | J30: 146560.32 | K30: 58287.88 | L30: 84594.85 | M30: 97214.78 | O30: 108900.79 | P30: 125937.38 | Q30: 40745.74 | S30: 105146.53
A31: 21 | B31: CMD | C31: 273646.7 | D31: 273646.7 | E31: 41285.9 | F31: 41071.9 | G31: 22435.77 | H31: 11220.43 | I31: 61608.05 | J31: 22435.77 | K31: 31245 | L31: 61607.99 | M31: 237194.17 | N31: 31240 | O31: 63128.33 | P31: 300322.5 | Q31: 88200.19 | S31: 282288.73 | T31: 88060.19
A32: 22 | B32: RESERVAS | C32: 48081.02 | D32: 48081.02 | E32: 217047.26 | G32: 79962.77 | I32: 61346.15 | K32: 57351.74 | L32: 79987.57 | M32: 10000 | O32: 18399.99 | P32: 36534.85 | Q32: 38168.7 | R32: 38168.7 | S32: 165161.13
A33: 23 | B33: SIMAG | C33: 28637.51 | E33: 92478.63 | G33: 2821.24 | I33: 1604 | K33: 3360 | M33: 3319.22 | O33: 4368.41 | P33: 181158.69 | Q33: 54351.55 | S33: 2500 | T33: 11667.45
A34: 24 | B34: SEMUNASED
A35: 25 | B35: SERVICIOS MEDICOS UASD
A36: 26 | B36: PRIMERA ARS HUMANO | C36: 259154.57 | E36: 439967.13 | F36: 870590.25 | G36: 404678.83 | H36: 262926.38 | I36: 432554.37 | J36: 534014.43 | K36: 317521.34 | L36: 304098.74 | M36: 374483.12 | N36: 268649.03 | O36: 442825.83 | P36: 313059.93 | Q36: 399800.36 | R36: 401045.51 | S36: 634790.11
B37: EXTRANJEROS | K37: 80323.32 | M37: 436800 | N37: 423700
A38: Total ARS PRIVADAS | C38: 1653183.8 | D38: 1069719.7 | E38: 2660296.9 | F38: 1344325 | G38: 1749703.1 | H38: 2138955 | I38: 1848685.2 | J38: 1511469.9 | K38: 1655884.3 | L38: 1667673.8 | M38: 2755112.7 | N38: 1127747 | O38: 1923083.8 | P38: 3163315.5 | Q38: 1850699.7 | R38: 731699.22 | S38: =SUM(S15:S36) -> 3336419.4 | T38: =SUM(T15:T36) -> 2096372.3 | U38: =SUM(U15:U36) -> 0 | V38: =SUM(V15:V36) -> 0 | W38: =SUM(W15:W36) -> 0 | X38: =SUM(X15:X36) -> 0 | Y38: =SUM(Y15:Y36) -> 0 | Z38: =SUM(Z15:Z36) -> 0
A39: TOTAL | C39: 6775024.9 | D39: 5902831.2 | E39: 9928728.9 | F39: 9338924.6 | G39: 7554726.7 | H39: 7825280.6 | I39: 7062883.1 | J39: 6892064.8 | K39: 7347874.1 | L39: 7518709.1 | M39: 9385616.8 | N39: 4055211.4 | O39: 9418657.9 | P39: 10942139 | Q39: 11865402 | R39: 6884742.7 | S39: =+S38+S14 -> 10841308 | T39: =+T38+T14 -> 12061612 | U39: =+U38+U14 -> 0 | V39: =+V38+V14 -> 0 | W39: =+W38+W14 -> 0 | X39: =+X38+X14 -> 0 | Y39: =+Y38+Y14 -> 0 | Z39: =+Z38+Z14 -> 0

Sheet GLOSA
A1: Servicio Nacional de Salud
A2: Dirección de Fiscalización
A3: Glosa /mes
A4: Establecimientos | B4: Facturado | C4: Recibido | D4: Glosado | E4: %
A5: Enero | B5: 6775024.9 | C5: 5902831.2 | D5: 102835 | E5: 0.017421301
A6: Febrero | B6: 9928728.9 | C6: 9338924.6 | D6: 221056.08 | E6: 0.0236704
A7: Marzo | B7: 7643032.2 | C7: 7825280.7 | D7: 99442.51 | E7: 0.012707852
A8: Abril | B8: 6994829.1 | C8: 6892064.8 | D8: 68054 | E8: 0.0098742542
A9: Mayo | B9: 7347874.1 | C9: 7518709.1 | D9: 116253.22 | E9: 0.015461859
A10: Junio | B10: 9385616.4 | C10: 4055211.4 | D10: 67756.32 | E10: 0.016708456
A11: Julio | B11: 9418657.9 | C11: 10942139 | D11: 116253.22 | E11: 0.01062436
A12: Agosto | B12: 11865402 | C12: 6884742.7 | D12: 36950 | E12: 0.0053669399
A13: Septiembre | B13: 11178188 | C13: =+'INGR SEGUN ORIGEN'!E30 -> 12277160 | D13: 88793.31 | E13: 0.0053669399
A14: Octubre
A15: Noviembre
A16: Diciembre
A17: Total | B17: 69359166 | C17: 59359903 | D17: 828600.35 | E17: 0.013958924
A19: Preparado por:
A20: Licda.
