Workbook

Sheet RESUMEN
A1: Form. No.6 SRS
A3: Servicio Nacional de Salud
A4: Dirección de Fizcalización
A5: Consolidado de Ingresos y Gastos por Fuente de Financiamiento
A6: HOSPITAL MATERNO INFANTIL SAN LORENZO DE LOS MINA
A7: RESUMEN DE EJECUCION ENERO-
C8: Ingresos Generales:
E9: 1.- Balance Inicial / Fuente:
E10: Anticipo Financiero | H10: Otros Aportes | L10: Contraseña: 0001
E11: Transferencias Corrientes
E12: Venta de Servicios
E13: 2.- Ingresos por Fuente / Cuenta
E14: Anticipo Financiero | G14: 0 | H14: Otros Aportes | I14: =+SEPTIEMBRE!I14+'AGOSTO '!I14+JULIO!I14 -> 2105668.7 | L14: OBJETAL | M14: FR | N14: VS
E15: Transferencias Corrientes | G15: =+SEPTIEMBRE!G15+'AGOSTO '!G15+JULIO!G15 -> 3.0637496e+08 | H15: Aportes Nomina SNS | I15: 0 | L15: 2.1 | M15: =G26 -> 5.6592929e+08 | N15: =H26 -> 0
E16: Venta de Servicios | G16: =+SEPTIEMBRE!G16+'AGOSTO '!G16+JULIO!G16 -> 22795995 | L16: 2.2 | M16: =G87 -> 2443769.3 | N16: =H87 -> 8735180.1
H17: TOTAL INGRESOS RDS | I17: =+G10+G11+G12+I10+G14+G15+G16+I14+I15 -> 3.3127662e+08 | L17: 2.3 | M17: ='[1]CONS. FUENTES FINAN'!G212 -> 15408530 | N17: ='[1]CONS. FUENTES FINAN'!H212 -> 999513.81
L18: 2.4 | M18: =G330 -> 0 | N18: =H330 -> 350986
L19: 2.6 | M19: =G336 -> 11931242 | N19: =H336 -> 2945979.2
L20: 2.7 | M20: ='[1]CONS. FUENTES FINAN'!G463 -> 0 | N20: ='[1]CONS. FUENTES FINAN'!H463 -> 0
A21: Código Presupuestario | F21: Descripción Gasto por Cuenta | G21: Distribución del Gasto por Fuente de Financiamiento | I21: TOTAL | J21: %
A22: Tipo | B22: Objeto | C22: Cuenta | D22: Sub-Cuenta | E22: Auxiliar | G22: Fondo 100 | H22: Venta de Servicios/ Otros Aportes
A24: 2 | F24: Gastos | G24: =+SEPTIEMBRE!G25+'AGOSTO '!G25+JULIO!G24+'OCTUBRE '!G25+'ENERO-JUNIO 2025'!G25+'RESUMEN TRIMESTRE OCTUBRE-DIC'!G25 -> 1.4259055e+09 | H24: =+SEPTIEMBRE!H25+'AGOSTO '!H25+JULIO!H24+'OCTUBRE '!H25+'ENERO-JUNIO 2025'!H25 -> 84207144 | I24: =+G24+H24 -> 1.5101126e+09 | J24: 1
A25: 2 | B25: 1 | F25: Servicios Personales | G25: =+SEPTIEMBRE!G26+'AGOSTO '!G26+JULIO!G25+'OCTUBRE '!G26+'ENERO-JUNIO 2025'!G26 -> 6.8607635e+08 | H25: =+SEPTIEMBRE!H26+'AGOSTO '!H26+JULIO!H25+'OCTUBRE '!H26+'ENERO-JUNIO 2025'!H26 -> 9644681.1 | I25: =+G25+H25 -> 6.9572103e+08 | J25: 0.59671635
A26: 2 | B26: 1 | C26: 1 | F26: Remuneraciones | G26: =+SEPTIEMBRE!G27+'AGOSTO '!G27+JULIO!G26+'OCTUBRE '!G27+'ENERO-JUNIO 2025'!G27 -> 5.6592929e+08 | H26: =+SEPTIEMBRE!H27+'AGOSTO '!H27+JULIO!H26+'OCTUBRE '!H27+'ENERO-JUNIO 2025'!H27 -> 0 | I26: =+G26+H26 -> 5.6592929e+08 | J26: 0.49290571
A27: 2 | B27: 1 | C27: 1 | D27: 1 | F27: Remuneraciones al personal fijo | G27: =+SEPTIEMBRE!G28+'AGOSTO '!G28+JULIO!G27+'OCTUBRE '!G28+'ENERO-JUNIO 2025'!G28 -> 5.521678e+08 | H27: =+SEPTIEMBRE!H28+'AGOSTO '!H28+JULIO!H27+'OCTUBRE '!H28+'ENERO-JUNIO 2025'!H28 -> 0 | I27: =+G27+H27 -> 5.521678e+08 | J27: 0.48334771
A28: 2 | B28: 1 | C28: 1 | D28: 1 | E28: 01 | F28: Sueldos a empleados fijos | G28: =+SEPTIEMBRE!G29+'AGOSTO '!G29+JULIO!G28+'OCTUBRE '!G29+'ENERO-JUNIO 2025'!G29 -> 5.521678e+08 | H28: =+SEPTIEMBRE!H29+'AGOSTO '!H29+JULIO!H28+'OCTUBRE '!H29+'ENERO-JUNIO 2025'!H29 -> 0 | I28: =+G28+H28 -> 5.521678e+08 | J28: 0.48334771
A29: 2 | B29: 1 | C29: 1 | D29: 1 | E29: 02 | F29: Sueldos a médicos | G29: =+SEPTIEMBRE!G30+'AGOSTO '!G30+JULIO!G29+'OCTUBRE '!G30+'ENERO-JUNIO 2025'!G30 -> 0 | H29: =+SEPTIEMBRE!H30+'AGOSTO '!H30+JULIO!H29+'OCTUBRE '!H30+'ENERO-JUNIO 2025'!H30 -> 0 | I29: =+G29+H29 -> 0 | J29: 0
A30: 2 | B30: 1 | C30: 1 | D30: 1 | E30: 03 | F30: Ascensos a militares | G30: =+SEPTIEMBRE!G31+'AGOSTO '!G31+JULIO!G30+'OCTUBRE '!G31+'ENERO-JUNIO 2025'!G31 -> 0 | H30: =+SEPTIEMBRE!H31+'AGOSTO '!H31+JULIO!H30+'OCTUBRE '!H31+'ENERO-JUNIO 2025'!H31 -> 0 | I30: =+G30+H30 -> 0 | J30: 0
A31: 2 | B31: 1 | C31: 1 | D31: 1 | E31: 04 | F31: Nuevas plazas maestros | G31: =+SEPTIEMBRE!G32+'AGOSTO '!G32+JULIO!G31+'OCTUBRE '!G32+'ENERO-JUNIO 2025'!G32 -> 0 | H31: =+SEPTIEMBRE!H32+'AGOSTO '!H32+JULIO!H31+'OCTUBRE '!H32+'ENERO-JUNIO 2025'!H32 -> 0 | I31: =+G31+H31 -> 0 | J31: 0
A32: 2 | B32: 1 | C32: 1 | D32: 1 | E32: 05 | F32: Incentivos y escalafón | G32: =+SEPTIEMBRE!G33+'AGOSTO '!G33+JULIO!G32+'OCTUBRE '!G33+'ENERO-JUNIO 2025'!G33 -> 0 | H32: =+SEPTIEMBRE!H33+'AGOSTO '!H33+JULIO!H32+'OCTUBRE '!H33+'ENERO-JUNIO 2025'!H33 -> 0 | I32: =+G32+H32 -> 0 | J32: 0
A33: 2 | B33: 1 | C33: 1 | D33: 1 | E33: 06 | F33: Nuevas plazas a médicos | G33: =+SEPTIEMBRE!G34+'AGOSTO '!G34+JULIO!G33+'OCTUBRE '!G34+'ENERO-JUNIO 2025'!G34 -> 0 | H33: =+SEPTIEMBRE!H34+'AGOSTO '!H34+JULIO!H33+'OCTUBRE '!H34+'ENERO-JUNIO 2025'!H34 -> 0 | I33: =+G33+H33 -> 0 | J33: 0
A34: 2 | B34: 1 | C34: 1 | D34: 2 | F34: Remuneraciones al personal con carácter transitorio | G34: =+SEPTIEMBRE!G35+'AGOSTO '!G35+JULIO!G34+'OCTUBRE '!G35+'ENERO-JUNIO 2025'!G35 -> 11194310 | H34: =+SEPTIEMBRE!H35+'AGOSTO '!H35+JULIO!H34+'OCTUBRE '!H35+'ENERO-JUNIO 2025'!H35 -> 0 | I34: =+G34+H34 -> 11194310
A35: 2 | B35: 1 | C35: 1 | D35: 2 | E35: 03 | F35: Suplencias | G35: =+SEPTIEMBRE!G36+'AGOSTO '!G36+JULIO!G35+'OCTUBRE '!G36+'ENERO-JUNIO 2025'!G36 -> 0 | H35: =+SEPTIEMBRE!H36+'AGOSTO '!H36+JULIO!H35+'OCTUBRE '!H36+'ENERO-JUNIO 2025'!H36 -> 0 | I35: =+G35+H35 -> 0 | J35: 0
A36: 2 | B36: 1 | C36: 1 | D36: 2 | E36: 05 | F36: Sueldo al personal nominal en período probatorio | G36: =+SEPTIEMBRE!G37+'AGOSTO '!G37+JULIO!G36+'OCTUBRE '!G37+'ENERO-JUNIO 2025'!G37 -> 0 | H36: =+SEPTIEMBRE!H37+'AGOSTO '!H37+JULIO!H36+'OCTUBRE '!H37+'ENERO-JUNIO 2025'!H37 -> 0 | I36: =+G36+H36 -> 0 | J36: 0
A37: 2 | B37: 1 | C37: 1 | D37: 2 | E37: 06 | F37: Jornales | G37: =+SEPTIEMBRE!G38+'AGOSTO '!G38+JULIO!G37+'OCTUBRE '!G38+'ENERO-JUNIO 2025'!G38 -> 0 | H37: =+SEPTIEMBRE!H38+'AGOSTO '!H38+JULIO!H37+'OCTUBRE '!H38+'ENERO-JUNIO 2025'!H38 -> 0 | I37: =+G37+H37 -> 0 | J37: 0
A38: 2 | B38: 1 | C38: 1 | D38: 2 | E38: 08 | F38: Empleados temporales | G38: =+SEPTIEMBRE!G39+'AGOSTO '!G39+JULIO!G38+'OCTUBRE '!G39+'ENERO-JUNIO 2025'!G39 -> 11194310 | H38: =+SEPTIEMBRE!H39+'AGOSTO '!H39+JULIO!H38+'OCTUBRE '!H39+'ENERO-JUNIO 2025'!H39 -> 0 | I38: =+G38+H38 -> 11194310 | J38: 0.0094567878
A39: 2 | B39: 1 | C39: 1 | D39: 2 | E39: 09 | F39: Personal de carácter eventual | G39: =+SEPTIEMBRE!G40+'AGOSTO '!G40+JULIO!G39+'OCTUBRE '!G40+'ENERO-JUNIO 2025'!G40 -> 0 | H39: =+SEPTIEMBRE!H40+'AGOSTO '!H40+JULIO!H39+'OCTUBRE '!H40+'ENERO-JUNIO 2025'!H40 -> 0 | I39: =+G39+H39 -> 0 | J39: 0
A40: 2 | B40: 1 | C40: 1 | D40: 2 | E40: 11 | F40: Interinato | G40: =+SEPTIEMBRE!G41+'AGOSTO '!G41+JULIO!G40+'OCTUBRE '!G41+'ENERO-JUNIO 2025'!G41 -> 0 | H40: =+SEPTIEMBRE!H41+'AGOSTO '!H41+JULIO!H40+'OCTUBRE '!H41+'ENERO-JUNIO 2025'!H41 -> 0 | I40: =+G40+H40 -> 0 | J40: 0
A41: 2 | B41: 1 | C41: 1 | D41: 3 | F41: Sueldos al personal fijo en trámite de pensiones | G41: =+SEPTIEMBRE!G42+'AGOSTO '!G42+JULIO!G41+'OCTUBRE '!G42+'ENERO-JUNIO 2025'!G42 -> 0 | H41: =+SEPTIEMBRE!H42+'AGOSTO '!H42+JULIO!H41+'OCTUBRE '!H42+'ENERO-JUNIO 2025'!H42 -> 0 | I41: =+G41+H41 -> 0
A42: 2 | B42: 1 | C42: 1 | D42: 3 | E42: 01 | F42: Sueldos al personal fijo en trámite de pensiones | G42: =+SEPTIEMBRE!G43+'AGOSTO '!G43+JULIO!G42+'OCTUBRE '!G43+'ENERO-JUNIO 2025'!G43 -> 0 | H42: =+SEPTIEMBRE!H43+'AGOSTO '!H43+JULIO!H42+'OCTUBRE '!H43+'ENERO-JUNIO 2025'!H43 -> 0 | I42: =+G42+H42 -> 0 | J42: 0
A43: 2 | B43: 1 | C43: 1 | D43: 4 | F43: Sueldo anual no. 13 | G43: =+SEPTIEMBRE!G44+'AGOSTO '!G44+JULIO!G43+'OCTUBRE '!G44+'ENERO-JUNIO 2025'!G44 -> 0 | H43: =+SEPTIEMBRE!H44+'AGOSTO '!H44+JULIO!H43+'OCTUBRE '!H44+'ENERO-JUNIO 2025'!H44 -> 0 | I43: =+G43+H43 -> 0
A44: 2 | B44: 1 | C44: 1 | D44: 4 | E44: 01 | F44: Sueldo anual no. 13 | G44: =+SEPTIEMBRE!G45+'AGOSTO '!G45+JULIO!G44+'OCTUBRE '!G45+'ENERO-JUNIO 2025'!G45 -> 0 | H44: =+SEPTIEMBRE!H45+'AGOSTO '!H45+JULIO!H44+'OCTUBRE '!H45+'ENERO-JUNIO 2025'!H45 -> 0 | I44: =+G44+H44 -> 0 | J44: 0
A45: 2 | B45: 1 | C45: 1 | D45: 5 | F45: Prestaciones económinas | G45: =+SEPTIEMBRE!G46+'AGOSTO '!G46+JULIO!G45+'OCTUBRE '!G46+'ENERO-JUNIO 2025'!G46 -> 2567178.5 | H45: =+SEPTIEMBRE!H46+'AGOSTO '!H46+JULIO!H45+'OCTUBRE '!H46+'ENERO-JUNIO 2025'!H46 -> 0 | I45: =+G45+H45 -> 2567178.5
A46: 2 | B46: 1 | C46: 1 | D46: 5 | E46: 01 | F46: Prestaciones económinas | G46: =+SEPTIEMBRE!G47+'AGOSTO '!G47+JULIO!G46+'OCTUBRE '!G47+'ENERO-JUNIO 2025'!G47 -> 0 | H46: =+SEPTIEMBRE!H47+'AGOSTO '!H47+JULIO!H46+'OCTUBRE '!H47+'ENERO-JUNIO 2025'!H47 -> 0 | I46: =+G46+H46 -> 0 | J46: 0
A47: 2 | B47: 1 | C47: 1 | D47: 5 | E47: 02 | F47: Pago de porcentaje por desvinculación de cargo | G47: =+SEPTIEMBRE!G48+'AGOSTO '!G48+JULIO!G47+'OCTUBRE '!G48+'ENERO-JUNIO 2025'!G48 -> 0 | H47: =+SEPTIEMBRE!H48+'AGOSTO '!H48+JULIO!H47+'OCTUBRE '!H48+'ENERO-JUNIO 2025'!H48 -> 0 | I47: =+G47+H47 -> 0 | J47: 0
A48: 2 | B48: 1 | C48: 1 | D48: 5 | E48: 03 | F48: Prestación laboral por desvinculación | G48: =+SEPTIEMBRE!G49+'AGOSTO '!G49+JULIO!G48+'OCTUBRE '!G49+'ENERO-JUNIO 2025'!G49 -> 1261233.3 | H48: =+SEPTIEMBRE!H49+'AGOSTO '!H49+JULIO!H48+'OCTUBRE '!H49+'ENERO-JUNIO 2025'!H49 -> 0 | I48: =+G48+H48 -> 1261233.3 | J48: 0.00010121538
A49: 2 | B49: 1 | C49: 1 | D49: 5 | E49: 04 | F49: Proporción de vacaciones no disfrutadas | G49: =+SEPTIEMBRE!G50+'AGOSTO '!G50+JULIO!G49+'OCTUBRE '!G50+'ENERO-JUNIO 2025'!G50 -> 1305945.2 | H49: =+SEPTIEMBRE!H50+'AGOSTO '!H50+JULIO!H49+'OCTUBRE '!H50+'ENERO-JUNIO 2025'!H50 -> 0 | I49: =+G49+H49 -> 1305945.2 | J49: 0
A50: 2 | B50: 1 | C50: 2 | F50: Sobresueldos | G50: =+SEPTIEMBRE!G51+'AGOSTO '!G51+JULIO!G50+'OCTUBRE '!G51+'ENERO-JUNIO 2025'!G51 -> 33460136 | H50: =+SEPTIEMBRE!H51+'AGOSTO '!H51+JULIO!H50+'OCTUBRE '!H51+'ENERO-JUNIO 2025'!H51 -> 9644681.1 | I50: =+G50+H50 -> 43104817
A51: 2 | B51: 1 | C51: 2 | D51: 1 | F51: Primas por antigüedad | G51: =+SEPTIEMBRE!G52+'AGOSTO '!G52+JULIO!G51+'OCTUBRE '!G52+'ENERO-JUNIO 2025'!G52 -> 27240640 | H51: =+SEPTIEMBRE!H52+'AGOSTO '!H52+JULIO!H51+'OCTUBRE '!H52+'ENERO-JUNIO 2025'!H52 -> 0 | I51: =+G51+H51 -> 27240640
A52: 2 | B52: 1 | C52: 2 | D52: 1 | E52: 01 | F52: Primas por antigüedad | G52: =+SEPTIEMBRE!G53+'AGOSTO '!G53+JULIO!G52+'OCTUBRE '!G53+'ENERO-JUNIO 2025'!G53 -> 27240640 | H52: =+SEPTIEMBRE!H53+'AGOSTO '!H53+JULIO!H52+'OCTUBRE '!H53+'ENERO-JUNIO 2025'!H53 -> 0 | I52: =+G52+H52 -> 27240640 | J52: 0.022644526
A53: 2 | B53: 1 | C53: 2 | D53: 2 | F53: Compensación | G53: =+SEPTIEMBRE!G54+'AGOSTO '!G54+JULIO!G53+'OCTUBRE '!G54+'ENERO-JUNIO 2025'!G54 -> 6219496.8 | H53: =+SEPTIEMBRE!H54+'AGOSTO '!H54+JULIO!H53+'OCTUBRE '!H54+'ENERO-JUNIO 2025'!H54 -> 9644681.1 | I53: =+G53+H53 -> 15864178
A54: 2 | B54: 1 | C54: 2 | D54: 2 | E54: 01 | F54: Compensación por gastos de alimentación | G54: =+SEPTIEMBRE!G55+'AGOSTO '!G55+JULIO!G54+'OCTUBRE '!G55+'ENERO-JUNIO 2025'!G55 -> 0 | H54: =+SEPTIEMBRE!H55+'AGOSTO '!H55+JULIO!H54+'OCTUBRE '!H55+'ENERO-JUNIO 2025'!H55 -> 0 | I54: =+G54+H54 -> 0 | J54: 0
A55: 2 | B55: 1 | C55: 2 | D55: 2 | E55: 03 | F55: Pago de horas extraordinarias | G55: =+SEPTIEMBRE!G56+'AGOSTO '!G56+JULIO!G55+'OCTUBRE '!G56+'ENERO-JUNIO 2025'!G56 -> 0 | H55: =+SEPTIEMBRE!H56+'AGOSTO '!H56+JULIO!H55+'OCTUBRE '!H56+'ENERO-JUNIO 2025'!H56 -> 0 | I55: =+G55+H55 -> 0 | J55: 0
A56: 2 | B56: 1 | C56: 2 | D56: 2 | E56: 04 | F56: Prima de transporte | G56: =+SEPTIEMBRE!G57+'AGOSTO '!G57+JULIO!G56+'OCTUBRE '!G57+'ENERO-JUNIO 2025'!G57 -> 0 | H56: =+SEPTIEMBRE!H57+'AGOSTO '!H57+JULIO!H56+'OCTUBRE '!H57+'ENERO-JUNIO 2025'!H57 -> 0 | I56: =+G56+H56 -> 0 | J56: 0
A57: 2 | B57: 1 | C57: 2 | D57: 2 | E57: 05 | F57: Compensación servicios de Seguridad | G57: =+SEPTIEMBRE!G58+'AGOSTO '!G58+JULIO!G57+'OCTUBRE '!G58+'ENERO-JUNIO 2025'!G58 -> 450000 | H57: =+SEPTIEMBRE!H58+'AGOSTO '!H58+JULIO!H57+'OCTUBRE '!H58+'ENERO-JUNIO 2025'!H58 -> 0 | I57: =+G57+H57 -> 450000 | J57: 0.00037642085
A58: 2 | B58: 1 | C58: 2 | D58: 2 | E58: 06 | F58: Incentivo por Rendimieto Individual | G58: =+SEPTIEMBRE!G59+'AGOSTO '!G59+JULIO!G58+'OCTUBRE '!G59+'ENERO-JUNIO 2025'!G59 -> 0 | H58: =+SEPTIEMBRE!H59+'AGOSTO '!H59+JULIO!H58+'OCTUBRE '!H59+'ENERO-JUNIO 2025'!H59 -> 9644681.1 | I58: =+G58+H58 -> 9644681.1 | J58: 0
A59: 2 | B59: 1 | C59: 2 | D59: 2 | E59: 07 | F59: Compensación por distancia | G59: =+SEPTIEMBRE!G60+'AGOSTO '!G60+JULIO!G59+'OCTUBRE '!G60+'ENERO-JUNIO 2025'!G60 -> 0 | H59: =+SEPTIEMBRE!H60+'AGOSTO '!H60+JULIO!H59+'OCTUBRE '!H60+'ENERO-JUNIO 2025'!H60 -> 0 | I59: =+G59+H59 -> 0 | J59: 0
A60: 2 | B60: 1 | C60: 2 | D60: 2 | E60: 08 | F60: Compensaciones especiales | G60: =+SEPTIEMBRE!G61+'AGOSTO '!G61+JULIO!G60+'OCTUBRE '!G61+'ENERO-JUNIO 2025'!G61 -> 3205400 | H60: =+SEPTIEMBRE!H61+'AGOSTO '!H61+JULIO!H60+'OCTUBRE '!H61+'ENERO-JUNIO 2025'!H61 -> 0 | I60: =+G60+H60 -> 3205400 | J60: 0.0025613348
A61: 2 | B61: 1 | C61: 2 | D61: 2 | E61: 09 | F61: Bono por desempeño a servidores de carrera | G61: =+SEPTIEMBRE!G62+'AGOSTO '!G62+JULIO!G61+'OCTUBRE '!G62+'ENERO-JUNIO 2025'!G62 -> 443970.11 | H61: =+SEPTIEMBRE!H62+'AGOSTO '!H62+JULIO!H61+'OCTUBRE '!H62+'ENERO-JUNIO 2025'!H62 -> 0 | I61: =+G61+H61 -> 443970.11 | J61: 0
A62: 2 | B62: 1 | C62: 2 | D62: 2 | E62: 10 | F62: Compensacion por cumplimiento de indicadores | G62: =+SEPTIEMBRE!G63+'AGOSTO '!G63+JULIO!G62+'OCTUBRE '!G63+'ENERO-JUNIO 2025'!G63 -> 2120126.7 | H62: =+SEPTIEMBRE!H63+'AGOSTO '!H63+JULIO!H62+'OCTUBRE '!H63+'ENERO-JUNIO 2025'!H63 -> 0 | I62: =+G62+H62 -> 2120126.7 | J62: 0.0023973323
A63: 2 | B63: 1 | C63: 3 | F63: Dietas y Gastos de Representación | G63: =+SEPTIEMBRE!G64+'AGOSTO '!G64+JULIO!G63+'OCTUBRE '!G64+'ENERO-JUNIO 2025'!G64 -> 0 | H63: =+SEPTIEMBRE!H64+'AGOSTO '!H64+JULIO!H63+'OCTUBRE '!H64+'ENERO-JUNIO 2025'!H64 -> 0 | I63: =+G63+H63 -> 0
A64: 2 | B64: 1 | C64: 3 | D64: 1 | F64: Dietas | G64: =+SEPTIEMBRE!G65+'AGOSTO '!G65+JULIO!G64+'OCTUBRE '!G65+'ENERO-JUNIO 2025'!G65 -> 0 | H64: =+SEPTIEMBRE!H65+'AGOSTO '!H65+JULIO!H64+'OCTUBRE '!H65+'ENERO-JUNIO 2025'!H65 -> 0 | I64: =+G64+H64 -> 0
A65: 2 | B65: 1 | C65: 3 | D65: 1 | E65: 01 | F65: Dietas en el país | G65: =+SEPTIEMBRE!G66+'AGOSTO '!G66+JULIO!G65+'OCTUBRE '!G66+'ENERO-JUNIO 2025'!G66 -> 0 | H65: =+SEPTIEMBRE!H66+'AGOSTO '!H66+JULIO!H65+'OCTUBRE '!H66+'ENERO-JUNIO 2025'!H66 -> 0 | I65: =+G65+H65 -> 0 | J65: 0
A66: 2 | B66: 1 | C66: 3 | D66: 1 | E66: 02 | F66: Dietas en el exterior | G66: =+SEPTIEMBRE!G67+'AGOSTO '!G67+JULIO!G66+'OCTUBRE '!G67+'ENERO-JUNIO 2025'!G67 -> 0 | H66: =+SEPTIEMBRE!H67+'AGOSTO '!H67+JULIO!H66+'OCTUBRE '!H67+'ENERO-JUNIO 2025'!H67 -> 0 | I66: =+G66+H66 -> 0 | J66: 0
A67: 2 | B67: 1 | C67: 3 | D67: 2 | F67: Gastos de representación | G67: =+SEPTIEMBRE!G68+'AGOSTO '!G68+JULIO!G67+'OCTUBRE '!G68+'ENERO-JUNIO 2025'!G68 -> 0 | H67: =+SEPTIEMBRE!H68+'AGOSTO '!H68+JULIO!H67+'OCTUBRE '!H68+'ENERO-JUNIO 2025'!H68 -> 0 | I67: =+G67+H67 -> 0
A68: 2 | B68: 1 | C68: 3 | D68: 2 | E68: 01 | F68: Gastos de representación en el país | G68: =+SEPTIEMBRE!G69+'AGOSTO '!G69+JULIO!G68+'OCTUBRE '!G69+'ENERO-JUNIO 2025'!G69 -> 0 | H68: =+SEPTIEMBRE!H69+'AGOSTO '!H69+JULIO!H68+'OCTUBRE '!H69+'ENERO-JUNIO 2025'!H69 -> 0 | I68: =+G68+H68 -> 0 | J68: 0
A69: 2 | B69: 1 | C69: 3 | D69: 2 | E69: 02 | F69: Gastos de representación en el exterior | G69: =+SEPTIEMBRE!G70+'AGOSTO '!G70+JULIO!G69+'OCTUBRE '!G70+'ENERO-JUNIO 2025'!G70 -> 0 | H69: =+SEPTIEMBRE!H70+'AGOSTO '!H70+JULIO!H69+'OCTUBRE '!H70+'ENERO-JUNIO 2025'!H70 -> 0 | I69: =+G69+H69 -> 0 | J69: 0
A70: 2 | B70: 1 | C70: 4 | F70: Gratificaciones y Bonificaciones | G70: =+SEPTIEMBRE!G71+'AGOSTO '!G71+JULIO!G70+'OCTUBRE '!G71+'ENERO-JUNIO 2025'!G71 -> 0 | H70: =+SEPTIEMBRE!H71+'AGOSTO '!H71+JULIO!H70+'OCTUBRE '!H71+'ENERO-JUNIO 2025'!H71 -> 0 | I70: =+G70+H70 -> 0
A71: 2 | B71: 1 | C71: 4 | D71: 1 | F71: Bonificaciones | G71: =+SEPTIEMBRE!G72+'AGOSTO '!G72+JULIO!G71+'OCTUBRE '!G72+'ENERO-JUNIO 2025'!G72 -> 0 | H71: =+SEPTIEMBRE!H72+'AGOSTO '!H72+JULIO!H71+'OCTUBRE '!H72+'ENERO-JUNIO 2025'!H72 -> 0 | I71: =+G71+H71 -> 0
A72: 2 | B72: 1 | C72: 4 | D72: 1 | E72: 01 | F72: Bonificaciones | G72: =+SEPTIEMBRE!G73+'AGOSTO '!G73+JULIO!G72+'OCTUBRE '!G73+'ENERO-JUNIO 2025'!G73 -> 0 | H72: =+SEPTIEMBRE!H73+'AGOSTO '!H73+JULIO!H72+'OCTUBRE '!H73+'ENERO-JUNIO 2025'!H73 -> 0 | I72: =+G72+H72 -> 0 | J72: 0
A73: 2 | B73: 1 | C73: 4 | D73: 2 | F73: Otras Gratificaciones y Bonificaciones | G73: =+SEPTIEMBRE!G74+'AGOSTO '!G74+JULIO!G73+'OCTUBRE '!G74+'ENERO-JUNIO 2025'!G74 -> 0 | H73: =+SEPTIEMBRE!H74+'AGOSTO '!H74+JULIO!H73+'OCTUBRE '!H74+'ENERO-JUNIO 2025'!H74 -> 0 | I73: =+G73+H73 -> 0
A74: 2 | B74: 1 | C74: 4 | D74: 2 | E74: 01 | F74: Bono escolar | G74: =+SEPTIEMBRE!G75+'AGOSTO '!G75+JULIO!G74+'OCTUBRE '!G75+'ENERO-JUNIO 2025'!G75 -> 0 | H74: =+SEPTIEMBRE!H75+'AGOSTO '!H75+JULIO!H74+'OCTUBRE '!H75+'ENERO-JUNIO 2025'!H75 -> 0 | I74: =+G74+H74 -> 0 | J74: 0
A75: 2 | B75: 1 | C75: 4 | D75: 2 | E75: 02 | F75: Gratificaciones por pasantías | G75: =+SEPTIEMBRE!G76+'AGOSTO '!G76+JULIO!G75+'OCTUBRE '!G76+'ENERO-JUNIO 2025'!G76 -> 0 | H75: =+SEPTIEMBRE!H76+'AGOSTO '!H76+JULIO!H75+'OCTUBRE '!H76+'ENERO-JUNIO 2025'!H76 -> 0 | I75: =+G75+H75 -> 0 | J75: 0
A76: 2 | B76: 1 | C76: 4 | D76: 2 | E76: 03 | F76: Gratificaciones por aniversario de institución | G76: =+SEPTIEMBRE!G77+'AGOSTO '!G77+JULIO!G76+'OCTUBRE '!G77+'ENERO-JUNIO 2025'!G77 -> 0 | H76: =+SEPTIEMBRE!H77+'AGOSTO '!H77+JULIO!H76+'OCTUBRE '!H77+'ENERO-JUNIO 2025'!H77 -> 0 | I76: =+G76+H76 -> 0 | J76: 0
A77: 2 | B77: 1 | C77: 5 | F77: Contribuciones a la Seguridad Social y Riesgo Laboral | G77: =+SEPTIEMBRE!G78+'AGOSTO '!G78+JULIO!G77+'OCTUBRE '!G78+'ENERO-JUNIO 2025'!G78 -> 86686924 | H77: =+SEPTIEMBRE!H78+'AGOSTO '!H78+JULIO!H77+'OCTUBRE '!H78+'ENERO-JUNIO 2025'!H78 -> 0 | I77: =+G77+H77 -> 86686924
A78: 2 | B78: 1 | C78: 5 | D78: 1 | F78: Contribuciones al seguro de salud | G78: =+SEPTIEMBRE!G79+'AGOSTO '!G79+JULIO!G78+'OCTUBRE '!G79+'ENERO-JUNIO 2025'!G79 -> 39942390 | H78: =+SEPTIEMBRE!H79+'AGOSTO '!H79+JULIO!H78+'OCTUBRE '!H79+'ENERO-JUNIO 2025'!H79 -> 0 | I78: =+G78+H78 -> 39942390
A79: 2 | B79: 1 | C79: 5 | D79: 1 | E79: 01 | F79: Contribuciones al seguro de salud | G79: =+SEPTIEMBRE!G80+'AGOSTO '!G80+JULIO!G79+'OCTUBRE '!G80+'ENERO-JUNIO 2025'!G80 -> 39942390 | H79: =+SEPTIEMBRE!H80+'AGOSTO '!H80+JULIO!H79+'OCTUBRE '!H80+'ENERO-JUNIO 2025'!H80 -> 0 | I79: =+G79+H79 -> 39942390 | J79: 0.034939845
A80: 2 | B80: 1 | C80: 5 | D80: 2 | F80: Contribuciones al seguro de pensiones | G80: =+SEPTIEMBRE!G81+'AGOSTO '!G81+JULIO!G80+'OCTUBRE '!G81+'ENERO-JUNIO 2025'!G81 -> 39998719 | H80: =+SEPTIEMBRE!H81+'AGOSTO '!H81+JULIO!H80+'OCTUBRE '!H81+'ENERO-JUNIO 2025'!H81 -> 0 | I80: =+G80+H80 -> 39998719
A81: 2 | B81: 1 | C81: 5 | D81: 2 | E81: 01 | F81: Contribuciones al seguro de pensiones | G81: =+SEPTIEMBRE!G82+'AGOSTO '!G82+JULIO!G81+'OCTUBRE '!G82+'ENERO-JUNIO 2025'!G82 -> 39998719 | H81: =+SEPTIEMBRE!H82+'AGOSTO '!H82+JULIO!H81+'OCTUBRE '!H82+'ENERO-JUNIO 2025'!H82 -> 0 | I81: =+G81+H81 -> 39998719 | J81: 0.034989133
A82: 2 | B82: 1 | C82: 5 | D82: 3 | F82: Contribuciones al seguro de riesgo laboral | G82: =+SEPTIEMBRE!G83+'AGOSTO '!G83+JULIO!G82+'OCTUBRE '!G83+'ENERO-JUNIO 2025'!G83 -> 6745814.6 | H82: =+SEPTIEMBRE!H83+'AGOSTO '!H83+JULIO!H82+'OCTUBRE '!H83+'ENERO-JUNIO 2025'!H83 -> 0 | I82: =+G82+H82 -> 6745814.6
A83: 2 | B83: 1 | C83: 5 | D83: 3 | E83: 01 | F83: Contribuciones al seguro de riesgo laboral | G83: =+SEPTIEMBRE!G84+'AGOSTO '!G84+JULIO!G83+'OCTUBRE '!G84+'ENERO-JUNIO 2025'!G84 -> 6745814.6 | H83: =+SEPTIEMBRE!H84+'AGOSTO '!H84+JULIO!H83+'OCTUBRE '!H84+'ENERO-JUNIO 2025'!H84 -> 0 | I83: =+G83+H83 -> 6745814.6 | J83: 0.0059020441
A84: 2 | B84: 1 | C84: 5 | D84: 4 | F84: Contribuciones al plan de retiro complementario | G84: =+SEPTIEMBRE!G85+'AGOSTO '!G85+JULIO!G84+'OCTUBRE '!G85+'ENERO-JUNIO 2025'!G85 -> 0 | H84: =+SEPTIEMBRE!H85+'AGOSTO '!H85+JULIO!H84+'OCTUBRE '!H85+'ENERO-JUNIO 2025'!H85 -> 0 | I84: =+G84+H84 -> 0
A85: 2 | B85: 1 | C85: 5 | D85: 4 | E85: 01 | F85: Contribuciones al plan de retiro complementario | G85: =+SEPTIEMBRE!G86+'AGOSTO '!G86+JULIO!G85+'OCTUBRE '!G86+'ENERO-JUNIO 2025'!G86 -> 0 | H85: =+SEPTIEMBRE!H86+'AGOSTO '!H86+JULIO!H85+'OCTUBRE '!H86+'ENERO-JUNIO 2025'!H86 -> 0 | I85: =+G85+H85 -> 0 | J85: 0
A86: 2 | B86: 2 | F86: Servicios No Personales | G86: =+SEPTIEMBRE!G87+'AGOSTO '!G87+JULIO!G86+'OCTUBRE '!G87+'ENERO-JUNIO 2025'!G87 -> 34653439 | H86: =+SEPTIEMBRE!H87+'AGOSTO '!H87+JULIO!H86+'OCTUBRE '!H87+'ENERO-JUNIO 2025'!H87 -> 27959692 | I86: =+G86+H86 -> 62613131 | J86: 0.071283414
A87: 2 | B87: 2 | C87: 1 | F87: Servicios Básicos | G87: =+SEPTIEMBRE!G88+'AGOSTO '!G88+JULIO!G87+'OCTUBRE '!G88+'ENERO-JUNIO 2025'!G88 -> 2443769.3 | H87: =+SEPTIEMBRE!H88+'AGOSTO '!H88+JULIO!H87+'OCTUBRE '!H88+'ENERO-JUNIO 2025'!H88 -> 8735180.1 | I87: =+G87+H87 -> 11178949
A88: 2 | B88: 2 | C88: 1 | D88: 1 | F88: Radiocomunicación | G88: =+SEPTIEMBRE!G89+'AGOSTO '!G89+JULIO!G88+'OCTUBRE '!G89+'ENERO-JUNIO 2025'!G89 -> 0 | H88: =+SEPTIEMBRE!H89+'AGOSTO '!H89+JULIO!H88+'OCTUBRE '!H89+'ENERO-JUNIO 2025'!H89 -> 0 | I88: =+G88+H88 -> 0
A89: 2 | B89: 2 | C89: 1 | D89: 1 | E89: 01 | F89: Radiocomunicación | G89: =+SEPTIEMBRE!G90+'AGOSTO '!G90+JULIO!G89+'OCTUBRE '!G90+'ENERO-JUNIO 2025'!G90 -> 0 | H89: =+SEPTIEMBRE!H90+'AGOSTO '!H90+JULIO!H89+'OCTUBRE '!H90+'ENERO-JUNIO 2025'!H90 -> 0 | I89: =+G89+H89 -> 0 | J89: 0
A90: 2 | B90: 2 | C90: 1 | D90: 2 | F90: Servicios telefónico de larga distancia | G90: =+SEPTIEMBRE!G91+'AGOSTO '!G91+JULIO!G90+'OCTUBRE '!G91+'ENERO-JUNIO 2025'!G91 -> 0 | H90: =+SEPTIEMBRE!H91+'AGOSTO '!H91+JULIO!H90+'OCTUBRE '!H91+'ENERO-JUNIO 2025'!H91 -> 0 | I90: =+G90+H90 -> 0
A91: 2 | B91: 2 | C91: 1 | D91: 2 | E91: 01 | F91: Servicios telefónico de larga distancia | G91: =+SEPTIEMBRE!G92+'AGOSTO '!G92+JULIO!G91+'OCTUBRE '!G92+'ENERO-JUNIO 2025'!G92 -> 0 | H91: =+SEPTIEMBRE!H92+'AGOSTO '!H92+JULIO!H91+'OCTUBRE '!H92+'ENERO-JUNIO 2025'!H92 -> 0 | I91: =+G91+H91 -> 0 | J91: 0
A92: 2 | B92: 2 | C92: 1 | D92: 3 | F92: Teléfono local | G92: =+SEPTIEMBRE!G93+'AGOSTO '!G93+JULIO!G92+'OCTUBRE '!G93+'ENERO-JUNIO 2025'!G93 -> 0 | H92: =+SEPTIEMBRE!H93+'AGOSTO '!H93+JULIO!H92+'OCTUBRE '!H93+'ENERO-JUNIO 2025'!H93 -> 2249714.2 | I92: =+G92+H92 -> 2249714.2
A93: 2 | B93: 2 | C93: 1 | D93: 3 | E93: 01 | F93: Teléfono local | G93: =+SEPTIEMBRE!G94+'AGOSTO '!G94+JULIO!G93+'OCTUBRE '!G94+'ENERO-JUNIO 2025'!G94 -> 0 | H93: =+SEPTIEMBRE!H94+'AGOSTO '!H94+JULIO!H93+'OCTUBRE '!H94+'ENERO-JUNIO 2025'!H94 -> 2249714.2 | I93: =+G93+H93 -> 2249714.2 | J93: 0.0017725578
A94: 2 | B94: 2 | C94: 1 | D94: 4 | F94: Telefax y correos | G94: =+SEPTIEMBRE!G95+'AGOSTO '!G95+JULIO!G94+'OCTUBRE '!G95+'ENERO-JUNIO 2025'!G95 -> 0 | H94: =+SEPTIEMBRE!H95+'AGOSTO '!H95+JULIO!H94+'OCTUBRE '!H95+'ENERO-JUNIO 2025'!H95 -> 0 | I94: =+G94+H94 -> 0
A95: 2 | B95: 2 | C95: 1 | D95: 4 | E95: 01 | F95: Telefax y correos | G95: =+SEPTIEMBRE!G96+'AGOSTO '!G96+JULIO!G95+'OCTUBRE '!G96+'ENERO-JUNIO 2025'!G96 -> 0 | H95: =+SEPTIEMBRE!H96+'AGOSTO '!H96+JULIO!H95+'OCTUBRE '!H96+'ENERO-JUNIO 2025'!H96 -> 0 | I95: =+G95+H95 -> 0 | J95: 0
A96: 2 | B96: 2 | C96: 1 | D96: 5 | F96: Servicio de Internet y televisión por cable | G96: =+SEPTIEMBRE!G97+'AGOSTO '!G97+JULIO!G96+'OCTUBRE '!G97+'ENERO-JUNIO 2025'!G97 -> 0 | H96: =+SEPTIEMBRE!H97+'AGOSTO '!H97+JULIO!H96+'OCTUBRE '!H97+'ENERO-JUNIO 2025'!H97 -> 210465.89 | I96: =+G96+H96 -> 210465.89
A97: 2 | B97: 2 | C97: 1 | D97: 5 | E97: 01 | F97: Servicio de Internet y televisión por cable | G97: =+SEPTIEMBRE!G98+'AGOSTO '!G98+JULIO!G97+'OCTUBRE '!G98+'ENERO-JUNIO 2025'!G98 -> 0 | H97: =+SEPTIEMBRE!H98+'AGOSTO '!H98+JULIO!H97+'OCTUBRE '!H98+'ENERO-JUNIO 2025'!H98 -> 210465.89 | I97: =+G97+H97 -> 210465.89 | J97: 0
A98: 2 | B98: 2 | C98: 1 | D98: 6 | F98: Electricidad | G98: =+SEPTIEMBRE!G99+'AGOSTO '!G99+JULIO!G98+'OCTUBRE '!G99+'ENERO-JUNIO 2025'!G99 -> 0 | H98: =+SEPTIEMBRE!H99+'AGOSTO '!H99+JULIO!H98+'OCTUBRE '!H99+'ENERO-JUNIO 2025'!H99 -> 0 | I98: =+G98+H98 -> 0
A99: 2 | B99: 2 | C99: 1 | D99: 6 | E99: 01 | F99: Energía eléctrica | G99: =+SEPTIEMBRE!G100+'AGOSTO '!G100+JULIO!G99+'OCTUBRE '!G100+'ENERO-JUNIO 2025'!G100 -> 0 | H99: =+SEPTIEMBRE!H100+'AGOSTO '!H100+JULIO!H99+'OCTUBRE '!H100+'ENERO-JUNIO 2025'!H100 -> 0 | I99: =+G99+H99 -> 0 | J99: 0
A100: 2 | B100: 2 | C100: 1 | D100: 6 | E100: 02 | F100: Electricidad no cortable | G100: =+SEPTIEMBRE!G101+'AGOSTO '!G101+JULIO!G100+'OCTUBRE '!G101+'ENERO-JUNIO 2025'!G101 -> 0 | H100: =+SEPTIEMBRE!H101+'AGOSTO '!H101+JULIO!H100+'OCTUBRE '!H101+'ENERO-JUNIO 2025'!H101 -> 0 | I100: =+G100+H100 -> 0 | J100: 0
A101: 2 | B101: 2 | C101: 1 | D101: 7 | F101: Agua | G101: =+SEPTIEMBRE!G102+'AGOSTO '!G102+JULIO!G101+'OCTUBRE '!G102+'ENERO-JUNIO 2025'!G102 -> 2443769.3 | H101: =+SEPTIEMBRE!H102+'AGOSTO '!H102+JULIO!H101+'OCTUBRE '!H102+'ENERO-JUNIO 2025'!H102 -> 0 | I101: =+G101+H101 -> 2443769.3
A102: 2 | B102: 2 | C102: 1 | D102: 7 | E102: 01 | F102: Agua | G102: =+SEPTIEMBRE!G103+'AGOSTO '!G103+JULIO!G102+'OCTUBRE '!G103+'ENERO-JUNIO 2025'!G103 -> 2443769.3 | H102: =+SEPTIEMBRE!H103+'AGOSTO '!H103+JULIO!H102+'OCTUBRE '!H103+'ENERO-JUNIO 2025'!H103 -> 0 | I102: =+G102+H102 -> 2443769.3 | J102: 0.00050636969
...

Sheet SEPTIEMBRE
A1: Form. No.6 SRS
A3: Servicio Nacional de Salud
A4: Dirección de Fizcalización
A5: Consolidado de Ingresos y Gastos por Fuente de Financiamiento
A6: HOSPITAL MATERNO INFANTIL SAN LORENZO DE LOS MINA
A7: SEPTIEMBRE 2025
C8: Ingresos Generales:
E9: 1.- Balance Inicial / Fuente:
E10: Anticipo Financiero | H10: Otros Aportes | L10: Contraseña: 0001
E11: Transferencias Corrientes
E12: Venta de Servicios | G12: 209079.81
E13: 2.- Ingresos por Fuente / Cuenta
E14: Anticipo Financiero | H14: Otros Aportes | I14: =+'[2]INGR SEGUN ORIGEN'!E38 -> 489300 | L14: OBJETAL | M14: FR | N14: VS
E15: Transferencias Corrientes | G15: =+'[2]INGR SEGUN ORIGEN'!E12 -> 1.0574137e+08 | H15: Aportes Nomina SNS | L15: 2.1 | M15: =G26 -> 71591504 | N15: =H26 -> 4413127.6
E16: Venta de Servicios | G16: =+'[2]INGR SEGUN ORIGEN'!E30 -> 12277160 | L16: 2.2 | M16: =G87 -> 7782458.8 | N16: =H87 -> 1557736.2
H17: TOTAL INGRESOS RDS | I17: =+G10+G11+G12+I10+G14+G15+G16+I14+I15 -> 1.1871691e+08 | L17: 2.3 | M17: ='[2]CONS. FUENTES FINAN'!G212 -> 25141648 | N17: ='[2]CONS. FUENTES FINAN'!H212 -> 3168875.7
L18: 2.4 | M18: =G330 -> 0 | N18: =H330 -> 21600
L19: 2.6 | M19: =G336 -> 5819603.3 | N19: =H336 -> 2245366
L20: 2.7 | M20: ='[2]CONS. FUENTES FINAN'!G463 -> 0 | N20: ='[2]CONS. FUENTES FINAN'!H463 -> 0
A21: 1 | F21: 2 | G21: 3 | I21: 4 | J21: 5
A22: Código Presupuestario | F22: Descripción Gasto por Cuenta | G22: Distribución del Gasto por Fuente de Financiamiento | I22: TOTAL | J22: %
A23: Tipo | B23: Objeto | C23: Cuenta | D23: Sub-Cuenta | E23: Auxiliar | G23: Fondo 100 | H23: Venta de Servicios/ Otros Aportes
A25: 2 | F25: Gastos | G25: =+G26+G87+G212+G330+G336+G463 -> 1.1033521e+08 | H25: =+H26+H87+H212+H330+H336+H463 -> 11406705 | I25: =SUM(G25:H25) -> 1.2174192e+08 | J25: =+J26+J87+J212+J330+J336+J463 -> 1
A26: 2 | B26: 1 | F26: Servicios Personales | G26: =+G27+G51+G64+G71+G78 -> 71591504 | H26: =+H27+H51+H64+H71+H78 -> 4413127.6 | I26: =SUM(G26:H26) -> 76004631 | J26: =I26/$I$25 -> 0.62430945
A27: 2 | B27: 1 | C27: 1 | F27: Remuneraciones | G27: =+G28+G35+G42+G44+G46 -> 59165425 | H27: =+H28+H35+H42+H44+H46 -> 0 | I27: =SUM(G27:H27) -> 59165425
A28: 2 | B28: 1 | C28: 1 | D28: 1 | F28: Remuneraciones al personal fijo | G28: =SUM(G29:G34) -> 58052894 | H28: =SUM(H29:H34) -> 0 | I28: =SUM(G28:H28) -> 58052894
A29: 2 | B29: 1 | C29: 1 | D29: 1 | E29: 01 | F29: Sueldos a empleados fijos | G29: ='[2]CUENTA T FONDO 100'!A126 -> 58052894 | H29: ='[2]CUENTA T VS'!A75 -> 0 | I29: =SUM(G29:H29) -> 58052894 | J29: =I29/$I$25 -> 0.47685213
A30: 2 | B30: 1 | C30: 1 | D30: 1 | E30: 02 | F30: Sueldos a médicos | G30: ='[2]CUENTA T FONDO 100'!B126 -> 0 | H30: ='[2]CUENTA T VS'!B75 -> 0 | I30: =SUM(G30:H30) -> 0 | J30: =I30/$I$25 -> 0
A31: 2 | B31: 1 | C31: 1 | D31: 1 | E31: 03 | F31: Ascensos a militares | G31: ='[2]CUENTA T FONDO 100'!C126 -> 0 | H31: ='[2]CUENTA T VS'!C75 -> 0 | I31: =SUM(G31:H31) -> 0 | J31: =I31/$I$25 -> 0
A32: 2 | B32: 1 | C32: 1 | D32: 1 | E32: 04 | F32: Nuevas plazas maestros | G32: ='[2]CUENTA T FONDO 100'!D126 -> 0 | H32: ='[2]CUENTA T VS'!D75 -> 0 | I32: =SUM(G32:H32) -> 0 | J32: =I32/$I$25 -> 0
A33: 2 | B33: 1 | C33: 1 | D33: 1 | E33: 05 | F33: Incentivos y escalafón | G33: ='[2]CUENTA T FONDO 100'!E126 -> 0 | H33: ='[2]CUENTA T VS'!E75 -> 0 | I33: =SUM(G33:H33) -> 0 | J33: =I33/$I$25 -> 0
A34: 2 | B34: 1 | C34: 1 | D34: 1 | E34: 06 | F34: Nuevas plazas a médicos | G34: ='[2]CUENTA T FONDO 100'!F126 -> 0 | H34: ='[2]CUENTA T VS'!F75 -> 0 | I34: =SUM(G34:H34) -> 0 | J34: =I34/$I$25 -> 0
A35: 2 | B35: 1 | C35: 1 | D35: 2 | F35: Remuneraciones al personal con carácter transitorio | G35: =SUM(G36:G41) -> 1112531 | H35: =SUM(H36:H41) -> 0 | I35: =SUM(G35:H35) -> 1112531
A36: 2 | B36: 1 | C36: 1 | D36: 2 | E36: 03 | F36: Suplencias | G36: ='[2]CUENTA T FONDO 100'!G126 -> 0 | H36: ='[2]CUENTA T VS'!G75 -> 0 | I36: =SUM(G36:H36) -> 0 | J36: =I36/$I$25 -> 0
A37: 2 | B37: 1 | C37: 1 | D37: 2 | E37: 05 | F37: Sueldo al personal nominal en período probatorio | G37: ='[2]CUENTA T FONDO 100'!H126 -> 0 | H37: ='[2]CUENTA T VS'!H75 -> 0 | I37: =SUM(G37:H37) -> 0 | J37: =I37/$I$25 -> 0
A38: 2 | B38: 1 | C38: 1 | D38: 2 | E38: 06 | F38: Jornales | G38: ='[2]CUENTA T FONDO 100'!I126 -> 0 | H38: ='[2]CUENTA T VS'!I75 -> 0 | I38: =SUM(G38:H38) -> 0 | J38: =I38/$I$25 -> 0
A39: 2 | B39: 1 | C39: 1 | D39: 2 | E39: 08 | F39: Empleados temporales | G39: ='[2]CUENTA T FONDO 100'!J126 -> 1112531 | H39: ='[2]CUENTA T VS'!J75 -> 0 | I39: =SUM(G39:H39) -> 1112531 | J39: =I39/$I$25 -> 0.0091384384
A40: 2 | B40: 1 | C40: 1 | D40: 2 | E40: 09 | F40: Personal de carácter eventual | G40: ='[2]CUENTA T FONDO 100'!K126 -> 0 | H40: ='[2]CUENTA T VS'!K75 -> 0 | I40: =SUM(G40:H40) -> 0 | J40: =I40/$I$25 -> 0
A41: 2 | B41: 1 | C41: 1 | D41: 2 | E41: 11 | F41: Interinato | G41: ='[2]CUENTA T FONDO 100'!L126 -> 0 | H41: ='[2]CUENTA T VS'!L75 -> 0 | I41: =SUM(G41:H41) -> 0 | J41: =I41/$I$25 -> 0
A42: 2 | B42: 1 | C42: 1 | D42: 3 | F42: Sueldos al personal fijo en trámite de pensiones | G42: =SUM(G43) -> 0 | H42: =SUM(H43) -> 0 | I42: =SUM(G42:H42) -> 0
A43: 2 | B43: 1 | C43: 1 | D43: 3 | E43: 01 | F43: Sueldos al personal fijo en trámite de pensiones | G43: ='[2]CUENTA T FONDO 100'!M126 -> 0 | H43: ='[2]CUENTA T VS'!M75 -> 0 | I43: =SUM(G43:H43) -> 0 | J43: =I43/$I$25 -> 0
A44: 2 | B44: 1 | C44: 1 | D44: 4 | F44: Sueldo anual no. 13 | G44: =SUM(G45) -> 0 | H44: =SUM(H45) -> 0 | I44: =SUM(G44:H44) -> 0
A45: 2 | B45: 1 | C45: 1 | D45: 4 | E45: 01 | F45: Sueldo anual no. 13 | G45: ='[2]CUENTA T FONDO 100'!N126 -> 0 | H45: ='[2]CUENTA T VS'!N75 -> 0 | I45: =SUM(G45:H45) -> 0 | J45: =I45/$I$25 -> 0
A46: 2 | B46: 1 | C46: 1 | D46: 5 | F46: Prestaciones económinas | G46: =SUM(G47:G50) -> 0 | H46: =SUM(H47:H50) -> 0 | I46: =SUM(G46:H46) -> 0
A47: 2 | B47: 1 | C47: 1 | D47: 5 | E47: 01 | F47: Prestaciones económinas | G47: ='[2]CUENTA T FONDO 100'!O126 -> 0 | H47: ='[2]CUENTA T VS'!O75 -> 0 | I47: =SUM(G47:H47) -> 0 | J47: =I47/$I$25 -> 0
A48: 2 | B48: 1 | C48: 1 | D48: 5 | E48: 02 | F48: Pago de porcentaje por desvinculación de cargo | G48: ='[2]CUENTA T FONDO 100'!P126 -> 0 | H48: ='[2]CUENTA T VS'!P75 -> 0 | I48: =SUM(G48:H48) -> 0 | J48: =I48/$I$25 -> 0
A49: 2 | B49: 1 | C49: 1 | D49: 5 | E49: 03 | F49: Prestación laboral por desvinculación | G49: ='[2]CUENTA T FONDO 100'!Q126 -> 0 | H49: ='[2]CUENTA T VS'!Q75 -> 0 | I49: =SUM(G49:H49) -> 0 | J49: =I49/$I$25 -> 0
A50: 2 | B50: 1 | C50: 1 | D50: 5 | E50: 04 | F50: Proporción de vacaciones no disfrutadas | G50: ='[2]CUENTA T FONDO 100'!R126 -> 0 | H50: ='[2]CUENTA T VS'!R75 -> 0 | I50: =SUM(G50:H50) -> 0 | J50: =I50/$I$25 -> 0
A51: 2 | B51: 1 | C51: 2 | F51: Sobresueldos | G51: =+G52+G54 -> 3321905.6 | H51: =+H52+H54 -> 4413127.6 | I51: =SUM(G51:H51) -> 7735033.2
A52: 2 | B52: 1 | C52: 2 | D52: 1 | F52: Primas por antigüedad | G52: =SUM(G53) -> 2702311.6 | H52: =SUM(H53) -> 0 | I52: =SUM(G52:H52) -> 2702311.6
A53: 2 | B53: 1 | C53: 2 | D53: 1 | E53: 01 | F53: Primas por antigüedad | G53: ='[2]CUENTA T FONDO 100'!S126 -> 2702311.6 | H53: ='[2]CUENTA T VS'!S75 -> 0 | I53: =SUM(G53:H53) -> 2702311.6 | J53: =I53/$I$25 -> 0.022197051
A54: 2 | B54: 1 | C54: 2 | D54: 2 | F54: Compensación | G54: =SUM(G55:G63) -> 619593.99 | H54: =SUM(H55:H63) -> 4413127.6 | I54: =SUM(G54:H54) -> 5032721.5
A55: 2 | B55: 1 | C55: 2 | D55: 2 | E55: 01 | F55: Compensación por gastos de alimentación | G55: ='[2]CUENTA T FONDO 100'!T126 -> 0 | H55: ='[2]CUENTA T VS'!T75 -> 0 | I55: =SUM(G55:H55) -> 0 | J55: =I55/$I$25 -> 0
A56: 2 | B56: 1 | C56: 2 | D56: 2 | E56: 03 | F56: Pago de horas extraordinarias | G56: ='[2]CUENTA T FONDO 100'!U126 -> 0 | H56: ='[2]CUENTA T VS'!U75 -> 0 | I56: =SUM(G56:H56) -> 0 | J56: =I56/$I$25 -> 0
A57: 2 | B57: 1 | C57: 2 | D57: 2 | E57: 04 | F57: Prima de transporte | G57: ='[2]CUENTA T FONDO 100'!V126 -> 0 | H57: ='[2]CUENTA T VS'!V75 -> 0 | I57: =SUM(G57:H57) -> 0 | J57: =I57/$I$25 -> 0
A58: 2 | B58: 1 | C58: 2 | D58: 2 | E58: 05 | F58: Compensación servicios de Seguridad | G58: ='[2]CUENTA T FONDO 100'!W126 -> 45000 | H58: ='[2]CUENTA T VS'!W75 -> 0 | I58: =SUM(G58:H58) -> 45000 | J58: =I58/$I$25 -> 0.00036963439
A59: 2 | B59: 1 | C59: 2 | D59: 2 | E59: 06 | F59: Incentivo por Rendimieto Individual | G59: ='[2]CUENTA T FONDO 100'!X126 -> 0 | H59: ='[2]CUENTA T VS'!X75 -> 4413127.6 | I59: =SUM(G59:H59) -> 4413127.6 | J59: =I59/$I$25 -> 0.03624986
A60: 2 | B60: 1 | C60: 2 | D60: 2 | E60: 07 | F60: Compensación por distancia | G60: ='[2]CUENTA T FONDO 100'!Y126 -> 0 | H60: ='[2]CUENTA T VS'!Y75 -> 0 | I60: =SUM(G60:H60) -> 0 | J60: =I60/$I$25 -> 0
A61: 2 | B61: 1 | C61: 2 | D61: 2 | E61: 08 | F61: Compensaciones especiales | G61: ='[2]CUENTA T FONDO 100'!Z126 -> 288000 | H61: ='[2]CUENTA T VS'!Z75 -> 0 | I61: =SUM(G61:H61) -> 288000 | J61: =I61/$I$25 -> 0.0023656601
A62: 2 | B62: 1 | C62: 2 | D62: 2 | E62: 09 | F62: Bono por desempeño a servidores de carrera | G62: ='[2]CUENTA T FONDO 100'!AA126 -> 0 | H62: ='[2]CUENTA T VS'!AA75 -> 0 | I62: =SUM(G62:H62) -> 0 | J62: =I62/$I$25 -> 0
A63: 2 | B63: 1 | C63: 2 | D63: 2 | E63: 10 | F63: Compensacion por cumplimiento de indicadores | G63: ='[2]CUENTA T FONDO 100'!AB126 -> 286593.99 | H63: ='[2]CUENTA T VS'!AB75 -> 0 | I63: =SUM(G63:H63) -> 286593.99 | J63: =I63/$I$25 -> 0.002354111
A64: 2 | B64: 1 | C64: 3 | F64: Dietas y Gastos de Representación | G64: =+G65+G68 -> 0 | H64: =+H65+H68 -> 0 | I64: =SUM(G64:H64) -> 0
A65: 2 | B65: 1 | C65: 3 | D65: 1 | F65: Dietas | G65: =SUM(G66:G67) -> 0 | H65: =SUM(H66:H67) -> 0 | I65: =SUM(G65:H65) -> 0
A66: 2 | B66: 1 | C66: 3 | D66: 1 | E66: 01 | F66: Dietas en el país | G66: ='[2]CUENTA T FONDO 100'!AC126 -> 0 | H66: ='[2]CUENTA T VS'!AC75 -> 0 | I66: =SUM(G66:H66) -> 0 | J66: =I66/$I$25 -> 0
A67: 2 | B67: 1 | C67: 3 | D67: 1 | E67: 02 | F67: Dietas en el exterior | G67: ='[2]CUENTA T FONDO 100'!AD126 -> 0 | H67: ='[2]CUENTA T VS'!AD75 -> 0 | I67: =SUM(G67:H67) -> 0 | J67: =I67/$I$25 -> 0
A68: 2 | B68: 1 | C68: 3 | D68: 2 | F68: Gastos de representación | G68: =SUM(G69:G70) -> 0 | H68: =SUM(H69:H70) -> 0 | I68: =SUM(G68:H68) -> 0
A69: 2 | B69: 1 | C69: 3 | D69: 2 | E69: 01 | F69: Gastos de representación en el país | G69: ='[2]CUENTA T FONDO 100'!AE126 -> 0 | H69: ='[2]CUENTA T VS'!AE75 -> 0 | I69: =SUM(G69:H69) -> 0 | J69: =I69/$I$25 -> 0
A70: 2 | B70: 1 | C70: 3 | D70: 2 | E70: 02 | F70: Gastos de representación en el exterior | G70: ='[2]CUENTA T FONDO 100'!AF126 -> 0 | H70: ='[2]CUENTA T VS'!AF75 -> 0 | I70: =SUM(G70:H70) -> 0 | J70: =I70/$I$25 -> 0
A71: 2 | B71: 1 | C71: 4 | F71: Gratificaciones y Bonificaciones | G71: =+G72+G74 -> 0 | H71: =+H72+H74 -> 0 | I71: =SUM(G71:H71) -> 0
A72: 2 | B72: 1 | C72: 4 | D72: 1 | F72: Bonificaciones | G72: =SUM(G73) -> 0 | H72: =SUM(H73) -> 0 | I72: =SUM(G72:H72) -> 0
A73: 2 | B73: 1 | C73: 4 | D73: 1 | E73: 01 | F73: Bonificaciones | G73: ='[2]CUENTA T FONDO 100'!AG126 -> 0 | H73: ='[2]CUENTA T VS'!AG75 -> 0 | I73: =SUM(G73:H73) -> 0 | J73: =I73/$I$25 -> 0
A74: 2 | B74: 1 | C74: 4 | D74: 2 | F74: Otras Gratificaciones y Bonificaciones | G74: =SUM(G75:G77) -> 0 | H74: =SUM(H75:H77) -> 0 | I74: =SUM(G74:H74) -> 0
A75: 2 | B75: 1 | C75: 4 | D75: 2 | E75: 01 | F75: Bono escolar | G75: ='[2]CUENTA T FONDO 100'!AH126 -> 0 | H75: ='[2]CUENTA T VS'!AH75 -> 0 | I75: =SUM(G75:H75) -> 0 | J75: =I75/$I$25 -> 0
A76: 2 | B76: 1 | C76: 4 | D76: 2 | E76: 02 | F76: Gratificaciones por pasantías | G76: ='[2]CUENTA T FONDO 100'!AI126 -> 0 | H76: ='[2]CUENTA T VS'!AI75 -> 0 | I76: =SUM(G76:H76) -> 0 | J76: =I76/$I$25 -> 0
A77: 2 | B77: 1 | C77: 4 | D77: 2 | E77: 03 | F77: Gratificaciones por aniversario de institución | G77: ='[2]CUENTA T FONDO 100'!AJ126 -> 0 | H77: ='[2]CUENTA T VS'!AJ75 -> 0 | I77: =SUM(G77:H77) -> 0 | J77: =I77/$I$25 -> 0
A78: 2 | B78: 1 | C78: 5 | F78: Contribuciones a la Seguridad Social y Riesgo Laboral | G78: =+G79+G81+G83+G85 -> 9104173.4 | H78: =+H79+H81+H83+H85 -> 0 | I78: =SUM(G78:H78) -> 9104173.4
A79: 2 | B79: 1 | C79: 5 | D79: 1 | F79: Contribuciones al seguro de salud | G79: =SUM(G80) -> 4194829.4 | H79: =SUM(H80) -> 0 | I79: =SUM(G79:H79) -> 4194829.4
A80: 2 | B80: 1 | C80: 5 | D80: 1 | E80: 01 | F80: Contribuciones al seguro de salud | G80: ='[2]CUENTA T FONDO 100'!AK126 -> 4194829.4 | H80: ='[2]CUENTA T VS'!AK75 -> 0 | I80: =SUM(G80:H80) -> 4194829.4 | J80: =I80/$I$25 -> 0.034456738
A81: 2 | B81: 1 | C81: 5 | D81: 2 | F81: Contribuciones al seguro de pensiones | G81: =SUM(G82) -> 4200746.8 | H81: =SUM(H82) -> 0 | I81: =SUM(G81:H81) -> 4200746.8
A82: 2 | B82: 1 | C82: 5 | D82: 2 | E82: 01 | F82: Contribuciones al seguro de pensiones | G82: ='[2]CUENTA T FONDO 100'!AL126 -> 4200746.8 | H82: ='[2]CUENTA T VS'!AL75 -> 0 | I82: =SUM(G82:H82) -> 4200746.8 | J82: =I82/$I$25 -> 0.034505344
A83: 2 | B83: 1 | C83: 5 | D83: 3 | F83: Contribuciones al seguro de riesgo laboral | G83: =SUM(G84) -> 708597.18 | H83: =SUM(H84) -> 0 | I83: =SUM(G83:H83) -> 708597.18
A84: 2 | B84: 1 | C84: 5 | D84: 3 | E84: 01 | F84: Contribuciones al seguro de riesgo laboral | G84: ='[2]CUENTA T FONDO 100'!AM126 -> 708597.18 | H84: ='[2]CUENTA T VS'!AM75 -> 0 | I84: =SUM(G84:H84) -> 708597.18 | J84: =I84/$I$25 -> 0.0058204863
A85: 2 | B85: 1 | C85: 5 | D85: 4 | F85: Contribuciones al plan de retiro complementario | G85: =SUM(G86) -> 0 | H85: =SUM(H86) -> 0 | I85: =SUM(G85:H85) -> 0
A86: 2 | B86: 1 | C86: 5 | D86: 4 | E86: 01 | F86: Contribuciones al plan de retiro complementario | G86: ='[2]CUENTA T FONDO 100'!AN126 -> 0 | H86: ='[2]CUENTA T VS'!AN75 -> 0 | I86: =SUM(G86:H86) -> 0 | J86: =I86/$I$25 -> 0
A87: 2 | B87: 2 | F87: Servicios No Personales | G87: =G88+G106+G111+G116+G125+G148+G157+G179+G208 -> 7782458.8 | H87: =H88+H106+H111+H116+H125+H148+H157+H179+H208 -> 1557736.2 | I87: =SUM(G87:H87) -> 9340195 | J87: =I87/$I$25 -> 0.076721273
A88: 2 | B88: 2 | C88: 1 | F88: Servicios Básicos | G88: =+G89+G91+G93+G95+G97+G99+G102+G104 -> 60535 | H88: =+H89+H91+H93+H95+H97+H99+H102+H104 -> 161421.68 | I88: =SUM(G88:H88) -> 221956.68
A89: 2 | B89: 2 | C89: 1 | D89: 1 | F89: Radiocomunicación | G89: =SUM(G90) -> 0 | H89: =SUM(H90) -> 0 | I89: =SUM(G89:H89) -> 0
A90: 2 | B90: 2 | C90: 1 | D90: 1 | E90: 01 | F90: Radiocomunicación | G90: ='[2]CUENTA T FONDO 100'!AO126 -> 0 | H90: ='[2]CUENTA T VS'!AO75 -> 0 | I90: =SUM(G90:H90) -> 0 | J90: =I90/$I$25 -> 0
A91: 2 | B91: 2 | C91: 1 | D91: 2 | F91: Servicios telefónico de larga distancia | G91: =SUM(G92) -> 0 | H91: =SUM(H92) -> 0 | I91: =SUM(G91:H91) -> 0
A92: 2 | B92: 2 | C92: 1 | D92: 2 | E92: 01 | F92: Servicios telefónico de larga distancia | G92: ='[2]CUENTA T FONDO 100'!AP126 -> 0 | H92: ='[2]CUENTA T VS'!AP75 -> 0 | I92: =SUM(G92:H92) -> 0 | J92: =I92/$I$25 -> 0
A93: 2 | B93: 2 | C93: 1 | D93: 3 | F93: Teléfono local | G93: =SUM(G94) -> 0 | H93: =SUM(H94) -> 111421.68 | I93: =SUM(G93:H93) -> 111421.68
A94: 2 | B94: 2 | C94: 1 | D94: 3 | E94: 01 | F94: Teléfono local | G94: ='[2]CUENTA T FONDO 100'!AQ126 -> 0 | H94: ='[2]CUENTA T VS'!AQ75 -> 111421.68 | I94: =SUM(G94:H94) -> 111421.68 | J94: =I94/$I$25 -> 0.00091522855
A95: 2 | B95: 2 | C95: 1 | D95: 4 | F95: Telefax y correos | G95: =SUM(G96) -> 0 | H95: =SUM(H96) -> 0 | I95: =SUM(G95:H95) -> 0
A96: 2 | B96: 2 | C96: 1 | D96: 4 | E96: 01 | F96: Telefax y correos | G96: ='[2]CUENTA T FONDO 100'!AR126 -> 0 | H96: ='[2]CUENTA T VS'!AR75 -> 0 | I96: =SUM(G96:H96) -> 0 | J96: =I96/$I$25 -> 0
A97: 2 | B97: 2 | C97: 1 | D97: 5 | F97: Servicio de Internet y televisión por cable | G97: =SUM(G98) -> 0 | H97: =SUM(H98) -> 0 | I97: =SUM(G97:H97) -> 0
A98: 2 | B98: 2 | C98: 1 | D98: 5 | E98: 01 | F98: Servicio de Internet y televisión por cable | G98: ='[2]CUENTA T FONDO 100'!AS126 -> 0 | H98: ='[2]CUENTA T VS'!AS75 -> 0 | I98: =SUM(G98:H98) -> 0 | J98: =I98/$I$25 -> 0
A99: 2 | B99: 2 | C99: 1 | D99: 6 | F99: Electricidad | G99: =SUM(G100:G101) -> 0 | H99: =SUM(H100:H101) -> 0 | I99: =SUM(G99:H99) -> 0
A100: 2 | B100: 2 | C100: 1 | D100: 6 | E100: 01 | F100: Energía eléctrica | G100: ='[2]CUENTA T FONDO 100'!AT126 -> 0 | H100: ='[2]CUENTA T VS'!AT75 -> 0 | I100: =SUM(G100:H100) -> 0 | J100: =I100/$I$25 -> 0
A101: 2 | B101: 2 | C101: 1 | D101: 6 | E101: 02 | F101: Electricidad no cortable | G101: ='[2]CUENTA T FONDO 100'!AU126 -> 0 | H101: ='[2]CUENTA T VS'!AU75 -> 0 | I101: =SUM(G101:H101) -> 0 | J101: =I101/$I$25 -> 0
A102: 2 | B102: 2 | C102: 1 | D102: 7 | F102: Agua | G102: =SUM(G103) -> 60535 | H102: =SUM(H103) -> 0 | I102: =SUM(G102:H102) -> 60535
...

Sheet AGOSTO 
A1: Form. No.6 SRS
A3: Servicio Nacional de Salud
A4: Dirección de Fizcalización
A5: Consolidado de Ingresos y Gastos por Fuente de Financiamiento
A6: NOMBRE ESTABLECIMIENTO
A7: AGOSTO 2025
C8: Ingresos Generales:
E9: 1.- Balance Inicial / Fuente:
E10: Anticipo Financiero | H10: Otros Aportes | L10: Contraseña: 0001
E11: Transferencias Corrientes
E12: Venta de Servicios | G12: 1771845.5
E13: 2.- Ingresos por Fuente / Cuenta
E14: Anticipo Financiero | H14: Otros Aportes | I14: =+'[3]INGR SEGUN ORIGEN'!E37 -> 590200 | L14: OBJETAL | M14: FR | N14: VS
E15: Transferencias Corrientes | G15: =+'[3]INGR SEGUN ORIGEN'!E12 -> 1.003168e+08 | H15: Aportes Nomina SNS | L15: 2.1 | M15: =G26 -> 71831261 | N15: =H26 -> 0
E16: Venta de Servicios | G16: =+'[3]INGR SEGUN ORIGEN'!E29 -> 6887322.7 | L16: 2.2 | M16: =G87 -> 3128332.8 | N16: =H87 -> 3852523.8
H17: TOTAL INGRESOS RDS | I17: =+G10+G11+G12+I10+G14+G15+G16+I14+I15 -> 1.0956616e+08 | L17: 2.3 | M17: ='[3]CONS. FUENTES FINAN'!G212 -> 14321740 | N17: ='[3]CONS. FUENTES FINAN'!H212 -> 2478357.5
L18: 2.4 | M18: =G330 -> 0 | N18: =H330 -> 33600
L19: 2.6 | M19: =G336 -> 10590779 | N19: =H336 -> 2395076.4
L20: 2.7 | M20: ='[3]CONS. FUENTES FINAN'!G463 -> 0 | N20: ='[3]CONS. FUENTES FINAN'!H463 -> 0
A21: 1 | F21: 2 | G21: 3 | I21: 4 | J21: 5
A22: Código Presupuestario | F22: Descripción Gasto por Cuenta | G22: Distribución del Gasto por Fuente de Financiamiento | I22: TOTAL | J22: %
A23: Tipo | B23: Objeto | C23: Cuenta | D23: Sub-Cuenta | E23: Auxiliar | G23: Fondo 100 | H23: Venta de Servicios/ Otros Aportes
A25: 2 | F25: Gastos | G25: =+G26+G87+G212+G330+G336+G463 -> 99872112 | H25: =+H26+H87+H212+H330+H336+H463 -> 8759557.7 | I25: =SUM(G25:H25) -> 1.0863167e+08 | J25: =+J26+J87+J212+J330+J336+J463 -> 1
A26: 2 | B26: 1 | F26: Servicios Personales | G26: =+G27+G51+G64+G71+G78 -> 71831261 | H26: =+H27+H51+H64+H71+H78 -> 0 | I26: =SUM(G26:H26) -> 71831261 | J26: =I26/$I$25 -> 0.66123683
A27: 2 | B27: 1 | C27: 1 | F27: Remuneraciones | G27: =+G28+G35+G42+G44+G46 -> 59410356 | H27: =+H28+H35+H42+H44+H46 -> 0 | I27: =SUM(G27:H27) -> 59410356 | J27: 0
A28: 2 | B28: 1 | C28: 1 | D28: 1 | F28: Remuneraciones al personal fijo | G28: =SUM(G29:G34) -> 57719080 | H28: =SUM(H29:H34) -> 0 | I28: =SUM(G28:H28) -> 57719080 | J28: 0
A29: 2 | B29: 1 | C29: 1 | D29: 1 | E29: 01 | F29: Sueldos a empleados fijos | G29: ='[3]CUENTA T FONDO 100'!A461 -> 57719080 | H29: ='[3]CUENTA T VS'!A225 -> 0 | I29: =SUM(G29:H29) -> 57719080 | J29: =I29/$I$25 -> 0.5313283
A30: 2 | B30: 1 | C30: 1 | D30: 1 | E30: 02 | F30: Sueldos a médicos | G30: ='[3]CUENTA T FONDO 100'!B461 -> 0 | H30: ='[3]CUENTA T VS'!B225 -> 0 | I30: =SUM(G30:H30) -> 0 | J30: =I30/$I$25 -> 0
A31: 2 | B31: 1 | C31: 1 | D31: 1 | E31: 03 | F31: Ascensos a militares | G31: ='[3]CUENTA T FONDO 100'!C461 -> 0 | H31: ='[3]CUENTA T VS'!C225 -> 0 | I31: =SUM(G31:H31) -> 0 | J31: =I31/$I$25 -> 0
A32: 2 | B32: 1 | C32: 1 | D32: 1 | E32: 04 | F32: Nuevas plazas maestros | G32: ='[3]CUENTA T FONDO 100'!D461 -> 0 | H32: ='[3]CUENTA T VS'!D225 -> 0 | I32: =SUM(G32:H32) -> 0 | J32: =I32/$I$25 -> 0
A33: 2 | B33: 1 | C33: 1 | D33: 1 | E33: 05 | F33: Incentivos y escalafón | G33: ='[3]CUENTA T FONDO 100'!E461 -> 0 | H33: ='[3]CUENTA T VS'!E225 -> 0 | I33: =SUM(G33:H33) -> 0 | J33: =I33/$I$25 -> 0
A34: 2 | B34: 1 | C34: 1 | D34: 1 | E34: 06 | F34: Nuevas plazas a médicos | G34: ='[3]CUENTA T FONDO 100'!F461 -> 0 | H34: ='[3]CUENTA T VS'!F225 -> 0 | I34: =SUM(G34:H34) -> 0 | J34: =I34/$I$25 -> 0
A35: 2 | B35: 1 | C35: 1 | D35: 2 | F35: Remuneraciones al personal con carácter transitorio | G35: =SUM(G36:G41) -> 1112531 | H35: =SUM(H36:H41) -> 0 | I35: =SUM(G35:H35) -> 1112531
A36: 2 | B36: 1 | C36: 1 | D36: 2 | E36: 03 | F36: Suplencias | G36: ='[3]CUENTA T FONDO 100'!G461 -> 0 | H36: ='[3]CUENTA T VS'!G225 -> 0 | I36: =SUM(G36:H36) -> 0 | J36: =I36/$I$25 -> 0
A37: 2 | B37: 1 | C37: 1 | D37: 2 | E37: 05 | F37: Sueldo al personal nominal en período probatorio | G37: ='[3]CUENTA T FONDO 100'!H461 -> 0 | H37: ='[3]CUENTA T VS'!H225 -> 0 | I37: =SUM(G37:H37) -> 0 | J37: =I37/$I$25 -> 0
A38: 2 | B38: 1 | C38: 1 | D38: 2 | E38: 06 | F38: Jornales | G38: ='[3]CUENTA T FONDO 100'!I461 -> 0 | H38: ='[3]CUENTA T VS'!I225 -> 0 | I38: =SUM(G38:H38) -> 0 | J38: =I38/$I$25 -> 0
A39: 2 | B39: 1 | C39: 1 | D39: 2 | E39: 08 | F39: Empleados temporales | G39: ='[3]CUENTA T FONDO 100'!J461 -> 1112531 | H39: ='[3]CUENTA T VS'!J225 -> 0 | I39: =SUM(G39:H39) -> 1112531 | J39: =I39/$I$25 -> 0.010241314
A40: 2 | B40: 1 | C40: 1 | D40: 2 | E40: 09 | F40: Personal de carácter eventual | G40: ='[3]CUENTA T FONDO 100'!K461 -> 0 | H40: ='[3]CUENTA T VS'!K225 -> 0 | I40: =SUM(G40:H40) -> 0 | J40: =I40/$I$25 -> 0
A41: 2 | B41: 1 | C41: 1 | D41: 2 | E41: 11 | F41: Interinato | G41: ='[3]CUENTA T FONDO 100'!L461 -> 0 | H41: ='[3]CUENTA T VS'!L225 -> 0 | I41: =SUM(G41:H41) -> 0 | J41: =I41/$I$25 -> 0
A42: 2 | B42: 1 | C42: 1 | D42: 3 | F42: Sueldos al personal fijo en trámite de pensiones | G42: =SUM(G43) -> 0 | H42: =SUM(H43) -> 0 | I42: =SUM(G42:H42) -> 0
A43: 2 | B43: 1 | C43: 1 | D43: 3 | E43: 01 | F43: Sueldos al personal fijo en trámite de pensiones | G43: ='[3]CUENTA T FONDO 100'!M461 -> 0 | H43: ='[3]CUENTA T VS'!M225 -> 0 | I43: =SUM(G43:H43) -> 0 | J43: =I43/$I$25 -> 0
A44: 2 | B44: 1 | C44: 1 | D44: 4 | F44: Sueldo anual no. 13 | G44: =SUM(G45) -> 0 | H44: =SUM(H45) -> 0 | I44: =SUM(G44:H44) -> 0
A45: 2 | B45: 1 | C45: 1 | D45: 4 | E45: 01 | F45: Sueldo anual no. 13 | G45: ='[3]CUENTA T FONDO 100'!N461 -> 0 | H45: ='[3]CUENTA T VS'!N225 -> 0 | I45: =SUM(G45:H45) -> 0 | J45: =I45/$I$25 -> 0
A46: 2 | B46: 1 | C46: 1 | D46: 5 | F46: Prestaciones económinas | G46: =SUM(G47:G50) -> 578744.8 | H46: =SUM(H47:H50) -> 0 | I46: =SUM(G46:H46) -> 578744.8
A47: 2 | B47: 1 | C47: 1 | D47: 5 | E47: 01 | F47: Prestaciones económinas | G47: ='[3]CUENTA T FONDO 100'!O461 -> 0 | H47: ='[3]CUENTA T VS'!O225 -> 0 | I47: =SUM(G47:H47) -> 0 | J47: =I47/$I$25 -> 0
A48: 2 | B48: 1 | C48: 1 | D48: 5 | E48: 02 | F48: Pago de porcentaje por desvinculación de cargo | G48: ='[3]CUENTA T FONDO 100'!P461 -> 0 | H48: ='[3]CUENTA T VS'!P225 -> 0 | I48: =SUM(G48:H48) -> 0 | J48: =I48/$I$25 -> 0
A49: 2 | B49: 1 | C49: 1 | D49: 5 | E49: 03 | F49: Prestación laboral por desvinculación | G49: ='[3]CUENTA T FONDO 100'!Q461 -> 130000 | H49: ='[3]CUENTA T VS'!Q225 -> 0 | I49: =SUM(G49:H49) -> 130000 | J49: =I49/$I$25 -> 0.0011967044
A50: 2 | B50: 1 | C50: 1 | D50: 5 | E50: 04 | F50: Proporción de vacaciones no disfrutadas | G50: ='[3]CUENTA T FONDO 100'!R461 -> 448744.8 | H50: ='[3]CUENTA T VS'!R225 -> 0 | I50: =SUM(G50:H50) -> 448744.8 | J50: =I50/$I$25 -> 0.0041308838
A51: 2 | B51: 1 | C51: 2 | F51: Sobresueldos | G51: =+G52+G54 -> 3368105.6 | H51: =+H52+H54 -> 0 | I51: =SUM(G51:H51) -> 3368105.6
A52: 2 | B52: 1 | C52: 2 | D52: 1 | F52: Primas por antigüedad | G52: =SUM(G53) -> 2702311.6 | H52: =SUM(H53) -> 0 | I52: =SUM(G52:H52) -> 2702311.6
A53: 2 | B53: 1 | C53: 2 | D53: 1 | E53: 01 | F53: Primas por antigüedad | G53: ='[3]CUENTA T FONDO 100'!S461 -> 2702311.6 | H53: ='[3]CUENTA T VS'!S225 -> 0 | I53: =SUM(G53:H53) -> 2702311.6 | J53: =I53/$I$25 -> 0.02487591
A54: 2 | B54: 1 | C54: 2 | D54: 2 | F54: Compensación | G54: =SUM(G55:G63) -> 665793.99 | H54: =SUM(H55:H63) -> 0 | I54: =SUM(G54:H54) -> 665793.99
A55: 2 | B55: 1 | C55: 2 | D55: 2 | E55: 01 | F55: Compensación por gastos de alimentación | G55: ='[3]CUENTA T FONDO 100'!T461 -> 0 | H55: ='[3]CUENTA T VS'!T225 -> 0 | I55: =SUM(G55:H55) -> 0 | J55: =I55/$I$25 -> 0
A56: 2 | B56: 1 | C56: 2 | D56: 2 | E56: 03 | F56: Pago de horas extraordinarias | G56: ='[3]CUENTA T FONDO 100'!U461 -> 0 | H56: ='[3]CUENTA T VS'!U225 -> 0 | I56: =SUM(G56:H56) -> 0 | J56: =I56/$I$25 -> 0
A57: 2 | B57: 1 | C57: 2 | D57: 2 | E57: 04 | F57: Prima de transporte | G57: ='[3]CUENTA T FONDO 100'!V461 -> 0 | H57: ='[3]CUENTA T VS'!V225 -> 0 | I57: =SUM(G57:H57) -> 0 | J57: =I57/$I$25 -> 0
A58: 2 | B58: 1 | C58: 2 | D58: 2 | E58: 05 | F58: Compensación servicios de Seguridad | G58: ='[3]CUENTA T FONDO 100'!W461 -> 45000 | H58: ='[3]CUENTA T VS'!W225 -> 0 | I58: =SUM(G58:H58) -> 45000 | J58: =I58/$I$25 -> 0.00041424384
A59: 2 | B59: 1 | C59: 2 | D59: 2 | E59: 06 | F59: Incentivo por Rendimieto Individual | G59: ='[3]CUENTA T FONDO 100'!X461 -> 0 | H59: ='[3]CUENTA T VS'!X225 -> 0 | I59: =SUM(G59:H59) -> 0 | J59: =I59/$I$25 -> 0
A60: 2 | B60: 1 | C60: 2 | D60: 2 | E60: 07 | F60: Compensación por distancia | G60: ='[3]CUENTA T FONDO 100'!Y461 -> 0 | H60: ='[3]CUENTA T VS'!Y225 -> 0 | I60: =SUM(G60:H60) -> 0 | J60: =I60/$I$25 -> 0
A61: 2 | B61: 1 | C61: 2 | D61: 2 | E61: 08 | F61: Compensaciones especiales | G61: ='[3]CUENTA T FONDO 100'!Z461 -> 334200 | H61: ='[3]CUENTA T VS'!Z225 -> 0 | I61: =SUM(G61:H61) -> 334200 | J61: =I61/$I$25 -> 0.0030764509
A62: 2 | B62: 1 | C62: 2 | D62: 2 | E62: 09 | F62: Bono por desempeño a servidores de carrera | G62: ='[3]CUENTA T FONDO 100'!AA461 -> 0 | H62: ='[3]CUENTA T VS'!AA225 -> 0 | I62: =SUM(G62:H62) -> 0 | J62: =I62/$I$25 -> 0
A63: 2 | B63: 1 | C63: 2 | D63: 2 | E63: 10 | F63: Compensacion por cumplimiento de indicadores | G63: ='[3]CUENTA T FONDO 100'!AB461 -> 286593.99 | H63: ='[3]CUENTA T VS'!AB225 -> 0 | I63: =SUM(G63:H63) -> 286593.99 | J63: =I63/$I$25 -> 0.0026382177
A64: 2 | B64: 1 | C64: 3 | F64: Dietas y Gastos de Representación | G64: =+G65+G68 -> 0 | H64: =+H65+H68 -> 0 | I64: =SUM(G64:H64) -> 0
A65: 2 | B65: 1 | C65: 3 | D65: 1 | F65: Dietas | G65: =SUM(G66:G67) -> 0 | H65: =SUM(H66:H67) -> 0 | I65: =SUM(G65:H65) -> 0
A66: 2 | B66: 1 | C66: 3 | D66: 1 | E66: 01 | F66: Dietas en el país | G66: ='[3]CUENTA T FONDO 100'!AC461 -> 0 | H66: ='[3]CUENTA T VS'!AC225 -> 0 | I66: =SUM(G66:H66) -> 0 | J66: =I66/$I$25 -> 0
A67: 2 | B67: 1 | C67: 3 | D67: 1 | E67: 02 | F67: Dietas en el exterior | G67: ='[3]CUENTA T FONDO 100'!AD461 -> 0 | H67: ='[3]CUENTA T VS'!AD225 -> 0 | I67: =SUM(G67:H67) -> 0 | J67: =I67/$I$25 -> 0
A68: 2 | B68: 1 | C68: 3 | D68: 2 | F68: Gastos de representación | G68: =SUM(G69:G70) -> 0 | H68: =SUM(H69:H70) -> 0 | I68: =SUM(G68:H68) -> 0
A69: 2 | B69: 1 | C69: 3 | D69: 2 | E69: 01 | F69: Gastos de representación en el país | G69: ='[3]CUENTA T FONDO 100'!AE461 -> 0 | H69: ='[3]CUENTA T VS'!AE225 -> 0 | I69: =SUM(G69:H69) -> 0 | J69: =I69/$I$25 -> 0
A70: 2 | B70: 1 | C70: 3 | D70: 2 | E70: 02 | F70: Gastos de representación en el exterior | G70: ='[3]CUENTA T FONDO 100'!AF461 -> 0 | H70: ='[3]CUENTA T VS'!AF225 -> 0 | I70: =SUM(G70:H70) -> 0 | J70: =I70/$I$25 -> 0
A71: 2 | B71: 1 | C71: 4 | F71: Gratificaciones y Bonificaciones | G71: =+G72+G74 -> 0 | H71: =+H72+H74 -> 0 | I71: =SUM(G71:H71) -> 0
A72: 2 | B72: 1 | C72: 4 | D72: 1 | F72: Bonificaciones | G72: =SUM(G73) -> 0 | H72: =SUM(H73) -> 0 | I72: =SUM(G72:H72) -> 0
A73: 2 | B73: 1 | C73: 4 | D73: 1 | E73: 01 | F73: Bonificaciones | G73: ='[3]CUENTA T FONDO 100'!AG461 -> 0 | H73: ='[3]CUENTA T VS'!AG225 -> 0 | I73: =SUM(G73:H73) -> 0 | J73: =I73/$I$25 -> 0
A74: 2 | B74: 1 | C74: 4 | D74: 2 | F74: Otras Gratificaciones y Bonificaciones | G74: =SUM(G75:G77) -> 0 | H74: =SUM(H75:H77) -> 0 | I74: =SUM(G74:H74) -> 0
A75: 2 | B75: 1 | C75: 4 | D75: 2 | E75: 01 | F75: Bono escolar | G75: ='[3]CUENTA T FONDO 100'!AH461 -> 0 | H75: ='[3]CUENTA T VS'!AH225 -> 0 | I75: =SUM(G75:H75) -> 0 | J75: =I75/$I$25 -> 0
A76: 2 | B76: 1 | C76: 4 | D76: 2 | E76: 02 | F76: Gratificaciones por pasantías | G76: ='[3]CUENTA T FONDO 100'!AI461 -> 0 | H76: ='[3]CUENTA T VS'!AI225 -> 0 | I76: =SUM(G76:H76) -> 0 | J76: =I76/$I$25 -> 0
A77: 2 | B77: 1 | C77: 4 | D77: 2 | E77: 03 | F77: Gratificaciones por aniversario de institución | G77: ='[3]CUENTA T FONDO 100'!AJ461 -> 0 | H77: ='[3]CUENTA T VS'!AJ225 -> 0 | I77: =SUM(G77:H77) -> 0 | J77: =I77/$I$25 -> 0
A78: 2 | B78: 1 | C78: 5 | F78: Contribuciones a la Seguridad Social y Riesgo Laboral | G78: =+G79+G81+G83+G85 -> 9052799.4 | H78: =+H79+H81+H83+H85 -> 0 | I78: =SUM(G78:H78) -> 9052799.4
A79: 2 | B79: 1 | C79: 5 | D79: 1 | F79: Contribuciones al seguro de salud | G79: =SUM(G80) -> 4171161.9 | H79: =SUM(H80) -> 0 | I79: =SUM(G79:H79) -> 4171161.9
A80: 2 | B80: 1 | C80: 5 | D80: 1 | E80: 01 | F80: Contribuciones al seguro de salud | G80: ='[3]CUENTA T FONDO 100'!AK461 -> 4171161.9 | H80: ='[3]CUENTA T VS'!AK225 -> 0 | I80: =SUM(G80:H80) -> 4171161.9 | J80: =I80/$I$25 -> 0.038397292
A81: 2 | B81: 1 | C81: 5 | D81: 2 | F81: Contribuciones al seguro de pensiones | G81: =SUM(G82) -> 4177046.1 | H81: =SUM(H82) -> 0 | I81: =SUM(G81:H81) -> 4177046.1
A82: 2 | B82: 1 | C82: 5 | D82: 2 | E82: 01 | F82: Contribuciones al seguro de pensiones | G82: ='[3]CUENTA T FONDO 100'!AL461 -> 4177046.1 | H82: ='[3]CUENTA T VS'!AL225 -> 0 | I82: =SUM(G82:H82) -> 4177046.1 | J82: =I82/$I$25 -> 0.038451458
A83: 2 | B83: 1 | C83: 5 | D83: 3 | F83: Contribuciones al seguro de riesgo laboral | G83: =SUM(G84) -> 704591.41 | H83: =SUM(H84) -> 0 | I83: =SUM(G83:H83) -> 704591.41
A84: 2 | B84: 1 | C84: 5 | D84: 3 | E84: 01 | F84: Contribuciones al seguro de riesgo laboral | G84: ='[3]CUENTA T FONDO 100'!AM461 -> 704591.41 | H84: ='[3]CUENTA T VS'!AM225 -> 0 | I84: =SUM(G84:H84) -> 704591.41 | J84: =I84/$I$25 -> 0.0064860589
A85: 2 | B85: 1 | C85: 5 | D85: 4 | F85: Contribuciones al plan de retiro complementario | G85: =SUM(G86) -> 0 | H85: =SUM(H86) -> 0 | I85: =SUM(G85:H85) -> 0
A86: 2 | B86: 1 | C86: 5 | D86: 4 | E86: 01 | F86: Contribuciones al plan de retiro complementario | G86: ='[3]CUENTA T FONDO 100'!AN461 -> 0 | H86: ='[3]CUENTA T VS'!AN225 -> 0 | I86: =SUM(G86:H86) -> 0 | J86: =I86/$I$25 -> 0
A87: 2 | B87: 2 | F87: Servicios No Personales | G87: =G88+G106+G111+G116+G125+G148+G157+G179+G208 -> 3128332.8 | H87: =H88+H106+H111+H116+H125+H148+H157+H179+H208 -> 3852523.8 | I87: =SUM(G87:H87) -> 6980856.6 | J87: =I87/$I$25 -> 0.064261708
A88: 2 | B88: 2 | C88: 1 | F88: Servicios Básicos | G88: =+G89+G91+G93+G95+G97+G99+G102+G104 -> 60535 | H88: =+H89+H91+H93+H95+H97+H99+H102+H104 -> 933611.83 | I88: =SUM(G88:H88) -> 994146.83
A89: 2 | B89: 2 | C89: 1 | D89: 1 | F89: Radiocomunicación | G89: =SUM(G90) -> 0 | H89: =SUM(H90) -> 0 | I89: =SUM(G89:H89) -> 0
A90: 2 | B90: 2 | C90: 1 | D90: 1 | E90: 01 | F90: Radiocomunicación | G90: ='[3]CUENTA T FONDO 100'!AO461 -> 0 | H90: ='[3]CUENTA T VS'!AO225 -> 0 | I90: =SUM(G90:H90) -> 0 | J90: =I90/$I$25 -> 0
A91: 2 | B91: 2 | C91: 1 | D91: 2 | F91: Servicios telefónico de larga distancia | G91: =SUM(G92) -> 0 | H91: =SUM(H92) -> 0 | I91: =SUM(G91:H91) -> 0
A92: 2 | B92: 2 | C92: 1 | D92: 2 | E92: 01 | F92: Servicios telefónico de larga distancia | G92: ='[3]CUENTA T FONDO 100'!AP461 -> 0 | H92: ='[3]CUENTA T VS'!AP225 -> 0 | I92: =SUM(G92:H92) -> 0 | J92: =I92/$I$25 -> 0
A93: 2 | B93: 2 | C93: 1 | D93: 3 | F93: Teléfono local | G93: =SUM(G94) -> 0 | H93: =SUM(H94) -> 213611.83 | I93: =SUM(G93:H93) -> 213611.83
A94: 2 | B94: 2 | C94: 1 | D94: 3 | E94: 01 | F94: Teléfono local | G94: ='[3]CUENTA T FONDO 100'!AQ461 -> 0 | H94: ='[3]CUENTA T VS'!AQ225 -> 213611.83 | I94: =SUM(G94:H94) -> 213611.83 | J94: =I94/$I$25 -> 0.0019663863
A95: 2 | B95: 2 | C95: 1 | D95: 4 | F95: Telefax y correos | G95: =SUM(G96) -> 0 | H95: =SUM(H96) -> 0 | I95: =SUM(G95:H95) -> 0
A96: 2 | B96: 2 | C96: 1 | D96: 4 | E96: 01 | F96: Telefax y correos | G96: ='[3]CUENTA T FONDO 100'!AR461 -> 0 | H96: ='[3]CUENTA T VS'!AR225 -> 0 | I96: =SUM(G96:H96) -> 0 | J96: =I96/$I$25 -> 0
A97: 2 | B97: 2 | C97: 1 | D97: 5 | F97: Servicio de Internet y televisión por cable | G97: =SUM(G98) -> 0 | H97: =SUM(H98) -> 0 | I97: =SUM(G97:H97) -> 0
A98: 2 | B98: 2 | C98: 1 | D98: 5 | E98: 01 | F98: Servicio de Internet y televisión por cable | G98: ='[3]CUENTA T FONDO 100'!AS461 -> 0 | H98: ='[3]CUENTA T VS'!AS225 -> 0 | I98: =SUM(G98:H98) -> 0 | J98: =I98/$I$25 -> 0
A99: 2 | B99: 2 | C99: 1 | D99: 6 | F99: Electricidad | G99: =SUM(G100:G101) -> 0 | H99: =SUM(H100:H101) -> 0 | I99: =SUM(G99:H99) -> 0
A100: 2 | B100: 2 | C100: 1 | D100: 6 | E100: 01 | F100: Energía eléctrica | G100: ='[3]CUENTA T FONDO 100'!AT461 -> 0 | H100: ='[3]CUENTA T VS'!AT225 -> 0 | I100: =SUM(G100:H100) -> 0 | J100: =I100/$I$25 -> 0
A101: 2 | B101: 2 | C101: 1 | D101: 6 | E101: 02 | F101: Electricidad no cortable | G101: ='[3]CUENTA T FONDO 100'!AU461 -> 0 | H101: ='[3]CUENTA T VS'!AU225 -> 0 | I101: =SUM(G101:H101) -> 0 | J101: =I101/$I$25 -> 0
A102: 2 | B102: 2 | C102: 1 | D102: 7 | F102: Agua | G102: =SUM(G103) -> 60535 | H102: =SUM(H103) -> 0 | I102: =SUM(G102:H102) -> 60535
...

Sheet JULIO
A1: Form. No.6 SRS
A3: Servicio Nacional de Salud
A4: Dirección de Fizcalización
A5: Consolidado de Ingresos y Gastos por Fuente de Financiamiento
A6: HOSPITAL MATERNO INFANTIL SAN LORENZO DE LOS MINA
A7: JULIO 2025
C8: Ingresos Generales:
E9: 1.- Balance Inicial / Fuente:
E10: Anticipo Financiero | H10: Otros Aportes | L10: Contraseña: 0001
E11: Transferencias Corrientes
E12: Venta de Servicios | G12: 1377881.2
E13: 2.- Ingresos por Fuente / Cuenta
E14: Anticipo Financiero | G14: 0 | H14: Otros Aportes | I14: =+'[1]INGR SEGUN ORIGEN'!E31 -> 1026168.7 | L14: OBJETAL | M14: FR | N14: VS
E15: Transferencias Corrientes | G15: =+'[1]INGR SEGUN ORIGEN'!E12 -> 1.003168e+08 | H15: Aportes Nomina SNS | I15: 0 | L15: 2.1 | M15: =G26 -> 58925421 | N15: =H26 -> 0
E16: Venta de Servicios | G16: =+'[1]INGR SEGUN ORIGEN'!E23 -> 3631511.4 | L16: 2.2 | M16: =G87 -> 60535 | N16: =H87 -> 1781904.1
H17: TOTAL INGRESOS RDS | I17: =+G10+G11+G12+I10+G14+G15+G16+I14+I15 -> 1.0635236e+08 | L17: 2.3 | M17: ='[1]CONS. FUENTES FINAN'!G212 -> 15408530 | N17: ='[1]CONS. FUENTES FINAN'!H212 -> 999513.81
L18: 2.4 | M18: =G330 -> 0 | N18: =H330 -> 30371
L19: 2.6 | M19: =G336 -> 2268904.4 | N19: =H336 -> 0
L20: 2.7 | M20: ='[1]CONS. FUENTES FINAN'!G463 -> 0 | N20: ='[1]CONS. FUENTES FINAN'!H463 -> 0
A21: Código Presupuestario | F21: Descripción Gasto por Cuenta | G21: Distribución del Gasto por Fuente de Financiamiento | I21: TOTAL | J21: %
A22: Tipo | B22: Objeto | C22: Cuenta | D22: Sub-Cuenta | E22: Auxiliar | G22: Fondo 100 | H22: Venta de Servicios/ Otros Aportes
A24: 2 | F24: Gastos | G24: 1.1029218e+08 | H24: 9254860.6 | I24: 1.1954704e+08 | J24: 1
A25: 2 | B25: 1 | F25: Servicios Personales | G25: 71335676 | H25: 0 | I25: 71335676 | J25: 0.59671635
A26: 2 | B26: 1 | C26: 1 | F26: Remuneraciones | G26: 58925421 | H26: 0 | I26: 58925421 | J26: 0.49290571
A27: 2 | B27: 1 | C27: 1 | D27: 1 | F27: Remuneraciones al personal fijo | G27: 57782790 | H27: 0 | I27: 57782790 | J27: 0.48334771
A28: 2 | B28: 1 | C28: 1 | D28: 1 | E28: 01 | F28: Sueldos a empleados fijos | G28: 57782790 | H28: 0 | I28: 57782790 | J28: 0.48334771
A29: 2 | B29: 1 | C29: 1 | D29: 1 | E29: 02 | F29: Sueldos a médicos | G29: 0 | H29: 0 | I29: 0 | J29: 0
A30: 2 | B30: 1 | C30: 1 | D30: 1 | E30: 03 | F30: Ascensos a militares | G30: 0 | H30: 0 | I30: 0 | J30: 0
A31: 2 | B31: 1 | C31: 1 | D31: 1 | E31: 04 | F31: Nuevas plazas maestros | G31: 0 | H31: 0 | I31: 0 | J31: 0
A32: 2 | B32: 1 | C32: 1 | D32: 1 | E32: 05 | F32: Incentivos y escalafón | G32: 0 | H32: 0 | I32: 0 | J32: 0
A33: 2 | B33: 1 | C33: 1 | D33: 1 | E33: 06 | F33: Nuevas plazas a médicos | G33: 0 | H33: 0 | I33: 0 | J33: 0
A34: 2 | B34: 1 | C34: 1 | D34: 2 | F34: Remuneraciones al personal con carácter transitorio | G34: 1130531 | H34: 0 | I34: 1130531
A35: 2 | B35: 1 | C35: 1 | D35: 2 | E35: 03 | F35: Suplencias | G35: 0 | H35: 0 | I35: 0 | J35: 0
A36: 2 | B36: 1 | C36: 1 | D36: 2 | E36: 05 | F36: Sueldo al personal nominal en período probatorio | G36: 0 | H36: 0 | I36: 0 | J36: 0
A37: 2 | B37: 1 | C37: 1 | D37: 2 | E37: 06 | F37: Jornales | G37: 0 | H37: 0 | I37: 0 | J37: 0
A38: 2 | B38: 1 | C38: 1 | D38: 2 | E38: 08 | F38: Empleados temporales | G38: 1130531 | H38: 0 | I38: 1130531 | J38: 0.0094567878
A39: 2 | B39: 1 | C39: 1 | D39: 2 | E39: 09 | F39: Personal de carácter eventual | G39: 0 | H39: 0 | I39: 0 | J39: 0
A40: 2 | B40: 1 | C40: 1 | D40: 2 | E40: 11 | F40: Interinato | G40: 0 | H40: 0 | I40: 0 | J40: 0
A41: 2 | B41: 1 | C41: 1 | D41: 3 | F41: Sueldos al personal fijo en trámite de pensiones | G41: 0 | H41: 0 | I41: 0
A42: 2 | B42: 1 | C42: 1 | D42: 3 | E42: 01 | F42: Sueldos al personal fijo en trámite de pensiones | G42: 0 | H42: 0 | I42: 0 | J42: 0
A43: 2 | B43: 1 | C43: 1 | D43: 4 | F43: Sueldo anual no. 13 | G43: 0 | H43: 0 | I43: 0
A44: 2 | B44: 1 | C44: 1 | D44: 4 | E44: 01 | F44: Sueldo anual no. 13 | G44: 0 | H44: 0 | I44: 0 | J44: 0
A45: 2 | B45: 1 | C45: 1 | D45: 5 | F45: Prestaciones económinas | G45: 12100 | H45: 0 | I45: 12100
A46: 2 | B46: 1 | C46: 1 | D46: 5 | E46: 01 | F46: Prestaciones económinas | G46: 0 | H46: 0 | I46: 0 | J46: 0
A47: 2 | B47: 1 | C47: 1 | D47: 5 | E47: 02 | F47: Pago de porcentaje por desvinculación de cargo | G47: 0 | H47: 0 | I47: 0 | J47: 0
A48: 2 | B48: 1 | C48: 1 | D48: 5 | E48: 03 | F48: Prestación laboral por desvinculación | G48: 12100 | H48: 0 | I48: 12100 | J48: 0.00010121538
A49: 2 | B49: 1 | C49: 1 | D49: 5 | E49: 04 | F49: Proporción de vacaciones no disfrutadas | G49: 0 | H49: 0 | I49: 0 | J49: 0
A50: 2 | B50: 1 | C50: 2 | F50: Sobresueldos | G50: 3344880.2 | H50: 0 | I50: 3344880.2
A51: 2 | B51: 1 | C51: 2 | D51: 1 | F51: Primas por antigüedad | G51: 2707086.2 | H51: 0 | I51: 2707086.2
A52: 2 | B52: 1 | C52: 2 | D52: 1 | E52: 01 | F52: Primas por antigüedad | G52: 2707086.2 | H52: 0 | I52: 2707086.2 | J52: 0.022644526
A53: 2 | B53: 1 | C53: 2 | D53: 2 | F53: Compensación | G53: 637793.99 | H53: 0 | I53: 637793.99
A54: 2 | B54: 1 | C54: 2 | D54: 2 | E54: 01 | F54: Compensación por gastos de alimentación | G54: 0 | H54: 0 | I54: 0 | J54: 0
A55: 2 | B55: 1 | C55: 2 | D55: 2 | E55: 03 | F55: Pago de horas extraordinarias | G55: 0 | H55: 0 | I55: 0 | J55: 0
A56: 2 | B56: 1 | C56: 2 | D56: 2 | E56: 04 | F56: Prima de transporte | G56: 0 | H56: 0 | I56: 0 | J56: 0
A57: 2 | B57: 1 | C57: 2 | D57: 2 | E57: 05 | F57: Compensación servicios de Seguridad | G57: 45000 | H57: 0 | I57: 45000 | J57: 0.00037642085
A58: 2 | B58: 1 | C58: 2 | D58: 2 | E58: 06 | F58: Incentivo por Rendimieto Individual | G58: 0 | H58: 0 | I58: 0 | J58: 0
A59: 2 | B59: 1 | C59: 2 | D59: 2 | E59: 07 | F59: Compensación por distancia | G59: 0 | H59: 0 | I59: 0 | J59: 0
A60: 2 | B60: 1 | C60: 2 | D60: 2 | E60: 08 | F60: Compensaciones especiales | G60: 306200 | H60: 0 | I60: 306200 | J60: 0.0025613348
A61: 2 | B61: 1 | C61: 2 | D61: 2 | E61: 09 | F61: Bono por desempeño a servidores de carrera | G61: 0 | H61: 0 | I61: 0 | J61: 0
A62: 2 | B62: 1 | C62: 2 | D62: 2 | E62: 10 | F62: Compensacion por cumplimiento de indicadores | G62: 286593.99 | H62: 0 | I62: 286593.99 | J62: 0.0023973323
A63: 2 | B63: 1 | C63: 3 | F63: Dietas y Gastos de Representación | G63: 0 | H63: 0 | I63: 0
A64: 2 | B64: 1 | C64: 3 | D64: 1 | F64: Dietas | G64: 0 | H64: 0 | I64: 0
A65: 2 | B65: 1 | C65: 3 | D65: 1 | E65: 01 | F65: Dietas en el país | G65: 0 | H65: 0 | I65: 0 | J65: 0
A66: 2 | B66: 1 | C66: 3 | D66: 1 | E66: 02 | F66: Dietas en el exterior | G66: 0 | H66: 0 | I66: 0 | J66: 0
A67: 2 | B67: 1 | C67: 3 | D67: 2 | F67: Gastos de representación | G67: 0 | H67: 0 | I67: 0
A68: 2 | B68: 1 | C68: 3 | D68: 2 | E68: 01 | F68: Gastos de representación en el país | G68: 0 | H68: 0 | I68: 0 | J68: 0
A69: 2 | B69: 1 | C69: 3 | D69: 2 | E69: 02 | F69: Gastos de representación en el exterior | G69: 0 | H69: 0 | I69: 0 | J69: 0
A70: 2 | B70: 1 | C70: 4 | F70: Gratificaciones y Bonificaciones | G70: 0 | H70: 0 | I70: 0
A71: 2 | B71: 1 | C71: 4 | D71: 1 | F71: Bonificaciones | G71: 0 | H71: 0 | I71: 0
A72: 2 | B72: 1 | C72: 4 | D72: 1 | E72: 01 | F72: Bonificaciones | G72: 0 | H72: 0 | I72: 0 | J72: 0
A73: 2 | B73: 1 | C73: 4 | D73: 2 | F73: Otras Gratificaciones y Bonificaciones | G73: 0 | H73: 0 | I73: 0
A74: 2 | B74: 1 | C74: 4 | D74: 2 | E74: 01 | F74: Bono escolar | G74: 0 | H74: 0 | I74: 0 | J74: 0
A75: 2 | B75: 1 | C75: 4 | D75: 2 | E75: 02 | F75: Gratificaciones por pasantías | G75: 0 | H75: 0 | I75: 0 | J75: 0
A76: 2 | B76: 1 | C76: 4 | D76: 2 | E76: 03 | F76: Gratificaciones por aniversario de institución | G76: 0 | H76: 0 | I76: 0 | J76: 0
A77: 2 | B77: 1 | C77: 5 | F77: Contribuciones a la Seguridad Social y Riesgo Laboral | G77: 9065374.6 | H77: 0 | I77: 9065374.6
A78: 2 | B78: 1 | C78: 5 | D78: 1 | F78: Contribuciones al seguro de salud | G78: 4176955.2 | H78: 0 | I78: 4176955.2
A79: 2 | B79: 1 | C79: 5 | D79: 1 | E79: 01 | F79: Contribuciones al seguro de salud | G79: 4176955.2 | H79: 0 | I79: 4176955.2 | J79: 0.034939845
A80: 2 | B80: 1 | C80: 5 | D80: 2 | F80: Contribuciones al seguro de pensiones | G80: 4182847.5 | H80: 0 | I80: 4182847.5
A81: 2 | B81: 1 | C81: 5 | D81: 2 | E81: 01 | F81: Contribuciones al seguro de pensiones | G81: 4182847.5 | H81: 0 | I81: 4182847.5 | J81: 0.034989133
A82: 2 | B82: 1 | C82: 5 | D82: 3 | F82: Contribuciones al seguro de riesgo laboral | G82: 705571.93 | H82: 0 | I82: 705571.93
A83: 2 | B83: 1 | C83: 5 | D83: 3 | E83: 01 | F83: Contribuciones al seguro de riesgo laboral | G83: 705571.93 | H83: 0 | I83: 705571.93 | J83: 0.0059020441
A84: 2 | B84: 1 | C84: 5 | D84: 4 | F84: Contribuciones al plan de retiro complementario | G84: 0 | H84: 0 | I84: 0
A85: 2 | B85: 1 | C85: 5 | D85: 4 | E85: 01 | F85: Contribuciones al plan de retiro complementario | G85: 0 | H85: 0 | I85: 0 | J85: 0
A86: 2 | B86: 2 | F86: Servicios No Personales | G86: 3509565.8 | H86: 5012155.8 | I86: 8521721.5 | J86: 0.071283414
A87: 2 | B87: 2 | C87: 1 | F87: Servicios Básicos | G87: 60535 | H87: 1781904.1 | I87: 1842439.1
A88: 2 | B88: 2 | C88: 1 | D88: 1 | F88: Radiocomunicación | G88: 0 | H88: 0 | I88: 0
A89: 2 | B89: 2 | C89: 1 | D89: 1 | E89: 01 | F89: Radiocomunicación | G89: 0 | H89: 0 | I89: 0 | J89: 0
A90: 2 | B90: 2 | C90: 1 | D90: 2 | F90: Servicios telefónico de larga distancia | G90: 0 | H90: 0 | I90: 0
A91: 2 | B91: 2 | C91: 1 | D91: 2 | E91: 01 | F91: Servicios telefónico de larga distancia | G91: 0 | H91: 0 | I91: 0 | J91: 0
A92: 2 | B92: 2 | C92: 1 | D92: 3 | F92: Teléfono local | G92: 0 | H92: 211904.05 | I92: 211904.05
A93: 2 | B93: 2 | C93: 1 | D93: 3 | E93: 01 | F93: Teléfono local | G93: 0 | H93: 211904.05 | I93: 211904.05 | J93: 0.0017725578
A94: 2 | B94: 2 | C94: 1 | D94: 4 | F94: Telefax y correos | G94: 0 | H94: 0 | I94: 0
A95: 2 | B95: 2 | C95: 1 | D95: 4 | E95: 01 | F95: Telefax y correos | G95: 0 | H95: 0 | I95: 0 | J95: 0
A96: 2 | B96: 2 | C96: 1 | D96: 5 | F96: Servicio de Internet y televisión por cable | G96: 0 | H96: 0 | I96: 0
A97: 2 | B97: 2 | C97: 1 | D97: 5 | E97: 01 | F97: Servicio de Internet y televisión por cable | G97: 0 | H97: 0 | I97: 0 | J97: 0
A98: 2 | B98: 2 | C98: 1 | D98: 6 | F98: Electricidad | G98: 0 | H98: 0 | I98: 0
A99: 2 | B99: 2 | C99: 1 | D99: 6 | E99: 01 | F99: Energía eléctrica | G99: 0 | H99: 0 | I99: 0 | J99: 0
A100: 2 | B100: 2 | C100: 1 | D100: 6 | E100: 02 | F100: Electricidad no cortable | G100: 0 | H100: 0 | I100: 0 | J100: 0
A101: 2 | B101: 2 | C101: 1 | D101: 7 | F101: Agua | G101: 60535 | H101: 0 | I101: 60535
A102: 2 | B102: 2 | C102: 1 | D102: 7 | E102: 01 | F102: Agua | G102: 60535 | H102: 0 | I102: 60535 | J102: 0.00050636969
...

Sheet OCTUBRE 
A1: Form. No.6 SRS
A3: Servicio Nacional de Salud
A4: Dirección de Fizcalización
A5: Consolidado de Ingresos y Gastos por Fuente de Financiamiento
A6: HOSPITAL MATERNO INFANTIL SAN LORENZO DE LOS MINA
A7: OCTUBRE 2025
C8: Ingresos Generales:
E9: 1.- Balance Inicial / Fuente:
E10: Anticipo Financiero | H10: Otros Aportes
E11: Transferencias Corrientes
E12: Venta de Servicios | G12: 209079.81
E13: 2.- Ingresos por Fuente / Cuenta
E14: Anticipo Financiero | H14: Otros Aportes
E15: Transferencias Corrientes | G15: =+'[4]INGR SEGUN ORIGEN'!E12 -> 1.0607056e+08 | H15: Aportes Nomina SNS
E16: Venta de Servicios | G16: =+'[4]INGR SEGUN ORIGEN'!E27+'[4]INGR SEGUN ORIGEN'!E34 -> 8172161.3
H17: TOTAL INGRESOS RDS | I17: =+G10+G11+G12+I10+G14+G15+G16+I14+I15 -> 1.144518e+08
A21: 1 | F21: 2 | G21: 3 | I21: 4 | J21: 5
A22: Código Presupuestario | F22: Descripción Gasto por Cuenta | G22: Distribución del Gasto por Fuente de Financiamiento | I22: TOTAL | J22: %
A23: Tipo | B23: Objeto | C23: Cuenta | D23: Sub-Cuenta | E23: Auxiliar | G23: Fondo 100 | H23: Venta de Servicios/ Otros Aportes
A25: 2 | F25: Gastos | G25: =+G26+G87+G212+G330+G336+G463 -> 1.0911345e+08 | H25: =+H26+H87+H212+H330+H336+H463 -> 8161061 | I25: =SUM(G25:H25) -> 1.1727451e+08 | J25: =+J26+J87+J212+J330+J336+J463 -> 1
A26: 2 | B26: 1 | F26: Servicios Personales | G26: =+G27+G51+G64+G71+G78 -> 72986847 | H26: =+H27+H51+H64+H71+H78 -> 0 | I26: =SUM(G26:H26) -> 72986847 | J26: =I26/$I$25 -> 0.62235902
A27: 2 | B27: 1 | C27: 1 | F27: Remuneraciones | G27: =+G28+G35+G42+G44+G46 -> 60398098 | H27: =+H28+H35+H42+H44+H46 -> 0 | I27: =SUM(G27:H27) -> 60398098
A28: 2 | B28: 1 | C28: 1 | D28: 1 | F28: Remuneraciones al personal fijo | G28: =SUM(G29:G34) -> 59105567 | H28: =SUM(H29:H34) -> 0 | I28: =SUM(G28:H28) -> 59105567
A29: 2 | B29: 1 | C29: 1 | D29: 1 | E29: 01 | F29: Sueldos a empleados fijos | G29: ='[4]CUENTA T FONDO 100'!A126 -> 59105567 | H29: ='[4]CUENTA T VS'!A75 -> 0 | I29: =SUM(G29:H29) -> 59105567 | J29: =I29/$I$25 -> 0.50399331
A30: 2 | B30: 1 | C30: 1 | D30: 1 | E30: 02 | F30: Sueldos a médicos | G30: ='[4]CUENTA T FONDO 100'!B126 -> 0 | H30: ='[4]CUENTA T VS'!B75 -> 0 | I30: =SUM(G30:H30) -> 0 | J30: =I30/$I$25 -> 0
A31: 2 | B31: 1 | C31: 1 | D31: 1 | E31: 03 | F31: Ascensos a militares | G31: ='[4]CUENTA T FONDO 100'!C126 -> 0 | H31: ='[4]CUENTA T VS'!C75 -> 0 | I31: =SUM(G31:H31) -> 0 | J31: =I31/$I$25 -> 0
A32: 2 | B32: 1 | C32: 1 | D32: 1 | E32: 04 | F32: Nuevas plazas maestros | G32: ='[4]CUENTA T FONDO 100'!D126 -> 0 | H32: ='[4]CUENTA T VS'!D75 -> 0 | I32: =SUM(G32:H32) -> 0 | J32: =I32/$I$25 -> 0
A33: 2 | B33: 1 | C33: 1 | D33: 1 | E33: 05 | F33: Incentivos y escalafón | G33: ='[4]CUENTA T FONDO 100'!E126 -> 0 | H33: ='[4]CUENTA T VS'!E75 -> 0 | I33: =SUM(G33:H33) -> 0 | J33: =I33/$I$25 -> 0
A34: 2 | B34: 1 | C34: 1 | D34: 1 | E34: 06 | F34: Nuevas plazas a médicos | G34: ='[4]CUENTA T FONDO 100'!F126 -> 0 | H34: ='[4]CUENTA T VS'!F75 -> 0 | I34: =SUM(G34:H34) -> 0 | J34: =I34/$I$25 -> 0
A35: 2 | B35: 1 | C35: 1 | D35: 2 | F35: Remuneraciones al personal con carácter transitorio | G35: =SUM(G36:G41) -> 1292531 | H35: =SUM(H36:H41) -> 0 | I35: =SUM(G35:H35) -> 1292531
A36: 2 | B36: 1 | C36: 1 | D36: 2 | E36: 03 | F36: Suplencias | G36: ='[4]CUENTA T FONDO 100'!G126 -> 0 | H36: ='[4]CUENTA T VS'!G75 -> 0 | I36: =SUM(G36:H36) -> 0 | J36: =I36/$I$25 -> 0
A37: 2 | B37: 1 | C37: 1 | D37: 2 | E37: 05 | F37: Sueldo al personal nominal en período probatorio | G37: ='[4]CUENTA T FONDO 100'!H126 -> 0 | H37: ='[4]CUENTA T VS'!H75 -> 0 | I37: =SUM(G37:H37) -> 0 | J37: =I37/$I$25 -> 0
A38: 2 | B38: 1 | C38: 1 | D38: 2 | E38: 06 | F38: Jornales | G38: ='[4]CUENTA T FONDO 100'!I126 -> 0 | H38: ='[4]CUENTA T VS'!I75 -> 0 | I38: =SUM(G38:H38) -> 0 | J38: =I38/$I$25 -> 0
A39: 2 | B39: 1 | C39: 1 | D39: 2 | E39: 08 | F39: Empleados temporales | G39: ='[4]CUENTA T FONDO 100'!J126 -> 1292531 | H39: ='[4]CUENTA T VS'!J75 -> 0 | I39: =SUM(G39:H39) -> 1292531 | J39: =I39/$I$25 -> 0.011021415
A40: 2 | B40: 1 | C40: 1 | D40: 2 | E40: 09 | F40: Personal de carácter eventual | G40: ='[4]CUENTA T FONDO 100'!K126 -> 0 | H40: ='[4]CUENTA T VS'!K75 -> 0 | I40: =SUM(G40:H40) -> 0 | J40: =I40/$I$25 -> 0
A41: 2 | B41: 1 | C41: 1 | D41: 2 | E41: 11 | F41: Interinato | G41: ='[4]CUENTA T FONDO 100'!L126 -> 0 | H41: ='[4]CUENTA T VS'!L75 -> 0 | I41: =SUM(G41:H41) -> 0 | J41: =I41/$I$25 -> 0
A42: 2 | B42: 1 | C42: 1 | D42: 3 | F42: Sueldos al personal fijo en trámite de pensiones | G42: =SUM(G43) -> 0 | H42: =SUM(H43) -> 0 | I42: =SUM(G42:H42) -> 0
A43: 2 | B43: 1 | C43: 1 | D43: 3 | E43: 01 | F43: Sueldos al personal fijo en trámite de pensiones | G43: ='[4]CUENTA T FONDO 100'!M126 -> 0 | H43: ='[4]CUENTA T VS'!M75 -> 0 | I43: =SUM(G43:H43) -> 0 | J43: =I43/$I$25 -> 0
A44: 2 | B44: 1 | C44: 1 | D44: 4 | F44: Sueldo anual no. 13 | G44: =SUM(G45) -> 0 | H44: =SUM(H45) -> 0 | I44: =SUM(G44:H44) -> 0
A45: 2 | B45: 1 | C45: 1 | D45: 4 | E45: 01 | F45: Sueldo anual no. 13 | G45: ='[4]CUENTA T FONDO 100'!N126 -> 0 | H45: ='[4]CUENTA T VS'!N75 -> 0 | I45: =SUM(G45:H45) -> 0 | J45: =I45/$I$25 -> 0
A46: 2 | B46: 1 | C46: 1 | D46: 5 | F46: Prestaciones económinas | G46: =SUM(G47:G50) -> 0 | H46: =SUM(H47:H50) -> 0 | I46: =SUM(G46:H46) -> 0
A47: 2 | B47: 1 | C47: 1 | D47: 5 | E47: 01 | F47: Prestaciones económinas | G47: ='[4]CUENTA T FONDO 100'!O126 -> 0 | H47: ='[4]CUENTA T VS'!O75 -> 0 | I47: =SUM(G47:H47) -> 0 | J47: =I47/$I$25 -> 0
A48: 2 | B48: 1 | C48: 1 | D48: 5 | E48: 02 | F48: Pago de porcentaje por desvinculación de cargo | G48: ='[4]CUENTA T FONDO 100'!P126 -> 0 | H48: ='[4]CUENTA T VS'!P75 -> 0 | I48: =SUM(G48:H48) -> 0 | J48: =I48/$I$25 -> 0
A49: 2 | B49: 1 | C49: 1 | D49: 5 | E49: 03 | F49: Prestación laboral por desvinculación | G49: ='[4]CUENTA T FONDO 100'!Q126 -> 0 | H49: ='[4]CUENTA T VS'!Q75 -> 0 | I49: =SUM(G49:H49) -> 0 | J49: =I49/$I$25 -> 0
A50: 2 | B50: 1 | C50: 1 | D50: 5 | E50: 04 | F50: Proporción de vacaciones no disfrutadas | G50: ='[4]CUENTA T FONDO 100'!R126 -> 0 | H50: ='[4]CUENTA T VS'!R75 -> 0 | I50: =SUM(G50:H50) -> 0 | J50: =I50/$I$25 -> 0
A51: 2 | B51: 1 | C51: 2 | F51: Sobresueldos | G51: =+G52+G54 -> 3295047.1 | H51: =+H52+H54 -> 0 | I51: =SUM(G51:H51) -> 3295047.1
A52: 2 | B52: 1 | C52: 2 | D52: 1 | F52: Primas por antigüedad | G52: =SUM(G53) -> 2702311.6 | H52: =SUM(H53) -> 0 | I52: =SUM(G52:H52) -> 2702311.6
A53: 2 | B53: 1 | C53: 2 | D53: 1 | E53: 01 | F53: Primas por antigüedad | G53: ='[4]CUENTA T FONDO 100'!S126 -> 2702311.6 | H53: ='[4]CUENTA T VS'!S75 -> 0 | I53: =SUM(G53:H53) -> 2702311.6 | J53: =I53/$I$25 -> 0.023042617
A54: 2 | B54: 1 | C54: 2 | D54: 2 | F54: Compensación | G54: =SUM(G55:G63) -> 592735.52 | H54: =SUM(H55:H63) -> 0 | I54: =SUM(G54:H54) -> 592735.52
A55: 2 | B55: 1 | C55: 2 | D55: 2 | E55: 01 | F55: Compensación por gastos de alimentación | G55: ='[4]CUENTA T FONDO 100'!T126 -> 0 | H55: ='[4]CUENTA T VS'!T75 -> 0 | I55: =SUM(G55:H55) -> 0 | J55: =I55/$I$25 -> 0
A56: 2 | B56: 1 | C56: 2 | D56: 2 | E56: 03 | F56: Pago de horas extraordinarias | G56: ='[4]CUENTA T FONDO 100'!U126 -> 0 | H56: ='[4]CUENTA T VS'!U75 -> 0 | I56: =SUM(G56:H56) -> 0 | J56: =I56/$I$25 -> 0
A57: 2 | B57: 1 | C57: 2 | D57: 2 | E57: 04 | F57: Prima de transporte | G57: ='[4]CUENTA T FONDO 100'!V126 -> 0 | H57: ='[4]CUENTA T VS'!V75 -> 0 | I57: =SUM(G57:H57) -> 0 | J57: =I57/$I$25 -> 0
A58: 2 | B58: 1 | C58: 2 | D58: 2 | E58: 05 | F58: Compensación servicios de Seguridad | G58: ='[4]CUENTA T FONDO 100'!W126 -> 45000 | H58: ='[4]CUENTA T VS'!W75 -> 0 | I58: =SUM(G58:H58) -> 45000 | J58: =I58/$I$25 -> 0.0003837151
A59: 2 | B59: 1 | C59: 2 | D59: 2 | E59: 06 | F59: Incentivo por Rendimieto Individual | G59: ='[4]CUENTA T FONDO 100'!X126 -> 0 | H59: ='[4]CUENTA T VS'!X75 -> 0 | I59: =SUM(G59:H59) -> 0 | J59: =I59/$I$25 -> 0
A60: 2 | B60: 1 | C60: 2 | D60: 2 | E60: 07 | F60: Compensación por distancia | G60: ='[4]CUENTA T FONDO 100'!Y126 -> 0 | H60: ='[4]CUENTA T VS'!Y75 -> 0 | I60: =SUM(G60:H60) -> 0 | J60: =I60/$I$25 -> 0
A61: 2 | B61: 1 | C61: 2 | D61: 2 | E61: 08 | F61: Compensaciones especiales | G61: ='[4]CUENTA T FONDO 100'!Z126 -> 278000 | H61: ='[4]CUENTA T VS'!Z75 -> 0 | I61: =SUM(G61:H61) -> 278000 | J61: =I61/$I$25 -> 0.0023705066
A62: 2 | B62: 1 | C62: 2 | D62: 2 | E62: 09 | F62: Bono por desempeño a servidores de carrera | G62: ='[4]CUENTA T FONDO 100'!AA126 -> 0 | H62: ='[4]CUENTA T VS'!AA75 -> 0 | I62: =SUM(G62:H62) -> 0 | J62: =I62/$I$25 -> 0
A63: 2 | B63: 1 | C63: 2 | D63: 2 | E63: 10 | F63: Compensacion por cumplimiento de indicadores | G63: ='[4]CUENTA T FONDO 100'!AB126 -> 269735.52 | H63: ='[4]CUENTA T VS'!AB75 -> 0 | I63: =SUM(G63:H63) -> 269735.52 | J63: =I63/$I$25 -> 0.0023000354
A64: 2 | B64: 1 | C64: 3 | F64: Dietas y Gastos de Representación | G64: =+G65+G68 -> 0 | H64: =+H65+H68 -> 0 | I64: =SUM(G64:H64) -> 0
A65: 2 | B65: 1 | C65: 3 | D65: 1 | F65: Dietas | G65: =SUM(G66:G67) -> 0 | H65: =SUM(H66:H67) -> 0 | I65: =SUM(G65:H65) -> 0
A66: 2 | B66: 1 | C66: 3 | D66: 1 | E66: 01 | F66: Dietas en el país | G66: ='[4]CUENTA T FONDO 100'!AC126 -> 0 | H66: ='[4]CUENTA T VS'!AC75 -> 0 | I66: =SUM(G66:H66) -> 0 | J66: =I66/$I$25 -> 0
A67: 2 | B67: 1 | C67: 3 | D67: 1 | E67: 02 | F67: Dietas en el exterior | G67: ='[4]CUENTA T FONDO 100'!AD126 -> 0 | H67: ='[4]CUENTA T VS'!AD75 -> 0 | I67: =SUM(G67:H67) -> 0 | J67: =I67/$I$25 -> 0
A68: 2 | B68: 1 | C68: 3 | D68: 2 | F68: Gastos de representación | G68: =SUM(G69:G70) -> 0 | H68: =SUM(H69:H70) -> 0 | I68: =SUM(G68:H68) -> 0
A69: 2 | B69: 1 | C69: 3 | D69: 2 | E69: 01 | F69: Gastos de representación en el país | G69: ='[4]CUENTA T FONDO 100'!AE126 -> 0 | H69: ='[4]CUENTA T VS'!AE75 -> 0 | I69: =SUM(G69:H69) -> 0 | J69: =I69/$I$25 -> 0
A70: 2 | B70: 1 | C70: 3 | D70: 2 | E70: 02 | F70: Gastos de representación en el exterior | G70: ='[4]CUENTA T FONDO 100'!AF126 -> 0 | H70: ='[4]CUENTA T VS'!AF75 -> 0 | I70: =SUM(G70:H70) -> 0 | J70: =I70/$I$25 -> 0
A71: 2 | B71: 1 | C71: 4 | F71: Gratificaciones y Bonificaciones | G71: =+G72+G74 -> 0 | H71: =+H72+H74 -> 0 | I71: =SUM(G71:H71) -> 0
A72: 2 | B72: 1 | C72: 4 | D72: 1 | F72: Bonificaciones | G72: =SUM(G73) -> 0 | H72: =SUM(H73) -> 0 | I72: =SUM(G72:H72) -> 0
A73: 2 | B73: 1 | C73: 4 | D73: 1 | E73: 01 | F73: Bonificaciones | G73: ='[4]CUENTA T FONDO 100'!AG126 -> 0 | H73: ='[4]CUENTA T VS'!AG75 -> 0 | I73: =SUM(G73:H73) -> 0 | J73: =I73/$I$25 -> 0
A74: 2 | B74: 1 | C74: 4 | D74: 2 | F74: Otras Gratificaciones y Bonificaciones | G74: =SUM(G75:G77) -> 0 | H74: =SUM(H75:H77) -> 0 | I74: =SUM(G74:H74) -> 0
A75: 2 | B75: 1 | C75: 4 | D75: 2 | E75: 01 | F75: Bono escolar | G75: ='[4]CUENTA T FONDO 100'!AH126 -> 0 | H75: ='[4]CUENTA T VS'!AH75 -> 0 | I75: =SUM(G75:H75) -> 0 | J75: =I75/$I$25 -> 0
A76: 2 | B76: 1 | C76: 4 | D76: 2 | E76: 02 | F76: Gratificaciones por pasantías | G76: ='[4]CUENTA T FONDO 100'!AI126 -> 0 | H76: ='[4]CUENTA T VS'!AI75 -> 0 | I76: =SUM(G76:H76) -> 0 | J76: =I76/$I$25 -> 0
A77: 2 | B77: 1 | C77: 4 | D77: 2 | E77: 03 | F77: Gratificaciones por aniversario de institución | G77: ='[4]CUENTA T FONDO 100'!AJ126 -> 0 | H77: ='[4]CUENTA T VS'!AJ75 -> 0 | I77: =SUM(G77:H77) -> 0 | J77: =I77/$I$25 -> 0
A78: 2 | B78: 1 | C78: 5 | F78: Contribuciones a la Seguridad Social y Riesgo Laboral | G78: =+G79+G81+G83+G85 -> 9293701.9 | H78: =+H79+H81+H83+H85 -> 0 | I78: =SUM(G78:H78) -> 9293701.9
A79: 2 | B79: 1 | C79: 5 | D79: 1 | F79: Contribuciones al seguro de salud | G79: =SUM(G80) -> 4282225.9 | H79: =SUM(H80) -> 0 | I79: =SUM(G79:H79) -> 4282225.9
A80: 2 | B80: 1 | C80: 5 | D80: 1 | E80: 01 | F80: Contribuciones al seguro de salud | G80: ='[4]CUENTA T FONDO 100'!AK126 -> 4282225.9 | H80: ='[4]CUENTA T VS'!AK75 -> 0 | I80: =SUM(G80:H80) -> 4282225.9 | J80: =I80/$I$25 -> 0.03651455
A81: 2 | B81: 1 | C81: 5 | D81: 2 | F81: Contribuciones al seguro de pensiones | G81: =SUM(G82) -> 4288266.7 | H81: =SUM(H82) -> 0 | I81: =SUM(G81:H81) -> 4288266.7
A82: 2 | B82: 1 | C82: 5 | D82: 2 | E82: 01 | F82: Contribuciones al seguro de pensiones | G82: ='[4]CUENTA T FONDO 100'!AL126 -> 4288266.7 | H82: ='[4]CUENTA T VS'!AL75 -> 0 | I82: =SUM(G82:H82) -> 4288266.7 | J82: =I82/$I$25 -> 0.03656606
A83: 2 | B83: 1 | C83: 5 | D83: 3 | F83: Contribuciones al seguro de riesgo laboral | G83: =SUM(G84) -> 723209.27 | H83: =SUM(H84) -> 0 | I83: =SUM(G83:H83) -> 723209.27
A84: 2 | B84: 1 | C84: 5 | D84: 3 | E84: 01 | F84: Contribuciones al seguro de riesgo laboral | G84: ='[4]CUENTA T FONDO 100'!AM126 -> 723209.27 | H84: ='[4]CUENTA T VS'!AM75 -> 0 | I84: =SUM(G84:H84) -> 723209.27 | J84: =I84/$I$25 -> 0.0061668071
A85: 2 | B85: 1 | C85: 5 | D85: 4 | F85: Contribuciones al plan de retiro complementario | G85: =SUM(G86) -> 0 | H85: =SUM(H86) -> 0 | I85: =SUM(G85:H85) -> 0
A86: 2 | B86: 1 | C86: 5 | D86: 4 | E86: 01 | F86: Contribuciones al plan de retiro complementario | G86: ='[4]CUENTA T FONDO 100'!AN126 -> 0 | H86: ='[4]CUENTA T VS'!AN75 -> 0 | I86: =SUM(G86:H86) -> 0 | J86: =I86/$I$25 -> 0
A87: 2 | B87: 2 | F87: Servicios No Personales | G87: =G88+G106+G111+G116+G125+G148+G157+G179+G208 -> 792898.06 | H87: =H88+H106+H111+H116+H125+H148+H157+H179+H208 -> 1964841.4 | I87: =SUM(G87:H87) -> 2757739.5 | J87: =I87/$I$25 -> 0.023515251
A88: 2 | B88: 2 | C88: 1 | F88: Servicios Básicos | G88: =+G89+G91+G93+G95+G97+G99+G102+G104 -> 60535 | H88: =+H89+H91+H93+H95+H97+H99+H102+H104 -> 1168099.9 | I88: =SUM(G88:H88) -> 1228634.9
A89: 2 | B89: 2 | C89: 1 | D89: 1 | F89: Radiocomunicación | G89: =SUM(G90) -> 0 | H89: =SUM(H90) -> 0 | I89: =SUM(G89:H89) -> 0
A90: 2 | B90: 2 | C90: 1 | D90: 1 | E90: 01 | F90: Radiocomunicación | G90: ='[4]CUENTA T FONDO 100'!AO126 -> 0 | H90: ='[4]CUENTA T VS'!AO75 -> 0 | I90: =SUM(G90:H90) -> 0 | J90: =I90/$I$25 -> 0
A91: 2 | B91: 2 | C91: 1 | D91: 2 | F91: Servicios telefónico de larga distancia | G91: =SUM(G92) -> 0 | H91: =SUM(H92) -> 0 | I91: =SUM(G91:H91) -> 0
A92: 2 | B92: 2 | C92: 1 | D92: 2 | E92: 01 | F92: Servicios telefónico de larga distancia | G92: ='[4]CUENTA T FONDO 100'!AP126 -> 0 | H92: ='[4]CUENTA T VS'!AP75 -> 0 | I92: =SUM(G92:H92) -> 0 | J92: =I92/$I$25 -> 0
A93: 2 | B93: 2 | C93: 1 | D93: 3 | F93: Teléfono local | G93: =SUM(G94) -> 0 | H93: =SUM(H94) -> 423099.93 | I93: =SUM(G93:H93) -> 423099.93
A94: 2 | B94: 2 | C94: 1 | D94: 3 | E94: 01 | F94: Teléfono local | G94: ='[4]CUENTA T FONDO 100'!AQ126 -> 0 | H94: ='[4]CUENTA T VS'!AQ75 -> 423099.93 | I94: =SUM(G94:H94) -> 423099.93 | J94: =I94/$I$25 -> 0.0036077741
A95: 2 | B95: 2 | C95: 1 | D95: 4 | F95: Telefax y correos | G95: =SUM(G96) -> 0 | H95: =SUM(H96) -> 0 | I95: =SUM(G95:H95) -> 0
A96: 2 | B96: 2 | C96: 1 | D96: 4 | E96: 01 | F96: Telefax y correos | G96: ='[4]CUENTA T FONDO 100'!AR126 -> 0 | H96: ='[4]CUENTA T VS'!AR75 -> 0 | I96: =SUM(G96:H96) -> 0 | J96: =I96/$I$25 -> 0
A97: 2 | B97: 2 | C97: 1 | D97: 5 | F97: Servicio de Internet y televisión por cable | G97: =SUM(G98) -> 0 | H97: =SUM(H98) -> 0 | I97: =SUM(G97:H97) -> 0
A98: 2 | B98: 2 | C98: 1 | D98: 5 | E98: 01 | F98: Servicio de Internet y televisión por cable | G98: ='[4]CUENTA T FONDO 100'!AS126 -> 0 | H98: ='[4]CUENTA T VS'!AS75 -> 0 | I98: =SUM(G98:H98) -> 0 | J98: =I98/$I$25 -> 0
A99: 2 | B99: 2 | C99: 1 | D99: 6 | F99: Electricidad | G99: =SUM(G100:G101) -> 0 | H99: =SUM(H100:H101) -> 0 | I99: =SUM(G99:H99) -> 0
A100: 2 | B100: 2 | C100: 1 | D100: 6 | E100: 01 | F100: Energía eléctrica | G100: ='[4]CUENTA T FONDO 100'!AT126 -> 0 | H100: ='[4]CUENTA T VS'!AT75 -> 0 | I100: =SUM(G100:H100) -> 0 | J100: =I100/$I$25 -> 0
A101: 2 | B101: 2 | C101: 1 | D101: 6 | E101: 02 | F101: Electricidad no cortable | G101: ='[4]CUENTA T FONDO 100'!AU126 -> 0 | H101: ='[4]CUENTA T VS'!AU75 -> 0 | I101: =SUM(G101:H101) -> 0 | J101: =I101/$I$25 -> 0
A102: 2 | B102: 2 | C102: 1 | D102: 7 | F102: Agua | G102: =SUM(G103) -> 60535 | H102: =SUM(H103) -> 0 | I102: =SUM(G102:H102) -> 60535
A103: 2 | B103: 2 | C103: 1 | D103: 7 | E103: 01 | F103: Agua | G103: ='[4]CUENTA T FONDO 100'!AV126 -> 60535 | H103: ='[4]CUENTA T VS'!AV75 -> 0 | I103: =SUM(G103:H103) -> 60535 | J103: =I103/$I$25 -> 0.00051618209
A104: 2 | B104: 2 | C104: 1 | D104: 8 | F104: Recolección de residuos sólidos | G104: =SUM(G105) -> 0 | H104: =SUM(H105) -> 745000 | I104: =SUM(G104:H104) -> 745000
A105: 2 | B105: 2 | C105: 1 | D105: 8 | E105: 01 | F105: Recolección de residuos sólidos | G105: ='[4]CUENTA T FONDO 100'!AW126 -> 0 | H105: ='[4]CUENTA T VS'!AW75 -> 745000 | I105: =SUM(G105:H105) -> 745000 | J105: =I105/$I$25 -> 0.0063526167
...

Sheet NOVIEMBRE
A1: Form. No.6 SRS
A3: Servicio Nacional de Salud
A4: Dirección de Fizcalización
A5: Consolidado de Ingresos y Gastos por Fuente de Financiamiento
A6: HOSPITAL MATERNO INFANTIL SAN LORENZO DE LOS MINA
A7: OCTUBRE 2025
C8: Ingresos Generales:
E9: 1.- Balance Inicial / Fuente:
E10: Anticipo Financiero | H10: Otros Aportes | L10: Contraseña: 0001
E11: Transferencias Corrientes
E12: Venta de Servicios | G12: 5363379
E13: 2.- Ingresos por Fuente / Cuenta
E14: Anticipo Financiero | H14: Otros Aportes | L14: OBJETAL | M14: FR | N14: VS
E15: Transferencias Corrientes | G15: =+'[7]INGR SEGUN ORIGEN'!E12 -> 1.5626822e+08 | H15: Aportes Nomina SNS | L15: 2.1 | M15: =G26 -> 1.3374081e+08 | N15: =H26 -> 0
E16: Venta de Servicios | G16: =+'[7]INGR SEGUN ORIGEN'!E35+'[7]INGR SEGUN ORIGEN'!E42 -> 9309369.1 | L16: 2.2 | M16: =G87 -> 1896797.1 | N16: =H87 -> 2083820.5
H17: TOTAL INGRESOS RDS | I17: =+G10+G11+G12+I10+G14+G15+G16+I14+I15 -> 1.7094097e+08 | L17: 2.3 | M17: ='[7]CONS. FUENTES FINAN'!G212 -> 13779851 | N17: ='[7]CONS. FUENTES FINAN'!H212 -> 2184325.9
L18: 2.4 | M18: =G330 -> 0 | N18: =H330 -> 3600
L19: 2.6 | M19: =G336 -> 8010447.3 | N19: =H336 -> 2755244.7
L20: 2.7 | M20: ='[7]CONS. FUENTES FINAN'!G463 -> 0 | N20: ='[7]CONS. FUENTES FINAN'!H463 -> 0
A21: 1 | F21: 2 | G21: 3 | I21: 4 | J21: 5
A22: Código Presupuestario | F22: Descripción Gasto por Cuenta | G22: Distribución del Gasto por Fuente de Financiamiento | I22: TOTAL | J22: %
A23: Tipo | B23: Objeto | C23: Cuenta | D23: Sub-Cuenta | E23: Auxiliar | G23: Fondo 100 | H23: Venta de Servicios/ Otros Aportes
A25: 2 | F25: Gastos | G25: =+G26+G87+G212+G330+G336+G463 -> 157427908 | H25: =+H26+H87+H212+H330+H336+H463 -> 7026991.1 | I25: =SUM(G25:H25) -> 1.644549e+08 | J25: =+J26+J87+J212+J330+J336+J463 -> 1
A26: 2 | B26: 1 | F26: Servicios Personales | G26: =+G27+G51+G64+G71+G78 -> 1.3374081e+08 | H26: =+H27+H51+H64+H71+H78 -> 0 | I26: =SUM(G26:H26) -> 1.3374081e+08 | J26: =I26/$I$25 -> 0.81323702
A27: 2 | B27: 1 | C27: 1 | F27: Remuneraciones | G27: =+G28+G35+G42+G44+G46 -> 1.2113301e+08 | H27: =+H28+H35+H42+H44+H46 -> 0 | I27: =SUM(G27:H27) -> 1.2113301e+08
A28: 2 | B28: 1 | C28: 1 | D28: 1 | F28: Remuneraciones al personal fijo | G28: =SUM(G29:G34) -> 59046800 | H28: =SUM(H29:H34) -> 0 | I28: =SUM(G28:H28) -> 59046800
A29: 2 | B29: 1 | C29: 1 | D29: 1 | E29: 01 | F29: Sueldos a empleados fijos | G29: ='[7]CUENTA T FONDO 100'!A97 -> 59046800 | H29: ='[7]CUENTA T VS'!A75 -> 0 | I29: =SUM(G29:H29) -> 59046800 | J29: =I29/$I$25 -> 0.35904555
A30: 2 | B30: 1 | C30: 1 | D30: 1 | E30: 02 | F30: Sueldos a médicos | G30: ='[7]CUENTA T FONDO 100'!B97 -> 0 | H30: ='[7]CUENTA T VS'!B75 -> 0 | I30: =SUM(G30:H30) -> 0 | J30: =I30/$I$25 -> 0
A31: 2 | B31: 1 | C31: 1 | D31: 1 | E31: 03 | F31: Ascensos a militares | G31: ='[7]CUENTA T FONDO 100'!C97 -> 0 | H31: ='[7]CUENTA T VS'!C75 -> 0 | I31: =SUM(G31:H31) -> 0 | J31: =I31/$I$25 -> 0
A32: 2 | B32: 1 | C32: 1 | D32: 1 | E32: 04 | F32: Nuevas plazas maestros | G32: ='[7]CUENTA T FONDO 100'!D97 -> 0 | H32: ='[7]CUENTA T VS'!D75 -> 0 | I32: =SUM(G32:H32) -> 0 | J32: =I32/$I$25 -> 0
A33: 2 | B33: 1 | C33: 1 | D33: 1 | E33: 05 | F33: Incentivos y escalafón | G33: ='[7]CUENTA T FONDO 100'!E97 -> 0 | H33: ='[7]CUENTA T VS'!E75 -> 0 | I33: =SUM(G33:H33) -> 0 | J33: =I33/$I$25 -> 0
A34: 2 | B34: 1 | C34: 1 | D34: 1 | E34: 06 | F34: Nuevas plazas a médicos | G34: ='[7]CUENTA T FONDO 100'!F97 -> 0 | H34: ='[7]CUENTA T VS'!F75 -> 0 | I34: =SUM(G34:H34) -> 0 | J34: =I34/$I$25 -> 0
A35: 2 | B35: 1 | C35: 1 | D35: 2 | F35: Remuneraciones al personal con carácter transitorio | G35: =SUM(G36:G41) -> 1342531 | H35: =SUM(H36:H41) -> 0 | I35: =SUM(G35:H35) -> 1342531
A36: 2 | B36: 1 | C36: 1 | D36: 2 | E36: 03 | F36: Suplencias | G36: ='[7]CUENTA T FONDO 100'!G97 -> 0 | H36: ='[7]CUENTA T VS'!G75 -> 0 | I36: =SUM(G36:H36) -> 0 | J36: =I36/$I$25 -> 0
A37: 2 | B37: 1 | C37: 1 | D37: 2 | E37: 05 | F37: Sueldo al personal nominal en período probatorio | G37: ='[7]CUENTA T FONDO 100'!H97 -> 0 | H37: ='[7]CUENTA T VS'!H75 -> 0 | I37: =SUM(G37:H37) -> 0 | J37: =I37/$I$25 -> 0
A38: 2 | B38: 1 | C38: 1 | D38: 2 | E38: 06 | F38: Jornales | G38: ='[7]CUENTA T FONDO 100'!I97 -> 0 | H38: ='[7]CUENTA T VS'!I75 -> 0 | I38: =SUM(G38:H38) -> 0 | J38: =I38/$I$25 -> 0
A39: 2 | B39: 1 | C39: 1 | D39: 2 | E39: 08 | F39: Empleados temporales | G39: ='[7]CUENTA T FONDO 100'!J97 -> 1342531 | H39: ='[7]CUENTA T VS'!J75 -> 0 | I39: =SUM(G39:H39) -> 1342531 | J39: =I39/$I$25 -> 0.008163521
A40: 2 | B40: 1 | C40: 1 | D40: 2 | E40: 09 | F40: Personal de carácter eventual | G40: ='[7]CUENTA T FONDO 100'!K97 -> 0 | H40: ='[7]CUENTA T VS'!K75 -> 0 | I40: =SUM(G40:H40) -> 0 | J40: =I40/$I$25 -> 0
A41: 2 | B41: 1 | C41: 1 | D41: 2 | E41: 11 | F41: Interinato | G41: ='[7]CUENTA T FONDO 100'!L97 -> 0 | H41: ='[7]CUENTA T VS'!L75 -> 0 | I41: =SUM(G41:H41) -> 0 | J41: =I41/$I$25 -> 0
A42: 2 | B42: 1 | C42: 1 | D42: 3 | F42: Sueldos al personal fijo en trámite de pensiones | G42: =SUM(G43) -> 0 | H42: =SUM(H43) -> 0 | I42: =SUM(G42:H42) -> 0
A43: 2 | B43: 1 | C43: 1 | D43: 3 | E43: 01 | F43: Sueldos al personal fijo en trámite de pensiones | G43: ='[7]CUENTA T FONDO 100'!M97 -> 0 | H43: ='[7]CUENTA T VS'!M75 -> 0 | I43: =SUM(G43:H43) -> 0 | J43: =I43/$I$25 -> 0
A44: 2 | B44: 1 | C44: 1 | D44: 4 | F44: Sueldo anual no. 13 | G44: =SUM(G45) -> 60212859 | H44: =SUM(H45) -> 0 | I44: =SUM(G44:H44) -> 60212859
A45: 2 | B45: 1 | C45: 1 | D45: 4 | E45: 01 | F45: Sueldo anual no. 13 | G45: ='[7]CUENTA T FONDO 100'!N97 -> 60212859 | H45: ='[7]CUENTA T VS'!N75 -> 0 | I45: =SUM(G45:H45) -> 60212859 | J45: =I45/$I$25 -> 0.366136
A46: 2 | B46: 1 | C46: 1 | D46: 5 | F46: Prestaciones económinas | G46: =SUM(G47:G50) -> 530819.29 | H46: =SUM(H47:H50) -> 0 | I46: =SUM(G46:H46) -> 530819.29
A47: 2 | B47: 1 | C47: 1 | D47: 5 | E47: 01 | F47: Prestaciones económinas | G47: ='[7]CUENTA T FONDO 100'!O97 -> 0 | H47: ='[7]CUENTA T VS'!O75 -> 0 | I47: =SUM(G47:H47) -> 0 | J47: =I47/$I$25 -> 0
A48: 2 | B48: 1 | C48: 1 | D48: 5 | E48: 02 | F48: Pago de porcentaje por desvinculación de cargo | G48: ='[7]CUENTA T FONDO 100'!P97 -> 0 | H48: ='[7]CUENTA T VS'!P75 -> 0 | I48: =SUM(G48:H48) -> 0 | J48: =I48/$I$25 -> 0
A49: 2 | B49: 1 | C49: 1 | D49: 5 | E49: 03 | F49: Prestación laboral por desvinculación | G49: ='[7]CUENTA T FONDO 100'!Q97 -> 51000 | H49: ='[7]CUENTA T VS'!Q75 -> 0 | I49: =SUM(G49:H49) -> 51000 | J49: =I49/$I$25 -> 0.00031011542
A50: 2 | B50: 1 | C50: 1 | D50: 5 | E50: 04 | F50: Proporción de vacaciones no disfrutadas | G50: ='[7]CUENTA T FONDO 100'!R97 -> 479819.29 | H50: ='[7]CUENTA T VS'!R75 -> 0 | I50: =SUM(G50:H50) -> 479819.29 | J50: =I50/$I$25 -> 0.0029176345
A51: 2 | B51: 1 | C51: 2 | F51: Sobresueldos | G51: =+G52+G54 -> 3315450.2 | H51: =+H52+H54 -> 0 | I51: =SUM(G51:H51) -> 3315450.2
A52: 2 | B52: 1 | C52: 2 | D52: 1 | F52: Primas por antigüedad | G52: =SUM(G53) -> 2652914.7 | H52: =SUM(H53) -> 0 | I52: =SUM(G52:H52) -> 2652914.7
A53: 2 | B53: 1 | C53: 2 | D53: 1 | E53: 01 | F53: Primas por antigüedad | G53: ='[7]CUENTA T FONDO 100'!S97 -> 2652914.7 | H53: ='[7]CUENTA T VS'!S75 -> 0 | I53: =SUM(G53:H53) -> 2652914.7 | J53: =I53/$I$25 -> 0.016131564
A54: 2 | B54: 1 | C54: 2 | D54: 2 | F54: Compensación | G54: =SUM(G55:G63) -> 662535.52 | H54: =SUM(H55:H63) -> 0 | I54: =SUM(G54:H54) -> 662535.52
A55: 2 | B55: 1 | C55: 2 | D55: 2 | E55: 01 | F55: Compensación por gastos de alimentación | G55: ='[7]CUENTA T FONDO 100'!T97 -> 0 | H55: ='[7]CUENTA T VS'!T75 -> 0 | I55: =SUM(G55:H55) -> 0 | J55: =I55/$I$25 -> 0
A56: 2 | B56: 1 | C56: 2 | D56: 2 | E56: 03 | F56: Pago de horas extraordinarias | G56: ='[7]CUENTA T FONDO 100'!U97 -> 0 | H56: ='[7]CUENTA T VS'!U75 -> 0 | I56: =SUM(G56:H56) -> 0 | J56: =I56/$I$25 -> 0
A57: 2 | B57: 1 | C57: 2 | D57: 2 | E57: 04 | F57: Prima de transporte | G57: ='[7]CUENTA T FONDO 100'!V97 -> 0 | H57: ='[7]CUENTA T VS'!V75 -> 0 | I57: =SUM(G57:H57) -> 0 | J57: =I57/$I$25 -> 0
A58: 2 | B58: 1 | C58: 2 | D58: 2 | E58: 05 | F58: Compensación servicios de Seguridad | G58: ='[7]CUENTA T FONDO 100'!W97 -> 75000 | H58: ='[7]CUENTA T VS'!W75 -> 0 | I58: =SUM(G58:H58) -> 75000 | J58: =I58/$I$25 -> 0.00045605209
A59: 2 | B59: 1 | C59: 2 | D59: 2 | E59: 06 | F59: Incentivo por Rendimieto Individual | G59: ='[7]CUENTA T FONDO 100'!X97 -> 0 | H59: ='[7]CUENTA T VS'!X75 -> 0 | I59: =SUM(G59:H59) -> 0 | J59: =I59/$I$25 -> 0
A60: 2 | B60: 1 | C60: 2 | D60: 2 | E60: 07 | F60: Compensación por distancia | G60: ='[7]CUENTA T FONDO 100'!Y97 -> 0 | H60: ='[7]CUENTA T VS'!Y75 -> 0 | I60: =SUM(G60:H60) -> 0 | J60: =I60/$I$25 -> 0
A61: 2 | B61: 1 | C61: 2 | D61: 2 | E61: 08 | F61: Compensaciones especiales | G61: ='[7]CUENTA T FONDO 100'!Z97 -> 317800 | H61: ='[7]CUENTA T VS'!Z75 -> 0 | I61: =SUM(G61:H61) -> 317800 | J61: =I61/$I$25 -> 0.0019324447
A62: 2 | B62: 1 | C62: 2 | D62: 2 | E62: 09 | F62: Bono por desempeño a servidores de carrera | G62: ='[7]CUENTA T FONDO 100'!AA97 -> 0 | H62: ='[7]CUENTA T VS'!AA75 -> 0 | I62: =SUM(G62:H62) -> 0 | J62: =I62/$I$25 -> 0
A63: 2 | B63: 1 | C63: 2 | D63: 2 | E63: 10 | F63: Compensacion por cumplimiento de indicadores | G63: ='[7]CUENTA T FONDO 100'!AB97 -> 269735.52 | H63: ='[7]CUENTA T VS'!AB75 -> 0 | I63: =SUM(G63:H63) -> 269735.52 | J63: =I63/$I$25 -> 0.0016401793
A64: 2 | B64: 1 | C64: 3 | F64: Dietas y Gastos de Representación | G64: =+G65+G68 -> 0 | H64: =+H65+H68 -> 0 | I64: =SUM(G64:H64) -> 0
A65: 2 | B65: 1 | C65: 3 | D65: 1 | F65: Dietas | G65: =SUM(G66:G67) -> 0 | H65: =SUM(H66:H67) -> 0 | I65: =SUM(G65:H65) -> 0
A66: 2 | B66: 1 | C66: 3 | D66: 1 | E66: 01 | F66: Dietas en el país | G66: ='[7]CUENTA T FONDO 100'!AC97 -> 0 | H66: ='[7]CUENTA T VS'!AC75 -> 0 | I66: =SUM(G66:H66) -> 0 | J66: =I66/$I$25 -> 0
A67: 2 | B67: 1 | C67: 3 | D67: 1 | E67: 02 | F67: Dietas en el exterior | G67: ='[7]CUENTA T FONDO 100'!AD97 -> 0 | H67: ='[7]CUENTA T VS'!AD75 -> 0 | I67: =SUM(G67:H67) -> 0 | J67: =I67/$I$25 -> 0
A68: 2 | B68: 1 | C68: 3 | D68: 2 | F68: Gastos de representación | G68: =SUM(G69:G70) -> 0 | H68: =SUM(H69:H70) -> 0 | I68: =SUM(G68:H68) -> 0
A69: 2 | B69: 1 | C69: 3 | D69: 2 | E69: 01 | F69: Gastos de representación en el país | G69: ='[7]CUENTA T FONDO 100'!AE97 -> 0 | H69: ='[7]CUENTA T VS'!AE75 -> 0 | I69: =SUM(G69:H69) -> 0 | J69: =I69/$I$25 -> 0
A70: 2 | B70: 1 | C70: 3 | D70: 2 | E70: 02 | F70: Gastos de representación en el exterior | G70: ='[7]CUENTA T FONDO 100'!AF97 -> 0 | H70: ='[7]CUENTA T VS'!AF75 -> 0 | I70: =SUM(G70:H70) -> 0 | J70: =I70/$I$25 -> 0
A71: 2 | B71: 1 | C71: 4 | F71: Gratificaciones y Bonificaciones | G71: =+G72+G74 -> 0 | H71: =+H72+H74 -> 0 | I71: =SUM(G71:H71) -> 0
A72: 2 | B72: 1 | C72: 4 | D72: 1 | F72: Bonificaciones | G72: =SUM(G73) -> 0 | H72: =SUM(H73) -> 0 | I72: =SUM(G72:H72) -> 0
A73: 2 | B73: 1 | C73: 4 | D73: 1 | E73: 01 | F73: Bonificaciones | G73: ='[7]CUENTA T FONDO 100'!AG97 -> 0 | H73: ='[7]CUENTA T VS'!AG75 -> 0 | I73: =SUM(G73:H73) -> 0 | J73: =I73/$I$25 -> 0
A74: 2 | B74: 1 | C74: 4 | D74: 2 | F74: Otras Gratificaciones y Bonificaciones | G74: =SUM(G75:G77) -> 0 | H74: =SUM(H75:H77) -> 0 | I74: =SUM(G74:H74) -> 0
A75: 2 | B75: 1 | C75: 4 | D75: 2 | E75: 01 | F75: Bono escolar | G75: ='[7]CUENTA T FONDO 100'!AH97 -> 0 | H75: ='[7]CUENTA T VS'!AH75 -> 0 | I75: =SUM(G75:H75) -> 0 | J75: =I75/$I$25 -> 0
A76: 2 | B76: 1 | C76: 4 | D76: 2 | E76: 02 | F76: Gratificaciones por pasantías | G76: ='[7]CUENTA T FONDO 100'!AI97 -> 0 | H76: ='[7]CUENTA T VS'!AI75 -> 0 | I76: =SUM(G76:H76) -> 0 | J76: =I76/$I$25 -> 0
A77: 2 | B77: 1 | C77: 4 | D77: 2 | E77: 03 | F77: Gratificaciones por aniversario de institución | G77: ='[7]CUENTA T FONDO 100'!AJ97 -> 0 | H77: ='[7]CUENTA T VS'!AJ75 -> 0 | I77: =SUM(G77:H77) -> 0 | J77: =I77/$I$25 -> 0
A78: 2 | B78: 1 | C78: 5 | F78: Contribuciones a la Seguridad Social y Riesgo Laboral | G78: =+G79+G81+G83+G85 -> 9292352.7 | H78: =+H79+H81+H83+H85 -> 0 | I78: =SUM(G78:H78) -> 9292352.7
A79: 2 | B79: 1 | C79: 5 | D79: 1 | F79: Contribuciones al seguro de salud | G79: =SUM(G80) -> 4281604.4 | H79: =SUM(H80) -> 0 | I79: =SUM(G79:H79) -> 4281604.4
A80: 2 | B80: 1 | C80: 5 | D80: 1 | E80: 01 | F80: Contribuciones al seguro de salud | G80: ='[7]CUENTA T FONDO 100'!AK97 -> 4281604.4 | H80: ='[7]CUENTA T VS'!AK75 -> 0 | I80: =SUM(G80:H80) -> 4281604.4 | J80: =I80/$I$25 -> 0.026035128
A81: 2 | B81: 1 | C81: 5 | D81: 2 | F81: Contribuciones al seguro de pensiones | G81: =SUM(G82) -> 4287644.2 | H81: =SUM(H82) -> 0 | I81: =SUM(G81:H81) -> 4287644.2
A82: 2 | B82: 1 | C82: 5 | D82: 2 | E82: 01 | F82: Contribuciones al seguro de pensiones | G82: ='[7]CUENTA T FONDO 100'!AL97 -> 4287644.2 | H82: ='[7]CUENTA T VS'!AL75 -> 0 | I82: =SUM(G82:H82) -> 4287644.2 | J82: =I82/$I$25 -> 0.026071855
A83: 2 | B83: 1 | C83: 5 | D83: 3 | F83: Contribuciones al seguro de riesgo laboral | G83: =SUM(G84) -> 723104.06 | H83: =SUM(H84) -> 0 | I83: =SUM(G83:H83) -> 723104.06
A84: 2 | B84: 1 | C84: 5 | D84: 3 | E84: 01 | F84: Contribuciones al seguro de riesgo laboral | G84: ='[7]CUENTA T FONDO 100'!AM97 -> 723104.06 | H84: ='[7]CUENTA T VS'!AM75 -> 0 | I84: =SUM(G84:H84) -> 723104.06 | J84: =I84/$I$25 -> 0.0043969749
A85: 2 | B85: 1 | C85: 5 | D85: 4 | F85: Contribuciones al plan de retiro complementario | G85: =SUM(G86) -> 0 | H85: =SUM(H86) -> 0 | I85: =SUM(G85:H85) -> 0
A86: 2 | B86: 1 | C86: 5 | D86: 4 | E86: 01 | F86: Contribuciones al plan de retiro complementario | G86: ='[7]CUENTA T FONDO 100'!AN97 -> 0 | H86: ='[7]CUENTA T VS'!AN75 -> 0 | I86: =SUM(G86:H86) -> 0 | J86: =I86/$I$25 -> 0
A87: 2 | B87: 2 | F87: Servicios No Personales | G87: =G88+G106+G111+G116+G125+G148+G157+G179+G208 -> 1896797.1 | H87: =H88+H106+H111+H116+H125+H148+H157+H179+H208 -> 2083820.5 | I87: =SUM(G87:H87) -> 3980617.7 | J87: =I87/$I$25 -> 0.02420492
A88: 2 | B88: 2 | C88: 1 | F88: Servicios Básicos | G88: =+G89+G91+G93+G95+G97+G99+G102+G104 -> 60535 | H88: =+H89+H91+H93+H95+H97+H99+H102+H104 -> 745000 | I88: =SUM(G88:H88) -> 805535
A89: 2 | B89: 2 | C89: 1 | D89: 1 | F89: Radiocomunicación | G89: =SUM(G90) -> 0 | H89: =SUM(H90) -> 0 | I89: =SUM(G89:H89) -> 0
A90: 2 | B90: 2 | C90: 1 | D90: 1 | E90: 01 | F90: Radiocomunicación | G90: ='[7]CUENTA T FONDO 100'!AO97 -> 0 | H90: ='[7]CUENTA T VS'!AO75 -> 0 | I90: =SUM(G90:H90) -> 0 | J90: =I90/$I$25 -> 0
A91: 2 | B91: 2 | C91: 1 | D91: 2 | F91: Servicios telefónico de larga distancia | G91: =SUM(G92) -> 0 | H91: =SUM(H92) -> 0 | I91: =SUM(G91:H91) -> 0
A92: 2 | B92: 2 | C92: 1 | D92: 2 | E92: 01 | F92: Servicios telefónico de larga distancia | G92: ='[7]CUENTA T FONDO 100'!AP97 -> 0 | H92: ='[7]CUENTA T VS'!AP75 -> 0 | I92: =SUM(G92:H92) -> 0 | J92: =I92/$I$25 -> 0
A93: 2 | B93: 2 | C93: 1 | D93: 3 | F93: Teléfono local | G93: =SUM(G94) -> 0 | H93: =SUM(H94) -> 0 | I93: =SUM(G93:H93) -> 0
A94: 2 | B94: 2 | C94: 1 | D94: 3 | E94: 01 | F94: Teléfono local | G94: ='[7]CUENTA T FONDO 100'!AQ97 -> 0 | H94: ='[7]CUENTA T VS'!AQ75 -> 0 | I94: =SUM(G94:H94) -> 0 | J94: =I94/$I$25 -> 0
A95: 2 | B95: 2 | C95: 1 | D95: 4 | F95: Telefax y correos | G95: =SUM(G96) -> 0 | H95: =SUM(H96) -> 0 | I95: =SUM(G95:H95) -> 0
A96: 2 | B96: 2 | C96: 1 | D96: 4 | E96: 01 | F96: Telefax y correos | G96: ='[7]CUENTA T FONDO 100'!AR97 -> 0 | H96: ='[7]CUENTA T VS'!AR75 -> 0 | I96: =SUM(G96:H96) -> 0 | J96: =I96/$I$25 -> 0
A97: 2 | B97: 2 | C97: 1 | D97: 5 | F97: Servicio de Internet y televisión por cable | G97: =SUM(G98) -> 0 | H97: =SUM(H98) -> 0 | I97: =SUM(G97:H97) -> 0
A98: 2 | B98: 2 | C98: 1 | D98: 5 | E98: 01 | F98: Servicio de Internet y televisión por cable | G98: ='[7]CUENTA T FONDO 100'!AS97 -> 0 | H98: ='[7]CUENTA T VS'!AS75 -> 0 | I98: =SUM(G98:H98) -> 0 | J98: =I98/$I$25 -> 0
A99: 2 | B99: 2 | C99: 1 | D99: 6 | F99: Electricidad | G99: =SUM(G100:G101) -> 0 | H99: =SUM(H100:H101) -> 0 | I99: =SUM(G99:H99) -> 0
A100: 2 | B100: 2 | C100: 1 | D100: 6 | E100: 01 | F100: Energía eléctrica | G100: ='[7]CUENTA T FONDO 100'!AT97 -> 0 | H100: ='[7]CUENTA T VS'!AT75 -> 0 | I100: =SUM(G100:H100) -> 0 | J100: =I100/$I$25 -> 0
A101: 2 | B101: 2 | C101: 1 | D101: 6 | E101: 02 | F101: Electricidad no cortable | G101: ='[7]CUENTA T FONDO 100'!AU97 -> 0 | H101: ='[7]CUENTA T VS'!AU75 -> 0 | I101: =SUM(G101:H101) -> 0 | J101: =I101/$I$25 -> 0
A102: 2 | B102: 2 | C102: 1 | D102: 7 | F102: Agua | G102: =SUM(G103) -> 60535 | H102: =SUM(H103) -> 0 | I102: =SUM(G102:H102) -> 60535
...

Sheet DICIEMBRE 2025
A1: Form. No.6 SRS
A3: Servicio Nacional de Salud
A4: Dirección de Fizcalización
A5: Consolidado de Ingresos y Gastos por Fuente de Financiamiento
A6: HOSPITAL MATERNO INFANTIL SAN LORENZO DE LOS MINA
A7: DICIEMBRE 2025
C8: Ingresos Generales:
E9: 1.- Balance Inicial / Fuente:
E10: Anticipo Financiero | H10: Otros Aportes | L10: Contraseña: 0001
E11: Transferencias Corrientes
E12: Venta de Servicios | G12: 2685939.8
E13: 2.- Ingresos por Fuente / Cuenta
E14: Anticipo Financiero | H14: Otros Aportes | L14: OBJETAL | M14: FR | N14: VS
E15: Transferencias Corrientes | G15: =+'[8]INGR SEGUN ORIGEN'!E12 -> 1.2257458e+08 | H15: Aportes Nomina SNS | L15: 2.1 | M15: =G26 -> 81717721 | N15: =H26 -> 0
E16: Venta de Servicios | G16: =+'[8]INGR SEGUN ORIGEN'!E26+'[8]INGR SEGUN ORIGEN'!E33 -> 16833212 | L16: 2.2 | M16: =G87 -> 13617256 | N16: =H87 -> 7601154.9
H17: TOTAL INGRESOS RDS | I17: =+G10+G11+G12+I10+G14+G15+G16+I14+I15 -> 1.4209373e+08 | L17: 2.3 | M17: ='[8]CONS. FUENTES FINAN'!G212 -> 71708916 | N17: ='[8]CONS. FUENTES FINAN'!H212 -> 11135613
L18: 2.4 | M18: =G330 -> 0 | N18: =H330 -> 16000
L19: 2.6 | M19: =G336 -> 17995006 | N19: =H336 -> 4350775.5
L20: 2.7 | M20: ='[8]CONS. FUENTES FINAN'!G463 -> 0 | N20: ='[8]CONS. FUENTES FINAN'!H463 -> 0
A21: 1 | F21: 2 | G21: 3 | I21: 4 | J21: 5
A22: Código Presupuestario | F22: Descripción Gasto por Cuenta | G22: Distribución del Gasto por Fuente de Financiamiento | I22: TOTAL | J22: %
A23: Tipo | B23: Objeto | C23: Cuenta | D23: Sub-Cuenta | E23: Auxiliar | G23: Fondo 100 | H23: Venta de Servicios/ Otros Aportes
A25: 2 | F25: Gastos | G25: =+G26+G87+G212+G330+G336+G463 -> 1.850389e+08 | H25: =+H26+H87+H212+H330+H336+H463 -> 23103544 | I25: =SUM(G25:H25) -> 2.0814244e+08 | J25: =+J26+J87+J212+J330+J336+J463 -> 1
A26: 2 | B26: 1 | F26: Servicios Personales | G26: =+G27+G51+G64+G71+G78 -> 81717721 | H26: =+H27+H51+H64+H71+H78 -> 0 | I26: =SUM(G26:H26) -> 81717721 | J26: =I26/$I$25 -> 0.39260479
A27: 2 | B27: 1 | C27: 1 | F27: Remuneraciones | G27: =+G28+G35+G42+G44+G46 -> 61417331 | H27: =+H28+H35+H42+H44+H46 -> 0 | I27: =SUM(G27:H27) -> 61417331
A28: 2 | B28: 1 | C28: 1 | D28: 1 | F28: Remuneraciones al personal fijo | G28: =SUM(G29:G34) -> 59174005 | H28: =SUM(H29:H34) -> 0 | I28: =SUM(G28:H28) -> 59174005
A29: 2 | B29: 1 | C29: 1 | D29: 1 | E29: 01 | F29: Sueldos a empleados fijos | G29: ='[8]CUENTA T FONDO 100'!A210 -> 59174005 | H29: ='[8]CUENTA T VS'!A498 -> 0 | I29: =SUM(G29:H29) -> 59174005 | J29: =I29/$I$25 -> 0.28429572
A30: 2 | B30: 1 | C30: 1 | D30: 1 | E30: 02 | F30: Sueldos a médicos | G30: ='[8]CUENTA T FONDO 100'!B210 -> 0 | H30: ='[8]CUENTA T VS'!B498 -> 0 | I30: =SUM(G30:H30) -> 0 | J30: =I30/$I$25 -> 0
A31: 2 | B31: 1 | C31: 1 | D31: 1 | E31: 03 | F31: Ascensos a militares | G31: ='[8]CUENTA T FONDO 100'!C210 -> 0 | H31: ='[8]CUENTA T VS'!C498 -> 0 | I31: =SUM(G31:H31) -> 0 | J31: =I31/$I$25 -> 0
A32: 2 | B32: 1 | C32: 1 | D32: 1 | E32: 04 | F32: Nuevas plazas maestros | G32: ='[8]CUENTA T FONDO 100'!D210 -> 0 | H32: ='[8]CUENTA T VS'!D498 -> 0 | I32: =SUM(G32:H32) -> 0 | J32: =I32/$I$25 -> 0
A33: 2 | B33: 1 | C33: 1 | D33: 1 | E33: 05 | F33: Incentivos y escalafón | G33: ='[8]CUENTA T FONDO 100'!E210 -> 0 | H33: ='[8]CUENTA T VS'!E498 -> 0 | I33: =SUM(G33:H33) -> 0 | J33: =I33/$I$25 -> 0
A34: 2 | B34: 1 | C34: 1 | D34: 1 | E34: 06 | F34: Nuevas plazas a médicos | G34: ='[8]CUENTA T FONDO 100'!F210 -> 0 | H34: ='[8]CUENTA T VS'!F498 -> 0 | I34: =SUM(G34:H34) -> 0 | J34: =I34/$I$25 -> 0
A35: 2 | B35: 1 | C35: 1 | D35: 2 | F35: Remuneraciones al personal con carácter transitorio | G35: =SUM(G36:G41) -> 1342531 | H35: =SUM(H36:H41) -> 0 | I35: =SUM(G35:H35) -> 1342531
A36: 2 | B36: 1 | C36: 1 | D36: 2 | E36: 03 | F36: Suplencias | G36: ='[8]CUENTA T FONDO 100'!G210 -> 0 | H36: ='[8]CUENTA T VS'!G498 -> 0 | I36: =SUM(G36:H36) -> 0 | J36: =I36/$I$25 -> 0
A37: 2 | B37: 1 | C37: 1 | D37: 2 | E37: 05 | F37: Sueldo al personal nominal en período probatorio | G37: ='[8]CUENTA T FONDO 100'!H210 -> 0 | H37: ='[8]CUENTA T VS'!H498 -> 0 | I37: =SUM(G37:H37) -> 0 | J37: =I37/$I$25 -> 0
A38: 2 | B38: 1 | C38: 1 | D38: 2 | E38: 06 | F38: Jornales | G38: ='[8]CUENTA T FONDO 100'!I210 -> 0 | H38: ='[8]CUENTA T VS'!I498 -> 0 | I38: =SUM(G38:H38) -> 0 | J38: =I38/$I$25 -> 0
A39: 2 | B39: 1 | C39: 1 | D39: 2 | E39: 08 | F39: Empleados temporales | G39: ='[8]CUENTA T FONDO 100'!J210 -> 1342531 | H39: ='[8]CUENTA T VS'!J498 -> 0 | I39: =SUM(G39:H39) -> 1342531 | J39: =I39/$I$25 -> 0.006450059
A40: 2 | B40: 1 | C40: 1 | D40: 2 | E40: 09 | F40: Personal de carácter eventual | G40: ='[8]CUENTA T FONDO 100'!K210 -> 0 | H40: ='[8]CUENTA T VS'!K498 -> 0 | I40: =SUM(G40:H40) -> 0 | J40: =I40/$I$25 -> 0
A41: 2 | B41: 1 | C41: 1 | D41: 2 | E41: 11 | F41: Interinato | G41: ='[8]CUENTA T FONDO 100'!L210 -> 0 | H41: ='[8]CUENTA T VS'!L498 -> 0 | I41: =SUM(G41:H41) -> 0 | J41: =I41/$I$25 -> 0
A42: 2 | B42: 1 | C42: 1 | D42: 3 | F42: Sueldos al personal fijo en trámite de pensiones | G42: =SUM(G43) -> 0 | H42: =SUM(H43) -> 0 | I42: =SUM(G42:H42) -> 0
A43: 2 | B43: 1 | C43: 1 | D43: 3 | E43: 01 | F43: Sueldos al personal fijo en trámite de pensiones | G43: ='[8]CUENTA T FONDO 100'!M210 -> 0 | H43: ='[8]CUENTA T VS'!M498 -> 0 | I43: =SUM(G43:H43) -> 0 | J43: =I43/$I$25 -> 0
A44: 2 | B44: 1 | C44: 1 | D44: 4 | F44: Sueldo anual no. 13 | G44: =SUM(G45) -> 0 | H44: =SUM(H45) -> 0 | I44: =SUM(G44:H44) -> 0
A45: 2 | B45: 1 | C45: 1 | D45: 4 | E45: 01 | F45: Sueldo anual no. 13 | G45: ='[8]CUENTA T FONDO 100'!N210 -> 0 | H45: ='[8]CUENTA T VS'!N498 -> 0 | I45: =SUM(G45:H45) -> 0 | J45: =I45/$I$25 -> 0
A46: 2 | B46: 1 | C46: 1 | D46: 5 | F46: Prestaciones económinas | G46: =SUM(G47:G50) -> 900795.02 | H46: =SUM(H47:H50) -> 0 | I46: =SUM(G46:H46) -> 900795.02
A47: 2 | B47: 1 | C47: 1 | D47: 5 | E47: 01 | F47: Prestaciones económinas | G47: ='[8]CUENTA T FONDO 100'!O210 -> 0 | H47: ='[8]CUENTA T VS'!O498 -> 0 | I47: =SUM(G47:H47) -> 0 | J47: =I47/$I$25 -> 0
A48: 2 | B48: 1 | C48: 1 | D48: 5 | E48: 02 | F48: Pago de porcentaje por desvinculación de cargo | G48: ='[8]CUENTA T FONDO 100'!P210 -> 0 | H48: ='[8]CUENTA T VS'!P498 -> 0 | I48: =SUM(G48:H48) -> 0 | J48: =I48/$I$25 -> 0
A49: 2 | B49: 1 | C49: 1 | D49: 5 | E49: 03 | F49: Prestación laboral por desvinculación | G49: ='[8]CUENTA T FONDO 100'!Q210 -> 558888 | H49: ='[8]CUENTA T VS'!Q498 -> 0 | I49: =SUM(G49:H49) -> 558888 | J49: =I49/$I$25 -> 0.0026851227
A50: 2 | B50: 1 | C50: 1 | D50: 5 | E50: 04 | F50: Proporción de vacaciones no disfrutadas | G50: ='[8]CUENTA T FONDO 100'!R210 -> 341907.02 | H50: ='[8]CUENTA T VS'!R498 -> 0 | I50: =SUM(G50:H50) -> 341907.02 | J50: =I50/$I$25 -> 0.0016426588
A51: 2 | B51: 1 | C51: 2 | F51: Sobresueldos | G51: =+G52+G54 -> 10988253 | H51: =+H52+H54 -> 0 | I51: =SUM(G51:H51) -> 10988253
A52: 2 | B52: 1 | C52: 2 | D52: 1 | F52: Primas por antigüedad | G52: =SUM(G53) -> 2652914.7 | H52: =SUM(H53) -> 0 | I52: =SUM(G52:H52) -> 2652914.7
A53: 2 | B53: 1 | C53: 2 | D53: 1 | E53: 01 | F53: Primas por antigüedad | G53: ='[8]CUENTA T FONDO 100'!S210 -> 2652914.7 | H53: ='[8]CUENTA T VS'!S498 -> 0 | I53: =SUM(G53:H53) -> 2652914.7 | J53: =I53/$I$25 -> 0.012745669
A54: 2 | B54: 1 | C54: 2 | D54: 2 | F54: Compensación | G54: =SUM(G55:G63) -> 8335338 | H54: =SUM(H55:H63) -> 0 | I54: =SUM(G54:H54) -> 8335338
A55: 2 | B55: 1 | C55: 2 | D55: 2 | E55: 01 | F55: Compensación por gastos de alimentación | G55: ='[8]CUENTA T FONDO 100'!T210 -> 0 | H55: ='[8]CUENTA T VS'!T498 -> 0 | I55: =SUM(G55:H55) -> 0 | J55: =I55/$I$25 -> 0
A56: 2 | B56: 1 | C56: 2 | D56: 2 | E56: 03 | F56: Pago de horas extraordinarias | G56: ='[8]CUENTA T FONDO 100'!U210 -> 0 | H56: ='[8]CUENTA T VS'!U498 -> 0 | I56: =SUM(G56:H56) -> 0 | J56: =I56/$I$25 -> 0
A57: 2 | B57: 1 | C57: 2 | D57: 2 | E57: 04 | F57: Prima de transporte | G57: ='[8]CUENTA T FONDO 100'!V210 -> 0 | H57: ='[8]CUENTA T VS'!V498 -> 0 | I57: =SUM(G57:H57) -> 0 | J57: =I57/$I$25 -> 0
A58: 2 | B58: 1 | C58: 2 | D58: 2 | E58: 05 | F58: Compensación servicios de Seguridad | G58: ='[8]CUENTA T FONDO 100'!W210 -> 75000 | H58: ='[8]CUENTA T VS'!W498 -> 0 | I58: =SUM(G58:H58) -> 75000 | J58: =I58/$I$25 -> 0.00036033016
A59: 2 | B59: 1 | C59: 2 | D59: 2 | E59: 06 | F59: Incentivo por Rendimieto Individual | G59: ='[8]CUENTA T FONDO 100'!X210 -> 0 | H59: ='[8]CUENTA T VS'!X498 -> 0 | I59: =SUM(G59:H59) -> 0 | J59: =I59/$I$25 -> 0
A60: 2 | B60: 1 | C60: 2 | D60: 2 | E60: 07 | F60: Compensación por distancia | G60: ='[8]CUENTA T FONDO 100'!Y210 -> 0 | H60: ='[8]CUENTA T VS'!Y498 -> 0 | I60: =SUM(G60:H60) -> 0 | J60: =I60/$I$25 -> 0
A61: 2 | B61: 1 | C61: 2 | D61: 2 | E61: 08 | F61: Compensaciones especiales | G61: ='[8]CUENTA T FONDO 100'!Z210 -> 301200 | H61: ='[8]CUENTA T VS'!Z498 -> 0 | I61: =SUM(G61:H61) -> 301200 | J61: =I61/$I$25 -> 0.0014470859
A62: 2 | B62: 1 | C62: 2 | D62: 2 | E62: 09 | F62: Bono por desempeño a servidores de carrera | G62: ='[8]CUENTA T FONDO 100'!AA210 -> 0 | H62: ='[8]CUENTA T VS'!AA498 -> 0 | I62: =SUM(G62:H62) -> 0 | J62: =I62/$I$25 -> 0
A63: 2 | B63: 1 | C63: 2 | D63: 2 | E63: 10 | F63: Compensacion por cumplimiento de indicadores | G63: ='[8]CUENTA T FONDO 100'!AB210 -> 7959138 | H63: ='[8]CUENTA T VS'!AB498 -> 0 | I63: =SUM(G63:H63) -> 7959138 | J63: =I63/$I$25 -> 0.0382389
A64: 2 | B64: 1 | C64: 3 | F64: Dietas y Gastos de Representación | G64: =+G65+G68 -> 0 | H64: =+H65+H68 -> 0 | I64: =SUM(G64:H64) -> 0
A65: 2 | B65: 1 | C65: 3 | D65: 1 | F65: Dietas | G65: =SUM(G66:G67) -> 0 | H65: =SUM(H66:H67) -> 0 | I65: =SUM(G65:H65) -> 0
A66: 2 | B66: 1 | C66: 3 | D66: 1 | E66: 01 | F66: Dietas en el país | G66: ='[8]CUENTA T FONDO 100'!AC210 -> 0 | H66: ='[8]CUENTA T VS'!AC498 -> 0 | I66: =SUM(G66:H66) -> 0 | J66: =I66/$I$25 -> 0
A67: 2 | B67: 1 | C67: 3 | D67: 1 | E67: 02 | F67: Dietas en el exterior | G67: ='[8]CUENTA T FONDO 100'!AD210 -> 0 | H67: ='[8]CUENTA T VS'!AD498 -> 0 | I67: =SUM(G67:H67) -> 0 | J67: =I67/$I$25 -> 0
A68: 2 | B68: 1 | C68: 3 | D68: 2 | F68: Gastos de representación | G68: =SUM(G69:G70) -> 0 | H68: =SUM(H69:H70) -> 0 | I68: =SUM(G68:H68) -> 0
A69: 2 | B69: 1 | C69: 3 | D69: 2 | E69: 01 | F69: Gastos de representación en el país | G69: ='[8]CUENTA T FONDO 100'!AE210 -> 0 | H69: ='[8]CUENTA T VS'!AE498 -> 0 | I69: =SUM(G69:H69) -> 0 | J69: =I69/$I$25 -> 0
A70: 2 | B70: 1 | C70: 3 | D70: 2 | E70: 02 | F70: Gastos de representación en el exterior | G70: ='[8]CUENTA T FONDO 100'!AF210 -> 0 | H70: ='[8]CUENTA T VS'!AF498 -> 0 | I70: =SUM(G70:H70) -> 0 | J70: =I70/$I$25 -> 0
A71: 2 | B71: 1 | C71: 4 | F71: Gratificaciones y Bonificaciones | G71: =+G72+G74 -> 0 | H71: =+H72+H74 -> 0 | I71: =SUM(G71:H71) -> 0
A72: 2 | B72: 1 | C72: 4 | D72: 1 | F72: Bonificaciones | G72: =SUM(G73) -> 0 | H72: =SUM(H73) -> 0 | I72: =SUM(G72:H72) -> 0
A73: 2 | B73: 1 | C73: 4 | D73: 1 | E73: 01 | F73: Bonificaciones | G73: ='[8]CUENTA T FONDO 100'!AG210 -> 0 | H73: ='[8]CUENTA T VS'!AG498 -> 0 | I73: =SUM(G73:H73) -> 0 | J73: =I73/$I$25 -> 0
A74: 2 | B74: 1 | C74: 4 | D74: 2 | F74: Otras Gratificaciones y Bonificaciones | G74: =SUM(G75:G77) -> 0 | H74: =SUM(H75:H77) -> 0 | I74: =SUM(G74:H74) -> 0
A75: 2 | B75: 1 | C75: 4 | D75: 2 | E75: 01 | F75: Bono escolar | G75: ='[8]CUENTA T FONDO 100'!AH210 -> 0 | H75: ='[8]CUENTA T VS'!AH498 -> 0 | I75: =SUM(G75:H75) -> 0 | J75: =I75/$I$25 -> 0
A76: 2 | B76: 1 | C76: 4 | D76: 2 | E76: 02 | F76: Gratificaciones por pasantías | G76: ='[8]CUENTA T FONDO 100'!AI210 -> 0 | H76: ='[8]CUENTA T VS'!AI498 -> 0 | I76: =SUM(G76:H76) -> 0 | J76: =I76/$I$25 -> 0
A77: 2 | B77: 1 | C77: 4 | D77: 2 | E77: 03 | F77: Gratificaciones por aniversario de institución | G77: ='[8]CUENTA T FONDO 100'!AJ210 -> 0 | H77: ='[8]CUENTA T VS'!AJ498 -> 0 | I77: =SUM(G77:H77) -> 0 | J77: =I77/$I$25 -> 0
A78: 2 | B78: 1 | C78: 5 | F78: Contribuciones a la Seguridad Social y Riesgo Laboral | G78: =+G79+G81+G83+G85 -> 9312137.1 | H78: =+H79+H81+H83+H85 -> 0 | I78: =SUM(G78:H78) -> 9312137.1
A79: 2 | B79: 1 | C79: 5 | D79: 1 | F79: Contribuciones al seguro de salud | G79: =SUM(G80) -> 4290757.5 | H79: =SUM(H80) -> 0 | I79: =SUM(G79:H79) -> 4290757.5
A80: 2 | B80: 1 | C80: 5 | D80: 1 | E80: 01 | F80: Contribuciones al seguro de salud | G80: ='[8]CUENTA T FONDO 100'!AK210 -> 4290757.5 | H80: ='[8]CUENTA T VS'!AK498 -> 0 | I80: =SUM(G80:H80) -> 4290757.5 | J80: =I80/$I$25 -> 0.020614524
A81: 2 | B81: 1 | C81: 5 | D81: 2 | F81: Contribuciones al seguro de pensiones | G81: =SUM(G82) -> 4296541.5 | H81: =SUM(H82) -> 0 | I81: =SUM(G81:H81) -> 4296541.5
A82: 2 | B82: 1 | C82: 5 | D82: 2 | E82: 01 | F82: Contribuciones al seguro de pensiones | G82: ='[8]CUENTA T FONDO 100'!AL210 -> 4296541.5 | H82: ='[8]CUENTA T VS'!AL498 -> 0 | I82: =SUM(G82:H82) -> 4296541.5 | J82: =I82/$I$25 -> 0.020642313
A83: 2 | B83: 1 | C83: 5 | D83: 3 | F83: Contribuciones al seguro de riesgo laboral | G83: =SUM(G84) -> 724838.13 | H83: =SUM(H84) -> 0 | I83: =SUM(G83:H83) -> 724838.13
A84: 2 | B84: 1 | C84: 5 | D84: 3 | E84: 01 | F84: Contribuciones al seguro de riesgo laboral | G84: ='[8]CUENTA T FONDO 100'!AM210 -> 724838.13 | H84: ='[8]CUENTA T VS'!AM498 -> 0 | I84: =SUM(G84:H84) -> 724838.13 | J84: =I84/$I$25 -> 0.0034824139
A85: 2 | B85: 1 | C85: 5 | D85: 4 | F85: Contribuciones al plan de retiro complementario | G85: =SUM(G86) -> 0 | H85: =SUM(H86) -> 0 | I85: =SUM(G85:H85) -> 0
A86: 2 | B86: 1 | C86: 5 | D86: 4 | E86: 01 | F86: Contribuciones al plan de retiro complementario | G86: ='[8]CUENTA T FONDO 100'!AN210 -> 0 | H86: ='[8]CUENTA T VS'!AN498 -> 0 | I86: =SUM(G86:H86) -> 0 | J86: =I86/$I$25 -> 0
A87: 2 | B87: 2 | F87: Servicios No Personales | G87: =G88+G106+G111+G116+G125+G148+G157+G179+G208 -> 13617256 | H87: =H88+H106+H111+H116+H125+H148+H157+H179+H208 -> 7601154.9 | I87: =SUM(G87:H87) -> 21218411 | J87: =I87/$I$25 -> 0.10194178
A88: 2 | B88: 2 | C88: 1 | F88: Servicios Básicos | G88: =+G89+G91+G93+G95+G97+G99+G102+G104 -> 211735 | H88: =+H89+H91+H93+H95+H97+H99+H102+H104 -> 1678516.1 | I88: =SUM(G88:H88) -> 1890251.1
A89: 2 | B89: 2 | C89: 1 | D89: 1 | F89: Radiocomunicación | G89: =SUM(G90) -> 0 | H89: =SUM(H90) -> 0 | I89: =SUM(G89:H89) -> 0
A90: 2 | B90: 2 | C90: 1 | D90: 1 | E90: 01 | F90: Radiocomunicación | G90: ='[8]CUENTA T FONDO 100'!AO210 -> 0 | H90: ='[8]CUENTA T VS'!AO498 -> 0 | I90: =SUM(G90:H90) -> 0 | J90: =I90/$I$25 -> 0
A91: 2 | B91: 2 | C91: 1 | D91: 2 | F91: Servicios telefónico de larga distancia | G91: =SUM(G92) -> 0 | H91: =SUM(H92) -> 0 | I91: =SUM(G91:H91) -> 0
A92: 2 | B92: 2 | C92: 1 | D92: 2 | E92: 01 | F92: Servicios telefónico de larga distancia | G92: ='[8]CUENTA T FONDO 100'!AP210 -> 0 | H92: ='[8]CUENTA T VS'!AP498 -> 0 | I92: =SUM(G92:H92) -> 0 | J92: =I92/$I$25 -> 0
A93: 2 | B93: 2 | C93: 1 | D93: 3 | F93: Teléfono local | G93: =SUM(G94) -> 0 | H93: =SUM(H94) -> 213516.07 | I93: =SUM(G93:H93) -> 213516.07
A94: 2 | B94: 2 | C94: 1 | D94: 3 | E94: 01 | F94: Teléfono local | G94: ='[8]CUENTA T FONDO 100'!AQ210 -> 0 | H94: ='[8]CUENTA T VS'!AQ498 -> 213516.07 | I94: =SUM(G94:H94) -> 213516.07 | J94: =I94/$I$25 -> 0.0010258171
A95: 2 | B95: 2 | C95: 1 | D95: 4 | F95: Telefax y correos | G95: =SUM(G96) -> 0 | H95: =SUM(H96) -> 0 | I95: =SUM(G95:H95) -> 0
A96: 2 | B96: 2 | C96: 1 | D96: 4 | E96: 01 | F96: Telefax y correos | G96: ='[8]CUENTA T FONDO 100'!AR210 -> 0 | H96: ='[8]CUENTA T VS'!AR498 -> 0 | I96: =SUM(G96:H96) -> 0 | J96: =I96/$I$25 -> 0
A97: 2 | B97: 2 | C97: 1 | D97: 5 | F97: Servicio de Internet y televisión por cable | G97: =SUM(G98) -> 0 | H97: =SUM(H98) -> 0 | I97: =SUM(G97:H97) -> 0
A98: 2 | B98: 2 | C98: 1 | D98: 5 | E98: 01 | F98: Servicio de Internet y televisión por cable | G98: ='[8]CUENTA T FONDO 100'!AS210 -> 0 | H98: ='[8]CUENTA T VS'!AS498 -> 0 | I98: =SUM(G98:H98) -> 0 | J98: =I98/$I$25 -> 0
A99: 2 | B99: 2 | C99: 1 | D99: 6 | F99: Electricidad | G99: =SUM(G100:G101) -> 0 | H99: =SUM(H100:H101) -> 0 | I99: =SUM(G99:H99) -> 0
A100: 2 | B100: 2 | C100: 1 | D100: 6 | E100: 01 | F100: Energía eléctrica | G100: ='[8]CUENTA T FONDO 100'!AT210 -> 0 | H100: ='[8]CUENTA T VS'!AT498 -> 0 | I100: =SUM(G100:H100) -> 0 | J100: =I100/$I$25 -> 0
A101: 2 | B101: 2 | C101: 1 | D101: 6 | E101: 02 | F101: Electricidad no cortable | G101: ='[8]CUENTA T FONDO 100'!AU210 -> 0 | H101: ='[8]CUENTA T VS'!AU498 -> 0 | I101: =SUM(G101:H101) -> 0 | J101: =I101/$I$25 -> 0
A102: 2 | B102: 2 | C102: 1 | D102: 7 | F102: Agua | G102: =SUM(G103) -> 211735 | H102: =SUM(H103) -> 0 | I102: =SUM(G102:H102) -> 211735
...

Sheet RESUMEN TRIMESTRE OCTUBRE-DIC
A1: Form. No.6 SRS
A3: Servicio Nacional de Salud
A4: Dirección de Fizcalización
A5: Consolidado de Ingresos y Gastos por Fuente de Financiamiento
A6: HOSPITAL MATERNO INFANTIL SAN LORENZO DE LOS MINA
A7: OCTUBRE-DICIEMBRE 2025
C8: Ingresos Generales:
E9: 1.- Balance Inicial / Fuente:
E10: Anticipo Financiero | H10: Otros Aportes | L10: Contraseña: 0001
E11: Transferencias Corrientes
E12: Venta de Servicios | G12: 2685939.8
E13: 2.- Ingresos por Fuente / Cuenta
E14: Anticipo Financiero | H14: Otros Aportes | L14: OBJETAL | M14: FR | N14: VS
E15: Transferencias Corrientes | G15: =+'[8]INGR SEGUN ORIGEN'!E12 -> 1.2257458e+08 | H15: Aportes Nomina SNS | L15: 2.1 | M15: =G26 -> 2.8844538e+08 | N15: =H26 -> 0
E16: Venta de Servicios | G16: =+'[8]INGR SEGUN ORIGEN'!E26+'[8]INGR SEGUN ORIGEN'!E33 -> 16833212 | L16: 2.2 | M16: =G87 -> 16306952 | N16: =H87 -> 11649817
H17: TOTAL INGRESOS RDS | I17: =+G10+G11+G12+I10+G14+G15+G16+I14+I15 -> 1.4209373e+08 | L17: 2.3 | M17: ='[8]CONS. FUENTES FINAN'!G212 -> 71708916 | N17: ='[8]CONS. FUENTES FINAN'!H212 -> 11135613
L18: 2.4 | M18: =G330 -> 0 | N18: =H330 -> 19600
L19: 2.6 | M19: =G336 -> 29442717 | N19: =H336 -> 7416727.6
L20: 2.7 | M20: ='[8]CONS. FUENTES FINAN'!G463 -> 0 | N20: ='[8]CONS. FUENTES FINAN'!H463 -> 0
A21: 1 | F21: 2 | G21: 3 | I21: 4 | J21: 5
A22: Código Presupuestario | F22: Descripción Gasto por Cuenta | G22: Distribución del Gasto por Fuente de Financiamiento | I22: TOTAL | J22: %
A23: Tipo | B23: Objeto | C23: Cuenta | D23: Sub-Cuenta | E23: Auxiliar | G23: Fondo 100 | H23: Venta de Servicios/ Otros Aportes
A25: 2 | F25: Gastos | G25: =+'OCTUBRE '!G25+NOVIEMBRE!G25+'DICIEMBRE 2025'!G25 -> 4.5158025e+08 | H25: =+'OCTUBRE '!H25+NOVIEMBRE!H25+'DICIEMBRE 2025'!H25 -> 38291596 | I25: =SUM(G25:H25) -> 4.8987185e+08 | J25: =+J26+J87+J212+J330+J336+J463 -> 1
A26: 2 | B26: 1 | F26: Servicios Personales | G26: =+'OCTUBRE '!G26+NOVIEMBRE!G26+'DICIEMBRE 2025'!G26 -> 2.8844538e+08 | H26: =+'OCTUBRE '!H26+NOVIEMBRE!H26+'DICIEMBRE 2025'!H26 -> 0 | I26: =SUM(G26:H26) -> 2.8844538e+08 | J26: =I26/$I$25 -> 0.58881804
A27: 2 | B27: 1 | C27: 1 | F27: Remuneraciones | G27: =+'OCTUBRE '!G27+NOVIEMBRE!G27+'DICIEMBRE 2025'!G27 -> 2.4294844e+08 | H27: =+'OCTUBRE '!H27+NOVIEMBRE!H27+'DICIEMBRE 2025'!H27 -> 0 | I27: =SUM(G27:H27) -> 2.4294844e+08
A28: 2 | B28: 1 | C28: 1 | D28: 1 | F28: Remuneraciones al personal fijo | G28: =+'OCTUBRE '!G28+NOVIEMBRE!G28+'DICIEMBRE 2025'!G28 -> 1.7732637e+08 | H28: =+'OCTUBRE '!H28+NOVIEMBRE!H28+'DICIEMBRE 2025'!H28 -> 0 | I28: =SUM(G28:H28) -> 1.7732637e+08
A29: 2 | B29: 1 | C29: 1 | D29: 1 | E29: 01 | F29: Sueldos a empleados fijos | G29: =+'OCTUBRE '!G29+NOVIEMBRE!G29+'DICIEMBRE 2025'!G29 -> 1.7732637e+08 | H29: =+'OCTUBRE '!H29+NOVIEMBRE!H29+'DICIEMBRE 2025'!H29 -> 0 | I29: =SUM(G29:H29) -> 1.7732637e+08 | J29: =I29/$I$25 -> 0.36198523
A30: 2 | B30: 1 | C30: 1 | D30: 1 | E30: 02 | F30: Sueldos a médicos | G30: =+'OCTUBRE '!G30+NOVIEMBRE!G30+'DICIEMBRE 2025'!G30 -> 0 | H30: =+'OCTUBRE '!H30+NOVIEMBRE!H30+'DICIEMBRE 2025'!H30 -> 0 | I30: =SUM(G30:H30) -> 0 | J30: =I30/$I$25 -> 0
A31: 2 | B31: 1 | C31: 1 | D31: 1 | E31: 03 | F31: Ascensos a militares | G31: =+'OCTUBRE '!G31+NOVIEMBRE!G31+'DICIEMBRE 2025'!G31 -> 0 | H31: =+'OCTUBRE '!H31+NOVIEMBRE!H31+'DICIEMBRE 2025'!H31 -> 0 | I31: =SUM(G31:H31) -> 0 | J31: =I31/$I$25 -> 0
A32: 2 | B32: 1 | C32: 1 | D32: 1 | E32: 04 | F32: Nuevas plazas maestros | G32: =+'OCTUBRE '!G32+NOVIEMBRE!G32+'DICIEMBRE 2025'!G32 -> 0 | H32: =+'OCTUBRE '!H32+NOVIEMBRE!H32+'DICIEMBRE 2025'!H32 -> 0 | I32: =SUM(G32:H32) -> 0 | J32: =I32/$I$25 -> 0
A33: 2 | B33: 1 | C33: 1 | D33: 1 | E33: 05 | F33: Incentivos y escalafón | G33: =+'OCTUBRE '!G33+NOVIEMBRE!G33+'DICIEMBRE 2025'!G33 -> 0 | H33: =+'OCTUBRE '!H33+NOVIEMBRE!H33+'DICIEMBRE 2025'!H33 -> 0 | I33: =SUM(G33:H33) -> 0 | J33: =I33/$I$25 -> 0
A34: 2 | B34: 1 | C34: 1 | D34: 1 | E34: 06 | F34: Nuevas plazas a médicos | G34: =+'OCTUBRE '!G34+NOVIEMBRE!G34+'DICIEMBRE 2025'!G34 -> 0 | H34: =+'OCTUBRE '!H34+NOVIEMBRE!H34+'DICIEMBRE 2025'!H34 -> 0 | I34: =SUM(G34:H34) -> 0 | J34: =I34/$I$25 -> 0
A35: 2 | B35: 1 | C35: 1 | D35: 2 | F35: Remuneraciones al personal con carácter transitorio | G35: =+'OCTUBRE '!G35+NOVIEMBRE!G35+'DICIEMBRE 2025'!G35 -> 3977593.1 | H35: =+'OCTUBRE '!H35+NOVIEMBRE!H35+'DICIEMBRE 2025'!H35 -> 0 | I35: =SUM(G35:H35) -> 3977593.1
A36: 2 | B36: 1 | C36: 1 | D36: 2 | E36: 03 | F36: Suplencias | G36: =+'OCTUBRE '!G36+NOVIEMBRE!G36+'DICIEMBRE 2025'!G36 -> 0 | H36: =+'OCTUBRE '!H36+NOVIEMBRE!H36+'DICIEMBRE 2025'!H36 -> 0 | I36: =SUM(G36:H36) -> 0 | J36: =I36/$I$25 -> 0
A37: 2 | B37: 1 | C37: 1 | D37: 2 | E37: 05 | F37: Sueldo al personal nominal en período probatorio | G37: =+'OCTUBRE '!G37+NOVIEMBRE!G37+'DICIEMBRE 2025'!G37 -> 0 | H37: =+'OCTUBRE '!H37+NOVIEMBRE!H37+'DICIEMBRE 2025'!H37 -> 0 | I37: =SUM(G37:H37) -> 0 | J37: =I37/$I$25 -> 0
A38: 2 | B38: 1 | C38: 1 | D38: 2 | E38: 06 | F38: Jornales | G38: =+'OCTUBRE '!G38+NOVIEMBRE!G38+'DICIEMBRE 2025'!G38 -> 0 | H38: =+'OCTUBRE '!H38+NOVIEMBRE!H38+'DICIEMBRE 2025'!H38 -> 0 | I38: =SUM(G38:H38) -> 0 | J38: =I38/$I$25 -> 0
A39: 2 | B39: 1 | C39: 1 | D39: 2 | E39: 08 | F39: Empleados temporales | G39: =+'OCTUBRE '!G39+NOVIEMBRE!G39+'DICIEMBRE 2025'!G39 -> 3977593.1 | H39: =+'OCTUBRE '!H39+NOVIEMBRE!H39+'DICIEMBRE 2025'!H39 -> 0 | I39: =SUM(G39:H39) -> 3977593.1 | J39: =I39/$I$25 -> 0.0081196605
A40: 2 | B40: 1 | C40: 1 | D40: 2 | E40: 09 | F40: Personal de carácter eventual | G40: =+'OCTUBRE '!G40+NOVIEMBRE!G40+'DICIEMBRE 2025'!G40 -> 0 | H40: =+'OCTUBRE '!H40+NOVIEMBRE!H40+'DICIEMBRE 2025'!H40 -> 0 | I40: =SUM(G40:H40) -> 0 | J40: =I40/$I$25 -> 0
A41: 2 | B41: 1 | C41: 1 | D41: 2 | E41: 11 | F41: Interinato | G41: =+'OCTUBRE '!G41+NOVIEMBRE!G41+'DICIEMBRE 2025'!G41 -> 0 | H41: =+'OCTUBRE '!H41+NOVIEMBRE!H41+'DICIEMBRE 2025'!H41 -> 0 | I41: =SUM(G41:H41) -> 0 | J41: =I41/$I$25 -> 0
A42: 2 | B42: 1 | C42: 1 | D42: 3 | F42: Sueldos al personal fijo en trámite de pensiones | G42: =+'OCTUBRE '!G42+NOVIEMBRE!G42+'DICIEMBRE 2025'!G42 -> 0 | H42: =+'OCTUBRE '!H42+NOVIEMBRE!H42+'DICIEMBRE 2025'!H42 -> 0 | I42: =SUM(G42:H42) -> 0
A43: 2 | B43: 1 | C43: 1 | D43: 3 | E43: 01 | F43: Sueldos al personal fijo en trámite de pensiones | G43: =+'OCTUBRE '!G43+NOVIEMBRE!G43+'DICIEMBRE 2025'!G43 -> 0 | H43: =+'OCTUBRE '!H43+NOVIEMBRE!H43+'DICIEMBRE 2025'!H43 -> 0 | I43: =SUM(G43:H43) -> 0 | J43: =I43/$I$25 -> 0
A44: 2 | B44: 1 | C44: 1 | D44: 4 | F44: Sueldo anual no. 13 | G44: =+'OCTUBRE '!G44+NOVIEMBRE!G44+'DICIEMBRE 2025'!G44 -> 60212859 | H44: =+'OCTUBRE '!H44+NOVIEMBRE!H44+'DICIEMBRE 2025'!H44 -> 0 | I44: =SUM(G44:H44) -> 60212859
A45: 2 | B45: 1 | C45: 1 | D45: 4 | E45: 01 | F45: Sueldo anual no. 13 | G45: =+'OCTUBRE '!G45+NOVIEMBRE!G45+'DICIEMBRE 2025'!G45 -> 60212859 | H45: =+'OCTUBRE '!H45+NOVIEMBRE!H45+'DICIEMBRE 2025'!H45 -> 0 | I45: =SUM(G45:H45) -> 60212859 | J45: =I45/$I$25 -> 0.12291553
A46: 2 | B46: 1 | C46: 1 | D46: 5 | F46: Prestaciones económinas | G46: =+'OCTUBRE '!G46+NOVIEMBRE!G46+'DICIEMBRE 2025'!G46 -> 1431614.3 | H46: =+'OCTUBRE '!H46+NOVIEMBRE!H46+'DICIEMBRE 2025'!H46 -> 0 | I46: =SUM(G46:H46) -> 1431614.3
A47: 2 | B47: 1 | C47: 1 | D47: 5 | E47: 01 | F47: Prestaciones económinas | G47: =+'OCTUBRE '!G47+NOVIEMBRE!G47+'DICIEMBRE 2025'!G47 -> 0 | H47: =+'OCTUBRE '!H47+NOVIEMBRE!H47+'DICIEMBRE 2025'!H47 -> 0 | I47: =SUM(G47:H47) -> 0 | J47: =I47/$I$25 -> 0
A48: 2 | B48: 1 | C48: 1 | D48: 5 | E48: 02 | F48: Pago de porcentaje por desvinculación de cargo | G48: =+'OCTUBRE '!G48+NOVIEMBRE!G48+'DICIEMBRE 2025'!G48 -> 0 | H48: =+'OCTUBRE '!H48+NOVIEMBRE!H48+'DICIEMBRE 2025'!H48 -> 0 | I48: =SUM(G48:H48) -> 0 | J48: =I48/$I$25 -> 0
A49: 2 | B49: 1 | C49: 1 | D49: 5 | E49: 03 | F49: Prestación laboral por desvinculación | G49: =+'OCTUBRE '!G49+NOVIEMBRE!G49+'DICIEMBRE 2025'!G49 -> 609888 | H49: =+'OCTUBRE '!H49+NOVIEMBRE!H49+'DICIEMBRE 2025'!H49 -> 0 | I49: =SUM(G49:H49) -> 609888 | J49: =I49/$I$25 -> 0.001244995
A50: 2 | B50: 1 | C50: 1 | D50: 5 | E50: 04 | F50: Proporción de vacaciones no disfrutadas | G50: =+'OCTUBRE '!G50+NOVIEMBRE!G50+'DICIEMBRE 2025'!G50 -> 821726.31 | H50: =+'OCTUBRE '!H50+NOVIEMBRE!H50+'DICIEMBRE 2025'!H50 -> 0 | I50: =SUM(G50:H50) -> 821726.31 | J50: =I50/$I$25 -> 0.0016774312
A51: 2 | B51: 1 | C51: 2 | F51: Sobresueldos | G51: =+'OCTUBRE '!G51+NOVIEMBRE!G51+'DICIEMBRE 2025'!G51 -> 17598750 | H51: =+'OCTUBRE '!H51+NOVIEMBRE!H51+'DICIEMBRE 2025'!H51 -> 0 | I51: =SUM(G51:H51) -> 17598750
A52: 2 | B52: 1 | C52: 2 | D52: 1 | F52: Primas por antigüedad | G52: =+'OCTUBRE '!G52+NOVIEMBRE!G52+'DICIEMBRE 2025'!G52 -> 8008140.9 | H52: =+'OCTUBRE '!H52+NOVIEMBRE!H52+'DICIEMBRE 2025'!H52 -> 0 | I52: =SUM(G52:H52) -> 8008140.9
A53: 2 | B53: 1 | C53: 2 | D53: 1 | E53: 01 | F53: Primas por antigüedad | G53: =+'OCTUBRE '!G53+NOVIEMBRE!G53+'DICIEMBRE 2025'!G53 -> 8008140.9 | H53: =+'OCTUBRE '!H53+NOVIEMBRE!H53+'DICIEMBRE 2025'!H53 -> 0 | I53: =SUM(G53:H53) -> 8008140.9 | J53: =I53/$I$25 -> 0.01634742
A54: 2 | B54: 1 | C54: 2 | D54: 2 | F54: Compensación | G54: =+'OCTUBRE '!G54+NOVIEMBRE!G54+'DICIEMBRE 2025'!G54 -> 9590609 | H54: =+'OCTUBRE '!H54+NOVIEMBRE!H54+'DICIEMBRE 2025'!H54 -> 0 | I54: =SUM(G54:H54) -> 9590609
A55: 2 | B55: 1 | C55: 2 | D55: 2 | E55: 01 | F55: Compensación por gastos de alimentación | G55: =+'OCTUBRE '!G55+NOVIEMBRE!G55+'DICIEMBRE 2025'!G55 -> 0 | H55: =+'OCTUBRE '!H55+NOVIEMBRE!H55+'DICIEMBRE 2025'!H55 -> 0 | I55: =SUM(G55:H55) -> 0 | J55: =I55/$I$25 -> 0
A56: 2 | B56: 1 | C56: 2 | D56: 2 | E56: 03 | F56: Pago de horas extraordinarias | G56: =+'OCTUBRE '!G56+NOVIEMBRE!G56+'DICIEMBRE 2025'!G56 -> 0 | H56: =+'OCTUBRE '!H56+NOVIEMBRE!H56+'DICIEMBRE 2025'!H56 -> 0 | I56: =SUM(G56:H56) -> 0 | J56: =I56/$I$25 -> 0
A57: 2 | B57: 1 | C57: 2 | D57: 2 | E57: 04 | F57: Prima de transporte | G57: =+'OCTUBRE '!G57+NOVIEMBRE!G57+'DICIEMBRE 2025'!G57 -> 0 | H57: =+'OCTUBRE '!H57+NOVIEMBRE!H57+'DICIEMBRE 2025'!H57 -> 0 | I57: =SUM(G57:H57) -> 0 | J57: =I57/$I$25 -> 0
A58: 2 | B58: 1 | C58: 2 | D58: 2 | E58: 05 | F58: Compensación servicios de Seguridad | G58: =+'OCTUBRE '!G58+NOVIEMBRE!G58+'DICIEMBRE 2025'!G58 -> 195000 | H58: =+'OCTUBRE '!H58+NOVIEMBRE!H58+'DICIEMBRE 2025'!H58 -> 0 | I58: =SUM(G58:H58) -> 195000 | J58: =I58/$I$25 -> 0.00039806329
A59: 2 | B59: 1 | C59: 2 | D59: 2 | E59: 06 | F59: Incentivo por Rendimieto Individual | G59: =+'OCTUBRE '!G59+NOVIEMBRE!G59+'DICIEMBRE 2025'!G59 -> 0 | H59: =+'OCTUBRE '!H59+NOVIEMBRE!H59+'DICIEMBRE 2025'!H59 -> 0 | I59: =SUM(G59:H59) -> 0 | J59: =I59/$I$25 -> 0
A60: 2 | B60: 1 | C60: 2 | D60: 2 | E60: 07 | F60: Compensación por distancia | G60: =+'OCTUBRE '!G60+NOVIEMBRE!G60+'DICIEMBRE 2025'!G60 -> 0 | H60: =+'OCTUBRE '!H60+NOVIEMBRE!H60+'DICIEMBRE 2025'!H60 -> 0 | I60: =SUM(G60:H60) -> 0 | J60: =I60/$I$25 -> 0
A61: 2 | B61: 1 | C61: 2 | D61: 2 | E61: 08 | F61: Compensaciones especiales | G61: =+'OCTUBRE '!G61+NOVIEMBRE!G61+'DICIEMBRE 2025'!G61 -> 897000 | H61: =+'OCTUBRE '!H61+NOVIEMBRE!H61+'DICIEMBRE 2025'!H61 -> 0 | I61: =SUM(G61:H61) -> 897000 | J61: =I61/$I$25 -> 0.0018310911
A62: 2 | B62: 1 | C62: 2 | D62: 2 | E62: 09 | F62: Bono por desempeño a servidores de carrera | G62: =+'OCTUBRE '!G62+NOVIEMBRE!G62+'DICIEMBRE 2025'!G62 -> 0 | H62: =+'OCTUBRE '!H62+NOVIEMBRE!H62+'DICIEMBRE 2025'!H62 -> 0 | I62: =SUM(G62:H62) -> 0 | J62: =I62/$I$25 -> 0
A63: 2 | B63: 1 | C63: 2 | D63: 2 | E63: 10 | F63: Compensacion por cumplimiento de indicadores | G63: =+'OCTUBRE '!G63+NOVIEMBRE!G63+'DICIEMBRE 2025'!G63 -> 8498609 | H63: =+'OCTUBRE '!H63+NOVIEMBRE!H63+'DICIEMBRE 2025'!H63 -> 0 | I63: =SUM(G63:H63) -> 8498609 | J63: =I63/$I$25 -> 0.017348637
A64: 2 | B64: 1 | C64: 3 | F64: Dietas y Gastos de Representación | G64: =+'OCTUBRE '!G64+NOVIEMBRE!G64+'DICIEMBRE 2025'!G64 -> 0 | H64: =+'OCTUBRE '!H64+NOVIEMBRE!H64+'DICIEMBRE 2025'!H64 -> 0 | I64: =SUM(G64:H64) -> 0
A65: 2 | B65: 1 | C65: 3 | D65: 1 | F65: Dietas | G65: =+'OCTUBRE '!G65+NOVIEMBRE!G65+'DICIEMBRE 2025'!G65 -> 0 | H65: =+'OCTUBRE '!H65+NOVIEMBRE!H65+'DICIEMBRE 2025'!H65 -> 0 | I65: =SUM(G65:H65) -> 0
A66: 2 | B66: 1 | C66: 3 | D66: 1 | E66: 01 | F66: Dietas en el país | G66: =+'OCTUBRE '!G66+NOVIEMBRE!G66+'DICIEMBRE 2025'!G66 -> 0 | H66: =+'OCTUBRE '!H66+NOVIEMBRE!H66+'DICIEMBRE 2025'!H66 -> 0 | I66: =SUM(G66:H66) -> 0 | J66: =I66/$I$25 -> 0
A67: 2 | B67: 1 | C67: 3 | D67: 1 | E67: 02 | F67: Dietas en el exterior | G67: =+'OCTUBRE '!G67+NOVIEMBRE!G67+'DICIEMBRE 2025'!G67 -> 0 | H67: =+'OCTUBRE '!H67+NOVIEMBRE!H67+'DICIEMBRE 2025'!H67 -> 0 | I67: =SUM(G67:H67) -> 0 | J67: =I67/$I$25 -> 0
A68: 2 | B68: 1 | C68: 3 | D68: 2 | F68: Gastos de representación | G68: =+'OCTUBRE '!G68+NOVIEMBRE!G68+'DICIEMBRE 2025'!G68 -> 0 | H68: =+'OCTUBRE '!H68+NOVIEMBRE!H68+'DICIEMBRE 2025'!H68 -> 0 | I68: =SUM(G68:H68) -> 0
A69: 2 | B69: 1 | C69: 3 | D69: 2 | E69: 01 | F69: Gastos de representación en el país | G69: =+'OCTUBRE '!G69+NOVIEMBRE!G69+'DICIEMBRE 2025'!G69 -> 0 | H69: =+'OCTUBRE '!H69+NOVIEMBRE!H69+'DICIEMBRE 2025'!H69 -> 0 | I69: =SUM(G69:H69) -> 0 | J69: =I69/$I$25 -> 0
A70: 2 | B70: 1 | C70: 3 | D70: 2 | E70: 02 | F70: Gastos de representación en el exterior | G70: =+'OCTUBRE '!G70+NOVIEMBRE!G70+'DICIEMBRE 2025'!G70 -> 0 | H70: =+'OCTUBRE '!H70+NOVIEMBRE!H70+'DICIEMBRE 2025'!H70 -> 0 | I70: =SUM(G70:H70) -> 0 | J70: =I70/$I$25 -> 0
A71: 2 | B71: 1 | C71: 4 | F71: Gratificaciones y Bonificaciones | G71: =+'OCTUBRE '!G71+NOVIEMBRE!G71+'DICIEMBRE 2025'!G71 -> 0 | H71: =+'OCTUBRE '!H71+NOVIEMBRE!H71+'DICIEMBRE 2025'!H71 -> 0 | I71: =SUM(G71:H71) -> 0
A72: 2 | B72: 1 | C72: 4 | D72: 1 | F72: Bonificaciones | G72: =+'OCTUBRE '!G72+NOVIEMBRE!G72+'DICIEMBRE 2025'!G72 -> 0 | H72: =+'OCTUBRE '!H72+NOVIEMBRE!H72+'DICIEMBRE 2025'!H72 -> 0 | I72: =SUM(G72:H72) -> 0
A73: 2 | B73: 1 | C73: 4 | D73: 1 | E73: 01 | F73: Bonificaciones | G73: =+'OCTUBRE '!G73+NOVIEMBRE!G73+'DICIEMBRE 2025'!G73 -> 0 | H73: =+'OCTUBRE '!H73+NOVIEMBRE!H73+'DICIEMBRE 2025'!H73 -> 0 | I73: =SUM(G73:H73) -> 0 | J73: =I73/$I$25 -> 0
A74: 2 | B74: 1 | C74: 4 | D74: 2 | F74: Otras Gratificaciones y Bonificaciones | G74: =+'OCTUBRE '!G74+NOVIEMBRE!G74+'DICIEMBRE 2025'!G74 -> 0 | H74: =+'OCTUBRE '!H74+NOVIEMBRE!H74+'DICIEMBRE 2025'!H74 -> 0 | I74: =SUM(G74:H74) -> 0
A75: 2 | B75: 1 | C75: 4 | D75: 2 | E75: 01 | F75: Bono escolar | G75: =+'OCTUBRE '!G75+NOVIEMBRE!G75+'DICIEMBRE 2025'!G75 -> 0 | H75: =+'OCTUBRE '!H75+NOVIEMBRE!H75+'DICIEMBRE 2025'!H75 -> 0 | I75: =SUM(G75:H75) -> 0 | J75: =I75/$I$25 -> 0
A76: 2 | B76: 1 | C76: 4 | D76: 2 | E76: 02 | F76: Gratificaciones por pasantías | G76: =+'OCTUBRE '!G76+NOVIEMBRE!G76+'DICIEMBRE 2025'!G76 -> 0 | H76: =+'OCTUBRE '!H76+NOVIEMBRE!H76+'DICIEMBRE 2025'!H76 -> 0 | I76: =SUM(G76:H76) -> 0 | J76: =I76/$I$25 -> 0
A77: 2 | B77: 1 | C77: 4 | D77: 2 | E77: 03 | F77: Gratificaciones por aniversario de institución | G77: =+'OCTUBRE '!G77+NOVIEMBRE!G77+'DICIEMBRE 2025'!G77 -> 0 | H77: =+'OCTUBRE '!H77+NOVIEMBRE!H77+'DICIEMBRE 2025'!H77 -> 0 | I77: =SUM(G77:H77) -> 0 | J77: =I77/$I$25 -> 0
A78: 2 | B78: 1 | C78: 5 | F78: Contribuciones a la Seguridad Social y Riesgo Laboral | G78: =+'OCTUBRE '!G78+NOVIEMBRE!G78+'DICIEMBRE 2025'!G78 -> 27898192 | H78: =+'OCTUBRE '!H78+NOVIEMBRE!H78+'DICIEMBRE 2025'!H78 -> 0 | I78: =SUM(G78:H78) -> 27898192
A79: 2 | B79: 1 | C79: 5 | D79: 1 | F79: Contribuciones al seguro de salud | G79: =+'OCTUBRE '!G79+NOVIEMBRE!G79+'DICIEMBRE 2025'!G79 -> 12854588 | H79: =+'OCTUBRE '!H79+NOVIEMBRE!H79+'DICIEMBRE 2025'!H79 -> 0 | I79: =SUM(G79:H79) -> 12854588
A80: 2 | B80: 1 | C80: 5 | D80: 1 | E80: 01 | F80: Contribuciones al seguro de salud | G80: =+'OCTUBRE '!G80+NOVIEMBRE!G80+'DICIEMBRE 2025'!G80 -> 12854588 | H80: =+'OCTUBRE '!H80+NOVIEMBRE!H80+'DICIEMBRE 2025'!H80 -> 0 | I80: =SUM(G80:H80) -> 12854588 | J80: =I80/$I$25 -> 0.026240715
A81: 2 | B81: 1 | C81: 5 | D81: 2 | F81: Contribuciones al seguro de pensiones | G81: =+'OCTUBRE '!G81+NOVIEMBRE!G81+'DICIEMBRE 2025'!G81 -> 12872452 | H81: =+'OCTUBRE '!H81+NOVIEMBRE!H81+'DICIEMBRE 2025'!H81 -> 0 | I81: =SUM(G81:H81) -> 12872452
A82: 2 | B82: 1 | C82: 5 | D82: 2 | E82: 01 | F82: Contribuciones al seguro de pensiones | G82: =+'OCTUBRE '!G82+NOVIEMBRE!G82+'DICIEMBRE 2025'!G82 -> 12872452 | H82: =+'OCTUBRE '!H82+NOVIEMBRE!H82+'DICIEMBRE 2025'!H82 -> 0 | I82: =SUM(G82:H82) -> 12872452 | J82: =I82/$I$25 -> 0.026277183
A83: 2 | B83: 1 | C83: 5 | D83: 3 | F83: Contribuciones al seguro de riesgo laboral | G83: =+'OCTUBRE '!G83+NOVIEMBRE!G83+'DICIEMBRE 2025'!G83 -> 2171151.5 | H83: =+'OCTUBRE '!H83+NOVIEMBRE!H83+'DICIEMBRE 2025'!H83 -> 0 | I83: =SUM(G83:H83) -> 2171151.5
A84: 2 | B84: 1 | C84: 5 | D84: 3 | E84: 01 | F84: Contribuciones al seguro de riesgo laboral | G84: =+'OCTUBRE '!G84+NOVIEMBRE!G84+'DICIEMBRE 2025'!G84 -> 2171151.5 | H84: =+'OCTUBRE '!H84+NOVIEMBRE!H84+'DICIEMBRE 2025'!H84 -> 0 | I84: =SUM(G84:H84) -> 2171151.5 | J84: =I84/$I$25 -> 0.0044320805
A85: 2 | B85: 1 | C85: 5 | D85: 4 | F85: Contribuciones al plan de retiro complementario | G85: =+'OCTUBRE '!G85+NOVIEMBRE!G85+'DICIEMBRE 2025'!G85 -> 0 | H85: =+'OCTUBRE '!H85+NOVIEMBRE!H85+'DICIEMBRE 2025'!H85 -> 0 | I85: =SUM(G85:H85) -> 0
A86: 2 | B86: 1 | C86: 5 | D86: 4 | E86: 01 | F86: Contribuciones al plan de retiro complementario | G86: =+'OCTUBRE '!G86+NOVIEMBRE!G86+'DICIEMBRE 2025'!G86 -> 0 | H86: =+'OCTUBRE '!H86+NOVIEMBRE!H86+'DICIEMBRE 2025'!H86 -> 0 | I86: =SUM(G86:H86) -> 0 | J86: =I86/$I$25 -> 0
A87: 2 | B87: 2 | F87: Servicios No Personales | G87: =+'OCTUBRE '!G87+NOVIEMBRE!G87+'DICIEMBRE 2025'!G87 -> 16306952 | H87: =+'OCTUBRE '!H87+NOVIEMBRE!H87+'DICIEMBRE 2025'!H87 -> 11649817 | I87: =SUM(G87:H87) -> 27956768 | J87: =I87/$I$25 -> 0.057069555
A88: 2 | B88: 2 | C88: 1 | F88: Servicios Básicos | G88: =+'OCTUBRE '!G88+NOVIEMBRE!G88+'DICIEMBRE 2025'!G88 -> 332805 | H88: =+'OCTUBRE '!H88+NOVIEMBRE!H88+'DICIEMBRE 2025'!H88 -> 3591616 | I88: =SUM(G88:H88) -> 3924421
A89: 2 | B89: 2 | C89: 1 | D89: 1 | F89: Radiocomunicación | G89: =+'OCTUBRE '!G89+NOVIEMBRE!G89+'DICIEMBRE 2025'!G89 -> 0 | H89: =+'OCTUBRE '!H89+NOVIEMBRE!H89+'DICIEMBRE 2025'!H89 -> 0 | I89: =SUM(G89:H89) -> 0
A90: 2 | B90: 2 | C90: 1 | D90: 1 | E90: 01 | F90: Radiocomunicación | G90: =+'OCTUBRE '!G90+NOVIEMBRE!G90+'DICIEMBRE 2025'!G90 -> 0 | H90: =+'OCTUBRE '!H90+NOVIEMBRE!H90+'DICIEMBRE 2025'!H90 -> 0 | I90: =SUM(G90:H90) -> 0 | J90: =I90/$I$25 -> 0
A91: 2 | B91: 2 | C91: 1 | D91: 2 | F91: Servicios telefónico de larga distancia | G91: =+'OCTUBRE '!G91+NOVIEMBRE!G91+'DICIEMBRE 2025'!G91 -> 0 | H91: =+'OCTUBRE '!H91+NOVIEMBRE!H91+'DICIEMBRE 2025'!H91 -> 0 | I91: =SUM(G91:H91) -> 0
A92: 2 | B92: 2 | C92: 1 | D92: 2 | E92: 01 | F92: Servicios telefónico de larga distancia | G92: =+'OCTUBRE '!G92+NOVIEMBRE!G92+'DICIEMBRE 2025'!G92 -> 0 | H92: =+'OCTUBRE '!H92+NOVIEMBRE!H92+'DICIEMBRE 2025'!H92 -> 0 | I92: =SUM(G92:H92) -> 0 | J92: =I92/$I$25 -> 0
A93: 2 | B93: 2 | C93: 1 | D93: 3 | F93: Teléfono local | G93: =+'OCTUBRE '!G93+NOVIEMBRE!G93+'DICIEMBRE 2025'!G93 -> 0 | H93: =+'OCTUBRE '!H93+NOVIEMBRE!H93+'DICIEMBRE 2025'!H93 -> 636616 | I93: =SUM(G93:H93) -> 636616
A94: 2 | B94: 2 | C94: 1 | D94: 3 | E94: 01 | F94: Teléfono local | G94: =+'OCTUBRE '!G94+NOVIEMBRE!G94+'DICIEMBRE 2025'!G94 -> 0 | H94: =+'OCTUBRE '!H94+NOVIEMBRE!H94+'DICIEMBRE 2025'!H94 -> 636616 | I94: =SUM(G94:H94) -> 636616 | J94: =I94/$I$25 -> 0.0012995562
A95: 2 | B95: 2 | C95: 1 | D95: 4 | F95: Telefax y correos | G95: =+'OCTUBRE '!G95+NOVIEMBRE!G95+'DICIEMBRE 2025'!G95 -> 0 | H95: =+'OCTUBRE '!H95+NOVIEMBRE!H95+'DICIEMBRE 2025'!H95 -> 0 | I95: =SUM(G95:H95) -> 0
A96: 2 | B96: 2 | C96: 1 | D96: 4 | E96: 01 | F96: Telefax y correos | G96: =+'OCTUBRE '!G96+NOVIEMBRE!G96+'DICIEMBRE 2025'!G96 -> 0 | H96: =+'OCTUBRE '!H96+NOVIEMBRE!H96+'DICIEMBRE 2025'!H96 -> 0 | I96: =SUM(G96:H96) -> 0 | J96: =I96/$I$25 -> 0
A97: 2 | B97: 2 | C97: 1 | D97: 5 | F97: Servicio de Internet y televisión por cable | G97: =+'OCTUBRE '!G97+NOVIEMBRE!G97+'DICIEMBRE 2025'!G97 -> 0 | H97: =+'OCTUBRE '!H97+NOVIEMBRE!H97+'DICIEMBRE 2025'!H97 -> 0 | I97: =SUM(G97:H97) -> 0
A98: 2 | B98: 2 | C98: 1 | D98: 5 | E98: 01 | F98: Servicio de Internet y televisión por cable | G98: =+'OCTUBRE '!G98+NOVIEMBRE!G98+'DICIEMBRE 2025'!G98 -> 0 | H98: =+'OCTUBRE '!H98+NOVIEMBRE!H98+'DICIEMBRE 2025'!H98 -> 0 | I98: =SUM(G98:H98) -> 0 | J98: =I98/$I$25 -> 0
A99: 2 | B99: 2 | C99: 1 | D99: 6 | F99: Electricidad | G99: =+'OCTUBRE '!G99+NOVIEMBRE!G99+'DICIEMBRE 2025'!G99 -> 0 | H99: =+'OCTUBRE '!H99+NOVIEMBRE!H99+'DICIEMBRE 2025'!H99 -> 0 | I99: =SUM(G99:H99) -> 0
A100: 2 | B100: 2 | C100: 1 | D100: 6 | E100: 01 | F100: Energía eléctrica | G100: =+'OCTUBRE '!G100+NOVIEMBRE!G100+'DICIEMBRE 2025'!G100 -> 0 | H100: =+'OCTUBRE '!H100+NOVIEMBRE!H100+'DICIEMBRE 2025'!H100 -> 0 | I100: =SUM(G100:H100) -> 0 | J100: =I100/$I$25 -> 0
A101: 2 | B101: 2 | C101: 1 | D101: 6 | E101: 02 | F101: Electricidad no cortable | G101: =+'OCTUBRE '!G101+NOVIEMBRE!G101+'DICIEMBRE 2025'!G101 -> 0 | H101: =+'OCTUBRE '!H101+NOVIEMBRE!H101+'DICIEMBRE 2025'!H101 -> 0 | I101: =SUM(G101:H101) -> 0 | J101: =I101/$I$25 -> 0
A102: 2 | B102: 2 | C102: 1 | D102: 7 | F102: Agua | G102: =+'OCTUBRE '!G102+NOVIEMBRE!G102+'DICIEMBRE 2025'!G102 -> 332805 | H102: =+'OCTUBRE '!H102+NOVIEMBRE!H102+'DICIEMBRE 2025'!H102 -> 0 | I102: =SUM(G102:H102) -> 332805
...

Sheet ENERO-JUNIO 2025
A1: Form. No.6 SRS
A3: Servicio Nacional de Salud
A4: Dirección de Fizcalización
A5: Consolidado de Ingresos y Gastos por Fuente de Financiamiento
A6: HOSPITAL MATERNO INFANTIL SAN LORENZO DE LOS MINA
A7: ENERO-JUNIO 2025
C8: Ingresos Generales:
E9: 1.- Balance Inicial / Fuente:
E10: Anticipo Financiero | G10: 0 | H10: Otros Aportes
E11: Transferencias Corrientes | G11: 0
E12: Venta de Servicios
E13: 2.- Ingresos por Fuente / Cuenta
E14: Anticipo Financiero | H14: Otros Aportes
E15: Transferencias Corrientes | H15: Aportes Nomina SNS
E16: Venta de Servicios
H17: TOTAL INGRESOS RDS | J17: =+G10+G11+G12+J10+G14+G15+G16+J14+J15 -> 0
A21: 1 | F21: 2 | G21: 3 | J21: 4 | K21: 5
A22: Código Presupuestario | F22: Descripción Gasto por Cuenta | G22: Distribución del Gasto por Fuente de Financiamiento | J22: TOTAL | K22: %
A23: Tipo | B23: Objeto | C23: Cuenta | D23: Sub-Cuenta | E23: Auxiliar | G23: Fondo 100 | H23: Venta de Servicios/ Otros Aportes | I23: Aportes Nomina SNS
A25: 2 | F25: Gastos | G25: =+G26+G87+G212+G330+G336+G463 -> 5.4471224e+08 | H25: =+'[5]junio 2025'!H25+'[5]mayo 2025'!H25+[5]abril!H25+[5]marzo!H25+[5]febrero!H25+'[5]enero '!H25 -> 46624960 | I25: =+I26+I87+I212+I330+I336+I463 -> 0 | J25: =SUM(G25:I25) -> 5.913372e+08 | K25: =+K26+K87+K212+K330+K336+K463 -> 1
A26: 2 | B26: 1 | F26: Servicios Personales | G26: =+G27+G51+G64+G71+G78 -> 3.9833106e+08 | H26: =+'[5]junio 2025'!H26+'[5]mayo 2025'!H26+[5]abril!H26+[5]marzo!H26+[5]febrero!H26+'[5]enero '!H26 -> 5231553.6 | I26: =+I27+I51+I64+I71+I78 -> 0 | J26: =SUM(G26:I26) -> 4.0356261e+08 | K26: =J26/$J$25 -> 0.68245767
A27: 2 | B27: 1 | C27: 1 | F27: Remuneraciones | G27: =+G28+G35+G42+G44+G46 -> 3.2802999e+08 | H27: =+'[5]junio 2025'!H27+'[5]mayo 2025'!H27+[5]abril!H27+[5]marzo!H27+[5]febrero!H27+'[5]enero '!H27 -> 0 | I27: =+I28+I35+I42+I44+I46 -> 0 | J27: =SUM(G27:I27) -> 3.2802999e+08 | K27: =J27/$J$25 -> 0.55472577
A28: 2 | B28: 1 | C28: 1 | D28: 1 | F28: Remuneraciones al personal fijo | G28: =SUM(G29:G34) -> 3.1950747e+08 | H28: =+'[5]junio 2025'!H28+'[5]mayo 2025'!H28+[5]abril!H28+[5]marzo!H28+[5]febrero!H28+'[5]enero '!H28 -> 0 | I28: =SUM(I29:I34) -> 0 | J28: =SUM(G28:I28) -> 3.1950747e+08 | K28: =J28/$J$25 -> 0.54031349
A29: 2 | B29: 1 | C29: 1 | D29: 1 | E29: 01 | F29: Sueldos a empleados fijos | G29: 3.1950747e+08 | H29: =+'[5]junio 2025'!H29+'[5]mayo 2025'!H29+[5]abril!H29+[5]marzo!H29+[5]febrero!H29+'[5]enero '!H29 -> 0 | I29: ='[6]CUENTA T NOMINA SNS'!A58 -> 0 | J29: =SUM(G29:I29) -> 3.1950747e+08 | K29: =J29/$J$25 -> 0.54031349
A30: 2 | B30: 1 | C30: 1 | D30: 1 | E30: 02 | F30: Sueldos a médicos | G30: ='[6]CUENTA T FONDO 100'!B288 -> 0 | H30: =+'[5]junio 2025'!H30+'[5]mayo 2025'!H30+[5]abril!H30+[5]marzo!H30+[5]febrero!H30+'[5]enero '!H30 -> 0 | I30: ='[6]CUENTA T NOMINA SNS'!B58 -> 0 | J30: =SUM(G30:I30) -> 0 | K30: =J30/$J$25 -> 0
A31: 2 | B31: 1 | C31: 1 | D31: 1 | E31: 03 | F31: Ascensos a militares | G31: ='[6]CUENTA T FONDO 100'!C288 -> 0 | H31: =+'[5]junio 2025'!H31+'[5]mayo 2025'!H31+[5]abril!H31+[5]marzo!H31+[5]febrero!H31+'[5]enero '!H31 -> 0 | I31: ='[6]CUENTA T NOMINA SNS'!C58 -> 0 | J31: =SUM(G31:I31) -> 0 | K31: =J31/$J$25 -> 0
A32: 2 | B32: 1 | C32: 1 | D32: 1 | E32: 04 | F32: Nuevas plazas maestros | G32: ='[6]CUENTA T FONDO 100'!D288 -> 0 | H32: =+'[5]junio 2025'!H32+'[5]mayo 2025'!H32+[5]abril!H32+[5]marzo!H32+[5]febrero!H32+'[5]enero '!H32 -> 0 | I32: ='[6]CUENTA T NOMINA SNS'!D58 -> 0 | J32: =SUM(G32:I32) -> 0 | K32: =J32/$J$25 -> 0
A33: 2 | B33: 1 | C33: 1 | D33: 1 | E33: 05 | F33: Incentivos y escalafón | G33: ='[6]CUENTA T FONDO 100'!E288 -> 0 | H33: =+'[5]junio 2025'!H33+'[5]mayo 2025'!H33+[5]abril!H33+[5]marzo!H33+[5]febrero!H33+'[5]enero '!H33 -> 0 | I33: ='[6]CUENTA T NOMINA SNS'!E58 -> 0 | J33: =SUM(G33:I33) -> 0 | K33: =J33/$J$25 -> 0
A34: 2 | B34: 1 | C34: 1 | D34: 1 | E34: 06 | F34: Nuevas plazas a médicos | G34: ='[6]CUENTA T FONDO 100'!F288 -> 0 | H34: =+'[5]junio 2025'!H34+'[5]mayo 2025'!H34+[5]abril!H34+[5]marzo!H34+[5]febrero!H34+'[5]enero '!H34 -> 0 | I34: ='[6]CUENTA T NOMINA SNS'!F58 -> 0 | J34: =SUM(G34:I34) -> 0 | K34: =J34/$J$25 -> 0
A35: 2 | B35: 1 | C35: 1 | D35: 2 | F35: Remuneraciones al personal con carácter transitorio | G35: =SUM(G36:G41) -> 6546186.2 | H35: =+'[5]junio 2025'!H35+'[5]mayo 2025'!H35+[5]abril!H35+[5]marzo!H35+[5]febrero!H35+'[5]enero '!H35 -> 0 | I35: =SUM(I36:I41) -> 0 | J35: =SUM(G35:I35) -> 6546186.2
A36: 2 | B36: 1 | C36: 1 | D36: 2 | E36: 03 | F36: Suplencias | G36: ='[6]CUENTA T FONDO 100'!G288 -> 0 | H36: =+'[5]junio 2025'!H36+'[5]mayo 2025'!H36+[5]abril!H36+[5]marzo!H36+[5]febrero!H36+'[5]enero '!H36 -> 0 | I36: ='[6]CUENTA T NOMINA SNS'!G58 -> 0 | J36: =SUM(G36:I36) -> 0 | K36: =J36/$J$25 -> 0
A37: 2 | B37: 1 | C37: 1 | D37: 2 | E37: 05 | F37: Sueldo al personal nominal en período probatorio | G37: ='[6]CUENTA T FONDO 100'!H288 -> 0 | H37: =+'[5]junio 2025'!H37+'[5]mayo 2025'!H37+[5]abril!H37+[5]marzo!H37+[5]febrero!H37+'[5]enero '!H37 -> 0 | I37: ='[6]CUENTA T NOMINA SNS'!H58 -> 0 | J37: =SUM(G37:I37) -> 0 | K37: =J37/$J$25 -> 0
A38: 2 | B38: 1 | C38: 1 | D38: 2 | E38: 06 | F38: Jornales | G38: ='[6]CUENTA T FONDO 100'!I288 -> 0 | H38: =+'[5]junio 2025'!H38+'[5]mayo 2025'!H38+[5]abril!H38+[5]marzo!H38+[5]febrero!H38+'[5]enero '!H38 -> 0 | I38: ='[6]CUENTA T NOMINA SNS'!I58 -> 0 | J38: =SUM(G38:I38) -> 0 | K38: =J38/$J$25 -> 0
A39: 2 | B39: 1 | C39: 1 | D39: 2 | E39: 08 | F39: Empleados temporales | G39: 6546186.2 | H39: =+'[5]junio 2025'!H39+'[5]mayo 2025'!H39+[5]abril!H39+[5]marzo!H39+[5]febrero!H39+'[5]enero '!H39 -> 0 | I39: ='[6]CUENTA T NOMINA SNS'!J58 -> 0 | J39: =SUM(G39:I39) -> 6546186.2 | K39: =J39/$J$25 -> 0.011070141
A40: 2 | B40: 1 | C40: 1 | D40: 2 | E40: 09 | F40: Personal de carácter eventual | G40: ='[6]CUENTA T FONDO 100'!K288 -> 0 | H40: =+'[5]junio 2025'!H40+'[5]mayo 2025'!H40+[5]abril!H40+[5]marzo!H40+[5]febrero!H40+'[5]enero '!H40 -> 0 | I40: ='[6]CUENTA T NOMINA SNS'!K58 -> 0 | J40: =SUM(G40:I40) -> 0 | K40: =J40/$J$25 -> 0
A41: 2 | B41: 1 | C41: 1 | D41: 2 | E41: 11 | F41: Interinato | G41: ='[6]CUENTA T FONDO 100'!L288 -> 0 | H41: =+'[5]junio 2025'!H41+'[5]mayo 2025'!H41+[5]abril!H41+[5]marzo!H41+[5]febrero!H41+'[5]enero '!H41 -> 0 | I41: ='[6]CUENTA T NOMINA SNS'!L58 -> 0 | J41: =SUM(G41:I41) -> 0 | K41: =J41/$J$25 -> 0
A42: 2 | B42: 1 | C42: 1 | D42: 3 | F42: Sueldos al personal fijo en trámite de pensiones | G42: =SUM(G43) -> 0 | H42: =+'[5]junio 2025'!H42+'[5]mayo 2025'!H42+[5]abril!H42+[5]marzo!H42+[5]febrero!H42+'[5]enero '!H42 -> 0 | I42: =SUM(I43) -> 0 | J42: =SUM(G42:I42) -> 0
A43: 2 | B43: 1 | C43: 1 | D43: 3 | E43: 01 | F43: Sueldos al personal fijo en trámite de pensiones | G43: ='[6]CUENTA T FONDO 100'!M288 -> 0 | H43: =+'[5]junio 2025'!H43+'[5]mayo 2025'!H43+[5]abril!H43+[5]marzo!H43+[5]febrero!H43+'[5]enero '!H43 -> 0 | I43: ='[6]CUENTA T NOMINA SNS'!M58 -> 0 | J43: =SUM(G43:I43) -> 0 | K43: =J43/$J$25 -> 0
A44: 2 | B44: 1 | C44: 1 | D44: 4 | F44: Sueldo anual no. 13 | G44: =SUM(G45) -> 0 | H44: =+'[5]junio 2025'!H44+'[5]mayo 2025'!H44+[5]abril!H44+[5]marzo!H44+[5]febrero!H44+'[5]enero '!H44 -> 0 | I44: =SUM(I45) -> 0 | J44: =SUM(G44:I44) -> 0
A45: 2 | B45: 1 | C45: 1 | D45: 4 | E45: 01 | F45: Sueldo anual no. 13 | G45: ='[6]CUENTA T FONDO 100'!N288 -> 0 | H45: =+'[5]junio 2025'!H45+'[5]mayo 2025'!H45+[5]abril!H45+[5]marzo!H45+[5]febrero!H45+'[5]enero '!H45 -> 0 | I45: ='[6]CUENTA T NOMINA SNS'!N58 -> 0 | J45: =SUM(G45:I45) -> 0 | K45: =J45/$J$25 -> 0
A46: 2 | B46: 1 | C46: 1 | D46: 5 | F46: Prestaciones económinas | G46: =SUM(G47:G50) -> 1976333.7 | H46: =+'[5]junio 2025'!H46+'[5]mayo 2025'!H46+[5]abril!H46+[5]marzo!H46+[5]febrero!H46+'[5]enero '!H46 -> 0 | I46: =SUM(I47:I50) -> 0 | J46: =SUM(G46:I46) -> 1976333.7
A47: 2 | B47: 1 | C47: 1 | D47: 5 | E47: 01 | F47: Prestaciones económinas | G47: ='[6]CUENTA T FONDO 100'!O288 -> 0 | H47: =+'[5]junio 2025'!H47+'[5]mayo 2025'!H47+[5]abril!H47+[5]marzo!H47+[5]febrero!H47+'[5]enero '!H47 -> 0 | I47: ='[6]CUENTA T NOMINA SNS'!O58 -> 0 | J47: =SUM(G47:I47) -> 0 | K47: =J47/$J$25 -> 0
A48: 2 | B48: 1 | C48: 1 | D48: 5 | E48: 02 | F48: Pago de porcentaje por desvinculación de cargo | G48: ='[6]CUENTA T FONDO 100'!P288 -> 0 | H48: =+'[5]junio 2025'!H48+'[5]mayo 2025'!H48+[5]abril!H48+[5]marzo!H48+[5]febrero!H48+'[5]enero '!H48 -> 0 | I48: ='[6]CUENTA T NOMINA SNS'!P58 -> 0 | J48: =SUM(G48:I48) -> 0 | K48: =J48/$J$25 -> 0
A49: 2 | B49: 1 | C49: 1 | D49: 5 | E49: 03 | F49: Prestación laboral por desvinculación | G49: 1119133.3 | H49: =+'[5]junio 2025'!H49+'[5]mayo 2025'!H49+[5]abril!H49+[5]marzo!H49+[5]febrero!H49+'[5]enero '!H49 -> 0 | I49: ='[6]CUENTA T NOMINA SNS'!Q58 -> 0 | J49: =SUM(G49:I49) -> 1119133.3 | K49: =J49/$J$25 -> 0.0018925468
A50: 2 | B50: 1 | C50: 1 | D50: 5 | E50: 04 | F50: Proporción de vacaciones no disfrutadas | G50: 857200.41 | H50: =+'[5]junio 2025'!H50+'[5]mayo 2025'!H50+[5]abril!H50+[5]marzo!H50+[5]febrero!H50+'[5]enero '!H50 -> 0 | I50: ='[6]CUENTA T NOMINA SNS'!R58 -> 0 | J50: =SUM(G50:I50) -> 857200.41 | K50: =J50/$J$25 -> 0.0014495966
A51: 2 | B51: 1 | C51: 2 | F51: Sobresueldos | G51: =+G52+G54 -> 20130198 | H51: =+'[5]junio 2025'!H51+'[5]mayo 2025'!H51+[5]abril!H51+[5]marzo!H51+[5]febrero!H51+'[5]enero '!H51 -> 5231553.6 | I51: =+I52+I54 -> 0 | J51: =SUM(G51:I51) -> 25361751
A52: 2 | B52: 1 | C52: 2 | D52: 1 | F52: Primas por antigüedad | G52: =SUM(G53) -> 16426618 | H52: =+'[5]junio 2025'!H52+'[5]mayo 2025'!H52+[5]abril!H52+[5]marzo!H52+[5]febrero!H52+'[5]enero '!H52 -> 0 | I52: =SUM(I53) -> 0 | J52: =SUM(G52:I52) -> 16426618
A53: 2 | B53: 1 | C53: 2 | D53: 1 | E53: 01 | F53: Primas por antigüedad | G53: 16426618 | H53: =+'[5]junio 2025'!H53+'[5]mayo 2025'!H53+[5]abril!H53+[5]marzo!H53+[5]febrero!H53+'[5]enero '!H53 -> 0 | I53: ='[6]CUENTA T NOMINA SNS'!S58 -> 0 | J53: =SUM(G53:I53) -> 16426618 | K53: =J53/$J$25 -> 0.027778767
A54: 2 | B54: 1 | C54: 2 | D54: 2 | F54: Compensación | G54: =SUM(G55:G63) -> 3703579.3 | H54: =+'[5]junio 2025'!H54+'[5]mayo 2025'!H54+[5]abril!H54+[5]marzo!H54+[5]febrero!H54+'[5]enero '!H54 -> 5231553.6 | I54: =SUM(I55:I63) -> 0 | J54: =SUM(G54:I54) -> 8935132.9
A55: 2 | B55: 1 | C55: 2 | D55: 2 | E55: 01 | F55: Compensación por gastos de alimentación | G55: ='[6]CUENTA T FONDO 100'!T288 -> 0 | H55: =+'[5]junio 2025'!H55+'[5]mayo 2025'!H55+[5]abril!H55+[5]marzo!H55+[5]febrero!H55+'[5]enero '!H55 -> 0 | I55: ='[6]CUENTA T NOMINA SNS'!T58 -> 0 | J55: =SUM(G55:I55) -> 0 | K55: =J55/$J$25 -> 0
A56: 2 | B56: 1 | C56: 2 | D56: 2 | E56: 03 | F56: Pago de horas extraordinarias | G56: ='[6]CUENTA T FONDO 100'!U288 -> 0 | H56: =+'[5]junio 2025'!H56+'[5]mayo 2025'!H56+[5]abril!H56+[5]marzo!H56+[5]febrero!H56+'[5]enero '!H56 -> 0 | I56: ='[6]CUENTA T NOMINA SNS'!U58 -> 0 | J56: =SUM(G56:I56) -> 0 | K56: =J56/$J$25 -> 0
A57: 2 | B57: 1 | C57: 2 | D57: 2 | E57: 04 | F57: Prima de transporte | G57: ='[6]CUENTA T FONDO 100'!V288 -> 0 | H57: =+'[5]junio 2025'!H57+'[5]mayo 2025'!H57+[5]abril!H57+[5]marzo!H57+[5]febrero!H57+'[5]enero '!H57 -> 0 | I57: ='[6]CUENTA T NOMINA SNS'!V58 -> 0 | J57: =SUM(G57:I57) -> 0 | K57: =J57/$J$25 -> 0
A58: 2 | B58: 1 | C58: 2 | D58: 2 | E58: 05 | F58: Compensación servicios de Seguridad | G58: 270000 | H58: =+'[5]junio 2025'!H58+'[5]mayo 2025'!H58+[5]abril!H58+[5]marzo!H58+[5]febrero!H58+'[5]enero '!H58 -> 0 | I58: ='[6]CUENTA T NOMINA SNS'!W58 -> 0 | J58: =SUM(G58:I58) -> 270000 | K58: =J58/$J$25 -> 0.00045659228
A59: 2 | B59: 1 | C59: 2 | D59: 2 | E59: 06 | F59: Incentivo por Rendimieto Individual | G59: ='[6]CUENTA T FONDO 100'!X288 -> 0 | H59: =+'[5]junio 2025'!H59+'[5]mayo 2025'!H59+[5]abril!H59+[5]marzo!H59+[5]febrero!H59+'[5]enero '!H59 -> 5231553.6 | I59: ='[6]CUENTA T NOMINA SNS'!X58 -> 0 | J59: =SUM(G59:I59) -> 5231553.6 | K59: =J59/$J$25 -> 0.0088469888
A60: 2 | B60: 1 | C60: 2 | D60: 2 | E60: 07 | F60: Compensación por distancia | G60: ='[6]CUENTA T FONDO 100'!Y288 -> 0 | H60: =+'[5]junio 2025'!H60+'[5]mayo 2025'!H60+[5]abril!H60+[5]marzo!H60+[5]febrero!H60+'[5]enero '!H60 -> 0 | I60: ='[6]CUENTA T NOMINA SNS'!Y58 -> 0 | J60: =SUM(G60:I60) -> 0 | K60: =J60/$J$25 -> 0
A61: 2 | B61: 1 | C61: 2 | D61: 2 | E61: 08 | F61: Compensaciones especiales | G61: 1999000 | H61: =+'[5]junio 2025'!H61+'[5]mayo 2025'!H61+[5]abril!H61+[5]marzo!H61+[5]febrero!H61+'[5]enero '!H61 -> 0 | I61: ='[6]CUENTA T NOMINA SNS'!Z58 -> 0 | J61: =SUM(G61:I61) -> 1999000 | K61: =J61/$J$25 -> 0.0033804739
A62: 2 | B62: 1 | C62: 2 | D62: 2 | E62: 09 | F62: Bono por desempeño a servidores de carrera | G62: 443970.11 | H62: =+'[5]junio 2025'!H62+'[5]mayo 2025'!H62+[5]abril!H62+[5]marzo!H62+[5]febrero!H62+'[5]enero '!H62 -> 0 | I62: ='[6]CUENTA T NOMINA SNS'!AA58 -> 0 | J62: =SUM(G62:I62) -> 443970.11 | K62: =J62/$J$25 -> 0.00075079009
A63: 2 | B63: 1 | C63: 2 | D63: 2 | E63: 10 | F63: Compensacion por cumplimiento de indicadores | G63: =308018.04+682591.14 -> 990609.18 | H63: =+'[5]junio 2025'!H63+'[5]mayo 2025'!H63+[5]abril!H63+[5]marzo!H63+[5]febrero!H63+'[5]enero '!H63 -> 0 | I63: ='[6]CUENTA T NOMINA SNS'!AB58 -> 0 | J63: =SUM(G63:I63) -> 990609.18 | K63: =J63/$J$25 -> 0.0016752019
A64: 2 | B64: 1 | C64: 3 | F64: Dietas y Gastos de Representación | G64: =+G65+G68 -> 0 | H64: =+'[5]junio 2025'!H64+'[5]mayo 2025'!H64+[5]abril!H64+[5]marzo!H64+[5]febrero!H64+'[5]enero '!H64 -> 0 | I64: =+I65+I68 -> 0 | J64: =SUM(G64:I64) -> 0
A65: 2 | B65: 1 | C65: 3 | D65: 1 | F65: Dietas | G65: =SUM(G66:G67) -> 0 | H65: =+'[5]junio 2025'!H65+'[5]mayo 2025'!H65+[5]abril!H65+[5]marzo!H65+[5]febrero!H65+'[5]enero '!H65 -> 0 | I65: =SUM(I66:I67) -> 0 | J65: =SUM(G65:I65) -> 0
A66: 2 | B66: 1 | C66: 3 | D66: 1 | E66: 01 | F66: Dietas en el país | G66: ='[6]CUENTA T FONDO 100'!AC288 -> 0 | H66: =+'[5]junio 2025'!H66+'[5]mayo 2025'!H66+[5]abril!H66+[5]marzo!H66+[5]febrero!H66+'[5]enero '!H66 -> 0 | I66: ='[6]CUENTA T NOMINA SNS'!AC58 -> 0 | J66: =SUM(G66:I66) -> 0 | K66: =J66/$J$25 -> 0
A67: 2 | B67: 1 | C67: 3 | D67: 1 | E67: 02 | F67: Dietas en el exterior | G67: ='[6]CUENTA T FONDO 100'!AD288 -> 0 | H67: =+'[5]junio 2025'!H67+'[5]mayo 2025'!H67+[5]abril!H67+[5]marzo!H67+[5]febrero!H67+'[5]enero '!H67 -> 0 | I67: ='[6]CUENTA T NOMINA SNS'!AD58 -> 0 | J67: =SUM(G67:I67) -> 0 | K67: =J67/$J$25 -> 0
A68: 2 | B68: 1 | C68: 3 | D68: 2 | F68: Gastos de representación | G68: =SUM(G69:G70) -> 0 | H68: =+'[5]junio 2025'!H68+'[5]mayo 2025'!H68+[5]abril!H68+[5]marzo!H68+[5]febrero!H68+'[5]enero '!H68 -> 0 | I68: =SUM(I69:I70) -> 0 | J68: =SUM(G68:I68) -> 0
A69: 2 | B69: 1 | C69: 3 | D69: 2 | E69: 01 | F69: Gastos de representación en el país | G69: ='[6]CUENTA T FONDO 100'!AE288 -> 0 | H69: =+'[5]junio 2025'!H69+'[5]mayo 2025'!H69+[5]abril!H69+[5]marzo!H69+[5]febrero!H69+'[5]enero '!H69 -> 0 | I69: ='[6]CUENTA T NOMINA SNS'!AE58 -> 0 | J69: =SUM(G69:I69) -> 0 | K69: =J69/$J$25 -> 0
A70: 2 | B70: 1 | C70: 3 | D70: 2 | E70: 02 | F70: Gastos de representación en el exterior | G70: ='[6]CUENTA T FONDO 100'!AF288 -> 0 | H70: =+'[5]junio 2025'!H70+'[5]mayo 2025'!H70+[5]abril!H70+[5]marzo!H70+[5]febrero!H70+'[5]enero '!H70 -> 0 | I70: ='[6]CUENTA T NOMINA SNS'!AF58 -> 0 | J70: =SUM(G70:I70) -> 0 | K70: =J70/$J$25 -> 0
A71: 2 | B71: 1 | C71: 4 | F71: Gratificaciones y Bonificaciones | G71: =+G72+G74 -> 0 | H71: =+'[5]junio 2025'!H71+'[5]mayo 2025'!H71+[5]abril!H71+[5]marzo!H71+[5]febrero!H71+'[5]enero '!H71 -> 0 | I71: =+I72+I74 -> 0 | J71: =SUM(G71:I71) -> 0
A72: 2 | B72: 1 | C72: 4 | D72: 1 | F72: Bonificaciones | G72: =SUM(G73) -> 0 | H72: =+'[5]junio 2025'!H72+'[5]mayo 2025'!H72+[5]abril!H72+[5]marzo!H72+[5]febrero!H72+'[5]enero '!H72 -> 0 | I72: =SUM(I73) -> 0 | J72: =SUM(G72:I72) -> 0
A73: 2 | B73: 1 | C73: 4 | D73: 1 | E73: 01 | F73: Bonificaciones | G73: ='[6]CUENTA T FONDO 100'!AG288 -> 0 | H73: =+'[5]junio 2025'!H73+'[5]mayo 2025'!H73+[5]abril!H73+[5]marzo!H73+[5]febrero!H73+'[5]enero '!H73 -> 0 | I73: ='[6]CUENTA T NOMINA SNS'!AG58 -> 0 | J73: =SUM(G73:I73) -> 0 | K73: =J73/$J$25 -> 0
A74: 2 | B74: 1 | C74: 4 | D74: 2 | F74: Otras Gratificaciones y Bonificaciones | G74: =SUM(G75:G77) -> 0 | H74: =+'[5]junio 2025'!H74+'[5]mayo 2025'!H74+[5]abril!H74+[5]marzo!H74+[5]febrero!H74+'[5]enero '!H74 -> 0 | I74: =SUM(I75:I77) -> 0 | J74: =SUM(G74:I74) -> 0
A75: 2 | B75: 1 | C75: 4 | D75: 2 | E75: 01 | F75: Bono escolar | G75: ='[6]CUENTA T FONDO 100'!AH288 -> 0 | H75: =+'[5]junio 2025'!H75+'[5]mayo 2025'!H75+[5]abril!H75+[5]marzo!H75+[5]febrero!H75+'[5]enero '!H75 -> 0 | I75: ='[6]CUENTA T NOMINA SNS'!AH58 -> 0 | J75: =SUM(G75:I75) -> 0 | K75: =J75/$J$25 -> 0
A76: 2 | B76: 1 | C76: 4 | D76: 2 | E76: 02 | F76: Gratificaciones por pasantías | G76: ='[6]CUENTA T FONDO 100'!AI288 -> 0 | H76: =+'[5]junio 2025'!H76+'[5]mayo 2025'!H76+[5]abril!H76+[5]marzo!H76+[5]febrero!H76+'[5]enero '!H76 -> 0 | I76: ='[6]CUENTA T NOMINA SNS'!AI58 -> 0 | J76: =SUM(G76:I76) -> 0 | K76: =J76/$J$25 -> 0
A77: 2 | B77: 1 | C77: 4 | D77: 2 | E77: 03 | F77: Gratificaciones por aniversario de institución | G77: ='[6]CUENTA T FONDO 100'!AJ288 -> 0 | H77: =+'[5]junio 2025'!H77+'[5]mayo 2025'!H77+[5]abril!H77+[5]marzo!H77+[5]febrero!H77+'[5]enero '!H77 -> 0 | I77: ='[6]CUENTA T NOMINA SNS'!AJ58 -> 0 | J77: =SUM(G77:I77) -> 0 | K77: =J77/$J$25 -> 0
A78: 2 | B78: 1 | C78: 5 | F78: Contribuciones a la Seguridad Social y Riesgo Laboral | G78: =+G79+G81+G83+G85 -> 50170874 | H78: =+'[5]junio 2025'!H78+'[5]mayo 2025'!H78+[5]abril!H78+[5]marzo!H78+[5]febrero!H78+'[5]enero '!H78 -> 0 | I78: =+I79+I81+I83+I85 -> 0 | J78: =SUM(G78:I78) -> 50170874
A79: 2 | B79: 1 | C79: 5 | D79: 1 | F79: Contribuciones al seguro de salud | G79: =SUM(G80) -> 23117218 | H79: =+'[5]junio 2025'!H79+'[5]mayo 2025'!H79+[5]abril!H79+[5]marzo!H79+[5]febrero!H79+'[5]enero '!H79 -> 0 | I79: =SUM(I80) -> 0 | J79: =SUM(G79:I79) -> 23117218
A80: 2 | B80: 1 | C80: 5 | D80: 1 | E80: 01 | F80: Contribuciones al seguro de salud | G80: 23117218 | H80: =+'[5]junio 2025'!H80+'[5]mayo 2025'!H80+[5]abril!H80+[5]marzo!H80+[5]febrero!H80+'[5]enero '!H80 -> 0 | I80: ='[6]CUENTA T NOMINA SNS'!AK58 -> 0 | J80: =SUM(G80:I80) -> 23117218 | K80: =J80/$J$25 -> 0.039093123
A81: 2 | B81: 1 | C81: 5 | D81: 2 | F81: Contribuciones al seguro de pensiones | G81: =SUM(G82) -> 23149812 | H81: =+'[5]junio 2025'!H81+'[5]mayo 2025'!H81+[5]abril!H81+[5]marzo!H81+[5]febrero!H81+'[5]enero '!H81 -> 0 | I81: =SUM(I82) -> 0 | J81: =SUM(G81:I81) -> 23149812
A82: 2 | B82: 1 | C82: 5 | D82: 2 | E82: 01 | F82: Contribuciones al seguro de pensiones | G82: 23149812 | H82: =+'[5]junio 2025'!H82+'[5]mayo 2025'!H82+[5]abril!H82+[5]marzo!H82+[5]febrero!H82+'[5]enero '!H82 -> 0 | I82: ='[6]CUENTA T NOMINA SNS'!AL58 -> 0 | J82: =SUM(G82:I82) -> 23149812 | K82: =J82/$J$25 -> 0.039148242
A83: 2 | B83: 1 | C83: 5 | D83: 3 | F83: Contribuciones al seguro de riesgo laboral | G83: =SUM(G84) -> 3903844.8 | H83: =+'[5]junio 2025'!H83+'[5]mayo 2025'!H83+[5]abril!H83+[5]marzo!H83+[5]febrero!H83+'[5]enero '!H83 -> 0 | I83: =SUM(I84) -> 0 | J83: =SUM(G83:I83) -> 3903844.8
A84: 2 | B84: 1 | C84: 5 | D84: 3 | E84: 01 | F84: Contribuciones al seguro de riesgo laboral | G84: 3903844.8 | H84: =+'[5]junio 2025'!H84+'[5]mayo 2025'!H84+[5]abril!H84+[5]marzo!H84+[5]febrero!H84+'[5]enero '!H84 -> 0 | I84: ='[6]CUENTA T NOMINA SNS'!AM58 -> 0 | J84: =SUM(G84:I84) -> 3903844.8 | K84: =J84/$J$25 -> 0.0066017236
A85: 2 | B85: 1 | C85: 5 | D85: 4 | F85: Contribuciones al plan de retiro complementario | G85: =SUM(G86) -> 0 | H85: =+'[5]junio 2025'!H85+'[5]mayo 2025'!H85+[5]abril!H85+[5]marzo!H85+[5]febrero!H85+'[5]enero '!H85 -> 0 | I85: =SUM(I86) -> 0 | J85: =SUM(G85:I85) -> 0
A86: 2 | B86: 1 | C86: 5 | D86: 4 | E86: 01 | F86: Contribuciones al plan de retiro complementario | G86: ='[6]CUENTA T FONDO 100'!AN288 -> 0 | H86: =+'[5]junio 2025'!H86+'[5]mayo 2025'!H86+[5]abril!H86+[5]marzo!H86+[5]febrero!H86+'[5]enero '!H86 -> 0 | I86: ='[6]CUENTA T NOMINA SNS'!AN58 -> 0 | J86: =SUM(G86:I86) -> 0 | K86: =J86/$J$25 -> 0
A87: 2 | B87: 2 | F87: Servicios No Personales | G87: =G88+G106+G111+G116+G125+G148+G157+G179+G208 -> 19440183 | H87: =+'[5]junio 2025'!H87+'[5]mayo 2025'!H87+[5]abril!H87+[5]marzo!H87+[5]febrero!H87+'[5]enero '!H87 -> 15572435 | I87: =I88+I106+I111+I116+I125+I148+I157+I179+I208 -> 0 | J87: =SUM(G87:I87) -> 35012618 | K87: =J87/$J$25 -> 0.059209226
A88: 2 | B88: 2 | C88: 1 | F88: Servicios Básicos | G88: =+G89+G91+G93+G95+G97+G99+G102+G104 -> 2201629.3 | H88: =+'[5]junio 2025'!H88+'[5]mayo 2025'!H88+[5]abril!H88+[5]marzo!H88+[5]febrero!H88+'[5]enero '!H88 -> 4690142.6 | I88: =+I89+I91+I93+I95+I97+I99+I102+I104 -> 0 | J88: =SUM(G88:I88) -> 6891771.9
A89: 2 | B89: 2 | C89: 1 | D89: 1 | F89: Radiocomunicación | G89: =SUM(G90) -> 0 | H89: =+'[5]junio 2025'!H89+'[5]mayo 2025'!H89+[5]abril!H89+[5]marzo!H89+[5]febrero!H89+'[5]enero '!H89 -> 0 | I89: =SUM(I90) -> 0 | J89: =SUM(G89:I89) -> 0
A90: 2 | B90: 2 | C90: 1 | D90: 1 | E90: 01 | F90: Radiocomunicación | G90: ='[6]CUENTA T FONDO 100'!AO288 -> 0 | H90: =+'[5]junio 2025'!H90+'[5]mayo 2025'!H90+[5]abril!H90+[5]marzo!H90+[5]febrero!H90+'[5]enero '!H90 -> 0 | J90: =SUM(G90:I90) -> 0 | K90: =J90/$J$25 -> 0
A91: 2 | B91: 2 | C91: 1 | D91: 2 | F91: Servicios telefónico de larga distancia | G91: =SUM(G92) -> 0 | H91: =+'[5]junio 2025'!H91+'[5]mayo 2025'!H91+[5]abril!H91+[5]marzo!H91+[5]febrero!H91+'[5]enero '!H91 -> 0 | I91: =SUM(I92) -> 0 | J91: =SUM(G91:I91) -> 0
A92: 2 | B92: 2 | C92: 1 | D92: 2 | E92: 01 | F92: Servicios telefónico de larga distancia | G92: ='[6]CUENTA T FONDO 100'!AP288 -> 0 | H92: =+'[5]junio 2025'!H92+'[5]mayo 2025'!H92+[5]abril!H92+[5]marzo!H92+[5]febrero!H92+'[5]enero '!H92 -> 0 | J92: =SUM(G92:I92) -> 0 | K92: =J92/$J$25 -> 0
A93: 2 | B93: 2 | C93: 1 | D93: 3 | F93: Teléfono local | G93: =SUM(G94) -> 0 | H93: =+'[5]junio 2025'!H93+'[5]mayo 2025'!H93+[5]abril!H93+[5]marzo!H93+[5]febrero!H93+'[5]enero '!H93 -> 1289676.8 | I93: =SUM(I94) -> 0 | J93: =SUM(G93:I93) -> 1289676.8
A94: 2 | B94: 2 | C94: 1 | D94: 3 | E94: 01 | F94: Teléfono local | G94: ='[6]CUENTA T FONDO 100'!AQ288 -> 0 | H94: =+'[5]junio 2025'!H94+'[5]mayo 2025'!H94+[5]abril!H94+[5]marzo!H94+[5]febrero!H94+'[5]enero '!H94 -> 1289676.8 | J94: =SUM(G94:I94) -> 1289676.8 | K94: =J94/$J$25 -> 0.0021809498
A95: 2 | B95: 2 | C95: 1 | D95: 4 | F95: Telefax y correos | G95: =SUM(G96) -> 0 | H95: =+'[5]junio 2025'!H95+'[5]mayo 2025'!H95+[5]abril!H95+[5]marzo!H95+[5]febrero!H95+'[5]enero '!H95 -> 0 | I95: =SUM(I96) -> 0 | J95: =SUM(G95:I95) -> 0
A96: 2 | B96: 2 | C96: 1 | D96: 4 | E96: 01 | F96: Telefax y correos | G96: ='[6]CUENTA T FONDO 100'!AR288 -> 0 | H96: =+'[5]junio 2025'!H96+'[5]mayo 2025'!H96+[5]abril!H96+[5]marzo!H96+[5]febrero!H96+'[5]enero '!H96 -> 0 | J96: =SUM(G96:I96) -> 0 | K96: =J96/$J$25 -> 0
A97: 2 | B97: 2 | C97: 1 | D97: 5 | F97: Servicio de Internet y televisión por cable | G97: =SUM(G98) -> 0 | H97: =+'[5]junio 2025'!H97+'[5]mayo 2025'!H97+[5]abril!H97+[5]marzo!H97+[5]febrero!H97+'[5]enero '!H97 -> 210465.89 | I97: =SUM(I98) -> 0 | J97: =SUM(G97:I97) -> 210465.89
A98: 2 | B98: 2 | C98: 1 | D98: 5 | E98: 01 | F98: Servicio de Internet y televisión por cable | G98: ='[6]CUENTA T FONDO 100'!AS288 -> 0 | H98: =+'[5]junio 2025'!H98+'[5]mayo 2025'!H98+[5]abril!H98+[5]marzo!H98+[5]febrero!H98+'[5]enero '!H98 -> 210465.89 | J98: =SUM(G98:I98) -> 210465.89 | K98: =J98/$J$25 -> 0.00035591519
A99: 2 | B99: 2 | C99: 1 | D99: 6 | F99: Electricidad | G99: =SUM(G100:G101) -> 0 | H99: =+'[5]junio 2025'!H99+'[5]mayo 2025'!H99+[5]abril!H99+[5]marzo!H99+[5]febrero!H99+'[5]enero '!H99 -> 0 | I99: =SUM(I100:I101) -> 0 | J99: =SUM(G99:I99) -> 0
A100: 2 | B100: 2 | C100: 1 | D100: 6 | E100: 01 | F100: Energía eléctrica | G100: ='[6]CUENTA T FONDO 100'!AT288 -> 0 | H100: =+'[5]junio 2025'!H100+'[5]mayo 2025'!H100+[5]abril!H100+[5]marzo!H100+[5]febrero!H100+'[5]enero '!H100 -> 0 | J100: =SUM(G100:I100) -> 0 | K100: =J100/$J$25 -> 0
A101: 2 | B101: 2 | C101: 1 | D101: 6 | E101: 02 | F101: Electricidad no cortable | G101: ='[6]CUENTA T FONDO 100'!AU288 -> 0 | H101: =+'[5]junio 2025'!H101+'[5]mayo 2025'!H101+[5]abril!H101+[5]marzo!H101+[5]febrero!H101+'[5]enero '!H101 -> 0 | J101: =SUM(G101:I101) -> 0 | K101: =J101/$J$25 -> 0
A102: 2 | B102: 2 | C102: 1 | D102: 7 | F102: Agua | G102: =SUM(G103) -> 2201629.3 | H102: =+'[5]junio 2025'!H102+'[5]mayo 2025'!H102+[5]abril!H102+[5]marzo!H102+[5]febrero!H102+'[5]enero '!H102 -> 0 | I102: =SUM(I103) -> 0 | J102: =SUM(G102:I102) -> 2201629.3
A103: 2 | B103: 2 | C103: 1 | D103: 7 | E103: 01 | F103: Agua | G103: 2201629.3 | H103: =+'[5]junio 2025'!H103+'[5]mayo 2025'!H103+[5]abril!H103+[5]marzo!H103+[5]febrero!H103+'[5]enero '!H103 -> 0 | J103: =SUM(G103:I103) -> 2201629.3 | K103: =J103/$J$25 -> 0.0037231368
A104: 2 | B104: 2 | C104: 1 | D104: 8 | F104: Recolección de residuos sólidos | G104: =SUM(G105) -> 0 | H104: =+'[5]junio 2025'!H104+'[5]mayo 2025'!H104+[5]abril!H104+[5]marzo!H104+[5]febrero!H104+'[5]enero '!H104 -> 3190000 | I104: =SUM(I105) -> 0 | J104: =SUM(G104:I104) -> 3190000
A105: 2 | B105: 2 | C105: 1 | D105: 8 | E105: 01 | F105: Recolección de residuos sólidos | G105: ='[6]CUENTA T FONDO 100'!AW288 -> 0 | H105: =+'[5]junio 2025'!H105+'[5]mayo 2025'!H105+[5]abril!H105+[5]marzo!H105+[5]febrero!H105+'[5]enero '!H105 -> 3190000 | J105: =SUM(G105:I105) -> 3190000 | K105: =J105/$J$25 -> 0.0053945532
...
