Workbook
Name OLE_LINK1: 'NOTAS 7 AL19'!$A$8
Name OLE_LINK3: 'NOTAS 7 AL19'!#REF!
Name OLE_LINK4: 'NOTAS 7 AL19'!$A$19

Sheet Estado de Situación
A1: Hospital Materno Infantil San Lorenzo de los Mina
A2: Estado de Situación Financiera
A3: Del ejercicio terminado al 30 de abril 2025
A4: (Valores en RD$)
B6: 2025 | D6: 2021
A7: Activos
A8: Activos corrientes
A9: Efectivo y equivalente de efectivo (Notas 7) | B9: =+'NOTAS 7 AL19'!C12 -> 3.0392686e+08 | D9: =+'NOTAS 7 AL19'!#REF! -> #REF!
A10: Cuenta por cobrar a corto plazo (Notas 8) | B10: =+'NOTAS 7 AL19'!C24 -> 82148815 | D10: =+'NOTAS 7 AL19'!#REF! -> #REF!
A11: Inventarios (Nota 9) | B11: =+'NOTAS 7 AL19'!C32 -> 92426425 | D11: =+'NOTAS 7 AL19'!#REF! -> #REF!
A12: Total activos corrientes | B12: =SUM(B9:B11) -> 4.785021e+08 | D12: =SUM(D9:D11) -> #REF!
A14: Activos no corrientes
A15: Propiedad, planta y equipo neto (Nota 10) | B15: =+'NOTA 10'!I13 -> 1.6507226e+08 | D15: =3988531.33-566295.13 -> 3422236.2
A16: Total activos no corrientes | B16: =SUM(B15:B15) -> 1.6507226e+08 | D16: =SUM(D15:D15) -> 3422236.2
A18: Total activos | B18: =+B12+B16 -> 6.4357436e+08 | D18: =+D12+D16 -> #REF!
A19: Pasivos corrientes
A21: Cuentas por pagar a corto plazo (Nota 11) | B21: =+'NOTAS 7 AL19'!C38 -> 21432969 | D21: =+'NOTAS 7 AL19'!#REF! -> #REF!
A22: Retenciones y acumulaciones por pagar (Nota 12) | B22: =+'NOTAS 7 AL19'!C46 -> 12190724 | D22: =+'NOTAS 7 AL19'!#REF! -> #REF!
A23: Beneficios a empleados a corto plazo (Nota 13) | B23: =+'NOTAS 7 AL19'!C52 -> 1251715.8 | D23: =+'NOTAS 7 AL19'!#REF! -> #REF!
A24: Total pasivos corrientes | B24: =SUM(B21:B23) -> 34875409 | D24: =SUM(D21:D23) -> #REF!
A26: Pasivos no corrientes
A27: Total pasivos no corrientes | B27: 0 | D27: 0
A29: Total pasivos | B29: =+B24+B27 -> 34875409 | D29: =+D24+D27 -> #REF!
A31: Activos Netos/Patrimonio (Nota 14)
A32: Capital | B32: 3.4196058e+08 | D32: 64803453
A33: Resultados positivos (ahorro)/negativo (desahorro) | B33: =+'Est. de Rendimiento Fin'!B24 -> 1.4970253e+08 | D33: =+'Est. de Rendimiento Fin'!#REF! -> #REF!
A34: Resultado acumulado | B34: =+'cambio en el patr.'!E13+'cambio en el patr.'!E8 -> 1.1703585e+08
A35: Patrimonio Neto | B35: =SUM(B32:B34) -> 6.0869896e+08 | D35: =SUM(D32:D34) -> #REF!
A36: Total Activos Netos/Patrimonio mas Pasivos | B36: =SUM(B29+B35) -> 6.4357436e+08 | D36: =SUM(D32:D34) -> #REF!
D37: =+D36-D18 -> #REF!
A48: ___________________________
A49: Licdo. Eugenio Rosario | B49: Licda. Milagros Martinez de la Rosa
A50: Encargado Administrativo y Financiero | B50: Contadora
A56: Dr. Armando Camejo
A57: Director General
A58: Dr. Leonardo Aquino
A59: Director General

Sheet Est. de Rendimiento Fin
A1: Hospital Materno Infantil San Lorenzo de los Mina
A2: Estado de Rendimiento Financiero
A3: Del ejercicio terminado al 30 de abril 2025
A4: (Valores en RD$)
B6: 2025
A7: Ingresos (Notas 15)
A8: Impuestos | B8: 0
A9: Ingresos por transacciones con contraprestación | B9: =+'NOTAS 7 AL19'!C67 -> 24062967
A10: Transferencias y donaciones | B10: =+'NOTAS 7 AL19'!C71 -> 5.0575311e+08
A11: Recargos, multas y otros ingresos | B11: =+'NOTAS 7 AL19'!C75 -> 1182489.4
A12: Total ingresos | B12: =SUM(B8:B11) -> 5.3099857e+08
A14: Gastos (Notas 16,17,18,19,20,21)
A15: Sueldos, salarios y beneficios a empleados | B15: =+'NOTAS 7 AL19'!C95 -> 2.7034844e+08
A16: Subvenciones y otros pagos por transferencias | B16: =+'NOTAS 7 AL19'!C99 -> 912359.7
A17: Suministros y material para consumo | B17: =+'NOTAS 7 AL19'!C112 -> 76810203
A18: Gasto de depreciación y amortización | B18: =+'NOTAS 7 AL19'!C120 -> 14142739
A19: Otros gastos | B19: =+'NOTAS 7 AL19'!C133 -> 19032242
A20: Gastos financieros | B20: =+'NOTAS 7 AL19'!C139 -> 50054.14
A21: Total gastos | B21: =SUM(B15:B20) -> 3.8129604e+08
A24: Resultado del período (ahorro / desahorro) | B24: =+B12-B21 -> 1.4970253e+08
A27: Las notas en las páginas 07 al 09 son parte integral de estos Estados Financieros.
A33: Licdo. Eugenio Rosario | B33: Licda. Milagros Martinez de la Rosa
A34: Encargado Administrativo y Financiero | B34: Contadora
A40: Dr. Armando Camejo
A41: Director General
A42: Dr. Leonardo Aquino
A43: Director General

Sheet Cambio del Patrimonio
A1: Hospital Materno Infantil San Lorenzo de los Mina
A2: Estado de Cambio de Activo Neto / Patrimonio | G2: corregir el encabezado del estado, valido para todos
A3: Del ejercicio terminado al 30 de junio 2024 y 2023
A4: (Valores en RD$)
B6: Capital Aportado | C6: Cambios en Políticas Contables | D6: Revaluación | E6: Resultados Acumulados | F6: Total Activos Netos / Patrimonio | H6: este estado esta mal elaborado, fvor revisar, según conversaciones
A8: Saldo al 31 de diciembre 2022 | B8: =+'Estado de Situación'!B32 -> 3.4196058e+08 | E8: =+'Estado de Situación'!B34 -> 1.1703585e+08 | F8: =+B8+C8+D8+E8 -> 4.5899643e+08
A9: Cambio en políticas contables | F9: =+B9+C9+D9+E9 -> 0
A10: Revaluación de Propiedad, planta y equipo | F10: =+B10+C10+D10+E10 -> 0
A11: Ajuste al patrimonio | F11: =+B11+C11+D11+E11 -> 0
A13: Resultado del período | F13: =+F8+E13 -> 4.5899643e+08
A14: Saldo al 31 de diciembre 2024 | C14: =SUM(C7:C13) -> 0 | D14: =SUM(D7:D13) -> 0 | F14: =+B14+C14+D14+E14+F13 -> 4.5899643e+08
A16: Cambio en políticas contables | F16: =+B16+C16+D16+E16 -> 0
A17: Revaluación de Propiedad, planta y equipo | F17: =+B17+C17+D17+E17 -> 0
A18: Efecto del gasto de depreciación de los activos revaluados | F18: =+B18+C18+D18+E18 -> 0
A19: Ajuste al patrimonio | F19: =+B19+C19+D19+E19 -> 0
A20: Resultado del período | E20: =+'Estado de Situación'!B33 -> 1.4970253e+08 | F20: =+B20+C20+D20+E20 -> 1.4970253e+08
F21: =+F18+F19+F20+F14 -> 6.0869896e+08
A25: Las notas en las páginas 07 al 09 son parte integral de estos Estados Financieros.
A34: ___________________________
A35: Licdo. Eugenio Rosario | B35: Licda. Milagros Martinez
A36: Encargado Administrativo y Financiero | B36: Contadora
A42: Dr. Armando Camejo
A43: Director General

Sheet cambio en el patr.
A1: Hospital Materno Infantil San Lorenzo de los Mina
A2: Estado de Cambio de Activo Neto / Patrimonio
A3: Del ejercicio al 30 de abril 2025
A4: (Valores en RD$)
B6: Capital Aportado | C6: Cambios en Políticas Contables | D6: Revaluación | E6: Resultados Acumulados | F6: Total Activos Netos / Patrimonio
A8: Saldo al 31 de diciembre 2022 | B8: =+'[1]Estado de Situación'!B32 -> 3.4196058e+08 | E8: -1.1119234e+08 | F8: =+B8+C8+D8+E8 -> 2.3076825e+08
A9: Ajuste al patrimonio | F9: =+B9+C9+D9+E9 -> 0
A10: Resultado del período | E10: 0 | F10: =SUM(B10:E10) -> 0
A11: Saldo al 31 de diciembre 2023 | B11: =SUM(B8:B10) -> 3.4196058e+08 | C11: =SUM(C7:C10) -> 0 | D11: =SUM(D7:D10) -> 0 | E11: =SUM(E7:E10) -> -1.1119234e+08 | F11: =SUM(F8:F10) -> 2.3076825e+08
A13: Ajuste al patrimonio | E13: 2.2822818e+08 | F13: =+E13 -> 2.2822818e+08
A14: Resultado del período | E14: =+'Est. de Rendimiento Fin'!B24 -> 1.4970253e+08 | F14: =+E14 -> 1.4970253e+08
A15: Saldo al 31 de diciembre 2024 | B15: =SUM(B11) -> 3.4196058e+08 | E15: =SUM(E11:E14) -> 2.6673837e+08 | F15: =SUM(F11:F14) -> 6.0869896e+08
A24: Licdo. Eugenio Rosario | E24: Licda. Milagros Martinez de la Rosa
A25: Encargado Administrativo y Financiero | E25: Contadora
B31: Dr. Armando Camejo
B32: Director General

Sheet Flujo de Efectivo
A1: Hospital Materno Infantil San Lorenzo de los Mina
A2: Estado de Flujo de Efectivo
A3: Del ejercicio terminado al 30 de abril 2025
A4: (Valores en RD$)
A5: Flujo de efectivo procedentes de actividades operativas
B7: 2025
A9: Cobros por venta de bienes y servicios y arrendamientos | B9: =+'NOTAS 7 AL19'!C67 -> 24062967
A10: Cobros de subvenciones, transferencias, y otras asignaciones | B10: =+'NOTAS 7 AL19'!C72 -> 5.0575311e+08
A11: Otros cobros | B11: =+'NOTAS 7 AL19'!C75 -> 1182489.4
A12: Pagos a los trabajadores o en beneficio de ellos | B12: -2.3692722e+08
A13: Pagos por contribuciones a la seguridad social | B13: =-'NOTAS 7 AL19'!C87-'NOTAS 7 AL19'!C88-'NOTAS 7 AL19'!C89 -> -33421226
A14: Pagos a proveedores | B14: -95147077
A15: Otros pagos | B15: =-'NOTAS 7 AL19'!C99 -> -912359.7
A16: Flujos de efectivo netos de las actividades de operación | B16: =SUM(B9:B15) -> 1.6459069e+08
A18: Flujos de efectivo de las actividades de inversión
A19: Pagos por adquisición de propiedad, planta y equipo | B19: =-'NOTA 10'!E7 -> -27598952
A20: Flujos de efectivo netos por las actividades de inversión | B20: =+B19 -> -27598952
A23: Incremento/(Disminución) neta en el efectivo y equivalentes al efectivo | B23: =+B16+B20 -> 1.3699173e+08
A24: Efectivo y equivalentes al efectivo al principio del periodo 01/01/2022 | B24: 1.6693513e+08
A25: Efectivo y equivalentes al efectivo al final del periodo | B25: =+B23+B24 -> 3.0392686e+08
A28: Las notas en las páginas 07 al 09 son parte integral de estos Estados Financieros.
A38: Licdo. Eugenio Rosario | B38: Licda. Milagros Martinez de la Rosa
A39: Encargado Administrativo y Financiero | B39: Contadora
A44: Dr. Armando Camejo
A45: Director General
A47: Dr. Leonardo Aquino
A48: Director General
A50: Dr. Armando Camejo
A51: Director General

Sheet  estado comp. presup.
A1: Hospital Materno Infantil San Lorenzo de los Mina
A2: Estado de Comparación de los Importes Presupuestados y Realizados
A3: Del ejercicio terminado al 30 de abril 2025
A4: Presupuesto sobre la Base de Efectivo
A5: (Clasificación de Ingresos y Gastos por Objeto)
A7: Concepto | C7: Presupuesto Reformado (A) | D7: Presupuesto Ejecutado (B) | E7: % de Variac Ejecución (C=B/A) | F7: Variación (D=A-B)
A8: 1 | B8: Ingresos totales | C8: =SUM(C9:C12) -> 1.504012e+09 | D8: =SUM(D9:D12) -> 5.3099857e+08 | E8: =+D8/C8 -> 0.35305474 | F8: =+C8-D8 -> 9.7301345e+08
A9: 1.4 | B9: Transferencias | C9: =1247948781 -> 1247948781 | D9: =+'NOTAS 7 AL19'!C71 -> 5.0575311e+08 | E9: =+D9/C9 -> 0.40526752 | F9: =+C9-D9 -> 7.4219567e+08
A10: 1.5 | B10: Ingresos por contraprestación | C10: 92836447 | D10: =+'NOTAS 7 AL19'!C67 -> 24062967 | E10: =+D10/C10 -> 0.25919741 | F10: =+C10-D10 -> 68773480
A11: 1.6 | B11: Otros ingresos | C11: 0 | D11: =+'NOTAS 7 AL19'!C75 -> 1182489.4 | E11: 0 | F11: =+C11-D11 -> -1182489.4
A12: 3.1 | B12: Disminucion de Activos Financieros | C12: 1.6322679e+08 | F12: =+C12-D12 -> 1.6322679e+08
A13: 2 | B13: Gastos totales | C13: =SUM(C14:C19) -> 1.504012e+09 | D13: =SUM(D14:D19) -> 3.9475226e+08 | E13: =+D13/C13 -> 0.26246616 | F13: =+C13-D13 -> 1.1092598e+09
A14: 2.1 | B14: Remuneraciones y contribuciones | C14: =844859288.58-5+10878647.92 -> 8.5573793e+08 | D14: =+'NOTAS 7 AL19'!C95-0.01 -> 2.7034844e+08 | E14: =+D14/C14 -> 0.31592434 | F14: =+C14-D14 -> 5.8538949e+08
A15: 2.2 | B15: Contratación de servicios | C15: =50217379.13+18830480.56+14501912.25 -> 83549772 | D15: =+'NOTAS 7 AL19'!C133+'NOTAS 7 AL19'!C139 -> 19082296 | E15: =+D15/C15 -> 0.22839435 | F15: =+C15-D15 -> 64467476
A16: 2.3 | B16: Materiales y suministros | C16: =399408759.41+14501912.25 -> 4.1391067e+08 | D16: =+'NOTAS 7 AL19'!C112 -> 76810203 | E16: =+D16/C16 -> 0.18557193 | F16: =+C16-D16 -> 3.3710047e+08
A17: 2.4 | B17: Transferencias corrientes | C17: 685000 | D17: =+'NOTAS 7 AL19'!C99 -> 912359.7 | E17: =+D17/C17 -> 1.331912 | F17: =+C17-D17 -> -227359.7
A18: 2.6 | B18: Bienes muebles, inmuebles e intangibles | C18: =135626733.94+14501912.26 -> 1.5012865e+08 | D18: =+'NOTA 10'!E7 -> 27598952 | E18: =+D18/C18 -> 0.18383535 | F18: =+C18-D18 -> 1.2252969e+08
A19: 2.9 | B19: Gastos financieros | C19: 0 | D19: 0 | E19: 0 | F19: =+C19-D19 -> 0
B20: Resultado financiero (1-2) | C20: =SUM(C8-C13) -> -2.3841858e-07 | D20: =+D8-D13 -> 1.3624631e+08 | F20: =+C20-D20 -> -1.3624631e+08
D21: =+D13-394752255.99 -> 0
A23: Nota: El Monto de RD$163,226,793.30, es un ingreso recibido mediante fondo financiador 121, que pertenece a disponibilidad de años anteriores
A49: Licdo. Eugenio Rosario | E49: Licda. Milagros Martinez de la Rosa
A50: Encargado Administrativo y Financiero | E50: Contadora
A55: Dr. Armando Camejo
A56: Director General
A58: Dr. Leonardo Aquino
A59: Director General
A61: Dr. Armando Camejo
A62: Director General

Sheet Estado Comparativo
A1: Hospital Materno Infantil San Lorenzo de los Mina
A2: Estado de Comparación de los Importes Presupuestados y Realizados
A3: Del ejercicio terminado al 31 de diciembre 2023
A4: Presupuesto sobre la Base de Efectivo
A5: (Clasificación de Ingresos y Gastos por Objeto)
A6: Concepto | C6: Presupuesto Reformado (A) | D6: Presupuesto Ejecutado (B) | E6: % de Variac Ejecución (C=B/A) | F6: Variación (D=A-B)
A7: 1 | B7: Ingresos totales | C7: =SUM(C8:C9) -> 3.8232418e+08 | D7: =SUM(D8:D9) -> 25245456 | E7: =+D7/C7 -> 0.066031545 | F7: =+C7-D7 -> 3.5707872e+08
A8: 1.5 | B8: Ingresos por contraprestación | C8: =130171600+3720000 -> 133891600 | D8: =+'NOTAS 7 AL19'!C67+'NOTAS 7 AL19'!C79 -> 24062967 | E8: =+D8/C8 -> 0.17971976 | F8: =+C8-D8 -> 1.0982863e+08
A9: 1.6 | B9: Otros ingresos | C9: 2.4843258e+08 | D9: =+'NOTAS 7 AL19'!C75 -> 1182489.4 | E9: =+D9/C9 -> 0.0047598002 | F9: =+C9-D9 -> 2.4725009e+08
A10: 2 | B10: Gastos totales | C10: =SUM(C11:C16) -> 3.2677766e+08 | D10: =SUM(D11:D16) -> #REF! | E10: =+D10/C10 -> #REF! | F10: =SUM(F11:F16) -> #REF!
A11: 2.1 | B11: Remuneraciones y contribuciones | C11: 13017160 | D11: =+'NOTAS 7 AL19'!C95 -> 2.7034844e+08 | E11: =+D11/C11 -> 20.76862 | F11: =+C11-D11 -> -2.5733128e+08
A12: 2.2 | B12: Contratación de servicios | C12: =199200+16959031.71 -> 17158232 | D12: =+'NOTAS 7 AL19'!C133-'NOTAS 7 AL19'!#REF! -> #REF! | E12: =+D12/C12 -> #REF! | F12: =+C12-D12 -> #REF!
A13: 2.3 | B13: Materiales y suministros | C13: =37000800+195705730 -> 232706530 | D13: =+'NOTAS 7 AL19'!C112 -> 76810203 | E13: =+D13/C13 -> 0.33007326 | F13: =+C13-D13 -> 1.5589633e+08
A14: 2.4 | B14: Transferencias corrientes | C14: 36000 | D14: =+'NOTAS 7 AL19'!#REF! -> #REF! | E14: =+D14/C14 -> #REF! | F14: =+C14-D14 -> #REF!
A15: 2.6 | B15: Bienes muebles, inmuebles e intangibles | C15: 63859742 | D15: =+'NOTA 10'!E7+'NOTA 10'!F7 -> 27598952 | E15: =+D15/C15 -> 0.43218076 | F15: =+C15-D15 -> 36260790
A16: 2.9 | B16: Gastos financieros | C16: 0 | D16: =+'NOTAS 7 AL19'!C139 -> 50054.14 | E16: 0 | F16: =+C16-D16 -> -50054.14
B17: Resultado financiero (1-2) | C17: =SUM(C7-C10) -> 55546515 | D17: =+D7-D10 -> #REF! | F17: =SUM(F7-F10) -> #REF!
A23: Las notas en las páginas 07 al 09 son parte integral de estos Estados Financieros.

Sheet dinámico de gastos al 30-06-24
A1: Cod.Capí­tulo | B1: Capí­tulo | C1: Cod.SubCapitulo | D1: SubCapitulo | E1: Cod.Unidad Ejecutora | F1: Unidad Ejecutora | G1: Cod.Fuentes Financiamiento | H1: Fuentes Financiamiento | I1: Cod.Actividad / Obra | J1: Actividad / Obra | K1: Cod.Función | L1: Función | M1: Cod.Programa | N1: Programa | O1: Cod.Organismos Financiadores | P1: Organismos Financiadores | Q1: Cod.Fuente Especifica | R1: Fuente Especifica | S1: Cod.Tp. Transacción | T1: Tp. Transacción | U1: Número Documento | V1: Cod.Inst. Rec. | W1: Inst. Rec. | X1: Concepto Formulario | Y1: Fch.Hist.Imputación | Z1: Fch.Hist.Registro | AA1: Cod.Ref CCP Cuenta | AB1: Ref CCP Cuenta | AC1: Cod.Ref CCP SubCuenta | AD1: Ref CCP SubCuenta | AE1: Cod.Ref CCP Aux | AF1: Ref CCP Aux | AG1: Devengado Aprobado | AH1: Pagado Aprobado
A2: 5180 | B2: DIRECCION CENTRAL DEL SERVICIO NACIONAL DE SALUD | C2: 01 | D2: DIRECCION CENTRAL DEL SERVICIO NACIONAL DE SALUD | E2: 0014 | F2: HOSPITAL MATERNO-INFANTIL SAN LORENZO DE LOS MINA | G2: 10 | H2: FONDO GENERAL | I2: 0001 | J2: Dirección y Coordinación | K2: 001 | L2: N/A | M2: 40 | N2: Salud materno neonatal | O2: 100 | P2: TESORO NACIONAL | Q2: 0100 | R2: FONDO GENERAL | S2: 000001 | T2: Pago | U2: 8 | V2: 0000 | W2: NO APLICA | X2: HOSANLORE. SUELDO ENERO 2024_x000D_ HOSPITAL SAN LORENZO DE LOS MINA_x000D_ FIJOS | Y2: 25/01/2024 | Z2: 25/01/2024 | AA2: 2.1.1 | AB2: REMUNERACIONES | AC2: 2.1.1.1 | AD2: Remuneraciones al personal fijo | AE2: 2.1.1.1.01 | AF2: Sueldos empleados fijos | AG2: 0 | AH2: 47719055
A3: 5180 | B3: DIRECCION CENTRAL DEL SERVICIO NACIONAL DE SALUD | C3: 01 | D3: DIRECCION CENTRAL DEL SERVICIO NACIONAL DE SALUD | E3: 0014 | F3: HOSPITAL MATERNO-INFANTIL SAN LORENZO DE LOS MINA | G3: 10 | H3: FONDO GENERAL | I3: 0001 | J3: Dirección y Coordinación | K3: 001 | L3: N/A | M3: 40 | N3: Salud materno neonatal | O3: 100 | P3: TESORO NACIONAL | Q3: 0100 | R3: FONDO GENERAL | S3: 000001 | T3: Pago | U3: 8 | V3: 0000 | W3: NO APLICA | X3: HOSANLORE. SUELDO ENERO 2024_x000D_ HOSPITAL SAN LORENZO DE LOS MINA_x000D_ FIJOS | Y3: 25/01/2024 | Z3: 25/01/2024 | AA3: 2.1.2 | AB3: SOBRESUELDOS | AC3: 2.1.2.1 | AD3: Primas por antigüedad | AE3: 2.1.2.1.01 | AF3: Primas por antigüedad | AG3: 0 | AH3: 2561925.4
A4: 5180 | B4: DIRECCION CENTRAL DEL SERVICIO NACIONAL DE SALUD | C4: 01 | D4: DIRECCION CENTRAL DEL SERVICIO NACIONAL DE SALUD | E4: 0014 | F4: HOSPITAL MATERNO-INFANTIL SAN LORENZO DE LOS MINA | G4: 10 | H4: FONDO GENERAL | I4: 0001 | J4: Dirección y Coordinación | K4: 001 | L4: N/A | M4: 40 | N4: Salud materno neonatal | O4: 100 | P4: TESORO NACIONAL | Q4: 0100 | R4: FONDO GENERAL | S4: 000001 | T4: Pago | U4: 8 | V4: 0000 | W4: NO APLICA | X4: HOSANLORE. SUELDO ENERO 2024_x000D_ HOSPITAL SAN LORENZO DE LOS MINA_x000D_ FIJOS | Y4: 25/01/2024 | Z4: 25/01/2024 | AA4: 2.1.2 | AB4: SOBRESUELDOS | AC4: 2.1.2.2 | AD4: Compensación | AE4: 2.1.2.2.08 | AF4: Compensaciones especiales | AG4: 0 | AH4: 396000
A5: 5180 | B5: DIRECCION CENTRAL DEL SERVICIO NACIONAL DE SALUD | C5: 01 | D5: DIRECCION CENTRAL DEL SERVICIO NACIONAL DE SALUD | E5: 0014 | F5: HOSPITAL MATERNO-INFANTIL SAN LORENZO DE LOS MINA | G5: 10 | H5: FONDO GENERAL | I5: 0001 | J5: Dirección y Coordinación | K5: 001 | L5: N/A | M5: 40 | N5: Salud materno neonatal | O5: 100 | P5: TESORO NACIONAL | Q5: 0100 | R5: FONDO GENERAL | S5: 000001 | T5: Pago | U5: 8 | V5: 0000 | W5: NO APLICA | X5: HOSANLORE. SUELDO ENERO 2024_x000D_ HOSPITAL SAN LORENZO DE LOS MINA_x000D_ FIJOS | Y5: 25/01/2024 | Z5: 25/01/2024 | AA5: 2.1.2 | AB5: SOBRESUELDOS | AC5: 2.1.2.2 | AD5: Compensación | AE5: 2.1.2.2.12 | AF5: Compensación por cargo al personal policial | AG5: 0 | AH5: 10717.4
A6: 5180 | B6: DIRECCION CENTRAL DEL SERVICIO NACIONAL DE SALUD | C6: 01 | D6: DIRECCION CENTRAL DEL SERVICIO NACIONAL DE SALUD | E6: 0014 | F6: HOSPITAL MATERNO-INFANTIL SAN LORENZO DE LOS MINA | G6: 10 | H6: FONDO GENERAL | I6: 0001 | J6: Dirección y Coordinación | K6: 001 | L6: N/A | M6: 40 | N6: Salud materno neonatal | O6: 100 | P6: TESORO NACIONAL | Q6: 0100 | R6: FONDO GENERAL | S6: 000001 | T6: Pago | U6: 8 | V6: 0000 | W6: NO APLICA | X6: HOSANLORE. SUELDO ENERO 2024_x000D_ HOSPITAL SAN LORENZO DE LOS MINA_x000D_ FIJOS | Y6: 25/01/2024 | Z6: 25/01/2024 | AA6: 2.1.2 | AB6: SOBRESUELDOS | AC6: 2.1.2.2 | AD6: Compensación | AE6: 2.1.2.2.13 | AF6: Incentivo por riesgo laboral al personal militar y policial | AG6: 0 | AH6: 64304.4
A7: 5180 | B7: DIRECCION CENTRAL DEL SERVICIO NACIONAL DE SALUD | C7: 01 | D7: DIRECCION CENTRAL DEL SERVICIO NACIONAL DE SALUD | E7: 0014 | F7: HOSPITAL MATERNO-INFANTIL SAN LORENZO DE LOS MINA | G7: 10 | H7: FONDO GENERAL | I7: 0001 | J7: Dirección y Coordinación | K7: 001 | L7: N/A | M7: 40 | N7: Salud materno neonatal | O7: 100 | P7: TESORO NACIONAL | Q7: 0100 | R7: FONDO GENERAL | S7: 000001 | T7: Pago | U7: 8 | V7: 0000 | W7: NO APLICA | X7: HOSANLORE. SUELDO ENERO 2024_x000D_ HOSPITAL SAN LORENZO DE LOS MINA_x000D_ FIJOS | Y7: 25/01/2024 | Z7: 25/01/2024 | AA7: 2.1.5 | AB7: CONTRIBUCIONES A LA SEGURIDAD SOCIAL | AC7: 2.1.5.1 | AD7: Contribuciones al seguro de salud | AE7: 2.1.5.1.01 | AF7: Contribuciones al seguro de salud | AG7: 0 | AH7: 3383280
A8: 5180 | B8: DIRECCION CENTRAL DEL SERVICIO NACIONAL DE SALUD | C8: 01 | D8: DIRECCION CENTRAL DEL SERVICIO NACIONAL DE SALUD | E8: 0014 | F8: HOSPITAL MATERNO-INFANTIL SAN LORENZO DE LOS MINA | G8: 10 | H8: FONDO GENERAL | I8: 0001 | J8: Dirección y Coordinación | K8: 001 | L8: N/A | M8: 40 | N8: Salud materno neonatal | O8: 100 | P8: TESORO NACIONAL | Q8: 0100 | R8: FONDO GENERAL | S8: 000001 | T8: Pago | U8: 8 | V8: 0000 | W8: NO APLICA | X8: HOSANLORE. SUELDO ENERO 2024_x000D_ HOSPITAL SAN LORENZO DE LOS MINA_x000D_ FIJOS | Y8: 25/01/2024 | Z8: 25/01/2024 | AA8: 2.1.5 | AB8: CONTRIBUCIONES A LA SEGURIDAD SOCIAL | AC8: 2.1.5.2 | AD8: Contribuciones al seguro de pensiones | AE8: 2.1.5.2.01 | AF8: Contribuciones al seguro de pensiones | AG8: 0 | AH8: 3388052.4
A9: 5180 | B9: DIRECCION CENTRAL DEL SERVICIO NACIONAL DE SALUD | C9: 01 | D9: DIRECCION CENTRAL DEL SERVICIO NACIONAL DE SALUD | E9: 0014 | F9: HOSPITAL MATERNO-INFANTIL SAN LORENZO DE LOS MINA | G9: 10 | H9: FONDO GENERAL | I9: 0001 | J9: Dirección y Coordinación | K9: 001 | L9: N/A | M9: 40 | N9: Salud materno neonatal | O9: 100 | P9: TESORO NACIONAL | Q9: 0100 | R9: FONDO GENERAL | S9: 000001 | T9: Pago | U9: 8 | V9: 0000 | W9: NO APLICA | X9: HOSANLORE. SUELDO ENERO 2024_x000D_ HOSPITAL SAN LORENZO DE LOS MINA_x000D_ FIJOS | Y9: 25/01/2024 | Z9: 25/01/2024 | AA9: 2.1.5 | AB9: CONTRIBUCIONES A LA SEGURIDAD SOCIAL | AC9: 2.1.5.3 | AD9: Contribuciones al seguro de riesgo laboral | AE9: 2.1.5.3.01 | AF9: Contribuciones al seguro de riesgo laboral | AG9: 0 | AH9: 571427.64
A10: 5180 | B10: DIRECCION CENTRAL DEL SERVICIO NACIONAL DE SALUD | C10: 01 | D10: DIRECCION CENTRAL DEL SERVICIO NACIONAL DE SALUD | E10: 0014 | F10: HOSPITAL MATERNO-INFANTIL SAN LORENZO DE LOS MINA | G10: 10 | H10: FONDO GENERAL | I10: 0001 | J10: Dirección y Coordinación | K10: 001 | L10: N/A | M10: 40 | N10: Salud materno neonatal | O10: 100 | P10: TESORO NACIONAL | Q10: 0100 | R10: FONDO GENERAL | S10: 000001 | T10: Pago | U10: 9 | V10: 0000 | W10: NO APLICA | X10: HOSANLORE. SUELDO ENERO 2024_x000D_ HOSPITAL SAN LORENZO DE LOS MINA_x000D_ TEMPORAL | Y10: 25/01/2024 | Z10: 25/01/2024 | AA10: 2.1.1 | AB10: REMUNERACIONES | AC10: 2.1.1.2 | AD10: Remuneraciones al personal de carácter temporal | AE10: 2.1.1.2.08 | AF10: Empleados temporales | AG10: 0 | AH10: 686003.26
A11: 5180 | B11: DIRECCION CENTRAL DEL SERVICIO NACIONAL DE SALUD | C11: 01 | D11: DIRECCION CENTRAL DEL SERVICIO NACIONAL DE SALUD | E11: 0014 | F11: HOSPITAL MATERNO-INFANTIL SAN LORENZO DE LOS MINA | G11: 10 | H11: FONDO GENERAL | I11: 0001 | J11: Dirección y Coordinación | K11: 001 | L11: N/A | M11: 40 | N11: Salud materno neonatal | O11: 100 | P11: TESORO NACIONAL | Q11: 0100 | R11: FONDO GENERAL | S11: 000001 | T11: Pago | U11: 9 | V11: 0000 | W11: NO APLICA | X11: HOSANLORE. SUELDO ENERO 2024_x000D_ HOSPITAL SAN LORENZO DE LOS MINA_x000D_ TEMPORAL | Y11: 25/01/2024 | Z11: 25/01/2024 | AA11: 2.1.5 | AB11: CONTRIBUCIONES A LA SEGURIDAD SOCIAL | AC11: 2.1.5.1 | AD11: Contribuciones al seguro de salud | AE11: 2.1.5.1.01 | AF11: Contribuciones al seguro de salud | AG11: 0 | AH11: 48637.63
A12: 5180 | B12: DIRECCION CENTRAL DEL SERVICIO NACIONAL DE SALUD | C12: 01 | D12: DIRECCION CENTRAL DEL SERVICIO NACIONAL DE SALUD | E12: 0014 | F12: HOSPITAL MATERNO-INFANTIL SAN LORENZO DE LOS MINA | G12: 10 | H12: FONDO GENERAL | I12: 0001 | J12: Dirección y Coordinación | K12: 001 | L12: N/A | M12: 40 | N12: Salud materno neonatal | O12: 100 | P12: TESORO NACIONAL | Q12: 0100 | R12: FONDO GENERAL | S12: 000001 | T12: Pago | U12: 9 | V12: 0000 | W12: NO APLICA | X12: HOSANLORE. SUELDO ENERO 2024_x000D_ HOSPITAL SAN LORENZO DE LOS MINA_x000D_ TEMPORAL | Y12: 25/01/2024 | Z12: 25/01/2024 | AA12: 2.1.5 | AB12: CONTRIBUCIONES A LA SEGURIDAD SOCIAL | AC12: 2.1.5.2 | AD12: Contribuciones al seguro de pensiones | AE12: 2.1.5.2.01 | AF12: Contribuciones al seguro de pensiones | AG12: 0 | AH12: 48706.23
A13: 5180 | B13: DIRECCION CENTRAL DEL SERVICIO NACIONAL DE SALUD | C13: 01 | D13: DIRECCION CENTRAL DEL SERVICIO NACIONAL DE SALUD | E13: 0014 | F13: HOSPITAL MATERNO-INFANTIL SAN LORENZO DE LOS MINA | G13: 10 | H13: FONDO GENERAL | I13: 0001 | J13: Dirección y Coordinación | K13: 001 | L13: N/A | M13: 40 | N13: Salud materno neonatal | O13: 100 | P13: TESORO NACIONAL | Q13: 0100 | R13: FONDO GENERAL | S13: 000001 | T13: Pago | U13: 9 | V13: 0000 | W13: NO APLICA | X13: HOSANLORE. SUELDO ENERO 2024_x000D_ HOSPITAL SAN LORENZO DE LOS MINA_x000D_ TEMPORAL | Y13: 25/01/2024 | Z13: 25/01/2024 | AA13: 2.1.5 | AB13: CONTRIBUCIONES A LA SEGURIDAD SOCIAL | AC13: 2.1.5.3 | AD13: Contribuciones al seguro de riesgo laboral | AE13: 2.1.5.3.01 | AF13: Contribuciones al seguro de riesgo laboral | AG13: 0 | AH13: 8109.74
... A1071: 5180 | B1071: DIRECCION CENTRAL DEL SERVICIO NACIONAL DE SALUD | C1071: 01 | D1071: DIRECCION CENTRAL DEL SERVICIO NACIONAL DE SALUD | E1071: 0014 | F1071: HOSPITAL MATERNO-INFANTIL SAN LORENZO DE LOS MINA | G1071: 10 | H1071: FONDO GENERAL | I1071: 0002 | J1071: Servicios de atención y control al neonato prematuro | K1071: 001 | L1071: N/A | M1071: 40 | N1071: Salud materno neonatal | O1071: 100 | P1071: TESORO NACIONAL | Q1071: 0100 | R1071: FONDO GENERAL | S1071: 000243 | T1071: DEVENGADO PROCESO DE COMPRAS PARA BIENES MUEBLES Y OBRAS | U1071: 1760 | V1071: 0000 | W1071: NO APLICA | X1071: PAGO DE FACT NCF B1500000033 POR ADQUISICION DE MOBILIARIOS DE OFICINA Y MONITOR SEGUN O/C HSLM-2024-00214. | Y1071: 19/06/2024 | Z1071: 19/06/2024 | AA1071: 2.6.1 | AB1071: MOBILIARIO Y EQUIPO | AC1071: 2.6.1.3 | AD1071: Equipos de tecnología de la información y comunicación | AE1071: 2.6.1.3.01 | AF1071: Equipos de tecnología de la información y comunicación | AG1071: 124872.68 | AH1071: 0
AG1073: =SUBTOTAL(9,AG2:AG1072) -> 4.5440444e+08 | AH1073: =SUBTOTAL(9,AH2:AH1072) -> 4.3675684e+08
AH1074: =+AH1073-AG1073 -> -17647601
AH1609: =SUBTOTAL(9,AH2:AH1608) -> 4.1910924e+08 | AI1609: 2.9258776e+08
AH1610: 4120195.3 | AI1610: 3469454.5
AH1611: =+AH1609+AH1610 -> 4.2322944e+08 | AI1611: 20570888
AI1612: 20541912
AI1613: =+AI1612+AI1611+AI1610+AI1609 -> 3.3717001e+08
AH1615: 20541912
AH1616: 20570888
AH1617: 3469454.5
AH1618: =+AH1615+AH1616+AH1617 -> 44582254
AH1620: 3.0662217e+08
AH1621: 614803.73
AH1622: =+AH1618+AH1620+AH1621 -> 3.5181923e+08

Sheet Hoja4
A1: Cod.Capí­tulo | B1: Capí­tulo | C1: Cod.SubCapitulo | D1: SubCapitulo | E1: Cod.Unidad Ejecutora | F1: Unidad Ejecutora | G1: Cod.Fuentes Financiamiento | H1: Fuentes Financiamiento | I1: Cod.Actividad / Obra | J1: Actividad / Obra | K1: Cod.Función | L1: Función | M1: Cod.Programa | N1: Programa | O1: Cod.Organismos Financiadores | P1: Organismos Financiadores | Q1: Cod.Fuente Especifica | R1: Fuente Especifica | S1: Cod.Tp. Transacción | T1: Tp. Transacción | U1: Número Documento | V1: Cod.Inst. Rec. | W1: Inst. Rec. | X1: Concepto Formulario | Y1: Fch.Hist.Imputación | Z1: Fch.Hist.Registro | AA1: Cod.Ref CCP Cuenta | AB1: Ref CCP Cuenta | AC1: Cod.Ref CCP SubCuenta | AD1: Ref CCP SubCuenta | AE1: Cod.Ref CCP Aux | AF1: Ref CCP Aux | AG1: Pagado Aprobado
A2: 5180 | B2: DIRECCION CENTRAL DEL SERVICIO NACIONAL DE SALUD | C2: 01 | D2: DIRECCION CENTRAL DEL SERVICIO NACIONAL DE SALUD | E2: 0014 | F2: HOSPITAL MATERNO-INFANTIL SAN LORENZO DE LOS MINA | G2: 10 | H2: FONDO GENERAL | I2: 0001 | J2: Dirección y Coordinación | K2: 001 | L2: N/A | M2: 40 | N2: Salud materno neonatal | O2: 100 | P2: TESORO NACIONAL | Q2: 0100 | R2: FONDO GENERAL | S2: 000001 | T2: Pago | U2: 2035 | V2: 0000 | W2: NO APLICA | X2: HOSANLORE. SUELDO NOMINA ADICIONAL TEMPORAL POR CREACION DE PLAZA CORRESPONDIENTE AL MES DE JUNIO 2024_x000D_ NOMINA ADICIONAL TEMPORAL POR CREACION DE PLAZA CORRESPONDIENTE AL MES DE JUNIO 2024 | Y2: 27/06/2024 | Z2: 27/06/2024 | AA2: 2.1.1 | AB2: REMUNERACIONES | AC2: 2.1.1.2 | AD2: Remuneraciones al personal de carácter temporal | AE2: 2.1.1.2.08 | AF2: Empleados temporales | AG2: 50000
A3: 5180 | B3: DIRECCION CENTRAL DEL SERVICIO NACIONAL DE SALUD | C3: 01 | D3: DIRECCION CENTRAL DEL SERVICIO NACIONAL DE SALUD | E3: 0014 | F3: HOSPITAL MATERNO-INFANTIL SAN LORENZO DE LOS MINA | G3: 10 | H3: FONDO GENERAL | I3: 0001 | J3: Dirección y Coordinación | K3: 001 | L3: N/A | M3: 40 | N3: Salud materno neonatal | O3: 100 | P3: TESORO NACIONAL | Q3: 0100 | R3: FONDO GENERAL | S3: 000001 | T3: Pago | U3: 1688 | V3: 0000 | W3: NO APLICA | X3: HOSANLORE. PAGO DE PRESTACIONES LABORALEX EX-EMPLEADOS | Y3: 11/06/2024 | Z3: 11/06/2024 | AA3: 2.1.1 | AB3: REMUNERACIONES | AC3: 2.1.1.5 | AD3: Prestaciones económicas | AE3: 2.1.1.5.03 | AF3: Prestación laboral por desvinculación | AG3: 55000
A4: 5180 | B4: DIRECCION CENTRAL DEL SERVICIO NACIONAL DE SALUD | C4: 01 | D4: DIRECCION CENTRAL DEL SERVICIO NACIONAL DE SALUD | E4: 0014 | F4: HOSPITAL MATERNO-INFANTIL SAN LORENZO DE LOS MINA | G4: 10 | H4: FONDO GENERAL | I4: 0001 | J4: Dirección y Coordinación | K4: 001 | L4: N/A | M4: 40 | N4: Salud materno neonatal | O4: 100 | P4: TESORO NACIONAL | Q4: 0100 | R4: FONDO GENERAL | S4: 000001 | T4: Pago | U4: 1690 | V4: 0000 | W4: NO APLICA | X4: HOSANLORE. PAGO DE VACACIONES NO DISFRUTADAS A EX-EMPLEADOS | Y4: 11/06/2024 | Z4: 11/06/2024 | AA4: 2.1.1 | AB4: REMUNERACIONES | AC4: 2.1.1.5 | AD4: Prestaciones económicas | AE4: 2.1.1.5.04 | AF4: Proporción de vacaciones no disfrutadas | AG4: 56650.2
A5: 5180 | B5: DIRECCION CENTRAL DEL SERVICIO NACIONAL DE SALUD | C5: 01 | D5: DIRECCION CENTRAL DEL SERVICIO NACIONAL DE SALUD | E5: 0014 | F5: HOSPITAL MATERNO-INFANTIL SAN LORENZO DE LOS MINA | G5: 10 | H5: FONDO GENERAL | I5: 0001 | J5: Dirección y Coordinación | K5: 001 | L5: N/A | M5: 40 | N5: Salud materno neonatal | O5: 100 | P5: TESORO NACIONAL | Q5: 0100 | R5: FONDO GENERAL | S5: 000001 | T5: Pago | U5: 1045 | V5: 0000 | W5: NO APLICA | X5: HOSANLORE. ADICIONAL FIJO ABRIL 2024 | Y5: 03/05/2024 | Z5: 03/05/2024 | AA5: 2.1.1 | AB5: REMUNERACIONES | AC5: 2.1.1.1 | AD5: Remuneraciones al personal fijo | AE5: 2.1.1.1.01 | AF5: Sueldos empleados fijos | AG5: 69663.1
A6: 5180 | B6: DIRECCION CENTRAL DEL SERVICIO NACIONAL DE SALUD | C6: 01 | D6: DIRECCION CENTRAL DEL SERVICIO NACIONAL DE SALUD | E6: 0014 | F6: HOSPITAL MATERNO-INFANTIL SAN LORENZO DE LOS MINA | G6: 10 | H6: FONDO GENERAL | I6: 0001 | J6: Dirección y Coordinación | K6: 001 | L6: N/A | M6: 40 | N6: Salud materno neonatal | O6: 100 | P6: TESORO NACIONAL | Q6: 0100 | R6: FONDO GENERAL | S6: 000001 | T6: Pago | U6: 25 | V6: 0000 | W6: NO APLICA | X6: HOSANLORE. PAGO DE VACACIONES NO DISFRUTADAS A EX- EMPLEADOS_x000D_ NOMINA FINAL FEBRERO 2024 | Y6: 04/03/2024 | Z6: 04/03/2024 | AA6: 2.1.1 | AB6: REMUNERACIONES | AC6: 2.1.1.5 | AD6: Prestaciones económicas | AE6: 2.1.1.5.04 | AF6: Proporción de vacaciones no disfrutadas | AG6: 156153.53
A7: 5180 | B7: DIRECCION CENTRAL DEL SERVICIO NACIONAL DE SALUD | C7: 01 | D7: DIRECCION CENTRAL DEL SERVICIO NACIONAL DE SALUD | E7: 0014 | F7: HOSPITAL MATERNO-INFANTIL SAN LORENZO DE LOS MINA | G7: 10 | H7: FONDO GENERAL | I7: 0001 | J7: Dirección y Coordinación | K7: 001 | L7: N/A | M7: 40 | N7: Salud materno neonatal | O7: 100 | P7: TESORO NACIONAL | Q7: 0100 | R7: FONDO GENERAL | S7: 000001 | T7: Pago | U7: 26 | V7: 0000 | W7: NO APLICA | X7: HOSANLORE. PAGO DE PRESTACIONES LABORALES EX-EMPLEADO._x000D_ NOMINA FINAL FEBRERO 2024 | Y7: 04/03/2024 | Z7: 04/03/2024 | AA7: 2.1.1 | AB7: REMUNERACIONES | AC7: 2.1.1.5 | AD7: Prestaciones económicas | AE7: 2.1.1.5.03 | AF7: Prestación laboral por desvinculación | AG7: 347000
A8: 5180 | B8: DIRECCION CENTRAL DEL SERVICIO NACIONAL DE SALUD | C8: 01 | D8: DIRECCION CENTRAL DEL SERVICIO NACIONAL DE SALUD | E8: 0014 | F8: HOSPITAL MATERNO-INFANTIL SAN LORENZO DE LOS MINA | G8: 10 | H8: FONDO GENERAL | I8: 0001 | J8: Dirección y Coordinación | K8: 001 | L8: N/A | M8: 40 | N8: Salud materno neonatal | O8: 100 | P8: TESORO NACIONAL | Q8: 0100 | R8: FONDO GENERAL | S8: 000001 | T8: Pago | U8: 9 | V8: 0000 | W8: NO APLICA | X8: HOSANLORE. SUELDO ENERO 2024_x000D_ HOSPITAL SAN LORENZO DE LOS MINA_x000D_ TEMPORAL | Y8: 25/01/2024 | Z8: 25/01/2024 | AA8: 2.1.1 | AB8: REMUNERACIONES | AC8: 2.1.1.2 | AD8: Remuneraciones al personal de carácter temporal | AE8: 2.1.1.2.08 | AF8: Empleados temporales | AG8: 686003.26
A9: 5180 | B9: DIRECCION CENTRAL DEL SERVICIO NACIONAL DE SALUD | C9: 01 | D9: DIRECCION CENTRAL DEL SERVICIO NACIONAL DE SALUD | E9: 0014 | F9: HOSPITAL MATERNO-INFANTIL SAN LORENZO DE LOS MINA | G9: 10 | H9: FONDO GENERAL | I9: 0001 | J9: Dirección y Coordinación | K9: 001 | L9: N/A | M9: 40 | N9: Salud materno neonatal | O9: 100 | P9: TESORO NACIONAL | Q9: 0100 | R9: FONDO GENERAL | S9: 000001 | T9: Pago | U9: 16 | V9: 0000 | W9: NO APLICA | X9: HOSANLORE. SUELDO FEBRERO 2024_x000D_ HOSPITAL SAN LORENZO DE LOS MINA_x000D_ TEMPORAL | Y9: 23/02/2024 | Z9: 23/02/2024 | AA9: 2.1.1 | AB9: REMUNERACIONES | AC9: 2.1.1.2 | AD9: Remuneraciones al personal de carácter temporal | AE9: 2.1.1.2.08 | AF9: Empleados temporales | AG9: 686003.26
A10: 5180 | B10: DIRECCION CENTRAL DEL SERVICIO NACIONAL DE SALUD | C10: 01 | D10: DIRECCION CENTRAL DEL SERVICIO NACIONAL DE SALUD | E10: 0014 | F10: HOSPITAL MATERNO-INFANTIL SAN LORENZO DE LOS MINA | G10: 10 | H10: FONDO GENERAL | I10: 0001 | J10: Dirección y Coordinación | K10: 001 | L10: N/A | M10: 40 | N10: Salud materno neonatal | O10: 100 | P10: TESORO NACIONAL | Q10: 0100 | R10: FONDO GENERAL | S10: 000001 | T10: Pago | U10: 166 | V10: 0000 | W10: NO APLICA | X10: HOSANLORE. SUELDO DE MARZO 2024_x000D_ NOMINA TEMPORAL | Y10: 21/03/2024 | Z10: 21/03/2024 | AA10: 2.1.1 | AB10: REMUNERACIONES | AC10: 2.1.1.2 | AD10: Remuneraciones al personal de carácter temporal | AE10: 2.1.1.2.08 | AF10: Empleados temporales | AG10: 732074.29
A11: 5180 | B11: DIRECCION CENTRAL DEL SERVICIO NACIONAL DE SALUD | C11: 01 | D11: DIRECCION CENTRAL DEL SERVICIO NACIONAL DE SALUD | E11: 0014 | F11: HOSPITAL MATERNO-INFANTIL SAN LORENZO DE LOS MINA | G11: 10 | H11: FONDO GENERAL | I11: 0001 | J11: Dirección y Coordinación | K11: 001 | L11: N/A | M11: 40 | N11: Salud materno neonatal | O11: 100 | P11: TESORO NACIONAL | Q11: 0100 | R11: FONDO GENERAL | S11: 000001 | T11: Pago | U11: 904 | V11: 0000 | W11: NO APLICA | X11: HOSANLORE. SUELDOS NOMINA TEMPORAL ABRIL 2024 | Y11: 22/04/2024 | Z11: 22/04/2024 | AA11: 2.1.1 | AB11: REMUNERACIONES | AC11: 2.1.1.2 | AD11: Remuneraciones al personal de carácter temporal | AE11: 2.1.1.2.08 | AF11: Empleados temporales | AG11: 732074.29
A12: 5180 | B12: DIRECCION CENTRAL DEL SERVICIO NACIONAL DE SALUD | C12: 01 | D12: DIRECCION CENTRAL DEL SERVICIO NACIONAL DE SALUD | E12: 0014 | F12: HOSPITAL MATERNO-INFANTIL SAN LORENZO DE LOS MINA | G12: 10 | H12: FONDO GENERAL | I12: 0001 | J12: Dirección y Coordinación | K12: 001 | L12: N/A | M12: 40 | N12: Salud materno neonatal | O12: 100 | P12: TESORO NACIONAL | Q12: 0100 | R12: FONDO GENERAL | S12: 000001 | T12: Pago | U12: 1295 | V12: 0000 | W12: NO APLICA | X12: HOSANLORE. SULEDO NOMINA TEMPORAL MAYO 2024 | Y12: 21/05/2024 | Z12: 21/05/2024 | AA12: 2.1.1 | AB12: REMUNERACIONES | AC12: 2.1.1.2 | AD12: Remuneraciones al personal de carácter temporal | AE12: 2.1.1.2.08 | AF12: Empleados temporales | AG12: 732074.29
A13: 5180 | B13: DIRECCION CENTRAL DEL SERVICIO NACIONAL DE SALUD | C13: 01 | D13: DIRECCION CENTRAL DEL SERVICIO NACIONAL DE SALUD | E13: 0014 | F13: HOSPITAL MATERNO-INFANTIL SAN LORENZO DE LOS MINA | G13: 10 | H13: FONDO GENERAL | I13: 0001 | J13: Dirección y Coordinación | K13: 001 | L13: N/A | M13: 40 | N13: Salud materno neonatal | O13: 100 | P13: TESORO NACIONAL | Q13: 0100 | R13: FONDO GENERAL | S13: 000001 | T13: Pago | U13: 1899 | V13: 0000 | W13: NO APLICA | X13: HOSANLORE. NOMINA SUELDO TEMPORAL JUNIO 2024_x000D_ SUELDO TEMPORAL JUNIO 2024 | Y13: 21/06/2024 | Z13: 21/06/2024 | AA13: 2.1.1 | AB13: REMUNERACIONES | AC13: 2.1.1.2 | AD13: Remuneraciones al personal de carácter temporal | AE13: 2.1.1.2.08 | AF13: Empleados temporales | AG13: 757074.29
... A446: 5180 | B446: DIRECCION CENTRAL DEL SERVICIO NACIONAL DE SALUD | C446: 01 | D446: DIRECCION CENTRAL DEL SERVICIO NACIONAL DE SALUD | E446: 0014 | F446: HOSPITAL MATERNO-INFANTIL SAN LORENZO DE LOS MINA | G446: 10 | H446: FONDO GENERAL | I446: 0001 | J446: Dirección y Coordinación | K446: 001 | L446: N/A | M446: 40 | N446: Salud materno neonatal | O446: 100 | P446: TESORO NACIONAL | Q446: 0100 | R446: FONDO GENERAL | S446: 000001 | T446: Pago | U446: 1044 | V446: 0000 | W446: NO APLICA | X446: Pago de Fact NCF No. B1500000008, por adquisicion de maquina industrial de costura, según orden de compra HSLM-2023-00755 | Y446: 03/05/2024 | Z446: 03/05/2024 | AA446: 2.6.5 | AB446: MAQUINARIA, OTROS EQUIPOS Y HERRAMIENTAS | AC446: 2.6.5.2 | AD446: Maquinaria y equipo industrial | AE446: 2.6.5.2.01 | AF446: Maquinaria y equipo industrial | AG446: 181720
AG448: =SUBTOTAL(9,AG2:AG447) -> 16311429
AG449: =+AG448-#REF! -> #REF!
AG984: =SUBTOTAL(9,AG2:AG983) -> #REF!
AG985: 4120195.3
AG986: =+AG984+AG985 -> #REF!

Sheet NOTAS 7 AL19
A1: Hospital Materno Infantil San Lorenzo de los Mina
A2: Nota a los Estados Financieros
A3: Del ejercicio terminado al 30 de abril 2025
A4: (Valores en RD$)
A6: Nota #7 Efectivo y equivalentes de efectivo.
A7: Detalle del efectivo y equivalente de efectivo al 30 de abril 2025 es como sigue:
A8: Descripción | C8: 2025
A9: Cuenta Bancaria Venta de Servicios No. 010-390450-6 | C9: =+'CONCILIACION '!G44 -> 1731116.6
A10: Cuenta Bancaria Fondo de Anticipo No. 960-454417-5 | C10: 0
A11: Cuenta Unica | C11: =+B14+B15 -> 3.0219372e+08
C12: =SUM(C8:C11) -> 3.0392686e+08
A14: Sub- Cuenta No. 0100269000 | B14: 3.0095074e+08
A15: Sub- Cuenta No. 995041000 | B15: 1242977.5
B16: =SUM(B14:B15) -> 3.0219372e+08
A17: TOTAL GENERAL
A19: Nota #8 Cuentas por cobrar a corto plazo
A20: Un detalle de las cuentas por cobrar 30 de abril 2025 es como sigue:
A21: Descripción | C21: 2024
A22: Cuentas por Cobrar por Ventas de Servicios | C22: =+CXC!B159 -> 18208482
A23: Cuentas por Cobrar Pacientes no Asegurados | C23: 63940334
A24: TOTAL GENERAL | C24: =SUM(C22:C23) -> 82148815
A25: Nota #9 Inventarios
A26: Un detalle de las partidas de inventario 30 de abril 2025 es como sigue:
A27: Descripción | C27: 2024
A28: Inventario De Utiles y Suministro de Oficina | C28: 7385934.8
A29: Inventario de Medicamentos | C29: =48965927.92+27706430.1 -> 76672358
A30: Inventario de Laboratorio | C30: 7545437.2
A31: Inventario de Perecederos | C31: 822695.3
A32: TOTAL GENERAL | C32: =SUM(C28:C31) -> 92426425
A34: Nota# 11 Cuentas por pagar a corto plazo
A35: Un detalle de las cuentas por pagar a corto plazo 30 de abril 2025 es como sigue:
A36: Descripción | C36: 2024
A37: Cuentas por Pagar a corto plazo proveedores (Sector Privado) | C37: =+'CUENTAS POR PAGAR'!N105 -> 21432969
A38: TOTAL GENERAL | C38: =SUM(C37:C37) -> 21432969
A40: Nota# 12 Retenciones y acumulaciones por pagar
A41: Un detalle de las retenciones y acumulaciones por pagar 30 de abril 2025 es como sigue:
A42: Descripción | C42: 2024
A43: Retenciones por pagar 5% | C43: =11389866.86+276884.63+183994.68 -> 11850746
A44: Retenciones por Pagar 10% | C44: =292785.08+2964.29 -> 295749.37
A45: Retencion de ITBIS | C45: =17550+26678.57 -> 44228.57
A46: TOTAL GENERAL | C46: =SUM(C43:C45) -> 12190724
A47: Nota# 13 Beneficios a empleados a corto plazo
A48: Un detalle de los beneficios a empleados a corto plazo 30 de abril 2025 es como sigue:
A49: Descripción | C49: 2024
A50: Incentivos por Pagar Empleados | C50: =+obligaciones!E13 -> 1249691.8
A51: Prestaciones Laborales | C51: =+obligaciones!E16 -> 0
A52: TOTAL GENERAL | C52: =SUM(C49:C51) -> 1251715.8
A53: Nota# 14 Patrimonio
A54: Un detalle del patrimonio al 30 de abril 2025 es como sigue:
A55: Activos Netos/Patrimonio | C55: 2024
A56: Capital | C56: 3.4196058e+08
A57: Resultados positivos (ahorro)/negativo (desahorro) | C57: =+'Est. de Rendimiento Fin'!B24 -> 1.4970253e+08
A58: Resultado acumulado | C58: =+'cambio en el patr.'!E11 -> -1.1119234e+08
A59: Ajuste periodos anteriores | C59: =+'cambio en el patr.'!E13 -> 2.2822818e+08
A60: Patrimonio Neto | C60: =+C56+C57+C58+C59 -> 6.0869896e+08
A62: Nota# 15. Ingresos por transacciones con contraprestaciones
A64: Un detalle de los ingresos por transacciones con contraprestaciones 30 de abril 2025 es como sigue:
A65: Descripción | C65: 2024
A66: Nota# 15.1. Ingresos por Contraprestacion
A67: Nota# 15.1 Ingresos por Venta de Servicios | C67: =+INGRESOS!E24+'INGRESOS FEBRERO'!E25+'INGRESOS MARZO'!E37+INGRESOS!E32 -> 24062967
A68: Total de Ingresos por Venta de Servicios | C68: =+C67 -> 24062967
A70: Nota# 15.2 Ingresos por Transferencia del Gobierno Central
A71: Transferencia del Gobierno Central / Ministerio de Salud | C71: 5.0575311e+08
A72: Sub-Total Transferencia del gobierno Central | C72: =SUM(C71:C71) -> 5.0575311e+08
A74: Nota# 15.4 Otros Ingresos
A75: Otros Ingresos | C75: =+INGRESOS!E29+'INGRESOS FEBRERO'!E31+'INGRESOS MARZO'!E44+INGRESOS!E39 -> 1182489.4
A76: Total de Otros Ingresos | C76: =+C75 -> 1182489.4
A78: Nota# 15.5 Anticipo Financiero
A79: Ingresos por Anticipo Financiero Cuenta Bancaria 960-454417-5 | C79: 0
A80: 15.5 Total de Ingresos por Anticipo Financiero Cuenta Bancaria 960-454417-5 | C80: =+C79 -> 0
A81: TOTAL GENERAL | C81: =+C67+C71+C75 -> 5.3099857e+08
A83: Nota # 16 Sueldos, Salarios y beneficios a empleados
A84: Un detalle de las cuentas sueldos, salarios, beneficios a empleados al 30 de abril 2025 es como sigue:
A85: Descripción | C85: 2024
A86: Sueldos | C86: =159434491.35+53482455.21-1107531.03-181111.08+3384964.48 -> 2.1501327e+08
A87: Contribuciones al seguro de salud | C87: =11529203.67+3870432.33 -> 15399636
A88: Contribuciones al seguro de pensiones | C88: =11545459.36+3875889.48 -> 15421349
A89: Contribuciones al seguro de riesgo laboral | C89: =1946469.26+653772.07 -> 2600241.3
A90: Remuneraciones al personal de carácter temporal | C90: =317753.09+1107531.03 -> 1425284.1
A91: Prestacion Laboral por desvinculacion | C91: =1333120.15+92400 -> 1425520.1
A92: Incentivo por Rendimiento Individual | C92: =5231553.59 -> 5231553.6
A93: Sueldo Anual 13 | C93: 0
A94: Sobresueldos | C94: =203792289.27-191338050.47+1377353.19 -> 13831592
A95: TOTAL GENERAL | C95: =SUM(C86:C94) -> 2.7034844e+08 | D95: =+C95-270348444.95 -> 0
A97: Nota# 17 Subvenciones y otros pagos por transferencias
A98: Un detalle Subvenciones y otros pagos por transferencias al 30 de abril 2025 es como sigue:
A99: Transferencias corrientes a personas | C99: =287786.7+624573 -> 912359.7
A100: TOTAL GENERAL | C100: =SUM(C99) -> 912359.7
A102: Nota# 18 Suministro y materiales para consumo
A103: Un detalle de los gastos de suministro y materiales para consumo al 30 de abril 2025 es como sigue:
A104: Descripción | C104: 2024
A106: Alimentos y Productos Agroforestales | C106: =5214653.04+907365 -> 6122018
A107: Textiles y Vestuarios | C107: =61630.73+1562980.47 -> 1624611.2
A108: Productos de Papel, Carton e Impresos | C108: =2078074.84+1707766.21 -> 3785841
A109: Combustibles, Lubricantes, Productos Quimicos y Conexos | C109: =2454417.07+506546.35+351015.88 -> 3311979.3
A110: Medicamentos, Util Medico y Productos Químicos de Uso Personal y de Laboratorios | C110: =11355336.6+9323811.55+19674791.99+6441109+2985728.89 -> 49780778
A111: Productos y Utiles Varios | C111: =22957907.64-19674791.99+8906360.83-4500.8 -> 12184976
A112: TOTAL GENERAL | C112: =SUM(C106:C111) -> 76810203
A113: Nota# 19 Gastos de depreciación y amortización
A114: Un detalle de los gastos de depreciación y amortización al 30 de abril 2025 es como sigue:
...

Sheet NOTA 10
A2: AÑO 2025
A4: Nota#10 Propiedad planta y equipo
B5: Terreno | C5: Infraestructura | D5: Edif. Y comp. | E5: Maq. Y Equipos | F5: Mob. Y equ. de ofic. | G5: Equipo,Transp y otros | H5: Const. En Proceso | I5: Total
A6: Costos de adquisición 2024 | B6: 0 | C6: 0 | D6: 0 | E6: 1.2590926e+08 | F6: 36903873 | G6: 0 | H6: 0 | I6: 1.6281313e+08
A7: Adiciones (AÑO 2025) | B7: 0 | C7: 0 | D7: 0 | E7: =22933910.83+4665041.39 -> 27598952 | G7: 0 | H7: 0 | I7: =+E7+F7 -> 27598952
A8: Saldo al final del periodo | B8: =SUM(B6:B7) -> 0 | C8: =SUM(C6:C7) -> 0 | D8: =SUM(D6:D7) -> 0 | E8: =SUM(E6:E7) -> 1.5350821e+08 | F8: =SUM(F6:F7) -> 36903873 | G8: =SUM(G6:G7) -> 0 | H8: =SUM(H6:H7) -> 0 | I8: =SUM(I6:I7) -> 1.9041208e+08
A10: Dep. Acum. al inicio del periodo | B10: 0 | D10: 0 | E10: 1926841.3 | F10: 9270238.7 | H10: 0 | I10: =SUM(B10:H10) -> 11197080
A11: Cargo del periodo | B11: 0 | C11: 0 | D11: 0 | E11: =+((E7*0.25)/12)+(((E6*0.25)/12)*4) -> 11067416 | F11: =+((F7*0.25)/12)+(((F6*0.25)/12)*4) -> 3075322.7 | H11: 0 | I11: =SUM(B11:H11) -> 14142739
A12: Saldo al final del periodo | B12: 0 | C12: 0 | D12: 0 | E12: =+E10+E11 -> 12994257 | F12: =+F10+F11 -> 12345561 | G12: =+G10+G11 -> 0 | H12: =+H10+H11 -> 0 | I12: =SUM(B12:H12) -> 25339819
A13: Prop. planta y equipos neto 2024 | B13: =SUM(B8-B12) -> 0 | C13: 0 | D13: =SUM(D8-D12) -> 0 | E13: =+E8-E12 -> 1.4051395e+08 | F13: =+F8-F12 -> 24558311 | G13: =+G8-G12 -> 0 | H13: =+H8-H12 -> 0 | I13: =SUM(I8-I12) -> 1.6507226e+08
A14: Nota: Nuestros Activos Fijos correspondiente a los años anteriores al 2021, estan siendo tasados, por lo que solo se reflejaran en este estado financiero los activos adquiridos durante el año 2021, 2022, 2023, 2024 y 2025, con su respectiva depreciacion.
A19: AÑO 2023
A21: Nota#10 Propiedad planta y equipo
B22: Terreno | C22: Infraestructura | D22: Edif. Y comp. | E22: Maq. Y Equipos | F22: Mob. Y equ. de ofic. | G22: Equipo,Transp y otros | H22: Const. En Proceso | I22: Total
A23: Costos de adquisición 2021 | B23: 1 | C23: 1 | D23: 1 | E23: 1674420 | F23: =2314111.33+10581957.22 -> 12896069 | G23: 1 | H23: 1 | I23: =+E23+F23 -> 14570489
A24: Adiciones (AÑO 2023) | B24: 0 | C24: 0 | D24: 0 | E24: =14051393.46+207414.5+48246.66+8339698.02 -> 22646753 | F24: =1893940.93+278000+280495.73+254362.5+286117.79+25804.24+394374.41+550970.21+970062.21+970224+175230+3152252+1444910+138549.7+58382.86+2382305.5+222902+129705.6+88500+170223.01+41300+186585.14+1753288.2+210134.4+172280+493068.19+103908.68+2039018.74+1113624.64+214052 -> 20194573 | G24: 0 | H24: 0 | I24: =+E24+F24 -> 42841325
A25: Saldo al final del periodo | B25: =SUM(B23+B24+#REF!-#REF!-#REF!-#REF!) -> #REF! | C25: =SUM(C23+C24+#REF!-#REF!-#REF!-#REF!) -> #REF! | D25: =SUM(D23+D24+#REF!-#REF!-#REF!-#REF!) -> #REF! | E25: =+E23+E24 -> 24321173 | F25: =+F23+F24 -> 33090641 | G25: =+G23+G24 -> 1 | H25: =+H23+H24 -> 1 | I25: =+I23+I24 -> 57411814
A27: Dep. Acum. al inicio del periodo | B27: 0 | D27: 0 | E27: 195349 | F27: 564252.85 | H27: 0 | I27: =SUM(B27:H27) -> 759601.85
A28: Cargo del periodo | B28: 0 | C28: 0 | D28: 0 | E28: =787877.58+471807.35+471807.35 -> 1731492.3 | F28: =6630044.48+393060.33+1682881.06 -> 8705985.9 | H28: 0 | I28: =SUM(B28:H28) -> 10437478
A29: Retiros | B29: 0 | C29: 0 | D29: 0 | F29: 0 | G29: 0 | H29: 0 | I29: =SUM(B29:H29) -> 0
A30: Saldo al final del periodo | B30: 0 | C30: 0 | D30: 0 | E30: =+E27+E28 -> 1926841.3 | F30: =+F27+F28 -> 9270238.7 | G30: 0 | H30: 0 | I30: =SUM(B30:H30) -> 11197080
A31: Prop. planta y equipos neto 2023 | B31: =SUM(B25-B30) -> #REF! | C31: =SUM(C25-C27-C28-C29) -> #REF! | D31: =SUM(D25-D30) -> #REF! | E31: =SUM(E25-E30) -> 22394331 | F31: =SUM(F25-F30) -> 23820403 | G31: =SUM(G25-G30) -> 1 | H31: =SUM(H25-H30) -> 1 | I31: =SUM(I25-I27-I28-I29) -> 46214734

Sheet Hoja6

Sheet obligaciones
B4: SERVICIO REGIONAL DE SALUD
B5: DIRECCIÓN DE FISCALIZACIÓN Y CONTROL
B6: DETALLE OBLIGACIONES CONTRAÍDAS PENDIENTES AL 30 DE ABRIL 2025
B7: HOSPITAL MATERNO INFANTIL SAN LORENZO DE LOS MINA
B8: A | C8: B | E8: C | F8: D | G8: E | H8: F
B9: TIPO | C9: PERÍODO | F9: STATUS PRESTAMO
C10: DESDE | D10: HASTA | E10: MONTO | F10: MONTO ORIGEN | G10: MONTO AMORTIZADO | H10: BALANCE PENDIENTE
B11: PROMESE CAL
B12: RETENCIONES DE IMPUESTOS (DGII) | C12: 44470 | D12: 45777 | E12: =6455721.37+191917.63+545919.42+146780.59+231604.06+289366.65+335354.64+387110.47+660164.03+254405.37+295100.71+268154.84+476725.77+301006.83+418780.67+471731.75+276884.63+183994.68 -> 12190724
B13: APROVISIONAMIENTOS DE INCENTIVOS | C13: 45505 | D13: 45777 | E13: =4432093.625+933892.46+332731.24+782528.07-5231553.59 -> 1249691.8
B14: SEGURIDAD SOCIAL
B15: APROVISIONAMIENTO DE REGALIA PASCUAL
B16: PRESTACIONES LABORALES
B17: VIATICOS
B18: PRÉSTAMOS Y/O ANTICIPOS FINANCIEROS OTORGADOS POR SENASA
B19: TOTAL | E19: =SUM(E12:E18)+E11 -> 13440416
B21: Nota. En el caso de las columnas D, E y F, solo aplican para llenado de los préstamos otogados por SENASA.
B25: Preparado por: | E25: Revisado por:

Sheet resumen compras
A1: REPUBLICA DOMINICANA
A2: SERVICIO NACIONAL DE SALUD
A3: LISTADO DE ORDENES DE COMPRAS DURANTE EL MES ABRIL 2024, VENTA DE SERVICIOS
A4: ESTABLECIMIENTO HOSPITAL MATERNO INFANTIL SAN LORENZO DE LOS MINA REGION SANTO DOMINGO ESTE
A5: Fecha | B5: No. Orden de Compra o Servicios | C5: No. De Factura Fiscal NCF | D5: Fuente. Financ FR-VS | E5: Beneficiario | F5: Rubro | G5: No. Cta. Objetal del Gasto | H5: Valor pesos dominicanos
A6: 45383 | B6: HSLM-2024-00285 | C6: HSLM-DAF-CM-2024-0086 | E6: CARLOS RAFAEL DE PAULA ROSSO | F6: 73152102 | G6: 2.2.7.2.08 | H6: 746173
A7: 45383 | B7: HSLM-2024-00286 | C7: HSLM-DAF-CD-2024-0050 | E7: LEFP CONSULTORES, SRL | F7: 81112501 | G7: 2.2.5.9.01 | H7: 195408
A8: 45384 | B8: HSLM-2024-00287 | C8: HSLM-DAF-CD-2024-0104 | E8: OFICLIN COMERCIAL, SRL | F8: 48101516 | G8: 2.6.1.4.01 | H8: 149956.3
A9: 45384 | B9: HSLM-2024-00288 | C9: HSLM-DAF-CD-2024-0105 | E9: G & M GELMAT COMERCIAL, SRL | F9: 52141501 | G9: 2.6.1.4.01 | H9: 211459.92
A10: 45384 | B10: HSLM-2024-00289 | C10: HSLM-DAF-CM-2024-0087 | E10: INSOCORP, SRL | F10: 42295123 | G10: 2.6.3.1.01 | H10: 1716900
A11: 45384 | B11: HSLM-2024-00290 | C11: HSLM-DAF-CM-2024-0085 | E11: BIO NOVA, SRL | F11: 41103001 | G11: 2.6.3.4.01 | H11: 326565
A12: 45384 | B12: HSLM-2024-00291 | C12: HSLM-DAF-CD-2024-0088 | E12: OSIRIS & CO, SA | F12: 42172101 | G12: 2.6.3.1.01 | H12: 609673.18
A13: 45385 | B13: HSLM-2024-00292 | C13: HSLM-DAF-CD-2024-0108 | E13: SAVEV SERVICIOS GENERALES, SRL | F13: 47121701 | G13: 2.3.9.3.01 | H13: 113280
A14: 45385 | B14: HSLM-2024-00293 | C14: HSLM-DAF-CD-2024-0106 | E14: GLOBAL MULTIPHARMA DOMINICANA RHM, SRL | F14: 42132201 | G14: 2.3.9.3.01 | H14: 204000
A15: 45385 | B15: HSLM-2024-00294 | C15: HSLM-DAF-CD-2024-0107 | E15: GLOBAL MULTIPHARMA DOMINICANA RHM, SRL | F15: 42312201 | G15: 2.3.9.3.01 | H15: 108000
A16: 45385 | B16: HSLM-2024-00295 | C16: HSLM-DAF-CD-2024-0103 | E16: ADLER AMICIS VALDEZ MARMOLEJOS | F16: 55121727 | G16: 2.3.9.9.05 | H16: 10620
A17: 45385 | B17: HSLM-2024-00296 | C17: HSLM-DAF-CM-2024-0089 | E17: Xavier Vargas, Ingeniería Electromecánica, EIRL | F17: 72101511 | G17: 2.2.7.2.08 | H17: 397424
... A72: 45401 | B72: HSLM-2024-00351 | C72: HSLM-DAF-CD-2024-0161 | E72: DISTRIBUIDORA RICEA E SANA DI M.C | F72: 42132205 | G72: 2.3.9.3.01 | H72: 177000
A73: 19/4/20224 | B73: HSLM-2024-00352 | C73: HSLM-DAF-CM-2024-0103 | E73: SERVIAMED DOMINICANA, SR. | F73: 42191807 | G73: 2.6.3.1.01 | H73: 254785.6
A74: 45401 | B74: HSLM-2024-00353 | C74: HSLM-DAF-CD-2024-0149 | E74: VENTAS DIVERSAS FARMACEUTICAS,SRL | F74: 51161812 | G74: 2.3.4.1.01 | H74: 6145
A75: 45401 | B75: HSLM-2024-00354 | C75: HSLM-DAF-CD-2024-0152 | E75: SMART SUPPLY MEDICAL DOMINICANA, SRL | F75: 42221503 | G75: 2.3.9.3.01 | H75: 141600
A76: 45401 | B76: HSLM-2024-00355 | C76: HSLM-DAF-CD-2024-0157 | E76: CRISTINA ROSARIO ROSARIO | F76: 48102107 | G76: 2.3.9.9.05 | H76: 60770
A77: 45401 | B77: HSLM-2024-00356 | C77: HSLM-DAF-CM-2024-0104 | E77: JM Distribución, SRL | F77: 14111704 | G77: 2.3.2.3.01 | H77: 416249.13
A78: 45404 | B78: HSLM-2024-00357 | C78: HSLM-DAF-CD-2024-0158 | E78: TENDAMED, SRL | F78: 42271903 | G78: 2.3.9.3.01 | H78: 78824
A79: 45404 | B79: HSLM-2024-00358 | C79: HSLM-DAF-CD-2024-0159 | E79: COMPRA-MED, SRL | F79: 42312202 | G79: 2.3.9.3.01 | H79: 159300
A80: 45404 | B80: HSLM-2024-00359 | C80: HSLM-DAF-CD-2024-0160 | E80: IMPRESOS C Y M, SRL | F80: 53101502 | G80: 2.3.2.3.01 | H80: 46728
A81: 45404 | B81: HSLM-2024-00360 | C81: HSLM-DAF-CD-2024-0156 | E81: ROPHARMA, SRL | F81: 51161703 | G81: 2.3.4.1.01 | H81: 254450
A82: 45404 | B82: HSLM-2024-00361 | C82: HSLM-DAF-CD-2024-0156 | E82: ROPHARMA, SRL | F82: 51161703 | G82: 2.3.4.1.01 | H82: 140850
A83: 45405 | B83: HSLM-2024-00362 | C83: HSLM-DAF-CD-2024-0163 | E83: SLYKING GROUP, SRL | F83: 80141607 | G83: 2.2.8.6.01 | H83: 174451.2
A84: 45405 | B84: HSLM-2024-00363 | C84: HSLM-DAF-CD-2024-0164 | E84: VENDIFAR, SRL | F84: 51161703 | G84: 2.3.4.1.01 | H84: 190000
A85: 45405 | B85: HSLM-2024-00364 | C85: HSLM-DAF-CD-2024-0166 | E85: MUEBLES OMAR | F85: 42221503 | G85: 2.3.9.3.01 | H85: 88087
... A101: 45407 | B101: HSLM-2024-00380 | C101: HSLM-DAF-CD-2024-0178 | E101: Q&Q Medical RD, SRL | F101: 41116003 | G101: 2.3.7.2.03 | H101: 80363.9
A102: 45407 | B102: HSLM-2024-00381 | C102: HSLM-DAF-CM-2024-0114 | E102: ARDAN, SRL | F102: 81112501 | G102: 2.2.5.9.01 | H102: 1726924.1
A103: 45408 | B103: HSLM-2024-00382 | C103: HMISLM-DAF-CD-2024-0179 | E103: BAUCOMER, SRL | F103: 51131801 | G103: 2.3.4.1.01 | H103: 226745
A104: 45412 | B104: HSLM-2024-00383 | C104: HMISLM-DAF-CD-2024-0181 | E104: COPEM HOSPICLINIC, SRL | F104: 42142503 | G104: 2.3.9.3.01 | H104: 149665.3
A105: 45412 | B105: HSLM-2024-00384 | C105: HMISLM-DAF-CD-2024-0180 | E105: IGBT SRL | F105: 73152102 | G105: 2.2.7.2.08 | H105: 233640
A106: 45412 | B106: HSLM-2024-00385 | C106: HSLM-DAF-CM-2024-0116 | E106: JM Distribución, SRL | F106: 52151503 | G106: 2.3.9.5.01 | H106: 771696.55
A107: 45412 | B107: HSLM-2024-00386 | C107: HSLM-DAF-CM-2024-0117 | E107: EXPRES SERVICE CONSERG EXSERCON, SRL | F107: 42295112 | G107: 2.3.9.6.01 | H107: 1156400
A108: 45412 | B108: HSLM-2024-00387 | C108: HSLM-DAF-CD-2024-0119 | E108: EXPRES SERVICE CONSERG EXSERCON, SRL | F108: 42295112 | G108: 2.3.9.6.01 | H108: 826000
A109: 45412 | B109: HSLM-2024-00388 | C109: HSLM-DAF-CM-2024-0120 | E109: MANTENERGIA ELECTRICA Y ABASTECIMIENTOS, SRL | F109: 73152102 | G109: 2.2.8.7.06 | H109: 1184600.7
A110: 45412 | B110: HSLM-2024-00389 | C110: HSLM-DAF-CD-2024-0126 | E110: Súper Laptop Browsing, SRL | F110: 41116122 | G110: 2.6.3.4.01 | H110: 113775
F111: Total Ordenes Compras RD$ | H111: =SUM(H6:H110) -> 37162273
A114: RESUMEN DE COMPRAS O SERVICIOS POR CUENTAS: | F114: RESUMEN DE PROCESO SEGÚN MODALIDAD:
A116: CUENTAS No. | B116: CANTIDAD | C116: MONTO | F116: TIPO | G116: CANTIDAD | H116: MONTO
A117: 2.2.2.2.01 | B117: 2 | C117: =H87+H49 -> 388515 | F117: Compra Directa | G117: 73 | H117: =H110+H105+H104+H103+H101+H100+H99+H98+H96+H95+H93+H89+H86+H85+H84+H83+H82+H80+H79+H78+H76+H75+H74+H72+H70+H68+H66+H65+H64+H63+H62+H59+H58+H57+H56+H55+H54+H53+H52+H51+H50+H49+H45+H43+H42+H41+H40+H39+H37+H36+H35+H34+H33+H31+H30+H29+H27+H26+H25+H24+H23+H22+H21+H20+H19+H18+H16+H15+H14+H13+H9+H8+H7 -> 9758705.3
A118: 2.3.1.1.01 | B118: 1 | C118: =H66 -> 61596
A119: 2.3.2.3.01 | B119: 3 | C119: =H91+H80+H77 -> 722577.13 | F119: Compra Menor | G119: 26 | H119: =H109+H108+H107+H106+H102+H97+H94+H92+H91+H90+H88+H87+H81+H77+H73+H71+H69+H67+H61+H60+H48+H47+H46+H44+H38+H32+H28+H17+H12+H11+H10+H6 -> 27403567
A120: 2.2.4.2.01 | B120: 1 | C120: =H19 -> 96000 | F120: Comparacion de precio
A121: 2.2.5.9.01 | B121: 2 | C121: =H102+H7 -> 1922332.1 | F121: TOTAL COMPRAS | H121: =SUM(H117:H120) -> 37162273
A122: 2.2.7.2.08 | B122: 3 | C122: =H105+H17+H6 -> 1377237
A123: 2.2.8.6.01 | B123: 1 | C123: =H83 -> 174451.2
A124: 2.2.8.7.06 | B124: 7 | C124: =H109+H70+H69+H68+H67+H61+H90 -> 5291325.5
A125: 2.3.1.1.01 | B125: 1 | C125: =H47 -> 714177.9
A126: 2.3.3.1.01 | B126: 4 | C126: =H99++H95+H88+H18 -> 855618
A127: 2.3.4.1.01 | B127: 16 | C127: =H103+H100+H98+H97+H89+H84+H82+H81+H74+H65+H64+H42+H33+H31+H22+H63 -> 3772248.6 | F127: ENC. DE COMPRAS:__________________________
A128: 2.3.7.1.01 | B128: 1 | C128: =H38 -> 520000
A129: 2.3.7.2.03 | B129: 11 | C129: =H35+H36+H46+H51+H54+H56+H57+H58+H62+H101+H30 -> 1763675.8
A130: 2.3.7.2.99 | B130: 1 | C130: =H28 -> 1139880
A131: 2.3.9.1.01 | B131: 2 | C131: =H55+H29 -> 443237.5
A132: 2.3.9.3.01 | B132: 28 | C132: =H104+H94+H93+H86+H85+H79+H78+H75+H72+H71+H60+H59+H53+H52+H50+H41+H40+H39+H34+H32+H27+H26+H25+H21+H20+H15+H14+H13 -> 6631497.8
A133: 2.3.9.5.01 | B133: 1 | C133: =H106 -> 771696.55
A134: 2.3.9.6.01 | B134: 4 | C134: =H108+H107+H92+H44 -> 5021859.3
A135: 2.3.9.8.02 | B135: 1 | C135: =H24 -> 10150.01
A136: 2.3.9.9.05 | B136: 2 | C136: =H16+H76 -> 71390
A137: 2.6.1.1.01 | B137: 3 | C137: =H96+H45+H23 -> 452315.48
A138: 2.6.1.4.01 | B138: 2 | C138: =H8+H9 -> 361416.22
A139: 2.6.3.1.01 | B139: 4 | C139: =H73+H48+H12+H10 -> 3808558.8
A140: 2.6.3.4.01 | B140: 2 | C140: =H11+H110 -> 440340 | F140: CERTIFICO CORRECTO:
A141: 2.6.5.6.01 | B141: 1 | C141: =H37 -> 105739.8
A142: 2.6.5.8.01 | B142: 1 | C142: =H43 -> 244437
A143: TOTAL RESUMEN | B143: =SUM(B120:B142) -> 99 | C143: =SUM(C117:C142) -> 37162273 | F143: __________________________
F144: DIRECTOR
F149: __________________________
F150: ADMINISTRADOR:
A156: CUENTAS No. | B156: MONTO
A157: 2.2.2 | B157: 388515
A158: 2.3.1 | B158: 61596
A159: 2.3.2 | B159: 722577.13
A160: 2.2.4 | B160: 96000
A161: 2.2.5 | B161: 1922332.1
A162: 2.2.7 | B162: 1377237
A163: 2.2.8 | B163: 174451.2
A164: 2.2.8 | B164: 5291325.5
A165: 2.3.1 | B165: 714177.9
A166: 2.3.3 | B166: 855618
A167: 2.3.4 | B167: 3772248.6
A168: 2.3.7 | B168: 520000
... A170: 2.3.7 | B170: 1139880
A171: 2.3.9 | B171: 443237.5 | C171: =+B171+B172+B173+B174+B175+B176+B167+B168+B169+B170 -> 20145636
A172: 2.3.9 | B172: 6631497.8
A173: 2.3.9 | B173: 771696.55
A174: 2.3.9 | B174: 5021859.3
A175: 2.3.9 | B175: 10150.01
A176: 2.3.9 | B176: 71390
A177: 2.6.1 | B177: 452315.48
A178: 2.6.1 | B178: 361416.22
A179: 2.6.3 | B179: 3808558.8
A180: 2.6.3 | B180: 440340
A181: 2.6.5 | B181: 105739.8
A182: 2.6.5 | B182: 244437

Sheet CXC
A4: HOSPITAL MATERNO INFANTIL SAN LORENZO DE LOS MINA
A5: CUENTAS POR COBRAR ARS AÑO 2025
A7: Auxiliar Cuentas por Cobrar SeNaSa Subsidiado
J8: Balance Anterior | K8: 2710241.1
A9: ARS | B9: FECHA DE CORTE AUDITORIA | C9: CANTIDAD DE EXPEDIENTES | D9: MONTO GENERAL DE FACTURACION | E9: MONTO AUDITADO | F9: MONTO GLOSADO | G9: % | H9: Valor Facturado | I9: Referencia Documento de pago (CK-T) | J9: Monto pagado | K9: Balance CxC
A10: ARS SENASA SUBSIDIADO | B10: 45657 | D10: 4014536.9 | E10: 4014536.9 | F10: 85535 | G10: =+F10/E10 -> 0.021306318 | H10: 3929001.9 | K10: =+K8+H10 -> 6639243
A11: ARS SENASA SUBSIDIADO | I11: 02/01/2025 | J11: 4783111.5 | K11: =+K10+H11-J11 -> 1856131.5
A12: ARS SENASA SUBSIDIADO | I12: 09/01/2025 | J12: 50000 | K12: =+K11+H12-J12 -> 1806131.5
A13: ARS SENASA SUBSIDIADO | B13: 45688 | D13: 4840265.3 | E13: 4840265.3 | F13: 147829.22 | G13: =+F13/E13 -> 0.030541553 | H13: =+E13-F13 -> 4692436.1 | K13: =+K12+H13-J13 -> 6498567.6
A14: ARS SENASA SUBSIDIADO | B14: 45693 | J14: 5841673.2 | K14: =+K13+H14-J14 -> 656894.41
A15: ARS SENASA SUBSIDIADO | D15: 3228340.8 | E15: 3228340.8 | F15: 81431.03 | G15: =+F15/E15 -> 0.025223803 | H15: =+E15-F15 -> 3146909.7 | K15: =+K14+H15-J15 -> 3803804.1
A16: ARS SENASA SUBSIDIADO | B16: 45716 | J16: =4595181.39+50000 -> 4645181.4 | K16: =+K15+H16-J16 -> -841377.26
A17: ARS SENASA SUBSIDIADO | B17: 45747 | D17: 3267715.2 | E17: =+D17 -> 3267715.2 | F17: 68054 | G17: =+F17/E17 -> 0.020826172 | H17: =+E17-F17 -> 3199661.2 | I17: 1/4/2025 | J17: 2942930.3 | K17: =+H17-J17+K16 -> -584646.35
A18: ARS SENASA SUBSIDIADO | I18: 01/04/2025 | J18: 50000 | K18: =+H18-J18+K17 -> -634646.35
I19: 03/04/2025 | J19: 50000 | K19: =+H19-J19+K18 -> -684646.35
A20: TOTALES | D20: =SUM(D10:D19) -> 15350858 | E20: =SUM(E10:E19) -> 15350858 | F20: =SUM(F10:F19) -> 382849.25 | G20: =SUM(G10:G19) -> 0.097897846 | H20: =SUM(H10:H19) -> 14968009 | I20: =SUM(I10:I19) -> 0 | J20: =SUM(J10:J19) -> 18362896 | K20: =+K19 -> -684646.35
A23: Auxiliar Cuentas por Cobrar Ars Privadas
I24: BALANCE ANTERIOR | J24: 15638558
A25: ARS | B25: FECHA DE CORTE | C25: NCF | D25: CANTIDAD DE FACTURAS | E25: MONTO FACTURADO | F25: Referencia Documento de pago (CK-T) | G25: MONTO GLOSADO | H25: MONTO PAGADO | I25: DESMONTE POSTERIOR AL PAGO | J25: Balance CxC
A26: HUMANO | B26: 45667 | C26: B0100001070 | E26: 44770.98 | J26: =+J24+E26-H26 -> 15683329
A27: P. HUMANO | B27: 45667 | C27: B0100001071 | E27: 259154.57 | J27: =+J26+E27-G27-H27 -> 15942483
A28: MAPFRE AMB. | B28: 45667 | C28: B0100001072 | E28: 39434.4 | J28: =+J27+E28-G28-H28 -> 15981917
A29: MAPFRE EMERG. | B29: 45667 | C29: B0100001073 | E29: 16378.75 | J29: =+J28+E29-G29-H29 -> 15998296
A30: MAPFRE HOSP. | B30: 45667 | C30: B0100001074 | E30: 155901.42 | J30: =+J29+E30-G30-H30 -> 16154198
A31: RENACER | B31: 45667 | C31: B0100001075 | E31: 275352.44 | J31: =+J30+E31-G31-H31 -> 16429550
A32: YUNEN | B32: 45667 | C32: B0100001076 | E32: 7848.94 | J32: =+J31+E32-G32-H32 -> 16437399
A33: ASEMAP | B33: 45667 | C33: B0100001077 | E33: 4869.52 | J33: =+J32+E33-G33-H33 -> 16442269
A34: FUTURO | B34: 45667 | C34: B0100001078 | E34: 269639.73 | G34: 2300 | J34: =+J33+E34-G34-H34 -> 16709608
A35: MONUMENTAL | B35: 45667 | C35: B0100001079 | E35: 75131.09 | J35: =+J34+E35-G35-H35 -> 16784739
A36: RESERVAS | B36: 45667 | C36: B0100001080 | E36: 48081.02 | J36: =+J35+E36-G36-H36 -> 16832820
A37: CMD | B37: 45667 | C37: B0100001081 | E37: 273646.7 | J37: =+J36+E37-G37-H37 -> 17106467
A38: META SALUD | B38: 45667 | C38: B0100001082 | E38: 1396 | J38: =+J37+E38-G38-H38 -> 17107863
A39: SIMAG | B39: 45667 | C39: B0100001083 | E39: 28637.51 | J39: =+J38+E39-G39-H39 -> 17136501
A40: GMA | B40: 45667 | C40: B0100001084 | E40: 76159.34 | J40: =+J39+E40-G40-H40 -> 17212660
A41: APS | B41: 45667 | C41: B0100001085 | E41: 69588.33 | J41: =+J40+E41-G41-H41 -> 17282248
A42: RENACER | B42: 45674 | H42: 156983.55 | J42: =+J41+E42-G42-H42 -> 17125265
A43: MAPFRE AMB. | B43: 45677 | H43: 143189.49 | J43: =+J42+E43-G43-H43 -> 16982075
A44: MAPFRE EMERG. | B44: 45677 | H44: 55488.8 | J44: =+J43+E44-G44-H44 -> 16926586
A45: MAPFRE HOSP. | B45: 45677 | H45: 8230.16 | J45: =+J44+E45-G45-H45 -> 16918356
A46: ARS SEMMA | B46: 45677 | H46: 15993.02 | J46: =+J45+E46-G46-H46 -> 16902363
A47: ARS ASEMAP | B47: 45680 | H47: 6475.14 | J47: =+J46+E47-G47-H47 -> 16895888
A48: ARS MONUMENTAL | B48: 45680 | H48: 71992.2 | J48: =+J47+E48-G48-H48 -> 16823896
A49: ARS CMD | B49: 45681 | H49: 273646.7 | J49: =+J48+E49-G49-H49 -> 16550249
A50: ARS FUTURO | B50: 45686 | H50: 234503.89 | J50: =+J49+E50-G50-H50 -> 16315745
A51: ARS RESERVAS | B51: 45687 | H51: 48081.02 | J51: =+J50+E51-G51-H51 -> 16267664
A52: ARS YUNEN | B52: 45688 | H52: 55135.74 | J52: =+J51+E52-G52-H52 -> 16212529
A53: HUMANO | B53: 45698 | C53: B01000001085 | E53: 16720.82 | J53: =+J52+E53-G53-H53 -> 16229249
A54: P. HUMANO | B54: 45698 | C54: B01000001086 | E54: 439967.13 | J54: =+J53+E54-G54-H54 -> 16669217
A55: MAPFRE AMB. | B55: 45698 | C55: B01000001087 | E55: 65463.45 | J55: =+J54+E55-G55-H55 -> 16734680
A56: MAPFRE EMERG. | B56: 45698 | C56: B01000001088 | E56: 12918.96 | J56: =+J55+E56-G56-H56 -> 16747599
A57: MAPFRE HOSP. | B57: 45698 | C57: B01000001089 | E57: 311477.59 | J57: =+J56+E57-G57-H57 -> 17059077
A58: RENACER | B58: 45698 | C58: B01000001090 | E58: 222716.34 | J58: =+J57+E58-G58-H58 -> 17281793
A59: meta salud | B59: 45698 | C59: B01000001091 | E59: 20821.36 | J59: =+J58+E59-G59-H59 -> 17302614
A60: APS | B60: 45698 | C60: B01000001092 | E60: 122630.62 | J60: =+J59+E60-G60-H60 -> 17425245
A61: YUNEN | B61: 45698 | C61: B01000001093 | E61: 14338.35 | J61: =+J60+E61-G61-H61 -> 17439583
A62: ASEMAP | B62: 45698 | C62: B01000001094 | E62: 102975.46 | J62: =+J61+E62-G62-H62 -> 17542559
A63: FUTURO | B63: 45698 | C63: B01000001095 | E63: 617068.65 | G63: 4547.79 | J63: =+J62+E63-G63-H63 -> 18155080
A64: MONUMENTAL | B64: 45698 | C64: B01000001096 | E64: 146560.32 | J64: =+J63+E64-G64-H64 -> 18301640
A65: RESERVAS | B65: 45698 | C65: B01000001097 | E65: 217047.26 | J65: =+J64+E65-G65-H65 -> 18518687
A66: CMD | B66: 45698 | C66: B01000001098 | E66: 41285.9 | J66: =+J65+E66-G66-H66 -> 18559973
A67: sigma | B67: 45698 | C67: B01000001099 | E67: 92478.63 | J67: =+J66+E67-G67-H67 -> 18652452
A68: GMA | B68: 45698 | C68: B01000001101 | E68: 186957.88 | J68: =+J67+E68-G68-H68 -> 18839410
A69: SEMMA | B69: 45698 | C69: B15000000290 | E69: 28868.13 | J69: =+J68+E69-G69-H69 -> 18868278
A70: SENASA PENSIONADO | B70: 45698 | C70: B1500000289 | E70: 10985.64 | J70: =+J69+E70-G70-H70 -> 18879263
A71: Contributivo | B71: 45698 | C71: B1500000288 | E71: 2417181.1 | G71: 68679.07 | J71: =+J70+E71-G71-H71 -> 21227765
A72: Contributivo | B72: 45693 | H72: 2152926.5 | J72: =+J71+E72-G72-H72 -> 19074839
A73: ARS Renacer | B73: 45706 | H73: 272552.44 | J73: =+J72+E73-G73-H73 -> 18802286
A74: ARS APS | B74: 45709 | H74: 8262.07 | J74: =+J73+E74-G74-H74 -> 18794024
A75: ARS ASEMAP | B75: 45698 | H75: 4869.52 | J75: =+J74+E75-G75-H75 -> 18789155
A76: ARS YUNEN | B76: 45714 | H76: 7848.94 | J76: =+J75+E76-G76-H76 -> 18781306
A77: ARS CMD | B77: 45714 | H77: 41071.9 | J77: =+J76+E77-G77-H77 -> 18740234
A78: ARS SEMMA | B78: 45716 | H78: 9531.6 | J78: =+J77+E78-G78-H78 -> 18730702
A79: HUMANO | B79: 45709 | H79: 97648.3 | J79: =+J78+E79-G79-H79 -> 18633054
A80: ARS PRIMER | B80: 45709 | H80: 870590.25 | J80: =+J79+E80-G80-H80 -> 17762464
A81: META SALUD | B81: 45712 | H81: 31949.94 | J81: =+J80+E81-G81-H81 -> 17730514
A82: HUMANO | B82: 45726 | C82: B01000001107 | E82: 83376.61 | J82: =+J81+E82-G82-H82 -> 17813890
A83: P. HUMANO | B83: 45726 | C83: B01000001108 | E83: 404678.83 | J83: =+J82+E83-G83-H83 -> 18218569
A84: MAPFRE AMB. | B84: 45726 | C84: B01000001104 | E84: 53140.7 | J84: =+J83+E84-G84-H84 -> 18271710
A85: MAPFRE EMERG. | B85: 45726 | C85: B01000001105 | E85: 6743.06 | J85: =+J84+E85-G85-H85 -> 18278453
A86: MAPFRE HOSP. | B86: 45726 | C86: B01000001106 | E86: 130031.72 | J86: =+J85+E86-G86-H86 -> 18408485
A87: RENACER | B87: 45726 | C87: B01000001120 | E87: 73918.68 | J87: =+J86+E87-G87-H87 -> 18482403
A88: meta salud | B88: 45726 | C88: B01000001118 | E88: 81556.77 | G88: 714.6 | J88: =+J87+E88-G88-H88 -> 18563246
A89: APS | B89: 45726 | C89: B01000001109 | E89: 43770.8 | J89: =+J88+E89-G89-H89 -> 18607016
A90: YUNEN | B90: 45726 | C90: B01000001119 | E90: 162551.53 | J90: =+J89+E90-G90-H90 -> 18769568
A91: ASEMAP | B91: 45726 | C91: B01000001110 | E91: 6619.63 | J91: =+J90+E91-G91-H91 -> 18776188
A92: FUTURO | B92: 45726 | C92: B01000001112 | E92: 372255.06 | G92: 6159.88 | J92: =+J91+E92-G92-H92 -> 19142283
A93: MONUMENTAL | B93: 45726 | C93: B01000001113 | E93: 85258.31 | J93: =+J92+E93-G93-H93 -> 19227541
A94: RESERVAS | B94: 45726 | C94: B01000001114 | E94: 79962.77 | J94: =+J93+E94-G94-H94 -> 19307504
A95: CMD | B95: 45726 | C95: B01000001115 | E95: 22435.77 | J95: =+J94+E95-G95-H95 -> 19329940
A96: sigma | B96: 45726 | C96: B01000001116 | E96: 2821.24 | J96: =+J95+E96-G96-H96 -> 19332761
A97: GMA | B97: 45726 | C97: B01000001117 | E97: 136798.59 | J97: =+J96+E97-G97-H97 -> 19469559
A98: SEMMA | B98: 45726 | C98: B15000000293 | E98: 10657.5 | J98: =+J97+E98-G98-H98 -> 19480217
A99: SENASA PENSIONADO | B99: 45726 | C99: B15000000295 | E99: 13000 | J99: =+J98+E99-G99-H99 -> 19493217
A100: Contributivo | B100: 45726 | C100: B15000000294 | E100: 2645113.9 | G100: 11137 | J100: =+J99+E100-G100-H100 -> 22127194
A101: Contributivo | B101: 45730 | H101: 1041144.3 | J101: =+J100+E101-G101-H101 -> 21086050
A102: ARS YUNEN | B102: 45744 | H102: 14338.35 | J102: =+J101+E102-G102-H102 -> 21071711
A103: ARS FUTURO | B103: 45741 | H103: 356314.76 | J103: =+J102+E103-G103-H103 -> 20715396
A104: ARS ASEMAP | B104: 45740 | H104: 102672.34 | J104: =+J103+E104-G104-H104 -> 20612724
A105: ARS PRIMER | B105: 45737 | H105: 262926.38 | J105: =+J104+E105-G105-H105 -> 20349798
A106: ARS HUMANO | B106: 45737 | H106: 34117.68 | J106: =+J105+E106-G106-H106 -> 20315680
...

Sheet CUENTAS POR PAGAR
A1: Servicio Nacional de Salud
A2: DIRECCION DE FISCALIZACION
A3: RELACION DEUDA
A4: ESTABLECIMIENTO: | B4: HOSPITAL MATERNO INFANTIL SAN LORENZO DE LOS MINA | D4: CUENTAS POR PAGAR A: | E4: 45748
A6: NO | B6: NOMBRES PROVEEDOR | C6: CONCEPTO | D6: FUENTE FINANCIMIENTO | E6: Años anteriores 2020 | F6: AL 31 DICIEMBRE 2021 | G6: AL 31 DICIEMBRE 2022 | H6: AL 31 DICIEMBRE 2023 | I6: Al 31 DICIEMBRE 2024 | J6: AL 31 DE ENERO 2025 | K6: AL 28 DE FEBRERO 2025 | L6: 31 DE MARZO 2025 | M6: 30 DE ABRIL 2025 | N6: TOTAL ADEUDA
A7: 1 | B7: Hospifar, SRL | D7: VS/FG | H7: 94965 | N7: =SUM(E7:M7) -> 94965
A8: =+A7+1 -> 2 | B8: Hospifar, SRL | D8: VS/FG | H8: 11375 | N8: =SUM(E8:M8) -> 11375
A9: =+A8+1 -> 3 | B9: Ventas Diversas Farmaceuticas, SRL (VENDIFAR) | D9: VS/FG | H9: 224775 | N9: =SUM(E9:M9) -> 224775
A10: =+A9+1 -> 4 | B10: GA INTERPRISE IMPORT, SRL | D10: VS/FG | H10: 287920 | N10: =SUM(E10:M10) -> 287920
A11: =+A10+1 -> 5 | B11: D, CORA INDUSTRIAL, S.R.L | D11: VS/FG | H11: 220483.05 | N11: =SUM(E11:M11) -> 220483.05
A12: =+A11+1 -> 6 | B12: VARA, SRL. | D12: VS/FG | H12: 58382.86 | N12: =SUM(E12:M12) -> 58382.86
A13: =+A12+1 -> 7 | B13: Ventas Diversas Farmaceuticas, SRL (VENDIFAR) | D13: VS/FG | H13: 171690 | N13: =SUM(E13:M13) -> 171690
A14: =+A13+1 -> 8 | B14: Morami, SRL | D14: VS/FG | H14: 213260 | N14: =SUM(E14:M14) -> 213260
A15: =+A14+1 -> 9 | B15: Leromed Pharma, SRL | D15: VS/FG | H15: 167208 | N15: =SUM(E15:M15) -> 167208
A16: =+A15+1 -> 10 | B16: Caribbean Integrated Solutions, SRL | D16: VS/FG | H16: 400 | N16: =SUM(E16:M16) -> 400
A17: =+A16+1 -> 11 | B17: Insocorp, S.R.L. | D17: VS/FG | H17: 150096 | N17: =SUM(E17:M17) -> 150096
A18: =+A17+1 -> 12 | B18: SLYKING GROUP, SRL | D18: VS/FG | I18: 39361.26 | N18: =SUM(E18:M18) -> 39361.26
A19: =+A18+1 -> 13 | B19: FARMACIA RUTH | D19: VS/FG | I19: 88100 | N19: =SUM(E19:M19) -> 88100
A20: =+A19+1 -> 14 | B20: Macrotech Farmacéutica, SRL | D20: VS/FG | I20: 215000 | N20: =SUM(E20:M20) -> 215000
A21: =+A20+1 -> 15 | B21: LE.F.P CONSULTORES SRL | D21: VS/FG | I21: 48852 | N21: =SUM(E21:M21) -> 48852
A22: =+A21+1 -> 16 | B22: LE.F.P CONSULTORES SRL | D22: VS/FG | I22: 48852 | N22: =SUM(E22:M22) -> 48852
A23: =+A22+1 -> 17 | B23: Bio Nova, SRL | D23: VS/FG | I23: 14391 | N23: =SUM(E23:M23) -> 14391
A24: =+A23+1 -> 18 | B24: FARMACIA RUTH | D24: VS/FG | I24: 3450 | N24: =SUM(E24:M24) -> 3450
A25: =+A24+1 -> 19 | B25: Insocorp, S.R.L. | D25: VS/FG | I25: 162462.4 | N25: =SUM(E25:M25) -> 162462.4
A26: =+A25+1 -> 20 | B26: FARMACIA RUTH | D26: VS/FG | I26: 77150 | N26: =SUM(E26:M26) -> 77150
A27: =+A26+1 -> 21 | B27: Q&Q Medical RD, SRL | D27: VS/FG | I27: 80363.9 | N27: =SUM(E27:M27) -> 80363.9
A28: =+A27+1 -> 22 | B28: SLYKING GROUP, SRL | D28: VS/FG | I28: 240720 | N28: =SUM(E28:M28) -> 240720
A29: =+A28+1 -> 23 | B29: Ventas Diversas Farmaceuticas, SRL (VENDIFAR) | D29: VS/FG | I29: 190410 | N29: =SUM(E29:M29) -> 190410
... A41: =+A40+1 -> 35 | B41: Gestiones Sanitarias & Ambientales, SRL (GESA) | D41: VS/FG | I41: 39530 | N41: =SUM(E41:M41) -> 39530
A42: =+A41+1 -> 36 | B42: Insocorp, S.R.L. | D42: VS/FG | J42: 20060 | N42: =SUM(E42:M42) -> 20060
A43: =+A42+1 -> 37 | B43: SMART SUPPLY MEDICAL DOMINICANA, SRL | D43: VS/FG | K43: 54008.6 | N43: =SUM(E43:M43) -> 54008.6
A44: =+A43+1 -> 38 | B44: LEHAIM SUMINISTROS SRL | D44: VS/FG | K44: 271400 | N44: =SUM(E44:M44) -> 271400
A45: =+A44+1 -> 39 | B45: LEHAIM SUMINISTROS SRL | D45: VS/FG | K45: 227500 | N45: =SUM(E45:M45) -> 227500
A46: =+A45+1 -> 40 | B46: REGULATORY | D46: VS/FG | K46: 1692273.2 | N46: =SUM(E46:M46) -> 1692273.2
A47: =+A46+1 -> 41 | B47: Insocorp, S.R.L. | D47: VS/FG | K47: 137691.84 | N47: =SUM(E47:M47) -> 137691.84
A48: =+A47+1 -> 42 | B48: CEM CARIBBEAN EQUIPMENT MEDICAL | D48: VS/FG | K48: 846850 | N48: =SUM(E48:M48) -> 846850
A49: =+A48+1 -> 43 | B49: Gastables del Caribe (GADECA),SRL | D49: VS/FG | K49: 263328.8 | N49: =SUM(E49:M49) -> 263328.8
A50: =+A49+1 -> 44 | B50: Super Latop Browsing SRL | D50: VS/FG | L50: 413000 | N50: =SUM(E50:M50) -> 413000
A51: =+A50+1 -> 45 | B51: PATRIA RIVAS LABORATORIO CLINICO | D51: VS/FG | L51: 3500 | N51: =SUM(E51:M51) -> 3500
A52: =+A51+1 -> 46 | B52: Miguelina Vasquez Castillo | D52: VS/FG | L52: 229450 | N52: =SUM(E52:M52) -> 229450
A53: =+A52+1 -> 47 | B53: Productos Cano, SRL | D53: VS/FG | L53: 53025 | N53: =SUM(E53:M53) -> 53025
A54: =+A53+1 -> 48 | B54: Bio Nova, SRL | D54: VS/FG | L54: 107989.6 | N54: =SUM(E54:M54) -> 107989.6
A55: =+A54+1 -> 49 | B55: Agua Planeta Azul, SA | D55: VS/FG | L55: 29500 | N55: =SUM(E55:M55) -> 29500
A56: =+A55+1 -> 50 | B56: Abrias Novo Group SRL | D56: VS/FG | L56: 216333.29 | N56: =SUM(E56:M56) -> 216333.29
A57: =+A56+1 -> 51 | B57: Bello-Lab, SRL | D57: VS/FG | L57: 112460 | N57: =SUM(E57:M57) -> 112460
A58: =+A57+1 -> 52 | B58: AGROGLOBAL EXPORT E IMPORT SRL | D58: VS/FG | L58: 161090 | N58: =SUM(E58:M58) -> 161090
A59: =+A58+1 -> 53 | B59: REGULATORY | D59: VS/FG | L59: 943434.36 | N59: =SUM(E59:M59) -> 943434.36
A60: =+A59+1 -> 54 | B60: Tu Amigo, SRL | D60: VS/FG | L60: 664800 | N60: =SUM(E60:M60) -> 664800
A61: =+A60+1 -> 55 | B61: I.V. Biodesinfección, SRL | D61: VS/FG | L61: 188564 | N61: =SUM(E61:M61) -> 188564
A62: =+A61+1 -> 56 | B62: Productos Cano, SRL | D62: VS/FG | L62: 41825 | N62: =SUM(E62:M62) -> 41825
A63: =+A62+1 -> 57 | B63: Corporacion Medica A.G., SRL | D63: VS/FG | M63: 271400 | N63: =SUM(E63:M63) -> 271400
A64: =+A63+1 -> 58 | B64: ROPHARMA, SRL | D64: VS/FG | M64: 110250 | N64: =SUM(E64:M64) -> 110250
A65: =+A64+1 -> 59 | B65: ROPHARMA, SRL | D65: VS/FG | M65: 272500 | N65: =SUM(E65:M65) -> 272500
A66: =+A65+1 -> 60 | B66: PATRIA RIVAS LABORATORIO CLINICO | D66: VS/FG | M66: 44763 | N66: =SUM(E66:M66) -> 44763
A67: =+A66+1 -> 61 | B67: Bio Win, SRL | D67: VS/FG | M67: 2400 | N67: =SUM(E67:M67) -> 2400
A68: =+A67+1 -> 62 | B68: Abrias Novo Group SRL | D68: VS/FG | M68: 199851.39 | N68: =SUM(E68:M68) -> 199851.39
A69: =+A68+1 -> 63 | B69: Abrias Novo Group SRL | D69: VS/FG | M69: 71293.48 | N69: =SUM(E69:M69) -> 71293.48
A70: =+A69+1 -> 64 | B70: G & M Gelmat Comercial, SRL | D70: VS/FG | M70: 148379.1 | N70: =SUM(E70:M70) -> 148379.1
A71: =+A70+1 -> 65 | B71: OFICCLIN COMERCIAL, SRL | D71: VS/FG | M71: 252000 | N71: =SUM(E71:M71) -> 252000
A72: =+A71+1 -> 66 | B72: AGROGLOBAL EXPORT E IMPORT SRL | D72: VS/FG | M72: 91355 | N72: =SUM(E72:M72) -> 91355
A73: =+A72+1 -> 67 | B73: Farmaco Internacional, SRL | D73: VS/FG | M73: 577560 | N73: =SUM(E73:M73) -> 577560
A74: =+A73+1 -> 68 | B74: Bio Nuclear, SA | D74: VS/FG | M74: 49106.2 | N74: =SUM(E74:M74) -> 49106.2
... A104: =+A103+1 -> 98 | B104: Bio Win, SRL | D104: VS/FG | M104: 2400 | N104: =SUM(E104:M104) -> 2400
A105: TOTAL GENERAL | E105: =SUM(E7:E104) -> 0 | G105: =SUM(G7:G104) -> 0 | H105: =SUM(H7:H104) -> 1600554.9 | I105: =SUM(I7:I104) -> 2980028.8 | J105: =SUM(J7:J104) -> 20060 | K105: =SUM(K7:K104) -> 3493052.4 | L105: =SUM(L7:L104) -> 3164971.2 | M105: =SUM(M7:M104) -> 10174302 | N105: =SUM(N7:N104) -> 21432969

Sheet Hoja5
A1: Form. No.6 SRS
A3: Servicio Nacional de Salud
A4: Dirección de Fizcalización
A5: Consolidado de Ingresos y Gastos por Fuente de Financiamiento
A6: HOSPITAL MATERNO INFANTIL SAN LORENZO DE LOS MINA
A7: ABRIL 2025
C8: Ingresos Generales:
E9: 1.- Balance Inicial / Fuente:
E10: Anticipo Financiero | H10: Otros Aportes
E11: Transferencias Corrientes
E12: Venta de Servicios | G12: 4614.79
E13: 2.- Ingresos por Fuente / Cuenta
E14: Anticipo Financiero | H14: Otros Aportes | I14: =+'[12]INGR SEGUN ORIGEN'!E39 -> 214750
E15: Transferencias Corrientes | G15: =+'[12]INGR SEGUN ORIGEN'!E12 -> 1.007793e+08 | H15: Aportes Nomina SNS | I15: 0
E16: Venta de Servicios | G16: =+'[12]INGR SEGUN ORIGEN'!E32 -> 6892064.8
H17: TOTAL INGRESOS RDS | I17: =+G10+G11+G12+I10+G14+G15+G16+I14+I15 -> 1.0789073e+08
A21: 1 | F21: 2 | G21: 3 | I21: 4 | J21: 5
A22: Código Presupuestario | F22: Descripción Gasto por Cuenta | G22: Distribución del Gasto por Fuente de Financiamiento | I22: TOTAL | J22: %
A23: Tipo | B23: Objeto | C23: Cuenta | D23: Sub-Cuenta | E23: Auxiliar | G23: Fondo 100 | H23: Venta de Servicios/ Otros Aportes
A25: 2 | F25: Gastos | G25: =+G26+G87+G212+G330+G336+G463 -> 91800340 | H25: =+H26+H87+H212+H330+H336+H463 -> 4881550.3 | I25: =SUM(G25:H25) -> 96681890 | J25: =+J26+J87+J212+J330+J336+J463 -> 1
A26: 2 | B26: 1 | F26: Servicios Personales | G26: =+G27+G51+G64+G71+G78 -> 66556156 | H26: =+H27+H51+H64+H71+H78 -> 0 | I26: =SUM(G26:H26) -> 66556156 | J26: =I26/$I$25 -> 0.68840355
A27: 2 | B27: 1 | C27: 1 | F27: Remuneraciones | G27: =+G28+G35+G42+G44+G46 -> 54771097 | H27: =+H28+H35+H42+H44+H46 -> 0 | I27: =SUM(G27:H27) -> 54771097 | J27: =I27/$I$25 -> 0.56650834
A28: 2 | B28: 1 | C28: 1 | D28: 1 | F28: Remuneraciones al personal fijo | G28: =SUM(G29:G34) -> 53482455 | H28: =SUM(H29:H34) -> 0 | I28: =SUM(G28:H28) -> 53482455 | J28: =I28/$I$25 -> 0.55317966
A29: 2 | B29: 1 | C29: 1 | D29: 1 | E29: 01 | F29: Sueldos a empleados fijos | G29: ='[12]CUENTA T FONDO 100'!A127 -> 53482455 | H29: ='[12]CUENTA T VS'!A89 -> 0 | I29: =SUM(G29:H29) -> 53482455 | J29: =I29/$I$25 -> 0.55317966
A30: 2 | B30: 1 | C30: 1 | D30: 1 | E30: 02 | F30: Sueldos a médicos | G30: ='[12]CUENTA T FONDO 100'!B127 -> 0 | H30: ='[12]CUENTA T VS'!B89 -> 0 | I30: =SUM(G30:H30) -> 0 | J30: =I30/$I$25 -> 0
A31: 2 | B31: 1 | C31: 1 | D31: 1 | E31: 03 | F31: Ascensos a militares | G31: ='[12]CUENTA T FONDO 100'!C127 -> 0 | H31: ='[12]CUENTA T VS'!C89 -> 0 | I31: =SUM(G31:H31) -> 0 | J31: =I31/$I$25 -> 0
A32: 2 | B32: 1 | C32: 1 | D32: 1 | E32: 04 | F32: Nuevas plazas maestros | G32: ='[12]CUENTA T FONDO 100'!D127 -> 0 | H32: ='[12]CUENTA T VS'!D89 -> 0 | I32: =SUM(G32:H32) -> 0 | J32: =I32/$I$25 -> 0
A33: 2 | B33: 1 | C33: 1 | D33: 1 | E33: 05 | F33: Incentivos y escalafón | G33: ='[12]CUENTA T FONDO 100'!E127 -> 0 | H33: ='[12]CUENTA T VS'!E89 -> 0 | I33: =SUM(G33:H33) -> 0 | J33: =I33/$I$25 -> 0
A34: 2 | B34: 1 | C34: 1 | D34: 1 | E34: 06 | F34: Nuevas plazas a médicos | G34: ='[12]CUENTA T FONDO 100'!F127 -> 0 | H34: ='[12]CUENTA T VS'!F89 -> 0 | I34: =SUM(G34:H34) -> 0 | J34: =I34/$I$25 -> 0
A35: 2 | B35: 1 | C35: 1 | D35: 2 | F35: Remuneraciones al personal con carácter transitorio | G35: =SUM(G36:G41) -> 1107531 | H35: =SUM(H36:H41) -> 0 | I35: =SUM(G35:H35) -> 1107531
A36: 2 | B36: 1 | C36: 1 | D36: 2 | E36: 03 | F36: Suplencias | G36: ='[12]CUENTA T FONDO 100'!G127 -> 0 | H36: ='[12]CUENTA T VS'!G89 -> 0 | I36: =SUM(G36:H36) -> 0 | J36: =I36/$I$25 -> 0
A37: 2 | B37: 1 | C37: 1 | D37: 2 | E37: 05 | F37: Sueldo al personal nominal en período probatorio | G37: ='[12]CUENTA T FONDO 100'!H127 -> 0 | H37: ='[12]CUENTA T VS'!H89 -> 0 | I37: =SUM(G37:H37) -> 0 | J37: =I37/$I$25 -> 0
A38: 2 | B38: 1 | C38: 1 | D38: 2 | E38: 06 | F38: Jornales | G38: ='[12]CUENTA T FONDO 100'!I127 -> 0 | H38: ='[12]CUENTA T VS'!I89 -> 0 | I38: =SUM(G38:H38) -> 0 | J38: =I38/$I$25 -> 0
A39: 2 | B39: 1 | C39: 1 | D39: 2 | E39: 08 | F39: Empleados temporales | G39: ='[12]CUENTA T FONDO 100'!J127 -> 1107531 | H39: ='[12]CUENTA T VS'!J89 -> 0 | I39: =SUM(G39:H39) -> 1107531 | J39: =I39/$I$25 -> 0.011455414
A40: 2 | B40: 1 | C40: 1 | D40: 2 | E40: 09 | F40: Personal de carácter eventual | G40: ='[12]CUENTA T FONDO 100'!K127 -> 0 | H40: ='[12]CUENTA T VS'!K89 -> 0 | I40: =SUM(G40:H40) -> 0 | J40: =I40/$I$25 -> 0
A41: 2 | B41: 1 | C41: 1 | D41: 2 | E41: 11 | F41: Interinato | G41: ='[12]CUENTA T FONDO 100'!L127 -> 0 | H41: ='[12]CUENTA T VS'!L89 -> 0 | I41: =SUM(G41:H41) -> 0 | J41: =I41/$I$25 -> 0
A42: 2 | B42: 1 | C42: 1 | D42: 3 | F42: Sueldos al personal fijo en trámite de pensiones | G42: =SUM(G43) -> 0 | H42: =SUM(H43) -> 0 | I42: =SUM(G42:H42) -> 0
A43: 2 | B43: 1 | C43: 1 | D43: 3 | E43: 01 | F43: Sueldos al personal fijo en trámite de pensiones | G43: ='[12]CUENTA T FONDO 100'!M127 -> 0 | H43: ='[12]CUENTA T VS'!M89 -> 0 | I43: =SUM(G43:H43) -> 0 | J43: =I43/$I$25 -> 0
A44: 2 | B44: 1 | C44: 1 | D44: 4 | F44: Sueldo anual no. 13 | G44: =SUM(G45) -> 0 | H44: =SUM(H45) -> 0 | I44: =SUM(G44:H44) -> 0
A45: 2 | B45: 1 | C45: 1 | D45: 4 | E45: 01 | F45: Sueldo anual no. 13 | G45: ='[12]CUENTA T FONDO 100'!N127 -> 0 | H45: ='[12]CUENTA T VS'!N89 -> 0 | I45: =SUM(G45:H45) -> 0 | J45: =I45/$I$25 -> 0
A46: 2 | B46: 1 | C46: 1 | D46: 5 | F46: Prestaciones económinas | G46: =SUM(G47:G50) -> 181111.08 | H46: =SUM(H47:H50) -> 0 | I46: =SUM(G46:H46) -> 181111.08
A47: 2 | B47: 1 | C47: 1 | D47: 5 | E47: 01 | F47: Prestaciones económinas | G47: ='[12]CUENTA T FONDO 100'!O127 -> 0 | H47: ='[12]CUENTA T VS'!O89 -> 0 | I47: =SUM(G47:H47) -> 0 | J47: =I47/$I$25 -> 0
A48: 2 | B48: 1 | C48: 1 | D48: 5 | E48: 02 | F48: Pago de porcentaje por desvinculación de cargo | G48: ='[12]CUENTA T FONDO 100'!P127 -> 0 | H48: ='[12]CUENTA T VS'!P89 -> 0 | I48: =SUM(G48:H48) -> 0 | J48: =I48/$I$25 -> 0
A49: 2 | B49: 1 | C49: 1 | D49: 5 | E49: 03 | F49: Prestación laboral por desvinculación | G49: ='[12]CUENTA T FONDO 100'!Q127 -> 92400 | H49: ='[12]CUENTA T VS'!Q89 -> 0 | I49: =SUM(G49:H49) -> 92400 | J49: =I49/$I$25 -> 0.00095571156
A50: 2 | B50: 1 | C50: 1 | D50: 5 | E50: 04 | F50: Proporción de vacaciones no disfrutadas | G50: ='[12]CUENTA T FONDO 100'!R127 -> 88711.08 | H50: ='[12]CUENTA T VS'!R89 -> 0 | I50: =SUM(G50:H50) -> 88711.08 | J50: =I50/$I$25 -> 0.00091755633
A51: 2 | B51: 1 | C51: 2 | F51: Sobresueldos | G51: =+G52+G54 -> 3384964.5 | H51: =+H52+H54 -> 0 | I51: =SUM(G51:H51) -> 3384964.5
A52: 2 | B52: 1 | C52: 2 | D52: 1 | F52: Primas por antigüedad | G52: =SUM(G53) -> 2739824.5 | H52: =SUM(H53) -> 0 | I52: =SUM(G52:H52) -> 2739824.5
A53: 2 | B53: 1 | C53: 2 | D53: 1 | E53: 01 | F53: Primas por antigüedad | G53: ='[12]CUENTA T FONDO 100'!S127 -> 2739824.5 | H53: ='[12]CUENTA T VS'!S89 -> 0 | I53: =SUM(G53:H53) -> 2739824.5 | J53: =I53/$I$25 -> 0.02833855
A54: 2 | B54: 1 | C54: 2 | D54: 2 | F54: Compensación | G54: =SUM(G55:G63) -> 645139.96 | H54: =SUM(H55:H63) -> 0 | I54: =SUM(G54:H54) -> 645139.96
A55: 2 | B55: 1 | C55: 2 | D55: 2 | E55: 01 | F55: Compensación por gastos de alimentación | G55: ='[12]CUENTA T FONDO 100'!T127 -> 0 | H55: ='[12]CUENTA T VS'!T89 -> 0 | I55: =SUM(G55:H55) -> 0 | J55: =I55/$I$25 -> 0
A56: 2 | B56: 1 | C56: 2 | D56: 2 | E56: 03 | F56: Pago de horas extraordinarias | G56: ='[12]CUENTA T FONDO 100'!U127 -> 0 | H56: ='[12]CUENTA T VS'!U89 -> 0 | I56: =SUM(G56:H56) -> 0 | J56: =I56/$I$25 -> 0
A57: 2 | B57: 1 | C57: 2 | D57: 2 | E57: 04 | F57: Prima de transporte | G57: ='[12]CUENTA T FONDO 100'!V127 -> 0 | H57: ='[12]CUENTA T VS'!V89 -> 0 | I57: =SUM(G57:H57) -> 0 | J57: =I57/$I$25 -> 0
A58: 2 | B58: 1 | C58: 2 | D58: 2 | E58: 05 | F58: Compensación servicios de Seguridad | G58: ='[12]CUENTA T FONDO 100'!W127 -> 45000 | H58: ='[12]CUENTA T VS'!W89 -> 0 | I58: =SUM(G58:H58) -> 45000 | J58: =I58/$I$25 -> 0.00046544394
A59: 2 | B59: 1 | C59: 2 | D59: 2 | E59: 06 | F59: Incentivo por Rendimieto Individual | G59: ='[12]CUENTA T FONDO 100'!X127 -> 0 | H59: ='[12]CUENTA T VS'!X89 -> 0 | I59: =SUM(G59:H59) -> 0 | J59: =I59/$I$25 -> 0
A60: 2 | B60: 1 | C60: 2 | D60: 2 | E60: 07 | F60: Compensación por distancia | G60: ='[12]CUENTA T FONDO 100'!Y127 -> 0 | H60: ='[12]CUENTA T VS'!Y89 -> 0 | I60: =SUM(G60:H60) -> 0 | J60: =I60/$I$25 -> 0
A61: 2 | B61: 1 | C61: 2 | D61: 2 | E61: 08 | F61: Compensaciones especiales | G61: ='[12]CUENTA T FONDO 100'!Z127 -> 339600 | H61: ='[12]CUENTA T VS'!Z89 -> 0 | I61: =SUM(G61:H61) -> 339600 | J61: =I61/$I$25 -> 0.0035125503
A62: 2 | B62: 1 | C62: 2 | D62: 2 | E62: 09 | F62: Bono por desempeño a servidores de carrera | G62: ='[12]CUENTA T FONDO 100'!AA127 -> 0 | H62: ='[12]CUENTA T VS'!AA89 -> 0 | I62: =SUM(G62:H62) -> 0 | J62: =I62/$I$25 -> 0
A63: 2 | B63: 1 | C63: 2 | D63: 2 | E63: 10 | F63: Compensacion por cumplimiento de indicadores | G63: ='[12]CUENTA T FONDO 100'!AB127 -> 260539.96 | H63: ='[12]CUENTA T VS'!AB89 -> 0 | I63: =SUM(G63:H63) -> 260539.96 | J63: =I63/$I$25 -> 0.0026948166
A64: 2 | B64: 1 | C64: 3 | F64: Dietas y Gastos de Representación | G64: =+G65+G68 -> 0 | H64: =+H65+H68 -> 0 | I64: =SUM(G64:H64) -> 0
A65: 2 | B65: 1 | C65: 3 | D65: 1 | F65: Dietas | G65: =SUM(G66:G67) -> 0 | H65: =SUM(H66:H67) -> 0 | I65: =SUM(G65:H65) -> 0
A66: 2 | B66: 1 | C66: 3 | D66: 1 | E66: 01 | F66: Dietas en el país | G66: ='[12]CUENTA T FONDO 100'!AC127 -> 0 | H66: ='[12]CUENTA T VS'!AC89 -> 0 | I66: =SUM(G66:H66) -> 0 | J66: =I66/$I$25 -> 0
A67: 2 | B67: 1 | C67: 3 | D67: 1 | E67: 02 | F67: Dietas en el exterior | G67: ='[12]CUENTA T FONDO 100'!AD127 -> 0 | H67: ='[12]CUENTA T VS'!AD89 -> 0 | I67: =SUM(G67:H67) -> 0 | J67: =I67/$I$25 -> 0
A68: 2 | B68: 1 | C68: 3 | D68: 2 | F68: Gastos de representación | G68: =SUM(G69:G70) -> 0 | H68: =SUM(H69:H70) -> 0 | I68: =SUM(G68:H68) -> 0
A69: 2 | B69: 1 | C69: 3 | D69: 2 | E69: 01 | F69: Gastos de representación en el país | G69: ='[12]CUENTA T FONDO 100'!AE127 -> 0 | H69: ='[12]CUENTA T VS'!AE89 -> 0 | I69: =SUM(G69:H69) -> 0 | J69: =I69/$I$25 -> 0
A70: 2 | B70: 1 | C70: 3 | D70: 2 | E70: 02 | F70: Gastos de representación en el exterior | G70: ='[12]CUENTA T FONDO 100'!AF127 -> 0 | H70: ='[12]CUENTA T VS'!AF89 -> 0 | I70: =SUM(G70:H70) -> 0 | J70: =I70/$I$25 -> 0
A71: 2 | B71: 1 | C71: 4 | F71: Gratificaciones y Bonificaciones | G71: =+G72+G74 -> 0 | H71: =+H72+H74 -> 0 | I71: =SUM(G71:H71) -> 0
A72: 2 | B72: 1 | C72: 4 | D72: 1 | F72: Bonificaciones | G72: =SUM(G73) -> 0 | H72: =SUM(H73) -> 0 | I72: =SUM(G72:H72) -> 0
A73: 2 | B73: 1 | C73: 4 | D73: 1 | E73: 01 | F73: Bonificaciones | G73: ='[12]CUENTA T FONDO 100'!AG127 -> 0 | H73: ='[12]CUENTA T VS'!AG89 -> 0 | I73: =SUM(G73:H73) -> 0 | J73: =I73/$I$25 -> 0
A74: 2 | B74: 1 | C74: 4 | D74: 2 | F74: Otras Gratificaciones y Bonificaciones | G74: =SUM(G75:G77) -> 0 | H74: =SUM(H75:H77) -> 0 | I74: =SUM(G74:H74) -> 0
A75: 2 | B75: 1 | C75: 4 | D75: 2 | E75: 01 | F75: Bono escolar | G75: ='[12]CUENTA T FONDO 100'!AH127 -> 0 | H75: ='[12]CUENTA T VS'!AH89 -> 0 | I75: =SUM(G75:H75) -> 0 | J75: =I75/$I$25 -> 0
A76: 2 | B76: 1 | C76: 4 | D76: 2 | E76: 02 | F76: Gratificaciones por pasantías | G76: ='[12]CUENTA T FONDO 100'!AI127 -> 0 | H76: ='[12]CUENTA T VS'!AI89 -> 0 | I76: =SUM(G76:H76) -> 0 | J76: =I76/$I$25 -> 0
A77: 2 | B77: 1 | C77: 4 | D77: 2 | E77: 03 | F77: Gratificaciones por aniversario de institución | G77: ='[12]CUENTA T FONDO 100'!AJ127 -> 0 | H77: ='[12]CUENTA T VS'!AJ89 -> 0 | I77: =SUM(G77:H77) -> 0 | J77: =I77/$I$25 -> 0
A78: 2 | B78: 1 | C78: 5 | F78: Contribuciones a la Seguridad Social y Riesgo Laboral | G78: =+G79+G81+G83+G85 -> 8400093.9 | H78: =+H79+H81+H83+H85 -> 0 | I78: =SUM(G78:H78) -> 8400093.9
A79: 2 | B79: 1 | C79: 5 | D79: 1 | F79: Contribuciones al seguro de salud | G79: =SUM(G80) -> 3870432.3 | H79: =SUM(H80) -> 0 | I79: =SUM(G79:H79) -> 3870432.3
A80: 2 | B80: 1 | C80: 5 | D80: 1 | E80: 01 | F80: Contribuciones al seguro de salud | G80: ='[12]CUENTA T FONDO 100'!AK127 -> 3870432.3 | H80: ='[12]CUENTA T VS'!AK89 -> 0 | I80: =SUM(G80:H80) -> 3870432.3 | J80: =I80/$I$25 -> 0.040032651
A81: 2 | B81: 1 | C81: 5 | D81: 2 | F81: Contribuciones al seguro de pensiones | G81: =SUM(G82) -> 3875889.5 | H81: =SUM(H82) -> 0 | I81: =SUM(G81:H81) -> 3875889.5
A82: 2 | B82: 1 | C82: 5 | D82: 2 | E82: 01 | F82: Contribuciones al seguro de pensiones | G82: ='[12]CUENTA T FONDO 100'!AL127 -> 3875889.5 | H82: ='[12]CUENTA T VS'!AL89 -> 0 | I82: =SUM(G82:H82) -> 3875889.5 | J82: =I82/$I$25 -> 0.040089095
A83: 2 | B83: 1 | C83: 5 | D83: 3 | F83: Contribuciones al seguro de riesgo laboral | G83: =SUM(G84) -> 653772.07 | H83: =SUM(H84) -> 0 | I83: =SUM(G83:H83) -> 653772.07
A84: 2 | B84: 1 | C84: 5 | D84: 3 | E84: 01 | F84: Contribuciones al seguro de riesgo laboral | G84: ='[12]CUENTA T FONDO 100'!AM127 -> 653772.07 | H84: ='[12]CUENTA T VS'!AM89 -> 0 | I84: =SUM(G84:H84) -> 653772.07 | J84: =I84/$I$25 -> 0.0067620944
A85: 2 | B85: 1 | C85: 5 | D85: 4 | F85: Contribuciones al plan de retiro complementario | G85: =SUM(G86) -> 0 | H85: =SUM(H86) -> 0 | I85: =SUM(G85:H85) -> 0
A86: 2 | B86: 1 | C86: 5 | D86: 4 | E86: 01 | F86: Contribuciones al plan de retiro complementario | G86: ='[12]CUENTA T FONDO 100'!AN127 -> 0 | H86: ='[12]CUENTA T VS'!AN89 -> 0 | I86: =SUM(G86:H86) -> 0 | J86: =I86/$I$25 -> 0
A87: 2 | B87: 2 | F87: Servicios No Personales | G87: =G88+G106+G111+G116+G125+G148+G157+G179+G208 -> 210535 | H87: =H88+H106+H111+H116+H125+H148+H157+H179+H208 -> 1256712.1 | I87: =SUM(G87:H87) -> 1467247.1 | J87: =I87/$I$25 -> 0.015176028
A88: 2 | B88: 2 | C88: 1 | F88: Servicios Básicos | G88: =+G89+G91+G93+G95+G97+G99+G102+G104 -> 60535 | H88: =+H89+H91+H93+H95+H97+H99+H102+H104 -> 285608.3 | I88: =SUM(G88:H88) -> 346143.3
A89: 2 | B89: 2 | C89: 1 | D89: 1 | F89: Radiocomunicación | G89: =SUM(G90) -> 0 | H89: =SUM(H90) -> 0 | I89: =SUM(G89:H89) -> 0
A90: 2 | B90: 2 | C90: 1 | D90: 1 | E90: 01 | F90: Radiocomunicación | G90: ='[12]CUENTA T FONDO 100'!AO127 -> 0 | H90: ='[12]CUENTA T VS'!AO89 -> 0 | I90: =SUM(G90:H90) -> 0 | J90: =I90/$I$25 -> 0
A91: 2 | B91: 2 | C91: 1 | D91: 2 | F91: Servicios telefónico de larga distancia | G91: =SUM(G92) -> 0 | H91: =SUM(H92) -> 0 | I91: =SUM(G91:H91) -> 0
A92: 2 | B92: 2 | C92: 1 | D92: 2 | E92: 01 | F92: Servicios telefónico de larga distancia | G92: ='[12]CUENTA T FONDO 100'!AP127 -> 0 | H92: ='[12]CUENTA T VS'!AP89 -> 0 | I92: =SUM(G92:H92) -> 0 | J92: =I92/$I$25 -> 0
A93: 2 | B93: 2 | C93: 1 | D93: 3 | F93: Teléfono local | G93: =SUM(G94) -> 0 | H93: =SUM(H94) -> 104569.42 | I93: =SUM(G93:H93) -> 104569.42
A94: 2 | B94: 2 | C94: 1 | D94: 3 | E94: 01 | F94: Teléfono local | G94: ='[12]CUENTA T FONDO 100'!AQ127 -> 0 | H94: ='[12]CUENTA T VS'!AQ89 -> 104569.42 | I94: =SUM(G94:H94) -> 104569.42 | J94: =I94/$I$25 -> 0.0010815823
A95: 2 | B95: 2 | C95: 1 | D95: 4 | F95: Telefax y correos | G95: =SUM(G96) -> 0 | H95: =SUM(H96) -> 0 | I95: =SUM(G95:H95) -> 0
A96: 2 | B96: 2 | C96: 1 | D96: 4 | E96: 01 | F96: Telefax y correos | G96: ='[12]CUENTA T FONDO 100'!AR127 -> 0 | H96: ='[12]CUENTA T VS'!AR89 -> 0 | I96: =SUM(G96:H96) -> 0 | J96: =I96/$I$25 -> 0
A97: 2 | B97: 2 | C97: 1 | D97: 5 | F97: Servicio de Internet y televisión por cable | G97: =SUM(G98) -> 0 | H97: =SUM(H98) -> 106038.88 | I97: =SUM(G97:H97) -> 106038.88
A98: 2 | B98: 2 | C98: 1 | D98: 5 | E98: 01 | F98: Servicio de Internet y televisión por cable | G98: ='[12]CUENTA T FONDO 100'!AS127 -> 0 | H98: ='[12]CUENTA T VS'!AS89 -> 106038.88 | I98: =SUM(G98:H98) -> 106038.88 | J98: =I98/$I$25 -> 0.0010967812
A99: 2 | B99: 2 | C99: 1 | D99: 6 | F99: Electricidad | G99: =SUM(G100:G101) -> 0 | H99: =SUM(H100:H101) -> 0 | I99: =SUM(G99:H99) -> 0
A100: 2 | B100: 2 | C100: 1 | D100: 6 | E100: 01 | F100: Energía eléctrica | G100: ='[12]CUENTA T FONDO 100'!AT127 -> 0 | H100: ='[12]CUENTA T VS'!AT89 -> 0 | I100: =SUM(G100:H100) -> 0 | J100: =I100/$I$25 -> 0
A101: 2 | B101: 2 | C101: 1 | D101: 6 | E101: 02 | F101: Electricidad no cortable | G101: ='[12]CUENTA T FONDO 100'!AU127 -> 0 | H101: ='[12]CUENTA T VS'!AU89 -> 0 | I101: =SUM(G101:H101) -> 0 | J101: =I101/$I$25 -> 0
A102: 2 | B102: 2 | C102: 1 | D102: 7 | F102: Agua | G102: =SUM(G103) -> 60535 | H102: =SUM(H103) -> 0 | I102: =SUM(G102:H102) -> 60535
A103: 2 | B103: 2 | C103: 1 | D103: 7 | E103: 01 | F103: Agua | G103: ='[12]CUENTA T FONDO 100'!AV127 -> 60535 | H103: ='[12]CUENTA T VS'!AV89 -> 0 | I103: =SUM(G103:H103) -> 60535 | J103: =I103/$I$25 -> 0.00062612554
A104: 2 | B104: 2 | C104: 1 | D104: 8 | F104: Recolección de residuos sólidos | G104: =SUM(G105) -> 0 | H104: =SUM(H105) -> 75000 | I104: =SUM(G104:H104) -> 75000
A105: 2 | B105: 2 | C105: 1 | D105: 8 | E105: 01 | F105: Recolección de residuos sólidos | G105: ='[12]CUENTA T FONDO 100'!AW127 -> 0 | H105: ='[12]CUENTA T VS'!AW89 -> 75000 | I105: =SUM(G105:H105) -> 75000 | J105: =I105/$I$25 -> 0.0007757399
...

Sheet ejecucion
A1: Form. No.6 SRS
A3: Servicio Nacional de Salud
A4: Dirección de Fizcalización
A5: Consolidado de Ingresos y Gastos por Fuente de Financiamiento
A6: HOSPITAL MATERNO INFANTIL SAN LORENZO DE LOS MINA
A7: TRIMESTRE ENERO-MARZO 2025
C8: Ingresos Generales:
E9: 1.- Balance Inicial / Fuente:
E10: Anticipo Financiero | G10: 0 | H10: Otros Aportes | M10: Contraseña: 0001
E11: Transferencias Corrientes | G11: 0
E12: Venta de Servicios | G12: =+'[2]ENERO 2025'!G12 -> 2244994.1
E13: 2.- Ingresos por Fuente / Cuenta
E14: Anticipo Financiero | H14: Otros Aportes | J14: =+'[2]MARZO 2025'!I14+'[2]FEBRERO 2025'!I14+'[2]ENERO 2025'!J14 -> 15987098 | M14: OBJETAL | N14: FR | O14: VS
E15: Transferencias Corrientes | G15: =+'[2]MARZO 2025'!G15+'[2]FEBRERO 2025'!G15 -> 2.0063359e+08 | H15: Aportes Nomina SNS | J15: =+'[2]MARZO 2025'!I15+'[2]FEBRERO 2025'!I15+'[2]ENERO 2025'!J15 -> 84553322 | M15: 2.1 | N15: =G26 -> 4.2830003e+08 | O15: =H26 -> 5231553.6
E16: Venta de Servicios | G16: =+'[2]MARZO 2025'!G16+'[2]FEBRERO 2025'!G16+'[2]ENERO 2025'!G16 -> 23406786 | M16: 2.2 | N16: =G87 -> 9962137 | O16: =H87 -> 8306683.9
H17: TOTAL INGRESOS RDS | J17: =+G10+G11+G12+J10+G14+G15+G16+J14+J15 -> 3.2682579e+08 | M17: 2.3 | N17: ='[3]CONS. FUENTES FINAN'!G212 -> 4970601.2 | O17: ='[3]CONS. FUENTES FINAN'!H212 -> 3062630.7
M18: 2.4 | N18: =G330 -> 0 | O18: =H330 -> 405851.31
M19: 2.6 | N19: =G336 -> 17857867 | O19: =H336 -> 5076044.2
M20: 2.7 | N20: ='[3]CONS. FUENTES FINAN'!G463 -> 0 | O20: ='[3]CONS. FUENTES FINAN'!H463 -> 0
A21: 1 | F21: 2 | G21: 3 | J21: 4 | K21: 5
A22: Código Presupuestario | F22: Descripción Gasto por Cuenta | G22: Distribución del Gasto por Fuente de Financiamiento | J22: TOTAL | K22: %
A23: Tipo | B23: Objeto | C23: Cuenta | D23: Sub-Cuenta | E23: Auxiliar | G23: Fondo 100 | H23: Venta de Servicios/ Otros Aportes | I23: Aportes Nomina SNS
A25: 2 | F25: Gastos | G25: =+G26+G87+G212+G330+G336+G463 -> 5.0227332e+08 | H25: =+H26+H87+H212+H330+H336+H463 -> 26312680 | I25: =+I26+I87+I212+I330+I336+I463 -> 0 | J25: =SUM(G25:I25) -> 5.28586e+08 | K25: =+K26+K87+K212+K330+K336+K463 -> 1
A26: 2 | B26: 1 | F26: Servicios Personales | G26: =+G27+G51+G64+G71+G78 -> 4.2830003e+08 | H26: =+H27+H51+H64+H71+H78 -> 5231553.6 | I26: =+I27+I51+I64+I71+I78 -> 0 | J26: =SUM(G26:I26) -> 4.3353158e+08 | K26: =J26/$J$25 -> 0.82017228
A27: 2 | B27: 1 | C27: 1 | F27: Remuneraciones | G27: =+G28+G35+G42+G44+G46 -> 3.933449e+08 | H27: =+H28+H35+H42+H44+H46 -> 0 | I27: =+I28+I35+I42+I44+I46 -> 0 | J27: =SUM(G27:I27) -> 3.933449e+08 | K27: =J27/$J$25 -> 0.74414551
A28: 2 | B28: 1 | C28: 1 | D28: 1 | F28: Remuneraciones al personal fijo | G28: =SUM(G29:G34) -> 3.8772665e+08 | H28: =SUM(H29:H34) -> 0 | I28: =SUM(I29:I34) -> 0 | J28: =SUM(G28:I28) -> 3.8772665e+08 | K28: =J28/$J$25 -> 0.7335167
A29: 2 | B29: 1 | C29: 1 | D29: 1 | E29: 01 | F29: Sueldos a empleados fijos | G29: =+'[2]MARZO 2025'!G29+'[2]FEBRERO 2025'!G29+'[2]ENERO 2025'!G29+Hoja5!G26 -> 2.2599065e+08 | H29: =+'[2]MARZO 2025'!H29+'[2]FEBRERO 2025'!H29+'[2]ENERO 2025'!H29+Hoja5!H26 -> 0 | I29: 0 | J29: =SUM(G29:I29) -> 2.2599065e+08 | K29: =J29/$J$25 -> 0.42753809
A30: 2 | B30: 1 | C30: 1 | D30: 1 | E30: 02 | F30: Sueldos a médicos | G30: =+'[2]MARZO 2025'!G30+'[2]FEBRERO 2025'!G30+'[2]ENERO 2025'!G30+Hoja5!G27 -> 54771097 | H30: =+'[2]MARZO 2025'!H30+'[2]FEBRERO 2025'!H30+'[2]ENERO 2025'!H30+Hoja5!H27 -> 0 | I30: 0 | J30: =SUM(G30:I30) -> 54771097 | K30: =J30/$J$25 -> 0.10361814
A31: 2 | B31: 1 | C31: 1 | D31: 1 | E31: 03 | F31: Ascensos a militares | G31: =+'[2]MARZO 2025'!G31+'[2]FEBRERO 2025'!G31+'[2]ENERO 2025'!G31+Hoja5!G28 -> 53482455 | H31: =+'[2]MARZO 2025'!H31+'[2]FEBRERO 2025'!H31+'[2]ENERO 2025'!H31+Hoja5!H28 -> 0 | I31: 0 | J31: =SUM(G31:I31) -> 53482455 | K31: =J31/$J$25 -> 0.10118023
A32: 2 | B32: 1 | C32: 1 | D32: 1 | E32: 04 | F32: Nuevas plazas maestros | G32: =+'[2]MARZO 2025'!G32+'[2]FEBRERO 2025'!G32+'[2]ENERO 2025'!G32+Hoja5!G29 -> 53482455 | H32: =+'[2]MARZO 2025'!H32+'[2]FEBRERO 2025'!H32+'[2]ENERO 2025'!H32+Hoja5!H29 -> 0 | I32: 0 | J32: =SUM(G32:I32) -> 53482455 | K32: =J32/$J$25 -> 0.10118023
A33: 2 | B33: 1 | C33: 1 | D33: 1 | E33: 05 | F33: Incentivos y escalafón | G33: =+'[2]MARZO 2025'!G33+'[2]FEBRERO 2025'!G33+'[2]ENERO 2025'!G33+Hoja5!G30 -> 0 | H33: =+'[2]MARZO 2025'!H33+'[2]FEBRERO 2025'!H33+'[2]ENERO 2025'!H33+Hoja5!H30 -> 0 | I33: 0 | J33: =SUM(G33:I33) -> 0 | K33: =J33/$J$25 -> 0
A34: 2 | B34: 1 | C34: 1 | D34: 1 | E34: 06 | F34: Nuevas plazas a médicos | G34: =+'[2]MARZO 2025'!G34+'[2]FEBRERO 2025'!G34+'[2]ENERO 2025'!G34+Hoja5!G31 -> 0 | H34: =+'[2]MARZO 2025'!H34+'[2]FEBRERO 2025'!H34+'[2]ENERO 2025'!H34+Hoja5!H31 -> 0 | I34: 0 | J34: =SUM(G34:I34) -> 0 | K34: =J34/$J$25 -> 0
A35: 2 | B35: 1 | C35: 1 | D35: 2 | F35: Remuneraciones al personal con carácter transitorio | G35: =+'[2]MARZO 2025'!G35+'[2]FEBRERO 2025'!G35+'[2]ENERO 2025'!G35+Hoja5!G32 -> 3177593.1 | H35: =+'[2]MARZO 2025'!H35+'[2]FEBRERO 2025'!H35+'[2]ENERO 2025'!H35+Hoja5!H32 -> 0 | I35: 0 | J35: =SUM(G35:I35) -> 3177593.1
A36: 2 | B36: 1 | C36: 1 | D36: 2 | E36: 03 | F36: Suplencias | G36: =+'[2]MARZO 2025'!G36+'[2]FEBRERO 2025'!G36+'[2]ENERO 2025'!G36+Hoja5!G33 -> 0 | H36: =+'[2]MARZO 2025'!H36+'[2]FEBRERO 2025'!H36+'[2]ENERO 2025'!H36+Hoja5!H33 -> 0 | I36: 0 | J36: =SUM(G36:I36) -> 0 | K36: =J36/$J$25 -> 0
A37: 2 | B37: 1 | C37: 1 | D37: 2 | E37: 05 | F37: Sueldo al personal nominal en período probatorio | G37: =+'[2]MARZO 2025'!G37+'[2]FEBRERO 2025'!G37+'[2]ENERO 2025'!G37+Hoja5!G34 -> 0 | H37: =+'[2]MARZO 2025'!H37+'[2]FEBRERO 2025'!H37+'[2]ENERO 2025'!H37+Hoja5!H34 -> 0 | I37: 0 | J37: =SUM(G37:I37) -> 0 | K37: =J37/$J$25 -> 0
A38: 2 | B38: 1 | C38: 1 | D38: 2 | E38: 06 | F38: Jornales | G38: =+'[2]MARZO 2025'!G38+'[2]FEBRERO 2025'!G38+'[2]ENERO 2025'!G38+Hoja5!G35 -> 1107531 | H38: =+'[2]MARZO 2025'!H38+'[2]FEBRERO 2025'!H38+'[2]ENERO 2025'!H38+Hoja5!H35 -> 0 | I38: 0 | J38: =SUM(G38:I38) -> 1107531 | K38: =J38/$J$25 -> 0.0020952712
A39: 2 | B39: 1 | C39: 1 | D39: 2 | E39: 08 | F39: Empleados temporales | G39: =+'[2]MARZO 2025'!G39+'[2]FEBRERO 2025'!G39+'[2]ENERO 2025'!G39+Hoja5!G36 -> 3177593.1 | H39: =+'[2]MARZO 2025'!H39+'[2]FEBRERO 2025'!H39+'[2]ENERO 2025'!H39+Hoja5!H36 -> 0 | I39: 0 | J39: =SUM(G39:I39) -> 3177593.1 | K39: =J39/$J$25 -> 0.0060114969
A40: 2 | B40: 1 | C40: 1 | D40: 2 | E40: 09 | F40: Personal de carácter eventual | G40: =+'[2]MARZO 2025'!G40+'[2]FEBRERO 2025'!G40+'[2]ENERO 2025'!G40+Hoja5!G37 -> 0 | H40: =+'[2]MARZO 2025'!H40+'[2]FEBRERO 2025'!H40+'[2]ENERO 2025'!H40+Hoja5!H37 -> 0 | I40: 0 | J40: =SUM(G40:I40) -> 0 | K40: =J40/$J$25 -> 0
A41: 2 | B41: 1 | C41: 1 | D41: 2 | E41: 11 | F41: Interinato | G41: =+'[2]MARZO 2025'!G41+'[2]FEBRERO 2025'!G41+'[2]ENERO 2025'!G41+Hoja5!G38 -> 0 | H41: =+'[2]MARZO 2025'!H41+'[2]FEBRERO 2025'!H41+'[2]ENERO 2025'!H41+Hoja5!H38 -> 0 | I41: 0 | J41: =SUM(G41:I41) -> 0 | K41: =J41/$J$25 -> 0
A42: 2 | B42: 1 | C42: 1 | D42: 3 | F42: Sueldos al personal fijo en trámite de pensiones | G42: =+'[2]MARZO 2025'!G42+'[2]FEBRERO 2025'!G42+'[2]ENERO 2025'!G42+Hoja5!G39 -> 1107531 | H42: =+'[2]MARZO 2025'!H42+'[2]FEBRERO 2025'!H42+'[2]ENERO 2025'!H42+Hoja5!H39 -> 0 | I42: 0 | J42: =SUM(G42:I42) -> 1107531
A43: 2 | B43: 1 | C43: 1 | D43: 3 | E43: 01 | F43: Sueldos al personal fijo en trámite de pensiones | G43: =+'[2]MARZO 2025'!G43+'[2]FEBRERO 2025'!G43+'[2]ENERO 2025'!G43+Hoja5!G40 -> 0 | H43: =+'[2]MARZO 2025'!H43+'[2]FEBRERO 2025'!H43+'[2]ENERO 2025'!H43+Hoja5!H40 -> 0 | I43: 0 | J43: =SUM(G43:I43) -> 0 | K43: =J43/$J$25 -> 0
A44: 2 | B44: 1 | C44: 1 | D44: 4 | F44: Sueldo anual no. 13 | G44: =+'[2]MARZO 2025'!G44+'[2]FEBRERO 2025'!G44+'[2]ENERO 2025'!G44+Hoja5!G41 -> 0 | H44: =+'[2]MARZO 2025'!H44+'[2]FEBRERO 2025'!H44+'[2]ENERO 2025'!H44+Hoja5!H41 -> 0 | I44: 0 | J44: =SUM(G44:I44) -> 0
A45: 2 | B45: 1 | C45: 1 | D45: 4 | E45: 01 | F45: Sueldo anual no. 13 | G45: =+'[2]MARZO 2025'!G45+'[2]FEBRERO 2025'!G45+'[2]ENERO 2025'!G45+Hoja5!G42 -> 0 | H45: =+'[2]MARZO 2025'!H45+'[2]FEBRERO 2025'!H45+'[2]ENERO 2025'!H45+Hoja5!H42 -> 0 | I45: 0 | J45: =SUM(G45:I45) -> 0 | K45: =J45/$J$25 -> 0
A46: 2 | B46: 1 | C46: 1 | D46: 5 | F46: Prestaciones económinas | G46: =+'[2]MARZO 2025'!G46+'[2]FEBRERO 2025'!G46+'[2]ENERO 2025'!G46+Hoja5!G43 -> 1333120.1 | H46: =+'[2]MARZO 2025'!H46+'[2]FEBRERO 2025'!H46+'[2]ENERO 2025'!H46+Hoja5!H43 -> 0 | I46: 0 | J46: =SUM(G46:I46) -> 1333120.1
A47: 2 | B47: 1 | C47: 1 | D47: 5 | E47: 01 | F47: Prestaciones económinas | G47: =+'[2]MARZO 2025'!G47+'[2]FEBRERO 2025'!G47+'[2]ENERO 2025'!G47+Hoja5!G44 -> 815000 | H47: =+'[2]MARZO 2025'!H47+'[2]FEBRERO 2025'!H47+'[2]ENERO 2025'!H47+Hoja5!H44 -> 0 | I47: 0 | J47: =SUM(G47:I47) -> 815000 | K47: =J47/$J$25 -> 0.0015418494
A48: 2 | B48: 1 | C48: 1 | D48: 5 | E48: 02 | F48: Pago de porcentaje por desvinculación de cargo | G48: =+'[2]MARZO 2025'!G48+'[2]FEBRERO 2025'!G48+'[2]ENERO 2025'!G48+Hoja5!G45 -> 0 | H48: =+'[2]MARZO 2025'!H48+'[2]FEBRERO 2025'!H48+'[2]ENERO 2025'!H48+Hoja5!H45 -> 0 | I48: 0 | J48: =SUM(G48:I48) -> 0 | K48: =J48/$J$25 -> 0
A49: 2 | B49: 1 | C49: 1 | D49: 5 | E49: 03 | F49: Prestación laboral por desvinculación | G49: =+'[2]MARZO 2025'!G49+'[2]FEBRERO 2025'!G49+'[2]ENERO 2025'!G49+Hoja5!G46 -> 181111.08 | H49: =+'[2]MARZO 2025'!H49+'[2]FEBRERO 2025'!H49+'[2]ENERO 2025'!H49+Hoja5!H46 -> 0 | I49: 0 | J49: =SUM(G49:I49) -> 181111.08 | K49: =J49/$J$25 -> 0.00034263314
A50: 2 | B50: 1 | C50: 1 | D50: 5 | E50: 04 | F50: Proporción de vacaciones no disfrutadas | G50: =+'[2]MARZO 2025'!G50+'[2]FEBRERO 2025'!G50+'[2]ENERO 2025'!G50+Hoja5!G47 -> 518120.15 | H50: =+'[2]MARZO 2025'!H50+'[2]FEBRERO 2025'!H50+'[2]ENERO 2025'!H50+Hoja5!H47 -> 0 | I50: 0 | J50: =SUM(G50:I50) -> 518120.15 | K50: =J50/$J$25 -> 0.00098020029
A51: 2 | B51: 1 | C51: 2 | F51: Sobresueldos | G51: =+'[2]MARZO 2025'!G51+'[2]FEBRERO 2025'!G51+'[2]ENERO 2025'!G51+Hoja5!G48 -> 9594398.8 | H51: =+'[2]MARZO 2025'!H51+'[2]FEBRERO 2025'!H51+'[2]ENERO 2025'!H51+Hoja5!H48 -> 5231553.6 | I51: 0 | J51: =SUM(G51:I51) -> 14825952
A52: 2 | B52: 1 | C52: 2 | D52: 1 | F52: Primas por antigüedad | G52: =+'[2]MARZO 2025'!G52+'[2]FEBRERO 2025'!G52+'[2]ENERO 2025'!G52+Hoja5!G49 -> 8348809.5 | H52: =+'[2]MARZO 2025'!H52+'[2]FEBRERO 2025'!H52+'[2]ENERO 2025'!H52+Hoja5!H49 -> 0 | I52: 0 | J52: =SUM(G52:I52) -> 8348809.5
A53: 2 | B53: 1 | C53: 2 | D53: 1 | E53: 01 | F53: Primas por antigüedad | G53: =+'[2]MARZO 2025'!G53+'[2]FEBRERO 2025'!G53+'[2]ENERO 2025'!G53+Hoja5!G50 -> 8345120.6 | H53: =+'[2]MARZO 2025'!H53+'[2]FEBRERO 2025'!H53+'[2]ENERO 2025'!H53+Hoja5!H50 -> 0 | I53: 0 | J53: =SUM(G53:I53) -> 8345120.6 | K53: =J53/$J$25 -> 0.015787631
A54: 2 | B54: 1 | C54: 2 | D54: 2 | F54: Compensación | G54: =+'[2]MARZO 2025'!G54+'[2]FEBRERO 2025'!G54+'[2]ENERO 2025'!G54+Hoja5!G51 -> 4722953.8 | H54: =+'[2]MARZO 2025'!H54+'[2]FEBRERO 2025'!H54+'[2]ENERO 2025'!H54+Hoja5!H51 -> 5231553.6 | I54: 0 | J54: =SUM(G54:I54) -> 9954507.4
A55: 2 | B55: 1 | C55: 2 | D55: 2 | E55: 01 | F55: Compensación por gastos de alimentación | G55: =+'[2]MARZO 2025'!G55+'[2]FEBRERO 2025'!G55+'[2]ENERO 2025'!G55+Hoja5!G52 -> 2739824.5 | H55: =+'[2]MARZO 2025'!H55+'[2]FEBRERO 2025'!H55+'[2]ENERO 2025'!H55+Hoja5!H52 -> 0 | I55: 0 | J55: =SUM(G55:I55) -> 2739824.5 | K55: =J55/$J$25 -> 0.0051833089
A56: 2 | B56: 1 | C56: 2 | D56: 2 | E56: 03 | F56: Pago de horas extraordinarias | G56: =+'[2]MARZO 2025'!G56+'[2]FEBRERO 2025'!G56+'[2]ENERO 2025'!G56+Hoja5!G53 -> 2739824.5 | H56: =+'[2]MARZO 2025'!H56+'[2]FEBRERO 2025'!H56+'[2]ENERO 2025'!H56+Hoja5!H53 -> 0 | I56: 0 | J56: =SUM(G56:I56) -> 2739824.5 | K56: =J56/$J$25 -> 0.0051833089
A57: 2 | B57: 1 | C57: 2 | D57: 2 | E57: 04 | F57: Prima de transporte | G57: =+'[2]MARZO 2025'!G57+'[2]FEBRERO 2025'!G57+'[2]ENERO 2025'!G57+Hoja5!G54 -> 645139.96 | H57: =+'[2]MARZO 2025'!H57+'[2]FEBRERO 2025'!H57+'[2]ENERO 2025'!H57+Hoja5!H54 -> 0 | I57: 0 | J57: =SUM(G57:I57) -> 645139.96 | K57: =J57/$J$25 -> 0.0012205014
A58: 2 | B58: 1 | C58: 2 | D58: 2 | E58: 05 | F58: Compensación servicios de Seguridad | G58: =+'[2]MARZO 2025'!G58+'[2]FEBRERO 2025'!G58+'[2]ENERO 2025'!G58+Hoja5!G55 -> 135000 | H58: =+'[2]MARZO 2025'!H58+'[2]FEBRERO 2025'!H58+'[2]ENERO 2025'!H58+Hoja5!H55 -> 0 | I58: 0 | J58: =SUM(G58:I58) -> 135000 | K58: =J58/$J$25 -> 0.00025539837
A59: 2 | B59: 1 | C59: 2 | D59: 2 | E59: 06 | F59: Incentivo por Rendimieto Individual | G59: =+'[2]MARZO 2025'!G59+'[2]FEBRERO 2025'!G59+'[2]ENERO 2025'!G59+Hoja5!G56 -> 0 | H59: =+'[2]MARZO 2025'!H59+'[2]FEBRERO 2025'!H59+'[2]ENERO 2025'!H59+Hoja5!H56 -> 5231553.6 | I59: 0 | J59: =SUM(G59:I59) -> 5231553.6 | K59: =J59/$J$25 -> 0.009897261
A60: 2 | B60: 1 | C60: 2 | D60: 2 | E60: 07 | F60: Compensación por distancia | G60: =+'[2]MARZO 2025'!G60+'[2]FEBRERO 2025'!G60+'[2]ENERO 2025'!G60+Hoja5!G57 -> 0 | H60: =+'[2]MARZO 2025'!H60+'[2]FEBRERO 2025'!H60+'[2]ENERO 2025'!H60+Hoja5!H57 -> 0 | I60: 0 | J60: =SUM(G60:I60) -> 0 | K60: =J60/$J$25 -> 0
A61: 2 | B61: 1 | C61: 2 | D61: 2 | E61: 08 | F61: Compensaciones especiales | G61: =+'[2]MARZO 2025'!G61+'[2]FEBRERO 2025'!G61+'[2]ENERO 2025'!G61+Hoja5!G58 -> 1039000 | H61: =+'[2]MARZO 2025'!H61+'[2]FEBRERO 2025'!H61+'[2]ENERO 2025'!H61+Hoja5!H58 -> 0 | I61: 0 | J61: =SUM(G61:I61) -> 1039000 | K61: =J61/$J$25 -> 0.0019656215
A62: 2 | B62: 1 | C62: 2 | D62: 2 | E62: 09 | F62: Bono por desempeño a servidores de carrera | G62: =+'[2]MARZO 2025'!G62+'[2]FEBRERO 2025'!G62+'[2]ENERO 2025'!G62+Hoja5!G59 -> 0 | H62: =+'[2]MARZO 2025'!H62+'[2]FEBRERO 2025'!H62+'[2]ENERO 2025'!H62+Hoja5!H59 -> 0 | I62: 0 | J62: =SUM(G62:I62) -> 0 | K62: =J62/$J$25 -> 0
A63: 2 | B63: 1 | C63: 2 | D63: 2 | E63: 10 | F63: Compensacion por cumplimiento de indicadores | G63: =+'[2]MARZO 2025'!G63+'[2]FEBRERO 2025'!G63+'[2]ENERO 2025'!G63+Hoja5!G60 -> 208989.3 | H63: =+'[2]MARZO 2025'!H63+'[2]FEBRERO 2025'!H63+'[2]ENERO 2025'!H63+Hoja5!H60 -> 0 | I63: 0 | J63: =SUM(G63:I63) -> 208989.3 | K63: =J63/$J$25 -> 0.00039537426
A64: 2 | B64: 1 | C64: 3 | F64: Dietas y Gastos de Representación | G64: =+'[2]MARZO 2025'!G64+'[2]FEBRERO 2025'!G64+'[2]ENERO 2025'!G64+Hoja5!G61 -> 339600 | H64: =+'[2]MARZO 2025'!H64+'[2]FEBRERO 2025'!H64+'[2]ENERO 2025'!H64+Hoja5!H61 -> 0 | I64: 0 | J64: =SUM(G64:I64) -> 339600
A65: 2 | B65: 1 | C65: 3 | D65: 1 | F65: Dietas | G65: =+'[2]MARZO 2025'!G65+'[2]FEBRERO 2025'!G65+'[2]ENERO 2025'!G65+Hoja5!G62 -> 0 | H65: =+'[2]MARZO 2025'!H65+'[2]FEBRERO 2025'!H65+'[2]ENERO 2025'!H65+Hoja5!H62 -> 0 | I65: 0 | J65: =SUM(G65:I65) -> 0
A66: 2 | B66: 1 | C66: 3 | D66: 1 | E66: 01 | F66: Dietas en el país | G66: =+'[2]MARZO 2025'!G66+'[2]FEBRERO 2025'!G66+'[2]ENERO 2025'!G66+Hoja5!G63 -> 260539.96 | H66: =+'[2]MARZO 2025'!H66+'[2]FEBRERO 2025'!H66+'[2]ENERO 2025'!H66+Hoja5!H63 -> 0 | I66: 0 | J66: =SUM(G66:I66) -> 260539.96 | K66: =J66/$J$25 -> 0.00049289985
A67: 2 | B67: 1 | C67: 3 | D67: 1 | E67: 02 | F67: Dietas en el exterior | G67: =+'[2]MARZO 2025'!G67+'[2]FEBRERO 2025'!G67+'[2]ENERO 2025'!G67+Hoja5!G64 -> 0 | H67: =+'[2]MARZO 2025'!H67+'[2]FEBRERO 2025'!H67+'[2]ENERO 2025'!H67+Hoja5!H64 -> 0 | I67: 0 | J67: =SUM(G67:I67) -> 0 | K67: =J67/$J$25 -> 0
A68: 2 | B68: 1 | C68: 3 | D68: 2 | F68: Gastos de representación | G68: =+'[2]MARZO 2025'!G68+'[2]FEBRERO 2025'!G68+'[2]ENERO 2025'!G68+Hoja5!G65 -> 0 | H68: =+'[2]MARZO 2025'!H68+'[2]FEBRERO 2025'!H68+'[2]ENERO 2025'!H68+Hoja5!H65 -> 0 | I68: 0 | J68: =SUM(G68:I68) -> 0
A69: 2 | B69: 1 | C69: 3 | D69: 2 | E69: 01 | F69: Gastos de representación en el país | G69: =+'[2]MARZO 2025'!G69+'[2]FEBRERO 2025'!G69+'[2]ENERO 2025'!G69+Hoja5!G66 -> 0 | H69: =+'[2]MARZO 2025'!H69+'[2]FEBRERO 2025'!H69+'[2]ENERO 2025'!H69+Hoja5!H66 -> 0 | I69: 0 | J69: =SUM(G69:I69) -> 0 | K69: =J69/$J$25 -> 0
A70: 2 | B70: 1 | C70: 3 | D70: 2 | E70: 02 | F70: Gastos de representación en el exterior | G70: =+'[2]MARZO 2025'!G70+'[2]FEBRERO 2025'!G70+'[2]ENERO 2025'!G70+Hoja5!G67 -> 0 | H70: =+'[2]MARZO 2025'!H70+'[2]FEBRERO 2025'!H70+'[2]ENERO 2025'!H70+Hoja5!H67 -> 0 | I70: 0 | J70: =SUM(G70:I70) -> 0 | K70: =J70/$J$25 -> 0
A71: 2 | B71: 1 | C71: 4 | F71: Gratificaciones y Bonificaciones | G71: =+'[2]MARZO 2025'!G71+'[2]FEBRERO 2025'!G71+'[2]ENERO 2025'!G71+Hoja5!G68 -> 0 | H71: =+'[2]MARZO 2025'!H71+'[2]FEBRERO 2025'!H71+'[2]ENERO 2025'!H71+Hoja5!H68 -> 0 | I71: 0 | J71: =SUM(G71:I71) -> 0
A72: 2 | B72: 1 | C72: 4 | D72: 1 | F72: Bonificaciones | G72: =+'[2]MARZO 2025'!G72+'[2]FEBRERO 2025'!G72+'[2]ENERO 2025'!G72+Hoja5!G69 -> 0 | H72: =+'[2]MARZO 2025'!H72+'[2]FEBRERO 2025'!H72+'[2]ENERO 2025'!H72+Hoja5!H69 -> 0 | I72: 0 | J72: =SUM(G72:I72) -> 0
A73: 2 | B73: 1 | C73: 4 | D73: 1 | E73: 01 | F73: Bonificaciones | G73: =+'[2]MARZO 2025'!G73+'[2]FEBRERO 2025'!G73+'[2]ENERO 2025'!G73+Hoja5!G70 -> 0 | H73: =+'[2]MARZO 2025'!H73+'[2]FEBRERO 2025'!H73+'[2]ENERO 2025'!H73+Hoja5!H70 -> 0 | I73: 0 | J73: =SUM(G73:I73) -> 0 | K73: =J73/$J$25 -> 0
A74: 2 | B74: 1 | C74: 4 | D74: 2 | F74: Otras Gratificaciones y Bonificaciones | G74: =+'[2]MARZO 2025'!G74+'[2]FEBRERO 2025'!G74+'[2]ENERO 2025'!G74+Hoja5!G71 -> 0 | H74: =+'[2]MARZO 2025'!H74+'[2]FEBRERO 2025'!H74+'[2]ENERO 2025'!H74+Hoja5!H71 -> 0 | I74: 0 | J74: =SUM(G74:I74) -> 0
A75: 2 | B75: 1 | C75: 4 | D75: 2 | E75: 01 | F75: Bono escolar | G75: =+'[2]MARZO 2025'!G75+'[2]FEBRERO 2025'!G75+'[2]ENERO 2025'!G75+Hoja5!G72 -> 0 | H75: =+'[2]MARZO 2025'!H75+'[2]FEBRERO 2025'!H75+'[2]ENERO 2025'!H75+Hoja5!H72 -> 0 | I75: 0 | J75: =SUM(G75:I75) -> 0 | K75: =J75/$J$25 -> 0
A76: 2 | B76: 1 | C76: 4 | D76: 2 | E76: 02 | F76: Gratificaciones por pasantías | G76: =+'[2]MARZO 2025'!G76+'[2]FEBRERO 2025'!G76+'[2]ENERO 2025'!G76+Hoja5!G73 -> 0 | H76: =+'[2]MARZO 2025'!H76+'[2]FEBRERO 2025'!H76+'[2]ENERO 2025'!H76+Hoja5!H73 -> 0 | I76: 0 | J76: =SUM(G76:I76) -> 0 | K76: =J76/$J$25 -> 0
A77: 2 | B77: 1 | C77: 4 | D77: 2 | E77: 03 | F77: Gratificaciones por aniversario de institución | G77: =+'[2]MARZO 2025'!G77+'[2]FEBRERO 2025'!G77+'[2]ENERO 2025'!G77+Hoja5!G74 -> 0 | H77: =+'[2]MARZO 2025'!H77+'[2]FEBRERO 2025'!H77+'[2]ENERO 2025'!H77+Hoja5!H74 -> 0 | I77: 0 | J77: =SUM(G77:I77) -> 0 | K77: =J77/$J$25 -> 0
A78: 2 | B78: 1 | C78: 5 | F78: Contribuciones a la Seguridad Social y Riesgo Laboral | G78: =+'[2]MARZO 2025'!G78+'[2]FEBRERO 2025'!G78+'[2]ENERO 2025'!G78+Hoja5!G75 -> 25021132 | H78: =+'[2]MARZO 2025'!H78+'[2]FEBRERO 2025'!H78+'[2]ENERO 2025'!H78+Hoja5!H75 -> 0 | I78: 0 | J78: =SUM(G78:I78) -> 25021132
A79: 2 | B79: 1 | C79: 5 | D79: 1 | F79: Contribuciones al seguro de salud | G79: =+'[2]MARZO 2025'!G79+'[2]FEBRERO 2025'!G79+'[2]ENERO 2025'!G79+Hoja5!G76 -> 11529204 | H79: =+'[2]MARZO 2025'!H79+'[2]FEBRERO 2025'!H79+'[2]ENERO 2025'!H79+Hoja5!H76 -> 0 | I79: 0 | J79: =SUM(G79:I79) -> 11529204
A80: 2 | B80: 1 | C80: 5 | D80: 1 | E80: 01 | F80: Contribuciones al seguro de salud | G80: =+'[2]MARZO 2025'!G80+'[2]FEBRERO 2025'!G80+'[2]ENERO 2025'!G80+Hoja5!G77 -> 11529204 | H80: =+'[2]MARZO 2025'!H80+'[2]FEBRERO 2025'!H80+'[2]ENERO 2025'!H80+Hoja5!H77 -> 0 | I80: 0 | J80: =SUM(G80:I80) -> 11529204 | K80: =J80/$J$25 -> 0.021811406
A81: 2 | B81: 1 | C81: 5 | D81: 2 | F81: Contribuciones al seguro de pensiones | G81: =+'[2]MARZO 2025'!G81+'[2]FEBRERO 2025'!G81+'[2]ENERO 2025'!G81+Hoja5!G78 -> 19945553 | H81: =+'[2]MARZO 2025'!H81+'[2]FEBRERO 2025'!H81+'[2]ENERO 2025'!H81+Hoja5!H78 -> 0 | I81: 0 | J81: =SUM(G81:I81) -> 19945553
A82: 2 | B82: 1 | C82: 5 | D82: 2 | E82: 01 | F82: Contribuciones al seguro de pensiones | G82: =+'[2]MARZO 2025'!G82+'[2]FEBRERO 2025'!G82+'[2]ENERO 2025'!G82+Hoja5!G79 -> 15415892 | H82: =+'[2]MARZO 2025'!H82+'[2]FEBRERO 2025'!H82+'[2]ENERO 2025'!H82+Hoja5!H79 -> 0 | I82: 0 | J82: =SUM(G82:I82) -> 15415892 | K82: =J82/$J$25 -> 0.029164397
A83: 2 | B83: 1 | C83: 5 | D83: 3 | F83: Contribuciones al seguro de riesgo laboral | G83: =+'[2]MARZO 2025'!G83+'[2]FEBRERO 2025'!G83+'[2]ENERO 2025'!G83+Hoja5!G80 -> 5816901.6 | H83: =+'[2]MARZO 2025'!H83+'[2]FEBRERO 2025'!H83+'[2]ENERO 2025'!H83+Hoja5!H80 -> 0 | I83: 0 | J83: =SUM(G83:I83) -> 5816901.6
A84: 2 | B84: 1 | C84: 5 | D84: 3 | E84: 01 | F84: Contribuciones al seguro de riesgo laboral | G84: =+'[2]MARZO 2025'!G84+'[2]FEBRERO 2025'!G84+'[2]ENERO 2025'!G84+Hoja5!G81 -> 5822358.7 | H84: =+'[2]MARZO 2025'!H84+'[2]FEBRERO 2025'!H84+'[2]ENERO 2025'!H84+Hoja5!H81 -> 0 | I84: 0 | J84: =SUM(G84:I84) -> 5822358.7 | K84: =J84/$J$25 -> 0.01101497
A85: 2 | B85: 1 | C85: 5 | D85: 4 | F85: Contribuciones al plan de retiro complementario | G85: =+'[2]MARZO 2025'!G85+'[2]FEBRERO 2025'!G85+'[2]ENERO 2025'!G85+Hoja5!G82 -> 3875889.5 | H85: =+'[2]MARZO 2025'!H85+'[2]FEBRERO 2025'!H85+'[2]ENERO 2025'!H85+Hoja5!H82 -> 0 | I85: 0 | J85: =SUM(G85:I85) -> 3875889.5
A86: 2 | B86: 1 | C86: 5 | D86: 4 | E86: 01 | F86: Contribuciones al plan de retiro complementario | G86: =+'[2]MARZO 2025'!G86+'[2]FEBRERO 2025'!G86+'[2]ENERO 2025'!G86+Hoja5!G83 -> 653772.07 | H86: =+'[2]MARZO 2025'!H86+'[2]FEBRERO 2025'!H86+'[2]ENERO 2025'!H86+Hoja5!H83 -> 0 | I86: 0 | J86: =SUM(G86:I86) -> 653772.07 | K86: =J86/$J$25 -> 0.001236832
A87: 2 | B87: 2 | F87: Servicios No Personales | G87: =+'[2]MARZO 2025'!G87+'[2]FEBRERO 2025'!G87+'[2]ENERO 2025'!G87+Hoja5!G84 -> 9962137 | H87: =+'[2]MARZO 2025'!H87+'[2]FEBRERO 2025'!H87+'[2]ENERO 2025'!H87+Hoja5!H84 -> 8306683.9 | I87: 0 | J87: =SUM(G87:I87) -> 18268821 | K87: =J87/$J$25 -> 0.034561681
A88: 2 | B88: 2 | C88: 1 | F88: Servicios Básicos | G88: =+'[2]MARZO 2025'!G88+'[2]FEBRERO 2025'!G88+'[2]ENERO 2025'!G88+Hoja5!G85 -> 2020024.3 | H88: =+'[2]MARZO 2025'!H88+'[2]FEBRERO 2025'!H88+'[2]ENERO 2025'!H88+Hoja5!H85 -> 2341561.9 | I88: 0 | J88: =SUM(G88:I88) -> 4361586.2
A89: 2 | B89: 2 | C89: 1 | D89: 1 | F89: Radiocomunicación | G89: =+'[2]MARZO 2025'!G89+'[2]FEBRERO 2025'!G89+'[2]ENERO 2025'!G89+Hoja5!G86 -> 0 | H89: =+'[2]MARZO 2025'!H89+'[2]FEBRERO 2025'!H89+'[2]ENERO 2025'!H89+Hoja5!H86 -> 0 | I89: 0 | J89: =SUM(G89:I89) -> 0
A90: 2 | B90: 2 | C90: 1 | D90: 1 | E90: 01 | F90: Radiocomunicación | G90: =+'[2]MARZO 2025'!G90+'[2]FEBRERO 2025'!G90+'[2]ENERO 2025'!G90+Hoja5!G87 -> 210535 | H90: =+'[2]MARZO 2025'!H90+'[2]FEBRERO 2025'!H90+'[2]ENERO 2025'!H90+Hoja5!H87 -> 1256712.1 | I90: 0 | J90: =SUM(G90:I90) -> 1467247.1 | K90: =J90/$J$25 -> 0.0027757964
A91: 2 | B91: 2 | C91: 1 | D91: 2 | F91: Servicios telefónico de larga distancia | G91: =+'[2]MARZO 2025'!G91+'[2]FEBRERO 2025'!G91+'[2]ENERO 2025'!G91+Hoja5!G88 -> 60535 | H91: =+'[2]MARZO 2025'!H91+'[2]FEBRERO 2025'!H91+'[2]ENERO 2025'!H91+Hoja5!H88 -> 285608.3 | I91: 0 | J91: =SUM(G91:I91) -> 346143.3
A92: 2 | B92: 2 | C92: 1 | D92: 2 | E92: 01 | F92: Servicios telefónico de larga distancia | G92: =+'[2]MARZO 2025'!G92+'[2]FEBRERO 2025'!G92+'[2]ENERO 2025'!G92+Hoja5!G89 -> 0 | H92: =+'[2]MARZO 2025'!H92+'[2]FEBRERO 2025'!H92+'[2]ENERO 2025'!H92+Hoja5!H89 -> 0 | I92: 0 | J92: =SUM(G92:I92) -> 0 | K92: =J92/$J$25 -> 0
A93: 2 | B93: 2 | C93: 1 | D93: 3 | F93: Teléfono local | G93: =+'[2]MARZO 2025'!G93+'[2]FEBRERO 2025'!G93+'[2]ENERO 2025'!G93+Hoja5!G90 -> 0 | H93: =+'[2]MARZO 2025'!H93+'[2]FEBRERO 2025'!H93+'[2]ENERO 2025'!H93+Hoja5!H90 -> 771561.92 | I93: 0 | J93: =SUM(G93:I93) -> 771561.92
A94: 2 | B94: 2 | C94: 1 | D94: 3 | E94: 01 | F94: Teléfono local | G94: =+'[2]MARZO 2025'!G94+'[2]FEBRERO 2025'!G94+'[2]ENERO 2025'!G94+Hoja5!G91 -> 0 | H94: =+'[2]MARZO 2025'!H94+'[2]FEBRERO 2025'!H94+'[2]ENERO 2025'!H94+Hoja5!H91 -> 771561.92 | I94: 0 | J94: =SUM(G94:I94) -> 771561.92 | K94: =J94/$J$25 -> 0.0014596715
A95: 2 | B95: 2 | C95: 1 | D95: 4 | F95: Telefax y correos | G95: =+'[2]MARZO 2025'!G95+'[2]FEBRERO 2025'!G95+'[2]ENERO 2025'!G95+Hoja5!G92 -> 0 | H95: =+'[2]MARZO 2025'!H95+'[2]FEBRERO 2025'!H95+'[2]ENERO 2025'!H95+Hoja5!H92 -> 0 | I95: 0 | J95: =SUM(G95:I95) -> 0
A96: 2 | B96: 2 | C96: 1 | D96: 4 | E96: 01 | F96: Telefax y correos | G96: =+'[2]MARZO 2025'!G96+'[2]FEBRERO 2025'!G96+'[2]ENERO 2025'!G96+Hoja5!G93 -> 0 | H96: =+'[2]MARZO 2025'!H96+'[2]FEBRERO 2025'!H96+'[2]ENERO 2025'!H96+Hoja5!H93 -> 104569.42 | I96: 0 | J96: =SUM(G96:I96) -> 104569.42 | K96: =J96/$J$25 -> 0.00019782858
A97: 2 | B97: 2 | C97: 1 | D97: 5 | F97: Servicio de Internet y televisión por cable | G97: =+'[2]MARZO 2025'!G97+'[2]FEBRERO 2025'!G97+'[2]ENERO 2025'!G97+Hoja5!G94 -> 0 | H97: =+'[2]MARZO 2025'!H97+'[2]FEBRERO 2025'!H97+'[2]ENERO 2025'!H97+Hoja5!H94 -> 104569.42 | I97: 0 | J97: =SUM(G97:I97) -> 104569.42
A98: 2 | B98: 2 | C98: 1 | D98: 5 | E98: 01 | F98: Servicio de Internet y televisión por cable | G98: =+'[2]MARZO 2025'!G98+'[2]FEBRERO 2025'!G98+'[2]ENERO 2025'!G98+Hoja5!G95 -> 0 | H98: =+'[2]MARZO 2025'!H98+'[2]FEBRERO 2025'!H98+'[2]ENERO 2025'!H98+Hoja5!H95 -> 0 | I98: 0 | J98: =SUM(G98:I98) -> 0 | K98: =J98/$J$25 -> 0
A99: 2 | B99: 2 | C99: 1 | D99: 6 | F99: Electricidad | G99: =+'[2]MARZO 2025'!G99+'[2]FEBRERO 2025'!G99+'[2]ENERO 2025'!G99+Hoja5!G96 -> 0 | H99: =+'[2]MARZO 2025'!H99+'[2]FEBRERO 2025'!H99+'[2]ENERO 2025'!H99+Hoja5!H96 -> 0 | I99: 0 | J99: =SUM(G99:I99) -> 0
A100: 2 | B100: 2 | C100: 1 | D100: 6 | E100: 01 | F100: Energía eléctrica | G100: =+'[2]MARZO 2025'!G100+'[2]FEBRERO 2025'!G100+'[2]ENERO 2025'!G100+Hoja5!G97 -> 0 | H100: =+'[2]MARZO 2025'!H100+'[2]FEBRERO 2025'!H100+'[2]ENERO 2025'!H100+Hoja5!H97 -> 106038.88 | I100: 0 | J100: =SUM(G100:I100) -> 106038.88 | K100: =J100/$J$25 -> 0.00020060857
A101: 2 | B101: 2 | C101: 1 | D101: 6 | E101: 02 | F101: Electricidad no cortable | G101: =+'[2]MARZO 2025'!G101+'[2]FEBRERO 2025'!G101+'[2]ENERO 2025'!G101+Hoja5!G98 -> 0 | H101: =+'[2]MARZO 2025'!H101+'[2]FEBRERO 2025'!H101+'[2]ENERO 2025'!H101+Hoja5!H98 -> 106038.88 | I101: 0 | J101: =SUM(G101:I101) -> 106038.88 | K101: =J101/$J$25 -> 0.00020060857
A102: 2 | B102: 2 | C102: 1 | D102: 7 | F102: Agua | G102: =+'[2]MARZO 2025'!G102+'[2]FEBRERO 2025'!G102+'[2]ENERO 2025'!G102+Hoja5!G99 -> 2020024.3 | H102: =+'[2]MARZO 2025'!H102+'[2]FEBRERO 2025'!H102+'[2]ENERO 2025'!H102+Hoja5!H99 -> 0 | I102: 0 | J102: =SUM(G102:I102) -> 2020024.3
...

Sheet CONCILIACION 
A6: Hospital Materno Infantil San Lorenzo de Los Mina
A7: Conciliación Bancaria al 30 de abril 2025
A10: Banco: | B10: BANRESERVAS | E10: CUENTA: 010-390450-6
G12: LIBRO
A13: BALANCE EN INICIAL AL 1ERO DEL MES DE ABRIL 2025 | G13: 4614.79
A14: MAS:
G15: 0
A16: Transferencia en transito | G16: 0
A17: Deposito | G17: =+'[11]TRANSFERENCIA RECIBIDAS'!B10 -> 6415962.7
A18: Reintegro comision nomina incentivo | G18: 7482.49
G19: =+G13+G16+G18+G17 -> 6428060
A20: MENOS:
A21: Cheques Emitidos | G21: =+'[11]CHEQUES EMITIDO '!D21 -> 222114.61
A22: Nominas | G22: =+'[11]NOMINA '!D9 -> 0
A23: Cargos Bancarios | G23: =+[11]comisiones!E40 -> 17193.48
A24: Transferencia | G24: =+[11]TRANSFERENCIAS!D40 -> 4457635.3
A26: Total de Debitos | G26: =SUM(G21:G25) -> 4696943.4
A28: TOTAL CONCILIADO | G28: =+G19-G26 -> 1731116.6
G31: BANCO
A32: BALANCE EN BANCO | G32: 3051985.9
A33: MAS:
A34: Depósitos en tránsito
G35: 0
A36: TOTAL DISPONIBLE | G36: =SUM(G32:G35) -> 3051985.9
A38: MENOS:
A39: Transferencia | G39: =-'[11]TRANSF EN TRANSITO'!D17 -> -1320869.2
A40: Cheques en transito | G40: =-'[11]CHEQUES EN TRAN'!D8 -> 0
A41: Nomina en transito | G41: 0
G42: =SUM(G39:G41) -> -1320869.2
A44: TOTAL CONCILIADO | G44: =+G36+G42 -> 1731116.6
A53: Preparado por: | D53: Licda. Milagros Martinez de la Rosa
D54: Contadora
A60: Aprobado Por | D60: Licdo Eugenio Rosario Rosario
D61: Director Administrativo y Financiero

Sheet INGRESOS
A3: Servicio Nacional de Salud
A4: Dirección de Fiscalización
A6: Comportamiento de Ingresos percibidos Segregados según Origen
A7: Establecimiento: HOSPITAL MATERNO INFANTIL SAN LORENZO DE LOS MINA Mes: ABRIL . Año: 2025 SRS: I
A8: . | B8: ARS | C8: Fecha deposito | D8: No. De Documento de referencia | E8: valor de Transferencia o Cheque
A9: INGRESOS | B9: FONDO 100(2.1) | E9: =4931430+462506+79621891.83 -> 85015828
B10: FONDO 100(2.3) | E10: 12593841
B11: FONDO 100(2.6) | E11: 3169632.1
A12: Sub-Total | E12: =SUM(E9:E11) -> 1.007793e+08
B13: SENASA POR ATENCION ODONTOLOGICA | C13: 45748 | E13: 50000
B14: SENASA POR ATENCION ODONTOLOGICA | C14: 45750 | E14: 50000
B15: SUBSIDIADO | C15: 45748 | E15: 2942930.3
B16: RENACER | C16: 45754 | E16: 73057.08
B17: CONTRIBUTIDO | C17: 45756 | E17: 10949.64
B18: ARS YUNEN | C18: 45757 | E18: 19489.76
B19: ARS CMD | C19: 45758 | E19: 22435.77
B20: CONTRIBUTIDO | C20: 45762 | E20: 2326715
B21: ARS SEMMA | C21: 45762 | E21: 28868.13
B22: ARS PALIC | C22: 45763 | E22: 51140.7
B23: ARS PALIC | C23: 45763 | E23: 129754.16
B24: ARS PALIC | C24: 45763 | E24: 6696.74
... B30: ARS MONUMENTAL | C30: 45775 | E30: 146560.32
B31: INGR. POR FACT DE SERV. DE INSTITUCIONES
A32: Sub-Total | E32: =SUM(E13:E31) -> 6892064.8
A33: OTROS APORTES | B33: Cafetería | C33: PAGO APLICADO EN EL MES DE DICIEMBRE CUBRIENDO DESDE ENERO A ABRIL RD$100,000.00
B34: Odontologia (facturacion servicios no contemplado en Plan Basico) | C34: 01-04 AL 30/04/2025 | E34: 214750
B35: Alquiler de espacios internos a terceros
B36: Aportes provenientes de convenios Institucionales
B37: INGRESOS POR SERVICIOS PACIENTES PRIVADOS Y DIFERENCIAS POR SEGUROS MEDICOS
B38: Otros (Identificar Fuente )
A39: Sub-Total | E39: =SUM(E33:E36) -> 214750
A40: Total General | E40: =E32+E39+E12 -> 1.0788612e+08

Sheet INGRESOS FEBRERO
A3: Servicio Nacional de Salud
A4: Dirección de Fiscalización
A6: Comportamiento de Ingresos percibidos Segregados según Origen
A7: Establecimiento: HOSPITAL MATERNO INFANTIL SAN LORENZO DE LOS MINA Mes: FEBRERO Año: 2025 SRS: I
A8: origen | B8: ARS | C8: Fecha deposito | D8: No. De Documento de referencia | E8: Valor de Transferencia o Cheque
A9: INGRESOS | B9: FONDO 100(2.1) | E9: 84553322
B10: FONDO 100(PARA OBJECTALES 2.2,2.3,2.6,2.7.) | E10: =+'[4]CONS. FUENTES FINAN'!G15 -> 1.003168e+08
A11: Sub-Total | E11: =SUM(E9:E10) -> 1.8487012e+08
A12: Venta de Servicio | B12: SUBSIDIADO | C12: 45693 | E12: =3928001.9+9500+1904171.25 -> 5841673.2
B13: CONTRIBUTIDO | C13: 45694 | E13: 2152926.5
B14: SENASA(POR ATENCION ODONTOGICA)
B15: ARS RENACER | C15: 45706 | E15: 272552.44
B16: APS | C16: 45709 | E16: 8262.07
B17: ASEMAP | C17: 45698 | E17: 4869.52
B18: YUNEN | C18: 45714 | E18: 7848.94
B19: CMD | C19: 45714 | E19: 41071.9
B20: SEMMA | C20: 45716 | E20: 9531.6
B21: HUMANO | C21: 45709 | E21: 97648.3
B22: PRIMERA | C22: 45709 | E22: =836513.99+34076.26 -> 870590.25
B23: META SALUD | C23: 45712 | E23: 31949.94
B24: INGR. POR FACT DE SERV. DE INSTITUCIONES
A25: Sub-Total | E25: =SUM(E12:E24) -> 9338924.6
B26: Cafetería | E26: 0
B27: Alquiler de espacios internos a terceros | E27: 0
B28: Aportes provenientes de convenios Institucionales (UCE) | E28: 20000
B29: INGRESOS POR SERVICIOS PACIENTES PRIVADOS Y DIFERENCIAS POR SEGUROS MEDICOS | E29: 190100
B30: Otros (Identificar Fuente )
A31: Sub-Total | E31: =SUM(E26:E30) -> 210100
A32: Total General | E32: =E25+E31+E11 -> 1.9441914e+08
A37: Bajo las funciones que nos asisten certificamos que el valor de los ingresos percibidos al MES DE FEBRERO 2025 correspondieron a (RD$109,865,819.70)
A39: Dado a los 28 dias del mes de FEBRERO del 2025
A43: Preparado por: | D43: Revisado por:
A49: Aprobado por:
B50: ___________________________________________

Sheet INGRESOS MARZO
A3: Servicio Nacional de Salud
A4: Dirección de Fiscalización
A6: Comportamiento de Ingresos percibidos Segregados según Origen
A7: Establecimiento: HOSPITAL MATERNO INFANTIL SAN LORENZO DE LOS MINA Mes: MARZO . Año: 2025 SRS: I
A8: . | B8: ARS | C8: Fecha deposito | D8: No. De Documento de referencia | E8: valor de Transferencia o Cheque
A9: INGRESOS | B9: FONDO 100(2.1) | E9: =79621891.83+4931430 -> 84553322
B10: FONDO 100(2.3) | E10: 12593841
B11: FONDO 100(2.6) | E11: =1000000+800000+800000+569632.08 -> 3169632.1
A12: Sub-Total | E12: =SUM(E9:E11) -> 1.003168e+08
A13: Venta de Servicio | B13: SUBSIDIADO | C13: 45719 | E13: 4595181.4
B14: SENASA POR ATENCION ODONTOLOGICA | C14: 45744 | E14: 50000
B15: CONTRIBUTIDO | C15: 45730 | E15: 1041144.3
B16: ARS YUNEN | C16: 45744 | E16: 14338.35
B17: ARS FUTURO | C17: 45741 | E17: 356314.76
B18: ARS ASEMAP | C18: 45740 | E18: 102672.34
B19: ARS PRIMERA | C19: 45737 | E19: 262926.38
B20: ARS HUMANO | C20: 45737 | E20: 34117.68
B21: ARS MONUMENTAL | C21: 45719 | E21: 237322.18
C22: 45730 | E22: 11220.43
B23: ARS RENACER, SA | C23: 45733 | E23: 222620.34
B24: ARS MAPHRE | C24: 45736 | E24: 16298.76
B25: ARS MAPHRE | C25: 45736 | E25: 15397.47
B26: ARS MAPHRE | C26: 45736 | E26: 30434.4
B27: ARS MAPHRE | C27: 45736 | E27: 65463.45
B28: ARS MAPHRE | C28: 45736 | E28: 12863.4
B29: ARS MAPHRE | C29: 45736 | E29: 155572.92
B30: ARS MAPHRE | C30: 45736 | E30: 309977.48
B31: ARS MAPHRE | C31: 45736 | E31: 504
B32: ARS META SALUD | C32: 45736 | E32: 1396
B33: ARS SEMMA | C33: 45737 | E33: 77169.4
B34: ARS APS | C34: 45737 | E34: 212345.21
B36: INGR. POR FACT DE SERV. DE INSTITUCIONES
A37: Sub-Total | E37: =SUM(E13:E36) -> 7825280.6
A38: OTROS APORTES | B38: Cafetería | C38: PAGO APLICADO EN EL MES DE DICIEMBRE CUBRIENDO DESDE ENERO A ABRIL RD$100,000.00
B39: Odontologia (facturacion servicios no contemplado en Plan Basico) | E39: 223625
B40: Alquiler de espacios internos a terceros
B41: Aportes provenientes de convenios Institucionales
B42: INGRESOS POR SERVICIOS PACIENTES PRIVADOS Y DIFERENCIAS POR SEGUROS MEDICOS
B43: Otros (Identificar Fuente )
A44: Sub-Total | E44: =SUM(E38:E41) -> 223625
A45: Total General | E45: =E37+E44+E12 -> 1.083657e+08
A48: Bajo las funciones que nos asisten certificamos que el valor de los ingresos percibidos durante el mes de marzo de 2025, correspondieron a un monto de RD$108,365,700.73
A51: Dado a los 31 dias del mes de marzo del año 2025.
A53: Cuenta Núm. | B53: Balance en libro | C53: Balance en Banco | D53: Balance Conciliado
A54: 010-390450-6 | B54: 4614.79 | C54: 7332169.7 | D54: 4614.79
A60: Preparado por: | D60: Revisado por:
B61: ____________________________________ | D61: ___________________________________
A62: Aprobado por:
B63: ________________________________

Sheet balance SIGEF

Sheet cxp
A1: Servicio Nacional de Salud
A2: Dirección de Control y Fiscalización
A3: Hospital Materno Infantil San Lorenzo de Los Mina
A4: Region Santo Domingo Este
A6: CUENTAS POR PAGAR 30 DE JUNIO 2024
A9: BENEFICIARIO | B9: Fecha | C9: O/C # | D9: Factura # | E9: Concepto | F9: Monto RD$ | G9: VS/LIB | H9: AÑO | I9: AÑOS ANTERIORES MONTO ANTES DEL 2019 | J9: AL 31 DE DICIEMBRE AÑO 2020 | K9: AL 31 DE DICIEMBRE AÑO 2021 | L9: AL 31 DE DICIEMBRE AÑO 2022 | M9: AL 31 DE DICIEMBRE DEL AÑO 2023 | N9: 45292 | O9: 45323 | P9: 45352 | Q9: 45383 | R9: 45413 | S9: 45444 | T9: TOTAL
A10: LABORATORIO QUIMICO J.A.F.S.A, | B10: 37435 | C10: 13724 | D10: N/S | E10: Galones de cloro y desifantante | F10: 5000 | G10: VS/LIB | H10: 2002 | I10: 5000 | T10: =SUM(I10:S10) -> 5000
A11: LABORATORIO QUIMICO J.A.F.S.A, | B11: 37452 | C11: 12330 | D11: S/N | E11: Galones de cloro y desifantante | F11: 4960 | G11: VS/LIB | H11: 2002 | I11: 4960 | T11: =SUM(I11:S11) -> 4960
A12: LABORATORIO QUIMICO J.A.F.S.A, | B12: 37493 | C12: 12451 | D12: S/N | E12: Galones de cloro y desifantante | F12: 5000 | G12: VS/LIB | H12: 2002 | I12: 5000 | T12: =SUM(I12:S12) -> 5000
A13: GEFARCA INDUTRIA FARMACEUTICA PEREZ ESPINOSA, C. POR A. | B13: 37516 | C13: 12494 | D13: 19301 | E13: Broncosamol solucion 20ml | F13: 160570 | G13: VS/LIB | H13: 2002 | I13: 160570 | T13: =SUM(I13:S13) -> 160570
A14: CAASD | B14: 38717 | D14: 51908749 / 53680282 | E14: SERVICIOS DE AGUA | F14: 16048 | G14: VS/LIB | H14: 2005 | I14: 16048 | T14: =SUM(I14:S14) -> 16048
A15: CAASD | B15: 39082 | D15: 53628425 / 55612019 | E15: SERVICIOS DE AGUA | F15: 317300 | G15: VS/LIB | H15: 2006 | I15: 317300 | T15: =SUM(I15:S15) -> 317300
A16: CAASD | B16: 39447 | D16: 55762890 / 57563516 | E16: SERVICIOS DE AGUA | F16: 309360 | G16: VS/LIB | H16: 2007 | I16: 309360 | T16: =SUM(I16:S16) -> 309360
A17: CAASD | B17: 39813 | D17: 57742426 / 59830745 | E17: SERVICIOS DE AGUA | F17: 365675 | G17: VS/LIB | H17: 2008 | I17: 365675 | T17: =SUM(I17:S17) -> 365675
A18: CAASD | B18: 40178 | D18: 60019251 / 62053746 | E18: SERVICIOS DE AGUA | F18: 364151 | G18: VS/LIB | H18: 2009 | I18: 364151 | T18: =SUM(I18:S18) -> 364151
A19: CAASD | B19: 40543 | D19: 6225761 / 64111504 | E19: SERVICIOS DE AGUA | F19: 364128 | G19: VS/LIB | H19: 2010 | I19: 364128 | T19: =SUM(I19:S19) -> 364128
A20: CAASD | B20: 40908 | D20: 64358222 / 67319668 | E20: SERVICIOS DE AGUA | F20: 364128 | G20: VS/LIB | H20: 2011 | I20: 364128 | T20: =SUM(I20:S20) -> 364128
A21: JONES FARMACEUTICA | B21: 41123 | C21: NO.0711 | D21: 1829 | E21: medicamentos | F21: 6000 | G21: VS/LIB | H21: 2012 | I21: 6000 | T21: =SUM(I21:S21) -> 6000
A22: JONES FARMACEUTICA | B22: 41129 | C22: NO.0712 | D22: 1839 | E22: medicamentos | F22: 7680 | G22: VS/LIB | H22: 2012 | I22: 7680 | T22: =SUM(I22:S22) -> 7680
A23: JONES FARMACEUTICA | B23: 41131 | C23: NO.0713 | D23: 1847 | E23: medicamentos | F23: 11860 | G23: VS/LIB | H23: 2012 | I23: 11860 | T23: =SUM(I23:S23) -> 11860
A24: JONES FARMACEUTICA | B24: 41143 | C24: NO.0714 | D24: 1861 | E24: medicamentos | F24: 16000 | G24: VS/LIB | H24: 2012 | I24: 16000 | T24: =SUM(I24:S24) -> 16000
A25: JONES FARMACEUTICA | B25: 41145 | C25: NO.0715 | D25: 1868 | E25: medicamentos | F25: 13000 | G25: VS/LIB | H25: 2012 | I25: 13000 | T25: =SUM(I25:S25) -> 13000
A26: JONES FARMACEUTICA | B26: 41151 | C26: NO.0716 | D26: 1875 | E26: medicamentos | F26: 13322 | G26: VS/LIB | H26: 2012 | I26: 13322 | T26: =SUM(I26:S26) -> 13322
A27: JONES FARMACEUTICA | B27: 41173 | C27: NO.0762 | D27: 1904 | E27: util menor med.quirurgcio | F27: 20000 | G27: VS/LIB | H27: 2012 | I27: 20000 | T27: =SUM(I27:S27) -> 20000
A28: JONES FARMACEUTICA | B28: 41178 | C28: NO.0758 | D28: 1909 | E28: util menor med.quirurgcio | F28: 16365 | G28: VS/LIB | H28: 2012 | I28: 16365 | T28: =SUM(I28:S28) -> 16365
A29: JONES FARMACEUTICA | B29: 41178 | C29: NO.0763 | D29: 1910 | E29: util menor med.quirurgcio | F29: 30190 | G29: VS/LIB | H29: 2012 | I29: 30190 | T29: =SUM(I29:S29) -> 30190
A30: JONES FARMACEUTICA | B30: 41180 | C30: NO.0764 | D30: 1912 | E30: util menor med.quirurgcio | F30: 28700 | G30: VS/LIB | H30: 2012 | I30: 28700 | T30: =SUM(I30:S30) -> 28700
A31: JONES FARMACEUTICA | B31: 41187 | C31: NO.1062 | D31: 1919 | E31: util menor med.quirurgcio | F31: 53780 | G31: VS/LIB | H31: 2012 | I31: 53780 | T31: =SUM(I31:S31) -> 53780
A32: JONES FARMACEUTICA | B32: 41197 | C32: NO.1063 | D32: 1927 | E32: util menor med.quirurgcio | F32: 56640 | G32: VS/LIB | H32: 2012 | I32: 56640 | T32: =SUM(I32:S32) -> 56640
A33: DANILO MATA ROSARIO(MAQUINOR) | B33: 41208 | C33: NO.1053 | D33: 211 | E33: Compra de reactivos y util med. | F33: 58788.8 | G33: VS/LIB | H33: 2012 | I33: 58788.8 | T33: =SUM(I33:S33) -> 58788.8
A34: JONES FARMACEUTICA | B34: 41208 | C34: NO.1064 | D34: 1936 | E34: util menor med.quirurgcio | F34: 21820 | G34: VS/LIB | H34: 2012 | I34: 21820 | T34: =SUM(I34:S34) -> 21820
A35: SERVIMER DOMINICANA, S.R.L | B35: 41208 | C35: 1049 | D35: A0100100115500001229 | E35: Compra de medicamentos utliles medico | F35: 57950 | G35: VS/LIB | H35: 2012 | I35: 57950 | T35: =SUM(I35:S35) -> 57950
A36: JONES FARMACEUTICA | B36: 41213 | C36: NO.1065 | D36: 1941 | E36: medicamentos | F36: 20000 | G36: VS/LIB | H36: 2012 | I36: 20000 | T36: =SUM(I36:S36) -> 20000
A37: JONES FARMACEUTICA | B37: 41225 | C37: NO.1094 | D37: 1948 | E37: medicamentos | F37: 21070 | G37: VS/LIB | H37: 2012 | I37: 21070 | T37: =SUM(I37:S37) -> 21070
A38: JONES FARMACEUTICA | B38: 41229 | C38: NO.1095 | D38: 1955 | E38: util menor med.quirurgcio | F38: 20231 | G38: VS/LIB | H38: 2012 | I38: 20231 | T38: =SUM(I38:S38) -> 20231
A39: JONES FARMACEUTICA | B39: 41236 | C39: NO.1097 | D39: 1964 | E39: util menor med.quirurgcio | F39: 41595 | G39: VS/LIB | H39: 2012 | I39: 41595 | T39: =SUM(I39:S39) -> 41595
A40: JONES FARMACEUTICA | B40: 41236 | C40: NO.1096 | D40: 1966 | E40: util menor med.quirurgcio | F40: 16380 | G40: VS/LIB | H40: 2012 | I40: 16380 | T40: =SUM(I40:S40) -> 16380
A41: JONES FARMACEUTICA | B41: 41250 | C41: NO.1220 | D41: 1974 | E41: util menor med.quirurgcio | F41: 45947.4 | G41: VS/LIB | H41: 2012 | I41: 45947.4 | T41: =SUM(I41:S41) -> 45947.4
A42: JONES FARMACEUTICA | B42: 41257 | C42: NO.1219 | D42: 1984 | E42: util menor med.quirurgcio | F42: 64135 | G42: VS/LIB | H42: 2012 | I42: 64135 | T42: =SUM(I42:S42) -> 64135
A43: JONES FARMACEUTICA | B43: 41263 | C43: NO.1217 | D43: 1995 | E43: util menor med.quirurgcio | F43: 24173 | G43: VS/LIB | H43: 2012 | I43: 24173 | T43: =SUM(I43:S43) -> 24173
A44: CAASD | B44: 41274 | D44: 67544661 / 69401910 | E44: SERVICIOS DE AGUA | F44: 364128 | G44: VS/LIB | H44: 2012 | I44: 364128 | T44: =SUM(I44:S44) -> 364128
A45: JONES FARMACEUTICA | B45: 41283 | C45: NO.2038 | D45: 2000 | E45: Compra de bupivacaina y biosidex | F45: 25445 | G45: VS/LIB | H45: 2013 | I45: 25445 | T45: =SUM(I45:S45) -> 25445
A46: DANILO MATA ROSARIO(MAQUINOR) | B46: 41289 | C46: NO.1957 | D46: 218 | E46: Compra de reactivos y util med. | F46: 78517.2 | G46: VS/LIB | H46: 2013 | I46: 78517.2 | T46: =SUM(I46:S46) -> 78517.2
A47: JONES FARMACEUTICA | B47: 41305 | C47: NO.1654 | D47: 2021 | E47: Compra de medicamentos | F47: 23535 | G47: VS/LIB | H47: 2013 | I47: 23535 | T47: =SUM(I47:S47) -> 23535
A48: JONES FARMACEUTICA | B48: 41309 | C48: NO.1579 | D48: 2026 | E48: medicamentos | F48: 3480 | G48: VS/LIB | H48: 2013 | I48: 3480 | T48: =SUM(I48:S48) -> 3480
A49: SERVIMER DOMINICANA, S.R.L | B49: 41311 | C49: 1595 | D49: A0100100115500001237 | E49: Compra de utliles medico | F49: 105925 | G49: VS/LIB | H49: 2013 | I49: 105925 | T49: =SUM(I49:S49) -> 105925
A50: JONES FARMACEUTICA | B50: 41352 | C50: NO.2013 | D50: 2057 | E50: medicamentos | F50: 64604 | G50: VS/LIB | H50: 2013 | I50: 64604 | T50: =SUM(I50:S50) -> 64604
A51: DANILO MATA ROSARIO(MAQUINOR) | B51: 41372 | C51: NO.1958 | D51: 220 | E51: Compra de reactivos y util med. | F51: 68322 | G51: VS/LIB | H51: 2013 | I51: 68322 | T51: =SUM(I51:S51) -> 68322
A52: SERVIMER DOMINICANA, S.R.L | B52: 41375 | C52: 2068 | D52: A0100100115500001238 | E52: Compra de utliles medico | F52: 99745 | G52: VS/LIB | H52: 2013 | I52: 99745 | T52: =SUM(I52:S52) -> 99745
A53: SANCHEZ Y MANCEBO, S. A. | B53: 41460 | C53: 2460 | D53: 1884 | E53: Compra de combustible para la caldera | F53: 315500 | G53: VS/LIB | H53: 2013 | I53: 315500 | T53: =SUM(I53:S53) -> 315500
A54: SANCHEZ Y MANCEBO, S. A. | B54: 41465 | C54: 2461 | D54: 1891 | E54: combustible para la planta | F54: 210400 | G54: VS/LIB | H54: 2013 | I54: 210400 | T54: =SUM(I54:S54) -> 210400
A55: SANCHEZ Y MANCEBO, S. A. | B55: 41472 | C55: 2462 | D55: 1892 | E55: Compra de combustible para la caldera | F55: 318800 | G55: VS/LIB | H55: 2013 | I55: 318800 | T55: =SUM(I55:S55) -> 318800
A56: SANCHEZ Y MANCEBO, S. A. | B56: 41478 | C56: 2463 | D56: 1896 | E56: combustible para la planta | F56: 216600 | G56: VS/LIB | H56: 2013 | I56: 216600 | T56: =SUM(I56:S56) -> 216600
A57: HOSPIRED | B57: 41484 | C57: 2707 | D57: 1329 | E57: alcohol isopropilico al 99% | F57: 2747.04 | G57: VS/LIB | H57: 2013 | I57: 2747.04 | T57: =SUM(I57:S57) -> 2747.04
A58: SANCHEZ Y MANCEBO, S. A. | B58: 41486 | C58: 2481 | D58: 1898 | E58: Compra de combustible para la caldera | F58: 324800 | G58: VS/LIB | H58: 2013 | I58: 324800 | T58: =SUM(I58:S58) -> 324800
A59: SANCHEZ Y MANCEBO, S. A. | B59: 41486 | C59: 2495 | D59: 1904 | E59: tickest combustible | F59: 39612.02 | G59: VS/LIB | H59: 2013 | I59: 39612.02 | T59: =SUM(I59:S59) -> 39612.02
A60: SANCHEZ Y MANCEBO, S. A. | B60: 41499 | C60: 2548 | D60: 1912 | E60: Compra de combustible para la caldera | F60: 324800 | G60: VS/LIB | H60: 2013 | I60: 324800 | T60: =SUM(I60:S60) -> 324800
A61: HOSPIRED | B61: 41509 | C61: 2682 | D61: 1377 | E61: alcohol isopropilico al 99% | F61: 6043.49 | G61: VS/LIB | H61: 2013 | I61: 6043.49 | T61: =SUM(I61:S61) -> 6043.49
A62: SANCHEZ Y MANCEBO, S. A. | B62: 41513 | C62: 2572 | D62: 1915 | E62: Compra de combustible para la caldera | F62: 328100 | G62: VS/LIB | H62: 2013 | I62: 328100 | T62: =SUM(I62:S62) -> 328100
A63: SANCHEZ Y MANCEBO, S. A. | B63: 41517 | C63: 2941 | D63: 1927 | E63: tickest combustible | F63: 30084.38 | G63: VS/LIB | H63: 2013 | I63: 30084.38 | T63: =SUM(I63:S63) -> 30084.38
A64: IDEAL PRINT | B64: 41518 | C64: 2561 | D64: 130705 | E64: Gasto por servico grafico | F64: 1970.6 | G64: VS/LIB | H64: 2013 | I64: 1970.6 | T64: =SUM(I64:S64) -> 1970.6
... A73: SANCHEZ Y MANCEBO, S. A. | B73: 41579 | C73: 2969 | D73: 1955 | E73: combustible para la planta | F73: 218600 | G73: VS/LIB | H73: 2013 | I73: 218600 | T73: =SUM(I73:S73) -> 218600
A74: SERVIMER DOMINICANA, S.R.L | B74: 41580 | C74: 1126 | D74: A0100100115500001230 | E74: Compra de utliles medico | F74: 111270 | G74: VS/LIB | H74: 2013 | I74: 111270 | T74: =SUM(I74:S74) -> 111270
A75: SERVIMER DOMINICANA, S.R.L | B75: 41585 | C75: 1127 | D75: A0100100115500001231 | E75: Compra de medicamentos utliles medico | F75: 71675 | G75: VS/LIB | H75: 2013 | I75: 71675 | T75: =SUM(I75:S75) -> 71675
A76: SERVIMER DOMINICANA, S.R.L | B76: 41586 | C76: 1128 | D76: A0100100115500001232 | E76: Compra de utliles medico | F76: 58400 | G76: VS/LIB | H76: 2013 | I76: 58400 | T76: =SUM(I76:S76) -> 58400
A77: UNICOMER | B77: 41589 | C77: 3037 | D77: 38124 | E77: Compra de nevera ejecutiva | F77: 15800 | G77: VS/LIB | H77: 2013 | I77: 15800 | T77: =SUM(I77:S77) -> 15800
A78: SANCHEZ Y MANCEBO, S. A. | B78: 41590 | C78: 2968 | D78: 1966 | E78: Compra de combustible para la caldera | F78: 324500 | G78: VS/LIB | H78: 2013 | I78: 324500 | T78: =SUM(I78:S78) -> 324500
A79: SERVIMER DOMINICANA, S.R.L | B79: 41590 | C79: 1129 | D79: A0100100115500001233 | E79: Compra de medicamentos utliles medico | F79: 33025 | G79: VS/LIB | H79: 2013 | I79: 33025 | T79: =SUM(I79:S79) -> 33025
A80: SERVIMER DOMINICANA, S.R.L | B80: 41594 | C80: 1130 | D80: A0100100115500001234 | E80: Compra de medicamentos utliles medico | F80: 143700 | G80: VS/LIB | H80: 2013 | I80: 143700 | T80: =SUM(I80:S80) -> 143700
A81: SIGMA FARMA SRL | B81: 41597 | C81: 3474 | D81: 4 | E81: compras de medicamento y ultil medico | F81: 272080 | G81: VS/LIB | H81: 2013 | I81: 272080 | T81: =SUM(I81:S81) -> 272080
A82: SIGMA FARMA SRL | B82: 41599 | C82: 3075 | D82: 3 | E82: compras de medicamento y ultil medico | F82: 230692 | G82: VS/LIB | H82: 2013 | I82: 230692 | T82: =SUM(I82:S82) -> 230692
A83: SIGMA FARMA SRL | B83: 41604 | C83: 3384 | D83: 5 | E83: compras de medicamento y ultil medico | F83: 267120 | G83: VS/LIB | H83: 2013 | I83: 267120 | T83: =SUM(I83:S83) -> 267120
A84: SANCHEZ Y MANCEBO, S. A. | B84: 41607 | C84: 3020 | D84: 1974 | E84: Compra de combustible para la caldera | F84: 326150 | G84: VS/LIB | H84: 2013 | I84: 326150 | T84: =SUM(I84:S84) -> 326150
A85: SANCHEZ Y MANCEBO, S. A. | B85: 41608 | C85: 3219 | D85: 1976 | E85: tickest combustible | F85: 50432.8 | G85: VS/LIB | H85: 2013 | I85: 50432.8 | T85: =SUM(I85:S85) -> 50432.8
A86: SIGMA FARMA SRL | B86: 41614 | C86: 3392 | D86: 7 | E86: Compra de sueros | F86: 144000 | G86: VS/LIB | H86: 2013 | I86: 144000 | T86: =SUM(I86:S86) -> 144000
A87: ASK CONSULTING GROUP SRL | B87: 41619 | C87: 3346 | D87: 485 | E87: Compra de vasos, cucharas, utiles de limpieza | F87: 94636 | G87: VS/LIB | H87: 2013 | I87: 94636 | T87: =SUM(I87:S87) -> 94636
A88: SIGMA FARMA SRL | B88: 41620 | C88: 3394 | D88: 10 | E88: Compra de sueros | F88: 162000 | G88: VS/LIB | H88: 2013 | I88: 162000 | T88: =SUM(I88:S88) -> 162000
A89: SERVIMER DOMINICANA, S.R.L | B89: 41621 | C89: 3387 | D89: A0100100115500001240 | E89: Compra de sedapore | F89: 28000 | G89: VS/LIB | H89: 2013 | I89: 28000 | T89: =SUM(I89:S89) -> 28000
A90: SIGMA FARMA SRL | B90: 41625 | C90: 3841 | D90: 13 | E90: Compra de gentamicina | F90: 33000 | G90: VS/LIB | H90: 2013 | I90: 33000 | T90: =SUM(I90:S90) -> 33000
A91: SERVIMER DOMINICANA, S.R.L | B91: 41626 | C91: 1229 | D91: A0100100115500001235 | E91: Compra de medicamentos utliles medico | F91: 98545 | G91: VS/LIB | H91: 2013 | I91: 98545 | T91: =SUM(I91:S91) -> 98545
A92: SERVIMER DOMINICANA, S.R.L | B92: 41628 | C92: 1238 | D92: A0100100115500001236 | E92: Compra de utliles medico | F92: 36500 | G92: VS/LIB | H92: 2013 | I92: 36500 | T92: =SUM(I92:S92) -> 36500
A93: CAASD | B93: 41639 | D93: 69586948 / 71682071 | E93: SERVICIOS DE AGUA | F93: 364128 | G93: VS/LIB | H93: 2013 | I93: 364128 | T93: =SUM(I93:S93) -> 364128
A94: ASK CONSULTING GROUP SRL | B94: 41641 | C94: 4063 | D94: 568 | E94: Compra de vasos y cucharas | F94: 29909.46 | G94: VS/LIB | H94: 2014 | I94: 29909.46 | T94: =SUM(I94:S94) -> 29909.46
A95: FEDERICO JOSE LLUBERES | B95: 41671 | C95: S/ORD | E95: Serv. De diseño y ejecucion de areas de ventil | F95: 225000 | G95: VS/LIB | H95: 2014 | I95: 225000 | T95: =SUM(I95:S95) -> 225000
A96: DAIKUI COMERCIAL | B96: 41684 | C96: 3658 | D96: 3373 | E96: compra de medicamentos | F96: 21670 | G96: VS/LIB | H96: 2014 | I96: 21670 | T96: =SUM(I96:S96) -> 21670
A97: DAIKUI COMERCIAL | B97: 41696 | C97: 4484 | D97: 3411 | E97: compra de medicamentos | F97: 5920 | G97: VS/LIB | H97: 2014 | I97: 5920 | T97: =SUM(I97:S97) -> 5920
A98: AGAFARMED EIRL | B98: 41732 | C98: 4109 | D98: 1041 | E98: Compra de agua bacterodine,ect | F98: 62650 | G98: VS/LIB | H98: 2014 | I98: 62650 | T98: =SUM(I98:S98) -> 62650
A99: AGAFARMED EIRL | B99: 41733 | C99: 4112 | D99: 1043 | E99: Compra de ranitidina | F99: 38000 | G99: VS/LIB | H99: 2014 | I99: 38000 | T99: =SUM(I99:S99) -> 38000
A100: MELOJALLOT MEDICAL | B100: 41740 | C100: 3287 | D100: 17943 | E100: Canula nasal | F100: 113280 | G100: VS/LIB | H100: 2014 | I100: 113280 | T100: =SUM(I100:S100) -> 113280
A101: MELOJALLOT MEDICAL | B101: 41745 | C101: 3286 | D101: 17958 | E101: Circuito de ventilacion neonatal | F101: 87025 | G101: VS/LIB | H101: 2014 | I101: 87025 | T101: =SUM(I101:S101) -> 87025
A102: MELOJALLOT MEDICAL | B102: 41760 | C102: 4483 | D102: 18046 | E102: compra de med.y util | F102: 276324.6 | G102: VS/LIB | H102: 2014 | I102: 276324.6 | T102: =SUM(I102:S102) -> 276324.6
A103: MELOJALLOT MEDICAL | B103: 41787 | C103: 4421 | D103: 18047 | E103: Compra de suero Latato de ringer | F103: 82656 | G103: VS/LIB | H103: 2014 | I103: 82656 | T103: =SUM(I103:S103) -> 82656
A104: MELOJALLOT MEDICAL | B104: 41789 | C104: 3315 | D104: 18056 | E104: Compra de suero Latato de ringer | F104: 103320 | G104: VS/LIB | H104: 2014 | I104: 103320 | T104: =SUM(I104:S104) -> 103320
A105: MELOJALLOT MEDICAL | B105: 41789 | C105: 4658 | D105: 18055 | E105: Compra de suero Latato de ringer | F105: 107065.4 | G105: VS/LIB | H105: 2014 | I105: 107065.4 | T105: =SUM(I105:S105) -> 107065.4
A106: MELOJALLOT MEDICAL | B106: 41789 | C106: 3316 | D106: 18057 | E106: Compra de suero Latato de ringer | F106: 95448 | G106: VS/LIB | H106: 2014 | I106: 95448 | T106: =SUM(I106:S106) -> 95448
A107: TINTAS GL | B107: 41792 | C107: 4601 | D107: 455 | E107: compra de cartuchos | F107: 99179 | G107: VS/LIB | H107: 2014 | I107: 99179 | T107: =SUM(I107:S107) -> 99179
... A115: INSERT OFFICE | B115: 41991 | C115: 49648 | D115: 289 | E115: compras de toner | F115: 8673 | G115: VS/LIB | H115: 2014 | I115: 8673 | T115: =SUM(I115:S115) -> 8673
A116: CAASD | B116: 42004 | D116: 71859001 / 7379727 | E116: SERVICIOS DE AGUA | F116: 364128 | G116: VS/LIB | H116: 2014 | I116: 364128 | T116: =SUM(I116:S116) -> 364128
A117: UBALDO SUPLY | B117: 42007 | C117: 50202 | D117: 1176 | E117: Compra de materiales desechables | F117: 187804 | G117: VS/LIB | H117: 2015 | I117: 187804 | T117: =SUM(I117:S117) -> 187804
A118: HIGIENE SUPLY SRL | B118: 42017 | C118: 2370 | D118: 13455 | E118: Compra de utiles de limpieza p/ la cocina | F118: 12401.94 | G118: VS/LIB | H118: 2015 | I118: 12401.94 | T118: =SUM(I118:S118) -> 12401.94
...

Sheet Hoja3
A1: Cod.Ref CCP Cuenta | B1: Devengado Aprobado | C1: Pagado Aprobado
A2: 2.1.1 | B2: 686003.26 | C2: 0
A3: 2.1.1 | B3: 47719055 | C3: 0
A4: 2.1.1 | B4: 47302104 | C4: 0
A5: 2.1.1 | B5: 686003.26 | C5: 0
A6: 2.1.1 | B6: 732074.29 | C6: 0
A7: 2.1.1 | B7: 47352666 | C7: 0
A8: 2.1.1 | B8: 732074.29 | C8: 0
A9: 2.1.1 | B9: 47416677 | C9: 0
A10: 2.1.1 | B10: 69663.1 | C10: 0
A11: 2.1.1 | B11: 732074.29 | C11: 0
A12: 2.1.1 | B12: 47606610 | C12: 0
A13: 2.1.1 | B13: 757074.29 | C13: 0
... A19: 2.1.1 | B19: 55000 | C19: 0
A20: Total 2.1.1 | B20: =SUBTOTAL(9,B2:B19) -> 2.9034566e+08
A21: 2.1.2 | B21: 2561925.4 | C21: 0
A22: 2.1.2 | B22: 396000 | C22: 0
A23: 2.1.2 | B23: 10717.4 | C23: 0
A24: 2.1.2 | B24: 64304.4 | C24: 0
A25: 2.1.2 | B25: 2451566.7 | C25: 0
A26: 2.1.2 | B26: 288600 | C26: 0
A27: 2.1.2 | B27: 10717.4 | C27: 0
A28: 2.1.2 | B28: 64304.4 | C28: 0
A29: 2.1.2 | B29: 2431233.3 | C29: 0
A30: 2.1.2 | B30: 283200 | C30: 0
A31: 2.1.2 | B31: 10717.4 | C31: 0
A32: 2.1.2 | B32: 58945.7 | C32: 0
... A44: 2.1.2 | B44: 58945.7 | C44: 0
A45: Total 2.1.2 | B45: =SUBTOTAL(9,B21:B44) -> 16891313
A46: 2.1.5 | B46: 48637.63 | C46: 0
A47: 2.1.5 | B47: 48706.23 | C47: 0
A48: 2.1.5 | B48: 8109.74 | C48: 0
A49: 2.1.5 | B49: 3383280 | C49: 0
A50: 2.1.5 | B50: 3388052.4 | C50: 0
A51: 2.1.5 | B51: 571427.64 | C51: 0
A52: 2.1.5 | B52: 3353718.2 | C52: 0
A53: 2.1.5 | B53: 3358448.8 | C53: 0
A54: 2.1.5 | B54: 566517.83 | C54: 0
A55: 2.1.5 | B55: 48637.63 | C55: 0
A56: 2.1.5 | B56: 48706.23 | C56: 0
A57: 2.1.5 | B57: 8140.96 | C57: 0
... A87: 2.1.5 | B87: 600 | C87: 0
A88: Total 2.1.5 | B88: =SUBTOTAL(9,B46:B87) -> 44582254
A89: 2.2.4 | B89: 34791.84 | C89: 0
A90: 2.2.4 | B90: 202624.15 | C90: 0
A91: 2.2.4 | B91: 74665.21 | C91: 0
A92: Total 2.2.4 | B92: =SUBTOTAL(9,B89:B91) -> 312081.2
A93: 2.2.5 | B93: 16089.95 | C93: 0
A94: 2.2.5 | B94: 16089.95 | C94: 0
A95: Total 2.2.5 | B95: =SUBTOTAL(9,B93:B94) -> 32179.9
A96: 2.2.7 | B96: 413472 | C96: 0
A97: 2.2.7 | B97: 868608 | C97: 0
A98: 2.2.7 | B98: 41300 | C98: 0
A99: 2.2.7 | B99: 834043 | C99: 0
A100: 2.2.7 | B100: 970224 | C100: 0
A101: 2.2.7 | B101: 1180000 | C101: 0
A102: 2.2.7 | B102: 33630 | C102: 0
A103: 2.2.7 | B103: 834043 | C103: 0
A104: 2.2.7 | B104: -834043 | C104: 0
A105: 2.2.7 | B105: 106766.4 | C105: 0
A106: 2.2.7 | B106: -106766.4 | C106: 0
A107: 2.2.7 | B107: 38444.4 | C107: 0
A108: 2.2.7 | B108: 106766.4 | C108: 0
A109: Total 2.2.7 | B109: =SUBTOTAL(9,B96:B108) -> 4486487.8
A110: 2.2.8 | B110: 36439.7 | C110: 0
A111: Total 2.2.8 | B111: =SUBTOTAL(9,B110:B110) -> 36439.7
A112: 2.2.9 | B112: 501087 | C112: 0
A113: 2.2.9 | B113: -501087 | C113: 0
A114: 2.2.9 | B114: 21063 | C114: 0
A115: 2.2.9 | B115: 35105 | C115: 0
A116: 2.2.9 | B116: -35105 | C116: 0
A117: 2.2.9 | B117: 105315 | C117: 0
A118: 2.2.9 | B118: 35105 | C118: 0
A119: 2.2.9 | B119: 220483.05 | C119: 0
A120: Total 2.2.9 | B120: =SUBTOTAL(9,B112:B119) -> 381966.05
A121: 2.3.1 | B121: 337500 | C121: 0
A122: 2.3.1 | B122: -337500 | C122: 0
A123: 2.3.1 | B123: 929768 | C123: 0
A124: 2.3.1 | B124: -929768 | C124: 0
A125: 2.3.1 | B125: 1253100 | C125: 0
A126: 2.3.1 | B126: -1253100 | C126: 0
A127: 2.3.1 | B127: 791125 | C127: 0
A128: 2.3.1 | B128: -791125 | C128: 0
A129: 2.3.1 | B129: 929768 | C129: 0
A130: 2.3.1 | B130: 337500 | C130: 0
A131: 2.3.1 | B131: 791125 | C131: 0
A132: 2.3.1 | B132: 1253100 | C132: 0
... A178: 2.3.1 | B178: 193945 | C178: 0
A179: Total 2.3.1 | B179: =SUBTOTAL(9,B121:B178) -> 12256005
A180: 2.3.2 | B180: 122460.17 | C180: 0
A181: 2.3.2 | B181: 518019.87 | C181: 0
A182: Total 2.3.2 | B182: =SUBTOTAL(9,B180:B181) -> 640480.04
A183: 2.3.3 | B183: 627.17 | C183: 0
A184: 2.3.3 | B184: 429225 | C184: 0
A185: 2.3.3 | B185: 518019.87 | C185: 0
A186: 2.3.3 | B186: -518019.87 | C186: 0
A187: 2.3.3 | B187: 435632.4 | C187: 0
A188: 2.3.3 | B188: 23364 | C188: 0
A189: 2.3.3 | B189: 19470 | C189: 0
A190: 2.3.3 | B190: 11552.2 | C190: 0
...

Sheet CONCILIACION 1
A6: Hospital Materno Infantil San Lorenzo de Los Mina
A7: Conciliación Bancaria al 30 de septiembre 2023
A10: Banco: | B10: BANRESERVAS | E10: CUENTA: Cta. 960-454417-5
G12: LIBRO
A13: BALANCE EN INICIAL AL 1ERO DEL MES SEPTIEMBRE 2023 | G13: 282.63
A14: MAS:
G15: 0
A16: Transferencia reintegradas | G16: =+[5]Hoja4!D7 -> 0
A17: Deposito | G17: =+'[5]TRANSFERENCIA RECIBIDAS'!B10 -> 3999142.4
A18: Nota de Credito
G19: =+G13+G15+G18+G17+G16 -> 3999425
A20: MENOS:
A21: Cheques Emitidos | G21: =+'[5]CHEQUES EMITIDO '!D14 -> 0
A22: Nominas | G22: =+'[5]NOMINA '!D9 -> 0
A23: Cargos Bancarios | G23: =+[5]comisiones!E33 -> 6277.04
A24: Transferencia | G24: =+[5]TRANSFERENCIAS!D18 -> 3992925
A25: Nota de Debito
A26: Total de Debitos | G26: =SUM(G21:G25) -> 3999202
A27: TOTAL CONCILIADO | G27: =G19-G26 -> 222.96
G30: BANCO
A31: BALANCE EN BANCO | G31: 222.96
A32: MAS:
A33: Depósitos en tránsito
A35: TOTAL DISPONIBLE | G35: =SUM(G31:G34) -> 222.96
A37: MENOS:
A38: Transferencia | G38: 0
A39: Cheques en transito | G39: 0
G40: =SUM(G38:G39) -> 0
A42: TOTAL CONCILIADO | G42: =G35+G40 -> 222.96
A47: Preparado por: | D47: Licda. Milagros Martinez de la Rosa
D48: Contadora
A54: Aprobado Por | D54: Licdo Eugenio Rosario Rosario
D55: Director Administrativo y Financiero

Sheet CONCILIACION 2
A6: Hospital Materno Infantil San Lorenzo de Los Mina
A7: Conciliación Bancaria al 30 de septiembre 2023
A10: Banco: | B10: BANRESERVAS | E10: CUENTA: 010-390450-6
G12: LIBRO
A13: BALANCE EN INICIAL AL 1ERO DEL MES DE SEPTIEMBRE 2023 | G13: 5933085.8
A14: MAS:
G15: 0
A16: Transferencia en transito
A17: Deposito | G17: =+'[6]TRANSFERENCIA RECIBIDAS'!B10 -> 2725910.9
A18: Reintegro | G18: 2218.24
G19: =+G13+G15+G18+G17+G16 -> 8661215
A20: MENOS:
A21: Cheques Emitidos | G21: =+'[6]CHEQUES EMITIDO '!D21 -> 306137.17
A22: Nominas | G22: =+'[6]NOMINA '!D9 -> 0
A23: Cargos Bancarios | G23: =+[6]comisiones!E40 -> 8256.51
A24: Transferencia | G24: =+[6]TRANSFERENCIAS!D45 -> 5509767.3
A25: Nota de Debito | G25: 180
A26: Total de Debitos | G26: =SUM(G21:G25) -> 5824341
A28: TOTAL CONCILIADO | G28: =+G19-G26 -> 2836874
G31: BANCO
A32: BALANCE EN BANCO | G32: 4499680.5
A33: MAS:
A34: Depósitos en tránsito | G34: 0
A36: TOTAL DISPONIBLE | G36: =SUM(G32:G35) -> 4499680.5
A38: MENOS:
A39: Transferencia | G39: =-'[6]TRANSF EN TRANSITO'!D22 -> -1563969.8
A40: Cheques en transito | G40: =-'[6]CHEQUES EN TRAN'!D10 -> -98836.61
G41: =SUM(G39:G40) -> -1662806.5
A43: TOTAL CONCILIADO | G43: =G36+G41 -> 2836874 | H43: =+G43-G28 -> 0
A48: Preparado por: | D48: Licda. Milagros Martinez de la Rosa
D49: Contadora
A55: Aprobado Por | D55: Licdo Eugenio Rosario Rosario
D56: Director Administrativo y Financiero

Sheet Hoja2
A6: Hospital Materno Infantil San Lorenzo de Los Mina
A7: Conciliación Bancaria al30 de abril 2023
A10: Banco: | B10: BANRESERVAS | E10: CUENTA: Cta. 960-454417-5
G12: LIBRO
A13: BALANCE EN INICIAL AL 1ERO DEL MES DE MARZO 2023 | G13: 0
A14: MAS:
G15: 0
A16: Transferencia reintegradas | G16: =+[7]Hoja4!D7 -> 0
A17: Deposito | G17: =+'[7]TRANSFERENCIA RECIBIDAS'!B10 -> 3999803.8
A18: Nota de Credito
G19: =+G13+G15+G18+G17+G16 -> 3999803.8
A20: MENOS:
A21: Cheques Emitidos | G21: =+'[7]CHEQUES EMITIDO '!D14 -> 0
A22: Nominas | G22: =+'[7]NOMINA '!D9 -> 0
A23: Cargos Bancarios | G23: =+[7]comisiones!E40 -> 6696.3
A24: Transferencia | G24: =+[7]TRANSFERENCIAS!D20 -> 3993107.4
A25: Nota de Debito
A26: Total de Debitos | G26: =SUM(G21:G25) -> 3999803.7
A27: TOTAL CONCILIADO | G27: =G19-G26 -> 0
G30: BANCO
A31: BALANCE EN BANCO | G31: 0
A32: MAS:
A33: Depósitos en tránsito
A35: TOTAL DISPONIBLE | G35: =SUM(G31:G34) -> 0
A37: MENOS:
A38: Transferencia | G38: 0
A39: Cheques en transito | G39: 0
G40: =SUM(G38:G39) -> 0
A42: TOTAL CONCILIADO | G42: =G35+G40 -> 0
A47: Preparado por: | D47: Licda. Milagros Martinez de la Rosa
D48: Contadora
A54: Aprobado Por | D54: Licdo Eugenio Rosario Rosario
D55: Director Administrativo y Financiero

Sheet CONCILIACION 1 31-12-2022
A6: Hospital Materno Infantil San Lorenzo de Los Mina
A7: Conciliación Bancaria al 31 de diciembre 2022
A10: Banco: | B10: BANRESERVAS | E10: CUENTA: 960-454417-5
G12: LIBRO
A13: BALANCE EN INICIAL AL 1ERO DEL MES DE DICIEMBRE 2022 | G13: 1378.41
A14: MAS:
A15: Reintegro CB | G15: 0
A16: Reintegro de Transferencias 1614 | G16: 0
A17: Deposito | G17: =+'[8]DEPOSITOS '!B10 -> 7793823.3
A18: Nota de Credito
G19: =+G13+G15+G17+G18+G16 -> 7795201.7
A20: MENOS:
A21: Cheques Emitidos | G21: =-'[8]CHEQUES EMITIDOS'!D10 -> -40000
A22: Nominas | G22: =-[8]NOMINAS!D10 -> 0
A23: Cargos Bancarios | G23: =-'[8]CARGOS BANCARIOS '!H61 -> -12102.28
A24: Transferencia | G24: =-'[8]TRANSF. '!D26 -> -7742978.2
A25: Nota de Debito
A26: Total de Debitos | G26: =SUM(G21:G25) -> -7795080.5
A27: TOTAL CONCILIADO | G27: =+G19+G26 -> 121.25
G30: BANCO
A31: BALANCE EN BANCO | G31: 121.25
A32: MAS:
A33: Depósitos en tránsito
A35: TOTAL DISPONIBLE | G35: =SUM(G31:G34) -> 121.25
A37: MENOS:
A38: Transferencia | G38: =-'[8]TRANSFERENCIAS EN TRANSITO'!D11 -> 0
A39: Cheques en transito | G39: 0
G40: 0
A42: TOTAL CONCILIADO | G42: =+G35+G40 -> 121.25
G44: =+G42-G27 -> 0

Sheet CONCILIACION 31-01-2023
A6: Hospital Materno Infantil San Lorenzo de Los Mina
A7: Conciliación Bancaria al 31 de enero 2023
A10: Banco: | B10: BANRESERVAS | E10: CUENTA: 010-390450-6
G12: LIBRO
A13: BALANCE EN INICIAL AL 1ERO DEL MES DE ENERO 2023 | G13: 1948473.9
A14: MAS:
A15: Reintegro ck 36940 | G15: 0
A16: Transferencia reintegradas | G16: 0
A17: Deposito | G17: =+'[9]TRANSFERENCIA RECIBIDAS'!B10 -> 9990515.7
A18: Nota de Credito
G19: =+G13+G15+G18+G17+G16 -> 11938990
A20: MENOS:
A21: Cheques Emitidos | G21: =+'[9]CHEQUES EMITIDO '!D10 -> 27800
A22: Nominas | G22: =+'[9]NOMINA '!D9 -> 58248.03
A23: Cargos Bancarios | G23: =+[9]comisiones!E40 -> 6414.01
A24: Transferencia | G24: =+[9]TRANSFERENCIAS!D27 -> 3312419.5
A25: Nota de Debito
A26: Total de Debitos | G26: =SUM(G21:G25) -> 3404881.5
A27: TOTAL CONCILIADO | G27: =G19-G26 -> 8534108.1
G30: BANCO
A31: BALANCE EN BANCO | G31: 8536326.3
A32: MAS:
A33: Depósitos en tránsito
A35: TOTAL DISPONIBLE | G35: =SUM(G31:G34) -> 8536326.3
A37: MENOS:
A38: Transferencia | G38: =-'[9]TRANSF EN TRANSITO'!D8 -> -2218.24
A39: Cheques en transito | G39: =-'[9]CK EN TRANSITO'!D12 -> 0
G40: =SUM(G38:G39) -> -2218.24
A42: TOTAL CONCILIADO | G42: =G35+G40 -> 8534108.1
A47: Preparado por: | D47: Licda. Milagros Martinez de la Rosa
D48: Analista Financiera
A52: Aprobado Por | D52: Licdo Eugenio Rosario Rosario
D53: Director Administrativo y Financiero

Sheet Hoja1
A2: Dirección de Control y Fiscalización
A3: Hospital Materno Infantil San Lorenzo de Los Mina
A4: Region Santo Domingo Este
A5: (Valore expresados en RD$)
A6: CUENTAS POR PAGAR AL 31/08/2022 DE AGOSTO 2022 (POR SUPLIDORES)
A7: # | B7: Suplidor | C7: Monto Deuda | D7: Acumulado 2015 | E7: 2016 | F7: 2017 | G7: 2018 | H7: 2019 | I7: 2020 | J7: 2021 | K7: 2022
A8: 1 | B8: A & S IMPORTADORA MEDICAS | C8: =SUM(D8:K8) -> 1508114.2 | E8: 0 | F8: 0 | K8: =28658+360070+137820+178475-28658+171620+160716+499413.17 -> 1508114.2
A9: =+A8+1 -> 2 | B9: ACTUALIDADES VD SRL | C9: =SUM(D9:K9) -> 267805.07 | J9: =+'[10]ENERO REB'!E257 -> 267805.07
A10: =+A9+1 -> 3 | B10: ADALBERTO RAFEL SEVERINO RONDON | C10: =SUM(D10:K10) -> 0
A11: =+A10+1 -> 4 | B11: ADLER AMICIS VALDEZ MARMOLEJOS | C11: =SUM(D11:K11) -> 961403 | G11: =107852+382261+182605-107852+241310+330518-182605-182605-8968-199656+265500-562860-265500 -> 0 | K11: =252992+1135691-300000+122720-250000 -> 961403
A12: =+A11+1 -> 5 | B12: AGAFARMED EIRL | C12: =SUM(D12:K12) -> 100650 | D12: =100650 -> 100650
A13: =+A12+1 -> 6 | B13: AIR LIQUIDE DOMINICANA, S. A. S. | C13: =SUM(D13:K13) -> 4156965.9 | E13: 0 | G13: 0 | K13: =2609720.48+61999.42+37434.54+19107.11+37434.54+44451.66+38214.22+19886.79+56541.66+73309.73+38214.22+41332.94+40217.68+40217.68+38214.22-2783.14-853280.01-1306582.7+58100.35+25207.86+72132.7+50391.45+41292.35+44931.99+46751.81+44931.99+48571.63+86224.35+64668.26+44931.99+68307.9+45+45841.9+74869.09+44931.99-44956.98+94413.53+68307.9+45841.9+66488.08+10+105960.61+44931.99-10+52211.27+44931.99+67397.99+22465.99+48571.63+41292.35+49481.54+45841.9+43112.17+69566.5+44931.99+46751.81+46751.81+45841.9+69217.81+44022.08+43112.17+45841.9+67397.99+49481.54+107388.67+65578.17+44022.08+64668.26+70127.72+41292.35+61938.53+44931.99+46751.81+88954.08+109599.05+38937.72+44022.08+63758.35 -> 4156965.9
A14: =+A13+1 -> 7 | B14: ALOHA IMPUTS DISTRIBUTION
A15: =+A14+1 -> 8 | B15: ALTAGRACIAS PHARMA SRL | C15: =SUM(D15:K15) -> 795105.3 | J15: =583026.3-335785 -> 247241.3 | K15: =1693206.8-760386.8-477220+92264 -> 547864
A16: =+A15+1 -> 9 | B16: ALGEBRA PRODUTION SRL
A17: =+A16+1 -> 10 | B17: AMARAM ENTERPRISE, ERL | C17: =SUM(D17:K17) -> 477851.68 | J17: =477851.68 -> 477851.68
A18: =+A17+1 -> 11 | B18: ANEST | E18: 0 | F18: 0 | G18: =17500+165800+52000-165800-69500 -> 0
A19: =+A18+1 -> 12 | B19: ASK CONSULTING GROUP SRL | C19: =SUM(D19:K19) -> 124545.46 | D19: =124545.46 -> 124545.46
A20: =+A19+1 -> 13 | B20: AYUNTAMIENTO STO DGO ESTE | E20: =3195-3195 -> 0 | F20: 0
A21: =+A20+1 -> 14 | B21: BELLO LAB SRL | C21: =SUM(D21:K21) -> 3349020.3 | E21: 0 | F21: 0 | G21: =1647950.84+324617-154787.76+103444-277396.58+33400+103333.2-271569.4-212551.2+247911.9-247911.9-247911.9-322504-264674-324617-136733.2 -> 0 | I21: =104960-104960 -> 0 | K21: =1609038.96+475587.44+42442+409357.16-250000+119840.06-42442+83352.8-289103.88+375920.76-350258.91+565432.7+18141.09+140666.52+441045.62 -> 3349020.3
A22: =+A21+1 -> 15 | B22: BIO-NUCLEAR SA | C22: =SUM(D22:K22) -> 1445542.4 | E22: =1272206.09-196939.6+9616.64-250625.44-12885.6-411805.99-47080.15-362485.95 -> 0 | F22: 0 | K22: =1445542.43 -> 1445542.4
A23: =+A22+1 -> 16 | B23: BIOVERDOLAGA, LAB DOMINICANO, SRL | C23: =SUM(D23:K23) -> 85779.98 | K23: 85779.98
A24: =+A23+1 -> 17 | B24: BIO-WIN, S.A | C24: =SUM(D24:K24) -> 7700 | E24: =4480+560+560-5600 -> 0 | F24: 0 | K24: =6950-4200+1650+1650+1650 -> 7700
A25: =+A24+1 -> 18 | B25: BRONTILLO | C25: =SUM(D25:K25) -> 1076350 | J25: =1430350+345000-345000-391800 -> 1038550 | K25: =644800-607000 -> 37800
A26: =+A25+1 -> 19 | B26: C&C SALUD | C26: =SUM(D26:K26) -> 55460 | D26: =55460 -> 55460
A27: =+A26+1 -> 20 | B27: CAASD | C27: =SUM(D27:K27) -> 5234933 | D27: 3557427 | E27: =342228 -> 342228 | F27: =153204 -> 153204 | G27: 216122 | H27: 836352 | K27: =43200+43200-43200+43200+43200-43200+43200 -> 129600
A28: =+A27+1 -> 21 | B28: CALPEQ COMERCIAL | C28: =SUM(D28:K28) -> 370978.43 | J28: =+'[10]ENERO REB'!E442 -> 370978.43
A29: =+A28+1 -> 22 | B29: CLAPE, S.R.L | C29: =SUM(D29:K29) -> 508344 | J29: =926386.14-250000-168042.14 -> 508344 | K29: =495733.4-495733.4 -> 0
A30: =+A29+1 -> 23 | B30: CARIBEAN MEDIA | C30: =SUM(D30:K30) -> 405692.26 | G30: =244497.18 -> 244497.18 | H30: =161194.52+0.56 -> 161195.08
A31: =+A30+1 -> 24 | B31: CEMEDI | C31: =SUM(D31:K31) -> 11300 | E31: 0 | F31: =2300-2300 -> 0 | G31: =39900+4900+2600+5200+4500-42500-4500-10100 -> 0 | K31: =9800+4100-9800+7200 -> 11300
A32: =+A31+1 -> 25 | B32: CASIMIRO MORETA | C32: =SUM(D32:K32) -> 60905.7 | K32: =60905.7 -> 60905.7
A33: =+A32+1 -> 26 | B33: CENTRO DE DIALISIS MOVIL GONZALEZ GONZALEZ | C33: =SUM(D33:K33) -> 265000 | J33: =135000-105000 -> 30000 | K33: =235000 -> 235000
A34: =+A33+1 -> 27 | B34: CENTRO DE LA SANGRE Y ESPECIALIDADES | C34: =SUM(D34:K34) -> 97500 | F34: =4500-4500 -> 0 | G34: =14100+60400+9000-4500+4499.15-4499.15-74500+130000-130000-4500 -> 0 | I34: =178000+25000+45000-500-178000+8500-69500+5500-14000 -> 0 | K34: =40000+41500+16000 -> 97500
A35: =+A34+1 -> 28 | B35: CIENCIAS TECNOLOGIA Y CONSULTAS (CIENTEC) | C35: =SUM(D35:K35) -> 1353393.7 | E35: 0 | I35: =590527-590527 -> 0 | K35: =1353393.69 -> 1353393.7
A36: =+A35+1 -> 29 | B36: CIRCUIMED, SRL | C36: =SUM(D36:K36) -> 63720 | K36: =63720 -> 63720
A37: =+A36+1 -> 30 | B37: COMEDORES ECONOMICOS | C37: =SUM(D37:K37) -> 128250 | F37: =128250 -> 128250
A38: =+A37+1 -> 31 | B38: COMERCIALIZADORA DE ALIMENTOS PIÑARIAS, SRL | C38: =SUM(D38:K38) -> 2547150 | K38: =367250+605750+494000+2500+555500-367250+349200+617975-300000-194000+416225 -> 2547150
A39: =+A38+1 -> 32 | B39: CONSORCIO TOOLS & RESOURCES- ECOCISA | C39: =SUM(D39:K39) -> 52864 | K39: =52864 -> 52864
A40: =+A39+1 -> 33 | B40: CONSTRUTORA DE PROYECTOS SARIH, SRL | C40: =SUM(D40:K40) -> 191444.1 | J40: =+'[10]ENERO REB'!E506 -> 191444.1
A41: =+A40+1 -> 34 | B41: CORPORACION LEGIS, SRL | C41: =SUM(D41:K41) -> 483249 | J41: =483249 -> 483249
A42: =+A41+1 -> 35 | B42: COPEM HOSPICLINIC | C42: =D42+E42+F42+G42+H42+I42+J42+K42 -> 516844.3 | K42: =173520+173324.3+170000 -> 516844.3
A43: =+A42+1 -> 36 | B43: CRISTALIA | C43: =SUM(D43:K43) -> 0
A44: =+A43+1 -> 37 | B44: CRISTINA ROSARIO ROSARIO | C44: =SUM(D44:K44) -> 4262708.8 | E44: 0 | F44: =1489607-89540-177709-62500-89975-247000-377565-220806-224512 -> 0 | J44: =3231238.5-190000-200000 -> 2841238.5 | K44: =659320+368632+124337+0.6-300000+759280-852289.6+221825+440365.3 -> 1421470.3
A45: =+A44+1 -> 38 | B45: CUSTOMED DOMINICANA, SRL. | C45: =SUM(D45:K45) -> 62894 | H45: =62894 -> 62894
A46: =+A45+1 -> 39 | B46: DAIKUI COMERCIAL | C46: =SUM(D46:K46) -> 37115 | D46: =37115 -> 37115
A47: =+A46+1 -> 40 | B47: DANILO MATA ROSARIO(MAQUINOR) | C47: =SUM(D47:K47) -> 205628 | D47: =205628 -> 205628
A48: =+A47+1 -> 41 | B48: DENTAL COSMETIC DR. PONCEANO, SRL | C48: =SUM(D48:K48) -> 814960 | J48: =906840-250000 -> 656840 | K48: =158120 -> 158120
A49: =+A48+1 -> 42 | B49: DESECHEBLES FELIX & BRAVO | C49: =SUM(D49:K49) -> 384750.8 | J49: =674395.2-167442-213062.4 -> 293890.8 | K49: 90860
A50: =+A49+1 -> 43 | B50: DESIGN, S.R.L | C50: =D50+E50+F50+G50+H50+I50+J50+K50 -> 347461.4 | K50: =347461.4 -> 347461.4
A51: =+A50+1 -> 44 | B51: DELIA JOSEFINA TATIS PERDOMO | C51: =D51+E51+F51+G51+H51+I51+J51+K51 -> 0
A52: =+A51+1 -> 45 | B52: DIAMELAB, S.R.L | C52: =SUM(D52:K52) -> 363969.8 | J52: =+'[10]ENERO REB'!E589 -> 158092 | K52: 205877.8
A53: =+A52+1 -> 46 | B53: DISTRIBUTION SERVICES GROUP (DISEGO) | C53: =D53+E53+F53+H53+G53+I53+J53+K53 -> 133322.3 | K53: =26107.5+107214.8 -> 133322.3
A54: =+A53+1 -> 47 | B54: DIMERCA, S.R.L | C54: =SUM(D54:K54) -> 145262.1 | J54: =145262.1 -> 145262.1
A55: =+A54+1 -> 48 | B55: DIOLAT | C55: =SUM(D55:K55) -> 2735840 | J55: =2166480 -> 2166480 | K55: =769360-200000 -> 569360
A56: =+A55+1 -> 49 | B56: EME SOLUCIONES ELECTRICAS | C56: =D56+J56+K56 -> 1021746.4 | J56: =440705.01 -> 440705.01 | K56: =581041.44 -> 581041.44
A57: =+A56+1 -> 50 | B57: EPX DOMINICANA, SRL | C57: =SUM(D57:K57) -> 2141916.4 | J57: =2768066.4-386000-240150 -> 2141916.4 | K57: =500875-300000-200875 -> 0
A58: =+A57+1 -> 51 | B58: EXPRESS SERVICE CONSERG EXSERCON | C58: =SUM(D58:K58) -> 553500 | K58: =136000+142500+152500+122500 -> 553500
A59: =+A58+1 -> 52 | B59: FARACH ,S.A | C59: =SUM(D59:K59) -> 701376.64 | I59: =256296+247884+196092.4+36540+113723.6-196092.4+69300-36540-247884+375397-256296-183023.6+39375-375397+95000-134375 -> 0 | J59: =592241.34-160246.7-150000 -> 281994.64 | K59: =149400+161650+162955.6+77891.8+184457+173050+1140+72172-658462.6-77891.8+23020+150000 -> 419382
A60: =+A59+1 -> 53 | B60: FARMACIA EUROPA C POR A | C60: =SUM(D60:K60) -> 97399.3 | D60: =18194 -> 18194 | E60: =78322.9+890-7.6 -> 79205.3
A61: =+A60+1 -> 54 | B61: FARMACIA RUTH | C61: =SUM(D61:K61) -> 1014837.5 | F61: 0 | G61: =64467+259364-206081+34175-117750-0.05+39400+0.05-73575 -> 0 | H61: =165935-165935 -> 0 | J61: =883552.5-250640 -> 632912.5 | K61: =381925 -> 381925
A62: =+A61+1 -> 55 | B62: FARNASA,S.R.L. | C62: =SUM(D62:K62) -> 1497646.6 | E62: =391152.68-263712.8-127439.88 -> 0 | F62: 0 | G62: =453674.8+211860.8-90234.8-200000-163440-211860.8 -> 0 | J62: =980222.78-400000 -> 580222.78 | K62: =1448783.08-531359.3 -> 917423.78
A63: =+A62+1 -> 56 | B63: FEDERICO JOSE LLUBERES | C63: =SUM(D63:K63) -> 225000 | D63: =225000 -> 225000
A64: =+A63+1 -> 57 | B64: FRAVAX | C64: =SUM(D64:K64) -> 739412 | G64: =691500-84000-264000-272366.31-71133.69 -> 0 | J64: =889412-150000 -> 739412
A65: =+A64+1 -> 58 | B65: FRIFARMA, SRL | C65: =D65+E65+F65+G65+J65+K65 -> 601000 | K65: =95000+95000+321250+95000-190000+335500-321250-95000+121000+144500 -> 601000
A66: =+A65+1 -> 59 | B66: GASTABLES DEL CARIBE, S.R.L. | C66: =SUM(D66:K66) -> 144211.34 | K66: =342023+144211.34-342023 -> 144211.34
A67: =+A66+1 -> 60 | B67: GEFARCA INSDUTRIA FARMACEUTICA | C67: =SUM(D67:K67) -> 160570 | D67: =160570 -> 160570
A68: =+A67+1 -> 61 | B68: GLOBAL MULTI- PHARMA DOMINICA | C68: =SUM(D68:K68) -> 2561976 | K68: =496964+435000+440000+520300+917575+225575-435000-61964+61964+921862-520300-440000 -> 2561976
A69: =+A68+1 -> 62 | B69: GRUPO Z HEAL THCARE PRODUCTS | C69: =SUM(D69:K69) -> 1451198.4 | J69: =1948638.63-354083.92-247172.77-320252-389978.39 -> 637151.55 | K69: =140464.6+85045.84+383363.41+313863.48-225510.44+116820 -> 814046.89
A70: =+A69+1 -> 63 | B70: HAUSPITAL | C70: =SUM(D70:K70) -> 692323.2 | J70: =1193729.68-404250-539990.98 -> 249488.7 | K70: =435754.5+7080 -> 442834.5
A71: =+A70+1 -> 64 | B71: HIGIENE SUPLY SRL | C71: =SUM(D71:K71) -> 12401.94 | D71: =12401.94 -> 12401.94
A72: =+A71+1 -> 65 | B72: HOSPIFAR | C72: =SUM(D72:K72) -> 4091339.5 | E72: 0 | G72: =111393.24+36570.34+170146.94-111393.24+81576-100000-188293.28+8850+65720-7500+56533.74-123603.74 -> 0 | J72: =4326719.5-362383.37 -> 3964336.1 | K72: =127003.4 -> 127003.4
A73: =+A72+1 -> 66 | B73: HOSPIRED | C73: =SUM(D73:K73) -> 15540.13 | D73: =15540.13 -> 15540.13
A74: =+A73+1 -> 67 | B74: HOSPITECH | C74: =SUM(D74:K74) -> 1212959 | J74: =1212990-31 -> 1212959
A75: =+A74+1 -> 68 | B75: I.M.D. MEDIC-INTER,SRL | C75: =SUM(D75:K75) -> 98000 | E75: 0 | F75: 0 | G75: =220500+90000-130500+67500+54000-180000-67500-54000 -> 0 | I75: =135000-135000 -> 0 | K75: =98000 -> 98000
A76: =+A75+1 -> 69 | B76: IDEAL PRINT | C76: =SUM(D76:K76) -> 1970.6 | D76: =1970.6 -> 1970.6
A77: =+A76+1 -> 70 | B77: IG. M&R INSULAR GROUP | C77: =SUM(D77:K77) -> 1594446.9 | K77: =369506.61+620918.5+0.03+571726.71-243000+126506.61-253013.2-6000+707801.67-300000 -> 1594446.9
A78: =+A77+1 -> 71 | B78: INDUMICA, S.R.L. | C78: =SUM(D78:K78) -> 91405.65 | D78: =91405.65 -> 91405.65
A79: =+A78+1 -> 72 | B79: ING. JOSE ANTONIO SANCHEZ | C79: =SUM(D79:K79) -> 30680 | D79: =30680 -> 30680
A80: =+A79+1 -> 73 | B80: INGENERIA TECNOLOGIA Y SERVICIOS OROZCO | C80: =SUM(D80:K80) -> 620713.04 | K80: 620713.04
A81: =+A80+1 -> 74 | B81: INNOVACIONES MEDICAS DEL CARIBE | C81: =SUM(D81:K81) -> 642552.46 | K81: =642552.46 -> 642552.46
A82: =+A81+1 -> 75 | B82: INSERT OFFICE | C82: =SUM(D82:K82) -> 464317.18 | D82: =464317.18 -> 464317.18
A83: =+A82+1 -> 76 | B83: INVERSIONES DOS PUNTAS, S,R.L | C83: =SUM(D83:K83) -> 1467540 | G83: =118076.97+62327.6+118745.76+317174.56-180404.57-286000-149920.32 -> 0 | J83: =274691.02 -> 274691.02 | K83: =1192849.02 -> 1192849
A84: =+A83+1 -> 77 | B84: INVERSIONES TARAMACA | C84: =SUM(D84:K84) -> 47350 | E84: =49524+1596-51120 -> 0 | F84: 0 | G84: =74633+26635+27055+27460+23950-74633-81150-23950 -> 0 | K84: =17416+32176+21850-17416-32176+55730-21850+1300-21850+17900+13750-48930+2450+27000 -> 47350
A85: =+A84+1 -> 78 | B85: JEL SERVICES, S.R.L
A86: =+A85+1 -> 79 | B86: JENAMA COMPANY SRL | C86: =SUM(D86:K86) -> 84800.7 | K86: =84800.7 -> 84800.7
A87: =+A86+1 -> 80 | B87: JOB COMERCIAL | C87: =SUM(D87:K87) -> 321101.3 | J87: =321101.3 -> 321101.3
A88: =+A87+1 -> 81 | B88: JOCACE, S.A | C88: =D88+E88+F88+G88+H88+I88+J88+K88 -> 108990 | K88: =108990 -> 108990
A89: =+A88+1 -> 82 | B89: JONES FARMACEUTICA | C89: =SUM(D89:K89) -> 665952.4 | D89: =665952.4 -> 665952.4
A90: =+A89+1 -> 83 | B90: KELNET COMPUTER, SRL | C90: =SUM(D90:K90) -> 59295 | J90: =+'[10]ENERO REB'!E999 -> 0 | K90: =59295 -> 59295
A91: =+A90+1 -> 84 | B91: KILNES SOLUTIONS | C91: =SUM(D91:K91) -> 76400.28 | G91: =89731.92-89731.92 -> 0 | H91: =76400+0.28 -> 76400.28
A92: =+A91+1 -> 85 | B92: KUMAGY SRL | C92: =J92+K92 -> 1267913.2 | J92: =1267913.2 -> 1267913.2
A93: =+A92+1 -> 86 | B93: KYANRED SUPPLY, SRL | C93: =SUM(D93:K93) -> 964483 | H93: =582241.5 -> 582241.5 | I93: =582241.5-200000 -> 382241.5
A94: =+A93+1 -> 87 | B94: LAB. CLINICO LIC. PATRIA RIVAS | E94: =46832+618+6520.5-53970.5+6687+4030-10717 -> 0 | F94: 0 | G94: =2363.5-2363.5 -> 0
A95: =+A94+1 -> 88 | B95: LABORATORIO QUIMICO, J.A.F.S.A | C95: =SUM(D95:K95) -> 14960 | D95: 14960 | J95: 0
A96: =+A95+1 -> 89 | B96: LAMBDA DIAGNOSTICOS | C96: =SUM(D96:K96) -> 878689.07 | E96: 0 | H96: =46404.42-46404.42 -> 0 | J96: =382052.34-152609.79-229442.55 -> 0 | K96: =579386.72+220391.54+303963.66-250000-129245.9+154193.05 -> 878689.07
A97: =+A96+1 -> 90 | B97: LEFP CONSULTORES | C97: =SUM(D97:K97) -> 195408 | K97: =195408+48852-97704+48852 -> 195408
A98: =+A97+1 -> 91 | B98: LEROMED FHARMA | C98: =SUM(D98:K98) -> 1794447.5 | E98: =569975-118800-172780-278395 -> 0 | F98: 0 | J98: =2062459.48-283110-592473-180422 -> 1006454.5 | K98: =180422+305287.24-305287.24+107471+500100 -> 787993
A99: =+A98+1 -> 92 | B99: LINKDICOM, S.R.L | C99: =SUM(D99:K99) -> 84950 | J99: =+'[10]ENERO REB'!E1062 -> 84950
A100: =+A99+1 -> 93 | B100: LOLA EVENTOS | C100: =SUM(D100:K100) -> 14006.6 | D100: =14006.6 -> 14006.6
A101: =+A100+1 -> 94 | B101: LORATOR | C101: =SUM(D101:K101) -> 25000 | E101: 0 | F101: =25000 -> 25000
...

Sheet DETALLES DE ESTADO DE RF
A1: Hospital Materno Infantil San Lorenzo de los Mina
A2: Estado de Rendimiento Financiero
A3: Corte Semestral 31 de Julio 20222022
A6: Nota# 14 Ingresos por transacciones con contraprestaciones
A7: Un detalle de los ingresos por transacciones con contraprestaciones al 31 de Julio 2022 de es como sigue::
A8: Descripción | B8: 2022 | C8: 2021
A10: Ingresos por Venta de Servicos Hospitalarios | B10: =46780535.74+355135 -> 47135671 | C10: =50429198.42+40500 -> 50469698
A11: Ingresos por Fondos de Anticipo Financiero | B11: 7416837.4 | C11: 11158926
A12: TOTAL GENERAL | B12: =SUM(B10:B11) -> 54552508 | C12: =SUM(C10:C11) -> 61628624
A14: Nota # 15 Sueldos, Salarios y beneficios a empleados
A15: Un detalle de las cuentas sueldos, salarios, beneficios a empleados al31 de Julio 2022de es como sigue::
A16: Descripción | B16: 2022 | C16: 2021
A18: Sueldos fijos
A19: Sueldos al personal contratado o igualado | B19: 3300078 | C19: 4018313.2
A20: Incentivo por Rendimiento Individual | B20: 4669202.9 | C20: 7907420.2
A21: Contribuciones al seguro de salud | B21: =38995.93*6 -> 233975.58 | C21: 284136.78
A22: Contribuciones al seguro de pensiones | B22: =39050.92*6 -> 234305.52 | C22: 281661.66
A23: Contribuciones al seguro de riesgo laboral | B23: =6600.16*6 -> 39600.96 | C23: 37830.84
A24: Prestacion Laboral por desvinculacion | C24: 105820.22
A25: Remuneraciones al personal de carácter temporal | C25: 5399061.2
A26: TOTAL GENERAL | B26: =SUM(B18:B25) -> 8477163 | C26: =SUM(C18:C25) -> 18034244
A28: Nota# 18 Subvenciones y otros pagos por transferencias
A29: Un detalle de la cuenta subvenciones y otros pagos por transferencia al31 de Julio 2022de es como sigue:: es como sigue:
A30: Descripción | B30: 2022 | C30: 2021
A31: Ayudas y donaciones ocasionales a hogares y personas | B31: =138000+41500 -> 179500 | C31: 118700
A32: TOTAL GENERAL | B32: =SUM(B31:B31) -> 179500 | C32: =SUM(C31:C31) -> 118700
A34: Nota# 16 Suministro y materiales para consumo
A35: Un detalle de los gastos de suministro y materiales para consumo al 31 de Julio 2022de es como sigue:: es como sigue:
A36: Descripción | B36: 2022 | C36: 2021
A38: Alimentos y bebidas para personas | B38: 8242270.3 | C38: 4734652.3
A39: Hilados y telas | C39: 115491.16
A40: Acabados textiles | C40: 42180.04
A41: Prendas de vestir | C41: 47729.6
A42: Productos de Papel. Cartón e impresos | B42: 1265220 | C42: =1613769.12+56640+1448353.1-1569940.84 -> 1548821.4
A43: Papel de escritorio | B43: 764000 | C43: 677020.34
A44: Libros, revistas y periodicos
A45: Especies timbradas
A46: Productos medicinales | B46: 19657708 | C46: 12048001
A47: Articulos de caucho | C47: 260992.4
A48: Articulos de plásticos | B48: 874426.02 | C48: 1725975
A49: Productos de Cemento | C49: 16825.2
A50: Productos de cal | C50: 36580
A51: Prodcutos de porcelana | C51: 4307
A52: Herramientas menores | C52: 32325.35
A53: Productos de hojalata | C53: 520
A54: Productos no ferrosos | C54: 23447.78
A55: Accesorio de metal | C55: =138859.84+14705.75+543006.67 -> 696572.26
A56: Gasolina | C56: 50000
A57: Gasoil | B57: 1270054 | C57: 312800
A58: Gas GLP | B58: 77970 | C58: 23246
A59: Insecticidas, fumigantes y otros | C59: 25308
A60: Pinturas, lacas, barnices, diluyentes y absorventes para pinturas | C60: =95845.5+314971.8 -> 410817.3
A61: Material para limpieza | B61: =97704+3135841.74 -> 3233545.7 | C61: =1268423.75+364660.92 -> 1633084.7
A62: Útiles de escritorios, oficina informática y enseñanza | B62: 1751051.7 | C62: 408309.3
A63: Útiles menores quirurgicos | B63: 29195047 | C63: =11696292.06+4313475.8 -> 16009768
A64: Productos químicos de uso personal y de laboratorios | B64: 15160556 | C64: =7631561.9+255987+58531.07+11528555.46 -> 19474635
A65: Útiles destinados actividades deportivas y recreativas
A66: Útiles de cocina y comedor
A67: Productos eléctricos y afines | B67: 84800.7 | C67: 1734620.6
A68: Otros respuestos y accesorios menores | B68: 762232.45 | C68: 142278.5
A69: Utiles Varios | B69: 13763.52 | C69: 1949348
A70: Productos y útiles diversos | B70: 72216 | C70: =850+52610.3 -> 53460.3
A71: TOTAL GENERAL | B71: =SUM(B38:B70) -> 82424862 | C71: =SUM(C38:C70) -> 64239117
A73: Nota# 17 Gastos de depreciación y amortización
A74: Un detalle de los gastos de depreciación y amortización al 31 de Julio 2022de es como sigue:: es como sigue:
A75: Descripción | B75: 2022 | C75: 2021
A77: Depreciación de Mobiliarios, equipo de oficina y cómputos | B77: =+'NOTAS 7 AL19'!C117 -> 0 | C77: =+'NOTAS 7 AL19'!#REF! -> #REF!
A78: Depreciación equipos de transporte.
A79: TOTAL GENERAL | B79: =SUM(B77:B78) -> 0 | C79: =SUM(C77:C78) -> #REF!
A81: Nota# 18 Otros gastos
A82: Un detalle de otros gastos al 31 de Julio 2022de es como sigue:: es como sigue:
A83: Descripción | B83: 2022 | C83: 2021
A85: Servicio de teléfono de larga distancia
A86: Teléfono local | B86: =219216.32+279499.39 -> 498715.71 | C86: 606940.72
A87: Servicio de internet y televisión por cable | B87: =124038.07+113896.25 -> 237934.32 | C87: 180577.94
A88: Agua | B88: 259200 | C88: =43200*6 -> 259200
A89: Recoleción de residuos sólidos | B89: 305000 | C89: 499300
A90: Pasaje | B90: 82000 | C90: 1450
A91: Fletes | C91: 103924.35
A92: Alquiler de equipo educacional | C92: 538080
A93: Alquiler equipo de computación | B93: 521269.73 | C93: 417025.44
A94: Alquiler equipo de comunicación | C94: 134520
A95: Alquiler de equipo de oficina y muebles | B95: 328816.25
A96: Otros Alquileres | B96: 6608 | C96: 3894
A97: Obras menores en edificaciones | B97: 741364.64
A98: Serviciios especiales de mantenimiento y reparación | B98: =324382+14160+107885.18 -> 446427.18
A99: Limpieza, desmalezamiento de tierras y terrenos | B99: 84134
A100: Mantenimiento y reparacion de equipo de oficina y muebles | C100: =517044.73+90+82700.3 -> 599835.03
A101: Instalaciones eléctricas | B101: 775507.8
A102: Mantenimientos de reparación de maquinarias y equipos | B102: 107557
A103: Otros servicios de mantenimiento y reparacion de maquinaria y equipos. | C103: 250155.13
A104: Gastos judiciales | B104: 747500
A105: Fumigación | B105: 95462
A106: Eventos generales | B106: 18255.07 | C106: 18290
A107: Servicios técnicos y profesionales | B107: =215940+263878+1637322.39+558890.41+1723250.88+71111.11+803179.09+560513.16+464444.44 -> 6298529.5 | C107: =136554+15320+727572+562945.68+500225.6+97704+1300318.39 -> 3340639.7
A108: TOTAL GENERAL | B108: =SUM(B85:B107) -> 11554281 | C108: =SUM(C85:C107) -> 6953832.3
A110: Nota# 19 Gastos Financieros
A111: Un detalle de los gastos financieros al 31 de Julio 2022de es como sigue:: es como sigue:
A112: Descripción | B112: 2022 | C112: 2021
A114: Comisiones bancarias | B114: 82335.75 | C114: 117963.06
...
