Workbook

Sheet RELACION DE PAGOS EMITIDOS
A5: DIRECCION DE FISCALIZACION Y CONTROL
A6: RELACION DE PAGOS EMITIDOS DURANTE EL MES
A7: ESTABLECIMIENTO:HOSPITAL MATERNO INFANTIL SAN LORENZO DE LOS MINA
A9: PAGOS CORRESPONDIENTES AL MES : JULIO 2025
A10: FECHA | B10: LIBRAMIENTO | C10: TRANSFERENCIA | D10: CHEQUE | E10: BENEFICIARIO | F10: NO.FACTURAS | G10: VALOR DE FACTURA | H10: VALOR PAGADO
A11: 45842 | C11: 208 | E11: TROPIGAS DOMINICANA SRL | F11: PAGO NCF E450000005443 ADQUISICION DE GAS LICUADO DE PETROLEO SEGÚN ORDEN DE COMPRA HSLM-2025-00066. | G11: 22638 | H11: 22638
A12: 45842 | C12: 209 | E12: P&D RECYCLING SRL | F12: PAGO NCF B1500000313 SERVICIO DE RECOGIDA DE DESESCHOS SOLIDOS SEGÚN O/C HSLM-2025-00578. | G12: 760000 | H12: 722000
A13: 45842 | C13: 210 | E13: FILIDENNY RODRIGUEZ DE ACEVEDO | F13: PAGO DE REGALIA PASCUAL PERSONAL FIJOS INACTIVOS 2024, DEBIDO A QUE SU CUENTA FUE CERRADA. | G13: 19496.18 | H13: 19496.18
A14: 45842 | C14: 211 | E14: JULIO CESAR GONZALEZ | F14: PAGO DE PRESTACIONES LABORALES POR VACACIONES NO DISFRUTADAS MAYO 2025, DEBIDO A QUE SU CUENTA FUE CERRADA. | G14: 8860.18 | H14: 8860.18
A15: 45842 | C15: 212 | E15: NEGOCIOS SUHEIDY RODRIGUEZ, SRL | F15: PAGO DE FACTURA NCF NO B1500000110, POR ADQUISICION DE TARIMAS PLASTICAS, SEGÚN ORDEN DE COMPRA HSLM-2025-00626 | G15: 118075.52 | H15: 113072.32
A16: 45845 | C16: 213 | E16: LABORATORIO CLINICO LICDA PATRIA RIVAS, SRL | F16: PAGO DE FACT NCF NO E450000000049, POR SERVICIO DE ESTUDIOS ESPECIALIZADOS SEGÚN ORDEN DE COMPRA HSLM-2025-00312 | G16: 14160 | H16: 14160
A17: 45845 | C17: 214 | E17: CENTRO DE LA SANGRE Y ESPECIALIDADES Y ESPECIALIDADES SRL | F17: PAGO NCF B1500000403 SERVICIO DE SANGRE PARA PACIENTES INTERNOS SEGÚN O/C HSLM-2025-00428. | G17: 24000 | H17: 22800
A18: 45845 | C18: 215 | E18: NEGOCIOS SUHEIDY RODRIGUEZ, SRL | F18: PAGO DE FACT NCF B1500000108, POR ADQUISICION DE FUNDAS PLASTICAS, SEGÚN ORDEN DE COMPRA HSLM-2025-00614 | G18: 1230740 | H18: 1178590
A19: 45845 | C19: 216 | E19: SERVICIO DE BIOMEDICINA MEDICO SERBIOMED SRL | F19: PAGO DE FACT NCF NO. B1500000226, POR ADQUISICION DE KIT DE PRUEBA DE ESTERILIZADOR DE VACIO DE PULSO MARCA SHINVA DE 350, SEGÚN ORDEN DE COMPRA HSLM-2025-00526 | G19: 247800 | H19: 237300
A20: 45845 | C20: 217 | E20: SERVICIO DE BIOMEDICINA MEDICO SERBIOMED SRL | F20: PAGO DE FACT NCF NO. B1500000225, POR SERVICIO DE MANTENIMIENTO PREVENTIVO DE AUTOCLAVE SHINVA 350 LITRO, SEGÚN ORDEN DE SERVICIO HSLM-2025-00528 | G20: 212400 | H20: 203400
A21: 45845 | C21: 218 | E21: CABOD, SRL | F21: PAGO DE FACT NCF NO. B1500001808 Y B1500001802, POR ADQUISICION DE DETERGENTE PARA LAVANDERIA, SEGÚN ORDEN DE COMPRA HSLM-2025-00615 | G21: 409306.6 | H21: 391963.1
A22: 45845 | C22: 219 | E22: XAVIER VARGAS, INGENIERIA ELECROMECANICA, EIRL | F22: PAGO DE FACT NCF NO. B1500000249, POR SERVICIO DE MANTENIMIENTO DE AIRES ACONDICIONADOS, SEGÚN ORDEN DE SERVICIO NO. HSLM-2025-00570 | G22: 594720 | H22: 569520
... A49: 45869 | C49: 247 | E49: LILIAN YOMAYRA ENCARNACION | F49: pago de regencia en permiso de drogas y farmacia, perteneciente al mes de julio 2025 | G49: 10000 | H49: 10000
A50: 45839 | D50: 37252 | E50: FREDY OSCAR RODRIGUEZ RIVAS | F50: COLABORACION PARA CAVAR HOYO Y CERTIFICACION DE ACTAS DE DEFUNCION | G50: 3600 | H50: 3600
A51: 45841 | D51: =+D50+1 -> 37253 | E51: PAOLA VIRIGILIO JAVIER | F51: COLABORACION PARA LA PACIENTE R/N PAOLA JAVIER LA CUAL SE LE REALIZARA UN DOPPLER CEREBRAL PARA DESCARTAR MUERTE CEREBRAL | G51: 10000 | H51: 10000
A52: 45841 | D52: =+D51+1 -> 37254 | E52: ISMAEL TEJEDA SIGARAN | F52: PAGO POR SERVICIO DE TRASLADO DE INSUMO DEL AREA DE FARMACIA. | G52: 18061.23 | H52: 15000
A53: 45841 | D53: =+D52+1 -> 37255 | E53: DELMIRA GARCIA | F53: REPICION DE FONDO DE CAJA CHICA | G53: 55105.58 | H53: 55105.58
A54: 45848 | D54: =+D53+1 -> 37256 | E54: OLEGARIO GUERRERO | F54: PAGO DE FACT NCF B1100000054 POR SERVICIO DE JARDINERIA DEL AREA VERDE Y PODA DE ARBOLES EXTERIOR E INTERIOR DE ESTE HOSPITAL. | G54: 9632.66 | H54: 8000
A55: 45848 | D55: =+D54+1 -> 37257 | E55: ESTHERLING YUBANET LARA DE LOS SANTOS | F55: PAGO DE FACT NCF B1100000053 POR SERVICIO DE REPARACION DE REBANADORA DEL AREA DE COCINA DE ESTE HOSPITAL. | G55: 12402.05 | H55: 10300
A56: 45853 | D56: =+D55+1 -> 37258 | E56: CRISTIAN ERASMO VENTURA | F56: PAGO DE FACT NCF B1100000055 POR SERVICIO DE CONFECCION DE 2 TAPAS DE REGISTROS, CONFECCION DE VERJAS PROTECTORAS PERIMETRAL, REPARACION DE LA PUERTA DE ENTRADA A CUARTO DE BOMBA Y REPARACION DE 2 BANCADAS DEL HOSPITAL | G56: 36122.46 | H56: 30000.01
A57: 45856 | D57: =+D56+1 -> 37259 | E57: ABRAHAN JOSE MENDOZA | F57: PAGO DE FACT NCF B1100000056 POR SERVICIO DE MANTENIMIENTO DE REMIENDO DE PARQUEO EN LAS EMERGENCIAS Y OBSTETRICIA, RESANE DE PAREDES DE DISTINTAS AREAS DEL HOSPITAL | G57: 8428.57 | H57: 7000
A58: 45859 | D58: =+D57+1 -> 37260 | E58: ABRAHAN JOSE MENDOZA | F58: PAGO DE FACT NCF B1100000057 POR SERVICIO DE REPARACION DE HUECO Y PULIDO DE PARED DEL DEPTO DE LABORATORIO DEL HOSPITAL | G58: 22877.56 | H58: 19000
A59: 45860 | D59: =+D58+1 -> 37261 | E59: NULO | F59: NULO | G59: 0
A60: 45860 | D60: =+D59+1 -> 37262 | E60: SANDRA TOLENTINO MARTINEZ | F60: PAGO POR SERVICIO DE ECOCARDIOGRAMA Y EVALUACION CARDIOVASCULAR PARA 7 PACIENTES INGRESADOS EN EL HOSPITAL A UN COSTO DE RD$3,000.00 C/U | G60: 21000 | H60: 21000
A61: 45860 | D61: =+D60+1 -> 37263 | E61: ALEXANDER MENDEZ CONTRERAS | F61: PAGO POR EL SERVICIO DE JARDINERIA Y MANTENIMIENTO DE AREAS VERDES DE ESTE HOSPITAL | G61: 18061.22 | H61: 15000
A62: 45860 | D62: =+D61+1 -> 37264 | E62: RUDDY SEGURA | F62: PAGO POR EL SERVICIO DE LIMPIEZA Y CLORIFICACION DE LAS CISTERNAS DE ESTE HOSPITAL | G62: 21673.47 | H62: 18000.01
A63: 45860 | D63: =+D62+1 -> 37265 | E63: NELSON YNFANTE VELAZQUEZ | F63: PAGO DE FACT NCF B1100000060 POR SERVICIO DE PINTURA PARA DIFERENTES AREAS DEL HOSPITAL | G63: 18061.22 | H63: 15000
A64: 45860 | D64: =+D63+1 -> 37266 | E64: NULO | F64: NULO | G64: 0
A65: 45860 | D65: =+D64+1 -> 37267 | E65: FREDY OSCAR RODRIGUEZ RIVAS | F65: COLABORACION PARA CAVAR HOYO Y CERTIFICACION DE ACTAS DE DEFUNCION. | G65: 3600 | H65: 3600
A66: 45860 | D66: =+D65+1 -> 37268 | E66: Ovidio De Jesús Duran Clemente | F66: PAGO POR SERVICIO DE TRANSPORTE DE LA AMBULANCIA CORRESPONDIENTE AL MES DE JULIO 2025 | G66: 20000 | H66: 20000
A67: 45867 | D67: 37269 | E67: DELMIRA GARCIA | F67: REPICION DE FONDO DE CAJA CHICA | G67: 54251.88 | H67: 54251.88
A68: 45867 | D68: 37270 | E68: EMMANUEL JIMENEZ | F68: PAGO POR SERVICIO DE TERAPIA FISICA A PACIENTE INGRESADA | G68: 22500 | H68: 22500
A69: 45867 | D69: 37271 | E69: RAFAEL ELIGIO MORENO MARTINEZ | F69: PAGO POR SERVICIO DE ANALISIS PARA LA PACIENTE CARINE OLIVER INGRESADA EN LA INSTITUCION | G69: 7871 | H69: 7871
A70: 01/07/2025 | B70: 2719 | E70: Macrotech Farmacéutica, SRL | F70: PAGO DE FACT NCF E450000001047 POR ADQUISICION DE UTILES MEDICOS SEGUN O/C HSLM-2025-00593. | G70: 578891.48
A71: 01/07/2025 | B71: 2724 | E71: Khris Aus Pharmacy, S.R.L | F71: PAGO DE FACT NCF B1500000155 POR ADQUISICION DE MEDICAMENTOS SEGUN O/C HSLM-2025-00601. | G71: 180000
A72: 02/07/2025 | B72: 2725 | E72: Industrias Nigua, S.A | F72: PAGO DE FACTS NCF E450000000513, E450000000524 Y E450000000525 POR ADQUISICION DE DESECHABLES SEGUN O/C HSLM-2025-00443. | G72: 387807.15
A73: 02/07/2025 | B73: 2729 | E73: JBW Leger Ingenieros, SRL | F73: PAGO DE FACT NCF B1500000063 POR ADQUISICION DE GABINETES EN ACERO INOXIDABLES PARA EL AREA DE UCI SEGUN O/C HSLM-2025-00211. | G73: 1361145
A74: 02/07/2025 | B74: 2735 | E74: PAPELERIA E IMPRESOS CRISHOAN, SRL | F74: PAGO DE FACT NCF B1500001716 POR ADQUISICION DE SERVILLETAS SEGUN O/C HSLM-2025-00589. | G74: 265393.8
A75: 02/07/2025 | B75: 2739 | E75: Grupo Xeron Medic SRL | F75: PAGO DE FACT NCF B1500000245 POR ADQUISICION DE DISPENSADORES DE GEL SEGUN O/C HSLM-2025-00590. | G75: 342200
A76: 02/07/2025 | B76: 2743 | E76: G & M Gelmat Comercial, SRL | F76: PAGO DE FACT NCF B1500000166 POR ADQUISICION DE MEDICAMENTOS SEGUN O/C HSLM-2025-00599. | G76: 200010
A77: 02/07/2025 | B77: 2747 | E77: Hauspital, SRL | F77: PAGO DE FACT NCF B1500000809 POR ADQUISICION DE CIRCUITO DE VENTILACION PEDIATRICO SEGUN O/C HSLM-2025-00602. | G77: 59000
A78: 02/07/2025 | B78: 2751 | E78: Pasofri, SRL | F78: PAGO DE FACT NCF B1500000340 POR ADQUISICION DE MAQUINA DE TERAPIA ELECTROCONVULSIVA SEGUN O/C HSLM-2025-00500. | G78: 70800
A79: 03/07/2025 | B79: 2756 | E79: JM Distribución, SRL | F79: PAGO DE FACT NCF B1500000302 POR ADQUISICION DE DESECHABLES SEGUN O/C HSLM-2025-00477. | G79: 72900.1
A80: 03/07/2025 | B80: 2760 | E80: G & M Gelmat Comercial, SRL | F80: PAGO DE FACT NCF B1500000168 POR ADQUISICION DE UNIDAD OFTALMOLOGICA CON CONTROL REMOTO SEGUN O/C HSLM-2025-00495. | G80: 671774
A81: 03/07/2025 | B81: 2764 | E81: Oficclin Comercial, SRL | F81: PAGO DE FACT NCF B1500000615 POR ADQUISICION DE LAMPARA DE HENDIDURA 5MG (LS-4) SEGUN O/C HSLM-2025-00464. | G81: 1999226.8
... A204: 31/07/2025 | B204: 3373 | E204: Diucam Group SRL | F204: PAGO DE FACT NCF B1500000014 POR ADQUISICION DE ALIMENTOS, SERVILLETAS, Y PAPEL ALUMINIO SEGUN O/C HSLM-2025-00550. | G204: 731311.6
A205: Total | G205: =SUM(G11:G204) -> 1.1954704e+08 | H205: =SUM(H11:H204) -> 8863243.5
A209: RESUMEN
A210: PAGO PROVEEDORES | C210: 47686120
A211: CAJA CHICA | C211: 109357.46
A212: NOMINA | C212: 71335676
A213: OTROS | C213: 415891.44
A214: TOTAL GENERAL | C214: =SUM(C210:C213) -> 1.1954704e+08

Sheet RELACION ORDENES DE COMPRAS
A4: SERVICIO NACIONAL DE SALUD
A5: DIRECCION DE FISCALIZACION
A6: RELACIÓN DE ORDENES DE COMPRAS DE BIENES Y SERVICIOS EFECTUADAS.
A7: ESTABLECIMIENTO: HOSPITAL MATERNO INFANTIL SAN LORENZO DE LOS MINA REGION OZAMA, MES DE JULIO 2025
A8: Fecha | B8: # Orden de Compra o Servicios | C8: # DE EXPEDIENTE(PROCESO CELEBRADO) | D8: No. De Factura Fiscal NCF | E8: Fuente. Financ (FR-VS) | F8: Beneficiario | G8: Rubro | H8: No. Cta. Objetal del Gasto | I8: Valor | J8: Status del proceso | K8: solo observar cuando se presentas esos procesos
A9: 45841.626 | B9: HSML-2025-00632 | C9: HSLM-DAF-CD-2025-0494 | E9: VS/FG | F9: Express Service Conserg Exsercon, SRL | G9: 42290000 | H9: Productos quirúrgicos | I9: 270820 | J9: Adjudicado
A10: 45841.626 | B10: HSML-2025-00631 | C10: HSLM-DAF-CD-2025-0495 | E10: VS/FG | F10: Express Service Conserg Exsercon, SRL | G10: 51160000 | H10: Medicamentos que afectan al sistema respiratorio | I10: 217120 | J10: Adjudicado
A11: 45842.668 | B11: HSML-2025-00677 | C11: HSLM-DAF-CM-2025-0165 | E11: VS/FG | F11: Actualidades VD, SRL | G11: 52140000 | H11: Aparatos electrodomésticos | I11: 177047 | J11: Adjudicado
A12: 45848.419 | B12: HSML-2025-00653 | C12: HSLM-DAF-CD-2025-0516 | E12: VS/FG | F12: Morami, SRL | G12: 42140000 | H12: Suministros, productos de tratamiento y cuidado del enfermo | I12: 206500 | J12: Adjudicado
A13: 45848.459 | B13: HSML-2025-00655 | C13: HSLM-DAF-CD-2025-0517 | E13: VS/FG | F13: Baucomer, SRL | G13: 51180000 | H13: Hormonas y antagonistas hormonales | I13: 245000 | J13: Adjudicado
A14: 45852.459 | B14: HSML-2025-00669 | C14: HSLM-DAF-CD-2025-0532 | E14: VS/FG | F14: Bio Win, SRL | G14: 41110000 | H14: Instrumentos de medida, observación y ensayo | I14: 30000 | J14: Adjudicado
A15: 45853.542 | B15: HSML-2025-00680 | C15: HSLM-DAF-CD-2025-0540 | E15: VS/FG | F15: AGROGLOBAL EXPORT E IMPORT, SRL | G15: 24110000 | H15: Recipientes y almacenamiento | I15: 63720 | J15: Adjudicado
A16: 45859.479 | B16: HSML-2025-00702 | C16: HSLM-DAF-CD-2025-0555 | E16: VS/FG | F16: Papelería E. Impresos Crishoan, SRL | G16: 47120000 | H16: Equipo de aseo | I16: 53336 | J16: Adjudicado
A17: 45859.585 | B17: HSML-2025-00727 | C17: HSLM-DAF-CD-2025-0557 | E17: VS/FG | F17: INSOCORP, SRL | G17: 42270000 | H17: Productos de resucitación, anestesia y respiratorio | I17: 47200 | J17: Adjudicado
A18: 45859.585 | B18: HSML-2025-00724 | C18: HSLM-DAF-CM-2025-0177 | E18: VS/FG | F18: INSOCORP, SRL | G18: 42290000 | H18: Productos quirúrgicos | I18: 1945820 | J18: Adjudicado
A19: 45861.376 | B19: HSML-2025-00710 | C19: HSLM-DAF-CD-2025-0563 | E19: VS/FG | F19: Morami, SRL | G19: 42140000 | H19: Suministros, productos de tratamiento y cuidado del enfermo | I19: 236000 | J19: Adjudicado
A20: 45861.444 | B20: HSML-2025-00712 | C20: HSLM-DAF-CD-2025-0566 | E20: VS/FG | F20: Ropharma, SRL | G20: 51190000 | H20: Agentes que afectan el agua y los electrolitos | I20: 136500 | J20: Adjudicado
... A27: 45866.459 | B27: HSML-2025-00754 | C27: HSLM-DAF-CM-2025-0182 | E27: VS/FG | F27: Farmaco Internacional, SRL | G27: 51100000 | H27: Medicamentos antiinfecciosos | I27: 294470 | J27: Adjudicado
A28: 45866.459 | B28: DECIERTO | C28: HSLM-DAF-CD-2025-0574 | E28: VS/FG | G28: 78180000 | H28: Servicios de mantenimiento o reparaciones de transportes | J28: Desierto
A29: 45866.502 | B29: HSML-2025-00733 | C29: HSLM-DAF-CD-2025-0577 | E29: VS/FG | F29: INSOCORP, SRL | G29: 42310000 | H29: Productos para el cuidado de heridas | I29: 247800 | J29: Adjudicado
A30: 45866.542 | B30: HSML-2025-00731 | C30: HSLM-DAF-CD-2025-0580 | E30: VS/FG | F30: INSOCORP, SRL | G30: 42290000 | H30: Productos quirúrgicos | I30: 59000 | J30: Adjudicado
A31: 45866.542 | B31: HSML-2025-00740 | C31: HSLM-DAF-CD-2025-0578 | E31: VS/FG | F31: Ofitop, S.R.L | G31: 56100000 | H31: Muebles de alojamiento | I31: 262509 | J31: Adjudicado
A32: 45866.542 | B32: HSML-2025-00732 | C32: HSLM-DAF-CD-2025-0579 | E32: VS/FG | F32: INSOCORP, SRL | G32: 42130000 | H32: Telas y vestidos médicos | I32: 271254 | J32: Adjudicado
A33: 45866.584 | B33: HSML-2025-00755 | C33: HSLM-DAF-CM-2025-0183 | E33: VS/FG | F33: INSOCORP, SRL | G33: 41110000 | H33: Instrumentos de medida, observación y ensayo | I33: 1456293.2 | J33: Evaluación
A34: 45866.584 | B34: HSML-2025-00739 | C34: HSLM-DAF-CD-2025-0582 | E34: VS/FG | F34: Khris Aus Pharmacy, S.R.L | G34: 42310000 | H34: Productos para el cuidado de heridas | I34: 160000 | J34: Adjudicado
A35: 45866.626 | B35: HSML-2025-00741 | C35: HSLM-DAF-CD-2025-0583 | E35: VS/FG | F35: Abrias Novo Group SRL | G35: 56110000 | H35: Muebles comerciales e industriales | I35: 80523 | J35: Adjudicado
A36: 45867.419 | B36: HSML-2025-00747 | C36: HSLM-DAF-CD-2025-0585 | E36: VS/FG | F36: Ofitop, S.R.L | G36: 56110000 | H36: Muebles comerciales e industriales | I36: 264511 | J36: Adjudicado
A37: 45867.459 | B37: HSML-2025-00738 | C37: HSLM-DAF-CD-2025-0588 | E37: VS/FG | F37: I.V. Biodesinfección, SRL | G37: 76100000 | H37: Servicios de descontaminación | I37: 9912 | J37: Adjudicado
A38: 45867.502 | B38: HSML-2025-00742 | C38: HSLM-DAF-CD-2025-0589 | E38: VS/FG | F38: Adler Amicis Valdez Marmolejos | G38: 82120000 | H38: Servicios de reproducción | I38: 167560 | J38: Adjudicado
A39: 45869.419 | B39: Analisis de oferta | C39: HSLM-DAF-CM-2025-0186 | E39: VS/FG | G39: 43210000 | H39: Equipo informático y accesorios | J39: Publicado
A40: 45869.427 | B40: HSML-2025-00751 | C40: HSLM-DAF-CD-2025-0596 | E40: VS/FG | F40: Asenp Quality Consulting,SRL | G40: 42290000 | H40: Productos quirúrgicos | I40: 70092 | J40: Adjudicado
A41: 45869.465 | B41: HSML-2025-00748 | C41: HSLM-DAF-CD-2025-0597 | E41: VS/FG | F41: Gestiones Sanitarias & Ambientales, SRL (GESA) | G41: 42260000 | H41: Equipo y suministros post mortem y funerarios | I41: 18290 | J41: Adjudicado
A42: 45869.502 | B42: HSML-2025-00749 | C42: HSLM-DAF-CD-2025-0599 | E42: VS/FG | F42: Morami, SRL | G42: 42290000 | H42: Productos quirúrgicos | I42: 106200 | J42: Adjudicado
A43: 45869.502 | B43: HSML-2025-00750 | C43: HSLM-DAF-CD-2025-0598 | E43: VS/FG | F43: Compra-Med, SRL | G43: 51160000 | H43: Medicamentos que afectan al sistema respiratorio | I43: 112995 | J43: Adjudicado
A44: 45869.376 | B44: Cancelado | C44: HSLM-DAF-CD-2025-0594 | E44: VS/FG | G44: 50130000 | H44: Productos lácteos y huevos | J44: Cancelado
A45: 45868.543 | B45: Analisis de oferta | C45: HSLM-DAF-CM-2025-0184 | E45: VS/FG | G45: 90100000 | H45: Restaurantes y catering (servicios de comidas y bebidas) | J45: Publicado
A46: 45867.502 | B46: Analisis de oferta | C46: HSLM-DAF-CD-2025-0590 | E46: VS/FG | G46: 82120000 | H46: Servicios de reproducción | J46: Evaluación
A47: 45867.459 | B47: Analisis de oferta | C47: HSLM-DAF-CD-2025-0586 | E47: VS/FG | G47: 39100000 | H47: Lámparas y bombillas y componentes para lámparas | J47: Evaluación
A48: 45867.418 | B48: HSML-2025-00736 | C48: HSLM-DAF-CD-2025-0584 | E48: VS/FG | F48: Suplimed, SRL | G48: 85120000 | H48: Práctica médica | I48: 195000 | J48: Adjudicado
A49: 45866.419 | B49: HSML-2025-00729 | C49: HSLM-DAF-CD-2025-0576 | E49: VS/FG | F49: Adler Amicis Valdez Marmolejos | G49: 82120000 | H49: Servicios de reproducción | I49: 88795 | J49: Adjudicado
A50: 45866.419 | B50: HSML-2025-00745 | C50: HSLM-DAF-CM-2025-0180 | E50: VS/FG | F50: CEM Caribbean Equipment Medical, SRL | G50: 41110000 | H50: Instrumentos de medida, observación y ensayo | I50: 600000 | J50: Adjudicado
A51: 45862.584 | B51: HSML-2025-00722 | C51: HSLM-DAF-CD-2025-0572 | E51: VS/FG | F51: Medequip, SRL | G51: 42270000 | H51: Productos de resucitación, anestesia y respiratorio | I51: 78258 | J51: Adjudicado
A52: 45861.627 | B52: HSML-2025-00717 | C52: HSLM-DAF-CD-2025-0568 | E52: VS/FG | F52: Macrotech Farmacéutica, SRL | G52: 41100000 | H52: Equipo de laboratorio y científico | I52: 92613 | J52: Adjudicado
A53: 45861.542 | B53: HSML-2025-00716 | C53: HSLM-DAF-CD-2025-0567 | E53: VS/FG | F53: Distribuidora Brito Contreras, SRL | G53: 51150000 | H53: Medicamentos para el sistema nervioso autónomo | I53: 96330 | J53: Adjudicado
A54: 45860.543 | B54: HSML-2025-00707 | C54: HSLM-DAF-CD-2025-0562 | E54: VS/FG | F54: Sean Dominican, SRL | G54: 51110000 | H54: Agentes antitumorales | I54: 150000 | J54: Adjudicado
A55: 45859.626 | B55: HSML-2025-00723 | C55: HSLM-DAF-CM-2025-0179 | E55: VS/FG | F55: Farmaco Internacional, SRL | G55: 42290000 | H55: Productos quirúrgicos | I55: 299770 | J55: Adjudicado
A56: 45859.584 | B56: HSML-2025-00725 | C56: HSLM-DAF-CM-2025-0178 | E56: VS/FG | F56: Toner Depot Multiservicios EORG, SRL | G56: 82120000 | H56: Servicios de reproducción | I56: 1625000 | J56: Adjudicado
A57: 45859.503 | B57: HSML-2025-00734 | C57: HSLM-DAF-CM-2025-0175 | E57: VS/FG | F57: Sandry Gomez Rodriguez | G57: 50110000 | H57: Productos de carne y aves de corral | I57: 628550 | J57: Adjudicado
A58: 45859.479 | B58: HSML-2025-00703 | C58: HSLM-DAF-CD-2025-0556 | E58: VS/FG | F58: Abrias Novo Group SRL | G58: 90100000 | H58: Restaurantes y catering (servicios de comidas y bebidas) | I58: 272167 | J58: Adjudicado
A59: 45855.584 | B59: HSML-2025-00698 | C59: HSLM-DAF-CD-2025-0551 | E59: VS/FG | F59: Papelería E. Impresos Crishoan, SRL | G59: 44120000 | H59: Suministros de oficina | I59: 171248 | J59: Adjudicado
... A108: 45860.503 | B108: HSML-2025-00715 | C108: HSLM-DAF-CD-2025-0560 | E108: VS/FG | F108: Bio Nova, SRL | G108: 41110000 | H108: Instrumentos de medida, observación y ensayo | I108: 49200 | J108: Adjudicado
A109: 45859.542 | B109: HSML-2025-00737 | C109: HSLM-DAF-CM-2025-0176 | E109: VS/FG | F109: Sandry Gomez Rodriguez | G109: 50100000 | H109: Frutos secos | J109: Adjudicado
A110: 45856.502 | B110: HSML-2025-00700 | C110: HSLM-DAF-CD-2025-0553 | E110: VS/FG | F110: Baucomer, SRL | G110: 51150000 | H110: Medicamentos para el sistema nervioso autónomo | I110: 210000 | J110: Adjudicado
A111: 45855.459 | B111: HSML-2025-00695 | C111: HSLM-DAF-CD-2025-0548 | E111: VS/FG | F111: Dumas Pharmaceuticals, SRL | G111: 42270000 | H111: Productos de resucitación, anestesia y respiratorio | I111: 238905 | J111: Adjudicado
A112: 45854.639 | B112: HSML-2025-00692 | C112: HSLM-DAF-CD-2025-0547 | E112: VS/FG | F112: RYS SOLUCIONES E INVERSIONES INTEGRALES, SRL | G112: 44110000 | H112: Accesorios de oficina y escritorio | I112: 254829 | J112: Adjudicado
A113: 45842.431 | B113: Cancelado | C113: HSLM-DAF-CD-2025-0500 | E113: VS/FG | G113: 42130000 | H113: Telas y vestidos médicos | J113: Cancelado
A114: 45868.584 | B114: Analisis de oferta | C114: HSLM-DAF-CM-2025-0185 | E114: VS/FG | G114: 42220000 | H114: Productos para administración intravenosa y arterial | J114: Publicado
A115: 45868.502 | B115: HSML-2025-00743 | C115: HSLM-DAF-CD-2025-0592 | E115: VS/FG | F115: Medina N Solutions, SRL | G115: 31210000 | H115: Pinturas y bases y acabados | I115: 158339.79 | J115: Adjudicado
A116: 45862.419 | B116: HSML-2025-00718 | C116: HSLM-DAF-CD-2025-0570 | E116: VS/FG | F116: Ofitop, S.R.L | G116: 56100000 | H116: Muebles de alojamiento | I116: 245075.97 | J116: Adjudicado
A117: 45861.403 | B117: HSML-2025-00711 | C117: HSLM-DAF-CD-2025-0564 | E117: VS/FG | F117: Grupo Xeron Medic SRL | G117: 51150000 | H117: Medicamentos para el sistema nervioso autónomo | I117: 210000 | J117: Adjudicado
A118: 45860.503 | B118: HSML-2025-00709 | C118: HSLM-DAF-CD-2025-0561 | E118: VS/FG | F118: JESUS FERMIN MARTINEZ LOPEZ | G118: 78110000 | H118: Transporte de pasajeros | I118: 128000 | J118: Adjudicado
A119: 45860.459 | B119: Rescindido | C119: HSLM-DAF-CD-2025-0559 | E119: VS/FG | F119: Medequip, SRL | G119: 42270000 | H119: Productos de resucitación, anestesia y respiratorio | I119: 8673 | J119: Adjudicado
A120: 45860.438 | B120: HSML-2025-00706 | C120: HSLM-DAF-CD-2025-0558 | E120: VS/FG | F120: Bio Nuclear, SA | G120: 81110000 | H120: Servicios informáticos | J120: Adjudicado
A121: 45855.502 | B121: HSML-2025-00696 | C121: HSLM-DAF-CD-2025-0550 | E121: VS/FG | F121: Antares Pharma, SRL | G121: 51100000 | H121: Medicamentos antiinfecciosos | I121: 206018 | J121: Adjudicado
A122: 45855.479 | B122: HSML-2025-00694 | C122: HSLM-DAF-CD-2025-0549 | E122: VS/FG | F122: CEM Caribbean Equipment Medical, SRL | G122: 41110000 | H122: Instrumentos de medida, observación y ensayo | I122: 10793 | J122: Adjudicado
A123: 45853.608 | B123: HSML-2025-00708 | C123: HSLM-DAF-CM-2025-0173 | E123: VS/FG | F123: RC Technology, SRL | G123: 43200000 | H123: Componentes para tecnología de la información, difusión o telecomunicaciones | I123: 1816280 | J123: Adjudicado
A124: 45842.419 | B124: HSML-2025-00635 | C124: HSLM-DAF-CD-2025-0497 | E124: VS/FG | F124: INVERSIONES FH, SRL | G124: 15100000 | H124: Combustibles | I124: 172000 | J124: Adjudicado
A125: 45842.419 | B125: HSML-2025-00633 | C125: HSLM-DAF-CD-2025-0498 | E125: VS/FG | F125: Diversidad de Articulos Diversidart, SRL | G125: 56100000 | H125: Muebles de alojamiento | I125: 271400 | J125: Adjudicado
A126: 45841.615 | B126: HSML-2025-00630 | C126: HSLM-DAF-CD-2025-0496 | E126: VS/FG | F126: Hospal Médica, SRL | G126: 42180000 | H126: Productos de examen y control del paciente | I126: 34220 | J126: Adjudicado
A127: 45868.556 | B127: HSML-2025-00744 | C127: HSLM-DAF-CD-2025-0593 | E127: VS/FG | F127: Diucam Group SRL | G127: 52120000 | H127: Ropa de cama, mantelerías, paños de cocina y toallas | I127: 191396 | J127: Adjudicado
A128: 45867.603 | B128: HSML-2025-00735 | C128: HSLM-DAF-CD-2025-0591 | E128: VS/FG | F128: Grupo Cometa, SAS | G128: 78180000 | H128: Servicios de mantenimiento o reparaciones de transportes | I128: 3160 | J128: Adjudicado
A129: 45867.459 | B129: HSML-2025-00746 | C129: HSLM-DAF-CD-2025-0587 | E129: VS/FG | F129: Ofitop, S.R.L | G129: 56100000 | H129: Muebles de alojamiento | I129: 241951 | J129: Adjudicado
A130: 45854.542 | B130: HSML-2025-00726 | C130: HSLM-DAF-CM-2025-0174 | E130: VS/FG | F130: CEM Caribbean Equipment Medical, SRL | G130: 41110000 | H130: Instrumentos de medida, observación y ensayo | I130: 479452 | J130: Adjudicado
A131: 45853.584 | B131: HSML-2025-00687 | C131: HSLM-DAF-CD-2025-0541 | E131: VS/FG | F131: Papelería E. Impresos Crishoan, SRL | G131: 82120000 | H131: Servicios de reproducción | I131: 259010 | J131: Adjudicado
A132: 45852.502 | B132: HSML-2025-00704 | C132: HSLM-DAF-CM-2025-0172 | E132: VS/FG | F132: INSOCORP, SRL | G132: 42180000 | H132: Productos de examen y control del paciente | I132: 199998 | J132: Adjudicado
... A143: 45845.444 | B143: HSML-2025-00637 | C143: HSLM-DAF-CD-2025-0502 | E143: VS/FG | F143: I.V. Biodesinfección, SRL | G143: 76100000 | H143: Servicios de descontaminación | I143: 197674 | J143: Adjudicado
D144: vs | F144: Sub-Total Compras RD$ | I144: =SUM(I9:I143) -> 33599531
A147: RESUMEN DE COMPRAS o SERVICIOS POR CUENTAS: | F147: RESUMEN DE PROCESO SEGÚN MODALIDAD:
A149: CUENTAS No. | B149: CANTIDAD | C149: MONTO | F149: TIPO | G149: CANTIDAD | H149: MONTO
F150: Compra Directa
F151: Compra Menor
F152: Comparacion de precio
F153: TOTAL COMPRAS | G153: =SUM(G150:G152) -> 0 | H153: =+H145 -> 0
E161: CERTIFICO CORRECTO:
E163: __________________________
E164: DIRECTOR
E166: __________________________
E167: ADMINISTRADOR:
E170: ENC. DE COMPRAS:__________________________
A191: TOTAL RESUMEN | C191: =SUM(C150:C190) -> 0

Sheet CUENTA T VS
A1: D E S G L O S E D E L A S C U E N T A S
A2: 211101 | B2: 211102 | C2: 211103 | D2: 211104 | E2: 211105 | F2: 211106 | G2: 211203 | H2: 211205 | I2: 211206 | J2: 211208 | K2: 211209 | L2: 211211 | M2: 211301 | N2: 211401 | O2: 211501 | P2: 211502 | Q2: 211503 | R2: 211504 | S2: 212101 | T2: 212201 | U2: 212203 | V2: 212204 | W2: 212205 | X2: 212206 | Y2: 212207 | Z2: 212208 | AA2: 212209 | AB2: 212210 | AC2: 213101 | AD2: 213102 | AE2: 213201 | AF2: 213202 | AG2: 214101 | AH2: 214201 | AI2: 214202 | AJ2: 214203 | AK2: 215101 | AL2: 215201 | AM2: 215301 | AN2: 215401 | AO2: 221101 | AP2: 221201 | AQ2: 221301 | AR2: 221401 | AS2: 221501 | AT2: 221601 | AU2: 221602 | AV2: 221701 | AW2: 221801 | AX2: 222101 | AY2: 222201 | AZ2: 223101 | BA2: 223201 | BB2: 224101 | BC2: 224201 | BD2: 224301 | BE2: 224401 | BF2: 225101 | BG2: 225201 | BH2: 225301 | BI2: 225302 | BJ2: 225303 | BK2: 225304 | BL2: 225305 | BM2: 225401 | BN2: 225501 | BO2: 225601 | BP2: 225701 | BQ2: 225801 | BR2: 225901 | BS2: 226101 | BT2: 226201 | BU2: 226301 | BV2: 226401 | BW2: 227101 | BX2: 227102 | BY2: 227103 | BZ2: 227104 | CA2: 227105 | CB2: 227106 | CC2: 227107 | CD2: 227199 | CE2: 227201 | CF2: 227202 | CG2: 227203 | CH2: 227204 | CI2: 227205 | CJ2: 227206 | CK2: 227207 | CL2: 227208 | CM2: 227299 | CN2: 227301 | CO2: 228101 | CP2: 228201 | CQ2: 228301 | CR2: 228401 | CS2: 228501 | CT2: 228502 | CU2: 228503 | CV2: 228601 | CW2: 228602 | CX2: 228603 | CY2: 228604 | CZ2: 228701 | DA2: 228702 | DB2: 228703 | DC2: 228704 | DD2: 228705 | DE2: 228706 | DF2: 228801 | DG2: 228802 | DH2: 228803 | DI2: 229201 | DJ2: 229203 | DK2: 231101 | DL2: 231102 | DM2: 231201 | DN2: 231301 | DO2: 231302 | DP2: 231303 | DQ2: 231401 | DR2: 232101 | DS2: 232201 | DT2: 232301 | DU2: 233101 | DV2: 233201 | DW2: 233301 | DX2: 233401 | DY2: 233501 | DZ2: 233601 | EA2: 234101 | EB2: 234201 | EC2: 235101 | ED2: 235201 | EE2: 235301 | EF2: 235401 | EG2: 235501 | EH2: 236101 | EI2: 236102 | EJ2: 236103 | EK2: 236104 | EL2: 236105 | EM2: 236201 | EN2: 236202 | EO2: 236203 | EP2: 236304 | EQ2: 236305 | ER2: 236306 | ES2: 236401 | ET2: 236402 | EU2: 236403 | EV2: 236404 | EW2: 236405 | EX2: 236406 | EY2: 236407 | EZ2: 236901 | FA2: 237101 | FB2: 237102 | FC2: 237103 | FD2: 237104 | FE2: 237105 | FF2: 237106 | FG2: 237107 | FH2: 237201 | FI2: 237202 | FJ2: 237203 | FK2: 237204 | FL2: 237205 | FM2: 237206 | FN2: 237299 | FO2: 238101 | FP2: 238201 | FQ2: 239101 | FR2: 239102 | FS2: 239201 | FT2: 239301 | FU2: 239401 | FV2: 239501 | FW2: 239601 | FX2: 239701 | FY2: 239801 | FZ2: 239802 | GA2: 239901 | GB2: 239904 | GC2: 241201 | GD2: 241202 | GE2: 241203 | GF2: 241204 | GG2: 241205 | GH2: 261101 | GI2: 261201 | GJ2: 261301 | GK2: 261401 | GL2: 261901 | GM2: 262101 | GN2: 262201 | GO2: 262301 | GP2: 262401 | GQ2: 263101 | GR2: 263201 | GS2: 263301 | GT2: 263401 | GU2: 264101 | GV2: 264201 | GW2: 264301 | GX2: 264401 | GY2: 264501 | GZ2: 264601 | HA2: 264701 | HB2: 264801 | HC2: 265101 | HD2: 265201 | HE2: 265301 | HF2: 265401 | HG2: 265501 | HH2: 265601 | HI2: 265701 | HJ2: 265801 | HK2: 266101 | HL2: 266201 | HM2: 267101 | HN2: 267201 | HO2: 267301 | HP2: 267401 | HQ2: 267501 | HR2: 267601 | HS2: 267701 | HT2: 267801 | HU2: 267901 | HV2: 268101 | HW2: 268201 | HX2: 268301 | HY2: 268302 | HZ2: 268401 | IA2: 268501 | IB2: 268601 | IC2: 268701 | ID2: 268802 | IE2: 268803 | IF2: 268804 | IG2: 268901 | IH2: 269101 | II2: 269102 | IJ2: 269201 | IK2: 269202 | IL2: 269301 | IM2: 269401 | IN2: 269501 | IO2: 269502 | IP2: 269503 | IQ2: 2269901 | IR2: 271101 | IS2: 271201 | IT2: 271301 | IU2: 271401 | IV2: 272101 | IW2: 272201 | IX2: 272301 | IY2: 272401 | IZ2: 272501 | JA2: 272601 | JB2: 272701 | JC2: 272801 | JD2: 272901 | JE2: 273101 | JF2: 273201 | JG2: 274101 | JH2: 274201 | JI2: Totales | JJ2: TRANSF NO. | JK2: VALOR | JL2: RETENCION | JM2: AÑOS ANTERIORES | JN2: 2022 | JO2: Total | JP2: Proveedor Informal
FD3: 22638 | JI3: =SUM(A3:JH3) -> 22638 | JJ3: 208 | JK3: 22638 | JL3: =+JI3-JK3 -> 0
AW4: 760000 | JI4: =SUM(A4:JH4) -> 760000 | JJ4: =+JJ3+1 -> 209 | JK4: 722000 | JL4: =+JI4-JK4 -> 38000
DE5: 19496.18 | JI5: =SUM(A5:JH5) -> 19496.18 | JJ5: =+JJ4+1 -> 210 | JK5: 19496.18 | JL5: =+JI5-JK5 -> 0
DE6: 8860.18 | JI6: =SUM(A6:JH6) -> 8860.18 | JJ6: =+JJ5+1 -> 211 | JK6: 8860.18 | JL6: =+JI6-JK6 -> 0
DE7: 118075.52 | JI7: =SUM(A7:JH7) -> 118075.52 | JJ7: =+JJ6+1 -> 212 | JK7: 113072.32 | JL7: =+JI7-JK7 -> 5003.2
DE8: 14160 | JI8: =SUM(A8:JH8) -> 14160 | JJ8: =+JJ7+1 -> 213 | JK8: 14160 | JL8: =+JI8-JK8 -> 0
EA9: 24000 | JI9: =SUM(A9:JH9) -> 24000 | JJ9: =+JJ8+1 -> 214 | JK9: 22800 | JL9: =+JI9-JK9 -> 1200
FQ10: 1230740 | JI10: =SUM(A10:JH10) -> 1230740 | JJ10: =+JJ9+1 -> 215 | JK10: 1178590 | JL10: =+JI10-JK10 -> 52150
CH11: 247800 | JI11: =SUM(A11:JH11) -> 247800 | JJ11: =+JJ10+1 -> 216 | JK11: 237300 | JL11: =+JI11-JK11 -> 10500
CH12: 212400 | JI12: =SUM(A12:JH12) -> 212400 | JJ12: =+JJ11+1 -> 217 | JK12: 203400 | JL12: =+JI12-JK12 -> 9000
CM13: 409306.6 | JI13: =SUM(A13:JH13) -> 409306.6 | JJ13: =+JJ12+1 -> 218 | JK13: 391963.1 | JL13: =+JI13-JK13 -> 17343.5
CL14: 594720 | JI14: =SUM(A14:JH14) -> 594720 | JJ14: =+JJ13+1 -> 219 | JK14: 569520 | JL14: =+JI14-JK14 -> 25200
HL15: 58764 | JI15: =SUM(A15:JH15) -> 58764 | JJ15: =+JJ14+1 -> 220 | JK15: 56274 | JL15: =+JI15-JK15 -> 2490
CJ16: 3026.1 | JI16: =SUM(A16:JH16) -> 3026.1 | JJ16: =+JJ15+1 -> 221 | JK16: 3026.1 | JL16: =+JI16-JK16 -> 0
HD17: 272200 | JI17: =SUM(A17:JH17) -> 272200 | JJ17: =+JJ16+1 -> 222 | JK17: 260666.1 | JL17: =+JI17-JK17 -> 11533.9
CS18: 147500 | JI18: =SUM(A18:JH18) -> 147500 | JJ18: =+JJ17+1 -> 223 | JK18: 118750 | JL18: =+JI18-JK18 -> 28750
AY19: 212400 | DV19: 26550 | JI19: =SUM(A19:JH19) -> 238950 | JJ19: =+JJ18+1 -> 224 | JK19: 228825 | JL19: =+JI19-JK19 -> 10125
BI20: 298861.54 | JI20: =SUM(A20:JH20) -> 298861.54 | JJ20: =+JJ19+1 -> 225 | JK20: 298861.54 | JL20: =+JI20-JK20 -> 0
DE21: 165375 | JI21: =SUM(A21:JH21) -> 165375 | JJ21: =+JJ20+1 -> 226 | JK21: 165375 | JL21: =+JI21-JK21 -> 0
BC22: 8000 | JI22: =SUM(A22:JH22) -> 8000 | JJ22: =+JJ21+1 -> 227 | JK22: 7600 | JL22: =+JI22-JK22 -> 400
EG23: 77390.01 | ER23: 2100 | FY23: 31450 | GB23: 1000 | HI23: 10500.01 | JI23: =SUM(A23:JH23) -> 122440.02 | JJ23: =+JJ22+1 -> 228 | JK23: 117251.88 | JL23: =+JI23-JK23 -> 5188.14
DE24: 165375 | JI24: =SUM(A24:JH24) -> 165375 | JJ24: =+JJ23+1 -> 229 | JK24: 165375 | JL24: =+JI24-JK24 -> 0
FN25: 431408 | JI25: =SUM(A25:JH25) -> 431408 | JJ25: =+JJ24+1 -> 230 | JK25: 413128 | JL25: =+JI25-JK25 -> 18280
DK26: 275330 | JI26: =SUM(A26:JH26) -> 275330 | JJ26: =+JJ25+1 -> 231 | JK26: 261563.5 | JL26: =+JI26-JK26 -> 13766.5
GO27: 389046 | JI27: =SUM(A27:JH27) -> 389046 | JJ27: =+JJ26+1 -> 232 | JK27: 372561 | JL27: =+JI27-JK27 -> 16485
AW28: 50000 | JI28: =SUM(A28:JH28) -> 50000 | JJ28: =+JJ27+1 -> 233 | JK28: 50000 | JL28: =+JI28-JK28 -> 0
AQ29: 211904.05 | JI29: =SUM(A29:JH29) -> 211904.05 | JJ29: =+JJ28+1 -> 234 | JK29: 211904.05 | JL29: =+JI29-JK29 -> 0
FD30: 22638 | JI30: =SUM(A30:JH30) -> 22638 | JJ30: =+JJ29+1 -> 235 | JK30: 22638 | JL30: =+JI30-JK30 -> 0
DK31: 85400 | JI31: =SUM(A31:JH31) -> 85400 | JJ31: =+JJ30+1 -> 236 | JK31: 81130 | JL31: =+JI31-JK31 -> 4270
AY32: 236295 | JI32: =SUM(A32:JH32) -> 236295 | JJ32: =+JJ31+1 -> 237 | JK32: 226282.5 | JL32: =+JI32-JK32 -> 10012.5
AY33: 132750 | JI33: =SUM(A33:JH33) -> 132750 | JJ33: =+JJ32+1 -> 238 | JK33: 127125 | JL33: =+JI33-JK33 -> 5625
FN34: 395831 | JI34: =SUM(A34:JH34) -> 395831 | JJ34: =+JJ33+1 -> 239 | JK34: 379058.5 | JL34: =+JI34-JK34 -> 16772.5
EA35: 128800 | JI35: =SUM(A35:JH35) -> 128800 | JJ35: =+JJ34+1 -> 240 | JK35: 128800 | JL35: =+JI35-JK35 -> 0
FT36: 168800 | JI36: =SUM(A36:JH36) -> 168800 | JJ36: =+JJ35+1 -> 241 | JK36: 160360 | JL36: =+JI36-JK36 -> 8440
EH37: 1483.02 | EN37: 20574.93 | FW37: 62731.97 | FY37: 118290 | FZ37: 34881 | GB37: 1230.48 | JI37: =SUM(A37:JH37) -> 239191.4 | JJ37: =+JJ36+1 -> 242 | JK37: 227231.83 | JL37: =+JI37-JK37 -> 11959.57
CZ38: 39530 | JI38: =SUM(A38:JH38) -> 39530 | JJ38: =+JJ37+1 -> 243 | JK38: 37855 | JL38: =+JI38-JK38 -> 1675
AW39: 760000 | JI39: =SUM(A39:JH39) -> 760000 | JJ39: =+JJ38+1 -> 244 | JK39: 722000 | JL39: =+JI39-JK39 -> 38000
FA40: 172000 | JI40: =SUM(A40:JH40) -> 172000 | JJ40: 246 | JK40: 170573.26 | JL40: =+JI40-JK40 -> 1426.74
DE41: 10000 | JI41: =SUM(A41:JH41) -> 10000 | JJ41: 247 | JK41: 10000 | JL41: =+JI41-JK41 -> 0
GD42: 3600 | JI42: =SUM(A42:JH42) -> 3600 | JJ42: 37252 | JK42: 3600 | JL42: =+JI42-JK42 -> 0
GD43: 10000 | JI43: =SUM(A43:JH43) -> 10000 | JJ43: 37253 | JK43: 10000 | JL43: =+JI43-JK43 -> 0
CM44: 18061.23 | JI44: =SUM(A44:JH44) -> 18061.23 | JJ44: 37254 | JK44: 15000 | JL44: =+JI44-JK44 -> 3061.23
GA45: 55105.58 | JI45: =SUM(A45:JH45) -> 55105.58 | JJ45: 37255 | JK45: 55105.58 | JL45: =+JI45-JK45 -> 0
CL46: 9632.66 | JI46: =SUM(A46:JH46) -> 9632.66 | JJ46: 37256 | JK46: 8000 | JL46: =+JI46-JK46 -> 1632.66
CL47: 12402.05 | JI47: =SUM(A47:JH47) -> 12402.05 | JJ47: 37257 | JK47: 10300 | JL47: =+JI47-JK47 -> 2102.05
CD48: 36122.6 | JI48: =SUM(A48:JH48) -> 36122.6 | JJ48: 37258 | JK48: 30000.01 | JL48: =+JI48-JK48 -> 6122.59
CD49: 8428.57 | JI49: =SUM(A49:JH49) -> 8428.57 | JJ49: 37259 | JK49: 7000 | JL49: =+JI49-JK49 -> 1428.57
CA50: 22877.56 | JI50: =SUM(A50:JH50) -> 22877.56 | JJ50: 37260 | JK50: 19000 | JL50: =+JI50-JK50 -> 3877.56
JI51: =SUM(A51:JH51) -> 0 | JJ51: 37261 | JL51: =+JI51-JK51 -> 0
DE52: 21000 | JI52: =SUM(A52:JH52) -> 21000 | JJ52: 37262 | JK52: 21000 | JL52: =+JI52-JK52 -> 0
CA53: 18061.22 | JI53: =SUM(A53:JH53) -> 18061.22 | JJ53: 37263 | JK53: 15000 | JL53: =+JI53-JK53 -> 3061.22
CA54: 21673.47 | JI54: =SUM(A54:JH54) -> 21673.47 | JJ54: 37264 | JK54: 18000.01 | JL54: =+JI54-JK54 -> 3673.46
CA55: 18061.22 | JI55: =SUM(A55:JH55) -> 18061.22 | JJ55: 37265 | JK55: 15000 | JL55: =+JI55-JK55 -> 3061.22
JI56: =SUM(A56:JH56) -> 0 | JJ56: 37266 | JL56: =+JI56-JK56 -> 0
GD57: 3600 | JI57: =SUM(A57:JH57) -> 3600 | JJ57: 37267 | JK57: 3600 | JL57: =+JI57-JK57 -> 0
GD58: 20000 | JI58: =SUM(A58:JH58) -> 20000 | JJ58: 37268 | JK58: 20000 | JL58: =+JI58-JK58 -> 0
GA59: 54251.88 | JI59: =SUM(A59:JH59) -> 54251.88 | JJ59: 37269 | JK59: 54251.88 | JL59: =+JI59-JK59 -> 0
GC60: 22500 | JI60: =SUM(A60:JH60) -> 22500 | JJ60: 37270 | JK60: 22500 | JL60: =+JI60-JK60 -> 0
GC61: 7871 | JI61: =SUM(A61:JH61) -> 7871 | JJ61: 37271 | JK61: 7871 | JL61: =+JI61-JK61 -> 0
JI62: =SUM(A62:JH62) -> 0 | JL62: =+JI62-JK62 -> 0
A63: =SUM(A3:A62) -> 0 | B63: =SUM(B3:B62) -> 0 | C63: =SUM(C3:C62) -> 0 | D63: =SUM(D3:D62) -> 0 | E63: =SUM(E3:E62) -> 0 | F63: =SUM(F3:F62) -> 0 | G63: =SUM(G3:G62) -> 0 | H63: =SUM(H3:H62) -> 0 | ... JI63: =SUM(JI3:JI62) -> 9254860.6
A64: =+A63 -> 0 | B64: =+B63 -> 0 | C64: =+C63 -> 0 | D64: =+D63 -> 0 | E64: =+E63 -> 0 | F64: =+F63 -> 0 | G64: =+G63 -> 0 | H64: =+H63 -> 0 | ... JI64: =+JI63 -> 9254860.6

Sheet CUENTA T FONDO 100
A1: D E S G L O S E D E L A S C U E N T A S
A2: 211101 | B2: 211102 | C2: 211103 | D2: 211104 | E2: 211105 | F2: 211106 | G2: 211203 | H2: 211205 | I2: 211206 | J2: 211208 | K2: 211209 | L2: 211211 | M2: 211301 | N2: 211401 | O2: 211501 | P2: 211502 | Q2: 211503 | R2: 211504 | S2: 212101 | T2: 212201 | U2: 212203 | V2: 212204 | W2: 212205 | X2: 212206 | Y2: 212207 | Z2: 212208 | AA2: 212209 | AB2: 212210 | AC2: 213101 | AD2: 213102 | AE2: 213201 | AF2: 213202 | AG2: 214101 | AH2: 214201 | AI2: 214202 | AJ2: 214203 | AK2: 215101 | AL2: 215201 | AM2: 215301 | AN2: 215401 | AO2: 221101 | AP2: 221201 | AQ2: 221301 | AR2: 221401 | AS2: 221501 | AT2: 221601 | AU2: 221602 | AV2: 221701 | AW2: 221801 | AX2: 222101 | AY2: 222201 | AZ2: 223101 | BA2: 223201 | BB2: 224101 | BC2: 224201 | BD2: 224301 | BE2: 224401 | BF2: 225101 | BG2: 225201 | BH2: 225301 | BI2: 225302 | BJ2: 225303 | BK2: 225304 | BL2: 225305 | BM2: 225401 | BN2: 225501 | BO2: 225601 | BP2: 225701 | BQ2: 225801 | BR2: 225901 | BS2: 226101 | BT2: 226201 | BU2: 226301 | BV2: 226401 | BW2: 227101 | BX2: 227102 | BY2: 227103 | BZ2: 227104 | CA2: 227105 | CB2: 227106 | CC2: 227107 | CD2: 227199 | CE2: 227201 | CF2: 227202 | CG2: 227203 | CH2: 227204 | CI2: 227205 | CJ2: 227206 | CK2: 227207 | CL2: 227208 | CM2: 227299 | CN2: 227301 | CO2: 228101 | CP2: 228201 | CQ2: 228301 | CR2: 228401 | CS2: 228501 | CT2: 228502 | CU2: 228503 | CV2: 228601 | CW2: 228602 | CX2: 228603 | CY2: 228604 | CZ2: 228701 | DA2: 228702 | DB2: 228703 | DC2: 228704 | DD2: 228705 | DE2: 228706 | DF2: 228801 | DG2: 228802 | DH2: 228803 | DI2: 229201 | DJ2: 229203 | DK2: 231101 | DL2: 231102 | DM2: 231201 | DN2: 231301 | DO2: 231302 | DP2: 231303 | DQ2: 231401 | DR2: 232101 | DS2: 232201 | DT2: 232301 | DU2: 233101 | DV2: 233201 | DW2: 233301 | DX2: 233401 | DY2: 233501 | DZ2: 233601 | EA2: 234101 | EB2: 234201 | EC2: 235101 | ED2: 235201 | EE2: 235301 | EF2: 235401 | EG2: 235501 | EH2: 236101 | EI2: 236102 | EJ2: 236103 | EK2: 236104 | EL2: 236105 | EM2: 236201 | EN2: 236202 | EO2: 236203 | EP2: 236304 | EQ2: 236305 | ER2: 236306 | ES2: 236401 | ET2: 236402 | EU2: 236403 | EV2: 236404 | EW2: 236405 | EX2: 236406 | EY2: 236407 | EZ2: 236901 | FA2: 237101 | FB2: 237102 | FC2: 237103 | FD2: 237104 | FE2: 237105 | FF2: 237106 | FG2: 237107 | FH2: 237201 | FI2: 237202 | FJ2: 237203 | FK2: 237204 | FL2: 237205 | FM2: 237206 | FN2: 237299 | FO2: 238101 | FP2: 238201 | FQ2: 239101 | FR2: 239102 | FS2: 239201 | FT2: 239301 | FU2: 239401 | FV2: 239501 | FW2: 239601 | FX2: 239701 | FY2: 239801 | FZ2: 239802 | GA2: 239901 | GB2: 239904 | GC2: 241201 | GD2: 241202 | GE2: 241203 | GF2: 241204 | GG2: 241205 | GH2: 261101 | GI2: 261201 | GJ2: 261301 | GK2: 261401 | GL2: 261901 | GM2: 262101 | GN2: 262201 | GO2: 262301 | GP2: 262401 | GQ2: 263101 | GR2: 263201 | GS2: 263301 | GT2: 263401 | GU2: 264101 | GV2: 264201 | GW2: 264301 | GX2: 264401 | GY2: 264501 | GZ2: 264601 | HA2: 264701 | HB2: 264801 | HC2: 265101 | HD2: 265201 | HE2: 265301 | HF2: 265401 | HG2: 265501 | HH2: 265601 | HI2: 265701 | HJ2: 265801 | HK2: 266101 | HL2: 266201 | HM2: 267101 | HN2: 267201 | HO2: 267301 | HP2: 267401 | HQ2: 267501 | HR2: 267601 | HS2: 267701 | HT2: 267801 | HU2: 267901 | HV2: 268101 | HW2: 268201 | HX2: 268301 | HY2: 268302 | HZ2: 268401 | IA2: 268501 | IB2: 268601 | IC2: 268701 | ID2: 268802 | IE2: 268803 | IF2: 268804 | IG2: 268901 | IH2: 269101 | II2: 269102 | IJ2: 269201 | IK2: 269202 | IL2: 269301 | IM2: 269401 | IN2: 269501 | IO2: 269502 | IP2: 269503 | IQ2: 2269901 | IR2: 271101 | IS2: 271201 | IT2: 271301 | IU2: 271401 | IV2: 272101 | IW2: 272201 | IX2: 272301 | IY2: 272401 | IZ2: 272501 | JA2: 272601 | JB2: 272701 | JC2: 272801 | JD2: 272901 | JE2: 273101 | JF2: 273201 | JG2: 274101 | JH2: 274201 | JI2: Totales | JJ2: LIBRAMIENTO | JK2: VALOR | JL2: RETENCION | JM2: AÑOS ANTERIORES | JN2: 2024 | JO2: Total | JP2: Proveedor Informal
FT3: 578891.48 | JI3: =SUM(A3:JH3) -> 578891.48 | JJ3: 2719 | JO3: =+JM3+JN3 -> 0
EA4: 180000 | JI4: =SUM(A4:JH4) -> 180000 | JJ4: 2724
EG5: 387807.15 | JI5: =SUM(A5:JH5) -> 387807.15 | JJ5: 2725
GL6: 1361145 | JI6: =SUM(A6:JH6) -> 1361145 | JJ6: 2729
DV7: 265393.8 | JI7: =SUM(A7:JH7) -> 265393.8 | JJ7: 2735
FQ8: 342200 | JI8: =SUM(A8:JH8) -> 342200 | JJ8: 2739
EA9: 200010 | JI9: =SUM(A9:JH9) -> 200010 | JJ9: 2743
FT10: 59000 | JI10: =SUM(A10:JH10) -> 59000 | JJ10: 2747
GQ11: 70800 | JI11: =SUM(A11:JH11) -> 70800 | JJ11: 2751
EG12: 72900.1 | JI12: =SUM(A12:JH12) -> 72900.1 | JJ12: 2756
GQ13: 671774 | JI13: =SUM(A13:JH13) -> 671774 | JJ13: 2760
GQ14: 1999226.8 | JI14: =SUM(A14:JH14) -> 1999226.8 | JJ14: 2764
BW15: 74179.46 | FY15: 809192.93 | JI15: =SUM(A15:JH15) -> 883372.39 | JJ15: 2771
AV16: 60535 | JI16: =SUM(A16:JH16) -> 60535 | JJ16: 2775
FJ17: 161376 | JI17: =SUM(A17:JH17) -> 161376 | JJ17: 2794
FJ18: 16605 | JI18: =SUM(A18:JH18) -> 16605 | JJ18: 2800
FT19: 220312.32 | JI19: =SUM(A19:JH19) -> 220312.32 | JJ19: 2804
FJ20: 185670.37 | JI20: =SUM(A20:JH20) -> 185670.37 | JJ20: 2808
FT21: 270007.6 | JI21: =SUM(A21:JH21) -> 270007.6 | JJ21: 2812
GK22: 251876.14 | JI22: =SUM(A22:JH22) -> 251876.14 | JJ22: 2817
FN23: 168860.36 | FZ23: 15463.9 | JI23: =SUM(A23:JH23) -> 184324.26 | JJ23: 2821
EG24: 26432 | FQ24: 5074 | JI24: =SUM(A24:JH24) -> 31506 | JJ24: 2825
FJ25: 162040 | FT25: 85083.9 | JI25: =SUM(A25:JH25) -> 247123.9 | JJ25: 2830
FJ26: 43108 | JI26: =SUM(A26:JH26) -> 43108 | JJ26: 2834
DW27: 39530 | FS27: 45902 | GB27: 1699.2 | JI27: =SUM(A27:JH27) -> 87131.2 | JJ27: 2838
Q28: 12100 | JI28: =SUM(A28:JH28) -> 12100 | JJ28: 2840
GH29: 216333.29 | JI29: =SUM(A29:JH29) -> 216333.29 | JJ29: 2847
FT30: 175000 | JI30: =SUM(A30:JH30) -> 175000 | JJ30: 2851
EA31: 210000 | FJ31: 7120 | JI31: =SUM(A31:JH31) -> 217120 | JJ31: 2855
FT32: 270820 | JI32: =SUM(A32:JH32) -> 270820 | JJ32: 2859
GR33: 239687.5 | JI33: =SUM(A33:JH33) -> 239687.5 | JJ33: 2863
EA34: 200000 | JI34: =SUM(A34:JH34) -> 200000 | JJ34: 2872
DS35: 1365869.3 | JI35: =SUM(A35:JH35) -> 1365869.3 | JJ35: 2876
DK36: 521100 | JI36: =SUM(A36:JH36) -> 521100 | JJ36: 2880
GQ37: 1298000 | JI37: =SUM(A37:JH37) -> 1298000 | JJ37: 2884
FT38: 323615 | JI38: =SUM(A38:JH38) -> 323615 | JJ38: 2888
FT39: 401200 | JI39: =SUM(A39:JH39) -> 401200 | JJ39: 2892
EA40: 1105000 | JI40: =SUM(A40:JH40) -> 1105000 | JJ40: 2900
EA41: 197000 | JI41: =SUM(A41:JH41) -> 197000 | JJ41: 2905
EA42: 270000 | JI42: =SUM(A42:JH42) -> 270000 | JJ42: 2909
EA43: 240000 | JI43: =SUM(A43:JH43) -> 240000 | JJ43: 2913
EA44: 180000 | JI44: =SUM(A44:JH44) -> 180000 | JJ44: 2917
EG45: 168000.97 | JI45: =SUM(A45:JH45) -> 168000.97 | JJ45: 2927
EA46: 120000 | JI46: =SUM(A46:JH46) -> 120000 | JJ46: 2931
EA47: 100350 | JI47: =SUM(A47:JH47) -> 100350 | JJ47: 2935
DU48: 12681.46 | FN48: 61810.76 | FQ48: 97981.3 | FT48: 16549.5 | JI48: =SUM(A48:JH48) -> 189023.02 | JJ48: 2939
GT49: 37217.2 | JI49: =SUM(A49:JH49) -> 37217.2 | JJ49: 2944
W50: 45000 | JI50: =SUM(A50:JH50) -> 45000 | JJ50: 2957
J51: 1130531 | AK51: 80154.65 | AL51: 80267.7 | AM51: 13466.76 | JI51: =SUM(A51:JH51) -> 1304420.1 | JJ51: 2959
A52: 57782790 | S52: 2707086.2 | Z52: 306200 | AB52: =101150.82+185443.17 -> 286593.99 | AK52: 4096800.5 | AL52: 4102579.8 | AM52: 692105.17 | JI52: =SUM(A52:JH52) -> 69974156 | JJ52: 2961
EA53: 128000 | JI53: =SUM(A53:JH53) -> 128000 | JJ53: 2989
EA54: 210000 | JI54: =SUM(A54:JH54) -> 210000 | JJ54: 2990
EA55: 245000 | JI55: =SUM(A55:JH55) -> 245000 | JJ55: 2996
FT56: 177000 | JI56: =SUM(A56:JH56) -> 177000 | JJ56: 3000
EA57: 210000 | JI57: =SUM(A57:JH57) -> 210000 | JJ57: 3004
EA58: 248500 | JI58: =SUM(A58:JH58) -> 248500 | JJ58: 3010
EA59: 92000 | JI59: =SUM(A59:JH59) -> 92000 | JJ59: 3014
FT60: 160159.96 | JI60: =SUM(A60:JH60) -> 160159.96 | JJ60: 3017
EA61: 210000 | JI61: =SUM(A61:JH61) -> 210000 | JJ61: 3024
EA62: 70623 | JI62: =SUM(A62:JH62) -> 70623 | JJ62: 3028
FT63: 213731.65 | JI63: =SUM(A63:JH63) -> 213731.65 | JJ63: 3032
FT64: 259600 | JI64: =SUM(A64:JH64) -> 259600 | JJ64: 3036
EA65: 270000 | JI65: =SUM(A65:JH65) -> 270000 | JJ65: 3041
FT66: 408600 | JI66: =SUM(A66:JH66) -> 408600 | JJ66: 3043
FT67: 259234.2 | JI67: =SUM(A67:JH67) -> 259234.2 | JJ67: 3046
FT68: 271456 | JI68: =SUM(A68:JH68) -> 271456 | JJ68: 3060
EA69: 88500 | JI69: =SUM(A69:JH69) -> 88500 | JJ69: 3064
EA70: 97500 | JI70: =SUM(A70:JH70) -> 97500 | JJ70: 3068
EA71: 225900 | JI71: =SUM(A71:JH71) -> 225900 | JJ71: 3072
FT72: 206500 | JI72: =SUM(A72:JH72) -> 206500 | JJ72: 3076
FT73: 211975.2 | JI73: =SUM(A73:JH73) -> 211975.2 | JJ73: 3080
BW74: 1649337.3 | JI74: =SUM(A74:JH74) -> 1649337.3 | JJ74: 3088
FT75: 295000 | JI75: =SUM(A75:JH75) -> 295000 | JJ75: 3096
FT76: 20650 | JI76: =SUM(A76:JH76) -> 20650 | JJ76: 3099
EA77: 148800 | FT77: 18408 | JI77: =SUM(A77:JH77) -> 167208 | JJ77: 3102
EA78: 172438 | FT78: 33580.44 | JI78: =SUM(A78:JH78) -> 206018.44 | JJ78: 3105
FT79: 456188 | JI79: =SUM(A79:JH79) -> 456188 | JJ79: 3109
FT80: 161955 | JI80: =SUM(A80:JH80) -> 161955 | JJ80: 3112
FB81: 664800 | JI81: =SUM(A81:JH81) -> 664800 | JJ81: 3130
CF82: 875914 | JI82: =SUM(A82:JH82) -> 875914 | JJ82: 3131
HJ83: 43070 | JI83: =SUM(A83:JH83) -> 43070 | JJ83: 3135
DK84: 35400 | FQ84: 213249.6 | JI84: =SUM(A84:JH84) -> 248649.6 | JJ84: 3144
HF85: 232932 | JI85: =SUM(A85:JH85) -> 232932 | JJ85: 3147
FQ86: 265500 | JI86: =SUM(A86:JH86) -> 265500 | JJ86: 3155
GB87: 185850 | JI87: =SUM(A87:JH87) -> 185850 | JJ87: 3158
HH88: 1700000 | JI88: =SUM(A88:JH88) -> 1700000 | JJ88: 3159
DT89: 211281.36 | JI89: =SUM(A89:JH89) -> 211281.36 | JJ89: 3168
CJ90: 849600 | JI90: =SUM(A90:JH90) -> 849600 | JJ90: 3169
FU91: 45076 | JI91: =SUM(A91:JH91) -> 45076 | JJ91: 3171
GR92: 275943 | JI92: =SUM(A92:JH92) -> 275943 | JJ92: 3177
DP93: 153400.21 | JI93: =SUM(A93:JH93) -> 153400.21 | JJ93: 3180
FS94: 6844 | JI94: =SUM(A94:JH94) -> 6844 | JJ94: 3187
FQ95: 40415 | JI95: =SUM(A95:JH95) -> 40415 | JJ95: 3192
FQ96: 231988 | JI96: =SUM(A96:JH96) -> 231988 | JJ96: 3195
GH97: 55696 | GK97: 44604 | JI97: =SUM(A97:JH97) -> 100300 | JJ97: 3205
FV98: 8684.8 | JI98: =SUM(A98:JH98) -> 8684.8 | JJ98: 3208
FS99: 50150 | FV99: 46020 | JI99: =SUM(A99:JH99) -> 96170 | JJ99: 3213
FS100: 0 | GH100: 23010 | HJ100: 30309.61 | JI100: =SUM(A100:JH100) -> 53319.61 | JJ100: 3216
...

Sheet CONS. FUENTES FINAN
A1: Form. No.6 SRS
A3: Servicio Nacional de Salud
A4: Dirección de Fizcalización
A5: Consolidado de Ingresos y Gastos por Fuente de Financiamiento
A6: HOSPITAL MATERNO INFANTIL SAN LORENZO DE LOS MINA
A7: JULIO 2025
C8: Ingresos Generales:
E9: 1.- Balance Inicial / Fuente:
E10: Anticipo Financiero | H10: Otros Aportes | L10: Contraseña: 0001
E11: Transferencias Corrientes
E12: Venta de Servicios | G12: 1771845.5
E13: 2.- Ingresos por Fuente / Cuenta
E14: Anticipo Financiero | H14: Otros Aportes | I14: =+'INGR SEGUN ORIGEN'!E47 -> 834400 | L14: OBJETAL | M14: FR | N14: VS
E15: Transferencias Corrientes | G15: =12593841.17+3169632.08+84553321.83 -> 1.003168e+08 | H15: Aportes Nomina SNS | I15: 0 | L15: 2.1 | M15: =G26 -> 0 | N15: =H26 -> 0
E16: Venta de Servicios | G16: =+'INGR SEGUN ORIGEN'!E39 -> 10942139 | L16: 2.2 | M16: =G87 -> 0 | N16: =H87 -> 1213383.4
H17: TOTAL INGRESOS RDS | I17: =+G10+G11+G12+I10+G14+G15+G16+I14+I15 -> 1.1386518e+08 | L17: 2.3 | M17: ='[1]CONS. FUENTES FINAN'!G212 -> 14433131 | N17: ='[1]CONS. FUENTES FINAN'!H212 -> 2432378.3
L18: 2.4 | M18: =G330 -> 0 | N18: =H330 -> 23400
L19: 2.6 | M19: =G336 -> 0 | N19: =H336 -> 3887510
L20: 2.7 | M20: ='[1]CONS. FUENTES FINAN'!G463 -> 0 | N20: ='[1]CONS. FUENTES FINAN'!H463 -> 0
A21: 1 | F21: 2 | G21: 3 | I21: 4 | J21: 5
A22: Código Presupuestario | F22: Descripción Gasto por Cuenta | G22: Distribución del Gasto por Fuente de Financiamiento | I22: TOTAL | J22: %
A23: Tipo | B23: Objeto | C23: Cuenta | D23: Sub-Cuenta | E23: Auxiliar | G23: Fondo 100 | H23: Venta de Servicios/ Otros Aportes
A25: 2 | F25: Gastos | G25: =+G26+G87+G212+G330+G336+G463 -> 0 | H25: =+H26+H87+H212+H330+H336+H463 -> 7556671.6 | I25: =SUM(G25:H25) -> 7556671.6 | J25: =+J26+J87+J212+J330+J336+J463 -> 1
A26: 2 | B26: 1 | F26: Servicios Personales | G26: =+G27+G51+G64+G71+G78 -> 0 | H26: =+H27+H51+H64+H71+H78 -> 0 | I26: =SUM(G26:H26) -> 0 | J26: =I26/$I$25 -> 0
A27: 2 | B27: 1 | C27: 1 | F27: Remuneraciones | G27: =+G28+G35+G42+G44+G46 -> 0 | H27: =+H28+H35+H42+H44+H46 -> 0 | I27: =SUM(G27:H27) -> 0 | J27: =I27/$I$25 -> 0
A28: 2 | B28: 1 | C28: 1 | D28: 1 | F28: Remuneraciones al personal fijo | G28: =SUM(G29:G34) -> 0 | H28: =SUM(H29:H34) -> 0 | I28: =SUM(G28:H28) -> 0 | J28: =I28/$I$25 -> 0
A29: 2 | B29: 1 | C29: 1 | D29: 1 | E29: 01 | F29: Sueldos a empleados fijos | G29: ='[1]CUENTA T FONDO 100'!A145 -> 0 | H29: ='[1]CUENTA T VS'!A96 -> 0 | I29: =SUM(G29:H29) -> 0 | J29: =I29/$I$25 -> 0
A30: 2 | B30: 1 | C30: 1 | D30: 1 | E30: 02 | F30: Sueldos a médicos | G30: ='[1]CUENTA T FONDO 100'!B145 -> 0 | H30: ='[1]CUENTA T VS'!B96 -> 0 | I30: =SUM(G30:H30) -> 0 | J30: =I30/$I$25 -> 0
A31: 2 | B31: 1 | C31: 1 | D31: 1 | E31: 03 | F31: Ascensos a militares | G31: ='[1]CUENTA T FONDO 100'!C145 -> 0 | H31: ='[1]CUENTA T VS'!C96 -> 0 | I31: =SUM(G31:H31) -> 0 | J31: =I31/$I$25 -> 0
A32: 2 | B32: 1 | C32: 1 | D32: 1 | E32: 04 | F32: Nuevas plazas maestros | G32: ='[1]CUENTA T FONDO 100'!D145 -> 0 | H32: ='[1]CUENTA T VS'!D96 -> 0 | I32: =SUM(G32:H32) -> 0 | J32: =I32/$I$25 -> 0
A33: 2 | B33: 1 | C33: 1 | D33: 1 | E33: 05 | F33: Incentivos y escalafón | G33: ='[1]CUENTA T FONDO 100'!E145 -> 0 | H33: ='[1]CUENTA T VS'!E96 -> 0 | I33: =SUM(G33:H33) -> 0 | J33: =I33/$I$25 -> 0
A34: 2 | B34: 1 | C34: 1 | D34: 1 | E34: 06 | F34: Nuevas plazas a médicos | G34: ='[1]CUENTA T FONDO 100'!F145 -> 0 | H34: ='[1]CUENTA T VS'!F96 -> 0 | I34: =SUM(G34:H34) -> 0 | J34: =I34/$I$25 -> 0
A35: 2 | B35: 1 | C35: 1 | D35: 2 | F35: Remuneraciones al personal con carácter transitorio | G35: =SUM(G36:G41) -> 0 | H35: =SUM(H36:H41) -> 0 | I35: =SUM(G35:H35) -> 0
A36: 2 | B36: 1 | C36: 1 | D36: 2 | E36: 03 | F36: Suplencias | G36: ='[1]CUENTA T FONDO 100'!G145 -> 0 | H36: ='[1]CUENTA T VS'!G96 -> 0 | I36: =SUM(G36:H36) -> 0 | J36: =I36/$I$25 -> 0
A37: 2 | B37: 1 | C37: 1 | D37: 2 | E37: 05 | F37: Sueldo al personal nominal en período probatorio | G37: ='[1]CUENTA T FONDO 100'!H145 -> 0 | H37: ='[1]CUENTA T VS'!H96 -> 0 | I37: =SUM(G37:H37) -> 0 | J37: =I37/$I$25 -> 0
A38: 2 | B38: 1 | C38: 1 | D38: 2 | E38: 06 | F38: Jornales | G38: ='[1]CUENTA T FONDO 100'!I145 -> 0 | H38: ='[1]CUENTA T VS'!I96 -> 0 | I38: =SUM(G38:H38) -> 0 | J38: =I38/$I$25 -> 0
A39: 2 | B39: 1 | C39: 1 | D39: 2 | E39: 08 | F39: Empleados temporales | G39: ='[1]CUENTA T FONDO 100'!J145 -> 0 | H39: ='[1]CUENTA T VS'!J96 -> 0 | I39: =SUM(G39:H39) -> 0 | J39: =I39/$I$25 -> 0
A40: 2 | B40: 1 | C40: 1 | D40: 2 | E40: 09 | F40: Personal de carácter eventual | G40: ='[1]CUENTA T FONDO 100'!K145 -> 0 | H40: ='[1]CUENTA T VS'!K96 -> 0 | I40: =SUM(G40:H40) -> 0 | J40: =I40/$I$25 -> 0
A41: 2 | B41: 1 | C41: 1 | D41: 2 | E41: 11 | F41: Interinato | G41: ='[1]CUENTA T FONDO 100'!L145 -> 0 | H41: ='[1]CUENTA T VS'!L96 -> 0 | I41: =SUM(G41:H41) -> 0 | J41: =I41/$I$25 -> 0
A42: 2 | B42: 1 | C42: 1 | D42: 3 | F42: Sueldos al personal fijo en trámite de pensiones | G42: =SUM(G43) -> 0 | H42: =SUM(H43) -> 0 | I42: =SUM(G42:H42) -> 0
A43: 2 | B43: 1 | C43: 1 | D43: 3 | E43: 01 | F43: Sueldos al personal fijo en trámite de pensiones | G43: ='[1]CUENTA T FONDO 100'!M145 -> 0 | H43: ='[1]CUENTA T VS'!M96 -> 0 | I43: =SUM(G43:H43) -> 0 | J43: =I43/$I$25 -> 0
A44: 2 | B44: 1 | C44: 1 | D44: 4 | F44: Sueldo anual no. 13 | G44: =SUM(G45) -> 0 | H44: =SUM(H45) -> 0 | I44: =SUM(G44:H44) -> 0
A45: 2 | B45: 1 | C45: 1 | D45: 4 | E45: 01 | F45: Sueldo anual no. 13 | G45: ='[1]CUENTA T FONDO 100'!N145 -> 0 | H45: ='[1]CUENTA T VS'!N96 -> 0 | I45: =SUM(G45:H45) -> 0 | J45: =I45/$I$25 -> 0
A46: 2 | B46: 1 | C46: 1 | D46: 5 | F46: Prestaciones económinas | G46: =SUM(G47:G50) -> 0 | H46: =SUM(H47:H50) -> 0 | I46: =SUM(G46:H46) -> 0
A47: 2 | B47: 1 | C47: 1 | D47: 5 | E47: 01 | F47: Prestaciones económinas | G47: ='[1]CUENTA T FONDO 100'!O145 -> 0 | H47: ='[1]CUENTA T VS'!O96 -> 0 | I47: =SUM(G47:H47) -> 0 | J47: =I47/$I$25 -> 0
A48: 2 | B48: 1 | C48: 1 | D48: 5 | E48: 02 | F48: Pago de porcentaje por desvinculación de cargo | G48: ='[1]CUENTA T FONDO 100'!P145 -> 0 | H48: ='[1]CUENTA T VS'!P96 -> 0 | I48: =SUM(G48:H48) -> 0 | J48: =I48/$I$25 -> 0
A49: 2 | B49: 1 | C49: 1 | D49: 5 | E49: 03 | F49: Prestación laboral por desvinculación | G49: ='[1]CUENTA T FONDO 100'!Q145 -> 0 | H49: ='[1]CUENTA T VS'!Q96 -> 0 | I49: =SUM(G49:H49) -> 0 | J49: =I49/$I$25 -> 0
A50: 2 | B50: 1 | C50: 1 | D50: 5 | E50: 04 | F50: Proporción de vacaciones no disfrutadas | G50: ='[1]CUENTA T FONDO 100'!R145 -> 0 | H50: ='[1]CUENTA T VS'!R96 -> 0 | I50: =SUM(G50:H50) -> 0 | J50: =I50/$I$25 -> 0
A51: 2 | B51: 1 | C51: 2 | F51: Sobresueldos | G51: =+G52+G54 -> 0 | H51: =+H52+H54 -> 0 | I51: =SUM(G51:H51) -> 0
A52: 2 | B52: 1 | C52: 2 | D52: 1 | F52: Primas por antigüedad | G52: =SUM(G53) -> 0 | H52: =SUM(H53) -> 0 | I52: =SUM(G52:H52) -> 0
A53: 2 | B53: 1 | C53: 2 | D53: 1 | E53: 01 | F53: Primas por antigüedad | G53: ='[1]CUENTA T FONDO 100'!S145 -> 0 | H53: ='[1]CUENTA T VS'!S96 -> 0 | I53: =SUM(G53:H53) -> 0 | J53: =I53/$I$25 -> 0
A54: 2 | B54: 1 | C54: 2 | D54: 2 | F54: Compensación | G54: =SUM(G55:G63) -> 0 | H54: =SUM(H55:H63) -> 0 | I54: =SUM(G54:H54) -> 0
A55: 2 | B55: 1 | C55: 2 | D55: 2 | E55: 01 | F55: Compensación por gastos de alimentación | G55: ='[1]CUENTA T FONDO 100'!T145 -> 0 | H55: ='[1]CUENTA T VS'!T96 -> 0 | I55: =SUM(G55:H55) -> 0 | J55: =I55/$I$25 -> 0
A56: 2 | B56: 1 | C56: 2 | D56: 2 | E56: 03 | F56: Pago de horas extraordinarias | G56: ='[1]CUENTA T FONDO 100'!U145 -> 0 | H56: ='[1]CUENTA T VS'!U96 -> 0 | I56: =SUM(G56:H56) -> 0 | J56: =I56/$I$25 -> 0
A57: 2 | B57: 1 | C57: 2 | D57: 2 | E57: 04 | F57: Prima de transporte | G57: ='[1]CUENTA T FONDO 100'!V145 -> 0 | H57: ='[1]CUENTA T VS'!V96 -> 0 | I57: =SUM(G57:H57) -> 0 | J57: =I57/$I$25 -> 0
A58: 2 | B58: 1 | C58: 2 | D58: 2 | E58: 05 | F58: Compensación servicios de Seguridad | G58: ='[1]CUENTA T FONDO 100'!W145 -> 0 | H58: ='[1]CUENTA T VS'!W96 -> 0 | I58: =SUM(G58:H58) -> 0 | J58: =I58/$I$25 -> 0
A59: 2 | B59: 1 | C59: 2 | D59: 2 | E59: 06 | F59: Incentivo por Rendimieto Individual | G59: ='[1]CUENTA T FONDO 100'!X145 -> 0 | H59: ='[1]CUENTA T VS'!X96 -> 0 | I59: =SUM(G59:H59) -> 0 | J59: =I59/$I$25 -> 0
A60: 2 | B60: 1 | C60: 2 | D60: 2 | E60: 07 | F60: Compensación por distancia | G60: ='[1]CUENTA T FONDO 100'!Y145 -> 0 | H60: ='[1]CUENTA T VS'!Y96 -> 0 | I60: =SUM(G60:H60) -> 0 | J60: =I60/$I$25 -> 0
A61: 2 | B61: 1 | C61: 2 | D61: 2 | E61: 08 | F61: Compensaciones especiales | G61: ='[1]CUENTA T FONDO 100'!Z145 -> 0 | H61: ='[1]CUENTA T VS'!Z96 -> 0 | I61: =SUM(G61:H61) -> 0 | J61: =I61/$I$25 -> 0
A62: 2 | B62: 1 | C62: 2 | D62: 2 | E62: 09 | F62: Bono por desempeño a servidores de carrera | G62: ='[1]CUENTA T FONDO 100'!AA145 -> 0 | H62: ='[1]CUENTA T VS'!AA96 -> 0 | I62: =SUM(G62:H62) -> 0 | J62: =I62/$I$25 -> 0
A63: 2 | B63: 1 | C63: 2 | D63: 2 | E63: 10 | F63: Compensacion por cumplimiento de indicadores | G63: ='[1]CUENTA T FONDO 100'!AB145 -> 0 | H63: ='[1]CUENTA T VS'!AB96 -> 0 | I63: =SUM(G63:H63) -> 0 | J63: =I63/$I$25 -> 0
A64: 2 | B64: 1 | C64: 3 | F64: Dietas y Gastos de Representación | G64: =+G65+G68 -> 0 | H64: =+H65+H68 -> 0 | I64: =SUM(G64:H64) -> 0
A65: 2 | B65: 1 | C65: 3 | D65: 1 | F65: Dietas | G65: =SUM(G66:G67) -> 0 | H65: =SUM(H66:H67) -> 0 | I65: =SUM(G65:H65) -> 0
A66: 2 | B66: 1 | C66: 3 | D66: 1 | E66: 01 | F66: Dietas en el país | G66: ='[1]CUENTA T FONDO 100'!AC145 -> 0 | H66: ='[1]CUENTA T VS'!AC96 -> 0 | I66: =SUM(G66:H66) -> 0 | J66: =I66/$I$25 -> 0
A67: 2 | B67: 1 | C67: 3 | D67: 1 | E67: 02 | F67: Dietas en el exterior | G67: ='[1]CUENTA T FONDO 100'!AD145 -> 0 | H67: ='[1]CUENTA T VS'!AD96 -> 0 | I67: =SUM(G67:H67) -> 0 | J67: =I67/$I$25 -> 0
A68: 2 | B68: 1 | C68: 3 | D68: 2 | F68: Gastos de representación | G68: =SUM(G69:G70) -> 0 | H68: =SUM(H69:H70) -> 0 | I68: =SUM(G68:H68) -> 0
A69: 2 | B69: 1 | C69: 3 | D69: 2 | E69: 01 | F69: Gastos de representación en el país | G69: ='[1]CUENTA T FONDO 100'!AE145 -> 0 | H69: ='[1]CUENTA T VS'!AE96 -> 0 | I69: =SUM(G69:H69) -> 0 | J69: =I69/$I$25 -> 0
A70: 2 | B70: 1 | C70: 3 | D70: 2 | E70: 02 | F70: Gastos de representación en el exterior | G70: ='[1]CUENTA T FONDO 100'!AF145 -> 0 | H70: ='[1]CUENTA T VS'!AF96 -> 0 | I70: =SUM(G70:H70) -> 0 | J70: =I70/$I$25 -> 0
A71: 2 | B71: 1 | C71: 4 | F71: Gratificaciones y Bonificaciones | G71: =+G72+G74 -> 0 | H71: =+H72+H74 -> 0 | I71: =SUM(G71:H71) -> 0
A72: 2 | B72: 1 | C72: 4 | D72: 1 | F72: Bonificaciones | G72: =SUM(G73) -> 0 | H72: =SUM(H73) -> 0 | I72: =SUM(G72:H72) -> 0
A73: 2 | B73: 1 | C73: 4 | D73: 1 | E73: 01 | F73: Bonificaciones | G73: ='[1]CUENTA T FONDO 100'!AG145 -> 0 | H73: ='[1]CUENTA T VS'!AG96 -> 0 | I73: =SUM(G73:H73) -> 0 | J73: =I73/$I$25 -> 0
A74: 2 | B74: 1 | C74: 4 | D74: 2 | F74: Otras Gratificaciones y Bonificaciones | G74: =SUM(G75:G77) -> 0 | H74: =SUM(H75:H77) -> 0 | I74: =SUM(G74:H74) -> 0
A75: 2 | B75: 1 | C75: 4 | D75: 2 | E75: 01 | F75: Bono escolar | G75: ='[1]CUENTA T FONDO 100'!AH145 -> 0 | H75: ='[1]CUENTA T VS'!AH96 -> 0 | I75: =SUM(G75:H75) -> 0 | J75: =I75/$I$25 -> 0
A76: 2 | B76: 1 | C76: 4 | D76: 2 | E76: 02 | F76: Gratificaciones por pasantías | G76: ='[1]CUENTA T FONDO 100'!AI145 -> 0 | H76: ='[1]CUENTA T VS'!AI96 -> 0 | I76: =SUM(G76:H76) -> 0 | J76: =I76/$I$25 -> 0
A77: 2 | B77: 1 | C77: 4 | D77: 2 | E77: 03 | F77: Gratificaciones por aniversario de institución | G77: ='[1]CUENTA T FONDO 100'!AJ145 -> 0 | H77: ='[1]CUENTA T VS'!AJ96 -> 0 | I77: =SUM(G77:H77) -> 0 | J77: =I77/$I$25 -> 0
A78: 2 | B78: 1 | C78: 5 | F78: Contribuciones a la Seguridad Social y Riesgo Laboral | G78: =+G79+G81+G83+G85 -> 0 | H78: =+H79+H81+H83+H85 -> 0 | I78: =SUM(G78:H78) -> 0
A79: 2 | B79: 1 | C79: 5 | D79: 1 | F79: Contribuciones al seguro de salud | G79: =SUM(G80) -> 0 | H79: =SUM(H80) -> 0 | I79: =SUM(G79:H79) -> 0
A80: 2 | B80: 1 | C80: 5 | D80: 1 | E80: 01 | F80: Contribuciones al seguro de salud | G80: ='[1]CUENTA T FONDO 100'!AK145 -> 0 | H80: ='[1]CUENTA T VS'!AK96 -> 0 | I80: =SUM(G80:H80) -> 0 | J80: =I80/$I$25 -> 0
A81: 2 | B81: 1 | C81: 5 | D81: 2 | F81: Contribuciones al seguro de pensiones | G81: =SUM(G82) -> 0 | H81: =SUM(H82) -> 0 | I81: =SUM(G81:H81) -> 0
A82: 2 | B82: 1 | C82: 5 | D82: 2 | E82: 01 | F82: Contribuciones al seguro de pensiones | G82: ='[1]CUENTA T FONDO 100'!AL145 -> 0 | H82: ='[1]CUENTA T VS'!AL96 -> 0 | I82: =SUM(G82:H82) -> 0 | J82: =I82/$I$25 -> 0
A83: 2 | B83: 1 | C83: 5 | D83: 3 | F83: Contribuciones al seguro de riesgo laboral | G83: =SUM(G84) -> 0 | H83: =SUM(H84) -> 0 | I83: =SUM(G83:H83) -> 0
A84: 2 | B84: 1 | C84: 5 | D84: 3 | E84: 01 | F84: Contribuciones al seguro de riesgo laboral | G84: ='[1]CUENTA T FONDO 100'!AM145 -> 0 | H84: ='[1]CUENTA T VS'!AM96 -> 0 | I84: =SUM(G84:H84) -> 0 | J84: =I84/$I$25 -> 0
A85: 2 | B85: 1 | C85: 5 | D85: 4 | F85: Contribuciones al plan de retiro complementario | G85: =SUM(G86) -> 0 | H85: =SUM(H86) -> 0 | I85: =SUM(G85:H85) -> 0
A86: 2 | B86: 1 | C86: 5 | D86: 4 | E86: 01 | F86: Contribuciones al plan de retiro complementario | G86: ='[1]CUENTA T FONDO 100'!AN145 -> 0 | H86: ='[1]CUENTA T VS'!AN96 -> 0 | I86: =SUM(G86:H86) -> 0 | J86: =I86/$I$25 -> 0
A87: 2 | B87: 2 | F87: Servicios No Personales | G87: =G88+G106+G111+G116+G125+G148+G157+G179+G208 -> 0 | H87: =H88+H106+H111+H116+H125+H148+H157+H179+H208 -> 1213383.4 | I87: =SUM(G87:H87) -> 1213383.4 | J87: =I87/$I$25 -> 0.16057114
A88: 2 | B88: 2 | C88: 1 | F88: Servicios Básicos | G88: =+G89+G91+G93+G95+G97+G99+G102+G104 -> 0 | H88: =+H89+H91+H93+H95+H97+H99+H102+H104 -> 259054.4 | I88: =SUM(G88:H88) -> 259054.4
A89: 2 | B89: 2 | C89: 1 | D89: 1 | F89: Radiocomunicación | G89: =SUM(G90) -> 0 | H89: =SUM(H90) -> 0 | I89: =SUM(G89:H89) -> 0
A90: 2 | B90: 2 | C90: 1 | D90: 1 | E90: 01 | F90: Radiocomunicación | G90: ='[1]CUENTA T FONDO 100'!AO145 -> 0 | H90: ='[1]CUENTA T VS'!AO96 -> 0 | I90: =SUM(G90:H90) -> 0 | J90: =I90/$I$25 -> 0
A91: 2 | B91: 2 | C91: 1 | D91: 2 | F91: Servicios telefónico de larga distancia | G91: =SUM(G92) -> 0 | H91: =SUM(H92) -> 0 | I91: =SUM(G91:H91) -> 0
A92: 2 | B92: 2 | C92: 1 | D92: 2 | E92: 01 | F92: Servicios telefónico de larga distancia | G92: ='[1]CUENTA T FONDO 100'!AP145 -> 0 | H92: ='[1]CUENTA T VS'!AP96 -> 0 | I92: =SUM(G92:H92) -> 0 | J92: =I92/$I$25 -> 0
A93: 2 | B93: 2 | C93: 1 | D93: 3 | F93: Teléfono local | G93: =SUM(G94) -> 0 | H93: =SUM(H94) -> 259054.4 | I93: =SUM(G93:H93) -> 259054.4
A94: 2 | B94: 2 | C94: 1 | D94: 3 | E94: 01 | F94: Teléfono local | G94: ='[1]CUENTA T FONDO 100'!AQ145 -> 0 | H94: ='[1]CUENTA T VS'!AQ96 -> 259054.4 | I94: =SUM(G94:H94) -> 259054.4 | J94: =I94/$I$25 -> 0.034281548
A95: 2 | B95: 2 | C95: 1 | D95: 4 | F95: Telefax y correos | G95: =SUM(G96) -> 0 | H95: =SUM(H96) -> 0 | I95: =SUM(G95:H95) -> 0
A96: 2 | B96: 2 | C96: 1 | D96: 4 | E96: 01 | F96: Telefax y correos | G96: ='[1]CUENTA T FONDO 100'!AR145 -> 0 | H96: ='[1]CUENTA T VS'!AR96 -> 0 | I96: =SUM(G96:H96) -> 0 | J96: =I96/$I$25 -> 0
A97: 2 | B97: 2 | C97: 1 | D97: 5 | F97: Servicio de Internet y televisión por cable | G97: =SUM(G98) -> 0 | H97: =SUM(H98) -> 0 | I97: =SUM(G97:H97) -> 0
A98: 2 | B98: 2 | C98: 1 | D98: 5 | E98: 01 | F98: Servicio de Internet y televisión por cable | G98: ='[1]CUENTA T FONDO 100'!AS145 -> 0 | H98: ='[1]CUENTA T VS'!AS96 -> 0 | I98: =SUM(G98:H98) -> 0 | J98: =I98/$I$25 -> 0
A99: 2 | B99: 2 | C99: 1 | D99: 6 | F99: Electricidad | G99: =SUM(G100:G101) -> 0 | H99: =SUM(H100:H101) -> 0 | I99: =SUM(G99:H99) -> 0
A100: 2 | B100: 2 | C100: 1 | D100: 6 | E100: 01 | F100: Energía eléctrica | G100: ='[1]CUENTA T FONDO 100'!AT145 -> 0 | H100: ='[1]CUENTA T VS'!AT96 -> 0 | I100: =SUM(G100:H100) -> 0 | J100: =I100/$I$25 -> 0
A101: 2 | B101: 2 | C101: 1 | D101: 6 | E101: 02 | F101: Electricidad no cortable | G101: ='[1]CUENTA T FONDO 100'!AU145 -> 0 | H101: ='[1]CUENTA T VS'!AU96 -> 0 | I101: =SUM(G101:H101) -> 0 | J101: =I101/$I$25 -> 0
A102: 2 | B102: 2 | C102: 1 | D102: 7 | F102: Agua | G102: =SUM(G103) -> 0 | H102: =SUM(H103) -> 0 | I102: =SUM(G102:H102) -> 0
...

Sheet GASTOS X ATENCION
A1: SERVICIO NACIONAL DE SALUD
A2: ='CONS. FUENTES FINAN'!A6 -> HOSPITAL MATERNO INFANTIL SAN LORENZO DE LOS MINA
A3: RESUMEN COMPARATIVO DE GASTOS ESPECIFICOS FONDO 100 Y VENTA DE SERVICIOS
A6: DETALLE | B6: FONDO 100 | C6: VENTA SERVICIOS | D6: TOTAL | E6: %
A8: Atención Directa
A9: Medicamentos e Insumos Médicos | B9: ='CONS. FUENTES FINAN'!G245+'CONS. FUENTES FINAN'!G315 -> 0 | C9: ='CONS. FUENTES FINAN'!H245+'CONS. FUENTES FINAN'!H315 -> 419800 | D9: =SUM(B9:C9) -> 419800 | E9: =+D9/D12 -> 0.31362328
A10: Oxigeno | B10: ='CONS. FUENTES FINAN'!G302 -> 0 | C10: ='CONS. FUENTES FINAN'!H302 -> 899773.6 | D10: =SUM(B10:C10) -> 899773.6 | E10: =+D10/D12 -> 0.67220092
A11: Reactivos e Insumos de Laboratorio | B11: ='CONS. FUENTES FINAN'!G296+'CONS. FUENTES FINAN'!G297+'CONS. FUENTES FINAN'!G298 -> 0 | C11: ='CONS. FUENTES FINAN'!H296+'CONS. FUENTES FINAN'!H297+'CONS. FUENTES FINAN'!H298 -> 18975 | D11: =SUM(B11:C11) -> 18975 | E11: =+D11/D12 -> 0.014175802
A12: Total | B12: =SUM(B9:B11) -> 0 | C12: =SUM(C9:C11) -> 1338548.6 | D12: =SUM(D9:D11) -> 1338548.6 | E12: =+D12/D39 -> 0.17713468
A13: Mantenimiento de Equipos
A14: Reparación y Mantenimiento Maquinaria y Eq. | B14: ='CONS. FUENTES FINAN'!G157+'CONS. FUENTES FINAN'!G188+'CONS. FUENTES FINAN'!G223+'CONS. FUENTES FINAN'!G252+'CONS. FUENTES FINAN'!G254+'CONS. FUENTES FINAN'!G256+'CONS. FUENTES FINAN'!G258+'CONS. FUENTES FINAN'!G261+'CONS. FUENTES FINAN'!G292+'CONS. FUENTES FINAN'!G293+'CONS. FUENTES FINAN'!G299+'CONS. FUENTES FINAN'!G300+'CONS. FUENTES FINAN'!G301+'CONS. FUENTES FINAN'!G324 -> 0 | C14: ='CONS. FUENTES FINAN'!H157+'CONS. FUENTES FINAN'!H188+'CONS. FUENTES FINAN'!H223+'CONS. FUENTES FINAN'!H252+'CONS. FUENTES FINAN'!H254+'CONS. FUENTES FINAN'!H256+'CONS. FUENTES FINAN'!H258+'CONS. FUENTES FINAN'!H261+'CONS. FUENTES FINAN'!H292+'CONS. FUENTES FINAN'!H293+'CONS. FUENTES FINAN'!H299+'CONS. FUENTES FINAN'!H300+'CONS. FUENTES FINAN'!H301+'CONS. FUENTES FINAN'!H324 -> 656488.94 | D14: =SUM(B14:C14) -> 656488.94 | E14: =+D14/D16 -> 0.99386863
A15: Productos Eléctricos y Afines | B15: ='CONS. FUENTES FINAN'!G320 -> 0 | C15: ='CONS. FUENTES FINAN'!H320 -> 4050.01 | D15: =SUM(B15:C15) -> 4050.01 | E15: =+D15/D16 -> 0.006131372
A16: Total | B16: =SUM(B14:B15) -> 0 | C16: =SUM(C14:C15) -> 660538.95 | D16: =SUM(D14:D15) -> 660538.95 | E16: =+D16/D39 -> 0.087411361
A17: Gastos Administrativos
A18: Servicios Personales | B18: ='CONS. FUENTES FINAN'!G26 -> 0 | C18: ='CONS. FUENTES FINAN'!H26 -> 0 | D18: =SUM(B18:C18) -> 0 | E18: =+D18/D34 -> 0
A19: Servicio Telefónico | B19: ='CONS. FUENTES FINAN'!G91+'CONS. FUENTES FINAN'!G93+'CONS. FUENTES FINAN'!G95+'CONS. FUENTES FINAN'!G97 -> 0 | C19: ='CONS. FUENTES FINAN'!H91+'CONS. FUENTES FINAN'!H93+'CONS. FUENTES FINAN'!H95+'CONS. FUENTES FINAN'!H97 -> 259054.4 | D19: =SUM(B19:C19) -> 259054.4 | E19: =+D19/D34 -> 0.15511551
A20: Servicios Basicos (electricidad, agua y residuos solidos) | B20: ='CONS. FUENTES FINAN'!G99+'CONS. FUENTES FINAN'!G102+'CONS. FUENTES FINAN'!G104 -> 0 | C20: ='CONS. FUENTES FINAN'!H99+'CONS. FUENTES FINAN'!H102+'CONS. FUENTES FINAN'!H104 -> 0 | D20: =SUM(B20:C20) -> 0 | E20: =+D20/D34 -> 0
A21: Viáticos | B21: ='CONS. FUENTES FINAN'!G111 -> 0 | C21: ='CONS. FUENTES FINAN'!H111 -> 0 | D21: =SUM(B21:C21) -> 0 | E21: =+D21/D34 -> 0
A22: Transporte y almacenaje | B22: ='CONS. FUENTES FINAN'!G116 -> 0 | C22: ='CONS. FUENTES FINAN'!H116 -> 24000 | D22: =SUM(B22:C22) -> 24000 | E22: =+D22/D34 -> 0.01437062
A23: Alquileres | B23: ='CONS. FUENTES FINAN'!G125 -> 0 | C23: ='CONS. FUENTES FINAN'!H125 -> 252960.9 | D23: =SUM(B23:C23) -> 252960.9 | E23: =+D23/D34 -> 0.15146687
A24: Comisiones y Gastos Bancarios | B24: ='CONS. FUENTES FINAN'!G182 -> 0 | C24: ='CONS. FUENTES FINAN'!H182 -> 11179.44 | D24: =SUM(B24:C24) -> 11179.44 | E24: =+D24/D34 -> 0.0066939785
A25: Materiales de Oficina, Impresión y Encuadernación | B25: ='CONS. FUENTES FINAN'!G109+'CONS. FUENTES FINAN'!G312 -> 0 | C25: ='CONS. FUENTES FINAN'!H109+'CONS. FUENTES FINAN'!H312 -> 0 | D25: =SUM(B25:C25) -> 0 | E25: =+D25/D34 -> 0
A26: Alimentos y Bebidas para Personas | B26: ='CONS. FUENTES FINAN'!G208+'CONS. FUENTES FINAN'!G214+'CONS. FUENTES FINAN'!G217+'CONS. FUENTES FINAN'!G219 -> 0 | C26: ='CONS. FUENTES FINAN'!H208+'CONS. FUENTES FINAN'!H214+'CONS. FUENTES FINAN'!H217+'CONS. FUENTES FINAN'!H219 -> 300691.8 | D26: =SUM(B26:C26) -> 300691.8 | E26: =+D26/D34 -> 0.18004698
A27: Productos de papel, carton e impesos | B27: ='CONS. FUENTES FINAN'!G232 -> 0 | C27: ='CONS. FUENTES FINAN'!H232 -> 107616 | D27: =SUM(B27:C27) -> 107616 | E27: =+D27/D34 -> 0.06443786
A28: Articulos de Plasticos | B28: ='CONS. FUENTES FINAN'!G259 -> 0 | C28: ='CONS. FUENTES FINAN'!H259 -> 249831.2 | D28: =SUM(B28:C28) -> 249831.2 | E28: =+D28/D34 -> 0.14959288
A29: Gasolina | B29: ='CONS. FUENTES FINAN'!G288 -> 0 | C29: ='CONS. FUENTES FINAN'!H288 -> 172000 | D29: =SUM(B29:C29) -> 172000 | E29: =+D29/D34 -> 0.10298944
A30: Gasoil | B30: ='CONS. FUENTES FINAN'!G289+'CONS. FUENTES FINAN'!G290 -> 0 | C30: ='CONS. FUENTES FINAN'!H289+'CONS. FUENTES FINAN'!H290 -> 0 | D30: =SUM(B30:C30) -> 0 | E30: =+D30/D34 -> 0
A31: GLP | B31: ='CONS. FUENTES FINAN'!G291+'CONS. FUENTES FINAN'!G294 -> 0 | C31: ='CONS. FUENTES FINAN'!H291+'CONS. FUENTES FINAN'!H294 -> 23844.13 | D31: =SUM(B31:C31) -> 23844.13 | E31: =+D31/D34 -> 0.014277289
A32: Materiales de Limpieza e Higiene | B32: ='CONS. FUENTES FINAN'!G309 -> 0 | C32: ='CONS. FUENTES FINAN'!H309 -> 0 | D32: =SUM(B32:C32) -> 0 | E32: =+D32/D34 -> 0
A33: Otros Egresos y Gastos | B33: ='CONS. FUENTES FINAN'!G89+'CONS. FUENTES FINAN'!G107+'CONS. FUENTES FINAN'!G148+'CONS. FUENTES FINAN'!G180+'CONS. FUENTES FINAN'!G184+'CONS. FUENTES FINAN'!G186+'CONS. FUENTES FINAN'!G192+'CONS. FUENTES FINAN'!G197+'CONS. FUENTES FINAN'!G204+'CONS. FUENTES FINAN'!G225+'CONS. FUENTES FINAN'!G303+'CONS. FUENTES FINAN'!G316+'CONS. FUENTES FINAN'!G318+'CONS. FUENTES FINAN'!G322+'CONS. FUENTES FINAN'!G327+'CONS. FUENTES FINAN'!G330 -> 0 | C33: ='CONS. FUENTES FINAN'!H89+'CONS. FUENTES FINAN'!H107+'CONS. FUENTES FINAN'!H148+'CONS. FUENTES FINAN'!H180+'CONS. FUENTES FINAN'!H184+'CONS. FUENTES FINAN'!H186+'CONS. FUENTES FINAN'!H192+'CONS. FUENTES FINAN'!H197+'CONS. FUENTES FINAN'!H204+'CONS. FUENTES FINAN'!H225+'CONS. FUENTES FINAN'!H303+'CONS. FUENTES FINAN'!H316+'CONS. FUENTES FINAN'!H318+'CONS. FUENTES FINAN'!H322+'CONS. FUENTES FINAN'!H327+'CONS. FUENTES FINAN'!H330 -> 268896.22 | D33: =SUM(B33:C33) -> 268896.22 | E33: =+D33/D34 -> 0.16100856
A34: Total | B34: =SUM(B17:B33) -> 0 | C34: =SUM(C17:C33) -> 1670074.1 | D34: =SUM(D17:D33) -> 1670074.1 | E34: =+D34/D39 -> 0.22100657
A35: Gastos Inversion y Capital
A36: Bienes Muebles, Inmuebles e Intangibles | B36: ='CONS. FUENTES FINAN'!G336 -> 0 | C36: ='CONS. FUENTES FINAN'!H336 -> 3887510 | D36: =SUM(B36:C36) -> 3887510 | E36: =+D36/D38 -> 1
A37: Obras | B37: ='CONS. FUENTES FINAN'!G463 -> 0 | C37: ='CONS. FUENTES FINAN'!H463 -> 0 | D37: =SUM(B37:C37) -> 0 | E37: =+D37/D38 -> 0
A38: Total | B38: =SUM(B36:B37) -> 0 | C38: =SUM(C36:C37) -> 3887510 | D38: =SUM(D36:D37) -> 3887510 | E38: =+D38/D39 -> 0.51444739
A39: Total General | B39: =+B12+B16+B34+B38 -> 0 | C39: =+C12+C16+C34+C38 -> 7556671.6 | D39: =+D12+D16+D34+D38 -> 7556671.6 | E39: =+E12+E16+E34+E38 -> 1
A40: Porciento | B40: =+B39/D39 -> 0 | C40: =+C39/D39 -> 1 | D40: =+B40+C40 -> 1

Sheet PLANTILLA PRESUPUESTO
A1: SERVICIO NACIONAL DE SALUD
A2: HOSPITAL MATERNO INFANTIL SAN LORENZO DE LOS MINA
A3: CONSOLIDADO GASTOS EJECUCION FINANCIERA 2025
A4: En RD$
A6: Detalle | B6: FONDO REPONIBLE | G6: VENTA SEVICIOS/OTROS APORTES | L6: TOTAL
A7: 2 - GASTOS | B7: 1ro | C7: 2do | D7: 3ro | E7: 4to | G7: 1ro | H7: 2do | I7: 3ro | J7: 4to | L7: 1ro | M7: 2do | N7: 3ro | O7: 4to
A8: 2.1 - REMUNERACIONES Y CONTRIBUCIONES | B8: =SUM(B9:B13) -> 1.9856074e+08 | C8: =SUM(C9:C13) -> 1.9977032e+08 | D8: =SUM(D9:D13) -> 71335676 | E8: =SUM(E9:E13) -> 0 | G8: =SUM(G9:G13) -> 5231553.6 | H8: =SUM(H9:H13) -> 0 | I8: =SUM(I9:I13) -> 0 | J8: =SUM(J9:J13) -> 0 | L8: =SUM(B8+G8) -> 2.0379229e+08 | M8: =SUM(C8+H8) -> 1.9977032e+08 | N8: =SUM(D8+I8) -> 71335676 | O8: =SUM(E8+J8) -> 0
A9: 2.1.1 - REMUNERACIONES | B9: =SUM('TRANSFERENCIA CORRIENTE'!C10:E10) -> 1.639452e+08 | C9: =SUM('TRANSFERENCIA CORRIENTE'!F10:H10) -> 1.6408478e+08 | D9: =SUM('TRANSFERENCIA CORRIENTE'!I10:K10) -> 58925421 | E9: =SUM('TRANSFERENCIA CORRIENTE'!L10:N10) -> 0 | G9: =SUM(VS!C10:E10) -> 0 | H9: =SUM(VS!F10:H10) -> 0 | I9: =SUM(VS!I10:K10) -> 0 | J9: =SUM(VS!L10:N10) -> 0 | L9: =SUM(B9+G9) -> 1.639452e+08 | M9: =SUM(C9+H9) -> 1.6408478e+08 | N9: =SUM(D9+I9) -> 58925421 | O9: =SUM(E9+J9) -> 0
A10: 2.1.2 - SOBRESUELDOS | B10: =SUM('TRANSFERENCIA CORRIENTE'!C11:E11) -> 9594398.8 | C10: =SUM('TRANSFERENCIA CORRIENTE'!F11:H11) -> 10535799 | D10: =SUM('TRANSFERENCIA CORRIENTE'!I11:K11) -> 3344880.2 | E10: =SUM('TRANSFERENCIA CORRIENTE'!L11:N11) -> 0 | G10: =SUM(VS!C11:E11) -> 5231553.6 | H10: =SUM(VS!F11:H11) -> 0 | I10: =SUM(VS!I11:K11) -> 0 | J10: =SUM(VS!L11:N11) -> 0 | L10: =SUM(B10+G10) -> 14825952 | M10: =SUM(C10+H10) -> 10535799 | N10: =SUM(D10+I10) -> 3344880.2 | O10: =SUM(E10+J10) -> 0
A11: 2.1.3 - DIETAS Y GASTOS DE REPRESENTACIÓN | B11: =SUM('TRANSFERENCIA CORRIENTE'!C12:E12) -> 0 | C11: =SUM('TRANSFERENCIA CORRIENTE'!F12:H12) -> 0 | D11: =SUM('TRANSFERENCIA CORRIENTE'!I12:K12) -> 0 | E11: =SUM('TRANSFERENCIA CORRIENTE'!L12:N12) -> 0 | G11: =SUM(VS!C12:E12) -> 0 | H11: =SUM(VS!F12:H12) -> 0 | I11: =SUM(VS!I12:K12) -> 0 | J11: =SUM(VS!L12:N12) -> 0 | L11: =SUM(B11+G11) -> 0 | M11: =SUM(C11+H11) -> 0 | N11: =SUM(D11+I11) -> 0 | O11: =SUM(E11+J11) -> 0
A12: 2.1.4 - GRATIFICACIONES Y BONIFICACIONES | B12: =SUM('TRANSFERENCIA CORRIENTE'!C13:E13) -> 0 | C12: =SUM('TRANSFERENCIA CORRIENTE'!F13:H13) -> 0 | D12: =SUM('TRANSFERENCIA CORRIENTE'!I13:K13) -> 0 | E12: =SUM('TRANSFERENCIA CORRIENTE'!L13:N13) -> 0 | G12: =SUM(VS!C13:E13) -> 0 | H12: =SUM(VS!F13:H13) -> 0 | I12: =SUM(VS!I13:K13) -> 0 | J12: =SUM(VS!L13:N13) -> 0 | L12: =SUM(B12+G12) -> 0 | M12: =SUM(C12+H12) -> 0 | N12: =SUM(D12+I12) -> 0 | O12: =SUM(E12+J12) -> 0
A13: 2.1.5 - CONTRIBUCIONES A LA SEGURIDAD SOCIAL | B13: =SUM('TRANSFERENCIA CORRIENTE'!C14:E14) -> 25021132 | C13: =SUM('TRANSFERENCIA CORRIENTE'!F14:H14) -> 25149742 | D13: =SUM('TRANSFERENCIA CORRIENTE'!I14:K14) -> 9065374.6 | E13: =SUM('TRANSFERENCIA CORRIENTE'!L14:N14) -> 0 | G13: =SUM(VS!C14:E14) -> 0 | H13: =SUM(VS!F14:H14) -> 0 | I13: =SUM(VS!I14:K14) -> 0 | J13: =SUM(VS!L14:N14) -> 0 | L13: =SUM(B13+G13) -> 25021132 | M13: =SUM(C13+H13) -> 25149742 | N13: =SUM(D13+I13) -> 9065374.6 | O13: =SUM(E13+J13) -> 0
A14: 2.2 - CONTRATACIÓN DE SERVICIOS | B14: =SUM(B15:B23) -> 9308364.9 | C14: =SUM(C15:C23) -> 10131818 | D14: =SUM(D15:D23) -> 0 | E14: =SUM(E15:E23) -> 0 | G14: =SUM(G15:G23) -> 8306683.8 | H14: =SUM(H15:H23) -> 7239413.8 | I14: =SUM(I15:I23) -> 5012155.8 | J14: =SUM(J15:J23) -> 0 | L14: =SUM(B14+G14) -> 17615049 | M14: =SUM(C14+H14) -> 17371232 | N14: =SUM(D14+I14) -> 5012155.8 | O14: =SUM(E14+J14) -> 0
A15: 2.2.1 - SERVICIOS BÁSICOS | B15: =SUM('TRANSFERENCIA CORRIENTE'!C16:E16) -> 2020024.3 | C15: =SUM('TRANSFERENCIA CORRIENTE'!F16:H16) -> 181605 | D15: =SUM('TRANSFERENCIA CORRIENTE'!J16:L16) -> 0 | E15: =SUM('TRANSFERENCIA CORRIENTE'!L16:N16) -> 0 | G15: =SUM(VS!C16:E16) -> 2341561.9 | H15: =SUM(VS!F16:H16) -> 2348580.7 | I15: =SUM(VS!I16:K16) -> 1781904.1 | J15: =SUM(VS!L16:N16) -> 0 | L15: =SUM(B15+G15) -> 4361586.2 | M15: =SUM(C15+H15) -> 2530185.7 | N15: =SUM(D15+I15) -> 1781904.1 | O15: =SUM(E15+J15) -> 0
A16: 2.2.2 - PUBLICIDAD, IMPRESIÓN Y ENCUADERNACIÓN | B16: =SUM('TRANSFERENCIA CORRIENTE'!C17:E17) -> 324206.83 | C16: =SUM('TRANSFERENCIA CORRIENTE'!F17:H17) -> 351993.83 | D16: =SUM('TRANSFERENCIA CORRIENTE'!J17:L17) -> 0 | E16: =SUM('TRANSFERENCIA CORRIENTE'!L17:N17) -> 0 | G16: =SUM(VS!C17:E17) -> 0 | H16: =SUM(VS!F17:H17) -> 310139.4 | I16: =SUM(VS!I17:K17) -> 581445 | J16: =SUM(VS!L17:N17) -> 0 | L16: =SUM(B16+G16) -> 324206.83 | M16: =SUM(C16+H16) -> 662133.23 | N16: =SUM(D16+I16) -> 581445 | O16: =SUM(E16+J16) -> 0
A17: 2.2.3 - VIÁTICOS | B17: =SUM('TRANSFERENCIA CORRIENTE'!C18:E18) -> 0 | C17: =SUM('TRANSFERENCIA CORRIENTE'!F18:H18) -> 0 | D17: =SUM('TRANSFERENCIA CORRIENTE'!J18:L18) -> 0 | E17: =SUM('TRANSFERENCIA CORRIENTE'!L18:N18) -> 0 | G17: =SUM(VS!C18:E18) -> 0 | H17: =SUM(VS!F18:H18) -> 0 | I17: =SUM(VS!I18:K18) -> 0 | J17: =SUM(VS!L18:N18) -> 0 | L17: =SUM(B17+G17) -> 0 | M17: =SUM(C17+H17) -> 0 | N17: =SUM(D17+I17) -> 0 | O17: =SUM(E17+J17) -> 0
A18: 2.2.4 - TRANSPORTE Y ALMACENAJE | B18: =SUM('TRANSFERENCIA CORRIENTE'!C19:E19) -> 0 | C18: =SUM('TRANSFERENCIA CORRIENTE'!F19:H19) -> 0 | D18: =SUM('TRANSFERENCIA CORRIENTE'!J19:L19) -> 0 | E18: =SUM('TRANSFERENCIA CORRIENTE'!L19:N19) -> 0 | G18: =SUM(VS!C19:E19) -> 56000 | H18: =SUM(VS!F19:H19) -> 96000 | I18: =SUM(VS!I19:K19) -> 8000 | J18: =SUM(VS!L19:N19) -> 0 | L18: =SUM(B18+G18) -> 56000 | M18: =SUM(C18+H18) -> 96000 | N18: =SUM(D18+I18) -> 8000 | O18: =SUM(E18+J18) -> 0
A19: 2.2.5 - ALQUILERES Y RENTAS | B19: =SUM('TRANSFERENCIA CORRIENTE'!C20:E20) -> 0 | C19: =SUM('TRANSFERENCIA CORRIENTE'!F20:H20) -> 150000 | D19: =SUM('TRANSFERENCIA CORRIENTE'!J20:L20) -> 0 | E19: =SUM('TRANSFERENCIA CORRIENTE'!L20:N20) -> 0 | G19: =SUM(VS!C20:E20) -> 519625.15 | H19: =SUM(VS!F20:H20) -> 759170.42 | I19: =SUM(VS!I20:K20) -> 298861.54 | J19: =SUM(VS!L20:N20) -> 0 | L19: =SUM(B19+G19) -> 519625.15 | M19: =SUM(C19+H19) -> 909170.42 | N19: =SUM(D19+I19) -> 298861.54 | O19: =SUM(E19+J19) -> 0
A20: 2.2.6 - SEGUROS | B20: =SUM('TRANSFERENCIA CORRIENTE'!C21:E21) -> 0 | C20: =SUM('TRANSFERENCIA CORRIENTE'!F21:H21) -> 0 | D20: =SUM('TRANSFERENCIA CORRIENTE'!J21:L21) -> 0 | E20: =SUM('TRANSFERENCIA CORRIENTE'!L21:N21) -> 0 | G20: =SUM(VS!C21:E21) -> 0 | H20: =SUM(VS!F21:H21) -> 0 | I20: =SUM(VS!I21:K21) -> 0 | J20: =SUM(VS!L21:N21) -> 0 | L20: =SUM(B20+G20) -> 0 | M20: =SUM(C20+H20) -> 0 | N20: =SUM(D20+I20) -> 0 | O20: =SUM(E20+J20) -> 0
A21: 2.2.7 - SERVICIOS DE CONSERVACIÓN, REPARACIONES MENORES E INSTALACIONES TEMPORALES | B21: =SUM('TRANSFERENCIA CORRIENTE'!C22:E22) -> 6474433.8 | C21: =SUM('TRANSFERENCIA CORRIENTE'!F22:H22) -> 5611474.3 | D21: =SUM('TRANSFERENCIA CORRIENTE'!J22:L22) -> 0 | E21: =SUM('TRANSFERENCIA CORRIENTE'!L22:N22) -> 0 | G21: =SUM(VS!C22:E22) -> 4556850.1 | H21: =SUM(VS!F22:H22) -> 1040817.6 | I21: =SUM(VS!I22:K22) -> 1632573.3 | J21: =SUM(VS!L22:N22) -> 0 | L21: =SUM(B21+G21) -> 11031284 | M21: =SUM(C21+H21) -> 6652291.9 | N21: =SUM(D21+I21) -> 1632573.3 | O21: =SUM(E21+J21) -> 0
A22: 2.2.8 - OTROS SERVICIOS NO INCLUIDOS EN CONCEPTOS ANTERIORES | B22: =SUM('TRANSFERENCIA CORRIENTE'!C23:E23) -> 489700 | C22: =SUM('TRANSFERENCIA CORRIENTE'!F23:H23) -> 413000 | D22: =SUM('TRANSFERENCIA CORRIENTE'!J23:L23) -> 0 | E22: =SUM('TRANSFERENCIA CORRIENTE'!L23:N23) -> 0 | G22: =SUM(VS!C23:E23) -> 832646.66 | H22: =SUM(VS!F23:H23) -> 1774418.3 | I22: =SUM(VS!I23:K23) -> 709371.88 | J22: =SUM(VS!L23:N23) -> 0 | L22: =SUM(B22+G22) -> 1322346.7 | M22: =SUM(C22+H22) -> 2187418.3 | N22: =SUM(D22+I22) -> 709371.88 | O22: =SUM(E22+J22) -> 0
A23: 2.2.9 - OTRAS CONTRATACIONES DE SERVICIOS | B23: =SUM('TRANSFERENCIA CORRIENTE'!C24:E24) -> 0 | C23: =SUM('TRANSFERENCIA CORRIENTE'!F24:H24) -> 3423745 | D23: =SUM('TRANSFERENCIA CORRIENTE'!J24:L24) -> 0 | E23: =SUM('TRANSFERENCIA CORRIENTE'!L24:N24) -> 0 | G23: =SUM(VS!C24:E24) -> 0 | H23: =SUM(VS!F24:H24) -> 910287.4 | I23: =SUM(VS!I24:K24) -> 0 | J23: =SUM(VS!L24:N24) -> 0 | L23: =SUM(B23+G23) -> 0 | M23: =SUM(C23+H23) -> 4334032.4 | N23: =SUM(D23+I23) -> 0 | O23: =SUM(E23+J23) -> 0
A24: 2.3 - MATERIALES Y SUMINISTROS | B24: =SUM(B25:B33) -> 46153283 | C24: =SUM(C25:C33) -> 52385651 | D24: =SUM(D25:D33) -> 38552154 | E24: =SUM(E25:E33) -> 0 | G24: =SUM(G25:G33) -> 7292547.3 | H24: =SUM(H25:H33) -> 6552680.6 | I24: =SUM(I25:I33) -> 3444623.9 | J24: =SUM(J25:J33) -> 0 | L24: =SUM(B24+G24) -> 53445831 | M24: =SUM(C24+H24) -> 58938331 | N24: =SUM(D24+I24) -> 41996778 | O24: =SUM(E24+J24) -> 0
A25: 2.3.1 - ALIMENTOS Y PRODUCTOS AGROFORESTALES | B25: =SUM('TRANSFERENCIA CORRIENTE'!C26:E26) -> 3713897.2 | C25: =SUM('TRANSFERENCIA CORRIENTE'!F26:H26) -> 4866999.2 | D25: =SUM('TRANSFERENCIA CORRIENTE'!I23:K23) -> 0 | E25: =SUM('TRANSFERENCIA CORRIENTE'!L26:N26) -> 0 | G25: =SUM(VS!C26:E26) -> 1500755.8 | H25: =SUM(VS!F26:H26) -> 663230 | I25: =SUM(VS!I26:K26) -> 360730 | J25: =SUM(VS!L26:N26) -> 0 | L25: =SUM(B25+G25) -> 5214653 | M25: =SUM(C25+H25) -> 5530229.2 | N25: =SUM(D25+I25) -> 360730 | O25: =SUM(E25+J25) -> 0
A26: 2.3.2 - TEXTILES Y VESTUARIOS | B26: =SUM('TRANSFERENCIA CORRIENTE'!C27:E27) -> 61630.73 | C26: =SUM('TRANSFERENCIA CORRIENTE'!F27:H27) -> 2375399.4 | D26: =SUM('TRANSFERENCIA CORRIENTE'!I24:K24) -> 0 | E26: =SUM('TRANSFERENCIA CORRIENTE'!L27:N27) -> 0 | G26: =SUM(VS!C27:E27) -> 0 | H26: =SUM(VS!F27:H27) -> 346306.4 | I26: =SUM(VS!I27:K27) -> 0 | J26: =SUM(VS!L27:N27) -> 0 | L26: =SUM(B26+G26) -> 61630.73 | M26: =SUM(C26+H26) -> 2721705.8 | N26: =SUM(D26+I26) -> 0 | O26: =SUM(E26+J26) -> 0
A27: 2.3.3 - PRODUCTOS DE PAPEL, CARTÓN E IMPRESOS | B27: =SUM('TRANSFERENCIA CORRIENTE'!C28:E28) -> 1826911.8 | C27: =SUM('TRANSFERENCIA CORRIENTE'!F28:H28) -> 2991695.7 | D27: =SUM('TRANSFERENCIA CORRIENTE'!I25:K25) -> 26146220 | E27: =SUM('TRANSFERENCIA CORRIENTE'!L28:N28) -> 0 | G27: =SUM(VS!C28:E28) -> 251163 | H27: =SUM(VS!F28:H28) -> 803989 | I27: =SUM(VS!I28:K28) -> 26550 | J27: =SUM(VS!L28:N28) -> 0 | L27: =SUM(B27+G27) -> 2078074.8 | M27: =SUM(C27+H27) -> 3795684.7 | N27: =SUM(D27+I27) -> 26172770 | O27: =SUM(E27+J27) -> 0
A28: 2.3.4 - PRODUCTOS FARMACÉUTICOS | B28: =SUM('TRANSFERENCIA CORRIENTE'!C29:E29) -> 10797336 | C28: =SUM('TRANSFERENCIA CORRIENTE'!F29:H29) -> 12009357 | D28: =SUM('TRANSFERENCIA CORRIENTE'!I26:K26) -> 1787251.8 | E28: =SUM('TRANSFERENCIA CORRIENTE'!L29:N29) -> 0 | G28: =SUM(VS!C29:E29) -> 558000 | H28: =SUM(VS!F29:H29) -> 402220.76 | I28: =SUM(VS!I29:K29) -> 152800 | J28: =SUM(VS!L29:N29) -> 0 | L28: =SUM(B28+G28) -> 11355336 | M28: =SUM(C28+H28) -> 12411577 | N28: =SUM(D28+I28) -> 1940051.8 | O28: =SUM(E28+J28) -> 0
A29: 2.3.5 - PRODUCTOS DE CUERO, CAUCHO Y PLÁSTICO | B29: =SUM('TRANSFERENCIA CORRIENTE'!C30:E30) -> 334708.95 | C29: =SUM('TRANSFERENCIA CORRIENTE'!F30:H30) -> 1024240.4 | D29: =SUM('TRANSFERENCIA CORRIENTE'!I27:K27) -> 1577150.7 | E29: =SUM('TRANSFERENCIA CORRIENTE'!L30:N30) -> 0 | G29: =SUM(VS!C30:E30) -> 567494.87 | H29: =SUM(VS!F30:H30) -> 0 | I29: =SUM(VS!I30:K30) -> 77390.01 | J29: =SUM(VS!L30:N30) -> 0 | L29: =SUM(B29+G29) -> 902203.82 | M29: =SUM(C29+H29) -> 1024240.4 | N29: =SUM(D29+I29) -> 1654540.7 | O29: =SUM(E29+J29) -> 0
A30: 2.3.6 - PRODUCTOS DE MINERALES, METÁLICOS Y NO METÁLICOS | B30: =SUM('TRANSFERENCIA CORRIENTE'!C31:E31) -> 11630.98 | C30: =SUM('TRANSFERENCIA CORRIENTE'!F31:H31) -> 667620.59 | D30: =SUM('TRANSFERENCIA CORRIENTE'!I28:K28) -> 1579886.7 | E30: =SUM('TRANSFERENCIA CORRIENTE'!L31:N31) -> 0 | G30: =SUM(VS!C31:E31) -> 293957.3 | H30: =SUM(VS!F31:H31) -> 0 | I30: =SUM(VS!I31:K31) -> 24157.95 | J30: =SUM(VS!L31:N31) -> 0 | L30: =SUM(B30+G30) -> 305588.28 | M30: =SUM(C30+H30) -> 667620.59 | N30: =SUM(D30+I30) -> 1604044.6 | O30: =SUM(E30+J30) -> 0
A31: 2.3.7 - COMBUSTIBLES, LUBRICANTES, PRODUCTOS QUÍMICOS Y CONEXOS | B31: =SUM('TRANSFERENCIA CORRIENTE'!C32:E32) -> 8910102 | C31: =SUM('TRANSFERENCIA CORRIENTE'!F32:H32) -> 10068979 | D31: =SUM('TRANSFERENCIA CORRIENTE'!I29:K29) -> 6806505 | E31: =SUM('TRANSFERENCIA CORRIENTE'!L32:N32) -> 0 | G31: =SUM(VS!C32:E32) -> 1660334.6 | H31: =SUM(VS!F32:H32) -> 1500202 | I31: =SUM(VS!I32:K32) -> 1044515 | J31: =SUM(VS!L32:N32) -> 0 | L31: =SUM(B31+G31) -> 10570437 | M31: =SUM(C31+H31) -> 11569181 | N31: =SUM(D31+I31) -> 7851020 | O31: =SUM(E31+J31) -> 0
A32: 2.3.8 - GASTOS QUE SE ASIGNARÁN DURANTE EL EJERCICIO (ART. 32 Y 33 LEY 423-06) | B32: =SUM('TRANSFERENCIA CORRIENTE'!C33:E33) -> 0 | C32: =SUM('TRANSFERENCIA CORRIENTE'!F33:H33) -> 0 | D32: =SUM('TRANSFERENCIA CORRIENTE'!I30:K30) -> 655140.22 | E32: =SUM('TRANSFERENCIA CORRIENTE'!L33:N33) -> 0 | G32: =SUM(VS!C33:E33) -> 0 | H32: =SUM(VS!F33:H33) -> 0 | I32: =SUM(VS!I33:K33) -> 0 | J32: =SUM(VS!L33:N33) -> 0 | L32: =SUM(B32+G32) -> 0 | M32: =SUM(C32+H32) -> 0 | N32: =SUM(D32+I32) -> 655140.22 | O32: =SUM(E32+J32) -> 0
A33: 2.3.9 - PRODUCTOS Y ÚTILES VARIOS | B33: =SUM('TRANSFERENCIA CORRIENTE'!C34:E34) -> 20497066 | C33: =SUM('TRANSFERENCIA CORRIENTE'!F34:H34) -> 18381359 | D33: =SUM('TRANSFERENCIA CORRIENTE'!I31:K31) -> 0 | E33: =SUM('TRANSFERENCIA CORRIENTE'!L34:N34) -> 0 | G33: =SUM(VS!C34:E34) -> 2460841.8 | H33: =SUM(VS!F34:H34) -> 2836732.4 | I33: =SUM(VS!I34:K34) -> 1758480.9 | J33: =SUM(VS!L34:N34) -> 0 | L33: =SUM(B33+G33) -> 22957908 | M33: =SUM(C33+H33) -> 21218092 | N33: =SUM(D33+I33) -> 1758480.9 | O33: =SUM(E33+J33) -> 0
A34: 2.4 - TRANSFERENCIAS CORRIENTES | B34: =SUM(B35:B41) -> 0 | C34: =SUM(C35:C41) -> 0 | D34: =SUM(D35:D41) -> 0 | E34: =SUM(E35:E41) -> 0 | G34: =SUM(G35:G41) -> 287786.7 | H34: =SUM(H35:H41) -> 1223981 | I34: =SUM(I35:I41) -> 67571 | J34: =SUM(J35:J41) -> 0 | L34: =SUM(B34+G34) -> 287786.7 | M34: =SUM(C34+H34) -> 1223981 | N34: =SUM(D34+I34) -> 67571 | O34: =SUM(E34+J34) -> 0
A35: 2.4.1 - TRANSFERENCIAS CORRIENTES AL SECTOR PRIVADO | B35: =SUM('TRANSFERENCIA CORRIENTE'!C36:E36) -> 0 | C35: =SUM('TRANSFERENCIA CORRIENTE'!F36:H36) -> 0 | D35: =SUM('TRANSFERENCIA CORRIENTE'!I36:K36) -> 0 | E35: =SUM('TRANSFERENCIA CORRIENTE'!L36:N36) -> 0 | G35: =SUM(VS!C36:E36) -> 287786.7 | H35: =SUM(VS!F36:H36) -> 1163981 | I35: =SUM(VS!I36:K36) -> 67571 | J35: =SUM(VS!L36:N36) -> 0 | L35: =SUM(B35+G35) -> 287786.7 | M35: =SUM(C35+H35) -> 1163981 | N35: =SUM(D35+I35) -> 67571 | O35: =SUM(E35+J35) -> 0
A36: 2.4.2 - TRANSFERENCIAS CORRIENTES AL GOBIERNO GENERAL NACIONAL | B36: =SUM('TRANSFERENCIA CORRIENTE'!C37:E37) -> 0 | C36: =SUM('TRANSFERENCIA CORRIENTE'!F37:H37) -> 0 | D36: =SUM('TRANSFERENCIA CORRIENTE'!I37:K37) -> 0 | E36: =SUM('TRANSFERENCIA CORRIENTE'!L37:N37) -> 0 | G36: =SUM(VS!C37:E37) -> 0 | H36: =SUM(VS!F37:H37) -> 60000 | I36: =SUM(VS!I37:K37) -> 0 | J36: =SUM(VS!L37:N37) -> 0 | L36: =SUM(B36+G36) -> 0 | M36: =SUM(C36+H36) -> 60000 | N36: =SUM(D36+I36) -> 0 | O36: =SUM(E36+J36) -> 0
A37: 2.4.3 - TRANSFERENCIAS CORRIENTES A GOBIERNOS GENERALES LOCALES | B37: =SUM('TRANSFERENCIA CORRIENTE'!C38:E38) -> 0 | C37: =SUM('TRANSFERENCIA CORRIENTE'!F38:H38) -> 0 | D37: =SUM('TRANSFERENCIA CORRIENTE'!I38:K38) -> 0 | E37: =SUM('TRANSFERENCIA CORRIENTE'!L38:N38) -> 0 | G37: =SUM(VS!C38:E38) -> 0 | H37: =SUM(VS!F38:H38) -> 0 | I37: =SUM(VS!I38:K38) -> 0 | J37: =SUM(VS!L38:N38) -> 0 | L37: =SUM(B37+G37) -> 0 | M37: =SUM(C37+H37) -> 0 | N37: =SUM(D37+I37) -> 0 | O37: =SUM(E37+J37) -> 0
A38: 2.4.4 - TRANSFERENCIAS CORRIENTES A EMPRESAS PÚBLICAS NO FINANCIERAS | B38: =SUM('TRANSFERENCIA CORRIENTE'!C39:E39) -> 0 | C38: =SUM('TRANSFERENCIA CORRIENTE'!F39:H39) -> 0 | D38: =SUM('TRANSFERENCIA CORRIENTE'!I39:K39) -> 0 | E38: =SUM('TRANSFERENCIA CORRIENTE'!L39:N39) -> 0 | G38: =SUM(VS!C39:E39) -> 0 | H38: =SUM(VS!F39:H39) -> 0 | I38: =SUM(VS!I39:K39) -> 0 | J38: =SUM(VS!L39:N39) -> 0 | L38: =SUM(B38+G38) -> 0 | M38: =SUM(C38+H38) -> 0 | N38: =SUM(D38+I38) -> 0 | O38: =SUM(E38+J38) -> 0
A39: 2.4.5 - TRANSFERENCIAS CORRIENTES A INSTITUCIONES PÚBLICAS FINANCIERAS | B39: =SUM('TRANSFERENCIA CORRIENTE'!C40:E40) -> 0 | C39: =SUM('TRANSFERENCIA CORRIENTE'!F40:H40) -> 0 | D39: =SUM('TRANSFERENCIA CORRIENTE'!I40:K40) -> 0 | E39: =SUM('TRANSFERENCIA CORRIENTE'!L40:N40) -> 0 | G39: =SUM(VS!C40:E40) -> 0 | H39: =SUM(VS!F40:H40) -> 0 | I39: =SUM(VS!I40:K40) -> 0 | J39: =SUM(VS!L40:N40) -> 0 | L39: =SUM(B39+G39) -> 0 | M39: =SUM(C39+H39) -> 0 | N39: =SUM(D39+I39) -> 0 | O39: =SUM(E39+J39) -> 0
A40: 2.4.7 - TRANSFERENCIAS CORRIENTES AL SECTOR EXTERNO | B40: =SUM('TRANSFERENCIA CORRIENTE'!C41:E41) -> 0 | C40: =SUM('TRANSFERENCIA CORRIENTE'!F41:H41) -> 0 | D40: =SUM('TRANSFERENCIA CORRIENTE'!I41:K41) -> 0 | E40: =SUM('TRANSFERENCIA CORRIENTE'!L41:N41) -> 0 | G40: =SUM(VS!C41:E41) -> 0 | H40: =SUM(VS!F41:H41) -> 0 | I40: =SUM(VS!I41:K41) -> 0 | J40: =SUM(VS!L41:N41) -> 0 | L40: =SUM(B40+G40) -> 0 | M40: =SUM(C40+H40) -> 0 | N40: =SUM(D40+I40) -> 0 | O40: =SUM(E40+J40) -> 0
A41: 2.4.9 - TRANSFERENCIAS CORRIENTES A OTRAS INSTITUCIONES PÚBLICAS | B41: =SUM('TRANSFERENCIA CORRIENTE'!C42:E42) -> 0 | C41: =SUM('TRANSFERENCIA CORRIENTE'!F42:H42) -> 0 | D41: =SUM('TRANSFERENCIA CORRIENTE'!I42:K42) -> 0 | E41: =SUM('TRANSFERENCIA CORRIENTE'!L42:N42) -> 0 | G41: =SUM(VS!C42:E42) -> 0 | H41: =SUM(VS!F42:H42) -> 0 | I41: =SUM(VS!I42:K42) -> 0 | J41: =SUM(VS!L42:N42) -> 0 | L41: =SUM(B41+G41) -> 0 | M41: =SUM(C41+H41) -> 0 | N41: =SUM(D41+I41) -> 0 | O41: =SUM(E41+J41) -> 0
A42: 2.5 - TRANSFERENCIAS DE CAPITAL | B42: =SUM(B43:B49) -> 0 | C42: =SUM(C43:C49) -> 0 | D42: =SUM(D43:D49) -> 0 | E42: =SUM(E43:E49) -> 0 | G42: =SUM(G43:G49) -> 0 | H42: =SUM(H43:H49) -> 0 | I42: =SUM(I43:I49) -> 0 | J42: =SUM(J43:J49) -> 0 | L42: =SUM(B42+G42) -> 0 | M42: =SUM(C42+H42) -> 0 | N42: =SUM(D42+I42) -> 0 | O42: =SUM(E42+J42) -> 0
A43: 2.5.1 - TRANSFERENCIAS DE CAPITAL AL SECTOR PRIVADO | B43: =SUM('TRANSFERENCIA CORRIENTE'!C44:E44) -> 0 | C43: =SUM('TRANSFERENCIA CORRIENTE'!F44:H44) -> 0 | D43: =SUM('TRANSFERENCIA CORRIENTE'!I44:K44) -> 0 | E43: =SUM('TRANSFERENCIA CORRIENTE'!L44:N44) -> 0 | G43: =SUM(VS!C44:E44) -> 0 | H43: =SUM(VS!F44:H44) -> 0 | I43: =SUM(VS!I44:K44) -> 0 | J43: =SUM(VS!L44:N44) -> 0 | L43: =SUM(B43+G43) -> 0 | M43: =SUM(C43+H43) -> 0 | N43: =SUM(D43+I43) -> 0 | O43: =SUM(E43+J43) -> 0
A44: 2.5.2 - TRANSFERENCIAS DE CAPITAL AL GOBIERNO GENERAL NACIONAL | B44: =SUM('TRANSFERENCIA CORRIENTE'!C45:E45) -> 0 | C44: =SUM('TRANSFERENCIA CORRIENTE'!F45:H45) -> 0 | D44: =SUM('TRANSFERENCIA CORRIENTE'!I45:K45) -> 0 | E44: =SUM('TRANSFERENCIA CORRIENTE'!L45:N45) -> 0 | G44: =SUM(VS!C45:E45) -> 0 | H44: =SUM(VS!F45:H45) -> 0 | I44: =SUM(VS!I45:K45) -> 0 | J44: =SUM(VS!L45:N45) -> 0 | L44: =SUM(B44+G44) -> 0 | M44: =SUM(C44+H44) -> 0 | N44: =SUM(D44+I44) -> 0 | O44: =SUM(E44+J44) -> 0
A45: 2.5.3 - TRANSFERENCIAS DE CAPITAL A GOBIERNOS GENERALES LOCALES | B45: =SUM('TRANSFERENCIA CORRIENTE'!C46:E46) -> 0 | C45: =SUM('TRANSFERENCIA CORRIENTE'!F46:H46) -> 0 | D45: =SUM('TRANSFERENCIA CORRIENTE'!I46:K46) -> 0 | E45: =SUM('TRANSFERENCIA CORRIENTE'!L46:N46) -> 0 | G45: =SUM(VS!C46:E46) -> 0 | H45: =SUM(VS!F46:H46) -> 0 | I45: =SUM(VS!I46:K46) -> 0 | J45: =SUM(VS!L46:N46) -> 0 | L45: =SUM(B45+G45) -> 0 | M45: =SUM(C45+H45) -> 0 | N45: =SUM(D45+I45) -> 0 | O45: =SUM(E45+J45) -> 0
A46: 2.5.4 - TRANSFERENCIAS DE CAPITAL A EMPRESAS PÚBLICAS NO FINANCIERAS | B46: =SUM('TRANSFERENCIA CORRIENTE'!C47:E47) -> 0 | C46: =SUM('TRANSFERENCIA CORRIENTE'!F47:H47) -> 0 | D46: =SUM('TRANSFERENCIA CORRIENTE'!I47:K47) -> 0 | E46: =SUM('TRANSFERENCIA CORRIENTE'!L47:N47) -> 0 | G46: =SUM(VS!C47:E47) -> 0 | H46: =SUM(VS!F47:H47) -> 0 | I46: =SUM(VS!I47:K47) -> 0 | J46: =SUM(VS!L47:N47) -> 0 | L46: =SUM(B46+G46) -> 0 | M46: =SUM(C46+H46) -> 0 | N46: =SUM(D46+I46) -> 0 | O46: =SUM(E46+J46) -> 0
A47: 2.5.5 - TRANSFERENCIAS DE CAPITAL A INSTITUCIONES PÚBLICAS FINANCIERAS | B47: =SUM('TRANSFERENCIA CORRIENTE'!C48:E48) -> 0 | C47: =SUM('TRANSFERENCIA CORRIENTE'!F48:H48) -> 0 | D47: =SUM('TRANSFERENCIA CORRIENTE'!I48:K48) -> 0 | E47: =SUM('TRANSFERENCIA CORRIENTE'!L48:N48) -> 0 | G47: =SUM(VS!C48:E48) -> 0 | H47: =SUM(VS!F48:H48) -> 0 | I47: =SUM(VS!I48:K48) -> 0 | J47: =SUM(VS!L48:N48) -> 0 | L47: =SUM(B47+G47) -> 0 | M47: =SUM(C47+H47) -> 0 | N47: =SUM(D47+I47) -> 0 | O47: =SUM(E47+J47) -> 0
A48: 2.5.6 - TRANSFERENCIAS DE CAPITAL AL SECTOR EXTERNO | B48: =SUM('TRANSFERENCIA CORRIENTE'!C49:E49) -> 0 | C48: =SUM('TRANSFERENCIA CORRIENTE'!F49:H49) -> 0 | D48: =SUM('TRANSFERENCIA CORRIENTE'!I49:K49) -> 0 | E48: =SUM('TRANSFERENCIA CORRIENTE'!L49:N49) -> 0 | G48: =SUM(VS!C49:E49) -> 0 | H48: =SUM(VS!F49:H49) -> 0 | I48: =SUM(VS!I49:K49) -> 0 | J48: =SUM(VS!L49:N49) -> 0 | L48: =SUM(B48+G48) -> 0 | M48: =SUM(C48+H48) -> 0 | N48: =SUM(D48+I48) -> 0 | O48: =SUM(E48+J48) -> 0
A49: 2.5.9 - TRANSFERENCIAS DE CAPITAL A OTRAS INSTITUCIONES PÚBLICAS | B49: =SUM('TRANSFERENCIA CORRIENTE'!C50:E50) -> 0 | C49: =SUM('TRANSFERENCIA CORRIENTE'!F50:H50) -> 0 | D49: =SUM('TRANSFERENCIA CORRIENTE'!I50:K50) -> 0 | E49: =SUM('TRANSFERENCIA CORRIENTE'!L50:N50) -> 0 | G49: =SUM(VS!C50:E50) -> 0 | H49: =SUM(VS!F50:H50) -> 0 | I49: =SUM(VS!I50:K50) -> 0 | J49: =SUM(VS!L50:N50) -> 0 | L49: =SUM(B49+G49) -> 0 | M49: =SUM(C49+H49) -> 0 | N49: =SUM(D49+I49) -> 0 | O49: =SUM(E49+J49) -> 0
A50: 2.6 - BIENES MUEBLES, INMUEBLES E INTANGIBLES | B50: =SUM(B51:B59) -> 17857867 | C50: =SUM(C51:C59) -> 14943855 | D50: =SUM(D51:D59) -> 9300722.7 | E50: =SUM(E51:E59) -> 0 | G50: =SUM(G51:G59) -> 5076044.2 | H50: =SUM(H51:H59) -> 5383431.2 | I50: =SUM(I51:I59) -> 730510.01 | J50: =SUM(J51:J59) -> 0 | L50: =SUM(B50+G50) -> 22933911 | M50: =SUM(C50+H50) -> 20327286 | N50: =SUM(D50+I50) -> 10031233 | O50: =SUM(E50+J50) -> 0
A51: 2.6.1 - MOBILIARIO Y EQUIPO | B51: =SUM('TRANSFERENCIA CORRIENTE'!C52:E52) -> 1110625.9 | C51: =SUM('TRANSFERENCIA CORRIENTE'!F52:H52) -> 3586435.1 | D51: =SUM('TRANSFERENCIA CORRIENTE'!I52:K52) -> 2268904.4 | E51: =SUM('TRANSFERENCIA CORRIENTE'!L52:N52) -> 0 | G51: =SUM(VS!C52:E52) -> 0 | H51: =SUM(VS!F52:H52) -> 7995.01 | I51: =SUM(VS!I52:K52) -> 0 | J51: =SUM(VS!L52:N52) -> 0 | L51: =SUM(B51+G51) -> 1110625.9 | M51: =SUM(C51+H51) -> 3594430.1 | N51: =SUM(D51+I51) -> 2268904.4 | O51: =SUM(E51+J51) -> 0
A52: 2.6.2 - MOBILIARIO Y EQUIPO EDUCACIONAL Y RECREATIVO | B52: =SUM('TRANSFERENCIA CORRIENTE'!C53:E53) -> 0 | C52: =SUM('TRANSFERENCIA CORRIENTE'!F53:H53) -> 182926.74 | D52: =SUM('TRANSFERENCIA CORRIENTE'!I53:K53) -> 0 | E52: =SUM('TRANSFERENCIA CORRIENTE'!L53:N53) -> 0 | G52: =SUM(VS!C53:E53) -> 0 | H52: =SUM(VS!F53:H53) -> 1399834 | I52: =SUM(VS!I53:K53) -> 389046 | J52: =SUM(VS!L53:N53) -> 0 | L52: =SUM(B52+G52) -> 0 | M52: =SUM(C52+H52) -> 1582760.7 | N52: =SUM(D52+I52) -> 389046 | O52: =SUM(E52+J52) -> 0
A53: 2.6.3 - EQUIPO E INSTRUMENTAL, CIENTÍFICO Y LABORATORIO | B53: =SUM('TRANSFERENCIA CORRIENTE'!C54:E54) -> 16744041 | C53: =SUM('TRANSFERENCIA CORRIENTE'!F54:H54) -> 6663622.6 | D53: =SUM('TRANSFERENCIA CORRIENTE'!I54:K54) -> 5025506.7 | E53: =SUM('TRANSFERENCIA CORRIENTE'!L54:N54) -> 0 | G53: =SUM(VS!C54:E54) -> 2963024.8 | H53: =SUM(VS!F54:H54) -> 3975602.1 | I53: =SUM(VS!I54:K54) -> 0 | J53: =SUM(VS!L54:N54) -> 0 | L53: =SUM(B53+G53) -> 19707066 | M53: =SUM(C53+H53) -> 10639225 | N53: =SUM(D53+I53) -> 5025506.7 | O53: =SUM(E53+J53) -> 0
A54: 2.6.4 - VEHÍCULOS Y EQUIPO DE TRANSPORTE, TRACCIÓN Y ELEVACIÓN | B54: =SUM('TRANSFERENCIA CORRIENTE'!C55:E55) -> 0 | C54: =SUM('TRANSFERENCIA CORRIENTE'!F55:H55) -> 0 | D54: =SUM('TRANSFERENCIA CORRIENTE'!I55:K55) -> 0 | E54: =SUM('TRANSFERENCIA CORRIENTE'!L55:N55) -> 0 | G54: =SUM(VS!C55:E55) -> 107609.37 | H54: =SUM(VS!F55:H55) -> 0 | I54: =SUM(VS!I55:K55) -> 0 | J54: =SUM(VS!L55:N55) -> 0 | L54: =SUM(B54+G54) -> 107609.37 | M54: =SUM(C54+H54) -> 0 | N54: =SUM(D54+I54) -> 0 | O54: =SUM(E54+J54) -> 0
A55: 2.6.5 - MAQUINARIA, OTROS EQUIPOS Y HERRAMIENTAS | B55: =SUM('TRANSFERENCIA CORRIENTE'!C56:E56) -> 3199.97 | C55: =SUM('TRANSFERENCIA CORRIENTE'!F56:H56) -> 4165309.5 | D55: =SUM('TRANSFERENCIA CORRIENTE'!I56:K56) -> 2006311.6 | E55: =SUM('TRANSFERENCIA CORRIENTE'!L56:N56) -> 0 | G55: =SUM(VS!C56:E56) -> 2005410 | H55: =SUM(VS!F56:H56) -> 0 | I55: =SUM(VS!I56:K56) -> 282700.01 | J55: =SUM(VS!L56:N56) -> 0 | L55: =SUM(B55+G55) -> 2008610 | M55: =SUM(C55+H55) -> 4165309.5 | N55: =SUM(D55+I55) -> 2289011.6 | O55: =SUM(E55+J55) -> 0
A56: 2.6.6 - EQUIPOS DE DEFENSA Y SEGURIDAD | B56: =SUM('TRANSFERENCIA CORRIENTE'!C57:E57) -> 0 | C56: =SUM('TRANSFERENCIA CORRIENTE'!F57:H57) -> 0 | D56: =SUM('TRANSFERENCIA CORRIENTE'!I57:K57) -> 0 | E56: =SUM('TRANSFERENCIA CORRIENTE'!L57:N57) -> 0 | G56: =SUM(VS!C57:E57) -> 0 | H56: =SUM(VS!F57:H57) -> 0 | I56: =SUM(VS!I57:K57) -> 58764 | J56: =SUM(VS!L57:N57) -> 0 | L56: =SUM(B56+G56) -> 0 | M56: =SUM(C56+H56) -> 0 | N56: =SUM(D56+I56) -> 58764 | O56: =SUM(E56+J56) -> 0
A57: 2.6.7 - ACTIVOS BIÓLOGICOS CULTIVABLES | B57: =SUM('TRANSFERENCIA CORRIENTE'!C58:E58) -> 0 | C57: =SUM('TRANSFERENCIA CORRIENTE'!F58:H58) -> 0 | D57: =SUM('TRANSFERENCIA CORRIENTE'!I58:K58) -> 0 | E57: =SUM('TRANSFERENCIA CORRIENTE'!L58:N58) -> 0 | G57: =SUM(VS!C58:E58) -> 0 | H57: =SUM(VS!F58:H58) -> 0 | I57: =SUM(VS!I58:K58) -> 0 | J57: =SUM(VS!L58:N58) -> 0 | L57: =SUM(B57+G57) -> 0 | M57: =SUM(C57+H57) -> 0 | N57: =SUM(D57+I57) -> 0 | O57: =SUM(E57+J57) -> 0
A58: 2.6.8 - BIENES INTANGIBLES | B58: =SUM('TRANSFERENCIA CORRIENTE'!C59:E59) -> 0 | C58: =SUM('TRANSFERENCIA CORRIENTE'!F59:H59) -> 0 | D58: =SUM('TRANSFERENCIA CORRIENTE'!I59:K59) -> 0 | E58: =SUM('TRANSFERENCIA CORRIENTE'!L59:N59) -> 0 | G58: =SUM(VS!C59:E59) -> 0 | H58: =SUM(VS!F59:H59) -> 0 | I58: =SUM(VS!I59:K59) -> 0 | J58: =SUM(VS!L59:N59) -> 0 | L58: =SUM(B58+G58) -> 0 | M58: =SUM(C58+H58) -> 0 | N58: =SUM(D58+I58) -> 0 | O58: =SUM(E58+J58) -> 0
A59: 2.6.9 - EDIFICIOS, ESTRUCTURAS, TIERRAS, TERRENOS Y OBJETOS DE VALOR | B59: =SUM('TRANSFERENCIA CORRIENTE'!C60:E60) -> 0 | C59: =SUM('TRANSFERENCIA CORRIENTE'!F60:H60) -> 345560.94 | D59: =SUM('TRANSFERENCIA CORRIENTE'!I60:K60) -> 0 | E59: =SUM('TRANSFERENCIA CORRIENTE'!L60:N60) -> 0 | G59: =SUM(VS!C60:E60) -> 0 | H59: =SUM(VS!F60:H60) -> 0 | I59: =SUM(VS!I60:K60) -> 0 | J59: =SUM(VS!L60:N60) -> 0 | L59: =SUM(B59+G59) -> 0 | M59: =SUM(C59+H59) -> 345560.94 | N59: =SUM(D59+I59) -> 0 | O59: =SUM(E59+J59) -> 0
A60: 2.7 - OBRAS | B60: =SUM(B61:B64) -> 0 | C60: =SUM(C61:C64) -> 0 | D60: =SUM(D61:D64) -> 0 | E60: =SUM(E61:E64) -> 0 | G60: =SUM(G61:G64) -> 0 | H60: =SUM(H61:H64) -> 0 | I60: =SUM(I61:I64) -> 0 | J60: =SUM(J61:J64) -> 0 | L60: =SUM(B60+G60) -> 0 | M60: =SUM(C60+H60) -> 0 | N60: =SUM(D60+I60) -> 0 | O60: =SUM(E60+J60) -> 0
A61: 2.7.1 - OBRAS EN EDIFICACIONES | B61: =SUM('TRANSFERENCIA CORRIENTE'!C62:E62) -> 0 | C61: =SUM('TRANSFERENCIA CORRIENTE'!F62:H62) -> 0 | D61: =SUM('TRANSFERENCIA CORRIENTE'!I62:K62) -> 0 | E61: =SUM('TRANSFERENCIA CORRIENTE'!L62:N62) -> 0 | G61: =SUM(VS!C62:E62) -> 0 | H61: =SUM(VS!F62:H62) -> 0 | I61: =SUM(VS!I62:K62) -> 0 | J61: =SUM(VS!L62:N62) -> 0 | L61: =SUM(B61+G61) -> 0 | M61: =SUM(C61+H61) -> 0 | N61: =SUM(D61+I61) -> 0 | O61: =SUM(E61+J61) -> 0
A62: 2.7.2 - INFRAESTRUCTURA | B62: =SUM('TRANSFERENCIA CORRIENTE'!C63:E63) -> 0 | C62: =SUM('TRANSFERENCIA CORRIENTE'!F63:H63) -> 0 | D62: =SUM('TRANSFERENCIA CORRIENTE'!I63:K63) -> 0 | E62: =SUM('TRANSFERENCIA CORRIENTE'!L63:N63) -> 0 | G62: =SUM(VS!C63:E63) -> 0 | H62: =SUM(VS!F63:H63) -> 0 | I62: =SUM(VS!I63:K63) -> 0 | J62: =SUM(VS!L63:N63) -> 0 | L62: =SUM(B62+G62) -> 0 | M62: =SUM(C62+H62) -> 0 | N62: =SUM(D62+I62) -> 0 | O62: =SUM(E62+J62) -> 0
A63: 2.7.3 - CONSTRUCCIONES EN BIENES CONCESIONADOS | B63: =SUM('TRANSFERENCIA CORRIENTE'!C64:E64) -> 0 | C63: =SUM('TRANSFERENCIA CORRIENTE'!F64:H64) -> 0 | D63: =SUM('TRANSFERENCIA CORRIENTE'!I64:K64) -> 0 | E63: =SUM('TRANSFERENCIA CORRIENTE'!L64:N64) -> 0 | G63: =SUM(VS!C64:E64) -> 0 | H63: =SUM(VS!F64:H64) -> 0 | I63: =SUM(VS!I64:K64) -> 0 | J63: =SUM(VS!L64:N64) -> 0 | L63: =SUM(B63+G63) -> 0 | M63: =SUM(C63+H63) -> 0 | N63: =SUM(D63+I63) -> 0 | O63: =SUM(E63+J63) -> 0
A64: 2.7.4 - GASTOS QUE SE ASIGNARÁN DURANTE EL EJERCICIO PARA INVERSIÓN (ART. 32 Y 33 LEY 423-06) | B64: =SUM('TRANSFERENCIA CORRIENTE'!C65:E65) -> 0 | C64: =SUM('TRANSFERENCIA CORRIENTE'!F65:H65) -> 0 | D64: =SUM('TRANSFERENCIA CORRIENTE'!I65:K65) -> 0 | E64: =SUM('TRANSFERENCIA CORRIENTE'!L65:N65) -> 0 | G64: =SUM(VS!C65:E65) -> 0 | H64: =SUM(VS!F65:H65) -> 0 | I64: =SUM(VS!I65:K65) -> 0 | J64: =SUM(VS!L65:N65) -> 0 | L64: =SUM(B64+G64) -> 0 | M64: =SUM(C64+H64) -> 0 | N64: =SUM(D64+I64) -> 0 | O64: =SUM(E64+J64) -> 0
A65: 2.8 - ADQUISICION DE ACTIVOS FINANCIEROS CON FINES DE POLÍTICA | B65: =SUM(B66:B67) -> 0 | C65: =SUM(C66:C67) -> 0 | D65: =SUM(D66:D67) -> 0 | E65: =SUM(E66:E67) -> 0 | G65: =SUM(G66:G67) -> 0 | H65: =SUM(H66:H67) -> 0 | I65: =SUM(I66:I67) -> 0 | J65: =SUM(J66:J67) -> 0 | L65: =SUM(B65+G65) -> 0 | M65: =SUM(C65+H65) -> 0 | N65: =SUM(D65+I65) -> 0 | O65: =SUM(E65+J65) -> 0
A66: 2.8.1 - CONCESIÓN DE PRESTAMOS | B66: =SUM('TRANSFERENCIA CORRIENTE'!C67:E67) -> 0 | C66: =SUM('TRANSFERENCIA CORRIENTE'!F67:H67) -> 0 | D66: =SUM('TRANSFERENCIA CORRIENTE'!I67:K67) -> 0 | E66: =SUM('TRANSFERENCIA CORRIENTE'!L67:N67) -> 0 | G66: =SUM(VS!C67:E67) -> 0 | H66: =SUM(VS!F67:H67) -> 0 | I66: =SUM(VS!I67:K67) -> 0 | J66: =SUM(VS!L67:N67) -> 0 | L66: =SUM(B66+G66) -> 0 | M66: =SUM(C66+H66) -> 0 | N66: =SUM(D66+I66) -> 0 | O66: =SUM(E66+J66) -> 0
A67: 2.8.2 - ADQUISICIÓN DE TÍTULOS VALORES REPRESENTATIVOS DE DEUDA | B67: =SUM('TRANSFERENCIA CORRIENTE'!C68:E68) -> 0 | C67: =SUM('TRANSFERENCIA CORRIENTE'!F68:H68) -> 0 | D67: =SUM('TRANSFERENCIA CORRIENTE'!I68:K68) -> 0 | E67: =SUM('TRANSFERENCIA CORRIENTE'!L68:N68) -> 0 | G67: =SUM(VS!C68:E68) -> 0 | H67: =SUM(VS!F68:H68) -> 0 | I67: =SUM(VS!I68:K68) -> 0 | J67: =SUM(VS!L68:N68) -> 0 | L67: =SUM(B67+G67) -> 0 | M67: =SUM(C67+H67) -> 0 | N67: =SUM(D67+I67) -> 0 | O67: =SUM(E67+J67) -> 0
A68: 2.9 - GASTOS FINANCIEROS | B68: =SUM(B69:B71) -> 0 | C68: =SUM(C69:C71) -> 0 | D68: =SUM(D69:D71) -> 0 | E68: =SUM(E69:E71) -> 0 | G68: =SUM(G69:G71) -> 0 | H68: =SUM(H69:H71) -> 0 | I68: =SUM(I69:I71) -> 0 | J68: =SUM(J69:J71) -> 0 | L68: =SUM(B68+G68) -> 0 | M68: =SUM(C68+H68) -> 0 | N68: =SUM(D68+I68) -> 0 | O68: =SUM(E68+J68) -> 0
A69: 2.9.1 - INTERESES DE LA DEUDA PÚBLICA INTERNA | B69: =SUM('TRANSFERENCIA CORRIENTE'!C70:E70) -> 0 | C69: =SUM('TRANSFERENCIA CORRIENTE'!F70:H70) -> 0 | D69: =SUM('TRANSFERENCIA CORRIENTE'!I70:K70) -> 0 | E69: =SUM('TRANSFERENCIA CORRIENTE'!L70:N70) -> 0 | G69: =SUM(VS!C70:E70) -> 0 | H69: =SUM(VS!F70:H70) -> 0 | I69: =SUM(VS!I70:K70) -> 0 | J69: =SUM(VS!L70:N70) -> 0 | L69: =SUM(B69+G69) -> 0 | M69: =SUM(C69+H69) -> 0 | N69: =SUM(D69+I69) -> 0 | O69: =SUM(E69+J69) -> 0
A70: 2.9.2 - INTERESES DE LA DEUDA PUBLICA EXTERNA | B70: =SUM('TRANSFERENCIA CORRIENTE'!C71:E71) -> 0 | C70: =SUM('TRANSFERENCIA CORRIENTE'!F71:H71) -> 0 | D70: =SUM('TRANSFERENCIA CORRIENTE'!I71:K71) -> 0 | E70: =SUM('TRANSFERENCIA CORRIENTE'!L71:N71) -> 0 | G70: =SUM(VS!C71:E71) -> 0 | H70: =SUM(VS!F71:H71) -> 0 | I70: =SUM(VS!I71:K71) -> 0 | J70: =SUM(VS!L71:N71) -> 0 | L70: =SUM(B70+G70) -> 0 | M70: =SUM(C70+H70) -> 0 | N70: =SUM(D70+I70) -> 0 | O70: =SUM(E70+J70) -> 0
A71: 2.9.4 - COMISIONES Y OTROS GASTOS BANCARIOS DE LA DEUDA PÚBLICA | B71: =SUM('TRANSFERENCIA CORRIENTE'!C72:E72) -> 0 | C71: =SUM('TRANSFERENCIA CORRIENTE'!F72:H72) -> 0 | D71: =SUM('TRANSFERENCIA CORRIENTE'!I72:K72) -> 0 | E71: =SUM('TRANSFERENCIA CORRIENTE'!L72:N72) -> 0 | H71: =SUM(VS!F72:H72) -> 0 | I71: =SUM(VS!I72:K72) -> 0 | J71: =SUM(VS!L72:N72) -> 0 | L71: =SUM(B71+G71) -> 0 | M71: =SUM(C71+H71) -> 0 | N71: =SUM(D71+I71) -> 0 | O71: =SUM(E71+J71) -> 0
A72: Total Gastos | B72: =+B8+B14+B24+B34+B42+B50+B60+B65+B68 -> 2.7188025e+08 | C72: =+C8+C14+C24+C34+C42+C50+C60+C65+C68 -> 2.7723165e+08 | D72: =+D8+D14+D24+D34+D42+D50+D60+D65+D68 -> 1.1918855e+08 | E72: =+E8+E14+E24+E34+E42+E50+E60+E65+E68 -> 0 | G72: =+G8+G14+G24+G34+G42+G50+G60+G65+G68 -> 26194616 | H72: =+H8+H14+H24+H34+H42+H50+H60+H65+H68 -> 20399507 | I72: =+I8+I14+I24+I34+I42+I50+I60+I65+I68 -> 9254860.6 | J72: =+J8+J14+J24+J34+J42+J50+J60+J65+J68 -> 0 | L72: =SUM(B72+G72) -> 2.9807487e+08 | M72: =SUM(C72+H72) -> 2.9763115e+08 | N72: =SUM(D72+I72) -> 1.2844341e+08 | O72: =SUM(E72+J72) -> 0
A73: 4 - APLICACIONES FINANCIERAS | B73: =SUM('TRANSFERENCIA CORRIENTE'!C74:E74) -> 0 | C73: =SUM('TRANSFERENCIA CORRIENTE'!F74:H74) -> 0 | D73: =SUM('TRANSFERENCIA CORRIENTE'!I74:K74) -> 0 | E73: =SUM('TRANSFERENCIA CORRIENTE'!L74:N74) -> 0 | G73: =SUM(VS!C74:E74) -> 0 | H73: =SUM(VS!F74:H74) -> 0 | I73: =SUM(VS!I74:K74) -> 0 | J73: =SUM(VS!L74:N74) -> 0 | L73: =SUM(B73+G73) -> 0 | M73: =SUM(C73+H73) -> 0 | N73: =SUM(D73+I73) -> 0 | O73: =SUM(E73+J73) -> 0
A74: 4.1 - INCREMENTO DE ACTIVOS FINANCIEROS | B74: =SUM('TRANSFERENCIA CORRIENTE'!C75:E75) -> 0 | C74: =SUM('TRANSFERENCIA CORRIENTE'!F75:H75) -> 0 | D74: =SUM('TRANSFERENCIA CORRIENTE'!I75:K75) -> 0 | E74: =SUM('TRANSFERENCIA CORRIENTE'!L75:N75) -> 0 | G74: =SUM(VS!C75:E75) -> 0 | H74: =SUM(VS!F75:H75) -> 0 | I74: =SUM(VS!I75:K75) -> 0 | J74: =SUM(VS!L75:N75) -> 0 | L74: =SUM(B74+G74) -> 0 | M74: =SUM(C74+H74) -> 0 | N74: =SUM(D74+I74) -> 0 | O74: =SUM(E74+J74) -> 0
A75: 4.1.1 - INCREMENTO DE ACTIVOS FINANCIEROS CORRIENTES | B75: =SUM('TRANSFERENCIA CORRIENTE'!C76:E76) -> 0 | C75: =SUM('TRANSFERENCIA CORRIENTE'!F76:H76) -> 0 | D75: =SUM('TRANSFERENCIA CORRIENTE'!I76:K76) -> 0 | E75: =SUM('TRANSFERENCIA CORRIENTE'!L76:N76) -> 0 | G75: =SUM(VS!C76:E76) -> 0 | H75: =SUM(VS!F76:H76) -> 0 | I75: =SUM(VS!I76:K76) -> 0 | J75: =SUM(VS!L76:N76) -> 0 | L75: =SUM(B75+G75) -> 0 | M75: =SUM(C75+H75) -> 0 | N75: =SUM(D75+I75) -> 0 | O75: =SUM(E75+J75) -> 0
A76: 4.1.2 - INCREMENTO DE ACTIVOS FINANCIEROS NO CORRIENTES | B76: =SUM('TRANSFERENCIA CORRIENTE'!C77:E77) -> 0 | C76: =SUM('TRANSFERENCIA CORRIENTE'!F77:H77) -> 0 | D76: =SUM('TRANSFERENCIA CORRIENTE'!I77:K77) -> 0 | E76: =SUM('TRANSFERENCIA CORRIENTE'!L77:N77) -> 0 | G76: =SUM(VS!C77:E77) -> 0 | H76: =SUM(VS!F77:H77) -> 0 | I76: =SUM(VS!I77:K77) -> 0 | J76: =SUM(VS!L77:N77) -> 0 | L76: =SUM(B76+G76) -> 0 | M76: =SUM(C76+H76) -> 0 | N76: =SUM(D76+I76) -> 0 | O76: =SUM(E76+J76) -> 0
A77: 4.2 - DISMINUCIÓN DE PASIVOS | B77: =SUM('TRANSFERENCIA CORRIENTE'!C78:E78) -> 0 | C77: =SUM('TRANSFERENCIA CORRIENTE'!F78:H78) -> 0 | D77: =SUM('TRANSFERENCIA CORRIENTE'!I78:K78) -> 0 | E77: =SUM('TRANSFERENCIA CORRIENTE'!L78:N78) -> 0 | G77: =SUM(VS!C78:E78) -> 0 | H77: =SUM(VS!F78:H78) -> 0 | I77: =SUM(VS!I78:K78) -> 0 | J77: =SUM(VS!L78:N78) -> 0 | L77: =SUM(B77+G77) -> 0 | M77: =SUM(C77+H77) -> 0 | N77: =SUM(D77+I77) -> 0 | O77: =SUM(E77+J77) -> 0
A78: 4.2.1 - DISMINUCIÓN DE PASIVOS CORRIENTES | B78: =SUM('TRANSFERENCIA CORRIENTE'!C79:E79) -> 0 | C78: =SUM('TRANSFERENCIA CORRIENTE'!F79:H79) -> 0 | D78: =SUM('TRANSFERENCIA CORRIENTE'!I79:K79) -> 0 | E78: =SUM('TRANSFERENCIA CORRIENTE'!L79:N79) -> 0 | G78: =SUM(VS!C79:E79) -> 0 | H78: =SUM(VS!F79:H79) -> 0 | I78: =SUM(VS!I79:K79) -> 0 | J78: =SUM(VS!L79:N79) -> 0 | L78: =SUM(B78+G78) -> 0 | M78: =SUM(C78+H78) -> 0 | N78: =SUM(D78+I78) -> 0 | O78: =SUM(E78+J78) -> 0
A79: 4.2.2 - DISMINUCIÓN DE PASIVOS NO CORRIENTES | B79: =SUM('TRANSFERENCIA CORRIENTE'!C80:E80) -> 0 | C79: =SUM('TRANSFERENCIA CORRIENTE'!F80:H80) -> 0 | D79: =SUM('TRANSFERENCIA CORRIENTE'!I80:K80) -> 0 | E79: =SUM('TRANSFERENCIA CORRIENTE'!L80:N80) -> 0 | G79: =SUM(VS!C80:E80) -> 0 | H79: =SUM(VS!F80:H80) -> 0 | I79: =SUM(VS!I80:K80) -> 0 | J79: =SUM(VS!L80:N80) -> 0 | L79: =SUM(B79+G79) -> 0 | M79: =SUM(C79+H79) -> 0 | N79: =SUM(D79+I79) -> 0 | O79: =SUM(E79+J79) -> 0
A80: 4.3 - DISMINUCIÓN DE FONDOS DE TERCEROS | B80: =SUM('TRANSFERENCIA CORRIENTE'!C81:E81) -> 0 | C80: =SUM('TRANSFERENCIA CORRIENTE'!F81:H81) -> 0 | D80: =SUM('TRANSFERENCIA CORRIENTE'!I81:K81) -> 0 | E80: =SUM('TRANSFERENCIA CORRIENTE'!L81:N81) -> 0 | G80: =SUM(VS!C81:E81) -> 0 | H80: =SUM(VS!F81:H81) -> 0 | I80: =SUM(VS!I81:K81) -> 0 | J80: =SUM(VS!L81:N81) -> 0 | L80: =SUM(B80+G80) -> 0 | M80: =SUM(C80+H80) -> 0 | N80: =SUM(D80+I80) -> 0 | O80: =SUM(E80+J80) -> 0
A81: 4.3.5 - DISMINUCIÓN DEPÓSITOS FONDOS DE TERCEROS | B81: =SUM('TRANSFERENCIA CORRIENTE'!C82:E82) -> 0 | C81: =SUM('TRANSFERENCIA CORRIENTE'!F82:H82) -> 0 | D81: =SUM('TRANSFERENCIA CORRIENTE'!I82:K82) -> 0 | E81: =SUM('TRANSFERENCIA CORRIENTE'!L82:N82) -> 0 | G81: =SUM(VS!C82:E82) -> 0 | H81: =SUM(VS!F82:H82) -> 0 | I81: =SUM(VS!I82:K82) -> 0 | J81: =SUM(VS!L82:N82) -> 0 | L81: =SUM(B81+G81) -> 0 | M81: =SUM(C81+H81) -> 0 | N81: =SUM(D81+I81) -> 0 | O81: =SUM(E81+J81) -> 0
A82: TOTAL APLICACIONES FINANCIERAS | B82: =SUM(B83) -> 2.7188025e+08 | C82: =SUM(C83) -> 2.7723165e+08 | D82: =SUM(D83) -> 1.1029218e+08 | E82: =SUM(E83) -> 0 | G82: =SUM(G83) -> 26194616 | H82: =SUM(H83) -> 20399507 | I82: =SUM(I83) -> 9254860.6 | J82: =SUM(J83) -> 0 | L82: =SUM(B82+G82) -> 2.9807487e+08 | M82: =SUM(C82+H82) -> 2.9763115e+08 | N82: =SUM(D82+I82) -> 1.1954704e+08 | O82: =SUM(E82+J82) -> 0
A83: TOTAL GASTOS Y APLICACIONES FINANCIERAS | B83: =SUM('TRANSFERENCIA CORRIENTE'!C85:E85) -> 2.7188025e+08 | C83: =SUM('TRANSFERENCIA CORRIENTE'!F85:H85) -> 2.7723165e+08 | D83: =SUM('TRANSFERENCIA CORRIENTE'!I85:K85) -> 1.1029218e+08 | E83: =SUM('TRANSFERENCIA CORRIENTE'!L85:N85) -> 0 | G83: =SUM(VS!C85:E85) -> 26194616 | H83: =SUM(VS!F85:H85) -> 20399507 | I83: =SUM(VS!I85:K85) -> 9254860.6 | J83: =SUM(VS!L85:N85) -> 0 | L83: =SUM(B83+G83) -> 2.9807487e+08 | M83: =SUM(C83+H83) -> 2.9763115e+08 | N83: =SUM(D83+I83) -> 1.1954704e+08 | O83: =SUM(E83+J83) -> 0

Sheet TRANSFERENCIA CORRIENTE
A1: SERVICIO NACIONAL DE SALUD
A2: HOSPITAL MATERNO INFANTIL SAN LORENZO DE LOS MINA
A3: REGION
A4: Ejecución de Gastos Fondo (100) 2025
A5: En RD$
A7: Detalle | B7: Total | C7: Enero | D7: Febrero | E7: Marzo | F7: Abril | G7: Mayo | H7: Junio | I7: Julio | J7: Agosto | K7: Septiembre | L7: Octubre | M7: Noviembre | N7: Diciembre
A8: 2 - GASTOS
A9: 2.1 - REMUNERACIONES Y CONTRIBUCIONES | B9: =SUM(C9:N9) -> 4.6966673e+08 | C9: =SUM(C10:C14) -> 65091180 | D9: =SUM(D10:D14) -> 67131936 | E9: =SUM(E10:E14) -> 66337620 | F9: =SUM(F10:F14) -> 66556156 | G9: =SUM(G10:G14) -> 66630551 | H9: =SUM(H10:H14) -> 66583615 | I9: =SUM(I10:I14) -> 71335676 | J9: =SUM(J10:J14) -> 0 | ... N9: =SUM(N10:N14) -> 0
A10: 2.1.1 - REMUNERACIONES | B10: =SUM(C10:N10) -> 3.8695541e+08 | C10: 53640339 | D10: 55586129 | E10: 54718737 | F10: 54771097 | G10: 54445140 | H10: 54868543 | I10: 58925421
A11: 2.1.2 - SOBRESUELDOS | B11: =SUM(C11:N11) -> 23475078 | C11: 3196999.6 | D11: 3197999.6 | E11: 3199399.6 | F11: 3384964.5 | G11: 3807608.3 | H11: 3343226.2 | I11: 3344880.2
A12: 2.1.3 - DIETAS Y GASTOS DE REPRESENTACIÓN | B12: =SUM(C12:N12) -> 0
A13: 2.1.4 - GRATIFICACIONES Y BONIFICACIONES | B13: =SUM(C13:N13) -> 0
A14: 2.1.5 - CONTRIBUCIONES A LA SEGURIDAD SOCIAL | B14: =SUM(C14:N14) -> 59236249 | C14: 8253841.6 | D14: 8347807.5 | E14: 8419483.2 | F14: 8400093.9 | G14: 8377802.1 | H14: 8371846.2 | I14: 9065374.6
A15: 2.2 - CONTRATACIÓN DE SERVICIOS | B15: =SUM(C15:N15) -> 22949749 | C15: =SUM(C16:C24) -> 0 | D15: =SUM(D16:D24) -> 1336968.6 | E15: =SUM(E16:E24) -> 7971396.2 | F15: =SUM(F16:F24) -> 210535 | G15: =SUM(G16:G24) -> 1680824.8 | H15: =SUM(H16:H24) -> 8240458.4 | I15: =SUM(I16:I24) -> 3509565.8 | J15: =SUM(J16:J24) -> 0 | ... N15: =SUM(N16:N24) -> 0
A16: 2.2.1 - SERVICIOS BÁSICOS | B16: =SUM(C16:N16) -> 2262164.3 | E16: 2020024.3 | F16: 60535 | G16: 60535 | H16: 60535 | I16: 60535
A17: 2.2.2 - PUBLICIDAD, IMPRESIÓN Y ENCUADERNACIÓN | B17: =SUM(C17:N17) -> 676200.66 | D17: 324206.83 | G17: 32889.84 | H17: 319103.99
A18: 2.2.3 - VIÁTICOS | B18: =SUM(C18:N18) -> 0
A19: 2.2.4 - TRANSPORTE Y ALMACENAJE | B19: =SUM(C19:N19) -> 0
A20: 2.2.5 - ALQUILERES Y RENTAS | B20: =SUM(C20:N20) -> 150000 | F20: 150000
A21: 2.2.6 - SEGUROS | B21: =SUM(C21:N21) -> 0
A22: 2.2.7 - SERVICIOS DE CONSERVACIÓN, REPARACIONES MENORES E INSTALACIONES TEMPORALES | B22: =SUM(C22:N22) -> 15534939 | D22: 523061.81 | E22: 5951371.9 | G22: 1174400 | H22: 4437074.3 | I22: 3449030.8
A23: 2.2.8 - OTROS SERVICIOS NO INCLUIDOS EN CONCEPTOS ANTERIORES | B23: =SUM(C23:N23) -> 902700 | D23: 489700 | G23: 413000
A24: 2.2.9 - OTRAS CONTRATACIONES DE SERVICIOS | B24: =SUM(C24:N24) -> 3423745 | H24: 3423745
A25: 2.3 - MATERIALES Y SUMINISTROS | B25: =SUM(C25:N25) -> 1.2468515e+08 | C25: =SUM(C26:C34) -> 4970600.4 | D25: =SUM(D26:D34) -> 14433131 | E25: =SUM(E26:E34) -> 26749552 | F25: =SUM(F26:F34) -> 20368607 | G25: =SUM(G26:G34) -> 16608513 | H25: =SUM(H26:H34) -> 15408530 | I25: =SUM(I26:I34) -> 26146220 | J25: =SUM(J26:J34) -> 0 | ... N25: =SUM(N26:N34) -> 0
A26: 2.3.1 - ALIMENTOS Y PRODUCTOS AGROFORESTALES | D26: 591460.4 | E26: 3122436.8 | F26: 812515 | G26: 1657538 | H26: 2396946.2 | I26: 1787251.8
A27: 2.3.2 - TEXTILES Y VESTUARIOS | D27: 61630.73 | F27: 1562980.5 | H27: 812418.96 | I27: 1577150.7
A28: 2.3.3 - PRODUCTOS DE PAPEL, CARTÓN E IMPRESOS | D28: 352366.67 | E28: 1474545.2 | F28: 1510942.2 | G28: 765138.96 | H28: 715614.54 | I28: 1579886.7
A29: 2.3.4 - PRODUCTOS FARMACÉUTICOS | C29: 1862880 | D29: 2014526.8 | E29: 6919929 | F29: 6349109 | G29: 2637285.6 | H29: 3022962 | I29: 6806505
A30: 2.3.5 - PRODUCTOS DE CUERO, CAUCHO Y PLÁSTICO | E30: 334708.95 | F30: 506546.35 | G30: 384413.08 | H30: 133281 | I30: 655140.22
A31: 2.3.6 - PRODUCTOS DE MINERALES, METÁLICOS Y NO METÁLICOS | D31: 11630.98 | F31: 351015.88 | G31: 215177.81 | H31: 101426.9
A32: 2.3.7 - COMBUSTIBLES, LUBRICANTES, PRODUCTOS QUÍMICOS Y CONEXOS | C32: 1844663.4 | D32: 3902915.5 | E32: 3162523 | F32: 2759191.9 | G32: 4409677.5 | H32: 2900109.8 | I32: 4028536.8
A33: 2.3.8 - GASTOS QUE SE ASIGNARÁN DURANTE EL EJERCICIO (ART. 32 Y 33 LEY 423-06)
A34: 2.3.9 - PRODUCTOS Y ÚTILES VARIOS | C34: 1263057 | D34: 7498600.4 | E34: 11735409 | F34: 6516306.6 | G34: 6539281.9 | H34: 5325771 | I34: 9711748.4
A35: 2.4 - TRANSFERENCIAS CORRIENTES | B35: =SUM(C35:N35) -> 0 | C35: =SUM(C36:C42) -> 0 | D35: =SUM(D36:D42) -> 0 | E35: =SUM(E36:E42) -> 0 | F35: =SUM(F36:F42) -> 0 | G35: =SUM(G36:G42) -> 0 | H35: =SUM(H36:H42) -> 0 | I35: =SUM(I36:I42) -> 0 | J35: =SUM(J36:J42) -> 0 | ... N35: =SUM(N36:N42) -> 0
A36: 2.4.1 - TRANSFERENCIAS CORRIENTES AL SECTOR PRIVADO | B36: =SUM(C36:N36) -> 0
A37: 2.4.2 - TRANSFERENCIAS CORRIENTES AL GOBIERNO GENERAL NACIONAL | B37: =SUM(C37:N37) -> 0
A38: 2.4.3 - TRANSFERENCIAS CORRIENTES A GOBIERNOS GENERALES LOCALES | B38: =SUM(C38:N38) -> 0
A39: 2.4.4 - TRANSFERENCIAS CORRIENTES A EMPRESAS PÚBLICAS NO FINANCIERAS | B39: =SUM(C39:N39) -> 0
A40: 2.4.5 - TRANSFERENCIAS CORRIENTES A INSTITUCIONES PÚBLICAS FINANCIERAS | B40: =SUM(C40:N40) -> 0
A41: 2.4.7 - TRANSFERENCIAS CORRIENTES AL SECTOR EXTERNO | B41: =SUM(C41:N41) -> 0
A42: 2.4.9 - TRANSFERENCIAS CORRIENTES A OTRAS INSTITUCIONES PÚBLICAS | B42: =SUM(C42:N42) -> 0
A43: 2.5 - TRANSFERENCIAS DE CAPITAL | B43: =SUM(C43:N43) -> 0 | C43: =SUM(C44:C50) -> 0 | D43: =SUM(D44:D50) -> 0 | E43: =SUM(E44:E50) -> 0 | F43: =SUM(F44:F50) -> 0 | G43: =SUM(G44:G50) -> 0 | H43: =SUM(H44:H50) -> 0 | I43: =SUM(I44:I50) -> 0 | J43: =SUM(J44:J50) -> 0 | ... N43: =SUM(N44:N50) -> 0
A44: 2.5.1 - TRANSFERENCIAS DE CAPITAL AL SECTOR PRIVADO | B44: =SUM(C44:N44) -> 0
A45: 2.5.2 - TRANSFERENCIAS DE CAPITAL AL GOBIERNO GENERAL NACIONAL | B45: =SUM(C45:N45) -> 0
A46: 2.5.3 - TRANSFERENCIAS DE CAPITAL A GOBIERNOS GENERALES LOCALES | B46: =SUM(C46:N46) -> 0
A47: 2.5.4 - TRANSFERENCIAS DE CAPITAL A EMPRESAS PÚBLICAS NO FINANCIERAS | B47: =SUM(C47:N47) -> 0
A48: 2.5.5 - TRANSFERENCIAS DE CAPITAL A INSTITUCIONES PÚBLICAS FINANCIERAS | B48: =SUM(C48:N48) -> 0
A49: 2.5.6 - TRANSFERENCIAS DE CAPITAL AL SECTOR EXTERNO | B49: =SUM(C49:N49) -> 0
A50: 2.5.9 - TRANSFERENCIAS DE CAPITAL A OTRAS INSTITUCIONES PÚBLICAS | B50: =SUM(C50:N50) -> 0
A51: 2.6 - BIENES MUEBLES, INMUEBLES E INTANGIBLES | B51: =SUM(C51:N51) -> 42102444 | C51: =SUM(C52:C60) -> 0 | D51: =SUM(D52:D60) -> 6461017.3 | E51: =SUM(E52:E60) -> 11396849 | F51: =SUM(F52:F60) -> 4665041.4 | G51: =SUM(G52:G60) -> 6580673.1 | H51: =SUM(H52:H60) -> 3698140.3 | I51: =SUM(I52:I60) -> 9300722.7 | J51: =SUM(J52:J60) -> 0 | ... N51: =SUM(N52:N60) -> 0
A52: 2.6.1 - MOBILIARIO Y EQUIPO | B52: =SUM(C52:N52) -> 6965965.3 | D52: 432420.86 | E52: 678205 | F52: 1812434.5 | G52: 231484.25 | H52: 1542516.3 | I52: 2268904.4
A53: 2.6.2 - MOBILIARIO Y EQUIPO EDUCACIONAL Y RECREATIVO | B53: =SUM(C53:N53) -> 182926.74 | G53: 182926.74
A54: 2.6.3 - EQUIPO E INSTRUMENTAL, CIENTÍFICO Y LABORATORIO | B54: =SUM(C54:N54) -> 28433170 | D54: 6028596.4 | E54: 10715444 | F54: 2635786.9 | G54: 2285211.7 | H54: 1742624 | I54: 5025506.7
A55: 2.6.4 - VEHÍCULOS Y EQUIPO DE TRANSPORTE, TRACCIÓN Y ELEVACIÓN | B55: =SUM(C55:N55) -> 0
A56: 2.6.5 - MAQUINARIA, OTROS EQUIPOS Y HERRAMIENTAS | B56: =SUM(C56:N56) -> 6174821.1 | E56: 3199.97 | F56: 216820 | G56: 3535489.5 | H56: 413000 | I56: 2006311.6
A57: 2.6.6 - EQUIPOS DE DEFENSA Y SEGURIDAD | B57: =SUM(C57:N57) -> 0
A58: 2.6.7 - ACTIVOS BIÓLOGICOS CULTIVABLES | B58: =SUM(C58:N58) -> 0
A59: 2.6.8 - BIENES INTANGIBLES | B59: =SUM(C59:N59) -> 0
A60: 2.6.9 - EDIFICIOS, ESTRUCTURAS, TIERRAS, TERRENOS Y OBJETOS DE VALOR | B60: =SUM(C60:N60) -> 345560.94 | G60: 345560.94
A61: 2.7 - OBRAS | B61: =SUM(C61:N61) -> 0 | C61: =SUM(C62:C65) -> 0 | D61: =SUM(D62:D65) -> 0 | E61: =SUM(E62:E65) -> 0 | F61: =SUM(F62:F65) -> 0 | G61: =SUM(G62:G65) -> 0 | H61: =SUM(H62:H65) -> 0 | I61: =SUM(I62:I65) -> 0 | J61: =SUM(J62:J65) -> 0 | ... N61: =SUM(N62:N65) -> 0
A62: 2.7.1 - OBRAS EN EDIFICACIONES | B62: =SUM(C62:N62) -> 0
A63: 2.7.2 - INFRAESTRUCTURA | B63: =SUM(C63:N63) -> 0
A64: 2.7.3 - CONSTRUCCIONES EN BIENES CONCESIONADOS | B64: =SUM(C64:N64) -> 0
A65: 2.7.4 - GASTOS QUE SE ASIGNARÁN DURANTE EL EJERCICIO PARA INVERSIÓN (ART. 32 Y 33 LEY 423-06) | B65: =SUM(C65:N65) -> 0
A66: 2.8 - ADQUISICION DE ACTIVOS FINANCIEROS CON FINES DE POLÍTICA | B66: =SUM(C66:N66) -> 0 | C66: =SUM(C67:C68) -> 0 | D66: =SUM(D67:D68) -> 0 | E66: =SUM(E67:E68) -> 0 | F66: =SUM(F67:F68) -> 0 | G66: =SUM(G67:G68) -> 0 | H66: =SUM(H67:H68) -> 0 | I66: =SUM(I67:I68) -> 0 | J66: =SUM(J67:J68) -> 0 | ... N66: =SUM(N67:N68) -> 0
A67: 2.8.1 - CONCESIÓN DE PRESTAMOS | B67: =SUM(C67:N67) -> 0
A68: 2.8.2 - ADQUISICIÓN DE TÍTULOS VALORES REPRESENTATIVOS DE DEUDA | B68: =SUM(C68:N68) -> 0
A69: 2.9 - GASTOS FINANCIEROS | B69: =SUM(C69:N69) -> 0 | C69: =SUM(C70:C72) -> 0 | D69: =SUM(D70:D72) -> 0 | E69: =SUM(E70:E72) -> 0 | F69: =SUM(F70:F72) -> 0 | G69: =SUM(G70:G72) -> 0 | H69: =SUM(H70:H72) -> 0 | I69: =SUM(I70:I72) -> 0 | J69: =SUM(J70:J72) -> 0 | ... N69: =SUM(N70:N72) -> 0
A70: 2.9.1 - INTERESES DE LA DEUDA PÚBLICA INTERNA | B70: =SUM(C70:N70) -> 0
A71: 2.9.2 - INTERESES DE LA DEUDA PUBLICA EXTERNA | B71: =SUM(C71:N71) -> 0
A72: 2.9.4 - COMISIONES Y OTROS GASTOS BANCARIOS DE LA DEUDA PÚBLICA | B72: =SUM(C72:N72) -> 0
A73: Total Gastos | B73: =B9+B15+B25+B35+B43+B51+B61+B66+B69 -> 6.5940408e+08 | C73: =C9+C15+C25+C35+C43+C51+C61+C66+C69 -> 70061780 | D73: =D9+D15+D25+D35+D43+D51+D61+D66+D69 -> 89363053 | E73: =E9+E15+E25+E35+E43+E51+E61+E66+E69 -> 1.1245542e+08 | F73: =F9+F15+F25+F35+F43+F51+F61+F66+F69 -> 91800340 | G73: =G9+G15+G25+G35+G43+G51+G61+G66+G69 -> 91500562 | H73: =H9+H15+H25+H35+H43+H51+H61+H66+H69 -> 93930744 | I73: =I9+I15+I25+I35+I43+I51+I61+I66+I69 -> 1.1029218e+08 | ... N73: =N9+N15+N25+N35+N43+N51+N61+N66+N69 -> 0
A74: 4 - APLICACIONES FINANCIERAS
A75: 4.1 - INCREMENTO DE ACTIVOS FINANCIEROS
A76: 4.1.1 - INCREMENTO DE ACTIVOS FINANCIEROS CORRIENTES
A77: 4.1.2 - INCREMENTO DE ACTIVOS FINANCIEROS NO CORRIENTES
A78: 4.2 - DISMINUCIÓN DE PASIVOS
A79: 4.2.1 - DISMINUCIÓN DE PASIVOS CORRIENTES
A80: 4.2.2 - DISMINUCIÓN DE PASIVOS NO CORRIENTES
A81: 4.3 - DISMINUCIÓN DE FONDOS DE TERCEROS
A82: 4.3.5 - DISMINUCIÓN DEPÓSITOS FONDOS DE TERCEROS
A83: TOTAL APLICACIONES FINANCIERAS
A85: TOTAL GASTOS Y APLICACIONES FINANCIERAS | B85: =+B83+B73 -> 6.5940408e+08 | C85: =+C83+C73 -> 70061780 | D85: =+D83+D73 -> 89363053 | E85: =+E83+E73 -> 1.1245542e+08 | F85: =+F83+F73 -> 91800340 | G85: =+G83+G73 -> 91500562 | H85: =+H83+H73 -> 93930744 | I85: =+I83+I73 -> 1.1029218e+08 | ... N85: =+N83+N73 -> 0
A86: Fuente: [fuente]
A87: Fecha de registro: hasta el [01] de [01] del [2025]
A88: Fecha de imputación: hasta el [31] de [07] del [2025]

Sheet VS
A1: SERVICIO NACIONAL DE SALUD
A2: HOSPITAL MATERNO INFANTIL SAN LORENZO DE LOS MINA
A3: REGION
A4: Ejecución de Gastos VENTA SERVICIOS 2025
A5: En RD$
A7: Detalle | B7: Total | C7: Enero | D7: Febrero | E7: Marzo | F7: Abril | G7: Mayo | H7: Junio | I7: Julio | J7: Agosto | K7: Septiembre | L7: Octubre | M7: Noviembre | N7: Diciembre
A8: 2 - GASTOS
A9: 2.1 - REMUNERACIONES Y CONTRIBUCIONES | B9: =SUM(C9:N9) -> 5231553.6 | C9: =SUM(C10:C14) -> 0 | D9: =SUM(D10:D14) -> 0 | E9: =SUM(E10:E14) -> 5231553.6 | F9: =SUM(F10:F14) -> 0 | G9: =SUM(G10:G14) -> 0 | H9: =SUM(H10:H14) -> 0 | I9: =SUM(I10:I14) -> 0 | J9: =SUM(J10:J14) -> 0 | ... N9: =SUM(N10:N14) -> 0
A10: 2.1.1 - REMUNERACIONES | B10: =SUM(C10:N10) -> 0
A11: 2.1.2 - SOBRESUELDOS | B11: =SUM(C11:N11) -> 5231553.6 | E11: 5231553.6
A12: 2.1.3 - DIETAS Y GASTOS DE REPRESENTACIÓN | B12: =SUM(C12:N12) -> 0
A13: 2.1.4 - GRATIFICACIONES Y BONIFICACIONES | B13: =SUM(C13:N13) -> 0
A14: 2.1.5 - CONTRIBUCIONES A LA SEGURIDAD SOCIAL | B14: =SUM(C14:N14) -> 0
A15: 2.2 - CONTRATACIÓN DE SERVICIOS | B15: =SUM(C15:N15) -> 20558253 | C15: =SUM(C16:C24) -> 2733844.3 | D15: =SUM(D16:D24) -> 1213383.4 | E15: =SUM(E16:E24) -> 4359456.2 | F15: =SUM(F16:F24) -> 1256712.1 | G15: =SUM(G16:G24) -> 2044062.6 | H15: =SUM(H16:H24) -> 3938639.1 | I15: =SUM(I16:I24) -> 5012155.8 | J15: =SUM(J16:J24) -> 0 | ... N15: =SUM(N16:N24) -> 0
A16: 2.2.1 - SERVICIOS BÁSICOS | B16: =SUM(C16:N16) -> 6472046.7 | C16: 351316.33 | D16: 259054.4 | E16: 1731191.2 | F16: 285608.3 | G16: 1098463.4 | H16: 964509 | I16: 1781904.1
A17: 2.2.2 - PUBLICIDAD, IMPRESIÓN Y ENCUADERNACIÓN | B17: =SUM(C17:N17) -> 891584.4 | H17: 310139.4 | I17: 581445
A18: 2.2.3 - VIÁTICOS | B18: =SUM(C18:N18) -> 0
A19: 2.2.4 - TRANSPORTE Y ALMACENAJE | B19: =SUM(C19:N19) -> 160000 | D19: 24000 | E19: 32000 | G19: 76000 | H19: 20000 | I19: 8000
A20: 2.2.5 - ALQUILERES Y RENTAS | B20: =SUM(C20:N20) -> 1577657.1 | C20: 266664.25 | D20: 252960.9 | F20: 229519.78 | G20: 529650.64 | I20: 298861.54
A21: 2.2.6 - SEGUROS | B21: =SUM(C21:N21) -> 0
A22: 2.2.7 - SERVICIOS DE CONSERVACIÓN, REPARACIONES MENORES E INSTALACIONES TEMPORALES | B22: =SUM(C22:N22) -> 7230241 | C22: 2064518.4 | D22: =215685.19+42142.86+18061.22+33714.29+21673.47+18061.22+115591.83+7826.53 -> 472756.61 | E22: 2019575.2 | F22: 199877.53 | G22: 205899.14 | H22: 635040.9 | I22: 1632573.3
A23: 2.2.8 - OTROS SERVICIOS NO INCLUIDOS EN CONCEPTOS ANTERIORES | B23: =SUM(C23:N23) -> 3316436.8 | C23: 51345.35 | D23: =193432+11179.44 -> 204611.44 | E23: 576689.87 | F23: =524513+17193.48 -> 541706.48 | G23: 134049.4 | H23: 1098662.4 | I23: 709371.88
A24: 2.2.9 - OTRAS CONTRATACIONES DE SERVICIOS | B24: =SUM(C24:N24) -> 910287.4 | H24: 910287.4
A25: 2.3 - MATERIALES Y SUMINISTROS | B25: =SUM(C25:N25) -> 17289852 | C25: =SUM(C26:C34) -> 3062630.7 | D25: =SUM(D26:D34) -> 2432378.3 | E25: =SUM(E26:E34) -> 1797538.3 | F25: =SUM(F26:F34) -> 2995765.2 | G25: =SUM(G26:G34) -> 2557401.6 | H25: =SUM(H26:H34) -> 999513.81 | I25: =SUM(I26:I34) -> 3444623.9 | J25: =SUM(J26:J34) -> 0 | ... N25: =SUM(N26:N34) -> 0
A26: 2.3.1 - ALIMENTOS Y PRODUCTOS AGROFORESTALES | B26: =SUM(C26:N26) -> 2524715.8 | C26: 541265 | D26: 300691.8 | E26: 658799 | F26: 94850 | G26: 355075 | H26: 213305 | I26: 360730
A27: 2.3.2 - TEXTILES Y VESTUARIOS | B27: =SUM(C27:N27) -> 346306.4 | G27: 141128 | H27: 205178.4
A28: 2.3.3 - PRODUCTOS DE PAPEL, CARTÓN E IMPRESOS | B28: =SUM(C28:N28) -> 1081702 | C28: 85550 | D28: 107616 | E28: 57997 | F28: 196824 | G28: 607165 | I28: 26550
A29: 2.3.4 - PRODUCTOS FARMACÉUTICOS | B29: =SUM(C29:N29) -> 1113020.8 | C29: 308000 | E29: 250000 | F29: 92000 | G29: 130100 | H29: 180120.76 | I29: 152800
A30: 2.3.5 - PRODUCTOS DE CUERO, CAUCHO Y PLÁSTICO | B30: =SUM(C30:N30) -> 644884.88 | D30: 249831.2 | E30: 317663.67 | I30: 77390.01
A31: 2.3.6 - PRODUCTOS DE MINERALES, METÁLICOS Y NO METÁLICOS | B31: =SUM(C31:N31) -> 318115.25 | D31: 183732.33 | E31: 110224.97 | I31: 24157.95
A32: 2.3.7 - COMBUSTIBLES, LUBRICANTES, PRODUCTOS QUÍMICOS Y CONEXOS | B32: =SUM(C32:N32) -> 4205051.6 | C32: 228412.84 | D32: 1114592.7 | E32: 317328.99 | F32: 226537 | G32: 1065923 | H32: 207742 | I32: 1044515
A33: 2.3.8 - GASTOS QUE SE ASIGNARÁN DURANTE EL EJERCICIO (ART. 32 Y 33 LEY 423-06) | B33: =SUM(C33:N33) -> 0
A34: 2.3.9 - PRODUCTOS Y ÚTILES VARIOS | B34: =SUM(C34:N34) -> 7056055.1 | C34: 1899402.8 | D34: =423850.01+52064.22 -> 475914.23 | E34: 85524.69 | F34: =2330135.61+55418.59 -> 2385554.2 | G34: 258010.6 | H34: 193167.65 | I34: 1758480.9
A35: 2.4 - TRANSFERENCIAS CORRIENTES | B35: =SUM(C35:N35) -> 1579338.7 | C35: =SUM(C36:C42) -> 136966.7 | D35: =SUM(D36:D42) -> 23400 | E35: =SUM(E36:E42) -> 127420 | F35: =SUM(F36:F42) -> 624573 | G35: =SUM(G36:G42) -> 480808 | H35: =SUM(H36:H42) -> 118600 | I35: =SUM(I36:I42) -> 67571 | J35: =SUM(J36:J42) -> 0 | ... N35: =SUM(N36:N42) -> 0
A36: 2.4.1 - TRANSFERENCIAS CORRIENTES AL SECTOR PRIVADO | B36: =SUM(C36:N36) -> 1519338.7 | C36: 136966.7 | D36: 23400 | E36: 127420 | F36: 624573 | G36: 480808 | H36: 58600 | I36: 67571
A37: 2.4.2 - TRANSFERENCIAS CORRIENTES AL GOBIERNO GENERAL NACIONAL | B37: =SUM(C37:N37) -> 60000 | H37: 60000
A38: 2.4.3 - TRANSFERENCIAS CORRIENTES A GOBIERNOS GENERALES LOCALES | B38: =SUM(C38:N38) -> 0
A39: 2.4.4 - TRANSFERENCIAS CORRIENTES A EMPRESAS PÚBLICAS NO FINANCIERAS | B39: =SUM(C39:N39) -> 0
A40: 2.4.5 - TRANSFERENCIAS CORRIENTES A INSTITUCIONES PÚBLICAS FINANCIERAS | B40: =SUM(C40:N40) -> 0
A41: 2.4.7 - TRANSFERENCIAS CORRIENTES AL SECTOR EXTERNO | B41: =SUM(C41:N41) -> 0
A42: 2.4.9 - TRANSFERENCIAS CORRIENTES A OTRAS INSTITUCIONES PÚBLICAS | B42: =SUM(C42:N42) -> 0
A43: 2.5 - TRANSFERENCIAS DE CAPITAL | B43: =SUM(C43:N43) -> 0 | C43: =SUM(C44:C50) -> 0 | D43: =SUM(D44:D50) -> 0 | E43: =SUM(E44:E50) -> 0 | F43: =SUM(F44:F50) -> 0 | G43: =SUM(G44:G50) -> 0 | H43: =SUM(H44:H50) -> 0 | I43: =SUM(I44:I50) -> 0 | J43: =SUM(J44:J50) -> 0 | ... N43: =SUM(N44:N50) -> 0
A44: 2.5.1 - TRANSFERENCIAS DE CAPITAL AL SECTOR PRIVADO | B44: =SUM(C44:N44) -> 0
A45: 2.5.2 - TRANSFERENCIAS DE CAPITAL AL GOBIERNO GENERAL NACIONAL | B45: =SUM(C45:N45) -> 0
A46: 2.5.3 - TRANSFERENCIAS DE CAPITAL A GOBIERNOS GENERALES LOCALES | B46: =SUM(C46:N46) -> 0
A47: 2.5.4 - TRANSFERENCIAS DE CAPITAL A EMPRESAS PÚBLICAS NO FINANCIERAS | B47: =SUM(C47:N47) -> 0
A48: 2.5.5 - TRANSFERENCIAS DE CAPITAL A INSTITUCIONES PÚBLICAS FINANCIERAS | B48: =SUM(C48:N48) -> 0
A49: 2.5.6 - TRANSFERENCIAS DE CAPITAL AL SECTOR EXTERNO | B49: =SUM(C49:N49) -> 0
A50: 2.5.9 - TRANSFERENCIAS DE CAPITAL A OTRAS INSTITUCIONES PÚBLICAS | B50: =SUM(C50:N50) -> 0
A51: 2.6 - BIENES MUEBLES, INMUEBLES E INTANGIBLES | B51: =SUM(C51:N51) -> 11189985 | C51: =SUM(C52:C60) -> 887994.84 | D51: =SUM(D52:D60) -> 3887510 | E51: =SUM(E52:E60) -> 300539.37 | F51: =SUM(F52:F60) -> 0 | G51: =SUM(G52:G60) -> 3927042.2 | H51: =SUM(H52:H60) -> 1456389 | I51: =SUM(I52:I60) -> 730510.01 | J51: =SUM(J52:J60) -> 0 | ... N51: =SUM(N52:N60) -> 0
A52: 2.6.1 - MOBILIARIO Y EQUIPO | B52: =SUM(C52:N52) -> 7995.01 | H52: 7995.01
A53: 2.6.2 - MOBILIARIO Y EQUIPO EDUCACIONAL Y RECREATIVO | B53: =SUM(C53:N53) -> 1788880 | H53: 1399834 | I53: 389046
A54: 2.6.3 - EQUIPO E INSTRUMENTAL, CIENTÍFICO Y LABORATORIO | B54: =SUM(C54:N54) -> 6938627 | C54: 887994.84 | D54: 2075030 | G54: 3927042.2 | H54: 48559.95
A55: 2.6.4 - VEHÍCULOS Y EQUIPO DE TRANSPORTE, TRACCIÓN Y ELEVACIÓN | B55: =SUM(C55:N55) -> 107609.37 | E55: 107609.37
A56: 2.6.5 - MAQUINARIA, OTROS EQUIPOS Y HERRAMIENTAS | B56: =SUM(C56:N56) -> 2288110 | D56: 1812480 | E56: 192930 | I56: 282700.01
A57: 2.6.6 - EQUIPOS DE DEFENSA Y SEGURIDAD | B57: =SUM(C57:N57) -> 58764 | I57: 58764
A58: 2.6.7 - ACTIVOS BIÓLOGICOS CULTIVABLES | B58: =SUM(C58:N58) -> 0
A59: 2.6.8 - BIENES INTANGIBLES | B59: =SUM(C59:N59) -> 0
A60: 2.6.9 - EDIFICIOS, ESTRUCTURAS, TIERRAS, TERRENOS Y OBJETOS DE VALOR | B60: =SUM(C60:N60) -> 0
A61: 2.7 - OBRAS | B61: =SUM(C61:N61) -> 0 | C61: =SUM(C62:C65) -> 0 | D61: =SUM(D62:D65) -> 0 | E61: =SUM(E62:E65) -> 0 | F61: =SUM(F62:F65) -> 0 | G61: =SUM(G62:G65) -> 0 | H61: =SUM(H62:H65) -> 0 | I61: =SUM(I62:I65) -> 0 | J61: =SUM(J62:J65) -> 0 | ... N61: =SUM(N62:N65) -> 0
A62: 2.7.1 - OBRAS EN EDIFICACIONES | B62: =SUM(C62:N62) -> 0
A63: 2.7.2 - INFRAESTRUCTURA | B63: =SUM(C63:N63) -> 0
A64: 2.7.3 - CONSTRUCCIONES EN BIENES CONCESIONADOS | B64: =SUM(C64:N64) -> 0
A65: 2.7.4 - GASTOS QUE SE ASIGNARÁN DURANTE EL EJERCICIO PARA INVERSIÓN (ART. 32 Y 33 LEY 423-06) | B65: =SUM(C65:N65) -> 0
A66: 2.8 - ADQUISICION DE ACTIVOS FINANCIEROS CON FINES DE POLÍTICA | B66: =SUM(C66:N66) -> 0 | C66: =SUM(C67:C68) -> 0 | D66: =SUM(D67:D68) -> 0 | E66: =SUM(E67:E68) -> 0 | F66: =SUM(F67:F68) -> 0 | G66: =SUM(G67:G68) -> 0 | H66: =SUM(H67:H68) -> 0 | I66: =SUM(I67:I68) -> 0 | J66: =SUM(J67:J68) -> 0 | ... N66: =SUM(N67:N68) -> 0
A67: 2.8.1 - CONCESIÓN DE PRESTAMOS | B67: =SUM(C67:N67) -> 0
A68: 2.8.2 - ADQUISICIÓN DE TÍTULOS VALORES REPRESENTATIVOS DE DEUDA | B68: =SUM(C68:N68) -> 0
A69: 2.9 - GASTOS FINANCIEROS | B69: =SUM(C69:N69) -> 0 | C69: =SUM(C70:C72) -> 0 | D69: =SUM(D70:D72) -> 0 | E69: =SUM(E70:E72) -> 0 | F69: =SUM(F70:F72) -> 0 | G69: =SUM(G70:G72) -> 0 | H69: =SUM(H70:H72) -> 0 | I69: =SUM(I70:I72) -> 0 | J69: =SUM(J70:J72) -> 0 | ... N69: =SUM(N70:N72) -> 0
A70: 2.9.1 - INTERESES DE LA DEUDA PÚBLICA INTERNA | B70: =SUM(C70:N70) -> 0
A71: 2.9.2 - INTERESES DE LA DEUDA PUBLICA EXTERNA | B71: =SUM(C71:N71) -> 0
A72: 2.9.4 - COMISIONES Y OTROS GASTOS BANCARIOS DE LA DEUDA PÚBLICA | B72: =SUM(C72:N72) -> 0
A73: Total Gastos | B73: =B9+B15+B25+B35+B43+B51+B61+B66+B69 -> 55848983 | C73: =C9+C15+C25+C35+C43+C51+C61+C66+C69 -> 6821436.5 | D73: =D9+D15+D25+D35+D43+D51+D61+D66+D69 -> 7556671.6 | E73: =E9+E15+E25+E35+E43+E51+E61+E66+E69 -> 11816507 | F73: =F9+F15+F25+F35+F43+F51+F61+F66+F69 -> 4877050.3 | G73: =G9+G15+G25+G35+G43+G51+G61+G66+G69 -> 9009314.4 | H73: =H9+H15+H25+H35+H43+H51+H61+H66+H69 -> 6513141.9 | I73: =I9+I15+I25+I35+I43+I51+I61+I66+I69 -> 9254860.6 | ... N73: =N9+N15+N25+N35+N43+N51+N61+N66+N69 -> 0
A74: 4 - APLICACIONES FINANCIERAS
A75: 4.1 - INCREMENTO DE ACTIVOS FINANCIEROS
A76: 4.1.1 - INCREMENTO DE ACTIVOS FINANCIEROS CORRIENTES
A77: 4.1.2 - INCREMENTO DE ACTIVOS FINANCIEROS NO CORRIENTES
A78: 4.2 - DISMINUCIÓN DE PASIVOS
A79: 4.2.1 - DISMINUCIÓN DE PASIVOS CORRIENTES
A80: 4.2.2 - DISMINUCIÓN DE PASIVOS NO CORRIENTES
A81: 4.3 - DISMINUCIÓN DE FONDOS DE TERCEROS
A82: 4.3.5 - DISMINUCIÓN DEPÓSITOS FONDOS DE TERCEROS
A83: TOTAL APLICACIONES FINANCIERAS
A85: TOTAL GASTOS Y APLICACIONES FINANCIERAS | B85: =+B83+B73 -> 55848983 | C85: =+C83+C73 -> 6821436.5 | D85: =+D83+D73 -> 7556671.6 | E85: =+E83+E73 -> 11816507 | F85: =+F83+F73 -> 4877050.3 | G85: =+G83+G73 -> 9009314.4 | H85: =+H83+H73 -> 6513141.9 | I85: =+I83+I73 -> 9254860.6
A86: Fuente: [fuente]
A87: Fecha de registro: hasta el [01] de [01] del [2025]
A88: Fecha de imputación: hasta el [31] de [07] del [2025]

Sheet OBLIGACIONES PENDIENTES
B4: SERVICIO REGIONAL DE SALUD
B5: DIRECCIÓN DE FISCALIZACIÓN Y CONTROL
B6: DETALLE OBLIGACIONES CONTRAÍDAS PENDIENTES AL 31 DE JULIO 2025
B7: HOSPITAL MATERNO INFANTIL SAN LORENZO DE LOS MINA
B8: A | C8: B | E8: C | F8: D | G8: E | H8: F
B9: TIPO | C9: PERÍODO | F9: STATUS PRESTAMO
C10: DESDE | D10: HASTA | E10: MONTO | F10: MONTO ORIGEN | G10: MONTO AMORTIZADO | H10: BALANCE PENDIENTE
B11: PROMESE CAL
B12: RETENCIONES DE IMPUESTOS (DGII) | C12: 44470 | D12: 45808 | E12: =6455721.37+191917.63+545919.42+146780.59+231604.06+289366.65+335354.64+387110.47+660164.03+254405.37+295100.71+268154.84+476725.77+301006.83+418780.67+471731.75+276884.63+183994.68+296760.59+288708.77+391617.11 -> 13167811
B13: APROVISIONAMIENTOS DE INCENTIVOS | C13: 45505 | D13: 45808 | E13: =4432093.625+933892.46+332731.24+782528.07-5231553.59+751870.91+363151.11+1094213.86 -> 3458927.7
B14: SEGURIDAD SOCIAL
B15: APROVISIONAMIENTO DE REGALIA PASCUAL
B16: PRESTACIONES LABORALES
B17: VIATICOS
B18: PRÉSTAMOS Y/O ANTICIPOS FINANCIEROS OTORGADOS POR SENASA
B19: TOTAL | E19: =SUM(E12:E18)+E11 -> 16626738
B21: Nota. En el caso de las columnas D, E y F, solo aplican para llenado de los préstamos otogados por SENASA.
B25: Preparado por: | E25: Revisado por:

Sheet INGR SEGUN ORIGEN
A3: Servicio Nacional de Salud
A4: Dirección de Fiscalización
A6: Comportamiento de Ingresos percibidos Segregados según Origen
A7: Establecimiento: HOSPITAL MATERNO INFANTIL SAN LORENZO DE LOS MINA Mes: JULIO . Año: 2025 SRS: I
A8: . | B8: ARS | C8: Fecha deposito | D8: No. De Documento de referencia | E8: valor de Transferencia o Cheque
A9: INGRESOS | B9: FONDO 100(2.1) | E9: =79621891.83+4931430 -> 84553322
B10: FONDO 100(2.3) | E10: 12593841
B11: FONDO 100(2.6) | E11: 3169632.1
A12: Sub-Total | E12: =SUM(E9:E11) -> 1.003168e+08
A13: ARS | B13: ARS SIGMA | C13: 45860 | E13: 4943.4
B14: ARS MONUMENTAL | C14: 45840 | E14: 125937.38
B15: ARS SIMAG | C15: 45840 | E15: 176215.29
B16: ARS HUMANO | C16: 45860 | E16: 48385.69
B17: ARS PRIMERA | C17: 45860 | E17: 313059.93
B18: ARS GMA | C18: 45860 | E18: 395386.07
B19: ARS FUTURO | C19: 45867 | E19: 649331.98
B20: ARS MAPHRE | C20: 45856 | E20: 7867.11
B21: ARS MAPHRE | C21: 45856 | E21: 9031.14
B22: ARS MAPHRE | C22: 45856 | E22: 24398.12
B23: ARS MAPHRE | C23: 45856 | E23: 47703.2
B24: ARS MAPHRE | C24: 45856 | E24: 48122.4
B25: ARS YUNEN | C25: 45869 | E25: 86993.18
... B38: ARS RESERVAS | C38: 45868 | E38: 18399.99
A39: Sub-Total | E39: =SUM(E13:E38) -> 10942139
A40: OTROS APORTES | B40: Cafetería
B41: Odontologia (facturacion servicios no contemplado en Plan Basico) | C41: DEL 01/07/2025 AL 31/07/2025 | E41: =272050+2650 -> 274700
B42: Alquiler de espacios internos a terceros
B43: Aportes provenientes de convenios Institucionales
B44: INGRESOS POR SERVICIOS PACIENTES PRIVADOS Y DIFERENCIAS POR SEGUROS MEDICOS
B45: Atenciones a Pacientes Extranjeros | C45: DEL 01/07/2025 AL 31/07/2025 | E45: 559700
B46: Otros (Identificar Fuente ) Recibidos directamente a la cuenta corriente010-390450-6 (sisaril)
A47: Sub-Total | E47: =SUM(E40:E46) -> 834400
A48: Total General | E48: =E39+E47+E12 -> 1.1209333e+08
A51: Bajo las funciones que nos asisten certificamos que el valor de los ingresos percibidos durante el mes de marzo de 2025, correspondieron a un monto de RD$104,560,836.52
A54: Dado a los 31/07/2025
A56: Cuenta Núm. | B56: Balance en libro | C56: Balance en Banco | D56: Balance Conciliado
A57: 010-390450-6
A63: Preparado por: | D63: Revisado por:
B64: ____________________________________ | D64: ___________________________________
A65: Aprobado por:
B66: ________________________________

Sheet DEUDA
A1: Servicio Nacional de Salud
A2: DIRECCION DE FISCALIZACION
A3: RELACION DEUDA
A4: ESTABLECIMIENTO: | B4: HOSPITAL MATERNO INFANTIL SAN LORENZO DE LOS MINA | D4: CUENTAS POR PAGAR A: | E4: 45839
A6: NO | B6: NOMBRES PROVEEDOR | C6: CONCEPTO | D6: FUENTE FINANCIMIENTO | E6: Años anteriores 2020 | F6: AL 31 DICIEMBRE 2021 | G6: AL 31 DICIEMBRE 2022 | H6: AL 31 DICIEMBRE 2023 | I6: Al 31 DICIEMBRE 2024 | J6: AL 31 DE ENERO 2025 | K6: AL 28 DE FEBRERO 2025 | L6: 31 DE MARZO 2025 | M6: 30 DE ABRIL 2025 | N6: 31 DE MAYO 2025 | O6: 30 DE JUNIO 2025 | P6: 31 DE JULIO 2025 | Q6: TOTAL ADEUDA
A7: 1 | B7: Hospifar, Srl | D7: VS/FG | H7: 11375 | Q7: =SUM(F7:P7) -> 11375
A8: =+A7+1 -> 2 | B8: Hospifar, Srl | D8: VS/FG | H8: 94965 | Q8: =SUM(F8:P8) -> 94965
A9: =+A8+1 -> 3 | B9: Ventas Diversas Farmaceuticas, Srl (Vendifar) | D9: VS/FG | H9: 224775 | Q9: =SUM(F9:P9) -> 224775
A10: =+A9+1 -> 4 | B10: Ga Interprise Import, Srl | D10: VS/FG | H10: 287920 | Q10: =SUM(F10:P10) -> 287920
A11: =+A10+1 -> 5 | B11: D, Cora Industrial, S.R.L | D11: VS/FG | H11: 220483.05 | Q11: =SUM(F11:P11) -> 220483.05
A12: =+A11+1 -> 6 | B12: Bio Nuclear, Sa | D12: VS/FG | H12: 4182 | Q12: =SUM(F12:P12) -> 4182
A13: =+A12+1 -> 7 | B13: Vara, Srl. | D13: VS/FG | H13: 58382.86 | Q13: =SUM(F13:P13) -> 58382.86
A14: =+A13+1 -> 8 | B14: Morami, Srl | D14: VS/FG | H14: 213260 | Q14: =SUM(F14:P14) -> 213260
A15: =+A14+1 -> 9 | B15: Caribbean Integrated Solutions, Srl | D15: VS/FG | H15: 400 | Q15: =SUM(F15:P15) -> 400
A16: =+A15+1 -> 10 | B16: Le.F.P Consultores Srl | D16: VS/FG | I16: 48852 | Q16: =SUM(F16:P16) -> 48852
A17: =+A16+1 -> 11 | B17: Le.F.P Consultores Srl | D17: VS/FG | I17: 48852 | Q17: =SUM(F17:P17) -> 48852
A18: =+A17+1 -> 12 | B18: Insocorp, S.R.L. | D18: VS/FG | I18: 162462.4 | Q18: =SUM(F18:P18) -> 162462.4
A19: =+A18+1 -> 13 | B19: Le.F.P Consultores Srl | D19: VS/FG | I19: 48852 | Q19: =SUM(F19:P19) -> 48852
A20: =+A19+1 -> 14 | B20: Le.F.P Consultores Srl | D20: VS/FG | I20: 48852 | Q20: =SUM(F20:P20) -> 48852
A21: =+A20+1 -> 15 | B21: Unique Representaciones, S.R.L | D21: VS/FG | I21: 112271.1 | Q21: =SUM(F21:P21) -> 112271.1
A22: =+A21+1 -> 16 | B22: Delia Josefina Tatis Perdomo | D22: VS/FG | I22: 56168 | Q22: =SUM(F22:P22) -> 56168
A23: =+A22+1 -> 17 | B23: J. Jireh Equipos Medicos Srl | D23: VS/FG | I23: 16520 | Q23: =SUM(F23:P23) -> 16520
A24: =+A23+1 -> 18 | B24: Insocorp, S.R.L. | D24: VS/FG | K24: 137691.84 | Q24: =SUM(F24:P24) -> 137691.84
A25: =+A24+1 -> 19 | B25: Agua Planeta Azul, Sa | D25: VS/FG | L25: 9500 | Q25: =SUM(F25:P25) -> 9500
A26: =+A25+1 -> 20 | B26: Farmacia Ruth | D26: VS/FG | M26: 13900 | Q26: =SUM(F26:P26) -> 13900
A27: =+A26+1 -> 21 | B27: Farmacia Ruth | D27: VS/FG | N27: 18500 | Q27: =SUM(F27:P27) -> 18500
A28: =+A27+1 -> 22 | B28: Farmacia Ruth | D28: VS/FG | O28: 23625 | Q28: =SUM(F28:P28) -> 23625
A29: =+A28+1 -> 23 | B29: Bio Win, Srl | D29: VS/FG | O29: 1200 | Q29: =SUM(F29:P29) -> 1200
A30: =+A29+1 -> 24 | B30: Agua Planeta Azul, Sa | D30: VS/FG | O30: 2700 | Q30: =SUM(F30:P30) -> 2700
A31: =+A30+1 -> 25 | B31: Agua Planeta Azul, Sa | D31: VS/FG | O31: 3900 | Q31: =SUM(F31:P31) -> 3900
A32: =+A31+1 -> 26 | B32: Agua Planeta Azul, Sa | D32: VS/FG | O32: 9060 | Q32: =SUM(F32:P32) -> 9060
A33: =+A32+1 -> 27 | B33: Agua Planeta Azul, Sa | D33: VS/FG | O33: 9120 | Q33: =SUM(F33:P33) -> 9120
A34: =+A33+1 -> 28 | B34: Agua Planeta Azul, Sa | D34: VS/FG | O34: 15750 | Q34: =SUM(F34:P34) -> 15750
A35: =+A34+1 -> 29 | B35: Bio Win, Srl | D35: VS/FG | O35: 1200 | Q35: =SUM(F35:P35) -> 1200
A36: =+A35+1 -> 30 | B36: Magnetique Srl | D36: VS/FG | O36: 469640 | Q36: =SUM(F36:P36) -> 469640
A37: =+A36+1 -> 31 | B37: Aneka Ingenieria & Servicios Srl | D37: VS/FG | O37: 40000 | Q37: =SUM(F37:P37) -> 40000
A38: =+A37+1 -> 32 | B38: Suplimed,Srl | D38: VS/FG | O38: 165375 | Q38: =SUM(F38:P38) -> 165375
A39: =+A38+1 -> 33 | B39: Bio Win, Srl | D39: VS/FG | O39: 1200 | Q39: =SUM(F39:P39) -> 1200
A40: =+A39+1 -> 34 | B40: Bio Win, Srl | D40: VS/FG | O40: 1200 | Q40: =SUM(F40:P40) -> 1200
A41: =+A40+1 -> 35 | B41: Bio Win, Srl | D41: VS/FG | P41: 1200 | Q41: =SUM(F41:P41) -> 1200
A42: =+A41+1 -> 36 | B42: Farmacia Ruth | D42: VS/FG | P42: 16100 | Q42: =SUM(F42:P42) -> 16100
A43: =+A42+1 -> 37 | B43: Ocap Srl | D43: VS/FG | P43: 141600 | Q43: =SUM(F43:P43) -> 141600
A44: =+A43+1 -> 38 | B44: I.V. Biodesinfección, Srl | D44: VS/FG | P44: 197673.6 | Q44: =SUM(F44:P44) -> 197673.6
A45: =+A44+1 -> 39 | B45: Bio Win, Srl | D45: VS/FG | P45: 1200 | Q45: =SUM(F45:P45) -> 1200
A46: =+A45+1 -> 40 | B46: Papelería E. Impresos Crishoan, Srl | D46: VS/FG | P46: 171247.5 | Q46: =SUM(F46:P46) -> 171247.5
A47: 1 | B47: Adler Amicis Valdez Marmolejos | D47: VS/FG | P47: 336559.6 | Q47: =SUM(F47:P47) -> 336559.6
A48: =+A47+1 -> 2 | B48: Insocorp, S.R.L. | D48: VS/FG | P48: 199998.2 | Q48: =SUM(F48:P48) -> 199998.2
A49: =+A48+1 -> 3 | B49: R Y S Soluciones E Inversiones Integrales Srl | D49: VS/FG | P49: 254828.6 | Q49: =SUM(F49:P49) -> 254828.6
A50: =+A49+1 -> 4 | B50: Transportes Jesus Fermin Martinez . | C50: SERVICIOS DE TRANSPORTE | D50: VS/FG | P50: 24000 | Q50: =SUM(F50:P50) -> 24000
A51: =+A50+1 -> 5 | B51: Grupo Xeron Medic Srl | D51: VS/FG | P51: 272019.5 | Q51: =SUM(F51:P51) -> 272019.5
A52: TOTAL GENERAL | E52: =SUM(E7:E51) -> 0 | F52: =SUM(F7:F51) -> 0 | G52: =SUM(G7:G51) -> 0 | H52: =SUM(H7:H51) -> 1115742.9 | I52: =SUM(I7:I51) -> 542829.5 | J52: =SUM(J7:J51) -> 0 | K52: =SUM(K7:K51) -> 137691.84 | L52: =SUM(L7:L51) -> 9500 | ... Q52: =SUM(Q7:Q51) -> 4198561.2

Sheet Hoja1
D1: 11550 | E1: INGRESOS POR EXTRANJEROS
A2: 155606.87 | B2: ARS YUNEN | D2: 3000 | E2: INGRESOS POR EXTRANJEROS | G2: 150000 | H2: CAFETERIA
A3: 3199661.2 | B3: ARS SENASA SUBSIDIADO | D3: 4000 | E3: INGRESOS POR EXTRANJEROS | G3: 15000 | H3: FEBRERO, MARZO Y ABRIL 2025, UCE
A4: 50000 | B4: ARS SENASA SUBSIDIADO | D4: 4000 | E4: INGRESOS POR EXTRANJEROS | G4: =SUM(G2:G3) -> 165000
A5: 12182.4 | B5: ASEMAP | D5: 4000 | E5: INGRESOS POR EXTRANJEROS
A6: 84594.85 | B6: ARS MONUMENTAL | D6: 8000 | E6: INGRESOS POR EXTRANJEROS
A7: 13000 | B7: SENASA PENSIONADO | D7: 3200 | E7: INGRESOS POR EXTRANJEROS
A8: 79987.57 | B8: ARS RESERVAS | D8: 4000 | E8: INGRESOS POR EXTRANJEROS
A9: 2588374.1 | B9: ARS SENASA CONTRIBUTIVO | D9: 4000 | E9: INGRESOS POR EXTRANJEROS
A10: 61607.99 | B10: CMD | D10: 3500 | E10: INGRESOS POR EXTRANJEROS
A11: 54068.8 | B11: ARS MAPHRE | D11: 2100 | E11: INGRESOS POR EXTRANJEROS
A12: 12721.54 | B12: ARS MAPHRE | D12: 3500 | E12: INGRESOS POR EXTRANJEROS
A13: 375966.29 | B13: ARS MAPHRE | D13: 4000 | E13: INGRESOS POR EXTRANJEROS
A14: 304098.74 | B14: ARS PRIMERA | D14: 4000 | E14: INGRESOS POR EXTRANJEROS
A15: 32863.84 | B15: ARS META SALUD | D15: 7100 | E15: INGRESOS POR EXTRANJEROS
A16: 493974.92 | B16: ARS FUTURO | D16: 23600 | E16: INGRESOS POR EXTRANJEROS
A17: =SUM(A2:A16) -> 7518709.1 | D17: 31300 | E17: INGRESOS POR EXTRANJEROS
D18: 22000
D19: 13900
D20: =SUM(D1:D19) -> 160750
D22: 1000 | E22: ODONTOLOGIA
D23: 1500
D24: 1800 | E24: ODONTOLOGIA
D25: 2000
D26: 2000
D27: 2000
D28: 2000
D29: 2000
D30: 2000
D31: 2000
D32: 2000
D33: 2000
D34: 2000
D35: 2000
D36: 2000
D37: 2500
D38: 2500 | E38: ODONTOLOGIA
D39: 2800 | E39: ODONTOLOGIA
D40: 2900 | E40: ODONTOLOGIA
D41: 3000
D42: 3000
D43: 3000
D44: 3000
D45: 3000
D46: 3000
D47: 3000
D48: 3100 | E48: ODONTOLOGIA
D49: 3500
D50: 3500
D51: 3700 | E51: ODONTOLOGIA
D52: 3700 | E52: ODONTOLOGIA
D53: 4100 | E53: ODONTOLOGIA
D54: 4400 | E54: ODONTOLOGIA
D55: 4600 | E55: ODONTOLOGIA
D56: 4600 | E56: ODONTOLOGIA
D57: 4700 | E57: ODONTOLOGIA
D58: 4900 | E58: ODONTOLOGIA
D59: 5000
D60: 5400 | E60: ODONTOLOGIA
D61: 5400 | E61: ODONTOLOGIA
D62: 5500 | E62: ODONTOLOGIA
D63: 5600 | E63: ODONTOLOGIA
D64: 5750 | E64: ODONTOLOGIA
D65: 5800 | E65: ODONTOLOGIA
D66: 5800
D67: 6000 | E67: ODONTOLOGIA
D68: 6200 | E68: ODONTOLOGIA
D69: 7000
D70: 7100 | E70: ODONTOLOGIA
D71: 7500 | E71: ODONTOLOGIA
D72: 8800 | E72: ODONTOLOGIA
D73: 9100 | E73: ODONTOLOGIA
D74: 10100 | E74: ODONTOLOGIA
D75: 11600 | E75: ODONTOLOGIA
D76: 11900 | E76: ODONTOLOGIA
D77: 14200 | E77: ODONTOLOGIA
D80: =SUM(D22:D79) -> 248550
D81: =+D80+D20 -> 409300
D82: =+D80+D20+A17+G4 -> 8093009.1
D83: 8093009.1
D84: =+D82-D83 -> 0

Sheet INGRESOS POR A.R.S
A2: Servicio Nacional De Salud
A3: Dirección de Fiscalizacion
A4: Ingresos Por Facturación ARS
A6: Establecimiento: | C6: HOSPITAL MATERNO INFANTIL SAN LORENZO DE LOS MINA
A8: ARS | C8: ENERO | E8: FEBRERO | G8: MARZO | I8: ABRIL | K8: MAYO | M8: JUNIO | O8: JULIO | Q8: AGOSTO | S8: SEPTIEMBRE | U8: OCTUBRE | W8: NOVIEMBRE | Y8: DICIEMBRE
C9: Facturado | D9: Recibido | E9: Facturado | F9: Recibido | G9: Facturado | H9: Recibido | I9: Facturado | J9: Recibido | K9: Facturado | L9: Recibido | M9: Facturado | N9: Recibido | O9: Facturado | P9: Recibido | Q9: Facturado | R9: Recibido | S9: Facturado | T9: Recibido | U9: Facturado | V9: Recibido | W9: Facturado | X9: Recibido | Y9: Facturado | Z9: Recibido
A10: 1 | B10: SENASA SUBSIDIADO | C10: 4027257.3 | D10: 4833111.5 | E10: 4840265.3 | F10: 5841673.2 | G10: =13000+3146909.72 -> 3159909.7 | H10: =4595181.39+50000 -> 4645181.4 | I10: =6959.16+1939523.55 -> 1946482.7 | J10: =100000+2942930.33+10949.64 -> 3053880 | K10: 3199661.2 | L10: =3199661.24+50000 -> 3249661.2 | M10: 5356651.5 | O10: 4812753.5 | P10: =50000+5296295.14 -> 5346295.1
A11: 2 | B11: SENASA CONTRIBUTIVO | C11: 1094583.8 | E11: 2417181.1 | F11: 2152926.5 | G11: 2645113.9 | H11: 1041144.3 | I11: 3267715.2 | J11: 2326715 | K11: 2490193.7 | L11: 2588374.1 | M11: 1240459.9 | N11: 2927464.4 | O11: 2661675 | P11: 2432528
A12: =+A11+1 -> 3 | B12: SENASA JUB. Y PENS. | C12: 0 | D12: 0 | E12: 10985.64 | G12: 0 | K12: 2134.86 | L12: 13000 | M12: 30812.76 | O12: 21145.63
A13: =+A12+1 -> 4 | B13: SENASA LARIMAR | M13: 2580
A14: Total SeNaSa | C14: =SUM(C10:C12) -> 5121841.1 | D14: =SUM(D10:D12) -> 4833111.5 | E14: =SUM(E10:E12) -> 7268432.1 | F14: =SUM(F10:F12) -> 7994599.7 | G14: =SUM(G10:G12) -> 5805023.6 | H14: =SUM(H10:H12) -> 5686325.7 | I14: =SUM(I10:I12) -> 5214198 | J14: =SUM(J10:J12) -> 5380594.9 | ... L14: =SUM(L10:L12) -> 5851035.3 | M14: =SUM(M10:M13) -> 6630504.1 | N14: =SUM(N10:N12) -> 2927464.4 | O14: =SUM(O10:O12) -> 7495574.1 | P14: =SUM(P10:P12) -> 7778823.1 | Q14: =SUM(Q10:Q12) -> 0 | R14: =SUM(R10:R12) -> 0 | S14: =SUM(S10:S12) -> 0 | T14: =SUM(T10:T12) -> 0 | U14: =SUM(U10:U12) -> 0 | ... Z14: =SUM(Z10:Z12) -> 0
A15: 5 | B15: PALIC SALUD | C15: 211714.57 | D15: 206908.45 | E15: =65463.45+12918.96+311477.59 -> 389860 | G15: =53140.7+6743.06+130031.72 -> 189915.48 | H15: =16298.76+15397.47+30434.4+65463.45+12863.4+155572.92+309977.48+504 -> 606511.88 | I15: =54068.8+12721.58+382067.66 -> 448858.04 | J15: =51140.7+129754.16+6696.74 -> 187591.6 | K15: =47703.2+8425.36+117128.56 -> 173257.12 | L15: =54068.8+12721.54+375966.29 -> 442756.63 | M15: =48122.4+9299.44+217424.9 -> 274846.74 | O15: =58784.4+11340.11+195826.12 -> 265950.63 | P15: =7867.11+9031.14+24398.12+47703.2+48122.4+117128.56+187255.14 -> 441505.67
A16: =+A15+1 -> 6 | B16: ARL
A17: =+A16+1 -> 7 | B17: RENACER | C17: 275352.44 | D17: 156983.55 | E17: 222716.34 | F17: 272552.44 | G17: 73918.68 | H17: 222620.34 | J17: 73057.08 | M17: 443337.56 | P17: 417359.58
A18: =+A17+1 -> 8 | B18: YUNEN | C18: 7848.94 | D18: 55135.74 | E18: 14338.35 | F18: 7848.94 | G18: 162551.53 | H18: 14338.35 | I18: 37897.65 | J18: 19489.76 | K18: 45390.42 | L18: 155606.87 | M18: 166835.63 | N18: =35073.61+44140.42 -> 79214.03 | O18: 19360.44 | P18: 86993.18
A19: =+A18+1 -> 9 | B19: UNIVERSAL
A20: =+A19+1 -> 10 | B20: ARS HUMANO | C20: 44770.98 | E20: 16720.82 | F20: 97648.3 | G20: 83376.61 | H20: 34117.68 | I20: 77617.28 | J20: 97704.2 | K20: 29761.8 | M20: 50732.77 | N20: 102719.16 | O20: 38168.82 | P20: 48385.69
A21: =+A20+1 -> 11 | B21: ARS PLANSALUD BANCO CENTRAL
A22: =+A21+1 -> 12 | B22: SEMMA | C22: 7193.05 | D22: 15993.02 | E22: 28868.13 | F22: 9531.6 | G22: 10657.5 | H22: 77169.4 | I22: 27941.11 | J22: =28868.13+6393.05 -> 35261.18 | K22: 99169.27 | M22: 36644.9 | N22: 8860.1 | O22: 19740.54
A23: =+A22+1 -> 13 | B23: FUTURO | C23: 269639.73 | D23: 234503.89 | E23: 617068.65 | G23: 366095.18 | H23: 356314.76 | I23: 395799.78 | J23: 388735.9 | K23: 525599.56 | L23: 493974.92 | M23: 236054.2 | N23: 213364.69 | O23: 651828.66 | P23: 649331.98
A24: =+A23+1 -> 14 | B24: APS | C24: 69588.33 | E24: 122630.62 | F24: 8262.07 | G24: 43770.8 | H24: 212345.21 | I24: 55860.67 | K24: 109234.31 | M24: 229878 | O24: 216887.67
A25: =+A24+1 -> 15 | B25: SALUD SEGURA
A26: =+A25+1 -> 16 | B26: CONSTITUCION
A27: =+A26+1 -> 17 | B27: META SALUD | C27: 1396 | E27: 20821.36 | F27: 31949.94 | G27: 80842.17 | H27: 1396 | I27: 32922.74 | K27: 3500 | L27: 32863.84 | M27: 41032.92 | O27: 11961.97
A28: =+A27+1 -> 18 | B28: ASEMAP | C28: 4869.52 | D28: 6475.14 | E28: 102975.46 | F28: 4869.52 | G28: 6619.63 | H28: 102672.34 | I28: 12257.4 | J28: 6619.63 | K28: 111906.17 | L28: 12182.4 | M28: 7768.47 | O28: 11676.13 | P28: =111902.77+6784.54 -> 118687.31
A29: =+A28+1 -> 19 | B29: GMA | C29: 76159.34 | E29: 186957.88 | G29: 136798.59 | I29: 83229.31 | K29: 9976.34 | M29: 108970.25 | O29: 49885.59 | P29: =395386.07+48652.64 -> 444038.71
A30: =+A29+1 -> 20 | B30: MONUMENTAL | C30: 75131.09 | D30: 71992.2 | E30: 146560.32 | G30: 85258.31 | H30: 237322.18 | I30: 119188.62 | J30: 146560.32 | K30: 58287.88 | L30: 84594.85 | M30: 97214.78 | O30: 108900.79 | P30: 125937.38
A31: =+A30+1 -> 21 | B31: CMD | C31: 273646.7 | D31: 273646.7 | E31: 41285.9 | F31: 41071.9 | G31: 22435.77 | H31: 11220.43 | I31: 61608.05 | J31: 22435.77 | K31: 31245 | L31: 61607.99 | M31: 237194.17 | N31: 31240 | O31: 63128.33 | P31: =63128.33+237194.17 -> 300322.5
A32: =+A31+1 -> 22 | B32: RESERVAS | C32: 48081.02 | D32: 48081.02 | E32: 217047.26 | G32: 79962.77 | I32: 61346.15 | K32: 57351.74 | L32: 79987.57 | M32: 10000 | O32: 18399.99 | P32: =18134.86+18399.99 -> 36534.85
A33: =+A32+1 -> 23 | B33: SIMAG | C33: 28637.51 | E33: 92478.63 | G33: 2821.24 | I33: 1604 | K33: 3360 | M33: 3319.22 | O33: 4368.41 | P33: =4943.4+176215.29 -> 181158.69
A34: =+A33+1 -> 24 | B34: SEMUNASED
A35: =+A34+1 -> 25 | B35: SERVICIOS MEDICOS UASD
A36: =+A35+1 -> 26 | B36: PRIMERA ARS HUMANO | C36: 259154.57 | E36: 439967.13 | F36: 870590.25 | G36: 404678.83 | H36: 262926.38 | I36: 432554.37 | J36: 534014.43 | K36: 317521.34 | L36: 304098.74 | M36: 374483.12 | N36: 268649.03 | O36: 442825.83 | P36: 313059.93
B37: EXTRANJEROS | K37: 80323.32 | M37: 436800 | N37: 423700
A38: Total ARS PRIVADAS | C38: =SUM(C15:C36) -> 1653183.8 | D38: =SUM(D15:D36) -> 1069719.7 | E38: =SUM(E15:E36) -> 2660296.9 | F38: =SUM(F15:F36) -> 1344325 | G38: =SUM(G15:G36) -> 1749703.1 | H38: =SUM(H15:H36) -> 2138955 | I38: =SUM(I15:I36) -> 1848685.2 | J38: =SUM(J15:J36) -> 1511469.9 | K38: =SUM(K15:K37) -> 1655884.3 | L38: =SUM(L15:L36) -> 1667673.8 | M38: =SUM(M15:M37) -> 2755112.7 | N38: =SUM(N15:N37) -> 1127747 | O38: =SUM(O15:O36) -> 1923083.8 | P38: =SUM(P15:P36) -> 3163315.5 | Q38: =SUM(Q15:Q36) -> 0 | R38: =SUM(R15:R36) -> 0 | S38: =SUM(S15:S36) -> 0 | T38: =SUM(T15:T36) -> 0 | U38: =SUM(U15:U36) -> 0 | V38: =SUM(V15:V36) -> 0 | ... Z38: =SUM(Z15:Z36) -> 0
A39: TOTAL | C39: =C14+C38 -> 6775024.9 | D39: =D14+D38 -> 5902831.2 | E39: =E14+E38 -> 9928728.9 | F39: =F14+F38 -> 9338924.6 | G39: =G14+G38 -> 7554726.7 | H39: =H14+H38 -> 7825280.6 | I39: =I14+I38 -> 7062883.1 | J39: =J14+J38 -> 6892064.8 | ... Z39: =Z14+Z38 -> 0
A41: Preparado por:
A42: Licda.

Sheet GLOSA
A1: Servicio Nacional de Salud
A2: Dirección de Fiscalización
A3: Glosa /mes
A4: Establecimientos | B4: Facturado | C4: Recibido | D4: Glosado | E4: %
A5: Enero | B5: 6775024.9 | C5: 5902831.2 | D5: 102835 | E5: =+D5/C5 -> 0.017421301
A6: Febrero | B6: 9928728.9 | C6: 9338924.6 | D6: =147829.22+68679.07+4547.79 -> 221056.08 | E6: =+D6/C6 -> 0.0236704
A7: Marzo | B7: 7643032.2 | C7: 7825280.7 | D7: 99442.51 | E7: =+D7/C7 -> 0.012707852
A8: Abril | B8: 6994829.1 | C8: 6892064.8 | D8: 68054 | E8: =+D8/C8 -> 0.0098742542
A9: Mayo | B9: 7347874.1 | C9: 7518709.1 | D9: =47721.02+68532.2 -> 116253.22 | E9: =+D9/C9 -> 0.015461859
A10: Junio | B10: 9385616.4 | C10: 4055211.4 | D10: 67756.32 | E10: =+D10/C10 -> 0.016708456
A11: Julio | B11: 9418657.9 | C11: 10942139 | D11: 116253.22 | E11: =+D11/C11 -> 0.01062436
A12: Agosto
A13: Septiembre
A14: Octubre
A15: Noviembre
A16: Diciembre
A17: Total | B17: =SUM(B5:B13) -> 57493764 | C17: =SUM(C5:C13) -> 52475160 | D17: =SUM(D5:D13) -> 791650.35 | E17: =+D17/C17 -> 0.015086192
A19: Preparado por:
A20: Licda.
