Workbook

Sheet RELACION DE PAGOS EMITIDOS
A5: DIRECCION DE FISCALIZACION Y CONTROL
A6: RELACION DE PAGOS EMITIDOS DURANTE EL MES
A7: ESTABLECIMIENTO:HOSPITAL MATERNO INFANTIL SAN LORENZO DE LOS MINA
A9: PAGOS CORRESPONDIENTES AL MES : MARZO 2025
A10: FECHA | B10: LIBRAMIENTO | C10: TRANSFERENCIA | D10: CHEQUE | E10: BENEFICIARIO | F10: NO.FACTURAS | G10: VALOR DE FACTURA | H10: VALOR PAGADO
A11: 45719 | C11: 58 | E11: P&D RECYCLING, SRL | F11: FACT B1500000304 | G11: 760000 | H11: 722000
A12: 45719 | C12: 59 | E12: REFRICLIMA HF, SRL | F12: FACT B1500000868 | G12: 192930 | H12: 184755
A13: 45721 | C13: 60 | E13: LEFP CONSULTORES, SRL | F13: FACT B1500000342 | G13: 48852 | H13: 46782
A14: 45721 | C14: 61 | E14: IV BIODESINFECCION, SRL | F14: FACT B1500000279 | G14: 188564 | H14: 180574
A15: 45721 | C15: 62 | E15: ORTRO CHEMICAL, SRL | F15: FACT B1500000367 | G15: 42000 | H15: 39900
A16: 45721 | C16: 63 | E16: INVERSIONES FH, SRL | F16: FACT B1500001471 | G16: 172000 | H16: 170573.26
A17: 45721 | C17: 64 | E17: TROPIGAS DOMINICANA, SRL | F17: E450000005356, E450000005368, E450000006369 | G17: 55029 | H17: 55029
A18: 45722 | C18: 65 | E18: LORA & ALMONTE REPARACIONES, SRL | F18: FACT B1500000194 | G18: 41305.02 | H18: 39555.02
A19: 45722 | C19: 66 | E19: HOSPAL MEDICAL, SRL | F19: FACT B1500017801 | G19: 34220 | H19: 32770
A20: 45722 | C20: 67 | E20: DIUCAM GROUP, SRL | F20: FACT B1500000007 | G20: 473584 | H20: 451814
A21: 45722 | C21: 68 | E21: DOCTORES MALLEN GUERRA | F21: COT. DM-COT009852-1 | G21: 61500 | H21: 58425
A22: 45723 | C22: 69 | E22: GTA ELEVATORS, SRL | F22: FACT B1500000019 | G22: 636067.2 | H22: 609115.2
... A31: 45730 | C31: 78 | E31: SOLUCIONES DE SERVICIOS Y TECNICAS ALTADIS, SRL | F31: PAGO DE FACT NCF NO. B1500000100 | G31: 107609.37 | H31: 103049.65
A32: 45730 | C32: 79 | E32: LILIAN YOMAIRA ENCARNACION | G32: 20000 | H32: 20000
A33: 45735 | C33: 80 | E33: ADLER AMICIS VALDEZ MARMOLEJOS | F33: FACT B1500000255 | G33: 26845 | H33: 25707.5
A34: 45735 | C34: 81 | E34: JESUS FERMIN MARTINEZ LOPEZ | F34: FACT B1500000423 | G34: 8000 | H34: 7600
A35: 45735 | C35: 82 | E35: SUPLIMED | F35: FACT B1500005690, B1500005703, B1500005706 | G35: 225000 | H35: 213750
A36: 45740 | C36: 83 | E36: CENTRO DE ESTUDIOS MEDICOS Y DIAGNOSTICOS POR IMÁGENES, SRL | F36: FACTS NCF B1500000364 Y B1500000370 | G36: 83800 | H36: 79610
A37: 45740 | C37: =+C36+1 -> 84 | E37: ADLER AMICIS VALDEZ MARMOLEJOS | F37: FACT NCF B1500000257 | G37: 31152 | H37: 29832
A38: 45740 | C38: =+C37+1 -> 85 | E38: TROPIGAS DOMINICANA, SRL | F38: FACT NCF E450000005393 | G38: 22542 | H38: 22542
A39: 45742 | C39: =+C38+1 -> 86 | E39: JESUS FERMIN MARTINEZ LOPEZ | F39: FACT B1500000426 | G39: 24000 | H39: 22800
A40: 45743 | C40: =+C39+1 -> 87 | E40: LORA & ALMONTE REPARACIONES, SRL | F40: FACT B1500000196 | G40: 105649.96 | H40: 101173.27
A41: 45743 | C41: =+C40+1 -> 88 | E41: COLEGIO DOMINICANO DE PROFESIONALES DE ENFERMERIA | F41: COLABORACION DE UN 50% PARA EL XVIII CONGRESO NACIONAL DE ENFERMERIA | G41: 40000 | H41: 40000
A42: 45743 | C42: =+C41+1 -> 89 | E42: PLANETA AZUL. SA | F42: FACT NCF E450000009903, E450000001760 | G42: 14000 | H42: 14000
A43: 45743 | C43: =+C42+1 -> 90 | E43: PLANETA AZUL. SA | F43: FACT NCF E450000009389, E450000009385 | G43: 11640 | H43: 11640
A44: 45743 | C44: =+C43+1 -> 91 | E44: PLANETA AZUL. SA | F44: FACT NCF E450000009396, E450000009390, E450000006400 | G44: 23580 | H44: 23580
A45: 45744 | C45: =+C44+1 -> 92 | E45: ELIGIUM, SRL | F45: PAGO DE FACT NCF NO. B1500000021 | G45: 272580 | H45: 261030
A46: 45744 | C46: =+C45+1 -> 93 | E46: MANTENERGIA ELECTRICA Y ABASTECIMIENTOS, SRL | F46: PAGO DE FACT B1500000162 | G46: 248711.41 | H46: 238172.79
A47: 45744 | C47: =+C46+1 -> 94 | E47: INGENIERIA Y CONSTRUCCIONES FASUMER, SRL | F47: PAGO DE FACT NCF NO B1500000151 | G47: 271800.26 | H47: 260283.3
A48: 45744 | C48: =+C47+1 -> 95 | E48: MANTENERGIA ELECTRICA Y ABASTECIMIENTOS, SRL | F48: PAGO FACT NCF NO. B1500000163 | G48: 230085.84 | H48: 220336.44
... A50: 45747 | C50: =+C49+1 -> 97 | E50: P&D RECYCLING, SRL | F50: PAGO DE FACT NCF NO. B1500000306 | G50: 760000 | H50: 722000
A51: 45747 | C51: 98 | E51: NOMINA POR PAGAR INCENTIVO | F51: NOMINA INCENTIVO | G51: 5231553.6 | H51: 5231553.6
A52: 45719 | D52: 37197 | E52: NULO | F52: NULO | G52: 0 | H52: 0
A53: 45719 | D53: 37198 | E53: BILLY DRAY GONZALEZ GONZALEZ | F53: COLABORACION PARA ESTUDIO ANGIOTOMOGRAFIA CEREBRAL, PARA EL PACIENTE JESUS GOZALEZ | G53: 26000 | H53: 26000
A54: 45719 | D54: 37199 | E54: HECTOR BIENVENIDO DIAZ BURGOS | F54: PAGO POR LA PLATAFORMA DATA INSTALADA EN LA INSTITUCION | G54: 14000 | H54: 14000
A55: 45727 | D55: 37200 | E55: OLEGARIO GUERRERO | F55: PAGO DE SERVICIO DE PINTADO EXTERIOR PARA CORREGIR Y REPARAR TUBERIA DE AGUA, COLOCACION DE CERAMICA EN AREA DE EMERGENCIA DEL HOSPITAL, SEGÚN ORDEN DE COMPRA 1933 | G55: 30102.04 | H55: 25000
A56: 45728 | D56: 37201 | E56: MARIE LAURE MONTREVIL | F56: COLABORACION PARA REALIZAR ESTUDIO DE ELECTROENCEFALOGRAMA A LA PACIENTE INTERNA NAIKA BELLEIRE | G56: 10000 | H56: 10000
A57: 45733 | D57: 37202 | E57: NULO | F57: NULO | G57: 0 | H57: 0
A58: 45734 | D58: 37203 | E58: ROXANNA JOSELYN CHEVALIER DE MEDINA | F58: COLABORACION PARA LA JORNDA DE RESIDENTES DE ANESTESIOLOGIA 2025 | G58: 34020 | H58: 34020
A59: 45735 | D59: 37204 | E59: DELMIRA GARCIA | F59: REPOSICION DEL FONDO DE CAJA CHICA RECIBOS 40266 AL 40302 | G59: 51304.69 | H59: 51304.69
A60: 45740 | D60: 37205 | E60: RUDDY SEGURA | F60: PAGO DE FACT NCF NO B1100000032 | G60: 21673.47 | H60: 18000
A61: 45740 | D61: 37206 | E61: NELSON YNFANTE VELAZQUEZ | F61: PAGO DE FACT NCF NO. B1100000031 | G61: 18061.22 | H61: 15000
A62: 45741 | D62: 37207 | E62: ALEXANDER MENDEZ CONTRERAS | F62: PAGO DE FACT NCF NO B1100000033 | G62: 18061.22 | H62: 15000
A63: 45742 | D63: 37208 | E63: FREDDY OSCAR RODRIGUEZ RIVAS | F63: COLABORACION PARA CAVAR HOYO | G63: 3400 | H63: 3400
A64: 45747 | E64: COMISIONES BANCARIAS | F64: COMISIONES BANCARIAS MES DE MARZO 2025 | G64: 8323.87 | H64: 8323.87
A65: 03/03/2025 | B65: 547 | E65: wilson Frias | F65: PAGO DE FACT NCF B1500000262 POR ADQUISICION DE MATERIALES FERRETEROS SEGUN O/C HSLM-2024-01182. | G65: 136100.09 | H65: 130333.14
A66: 03/03/2025 | B66: 551 | E66: wilson Frias | F66: PAGO DE FACT NCF B1500000262 POR ADQUISICION DE BASE P/ FOTOCELDA SEGUN O/C HSLM-2024-01182. | G66: 3199.97 | H66: 3064.38
A67: 03/03/2025 | B67: 554 | E67: Ameriline Pharmaceutical, SRL | F67: PAGO NCF B1500000444 POR ADQUSICION DE MEDICAMENTOS SEGUN O/C HSLM-2025-00024 | G67: 86700 | H67: 82365
A68: 03/03/2025 | B68: 558 | E68: Insocorp, SRL | F68: PAGO DE FACT NCF B1500000196 Y B1500000206 POR ADQUISICION DE EQUIPOS MEDICOS SEGUN O/C HSLM-2024-01162. | G68: 999401 | H68: 957053.5
A69: 03/03/2025 | B69: 562 | E69: Insocorp, SRL | F69: PAGO DE FACT NCF B1500000206 POR ADQUISICION DE UTILES MEDICOS SEGUN O/C HSLM-2024-01162. | G69: 265051.6 | H69: 253820.6
A70: 03/03/2025 | B70: 566 | E70: Laboratorios Rhyno, SRL | F70: PAGO DE FACT NCF B1500000038 POR ADQUISICION DE SOFTWARE DETECTOR DIGITAL DE RAYOS X SEGUN O/C HSLM-2025-00078. | G70: 1968240 | H70: 1884840
A71: 03/03/2025 | B71: 570 | E71: Livao Farmacéutica, SRL | F71: PAGO DE FACT NCF B1500000319 POR ADQUISICION DE DETECTOR DIGITAL, PORTATIL E INALAMBRICO SEGUN O/C HSLM-2025-00036. | G71: 873200 | H71: 836200
A72: 03/03/2025 | B72: 574 | E72: G & M Gelmat Comercial, SRL | F72: PAGO DE FACT NCF B1500000109 POR ADQUISICION DE MEDICAMENTOS Y UTILES MEDICOS SEGUN O/C HSLM-2025-00107. | G72: 264711.6 | H72: 252030
A73: 03/03/2025 | B73: 578 | E73: Hauspital, SRL | F73: PAGO DE FACT NCF B1500000786 POR ADQUISICION DE MEDICAMENTOS Y UTILES MEDICOS SEGUN O/C HSLM-2025-00097. | G73: 240515 | H73: 230271.25
A74: 03/03/2025 | B74: 582 | E74: CRISTINA ROSARIO ROSARIO | F74: PAGO DE FACT NCF B1500000370 POR ADQUISICION DE MEDICAMENTOS Y UTILES MEDICOS SEGUN O/C HSLM-2025-00034. | G74: 267156.5 | H74: 254722.75
A75: 03/03/2025 | B75: 586 | E75: Ropharma, SRL | F75: PAGO DE FACT NCF B1500001259 POR ADQUISICION DE MEDICAMENTOS SEGUN O/C HSLM-2025-00133. | G75: 151000 | H75: 143450
A76: 04/03/2025 | B76: 591 | E76: Dumas Pharmaceuticals, S.R.L. | F76: PAGO DE FACT NCF B1500000891 POR ADQUISICION DE MEDICAMENTOS Y UTIL MEDICO SEGUN O/C HSLM-2025-00071. | G76: 126100 | H76: 120470
... A124: 12/03/2025 | B124: 820 | E124: PAPELERIA E IMPRESOS CRISHOAN, SRL | F124: PAGO DE FACT NCF B1500001646 POR ADQUISICION DE MATERIAL IMPRESO SEGUN O/C HSLM-2025-00139. | G124: 271754 | H124: 260239
A125: 12/03/2025 | B125: 824 | E125: Diucam Group SRL | F125: PAGO DE FACT NCF B1500000008 POR ADQUISICION DE ALIMENTOS, SERVILLETAS Y PAPEL DE ALUMINIO SEGUN O/C HSLM-2025-00106. | G125: 679000.24
A126: 12/03/2025 | B126: 828 | E126: Livao Farmacéutica, SRL | F126: PAGO DE FACT NCF B1500000334 POR ADQUISICION DE LECHE ENFAMIL NEURO PRO PREMATURE SEGUN O/C HSLM-2025-00086. | G126: 19520
A127: 13/03/2025 | B127: 838 | E127: CORPORACION DEL ACUEDUCTO Y ALCANTARILLADO DE SANTO DOMINGO | F127: PAGO DE FACT NCF E450000003130 POR ADQUISICION DE SERVICIO DE AGUA CORRESPONDIENTE AL MES DE MARZO 2025. | G127: 60535
A128: 13/03/2025 | B128: 842 | E128: Distribuidora Ricca E Sana DI M.C, SRL | F128: PAGO DE FACT NCF B1500000151 POR ADQUISICION DE UTILES MEDICOS SEGUN O/C HSLM-2025-00174. | G128: 214760
A129: 13/03/2025 | B129: 846 | E129: Grupo Xeron Medic SRL | F129: PAGO DE FACT NCF B1500000171 POR ADQUISICION DE MEDICAMENTOS Y UTILES MEDICOS SEGUN O/C HSLM-2025-00122. | G129: 257756
A130: 13/03/2025 | B130: 850 | E130: G & M Gelmat Comercial, SRL | F130: PAGO DE FACT NCF B1500000111 POR ADQUISICION DE UTILES MEDICOS SEGUN O/C HSLM-2025-00151. | G130: 208010.4
A131: 13/03/2025 | B131: 854 | E131: G & M Gelmat Comercial, SRL | F131: PAGO DE FACT NCF B1500000114 POR ADQUISICION DE MEDICAMENTOS Y UTILES MEDICOS SEGUN O/C HSLM-2025-00173. | G131: 30892.95
A132: 13/03/2025 | B132: 858 | E132: First Medical Depot By Guzman, SRL | F132: PAGO DE FACT NCF B1500000493 POR ADQUISICION DE TORRE DE LAPAROSCOPIA SEGUN O/C HSLM-2025-00163. | G132: 1882100
A133: 13/03/2025 | B133: 862 | E133: Laboratorios Rhyno, SRL | F133: PAGO DE FACT NCF B1500000039 POR ADQUISICION DE CAMARA LAPAROSCOPICA, FUEN DE LUZ , MONITORES Y SISTEMA DE INSUFLACION SEGUN O/C HSLM-2025-00169. | G133: 1787700
A134: 13/03/2025 | B134: 867 | E134: PLASTIFAR,SA | F134: PAGO DE FACT NCF E450000000043 POR ADQUISICION DE DESECHABLES SEGUN O/C HSLM-2024-01073. | G134: 334708.95
A135: 13/03/2025 | B135: 871 | E135: HOSPITAL MATERNO INFANTIL SAN LORENZO DE LOS MINAS | F135: HOSANLORE.NOMINA SUELDO PERSONAL DE VIGILANCIA MARZO 2025 | G135: 45000
A136: 13/03/2025 | B136: 872 | E136: BAUCOMER, SRL | F136: PAGO FACTURA NCF B1500000558 POR ADQUISICION DE UTILES MEDICOS SEGUN O/C HSLM-2025-00230. | G136: 141954
... A165: 21/03/2025 | B165: 1054 | E165: CRISTINA ROSARIO ROSARIO | F165: PAGO DE FACT NCF B1500000374 POR ADQUISICION DE MEDICAMENTOS SEGUN O/C HSLM-2025-00233. | G165: 208800
A166: 21/03/2025 | B166: 1058 | C166: 30710970 | E166: Sean Dominican, SRL | F166: PAGO DE FACT NCF B1500004758 POR ADQUISICION DE MEDICAMENTOS SEGUN O/C HSLM-2025-00247. | G166: 191040
A167: 21/03/2025 | B167: 1062 | C167: =+G125 -> 679000.24 | E167: AGROGLOBAL EXPORT E IMPORT, SRL | F167: PAGO DE FACT NCF B1500000712 POR ADQUISICION DE ALIMENTOS SEGUN O/C HSLM-2025-00208. | G167: 322900
A168: 24/03/2025 | B168: 1078 | C168: =+G61+G56+G55+G36 -> 141963.26 | E168: Macrotech Farmacéutica, SRL | F168: PAGO DE FACT NCF E450000000591 POR ADQUISICION DE UTILES MEDICOS SEGUN O/C HSLM-2025-00105. | G168: 187042.98
A169: 24/03/2025 | B169: 1082 | C169: =+G122+G124+G126+G127+G128+G129+G131+G130+G132 -> 3006872.3 | E169: CRISTINA ROSARIO ROSARIO | F169: PAGO DE FACT NCF B1500000377 POR ADQUISICION DE PRODUCTOS FARMACEUTICOS Y DESINFECTANTE WESCOCIDE SEGUN O/C HSLM-2025-00245. | G169: 189650
A170: 24/03/2025 | B170: 1086 | E170: Empresa Rotricomercial, SRL | F170: PAGO DE FACT NCF B1500000359 POR ADQUISICION DE MEDICAMENTOS SEGUN O/C HSLM-2025-00221. | G170: 272000
A171: 24/03/2025 | B171: 1090 | E171: Pharmasem, SRL | F171: PAGO DE FACT NCF B1500000023 POR ADQUISICION DE MEDICAMENTOS SEGUN O/C HSLM-2025-00206. | G171: 192000
A172: 24/03/2025 | B172: 1094 | E172: AGROGLOBAL EXPORT E IMPORT, SRL | F172: PAGO DE FACT NCF B1500000711 POR ADQUISICION DE ALIMENTOS SEGUN O/C HSLM-2025-00210. | G172: 168400
A173: 24/03/2025 | B173: 1098 | C173: 11495300 | E173: Nifarmed, SRL | F173: PAGO DE FACT NCF B1500001455 POR ADQUISICION DE MEDICAMENTOS SEGUN O/C HSLM-2025-00246. | G173: 121662
A174: 25/03/2025 | B174: 1118 | C174: 100061.7 | E174: Empresa Rotricomercial, SRL | F174: PAGO DE FACT NCF B1500000358 POR ADQUISICION DE MEDICAMENTOS SEGUN O/C HSLM-2025-00126. | G174: 249000
A175: 25/03/2025 | B175: 1122 | C175: 65091180 | E175: Macrotech Farmacéutica, SRL | F175: PAGO DE FACT NCF E450000000702 POR ADQUISICION DE UTILES MEDICOS SEGUN O/C HSLM-2025-00249. | G175: 889762.48
A176: 27/03/2025 | B176: 1142 | C176: 183318.35 | E176: Food Caraballo & Núñez, SRL | F176: PAGO DE FACT NCF B1500000109 POR ADQUISICION DE ALIMENTOS E INSUMOS DE DESPENSA SEGUN O/C HSLM- 2025-00244. | G176: 700640.27
A177: 27/03/2025 | B177: 1146 | E177: Trasts Meds & Devices, SRL | F177: PAGO DE FACT NCF B1500000005 POR ADQUISICION DE ELECTRODOS NEUROLINE SEGUN O/C HSLM-2025-00197. | G177: 259600
A178: 27/03/2025 | B178: 1152 | E178: Grupo Xeron Medic SRL | F178: PAGO DE FACT NCF B1500000173 POR ADQUISICION DE MEDICAMENTOS SEGUN O/C HSLM-2025-00155. | G178: 270000
A179: 28/03/2025 | B179: 1158 | C179: =+C166+C173+8138143.86 -> 50344414 | E179: Ropharma, SRL | F179: PAGO DE FACT NCF B1500001288 POR ADQUISICION DE MEDICAMENTOS SEGUN O/C HSLM-2025-00269. | G179: 272500
A180: 28/03/2025 | B180: 1162 | C180: =+C167+C174 -> 779061.94 | E180: Ropharma, SRL | F180: PAGO DE FACT NCF B1500001290 POR ADQUISICION DE MEDICAMENTOS SEGUN O/C HSLM-2025-00278. | G180: 272580
A181: 28/03/2025 | B181: 1166 | C181: =+C168+C175 -> 65233143 | E181: CRISTINA ROSARIO ROSARIO | F181: PAGO DE FACT NCF B1500000375 POR ADQUISICION DE UTILES MEDICOS SEGUN O/C HSLM-2025-00223. | G181: 162722
A182: 28/03/2025 | B182: 1170 | C182: =+C169+C176 -> 3190190.7 | E182: Empresa Rotricomercial, SRL | F182: PAGO DE FACT NCF B1500000361 POR ADQUISICION DE MEDICAMENTOS SEGUN O/C HSLM-2025-00228. | G182: 270000
A183: 31/03/2025 | B183: 1174 | E183: CRISTINA ROSARIO ROSARIO | F183: PAGO DE FACT NCF B1500000376 POR ADQUISICION DE UTILES MEDICOS SEGUN O/C HSLM- 2025-00224. | G183: 212284
A184: 31/03/2025 | B184: 1179 | C184: 0.1113 | E184: Farmaco Internacional, SRL | F184: Pago de Fact NCF No. B1500000950, por adquisicion de util medico, según orden de compra HSLM-2024-01035 | G184: 207868.8
A185: 31/03/2025 | B185: 1183 | E185: Farmaco Internacional, SRL | F185: Pago Fact NCF No. B1500001027, por adquisicion de util medico, según orden de compra HSLM-2025-00266 | G185: 272627.2
A186: 31/03/2025 | B186: 1189 | E186: Farmaco Internacional, SRL | F186: Pago Fact NCF No. B1500001028, por adquisicion de util medico, según orden de compra HSLM-2025-00267 | G186: 135036
A187: AÑO 2023 | B187: 2044133.3
A188: AÑO 2024 | B188: 7844142.9
A189: 45658 | B189: 6000812.9
...

Sheet RELACION ORDENES DE COMPRAS
A3: Republica Dominicana
A6: RELACIÓN DE ORDENES DE COMPRAS O SERVICIOS EFECTUADAS DURANTE EL MES
A7: ESTABLECIMIENTO_______________________________________________________________REGION_____________________
A8: Fecha | B8: # De Orden de Compras | C8: Proceso Realizado | D8: No. De Factura Fiscal NCF | E8: Fuente. Financ (FR-VS) | F8: Beneficiario | G8: Rubro | H8: No. Cta. Objetal del Gasto | I8: Valor
A9: 45719.501 | B9: HSLM-DAF-CD-2025-0178 | C9: Compras por Debajo del Umbral | E9: FR/VS | F9: PROYEFIC INGENIERIA Y SERVICIOS, SRL | G9: 72100000 | I9: 272432.5
A10: 45719.501 | B10: HSLM-DAF-CD-2025-0180 | C10: Compras por Debajo del Umbral | E10: FR/VS | F10: INGENIERIA Y CONSTRUCCIONES FASUMER, SRL | G10: 72100000 | I10: 271800.26
A11: 45719.501 | B11: HSLM-DAF-CD-2025-0179 | C11: Compras por Debajo del Umbral | E11: FR/VS | F11: Eligium, EIRL | G11: 72100000 | I11: 272580
A12: 45720.501 | B12: HSLM-DAF-CD-2025-0181 | C12: Compras por Debajo del Umbral | E12: FR/VS | F12: Bio Win, SRL | G12: 41110000 | I12: 30000
A13: 45720.542 | B13: HSLM-DAF-CD-2025-0183 | C13: Compras por Debajo del Umbral | E13: FR/VS | F13: Express Service Conserg Exsercon, SRL | G13: 42180000 | I13: 230320
A14: 45720.542 | B14: HSLM-DAF-CM-2025-0050 | C14: Compras Menores | E14: FR/VS | F14: Corporacion Medica A.G., SRL | G14: 42310000 | I14: 525648
A15: 45720.542 | B15: HSLM-DAF-CD-2025-0184 | C15: Compras por Debajo del Umbral | E15: FR/VS | F15: INVERSIONES FH, SRL | G15: 15100000 | I15: 172000
A16: 45720.542 | B16: HSLM-DAF-CD-2025-0182 | C16: Compras por Debajo del Umbral | E16: FR/VS | F16: Corporacion Medica A.G., SRL | G16: 42130000 | I16: 201500
A17: 45720.584 | B17: HSLM-DAF-CM-2025-0051 | C17: Compras Menores | E17: FR/VS | F17: Farmaco Internacional, SRL | G17: 42310000 | I17: 1937560
A18: 45720.626 | B18: HSLM-DAF-CM-2025-0052 | C18: Compras Menores | E18: FR/VS | F18: Baucomer, SRL | G18: 51150000 | I18: 1518000
A19: 45720.626 | B19: HSLM-DAF-CM-2025-0053 | C19: Compras Menores | E19: FR/VS | F19: Baucomer, SRL | G19: 42310000 | I19: 1056640
A20: 45721.501 | B20: HSLM-DAF-CD-2025-0185 | C20: Compras por Debajo del Umbral | E20: FR/VS | F20: Cristina Rosario Rosario | G20: 42140000 | I20: 212284
... A67: 45735.424 | B67: HSLM-DAF-CD-2025-0223 | C67: Compras por Debajo del Umbral | E67: FR/VS | F67: Ropharma, SRL | G67: 51170000 | I67: 180000
A68: 45735.438 | B68: HSLM-DAF-CD-2025-0224 | C68: Compras por Debajo del Umbral | D68: CANCELADO | E68: FR/VS | F68: CANCELADO | G68: 51100000 | I68: 0
A69: 45735.459 | B69: HSLM-DAF-CD-2025-0221 | C69: Compras por Debajo del Umbral | E69: FR/VS | F69: Felipe Antonio Morey Paulino | G69: 82120000 | I69: 196824
A70: 45735.502 | B70: HSLM-DAF-CD-2025-0225 | C70: Compras por Debajo del Umbral | E70: FR/VS | F70: Empresa Rotricomercial, SRL | G70: 51150000 | I70: 210000
A71: 45735.618 | B71: HSLM-DAF-CD-2025-0226 | C71: Compras por Debajo del Umbral | E71: FR/VS | F71: Grupo Irmaceli Services, S.R.L. | G71: 46190000 | I71: 61950
A72: 45735.668 | B72: HSLM-DAF-CD-2025-0227 | C72: Compras por Debajo del Umbral | E72: FR/VS | F72: Lora & Almonte Reparaciones, SRL | G72: 27110000 | I72: 105650
A73: 45736.479 | B73: HSLM-DAF-CM-2025-0065 | C73: Compras Menores | D73: CANCELADO | E73: FR/VS | F73: CANCELADO | G73: 50110000 | I73: 0
A74: 45736.542 | B74: HSLM-DAF-CM-2025-0064 | C74: Compras Menores | E74: FR/VS | F74: BAAM & ASOCIADOS | G74: 44100000 | I74: 436278.18
A75: 45736.604 | B75: HSLM-DAF-CD-2025-0228 | C75: Compras por Debajo del Umbral | E75: FR/VS | F75: Ropharma, SRL | G75: 51190000 | I75: 272580
A76: 45736.626 | B76: HSLM-DAF-CD-2025-0229 | C76: Compras por Debajo del Umbral | E76: FR/VS | F76: Bello-Lab, SRL | G76: 41100000 | I76: 123885
A77: 45736.646 | B77: HSLM-DAF-CM-2025-0066 | C77: Compras Menores | E77: FR/VS | F77: Sandry Gomez Rodriguez | G77: 50100000 | I77: 436930
A78: 45737.418 | B78: HSLM-DAF-CD-2025-0230 | C78: Compras por Debajo del Umbral | E78: FR/VS | F78: Copem Hospiclinic, SRL | G78: 51140000 | I78: 219375
A79: 45737.502 | B79: HSLM-DAF-CM-2025-0067 | C79: Compras Menores | E79: FR/VS | F79: Tu Amigo, SRL | G79: 15100000 | I79: 664800
A80: 45737.521 | B80: HSLM-DAF-CD-2025-0231 | C80: Compras por Debajo del Umbral | E80: FR/VS | F80: Copem Hospiclinic, SRL | G80: 51180000 | I80: 272500
A81: 45737.549 | B81: HSLM-DAF-CD-2025-0232 | C81: Compras por Debajo del Umbral | E81: FR/VS | F81: Bio Desinfeccion, SRL | G81: 76100000 | I81: 188564
A82: 45737.709 | B82: HSLM-DAF-CD-2025-0233 | C82: Compras por Debajo del Umbral | E82: FR/VS | F82: Bio Nova, SRL | G82: 41110000 | I82: 103887
A83: 45740.459 | B83: HSLM-DAF-CD-2025-0235 | C83: Compras por Debajo del Umbral | E83: FR/VS | F83: Abrias Novo Group SRL | G83: 52130000 | I83: 129800
A84: 45740.459 | B84: HSLM-DAF-CD-2025-0234 | C84: Compras por Debajo del Umbral | E84: FR/VS | F84: Abrias Novo Group SRL | G84: 56100000 | I84: 252028
A85: 45740.459 | B85: HSLM-DAF-CM-2025-0068 | C85: Compras Menores | E85: FR/VS | F85: Food Caraballo & Nuñez | G85: 50130000 | I85: 269657.5
... A96: 45742.542 | B96: HSLM-DAF-CM-2025-0073 | C96: Compras Menores | E96: FR/VS | F96: Hospitronica | G96: 42190000 | I96: 621605.1
A97: 45742.585 | B97: HSLM-DAF-CM-2025-0072 | C97: Compras Menores | E97: FR/VS | G97: 50190000
A98: 45742.626 | B98: HSLM-DAF-CD-2025-0243 | C98: Compras por Debajo del Umbral | E98: FR/VS | F98: Sandry Gomez Rodriguez | G98: 50110000 | I98: 234200
A99: 45744.376 | B99: HSLM-DAF-CD-2025-0244 | C99: Compras por Debajo del Umbral | E99: FR/VS | F99: Grupo Xeron Medic SRL | G99: 51190000 | I99: 250000
A100: 45744.419 | B100: HSLM-DAF-CD-2025-0245 | C100: Compras por Debajo del Umbral | E100: FR/VS | F100: Papelería E. Impresos Crishoan, SRL | G100: 82120000 | I100: 261960
A101: 45744.438 | B101: HSLM-DAF-CM-2025-0074 | C101: Compras Menores | E101: FR/VS | G101: 41100000
A102: 45744.501 | B102: HSLM-DAF-CM-2025-0075 | C102: Compras Menores | E102: FR/VS | F102: Cabod | G102: 12160000 | I102: 1599254
A103: 45744.51 | B103: HSLM-DAF-CD-2025-0246 | C103: Compras por Debajo del Umbral | E103: FR/VS | F103: Baucomer, SRL | G103: 51120000 | I103: 257000
A104: 45744.542 | B104: HSLM-DAF-CD-2025-0247 | C104: Compras por Debajo del Umbral | E104: FR/VS | F104: CEM Caribbean Equipment Medical | G104: 41110000 | I104: 90263.5
A105: 45744.611 | B105: HSLM-DAF-CM-2025-0076 | C105: Compras Menores | E105: FR/VS | G105: 81100000
A106: 45747.396 | B106: HSLM-DAF-CD-2025-0249 | C106: Compras por Debajo del Umbral | E106: FR/VS | F106: Grupo Xeron Medic SRL | G106: 51190000 | I106: 250000
A107: 45747.419 | B107: HSLM-DAF-CD-2025-0248 | C107: Compras por Debajo del Umbral | E107: FR/VS | F107: Abrias Novo Group SRL | G107: 52130000 | I107: 228440
A108: 45747.459 | B108: HSLM-DAF-CD-2025-0252 | C108: Compras por Debajo del Umbral | E108: FR/VS | F108: Ropharma, SRL | G108: 51160000 | I108: 220000
A109: 45747.709 | B109: HSLM-DAF-CD-2025-0250 | C109: Compras por Debajo del Umbral | E109: FR/VS | G109: 85120000
A110: 45747.709 | B110: HSLM-DAF-CD-2025-0251 | C110: Compras por Debajo del Umbral | E110: FR/VS | G110: 85120000
H111: TOTAL GENERAL | I111: =SUM(I9:I110) -> 33649567
A116: CUENTAS No. | B116: HSLM-DAF-CD-2025-0251 | C116: Compras por Debajo del Umbral | D116: MONTO | G116: TIPO | H116: CANTIDAD
G117: Compra Directa
G118: Compra Menor
G119: Comparacion de precio
A120: TOTAL RESUMEN | G120: TOTAL COMPRAS
A123: CERTIFICO CORRECTO:
A125: __________________________ | G125: ENC. DE COMPRAS:__________________________
A126: DIRECTOR
A128: __________________________
A129: ADMINISTRADOR:

Sheet CONS. FUENTES FINAN
A1: Form. No.6 SRS
A3: Servicio Nacional de Salud
A4: Dirección de Fizcalización
A5: Consolidado de Ingresos y Gastos por Fuente de Financiamiento
A6: HOSPITAL MATERNO INFANTIL SAN LORENZO DE LOS MINA
A7: MARZO 2025
C8: Ingresos Generales:
E9: 1.- Balance Inicial / Fuente:
E10: Anticipo Financiero | H10: Otros Aportes | L10: Contraseña: 0001
E11: Transferencias Corrientes
E12: Venta de Servicios | G12: 2511952.5
E13: 2.- Ingresos por Fuente / Cuenta
E14: Anticipo Financiero | H14: Otros Aportes | I14: =+'INGR SEGUN ORIGEN'!E39 -> 223625 | L14: OBJETAL | M14: FR | N14: VS
E15: Transferencias Corrientes | G15: =+'INGR SEGUN ORIGEN'!E12 -> 1.003168e+08 | H15: Aportes Nomina SNS | I15: 0 | L15: 2.1 | M15: =G26 -> 66337620 | N15: =H26 -> 5231553.6
E16: Venta de Servicios | G16: =+'INGR SEGUN ORIGEN'!E37 -> 7825280.6 | L16: 2.2 | M16: =G87 -> 7971396.2 | N16: =H87 -> 4359456.2
H17: TOTAL INGRESOS RDS | I17: =+G10+G11+G12+I10+G14+G15+G16+I14+I15 -> 1.1087765e+08 | L17: 2.3 | M17: ='CONS. FUENTES FINAN'!G212 -> 26749552 | N17: ='CONS. FUENTES FINAN'!H212 -> 1797538.3
L18: 2.4 | M18: =G330 -> 0 | N18: =H330 -> 127420
L19: 2.6 | M19: =G336 -> 11396849 | N19: =H336 -> 300539.37
L20: 2.7 | M20: ='CONS. FUENTES FINAN'!G463 -> 0 | N20: ='CONS. FUENTES FINAN'!H463 -> 0
A21: 1 | F21: 2 | G21: 3 | I21: 4 | J21: 5
A22: Código Presupuestario | F22: Descripción Gasto por Cuenta | G22: Distribución del Gasto por Fuente de Financiamiento | I22: TOTAL | J22: %
A23: Tipo | B23: Objeto | C23: Cuenta | D23: Sub-Cuenta | E23: Auxiliar | G23: Fondo 100 | H23: Venta de Servicios/ Otros Aportes
A25: 2 | F25: Gastos | G25: =+G26+G87+G212+G330+G336+G463 -> 1.1245542e+08 | H25: =+H26+H87+H212+H330+H336+H463 -> 11816507 | I25: =SUM(G25:H25) -> 1.2427192e+08 | J25: =+J26+J87+J212+J330+J336+J463 -> 1
A26: 2 | B26: 1 | F26: Servicios Personales | G26: =+G27+G51+G64+G71+G78 -> 66337620 | H26: =+H27+H51+H64+H71+H78 -> 5231553.6 | I26: =SUM(G26:H26) -> 71569173 | J26: =I26/$I$25 -> 0.57590782
A27: 2 | B27: 1 | C27: 1 | F27: Remuneraciones | G27: =+G28+G35+G42+G44+G46 -> 54718737 | H27: =+H28+H35+H42+H44+H46 -> 0 | I27: =SUM(G27:H27) -> 54718737 | J27: =I27/$I$25 -> 0.44031455
A28: 2 | B28: 1 | C28: 1 | D28: 1 | F28: Remuneraciones al personal fijo | G28: =SUM(G29:G34) -> 53611206 | H28: =SUM(H29:H34) -> 0 | I28: =SUM(G28:H28) -> 53611206 | J28: =I28/$I$25 -> 0.4314024
A29: 2 | B29: 1 | C29: 1 | D29: 1 | E29: 01 | F29: Sueldos a empleados fijos | G29: ='CUENTA T FONDO 100'!A127 -> 53611206 | H29: ='CUENTA T VS'!A96 -> 0 | I29: =SUM(G29:H29) -> 53611206 | J29: =I29/$I$25 -> 0.4314024
A30: 2 | B30: 1 | C30: 1 | D30: 1 | E30: 02 | F30: Sueldos a médicos | G30: ='CUENTA T FONDO 100'!B127 -> 0 | H30: ='CUENTA T VS'!B96 -> 0 | I30: =SUM(G30:H30) -> 0 | J30: =I30/$I$25 -> 0
A31: 2 | B31: 1 | C31: 1 | D31: 1 | E31: 03 | F31: Ascensos a militares | G31: ='CUENTA T FONDO 100'!C127 -> 0 | H31: ='CUENTA T VS'!C96 -> 0 | I31: =SUM(G31:H31) -> 0 | J31: =I31/$I$25 -> 0
A32: 2 | B32: 1 | C32: 1 | D32: 1 | E32: 04 | F32: Nuevas plazas maestros | G32: ='CUENTA T FONDO 100'!D127 -> 0 | H32: ='CUENTA T VS'!D96 -> 0 | I32: =SUM(G32:H32) -> 0 | J32: =I32/$I$25 -> 0
A33: 2 | B33: 1 | C33: 1 | D33: 1 | E33: 05 | F33: Incentivos y escalafón | G33: ='CUENTA T FONDO 100'!E127 -> 0 | H33: ='CUENTA T VS'!E96 -> 0 | I33: =SUM(G33:H33) -> 0 | J33: =I33/$I$25 -> 0
A34: 2 | B34: 1 | C34: 1 | D34: 1 | E34: 06 | F34: Nuevas plazas a médicos | G34: ='CUENTA T FONDO 100'!F127 -> 0 | H34: ='CUENTA T VS'!F96 -> 0 | I34: =SUM(G34:H34) -> 0 | J34: =I34/$I$25 -> 0
A35: 2 | B35: 1 | C35: 1 | D35: 2 | F35: Remuneraciones al personal con carácter transitorio | G35: =SUM(G36:G41) -> 1107531 | H35: =SUM(H36:H41) -> 0 | I35: =SUM(G35:H35) -> 1107531
A36: 2 | B36: 1 | C36: 1 | D36: 2 | E36: 03 | F36: Suplencias | G36: ='CUENTA T FONDO 100'!G127 -> 0 | H36: ='CUENTA T VS'!G96 -> 0 | I36: =SUM(G36:H36) -> 0 | J36: =I36/$I$25 -> 0
A37: 2 | B37: 1 | C37: 1 | D37: 2 | E37: 05 | F37: Sueldo al personal nominal en período probatorio | G37: ='CUENTA T FONDO 100'!H127 -> 0 | H37: ='CUENTA T VS'!H96 -> 0 | I37: =SUM(G37:H37) -> 0 | J37: =I37/$I$25 -> 0
A38: 2 | B38: 1 | C38: 1 | D38: 2 | E38: 06 | F38: Jornales | G38: ='CUENTA T FONDO 100'!I127 -> 0 | H38: ='CUENTA T VS'!I96 -> 0 | I38: =SUM(G38:H38) -> 0 | J38: =I38/$I$25 -> 0
A39: 2 | B39: 1 | C39: 1 | D39: 2 | E39: 08 | F39: Empleados temporales | G39: ='CUENTA T FONDO 100'!J127 -> 1107531 | H39: ='CUENTA T VS'!J96 -> 0 | I39: =SUM(G39:H39) -> 1107531 | J39: =I39/$I$25 -> 0.008912158
A40: 2 | B40: 1 | C40: 1 | D40: 2 | E40: 09 | F40: Personal de carácter eventual | G40: ='CUENTA T FONDO 100'!K127 -> 0 | H40: ='CUENTA T VS'!K96 -> 0 | I40: =SUM(G40:H40) -> 0 | J40: =I40/$I$25 -> 0
A41: 2 | B41: 1 | C41: 1 | D41: 2 | E41: 11 | F41: Interinato | G41: ='CUENTA T FONDO 100'!L127 -> 0 | H41: ='CUENTA T VS'!L96 -> 0 | I41: =SUM(G41:H41) -> 0 | J41: =I41/$I$25 -> 0
A42: 2 | B42: 1 | C42: 1 | D42: 3 | F42: Sueldos al personal fijo en trámite de pensiones | G42: =SUM(G43) -> 0 | H42: =SUM(H43) -> 0 | I42: =SUM(G42:H42) -> 0
A43: 2 | B43: 1 | C43: 1 | D43: 3 | E43: 01 | F43: Sueldos al personal fijo en trámite de pensiones | G43: ='CUENTA T FONDO 100'!M127 -> 0 | H43: ='CUENTA T VS'!M96 -> 0 | I43: =SUM(G43:H43) -> 0 | J43: =I43/$I$25 -> 0
A44: 2 | B44: 1 | C44: 1 | D44: 4 | F44: Sueldo anual no. 13 | G44: =SUM(G45) -> 0 | H44: =SUM(H45) -> 0 | I44: =SUM(G44:H44) -> 0
A45: 2 | B45: 1 | C45: 1 | D45: 4 | E45: 01 | F45: Sueldo anual no. 13 | G45: ='CUENTA T FONDO 100'!N127 -> 0 | H45: ='CUENTA T VS'!N96 -> 0 | I45: =SUM(G45:H45) -> 0 | J45: =I45/$I$25 -> 0
A46: 2 | B46: 1 | C46: 1 | D46: 5 | F46: Prestaciones económinas | G46: =SUM(G47:G50) -> 0 | H46: =SUM(H47:H50) -> 0 | I46: =SUM(G46:H46) -> 0
A47: 2 | B47: 1 | C47: 1 | D47: 5 | E47: 01 | F47: Prestaciones económinas | G47: ='CUENTA T FONDO 100'!O127 -> 0 | H47: ='CUENTA T VS'!O96 -> 0 | I47: =SUM(G47:H47) -> 0 | J47: =I47/$I$25 -> 0
A48: 2 | B48: 1 | C48: 1 | D48: 5 | E48: 02 | F48: Pago de porcentaje por desvinculación de cargo | G48: ='CUENTA T FONDO 100'!P127 -> 0 | H48: ='CUENTA T VS'!P96 -> 0 | I48: =SUM(G48:H48) -> 0 | J48: =I48/$I$25 -> 0
A49: 2 | B49: 1 | C49: 1 | D49: 5 | E49: 03 | F49: Prestación laboral por desvinculación | G49: ='CUENTA T FONDO 100'!Q127 -> 0 | H49: ='CUENTA T VS'!Q96 -> 0 | I49: =SUM(G49:H49) -> 0 | J49: =I49/$I$25 -> 0
A50: 2 | B50: 1 | C50: 1 | D50: 5 | E50: 04 | F50: Proporción de vacaciones no disfrutadas | G50: ='CUENTA T FONDO 100'!R127 -> 0 | H50: ='CUENTA T VS'!R96 -> 0 | I50: =SUM(G50:H50) -> 0 | J50: =I50/$I$25 -> 0
A51: 2 | B51: 1 | C51: 2 | F51: Sobresueldos | G51: =+G52+G54 -> 3199399.6 | H51: =+H52+H54 -> 5231553.6 | I51: =SUM(G51:H51) -> 8430953.2
A52: 2 | B52: 1 | C52: 2 | D52: 1 | F52: Primas por antigüedad | G52: =SUM(G53) -> 2752136.5 | H52: =SUM(H53) -> 0 | I52: =SUM(G52:H52) -> 2752136.5
A53: 2 | B53: 1 | C53: 2 | D53: 1 | E53: 01 | F53: Primas por antigüedad | G53: ='CUENTA T FONDO 100'!S127 -> 2752136.5 | H53: ='CUENTA T VS'!S96 -> 0 | I53: =SUM(G53:H53) -> 2752136.5 | J53: =I53/$I$25 -> 0.022146084
A54: 2 | B54: 1 | C54: 2 | D54: 2 | F54: Compensación | G54: =SUM(G55:G63) -> 447263.1 | H54: =SUM(H55:H63) -> 5231553.6 | I54: =SUM(G54:H54) -> 5678816.7
A55: 2 | B55: 1 | C55: 2 | D55: 2 | E55: 01 | F55: Compensación por gastos de alimentación | G55: ='CUENTA T FONDO 100'!T127 -> 0 | H55: ='CUENTA T VS'!T96 -> 0 | I55: =SUM(G55:H55) -> 0 | J55: =I55/$I$25 -> 0
A56: 2 | B56: 1 | C56: 2 | D56: 2 | E56: 03 | F56: Pago de horas extraordinarias | G56: ='CUENTA T FONDO 100'!U127 -> 0 | H56: ='CUENTA T VS'!U96 -> 0 | I56: =SUM(G56:H56) -> 0 | J56: =I56/$I$25 -> 0
A57: 2 | B57: 1 | C57: 2 | D57: 2 | E57: 04 | F57: Prima de transporte | G57: ='CUENTA T FONDO 100'!V127 -> 0 | H57: ='CUENTA T VS'!V96 -> 0 | I57: =SUM(G57:H57) -> 0 | J57: =I57/$I$25 -> 0
A58: 2 | B58: 1 | C58: 2 | D58: 2 | E58: 05 | F58: Compensación servicios de Seguridad | G58: ='CUENTA T FONDO 100'!W127 -> 45000 | H58: ='CUENTA T VS'!W96 -> 0 | I58: =SUM(G58:H58) -> 45000 | J58: =I58/$I$25 -> 0.00036210914
A59: 2 | B59: 1 | C59: 2 | D59: 2 | E59: 06 | F59: Incentivo por Rendimieto Individual | G59: ='CUENTA T FONDO 100'!X127 -> 0 | H59: ='CUENTA T VS'!X96 -> 5231553.6 | I59: =SUM(G59:H59) -> 5231553.6 | J59: =I59/$I$25 -> 0.042097631
A60: 2 | B60: 1 | C60: 2 | D60: 2 | E60: 07 | F60: Compensación por distancia | G60: ='CUENTA T FONDO 100'!Y127 -> 0 | H60: ='CUENTA T VS'!Y96 -> 0 | I60: =SUM(G60:H60) -> 0 | J60: =I60/$I$25 -> 0
A61: 2 | B61: 1 | C61: 2 | D61: 2 | E61: 08 | F61: Compensaciones especiales | G61: ='CUENTA T FONDO 100'!Z127 -> 332600 | H61: ='CUENTA T VS'!Z96 -> 0 | I61: =SUM(G61:H61) -> 332600 | J61: =I61/$I$25 -> 0.0026763889
A62: 2 | B62: 1 | C62: 2 | D62: 2 | E62: 09 | F62: Bono por desempeño a servidores de carrera | G62: ='CUENTA T FONDO 100'!AA127 -> 0 | H62: ='CUENTA T VS'!AA96 -> 0 | I62: =SUM(G62:H62) -> 0 | J62: =I62/$I$25 -> 0
A63: 2 | B63: 1 | C63: 2 | D63: 2 | E63: 10 | F63: Compensacion por cumplimiento de indicadores | G63: ='CUENTA T FONDO 100'!AB127 -> 69663.1 | H63: ='CUENTA T VS'!AB96 -> 0 | I63: =SUM(G63:H63) -> 69663.1 | J63: =I63/$I$25 -> 0.0005605699
A64: 2 | B64: 1 | C64: 3 | F64: Dietas y Gastos de Representación | G64: =+G65+G68 -> 0 | H64: =+H65+H68 -> 0 | I64: =SUM(G64:H64) -> 0
A65: 2 | B65: 1 | C65: 3 | D65: 1 | F65: Dietas | G65: =SUM(G66:G67) -> 0 | H65: =SUM(H66:H67) -> 0 | I65: =SUM(G65:H65) -> 0
A66: 2 | B66: 1 | C66: 3 | D66: 1 | E66: 01 | F66: Dietas en el país | G66: ='CUENTA T FONDO 100'!AC127 -> 0 | H66: ='CUENTA T VS'!AC96 -> 0 | I66: =SUM(G66:H66) -> 0 | J66: =I66/$I$25 -> 0
A67: 2 | B67: 1 | C67: 3 | D67: 1 | E67: 02 | F67: Dietas en el exterior | G67: ='CUENTA T FONDO 100'!AD127 -> 0 | H67: ='CUENTA T VS'!AD96 -> 0 | I67: =SUM(G67:H67) -> 0 | J67: =I67/$I$25 -> 0
A68: 2 | B68: 1 | C68: 3 | D68: 2 | F68: Gastos de representación | G68: =SUM(G69:G70) -> 0 | H68: =SUM(H69:H70) -> 0 | I68: =SUM(G68:H68) -> 0
A69: 2 | B69: 1 | C69: 3 | D69: 2 | E69: 01 | F69: Gastos de representación en el país | G69: ='CUENTA T FONDO 100'!AE127 -> 0 | H69: ='CUENTA T VS'!AE96 -> 0 | I69: =SUM(G69:H69) -> 0 | J69: =I69/$I$25 -> 0
A70: 2 | B70: 1 | C70: 3 | D70: 2 | E70: 02 | F70: Gastos de representación en el exterior | G70: ='CUENTA T FONDO 100'!AF127 -> 0 | H70: ='CUENTA T VS'!AF96 -> 0 | I70: =SUM(G70:H70) -> 0 | J70: =I70/$I$25 -> 0
A71: 2 | B71: 1 | C71: 4 | F71: Gratificaciones y Bonificaciones | G71: =+G72+G74 -> 0 | H71: =+H72+H74 -> 0 | I71: =SUM(G71:H71) -> 0
A72: 2 | B72: 1 | C72: 4 | D72: 1 | F72: Bonificaciones | G72: =SUM(G73) -> 0 | H72: =SUM(H73) -> 0 | I72: =SUM(G72:H72) -> 0
A73: 2 | B73: 1 | C73: 4 | D73: 1 | E73: 01 | F73: Bonificaciones | G73: ='CUENTA T FONDO 100'!AG127 -> 0 | H73: ='CUENTA T VS'!AG96 -> 0 | I73: =SUM(G73:H73) -> 0 | J73: =I73/$I$25 -> 0
A74: 2 | B74: 1 | C74: 4 | D74: 2 | F74: Otras Gratificaciones y Bonificaciones | G74: =SUM(G75:G77) -> 0 | H74: =SUM(H75:H77) -> 0 | I74: =SUM(G74:H74) -> 0
A75: 2 | B75: 1 | C75: 4 | D75: 2 | E75: 01 | F75: Bono escolar | G75: ='CUENTA T FONDO 100'!AH127 -> 0 | H75: ='CUENTA T VS'!AH96 -> 0 | I75: =SUM(G75:H75) -> 0 | J75: =I75/$I$25 -> 0
A76: 2 | B76: 1 | C76: 4 | D76: 2 | E76: 02 | F76: Gratificaciones por pasantías | G76: ='CUENTA T FONDO 100'!AI127 -> 0 | H76: ='CUENTA T VS'!AI96 -> 0 | I76: =SUM(G76:H76) -> 0 | J76: =I76/$I$25 -> 0
A77: 2 | B77: 1 | C77: 4 | D77: 2 | E77: 03 | F77: Gratificaciones por aniversario de institución | G77: ='CUENTA T FONDO 100'!AJ127 -> 0 | H77: ='CUENTA T VS'!AJ96 -> 0 | I77: =SUM(G77:H77) -> 0 | J77: =I77/$I$25 -> 0
A78: 2 | B78: 1 | C78: 5 | F78: Contribuciones a la Seguridad Social y Riesgo Laboral | G78: =+G79+G81+G83+G85 -> 8419483.2 | H78: =+H79+H81+H83+H85 -> 0 | I78: =SUM(G78:H78) -> 8419483.2
A79: 2 | B79: 1 | C79: 5 | D79: 1 | F79: Contribuciones al seguro de salud | G79: =SUM(G80) -> 3879560.8 | H79: =SUM(H80) -> 0 | I79: =SUM(G79:H79) -> 3879560.8
A80: 2 | B80: 1 | C80: 5 | D80: 1 | E80: 01 | F80: Contribuciones al seguro de salud | G80: ='CUENTA T FONDO 100'!AK127 -> 3879560.8 | H80: ='CUENTA T VS'!AK96 -> 0 | I80: =SUM(G80:H80) -> 3879560.8 | J80: =I80/$I$25 -> 0.031218321
A81: 2 | B81: 1 | C81: 5 | D81: 2 | F81: Contribuciones al seguro de pensiones | G81: =SUM(G82) -> 3885030.8 | H81: =SUM(H82) -> 0 | I81: =SUM(G81:H81) -> 3885030.8
A82: 2 | B82: 1 | C82: 5 | D82: 2 | E82: 01 | F82: Contribuciones al seguro de pensiones | G82: ='CUENTA T FONDO 100'!AL127 -> 3885030.8 | H82: ='CUENTA T VS'!AL96 -> 0 | I82: =SUM(G82:H82) -> 3885030.8 | J82: =I82/$I$25 -> 0.031262337
A83: 2 | B83: 1 | C83: 5 | D83: 3 | F83: Contribuciones al seguro de riesgo laboral | G83: =SUM(G84) -> 654891.59 | H83: =SUM(H84) -> 0 | I83: =SUM(G83:H83) -> 654891.59
A84: 2 | B84: 1 | C84: 5 | D84: 3 | E84: 01 | F84: Contribuciones al seguro de riesgo laboral | G84: ='CUENTA T FONDO 100'!AM127 -> 654891.59 | H84: ='CUENTA T VS'!AM96 -> 0 | I84: =SUM(G84:H84) -> 654891.59 | J84: =I84/$I$25 -> 0.0052698274
A85: 2 | B85: 1 | C85: 5 | D85: 4 | F85: Contribuciones al plan de retiro complementario | G85: =SUM(G86) -> 0 | H85: =SUM(H86) -> 0 | I85: =SUM(G85:H85) -> 0
A86: 2 | B86: 1 | C86: 5 | D86: 4 | E86: 01 | F86: Contribuciones al plan de retiro complementario | G86: ='CUENTA T FONDO 100'!AN127 -> 0 | H86: ='CUENTA T VS'!AN96 -> 0 | I86: =SUM(G86:H86) -> 0 | J86: =I86/$I$25 -> 0
A87: 2 | B87: 2 | F87: Servicios No Personales | G87: =G88+G106+G111+G116+G125+G148+G157+G179+G208 -> 7971396.2 | H87: =H88+H106+H111+H116+H125+H148+H157+H179+H208 -> 4359456.2 | I87: =SUM(G87:H87) -> 12330852 | J87: =I87/$I$25 -> 0.099224765
A88: 2 | B88: 2 | C88: 1 | F88: Servicios Básicos | G88: =+G89+G91+G93+G95+G97+G99+G102+G104 -> 2020024.3 | H88: =+H89+H91+H93+H95+H97+H99+H102+H104 -> 1731191.2 | I88: =SUM(G88:H88) -> 3751215.5
A89: 2 | B89: 2 | C89: 1 | D89: 1 | F89: Radiocomunicación | G89: =SUM(G90) -> 0 | H89: =SUM(H90) -> 0 | I89: =SUM(G89:H89) -> 0
A90: 2 | B90: 2 | C90: 1 | D90: 1 | E90: 01 | F90: Radiocomunicación | G90: ='CUENTA T FONDO 100'!AO127 -> 0 | H90: ='CUENTA T VS'!AO96 -> 0 | I90: =SUM(G90:H90) -> 0 | J90: =I90/$I$25 -> 0
A91: 2 | B91: 2 | C91: 1 | D91: 2 | F91: Servicios telefónico de larga distancia | G91: =SUM(G92) -> 0 | H91: =SUM(H92) -> 0 | I91: =SUM(G91:H91) -> 0
A92: 2 | B92: 2 | C92: 1 | D92: 2 | E92: 01 | F92: Servicios telefónico de larga distancia | G92: ='CUENTA T FONDO 100'!AP127 -> 0 | H92: ='CUENTA T VS'!AP96 -> 0 | I92: =SUM(G92:H92) -> 0 | J92: =I92/$I$25 -> 0
A93: 2 | B93: 2 | C93: 1 | D93: 3 | F93: Teléfono local | G93: =SUM(G94) -> 0 | H93: =SUM(H94) -> 211191.19 | I93: =SUM(G93:H93) -> 211191.19
A94: 2 | B94: 2 | C94: 1 | D94: 3 | E94: 01 | F94: Teléfono local | G94: ='CUENTA T FONDO 100'!AQ127 -> 0 | H94: ='CUENTA T VS'!AQ96 -> 211191.19 | I94: =SUM(G94:H94) -> 211191.19 | J94: =I94/$I$25 -> 0.001699428
A95: 2 | B95: 2 | C95: 1 | D95: 4 | F95: Telefax y correos | G95: =SUM(G96) -> 0 | H95: =SUM(H96) -> 0 | I95: =SUM(G95:H95) -> 0
A96: 2 | B96: 2 | C96: 1 | D96: 4 | E96: 01 | F96: Telefax y correos | G96: ='CUENTA T FONDO 100'!AR127 -> 0 | H96: ='CUENTA T VS'!AR96 -> 0 | I96: =SUM(G96:H96) -> 0 | J96: =I96/$I$25 -> 0
A97: 2 | B97: 2 | C97: 1 | D97: 5 | F97: Servicio de Internet y televisión por cable | G97: =SUM(G98) -> 0 | H97: =SUM(H98) -> 0 | I97: =SUM(G97:H97) -> 0
A98: 2 | B98: 2 | C98: 1 | D98: 5 | E98: 01 | F98: Servicio de Internet y televisión por cable | G98: ='CUENTA T FONDO 100'!AS127 -> 0 | H98: ='CUENTA T VS'!AS96 -> 0 | I98: =SUM(G98:H98) -> 0 | J98: =I98/$I$25 -> 0
A99: 2 | B99: 2 | C99: 1 | D99: 6 | F99: Electricidad | G99: =SUM(G100:G101) -> 0 | H99: =SUM(H100:H101) -> 0 | I99: =SUM(G99:H99) -> 0
A100: 2 | B100: 2 | C100: 1 | D100: 6 | E100: 01 | F100: Energía eléctrica | G100: ='CUENTA T FONDO 100'!AT127 -> 0 | H100: ='CUENTA T VS'!AT96 -> 0 | I100: =SUM(G100:H100) -> 0 | J100: =I100/$I$25 -> 0
A101: 2 | B101: 2 | C101: 1 | D101: 6 | E101: 02 | F101: Electricidad no cortable | G101: ='CUENTA T FONDO 100'!AU127 -> 0 | H101: ='CUENTA T VS'!AU96 -> 0 | I101: =SUM(G101:H101) -> 0 | J101: =I101/$I$25 -> 0
A102: 2 | B102: 2 | C102: 1 | D102: 7 | F102: Agua | G102: =SUM(G103) -> 2020024.3 | H102: =SUM(H103) -> 0 | I102: =SUM(G102:H102) -> 2020024.3
...

Sheet CUENTA T FONDO 100
A1: D E S G L O S E D E L A S C U E N T A S
A2: 211101 | B2: 211102 | C2: 211103 | D2: 211104 | E2: 211105 | F2: 211106 | G2: 211203 | H2: 211205 | I2: 211206 | J2: 211208 | K2: 211209 | L2: 211211 | M2: 211301 | N2: 211401 | O2: 211501 | P2: 211502 | Q2: 211503 | R2: 211504 | S2: 212101 | T2: 212201 | U2: 212203 | V2: 212204 | W2: 212205 | X2: 212206 | Y2: 212207 | Z2: 212208 | AA2: 212209 | AB2: 212210 | AC2: 213101 | AD2: 213102 | AE2: 213201 | AF2: 213202 | AG2: 214101 | AH2: 214201 | AI2: 214202 | AJ2: 214203 | AK2: 215101 | AL2: 215201 | AM2: 215301 | AN2: 215401 | AO2: 221101 | AP2: 221201 | AQ2: 221301 | AR2: 221401 | AS2: 221501 | AT2: 221601 | AU2: 221602 | AV2: 221701 | AW2: 221801 | AX2: 222101 | AY2: 222201 | AZ2: 223101 | BA2: 223201 | BB2: 224101 | BC2: 224201 | BD2: 224301 | BE2: 224401 | BF2: 225101 | BG2: 225201 | BH2: 225301 | BI2: 225302 | BJ2: 225303 | BK2: 225304 | BL2: 225305 | BM2: 225401 | BN2: 225501 | BO2: 225601 | BP2: 225701 | BQ2: 225801 | BR2: 225901 | BS2: 226101 | BT2: 226201 | BU2: 226301 | BV2: 226401 | BW2: 227101 | BX2: 227102 | BY2: 227103 | BZ2: 227104 | CA2: 227105 | CB2: 227106 | CC2: 227107 | CD2: 227199 | CE2: 227201 | CF2: 227202 | CG2: 227203 | CH2: 227204 | CI2: 227205 | CJ2: 227206 | CK2: 227207 | CL2: 227208 | CM2: 227299 | CN2: 227301 | CO2: 228101 | CP2: 228201 | CQ2: 228301 | CR2: 228401 | CS2: 228501 | CT2: 228502 | CU2: 228503 | CV2: 228601 | CW2: 228602 | CX2: 228603 | CY2: 228604 | CZ2: 228701 | DA2: 228702 | DB2: 228703 | DC2: 228704 | DD2: 228705 | DE2: 228706 | DF2: 228801 | DG2: 228802 | DH2: 228803 | DI2: 229201 | DJ2: 229203 | DK2: 231101 | DL2: 231102 | DM2: 231201 | DN2: 231301 | DO2: 231302 | DP2: 231303 | DQ2: 231401 | DR2: 232101 | DS2: 232201 | DT2: 232301 | DU2: 233101 | DV2: 233201 | DW2: 233301 | DX2: 233401 | DY2: 233501 | DZ2: 233601 | EA2: 234101 | EB2: 234201 | EC2: 235101 | ED2: 235201 | EE2: 235301 | EF2: 235401 | EG2: 235501 | EH2: 236101 | EI2: 236102 | EJ2: 236103 | EK2: 236104 | EL2: 236105 | EM2: 236201 | EN2: 236202 | EO2: 236203 | EP2: 236304 | EQ2: 236305 | ER2: 236306 | ES2: 236401 | ET2: 236402 | EU2: 236403 | EV2: 236404 | EW2: 236405 | EX2: 236406 | EY2: 236407 | EZ2: 236901 | FA2: 237101 | FB2: 237102 | FC2: 237103 | FD2: 237104 | FE2: 237105 | FF2: 237106 | FG2: 237107 | FH2: 237201 | FI2: 237202 | FJ2: 237203 | FK2: 237204 | FL2: 237205 | FM2: 237206 | FN2: 237299 | FO2: 238101 | FP2: 238201 | FQ2: 239101 | FR2: 239102 | FS2: 239201 | FT2: 239301 | FU2: 239401 | FV2: 239501 | FW2: 239601 | FX2: 239701 | FY2: 239801 | FZ2: 239802 | GA2: 239901 | GB2: 239904 | GC2: 241201 | GD2: 241202 | GE2: 241203 | GF2: 241204 | GG2: 241205 | GH2: 261101 | GI2: 261201 | GJ2: 261301 | GK2: 261401 | GL2: 261901 | GM2: 262101 | GN2: 262201 | GO2: 262301 | GP2: 262401 | GQ2: 263101 | GR2: 263201 | GS2: 263301 | GT2: 263401 | GU2: 264101 | GV2: 264201 | GW2: 264301 | GX2: 264401 | GY2: 264501 | GZ2: 264601 | HA2: 264701 | HB2: 264801 | HC2: 265101 | HD2: 265201 | HE2: 265301 | HF2: 265401 | HG2: 265501 | HH2: 265601 | HI2: 265701 | HJ2: 265801 | HK2: 266101 | HL2: 266201 | HM2: 267101 | HN2: 267201 | HO2: 267301 | HP2: 267401 | HQ2: 267501 | HR2: 267601 | HS2: 267701 | HT2: 267801 | HU2: 267901 | HV2: 268101 | HW2: 268201 | HX2: 268301 | HY2: 268302 | HZ2: 268401 | IA2: 268501 | IB2: 268601 | IC2: 268701 | ID2: 268802 | IE2: 268803 | IF2: 268804 | IG2: 268901 | IH2: 269101 | II2: 269102 | IJ2: 269201 | IK2: 269202 | IL2: 269301 | IM2: 269401 | IN2: 269501 | IO2: 269502 | IP2: 269503 | IQ2: 2269901 | IR2: 271101 | IS2: 271201 | IT2: 271301 | IU2: 271401 | IV2: 272101 | IW2: 272201 | IX2: 272301 | IY2: 272401 | IZ2: 272501 | JA2: 272601 | JB2: 272701 | JC2: 272801 | JD2: 272901 | JE2: 273101 | JF2: 273201 | JG2: 274101 | JH2: 274201 | JI2: Totales | JJ2: TRANSF NO. | JK2: VALOR | JL2: RETENCION | JM2: AÑOS ANTERIORES | JN2: 2024 | JO2: Total | JP2: Proveedor Informal
FW3: 90000.1 | FY3: 19599.99 | FZ3: 4000.01 | GB3: 22499.99 | JI3: =SUM(A3:JH3) -> 136100.09 | JJ3: 547 | JL3: =+JI3-JK3 -> 136100.09 | JO3: =+JM3+JN3 -> 0
HH4: 3199.97 | JI4: =SUM(A4:JH4) -> 3199.97 | JJ4: 551 | JL4: =+JI4-JK4 -> 3199.97
EA5: 86700 | JI5: =SUM(A5:JH5) -> 86700 | JJ5: 554 | JL5: =+JI5-JK5 -> 86700
GQ6: 999401 | JI6: =SUM(A6:JH6) -> 999401 | JJ6: 558 | JL6: =+JI6-JK6 -> 999401
FT7: 265051.6 | JI7: =SUM(A7:JH7) -> 265051.6 | JJ7: 562 | JL7: =+JI7-JK7 -> 265051.6
GQ8: 1968240 | JI8: =SUM(A8:JH8) -> 1968240 | JJ8: 566 | JL8: =+JI8-JK8 -> 1968240
GQ9: 873200 | JI9: =SUM(A9:JH9) -> 873200 | JJ9: 570 | JL9: =+JI9-JK9 -> 873200
EA10: 57000 | FT10: 207711.6 | JI10: =SUM(A10:JH10) -> 264711.6 | JJ10: 574 | JL10: =+JI10-JK10 -> 264711.6
EA11: 6875 | FT11: 233640 | JI11: =SUM(A11:JH11) -> 240515 | JJ11: 578 | JL11: =+JI11-JK11 -> 240515
EA12: 146000 | FT12: 121156.5 | JI12: =SUM(A12:JH12) -> 267156.5 | JJ12: 582 | JL12: =+JI12-JK12 -> 267156.5
EA13: 151000 | JI13: =SUM(A13:JH13) -> 151000 | JJ13: 586 | JL13: =+JI13-JK13 -> 151000
EA14: 37600 | FT14: 88500 | JI14: =SUM(A14:JH14) -> 126100 | JJ14: 591 | JL14: =+JI14-JK14 -> 126100
GJ15: 6490 | JI15: =SUM(A15:JH15) -> 6490 | JJ15: 595 | JL15: =+JI15-JK15 -> 6490
GJ16: 57230 | JI16: =SUM(A16:JH16) -> 57230 | JJ16: 599 | JL16: =+JI16-JK16 -> 57230
GJ17: 120360 | JI17: =SUM(A17:JH17) -> 120360 | JJ17: 603 | JL17: =+JI17-JK17 -> 120360
EA18: 90000 | JI18: =SUM(A18:JH18) -> 90000 | JJ18: 607 | JL18: =+JI18-JK18 -> 90000
EA19: 47400 | FT19: 224790 | JI19: =SUM(A19:JH19) -> 272190 | JJ19: 611 | JL19: =+JI19-JK19 -> 272190
FN20: 144969.28 | FT20: 90109.52 | JI20: =SUM(A20:JH20) -> 235078.8 | JJ20: 615 | JL20: =+JI20-JK20 -> 235078.8
GR21: 15930 | JI21: =SUM(A21:JH21) -> 15930 | JJ21: 619 | JL21: =+JI21-JK21 -> 15930
AV22: 1959489.3 | JI22: =SUM(A22:JH22) -> 1959489.3 | JJ22: 624 | JL22: =+JI22-JK22 -> 1959489.3
FQ23: 160215.06 | JI23: =SUM(A23:JH23) -> 160215.06 | JJ23: 626 | JL23: =+JI23-JK23 -> 160215.06
FT24: 186440 | JI24: =SUM(A24:JH24) -> 186440 | JJ24: 632 | JL24: =+JI24-JK24 -> 186440
FJ25: 268000 | JI25: =SUM(A25:JH25) -> 268000 | JJ25: 655 | JL25: =+JI25-JK25 -> 268000
FN26: 14300 | JI26: =SUM(A26:JH26) -> 14300 | JJ26: 661 | JL26: =+JI26-JK26 -> 14300
FT27: 235823 | JI27: =SUM(A27:JH27) -> 235823 | JJ27: 665 | JL27: =+JI27-JK27 -> 235823
FT28: 270000 | JI28: =SUM(A28:JH28) -> 270000 | JJ28: 669 | JL28: =+JI28-JK28 -> 270000
BW29: 1091212.1 | JI29: =SUM(A29:JH29) -> 1091212.1 | JJ29: 673 | JL29: =+JI29-JK29 -> 1091212.1
BW30: 1692916.7 | JI30: =SUM(A30:JH30) -> 1692916.7 | JJ30: 677 | JL30: =+JI30-JK30 -> 1692916.7
EA31: 33000 | FT31: 206647.5 | JI31: =SUM(A31:JH31) -> 239647.5 | JJ31: 681 | JL31: =+JI31-JK31 -> 239647.5
FT32: 129664 | JI32: =SUM(A32:JH32) -> 129664 | JJ32: 685 | JL32: =+JI32-JK32 -> 129664
GH33: 241546 | JI33: =SUM(A33:JH33) -> 241546 | JJ33: 689 | JL33: =+JI33-JK33 -> 241546
DK34: 222558.2 | DV34: 18408 | FA34: 1829 | JI34: =SUM(A34:JH34) -> 242795.2 | JJ34: 693 | JL34: =+JI34-JK34 -> 242795.2
FT35: 208010.4 | JI35: =SUM(A35:JH35) -> 208010.4 | JJ35: 697 | JL35: =+JI35-JK35 -> 208010.4
FT36: 203078 | JI36: =SUM(A36:JH36) -> 203078 | JJ36: 701 | JL36: =+JI36-JK36 -> 203078
DK37: 264630 | JI37: =SUM(A37:JH37) -> 264630 | JJ37: 705 | JL37: =+JI37-JK37 -> 264630
GH38: 241546 | JI38: =SUM(A38:JH38) -> 241546 | JJ38: 709 | JL38: =+JI38-JK38 -> 241546
FM39: 203654.83 | JI39: =SUM(A39:JH39) -> 203654.83 | JJ39: 717 | JL39: =+JI39-JK39 -> 203654.83
EA40: 198000 | FT40: 67496 | JI40: =SUM(A40:JH40) -> 265496 | JJ40: 721 | JL40: =+JI40-JK40 -> 265496
EA41: 92000 | JI41: =SUM(A41:JH41) -> 92000 | JJ41: 725 | JL41: =+JI41-JK41 -> 92000
FJ42: 407143.97 | JI42: =SUM(A42:JH42) -> 407143.97 | JJ42: 729 | JL42: =+JI42-JK42 -> 407143.97
FA43: 554000 | JI43: =SUM(A43:JH43) -> 554000 | JJ43: 733 | JL43: =+JI43-JK43 -> 554000
FT44: 188800 | JI44: =SUM(A44:JH44) -> 188800 | JJ44: 737 | JL44: =+JI44-JK44 -> 188800
DV45: 1250.8 | FJ45: 576004 | JI45: =SUM(A45:JH45) -> 577254.8 | JJ45: 741 | JL45: =+JI45-JK45 -> 577254.8
FT46: 256060 | JI46: =SUM(A46:JH46) -> 256060 | JJ46: 747 | JL46: =+JI46-JK46 -> 256060
EA47: 54720 | JI47: =SUM(A47:JH47) -> 54720 | JJ47: 751 | JL47: =+JI47-JK47 -> 54720
GR48: 32450 | JI48: =SUM(A48:JH48) -> 32450 | JJ48: 757 | JL48: =+JI48-JK48 -> 32450
FJ49: 113775 | JI49: =SUM(A49:JH49) -> 113775 | JJ49: 761 | JL49: =+JI49-JK49 -> 113775
FJ50: 47600 | FT50: 68440 | JI50: =SUM(A50:JH50) -> 116040 | JJ50: 765 | JL50: =+JI50-JK50 -> 116040
DK51: 220000 | JI51: =SUM(A51:JH51) -> 220000 | JJ51: 769 | JL51: =+JI51-JK51 -> 220000
GH52: 11033 | GQ52: 64900 | JI52: =SUM(A52:JH52) -> 75933 | JJ52: 775 | JL52: =+JI52-JK52 -> 75933
BW53: 1583621.6 | JI53: =SUM(A53:JH53) -> 1583621.6 | JJ53: 780 | JL53: =+JI53-JK53 -> 1583621.6
BW54: 1583621.6 | JI54: =SUM(A54:JH54) -> 1583621.6 | JJ54: 784 | JL54: =+JI54-JK54 -> 1583621.6
FT55: 661624 | JI55: =SUM(A55:JH55) -> 661624 | JJ55: 789 | JL55: =+JI55-JK55 -> 661624
GQ56: 1650000 | JI56: =SUM(A56:JH56) -> 1650000 | JJ56: 793 | JL56: =+JI56-JK56 -> 1650000
EA57: 238550 | FT57: 29989.7 | JI57: =SUM(A57:JH57) -> 268539.7 | JJ57: 797 | JL57: =+JI57-JK57 -> 268539.7
DW58: 771838 | JI58: =SUM(A58:JH58) -> 771838 | JJ58: 801 | JL58: =+JI58-JK58 -> 771838
DK59: 564972.5 | JI59: =SUM(A59:JH59) -> 564972.5 | JJ59: 805 | JL59: =+JI59-JK59 -> 564972.5
EA60: 27324 | FT60: 34220 | JI60: =SUM(A60:JH60) -> 61544 | JJ60: 809 | JL60: =+JI60-JK60 -> 61544
FJ61: 1250 | FT61: 19413.36 | JI61: =SUM(A61:JH61) -> 20663.36 | JJ61: 812 | JL61: =+JI61-JK61 -> 20663.36
DW62: 271754 | JI62: =SUM(A62:JH62) -> 271754 | JJ62: 820 | JL62: =+JI62-JK62 -> 271754
DK63: 654102.24 | DV63: 21712 | GB63: 3186 | JI63: =SUM(A63:JH63) -> 679000.24 | JJ63: 824 | JL63: =+JI63-JK63 -> 679000.24
DK64: 19520 | JI64: =SUM(A64:JH64) -> 19520 | JJ64: 828 | JL64: =+JI64-JK64 -> 19520
AV65: 60535 | JI65: =SUM(A65:JH65) -> 60535 | JJ65: 838 | JL65: =+JI65-JK65 -> 60535
FT66: 214760 | JI66: =SUM(A66:JH66) -> 214760 | JJ66: 842 | JL66: =+JI66-JK66 -> 214760
EA67: 218816 | FW67: 38940 | JI67: =SUM(A67:JH67) -> 257756 | JJ67: 846 | JL67: =+JI67-JK67 -> 257756
FT68: 208010.4 | JI68: =SUM(A68:JH68) -> 208010.4 | JJ68: 850 | JL68: =+JI68-JK68 -> 208010.4
EA69: 12600 | FT69: 18292.95 | JI69: =SUM(A69:JH69) -> 30892.95 | JJ69: 854 | JL69: =+JI69-JK69 -> 30892.95
GQ70: 1882100 | JI70: =SUM(A70:JH70) -> 1882100 | JJ70: 858 | JL70: =+JI70-JK70 -> 1882100
GQ71: 1787700 | JI71: =SUM(A71:JH71) -> 1787700 | JJ71: 862 | JL71: =+JI71-JK71 -> 1787700
EG72: 334708.95 | JI72: =SUM(A72:JH72) -> 334708.95 | JJ72: 867 | JL72: =+JI72-JK72 -> 334708.95
W73: 45000 | JI73: =SUM(A73:JH73) -> 45000 | JJ73: 871 | JL73: =+JI73-JK73 -> 45000
FT74: 141954 | JI74: =SUM(A74:JH74) -> 141954 | JJ74: 872 | JL74: =+JI74-JK74 -> 141954
J75: 1107531 | AK75: 78523.95 | AL75: 78634.7 | AM75: 13079.29 | JI75: =SUM(A75:JH75) -> 1277769 | JJ75: 874 | JL75: =+JI75-JK75 -> 1277769
FT76: 1056640 | JI76: =SUM(A76:JH76) -> 1056640 | JJ76: 878 | JL76: =+JI76-JK76 -> 1056640
EA77: 1518000 | JI77: =SUM(A77:JH77) -> 1518000 | JJ77: 885 | JL77: =+JI77-JK77 -> 1518000
GQ78: 1177510.2 | JI78: =SUM(A78:JH78) -> 1177510.2 | JJ78: 889 | JL78: =+JI78-JK78 -> 1177510.2
FT79: 272521 | JI79: =SUM(A79:JH79) -> 272521 | JJ79: 893 | JL79: =+JI79-JK79 -> 272521
DV80: 8496 | DW80: 260780 | JI80: =SUM(A80:JH80) -> 269276 | JJ80: 924 | JL80: =+JI80-JK80 -> 269276
A81: 53611206 | S81: 2752136.5 | Z81: 332600 | AB81: =10717.4+58945.7 -> 69663.1 | AK81: 3801036.8 | AL81: 3806396.1 | AM81: 641812.3 | JI81: =SUM(A81:JH81) -> 65014851 | JJ81: 926 | JL81: =+JI81-JK81 -> 65014851
FT82: 634769.2 | JI82: =SUM(A82:JH82) -> 634769.2 | JJ82: 953 | JL82: =+JI82-JK82 -> 634769.2
DV83: 105020 | FS83: 132475.4 | JI83: =SUM(A83:JH83) -> 237495.4 | JJ83: 957 | JL83: =+JI83-JK83 -> 237495.4
FT84: 456188 | JI84: =SUM(A84:JH84) -> 456188 | JJ84: 962 | JL84: =+JI84-JK84 -> 456188
EA85: 200000 | JI85: =SUM(A85:JH85) -> 200000 | JJ85: 966 | JL85: =+JI85-JK85 -> 200000
EA86: 179280 | JI86: =SUM(A86:JH86) -> 179280 | JJ86: 970 | JL86: =+JI86-JK86 -> 179280
FJ87: 703496.94 | JI87: =SUM(A87:JH87) -> 703496.94 | JJ87: 974 | JL87: =+JI87-JK87 -> 703496.94
FT88: 176528 | JI88: =SUM(A88:JH88) -> 176528 | JJ88: 978 | JL88: =+JI88-JK88 -> 176528
FT89: 201500 | JI89: =SUM(A89:JH89) -> 201500 | JJ89: 982 | JL89: =+JI89-JK89 -> 201500
EA90: 169632 | JI90: =SUM(A90:JH90) -> 169632 | JJ90: 989 | JL90: =+JI90-JK90 -> 169632
EA91: 243000 | JI91: =SUM(A91:JH91) -> 243000 | JJ91: 993 | JL91: =+JI91-JK91 -> 243000
GQ92: 264013.2 | JI92: =SUM(A92:JH92) -> 264013.2 | JJ92: 997 | JL92: =+JI92-JK92 -> 264013.2
FT93: 230320 | JI93: =SUM(A93:JH93) -> 230320 | JJ93: 1001 | JL93: =+JI93-JK93 -> 230320
FT94: 140656 | JI94: =SUM(A94:JH94) -> 140656 | JJ94: 1005 | JL94: =+JI94-JK94 -> 140656
FQ95: 209296.6 | JI95: =SUM(A95:JH95) -> 209296.6 | JJ95: 1009 | JL95: =+JI95-JK95 -> 209296.6
FT96: 247800 | JI96: =SUM(A96:JH96) -> 247800 | JJ96: 1013 | JL96: =+JI96-JK96 -> 247800
FT97: 542800 | JI97: =SUM(A97:JH97) -> 542800 | JJ97: 1017 | JL97: =+JI97-JK97 -> 542800
FT98: 188847.2 | JI98: =SUM(A98:JH98) -> 188847.2 | JJ98: 1021 | JL98: =+JI98-JK98 -> 188847.2
EA99: 271700 | JI99: =SUM(A99:JH99) -> 271700 | JJ99: 1025 | JL99: =+JI99-JK99 -> 271700
EA100: 97500 | JI100: =SUM(A100:JH100) -> 97500 | JJ100: 1029 | JL100: =+JI100-JK100 -> 97500
...

Sheet CUENTA T VS
A1: D E S G L O S E D E L A S C U E N T A S
A2: 211101 | B2: 211102 | C2: 211103 | D2: 211104 | E2: 211105 | F2: 211106 | G2: 211203 | H2: 211205 | I2: 211206 | J2: 211208 | K2: 211209 | L2: 211211 | M2: 211301 | N2: 211401 | O2: 211501 | P2: 211502 | Q2: 211503 | R2: 211504 | S2: 212101 | T2: 212201 | U2: 212203 | V2: 212204 | W2: 212205 | X2: 212206 | Y2: 212207 | Z2: 212208 | AA2: 212209 | AB2: 212210 | AC2: 213101 | AD2: 213102 | AE2: 213201 | AF2: 213202 | AG2: 214101 | AH2: 214201 | AI2: 214202 | AJ2: 214203 | AK2: 215101 | AL2: 215201 | AM2: 215301 | AN2: 215401 | AO2: 221101 | AP2: 221201 | AQ2: 221301 | AR2: 221401 | AS2: 221501 | AT2: 221601 | AU2: 221602 | AV2: 221701 | AW2: 221801 | AX2: 222101 | AY2: 222201 | AZ2: 223101 | BA2: 223201 | BB2: 224101 | BC2: 224201 | BD2: 224301 | BE2: 224401 | BF2: 225101 | BG2: 225201 | BH2: 225301 | BI2: 225302 | BJ2: 225303 | BK2: 225304 | BL2: 225305 | BM2: 225401 | BN2: 225501 | BO2: 225601 | BP2: 225701 | BQ2: 225801 | BR2: 225901 | BS2: 226101 | BT2: 226201 | BU2: 226301 | BV2: 226401 | BW2: 227101 | BX2: 227102 | BY2: 227103 | BZ2: 227104 | CA2: 227105 | CB2: 227106 | CC2: 227107 | CD2: 227199 | CE2: 227201 | CF2: 227202 | CG2: 227203 | CH2: 227204 | CI2: 227205 | CJ2: 227206 | CK2: 227207 | CL2: 227208 | CM2: 227299 | CN2: 227301 | CO2: 228101 | CP2: 228201 | CQ2: 228301 | CR2: 228401 | CS2: 228501 | CT2: 228502 | CU2: 228503 | CV2: 228601 | CW2: 228602 | CX2: 228603 | CY2: 228604 | CZ2: 228701 | DA2: 228702 | DB2: 228703 | DC2: 228704 | DD2: 228705 | DE2: 228706 | DF2: 228801 | DG2: 228802 | DH2: 228803 | DI2: 229201 | DJ2: 229203 | DK2: 231101 | DL2: 231102 | DM2: 231201 | DN2: 231301 | DO2: 231302 | DP2: 231303 | DQ2: 231401 | DR2: 232101 | DS2: 232201 | DT2: 232301 | DU2: 233101 | DV2: 233201 | DW2: 233301 | DX2: 233401 | DY2: 233501 | DZ2: 233601 | EA2: 234101 | EB2: 234201 | EC2: 235101 | ED2: 235201 | EE2: 235301 | EF2: 235401 | EG2: 235501 | EH2: 236101 | EI2: 236102 | EJ2: 236103 | EK2: 236104 | EL2: 236105 | EM2: 236201 | EN2: 236202 | EO2: 236203 | EP2: 236304 | EQ2: 236305 | ER2: 236306 | ES2: 236401 | ET2: 236402 | EU2: 236403 | EV2: 236404 | EW2: 236405 | EX2: 236406 | EY2: 236407 | EZ2: 236901 | FA2: 237101 | FB2: 237102 | FC2: 237103 | FD2: 237104 | FE2: 237105 | FF2: 237106 | FG2: 237107 | FH2: 237201 | FI2: 237202 | FJ2: 237203 | FK2: 237204 | FL2: 237205 | FM2: 237206 | FN2: 237299 | FO2: 238101 | FP2: 238201 | FQ2: 239101 | FR2: 239102 | FS2: 239201 | FT2: 239301 | FU2: 239401 | FV2: 239501 | FW2: 239601 | FX2: 239701 | FY2: 239801 | FZ2: 239802 | GA2: 239901 | GB2: 239904 | GC2: 241201 | GD2: 241202 | GE2: 241203 | GF2: 241204 | GG2: 241205 | GH2: 261101 | GI2: 261201 | GJ2: 261301 | GK2: 261401 | GL2: 261901 | GM2: 262101 | GN2: 262201 | GO2: 262301 | GP2: 262401 | GQ2: 263101 | GR2: 263201 | GS2: 263301 | GT2: 263401 | GU2: 264101 | GV2: 264201 | GW2: 264301 | GX2: 264401 | GY2: 264501 | GZ2: 264601 | HA2: 264701 | HB2: 264801 | HC2: 265101 | HD2: 265201 | HE2: 265301 | HF2: 265401 | HG2: 265501 | HH2: 265601 | HI2: 265701 | HJ2: 265801 | HK2: 266101 | HL2: 266201 | HM2: 267101 | HN2: 267201 | HO2: 267301 | HP2: 267401 | HQ2: 267501 | HR2: 267601 | HS2: 267701 | HT2: 267801 | HU2: 267901 | HV2: 268101 | HW2: 268201 | HX2: 268301 | HY2: 268302 | HZ2: 268401 | IA2: 268501 | IB2: 268601 | IC2: 268701 | ID2: 268802 | IE2: 268803 | IF2: 268804 | IG2: 268901 | IH2: 269101 | II2: 269102 | IJ2: 269201 | IK2: 269202 | IL2: 269301 | IM2: 269401 | IN2: 269501 | IO2: 269502 | IP2: 269503 | IQ2: 2269901 | IR2: 271101 | IS2: 271201 | IT2: 271301 | IU2: 271401 | IV2: 272101 | IW2: 272201 | IX2: 272301 | IY2: 272401 | IZ2: 272501 | JA2: 272601 | JB2: 272701 | JC2: 272801 | JD2: 272901 | JE2: 273101 | JF2: 273201 | JG2: 274101 | JH2: 274201 | JI2: Totales | JJ2: TRANSF NO. | JK2: VALOR | JL2: RETENCION | JM2: AÑOS ANTERIORES | JN2: 2022 | JO2: Total | JP2: Proveedor Informal
AW3: 760000 | JI3: =SUM(A3:JH3) -> 760000 | JJ3: 58 | JK3: 722000 | JL3: =+JI3-JK3 -> 38000
HF4: 192930 | JI4: =SUM(A4:JH4) -> 192930 | JJ4: 59 | JK4: 184755 | JL4: =+JI4-JK4 -> 8175
DD5: 48852 | JI5: =SUM(A5:JH5) -> 48852 | JJ5: 60 | JK5: 46782 | JL5: =+JI5-JK5 -> 2070
CU6: 188564 | JI6: =SUM(A6:JH6) -> 188564 | JJ6: 61 | JK6: 180574 | JL6: =+JI6-JK6 -> 7990
FN7: 42000 | JI7: =SUM(A7:JH7) -> 42000 | JJ7: 62 | JK7: 39900 | JL7: =+JI7-JK7 -> 2100
FA8: 172000 | JI8: =SUM(A8:JH8) -> 172000 | JJ8: 63 | JK8: 170573.26 | JL8: =+JI8-JK8 -> 1426.74
FD9: 55029 | JI9: =SUM(A9:JH9) -> 55029 | JJ9: 64 | JK9: 55029 | JL9: =+JI9-JK9 -> 0
EG10: 15340.03 | EP10: 16250 | ER10: 7825 | FN10: 1889.99 | JI10: =SUM(A10:JH10) -> 41305.02 | JJ10: 65 | JK10: 39555.02 | JL10: =+JI10-JK10 -> 1750
FT11: 34220 | JI11: =SUM(A11:JH11) -> 34220 | JJ11: 66 | JK11: 32770 | JL11: =+JI11-JK11 -> 1450
DK12: 473584 | JI12: =SUM(A12:JH12) -> 473584 | JJ12: 67 | JK12: 451814 | JL12: =+JI12-JK12 -> 21770
CJ13: 0 | EA13: 61500 | JI13: =SUM(A13:JH13) -> 61500 | JJ13: 68 | JK13: 58425 | JL13: =+JI13-JK13 -> 3075
CJ14: 636067.2 | JI14: =SUM(A14:JH14) -> 636067.2 | JJ14: 69 | JK14: 609115.2 | JL14: =+JI14-JK14 -> 26952
AQ15: 211191.19 | JI15: =SUM(A15:JH15) -> 211191.19 | JJ15: 70 | JK15: 211191.19 | JL15: =+JI15-JK15 -> 0
DK16: 36420 | JI16: =SUM(A16:JH16) -> 36420 | JJ16: 71 | JK16: 36420 | JL16: =+JI16-JK16 -> 0
EA17: 188500 | JI17: =SUM(A17:JH17) -> 188500 | JJ17: 72 | JK17: 179075 | JL17: =+JI17-JK17 -> 9425
DE18: 2150 | JI18: =SUM(A18:JH18) -> 2150 | JJ18: 73 | JK18: 2042.5 | JL18: =+JI18-JK18 -> 107.5
FD19: 23868 | JI19: =SUM(A19:JH19) -> 23868 | JJ19: 74 | JK19: 23868 | JL19: =+JI19-JK19 -> 0
DK20: 85575 | JI20: =SUM(A20:JH20) -> 85575 | JJ20: 75 | JK20: 81296.25 | JL20: =+JI20-JK20 -> 4278.75
EE21: 282823.65 | JI21: =SUM(A21:JH21) -> 282823.65 | JJ21: 76 | JK21: 270839.6 | JL21: =+JI21-JK21 -> 11984.05
DK22: 14000 | JI22: =SUM(A22:JH22) -> 14000 | JJ22: 77 | JK22: 14000 | JL22: =+JI22-JK22 -> 0
GZ23: 107609.37 | JI23: =SUM(A23:JH23) -> 107609.37 | JJ23: 78 | JK23: 103049.65 | JL23: =+JI23-JK23 -> 4559.72
DE24: 20000 | JI24: =SUM(A24:JH24) -> 20000 | JJ24: 79 | JK24: 20000 | JL24: =+JI24-JK24 -> 0
DW25: 26845 | JI25: =SUM(A25:JH25) -> 26845 | JJ25: 80 | JK25: 25707.5 | JL25: =+JI25-JK25 -> 1137.5
BC26: 8000 | JI26: =SUM(A26:JH26) -> 8000 | JJ26: 81 | JK26: 7600 | JL26: =+JI26-JK26 -> 400
DE27: 225000 | JI27: =SUM(A27:JH27) -> 225000 | JJ27: 82 | JK27: 213750 | JL27: =+JI27-JK27 -> 11250
DE28: 83800 | JI28: =SUM(A28:JH28) -> 83800 | JJ28: =+JJ27+1 -> 83 | JK28: 79610 | JL28: =+JI28-JK28 -> 4190
DW29: 31152 | JI29: =SUM(A29:JH29) -> 31152 | JJ29: =+JJ28+1 -> 84 | JK29: 29832 | JL29: =+JI29-JK29 -> 1320
FD30: 22542 | JI30: =SUM(A30:JH30) -> 22542 | JJ30: =+JJ29+1 -> 85 | JK30: 22542 | JL30: =+JI30-JK30 -> 0
BC31: 24000 | JI31: =SUM(A31:JH31) -> 24000 | JJ31: =+JJ30+1 -> 86 | JK31: 22800 | JL31: =+JI31-JK31 -> 1200
EG32: 19499.99 | EM32: 15149.94 | EP32: 71000.03 | JI32: =SUM(A32:JH32) -> 105649.96 | JJ32: =+JJ31+1 -> 87 | JK32: 101173.27 | JL32: =+JI32-JK32 -> 4476.69
GD33: 40000 | JI33: =SUM(A33:JH33) -> 40000 | JJ33: =+JJ32+1 -> 88 | JK33: 40000 | JL33: =+JI33-JK33 -> 0
DK34: 14000 | JI34: =SUM(A34:JH34) -> 14000 | JJ34: =+JJ33+1 -> 89 | JK34: 14000 | JL34: =+JI34-JK34 -> 0
DK35: 11640 | JI35: =SUM(A35:JH35) -> 11640 | JJ35: =+JJ34+1 -> 90 | JK35: 11640 | JL35: =+JI35-JK35 -> 0
DK36: 23580 | JI36: =SUM(A36:JH36) -> 23580 | JJ36: =+JJ35+1 -> 91 | JK36: 23580 | JL36: =+JI36-JK36 -> 0
BW37: 272580 | JI37: =SUM(A37:JH37) -> 272580 | JJ37: =+JJ36+1 -> 92 | JK37: 261030 | JL37: =+JI37-JK37 -> 11550
CL38: 248711.41 | JI38: =SUM(A38:JH38) -> 248711.41 | JJ38: =+JJ37+1 -> 93 | JK38: 238172.79 | JL38: =+JI38-JK38 -> 10538.62
BW39: 271800.26 | JI39: =SUM(A39:JH39) -> 271800.26 | JJ39: =+JJ38+1 -> 94 | JK39: 260283.3 | JL39: =+JI39-JK39 -> 11516.96
CL40: 230085.84 | JI40: =SUM(A40:JH40) -> 230085.84 | JJ40: =+JJ39+1 -> 95 | JK40: 220336.44 | JL40: =+JI40-JK40 -> 9749.4
BW41: 272432.5 | JI41: =SUM(A41:JH41) -> 272432.5 | JJ41: =+JJ40+1 -> 96 | JK41: 260888.75 | JL41: =+JI41-JK41 -> 11543.75
AW42: 760000 | JI42: =SUM(A42:JH42) -> 760000 | JJ42: =+JJ41+1 -> 97 | JK42: 722000 | JL42: =+JI42-JK42 -> 38000
X43: 5231553.6 | JI43: =SUM(A43:JH43) -> 5231553.6 | JJ43: =+JJ42+1 -> 98 | JK43: 5231553.6 | JL43: =+JI43-JK43 -> 0
JI44: =SUM(A44:JH44) -> 0 | JJ44: 37197 | JL44: =+JI44-JK44 -> 0
GD45: 26000 | JI45: =SUM(A45:JH45) -> 26000 | JJ45: 37198 | JK45: 26000 | JL45: =+JI45-JK45 -> 0
GD46: 14000 | JI46: =SUM(A46:JH46) -> 14000 | JJ46: 37199 | JK46: 14000 | JL46: =+JI46-JK46 -> 0
BW47: 30102.04 | JI47: =SUM(A47:JH47) -> 30102.04 | JJ47: 37200 | JK47: 30102.04 | JL47: =+JI47-JK47 -> 0
GD48: 10000 | JI48: =SUM(A48:JH48) -> 10000 | JJ48: 37201 | JK48: 10000 | JL48: =+JI48-JK48 -> 0
JI49: =SUM(A49:JH49) -> 0 | JJ49: 37202 | JL49: =+JI49-JK49 -> 0
GD50: 34020 | JI50: =SUM(A50:JH50) -> 34020 | JJ50: 37203 | JK50: 34020 | JL50: =+JI50-JK50 -> 0
GA51: 51304.69 | JI51: =SUM(A51:JH51) -> 51304.69 | JJ51: 37204 | JK51: 51304.69 | JL51: =+JI51-JK51 -> 0
BW52: 21673.47 | JI52: =SUM(A52:JH52) -> 21673.47 | JJ52: 37205 | JK52: 18000 | JL52: =+JI52-JK52 -> 3673.47
BW53: 18061.22 | JI53: =SUM(A53:JH53) -> 18061.22 | JJ53: 37206 | JK53: 15000 | JL53: =+JI53-JK53 -> 3061.22
BW54: 18061.22 | JI54: =SUM(A54:JH54) -> 18061.22 | JJ54: 37207 | JK54: 15000 | JL54: =+JI54-JK54 -> 3061.22
GD55: 3400 | JI55: =SUM(A55:JH55) -> 3400 | JJ55: 37208 | JK55: 3400 | JL55: =+JI55-JK55 -> 0
CP56: 8323.87 | JI56: =SUM(A56:JH56) -> 8323.87 | JL56: =+JI56-JK56 -> 8323.87
JI57: =SUM(A57:JH57) -> 0 | JL57: =+JI57-JK57 -> 0
JI58: =SUM(A58:JH58) -> 0 | JL58: =+JI58-JK58 -> 0
JI59: =SUM(A59:JH59) -> 0 | JL59: =+JI59-JK59 -> 0
JI60: =SUM(A60:JH60) -> 0 | JL60: =+JI60-JK60 -> 0
JI61: =SUM(A61:JH61) -> 0 | JL61: =+JI61-JK61 -> 0
JI62: =SUM(A62:JH62) -> 0 | JL62: =+JI62-JK62 -> 0
JI63: =SUM(A63:JH63) -> 0 | JL63: =+JI63-JK63 -> 0
JI64: =SUM(A64:JH64) -> 0 | JL64: =+JI64-JK64 -> 0
JI65: =SUM(A65:JH65) -> 0 | JL65: =+JI65-JK65 -> 0
JI66: =SUM(A66:JH66) -> 0 | JL66: =+JI66-JK66 -> 0
JI67: =SUM(A67:JH67) -> 0 | JL67: =+JI67-JK67 -> 0
JI68: =SUM(A68:JH68) -> 0 | JL68: =+JI68-JK68 -> 0
... JI78: =SUM(A78:JH78) -> 0 | JL78: =+JI78-JK78 -> 0
A79: =SUM(A3:A78) -> 0 | B79: =SUM(B3:B78) -> 0 | C79: =SUM(C3:C78) -> 0 | D79: =SUM(D3:D78) -> 0 | E79: =SUM(E3:E78) -> 0 | F79: =SUM(F3:F78) -> 0 | G79: =SUM(G3:G78) -> 0 | H79: =SUM(H3:H78) -> 0 | ... JI79: =SUM(JI3:JI78) -> 11816507 | JK79: =SUM(JK3:JK78) -> 11536401 | JL79: =SUM(JL3:JL78) -> 280106.46 | JM79: =SUM(JM3:JM78) -> 0 | JN79: =SUM(JN3:JN78) -> 0 | JO79: =SUM(JO3:JO78) -> 0 | JP79: =SUM(JP3:JP78) -> 0
A80: 211101 | B80: 211102 | C80: 211103 | D80: 211104 | E80: 211105 | F80: 211106 | G80: 211203 | H80: 211205 | I80: 211206 | J80: 211208 | K80: 211209 | L80: 211211 | M80: 211301 | N80: 211401 | O80: 211501 | P80: 211502 | Q80: 211503 | R80: 211504 | S80: 212101 | T80: 212201 | U80: 212203 | V80: 212204 | W80: 212205 | X80: 212206 | Y80: 212207 | Z80: 212208 | AA80: 212209 | AB80: 212210 | AC80: 213101 | AD80: 213102 | AE80: 213201 | AF80: 213202 | AG80: 214101 | AH80: 214201 | AI80: 214202 | AJ80: 214203 | AK80: 215101 | AL80: 215201 | AM80: 215301 | AN80: 215401 | AO80: 221101 | AP80: 221201 | AQ80: 221301 | AR80: 221401 | AS80: 221501 | AT80: 221601 | AU80: 221602 | AV80: 221701 | AW80: 221801 | AX80: 222101 | AY80: 222201 | AZ80: 223101 | BA80: 223201 | BB80: 224101 | BC80: 224201 | BD80: 224301 | BE80: 224401 | BF80: 225101 | BG80: 225201 | BH80: 225301 | BI80: 225302 | BJ80: 225303 | BK80: 225304 | BL80: 225305 | BM80: 225401 | BN80: 225501 | BO80: 225601 | BP80: 225701 | BQ80: 225801 | BR80: 225901 | BS80: 226101 | BT80: 226201 | BU80: 226301 | BV80: 226401 | BW80: 227101 | BX80: 227102 | BY80: 227103 | BZ80: 227104 | CA80: 227105 | CB80: 227106 | CC80: 227107 | CD80: 227199 | CE80: 227201 | CF80: 227202 | CG80: 227203 | CH80: 227204 | CI80: 227205 | CJ80: 227206 | CK80: 227207 | CL80: 227208 | CM80: 227299 | CN80: 227301 | CO80: 228101 | CP80: 228201 | CQ80: 228301 | CR80: 228401 | CS80: 228501 | CT80: 228502 | CU80: 228503 | CV80: 228601 | CW80: 228602 | CX80: 228603 | CY80: 228604 | CZ80: 228701 | DA80: 228702 | DB80: 228703 | DC80: 228704 | DD80: 228705 | DE80: 228706 | DF80: 228801 | DG80: 228802 | DH80: 228803 | DI80: 229201 | DJ80: 229203 | DK80: 231101 | DL80: 231102 | DM80: 231201 | DN80: 231301 | DO80: 231302 | DP80: 231303 | DQ80: 231401 | DR80: 232101 | DS80: 232201 | DT80: 232301 | DU80: 233101 | DV80: 233201 | DW80: 233301 | DX80: 233401 | DY80: 233501 | DZ80: 233601 | EA80: 234101 | EB80: 234201 | EC80: 235101 | ED80: 235201 | EE80: 235301 | EF80: 235401 | EG80: 235501 | EH80: 236101 | EI80: 236102 | EJ80: 236103 | EK80: 236104 | EL80: 236105 | EM80: 236201 | EN80: 236202 | EO80: 236203 | EP80: 236304 | EQ80: 236305 | ER80: 236306 | ES80: 236401 | ET80: 236402 | EU80: 236403 | EV80: 236404 | EW80: 236405 | EX80: 236406 | EY80: 236407 | EZ80: 236901 | FA80: 237101 | FB80: 237102 | FC80: 237103 | FD80: 237104 | FE80: 237105 | FF80: 237106 | FG80: 237107 | FH80: 237201 | FI80: 237202 | FJ80: 237203 | FK80: 237204 | FL80: 237205 | FM80: 237206 | FN80: 237299 | FO80: 238101 | FP80: 238201 | FQ80: 239101 | FR80: 239102 | FS80: 239201 | FT80: 239301 | FU80: 239401 | FV80: 239501 | FW80: 239601 | FX80: 239701 | FY80: 239801 | FZ80: 239802 | GA80: 239901 | GB80: 239904 | GC80: 241201 | GD80: 241202 | GE80: 241203 | GF80: 241204 | GG80: 241205 | GH80: 261101 | GI80: 261201 | GJ80: 261301 | GK80: 261401 | GL80: 261901 | GM80: 262101 | GN80: 262201 | GO80: 262301 | GP80: 262401 | GQ80: 263101 | GR80: 263201 | GS80: 263301 | GT80: 263401 | GU80: 264101 | GV80: 264201 | GW80: 264301 | GX80: 264401 | GY80: 264501 | GZ80: 264601 | HA80: 264701 | HB80: 264801 | HC80: 265101 | HD80: 265201 | HE80: 265301 | HF80: 265401 | HG80: 265501 | HH80: 265601 | HI80: 265701 | HJ80: 265801 | HK80: 266101 | HL80: 266201 | HM80: 267101 | HN80: 267201 | HO80: 267301 | HP80: 267401 | HQ80: 267501 | HR80: 267601 | HS80: 267701 | HT80: 267801 | HU80: 267901 | HV80: 268101 | HW80: 268201 | HX80: 268301 | HY80: 268302 | HZ80: 268401 | IA80: 268501 | IB80: 268601 | IC80: 268701 | ID80: 268802 | IE80: 268803 | IF80: 268804 | IG80: 268901 | IH80: 269101 | II80: 269102 | IJ80: 269201 | IK80: 269202 | IL80: 269301 | IM80: 269401 | IN80: 269501 | IO80: 269502 | IP80: 269503 | IQ80: 2269901 | IR80: 271101 | IS80: 271201 | IT80: 271301 | IU80: 271401 | IV80: 272101 | IW80: 272201 | IX80: 272301 | IY80: 272401 | IZ80: 272501 | JA80: 272601 | JB80: 272701 | JC80: 272801 | JD80: 272901 | JE80: 273101 | JF80: 273201 | JG80: 274101 | JH80: 274201 | JI80: Totales
JI81: =SUM(A81:JH81) -> 0
JI82: =SUM(A82:JH82) -> 0
JI83: =SUM(A83:JH83) -> 0
JI84: =SUM(A84:JH84) -> 0
JI85: =SUM(A85:JH85) -> 0
JI86: =SUM(A86:JH86) -> 0
JI87: =SUM(A87:JH87) -> 0
JI88: =SUM(A88:JH88) -> 0
JI89: =SUM(A89:JH89) -> 0
JI90: =SUM(A90:JH90) -> 0
JI91: =SUM(A91:JH91) -> 0
JI92: =SUM(A92:JH92) -> 0
... JI94: =SUM(A94:JH94) -> 0
A95: =SUM(A81:A94) -> 0 | B95: =SUM(B81:B94) -> 0 | C95: =SUM(C81:C94) -> 0 | D95: =SUM(D81:D94) -> 0 | E95: =SUM(E81:E94) -> 0 | F95: =SUM(F81:F94) -> 0 | G95: =SUM(G81:G94) -> 0 | H95: =SUM(H81:H94) -> 0 | ... JI95: =SUM(JI81:JI94) -> 0
A96: =A79+A95 -> 0 | B96: =B79+B95 -> 0 | C96: =C79+C95 -> 0 | D96: =D79+D95 -> 0 | E96: =E79+E95 -> 0 | F96: =F79+F95 -> 0 | G96: =G79+G95 -> 0 | H96: =H79+H95 -> 0 | ... JI96: =JI79+JI95 -> 11816507

Sheet GASTOS X ATENCION
A1: SERVICIO NACIONAL DE SALUD
A2: ='CONS. FUENTES FINAN'!A6 -> HOSPITAL MATERNO INFANTIL SAN LORENZO DE LOS MINA
A3: RESUMEN COMPARATIVO DE GASTOS ESPECIFICOS FONDO 100 Y VENTA DE SERVICIOS
A6: DETALLE | B6: FONDO 100 | C6: VENTA SERVICIOS | D6: TOTAL | E6: %
A8: Atención Directa
A9: Medicamentos e Insumos Médicos | B9: ='CONS. FUENTES FINAN'!G245+'CONS. FUENTES FINAN'!G315 -> 17715524 | C9: ='CONS. FUENTES FINAN'!H245+'CONS. FUENTES FINAN'!H315 -> 284220 | D9: =SUM(B9:C9) -> 17999744 | E9: =+D9/D12 -> 0.8803263
A10: Oxigeno | B10: ='CONS. FUENTES FINAN'!G302 -> 159269.28 | C10: ='CONS. FUENTES FINAN'!H302 -> 43889.99 | D10: =SUM(B10:C10) -> 203159.27 | E10: =+D10/D12 -> 0.0099360548
A11: Reactivos e Insumos de Laboratorio | B11: ='CONS. FUENTES FINAN'!G296+'CONS. FUENTES FINAN'!G297+'CONS. FUENTES FINAN'!G298 -> 2243769.9 | C11: ='CONS. FUENTES FINAN'!H296+'CONS. FUENTES FINAN'!H297+'CONS. FUENTES FINAN'!H298 -> 0 | D11: =SUM(B11:C11) -> 2243769.9 | E11: =+D11/D12 -> 0.10973765
A12: Total | B12: =SUM(B9:B11) -> 20118564 | C12: =SUM(C9:C11) -> 328109.99 | D12: =SUM(D9:D11) -> 20446674 | E12: =+D12/D39 -> 0.16453172
A13: Mantenimiento de Equipos
A14: Reparación y Mantenimiento Maquinaria y Eq. | B14: ='CONS. FUENTES FINAN'!G157+'CONS. FUENTES FINAN'!G188+'CONS. FUENTES FINAN'!G223+'CONS. FUENTES FINAN'!G252+'CONS. FUENTES FINAN'!G254+'CONS. FUENTES FINAN'!G256+'CONS. FUENTES FINAN'!G258+'CONS. FUENTES FINAN'!G261+'CONS. FUENTES FINAN'!G292+'CONS. FUENTES FINAN'!G293+'CONS. FUENTES FINAN'!G299+'CONS. FUENTES FINAN'!G300+'CONS. FUENTES FINAN'!G301+'CONS. FUENTES FINAN'!G324 -> 6178626.8 | C14: ='CONS. FUENTES FINAN'!H157+'CONS. FUENTES FINAN'!H188+'CONS. FUENTES FINAN'!H223+'CONS. FUENTES FINAN'!H252+'CONS. FUENTES FINAN'!H254+'CONS. FUENTES FINAN'!H256+'CONS. FUENTES FINAN'!H258+'CONS. FUENTES FINAN'!H261+'CONS. FUENTES FINAN'!H292+'CONS. FUENTES FINAN'!H293+'CONS. FUENTES FINAN'!H299+'CONS. FUENTES FINAN'!H300+'CONS. FUENTES FINAN'!H301+'CONS. FUENTES FINAN'!H324 -> 2601187.8 | D14: =SUM(B14:C14) -> 8779814.6 | E14: =+D14/D16 -> 0.95762161
A15: Productos Eléctricos y Afines | B15: ='CONS. FUENTES FINAN'!G320 -> 388540.1 | C15: ='CONS. FUENTES FINAN'!H320 -> 0 | D15: =SUM(B15:C15) -> 388540.1 | E15: =+D15/D16 -> 0.042378389
A16: Total | B16: =SUM(B14:B15) -> 6567166.9 | C16: =SUM(C14:C15) -> 2601187.8 | D16: =SUM(D14:D15) -> 9168354.7 | E16: =+D16/D39 -> 0.073776556
A17: Gastos Administrativos
A18: Servicios Personales | B18: ='CONS. FUENTES FINAN'!G26 -> 66337620 | C18: ='CONS. FUENTES FINAN'!H26 -> 5231553.6 | D18: =SUM(B18:C18) -> 71569173 | E18: =+D18/D34 -> 0.86270008
A19: Servicio Telefónico | B19: ='CONS. FUENTES FINAN'!G91+'CONS. FUENTES FINAN'!G93+'CONS. FUENTES FINAN'!G95+'CONS. FUENTES FINAN'!G97 -> 0 | C19: ='CONS. FUENTES FINAN'!H91+'CONS. FUENTES FINAN'!H93+'CONS. FUENTES FINAN'!H95+'CONS. FUENTES FINAN'!H97 -> 211191.19 | D19: =SUM(B19:C19) -> 211191.19 | E19: =+D19/D34 -> 0.0025457141
A20: Servicios Basicos (electricidad, agua y residuos solidos) | B20: ='CONS. FUENTES FINAN'!G99+'CONS. FUENTES FINAN'!G102+'CONS. FUENTES FINAN'!G104 -> 2020024.3 | C20: ='CONS. FUENTES FINAN'!H99+'CONS. FUENTES FINAN'!H102+'CONS. FUENTES FINAN'!H104 -> 1520000 | D20: =SUM(B20:C20) -> 3540024.3 | E20: =+D20/D34 -> 0.042671713
A21: Viáticos | B21: ='CONS. FUENTES FINAN'!G111 -> 0 | C21: ='CONS. FUENTES FINAN'!H111 -> 0 | D21: =SUM(B21:C21) -> 0 | E21: =+D21/D34 -> 0
A22: Transporte y almacenaje | B22: ='CONS. FUENTES FINAN'!G116 -> 0 | C22: ='CONS. FUENTES FINAN'!H116 -> 32000 | D22: =SUM(B22:C22) -> 32000 | E22: =+D22/D34 -> 0.00038573035
A23: Alquileres | B23: ='CONS. FUENTES FINAN'!G125 -> 0 | C23: ='CONS. FUENTES FINAN'!H125 -> 0 | D23: =SUM(B23:C23) -> 0 | E23: =+D23/D34 -> 0
A24: Comisiones y Gastos Bancarios | B24: ='CONS. FUENTES FINAN'!G182 -> 0 | C24: ='CONS. FUENTES FINAN'!H182 -> 8323.87 | D24: =SUM(B24:C24) -> 8323.87 | E24: =+D24/D34 -> 0.00010033654
A25: Materiales de Oficina, Impresión y Encuadernación | B25: ='CONS. FUENTES FINAN'!G109+'CONS. FUENTES FINAN'!G312 -> 132475.4 | C25: ='CONS. FUENTES FINAN'!H109+'CONS. FUENTES FINAN'!H312 -> 0 | D25: =SUM(B25:C25) -> 132475.4 | E25: =+D25/D34 -> 0.0015968682
A26: Alimentos y Bebidas para Personas | B26: ='CONS. FUENTES FINAN'!G208+'CONS. FUENTES FINAN'!G214+'CONS. FUENTES FINAN'!G217+'CONS. FUENTES FINAN'!G219 -> 3122436.8 | C26: ='CONS. FUENTES FINAN'!H208+'CONS. FUENTES FINAN'!H214+'CONS. FUENTES FINAN'!H217+'CONS. FUENTES FINAN'!H219 -> 658799 | D26: =SUM(B26:C26) -> 3781235.8 | E26: =+D26/D34 -> 0.045579295
A27: Productos de papel, carton e impesos | B27: ='CONS. FUENTES FINAN'!G232 -> 1474545.2 | C27: ='CONS. FUENTES FINAN'!H232 -> 57997 | D27: =SUM(B27:C27) -> 1532542.2 | E27: =+D27/D34 -> 0.018473376
A28: Articulos de Plasticos | B28: ='CONS. FUENTES FINAN'!G259 -> 334708.95 | C28: ='CONS. FUENTES FINAN'!H259 -> 34840.02 | D28: =SUM(B28:C28) -> 369548.97 | E28: =+D28/D34 -> 0.0044545704
A29: Gasolina | B29: ='CONS. FUENTES FINAN'!G288 -> 555829 | C29: ='CONS. FUENTES FINAN'!H288 -> 172000 | D29: =SUM(B29:C29) -> 727829 | E29: =+D29/D34 -> 0.0087733043
A30: Gasoil | B30: ='CONS. FUENTES FINAN'!G289+'CONS. FUENTES FINAN'!G290 -> 0 | C30: ='CONS. FUENTES FINAN'!H289+'CONS. FUENTES FINAN'!H290 -> 0 | D30: =SUM(B30:C30) -> 0 | E30: =+D30/D34 -> 0
A31: GLP | B31: ='CONS. FUENTES FINAN'!G291+'CONS. FUENTES FINAN'!G294 -> 0 | C31: ='CONS. FUENTES FINAN'!H291+'CONS. FUENTES FINAN'!H294 -> 101439 | D31: =SUM(B31:C31) -> 101439 | E31: =+D31/D34 -> 0.0012227532
A32: Materiales de Limpieza e Higiene | B32: ='CONS. FUENTES FINAN'!G309 -> 369511.66 | C32: ='CONS. FUENTES FINAN'!H309 -> 0 | D32: =SUM(B32:C32) -> 369511.66 | E32: =+D32/D34 -> 0.0044541207
A33: Otros Egresos y Gastos | B33: ='CONS. FUENTES FINAN'!G89+'CONS. FUENTES FINAN'!G107+'CONS. FUENTES FINAN'!G148+'CONS. FUENTES FINAN'!G180+'CONS. FUENTES FINAN'!G184+'CONS. FUENTES FINAN'!G186+'CONS. FUENTES FINAN'!G192+'CONS. FUENTES FINAN'!G197+'CONS. FUENTES FINAN'!G204+'CONS. FUENTES FINAN'!G225+'CONS. FUENTES FINAN'!G303+'CONS. FUENTES FINAN'!G316+'CONS. FUENTES FINAN'!G318+'CONS. FUENTES FINAN'!G322+'CONS. FUENTES FINAN'!G327+'CONS. FUENTES FINAN'!G330 -> 25685.99 | C33: ='CONS. FUENTES FINAN'!H89+'CONS. FUENTES FINAN'!H107+'CONS. FUENTES FINAN'!H148+'CONS. FUENTES FINAN'!H180+'CONS. FUENTES FINAN'!H184+'CONS. FUENTES FINAN'!H186+'CONS. FUENTES FINAN'!H192+'CONS. FUENTES FINAN'!H197+'CONS. FUENTES FINAN'!H204+'CONS. FUENTES FINAN'!H225+'CONS. FUENTES FINAN'!H303+'CONS. FUENTES FINAN'!H316+'CONS. FUENTES FINAN'!H318+'CONS. FUENTES FINAN'!H322+'CONS. FUENTES FINAN'!H327+'CONS. FUENTES FINAN'!H330 -> 558526.69 | D33: =SUM(B33:C33) -> 584212.68 | E33: =+D33/D34 -> 0.0070421426
A34: Total | B34: =SUM(B17:B33) -> 74372837 | C34: =SUM(C17:C33) -> 8586670.4 | D34: =SUM(D17:D33) -> 82959507 | E34: =+D34/D39 -> 0.66756436
A35: Gastos Inversion y Capital
A36: Bienes Muebles, Inmuebles e Intangibles | B36: ='CONS. FUENTES FINAN'!G336 -> 11396849 | C36: ='CONS. FUENTES FINAN'!H336 -> 300539.37 | D36: =SUM(B36:C36) -> 11697389 | E36: =+D36/D38 -> 1
A37: Obras | B37: ='CONS. FUENTES FINAN'!G463 -> 0 | C37: ='CONS. FUENTES FINAN'!H463 -> 0 | D37: =SUM(B37:C37) -> 0 | E37: =+D37/D38 -> 0
A38: Total | B38: =SUM(B36:B37) -> 11396849 | C38: =SUM(C36:C37) -> 300539.37 | D38: =SUM(D36:D37) -> 11697389 | E38: =+D38/D39 -> 0.094127365
A39: Total General | B39: =+B12+B16+B34+B38 -> 1.1245542e+08 | C39: =+C12+C16+C34+C38 -> 11816507 | D39: =+D12+D16+D34+D38 -> 1.2427192e+08 | E39: =+E12+E16+E34+E38 -> 1
A40: Porciento | B40: =+B39/D39 -> 0.9049141 | C40: =+C39/D39 -> 0.095085898 | D40: =+B40+C40 -> 1

Sheet PLANTILLA PRESUPUESTO
A1: SERVICIO NACIONAL DE SALUD
A2: HOSPITAL MATERNO INFANTIL SAN LORENZO DE LOS MINA
A3: CONSOLIDADO GASTOS EJECUCION FINANCIERA 2025
A4: En RD$
A6: Detalle | B6: FONDO REPONIBLE | G6: VENTA SEVICIOS/OTROS APORTES | L6: TOTAL
A7: 2 - GASTOS | B7: 1ro | C7: 2do | D7: 3ro | E7: 4to | G7: 1ro | H7: 2do | I7: 3ro | J7: 4to | L7: 1ro | M7: 2do | N7: 3ro | O7: 4to
A8: 2.1 - REMUNERACIONES Y CONTRIBUCIONES | B8: =SUM(B9:B13) -> 1.9856074e+08 | C8: =SUM(C9:C13) -> 0 | D8: =SUM(D9:D13) -> 0 | E8: =SUM(E9:E13) -> 0 | G8: =SUM(G9:G13) -> 5231553.6 | H8: =SUM(H9:H13) -> 0 | I8: =SUM(I9:I13) -> 0 | J8: =SUM(J9:J13) -> 0 | L8: =SUM(B8+G8) -> 2.0379229e+08 | M8: =SUM(C8+H8) -> 0 | N8: =SUM(D8+I8) -> 0 | O8: =SUM(E8+J8) -> 0
A9: 2.1.1 - REMUNERACIONES | B9: =SUM('TRANSFERENCIA CORRIENTE'!C10:E10) -> 1.639452e+08 | C9: =SUM('TRANSFERENCIA CORRIENTE'!F10:H10) -> 0 | D9: =SUM('TRANSFERENCIA CORRIENTE'!I10:K10) -> 0 | E9: =SUM('TRANSFERENCIA CORRIENTE'!L10:N10) -> 0 | G9: =SUM(VS!C10:E10) -> 0 | H9: =SUM(VS!F10:H10) -> 0 | I9: =SUM(VS!I10:K10) -> 0 | J9: =SUM(VS!L10:N10) -> 0 | L9: =SUM(B9+G9) -> 1.639452e+08 | M9: =SUM(C9+H9) -> 0 | N9: =SUM(D9+I9) -> 0 | O9: =SUM(E9+J9) -> 0
A10: 2.1.2 - SOBRESUELDOS | B10: =SUM('TRANSFERENCIA CORRIENTE'!C11:E11) -> 9594398.8 | C10: =SUM('TRANSFERENCIA CORRIENTE'!F11:H11) -> 0 | D10: =SUM('TRANSFERENCIA CORRIENTE'!I11:K11) -> 0 | E10: =SUM('TRANSFERENCIA CORRIENTE'!L11:N11) -> 0 | G10: =SUM(VS!C11:E11) -> 5231553.6 | H10: =SUM(VS!F11:H11) -> 0 | I10: =SUM(VS!I11:K11) -> 0 | J10: =SUM(VS!L11:N11) -> 0 | L10: =SUM(B10+G10) -> 14825952 | M10: =SUM(C10+H10) -> 0 | N10: =SUM(D10+I10) -> 0 | O10: =SUM(E10+J10) -> 0
A11: 2.1.3 - DIETAS Y GASTOS DE REPRESENTACIÓN | B11: =SUM('TRANSFERENCIA CORRIENTE'!C12:E12) -> 0 | C11: =SUM('TRANSFERENCIA CORRIENTE'!F12:H12) -> 0 | D11: =SUM('TRANSFERENCIA CORRIENTE'!I12:K12) -> 0 | E11: =SUM('TRANSFERENCIA CORRIENTE'!L12:N12) -> 0 | G11: =SUM(VS!C12:E12) -> 0 | H11: =SUM(VS!F12:H12) -> 0 | I11: =SUM(VS!I12:K12) -> 0 | J11: =SUM(VS!L12:N12) -> 0 | L11: =SUM(B11+G11) -> 0 | M11: =SUM(C11+H11) -> 0 | N11: =SUM(D11+I11) -> 0 | O11: =SUM(E11+J11) -> 0
A12: 2.1.4 - GRATIFICACIONES Y BONIFICACIONES | B12: =SUM('TRANSFERENCIA CORRIENTE'!C13:E13) -> 0 | C12: =SUM('TRANSFERENCIA CORRIENTE'!F13:H13) -> 0 | D12: =SUM('TRANSFERENCIA CORRIENTE'!I13:K13) -> 0 | E12: =SUM('TRANSFERENCIA CORRIENTE'!L13:N13) -> 0 | G12: =SUM(VS!C13:E13) -> 0 | H12: =SUM(VS!F13:H13) -> 0 | I12: =SUM(VS!I13:K13) -> 0 | J12: =SUM(VS!L13:N13) -> 0 | L12: =SUM(B12+G12) -> 0 | M12: =SUM(C12+H12) -> 0 | N12: =SUM(D12+I12) -> 0 | O12: =SUM(E12+J12) -> 0
A13: 2.1.5 - CONTRIBUCIONES A LA SEGURIDAD SOCIAL | B13: =SUM('TRANSFERENCIA CORRIENTE'!C14:E14) -> 25021132 | C13: =SUM('TRANSFERENCIA CORRIENTE'!F14:H14) -> 0 | D13: =SUM('TRANSFERENCIA CORRIENTE'!I14:K14) -> 0 | E13: =SUM('TRANSFERENCIA CORRIENTE'!L14:N14) -> 0 | G13: =SUM(VS!C14:E14) -> 0 | H13: =SUM(VS!F14:H14) -> 0 | I13: =SUM(VS!I14:K14) -> 0 | J13: =SUM(VS!L14:N14) -> 0 | L13: =SUM(B13+G13) -> 25021132 | M13: =SUM(C13+H13) -> 0 | N13: =SUM(D13+I13) -> 0 | O13: =SUM(E13+J13) -> 0
A14: 2.2 - CONTRATACIÓN DE SERVICIOS | B14: =SUM(B15:B23) -> 9308364.9 | C14: =SUM(C15:C23) -> 0 | D14: =SUM(D15:D23) -> 0 | E14: =SUM(E15:E23) -> 0 | G14: =SUM(G15:G23) -> 8306683.8 | H14: =SUM(H15:H23) -> 0 | I14: =SUM(I15:I23) -> 0 | J14: =SUM(J15:J23) -> 0 | L14: =SUM(B14+G14) -> 17615049 | M14: =SUM(C14+H14) -> 0 | N14: =SUM(D14+I14) -> 0 | O14: =SUM(E14+J14) -> 0
A15: 2.2.1 - SERVICIOS BÁSICOS | B15: =SUM('TRANSFERENCIA CORRIENTE'!C16:E16) -> 2020024.3 | C15: =SUM('TRANSFERENCIA CORRIENTE'!F16:H16) -> 0 | D15: =SUM('TRANSFERENCIA CORRIENTE'!J16:L16) -> 0 | E15: =SUM('TRANSFERENCIA CORRIENTE'!L16:N16) -> 0 | G15: =SUM(VS!C16:E16) -> 2341561.9 | H15: =SUM(VS!F16:H16) -> 0 | I15: =SUM(VS!I16:K16) -> 0 | J15: =SUM(VS!L16:N16) -> 0 | L15: =SUM(B15+G15) -> 4361586.2 | M15: =SUM(C15+H15) -> 0 | N15: =SUM(D15+I15) -> 0 | O15: =SUM(E15+J15) -> 0
A16: 2.2.2 - PUBLICIDAD, IMPRESIÓN Y ENCUADERNACIÓN | B16: =SUM('TRANSFERENCIA CORRIENTE'!C17:E17) -> 324206.83 | C16: =SUM('TRANSFERENCIA CORRIENTE'!F17:H17) -> 0 | D16: =SUM('TRANSFERENCIA CORRIENTE'!J17:L17) -> 0 | E16: =SUM('TRANSFERENCIA CORRIENTE'!L17:N17) -> 0 | G16: =SUM(VS!C17:E17) -> 0 | H16: =SUM(VS!F17:H17) -> 0 | I16: =SUM(VS!I17:K17) -> 0 | J16: =SUM(VS!L17:N17) -> 0 | L16: =SUM(B16+G16) -> 324206.83 | M16: =SUM(C16+H16) -> 0 | N16: =SUM(D16+I16) -> 0 | O16: =SUM(E16+J16) -> 0
A17: 2.2.3 - VIÁTICOS | B17: =SUM('TRANSFERENCIA CORRIENTE'!C18:E18) -> 0 | C17: =SUM('TRANSFERENCIA CORRIENTE'!F18:H18) -> 0 | D17: =SUM('TRANSFERENCIA CORRIENTE'!J18:L18) -> 0 | E17: =SUM('TRANSFERENCIA CORRIENTE'!L18:N18) -> 0 | G17: =SUM(VS!C18:E18) -> 0 | H17: =SUM(VS!F18:H18) -> 0 | I17: =SUM(VS!I18:K18) -> 0 | J17: =SUM(VS!L18:N18) -> 0 | L17: =SUM(B17+G17) -> 0 | M17: =SUM(C17+H17) -> 0 | N17: =SUM(D17+I17) -> 0 | O17: =SUM(E17+J17) -> 0
A18: 2.2.4 - TRANSPORTE Y ALMACENAJE | B18: =SUM('TRANSFERENCIA CORRIENTE'!C19:E19) -> 0 | C18: =SUM('TRANSFERENCIA CORRIENTE'!F19:H19) -> 0 | D18: =SUM('TRANSFERENCIA CORRIENTE'!J19:L19) -> 0 | E18: =SUM('TRANSFERENCIA CORRIENTE'!L19:N19) -> 0 | G18: =SUM(VS!C19:E19) -> 56000 | H18: =SUM(VS!F19:H19) -> 0 | I18: =SUM(VS!I19:K19) -> 0 | J18: =SUM(VS!L19:N19) -> 0 | L18: =SUM(B18+G18) -> 56000 | M18: =SUM(C18+H18) -> 0 | N18: =SUM(D18+I18) -> 0 | O18: =SUM(E18+J18) -> 0
A19: 2.2.5 - ALQUILERES Y RENTAS | B19: =SUM('TRANSFERENCIA CORRIENTE'!C20:E20) -> 0 | C19: =SUM('TRANSFERENCIA CORRIENTE'!F20:H20) -> 0 | D19: =SUM('TRANSFERENCIA CORRIENTE'!J20:L20) -> 0 | E19: =SUM('TRANSFERENCIA CORRIENTE'!L20:N20) -> 0 | G19: =SUM(VS!C20:E20) -> 519625.15 | H19: =SUM(VS!F20:H20) -> 0 | I19: =SUM(VS!I20:K20) -> 0 | J19: =SUM(VS!L20:N20) -> 0 | L19: =SUM(B19+G19) -> 519625.15 | M19: =SUM(C19+H19) -> 0 | N19: =SUM(D19+I19) -> 0 | O19: =SUM(E19+J19) -> 0
A20: 2.2.6 - SEGUROS | B20: =SUM('TRANSFERENCIA CORRIENTE'!C21:E21) -> 0 | C20: =SUM('TRANSFERENCIA CORRIENTE'!F21:H21) -> 0 | D20: =SUM('TRANSFERENCIA CORRIENTE'!J21:L21) -> 0 | E20: =SUM('TRANSFERENCIA CORRIENTE'!L21:N21) -> 0 | G20: =SUM(VS!C21:E21) -> 0 | H20: =SUM(VS!F21:H21) -> 0 | I20: =SUM(VS!I21:K21) -> 0 | J20: =SUM(VS!L21:N21) -> 0 | L20: =SUM(B20+G20) -> 0 | M20: =SUM(C20+H20) -> 0 | N20: =SUM(D20+I20) -> 0 | O20: =SUM(E20+J20) -> 0
A21: 2.2.7 - SERVICIOS DE CONSERVACIÓN, REPARACIONES MENORES E INSTALACIONES TEMPORALES | B21: =SUM('TRANSFERENCIA CORRIENTE'!C22:E22) -> 6474433.8 | C21: =SUM('TRANSFERENCIA CORRIENTE'!F22:H22) -> 0 | D21: =SUM('TRANSFERENCIA CORRIENTE'!J22:L22) -> 0 | E21: =SUM('TRANSFERENCIA CORRIENTE'!L22:N22) -> 0 | G21: =SUM(VS!C22:E22) -> 4556850.1 | H21: =SUM(VS!F22:H22) -> 0 | I21: =SUM(VS!I22:K22) -> 0 | J21: =SUM(VS!L22:N22) -> 0 | L21: =SUM(B21+G21) -> 11031284 | M21: =SUM(C21+H21) -> 0 | N21: =SUM(D21+I21) -> 0 | O21: =SUM(E21+J21) -> 0
A22: 2.2.8 - OTROS SERVICIOS NO INCLUIDOS EN CONCEPTOS ANTERIORES | B22: =SUM('TRANSFERENCIA CORRIENTE'!C23:E23) -> 489700 | C22: =SUM('TRANSFERENCIA CORRIENTE'!F23:H23) -> 0 | D22: =SUM('TRANSFERENCIA CORRIENTE'!J23:L23) -> 0 | E22: =SUM('TRANSFERENCIA CORRIENTE'!L23:N23) -> 0 | G22: =SUM(VS!C23:E23) -> 832646.66 | H22: =SUM(VS!F23:H23) -> 0 | I22: =SUM(VS!I23:K23) -> 0 | J22: =SUM(VS!L23:N23) -> 0 | L22: =SUM(B22+G22) -> 1322346.7 | M22: =SUM(C22+H22) -> 0 | N22: =SUM(D22+I22) -> 0 | O22: =SUM(E22+J22) -> 0
A23: 2.2.9 - OTRAS CONTRATACIONES DE SERVICIOS | B23: =SUM('TRANSFERENCIA CORRIENTE'!C24:E24) -> 0 | C23: =SUM('TRANSFERENCIA CORRIENTE'!F24:H24) -> 0 | D23: =SUM('TRANSFERENCIA CORRIENTE'!J24:L24) -> 0 | E23: =SUM('TRANSFERENCIA CORRIENTE'!L24:N24) -> 0 | G23: =SUM(VS!C24:E24) -> 0 | H23: =SUM(VS!F24:H24) -> 0 | I23: =SUM(VS!I24:K24) -> 0 | J23: =SUM(VS!L24:N24) -> 0 | L23: =SUM(B23+G23) -> 0 | M23: =SUM(C23+H23) -> 0 | N23: =SUM(D23+I23) -> 0 | O23: =SUM(E23+J23) -> 0
A24: 2.3 - MATERIALES Y SUMINISTROS | B24: =SUM(B25:B33) -> 46153283 | C24: =SUM(C25:C33) -> 0 | D24: =SUM(D25:D33) -> 0 | E24: =SUM(E25:E33) -> 0 | G24: =SUM(G25:G33) -> 7292547.3 | H24: =SUM(H25:H33) -> 0 | I24: =SUM(I25:I33) -> 0 | J24: =SUM(J25:J33) -> 0 | L24: =SUM(B24+G24) -> 53445831 | M24: =SUM(C24+H24) -> 0 | N24: =SUM(D24+I24) -> 0 | O24: =SUM(E24+J24) -> 0
A25: 2.3.1 - ALIMENTOS Y PRODUCTOS AGROFORESTALES | B25: =SUM('TRANSFERENCIA CORRIENTE'!C26:E26) -> 3713897.2 | C25: =SUM('TRANSFERENCIA CORRIENTE'!F26:H26) -> 0 | D25: =SUM('TRANSFERENCIA CORRIENTE'!I23:K23) -> 0 | E25: =SUM('TRANSFERENCIA CORRIENTE'!L26:N26) -> 0 | G25: =SUM(VS!C26:E26) -> 1500755.8 | H25: =SUM(VS!F26:H26) -> 0 | I25: =SUM(VS!I26:K26) -> 0 | J25: =SUM(VS!L26:N26) -> 0 | L25: =SUM(B25+G25) -> 5214653 | M25: =SUM(C25+H25) -> 0 | N25: =SUM(D25+I25) -> 0 | O25: =SUM(E25+J25) -> 0
A26: 2.3.2 - TEXTILES Y VESTUARIOS | B26: =SUM('TRANSFERENCIA CORRIENTE'!C27:E27) -> 61630.73 | C26: =SUM('TRANSFERENCIA CORRIENTE'!F27:H27) -> 0 | D26: =SUM('TRANSFERENCIA CORRIENTE'!I24:K24) -> 0 | E26: =SUM('TRANSFERENCIA CORRIENTE'!L27:N27) -> 0 | G26: =SUM(VS!C27:E27) -> 0 | H26: =SUM(VS!F27:H27) -> 0 | I26: =SUM(VS!I27:K27) -> 0 | J26: =SUM(VS!L27:N27) -> 0 | L26: =SUM(B26+G26) -> 61630.73 | M26: =SUM(C26+H26) -> 0 | N26: =SUM(D26+I26) -> 0 | O26: =SUM(E26+J26) -> 0
A27: 2.3.3 - PRODUCTOS DE PAPEL, CARTÓN E IMPRESOS | B27: =SUM('TRANSFERENCIA CORRIENTE'!C28:E28) -> 1826911.8 | C27: =SUM('TRANSFERENCIA CORRIENTE'!F28:H28) -> 0 | D27: =SUM('TRANSFERENCIA CORRIENTE'!I25:K25) -> 0 | E27: =SUM('TRANSFERENCIA CORRIENTE'!L28:N28) -> 0 | G27: =SUM(VS!C28:E28) -> 251163 | H27: =SUM(VS!F28:H28) -> 0 | I27: =SUM(VS!I28:K28) -> 0 | J27: =SUM(VS!L28:N28) -> 0 | L27: =SUM(B27+G27) -> 2078074.8 | M27: =SUM(C27+H27) -> 0 | N27: =SUM(D27+I27) -> 0 | O27: =SUM(E27+J27) -> 0
A28: 2.3.4 - PRODUCTOS FARMACÉUTICOS | B28: =SUM('TRANSFERENCIA CORRIENTE'!C29:E29) -> 10797336 | C28: =SUM('TRANSFERENCIA CORRIENTE'!F29:H29) -> 0 | D28: =SUM('TRANSFERENCIA CORRIENTE'!I26:K26) -> 0 | E28: =SUM('TRANSFERENCIA CORRIENTE'!L29:N29) -> 0 | G28: =SUM(VS!C29:E29) -> 558000 | H28: =SUM(VS!F29:H29) -> 0 | I28: =SUM(VS!I29:K29) -> 0 | J28: =SUM(VS!L29:N29) -> 0 | L28: =SUM(B28+G28) -> 11355336 | M28: =SUM(C28+H28) -> 0 | N28: =SUM(D28+I28) -> 0 | O28: =SUM(E28+J28) -> 0
A29: 2.3.5 - PRODUCTOS DE CUERO, CAUCHO Y PLÁSTICO | B29: =SUM('TRANSFERENCIA CORRIENTE'!C30:E30) -> 334708.95 | C29: =SUM('TRANSFERENCIA CORRIENTE'!F30:H30) -> 0 | D29: =SUM('TRANSFERENCIA CORRIENTE'!I27:K27) -> 0 | E29: =SUM('TRANSFERENCIA CORRIENTE'!L30:N30) -> 0 | G29: =SUM(VS!C30:E30) -> 567494.87 | H29: =SUM(VS!F30:H30) -> 0 | I29: =SUM(VS!I30:K30) -> 0 | J29: =SUM(VS!L30:N30) -> 0 | L29: =SUM(B29+G29) -> 902203.82 | M29: =SUM(C29+H29) -> 0 | N29: =SUM(D29+I29) -> 0 | O29: =SUM(E29+J29) -> 0
A30: 2.3.6 - PRODUCTOS DE MINERALES, METÁLICOS Y NO METÁLICOS | B30: =SUM('TRANSFERENCIA CORRIENTE'!C31:E31) -> 11630.98 | C30: =SUM('TRANSFERENCIA CORRIENTE'!F31:H31) -> 0 | D30: =SUM('TRANSFERENCIA CORRIENTE'!I28:K28) -> 0 | E30: =SUM('TRANSFERENCIA CORRIENTE'!L31:N31) -> 0 | G30: =SUM(VS!C31:E31) -> 293957.3 | H30: =SUM(VS!F31:H31) -> 0 | I30: =SUM(VS!I31:K31) -> 0 | J30: =SUM(VS!L31:N31) -> 0 | L30: =SUM(B30+G30) -> 305588.28 | M30: =SUM(C30+H30) -> 0 | N30: =SUM(D30+I30) -> 0 | O30: =SUM(E30+J30) -> 0
A31: 2.3.7 - COMBUSTIBLES, LUBRICANTES, PRODUCTOS QUÍMICOS Y CONEXOS | B31: =SUM('TRANSFERENCIA CORRIENTE'!C32:E32) -> 8910102 | C31: =SUM('TRANSFERENCIA CORRIENTE'!F32:H32) -> 0 | D31: =SUM('TRANSFERENCIA CORRIENTE'!I29:K29) -> 0 | E31: =SUM('TRANSFERENCIA CORRIENTE'!L32:N32) -> 0 | G31: =SUM(VS!C32:E32) -> 1660334.6 | H31: =SUM(VS!F32:H32) -> 0 | I31: =SUM(VS!I32:K32) -> 0 | J31: =SUM(VS!L32:N32) -> 0 | L31: =SUM(B31+G31) -> 10570437 | M31: =SUM(C31+H31) -> 0 | N31: =SUM(D31+I31) -> 0 | O31: =SUM(E31+J31) -> 0
A32: 2.3.8 - GASTOS QUE SE ASIGNARÁN DURANTE EL EJERCICIO (ART. 32 Y 33 LEY 423-06) | B32: =SUM('TRANSFERENCIA CORRIENTE'!C33:E33) -> 0 | C32: =SUM('TRANSFERENCIA CORRIENTE'!F33:H33) -> 0 | D32: =SUM('TRANSFERENCIA CORRIENTE'!I30:K30) -> 0 | E32: =SUM('TRANSFERENCIA CORRIENTE'!L33:N33) -> 0 | G32: =SUM(VS!C33:E33) -> 0 | H32: =SUM(VS!F33:H33) -> 0 | I32: =SUM(VS!I33:K33) -> 0 | J32: =SUM(VS!L33:N33) -> 0 | L32: =SUM(B32+G32) -> 0 | M32: =SUM(C32+H32) -> 0 | N32: =SUM(D32+I32) -> 0 | O32: =SUM(E32+J32) -> 0
A33: 2.3.9 - PRODUCTOS Y ÚTILES VARIOS | B33: =SUM('TRANSFERENCIA CORRIENTE'!C34:E34) -> 20497066 | C33: =SUM('TRANSFERENCIA CORRIENTE'!F34:H34) -> 0 | D33: =SUM('TRANSFERENCIA CORRIENTE'!I31:K31) -> 0 | E33: =SUM('TRANSFERENCIA CORRIENTE'!L34:N34) -> 0 | G33: =SUM(VS!C34:E34) -> 2460841.8 | H33: =SUM(VS!F34:H34) -> 0 | I33: =SUM(VS!I34:K34) -> 0 | J33: =SUM(VS!L34:N34) -> 0 | L33: =SUM(B33+G33) -> 22957908 | M33: =SUM(C33+H33) -> 0 | N33: =SUM(D33+I33) -> 0 | O33: =SUM(E33+J33) -> 0
A34: 2.4 - TRANSFERENCIAS CORRIENTES | B34: =SUM(B35:B41) -> 0 | C34: =SUM(C35:C41) -> 0 | D34: =SUM(D35:D41) -> 0 | E34: =SUM(E35:E41) -> 0 | G34: =SUM(G35:G41) -> 287786.7 | H34: =SUM(H35:H41) -> 0 | I34: =SUM(I35:I41) -> 0 | J34: =SUM(J35:J41) -> 0 | L34: =SUM(B34+G34) -> 287786.7 | M34: =SUM(C34+H34) -> 0 | N34: =SUM(D34+I34) -> 0 | O34: =SUM(E34+J34) -> 0
A35: 2.4.1 - TRANSFERENCIAS CORRIENTES AL SECTOR PRIVADO | B35: =SUM('TRANSFERENCIA CORRIENTE'!C36:E36) -> 0 | C35: =SUM('TRANSFERENCIA CORRIENTE'!F36:H36) -> 0 | D35: =SUM('TRANSFERENCIA CORRIENTE'!I36:K36) -> 0 | E35: =SUM('TRANSFERENCIA CORRIENTE'!L36:N36) -> 0 | G35: =SUM(VS!C36:E36) -> 287786.7 | H35: =SUM(VS!F36:H36) -> 0 | I35: =SUM(VS!I36:K36) -> 0 | J35: =SUM(VS!L36:N36) -> 0 | L35: =SUM(B35+G35) -> 287786.7 | M35: =SUM(C35+H35) -> 0 | N35: =SUM(D35+I35) -> 0 | O35: =SUM(E35+J35) -> 0
A36: 2.4.2 - TRANSFERENCIAS CORRIENTES AL GOBIERNO GENERAL NACIONAL | B36: =SUM('TRANSFERENCIA CORRIENTE'!C37:E37) -> 0 | C36: =SUM('TRANSFERENCIA CORRIENTE'!F37:H37) -> 0 | D36: =SUM('TRANSFERENCIA CORRIENTE'!I37:K37) -> 0 | E36: =SUM('TRANSFERENCIA CORRIENTE'!L37:N37) -> 0 | G36: =SUM(VS!C37:E37) -> 0 | H36: =SUM(VS!F37:H37) -> 0 | I36: =SUM(VS!I37:K37) -> 0 | J36: =SUM(VS!L37:N37) -> 0 | L36: =SUM(B36+G36) -> 0 | M36: =SUM(C36+H36) -> 0 | N36: =SUM(D36+I36) -> 0 | O36: =SUM(E36+J36) -> 0
A37: 2.4.3 - TRANSFERENCIAS CORRIENTES A GOBIERNOS GENERALES LOCALES | B37: =SUM('TRANSFERENCIA CORRIENTE'!C38:E38) -> 0 | C37: =SUM('TRANSFERENCIA CORRIENTE'!F38:H38) -> 0 | D37: =SUM('TRANSFERENCIA CORRIENTE'!I38:K38) -> 0 | E37: =SUM('TRANSFERENCIA CORRIENTE'!L38:N38) -> 0 | G37: =SUM(VS!C38:E38) -> 0 | H37: =SUM(VS!F38:H38) -> 0 | I37: =SUM(VS!I38:K38) -> 0 | J37: =SUM(VS!L38:N38) -> 0 | L37: =SUM(B37+G37) -> 0 | M37: =SUM(C37+H37) -> 0 | N37: =SUM(D37+I37) -> 0 | O37: =SUM(E37+J37) -> 0
A38: 2.4.4 - TRANSFERENCIAS CORRIENTES A EMPRESAS PÚBLICAS NO FINANCIERAS | B38: =SUM('TRANSFERENCIA CORRIENTE'!C39:E39) -> 0 | C38: =SUM('TRANSFERENCIA CORRIENTE'!F39:H39) -> 0 | D38: =SUM('TRANSFERENCIA CORRIENTE'!I39:K39) -> 0 | E38: =SUM('TRANSFERENCIA CORRIENTE'!L39:N39) -> 0 | G38: =SUM(VS!C39:E39) -> 0 | H38: =SUM(VS!F39:H39) -> 0 | I38: =SUM(VS!I39:K39) -> 0 | J38: =SUM(VS!L39:N39) -> 0 | L38: =SUM(B38+G38) -> 0 | M38: =SUM(C38+H38) -> 0 | N38: =SUM(D38+I38) -> 0 | O38: =SUM(E38+J38) -> 0
A39: 2.4.5 - TRANSFERENCIAS CORRIENTES A INSTITUCIONES PÚBLICAS FINANCIERAS | B39: =SUM('TRANSFERENCIA CORRIENTE'!C40:E40) -> 0 | C39: =SUM('TRANSFERENCIA CORRIENTE'!F40:H40) -> 0 | D39: =SUM('TRANSFERENCIA CORRIENTE'!I40:K40) -> 0 | E39: =SUM('TRANSFERENCIA CORRIENTE'!L40:N40) -> 0 | G39: =SUM(VS!C40:E40) -> 0 | H39: =SUM(VS!F40:H40) -> 0 | I39: =SUM(VS!I40:K40) -> 0 | J39: =SUM(VS!L40:N40) -> 0 | L39: =SUM(B39+G39) -> 0 | M39: =SUM(C39+H39) -> 0 | N39: =SUM(D39+I39) -> 0 | O39: =SUM(E39+J39) -> 0
A40: 2.4.7 - TRANSFERENCIAS CORRIENTES AL SECTOR EXTERNO | B40: =SUM('TRANSFERENCIA CORRIENTE'!C41:E41) -> 0 | C40: =SUM('TRANSFERENCIA CORRIENTE'!F41:H41) -> 0 | D40: =SUM('TRANSFERENCIA CORRIENTE'!I41:K41) -> 0 | E40: =SUM('TRANSFERENCIA CORRIENTE'!L41:N41) -> 0 | G40: =SUM(VS!C41:E41) -> 0 | H40: =SUM(VS!F41:H41) -> 0 | I40: =SUM(VS!I41:K41) -> 0 | J40: =SUM(VS!L41:N41) -> 0 | L40: =SUM(B40+G40) -> 0 | M40: =SUM(C40+H40) -> 0 | N40: =SUM(D40+I40) -> 0 | O40: =SUM(E40+J40) -> 0
A41: 2.4.9 - TRANSFERENCIAS CORRIENTES A OTRAS INSTITUCIONES PÚBLICAS | B41: =SUM('TRANSFERENCIA CORRIENTE'!C42:E42) -> 0 | C41: =SUM('TRANSFERENCIA CORRIENTE'!F42:H42) -> 0 | D41: =SUM('TRANSFERENCIA CORRIENTE'!I42:K42) -> 0 | E41: =SUM('TRANSFERENCIA CORRIENTE'!L42:N42) -> 0 | G41: =SUM(VS!C42:E42) -> 0 | H41: =SUM(VS!F42:H42) -> 0 | I41: =SUM(VS!I42:K42) -> 0 | J41: =SUM(VS!L42:N42) -> 0 | L41: =SUM(B41+G41) -> 0 | M41: =SUM(C41+H41) -> 0 | N41: =SUM(D41+I41) -> 0 | O41: =SUM(E41+J41) -> 0
A42: 2.5 - TRANSFERENCIAS DE CAPITAL | B42: =SUM(B43:B49) -> 0 | C42: =SUM(C43:C49) -> 0 | D42: =SUM(D43:D49) -> 0 | E42: =SUM(E43:E49) -> 0 | G42: =SUM(G43:G49) -> 0 | H42: =SUM(H43:H49) -> 0 | I42: =SUM(I43:I49) -> 0 | J42: =SUM(J43:J49) -> 0 | L42: =SUM(B42+G42) -> 0 | M42: =SUM(C42+H42) -> 0 | N42: =SUM(D42+I42) -> 0 | O42: =SUM(E42+J42) -> 0
A43: 2.5.1 - TRANSFERENCIAS DE CAPITAL AL SECTOR PRIVADO | B43: =SUM('TRANSFERENCIA CORRIENTE'!C44:E44) -> 0 | C43: =SUM('TRANSFERENCIA CORRIENTE'!F44:H44) -> 0 | D43: =SUM('TRANSFERENCIA CORRIENTE'!I44:K44) -> 0 | E43: =SUM('TRANSFERENCIA CORRIENTE'!L44:N44) -> 0 | G43: =SUM(VS!C44:E44) -> 0 | H43: =SUM(VS!F44:H44) -> 0 | I43: =SUM(VS!I44:K44) -> 0 | J43: =SUM(VS!L44:N44) -> 0 | L43: =SUM(B43+G43) -> 0 | M43: =SUM(C43+H43) -> 0 | N43: =SUM(D43+I43) -> 0 | O43: =SUM(E43+J43) -> 0
A44: 2.5.2 - TRANSFERENCIAS DE CAPITAL AL GOBIERNO GENERAL NACIONAL | B44: =SUM('TRANSFERENCIA CORRIENTE'!C45:E45) -> 0 | C44: =SUM('TRANSFERENCIA CORRIENTE'!F45:H45) -> 0 | D44: =SUM('TRANSFERENCIA CORRIENTE'!I45:K45) -> 0 | E44: =SUM('TRANSFERENCIA CORRIENTE'!L45:N45) -> 0 | G44: =SUM(VS!C45:E45) -> 0 | H44: =SUM(VS!F45:H45) -> 0 | I44: =SUM(VS!I45:K45) -> 0 | J44: =SUM(VS!L45:N45) -> 0 | L44: =SUM(B44+G44) -> 0 | M44: =SUM(C44+H44) -> 0 | N44: =SUM(D44+I44) -> 0 | O44: =SUM(E44+J44) -> 0
A45: 2.5.3 - TRANSFERENCIAS DE CAPITAL A GOBIERNOS GENERALES LOCALES | B45: =SUM('TRANSFERENCIA CORRIENTE'!C46:E46) -> 0 | C45: =SUM('TRANSFERENCIA CORRIENTE'!F46:H46) -> 0 | D45: =SUM('TRANSFERENCIA CORRIENTE'!I46:K46) -> 0 | E45: =SUM('TRANSFERENCIA CORRIENTE'!L46:N46) -> 0 | G45: =SUM(VS!C46:E46) -> 0 | H45: =SUM(VS!F46:H46) -> 0 | I45: =SUM(VS!I46:K46) -> 0 | J45: =SUM(VS!L46:N46) -> 0 | L45: =SUM(B45+G45) -> 0 | M45: =SUM(C45+H45) -> 0 | N45: =SUM(D45+I45) -> 0 | O45: =SUM(E45+J45) -> 0
A46: 2.5.4 - TRANSFERENCIAS DE CAPITAL A EMPRESAS PÚBLICAS NO FINANCIERAS | B46: =SUM('TRANSFERENCIA CORRIENTE'!C47:E47) -> 0 | C46: =SUM('TRANSFERENCIA CORRIENTE'!F47:H47) -> 0 | D46: =SUM('TRANSFERENCIA CORRIENTE'!I47:K47) -> 0 | E46: =SUM('TRANSFERENCIA CORRIENTE'!L47:N47) -> 0 | G46: =SUM(VS!C47:E47) -> 0 | H46: =SUM(VS!F47:H47) -> 0 | I46: =SUM(VS!I47:K47) -> 0 | J46: =SUM(VS!L47:N47) -> 0 | L46: =SUM(B46+G46) -> 0 | M46: =SUM(C46+H46) -> 0 | N46: =SUM(D46+I46) -> 0 | O46: =SUM(E46+J46) -> 0
A47: 2.5.5 - TRANSFERENCIAS DE CAPITAL A INSTITUCIONES PÚBLICAS FINANCIERAS | B47: =SUM('TRANSFERENCIA CORRIENTE'!C48:E48) -> 0 | C47: =SUM('TRANSFERENCIA CORRIENTE'!F48:H48) -> 0 | D47: =SUM('TRANSFERENCIA CORRIENTE'!I48:K48) -> 0 | E47: =SUM('TRANSFERENCIA CORRIENTE'!L48:N48) -> 0 | G47: =SUM(VS!C48:E48) -> 0 | H47: =SUM(VS!F48:H48) -> 0 | I47: =SUM(VS!I48:K48) -> 0 | J47: =SUM(VS!L48:N48) -> 0 | L47: =SUM(B47+G47) -> 0 | M47: =SUM(C47+H47) -> 0 | N47: =SUM(D47+I47) -> 0 | O47: =SUM(E47+J47) -> 0
A48: 2.5.6 - TRANSFERENCIAS DE CAPITAL AL SECTOR EXTERNO | B48: =SUM('TRANSFERENCIA CORRIENTE'!C49:E49) -> 0 | C48: =SUM('TRANSFERENCIA CORRIENTE'!F49:H49) -> 0 | D48: =SUM('TRANSFERENCIA CORRIENTE'!I49:K49) -> 0 | E48: =SUM('TRANSFERENCIA CORRIENTE'!L49:N49) -> 0 | G48: =SUM(VS!C49:E49) -> 0 | H48: =SUM(VS!F49:H49) -> 0 | I48: =SUM(VS!I49:K49) -> 0 | J48: =SUM(VS!L49:N49) -> 0 | L48: =SUM(B48+G48) -> 0 | M48: =SUM(C48+H48) -> 0 | N48: =SUM(D48+I48) -> 0 | O48: =SUM(E48+J48) -> 0
A49: 2.5.9 - TRANSFERENCIAS DE CAPITAL A OTRAS INSTITUCIONES PÚBLICAS | B49: =SUM('TRANSFERENCIA CORRIENTE'!C50:E50) -> 0 | C49: =SUM('TRANSFERENCIA CORRIENTE'!F50:H50) -> 0 | D49: =SUM('TRANSFERENCIA CORRIENTE'!I50:K50) -> 0 | E49: =SUM('TRANSFERENCIA CORRIENTE'!L50:N50) -> 0 | G49: =SUM(VS!C50:E50) -> 0 | H49: =SUM(VS!F50:H50) -> 0 | I49: =SUM(VS!I50:K50) -> 0 | J49: =SUM(VS!L50:N50) -> 0 | L49: =SUM(B49+G49) -> 0 | M49: =SUM(C49+H49) -> 0 | N49: =SUM(D49+I49) -> 0 | O49: =SUM(E49+J49) -> 0
A50: 2.6 - BIENES MUEBLES, INMUEBLES E INTANGIBLES | B50: =SUM(B51:B59) -> 17857867 | C50: =SUM(C51:C59) -> 0 | D50: =SUM(D51:D59) -> 0 | E50: =SUM(E51:E59) -> 0 | G50: =SUM(G51:G59) -> 5076044.2 | H50: =SUM(H51:H59) -> 0 | I50: =SUM(I51:I59) -> 0 | J50: =SUM(J51:J59) -> 0 | L50: =SUM(B50+G50) -> 22933911 | M50: =SUM(C50+H50) -> 0 | N50: =SUM(D50+I50) -> 0 | O50: =SUM(E50+J50) -> 0
A51: 2.6.1 - MOBILIARIO Y EQUIPO | B51: =SUM('TRANSFERENCIA CORRIENTE'!C52:E52) -> 1110625.9 | C51: =SUM('TRANSFERENCIA CORRIENTE'!F52:H52) -> 0 | D51: =SUM('TRANSFERENCIA CORRIENTE'!I52:K52) -> 0 | E51: =SUM('TRANSFERENCIA CORRIENTE'!L52:N52) -> 0 | G51: =SUM(VS!C52:E52) -> 0 | H51: =SUM(VS!F52:H52) -> 0 | I51: =SUM(VS!I52:K52) -> 0 | J51: =SUM(VS!L52:N52) -> 0 | L51: =SUM(B51+G51) -> 1110625.9 | M51: =SUM(C51+H51) -> 0 | N51: =SUM(D51+I51) -> 0 | O51: =SUM(E51+J51) -> 0
A52: 2.6.2 - MOBILIARIO Y EQUIPO EDUCACIONAL Y RECREATIVO | B52: =SUM('TRANSFERENCIA CORRIENTE'!C53:E53) -> 0 | C52: =SUM('TRANSFERENCIA CORRIENTE'!F53:H53) -> 0 | D52: =SUM('TRANSFERENCIA CORRIENTE'!I53:K53) -> 0 | E52: =SUM('TRANSFERENCIA CORRIENTE'!L53:N53) -> 0 | G52: =SUM(VS!C53:E53) -> 0 | H52: =SUM(VS!F53:H53) -> 0 | I52: =SUM(VS!I53:K53) -> 0 | J52: =SUM(VS!L53:N53) -> 0 | L52: =SUM(B52+G52) -> 0 | M52: =SUM(C52+H52) -> 0 | N52: =SUM(D52+I52) -> 0 | O52: =SUM(E52+J52) -> 0
A53: 2.6.3 - EQUIPO E INSTRUMENTAL, CIENTÍFICO Y LABORATORIO | B53: =SUM('TRANSFERENCIA CORRIENTE'!C54:E54) -> 16744041 | C53: =SUM('TRANSFERENCIA CORRIENTE'!F54:H54) -> 0 | D53: =SUM('TRANSFERENCIA CORRIENTE'!I54:K54) -> 0 | E53: =SUM('TRANSFERENCIA CORRIENTE'!L54:N54) -> 0 | G53: =SUM(VS!C54:E54) -> 2963024.8 | H53: =SUM(VS!F54:H54) -> 0 | I53: =SUM(VS!I54:K54) -> 0 | J53: =SUM(VS!L54:N54) -> 0 | L53: =SUM(B53+G53) -> 19707066 | M53: =SUM(C53+H53) -> 0 | N53: =SUM(D53+I53) -> 0 | O53: =SUM(E53+J53) -> 0
A54: 2.6.4 - VEHÍCULOS Y EQUIPO DE TRANSPORTE, TRACCIÓN Y ELEVACIÓN | B54: =SUM('TRANSFERENCIA CORRIENTE'!C55:E55) -> 0 | C54: =SUM('TRANSFERENCIA CORRIENTE'!F55:H55) -> 0 | D54: =SUM('TRANSFERENCIA CORRIENTE'!I55:K55) -> 0 | E54: =SUM('TRANSFERENCIA CORRIENTE'!L55:N55) -> 0 | G54: =SUM(VS!C55:E55) -> 107609.37 | H54: =SUM(VS!F55:H55) -> 0 | I54: =SUM(VS!I55:K55) -> 0 | J54: =SUM(VS!L55:N55) -> 0 | L54: =SUM(B54+G54) -> 107609.37 | M54: =SUM(C54+H54) -> 0 | N54: =SUM(D54+I54) -> 0 | O54: =SUM(E54+J54) -> 0
A55: 2.6.5 - MAQUINARIA, OTROS EQUIPOS Y HERRAMIENTAS | B55: =SUM('TRANSFERENCIA CORRIENTE'!C56:E56) -> 3199.97 | C55: =SUM('TRANSFERENCIA CORRIENTE'!F56:H56) -> 0 | D55: =SUM('TRANSFERENCIA CORRIENTE'!I56:K56) -> 0 | E55: =SUM('TRANSFERENCIA CORRIENTE'!L56:N56) -> 0 | G55: =SUM(VS!C56:E56) -> 2005410 | H55: =SUM(VS!F56:H56) -> 0 | I55: =SUM(VS!I56:K56) -> 0 | J55: =SUM(VS!L56:N56) -> 0 | L55: =SUM(B55+G55) -> 2008610 | M55: =SUM(C55+H55) -> 0 | N55: =SUM(D55+I55) -> 0 | O55: =SUM(E55+J55) -> 0
A56: 2.6.6 - EQUIPOS DE DEFENSA Y SEGURIDAD | B56: =SUM('TRANSFERENCIA CORRIENTE'!C57:E57) -> 0 | C56: =SUM('TRANSFERENCIA CORRIENTE'!F57:H57) -> 0 | D56: =SUM('TRANSFERENCIA CORRIENTE'!I57:K57) -> 0 | E56: =SUM('TRANSFERENCIA CORRIENTE'!L57:N57) -> 0 | G56: =SUM(VS!C57:E57) -> 0 | H56: =SUM(VS!F57:H57) -> 0 | I56: =SUM(VS!I57:K57) -> 0 | J56: =SUM(VS!L57:N57) -> 0 | L56: =SUM(B56+G56) -> 0 | M56: =SUM(C56+H56) -> 0 | N56: =SUM(D56+I56) -> 0 | O56: =SUM(E56+J56) -> 0
A57: 2.6.7 - ACTIVOS BIÓLOGICOS CULTIVABLES | B57: =SUM('TRANSFERENCIA CORRIENTE'!C58:E58) -> 0 | C57: =SUM('TRANSFERENCIA CORRIENTE'!F58:H58) -> 0 | D57: =SUM('TRANSFERENCIA CORRIENTE'!I58:K58) -> 0 | E57: =SUM('TRANSFERENCIA CORRIENTE'!L58:N58) -> 0 | G57: =SUM(VS!C58:E58) -> 0 | H57: =SUM(VS!F58:H58) -> 0 | I57: =SUM(VS!I58:K58) -> 0 | J57: =SUM(VS!L58:N58) -> 0 | L57: =SUM(B57+G57) -> 0 | M57: =SUM(C57+H57) -> 0 | N57: =SUM(D57+I57) -> 0 | O57: =SUM(E57+J57) -> 0
A58: 2.6.8 - BIENES INTANGIBLES | B58: =SUM('TRANSFERENCIA CORRIENTE'!C59:E59) -> 0 | C58: =SUM('TRANSFERENCIA CORRIENTE'!F59:H59) -> 0 | D58: =SUM('TRANSFERENCIA CORRIENTE'!I59:K59) -> 0 | E58: =SUM('TRANSFERENCIA CORRIENTE'!L59:N59) -> 0 | G58: =SUM(VS!C59:E59) -> 0 | H58: =SUM(VS!F59:H59) -> 0 | I58: =SUM(VS!I59:K59) -> 0 | J58: =SUM(VS!L59:N59) -> 0 | L58: =SUM(B58+G58) -> 0 | M58: =SUM(C58+H58) -> 0 | N58: =SUM(D58+I58) -> 0 | O58: =SUM(E58+J58) -> 0
A59: 2.6.9 - EDIFICIOS, ESTRUCTURAS, TIERRAS, TERRENOS Y OBJETOS DE VALOR | B59: =SUM('TRANSFERENCIA CORRIENTE'!C60:E60) -> 0 | C59: =SUM('TRANSFERENCIA CORRIENTE'!F60:H60) -> 0 | D59: =SUM('TRANSFERENCIA CORRIENTE'!I60:K60) -> 0 | E59: =SUM('TRANSFERENCIA CORRIENTE'!L60:N60) -> 0 | G59: =SUM(VS!C60:E60) -> 0 | H59: =SUM(VS!F60:H60) -> 0 | I59: =SUM(VS!I60:K60) -> 0 | J59: =SUM(VS!L60:N60) -> 0 | L59: =SUM(B59+G59) -> 0 | M59: =SUM(C59+H59) -> 0 | N59: =SUM(D59+I59) -> 0 | O59: =SUM(E59+J59) -> 0
A60: 2.7 - OBRAS | B60: =SUM(B61:B64) -> 0 | C60: =SUM(C61:C64) -> 0 | D60: =SUM(D61:D64) -> 0 | E60: =SUM(E61:E64) -> 0 | G60: =SUM(G61:G64) -> 0 | H60: =SUM(H61:H64) -> 0 | I60: =SUM(I61:I64) -> 0 | J60: =SUM(J61:J64) -> 0 | L60: =SUM(B60+G60) -> 0 | M60: =SUM(C60+H60) -> 0 | N60: =SUM(D60+I60) -> 0 | O60: =SUM(E60+J60) -> 0
A61: 2.7.1 - OBRAS EN EDIFICACIONES | B61: =SUM('TRANSFERENCIA CORRIENTE'!C62:E62) -> 0 | C61: =SUM('TRANSFERENCIA CORRIENTE'!F62:H62) -> 0 | D61: =SUM('TRANSFERENCIA CORRIENTE'!I62:K62) -> 0 | E61: =SUM('TRANSFERENCIA CORRIENTE'!L62:N62) -> 0 | G61: =SUM(VS!C62:E62) -> 0 | H61: =SUM(VS!F62:H62) -> 0 | I61: =SUM(VS!I62:K62) -> 0 | J61: =SUM(VS!L62:N62) -> 0 | L61: =SUM(B61+G61) -> 0 | M61: =SUM(C61+H61) -> 0 | N61: =SUM(D61+I61) -> 0 | O61: =SUM(E61+J61) -> 0
A62: 2.7.2 - INFRAESTRUCTURA | B62: =SUM('TRANSFERENCIA CORRIENTE'!C63:E63) -> 0 | C62: =SUM('TRANSFERENCIA CORRIENTE'!F63:H63) -> 0 | D62: =SUM('TRANSFERENCIA CORRIENTE'!I63:K63) -> 0 | E62: =SUM('TRANSFERENCIA CORRIENTE'!L63:N63) -> 0 | G62: =SUM(VS!C63:E63) -> 0 | H62: =SUM(VS!F63:H63) -> 0 | I62: =SUM(VS!I63:K63) -> 0 | J62: =SUM(VS!L63:N63) -> 0 | L62: =SUM(B62+G62) -> 0 | M62: =SUM(C62+H62) -> 0 | N62: =SUM(D62+I62) -> 0 | O62: =SUM(E62+J62) -> 0
A63: 2.7.3 - CONSTRUCCIONES EN BIENES CONCESIONADOS | B63: =SUM('TRANSFERENCIA CORRIENTE'!C64:E64) -> 0 | C63: =SUM('TRANSFERENCIA CORRIENTE'!F64:H64) -> 0 | D63: =SUM('TRANSFERENCIA CORRIENTE'!I64:K64) -> 0 | E63: =SUM('TRANSFERENCIA CORRIENTE'!L64:N64) -> 0 | G63: =SUM(VS!C64:E64) -> 0 | H63: =SUM(VS!F64:H64) -> 0 | I63: =SUM(VS!I64:K64) -> 0 | J63: =SUM(VS!L64:N64) -> 0 | L63: =SUM(B63+G63) -> 0 | M63: =SUM(C63+H63) -> 0 | N63: =SUM(D63+I63) -> 0 | O63: =SUM(E63+J63) -> 0
A64: 2.7.4 - GASTOS QUE SE ASIGNARÁN DURANTE EL EJERCICIO PARA INVERSIÓN (ART. 32 Y 33 LEY 423-06) | B64: =SUM('TRANSFERENCIA CORRIENTE'!C65:E65) -> 0 | C64: =SUM('TRANSFERENCIA CORRIENTE'!F65:H65) -> 0 | D64: =SUM('TRANSFERENCIA CORRIENTE'!I65:K65) -> 0 | E64: =SUM('TRANSFERENCIA CORRIENTE'!L65:N65) -> 0 | G64: =SUM(VS!C65:E65) -> 0 | H64: =SUM(VS!F65:H65) -> 0 | I64: =SUM(VS!I65:K65) -> 0 | J64: =SUM(VS!L65:N65) -> 0 | L64: =SUM(B64+G64) -> 0 | M64: =SUM(C64+H64) -> 0 | N64: =SUM(D64+I64) -> 0 | O64: =SUM(E64+J64) -> 0
A65: 2.8 - ADQUISICION DE ACTIVOS FINANCIEROS CON FINES DE POLÍTICA | B65: =SUM(B66:B67) -> 0 | C65: =SUM(C66:C67) -> 0 | D65: =SUM(D66:D67) -> 0 | E65: =SUM(E66:E67) -> 0 | G65: =SUM(G66:G67) -> 0 | H65: =SUM(H66:H67) -> 0 | I65: =SUM(I66:I67) -> 0 | J65: =SUM(J66:J67) -> 0 | L65: =SUM(B65+G65) -> 0 | M65: =SUM(C65+H65) -> 0 | N65: =SUM(D65+I65) -> 0 | O65: =SUM(E65+J65) -> 0
A66: 2.8.1 - CONCESIÓN DE PRESTAMOS | B66: =SUM('TRANSFERENCIA CORRIENTE'!C67:E67) -> 0 | C66: =SUM('TRANSFERENCIA CORRIENTE'!F67:H67) -> 0 | D66: =SUM('TRANSFERENCIA CORRIENTE'!I67:K67) -> 0 | E66: =SUM('TRANSFERENCIA CORRIENTE'!L67:N67) -> 0 | G66: =SUM(VS!C67:E67) -> 0 | H66: =SUM(VS!F67:H67) -> 0 | I66: =SUM(VS!I67:K67) -> 0 | J66: =SUM(VS!L67:N67) -> 0 | L66: =SUM(B66+G66) -> 0 | M66: =SUM(C66+H66) -> 0 | N66: =SUM(D66+I66) -> 0 | O66: =SUM(E66+J66) -> 0
A67: 2.8.2 - ADQUISICIÓN DE TÍTULOS VALORES REPRESENTATIVOS DE DEUDA | B67: =SUM('TRANSFERENCIA CORRIENTE'!C68:E68) -> 0 | C67: =SUM('TRANSFERENCIA CORRIENTE'!F68:H68) -> 0 | D67: =SUM('TRANSFERENCIA CORRIENTE'!I68:K68) -> 0 | E67: =SUM('TRANSFERENCIA CORRIENTE'!L68:N68) -> 0 | G67: =SUM(VS!C68:E68) -> 0 | H67: =SUM(VS!F68:H68) -> 0 | I67: =SUM(VS!I68:K68) -> 0 | J67: =SUM(VS!L68:N68) -> 0 | L67: =SUM(B67+G67) -> 0 | M67: =SUM(C67+H67) -> 0 | N67: =SUM(D67+I67) -> 0 | O67: =SUM(E67+J67) -> 0
A68: 2.9 - GASTOS FINANCIEROS | B68: =SUM(B69:B71) -> 0 | C68: =SUM(C69:C71) -> 0 | D68: =SUM(D69:D71) -> 0 | E68: =SUM(E69:E71) -> 0 | G68: =SUM(G69:G71) -> 0 | H68: =SUM(H69:H71) -> 0 | I68: =SUM(I69:I71) -> 0 | J68: =SUM(J69:J71) -> 0 | L68: =SUM(B68+G68) -> 0 | M68: =SUM(C68+H68) -> 0 | N68: =SUM(D68+I68) -> 0 | O68: =SUM(E68+J68) -> 0
A69: 2.9.1 - INTERESES DE LA DEUDA PÚBLICA INTERNA | B69: =SUM('TRANSFERENCIA CORRIENTE'!C70:E70) -> 0 | C69: =SUM('TRANSFERENCIA CORRIENTE'!F70:H70) -> 0 | D69: =SUM('TRANSFERENCIA CORRIENTE'!I70:K70) -> 0 | E69: =SUM('TRANSFERENCIA CORRIENTE'!L70:N70) -> 0 | G69: =SUM(VS!C70:E70) -> 0 | H69: =SUM(VS!F70:H70) -> 0 | I69: =SUM(VS!I70:K70) -> 0 | J69: =SUM(VS!L70:N70) -> 0 | L69: =SUM(B69+G69) -> 0 | M69: =SUM(C69+H69) -> 0 | N69: =SUM(D69+I69) -> 0 | O69: =SUM(E69+J69) -> 0
A70: 2.9.2 - INTERESES DE LA DEUDA PUBLICA EXTERNA | B70: =SUM('TRANSFERENCIA CORRIENTE'!C71:E71) -> 0 | C70: =SUM('TRANSFERENCIA CORRIENTE'!F71:H71) -> 0 | D70: =SUM('TRANSFERENCIA CORRIENTE'!I71:K71) -> 0 | E70: =SUM('TRANSFERENCIA CORRIENTE'!L71:N71) -> 0 | G70: =SUM(VS!C71:E71) -> 0 | H70: =SUM(VS!F71:H71) -> 0 | I70: =SUM(VS!I71:K71) -> 0 | J70: =SUM(VS!L71:N71) -> 0 | L70: =SUM(B70+G70) -> 0 | M70: =SUM(C70+H70) -> 0 | N70: =SUM(D70+I70) -> 0 | O70: =SUM(E70+J70) -> 0
A71: 2.9.4 - COMISIONES Y OTROS GASTOS BANCARIOS DE LA DEUDA PÚBLICA | B71: =SUM('TRANSFERENCIA CORRIENTE'!C72:E72) -> 0 | C71: =SUM('TRANSFERENCIA CORRIENTE'!F72:H72) -> 0 | D71: =SUM('TRANSFERENCIA CORRIENTE'!I72:K72) -> 0 | E71: =SUM('TRANSFERENCIA CORRIENTE'!L72:N72) -> 0 | H71: =SUM(VS!F72:H72) -> 0 | I71: =SUM(VS!I72:K72) -> 0 | J71: =SUM(VS!L72:N72) -> 0 | L71: =SUM(B71+G71) -> 0 | M71: =SUM(C71+H71) -> 0 | N71: =SUM(D71+I71) -> 0 | O71: =SUM(E71+J71) -> 0
A72: Total Gastos | B72: =+B8+B14+B24+B34+B42+B50+B60+B65+B68 -> 2.7188025e+08 | C72: =+C8+C14+C24+C34+C42+C50+C60+C65+C68 -> 0 | D72: =+D8+D14+D24+D34+D42+D50+D60+D65+D68 -> 0 | E72: =+E8+E14+E24+E34+E42+E50+E60+E65+E68 -> 0 | G72: =+G8+G14+G24+G34+G42+G50+G60+G65+G68 -> 26194616 | H72: =+H8+H14+H24+H34+H42+H50+H60+H65+H68 -> 0 | I72: =+I8+I14+I24+I34+I42+I50+I60+I65+I68 -> 0 | J72: =+J8+J14+J24+J34+J42+J50+J60+J65+J68 -> 0 | L72: =SUM(B72+G72) -> 2.9807487e+08 | M72: =SUM(C72+H72) -> 0 | N72: =SUM(D72+I72) -> 0 | O72: =SUM(E72+J72) -> 0
A73: 4 - APLICACIONES FINANCIERAS | B73: =SUM('TRANSFERENCIA CORRIENTE'!C74:E74) -> 0 | C73: =SUM('TRANSFERENCIA CORRIENTE'!F74:H74) -> 0 | D73: =SUM('TRANSFERENCIA CORRIENTE'!I74:K74) -> 0 | E73: =SUM('TRANSFERENCIA CORRIENTE'!L74:N74) -> 0 | G73: =SUM(VS!C74:E74) -> 0 | H73: =SUM(VS!F74:H74) -> 0 | I73: =SUM(VS!I74:K74) -> 0 | J73: =SUM(VS!L74:N74) -> 0 | L73: =SUM(B73+G73) -> 0 | M73: =SUM(C73+H73) -> 0 | N73: =SUM(D73+I73) -> 0 | O73: =SUM(E73+J73) -> 0
A74: 4.1 - INCREMENTO DE ACTIVOS FINANCIEROS | B74: =SUM('TRANSFERENCIA CORRIENTE'!C75:E75) -> 0 | C74: =SUM('TRANSFERENCIA CORRIENTE'!F75:H75) -> 0 | D74: =SUM('TRANSFERENCIA CORRIENTE'!I75:K75) -> 0 | E74: =SUM('TRANSFERENCIA CORRIENTE'!L75:N75) -> 0 | G74: =SUM(VS!C75:E75) -> 0 | H74: =SUM(VS!F75:H75) -> 0 | I74: =SUM(VS!I75:K75) -> 0 | J74: =SUM(VS!L75:N75) -> 0 | L74: =SUM(B74+G74) -> 0 | M74: =SUM(C74+H74) -> 0 | N74: =SUM(D74+I74) -> 0 | O74: =SUM(E74+J74) -> 0
A75: 4.1.1 - INCREMENTO DE ACTIVOS FINANCIEROS CORRIENTES | B75: =SUM('TRANSFERENCIA CORRIENTE'!C76:E76) -> 0 | C75: =SUM('TRANSFERENCIA CORRIENTE'!F76:H76) -> 0 | D75: =SUM('TRANSFERENCIA CORRIENTE'!I76:K76) -> 0 | E75: =SUM('TRANSFERENCIA CORRIENTE'!L76:N76) -> 0 | G75: =SUM(VS!C76:E76) -> 0 | H75: =SUM(VS!F76:H76) -> 0 | I75: =SUM(VS!I76:K76) -> 0 | J75: =SUM(VS!L76:N76) -> 0 | L75: =SUM(B75+G75) -> 0 | M75: =SUM(C75+H75) -> 0 | N75: =SUM(D75+I75) -> 0 | O75: =SUM(E75+J75) -> 0
A76: 4.1.2 - INCREMENTO DE ACTIVOS FINANCIEROS NO CORRIENTES | B76: =SUM('TRANSFERENCIA CORRIENTE'!C77:E77) -> 0 | C76: =SUM('TRANSFERENCIA CORRIENTE'!F77:H77) -> 0 | D76: =SUM('TRANSFERENCIA CORRIENTE'!I77:K77) -> 0 | E76: =SUM('TRANSFERENCIA CORRIENTE'!L77:N77) -> 0 | G76: =SUM(VS!C77:E77) -> 0 | H76: =SUM(VS!F77:H77) -> 0 | I76: =SUM(VS!I77:K77) -> 0 | J76: =SUM(VS!L77:N77) -> 0 | L76: =SUM(B76+G76) -> 0 | M76: =SUM(C76+H76) -> 0 | N76: =SUM(D76+I76) -> 0 | O76: =SUM(E76+J76) -> 0
A77: 4.2 - DISMINUCIÓN DE PASIVOS | B77: =SUM('TRANSFERENCIA CORRIENTE'!C78:E78) -> 0 | C77: =SUM('TRANSFERENCIA CORRIENTE'!F78:H78) -> 0 | D77: =SUM('TRANSFERENCIA CORRIENTE'!I78:K78) -> 0 | E77: =SUM('TRANSFERENCIA CORRIENTE'!L78:N78) -> 0 | G77: =SUM(VS!C78:E78) -> 0 | H77: =SUM(VS!F78:H78) -> 0 | I77: =SUM(VS!I78:K78) -> 0 | J77: =SUM(VS!L78:N78) -> 0 | L77: =SUM(B77+G77) -> 0 | M77: =SUM(C77+H77) -> 0 | N77: =SUM(D77+I77) -> 0 | O77: =SUM(E77+J77) -> 0
A78: 4.2.1 - DISMINUCIÓN DE PASIVOS CORRIENTES | B78: =SUM('TRANSFERENCIA CORRIENTE'!C79:E79) -> 0 | C78: =SUM('TRANSFERENCIA CORRIENTE'!F79:H79) -> 0 | D78: =SUM('TRANSFERENCIA CORRIENTE'!I79:K79) -> 0 | E78: =SUM('TRANSFERENCIA CORRIENTE'!L79:N79) -> 0 | G78: =SUM(VS!C79:E79) -> 0 | H78: =SUM(VS!F79:H79) -> 0 | I78: =SUM(VS!I79:K79) -> 0 | J78: =SUM(VS!L79:N79) -> 0 | L78: =SUM(B78+G78) -> 0 | M78: =SUM(C78+H78) -> 0 | N78: =SUM(D78+I78) -> 0 | O78: =SUM(E78+J78) -> 0
A79: 4.2.2 - DISMINUCIÓN DE PASIVOS NO CORRIENTES | B79: =SUM('TRANSFERENCIA CORRIENTE'!C80:E80) -> 0 | C79: =SUM('TRANSFERENCIA CORRIENTE'!F80:H80) -> 0 | D79: =SUM('TRANSFERENCIA CORRIENTE'!I80:K80) -> 0 | E79: =SUM('TRANSFERENCIA CORRIENTE'!L80:N80) -> 0 | G79: =SUM(VS!C80:E80) -> 0 | H79: =SUM(VS!F80:H80) -> 0 | I79: =SUM(VS!I80:K80) -> 0 | J79: =SUM(VS!L80:N80) -> 0 | L79: =SUM(B79+G79) -> 0 | M79: =SUM(C79+H79) -> 0 | N79: =SUM(D79+I79) -> 0 | O79: =SUM(E79+J79) -> 0
A80: 4.3 - DISMINUCIÓN DE FONDOS DE TERCEROS | B80: =SUM('TRANSFERENCIA CORRIENTE'!C81:E81) -> 0 | C80: =SUM('TRANSFERENCIA CORRIENTE'!F81:H81) -> 0 | D80: =SUM('TRANSFERENCIA CORRIENTE'!I81:K81) -> 0 | E80: =SUM('TRANSFERENCIA CORRIENTE'!L81:N81) -> 0 | G80: =SUM(VS!C81:E81) -> 0 | H80: =SUM(VS!F81:H81) -> 0 | I80: =SUM(VS!I81:K81) -> 0 | J80: =SUM(VS!L81:N81) -> 0 | L80: =SUM(B80+G80) -> 0 | M80: =SUM(C80+H80) -> 0 | N80: =SUM(D80+I80) -> 0 | O80: =SUM(E80+J80) -> 0
A81: 4.3.5 - DISMINUCIÓN DEPÓSITOS FONDOS DE TERCEROS | B81: =SUM('TRANSFERENCIA CORRIENTE'!C82:E82) -> 0 | C81: =SUM('TRANSFERENCIA CORRIENTE'!F82:H82) -> 0 | D81: =SUM('TRANSFERENCIA CORRIENTE'!I82:K82) -> 0 | E81: =SUM('TRANSFERENCIA CORRIENTE'!L82:N82) -> 0 | G81: =SUM(VS!C82:E82) -> 0 | H81: =SUM(VS!F82:H82) -> 0 | I81: =SUM(VS!I82:K82) -> 0 | J81: =SUM(VS!L82:N82) -> 0 | L81: =SUM(B81+G81) -> 0 | M81: =SUM(C81+H81) -> 0 | N81: =SUM(D81+I81) -> 0 | O81: =SUM(E81+J81) -> 0
A82: TOTAL APLICACIONES FINANCIERAS | B82: =SUM(B83) -> 2.7188025e+08 | C82: =SUM(C83) -> 0 | D82: =SUM(D83) -> 0 | E82: =SUM(E83) -> 0 | G82: =SUM(G83) -> 26194616 | H82: =SUM(H83) -> 0 | I82: =SUM(I83) -> 0 | J82: =SUM(J83) -> 0 | L82: =SUM(B82+G82) -> 2.9807487e+08 | M82: =SUM(C82+H82) -> 0 | N82: =SUM(D82+I82) -> 0 | O82: =SUM(E82+J82) -> 0
A83: TOTAL GASTOS Y APLICACIONES FINANCIERAS | B83: =SUM('TRANSFERENCIA CORRIENTE'!C85:E85) -> 2.7188025e+08 | C83: =SUM('TRANSFERENCIA CORRIENTE'!F85:H85) -> 0 | D83: =SUM('TRANSFERENCIA CORRIENTE'!I85:K85) -> 0 | E83: =SUM('TRANSFERENCIA CORRIENTE'!L85:N85) -> 0 | G83: =SUM(VS!C85:E85) -> 26194616 | H83: =SUM(VS!F85:H85) -> 0 | I83: =SUM(VS!I85:K85) -> 0 | J83: =SUM(VS!L85:N85) -> 0 | L83: =SUM(B83+G83) -> 2.9807487e+08 | M83: =SUM(C83+H83) -> 0 | N83: =SUM(D83+I83) -> 0 | O83: =SUM(E83+J83) -> 0

Sheet TRANSFERENCIA CORRIENTE
A1: SERVICIO NACIONAL DE SALUD
A2: HOSPITAL MATERNO INFANTIL SAN LORENZO DE LOS MINA
A3: REGION
A4: Ejecución de Gastos Fondo (100) 2025
A5: En RD$
A7: Detalle | B7: Total | C7: Enero | D7: Febrero | E7: Marzo | F7: Abril | G7: Mayo | H7: Junio | I7: Julio | J7: Agosto | K7: Septiembre | L7: Octubre | M7: Noviembre | N7: Diciembre
A8: 2 - GASTOS
A9: 2.1 - REMUNERACIONES Y CONTRIBUCIONES | B9: =SUM(C9:N9) -> 1.9856074e+08 | C9: =SUM(C10:C14) -> 65091180 | D9: =SUM(D10:D14) -> 67131936 | E9: =SUM(E10:E14) -> 66337620 | F9: =SUM(F10:F14) -> 0 | G9: =SUM(G10:G14) -> 0 | H9: =SUM(H10:H14) -> 0 | I9: =SUM(I10:I14) -> 0 | J9: =SUM(J10:J14) -> 0 | ... N9: =SUM(N10:N14) -> 0
A10: 2.1.1 - REMUNERACIONES | B10: =SUM(C10:N10) -> 1.639452e+08 | C10: 53640339 | D10: 55586129 | E10: 54718737
A11: 2.1.2 - SOBRESUELDOS | B11: =SUM(C11:N11) -> 9594398.8 | C11: 3196999.6 | D11: 3197999.6 | E11: 3199399.6
A12: 2.1.3 - DIETAS Y GASTOS DE REPRESENTACIÓN | B12: =SUM(C12:N12) -> 0
A13: 2.1.4 - GRATIFICACIONES Y BONIFICACIONES | B13: =SUM(C13:N13) -> 0
A14: 2.1.5 - CONTRIBUCIONES A LA SEGURIDAD SOCIAL | B14: =SUM(C14:N14) -> 25021132 | C14: 8253841.6 | D14: 8347807.5 | E14: 8419483.2
A15: 2.2 - CONTRATACIÓN DE SERVICIOS | B15: =SUM(C15:N15) -> 9308364.9 | C15: =SUM(C16:C24) -> 0 | D15: =SUM(D16:D24) -> 1336968.6 | E15: =SUM(E16:E24) -> 7971396.2 | F15: =SUM(F16:F24) -> 0 | G15: =SUM(G16:G24) -> 0 | H15: =SUM(H16:H24) -> 0 | I15: =SUM(I16:I24) -> 0 | J15: =SUM(J16:J24) -> 0 | ... N15: =SUM(N16:N24) -> 0
A16: 2.2.1 - SERVICIOS BÁSICOS | B16: =SUM(C16:N16) -> 2020024.3 | E16: 2020024.3
A17: 2.2.2 - PUBLICIDAD, IMPRESIÓN Y ENCUADERNACIÓN | B17: =SUM(C17:N17) -> 324206.83 | D17: 324206.83
A18: 2.2.3 - VIÁTICOS | B18: =SUM(C18:N18) -> 0
A19: 2.2.4 - TRANSPORTE Y ALMACENAJE | B19: =SUM(C19:N19) -> 0
A20: 2.2.5 - ALQUILERES Y RENTAS | B20: =SUM(C20:N20) -> 0
A21: 2.2.6 - SEGUROS | B21: =SUM(C21:N21) -> 0
A22: 2.2.7 - SERVICIOS DE CONSERVACIÓN, REPARACIONES MENORES E INSTALACIONES TEMPORALES | B22: =SUM(C22:N22) -> 6474433.8 | D22: 523061.81 | E22: 5951371.9
A23: 2.2.8 - OTROS SERVICIOS NO INCLUIDOS EN CONCEPTOS ANTERIORES | B23: =SUM(C23:N23) -> 489700 | D23: 489700
A24: 2.2.9 - OTRAS CONTRATACIONES DE SERVICIOS | B24: =SUM(C24:N24) -> 0
A25: 2.3 - MATERIALES Y SUMINISTROS | B25: =SUM(C25:N25) -> 46153283 | C25: =SUM(C26:C34) -> 4970600.4 | D25: =SUM(D26:D34) -> 14433131 | E25: =SUM(E26:E34) -> 26749552 | F25: =SUM(F26:F34) -> 0 | G25: =SUM(G26:G34) -> 0 | H25: =SUM(H26:H34) -> 0 | I25: =SUM(I26:I34) -> 0 | J25: =SUM(J26:J34) -> 0 | ... N25: =SUM(N26:N34) -> 0
A26: 2.3.1 - ALIMENTOS Y PRODUCTOS AGROFORESTALES | D26: 591460.4 | E26: 3122436.8
A27: 2.3.2 - TEXTILES Y VESTUARIOS | D27: 61630.73
A28: 2.3.3 - PRODUCTOS DE PAPEL, CARTÓN E IMPRESOS | D28: 352366.67 | E28: 1474545.2
A29: 2.3.4 - PRODUCTOS FARMACÉUTICOS | C29: 1862880 | D29: 2014526.8 | E29: 6919929
A30: 2.3.5 - PRODUCTOS DE CUERO, CAUCHO Y PLÁSTICO | E30: 334708.95
A31: 2.3.6 - PRODUCTOS DE MINERALES, METÁLICOS Y NO METÁLICOS | D31: 11630.98
A32: 2.3.7 - COMBUSTIBLES, LUBRICANTES, PRODUCTOS QUÍMICOS Y CONEXOS | C32: 1844663.4 | D32: 3902915.5 | E32: 3162523
A33: 2.3.8 - GASTOS QUE SE ASIGNARÁN DURANTE EL EJERCICIO (ART. 32 Y 33 LEY 423-06)
A34: 2.3.9 - PRODUCTOS Y ÚTILES VARIOS | C34: 1263057 | D34: 7498600.4 | E34: 11735409
A35: 2.4 - TRANSFERENCIAS CORRIENTES | B35: =SUM(C35:N35) -> 0 | C35: =SUM(C36:C42) -> 0 | D35: =SUM(D36:D42) -> 0 | E35: =SUM(E36:E42) -> 0 | F35: =SUM(F36:F42) -> 0 | G35: =SUM(G36:G42) -> 0 | H35: =SUM(H36:H42) -> 0 | I35: =SUM(I36:I42) -> 0 | J35: =SUM(J36:J42) -> 0 | ... N35: =SUM(N36:N42) -> 0
A36: 2.4.1 - TRANSFERENCIAS CORRIENTES AL SECTOR PRIVADO | B36: =SUM(C36:N36) -> 0
A37: 2.4.2 - TRANSFERENCIAS CORRIENTES AL GOBIERNO GENERAL NACIONAL | B37: =SUM(C37:N37) -> 0
A38: 2.4.3 - TRANSFERENCIAS CORRIENTES A GOBIERNOS GENERALES LOCALES | B38: =SUM(C38:N38) -> 0
A39: 2.4.4 - TRANSFERENCIAS CORRIENTES A EMPRESAS PÚBLICAS NO FINANCIERAS | B39: =SUM(C39:N39) -> 0
A40: 2.4.5 - TRANSFERENCIAS CORRIENTES A INSTITUCIONES PÚBLICAS FINANCIERAS | B40: =SUM(C40:N40) -> 0
A41: 2.4.7 - TRANSFERENCIAS CORRIENTES AL SECTOR EXTERNO | B41: =SUM(C41:N41) -> 0
A42: 2.4.9 - TRANSFERENCIAS CORRIENTES A OTRAS INSTITUCIONES PÚBLICAS | B42: =SUM(C42:N42) -> 0
A43: 2.5 - TRANSFERENCIAS DE CAPITAL | B43: =SUM(C43:N43) -> 0 | C43: =SUM(C44:C50) -> 0 | D43: =SUM(D44:D50) -> 0 | E43: =SUM(E44:E50) -> 0 | F43: =SUM(F44:F50) -> 0 | G43: =SUM(G44:G50) -> 0 | H43: =SUM(H44:H50) -> 0 | I43: =SUM(I44:I50) -> 0 | J43: =SUM(J44:J50) -> 0 | ... N43: =SUM(N44:N50) -> 0
A44: 2.5.1 - TRANSFERENCIAS DE CAPITAL AL SECTOR PRIVADO | B44: =SUM(C44:N44) -> 0
A45: 2.5.2 - TRANSFERENCIAS DE CAPITAL AL GOBIERNO GENERAL NACIONAL | B45: =SUM(C45:N45) -> 0
A46: 2.5.3 - TRANSFERENCIAS DE CAPITAL A GOBIERNOS GENERALES LOCALES | B46: =SUM(C46:N46) -> 0
A47: 2.5.4 - TRANSFERENCIAS DE CAPITAL A EMPRESAS PÚBLICAS NO FINANCIERAS | B47: =SUM(C47:N47) -> 0
A48: 2.5.5 - TRANSFERENCIAS DE CAPITAL A INSTITUCIONES PÚBLICAS FINANCIERAS | B48: =SUM(C48:N48) -> 0
A49: 2.5.6 - TRANSFERENCIAS DE CAPITAL AL SECTOR EXTERNO | B49: =SUM(C49:N49) -> 0
A50: 2.5.9 - TRANSFERENCIAS DE CAPITAL A OTRAS INSTITUCIONES PÚBLICAS | B50: =SUM(C50:N50) -> 0
A51: 2.6 - BIENES MUEBLES, INMUEBLES E INTANGIBLES | B51: =SUM(C51:N51) -> 17857867 | C51: =SUM(C52:C60) -> 0 | D51: =SUM(D52:D60) -> 6461017.3 | E51: =SUM(E52:E60) -> 11396849 | F51: =SUM(F52:F60) -> 0 | G51: =SUM(G52:G60) -> 0 | H51: =SUM(H52:H60) -> 0 | I51: =SUM(I52:I60) -> 0 | J51: =SUM(J52:J60) -> 0 | ... N51: =SUM(N52:N60) -> 0
A52: 2.6.1 - MOBILIARIO Y EQUIPO | B52: =SUM(C52:N52) -> 1110625.9 | D52: 432420.86 | E52: 678205
A53: 2.6.2 - MOBILIARIO Y EQUIPO EDUCACIONAL Y RECREATIVO | B53: =SUM(C53:N53) -> 0
A54: 2.6.3 - EQUIPO E INSTRUMENTAL, CIENTÍFICO Y LABORATORIO | B54: =SUM(C54:N54) -> 16744041 | D54: 6028596.4 | E54: 10715444
A55: 2.6.4 - VEHÍCULOS Y EQUIPO DE TRANSPORTE, TRACCIÓN Y ELEVACIÓN | B55: =SUM(C55:N55) -> 0
A56: 2.6.5 - MAQUINARIA, OTROS EQUIPOS Y HERRAMIENTAS | B56: =SUM(C56:N56) -> 3199.97 | E56: 3199.97
A57: 2.6.6 - EQUIPOS DE DEFENSA Y SEGURIDAD | B57: =SUM(C57:N57) -> 0
A58: 2.6.7 - ACTIVOS BIÓLOGICOS CULTIVABLES | B58: =SUM(C58:N58) -> 0
A59: 2.6.8 - BIENES INTANGIBLES | B59: =SUM(C59:N59) -> 0
A60: 2.6.9 - EDIFICIOS, ESTRUCTURAS, TIERRAS, TERRENOS Y OBJETOS DE VALOR | B60: =SUM(C60:N60) -> 0
A61: 2.7 - OBRAS | B61: =SUM(C61:N61) -> 0 | C61: =SUM(C62:C65) -> 0 | D61: =SUM(D62:D65) -> 0 | E61: =SUM(E62:E65) -> 0 | F61: =SUM(F62:F65) -> 0 | G61: =SUM(G62:G65) -> 0 | H61: =SUM(H62:H65) -> 0 | I61: =SUM(I62:I65) -> 0 | J61: =SUM(J62:J65) -> 0 | ... N61: =SUM(N62:N65) -> 0
A62: 2.7.1 - OBRAS EN EDIFICACIONES | B62: =SUM(C62:N62) -> 0
A63: 2.7.2 - INFRAESTRUCTURA | B63: =SUM(C63:N63) -> 0
A64: 2.7.3 - CONSTRUCCIONES EN BIENES CONCESIONADOS | B64: =SUM(C64:N64) -> 0
A65: 2.7.4 - GASTOS QUE SE ASIGNARÁN DURANTE EL EJERCICIO PARA INVERSIÓN (ART. 32 Y 33 LEY 423-06) | B65: =SUM(C65:N65) -> 0
A66: 2.8 - ADQUISICION DE ACTIVOS FINANCIEROS CON FINES DE POLÍTICA | B66: =SUM(C66:N66) -> 0 | C66: =SUM(C67:C68) -> 0 | D66: =SUM(D67:D68) -> 0 | E66: =SUM(E67:E68) -> 0 | F66: =SUM(F67:F68) -> 0 | G66: =SUM(G67:G68) -> 0 | H66: =SUM(H67:H68) -> 0 | I66: =SUM(I67:I68) -> 0 | J66: =SUM(J67:J68) -> 0 | ... N66: =SUM(N67:N68) -> 0
A67: 2.8.1 - CONCESIÓN DE PRESTAMOS | B67: =SUM(C67:N67) -> 0
A68: 2.8.2 - ADQUISICIÓN DE TÍTULOS VALORES REPRESENTATIVOS DE DEUDA | B68: =SUM(C68:N68) -> 0
A69: 2.9 - GASTOS FINANCIEROS | B69: =SUM(C69:N69) -> 0 | C69: =SUM(C70:C72) -> 0 | D69: =SUM(D70:D72) -> 0 | E69: =SUM(E70:E72) -> 0 | F69: =SUM(F70:F72) -> 0 | G69: =SUM(G70:G72) -> 0 | H69: =SUM(H70:H72) -> 0 | I69: =SUM(I70:I72) -> 0 | J69: =SUM(J70:J72) -> 0 | ... N69: =SUM(N70:N72) -> 0
A70: 2.9.1 - INTERESES DE LA DEUDA PÚBLICA INTERNA | B70: =SUM(C70:N70) -> 0
A71: 2.9.2 - INTERESES DE LA DEUDA PUBLICA EXTERNA | B71: =SUM(C71:N71) -> 0
A72: 2.9.4 - COMISIONES Y OTROS GASTOS BANCARIOS DE LA DEUDA PÚBLICA | B72: =SUM(C72:N72) -> 0
A73: Total Gastos | B73: =B9+B15+B25+B35+B43+B51+B61+B66+B69 -> 2.7188025e+08 | C73: =C9+C15+C25+C35+C43+C51+C61+C66+C69 -> 70061780 | D73: =D9+D15+D25+D35+D43+D51+D61+D66+D69 -> 89363053 | E73: =E9+E15+E25+E35+E43+E51+E61+E66+E69 -> 1.1245542e+08 | F73: =F9+F15+F25+F35+F43+F51+F61+F66+F69 -> 0 | G73: =G9+G15+G25+G35+G43+G51+G61+G66+G69 -> 0 | H73: =H9+H15+H25+H35+H43+H51+H61+H66+H69 -> 0 | I73: =I9+I15+I25+I35+I43+I51+I61+I66+I69 -> 0 | ... N73: =N9+N15+N25+N35+N43+N51+N61+N66+N69 -> 0
A74: 4 - APLICACIONES FINANCIERAS
A75: 4.1 - INCREMENTO DE ACTIVOS FINANCIEROS
A76: 4.1.1 - INCREMENTO DE ACTIVOS FINANCIEROS CORRIENTES
A77: 4.1.2 - INCREMENTO DE ACTIVOS FINANCIEROS NO CORRIENTES
A78: 4.2 - DISMINUCIÓN DE PASIVOS
A79: 4.2.1 - DISMINUCIÓN DE PASIVOS CORRIENTES
A80: 4.2.2 - DISMINUCIÓN DE PASIVOS NO CORRIENTES
A81: 4.3 - DISMINUCIÓN DE FONDOS DE TERCEROS
A82: 4.3.5 - DISMINUCIÓN DEPÓSITOS FONDOS DE TERCEROS
A83: TOTAL APLICACIONES FINANCIERAS
A85: TOTAL GASTOS Y APLICACIONES FINANCIERAS | B85: =+B83+B73 -> 2.7188025e+08 | C85: =+C83+C73 -> 70061780 | D85: =+D83+D73 -> 89363053 | E85: =+E83+E73 -> 1.1245542e+08 | F85: =+F83+F73 -> 0 | G85: =+G83+G73 -> 0 | H85: =+H83+H73 -> 0 | I85: =+I83+I73 -> 0 | ... N85: =+N83+N73 -> 0
A86: Fuente: [fuente]
A87: Fecha de registro: hasta el [día] de [mes] del [año]
A88: Fecha de imputación: hasta el [día] de [mes] del [año]

Sheet VS
A1: SERVICIO NACIONAL DE SALUD
A2: HOSPITAL MATERNO INFANTIL SAN LORENZO DE LOS MINA
A3: REGION
A4: Ejecución de Gastos VENTA SERVICIOS 2024
A5: En RD$
A7: Detalle | B7: Total | C7: Enero | D7: Febrero | E7: Marzo | F7: Abril | G7: Mayo | H7: Junio | I7: Julio | J7: Agosto | K7: Septiembre | L7: Octubre | M7: Noviembre | N7: Diciembre
A8: 2 - GASTOS
A9: 2.1 - REMUNERACIONES Y CONTRIBUCIONES | B9: =SUM(C9:N9) -> 5231553.6 | C9: =SUM(C10:C14) -> 0 | D9: =SUM(D10:D14) -> 0 | E9: =SUM(E10:E14) -> 5231553.6 | F9: =SUM(F10:F14) -> 0 | G9: =SUM(G10:G14) -> 0 | H9: =SUM(H10:H14) -> 0 | I9: =SUM(I10:I14) -> 0 | J9: =SUM(J10:J14) -> 0 | ... N9: =SUM(N10:N14) -> 0
A10: 2.1.1 - REMUNERACIONES | B10: =SUM(C10:N10) -> 0
A11: 2.1.2 - SOBRESUELDOS | B11: =SUM(C11:N11) -> 5231553.6 | E11: 5231553.6
A12: 2.1.3 - DIETAS Y GASTOS DE REPRESENTACIÓN | B12: =SUM(C12:N12) -> 0
A13: 2.1.4 - GRATIFICACIONES Y BONIFICACIONES | B13: =SUM(C13:N13) -> 0
A14: 2.1.5 - CONTRIBUCIONES A LA SEGURIDAD SOCIAL | B14: =SUM(C14:N14) -> 0
A15: 2.2 - CONTRATACIÓN DE SERVICIOS | B15: =SUM(C15:N15) -> 8306683.8 | C15: =SUM(C16:C24) -> 2733844.3 | D15: =SUM(D16:D24) -> 1213383.4 | E15: =SUM(E16:E24) -> 4359456.2 | F15: =SUM(F16:F24) -> 0 | G15: =SUM(G16:G24) -> 0 | H15: =SUM(H16:H24) -> 0 | I15: =SUM(I16:I24) -> 0 | J15: =SUM(J16:J24) -> 0 | ... N15: =SUM(N16:N24) -> 0
A16: 2.2.1 - SERVICIOS BÁSICOS | B16: =SUM(C16:N16) -> 2341561.9 | C16: 351316.33 | D16: 259054.4 | E16: 1731191.2
A17: 2.2.2 - PUBLICIDAD, IMPRESIÓN Y ENCUADERNACIÓN | B17: =SUM(C17:N17) -> 0
A18: 2.2.3 - VIÁTICOS | B18: =SUM(C18:N18) -> 0
A19: 2.2.4 - TRANSPORTE Y ALMACENAJE | B19: =SUM(C19:N19) -> 56000 | D19: 24000 | E19: 32000
A20: 2.2.5 - ALQUILERES Y RENTAS | B20: =SUM(C20:N20) -> 519625.15 | C20: 266664.25 | D20: 252960.9
A21: 2.2.6 - SEGUROS | B21: =SUM(C21:N21) -> 0
A22: 2.2.7 - SERVICIOS DE CONSERVACIÓN, REPARACIONES MENORES E INSTALACIONES TEMPORALES | B22: =SUM(C22:N22) -> 4556850.1 | C22: 2064518.4 | D22: =215685.19+42142.86+18061.22+33714.29+21673.47+18061.22+115591.83+7826.53 -> 472756.61 | E22: 2019575.2
A23: 2.2.8 - OTROS SERVICIOS NO INCLUIDOS EN CONCEPTOS ANTERIORES | B23: =SUM(C23:N23) -> 832646.66 | C23: 51345.35 | D23: =193432+11179.44 -> 204611.44 | E23: 576689.87
A24: 2.2.9 - OTRAS CONTRATACIONES DE SERVICIOS | B24: =SUM(C24:N24) -> 0
A25: 2.3 - MATERIALES Y SUMINISTROS | B25: =SUM(C25:N25) -> 7292547.3 | C25: =SUM(C26:C34) -> 3062630.7 | D25: =SUM(D26:D34) -> 2432378.3 | E25: =SUM(E26:E34) -> 1797538.3 | F25: =SUM(F26:F34) -> 0 | G25: =SUM(G26:G34) -> 0 | H25: =SUM(H26:H34) -> 0 | I25: =SUM(I26:I34) -> 0 | J25: =SUM(J26:J34) -> 0 | ... N25: =SUM(N26:N34) -> 0
A26: 2.3.1 - ALIMENTOS Y PRODUCTOS AGROFORESTALES | B26: =SUM(C26:N26) -> 1500755.8 | C26: 541265 | D26: 300691.8 | E26: 658799
A27: 2.3.2 - TEXTILES Y VESTUARIOS | B27: =SUM(C27:N27) -> 0
A28: 2.3.3 - PRODUCTOS DE PAPEL, CARTÓN E IMPRESOS | B28: =SUM(C28:N28) -> 251163 | C28: 85550 | D28: 107616 | E28: 57997
A29: 2.3.4 - PRODUCTOS FARMACÉUTICOS | B29: =SUM(C29:N29) -> 558000 | C29: 308000 | E29: 250000
A30: 2.3.5 - PRODUCTOS DE CUERO, CAUCHO Y PLÁSTICO | B30: =SUM(C30:N30) -> 567494.87 | D30: 249831.2 | E30: 317663.67
A31: 2.3.6 - PRODUCTOS DE MINERALES, METÁLICOS Y NO METÁLICOS | B31: =SUM(C31:N31) -> 293957.3 | D31: 183732.33 | E31: 110224.97
A32: 2.3.7 - COMBUSTIBLES, LUBRICANTES, PRODUCTOS QUÍMICOS Y CONEXOS | B32: =SUM(C32:N32) -> 1660334.6 | C32: 228412.84 | D32: 1114592.7 | E32: 317328.99
A33: 2.3.8 - GASTOS QUE SE ASIGNARÁN DURANTE EL EJERCICIO (ART. 32 Y 33 LEY 423-06) | B33: =SUM(C33:N33) -> 0
A34: 2.3.9 - PRODUCTOS Y ÚTILES VARIOS | B34: =SUM(C34:N34) -> 2460841.8 | C34: 1899402.8 | D34: =423850.01+52064.22 -> 475914.23 | E34: 85524.69
A35: 2.4 - TRANSFERENCIAS CORRIENTES | B35: =SUM(C35:N35) -> 287786.7 | C35: =SUM(C36:C42) -> 136966.7 | D35: =SUM(D36:D42) -> 23400 | E35: =SUM(E36:E42) -> 127420 | F35: =SUM(F36:F42) -> 0 | G35: =SUM(G36:G42) -> 0 | H35: =SUM(H36:H42) -> 0 | I35: =SUM(I36:I42) -> 0 | J35: =SUM(J36:J42) -> 0 | ... N35: =SUM(N36:N42) -> 0
A36: 2.4.1 - TRANSFERENCIAS CORRIENTES AL SECTOR PRIVADO | B36: =SUM(C36:N36) -> 287786.7 | C36: 136966.7 | D36: 23400 | E36: 127420
A37: 2.4.2 - TRANSFERENCIAS CORRIENTES AL GOBIERNO GENERAL NACIONAL | B37: =SUM(C37:N37) -> 0
A38: 2.4.3 - TRANSFERENCIAS CORRIENTES A GOBIERNOS GENERALES LOCALES | B38: =SUM(C38:N38) -> 0
A39: 2.4.4 - TRANSFERENCIAS CORRIENTES A EMPRESAS PÚBLICAS NO FINANCIERAS | B39: =SUM(C39:N39) -> 0
A40: 2.4.5 - TRANSFERENCIAS CORRIENTES A INSTITUCIONES PÚBLICAS FINANCIERAS | B40: =SUM(C40:N40) -> 0
A41: 2.4.7 - TRANSFERENCIAS CORRIENTES AL SECTOR EXTERNO | B41: =SUM(C41:N41) -> 0
A42: 2.4.9 - TRANSFERENCIAS CORRIENTES A OTRAS INSTITUCIONES PÚBLICAS | B42: =SUM(C42:N42) -> 0
A43: 2.5 - TRANSFERENCIAS DE CAPITAL | B43: =SUM(C43:N43) -> 0 | C43: =SUM(C44:C50) -> 0 | D43: =SUM(D44:D50) -> 0 | E43: =SUM(E44:E50) -> 0 | F43: =SUM(F44:F50) -> 0 | G43: =SUM(G44:G50) -> 0 | H43: =SUM(H44:H50) -> 0 | I43: =SUM(I44:I50) -> 0 | J43: =SUM(J44:J50) -> 0 | ... N43: =SUM(N44:N50) -> 0
A44: 2.5.1 - TRANSFERENCIAS DE CAPITAL AL SECTOR PRIVADO | B44: =SUM(C44:N44) -> 0
A45: 2.5.2 - TRANSFERENCIAS DE CAPITAL AL GOBIERNO GENERAL NACIONAL | B45: =SUM(C45:N45) -> 0
A46: 2.5.3 - TRANSFERENCIAS DE CAPITAL A GOBIERNOS GENERALES LOCALES | B46: =SUM(C46:N46) -> 0
A47: 2.5.4 - TRANSFERENCIAS DE CAPITAL A EMPRESAS PÚBLICAS NO FINANCIERAS | B47: =SUM(C47:N47) -> 0
A48: 2.5.5 - TRANSFERENCIAS DE CAPITAL A INSTITUCIONES PÚBLICAS FINANCIERAS | B48: =SUM(C48:N48) -> 0
A49: 2.5.6 - TRANSFERENCIAS DE CAPITAL AL SECTOR EXTERNO | B49: =SUM(C49:N49) -> 0
A50: 2.5.9 - TRANSFERENCIAS DE CAPITAL A OTRAS INSTITUCIONES PÚBLICAS | B50: =SUM(C50:N50) -> 0
A51: 2.6 - BIENES MUEBLES, INMUEBLES E INTANGIBLES | B51: =SUM(C51:N51) -> 5076044.2 | C51: =SUM(C52:C60) -> 887994.84 | D51: =SUM(D52:D60) -> 3887510 | E51: =SUM(E52:E60) -> 300539.37 | F51: =SUM(F52:F60) -> 0 | G51: =SUM(G52:G60) -> 0 | H51: =SUM(H52:H60) -> 0 | I51: =SUM(I52:I60) -> 0 | J51: =SUM(J52:J60) -> 0 | ... N51: =SUM(N52:N60) -> 0
A52: 2.6.1 - MOBILIARIO Y EQUIPO | B52: =SUM(C52:N52) -> 0
A53: 2.6.2 - MOBILIARIO Y EQUIPO EDUCACIONAL Y RECREATIVO | B53: =SUM(C53:N53) -> 0
A54: 2.6.3 - EQUIPO E INSTRUMENTAL, CIENTÍFICO Y LABORATORIO | B54: =SUM(C54:N54) -> 2963024.8 | C54: 887994.84 | D54: 2075030
A55: 2.6.4 - VEHÍCULOS Y EQUIPO DE TRANSPORTE, TRACCIÓN Y ELEVACIÓN | B55: =SUM(C55:N55) -> 107609.37 | E55: 107609.37
A56: 2.6.5 - MAQUINARIA, OTROS EQUIPOS Y HERRAMIENTAS | B56: =SUM(C56:N56) -> 2005410 | D56: 1812480 | E56: 192930
A57: 2.6.6 - EQUIPOS DE DEFENSA Y SEGURIDAD | B57: =SUM(C57:N57) -> 0
A58: 2.6.7 - ACTIVOS BIÓLOGICOS CULTIVABLES | B58: =SUM(C58:N58) -> 0
A59: 2.6.8 - BIENES INTANGIBLES | B59: =SUM(C59:N59) -> 0
A60: 2.6.9 - EDIFICIOS, ESTRUCTURAS, TIERRAS, TERRENOS Y OBJETOS DE VALOR | B60: =SUM(C60:N60) -> 0
A61: 2.7 - OBRAS | B61: =SUM(C61:N61) -> 0 | C61: =SUM(C62:C65) -> 0 | D61: =SUM(D62:D65) -> 0 | E61: =SUM(E62:E65) -> 0 | F61: =SUM(F62:F65) -> 0 | G61: =SUM(G62:G65) -> 0 | H61: =SUM(H62:H65) -> 0 | I61: =SUM(I62:I65) -> 0 | J61: =SUM(J62:J65) -> 0 | ... N61: =SUM(N62:N65) -> 0
A62: 2.7.1 - OBRAS EN EDIFICACIONES | B62: =SUM(C62:N62) -> 0
A63: 2.7.2 - INFRAESTRUCTURA | B63: =SUM(C63:N63) -> 0
A64: 2.7.3 - CONSTRUCCIONES EN BIENES CONCESIONADOS | B64: =SUM(C64:N64) -> 0
A65: 2.7.4 - GASTOS QUE SE ASIGNARÁN DURANTE EL EJERCICIO PARA INVERSIÓN (ART. 32 Y 33 LEY 423-06) | B65: =SUM(C65:N65) -> 0
A66: 2.8 - ADQUISICION DE ACTIVOS FINANCIEROS CON FINES DE POLÍTICA | B66: =SUM(C66:N66) -> 0 | C66: =SUM(C67:C68) -> 0 | D66: =SUM(D67:D68) -> 0 | E66: =SUM(E67:E68) -> 0 | F66: =SUM(F67:F68) -> 0 | G66: =SUM(G67:G68) -> 0 | H66: =SUM(H67:H68) -> 0 | I66: =SUM(I67:I68) -> 0 | J66: =SUM(J67:J68) -> 0 | ... N66: =SUM(N67:N68) -> 0
A67: 2.8.1 - CONCESIÓN DE PRESTAMOS | B67: =SUM(C67:N67) -> 0
A68: 2.8.2 - ADQUISICIÓN DE TÍTULOS VALORES REPRESENTATIVOS DE DEUDA | B68: =SUM(C68:N68) -> 0
A69: 2.9 - GASTOS FINANCIEROS | B69: =SUM(C69:N69) -> 0 | C69: =SUM(C70:C72) -> 0 | D69: =SUM(D70:D72) -> 0 | E69: =SUM(E70:E72) -> 0 | F69: =SUM(F70:F72) -> 0 | G69: =SUM(G70:G72) -> 0 | H69: =SUM(H70:H72) -> 0 | I69: =SUM(I70:I72) -> 0 | J69: =SUM(J70:J72) -> 0 | ... N69: =SUM(N70:N72) -> 0
A70: 2.9.1 - INTERESES DE LA DEUDA PÚBLICA INTERNA | B70: =SUM(C70:N70) -> 0
A71: 2.9.2 - INTERESES DE LA DEUDA PUBLICA EXTERNA | B71: =SUM(C71:N71) -> 0
A72: 2.9.4 - COMISIONES Y OTROS GASTOS BANCARIOS DE LA DEUDA PÚBLICA | B72: =SUM(C72:N72) -> 0
A73: Total Gastos | B73: =B9+B15+B25+B35+B43+B51+B61+B66+B69 -> 26194616 | C73: =C9+C15+C25+C35+C43+C51+C61+C66+C69 -> 6821436.5 | D73: =D9+D15+D25+D35+D43+D51+D61+D66+D69 -> 7556671.6 | E73: =E9+E15+E25+E35+E43+E51+E61+E66+E69 -> 11816507 | F73: =F9+F15+F25+F35+F43+F51+F61+F66+F69 -> 0 | G73: =G9+G15+G25+G35+G43+G51+G61+G66+G69 -> 0 | H73: =H9+H15+H25+H35+H43+H51+H61+H66+H69 -> 0 | I73: =I9+I15+I25+I35+I43+I51+I61+I66+I69 -> 0 | ... N73: =N9+N15+N25+N35+N43+N51+N61+N66+N69 -> 0
A74: 4 - APLICACIONES FINANCIERAS
A75: 4.1 - INCREMENTO DE ACTIVOS FINANCIEROS
A76: 4.1.1 - INCREMENTO DE ACTIVOS FINANCIEROS CORRIENTES
A77: 4.1.2 - INCREMENTO DE ACTIVOS FINANCIEROS NO CORRIENTES
A78: 4.2 - DISMINUCIÓN DE PASIVOS
A79: 4.2.1 - DISMINUCIÓN DE PASIVOS CORRIENTES
A80: 4.2.2 - DISMINUCIÓN DE PASIVOS NO CORRIENTES
A81: 4.3 - DISMINUCIÓN DE FONDOS DE TERCEROS
A82: 4.3.5 - DISMINUCIÓN DEPÓSITOS FONDOS DE TERCEROS
A83: TOTAL APLICACIONES FINANCIERAS
A85: TOTAL GASTOS Y APLICACIONES FINANCIERAS | B85: =+B83+B73 -> 26194616 | C85: =+C83+C73 -> 6821436.5 | D85: =+D83+D73 -> 7556671.6 | E85: =+E83+E73 -> 11816507
A86: Fuente: [fuente]
A87: Fecha de registro: hasta el [día] de [mes] del [año]
A88: Fecha de imputación: hasta el [día] de [mes] del [año]

Sheet OBLIGACIONES PENDIENTES
B4: SERVICIO REGIONAL DE SALUD
B5: DIRECCIÓN DE FISCALIZACIÓN Y CONTROL
B6: DETALLE OBLIGACIONES CONTRAÍDAS PENDIENTES AL 31 DE MARZO 2025
B7: HOSPITAL MATERNO INFANTIL SAN LORENZO DE LOS MINA
B8: A | C8: B | E8: C | F8: D | G8: E | H8: F
B9: TIPO | C9: PERÍODO | F9: STATUS PRESTAMO
C10: DESDE | D10: HASTA | E10: MONTO | F10: MONTO ORIGEN | G10: MONTO AMORTIZADO | H10: BALANCE PENDIENTE
B11: PROMESE CAL
B12: RETENCIONES DE IMPUESTOS (DGII) | C12: 44470 | D12: 45747 | E12: =6455721.37+191917.63+545919.42+146780.59+231604.06+289366.65+335354.64+387110.47+660164.03+254405.37+295100.71+268154.84+476725.77+301006.83+418780.67+471731.75+276884.63 -> 12006729
B13: APROVISIONAMIENTOS DE INCENTIVOS | C13: 45505 | D13: 45747 | E13: =4432093.625+933892.46+332731.24+782528.07 -> 6481245.4
B14: SEGURIDAD SOCIAL
B15: APROVISIONAMIENTO DE REGALIA PASCUAL
B16: PRESTACIONES LABORALES | C16: 45689 | D16: 45747 | E16: 181111.08
B17: VIATICOS
B18: PRÉSTAMOS Y/O ANTICIPOS FINANCIEROS OTORGADOS POR SENASA
B19: TOTAL | E19: =SUM(E12:E18)+E11 -> 18669086
B21: Nota. En el caso de las columnas D, E y F, solo aplican para llenado de los préstamos otogados por SENASA.
B25: Preparado por: | E25: Revisado por:

Sheet INGR SEGUN ORIGEN
A3: Servicio Nacional de Salud
A4: Dirección de Fiscalización
A6: Comportamiento de Ingresos percibidos Segregados según Origen
A7: Establecimiento: HOSPITAL MATERNO INFANTIL SAN LORENZO DE LOS MINA Mes: MARZO . Año: 2025 SRS: I
A8: . | B8: ARS | C8: Fecha deposito | D8: No. De Documento de referencia | E8: valor de Transferencia o Cheque
A9: INGRESOS | B9: FONDO 100(2.1) | E9: =79621891.83+4931430 -> 84553322
B10: FONDO 100(2.3) | E10: 12593841
B11: FONDO 100(2.6) | E11: =1000000+800000+800000+569632.08 -> 3169632.1
A12: Sub-Total | E12: =SUM(E9:E11) -> 1.003168e+08
A13: Venta de Servicio | B13: SUBSIDIADO | C13: 45719 | E13: 4595181.4
B14: SENASA POR ATENCION ODONTOLOGICA | C14: 45744 | E14: 50000
B15: CONTRIBUTIDO | C15: 45730 | E15: 1041144.3
B16: ARS YUNEN | C16: 45744 | E16: 14338.35
B17: ARS FUTURO | C17: 45741 | E17: 356314.76
B18: ARS ASEMAP | C18: 45740 | E18: 102672.34
B19: ARS PRIMERA | C19: 45737 | E19: 262926.38
B20: ARS HUMANO | C20: 45737 | E20: 34117.68
B21: ARS MONUMENTAL | C21: 45719 | E21: 237322.18
C22: 45730 | E22: 11220.43
B23: ARS RENACER, SA | C23: 45733 | E23: 222620.34
B24: ARS MAPHRE | C24: 45736 | E24: 16298.76
B25: ARS MAPHRE | C25: 45736 | E25: 15397.47
B26: ARS MAPHRE | C26: 45736 | E26: 30434.4
B27: ARS MAPHRE | C27: 45736 | E27: 65463.45
B28: ARS MAPHRE | C28: 45736 | E28: 12863.4
B29: ARS MAPHRE | C29: 45736 | E29: 155572.92
B30: ARS MAPHRE | C30: 45736 | E30: 309977.48
B31: ARS MAPHRE | C31: 45736 | E31: 504
B32: ARS META SALUD | C32: 45736 | E32: 1396
B33: ARS SEMMA | C33: 45737 | E33: 77169.4
B34: ARS APS | C34: 45737 | E34: 212345.21
B36: INGR. POR FACT DE SERV. DE INSTITUCIONES
A37: Sub-Total | E37: =SUM(E13:E36) -> 7825280.6
A38: OTROS APORTES | B38: Cafetería | C38: PAGO APLICADO EN EL MES DE DICIEMBRE CUBRIENDO DESDE ENERO A ABRIL RD$100,000.00
B39: Odontologia (facturacion servicios no contemplado en Plan Basico) | E39: 223625
B40: Alquiler de espacios internos a terceros
B41: Aportes provenientes de convenios Institucionales
B42: INGRESOS POR SERVICIOS PACIENTES PRIVADOS Y DIFERENCIAS POR SEGUROS MEDICOS
B43: Otros (Identificar Fuente )
A44: Sub-Total | E44: =SUM(E38:E41) -> 223625
A45: Total General | E45: =E37+E44+E12 -> 1.083657e+08
A48: Bajo las funciones que nos asisten certificamos que el valor de los ingresos percibidos durante el mes de marzo de 2025, correspondieron a un monto de RD$108,365,700.73
A51: Dado a los 31 dias del mes de marzo del año 2025.
A53: Cuenta Núm. | B53: Balance en libro | C53: Balance en Banco | D53: Balance Conciliado
A54: 010-390450-6 | B54: 4614.79 | C54: 7332169.7 | D54: 4614.79
A60: Preparado por: | D60: Revisado por:
B61: ____________________________________ | D61: ___________________________________
A62: Aprobado por:
B63: ________________________________

Sheet DEUDA
A1: Servicio Nacional de Salud
A2: DIRECCION DE FISCALIZACION
A3: RELACION DEUDA
A4: ESTABLECIMIENTO: | B4: HOSPITAL MATERNO INFANTIL SAN LORENZO DE LOS MINA | D4: CUENTAS POR PAGAR A: | E4: 45717
A6: NO | B6: NOMBRES PROVEEDOR | C6: CONCEPTO | D6: FUENTE FINANCIMIENTO | E6: Años anteriores 2020 | F6: AL 31 DICIEMBRE 2021 | G6: AL 31 DICIEMBRE 2022 | H6: AL 31 DICIEMBRE 2023 | I6: Al 31 DICIEMBRE 2024 | J6: AL 31 DE ENERO 2025 | K6: AL 28 DE FEBRERO 2025 | L6: 31 DE MARZO 2025 | M6: TOTAL ADEUDA
A7: 1 | B7: Copem Hospiclinic, SRL | D7: VS/FG | G7: 14300 | M7: =SUM(E7:L7) -> 14300
A8: 2 | B8: Hospifar, SRL | D8: VS/FG | H8: 11375 | M8: =SUM(E8:L8) -> 11375
A9: 3 | B9: Hospifar, SRL | D9: VS/FG | H9: 94965 | M9: =SUM(E9:L9) -> 94965
A10: 4 | B10: BRONTILLO | D10: VS/FG | H10: 88116 | M10: =SUM(E10:L10) -> 88116
A11: 5 | B11: Ventas Diversas Farmaceuticas, SRL (VENDIFAR) | D11: VS/FG | H11: 224775 | M11: =SUM(E11:L11) -> 224775
A12: 6 | B12: GA INTERPRISE IMPORT, SRL | D12: VS/FG | H12: 287920 | M12: =SUM(E12:L12) -> 287920
A13: 7 | B13: D, CORA INDUSTRIAL, S.R.L | D13: VS/FG | H13: 220483.05 | M13: =SUM(E13:L13) -> 220483.05
A14: 8 | B14: VARA, SRL. | D14: VS/FG | H14: 58382.86 | M14: =SUM(E14:L14) -> 58382.86
A15: 9 | B15: Ventas Diversas Farmaceuticas, SRL (VENDIFAR) | D15: VS/FG | H15: 171690 | M15: =SUM(E15:L15) -> 171690
A16: 10 | B16: RONAJUS FARMACEUTICA SRL | D16: VS/FG | H16: 200600 | M16: =SUM(E16:L16) -> 200600
A17: 11 | B17: Morami, SRL | D17: VS/FG | H17: 213260 | M17: =SUM(E17:L17) -> 213260
A18: 12 | B18: Leromed Pharma, SRL | D18: VS/FG | H18: 167208 | M18: =SUM(E18:L18) -> 167208
A19: 13 | B19: Caribbean Integrated Solutions, SRL | D19: VS/FG | H19: 400 | M19: =SUM(E19:L19) -> 400
A20: 14 | B20: Insocorp, S.R.L. | D20: VS/FG | H20: 150096 | M20: =SUM(E20:L20) -> 150096
A21: 15 | B21: SLYKING GROUP, SRL | D21: VS/FG | I21: 39361.26 | M21: =SUM(E21:L21) -> 39361.26
A22: 16 | B22: FARMACIA RUTH | D22: VS/FG | I22: 88100 | M22: =SUM(E22:L22) -> 88100
A23: 17 | B23: Macrotech Farmacéutica, SRL | D23: VS/FG | I23: 215000 | M23: =SUM(E23:L23) -> 215000
A24: 18 | B24: Air Liquide Dominicana, SAS | D24: VS/FG | I24: 6369.3686 | M24: =SUM(E24:L24) -> 6369.3686
A25: 19 | B25: LE.F.P CONSULTORES SRL | D25: VS/FG | I25: 48852 | M25: =SUM(E25:L25) -> 48852
A26: 20 | B26: LE.F.P CONSULTORES SRL | D26: VS/FG | I26: 48852 | M26: =SUM(E26:L26) -> 48852
A27: 21 | B27: Bello-Lab, SRL | D27: VS/FG | I27: 254862 | M27: =SUM(E27:L27) -> 254862
A28: 22 | B28: Bio Nova, SRL | D28: VS/FG | I28: 14391 | M28: =SUM(E28:L28) -> 14391
A29: 23 | B29: Air Liquide Dominicana, SAS | D29: VS/FG | I29: 12832.5 | M29: =SUM(E29:L29) -> 12832.5
A30: 24 | B30: FARMACIA RUTH | D30: VS/FG | I30: 3450 | M30: =SUM(E30:L30) -> 3450
A31: 25 | B31: Air Liquide Dominicana, SAS | D31: VS/FG | I31: 5459.4588 | M31: =SUM(E31:L31) -> 5459.4588
A32: 26 | B32: FARMACIA RUTH | D32: VS/FG | I32: 77150 | M32: =SUM(E32:L32) -> 77150
... A91: 85 | B91: JT Investdent, SRL | D91: VS/FG | I91: 244288.8 | M91: =SUM(E91:L91) -> 244288.8
A92: 86 | B92: ALCALDIA SANTO DOMINGO ESTE | D92: VS/FG | J92: 25000 | M92: =SUM(E92:L92) -> 25000
A93: 87 | B93: Air Liquide Dominicana, SAS | D93: VS/FG | J93: 5459.46 | M93: =SUM(E93:L93) -> 5459.46
A94: 88 | B94: Papelería E. Impresos Crishoan, SRL | D94: VS/FG | J94: 226357.04 | M94: =SUM(E94:L94) -> 226357.04
A95: 89 | B95: Air Liquide Dominicana, SAS | D95: VS/FG | J95: 8982.75 | M95: =SUM(E95:L95) -> 8982.75
A96: 90 | B96: Air Liquide Dominicana, SAS | D96: VS/FG | J96: 5459.46 | M96: =SUM(E96:L96) -> 5459.46
A97: 91 | B97: Insocorp, S.R.L. | D97: VS/FG | J97: 20060 | M97: =SUM(E97:L97) -> 20060
A98: 92 | B98: Air Liquide Dominicana, SAS | D98: VS/FG | J98: 5459.46 | M98: =SUM(E98:L98) -> 5459.46
A99: 93 | B99: Air Liquide Dominicana, SAS | D99: VS/FG | J99: 386946.77 | M99: =SUM(E99:L99) -> 386946.77
A100: 94 | B100: Air Liquide Dominicana, SAS | D100: VS/FG | J100: 13698.11 | M100: =SUM(E100:L100) -> 13698.11
A101: 95 | B101: Air Liquide Dominicana, SAS | D101: VS/FG | J101: 4549.55 | M101: =SUM(E101:L101) -> 4549.55
A102: 96 | B102: Air Liquide Dominicana, SAS | D102: VS/FG | J102: 889801.17 | M102: =SUM(E102:L102) -> 889801.17
A103: 97 | B103: Q&Q Medical RD, SRL | D103: VS/FG | J103: 69561 | M103: =SUM(E103:L103) -> 69561
... A113: 107 | B113: GRUPO LIVAO SRL | D113: VS/FG | J113: 158120 | M113: =SUM(E113:L113) -> 158120
A114: 108 | B114: ALCALDIA SANTO DOMINGO ESTE | D114: VS/FG | K114: 25000 | M114: =SUM(E114:L114) -> 25000
A115: 109 | B115: Air Liquide Dominicana, SAS | D115: VS/FG | K115: 5508.92 | M115: =SUM(E115:L115) -> 5508.92
A116: 110 | B116: Insocorp, S.R.L. | D116: VS/FG | K116: 454300 | M116: =SUM(E116:L116) -> 454300
A117: 111 | B117: Insocorp, S.R.L. | D117: VS/FG | K117: 66080 | M117: =SUM(E117:L117) -> 66080
A118: 112 | B118: RONAJUS FARMACEUTICA SRL | D118: VS/FG | K118: 109657.6 | M118: =SUM(E118:L118) -> 109657.6
A119: 113 | B119: LEHAIM SUMINISTROS SRL | D119: VS/FG | K119: 212400 | M119: =SUM(E119:L119) -> 212400
A120: 114 | B120: LEHAIM SUMINISTROS SRL | D120: VS/FG | K120: 123900 | M120: =SUM(E120:L120) -> 123900
A121: 115 | B121: Bio Win, SRL | D121: VS/FG | K121: 2300 | M121: =SUM(E121:L121) -> 2300
A122: 116 | B122: LEHAIM SUMINISTROS SRL | D122: VS/FG | K122: 135700 | M122: =SUM(E122:L122) -> 135700
A123: 117 | B123: Air Liquide Dominicana, SAS | D123: VS/FG | K123: 8189.19 | M123: =SUM(E123:L123) -> 8189.19
A124: 118 | B124: Air Liquide Dominicana, SAS | D124: VS/FG | K124: 687457.37 | M124: =SUM(E124:L124) -> 687457.37
A125: 119 | B125: Global Multi-Pharma Dominicana THM, SRL | D125: VS/FG | K125: 90000 | M125: =SUM(E125:L125) -> 90000
... A148: 142 | B148: Air Liquide Dominicana, SAS | D148: VS/FG | K148: 819682.03 | M148: =SUM(E148:L148) -> 819682.03
A149: 143 | B149: ALCALDIA SANTO DOMINGO ESTE | D149: VS/FG | L149: 25000 | M149: =SUM(E149:L149) -> 25000
A150: 144 | B150: Super Latop Browsing SRL | D150: VS/FG | L150: 413000 | M150: =SUM(E150:L150) -> 413000
A151: 145 | B151: Abrias Novo Group SRL | D151: VS/FG | L151: 216333.29 | M151: =SUM(E151:L151) -> 216333.29
A152: 146 | B152: Abrias Novo Group SRL | D152: VS/FG | L152: 216333.29 | M152: =SUM(E152:L152) -> 216333.29
A153: 147 | B153: Air Liquide Dominicana, SAS | D153: VS/FG | L153: 8189.19 | M153: =SUM(E153:L153) -> 8189.19
A154: 148 | B154: Insocorp, S.R.L. | D154: VS/FG | L154: 96382.4 | M154: =SUM(E154:L154) -> 96382.4
A155: 149 | B155: Grupo Xeron Medic SRL | D155: VS/FG | L155: 162722 | M155: =SUM(E155:L155) -> 162722
A156: 150 | B156: Grupo Xeron Medic SRL | D156: VS/FG | L156: 212284 | M156: =SUM(E156:L156) -> 212284
A157: 151 | B157: Empresas Cabod, EIRL | D157: VS/FG | L157: 89739 | M157: =SUM(E157:L157) -> 89739
A158: 152 | B158: PATRIA RIVAS LABORATORIO CLINICO | D158: VS/FG | L158: 3500 | M158: =SUM(E158:L158) -> 3500
A159: 153 | B159: Corporacion Medica A.G., SRL | D159: VS/FG | L159: 525648 | M159: =SUM(E159:L159) -> 525648
A160: 154 | B160: Air Liquide Dominicana, SAS | D160: VS/FG | L160: 7279.28 | M160: =SUM(E160:L160) -> 7279.28
... A193: 187 | B193: Grupo Xeron Medic SRL | D193: VS/FG | L193: 250000 | M193: =SUM(E193:L193) -> 250000
A194: TOTAL GENERAL | E194: =SUM(E7:E193) -> 0 | G194: =SUM(G7:G193) -> 14300 | H194: =SUM(H7:H193) -> 1889270.9 | I194: =SUM(I7:I193) -> 7319861.2 | J194: =SUM(J7:J193) -> 2271930.5 | K194: =SUM(K7:K193) -> 6892151.5 | L194: =SUM(L7:L193) -> 7649585.1 | M194: =SUM(M7:M193) -> 26037099

Sheet INGRESOS POR A.R.S
A2: Servicio Nacional De Salud
A3: Dirección de Fiscalizacion
A4: Ingresos Por Facturación ARS
A6: Establecimiento: | C6: HOSPITAL MATERNO INFANTIL SAN LORENZO DE LOS MINA
A8: ARS | C8: ENERO | E8: FEBRERO | G8: MARZO | I8: ABRIL | K8: MAYO | M8: JUNIO | O8: JULIO | Q8: AGOSTO | S8: SEPTIEMBRE | U8: OCTUBRE | W8: NOVIEMBRE | Y8: DICIEMBRE
C9: Facturado | D9: Recibido | E9: Facturado | F9: Recibido | G9: Facturado | H9: Recibido | I9: Facturado | J9: Recibido | K9: Facturado | L9: Recibido | M9: Facturado | N9: Recibido | O9: Facturado | P9: Recibido | Q9: Facturado | R9: Recibido | S9: Facturado | T9: Recibido | U9: Facturado | V9: Recibido | W9: Facturado | X9: Recibido | Y9: Facturado | Z9: Recibido
A10: 1 | B10: SENASA SUBSIDIADO | C10: 4027257.3 | D10: 4833111.5 | E10: 4840265.3 | F10: 5841673.2 | G10: =13000+3146909.72 -> 3159909.7 | H10: =4595181.39+50000 -> 4645181.4
A11: 2 | B11: SENASA CONTRIBUTIVO | C11: 1094583.8 | E11: 2417181.1 | F11: 2152926.5 | G11: 2645113.9 | H11: 1041144.3
B12: SENASA JUB. Y PENS. | C12: 0 | D12: 0 | E12: 10985.64 | G12: 0
A13: Total SeNaSa | C13: =SUM(C10:C12) -> 5121841.1 | D13: =SUM(D10:D12) -> 4833111.5 | E13: =SUM(E10:E12) -> 7268432.1 | F13: =SUM(F10:F12) -> 7994599.7 | G13: =SUM(G10:G12) -> 5805023.6 | H13: =SUM(H10:H12) -> 5686325.7 | I13: =SUM(I10:I12) -> 0 | J13: =SUM(J10:J12) -> 0 | ... Z13: =SUM(Z10:Z12) -> 0
A14: 3 | B14: PALIC SALUD | C14: 211714.57 | D14: 206908.45 | E14: =65463.45+12918.96+311477.59 -> 389860 | G14: =53140.7+6743.06+130031.72 -> 189915.48 | H14: =16298.76+15397.47+30434.4+65463.45+12863.4+155572.92+309977.48+504 -> 606511.88
A15: 4 | B15: ARL
A16: 5 | B16: RENACER | C16: 275352.44 | D16: 156983.55 | E16: 222716.34 | F16: 272552.44 | G16: 73918.68 | H16: 222620.34
A17: 6 | B17: YUNEN | C17: 7848.94 | D17: 55135.74 | E17: 14338.35 | F17: 7848.94 | G17: 162551.53 | H17: 14338.35
A18: 7 | B18: UNIVERSAL
A19: 8 | B19: ARS HUMANO | C19: 44770.98 | E19: 16720.82 | F19: 97648.3 | G19: 83376.61 | H19: 34117.68
A20: 9 | B20: ARS PLANSALUD BANCO CENTRAL
A21: 10 | B21: SEMMA | C21: 7193.05 | D21: 15993.02 | E21: 28868.13 | F21: 9531.6 | G21: 10657.5 | H21: 77169.4
A22: 11 | B22: FUTURO | C22: 269639.73 | D22: 234503.89 | E22: 617068.65 | G22: 366095.18 | H22: 356314.76
A23: 12 | B23: APS | C23: 69588.33 | E23: 122630.62 | F23: 8262.07 | G23: 43770.8 | H23: 212345.21
A24: 13 | B24: SALUD SEGURA
A25: 14 | B25: CONSTITUCION
A26: 15 | B26: META SALUD | C26: 1396 | E26: 20821.36 | F26: 31949.94 | G26: 80842.17 | H26: 1396
A27: 16 | B27: ASEMAP | C27: 4869.52 | D27: 6475.14 | E27: 102975.46 | F27: 4869.52 | G27: 6619.63 | H27: 102672.34
A28: 17 | B28: GMA | C28: 76159.34 | E28: 186957.88 | G28: 136798.59
A29: 18 | B29: MONUMENTAL | C29: 75131.09 | D29: 71992.2 | E29: 146560.32 | G29: 85258.31 | H29: 237322.18
A30: 19 | B30: CMD | C30: 273646.7 | D30: 273646.7 | E30: 41285.9 | F30: 41071.9 | G30: 22435.77 | H30: 11220.43
A31: 20 | B31: RESERVAS | C31: 48081.02 | D31: 48081.02 | E31: 217047.26 | G31: 79962.77
A32: 21 | B32: SIMAG | C32: 28637.51 | E32: 92478.63 | G32: 2821.24
A33: 22 | B33: SEMUNASED
A34: 23 | B34: SERVICIOS MEDICOS UASD
A35: 24 | B35: PRIMERA ARS HUMANO | C35: 259154.57 | E35: 439967.13 | F35: 870590.25 | G35: 404678.83 | H35: 262926.38
A36: Total ARS PRIVADAS | C36: =SUM(C14:C35) -> 1653183.8 | D36: =SUM(D14:D35) -> 1069719.7 | E36: =SUM(E14:E35) -> 2660296.9 | F36: =SUM(F14:F35) -> 1344325 | G36: =SUM(G14:G35) -> 1749703.1 | H36: =SUM(H14:H35) -> 2138955 | I36: =SUM(I14:I35) -> 0 | J36: =SUM(J14:J35) -> 0 | ... Z36: =SUM(Z14:Z35) -> 0
A37: TOTAL | C37: =C13+C36 -> 6775024.9 | D37: =D13+D36 -> 5902831.2 | E37: =E13+E36 -> 9928728.9 | F37: =F13+F36 -> 9338924.6 | G37: =G13+G36 -> 7554726.7 | H37: =H13+H36 -> 7825280.6 | I37: =I13+I36 -> 0 | J37: =J13+J36 -> 0 | ... Z37: =Z13+Z36 -> 0
A39: Preparado por:
A40: Licda.

Sheet GLOSA
A1: Servicio Nacional de Salud
A2: Dirección de Fiscalización
A3: Glosa /mes
A4: Establecimientos | B4: Facturado | C4: Recibido | D4: Glosado | E4: %
A5: Enero | B5: 6775024.9 | C5: 5902831.2 | D5: 102835 | E5: =+D5/C5 -> 0.017421301
A6: Febrero | B6: 9928728.9 | C6: 9338924.6 | D6: =147829.22+68679.07+4547.79 -> 221056.08 | E6: =+D6/C6 -> 0.0236704
A7: Marzo | B7: 7643032.2 | C7: 7825280.7 | D7: 99442.51 | E7: =+D7/C7 -> 0.012707852
A8: Abril
A9: Mayo
A10: Junio
A11: Julio
A12: Agosto
A13: Septiembre
A14: Octubre
A15: Noviembre
A16: Diciembre
A17: Total | B17: =SUM(B5:B13) -> 24346786 | C17: =SUM(C5:C13) -> 23067036 | D17: =SUM(D5:D13) -> 423333.59 | E17: =+D17/C17 -> 0.018352318
A19: Preparado por:
A20: Licda.
