Workbook

Sheet MARZO 2025
A1: Form. No.6 SRS
A3: Servicio Nacional de Salud
A4: Dirección de Fizcalización
A5: Consolidado de Ingresos y Gastos por Fuente de Financiamiento
A6: HOSPITAL MATERNO INFANTIL SAN LORENZO DE LOS MINA
A7: MARZO 2025
C8: Ingresos Generales:
E9: 1.- Balance Inicial / Fuente:
E10: Anticipo Financiero | H10: Otros Aportes | L10: Contraseña: 0001
E11: Transferencias Corrientes
E12: Venta de Servicios | G12: 2511952.5
E13: 2.- Ingresos por Fuente / Cuenta
E14: Anticipo Financiero | H14: Otros Aportes | I14: =+'[1]INGR SEGUN ORIGEN'!E39 -> 223625 | L14: OBJETAL | M14: FR | N14: VS
E15: Transferencias Corrientes | G15: =+'[1]INGR SEGUN ORIGEN'!E12 -> 1.003168e+08 | H15: Aportes Nomina SNS | I15: 0 | L15: 2.1 | M15: =G26 -> 66337620 | N15: =H26 -> 5231553.6
E16: Venta de Servicios | G16: =+'[1]INGR SEGUN ORIGEN'!E37 -> 7825280.6 | L16: 2.2 | M16: =G87 -> 7971396.2 | N16: =H87 -> 4359456.2
H17: TOTAL INGRESOS RDS | I17: =+G10+G11+G12+I10+G14+G15+G16+I14+I15 -> 1.1087765e+08 | L17: 2.3 | M17: ='[1]CONS. FUENTES FINAN'!G212 -> 26749552 | N17: ='[1]CONS. FUENTES FINAN'!H212 -> 1797538.3
L18: 2.4 | M18: =G330 -> 0 | N18: =H330 -> 127420
L19: 2.6 | M19: =G336 -> 11396849 | N19: =H336 -> 300539.37
L20: 2.7 | M20: ='[1]CONS. FUENTES FINAN'!G463 -> 0 | N20: ='[1]CONS. FUENTES FINAN'!H463 -> 0
A21: 1 | F21: 2 | G21: 3 | I21: 4 | J21: 5
A22: Código Presupuestario | F22: Descripción Gasto por Cuenta | G22: Distribución del Gasto por Fuente de Financiamiento | I22: TOTAL | J22: %
A23: Tipo | B23: Objeto | C23: Cuenta | D23: Sub-Cuenta | E23: Auxiliar | G23: Fondo 100 | H23: Venta de Servicios/ Otros Aportes
A25: 2 | F25: Gastos | G25: =+G26+G87+G212+G330+G336+G463 -> 1.1245542e+08 | H25: =+H26+H87+H212+H330+H336+H463 -> 11816507 | I25: =SUM(G25:H25) -> 1.2427192e+08 | J25: =+J26+J87+J212+J330+J336+J463 -> 1
A26: 2 | B26: 1 | F26: Servicios Personales | G26: =+G27+G51+G64+G71+G78 -> 66337620 | H26: =+H27+H51+H64+H71+H78 -> 5231553.6 | I26: =SUM(G26:H26) -> 71569173 | J26: =I26/$I$25 -> 0.57590782
A27: 2 | B27: 1 | C27: 1 | F27: Remuneraciones | G27: =+G28+G35+G42+G44+G46 -> 54718737 | H27: =+H28+H35+H42+H44+H46 -> 0 | I27: =SUM(G27:H27) -> 54718737 | J27: =I27/$I$25 -> 0.44031455
A28: 2 | B28: 1 | C28: 1 | D28: 1 | F28: Remuneraciones al personal fijo | G28: =SUM(G29:G34) -> 53611206 | H28: =SUM(H29:H34) -> 0 | I28: =SUM(G28:H28) -> 53611206 | J28: =I28/$I$25 -> 0.4314024
A29: 2 | B29: 1 | C29: 1 | D29: 1 | E29: 01 | F29: Sueldos a empleados fijos | G29: ='[1]CUENTA T FONDO 100'!A127 -> 53611206 | H29: ='[1]CUENTA T VS'!A96 -> 0 | I29: =SUM(G29:H29) -> 53611206 | J29: =I29/$I$25 -> 0.4314024
A30: 2 | B30: 1 | C30: 1 | D30: 1 | E30: 02 | F30: Sueldos a médicos | G30: ='[1]CUENTA T FONDO 100'!B127 -> 0 | H30: ='[1]CUENTA T VS'!B96 -> 0 | I30: =SUM(G30:H30) -> 0 | J30: =I30/$I$25 -> 0
A31: 2 | B31: 1 | C31: 1 | D31: 1 | E31: 03 | F31: Ascensos a militares | G31: ='[1]CUENTA T FONDO 100'!C127 -> 0 | H31: ='[1]CUENTA T VS'!C96 -> 0 | I31: =SUM(G31:H31) -> 0 | J31: =I31/$I$25 -> 0
A32: 2 | B32: 1 | C32: 1 | D32: 1 | E32: 04 | F32: Nuevas plazas maestros | G32: ='[1]CUENTA T FONDO 100'!D127 -> 0 | H32: ='[1]CUENTA T VS'!D96 -> 0 | I32: =SUM(G32:H32) -> 0 | J32: =I32/$I$25 -> 0
A33: 2 | B33: 1 | C33: 1 | D33: 1 | E33: 05 | F33: Incentivos y escalafón | G33: ='[1]CUENTA T FONDO 100'!E127 -> 0 | H33: ='[1]CUENTA T VS'!E96 -> 0 | I33: =SUM(G33:H33) -> 0 | J33: =I33/$I$25 -> 0
A34: 2 | B34: 1 | C34: 1 | D34: 1 | E34: 06 | F34: Nuevas plazas a médicos | G34: ='[1]CUENTA T FONDO 100'!F127 -> 0 | H34: ='[1]CUENTA T VS'!F96 -> 0 | I34: =SUM(G34:H34) -> 0 | J34: =I34/$I$25 -> 0
A35: 2 | B35: 1 | C35: 1 | D35: 2 | F35: Remuneraciones al personal con carácter transitorio | G35: =SUM(G36:G41) -> 1107531 | H35: =SUM(H36:H41) -> 0 | I35: =SUM(G35:H35) -> 1107531
A36: 2 | B36: 1 | C36: 1 | D36: 2 | E36: 03 | F36: Suplencias | G36: ='[1]CUENTA T FONDO 100'!G127 -> 0 | H36: ='[1]CUENTA T VS'!G96 -> 0 | I36: =SUM(G36:H36) -> 0 | J36: =I36/$I$25 -> 0
A37: 2 | B37: 1 | C37: 1 | D37: 2 | E37: 05 | F37: Sueldo al personal nominal en período probatorio | G37: ='[1]CUENTA T FONDO 100'!H127 -> 0 | H37: ='[1]CUENTA T VS'!H96 -> 0 | I37: =SUM(G37:H37) -> 0 | J37: =I37/$I$25 -> 0
A38: 2 | B38: 1 | C38: 1 | D38: 2 | E38: 06 | F38: Jornales | G38: ='[1]CUENTA T FONDO 100'!I127 -> 0 | H38: ='[1]CUENTA T VS'!I96 -> 0 | I38: =SUM(G38:H38) -> 0 | J38: =I38/$I$25 -> 0
A39: 2 | B39: 1 | C39: 1 | D39: 2 | E39: 08 | F39: Empleados temporales | G39: ='[1]CUENTA T FONDO 100'!J127 -> 1107531 | H39: ='[1]CUENTA T VS'!J96 -> 0 | I39: =SUM(G39:H39) -> 1107531 | J39: =I39/$I$25 -> 0.008912158
A40: 2 | B40: 1 | C40: 1 | D40: 2 | E40: 09 | F40: Personal de carácter eventual | G40: ='[1]CUENTA T FONDO 100'!K127 -> 0 | H40: ='[1]CUENTA T VS'!K96 -> 0 | I40: =SUM(G40:H40) -> 0 | J40: =I40/$I$25 -> 0
A41: 2 | B41: 1 | C41: 1 | D41: 2 | E41: 11 | F41: Interinato | G41: ='[1]CUENTA T FONDO 100'!L127 -> 0 | H41: ='[1]CUENTA T VS'!L96 -> 0 | I41: =SUM(G41:H41) -> 0 | J41: =I41/$I$25 -> 0
A42: 2 | B42: 1 | C42: 1 | D42: 3 | F42: Sueldos al personal fijo en trámite de pensiones | G42: =SUM(G43) -> 0 | H42: =SUM(H43) -> 0 | I42: =SUM(G42:H42) -> 0
A43: 2 | B43: 1 | C43: 1 | D43: 3 | E43: 01 | F43: Sueldos al personal fijo en trámite de pensiones | G43: ='[1]CUENTA T FONDO 100'!M127 -> 0 | H43: ='[1]CUENTA T VS'!M96 -> 0 | I43: =SUM(G43:H43) -> 0 | J43: =I43/$I$25 -> 0
A44: 2 | B44: 1 | C44: 1 | D44: 4 | F44: Sueldo anual no. 13 | G44: =SUM(G45) -> 0 | H44: =SUM(H45) -> 0 | I44: =SUM(G44:H44) -> 0
A45: 2 | B45: 1 | C45: 1 | D45: 4 | E45: 01 | F45: Sueldo anual no. 13 | G45: ='[1]CUENTA T FONDO 100'!N127 -> 0 | H45: ='[1]CUENTA T VS'!N96 -> 0 | I45: =SUM(G45:H45) -> 0 | J45: =I45/$I$25 -> 0
A46: 2 | B46: 1 | C46: 1 | D46: 5 | F46: Prestaciones económinas | G46: =SUM(G47:G50) -> 0 | H46: =SUM(H47:H50) -> 0 | I46: =SUM(G46:H46) -> 0
A47: 2 | B47: 1 | C47: 1 | D47: 5 | E47: 01 | F47: Prestaciones económinas | G47: ='[1]CUENTA T FONDO 100'!O127 -> 0 | H47: ='[1]CUENTA T VS'!O96 -> 0 | I47: =SUM(G47:H47) -> 0 | J47: =I47/$I$25 -> 0
A48: 2 | B48: 1 | C48: 1 | D48: 5 | E48: 02 | F48: Pago de porcentaje por desvinculación de cargo | G48: ='[1]CUENTA T FONDO 100'!P127 -> 0 | H48: ='[1]CUENTA T VS'!P96 -> 0 | I48: =SUM(G48:H48) -> 0 | J48: =I48/$I$25 -> 0
A49: 2 | B49: 1 | C49: 1 | D49: 5 | E49: 03 | F49: Prestación laboral por desvinculación | G49: ='[1]CUENTA T FONDO 100'!Q127 -> 0 | H49: ='[1]CUENTA T VS'!Q96 -> 0 | I49: =SUM(G49:H49) -> 0 | J49: =I49/$I$25 -> 0
A50: 2 | B50: 1 | C50: 1 | D50: 5 | E50: 04 | F50: Proporción de vacaciones no disfrutadas | G50: ='[1]CUENTA T FONDO 100'!R127 -> 0 | H50: ='[1]CUENTA T VS'!R96 -> 0 | I50: =SUM(G50:H50) -> 0 | J50: =I50/$I$25 -> 0
A51: 2 | B51: 1 | C51: 2 | F51: Sobresueldos | G51: =+G52+G54 -> 3199399.6 | H51: =+H52+H54 -> 5231553.6 | I51: =SUM(G51:H51) -> 8430953.2
A52: 2 | B52: 1 | C52: 2 | D52: 1 | F52: Primas por antigüedad | G52: =SUM(G53) -> 2752136.5 | H52: =SUM(H53) -> 0 | I52: =SUM(G52:H52) -> 2752136.5
A53: 2 | B53: 1 | C53: 2 | D53: 1 | E53: 01 | F53: Primas por antigüedad | G53: ='[1]CUENTA T FONDO 100'!S127 -> 2752136.5 | H53: ='[1]CUENTA T VS'!S96 -> 0 | I53: =SUM(G53:H53) -> 2752136.5 | J53: =I53/$I$25 -> 0.022146084
A54: 2 | B54: 1 | C54: 2 | D54: 2 | F54: Compensación | G54: =SUM(G55:G63) -> 447263.1 | H54: =SUM(H55:H63) -> 5231553.6 | I54: =SUM(G54:H54) -> 5678816.7
A55: 2 | B55: 1 | C55: 2 | D55: 2 | E55: 01 | F55: Compensación por gastos de alimentación | G55: ='[1]CUENTA T FONDO 100'!T127 -> 0 | H55: ='[1]CUENTA T VS'!T96 -> 0 | I55: =SUM(G55:H55) -> 0 | J55: =I55/$I$25 -> 0
A56: 2 | B56: 1 | C56: 2 | D56: 2 | E56: 03 | F56: Pago de horas extraordinarias | G56: ='[1]CUENTA T FONDO 100'!U127 -> 0 | H56: ='[1]CUENTA T VS'!U96 -> 0 | I56: =SUM(G56:H56) -> 0 | J56: =I56/$I$25 -> 0
A57: 2 | B57: 1 | C57: 2 | D57: 2 | E57: 04 | F57: Prima de transporte | G57: ='[1]CUENTA T FONDO 100'!V127 -> 0 | H57: ='[1]CUENTA T VS'!V96 -> 0 | I57: =SUM(G57:H57) -> 0 | J57: =I57/$I$25 -> 0
A58: 2 | B58: 1 | C58: 2 | D58: 2 | E58: 05 | F58: Compensación servicios de Seguridad | G58: ='[1]CUENTA T FONDO 100'!W127 -> 45000 | H58: ='[1]CUENTA T VS'!W96 -> 0 | I58: =SUM(G58:H58) -> 45000 | J58: =I58/$I$25 -> 0.00036210914
A59: 2 | B59: 1 | C59: 2 | D59: 2 | E59: 06 | F59: Incentivo por Rendimieto Individual | G59: ='[1]CUENTA T FONDO 100'!X127 -> 0 | H59: ='[1]CUENTA T VS'!X96 -> 5231553.6 | I59: =SUM(G59:H59) -> 5231553.6 | J59: =I59/$I$25 -> 0.042097631
A60: 2 | B60: 1 | C60: 2 | D60: 2 | E60: 07 | F60: Compensación por distancia | G60: ='[1]CUENTA T FONDO 100'!Y127 -> 0 | H60: ='[1]CUENTA T VS'!Y96 -> 0 | I60: =SUM(G60:H60) -> 0 | J60: =I60/$I$25 -> 0
A61: 2 | B61: 1 | C61: 2 | D61: 2 | E61: 08 | F61: Compensaciones especiales | G61: ='[1]CUENTA T FONDO 100'!Z127 -> 332600 | H61: ='[1]CUENTA T VS'!Z96 -> 0 | I61: =SUM(G61:H61) -> 332600 | J61: =I61/$I$25 -> 0.0026763889
A62: 2 | B62: 1 | C62: 2 | D62: 2 | E62: 09 | F62: Bono por desempeño a servidores de carrera | G62: ='[1]CUENTA T FONDO 100'!AA127 -> 0 | H62: ='[1]CUENTA T VS'!AA96 -> 0 | I62: =SUM(G62:H62) -> 0 | J62: =I62/$I$25 -> 0
A63: 2 | B63: 1 | C63: 2 | D63: 2 | E63: 10 | F63: Compensacion por cumplimiento de indicadores | G63: ='[1]CUENTA T FONDO 100'!AB127 -> 69663.1 | H63: ='[1]CUENTA T VS'!AB96 -> 0 | I63: =SUM(G63:H63) -> 69663.1 | J63: =I63/$I$25 -> 0.0005605699
A64: 2 | B64: 1 | C64: 3 | F64: Dietas y Gastos de Representación | G64: =+G65+G68 -> 0 | H64: =+H65+H68 -> 0 | I64: =SUM(G64:H64) -> 0
A65: 2 | B65: 1 | C65: 3 | D65: 1 | F65: Dietas | G65: =SUM(G66:G67) -> 0 | H65: =SUM(H66:H67) -> 0 | I65: =SUM(G65:H65) -> 0
A66: 2 | B66: 1 | C66: 3 | D66: 1 | E66: 01 | F66: Dietas en el país | G66: ='[1]CUENTA T FONDO 100'!AC127 -> 0 | H66: ='[1]CUENTA T VS'!AC96 -> 0 | I66: =SUM(G66:H66) -> 0 | J66: =I66/$I$25 -> 0
A67: 2 | B67: 1 | C67: 3 | D67: 1 | E67: 02 | F67: Dietas en el exterior | G67: ='[1]CUENTA T FONDO 100'!AD127 -> 0 | H67: ='[1]CUENTA T VS'!AD96 -> 0 | I67: =SUM(G67:H67) -> 0 | J67: =I67/$I$25 -> 0
A68: 2 | B68: 1 | C68: 3 | D68: 2 | F68: Gastos de representación | G68: =SUM(G69:G70) -> 0 | H68: =SUM(H69:H70) -> 0 | I68: =SUM(G68:H68) -> 0
A69: 2 | B69: 1 | C69: 3 | D69: 2 | E69: 01 | F69: Gastos de representación en el país | G69: ='[1]CUENTA T FONDO 100'!AE127 -> 0 | H69: ='[1]CUENTA T VS'!AE96 -> 0 | I69: =SUM(G69:H69) -> 0 | J69: =I69/$I$25 -> 0
A70: 2 | B70: 1 | C70: 3 | D70: 2 | E70: 02 | F70: Gastos de representación en el exterior | G70: ='[1]CUENTA T FONDO 100'!AF127 -> 0 | H70: ='[1]CUENTA T VS'!AF96 -> 0 | I70: =SUM(G70:H70) -> 0 | J70: =I70/$I$25 -> 0
A71: 2 | B71: 1 | C71: 4 | F71: Gratificaciones y Bonificaciones | G71: =+G72+G74 -> 0 | H71: =+H72+H74 -> 0 | I71: =SUM(G71:H71) -> 0
A72: 2 | B72: 1 | C72: 4 | D72: 1 | F72: Bonificaciones | G72: =SUM(G73) -> 0 | H72: =SUM(H73) -> 0 | I72: =SUM(G72:H72) -> 0
A73: 2 | B73: 1 | C73: 4 | D73: 1 | E73: 01 | F73: Bonificaciones | G73: ='[1]CUENTA T FONDO 100'!AG127 -> 0 | H73: ='[1]CUENTA T VS'!AG96 -> 0 | I73: =SUM(G73:H73) -> 0 | J73: =I73/$I$25 -> 0
A74: 2 | B74: 1 | C74: 4 | D74: 2 | F74: Otras Gratificaciones y Bonificaciones | G74: =SUM(G75:G77) -> 0 | H74: =SUM(H75:H77) -> 0 | I74: =SUM(G74:H74) -> 0
A75: 2 | B75: 1 | C75: 4 | D75: 2 | E75: 01 | F75: Bono escolar | G75: ='[1]CUENTA T FONDO 100'!AH127 -> 0 | H75: ='[1]CUENTA T VS'!AH96 -> 0 | I75: =SUM(G75:H75) -> 0 | J75: =I75/$I$25 -> 0
A76: 2 | B76: 1 | C76: 4 | D76: 2 | E76: 02 | F76: Gratificaciones por pasantías | G76: ='[1]CUENTA T FONDO 100'!AI127 -> 0 | H76: ='[1]CUENTA T VS'!AI96 -> 0 | I76: =SUM(G76:H76) -> 0 | J76: =I76/$I$25 -> 0
A77: 2 | B77: 1 | C77: 4 | D77: 2 | E77: 03 | F77: Gratificaciones por aniversario de institución | G77: ='[1]CUENTA T FONDO 100'!AJ127 -> 0 | H77: ='[1]CUENTA T VS'!AJ96 -> 0 | I77: =SUM(G77:H77) -> 0 | J77: =I77/$I$25 -> 0
A78: 2 | B78: 1 | C78: 5 | F78: Contribuciones a la Seguridad Social y Riesgo Laboral | G78: =+G79+G81+G83+G85 -> 8419483.2 | H78: =+H79+H81+H83+H85 -> 0 | I78: =SUM(G78:H78) -> 8419483.2
A79: 2 | B79: 1 | C79: 5 | D79: 1 | F79: Contribuciones al seguro de salud | G79: =SUM(G80) -> 3879560.8 | H79: =SUM(H80) -> 0 | I79: =SUM(G79:H79) -> 3879560.8
A80: 2 | B80: 1 | C80: 5 | D80: 1 | E80: 01 | F80: Contribuciones al seguro de salud | G80: ='[1]CUENTA T FONDO 100'!AK127 -> 3879560.8 | H80: ='[1]CUENTA T VS'!AK96 -> 0 | I80: =SUM(G80:H80) -> 3879560.8 | J80: =I80/$I$25 -> 0.031218321
A81: 2 | B81: 1 | C81: 5 | D81: 2 | F81: Contribuciones al seguro de pensiones | G81: =SUM(G82) -> 3885030.8 | H81: =SUM(H82) -> 0 | I81: =SUM(G81:H81) -> 3885030.8
A82: 2 | B82: 1 | C82: 5 | D82: 2 | E82: 01 | F82: Contribuciones al seguro de pensiones | G82: ='[1]CUENTA T FONDO 100'!AL127 -> 3885030.8 | H82: ='[1]CUENTA T VS'!AL96 -> 0 | I82: =SUM(G82:H82) -> 3885030.8 | J82: =I82/$I$25 -> 0.031262337
A83: 2 | B83: 1 | C83: 5 | D83: 3 | F83: Contribuciones al seguro de riesgo laboral | G83: =SUM(G84) -> 654891.59 | H83: =SUM(H84) -> 0 | I83: =SUM(G83:H83) -> 654891.59
A84: 2 | B84: 1 | C84: 5 | D84: 3 | E84: 01 | F84: Contribuciones al seguro de riesgo laboral | G84: ='[1]CUENTA T FONDO 100'!AM127 -> 654891.59 | H84: ='[1]CUENTA T VS'!AM96 -> 0 | I84: =SUM(G84:H84) -> 654891.59 | J84: =I84/$I$25 -> 0.0052698274
A85: 2 | B85: 1 | C85: 5 | D85: 4 | F85: Contribuciones al plan de retiro complementario | G85: =SUM(G86) -> 0 | H85: =SUM(H86) -> 0 | I85: =SUM(G85:H85) -> 0
A86: 2 | B86: 1 | C86: 5 | D86: 4 | E86: 01 | F86: Contribuciones al plan de retiro complementario | G86: ='[1]CUENTA T FONDO 100'!AN127 -> 0 | H86: ='[1]CUENTA T VS'!AN96 -> 0 | I86: =SUM(G86:H86) -> 0 | J86: =I86/$I$25 -> 0
A87: 2 | B87: 2 | F87: Servicios No Personales | G87: =G88+G106+G111+G116+G125+G148+G157+G179+G208 -> 7971396.2 | H87: =H88+H106+H111+H116+H125+H148+H157+H179+H208 -> 4359456.2 | I87: =SUM(G87:H87) -> 12330852 | J87: =I87/$I$25 -> 0.099224765
A88: 2 | B88: 2 | C88: 1 | F88: Servicios Básicos | G88: =+G89+G91+G93+G95+G97+G99+G102+G104 -> 2020024.3 | H88: =+H89+H91+H93+H95+H97+H99+H102+H104 -> 1731191.2 | I88: =SUM(G88:H88) -> 3751215.5
A89: 2 | B89: 2 | C89: 1 | D89: 1 | F89: Radiocomunicación | G89: =SUM(G90) -> 0 | H89: =SUM(H90) -> 0 | I89: =SUM(G89:H89) -> 0
A90: 2 | B90: 2 | C90: 1 | D90: 1 | E90: 01 | F90: Radiocomunicación | G90: ='[1]CUENTA T FONDO 100'!AO127 -> 0 | H90: ='[1]CUENTA T VS'!AO96 -> 0 | I90: =SUM(G90:H90) -> 0 | J90: =I90/$I$25 -> 0
A91: 2 | B91: 2 | C91: 1 | D91: 2 | F91: Servicios telefónico de larga distancia | G91: =SUM(G92) -> 0 | H91: =SUM(H92) -> 0 | I91: =SUM(G91:H91) -> 0
A92: 2 | B92: 2 | C92: 1 | D92: 2 | E92: 01 | F92: Servicios telefónico de larga distancia | G92: ='[1]CUENTA T FONDO 100'!AP127 -> 0 | H92: ='[1]CUENTA T VS'!AP96 -> 0 | I92: =SUM(G92:H92) -> 0 | J92: =I92/$I$25 -> 0
A93: 2 | B93: 2 | C93: 1 | D93: 3 | F93: Teléfono local | G93: =SUM(G94) -> 0 | H93: =SUM(H94) -> 211191.19 | I93: =SUM(G93:H93) -> 211191.19
A94: 2 | B94: 2 | C94: 1 | D94: 3 | E94: 01 | F94: Teléfono local | G94: ='[1]CUENTA T FONDO 100'!AQ127 -> 0 | H94: ='[1]CUENTA T VS'!AQ96 -> 211191.19 | I94: =SUM(G94:H94) -> 211191.19 | J94: =I94/$I$25 -> 0.001699428
A95: 2 | B95: 2 | C95: 1 | D95: 4 | F95: Telefax y correos | G95: =SUM(G96) -> 0 | H95: =SUM(H96) -> 0 | I95: =SUM(G95:H95) -> 0
A96: 2 | B96: 2 | C96: 1 | D96: 4 | E96: 01 | F96: Telefax y correos | G96: ='[1]CUENTA T FONDO 100'!AR127 -> 0 | H96: ='[1]CUENTA T VS'!AR96 -> 0 | I96: =SUM(G96:H96) -> 0 | J96: =I96/$I$25 -> 0
A97: 2 | B97: 2 | C97: 1 | D97: 5 | F97: Servicio de Internet y televisión por cable | G97: =SUM(G98) -> 0 | H97: =SUM(H98) -> 0 | I97: =SUM(G97:H97) -> 0
A98: 2 | B98: 2 | C98: 1 | D98: 5 | E98: 01 | F98: Servicio de Internet y televisión por cable | G98: ='[1]CUENTA T FONDO 100'!AS127 -> 0 | H98: ='[1]CUENTA T VS'!AS96 -> 0 | I98: =SUM(G98:H98) -> 0 | J98: =I98/$I$25 -> 0
A99: 2 | B99: 2 | C99: 1 | D99: 6 | F99: Electricidad | G99: =SUM(G100:G101) -> 0 | H99: =SUM(H100:H101) -> 0 | I99: =SUM(G99:H99) -> 0
A100: 2 | B100: 2 | C100: 1 | D100: 6 | E100: 01 | F100: Energía eléctrica | G100: ='[1]CUENTA T FONDO 100'!AT127 -> 0 | H100: ='[1]CUENTA T VS'!AT96 -> 0 | I100: =SUM(G100:H100) -> 0 | J100: =I100/$I$25 -> 0
A101: 2 | B101: 2 | C101: 1 | D101: 6 | E101: 02 | F101: Electricidad no cortable | G101: ='[1]CUENTA T FONDO 100'!AU127 -> 0 | H101: ='[1]CUENTA T VS'!AU96 -> 0 | I101: =SUM(G101:H101) -> 0 | J101: =I101/$I$25 -> 0
A102: 2 | B102: 2 | C102: 1 | D102: 7 | F102: Agua | G102: =SUM(G103) -> 2020024.3 | H102: =SUM(H103) -> 0 | I102: =SUM(G102:H102) -> 2020024.3
...

Sheet FEBRERO 2025
A1: Form. No.6 SRS
A3: Servicio Nacional de Salud
A4: Dirección de Fizcalización
A5: Consolidado de Ingresos y Gastos por Fuente de Financiamiento
A6: HOSPITAL MATERNO INFANTIL SAN LORENZO DE LOS MINA
A7: FEBRERO 2025
C8: Ingresos Generales:
E9: 1.- Balance Inicial / Fuente:
E10: Anticipo Financiero | H10: Otros Aportes | L10: Contraseña: 0001
E11: Transferencias Corrientes
E12: Venta de Servicios | G12: 500388.24
E13: 2.- Ingresos por Fuente / Cuenta
E14: Anticipo Financiero | H14: Otros Aportes | L14: OBJETAL | M14: FR | N14: VS
E15: Transferencias Corrientes | G15: =12593841.17+3169632.08+84553321.83 -> 1.003168e+08 | H15: Aportes Nomina SNS | I15: 0 | L15: 2.1 | M15: =G26 -> 67131936 | N15: =H26 -> 0
E16: Venta de Servicios | G16: =+'[2]INGR SEGUN ORIGEN'!E31+'[2]INGR SEGUN ORIGEN'!E25 -> 9549024.6 | L16: 2.2 | M16: =G87 -> 1336968.6 | N16: =H87 -> 1213383.4
H17: TOTAL INGRESOS RDS | I17: =+G10+G11+G12+I10+G14+G15+G16+I14+I15 -> 1.1036621e+08 | L17: 2.3 | M17: ='[2]CONS. FUENTES FINAN'!G212 -> 14433131 | N17: ='[2]CONS. FUENTES FINAN'!H212 -> 2432378.3
L18: 2.4 | M18: =G330 -> 0 | N18: =H330 -> 23400
L19: 2.6 | M19: =G336 -> 6461017.3 | N19: =H336 -> 3887510
L20: 2.7 | M20: ='[2]CONS. FUENTES FINAN'!G463 -> 0 | N20: ='[2]CONS. FUENTES FINAN'!H463 -> 0
A21: 1 | F21: 2 | G21: 3 | I21: 4 | J21: 5
A22: Código Presupuestario | F22: Descripción Gasto por Cuenta | G22: Distribución del Gasto por Fuente de Financiamiento | I22: TOTAL | J22: %
A23: Tipo | B23: Objeto | C23: Cuenta | D23: Sub-Cuenta | E23: Auxiliar | G23: Fondo 100 | H23: Venta de Servicios/ Otros Aportes
A25: 2 | F25: Gastos | G25: =+G26+G87+G212+G330+G336+G463 -> 89363053 | H25: =+H26+H87+H212+H330+H336+H463 -> 7556671.6 | I25: =SUM(G25:H25) -> 96919725 | J25: =+J26+J87+J212+J330+J336+J463 -> 1
A26: 2 | B26: 1 | F26: Servicios Personales | G26: =+G27+G51+G64+G71+G78 -> 67131936 | H26: =+H27+H51+H64+H71+H78 -> 0 | I26: =SUM(G26:H26) -> 67131936 | J26: =I26/$I$25 -> 0.69265504
A27: 2 | B27: 1 | C27: 1 | F27: Remuneraciones | G27: =+G28+G35+G42+G44+G46 -> 55586129 | H27: =+H28+H35+H42+H44+H46 -> 0 | I27: =SUM(G27:H27) -> 55586129 | J27: =I27/$I$25 -> 0.57352751
A28: 2 | B28: 1 | C28: 1 | D28: 1 | F28: Remuneraciones al personal fijo | G28: =SUM(G29:G34) -> 53156478 | H28: =SUM(H29:H34) -> 0 | I28: =SUM(G28:H28) -> 53156478 | J28: =I28/$I$25 -> 0.54845882
A29: 2 | B29: 1 | C29: 1 | D29: 1 | E29: 01 | F29: Sueldos a empleados fijos | G29: ='[2]CUENTA T FONDO 100'!A116 -> 53156478 | H29: ='[2]CUENTA T VS'!A96 -> 0 | I29: =SUM(G29:H29) -> 53156478 | J29: =I29/$I$25 -> 0.54845882
A30: 2 | B30: 1 | C30: 1 | D30: 1 | E30: 02 | F30: Sueldos a médicos | G30: ='[2]CUENTA T FONDO 100'!B116 -> 0 | H30: ='[2]CUENTA T VS'!B96 -> 0 | I30: =SUM(G30:H30) -> 0 | J30: =I30/$I$25 -> 0
A31: 2 | B31: 1 | C31: 1 | D31: 1 | E31: 03 | F31: Ascensos a militares | G31: ='[2]CUENTA T FONDO 100'!C116 -> 0 | H31: ='[2]CUENTA T VS'!C96 -> 0 | I31: =SUM(G31:H31) -> 0 | J31: =I31/$I$25 -> 0
A32: 2 | B32: 1 | C32: 1 | D32: 1 | E32: 04 | F32: Nuevas plazas maestros | G32: ='[2]CUENTA T FONDO 100'!D116 -> 0 | H32: ='[2]CUENTA T VS'!D96 -> 0 | I32: =SUM(G32:H32) -> 0 | J32: =I32/$I$25 -> 0
A33: 2 | B33: 1 | C33: 1 | D33: 1 | E33: 05 | F33: Incentivos y escalafón | G33: ='[2]CUENTA T FONDO 100'!E116 -> 0 | H33: ='[2]CUENTA T VS'!E96 -> 0 | I33: =SUM(G33:H33) -> 0 | J33: =I33/$I$25 -> 0
A34: 2 | B34: 1 | C34: 1 | D34: 1 | E34: 06 | F34: Nuevas plazas a médicos | G34: ='[2]CUENTA T FONDO 100'!F116 -> 0 | H34: ='[2]CUENTA T VS'!F96 -> 0 | I34: =SUM(G34:H34) -> 0 | J34: =I34/$I$25 -> 0
A35: 2 | B35: 1 | C35: 1 | D35: 2 | F35: Remuneraciones al personal con carácter transitorio | G35: =SUM(G36:G41) -> 1096531 | H35: =SUM(H36:H41) -> 0 | I35: =SUM(G35:H35) -> 1096531
A36: 2 | B36: 1 | C36: 1 | D36: 2 | E36: 03 | F36: Suplencias | G36: ='[2]CUENTA T FONDO 100'!G116 -> 0 | H36: ='[2]CUENTA T VS'!G96 -> 0 | I36: =SUM(G36:H36) -> 0 | J36: =I36/$I$25 -> 0
A37: 2 | B37: 1 | C37: 1 | D37: 2 | E37: 05 | F37: Sueldo al personal nominal en período probatorio | G37: ='[2]CUENTA T FONDO 100'!H116 -> 0 | H37: ='[2]CUENTA T VS'!H96 -> 0 | I37: =SUM(G37:H37) -> 0 | J37: =I37/$I$25 -> 0
A38: 2 | B38: 1 | C38: 1 | D38: 2 | E38: 06 | F38: Jornales | G38: ='[2]CUENTA T FONDO 100'!I116 -> 0 | H38: ='[2]CUENTA T VS'!I96 -> 0 | I38: =SUM(G38:H38) -> 0 | J38: =I38/$I$25 -> 0
A39: 2 | B39: 1 | C39: 1 | D39: 2 | E39: 08 | F39: Empleados temporales | G39: ='[2]CUENTA T FONDO 100'!J116 -> 1096531 | H39: ='[2]CUENTA T VS'!J96 -> 0 | I39: =SUM(G39:H39) -> 1096531 | J39: =I39/$I$25 -> 0.011313807
A40: 2 | B40: 1 | C40: 1 | D40: 2 | E40: 09 | F40: Personal de carácter eventual | G40: ='[2]CUENTA T FONDO 100'!K116 -> 0 | H40: ='[2]CUENTA T VS'!K96 -> 0 | I40: =SUM(G40:H40) -> 0 | J40: =I40/$I$25 -> 0
A41: 2 | B41: 1 | C41: 1 | D41: 2 | E41: 11 | F41: Interinato | G41: ='[2]CUENTA T FONDO 100'!L116 -> 0 | H41: ='[2]CUENTA T VS'!L96 -> 0 | I41: =SUM(G41:H41) -> 0 | J41: =I41/$I$25 -> 0
A42: 2 | B42: 1 | C42: 1 | D42: 3 | F42: Sueldos al personal fijo en trámite de pensiones | G42: =SUM(G43) -> 0 | H42: =SUM(H43) -> 0 | I42: =SUM(G42:H42) -> 0
A43: 2 | B43: 1 | C43: 1 | D43: 3 | E43: 01 | F43: Sueldos al personal fijo en trámite de pensiones | G43: ='[2]CUENTA T FONDO 100'!M116 -> 0 | H43: ='[2]CUENTA T VS'!M96 -> 0 | I43: =SUM(G43:H43) -> 0 | J43: =I43/$I$25 -> 0
A44: 2 | B44: 1 | C44: 1 | D44: 4 | F44: Sueldo anual no. 13 | G44: =SUM(G45) -> 0 | H44: =SUM(H45) -> 0 | I44: =SUM(G44:H44) -> 0
A45: 2 | B45: 1 | C45: 1 | D45: 4 | E45: 01 | F45: Sueldo anual no. 13 | G45: ='[2]CUENTA T FONDO 100'!N116 -> 0 | H45: ='[2]CUENTA T VS'!N96 -> 0 | I45: =SUM(G45:H45) -> 0 | J45: =I45/$I$25 -> 0
A46: 2 | B46: 1 | C46: 1 | D46: 5 | F46: Prestaciones económinas | G46: =SUM(G47:G50) -> 1333120.1 | H46: =SUM(H47:H50) -> 0 | I46: =SUM(G46:H46) -> 1333120.1
A47: 2 | B47: 1 | C47: 1 | D47: 5 | E47: 01 | F47: Prestaciones económinas | G47: ='[2]CUENTA T FONDO 100'!O116 -> 815000 | H47: ='[2]CUENTA T VS'!O96 -> 0 | I47: =SUM(G47:H47) -> 815000 | J47: =I47/$I$25 -> 0.008409021
A48: 2 | B48: 1 | C48: 1 | D48: 5 | E48: 02 | F48: Pago de porcentaje por desvinculación de cargo | G48: ='[2]CUENTA T FONDO 100'!P116 -> 0 | H48: ='[2]CUENTA T VS'!P96 -> 0 | I48: =SUM(G48:H48) -> 0 | J48: =I48/$I$25 -> 0
A49: 2 | B49: 1 | C49: 1 | D49: 5 | E49: 03 | F49: Prestación laboral por desvinculación | G49: ='[2]CUENTA T FONDO 100'!Q116 -> 0 | H49: ='[2]CUENTA T VS'!Q96 -> 0 | I49: =SUM(G49:H49) -> 0 | J49: =I49/$I$25 -> 0
A50: 2 | B50: 1 | C50: 1 | D50: 5 | E50: 04 | F50: Proporción de vacaciones no disfrutadas | G50: ='[2]CUENTA T FONDO 100'!R116 -> 518120.15 | H50: ='[2]CUENTA T VS'!R96 -> 0 | I50: =SUM(G50:H50) -> 518120.15 | J50: =I50/$I$25 -> 0.005345869
A51: 2 | B51: 1 | C51: 2 | F51: Sobresueldos | G51: =+G52+G54 -> 3197999.6 | H51: =+H52+H54 -> 0 | I51: =SUM(G51:H51) -> 3197999.6
A52: 2 | B52: 1 | C52: 2 | D52: 1 | F52: Primas por antigüedad | G52: =SUM(G53) -> 2752136.5 | H52: =SUM(H53) -> 0 | I52: =SUM(G52:H52) -> 2752136.5
A53: 2 | B53: 1 | C53: 2 | D53: 1 | E53: 01 | F53: Primas por antigüedad | G53: ='[2]CUENTA T FONDO 100'!S116 -> 2752136.5 | H53: ='[2]CUENTA T VS'!S96 -> 0 | I53: =SUM(G53:H53) -> 2752136.5 | J53: =I53/$I$25 -> 0.028396041
A54: 2 | B54: 1 | C54: 2 | D54: 2 | F54: Compensación | G54: =SUM(G55:G63) -> 445863.1 | H54: =SUM(H55:H63) -> 0 | I54: =SUM(G54:H54) -> 445863.1
A55: 2 | B55: 1 | C55: 2 | D55: 2 | E55: 01 | F55: Compensación por gastos de alimentación | G55: ='[2]CUENTA T FONDO 100'!T116 -> 0 | H55: ='[2]CUENTA T VS'!T96 -> 0 | I55: =SUM(G55:H55) -> 0 | J55: =I55/$I$25 -> 0
A56: 2 | B56: 1 | C56: 2 | D56: 2 | E56: 03 | F56: Pago de horas extraordinarias | G56: ='[2]CUENTA T FONDO 100'!U116 -> 0 | H56: ='[2]CUENTA T VS'!U96 -> 0 | I56: =SUM(G56:H56) -> 0 | J56: =I56/$I$25 -> 0
A57: 2 | B57: 1 | C57: 2 | D57: 2 | E57: 04 | F57: Prima de transporte | G57: ='[2]CUENTA T FONDO 100'!V116 -> 0 | H57: ='[2]CUENTA T VS'!V96 -> 0 | I57: =SUM(G57:H57) -> 0 | J57: =I57/$I$25 -> 0
A58: 2 | B58: 1 | C58: 2 | D58: 2 | E58: 05 | F58: Compensación servicios de Seguridad | G58: ='[2]CUENTA T FONDO 100'!W116 -> 45000 | H58: ='[2]CUENTA T VS'!W96 -> 0 | I58: =SUM(G58:H58) -> 45000 | J58: =I58/$I$25 -> 0.00046430177
A59: 2 | B59: 1 | C59: 2 | D59: 2 | E59: 06 | F59: Incentivo por Rendimieto Individual | G59: ='[2]CUENTA T FONDO 100'!X116 -> 0 | H59: ='[2]CUENTA T VS'!X96 -> 0 | I59: =SUM(G59:H59) -> 0 | J59: =I59/$I$25 -> 0
A60: 2 | B60: 1 | C60: 2 | D60: 2 | E60: 07 | F60: Compensación por distancia | G60: ='[2]CUENTA T FONDO 100'!Y116 -> 0 | H60: ='[2]CUENTA T VS'!Y96 -> 0 | I60: =SUM(G60:H60) -> 0 | J60: =I60/$I$25 -> 0
A61: 2 | B61: 1 | C61: 2 | D61: 2 | E61: 08 | F61: Compensaciones especiales | G61: ='[2]CUENTA T FONDO 100'!Z116 -> 331200 | H61: ='[2]CUENTA T VS'!Z96 -> 0 | I61: =SUM(G61:H61) -> 331200 | J61: =I61/$I$25 -> 0.003417261
A62: 2 | B62: 1 | C62: 2 | D62: 2 | E62: 09 | F62: Bono por desempeño a servidores de carrera | G62: ='[2]CUENTA T FONDO 100'!AA116 -> 0 | H62: ='[2]CUENTA T VS'!AA96 -> 0 | I62: =SUM(G62:H62) -> 0 | J62: =I62/$I$25 -> 0
A63: 2 | B63: 1 | C63: 2 | D63: 2 | E63: 10 | F63: Compensacion por cumplimiento de indicadores | G63: ='[2]CUENTA T FONDO 100'!AB116 -> 69663.1 | H63: ='[2]CUENTA T VS'!AB96 -> 0 | I63: =SUM(G63:H63) -> 69663.1 | J63: =I63/$I$25 -> 0.00071877113
A64: 2 | B64: 1 | C64: 3 | F64: Dietas y Gastos de Representación | G64: =+G65+G68 -> 0 | H64: =+H65+H68 -> 0 | I64: =SUM(G64:H64) -> 0
A65: 2 | B65: 1 | C65: 3 | D65: 1 | F65: Dietas | G65: =SUM(G66:G67) -> 0 | H65: =SUM(H66:H67) -> 0 | I65: =SUM(G65:H65) -> 0
A66: 2 | B66: 1 | C66: 3 | D66: 1 | E66: 01 | F66: Dietas en el país | G66: ='[2]CUENTA T FONDO 100'!AC116 -> 0 | H66: ='[2]CUENTA T VS'!AC96 -> 0 | I66: =SUM(G66:H66) -> 0 | J66: =I66/$I$25 -> 0
A67: 2 | B67: 1 | C67: 3 | D67: 1 | E67: 02 | F67: Dietas en el exterior | G67: ='[2]CUENTA T FONDO 100'!AD116 -> 0 | H67: ='[2]CUENTA T VS'!AD96 -> 0 | I67: =SUM(G67:H67) -> 0 | J67: =I67/$I$25 -> 0
A68: 2 | B68: 1 | C68: 3 | D68: 2 | F68: Gastos de representación | G68: =SUM(G69:G70) -> 0 | H68: =SUM(H69:H70) -> 0 | I68: =SUM(G68:H68) -> 0
A69: 2 | B69: 1 | C69: 3 | D69: 2 | E69: 01 | F69: Gastos de representación en el país | G69: ='[2]CUENTA T FONDO 100'!AE116 -> 0 | H69: ='[2]CUENTA T VS'!AE96 -> 0 | I69: =SUM(G69:H69) -> 0 | J69: =I69/$I$25 -> 0
A70: 2 | B70: 1 | C70: 3 | D70: 2 | E70: 02 | F70: Gastos de representación en el exterior | G70: ='[2]CUENTA T FONDO 100'!AF116 -> 0 | H70: ='[2]CUENTA T VS'!AF96 -> 0 | I70: =SUM(G70:H70) -> 0 | J70: =I70/$I$25 -> 0
A71: 2 | B71: 1 | C71: 4 | F71: Gratificaciones y Bonificaciones | G71: =+G72+G74 -> 0 | H71: =+H72+H74 -> 0 | I71: =SUM(G71:H71) -> 0
A72: 2 | B72: 1 | C72: 4 | D72: 1 | F72: Bonificaciones | G72: =SUM(G73) -> 0 | H72: =SUM(H73) -> 0 | I72: =SUM(G72:H72) -> 0
A73: 2 | B73: 1 | C73: 4 | D73: 1 | E73: 01 | F73: Bonificaciones | G73: ='[2]CUENTA T FONDO 100'!AG116 -> 0 | H73: ='[2]CUENTA T VS'!AG96 -> 0 | I73: =SUM(G73:H73) -> 0 | J73: =I73/$I$25 -> 0
A74: 2 | B74: 1 | C74: 4 | D74: 2 | F74: Otras Gratificaciones y Bonificaciones | G74: =SUM(G75:G77) -> 0 | H74: =SUM(H75:H77) -> 0 | I74: =SUM(G74:H74) -> 0
A75: 2 | B75: 1 | C75: 4 | D75: 2 | E75: 01 | F75: Bono escolar | G75: ='[2]CUENTA T FONDO 100'!AH116 -> 0 | H75: ='[2]CUENTA T VS'!AH96 -> 0 | I75: =SUM(G75:H75) -> 0 | J75: =I75/$I$25 -> 0
A76: 2 | B76: 1 | C76: 4 | D76: 2 | E76: 02 | F76: Gratificaciones por pasantías | G76: ='[2]CUENTA T FONDO 100'!AI116 -> 0 | H76: ='[2]CUENTA T VS'!AI96 -> 0 | I76: =SUM(G76:H76) -> 0 | J76: =I76/$I$25 -> 0
A77: 2 | B77: 1 | C77: 4 | D77: 2 | E77: 03 | F77: Gratificaciones por aniversario de institución | G77: ='[2]CUENTA T FONDO 100'!AJ116 -> 0 | H77: ='[2]CUENTA T VS'!AJ96 -> 0 | I77: =SUM(G77:H77) -> 0 | J77: =I77/$I$25 -> 0
A78: 2 | B78: 1 | C78: 5 | F78: Contribuciones a la Seguridad Social y Riesgo Laboral | G78: =+G79+G81+G83+G85 -> 8347807.5 | H78: =+H79+H81+H83+H85 -> 0 | I78: =SUM(G78:H78) -> 8347807.5
A79: 2 | B79: 1 | C79: 5 | D79: 1 | F79: Contribuciones al seguro de salud | G79: =SUM(G80) -> 3846540.6 | H79: =SUM(H80) -> 0 | I79: =SUM(G79:H79) -> 3846540.6
A80: 2 | B80: 1 | C80: 5 | D80: 1 | E80: 01 | F80: Contribuciones al seguro de salud | G80: ='[2]CUENTA T FONDO 100'!AK116 -> 3846540.6 | H80: ='[2]CUENTA T VS'!AK96 -> 0 | I80: =SUM(G80:H80) -> 3846540.6 | J80: =I80/$I$25 -> 0.039687903
A81: 2 | B81: 1 | C81: 5 | D81: 2 | F81: Contribuciones al seguro de pensiones | G81: =SUM(G82) -> 3851964.1 | H81: =SUM(H82) -> 0 | I81: =SUM(G81:H81) -> 3851964.1
A82: 2 | B82: 1 | C82: 5 | D82: 2 | E82: 01 | F82: Contribuciones al seguro de pensiones | G82: ='[2]CUENTA T FONDO 100'!AL116 -> 3851964.1 | H82: ='[2]CUENTA T VS'!AL96 -> 0 | I82: =SUM(G82:H82) -> 3851964.1 | J82: =I82/$I$25 -> 0.039743861
A83: 2 | B83: 1 | C83: 5 | D83: 3 | F83: Contribuciones al seguro de riesgo laboral | G83: =SUM(G84) -> 649302.85 | H83: =SUM(H84) -> 0 | I83: =SUM(G83:H83) -> 649302.85
A84: 2 | B84: 1 | C84: 5 | D84: 3 | E84: 01 | F84: Contribuciones al seguro de riesgo laboral | G84: ='[2]CUENTA T FONDO 100'!AM116 -> 649302.85 | H84: ='[2]CUENTA T VS'!AM96 -> 0 | I84: =SUM(G84:H84) -> 649302.85 | J84: =I84/$I$25 -> 0.0066993881
A85: 2 | B85: 1 | C85: 5 | D85: 4 | F85: Contribuciones al plan de retiro complementario | G85: =SUM(G86) -> 0 | H85: =SUM(H86) -> 0 | I85: =SUM(G85:H85) -> 0
A86: 2 | B86: 1 | C86: 5 | D86: 4 | E86: 01 | F86: Contribuciones al plan de retiro complementario | G86: ='[2]CUENTA T FONDO 100'!AN116 -> 0 | H86: ='[2]CUENTA T VS'!AN96 -> 0 | I86: =SUM(G86:H86) -> 0 | J86: =I86/$I$25 -> 0
A87: 2 | B87: 2 | F87: Servicios No Personales | G87: =G88+G106+G111+G116+G125+G148+G157+G179+G208 -> 1336968.6 | H87: =H88+H106+H111+H116+H125+H148+H157+H179+H208 -> 1213383.4 | I87: =SUM(G87:H87) -> 2550352 | J87: =I87/$I$25 -> 0.026314065
A88: 2 | B88: 2 | C88: 1 | F88: Servicios Básicos | G88: =+G89+G91+G93+G95+G97+G99+G102+G104 -> 0 | H88: =+H89+H91+H93+H95+H97+H99+H102+H104 -> 259054.4 | I88: =SUM(G88:H88) -> 259054.4
A89: 2 | B89: 2 | C89: 1 | D89: 1 | F89: Radiocomunicación | G89: =SUM(G90) -> 0 | H89: =SUM(H90) -> 0 | I89: =SUM(G89:H89) -> 0
A90: 2 | B90: 2 | C90: 1 | D90: 1 | E90: 01 | F90: Radiocomunicación | G90: ='[2]CUENTA T FONDO 100'!AO116 -> 0 | H90: ='[2]CUENTA T VS'!AO96 -> 0 | I90: =SUM(G90:H90) -> 0 | J90: =I90/$I$25 -> 0
A91: 2 | B91: 2 | C91: 1 | D91: 2 | F91: Servicios telefónico de larga distancia | G91: =SUM(G92) -> 0 | H91: =SUM(H92) -> 0 | I91: =SUM(G91:H91) -> 0
A92: 2 | B92: 2 | C92: 1 | D92: 2 | E92: 01 | F92: Servicios telefónico de larga distancia | G92: ='[2]CUENTA T FONDO 100'!AP116 -> 0 | H92: ='[2]CUENTA T VS'!AP96 -> 0 | I92: =SUM(G92:H92) -> 0 | J92: =I92/$I$25 -> 0
A93: 2 | B93: 2 | C93: 1 | D93: 3 | F93: Teléfono local | G93: =SUM(G94) -> 0 | H93: =SUM(H94) -> 259054.4 | I93: =SUM(G93:H93) -> 259054.4
A94: 2 | B94: 2 | C94: 1 | D94: 3 | E94: 01 | F94: Teléfono local | G94: ='[2]CUENTA T FONDO 100'!AQ116 -> 0 | H94: ='[2]CUENTA T VS'!AQ96 -> 259054.4 | I94: =SUM(G94:H94) -> 259054.4 | J94: =I94/$I$25 -> 0.0026728759
A95: 2 | B95: 2 | C95: 1 | D95: 4 | F95: Telefax y correos | G95: =SUM(G96) -> 0 | H95: =SUM(H96) -> 0 | I95: =SUM(G95:H95) -> 0
A96: 2 | B96: 2 | C96: 1 | D96: 4 | E96: 01 | F96: Telefax y correos | G96: ='[2]CUENTA T FONDO 100'!AR116 -> 0 | H96: ='[2]CUENTA T VS'!AR96 -> 0 | I96: =SUM(G96:H96) -> 0 | J96: =I96/$I$25 -> 0
A97: 2 | B97: 2 | C97: 1 | D97: 5 | F97: Servicio de Internet y televisión por cable | G97: =SUM(G98) -> 0 | H97: =SUM(H98) -> 0 | I97: =SUM(G97:H97) -> 0
A98: 2 | B98: 2 | C98: 1 | D98: 5 | E98: 01 | F98: Servicio de Internet y televisión por cable | G98: ='[2]CUENTA T FONDO 100'!AS116 -> 0 | H98: ='[2]CUENTA T VS'!AS96 -> 0 | I98: =SUM(G98:H98) -> 0 | J98: =I98/$I$25 -> 0
A99: 2 | B99: 2 | C99: 1 | D99: 6 | F99: Electricidad | G99: =SUM(G100:G101) -> 0 | H99: =SUM(H100:H101) -> 0 | I99: =SUM(G99:H99) -> 0
A100: 2 | B100: 2 | C100: 1 | D100: 6 | E100: 01 | F100: Energía eléctrica | G100: ='[2]CUENTA T FONDO 100'!AT116 -> 0 | H100: ='[2]CUENTA T VS'!AT96 -> 0 | I100: =SUM(G100:H100) -> 0 | J100: =I100/$I$25 -> 0
A101: 2 | B101: 2 | C101: 1 | D101: 6 | E101: 02 | F101: Electricidad no cortable | G101: ='[2]CUENTA T FONDO 100'!AU116 -> 0 | H101: ='[2]CUENTA T VS'!AU96 -> 0 | I101: =SUM(G101:H101) -> 0 | J101: =I101/$I$25 -> 0
A102: 2 | B102: 2 | C102: 1 | D102: 7 | F102: Agua | G102: =SUM(G103) -> 0 | H102: =SUM(H103) -> 0 | I102: =SUM(G102:H102) -> 0
...

Sheet ENERO 2025
A1: Form. No.6 SRS
A3: Servicio Nacional de Salud
A4: Dirección de Fizcalización
A5: Consolidado de Ingresos y Gastos por Fuente de Financiamiento
A6: HOSPITAL MATERNO INFANTIL SAN LORENZO DE LOS MINA
A7: ENERO 2025
C8: Ingresos Generales:
E9: 1.- Balance Inicial / Fuente:
E10: Anticipo Financiero | G10: 0 | H10: Otros Aportes | M10: Contraseña: 0001
E11: Transferencias Corrientes | G11: 0
E12: Venta de Servicios | G12: 2244994.1
E13: 2.- Ingresos por Fuente / Cuenta
E14: Anticipo Financiero | H14: Otros Aportes | J14: =+'[3]INGRESOS SEGUN ORIGEN'!E8 -> 15763473 | M14: OBJETAL | N14: FR | O14: VS
E15: Transferencias Corrientes | H15: Aportes Nomina SNS | J15: =+'[3]INGRESOS SEGUN ORIGEN'!E7 -> 84553322 | M15: 2.1 | N15: =G26 -> 65091180 | O15: =H26 -> 0
E16: Venta de Servicios | G16: =+'[3]INGRESOS SEGUN ORIGEN'!E24+'[3]INGRESOS SEGUN ORIGEN'!E29 -> 6032481.2 | M16: 2.2 | N16: =G87 -> 0 | O16: =H87 -> 2733844.3
H17: TOTAL INGRESOS RDS | J17: =+G10+G11+G12+J10+G14+G15+G16+J14+J15 -> 1.0859427e+08 | M17: 2.3 | N17: ='[3]CONS. FUENTES FINAN'!G212 -> 4970601.2 | O17: ='[3]CONS. FUENTES FINAN'!H212 -> 3062630.7
M18: 2.4 | N18: =G330 -> 0 | O18: =H330 -> 136966.7
M19: 2.6 | N19: =G336 -> 0 | O19: =H336 -> 887994.84
M20: 2.7 | N20: ='[3]CONS. FUENTES FINAN'!G463 -> 0 | O20: ='[3]CONS. FUENTES FINAN'!H463 -> 0
A21: 1 | F21: 2 | G21: 3 | J21: 4 | K21: 5
A22: Código Presupuestario | F22: Descripción Gasto por Cuenta | G22: Distribución del Gasto por Fuente de Financiamiento | J22: TOTAL | K22: %
A23: Tipo | B23: Objeto | C23: Cuenta | D23: Sub-Cuenta | E23: Auxiliar | G23: Fondo 100 | H23: Venta de Servicios/ Otros Aportes | I23: Aportes Nomina SNS
A25: 2 | F25: Gastos | G25: =+G26+G87+G212+G330+G336+G463 -> 70061781 | H25: =+H26+H87+H212+H330+H336+H463 -> 6821436.5 | I25: =+I26+I87+I212+I330+I336+I463 -> 0 | J25: =SUM(G25:I25) -> 76883218 | K25: =+K26+K87+K212+K330+K336+K463 -> 1 | L25: =+G25+'FEBRERO 2025'!G25 -> 1.5942483e+08 | M25: =+H25+'FEBRERO 2025'!H25 -> 14378108
A26: 2 | B26: 1 | F26: Servicios Personales | G26: =+G27+G51+G64+G71+G78 -> 65091180 | H26: =+H27+H51+H64+H71+H78 -> 0 | I26: =+I27+I51+I64+I71+I78 -> 0 | J26: =SUM(G26:I26) -> 65091180 | K26: =J26/$J$25 -> 0.84662404
A27: 2 | B27: 1 | C27: 1 | F27: Remuneraciones | G27: =+G28+G35+G42+G44+G46 -> 53640339 | H27: =+H28+H35+H42+H44+H46 -> 0 | I27: =+I28+I35+I42+I44+I46 -> 0 | J27: =SUM(G27:I27) -> 53640339 | K27: =J27/$J$25 -> 0.69768592
A28: 2 | B28: 1 | C28: 1 | D28: 1 | F28: Remuneraciones al personal fijo | G28: =SUM(G29:G34) -> 52666808 | H28: =SUM(H29:H34) -> 0 | I28: =SUM(I29:I34) -> 0 | J28: =SUM(G28:I28) -> 52666808 | K28: =J28/$J$25 -> 0.68502346
A29: 2 | B29: 1 | C29: 1 | D29: 1 | E29: 01 | F29: Sueldos a empleados fijos | G29: ='[3]CUENTA T FONDO 100'!A288 -> 52666808 | H29: ='[3]CUENTA T VS'!A81 -> 0 | I29: ='[3]CUENTA T NOMINA SNS'!A58 -> 0 | J29: =SUM(G29:I29) -> 52666808 | K29: =J29/$J$25 -> 0.68502346
A30: 2 | B30: 1 | C30: 1 | D30: 1 | E30: 02 | F30: Sueldos a médicos | G30: ='[3]CUENTA T FONDO 100'!B288 -> 0 | H30: ='[3]CUENTA T VS'!B81 -> 0 | I30: ='[3]CUENTA T NOMINA SNS'!B58 -> 0 | J30: =SUM(G30:I30) -> 0 | K30: =J30/$J$25 -> 0
A31: 2 | B31: 1 | C31: 1 | D31: 1 | E31: 03 | F31: Ascensos a militares | G31: ='[3]CUENTA T FONDO 100'!C288 -> 0 | H31: ='[3]CUENTA T VS'!C81 -> 0 | I31: ='[3]CUENTA T NOMINA SNS'!C58 -> 0 | J31: =SUM(G31:I31) -> 0 | K31: =J31/$J$25 -> 0
A32: 2 | B32: 1 | C32: 1 | D32: 1 | E32: 04 | F32: Nuevas plazas maestros | G32: ='[3]CUENTA T FONDO 100'!D288 -> 0 | H32: ='[3]CUENTA T VS'!D81 -> 0 | I32: ='[3]CUENTA T NOMINA SNS'!D58 -> 0 | J32: =SUM(G32:I32) -> 0 | K32: =J32/$J$25 -> 0
A33: 2 | B33: 1 | C33: 1 | D33: 1 | E33: 05 | F33: Incentivos y escalafón | G33: ='[3]CUENTA T FONDO 100'!E288 -> 0 | H33: ='[3]CUENTA T VS'!E81 -> 0 | I33: ='[3]CUENTA T NOMINA SNS'!E58 -> 0 | J33: =SUM(G33:I33) -> 0 | K33: =J33/$J$25 -> 0
A34: 2 | B34: 1 | C34: 1 | D34: 1 | E34: 06 | F34: Nuevas plazas a médicos | G34: ='[3]CUENTA T FONDO 100'!F288 -> 0 | H34: ='[3]CUENTA T VS'!F81 -> 0 | I34: ='[3]CUENTA T NOMINA SNS'!F58 -> 0 | J34: =SUM(G34:I34) -> 0 | K34: =J34/$J$25 -> 0
A35: 2 | B35: 1 | C35: 1 | D35: 2 | F35: Remuneraciones al personal con carácter transitorio | G35: =SUM(G36:G41) -> 973531.03 | H35: =SUM(H36:H41) -> 0 | I35: =SUM(I36:I41) -> 0 | J35: =SUM(G35:I35) -> 973531.03
A36: 2 | B36: 1 | C36: 1 | D36: 2 | E36: 03 | F36: Suplencias | G36: ='[3]CUENTA T FONDO 100'!G288 -> 0 | H36: ='[3]CUENTA T VS'!G81 -> 0 | I36: ='[3]CUENTA T NOMINA SNS'!G58 -> 0 | J36: =SUM(G36:I36) -> 0 | K36: =J36/$J$25 -> 0
A37: 2 | B37: 1 | C37: 1 | D37: 2 | E37: 05 | F37: Sueldo al personal nominal en período probatorio | G37: ='[3]CUENTA T FONDO 100'!H288 -> 0 | H37: ='[3]CUENTA T VS'!H81 -> 0 | I37: ='[3]CUENTA T NOMINA SNS'!H58 -> 0 | J37: =SUM(G37:I37) -> 0 | K37: =J37/$J$25 -> 0
A38: 2 | B38: 1 | C38: 1 | D38: 2 | E38: 06 | F38: Jornales | G38: ='[3]CUENTA T FONDO 100'!I288 -> 0 | H38: ='[3]CUENTA T VS'!I81 -> 0 | I38: ='[3]CUENTA T NOMINA SNS'!I58 -> 0 | J38: =SUM(G38:I38) -> 0 | K38: =J38/$J$25 -> 0
A39: 2 | B39: 1 | C39: 1 | D39: 2 | E39: 08 | F39: Empleados temporales | G39: ='[3]CUENTA T FONDO 100'!J288 -> 973531.03 | H39: ='[3]CUENTA T VS'!J81 -> 0 | I39: ='[3]CUENTA T NOMINA SNS'!J58 -> 0 | J39: =SUM(G39:I39) -> 973531.03 | K39: =J39/$J$25 -> 0.012662465
A40: 2 | B40: 1 | C40: 1 | D40: 2 | E40: 09 | F40: Personal de carácter eventual | G40: ='[3]CUENTA T FONDO 100'!K288 -> 0 | H40: ='[3]CUENTA T VS'!K81 -> 0 | I40: ='[3]CUENTA T NOMINA SNS'!K58 -> 0 | J40: =SUM(G40:I40) -> 0 | K40: =J40/$J$25 -> 0
A41: 2 | B41: 1 | C41: 1 | D41: 2 | E41: 11 | F41: Interinato | G41: ='[3]CUENTA T FONDO 100'!L288 -> 0 | H41: ='[3]CUENTA T VS'!L81 -> 0 | I41: ='[3]CUENTA T NOMINA SNS'!L58 -> 0 | J41: =SUM(G41:I41) -> 0 | K41: =J41/$J$25 -> 0
A42: 2 | B42: 1 | C42: 1 | D42: 3 | F42: Sueldos al personal fijo en trámite de pensiones | G42: =SUM(G43) -> 0 | H42: =SUM(H43) -> 0 | I42: =SUM(I43) -> 0 | J42: =SUM(G42:I42) -> 0
A43: 2 | B43: 1 | C43: 1 | D43: 3 | E43: 01 | F43: Sueldos al personal fijo en trámite de pensiones | G43: ='[3]CUENTA T FONDO 100'!M288 -> 0 | H43: ='[3]CUENTA T VS'!M81 -> 0 | I43: ='[3]CUENTA T NOMINA SNS'!M58 -> 0 | J43: =SUM(G43:I43) -> 0 | K43: =J43/$J$25 -> 0
A44: 2 | B44: 1 | C44: 1 | D44: 4 | F44: Sueldo anual no. 13 | G44: =SUM(G45) -> 0 | H44: =SUM(H45) -> 0 | I44: =SUM(I45) -> 0 | J44: =SUM(G44:I44) -> 0
A45: 2 | B45: 1 | C45: 1 | D45: 4 | E45: 01 | F45: Sueldo anual no. 13 | G45: ='[3]CUENTA T FONDO 100'!N288 -> 0 | H45: ='[3]CUENTA T VS'!N81 -> 0 | I45: ='[3]CUENTA T NOMINA SNS'!N58 -> 0 | J45: =SUM(G45:I45) -> 0 | K45: =J45/$J$25 -> 0
A46: 2 | B46: 1 | C46: 1 | D46: 5 | F46: Prestaciones económinas | G46: =SUM(G47:G50) -> 0 | H46: =SUM(H47:H50) -> 0 | I46: =SUM(I47:I50) -> 0 | J46: =SUM(G46:I46) -> 0
A47: 2 | B47: 1 | C47: 1 | D47: 5 | E47: 01 | F47: Prestaciones económinas | G47: ='[3]CUENTA T FONDO 100'!O288 -> 0 | H47: ='[3]CUENTA T VS'!O81 -> 0 | I47: ='[3]CUENTA T NOMINA SNS'!O58 -> 0 | J47: =SUM(G47:I47) -> 0 | K47: =J47/$J$25 -> 0
A48: 2 | B48: 1 | C48: 1 | D48: 5 | E48: 02 | F48: Pago de porcentaje por desvinculación de cargo | G48: ='[3]CUENTA T FONDO 100'!P288 -> 0 | H48: ='[3]CUENTA T VS'!P81 -> 0 | I48: ='[3]CUENTA T NOMINA SNS'!P58 -> 0 | J48: =SUM(G48:I48) -> 0 | K48: =J48/$J$25 -> 0
A49: 2 | B49: 1 | C49: 1 | D49: 5 | E49: 03 | F49: Prestación laboral por desvinculación | G49: ='[3]CUENTA T FONDO 100'!Q288 -> 0 | H49: ='[3]CUENTA T VS'!Q81 -> 0 | I49: ='[3]CUENTA T NOMINA SNS'!Q58 -> 0 | J49: =SUM(G49:I49) -> 0 | K49: =J49/$J$25 -> 0
A50: 2 | B50: 1 | C50: 1 | D50: 5 | E50: 04 | F50: Proporción de vacaciones no disfrutadas | G50: ='[3]CUENTA T FONDO 100'!R288 -> 0 | H50: ='[3]CUENTA T VS'!R81 -> 0 | I50: ='[3]CUENTA T NOMINA SNS'!R58 -> 0 | J50: =SUM(G50:I50) -> 0 | K50: =J50/$J$25 -> 0
A51: 2 | B51: 1 | C51: 2 | F51: Sobresueldos | G51: =+G52+G54 -> 3196999.6 | H51: =+H52+H54 -> 0 | I51: =+I52+I54 -> 0 | J51: =SUM(G51:I51) -> 3196999.6
A52: 2 | B52: 1 | C52: 2 | D52: 1 | F52: Primas por antigüedad | G52: =SUM(G53) -> 2752136.5 | H52: =SUM(H53) -> 0 | I52: =SUM(I53) -> 0 | J52: =SUM(G52:I52) -> 2752136.5
A53: 2 | B53: 1 | C53: 2 | D53: 1 | E53: 01 | F53: Primas por antigüedad | G53: ='[3]CUENTA T FONDO 100'!S288 -> 2752136.5 | H53: ='[3]CUENTA T VS'!S81 -> 0 | I53: ='[3]CUENTA T NOMINA SNS'!S58 -> 0 | J53: =SUM(G53:I53) -> 2752136.5 | K53: =J53/$J$25 -> 0.035796323
A54: 2 | B54: 1 | C54: 2 | D54: 2 | F54: Compensación | G54: =SUM(G55:G63) -> 444863.1 | H54: =SUM(H55:H63) -> 0 | I54: =SUM(I55:I63) -> 0 | J54: =SUM(G54:I54) -> 444863.1
A55: 2 | B55: 1 | C55: 2 | D55: 2 | E55: 01 | F55: Compensación por gastos de alimentación | G55: ='[3]CUENTA T FONDO 100'!T288 -> 0 | H55: ='[3]CUENTA T VS'!T81 -> 0 | I55: ='[3]CUENTA T NOMINA SNS'!T58 -> 0 | J55: =SUM(G55:I55) -> 0 | K55: =J55/$J$25 -> 0
A56: 2 | B56: 1 | C56: 2 | D56: 2 | E56: 03 | F56: Pago de horas extraordinarias | G56: ='[3]CUENTA T FONDO 100'!U288 -> 0 | H56: ='[3]CUENTA T VS'!U81 -> 0 | I56: ='[3]CUENTA T NOMINA SNS'!U58 -> 0 | J56: =SUM(G56:I56) -> 0 | K56: =J56/$J$25 -> 0
A57: 2 | B57: 1 | C57: 2 | D57: 2 | E57: 04 | F57: Prima de transporte | G57: ='[3]CUENTA T FONDO 100'!V288 -> 0 | H57: ='[3]CUENTA T VS'!V81 -> 0 | I57: ='[3]CUENTA T NOMINA SNS'!V58 -> 0 | J57: =SUM(G57:I57) -> 0 | K57: =J57/$J$25 -> 0
A58: 2 | B58: 1 | C58: 2 | D58: 2 | E58: 05 | F58: Compensación servicios de Seguridad | G58: ='[3]CUENTA T FONDO 100'!W288 -> 45000 | H58: ='[3]CUENTA T VS'!W81 -> 0 | I58: ='[3]CUENTA T NOMINA SNS'!W58 -> 0 | J58: =SUM(G58:I58) -> 45000 | K58: =J58/$J$25 -> 0.00058530329
A59: 2 | B59: 1 | C59: 2 | D59: 2 | E59: 06 | F59: Incentivo por Rendimieto Individual | G59: ='[3]CUENTA T FONDO 100'!X288 -> 0 | H59: ='[3]CUENTA T VS'!X81 -> 0 | I59: ='[3]CUENTA T NOMINA SNS'!X58 -> 0 | J59: =SUM(G59:I59) -> 0 | K59: =J59/$J$25 -> 0
A60: 2 | B60: 1 | C60: 2 | D60: 2 | E60: 07 | F60: Compensación por distancia | G60: ='[3]CUENTA T FONDO 100'!Y288 -> 0 | H60: ='[3]CUENTA T VS'!Y81 -> 0 | I60: ='[3]CUENTA T NOMINA SNS'!Y58 -> 0 | J60: =SUM(G60:I60) -> 0 | K60: =J60/$J$25 -> 0
A61: 2 | B61: 1 | C61: 2 | D61: 2 | E61: 08 | F61: Compensaciones especiales | G61: ='[3]CUENTA T FONDO 100'!Z288 -> 330200 | H61: ='[3]CUENTA T VS'!Z81 -> 0 | I61: ='[3]CUENTA T NOMINA SNS'!Z58 -> 0 | J61: =SUM(G61:I61) -> 330200 | K61: =J61/$J$25 -> 0.0042948255
A62: 2 | B62: 1 | C62: 2 | D62: 2 | E62: 09 | F62: Bono por desempeño a servidores de carrera | G62: ='[3]CUENTA T FONDO 100'!AA288 -> 0 | H62: ='[3]CUENTA T VS'!AA81 -> 0 | I62: ='[3]CUENTA T NOMINA SNS'!AA58 -> 0 | J62: =SUM(G62:I62) -> 0 | K62: =J62/$J$25 -> 0
A63: 2 | B63: 1 | C63: 2 | D63: 2 | E63: 10 | F63: Compensacion por cumplimiento de indicadores | G63: ='[3]CUENTA T FONDO 100'!AB288 -> 69663.1 | H63: ='[3]CUENTA T VS'!AB81 -> 0 | I63: ='[3]CUENTA T NOMINA SNS'!AB58 -> 0 | J63: =SUM(G63:I63) -> 69663.1 | K63: =J63/$J$25 -> 0.00090608981
A64: 2 | B64: 1 | C64: 3 | F64: Dietas y Gastos de Representación | G64: =+G65+G68 -> 0 | H64: =+H65+H68 -> 0 | I64: =+I65+I68 -> 0 | J64: =SUM(G64:I64) -> 0
A65: 2 | B65: 1 | C65: 3 | D65: 1 | F65: Dietas | G65: =SUM(G66:G67) -> 0 | H65: =SUM(H66:H67) -> 0 | I65: =SUM(I66:I67) -> 0 | J65: =SUM(G65:I65) -> 0
A66: 2 | B66: 1 | C66: 3 | D66: 1 | E66: 01 | F66: Dietas en el país | G66: ='[3]CUENTA T FONDO 100'!AC288 -> 0 | H66: ='[3]CUENTA T VS'!AC81 -> 0 | I66: ='[3]CUENTA T NOMINA SNS'!AC58 -> 0 | J66: =SUM(G66:I66) -> 0 | K66: =J66/$J$25 -> 0
A67: 2 | B67: 1 | C67: 3 | D67: 1 | E67: 02 | F67: Dietas en el exterior | G67: ='[3]CUENTA T FONDO 100'!AD288 -> 0 | H67: ='[3]CUENTA T VS'!AD81 -> 0 | I67: ='[3]CUENTA T NOMINA SNS'!AD58 -> 0 | J67: =SUM(G67:I67) -> 0 | K67: =J67/$J$25 -> 0
A68: 2 | B68: 1 | C68: 3 | D68: 2 | F68: Gastos de representación | G68: =SUM(G69:G70) -> 0 | H68: =SUM(H69:H70) -> 0 | I68: =SUM(I69:I70) -> 0 | J68: =SUM(G68:I68) -> 0
A69: 2 | B69: 1 | C69: 3 | D69: 2 | E69: 01 | F69: Gastos de representación en el país | G69: ='[3]CUENTA T FONDO 100'!AE288 -> 0 | H69: ='[3]CUENTA T VS'!AE81 -> 0 | I69: ='[3]CUENTA T NOMINA SNS'!AE58 -> 0 | J69: =SUM(G69:I69) -> 0 | K69: =J69/$J$25 -> 0
A70: 2 | B70: 1 | C70: 3 | D70: 2 | E70: 02 | F70: Gastos de representación en el exterior | G70: ='[3]CUENTA T FONDO 100'!AF288 -> 0 | H70: ='[3]CUENTA T VS'!AF81 -> 0 | I70: ='[3]CUENTA T NOMINA SNS'!AF58 -> 0 | J70: =SUM(G70:I70) -> 0 | K70: =J70/$J$25 -> 0
A71: 2 | B71: 1 | C71: 4 | F71: Gratificaciones y Bonificaciones | G71: =+G72+G74 -> 0 | H71: =+H72+H74 -> 0 | I71: =+I72+I74 -> 0 | J71: =SUM(G71:I71) -> 0
A72: 2 | B72: 1 | C72: 4 | D72: 1 | F72: Bonificaciones | G72: =SUM(G73) -> 0 | H72: =SUM(H73) -> 0 | I72: =SUM(I73) -> 0 | J72: =SUM(G72:I72) -> 0
A73: 2 | B73: 1 | C73: 4 | D73: 1 | E73: 01 | F73: Bonificaciones | G73: ='[3]CUENTA T FONDO 100'!AG288 -> 0 | H73: ='[3]CUENTA T VS'!AG81 -> 0 | I73: ='[3]CUENTA T NOMINA SNS'!AG58 -> 0 | J73: =SUM(G73:I73) -> 0 | K73: =J73/$J$25 -> 0
A74: 2 | B74: 1 | C74: 4 | D74: 2 | F74: Otras Gratificaciones y Bonificaciones | G74: =SUM(G75:G77) -> 0 | H74: =SUM(H75:H77) -> 0 | I74: =SUM(I75:I77) -> 0 | J74: =SUM(G74:I74) -> 0
A75: 2 | B75: 1 | C75: 4 | D75: 2 | E75: 01 | F75: Bono escolar | G75: ='[3]CUENTA T FONDO 100'!AH288 -> 0 | H75: ='[3]CUENTA T VS'!AH81 -> 0 | I75: ='[3]CUENTA T NOMINA SNS'!AH58 -> 0 | J75: =SUM(G75:I75) -> 0 | K75: =J75/$J$25 -> 0
A76: 2 | B76: 1 | C76: 4 | D76: 2 | E76: 02 | F76: Gratificaciones por pasantías | G76: ='[3]CUENTA T FONDO 100'!AI288 -> 0 | H76: ='[3]CUENTA T VS'!AI81 -> 0 | I76: ='[3]CUENTA T NOMINA SNS'!AI58 -> 0 | J76: =SUM(G76:I76) -> 0 | K76: =J76/$J$25 -> 0
A77: 2 | B77: 1 | C77: 4 | D77: 2 | E77: 03 | F77: Gratificaciones por aniversario de institución | G77: ='[3]CUENTA T FONDO 100'!AJ288 -> 0 | H77: ='[3]CUENTA T VS'!AJ81 -> 0 | I77: ='[3]CUENTA T NOMINA SNS'!AJ58 -> 0 | J77: =SUM(G77:I77) -> 0 | K77: =J77/$J$25 -> 0
A78: 2 | B78: 1 | C78: 5 | F78: Contribuciones a la Seguridad Social y Riesgo Laboral | G78: =+G79+G81+G83+G85 -> 8253841.6 | H78: =+H79+H81+H83+H85 -> 0 | I78: =+I79+I81+I83+I85 -> 0 | J78: =SUM(G78:I78) -> 8253841.6
A79: 2 | B79: 1 | C79: 5 | D79: 1 | F79: Contribuciones al seguro de salud | G79: =SUM(G80) -> 3803102.3 | H79: =SUM(H80) -> 0 | I79: =SUM(I80) -> 0 | J79: =SUM(G79:I79) -> 3803102.3
A80: 2 | B80: 1 | C80: 5 | D80: 1 | E80: 01 | F80: Contribuciones al seguro de salud | G80: ='[3]CUENTA T FONDO 100'!AK288 -> 3803102.3 | H80: ='[3]CUENTA T VS'!AK81 -> 0 | I80: ='[3]CUENTA T NOMINA SNS'!AK58 -> 0 | J80: =SUM(G80:I80) -> 3803102.3 | K80: =J80/$J$25 -> 0.049465962
A81: 2 | B81: 1 | C81: 5 | D81: 2 | F81: Contribuciones al seguro de pensiones | G81: =SUM(G82) -> 3808464.5 | H81: =SUM(H82) -> 0 | I81: =SUM(I82) -> 0 | J81: =SUM(G81:I81) -> 3808464.5
A82: 2 | B82: 1 | C82: 5 | D82: 2 | E82: 01 | F82: Contribuciones al seguro de pensiones | G82: ='[3]CUENTA T FONDO 100'!AL288 -> 3808464.5 | H82: ='[3]CUENTA T VS'!AL81 -> 0 | I82: ='[3]CUENTA T NOMINA SNS'!AL58 -> 0 | J82: =SUM(G82:I82) -> 3808464.5 | K82: =J82/$J$25 -> 0.049535706
A83: 2 | B83: 1 | C83: 5 | D83: 3 | F83: Contribuciones al seguro de riesgo laboral | G83: =SUM(G84) -> 642274.82 | H83: =SUM(H84) -> 0 | I83: =SUM(I84) -> 0 | J83: =SUM(G83:I83) -> 642274.82
A84: 2 | B84: 1 | C84: 5 | D84: 3 | E84: 01 | F84: Contribuciones al seguro de riesgo laboral | G84: ='[3]CUENTA T FONDO 100'!AM288 -> 642274.82 | H84: ='[3]CUENTA T VS'!AM81 -> 0 | I84: ='[3]CUENTA T NOMINA SNS'!AM58 -> 0 | J84: =SUM(G84:I84) -> 642274.82 | K84: =J84/$J$25 -> 0.0083539014
A85: 2 | B85: 1 | C85: 5 | D85: 4 | F85: Contribuciones al plan de retiro complementario | G85: =SUM(G86) -> 0 | H85: =SUM(H86) -> 0 | I85: =SUM(I86) -> 0 | J85: =SUM(G85:I85) -> 0
A86: 2 | B86: 1 | C86: 5 | D86: 4 | E86: 01 | F86: Contribuciones al plan de retiro complementario | G86: ='[3]CUENTA T FONDO 100'!AN288 -> 0 | H86: ='[3]CUENTA T VS'!AN81 -> 0 | I86: ='[3]CUENTA T NOMINA SNS'!AN58 -> 0 | J86: =SUM(G86:I86) -> 0 | K86: =J86/$J$25 -> 0
A87: 2 | B87: 2 | F87: Servicios No Personales | G87: =G88+G106+G111+G116+G125+G148+G157+G179+G208 -> 0 | H87: =H88+H106+H111+H116+H125+H148+H157+H179+H208 -> 2733844.3 | I87: =I88+I106+I111+I116+I125+I148+I157+I179+I208 -> 0 | J87: =SUM(G87:I87) -> 2733844.3 | K87: =J87/$J$25 -> 0.035558401
A88: 2 | B88: 2 | C88: 1 | F88: Servicios Básicos | G88: =+G89+G91+G93+G95+G97+G99+G102+G104 -> 0 | H88: =+H89+H91+H93+H95+H97+H99+H102+H104 -> 351316.33 | I88: =+I89+I91+I93+I95+I97+I99+I102+I104 -> 0 | J88: =SUM(G88:I88) -> 351316.33
A89: 2 | B89: 2 | C89: 1 | D89: 1 | F89: Radiocomunicación | G89: =SUM(G90) -> 0 | H89: =SUM(H90) -> 0 | I89: =SUM(I90) -> 0 | J89: =SUM(G89:I89) -> 0
A90: 2 | B90: 2 | C90: 1 | D90: 1 | E90: 01 | F90: Radiocomunicación | G90: ='[3]CUENTA T FONDO 100'!AO288 -> 0 | H90: ='[3]CUENTA T VS'!AO81 -> 0 | J90: =SUM(G90:I90) -> 0 | K90: =J90/$J$25 -> 0
A91: 2 | B91: 2 | C91: 1 | D91: 2 | F91: Servicios telefónico de larga distancia | G91: =SUM(G92) -> 0 | H91: =SUM(H92) -> 0 | I91: =SUM(I92) -> 0 | J91: =SUM(G91:I91) -> 0
A92: 2 | B92: 2 | C92: 1 | D92: 2 | E92: 01 | F92: Servicios telefónico de larga distancia | G92: ='[3]CUENTA T FONDO 100'!AP288 -> 0 | H92: ='[3]CUENTA T VS'!AP81 -> 0 | J92: =SUM(G92:I92) -> 0 | K92: =J92/$J$25 -> 0
A93: 2 | B93: 2 | C93: 1 | D93: 3 | F93: Teléfono local | G93: =SUM(G94) -> 0 | H93: =SUM(H94) -> 301316.33 | I93: =SUM(I94) -> 0 | J93: =SUM(G93:I93) -> 301316.33
A94: 2 | B94: 2 | C94: 1 | D94: 3 | E94: 01 | F94: Teléfono local | G94: ='[3]CUENTA T FONDO 100'!AQ288 -> 0 | H94: ='[3]CUENTA T VS'!AQ81 -> 301316.33 | J94: =SUM(G94:I94) -> 301316.33 | K94: =J94/$J$25 -> 0.0039191431
A95: 2 | B95: 2 | C95: 1 | D95: 4 | F95: Telefax y correos | G95: =SUM(G96) -> 0 | H95: =SUM(H96) -> 0 | I95: =SUM(I96) -> 0 | J95: =SUM(G95:I95) -> 0
A96: 2 | B96: 2 | C96: 1 | D96: 4 | E96: 01 | F96: Telefax y correos | G96: ='[3]CUENTA T FONDO 100'!AR288 -> 0 | H96: ='[3]CUENTA T VS'!AR81 -> 0 | J96: =SUM(G96:I96) -> 0 | K96: =J96/$J$25 -> 0
A97: 2 | B97: 2 | C97: 1 | D97: 5 | F97: Servicio de Internet y televisión por cable | G97: =SUM(G98) -> 0 | H97: =SUM(H98) -> 0 | I97: =SUM(I98) -> 0 | J97: =SUM(G97:I97) -> 0
A98: 2 | B98: 2 | C98: 1 | D98: 5 | E98: 01 | F98: Servicio de Internet y televisión por cable | G98: ='[3]CUENTA T FONDO 100'!AS288 -> 0 | H98: ='[3]CUENTA T VS'!AS81 -> 0 | J98: =SUM(G98:I98) -> 0 | K98: =J98/$J$25 -> 0
A99: 2 | B99: 2 | C99: 1 | D99: 6 | F99: Electricidad | G99: =SUM(G100:G101) -> 0 | H99: =SUM(H100:H101) -> 0 | I99: =SUM(I100:I101) -> 0 | J99: =SUM(G99:I99) -> 0
A100: 2 | B100: 2 | C100: 1 | D100: 6 | E100: 01 | F100: Energía eléctrica | G100: ='[3]CUENTA T FONDO 100'!AT288 -> 0 | H100: ='[3]CUENTA T VS'!AT81 -> 0 | J100: =SUM(G100:I100) -> 0 | K100: =J100/$J$25 -> 0
A101: 2 | B101: 2 | C101: 1 | D101: 6 | E101: 02 | F101: Electricidad no cortable | G101: ='[3]CUENTA T FONDO 100'!AU288 -> 0 | H101: ='[3]CUENTA T VS'!AU81 -> 0 | J101: =SUM(G101:I101) -> 0 | K101: =J101/$J$25 -> 0
A102: 2 | B102: 2 | C102: 1 | D102: 7 | F102: Agua | G102: =SUM(G103) -> 0 | H102: =SUM(H103) -> 0 | I102: =SUM(I103) -> 0 | J102: =SUM(G102:I102) -> 0
...

Sheet TRIMESTRAL
A1: Form. No.6 SRS
A3: Servicio Nacional de Salud
A4: Dirección de Fizcalización
A5: Consolidado de Ingresos y Gastos por Fuente de Financiamiento
A6: HOSPITAL MATERNO INFANTIL SAN LORENZO DE LOS MINA
A7: TRIMESTRE ENERO-MARZO 2025
C8: Ingresos Generales:
E9: 1.- Balance Inicial / Fuente:
E10: Anticipo Financiero | G10: 0 | H10: Otros Aportes | M10: Contraseña: 0001
E11: Transferencias Corrientes | G11: 0
E12: Venta de Servicios | G12: =+'ENERO 2025'!G12 -> 2244994.1
E13: 2.- Ingresos por Fuente / Cuenta
E14: Anticipo Financiero | H14: Otros Aportes | M14: OBJETAL | N14: FR | O14: VS
E15: Transferencias Corrientes | G15: 3.0095039e+08 | H15: Aportes Nomina SNS | M15: 2.1 | N15: =G26 -> 1.9856074e+08 | O15: =H26 -> 5231553.6
E16: Venta de Servicios | G16: 23630411 | M16: 2.2 | N16: =G87 -> 9308364.9 | O16: =H87 -> 8306683.9
H17: TOTAL INGRESOS RDS | J17: =+G15+G16 -> 3.245808e+08 | M17: 2.3 | N17: ='[3]CONS. FUENTES FINAN'!G212 -> 4970601.2 | O17: ='[3]CONS. FUENTES FINAN'!H212 -> 3062630.7
M18: 2.4 | N18: =G330 -> 0 | O18: =H330 -> 287786.7
M19: 2.6 | N19: =G336 -> 17857867 | O19: =H336 -> 5076044.2
M20: 2.7 | N20: ='[3]CONS. FUENTES FINAN'!G463 -> 0 | O20: ='[3]CONS. FUENTES FINAN'!H463 -> 0
A21: 1 | F21: 2 | G21: 3 | J21: 4 | K21: 5
A22: Código Presupuestario | F22: Descripción Gasto por Cuenta | G22: Distribución del Gasto por Fuente de Financiamiento | J22: TOTAL | K22: %
A23: Tipo | B23: Objeto | C23: Cuenta | D23: Sub-Cuenta | E23: Auxiliar | G23: Fondo 100 | H23: Venta de Servicios/ Otros Aportes | I23: Aportes Nomina SNS
A25: 2 | F25: Gastos | G25: =+G26+G87+G212+G330+G336+G463 -> 2.7188025e+08 | H25: =+H26+H87+H212+H330+H336+H463 -> 26194616 | I25: =+I26+I87+I212+I330+I336+I463 -> 0 | J25: =SUM(G25:I25) -> 2.9807487e+08 | K25: =+K26+K87+K212+K330+K336+K463 -> 1
A26: 2 | B26: 1 | F26: Servicios Personales | G26: =+G27+G51+G64+G71+G78 -> 1.9856074e+08 | H26: =+H27+H51+H64+H71+H78 -> 5231553.6 | I26: =+I27+I51+I64+I71+I78 -> 0 | J26: =SUM(G26:I26) -> 2.0379229e+08 | K26: =J26/$J$25 -> 0.68369498
A27: 2 | B27: 1 | C27: 1 | F27: Remuneraciones | G27: =+G28+G35+G42+G44+G46 -> 1.639452e+08 | H27: =+H28+H35+H42+H44+H46 -> 0 | I27: =+I28+I35+I42+I44+I46 -> 0 | J27: =SUM(G27:I27) -> 1.639452e+08 | K27: =J27/$J$25 -> 0.55001351
A28: 2 | B28: 1 | C28: 1 | D28: 1 | F28: Remuneraciones al personal fijo | G28: =SUM(G29:G34) -> 1.5943449e+08 | H28: =SUM(H29:H34) -> 0 | I28: =SUM(I29:I34) -> 0 | J28: =SUM(G28:I28) -> 1.5943449e+08 | K28: =J28/$J$25 -> 0.53488069
A29: 2 | B29: 1 | C29: 1 | D29: 1 | E29: 01 | F29: Sueldos a empleados fijos | G29: =+'MARZO 2025'!G29+'FEBRERO 2025'!G29+'ENERO 2025'!G29 -> 1.5943449e+08 | H29: =+'MARZO 2025'!H29+'FEBRERO 2025'!H29+'ENERO 2025'!H29 -> 0 | I29: 0 | J29: =SUM(G29:I29) -> 1.5943449e+08 | K29: =J29/$J$25 -> 0.53488069
A30: 2 | B30: 1 | C30: 1 | D30: 1 | E30: 02 | F30: Sueldos a médicos | G30: =+'MARZO 2025'!G30+'FEBRERO 2025'!G30+'ENERO 2025'!G30 -> 0 | H30: =+'MARZO 2025'!H30+'FEBRERO 2025'!H30+'ENERO 2025'!H30 -> 0 | I30: 0 | J30: =SUM(G30:I30) -> 0 | K30: =J30/$J$25 -> 0
A31: 2 | B31: 1 | C31: 1 | D31: 1 | E31: 03 | F31: Ascensos a militares | G31: =+'MARZO 2025'!G31+'FEBRERO 2025'!G31+'ENERO 2025'!G31 -> 0 | H31: =+'MARZO 2025'!H31+'FEBRERO 2025'!H31+'ENERO 2025'!H31 -> 0 | I31: 0 | J31: =SUM(G31:I31) -> 0 | K31: =J31/$J$25 -> 0
A32: 2 | B32: 1 | C32: 1 | D32: 1 | E32: 04 | F32: Nuevas plazas maestros | G32: =+'MARZO 2025'!G32+'FEBRERO 2025'!G32+'ENERO 2025'!G32 -> 0 | H32: =+'MARZO 2025'!H32+'FEBRERO 2025'!H32+'ENERO 2025'!H32 -> 0 | I32: 0 | J32: =SUM(G32:I32) -> 0 | K32: =J32/$J$25 -> 0
A33: 2 | B33: 1 | C33: 1 | D33: 1 | E33: 05 | F33: Incentivos y escalafón | G33: =+'MARZO 2025'!G33+'FEBRERO 2025'!G33+'ENERO 2025'!G33 -> 0 | H33: =+'MARZO 2025'!H33+'FEBRERO 2025'!H33+'ENERO 2025'!H33 -> 0 | I33: 0 | J33: =SUM(G33:I33) -> 0 | K33: =J33/$J$25 -> 0
A34: 2 | B34: 1 | C34: 1 | D34: 1 | E34: 06 | F34: Nuevas plazas a médicos | G34: =+'MARZO 2025'!G34+'FEBRERO 2025'!G34+'ENERO 2025'!G34 -> 0 | H34: =+'MARZO 2025'!H34+'FEBRERO 2025'!H34+'ENERO 2025'!H34 -> 0 | I34: 0 | J34: =SUM(G34:I34) -> 0 | K34: =J34/$J$25 -> 0
A35: 2 | B35: 1 | C35: 1 | D35: 2 | F35: Remuneraciones al personal con carácter transitorio | G35: =+'MARZO 2025'!G35+'FEBRERO 2025'!G35+'ENERO 2025'!G35 -> 3177593.1 | H35: =+'MARZO 2025'!H35+'FEBRERO 2025'!H35+'ENERO 2025'!H35 -> 0 | I35: 0 | J35: =SUM(G35:I35) -> 3177593.1
A36: 2 | B36: 1 | C36: 1 | D36: 2 | E36: 03 | F36: Suplencias | G36: =+'MARZO 2025'!G36+'FEBRERO 2025'!G36+'ENERO 2025'!G36 -> 0 | H36: =+'MARZO 2025'!H36+'FEBRERO 2025'!H36+'ENERO 2025'!H36 -> 0 | I36: 0 | J36: =SUM(G36:I36) -> 0 | K36: =J36/$J$25 -> 0
A37: 2 | B37: 1 | C37: 1 | D37: 2 | E37: 05 | F37: Sueldo al personal nominal en período probatorio | G37: =+'MARZO 2025'!G37+'FEBRERO 2025'!G37+'ENERO 2025'!G37 -> 0 | H37: =+'MARZO 2025'!H37+'FEBRERO 2025'!H37+'ENERO 2025'!H37 -> 0 | I37: 0 | J37: =SUM(G37:I37) -> 0 | K37: =J37/$J$25 -> 0
A38: 2 | B38: 1 | C38: 1 | D38: 2 | E38: 06 | F38: Jornales | G38: =+'MARZO 2025'!G38+'FEBRERO 2025'!G38+'ENERO 2025'!G38 -> 0 | H38: =+'MARZO 2025'!H38+'FEBRERO 2025'!H38+'ENERO 2025'!H38 -> 0 | I38: 0 | J38: =SUM(G38:I38) -> 0 | K38: =J38/$J$25 -> 0
A39: 2 | B39: 1 | C39: 1 | D39: 2 | E39: 08 | F39: Empleados temporales | G39: =+'MARZO 2025'!G39+'FEBRERO 2025'!G39+'ENERO 2025'!G39 -> 3177593.1 | H39: =+'MARZO 2025'!H39+'FEBRERO 2025'!H39+'ENERO 2025'!H39 -> 0 | I39: 0 | J39: =SUM(G39:I39) -> 3177593.1 | K39: =J39/$J$25 -> 0.010660386
A40: 2 | B40: 1 | C40: 1 | D40: 2 | E40: 09 | F40: Personal de carácter eventual | G40: =+'MARZO 2025'!G40+'FEBRERO 2025'!G40+'ENERO 2025'!G40 -> 0 | H40: =+'MARZO 2025'!H40+'FEBRERO 2025'!H40+'ENERO 2025'!H40 -> 0 | I40: 0 | J40: =SUM(G40:I40) -> 0 | K40: =J40/$J$25 -> 0
A41: 2 | B41: 1 | C41: 1 | D41: 2 | E41: 11 | F41: Interinato | G41: =+'MARZO 2025'!G41+'FEBRERO 2025'!G41+'ENERO 2025'!G41 -> 0 | H41: =+'MARZO 2025'!H41+'FEBRERO 2025'!H41+'ENERO 2025'!H41 -> 0 | I41: 0 | J41: =SUM(G41:I41) -> 0 | K41: =J41/$J$25 -> 0
A42: 2 | B42: 1 | C42: 1 | D42: 3 | F42: Sueldos al personal fijo en trámite de pensiones | G42: =+'MARZO 2025'!G42+'FEBRERO 2025'!G42+'ENERO 2025'!G42 -> 0 | H42: =+'MARZO 2025'!H42+'FEBRERO 2025'!H42+'ENERO 2025'!H42 -> 0 | I42: 0 | J42: =SUM(G42:I42) -> 0
A43: 2 | B43: 1 | C43: 1 | D43: 3 | E43: 01 | F43: Sueldos al personal fijo en trámite de pensiones | G43: =+'MARZO 2025'!G43+'FEBRERO 2025'!G43+'ENERO 2025'!G43 -> 0 | H43: =+'MARZO 2025'!H43+'FEBRERO 2025'!H43+'ENERO 2025'!H43 -> 0 | I43: 0 | J43: =SUM(G43:I43) -> 0 | K43: =J43/$J$25 -> 0
A44: 2 | B44: 1 | C44: 1 | D44: 4 | F44: Sueldo anual no. 13 | G44: =+'MARZO 2025'!G44+'FEBRERO 2025'!G44+'ENERO 2025'!G44 -> 0 | H44: =+'MARZO 2025'!H44+'FEBRERO 2025'!H44+'ENERO 2025'!H44 -> 0 | I44: 0 | J44: =SUM(G44:I44) -> 0
A45: 2 | B45: 1 | C45: 1 | D45: 4 | E45: 01 | F45: Sueldo anual no. 13 | G45: =+'MARZO 2025'!G45+'FEBRERO 2025'!G45+'ENERO 2025'!G45 -> 0 | H45: =+'MARZO 2025'!H45+'FEBRERO 2025'!H45+'ENERO 2025'!H45 -> 0 | I45: 0 | J45: =SUM(G45:I45) -> 0 | K45: =J45/$J$25 -> 0
A46: 2 | B46: 1 | C46: 1 | D46: 5 | F46: Prestaciones económinas | G46: =+'MARZO 2025'!G46+'FEBRERO 2025'!G46+'ENERO 2025'!G46 -> 1333120.1 | H46: =+'MARZO 2025'!H46+'FEBRERO 2025'!H46+'ENERO 2025'!H46 -> 0 | I46: 0 | J46: =SUM(G46:I46) -> 1333120.1
A47: 2 | B47: 1 | C47: 1 | D47: 5 | E47: 01 | F47: Prestaciones económinas | G47: =+'MARZO 2025'!G47+'FEBRERO 2025'!G47+'ENERO 2025'!G47 -> 815000 | H47: =+'MARZO 2025'!H47+'FEBRERO 2025'!H47+'ENERO 2025'!H47 -> 0 | I47: 0 | J47: =SUM(G47:I47) -> 815000 | K47: =J47/$J$25 -> 0.0027342124
A48: 2 | B48: 1 | C48: 1 | D48: 5 | E48: 02 | F48: Pago de porcentaje por desvinculación de cargo | G48: =+'MARZO 2025'!G48+'FEBRERO 2025'!G48+'ENERO 2025'!G48 -> 0 | H48: =+'MARZO 2025'!H48+'FEBRERO 2025'!H48+'ENERO 2025'!H48 -> 0 | I48: 0 | J48: =SUM(G48:I48) -> 0 | K48: =J48/$J$25 -> 0
A49: 2 | B49: 1 | C49: 1 | D49: 5 | E49: 03 | F49: Prestación laboral por desvinculación | G49: =+'MARZO 2025'!G49+'FEBRERO 2025'!G49+'ENERO 2025'!G49 -> 0 | H49: =+'MARZO 2025'!H49+'FEBRERO 2025'!H49+'ENERO 2025'!H49 -> 0 | I49: 0 | J49: =SUM(G49:I49) -> 0 | K49: =J49/$J$25 -> 0
A50: 2 | B50: 1 | C50: 1 | D50: 5 | E50: 04 | F50: Proporción de vacaciones no disfrutadas | G50: =+'MARZO 2025'!G50+'FEBRERO 2025'!G50+'ENERO 2025'!G50 -> 518120.15 | H50: =+'MARZO 2025'!H50+'FEBRERO 2025'!H50+'ENERO 2025'!H50 -> 0 | I50: 0 | J50: =SUM(G50:I50) -> 518120.15 | K50: =J50/$J$25 -> 0.0017382215
A51: 2 | B51: 1 | C51: 2 | F51: Sobresueldos | G51: =+'MARZO 2025'!G51+'FEBRERO 2025'!G51+'ENERO 2025'!G51 -> 9594398.8 | H51: =+'MARZO 2025'!H51+'FEBRERO 2025'!H51+'ENERO 2025'!H51 -> 5231553.6 | I51: 0 | J51: =SUM(G51:I51) -> 14825952
A52: 2 | B52: 1 | C52: 2 | D52: 1 | F52: Primas por antigüedad | G52: =+'MARZO 2025'!G52+'FEBRERO 2025'!G52+'ENERO 2025'!G52 -> 8256409.5 | H52: =+'MARZO 2025'!H52+'FEBRERO 2025'!H52+'ENERO 2025'!H52 -> 0 | I52: 0 | J52: =SUM(G52:I52) -> 8256409.5
A53: 2 | B53: 1 | C53: 2 | D53: 1 | E53: 01 | F53: Primas por antigüedad | G53: =+'MARZO 2025'!G53+'FEBRERO 2025'!G53+'ENERO 2025'!G53 -> 8256409.5 | H53: =+'MARZO 2025'!H53+'FEBRERO 2025'!H53+'ENERO 2025'!H53 -> 0 | I53: 0 | J53: =SUM(G53:I53) -> 8256409.5 | K53: =J53/$J$25 -> 0.027699113
A54: 2 | B54: 1 | C54: 2 | D54: 2 | F54: Compensación | G54: =+'MARZO 2025'!G54+'FEBRERO 2025'!G54+'ENERO 2025'!G54 -> 1337989.3 | H54: =+'MARZO 2025'!H54+'FEBRERO 2025'!H54+'ENERO 2025'!H54 -> 5231553.6 | I54: 0 | J54: =SUM(G54:I54) -> 6569542.9
A55: 2 | B55: 1 | C55: 2 | D55: 2 | E55: 01 | F55: Compensación por gastos de alimentación | G55: =+'MARZO 2025'!G55+'FEBRERO 2025'!G55+'ENERO 2025'!G55 -> 0 | H55: =+'MARZO 2025'!H55+'FEBRERO 2025'!H55+'ENERO 2025'!H55 -> 0 | I55: 0 | J55: =SUM(G55:I55) -> 0 | K55: =J55/$J$25 -> 0
A56: 2 | B56: 1 | C56: 2 | D56: 2 | E56: 03 | F56: Pago de horas extraordinarias | G56: =+'MARZO 2025'!G56+'FEBRERO 2025'!G56+'ENERO 2025'!G56 -> 0 | H56: =+'MARZO 2025'!H56+'FEBRERO 2025'!H56+'ENERO 2025'!H56 -> 0 | I56: 0 | J56: =SUM(G56:I56) -> 0 | K56: =J56/$J$25 -> 0
A57: 2 | B57: 1 | C57: 2 | D57: 2 | E57: 04 | F57: Prima de transporte | G57: =+'MARZO 2025'!G57+'FEBRERO 2025'!G57+'ENERO 2025'!G57 -> 0 | H57: =+'MARZO 2025'!H57+'FEBRERO 2025'!H57+'ENERO 2025'!H57 -> 0 | I57: 0 | J57: =SUM(G57:I57) -> 0 | K57: =J57/$J$25 -> 0
A58: 2 | B58: 1 | C58: 2 | D58: 2 | E58: 05 | F58: Compensación servicios de Seguridad | G58: =+'MARZO 2025'!G58+'FEBRERO 2025'!G58+'ENERO 2025'!G58 -> 135000 | H58: =+'MARZO 2025'!H58+'FEBRERO 2025'!H58+'ENERO 2025'!H58 -> 0 | I58: 0 | J58: =SUM(G58:I58) -> 135000 | K58: =J58/$J$25 -> 0.00045290635
A59: 2 | B59: 1 | C59: 2 | D59: 2 | E59: 06 | F59: Incentivo por Rendimieto Individual | G59: =+'MARZO 2025'!G59+'FEBRERO 2025'!G59+'ENERO 2025'!G59 -> 0 | H59: =+'MARZO 2025'!H59+'FEBRERO 2025'!H59+'ENERO 2025'!H59 -> 5231553.6 | I59: 0 | J59: =SUM(G59:I59) -> 5231553.6 | K59: =J59/$J$25 -> 0.01755114
A60: 2 | B60: 1 | C60: 2 | D60: 2 | E60: 07 | F60: Compensación por distancia | G60: =+'MARZO 2025'!G60+'FEBRERO 2025'!G60+'ENERO 2025'!G60 -> 0 | H60: =+'MARZO 2025'!H60+'FEBRERO 2025'!H60+'ENERO 2025'!H60 -> 0 | I60: 0 | J60: =SUM(G60:I60) -> 0 | K60: =J60/$J$25 -> 0
A61: 2 | B61: 1 | C61: 2 | D61: 2 | E61: 08 | F61: Compensaciones especiales | G61: =+'MARZO 2025'!G61+'FEBRERO 2025'!G61+'ENERO 2025'!G61 -> 994000 | H61: =+'MARZO 2025'!H61+'FEBRERO 2025'!H61+'ENERO 2025'!H61 -> 0 | I61: 0 | J61: =SUM(G61:I61) -> 994000 | K61: =J61/$J$25 -> 0.0033347327
A62: 2 | B62: 1 | C62: 2 | D62: 2 | E62: 09 | F62: Bono por desempeño a servidores de carrera | G62: =+'MARZO 2025'!G62+'FEBRERO 2025'!G62+'ENERO 2025'!G62 -> 0 | H62: =+'MARZO 2025'!H62+'FEBRERO 2025'!H62+'ENERO 2025'!H62 -> 0 | I62: 0 | J62: =SUM(G62:I62) -> 0 | K62: =J62/$J$25 -> 0
A63: 2 | B63: 1 | C63: 2 | D63: 2 | E63: 10 | F63: Compensacion por cumplimiento de indicadores | G63: =+'MARZO 2025'!G63+'FEBRERO 2025'!G63+'ENERO 2025'!G63 -> 208989.3 | H63: =+'MARZO 2025'!H63+'FEBRERO 2025'!H63+'ENERO 2025'!H63 -> 0 | I63: 0 | J63: =SUM(G63:I63) -> 208989.3 | K63: =J63/$J$25 -> 0.00070113023
A64: 2 | B64: 1 | C64: 3 | F64: Dietas y Gastos de Representación | G64: =+'MARZO 2025'!G64+'FEBRERO 2025'!G64+'ENERO 2025'!G64 -> 0 | H64: =+'MARZO 2025'!H64+'FEBRERO 2025'!H64+'ENERO 2025'!H64 -> 0 | I64: 0 | J64: =SUM(G64:I64) -> 0
A65: 2 | B65: 1 | C65: 3 | D65: 1 | F65: Dietas | G65: =+'MARZO 2025'!G65+'FEBRERO 2025'!G65+'ENERO 2025'!G65 -> 0 | H65: =+'MARZO 2025'!H65+'FEBRERO 2025'!H65+'ENERO 2025'!H65 -> 0 | I65: 0 | J65: =SUM(G65:I65) -> 0
A66: 2 | B66: 1 | C66: 3 | D66: 1 | E66: 01 | F66: Dietas en el país | G66: =+'MARZO 2025'!G66+'FEBRERO 2025'!G66+'ENERO 2025'!G66 -> 0 | H66: =+'MARZO 2025'!H66+'FEBRERO 2025'!H66+'ENERO 2025'!H66 -> 0 | I66: 0 | J66: =SUM(G66:I66) -> 0 | K66: =J66/$J$25 -> 0
A67: 2 | B67: 1 | C67: 3 | D67: 1 | E67: 02 | F67: Dietas en el exterior | G67: =+'MARZO 2025'!G67+'FEBRERO 2025'!G67+'ENERO 2025'!G67 -> 0 | H67: =+'MARZO 2025'!H67+'FEBRERO 2025'!H67+'ENERO 2025'!H67 -> 0 | I67: 0 | J67: =SUM(G67:I67) -> 0 | K67: =J67/$J$25 -> 0
A68: 2 | B68: 1 | C68: 3 | D68: 2 | F68: Gastos de representación | G68: =+'MARZO 2025'!G68+'FEBRERO 2025'!G68+'ENERO 2025'!G68 -> 0 | H68: =+'MARZO 2025'!H68+'FEBRERO 2025'!H68+'ENERO 2025'!H68 -> 0 | I68: 0 | J68: =SUM(G68:I68) -> 0
A69: 2 | B69: 1 | C69: 3 | D69: 2 | E69: 01 | F69: Gastos de representación en el país | G69: =+'MARZO 2025'!G69+'FEBRERO 2025'!G69+'ENERO 2025'!G69 -> 0 | H69: =+'MARZO 2025'!H69+'FEBRERO 2025'!H69+'ENERO 2025'!H69 -> 0 | I69: 0 | J69: =SUM(G69:I69) -> 0 | K69: =J69/$J$25 -> 0
A70: 2 | B70: 1 | C70: 3 | D70: 2 | E70: 02 | F70: Gastos de representación en el exterior | G70: =+'MARZO 2025'!G70+'FEBRERO 2025'!G70+'ENERO 2025'!G70 -> 0 | H70: =+'MARZO 2025'!H70+'FEBRERO 2025'!H70+'ENERO 2025'!H70 -> 0 | I70: 0 | J70: =SUM(G70:I70) -> 0 | K70: =J70/$J$25 -> 0
A71: 2 | B71: 1 | C71: 4 | F71: Gratificaciones y Bonificaciones | G71: =+'MARZO 2025'!G71+'FEBRERO 2025'!G71+'ENERO 2025'!G71 -> 0 | H71: =+'MARZO 2025'!H71+'FEBRERO 2025'!H71+'ENERO 2025'!H71 -> 0 | I71: 0 | J71: =SUM(G71:I71) -> 0
A72: 2 | B72: 1 | C72: 4 | D72: 1 | F72: Bonificaciones | G72: =+'MARZO 2025'!G72+'FEBRERO 2025'!G72+'ENERO 2025'!G72 -> 0 | H72: =+'MARZO 2025'!H72+'FEBRERO 2025'!H72+'ENERO 2025'!H72 -> 0 | I72: 0 | J72: =SUM(G72:I72) -> 0
A73: 2 | B73: 1 | C73: 4 | D73: 1 | E73: 01 | F73: Bonificaciones | G73: =+'MARZO 2025'!G73+'FEBRERO 2025'!G73+'ENERO 2025'!G73 -> 0 | H73: =+'MARZO 2025'!H73+'FEBRERO 2025'!H73+'ENERO 2025'!H73 -> 0 | I73: 0 | J73: =SUM(G73:I73) -> 0 | K73: =J73/$J$25 -> 0
A74: 2 | B74: 1 | C74: 4 | D74: 2 | F74: Otras Gratificaciones y Bonificaciones | G74: =+'MARZO 2025'!G74+'FEBRERO 2025'!G74+'ENERO 2025'!G74 -> 0 | H74: =+'MARZO 2025'!H74+'FEBRERO 2025'!H74+'ENERO 2025'!H74 -> 0 | I74: 0 | J74: =SUM(G74:I74) -> 0
A75: 2 | B75: 1 | C75: 4 | D75: 2 | E75: 01 | F75: Bono escolar | G75: =+'MARZO 2025'!G75+'FEBRERO 2025'!G75+'ENERO 2025'!G75 -> 0 | H75: =+'MARZO 2025'!H75+'FEBRERO 2025'!H75+'ENERO 2025'!H75 -> 0 | I75: 0 | J75: =SUM(G75:I75) -> 0 | K75: =J75/$J$25 -> 0
A76: 2 | B76: 1 | C76: 4 | D76: 2 | E76: 02 | F76: Gratificaciones por pasantías | G76: =+'MARZO 2025'!G76+'FEBRERO 2025'!G76+'ENERO 2025'!G76 -> 0 | H76: =+'MARZO 2025'!H76+'FEBRERO 2025'!H76+'ENERO 2025'!H76 -> 0 | I76: 0 | J76: =SUM(G76:I76) -> 0 | K76: =J76/$J$25 -> 0
A77: 2 | B77: 1 | C77: 4 | D77: 2 | E77: 03 | F77: Gratificaciones por aniversario de institución | G77: =+'MARZO 2025'!G77+'FEBRERO 2025'!G77+'ENERO 2025'!G77 -> 0 | H77: =+'MARZO 2025'!H77+'FEBRERO 2025'!H77+'ENERO 2025'!H77 -> 0 | I77: 0 | J77: =SUM(G77:I77) -> 0 | K77: =J77/$J$25 -> 0
A78: 2 | B78: 1 | C78: 5 | F78: Contribuciones a la Seguridad Social y Riesgo Laboral | G78: =+'MARZO 2025'!G78+'FEBRERO 2025'!G78+'ENERO 2025'!G78 -> 25021132 | H78: =+'MARZO 2025'!H78+'FEBRERO 2025'!H78+'ENERO 2025'!H78 -> 0 | I78: 0 | J78: =SUM(G78:I78) -> 25021132
A79: 2 | B79: 1 | C79: 5 | D79: 1 | F79: Contribuciones al seguro de salud | G79: =+'MARZO 2025'!G79+'FEBRERO 2025'!G79+'ENERO 2025'!G79 -> 11529204 | H79: =+'MARZO 2025'!H79+'FEBRERO 2025'!H79+'ENERO 2025'!H79 -> 0 | I79: 0 | J79: =SUM(G79:I79) -> 11529204
A80: 2 | B80: 1 | C80: 5 | D80: 1 | E80: 01 | F80: Contribuciones al seguro de salud | G80: =+'MARZO 2025'!G80+'FEBRERO 2025'!G80+'ENERO 2025'!G80 -> 11529204 | H80: =+'MARZO 2025'!H80+'FEBRERO 2025'!H80+'ENERO 2025'!H80 -> 0 | I80: 0 | J80: =SUM(G80:I80) -> 11529204 | K80: =J80/$J$25 -> 0.038678886
A81: 2 | B81: 1 | C81: 5 | D81: 2 | F81: Contribuciones al seguro de pensiones | G81: =+'MARZO 2025'!G81+'FEBRERO 2025'!G81+'ENERO 2025'!G81 -> 11545459 | H81: =+'MARZO 2025'!H81+'FEBRERO 2025'!H81+'ENERO 2025'!H81 -> 0 | I81: 0 | J81: =SUM(G81:I81) -> 11545459
A82: 2 | B82: 1 | C82: 5 | D82: 2 | E82: 01 | F82: Contribuciones al seguro de pensiones | G82: =+'MARZO 2025'!G82+'FEBRERO 2025'!G82+'ENERO 2025'!G82 -> 11545459 | H82: =+'MARZO 2025'!H82+'FEBRERO 2025'!H82+'ENERO 2025'!H82 -> 0 | I82: 0 | J82: =SUM(G82:I82) -> 11545459 | K82: =J82/$J$25 -> 0.038733421
A83: 2 | B83: 1 | C83: 5 | D83: 3 | F83: Contribuciones al seguro de riesgo laboral | G83: =+'MARZO 2025'!G83+'FEBRERO 2025'!G83+'ENERO 2025'!G83 -> 1946469.3 | H83: =+'MARZO 2025'!H83+'FEBRERO 2025'!H83+'ENERO 2025'!H83 -> 0 | I83: 0 | J83: =SUM(G83:I83) -> 1946469.3
A84: 2 | B84: 1 | C84: 5 | D84: 3 | E84: 01 | F84: Contribuciones al seguro de riesgo laboral | G84: =+'MARZO 2025'!G84+'FEBRERO 2025'!G84+'ENERO 2025'!G84 -> 1946469.3 | H84: =+'MARZO 2025'!H84+'FEBRERO 2025'!H84+'ENERO 2025'!H84 -> 0 | I84: 0 | J84: =SUM(G84:I84) -> 1946469.3 | K84: =J84/$J$25 -> 0.0065301355
A85: 2 | B85: 1 | C85: 5 | D85: 4 | F85: Contribuciones al plan de retiro complementario | G85: =+'MARZO 2025'!G85+'FEBRERO 2025'!G85+'ENERO 2025'!G85 -> 0 | H85: =+'MARZO 2025'!H85+'FEBRERO 2025'!H85+'ENERO 2025'!H85 -> 0 | I85: 0 | J85: =SUM(G85:I85) -> 0
A86: 2 | B86: 1 | C86: 5 | D86: 4 | E86: 01 | F86: Contribuciones al plan de retiro complementario | G86: =+'MARZO 2025'!G86+'FEBRERO 2025'!G86+'ENERO 2025'!G86 -> 0 | H86: =+'MARZO 2025'!H86+'FEBRERO 2025'!H86+'ENERO 2025'!H86 -> 0 | I86: 0 | J86: =SUM(G86:I86) -> 0 | K86: =J86/$J$25 -> 0
A87: 2 | B87: 2 | F87: Servicios No Personales | G87: =+'MARZO 2025'!G87+'FEBRERO 2025'!G87+'ENERO 2025'!G87 -> 9308364.9 | H87: =+'MARZO 2025'!H87+'FEBRERO 2025'!H87+'ENERO 2025'!H87 -> 8306683.9 | I87: 0 | J87: =SUM(G87:I87) -> 17615049 | K87: =J87/$J$25 -> 0.059096055
A88: 2 | B88: 2 | C88: 1 | F88: Servicios Básicos | G88: =+'MARZO 2025'!G88+'FEBRERO 2025'!G88+'ENERO 2025'!G88 -> 2020024.3 | H88: =+'MARZO 2025'!H88+'FEBRERO 2025'!H88+'ENERO 2025'!H88 -> 2341561.9 | I88: 0 | J88: =SUM(G88:I88) -> 4361586.2
A89: 2 | B89: 2 | C89: 1 | D89: 1 | F89: Radiocomunicación | G89: =+'MARZO 2025'!G89+'FEBRERO 2025'!G89+'ENERO 2025'!G89 -> 0 | H89: =+'MARZO 2025'!H89+'FEBRERO 2025'!H89+'ENERO 2025'!H89 -> 0 | I89: 0 | J89: =SUM(G89:I89) -> 0
A90: 2 | B90: 2 | C90: 1 | D90: 1 | E90: 01 | F90: Radiocomunicación | G90: =+'MARZO 2025'!G90+'FEBRERO 2025'!G90+'ENERO 2025'!G90 -> 0 | H90: =+'MARZO 2025'!H90+'FEBRERO 2025'!H90+'ENERO 2025'!H90 -> 0 | I90: 0 | J90: =SUM(G90:I90) -> 0 | K90: =J90/$J$25 -> 0
A91: 2 | B91: 2 | C91: 1 | D91: 2 | F91: Servicios telefónico de larga distancia | G91: =+'MARZO 2025'!G91+'FEBRERO 2025'!G91+'ENERO 2025'!G91 -> 0 | H91: =+'MARZO 2025'!H91+'FEBRERO 2025'!H91+'ENERO 2025'!H91 -> 0 | I91: 0 | J91: =SUM(G91:I91) -> 0
A92: 2 | B92: 2 | C92: 1 | D92: 2 | E92: 01 | F92: Servicios telefónico de larga distancia | G92: =+'MARZO 2025'!G92+'FEBRERO 2025'!G92+'ENERO 2025'!G92 -> 0 | H92: =+'MARZO 2025'!H92+'FEBRERO 2025'!H92+'ENERO 2025'!H92 -> 0 | I92: 0 | J92: =SUM(G92:I92) -> 0 | K92: =J92/$J$25 -> 0
A93: 2 | B93: 2 | C93: 1 | D93: 3 | F93: Teléfono local | G93: =+'MARZO 2025'!G93+'FEBRERO 2025'!G93+'ENERO 2025'!G93 -> 0 | H93: =+'MARZO 2025'!H93+'FEBRERO 2025'!H93+'ENERO 2025'!H93 -> 771561.92 | I93: 0 | J93: =SUM(G93:I93) -> 771561.92
A94: 2 | B94: 2 | C94: 1 | D94: 3 | E94: 01 | F94: Teléfono local | G94: =+'MARZO 2025'!G94+'FEBRERO 2025'!G94+'ENERO 2025'!G94 -> 0 | H94: =+'MARZO 2025'!H94+'FEBRERO 2025'!H94+'ENERO 2025'!H94 -> 771561.92 | I94: 0 | J94: =SUM(G94:I94) -> 771561.92 | K94: =J94/$J$25 -> 0.0025884837
A95: 2 | B95: 2 | C95: 1 | D95: 4 | F95: Telefax y correos | G95: =+'MARZO 2025'!G95+'FEBRERO 2025'!G95+'ENERO 2025'!G95 -> 0 | H95: =+'MARZO 2025'!H95+'FEBRERO 2025'!H95+'ENERO 2025'!H95 -> 0 | I95: 0 | J95: =SUM(G95:I95) -> 0
A96: 2 | B96: 2 | C96: 1 | D96: 4 | E96: 01 | F96: Telefax y correos | G96: =+'MARZO 2025'!G96+'FEBRERO 2025'!G96+'ENERO 2025'!G96 -> 0 | H96: =+'MARZO 2025'!H96+'FEBRERO 2025'!H96+'ENERO 2025'!H96 -> 0 | I96: 0 | J96: =SUM(G96:I96) -> 0 | K96: =J96/$J$25 -> 0
A97: 2 | B97: 2 | C97: 1 | D97: 5 | F97: Servicio de Internet y televisión por cable | G97: =+'MARZO 2025'!G97+'FEBRERO 2025'!G97+'ENERO 2025'!G97 -> 0 | H97: =+'MARZO 2025'!H97+'FEBRERO 2025'!H97+'ENERO 2025'!H97 -> 0 | I97: 0 | J97: =SUM(G97:I97) -> 0
A98: 2 | B98: 2 | C98: 1 | D98: 5 | E98: 01 | F98: Servicio de Internet y televisión por cable | G98: =+'MARZO 2025'!G98+'FEBRERO 2025'!G98+'ENERO 2025'!G98 -> 0 | H98: =+'MARZO 2025'!H98+'FEBRERO 2025'!H98+'ENERO 2025'!H98 -> 0 | I98: 0 | J98: =SUM(G98:I98) -> 0 | K98: =J98/$J$25 -> 0
A99: 2 | B99: 2 | C99: 1 | D99: 6 | F99: Electricidad | G99: =+'MARZO 2025'!G99+'FEBRERO 2025'!G99+'ENERO 2025'!G99 -> 0 | H99: =+'MARZO 2025'!H99+'FEBRERO 2025'!H99+'ENERO 2025'!H99 -> 0 | I99: 0 | J99: =SUM(G99:I99) -> 0
A100: 2 | B100: 2 | C100: 1 | D100: 6 | E100: 01 | F100: Energía eléctrica | G100: =+'MARZO 2025'!G100+'FEBRERO 2025'!G100+'ENERO 2025'!G100 -> 0 | H100: =+'MARZO 2025'!H100+'FEBRERO 2025'!H100+'ENERO 2025'!H100 -> 0 | I100: 0 | J100: =SUM(G100:I100) -> 0 | K100: =J100/$J$25 -> 0
A101: 2 | B101: 2 | C101: 1 | D101: 6 | E101: 02 | F101: Electricidad no cortable | G101: =+'MARZO 2025'!G101+'FEBRERO 2025'!G101+'ENERO 2025'!G101 -> 0 | H101: =+'MARZO 2025'!H101+'FEBRERO 2025'!H101+'ENERO 2025'!H101 -> 0 | I101: 0 | J101: =SUM(G101:I101) -> 0 | K101: =J101/$J$25 -> 0
A102: 2 | B102: 2 | C102: 1 | D102: 7 | F102: Agua | G102: =+'MARZO 2025'!G102+'FEBRERO 2025'!G102+'ENERO 2025'!G102 -> 2020024.3 | H102: =+'MARZO 2025'!H102+'FEBRERO 2025'!H102+'ENERO 2025'!H102 -> 0 | I102: 0 | J102: =SUM(G102:I102) -> 2020024.3
...

Sheet BIMENSUAL
A1: Form. No.6 SRS
A3: Servicio Nacional de Salud
A4: Dirección de Fizcalización
A5: Consolidado de Ingresos y Gastos por Fuente de Financiamiento
A6: HOSPITAL MATERNO INFANTIL SAN LORENZO DE LOS MINA
A7: TRIMESTRE ENERO-MARZO 2025
C8: Ingresos Generales:
E9: 1.- Balance Inicial / Fuente:
E10: Anticipo Financiero | G10: 0 | H10: Otros Aportes | M10: Contraseña: 0001
E11: Transferencias Corrientes | G11: 0
E12: Venta de Servicios | G12: =+'ENERO 2025'!G12 -> 2244994.1
E13: 2.- Ingresos por Fuente / Cuenta
E14: Anticipo Financiero | H14: Otros Aportes | J14: =+'MARZO 2025'!I14+'FEBRERO 2025'!I14+'ENERO 2025'!J14 -> 15987098 | M14: OBJETAL | N14: FR | O14: VS
E15: Transferencias Corrientes | G15: =+'MARZO 2025'!G15+'FEBRERO 2025'!G15 -> 2.0063359e+08 | H15: Aportes Nomina SNS | J15: =+'MARZO 2025'!I15+'FEBRERO 2025'!I15+'ENERO 2025'!J15 -> 84553322 | M15: 2.1 | N15: =G26 -> 1.3222312e+08 | O15: =H26 -> 0
E16: Venta de Servicios | G16: =+'MARZO 2025'!G16+'FEBRERO 2025'!G16+'ENERO 2025'!G16 -> 23406786 | M16: 2.2 | N16: =G87 -> 1336968.6 | O16: =H87 -> 3947227.6
H17: TOTAL INGRESOS RDS | J17: =+G10+G11+G12+J10+G14+G15+G16+J14+J15 -> 3.2682579e+08 | M17: 2.3 | N17: ='[3]CONS. FUENTES FINAN'!G212 -> 4970601.2 | O17: ='[3]CONS. FUENTES FINAN'!H212 -> 3062630.7
M18: 2.4 | N18: =G330 -> 0 | O18: =H330 -> 160366.7
M19: 2.6 | N19: =G336 -> 6461017.3 | O19: =H336 -> 4775504.8
M20: 2.7 | N20: ='[3]CONS. FUENTES FINAN'!G463 -> 0 | O20: ='[3]CONS. FUENTES FINAN'!H463 -> 0
A21: 1 | F21: 2 | G21: 3 | J21: 4 | K21: 5
A22: Código Presupuestario | F22: Descripción Gasto por Cuenta | G22: Distribución del Gasto por Fuente de Financiamiento | J22: TOTAL | K22: %
A23: Tipo | B23: Objeto | C23: Cuenta | D23: Sub-Cuenta | E23: Auxiliar | G23: Fondo 100 | H23: Venta de Servicios/ Otros Aportes | I23: Aportes Nomina SNS
A25: 2 | F25: Gastos | G25: =+G26+G87+G212+G330+G336+G463 -> 1.5942483e+08 | H25: =+H26+H87+H212+H330+H336+H463 -> 14378108 | I25: =+I26+I87+I212+I330+I336+I463 -> 0 | J25: =+G25+H25 -> 1.7380294e+08 | K25: =+K26+K87+K212+K330+K336+K463 -> 1
A26: 2 | B26: 1 | F26: Servicios Personales | G26: =+G27+G51+G64+G71+G78 -> 1.3222312e+08 | H26: =+H27+H51+H64+H71+H78 -> 0 | J26: =+G26+H26 -> 1.3222312e+08 | K26: =J26/$J$25 -> 0.76076454
A27: 2 | B27: 1 | C27: 1 | F27: Remuneraciones | G27: =+G28+G35+G42+G44+G46 -> 1.0922647e+08 | H27: =+H28+H35+H42+H44+H46 -> 0 | J27: =+G27+H27 -> 1.0922647e+08 | K27: =J27/$J$25 -> 0.62845005
A28: 2 | B28: 1 | C28: 1 | D28: 1 | F28: Remuneraciones al personal fijo | G28: =SUM(G29:G34) -> 1.0582329e+08 | H28: =SUM(H29:H34) -> 0 | J28: =+G28+H28 -> 1.0582329e+08 | K28: =J28/$J$25 -> 0.60886935
A29: 2 | B29: 1 | C29: 1 | D29: 1 | E29: 01 | F29: Sueldos a empleados fijos | G29: =+'ENERO 2025'!G29+'FEBRERO 2025'!G29 -> 1.0582329e+08 | H29: =+'ENERO 2025'!H29+'FEBRERO 2025'!H29 -> 0 | J29: =+G29+H29 -> 1.0582329e+08 | K29: =J29/$J$25 -> 0.60886935
A30: 2 | B30: 1 | C30: 1 | D30: 1 | E30: 02 | F30: Sueldos a médicos | G30: =+'ENERO 2025'!G30+'FEBRERO 2025'!G30 -> 0 | H30: =+'ENERO 2025'!H30+'FEBRERO 2025'!H30 -> 0 | J30: =+G30+H30 -> 0 | K30: =J30/$J$25 -> 0
A31: 2 | B31: 1 | C31: 1 | D31: 1 | E31: 03 | F31: Ascensos a militares | G31: =+'ENERO 2025'!G31+'FEBRERO 2025'!G31 -> 0 | H31: =+'ENERO 2025'!H31+'FEBRERO 2025'!H31 -> 0 | J31: =+G31+H31 -> 0 | K31: =J31/$J$25 -> 0
A32: 2 | B32: 1 | C32: 1 | D32: 1 | E32: 04 | F32: Nuevas plazas maestros | G32: =+'ENERO 2025'!G32+'FEBRERO 2025'!G32 -> 0 | H32: =+'ENERO 2025'!H32+'FEBRERO 2025'!H32 -> 0 | J32: =+G32+H32 -> 0 | K32: =J32/$J$25 -> 0
A33: 2 | B33: 1 | C33: 1 | D33: 1 | E33: 05 | F33: Incentivos y escalafón | G33: =+'ENERO 2025'!G33+'FEBRERO 2025'!G33 -> 0 | H33: =+'ENERO 2025'!H33+'FEBRERO 2025'!H33 -> 0 | J33: =+G33+H33 -> 0 | K33: =J33/$J$25 -> 0
A34: 2 | B34: 1 | C34: 1 | D34: 1 | E34: 06 | F34: Nuevas plazas a médicos | G34: =+'ENERO 2025'!G34+'FEBRERO 2025'!G34 -> 0 | H34: =+'ENERO 2025'!H34+'FEBRERO 2025'!H34 -> 0 | J34: =+G34+H34 -> 0 | K34: =J34/$J$25 -> 0
A35: 2 | B35: 1 | C35: 1 | D35: 2 | F35: Remuneraciones al personal con carácter transitorio | G35: =+'ENERO 2025'!G35+'FEBRERO 2025'!G35 -> 2070062.1 | H35: =+'ENERO 2025'!H35+'FEBRERO 2025'!H35 -> 0 | J35: =+G35+H35 -> 2070062.1
A36: 2 | B36: 1 | C36: 1 | D36: 2 | E36: 03 | F36: Suplencias | G36: =+'ENERO 2025'!G36+'FEBRERO 2025'!G36 -> 0 | H36: =+'ENERO 2025'!H36+'FEBRERO 2025'!H36 -> 0 | J36: =+G36+H36 -> 0 | K36: =J36/$J$25 -> 0
A37: 2 | B37: 1 | C37: 1 | D37: 2 | E37: 05 | F37: Sueldo al personal nominal en período probatorio | G37: =+'ENERO 2025'!G37+'FEBRERO 2025'!G37 -> 0 | H37: =+'ENERO 2025'!H37+'FEBRERO 2025'!H37 -> 0 | J37: =+G37+H37 -> 0 | K37: =J37/$J$25 -> 0
A38: 2 | B38: 1 | C38: 1 | D38: 2 | E38: 06 | F38: Jornales | G38: =+'ENERO 2025'!G38+'FEBRERO 2025'!G38 -> 0 | H38: =+'ENERO 2025'!H38+'FEBRERO 2025'!H38 -> 0 | J38: =+G38+H38 -> 0 | K38: =J38/$J$25 -> 0
A39: 2 | B39: 1 | C39: 1 | D39: 2 | E39: 08 | F39: Empleados temporales | G39: =+'ENERO 2025'!G39+'FEBRERO 2025'!G39 -> 2070062.1 | H39: =+'ENERO 2025'!H39+'FEBRERO 2025'!H39 -> 0 | J39: =+G39+H39 -> 2070062.1 | K39: =J39/$J$25 -> 0.011910397
A40: 2 | B40: 1 | C40: 1 | D40: 2 | E40: 09 | F40: Personal de carácter eventual | G40: =+'ENERO 2025'!G40+'FEBRERO 2025'!G40 -> 0 | H40: =+'ENERO 2025'!H40+'FEBRERO 2025'!H40 -> 0 | J40: =+G40+H40 -> 0 | K40: =J40/$J$25 -> 0
A41: 2 | B41: 1 | C41: 1 | D41: 2 | E41: 11 | F41: Interinato | G41: =+'ENERO 2025'!G41+'FEBRERO 2025'!G41 -> 0 | H41: =+'ENERO 2025'!H41+'FEBRERO 2025'!H41 -> 0 | J41: =+G41+H41 -> 0 | K41: =J41/$J$25 -> 0
A42: 2 | B42: 1 | C42: 1 | D42: 3 | F42: Sueldos al personal fijo en trámite de pensiones | G42: =+'ENERO 2025'!G42+'FEBRERO 2025'!G42 -> 0 | H42: =+'ENERO 2025'!H42+'FEBRERO 2025'!H42 -> 0 | J42: =+G42+H42 -> 0
A43: 2 | B43: 1 | C43: 1 | D43: 3 | E43: 01 | F43: Sueldos al personal fijo en trámite de pensiones | G43: =+'ENERO 2025'!G43+'FEBRERO 2025'!G43 -> 0 | H43: =+'ENERO 2025'!H43+'FEBRERO 2025'!H43 -> 0 | J43: =+G43+H43 -> 0 | K43: =J43/$J$25 -> 0
A44: 2 | B44: 1 | C44: 1 | D44: 4 | F44: Sueldo anual no. 13 | G44: =+'ENERO 2025'!G44+'FEBRERO 2025'!G44 -> 0 | H44: =+'ENERO 2025'!H44+'FEBRERO 2025'!H44 -> 0 | J44: =+G44+H44 -> 0
A45: 2 | B45: 1 | C45: 1 | D45: 4 | E45: 01 | F45: Sueldo anual no. 13 | G45: =+'ENERO 2025'!G45+'FEBRERO 2025'!G45 -> 0 | H45: =+'ENERO 2025'!H45+'FEBRERO 2025'!H45 -> 0 | J45: =+G45+H45 -> 0 | K45: =J45/$J$25 -> 0
A46: 2 | B46: 1 | C46: 1 | D46: 5 | F46: Prestaciones económinas | G46: =+'ENERO 2025'!G46+'FEBRERO 2025'!G46 -> 1333120.1 | H46: =+'ENERO 2025'!H46+'FEBRERO 2025'!H46 -> 0 | J46: =+G46+H46 -> 1333120.1
A47: 2 | B47: 1 | C47: 1 | D47: 5 | E47: 01 | F47: Prestaciones económinas | G47: =+'ENERO 2025'!G47+'FEBRERO 2025'!G47 -> 815000 | H47: =+'ENERO 2025'!H47+'FEBRERO 2025'!H47 -> 0 | J47: =+G47+H47 -> 815000 | K47: =J47/$J$25 -> 0.0046892187
A48: 2 | B48: 1 | C48: 1 | D48: 5 | E48: 02 | F48: Pago de porcentaje por desvinculación de cargo | G48: =+'ENERO 2025'!G48+'FEBRERO 2025'!G48 -> 0 | H48: =+'ENERO 2025'!H48+'FEBRERO 2025'!H48 -> 0 | J48: =+G48+H48 -> 0 | K48: =J48/$J$25 -> 0
A49: 2 | B49: 1 | C49: 1 | D49: 5 | E49: 03 | F49: Prestación laboral por desvinculación | G49: =+'ENERO 2025'!G49+'FEBRERO 2025'!G49 -> 0 | H49: =+'ENERO 2025'!H49+'FEBRERO 2025'!H49 -> 0 | J49: =+G49+H49 -> 0 | K49: =J49/$J$25 -> 0
A50: 2 | B50: 1 | C50: 1 | D50: 5 | E50: 04 | F50: Proporción de vacaciones no disfrutadas | G50: =+'ENERO 2025'!G50+'FEBRERO 2025'!G50 -> 518120.15 | H50: =+'ENERO 2025'!H50+'FEBRERO 2025'!H50 -> 0 | J50: =+G50+H50 -> 518120.15 | K50: =J50/$J$25 -> 0.0029810781
A51: 2 | B51: 1 | C51: 2 | F51: Sobresueldos | G51: =+'ENERO 2025'!G51+'FEBRERO 2025'!G51 -> 6394999.2 | H51: =+'ENERO 2025'!H51+'FEBRERO 2025'!H51 -> 0 | J51: =+G51+H51 -> 6394999.2
A52: 2 | B52: 1 | C52: 2 | D52: 1 | F52: Primas por antigüedad | G52: =+'ENERO 2025'!G52+'FEBRERO 2025'!G52 -> 5504273 | H52: =+'ENERO 2025'!H52+'FEBRERO 2025'!H52 -> 0 | J52: =+G52+H52 -> 5504273
A53: 2 | B53: 1 | C53: 2 | D53: 1 | E53: 01 | F53: Primas por antigüedad | G53: =+'ENERO 2025'!G53+'FEBRERO 2025'!G53 -> 5504273 | H53: =+'ENERO 2025'!H53+'FEBRERO 2025'!H53 -> 0 | J53: =+G53+H53 -> 5504273 | K53: =J53/$J$25 -> 0.031669619
A54: 2 | B54: 1 | C54: 2 | D54: 2 | F54: Compensación | G54: =+'ENERO 2025'!G54+'FEBRERO 2025'!G54 -> 890726.2 | H54: =+'ENERO 2025'!H54+'FEBRERO 2025'!H54 -> 0 | J54: =+G54+H54 -> 890726.2
A55: 2 | B55: 1 | C55: 2 | D55: 2 | E55: 01 | F55: Compensación por gastos de alimentación | G55: =+'ENERO 2025'!G55+'FEBRERO 2025'!G55 -> 0 | H55: =+'ENERO 2025'!H55+'FEBRERO 2025'!H55 -> 0 | J55: =+G55+H55 -> 0 | K55: =J55/$J$25 -> 0
A56: 2 | B56: 1 | C56: 2 | D56: 2 | E56: 03 | F56: Pago de horas extraordinarias | G56: =+'ENERO 2025'!G56+'FEBRERO 2025'!G56 -> 0 | H56: =+'ENERO 2025'!H56+'FEBRERO 2025'!H56 -> 0 | J56: =+G56+H56 -> 0 | K56: =J56/$J$25 -> 0
A57: 2 | B57: 1 | C57: 2 | D57: 2 | E57: 04 | F57: Prima de transporte | G57: =+'ENERO 2025'!G57+'FEBRERO 2025'!G57 -> 0 | H57: =+'ENERO 2025'!H57+'FEBRERO 2025'!H57 -> 0 | J57: =+G57+H57 -> 0 | K57: =J57/$J$25 -> 0
A58: 2 | B58: 1 | C58: 2 | D58: 2 | E58: 05 | F58: Compensación servicios de Seguridad | G58: =+'ENERO 2025'!G58+'FEBRERO 2025'!G58 -> 90000 | H58: =+'ENERO 2025'!H58+'FEBRERO 2025'!H58 -> 0 | J58: =+G58+H58 -> 90000 | K58: =J58/$J$25 -> 0.00051782783
A59: 2 | B59: 1 | C59: 2 | D59: 2 | E59: 06 | F59: Incentivo por Rendimieto Individual | G59: =+'ENERO 2025'!G59+'FEBRERO 2025'!G59 -> 0 | H59: =+'ENERO 2025'!H59+'FEBRERO 2025'!H59 -> 0 | J59: =+G59+H59 -> 0 | K59: =J59/$J$25 -> 0
A60: 2 | B60: 1 | C60: 2 | D60: 2 | E60: 07 | F60: Compensación por distancia | G60: =+'ENERO 2025'!G60+'FEBRERO 2025'!G60 -> 0 | H60: =+'ENERO 2025'!H60+'FEBRERO 2025'!H60 -> 0 | J60: =+G60+H60 -> 0 | K60: =J60/$J$25 -> 0
A61: 2 | B61: 1 | C61: 2 | D61: 2 | E61: 08 | F61: Compensaciones especiales | G61: =+'ENERO 2025'!G61+'FEBRERO 2025'!G61 -> 661400 | H61: =+'ENERO 2025'!H61+'FEBRERO 2025'!H61 -> 0 | J61: =+G61+H61 -> 661400 | K61: =J61/$J$25 -> 0.0038054592
A62: 2 | B62: 1 | C62: 2 | D62: 2 | E62: 09 | F62: Bono por desempeño a servidores de carrera | G62: =+'ENERO 2025'!G62+'FEBRERO 2025'!G62 -> 0 | H62: =+'ENERO 2025'!H62+'FEBRERO 2025'!H62 -> 0 | J62: =+G62+H62 -> 0 | K62: =J62/$J$25 -> 0
A63: 2 | B63: 1 | C63: 2 | D63: 2 | E63: 10 | F63: Compensacion por cumplimiento de indicadores | G63: =+'ENERO 2025'!G63+'FEBRERO 2025'!G63 -> 139326.2 | H63: =+'ENERO 2025'!H63+'FEBRERO 2025'!H63 -> 0 | J63: =+G63+H63 -> 139326.2 | K63: =J63/$J$25 -> 0.00080163315
A64: 2 | B64: 1 | C64: 3 | F64: Dietas y Gastos de Representación | G64: =+'ENERO 2025'!G64+'FEBRERO 2025'!G64 -> 0 | H64: =+'ENERO 2025'!H64+'FEBRERO 2025'!H64 -> 0 | J64: =+G64+H64 -> 0
A65: 2 | B65: 1 | C65: 3 | D65: 1 | F65: Dietas | G65: =+'ENERO 2025'!G65+'FEBRERO 2025'!G65 -> 0 | H65: =+'ENERO 2025'!H65+'FEBRERO 2025'!H65 -> 0 | J65: =+G65+H65 -> 0
A66: 2 | B66: 1 | C66: 3 | D66: 1 | E66: 01 | F66: Dietas en el país | G66: =+'ENERO 2025'!G66+'FEBRERO 2025'!G66 -> 0 | H66: =+'ENERO 2025'!H66+'FEBRERO 2025'!H66 -> 0 | J66: =+G66+H66 -> 0 | K66: =J66/$J$25 -> 0
A67: 2 | B67: 1 | C67: 3 | D67: 1 | E67: 02 | F67: Dietas en el exterior | G67: =+'ENERO 2025'!G67+'FEBRERO 2025'!G67 -> 0 | H67: =+'ENERO 2025'!H67+'FEBRERO 2025'!H67 -> 0 | J67: =+G67+H67 -> 0 | K67: =J67/$J$25 -> 0
A68: 2 | B68: 1 | C68: 3 | D68: 2 | F68: Gastos de representación | G68: =+'ENERO 2025'!G68+'FEBRERO 2025'!G68 -> 0 | H68: =+'ENERO 2025'!H68+'FEBRERO 2025'!H68 -> 0 | J68: =+G68+H68 -> 0
A69: 2 | B69: 1 | C69: 3 | D69: 2 | E69: 01 | F69: Gastos de representación en el país | G69: =+'ENERO 2025'!G69+'FEBRERO 2025'!G69 -> 0 | H69: =+'ENERO 2025'!H69+'FEBRERO 2025'!H69 -> 0 | J69: =+G69+H69 -> 0 | K69: =J69/$J$25 -> 0
A70: 2 | B70: 1 | C70: 3 | D70: 2 | E70: 02 | F70: Gastos de representación en el exterior | G70: =+'ENERO 2025'!G70+'FEBRERO 2025'!G70 -> 0 | H70: =+'ENERO 2025'!H70+'FEBRERO 2025'!H70 -> 0 | J70: =+G70+H70 -> 0 | K70: =J70/$J$25 -> 0
A71: 2 | B71: 1 | C71: 4 | F71: Gratificaciones y Bonificaciones | G71: =+'ENERO 2025'!G71+'FEBRERO 2025'!G71 -> 0 | H71: =+'ENERO 2025'!H71+'FEBRERO 2025'!H71 -> 0 | J71: =+G71+H71 -> 0
A72: 2 | B72: 1 | C72: 4 | D72: 1 | F72: Bonificaciones | G72: =+'ENERO 2025'!G72+'FEBRERO 2025'!G72 -> 0 | H72: =+'ENERO 2025'!H72+'FEBRERO 2025'!H72 -> 0 | J72: =+G72+H72 -> 0
A73: 2 | B73: 1 | C73: 4 | D73: 1 | E73: 01 | F73: Bonificaciones | G73: =+'ENERO 2025'!G73+'FEBRERO 2025'!G73 -> 0 | H73: =+'ENERO 2025'!H73+'FEBRERO 2025'!H73 -> 0 | J73: =+G73+H73 -> 0 | K73: =J73/$J$25 -> 0
A74: 2 | B74: 1 | C74: 4 | D74: 2 | F74: Otras Gratificaciones y Bonificaciones | G74: =+'ENERO 2025'!G74+'FEBRERO 2025'!G74 -> 0 | H74: =+'ENERO 2025'!H74+'FEBRERO 2025'!H74 -> 0 | J74: =+G74+H74 -> 0
A75: 2 | B75: 1 | C75: 4 | D75: 2 | E75: 01 | F75: Bono escolar | G75: =+'ENERO 2025'!G75+'FEBRERO 2025'!G75 -> 0 | H75: =+'ENERO 2025'!H75+'FEBRERO 2025'!H75 -> 0 | J75: =+G75+H75 -> 0 | K75: =J75/$J$25 -> 0
A76: 2 | B76: 1 | C76: 4 | D76: 2 | E76: 02 | F76: Gratificaciones por pasantías | G76: =+'ENERO 2025'!G76+'FEBRERO 2025'!G76 -> 0 | H76: =+'ENERO 2025'!H76+'FEBRERO 2025'!H76 -> 0 | J76: =+G76+H76 -> 0 | K76: =J76/$J$25 -> 0
A77: 2 | B77: 1 | C77: 4 | D77: 2 | E77: 03 | F77: Gratificaciones por aniversario de institución | G77: =+'ENERO 2025'!G77+'FEBRERO 2025'!G77 -> 0 | H77: =+'ENERO 2025'!H77+'FEBRERO 2025'!H77 -> 0 | J77: =+G77+H77 -> 0 | K77: =J77/$J$25 -> 0
A78: 2 | B78: 1 | C78: 5 | F78: Contribuciones a la Seguridad Social y Riesgo Laboral | G78: =+'ENERO 2025'!G78+'FEBRERO 2025'!G78 -> 16601649 | H78: =+'ENERO 2025'!H78+'FEBRERO 2025'!H78 -> 0 | J78: =+G78+H78 -> 16601649
A79: 2 | B79: 1 | C79: 5 | D79: 1 | F79: Contribuciones al seguro de salud | G79: =+'ENERO 2025'!G79+'FEBRERO 2025'!G79 -> 7649642.9 | H79: =+'ENERO 2025'!H79+'FEBRERO 2025'!H79 -> 0 | J79: =+G79+H79 -> 7649642.9
A80: 2 | B80: 1 | C80: 5 | D80: 1 | E80: 01 | F80: Contribuciones al seguro de salud | G80: =+'ENERO 2025'!G80+'FEBRERO 2025'!G80 -> 7649642.9 | H80: =+'ENERO 2025'!H80+'FEBRERO 2025'!H80 -> 0 | J80: =+G80+H80 -> 7649642.9 | K80: =J80/$J$25 -> 0.044013311
A81: 2 | B81: 1 | C81: 5 | D81: 2 | F81: Contribuciones al seguro de pensiones | G81: =+'ENERO 2025'!G81+'FEBRERO 2025'!G81 -> 7660428.6 | H81: =+'ENERO 2025'!H81+'FEBRERO 2025'!H81 -> 0 | J81: =+G81+H81 -> 7660428.6
A82: 2 | B82: 1 | C82: 5 | D82: 2 | E82: 01 | F82: Contribuciones al seguro de pensiones | G82: =+'ENERO 2025'!G82+'FEBRERO 2025'!G82 -> 7660428.6 | H82: =+'ENERO 2025'!H82+'FEBRERO 2025'!H82 -> 0 | J82: =+G82+H82 -> 7660428.6 | K82: =J82/$J$25 -> 0.044075368
A83: 2 | B83: 1 | C83: 5 | D83: 3 | F83: Contribuciones al seguro de riesgo laboral | G83: =+'ENERO 2025'!G83+'FEBRERO 2025'!G83 -> 1291577.7 | H83: =+'ENERO 2025'!H83+'FEBRERO 2025'!H83 -> 0 | J83: =+G83+H83 -> 1291577.7
A84: 2 | B84: 1 | C84: 5 | D84: 3 | E84: 01 | F84: Contribuciones al seguro de riesgo laboral | G84: =+'ENERO 2025'!G84+'FEBRERO 2025'!G84 -> 1291577.7 | H84: =+'ENERO 2025'!H84+'FEBRERO 2025'!H84 -> 0 | J84: =+G84+H84 -> 1291577.7 | K84: =J84/$J$25 -> 0.0074312762
A85: 2 | B85: 1 | C85: 5 | D85: 4 | F85: Contribuciones al plan de retiro complementario | G85: =+'ENERO 2025'!G85+'FEBRERO 2025'!G85 -> 0 | H85: =+'ENERO 2025'!H85+'FEBRERO 2025'!H85 -> 0 | J85: =+G85+H85 -> 0
A86: 2 | B86: 1 | C86: 5 | D86: 4 | E86: 01 | F86: Contribuciones al plan de retiro complementario | G86: =+'ENERO 2025'!G86+'FEBRERO 2025'!G86 -> 0 | H86: =+'ENERO 2025'!H86+'FEBRERO 2025'!H86 -> 0 | J86: =+G86+H86 -> 0 | K86: =J86/$J$25 -> 0
A87: 2 | B87: 2 | F87: Servicios No Personales | G87: =+'ENERO 2025'!G87+'FEBRERO 2025'!G87 -> 1336968.6 | H87: =+'ENERO 2025'!H87+'FEBRERO 2025'!H87 -> 3947227.6 | J87: =+G87+H87 -> 5284196.3 | K87: =J87/$J$25 -> 0.030403376
A88: 2 | B88: 2 | C88: 1 | F88: Servicios Básicos | G88: =+'ENERO 2025'!G88+'FEBRERO 2025'!G88 -> 0 | H88: =+'ENERO 2025'!H88+'FEBRERO 2025'!H88 -> 610370.73 | J88: =+G88+H88 -> 610370.73
A89: 2 | B89: 2 | C89: 1 | D89: 1 | F89: Radiocomunicación | G89: =+'ENERO 2025'!G89+'FEBRERO 2025'!G89 -> 0 | H89: =+'ENERO 2025'!H89+'FEBRERO 2025'!H89 -> 0 | J89: =+G89+H89 -> 0
A90: 2 | B90: 2 | C90: 1 | D90: 1 | E90: 01 | F90: Radiocomunicación | G90: =+'ENERO 2025'!G90+'FEBRERO 2025'!G90 -> 0 | H90: =+'ENERO 2025'!H90+'FEBRERO 2025'!H90 -> 0 | J90: =+G90+H90 -> 0 | K90: =J90/$J$25 -> 0
A91: 2 | B91: 2 | C91: 1 | D91: 2 | F91: Servicios telefónico de larga distancia | G91: =+'ENERO 2025'!G91+'FEBRERO 2025'!G91 -> 0 | H91: =+'ENERO 2025'!H91+'FEBRERO 2025'!H91 -> 0 | J91: =+G91+H91 -> 0
A92: 2 | B92: 2 | C92: 1 | D92: 2 | E92: 01 | F92: Servicios telefónico de larga distancia | G92: =+'ENERO 2025'!G92+'FEBRERO 2025'!G92 -> 0 | H92: =+'ENERO 2025'!H92+'FEBRERO 2025'!H92 -> 0 | J92: =+G92+H92 -> 0 | K92: =J92/$J$25 -> 0
A93: 2 | B93: 2 | C93: 1 | D93: 3 | F93: Teléfono local | G93: =+'ENERO 2025'!G93+'FEBRERO 2025'!G93 -> 0 | H93: =+'ENERO 2025'!H93+'FEBRERO 2025'!H93 -> 560370.73 | J93: =+G93+H93 -> 560370.73
A94: 2 | B94: 2 | C94: 1 | D94: 3 | E94: 01 | F94: Teléfono local | G94: =+'ENERO 2025'!G94+'FEBRERO 2025'!G94 -> 0 | H94: =+'ENERO 2025'!H94+'FEBRERO 2025'!H94 -> 560370.73 | J94: =+G94+H94 -> 560370.73 | K94: =J94/$J$25 -> 0.0032241729
A95: 2 | B95: 2 | C95: 1 | D95: 4 | F95: Telefax y correos | G95: =+'ENERO 2025'!G95+'FEBRERO 2025'!G95 -> 0 | H95: =+'ENERO 2025'!H95+'FEBRERO 2025'!H95 -> 0 | J95: =+G95+H95 -> 0
A96: 2 | B96: 2 | C96: 1 | D96: 4 | E96: 01 | F96: Telefax y correos | G96: =+'ENERO 2025'!G96+'FEBRERO 2025'!G96 -> 0 | H96: =+'ENERO 2025'!H96+'FEBRERO 2025'!H96 -> 0 | J96: =+G96+H96 -> 0 | K96: =J96/$J$25 -> 0
A97: 2 | B97: 2 | C97: 1 | D97: 5 | F97: Servicio de Internet y televisión por cable | G97: =+'ENERO 2025'!G97+'FEBRERO 2025'!G97 -> 0 | H97: =+'ENERO 2025'!H97+'FEBRERO 2025'!H97 -> 0 | J97: =+G97+H97 -> 0
A98: 2 | B98: 2 | C98: 1 | D98: 5 | E98: 01 | F98: Servicio de Internet y televisión por cable | G98: =+'ENERO 2025'!G98+'FEBRERO 2025'!G98 -> 0 | H98: =+'ENERO 2025'!H98+'FEBRERO 2025'!H98 -> 0 | J98: =+G98+H98 -> 0 | K98: =J98/$J$25 -> 0
A99: 2 | B99: 2 | C99: 1 | D99: 6 | F99: Electricidad | G99: =+'ENERO 2025'!G99+'FEBRERO 2025'!G99 -> 0 | H99: =+'ENERO 2025'!H99+'FEBRERO 2025'!H99 -> 0 | J99: =+G99+H99 -> 0
A100: 2 | B100: 2 | C100: 1 | D100: 6 | E100: 01 | F100: Energía eléctrica | G100: =+'ENERO 2025'!G100+'FEBRERO 2025'!G100 -> 0 | H100: =+'ENERO 2025'!H100+'FEBRERO 2025'!H100 -> 0 | J100: =+G100+H100 -> 0 | K100: =J100/$J$25 -> 0
A101: 2 | B101: 2 | C101: 1 | D101: 6 | E101: 02 | F101: Electricidad no cortable | G101: =+'ENERO 2025'!G101+'FEBRERO 2025'!G101 -> 0 | H101: =+'ENERO 2025'!H101+'FEBRERO 2025'!H101 -> 0 | J101: =+G101+H101 -> 0 | K101: =J101/$J$25 -> 0
A102: 2 | B102: 2 | C102: 1 | D102: 7 | F102: Agua | G102: =+'ENERO 2025'!G102+'FEBRERO 2025'!G102 -> 0 | H102: =+'ENERO 2025'!H102+'FEBRERO 2025'!H102 -> 0 | J102: =+G102+H102 -> 0
...
