Workbook

Sheet RELACION CHEQUES EMITIDOS
A5: DIRECCION DE FISCALIZACION Y CONTROL
A6: RELACION DE LIBRAMIENTOS/CHEQUES/ TRANSFERENCIAS EMITIDOS DURANTE EL MES ENERO 2025
A7: ESTABLECIMIENTO: HOSPITAL MATERNO INFANTIL SAN LORENZO DE LOS MINA
A8: CORRESPONDIENTES AL MES : ENERO 2025
A9: FECHA | B9: LIBRAMIENTO | C9: TRANSFERENCIA | D9: CHEQUE | E9: BENEFICIARIO | F9: NO.FACTURAS | G9: VALOR DE FACTURA | H9: VALOR PAGADO
A10: 45667 | C10: TRANSF. 001 | E10: EQMAPHAR, SRL | F10: PAGO DE FACT NCF NO. B1500000006, POR ADQUISICION DE CALENTADORES PARA PACIENTES Y MANTAS TERMICAS NEONATALES, SEGÚN ORDEN DE COMPRA HSLM-2024-01349 | G10: 1129894.8 | H10: 1082017.9
A11: 45667 | C11: TRANSF. 002 | E11: LEHAIM SUMINISTROS, SRL | F11: PAGO DE FACT NCF NO. B1500000004, POR ADQUISICION DE MEDICAMENTOS, SEGÚN ORDEN DE COMPRA HSLM-2024-01377 | G11: 258000 | H11: 245100
A12: 45670 | C12: TRANSF. 003 | E12: GRAFISOL, SRL | F12: APORTE ECONOMICO PARA LA REVISTA MEDICA CIENTIFICA | G12: 100000 | H12: 100000
A13: 45670 | C13: TRANSF. 004 | E13: FARMACO QUIMICA NACIONAL S.A | F13: COMPRA DE VALVULA HIDROCEFALICA PARA RN INGRESADO EN EL HOSPITAL. | G13: 30166.7 | H13: 30166.7
A14: 45671 | C14: TRANSF. 005 | E14: CENTRO DE ESTUDIOS MEDICOS Y DIAGNOSTICOS POR IMÁGENES, SRL | F14: PAGO DE FACT NCF B1500000352, POR SERVICIOS DE ESTUDIOS ESPECIALIZADOS A PACIENTES INTERNOS SEGÚN O/C 2024-000116 | G14: 10100 | H14: 9595
A15: 45671 | C15: TRANSF. 006 | E15: TONER DEPOT MULTISERVICIOS EORG, SRL | F15: PAGO DE FACT NCF NO. B1500008206, POR PAGO DE SERVICIOS DE IMPRESIÓN O/C 2024-00767 | G15: 266664.26 | H15: 255364.93
A16: 45671 | C16: TRANSF. 007 | E16: AYUNTAMIENTO SANTO DOMINGO ESTE | F16: PAGO DE FACT B1500054922 Y B1500055023, POR SERVICIO DE RECOGIDA DE DESECHOS SOLIDOS | G16: 50000 | H16: 50000
A17: 45671 | C17: TRANSF. 008 | E17: LABORATORIO CLINICO LICDA PATRIA RIVAS, SRL | F17: PAGO DE FACT NCF NO. B1500002239, POR SERVICIO DE PRUEBAS ESPECIALES A PACIENTES INTERNOS, SEGÚN O/C 2024-00107 | G17: 17740 | H17: 16853
A18: 45671 | C18: TRANSF. 009 | E18: PLANETA AZUL | F18: PAGO DE FACT E4500006333, E4500006338, E4500006340, E4500007753, E4500006344, POR ADQUISICIONES DE BOTELLONES DE AGUA SEGÚN ORDEN DE COMPRA 2024-00796 | G18: 37740 | H18: 37740
A19: 45671 | C19: TRANSF. 010 | E19: TROPIGAS, SRL | F19: PAGO DE FACT NCF E4500005333 Y E450000005343, POR ADQUISICON DE GLP, SEGÚN ORDEN DE COMPRA 2024-00326 | G19: 49512.84 | H19: 49512.84
A20: 45672 | C20: TRANSF. 011 | E20: PRODUCTOS CANO SRL | F20: PAGO NCF B1500001242 ADQUISICION DE PAN SEGÚN O/C HSLM-2024-00631 | G20: 98115 | H20: 93209.25
A21: 45672 | C21: TRANSF. 012 | E21: BIO WIN SRL | F21: PAGO NCF B1500002379, B1500002382, B1500002083, B1500002090. ADQUISICION DE SANGRE DE CARNERO SEGÚN O/C HSLM-2024-00988. | G21: 6900 | H21: 6555
... A37: 45687 | C37: TRANSF. 028 | E37: SUED & FARGESA, SRL | F37: PAGO DE FACT NCF NO. E45000001159, POR ADQUISICION DE UNA GRAPADORA MAS 1 CARTUCHO DE GRAPAS AJUSTABLES DE 55MM | G37: 47176.05 | H37: 45177.07
A38: 22/01/2025 | B38: 4 | E38: HOSPITAL MATERNO INFANTIL SAN LORENZO DE LOS MINAS | F38: HOSANLORE. NOMINA SUELDO TEMPORAL ENERO 2025 | G38: 1123146.4 | H38: 1010139.8 | I38: =+G38-H38 -> 113006.56
A39: 22/01/2025 | B39: 6 | E39: HOSPITAL MATERNO INFANTIL SAN LORENZO DE LOS MINAS | F39: HOSANLORE. NOMINA SUELDO PERSONAL DE VIGILANCIA ENERO 2025 | G39: 45000 | H39: 43452.75 | I39: =+G39-H39 -> 1547.25
A40: 27/01/2025 | B40: 9 | E40: HOSPITAL MATERNO INFANTIL SAN LORENZO DE LOS MINAS | F40: HOSANLORE. NOMINA SUELDO FIJO ENERO 2025 | G40: 63923034 | H40: 42730628 | I40: =+G40-H40 -> 21192406
A41: 31/01/2025 | B41: 16 | E41: Grupo Xeron Medic SRL | F41: pago factura b1500000145 por medicamento orden compa HSLM-2024-01367 | G41: 55550 | H41: 52772.5 | I41: =+G41-H41 -> 2777.5
A42: 31/01/2025 | B42: 23 | E42: Grupo Xeron Medic SRL | F42: PAGO DE FACT NCF B1500000155 POR ADQUISICION DE MEDICAMENTOS SEGUN O/C HSLM-2025-00007. | G42: 252000 | H42: 239400 | I42: =+G42-H42 -> 12600
A43: 31/01/2025 | B43: 25 | E43: Bello-Lab, SRL | F43: Pago de Fact NCF No. B1500001014, por adquisicion de medicamentos, segun orden de compra, HSLM-2024-01400 | G43: 467802 | H43: 447957 | I43: =+G43-H43 -> 19845
A44: 31/01/2025 | B44: 31 | E44: Bello-Lab, SRL | F44: Pago de Fact NCF No. B1500001011, por adquisicion de reactivos, según orden de compra, HSLM-2024-01363 | G44: 332252 | H44: 316538.5 | I44: =+G44-H44 -> 15713.5
A45: 31/01/2025 | B45: 35 | E45: Oficclin Comercial, SRL | F45: Pago de Fact NCF No. B1500000557, por adquisicion de medicamentos, según orden de compra, HSLM-2025-00028 | G45: 271350 | H45: 257782.5 | I45: =+G45-H45 -> 13567.5
A46: 31/01/2025 | B46: 36 | E46: Farmaco Internacional, SRL | F46: PAGO FACTURA NCF B1500000996 POR ADQUISICION DE UTIL MEDICO SEGUN ORDEN DE COMPRA HSLM-2024-0139. | G46: 129664 | H46: 123180.8 | I46: =+G46-H46 -> 6483.2
A47: 31/01/2025 | B47: 43 | E47: CEM Caribbean Equipment Medical, SRL | F47: PAGO DE FACT NCF B1500001096 POR ADQUISICION DE UTILES MEDICOS SEGUN O/C HSLM-2024-01374. | G47: 235971.68 | H47: 225972.88 | I47: =+G47-H47 -> 9998.8
A48: 31/01/2025 | B48: 45 | E48: Socomedi Multisolutions, SRL | F48: PAGO FACTURA NCF B1500000368 POR ADQUISICION DE MEDICAMENTOS SEGUN O/C HSLM-2025-00042. | G48: 240000 | H48: 228000 | I48: =+G48-H48 -> 12000
A49: 31/01/2025 | B49: 49 | E49: Lambda Diagnósticos, SRL | F49: Pago de Fact NCF No. B1500002232, por adquisicion de reactivos, según orden de compra, HSLM-2024-01306 | G49: 703592.61 | H49: 668417.76 | I49: =+G49-H49 -> 35174.85
... A58: 31/01/2025 | B58: 84 | E58: Grupo Xeron Medic SRL | F58: PAGO FACT NCF B1500000157, POR ADQUISICION DE MEDICAMENTOS SEGUN ORDEN DE COMPRA HSLM-2025-00006. | G58: 236000 | H58: 224200 | I58: =+G58-H58 -> 11800
A59: 45660 | D59: 37174 | E59: FREDDY OSCAR RODRIGUEZ RIVAS | F59: COLABORACION PARA CAVACION DE HOYOS Y CERTIFICACION DE ACTAS | G59: 3400 | H59: 3400 | I59: =+G59-H59 -> 0
A60: 45671 | D60: =+D59+1 -> 37175 | E60: DELMIRA GARCIA | F60: REPOSICION DEL FONDO DE CAJA CHICA | G60: 49134.32 | H60: 49134.32 | I60: =+G60-H60 -> 0
A61: 45671 | D61: =+D60+1 -> 37176 | E61: JHONNY CASTILLO SORIANO | F61: PAGO POR SERVICIO DE MANTENIMIENTO MECANICO A LA AMBULANCIA DEL HOSPITAL, SEGÚN O/S 1915 | G61: 23600 | H61: 19600 | I61: =+G61-H61 -> 4000
A62: 45674 | D62: =+D61+1 -> 37177 | E62: OLEGARIO GUERRERO | F62: SERVICIO DE MANTENIMIENTO DE PINTURA AL DEPTO DE SEGURIDAD DEL HOSPITAL | G62: 21673.46 | H62: 18000 | I62: =+G62-H62 -> 3673.46
A63: 45679 | D63: =+D62+1 -> 37178 | E63: ALEXANDER MENDEZ CONTRERAS | F63: PAGO POR MANTENIMIENTO, LIMPIEZA Y CLORIFICACION DE LA CSTERNA DEL HOSPITAL | G63: 18061.22 | H63: 15000 | I63: =+G63-H63 -> 3061.22
A64: 45679 | D64: =+D63+1 -> 37179 | E64: NULO | F64: NULO | G64: 0 | H64: 0 | I64: =+G64-H64 -> 0
A65: 45679 | D65: =+D64+1 -> 37180 | E65: CARLOS ALEJANDRO SANCHEZ ORTEGA | F65: PAGO POR SERVICIO DE MANTENIMIENTO MECANICO A LA AMBULANCIA DEL HOSPITAL, SEGÚN O/S 1918 | G65: 42142.86 | H65: 35000 | I65: =+G65-H65 -> 7142.86
A66: 45679 | D66: =+D65+1 -> 37181 | E66: DELMIRA GARCIA | F66: REPOSICION DEL FONDO DE CAJA CHICA | G66: 50927.38 | H66: 50927.38 | I66: =+G66-H66 -> 0
A67: 45681 | D67: =+D66+1 -> 37182 | E67: NELSON YNFANTE VELAZQUEZ | F67: SERVICIO DE PINTURA PARA DIFERENTES AREA DEL HOSPITAL | G67: 18061.22 | H67: 15000 | I67: =+G67-H67 -> 3061.22
A68: 45681 | D68: =+D67+1 -> 37183 | E68: RUDDY SEGURA | F68: SERVICIO DE LIMPIEZA DE ESCOMBROS DE JARDINERIA Y AREAS VERDE | G68: 21673.47 | H68: 18000 | I68: =+G68-H68 -> 3673.47
A69: 45685 | D69: =+D68+1 -> 37184 | E69: VICTOR DE LA CRUZ CARELA | F69: PAGO POR REPARACION Y MANTENIMIENTO PREVENTIVO DEL AIRE ACONDICIONADO TIPO PAQUETE DEL AREA DE CONSULTA, SEGUN DOCUMENTACION ANEXA. | G69: 31306.12 | H69: 26000 | I69: =+G69-H69 -> 5306.12
A70: 45685 | D70: =+D69+1 -> 37185 | E70: FREDDY OSCAR RODRIGUEZ RIVAS | F70: COLABORACION PARA CAVACION DE HOYOS Y CERTIFICACION DE ACTAS | G70: 3400 | H70: 3400 | I70: =+G70-H70 -> 0
G71: =SUM(G10:G70) -> 76869860
A75: RESUMEN
A76: PAGO PROVEEDORES | C76: 11495300
A77: CAJA CHICA | C77: =+G66+G60 -> 100061.7
A78: NOMINA | C78: =+G38+G39+G40 -> 65091180
A79: OTROS | C79: =+G70+G69+G68+G67+G65+G63+G62+G61+G59 -> 183318.35
G140: =SUM(G10:G58) -> 76586480

Sheet RELACION ORDENES DE COMPRAS
A1: HOSPITAL MATERNO INFANTIL SAN LORENZO DE LOS MINA
A2: ORDENES DE COMPRA MES DE ENERO 2025
A4: Capitulo | B4: Unidad de Compras | C4: Referencia del Proceso | D4: Proceso de Compra | E4: Proceso de Compra Mypyme | F4: Proceso de Compra Mypyme Mujer | G4: Modalidad | H4: Monto | I4: Estado del Procedimiento | J4: Rubro Del Proceso | K4: Descripción Rubro | L4: Empresa Adjudicada | M4: Estado Del Contrato | N4: Cantidad de Contratos | O4: Monto Por Contratos | P4: Tipo de Empresa Adjudicada | Q4: FECHA
A5: DIRECCION CENTRAL DEL SERVICIO NACIONAL DE SALUD | B5: Hospital Materno Infantil San Lorenzo de Los Minas | C5: HSLM-DAF-CD-2025-0001 | D5: ADQUISICION DE TIKETS DE COMBUSTIBLE | E5: No | F5: No | G5: Compras por Debajo del Umbral | H5: 172000 | I5: Adjudicado | J5: 15100000 | K5: Combustibles | L5: Inversiones FH, SRL | N5: 0 | O5: 172000 | P5: Grande | Q5: 45659.458
A6: DIRECCION CENTRAL DEL SERVICIO NACIONAL DE SALUD | B6: Hospital Materno Infantil San Lorenzo de Los Minas | C6: HSLM-DAF-CD-2025-0002 | D6: COMPRA DE EMBUTIDOS | E6: No | F6: No | G6: Compras por Debajo del Umbral | H6: 113000 | I6: Adjudicado | J6: 50130000 | K6: Productos lácteos y huevos | N6: 0 | P6: Grande | Q6: 45659.5
A7: DIRECCION CENTRAL DEL SERVICIO NACIONAL DE SALUD | B7: Hospital Materno Infantil San Lorenzo de Los Minas | C7: HSLM-DAF-CM-2025-0001 | D7: CARNES | E7: No | F7: No | G7: Compras Menores | H7: 573000 | I7: Adjudicado | J7: 50110000 | K7: Productos de carne y aves de corral | L7: Sandry Gomez Rodriguez | M7: Activo | N7: 1 | O7: 572250 | P7: Grande | Q7: 45659.5
A8: DIRECCION CENTRAL DEL SERVICIO NACIONAL DE SALUD | B8: Hospital Materno Infantil San Lorenzo de Los Minas | C8: HSLM-DAF-CM-2025-0002 | D8: ADQUISICION DE VEGETALES | E8: No | F8: No | G8: Compras Menores | H8: 434960 | I8: Adjudicado | J8: 50100000 | K8: Frutos secos | L8: Sandry Gomez Rodriguez | M8: Activo | N8: 1 | O8: 405410 | P8: Grande | Q8: 45659.563
A9: DIRECCION CENTRAL DEL SERVICIO NACIONAL DE SALUD | B9: Hospital Materno Infantil San Lorenzo de Los Minas | C9: HSLM-DAF-CM-2025-0003 | D9: DESPENSA | E9: No | F9: No | G9: Compras Menores | H9: 387750 | I9: Adjudicado | J9: 50190000 | K9: Alimentos preparados y conservados | L9: Distribuidora Latino, SRL | M9: Activo | N9: 2 | O9: 242795 | P9: Grande | Q9: 45659.668
A10: DIRECCION CENTRAL DEL SERVICIO NACIONAL DE SALUD | B10: Hospital Materno Infantil San Lorenzo de Los Minas | C10: HSLM-DAF-CM-2025-0003 | D10: DESPENSA | E10: No | F10: No | G10: Compras Menores | H10: 387750 | I10: Adjudicado | J10: 50190000 | K10: Alimentos preparados y conservados | L10: Diucam Group SRL | M10: Activo | N10: 2 | O10: 473584 | P10: Mipyme Mujer | Q10: 45659.667
A11: DIRECCION CENTRAL DEL SERVICIO NACIONAL DE SALUD | B11: Hospital Materno Infantil San Lorenzo de Los Minas | C11: HSLM-DAF-CD-2025-0003 | D11: SOLUCION SALINO AL 9% DE 1000 ML | E11: No | F11: No | G11: Compras por Debajo del Umbral | H11: 240000 | I11: Adjudicado | J11: 51190000 | K11: Agentes que afectan el agua y los electrolitos | N11: 0 | P11: Grande | Q11: 45660.418
A12: DIRECCION CENTRAL DEL SERVICIO NACIONAL DE SALUD | B12: Hospital Materno Infantil San Lorenzo de Los Minas | C12: HSLM-DAF-CD-2025-0004 | D12: ADQUISICION DE SOLUCION SALINO AL 9% DE 1000 ML Y ESPARADRAPO | E12: No | F12: No | G12: Compras por Debajo del Umbral | H12: 218656 | I12: Adjudicado | J12: 42310000 | K12: Productos para el cuidado de heridas | N12: 0 | P12: Grande | Q12: 45660.438
A13: DIRECCION CENTRAL DEL SERVICIO NACIONAL DE SALUD | B13: Hospital Materno Infantil San Lorenzo de Los Minas | C13: HSLM-DAF-CD-2025-0006 | D13: MISOPROSTOL 200MG | E13: No | F13: No | G13: Compras por Debajo del Umbral | H13: 180000 | I13: Adjudicado | J13: 51170000 | K13: Medicamentos que afectan al sistema gastrointestinal | N13: 0 | P13: Grande | Q13: 45660.542
A14: DIRECCION CENTRAL DEL SERVICIO NACIONAL DE SALUD | B14: Hospital Materno Infantil San Lorenzo de Los Minas | C14: HSLM-DAF-CD-2025-0005 | D14: HALOPERIDOL 5ML AMP | E14: No | F14: No | G14: Compras por Debajo del Umbral | H14: 236000 | I14: Adjudicado | J14: 51140000 | K14: Medicamentos para el sistema nervioso central | N14: 0 | P14: Grande | Q14: 45660.542
A15: DIRECCION CENTRAL DEL SERVICIO NACIONAL DE SALUD | B15: Hospital Materno Infantil San Lorenzo de Los Minas | C15: HSLM-DAF-CD-2025-0007 | D15: SOLUCION SALINO AL 9% DE 100 ML | E15: No | F15: No | G15: Compras por Debajo del Umbral | H15: 240000 | I15: Adjudicado | J15: 51190000 | K15: Agentes que afectan el agua y los electrolitos | N15: 0 | P15: Grande | Q15: 45660.552
A16: DIRECCION CENTRAL DEL SERVICIO NACIONAL DE SALUD | B16: Hospital Materno Infantil San Lorenzo de Los Minas | C16: HSLM-DAF-CD-2025-0008 | D16: ADQUISICION DE GERDEX | E16: No | F16: No | G16: Compras por Debajo del Umbral | H16: 218400 | I16: Adjudicado | J16: 42280000 | K16: Productos para la esterilización médica | N16: 0 | P16: Grande | Q16: 45664.382
A17: DIRECCION CENTRAL DEL SERVICIO NACIONAL DE SALUD | B17: Hospital Materno Infantil San Lorenzo de Los Minas | C17: HSLM-DAF-CM-2025-0004 | D17: ADQUISICION DE DETERGENTE PARA LAVANDERIA | E17: No | F17: No | G17: Compras Menores | H17: 1277300 | I17: Adjudicado | J17: 12160000 | K17: Aditivos | L17: Cabod, EIRL | M17: Activo | N17: 1 | O17: 1507214 | P17: MiPyme | Q17: 45664.417
A18: DIRECCION CENTRAL DEL SERVICIO NACIONAL DE SALUD | B18: Hospital Materno Infantil San Lorenzo de Los Minas | C18: HSLM-DAF-CD-2025-0009 | D18: ADQUISICION DE UTILES MEDICOS, PLACAS Y ELECTRODOS. | E18: No | F18: No | G18: Compras por Debajo del Umbral | H18: 232500 | I18: Adjudicado | J18: 42290000 | K18: Productos quirúrgicos | N18: 0 | P18: Grande | Q18: 45664.458
A19: DIRECCION CENTRAL DEL SERVICIO NACIONAL DE SALUD | B19: Hospital Materno Infantil San Lorenzo de Los Minas | C19: HSLM-DAF-CD-2025-0011 | D19: ADQUISICION DE UTILES MEDICOS, HILO,PAPEL DE SONOGRAFIA Y CINTA AUTOCLAVE. | E19: No | F19: No | G19: Compras por Debajo del Umbral | H19: 246580 | I19: Adjudicado | J19: 42310000 | K19: Productos para el cuidado de heridas | N19: 0 | P19: Grande | Q19: 45664.469
A20: DIRECCION CENTRAL DEL SERVICIO NACIONAL DE SALUD | B20: Hospital Materno Infantil San Lorenzo de Los Minas | C20: HSLM-DAF-CD-2025-0010 | D20: ADQUISICION DE ROLLOS DE PAPEL LABELS ZEBRA 2X1 | E20: No | F20: No | G20: Compras por Debajo del Umbral | H20: 191100 | I20: Adjudicado | J20: 14110000 | K20: Productos de papel | L20: Papelería E. Impresos Crishoan, SRL | M20: Activo | N20: 1 | O20: 226357 | P20: Grande | Q20: 45664.5
A21: DIRECCION CENTRAL DEL SERVICIO NACIONAL DE SALUD | B21: Hospital Materno Infantil San Lorenzo de Los Minas | C21: HSLM-DAF-CM-2025-0005 | D21: MATERIALES DE LIMPIEZA | E21: No | F21: No | G21: Compras Menores | H21: 396660 | I21: Cancelado | J21: 47130000 | K21: Suministros de aseo y limpieza | N21: 0 | P21: Grande | Q21: 45664.5
A22: DIRECCION CENTRAL DEL SERVICIO NACIONAL DE SALUD | B22: Hospital Materno Infantil San Lorenzo de Los Minas | C22: HSLM-DAF-CD-2025-0012 | D22: ADQUISICION DE UTILES MEDICOS, PERITAS NASALES Y ESPARADRAPOS. | E22: No | F22: No | G22: Compras por Debajo del Umbral | H22: 228100 | I22: Adjudicado | J22: 42310000 | K22: Productos para el cuidado de heridas | L22: Global Multi-Pharma Dominicana THM, SRL | M22: Activo | N22: 1 | O22: 269158 | P22: MiPyme | Q22: 45664.504
A23: DIRECCION CENTRAL DEL SERVICIO NACIONAL DE SALUD | B23: Hospital Materno Infantil San Lorenzo de Los Minas | C23: HSLM-DAF-CD-2025-0014 | D23: ADQUISICION DE UTILES MEDICOS, GORRO DE ENFERMERIA AZUL Y APOSITO PEDIATRICO. | E23: No | F23: No | G23: Compras por Debajo del Umbral | H23: 228000 | I23: Adjudicado | J23: 42130000 | K23: Telas y vestidos médicos | N23: 0 | P23: Grande | Q23: 45664.542
A24: DIRECCION CENTRAL DEL SERVICIO NACIONAL DE SALUD | B24: Hospital Materno Infantil San Lorenzo de Los Minas | C24: HSLM-DAF-CD-2025-0013 | D24: LECTOR DE CD | E24: No | F24: No | G24: Compras por Debajo del Umbral | H24: 5500 | I24: Adjudicado | J24: 43210000 | K24: Equipo informático y accesorios | N24: 0 | P24: Grande | Q24: 45664.542
A25: DIRECCION CENTRAL DEL SERVICIO NACIONAL DE SALUD | B25: Hospital Materno Infantil San Lorenzo de Los Minas | C25: HSLM-DAF-CD-2025-0015 | D25: ADQUISICION DE UTILES MEDICOS, TERMOMETRO ORAL Y CUBRE ZAPATOS. | E25: No | F25: No | G25: Compras por Debajo del Umbral | H25: 228300 | I25: Adjudicado | J25: 42180000 | K25: Productos de examen y control del paciente | L25: Global Multi-Pharma Dominicana THM, SRL | M25: Activo | N25: 1 | O25: 269394 | P25: MiPyme | Q25: 45664.552
A26: DIRECCION CENTRAL DEL SERVICIO NACIONAL DE SALUD | B26: Hospital Materno Infantil San Lorenzo de Los Minas | C26: HSLM-DAF-CD-2025-0017 | D26: CONTROL PARA MAQUINA MEDMAY | E26: No | F26: No | G26: Compras por Debajo del Umbral | H26: 15000 | I26: Adjudicado | J26: 41110000 | K26: Instrumentos de medida, observación y ensayo | L26: Bio Nova, SRL | M26: Activo | N26: 1 | O26: 16605 | P26: Grande | Q26: 45665.459
A27: DIRECCION CENTRAL DEL SERVICIO NACIONAL DE SALUD | B27: Hospital Materno Infantil San Lorenzo de Los Minas | C27: HSLM-DAF-CD-2025-0016 | D27: LLAVES | E27: No | F27: No | G27: Compras por Debajo del Umbral | H27: 78800 | I27: Adjudicado | J27: 40140000 | K27: Distribución de fluidos y gas | L27: Medina N Solutions, SRL | M27: Activo | N27: 1 | O27: 128507 | P27: MiPyme | Q27: 45665.501
A28: DIRECCION CENTRAL DEL SERVICIO NACIONAL DE SALUD | B28: Hospital Materno Infantil San Lorenzo de Los Minas | C28: HSLM-DAF-CM-2025-0006 | D28: REACTIVOS EQUIPO F200 | E28: No | F28: No | G28: Compras Menores | H28: 380000 | I28: Adjudicado | J28: 41110000 | K28: Instrumentos de medida, observación y ensayo | L28: Bello-Lab, SRL | M28: Activo | N28: 2 | O28: 9900 | P28: Mipyme Mujer | Q28: 45667.333
A29: DIRECCION CENTRAL DEL SERVICIO NACIONAL DE SALUD | B29: Hospital Materno Infantil San Lorenzo de Los Minas | C29: HSLM-DAF-CM-2025-0006 | D29: REACTIVOS EQUIPO F200 | E29: No | F29: No | G29: Compras Menores | H29: 380000 | I29: Adjudicado | J29: 41110000 | K29: Instrumentos de medida, observación y ensayo | L29: Lambda Diagnósticos, SRL | M29: Activo | N29: 2 | O29: 362162 | P29: Grande | Q29: 45667.333
A30: DIRECCION CENTRAL DEL SERVICIO NACIONAL DE SALUD | B30: Hospital Materno Infantil San Lorenzo de Los Minas | C30: HSLM-DAF-CD-2025-0018 | D30: ADQUISICION DE ACIDO TRANEXAMICO 500MG/5ML AMPOLLA | E30: No | F30: No | G30: Compras por Debajo del Umbral | H30: 240000 | I30: Adjudicado | J30: 51140000 | K30: Medicamentos para el sistema nervioso central | L30: Ronajus Farmaceutica, SRL | M30: Activo | N30: 1 | O30: 240000 | P30: MiPyme | Q30: 45667.438
A31: DIRECCION CENTRAL DEL SERVICIO NACIONAL DE SALUD | B31: Hospital Materno Infantil San Lorenzo de Los Minas | C31: HSLM-DAF-CD-2025-0019 | D31: ADQUISICION DE INSUMOS PARA SER UTILIZADOS POR EL ALMACEN DE FARMACIA | E31: No | F31: No | G31: Compras por Debajo del Umbral | H31: 160000 | I31: Adjudicado | J31: 51140000 | K31: Medicamentos para el sistema nervioso central | L31: Ronajus Farmaceutica, SRL | M31: Activo | N31: 1 | O31: 150005 | P31: MiPyme | Q31: 45667.458
A32: DIRECCION CENTRAL DEL SERVICIO NACIONAL DE SALUD | B32: Hospital Materno Infantil San Lorenzo de Los Minas | C32: HSLM-DAF-CD-2025-0020 | D32: ADQUISICION DE TIRILLAS DE GLUCOMETRO SMARTEST | E32: No | F32: No | G32: Compras por Debajo del Umbral | H32: 220400 | I32: Abierto | J32: 41110000 | K32: Instrumentos de medida, observación y ensayo | N32: 0 | P32: Grande | Q32: 45667.465
A33: DIRECCION CENTRAL DEL SERVICIO NACIONAL DE SALUD | B33: Hospital Materno Infantil San Lorenzo de Los Minas | C33: HSLM-DAF-CM-2025-0007 | D33: INSUMOS PARA LA MAQUINA BS-380 | E33: No | F33: No | G33: Compras Menores | H33: 927000 | I33: Adjudicado | J33: 41100000 | K33: Equipo de laboratorio y científico | L33: Ciencia Tecnología y Consultas, SRL | M33: Activo | N33: 1 | O33: 616702 | P33: Grande | Q33: 45667.5
A34: DIRECCION CENTRAL DEL SERVICIO NACIONAL DE SALUD | B34: Hospital Materno Infantil San Lorenzo de Los Minas | C34: HSLM-DAF-CD-2025-0022 | D34: ADQUISICION DE GUANTES LATEX DE EXAMEN M | E34: No | F34: No | G34: Compras por Debajo del Umbral | H34: 197500 | I34: Adjudicado | J34: 42130000 | K34: Telas y vestidos médicos | L34: Ventas Diversas Farmaceuticas, SRL | M34: Activo | N34: 1 | O34: 233050 | P34: MiPyme | Q34: 45667.51
A35: DIRECCION CENTRAL DEL SERVICIO NACIONAL DE SALUD | B35: Hospital Materno Infantil San Lorenzo de Los Minas | C35: HSLM-DAF-CD-2025-0023 | D35: ADQUISICION DE CEFTRIAXONA 1G | E35: No | F35: No | G35: Compras por Debajo del Umbral | H35: 180000 | I35: Adjudicado | J35: 51100000 | K35: Medicamentos antiinfecciosos | L35: Socomedi Multisolutions, SRL | M35: Activo | N35: 1 | O35: 180000 | P35: Grande | Q35: 45667.531
A36: DIRECCION CENTRAL DEL SERVICIO NACIONAL DE SALUD | B36: Hospital Materno Infantil San Lorenzo de Los Minas | C36: HSLM-DAF-CD-2025-0021 | D36: ADQUISICION DE AGUA OXIGENADA, CLAMP UMBILICAL, HEMOVAC BRAZALETES PEDIATRICOS CATETER JELCO #24 | E36: No | F36: No | G36: Compras por Debajo del Umbral | H36: 164000 | I36: Adjudicado | J36: 51100000 | K36: Medicamentos antiinfecciosos | L36: A&S Importadora Medicas, SRL | M36: Activo | N36: 1 | O36: 178260 | P36: Mipyme Mujer | Q36: 45667.535
A37: DIRECCION CENTRAL DEL SERVICIO NACIONAL DE SALUD | B37: Hospital Materno Infantil San Lorenzo de Los Minas | C37: HSLM-DAF-CM-2025-0008 | D37: REACTIVOS MIUREX | E37: No | F37: No | G37: Compras Menores | H37: 363500 | I37: Adjudicado | J37: 41110000 | K37: Instrumentos de medida, observación y ensayo | L37: Bio Nuclear, SA | M37: Activo | N37: 1 | O37: 91807 | P37: Grande | Q37: 45667.542
A38: DIRECCION CENTRAL DEL SERVICIO NACIONAL DE SALUD | B38: Hospital Materno Infantil San Lorenzo de Los Minas | C38: HSLM-DAF-CD-2025-0024 | D38: LEVETIRACETAM 500 MG | E38: No | F38: No | G38: Compras por Debajo del Umbral | H38: 185400 | I38: Adjudicado | J38: 51140000 | K38: Medicamentos para el sistema nervioso central | L38: Ameriline Pharmaceutical, SRL | M38: Activo | N38: 1 | O38: 185400 | P38: Grande | Q38: 45667.566
A39: DIRECCION CENTRAL DEL SERVICIO NACIONAL DE SALUD | B39: Hospital Materno Infantil San Lorenzo de Los Minas | C39: HSLM-DAF-CD-2025-0025 | D39: ADQUISICION DE CANULAS DE MAYO Y JERINGAS DE 10 CC | E39: No | F39: No | G39: Compras por Debajo del Umbral | H39: 165000 | I39: Adjudicado | J39: 42220000 | K39: Productos para administración intravenosa y arterial | L39: Lehaim Suministros , SRL | M39: Activo | N39: 1 | O39: 264792 | P39: Grande | Q39: 45667.583
A40: DIRECCION CENTRAL DEL SERVICIO NACIONAL DE SALUD | B40: Hospital Materno Infantil San Lorenzo de Los Minas | C40: HSLM-DAF-CD-2025-0026 | D40: ADQUISICION DE PARACETAMOL 1GR | E40: No | F40: No | G40: Compras por Debajo del Umbral | H40: 86700 | I40: Adjudicado | J40: 51140000 | K40: Medicamentos para el sistema nervioso central | L40: Ameriline Pharmaceutical, SRL | M40: Activo | N40: 1 | O40: 86700 | P40: Grande | Q40: 45667.604
A41: DIRECCION CENTRAL DEL SERVICIO NACIONAL DE SALUD | B41: Hospital Materno Infantil San Lorenzo de Los Minas | C41: HSLM-DAF-CD-2025-0027 | D41: CEFTRIAZONA | E41: No | F41: No | G41: Compras por Debajo del Umbral | H41: 234000 | I41: Cancelado | J41: 51100000 | K41: Medicamentos antiinfecciosos | N41: 0 | P41: Grande | Q41: 45667.604
A42: DIRECCION CENTRAL DEL SERVICIO NACIONAL DE SALUD | B42: Hospital Materno Infantil San Lorenzo de Los Minas | C42: HSLM-DAF-CD-2025-0028 | D42: PCR, ANTI Y AGUA BIDESTILADA | E42: No | F42: No | G42: Compras por Debajo del Umbral | H42: 160350 | I42: Adjudicado | J42: 41110000 | K42: Instrumentos de medida, observación y ensayo | L42: Bello-Lab, SRL | M42: Activo | N42: 1 | O42: 161700 | P42: Mipyme Mujer | Q42: 45667.646
A43: DIRECCION CENTRAL DEL SERVICIO NACIONAL DE SALUD | B43: Hospital Materno Infantil San Lorenzo de Los Minas | C43: HSLM-DAF-CD-2025-0029 | D43: ACIDO ACETILSALICILICO, CLARITROMICINA y DIMENHIDRINATO | E43: No | F43: No | G43: Compras por Debajo del Umbral | H43: 242000 | I43: Adjudicado | J43: 51170000 | K43: Medicamentos que afectan al sistema gastrointestinal | L43: Oficclin Comercial, SRL | M43: Activo | N43: 1 | O43: 271350 | P43: MiPyme | Q43: 45667.674
A44: DIRECCION CENTRAL DEL SERVICIO NACIONAL DE SALUD | B44: Hospital Materno Infantil San Lorenzo de Los Minas | C44: HSLM-DAF-CD-2025-0030 | D44: ADQUISICION DE LAPIZ DE ELECTROCAUTERIO Y BAJANTE NORMAL | E44: No | F44: No | G44: Compras por Debajo del Umbral | H44: 160000 | I44: Adjudicado | J44: 42290000 | K44: Productos quirúrgicos | L44: Lehaim Suministros , SRL | M44: Activo | N44: 1 | O44: 167560 | P44: Grande | Q44: 45667.688
A45: DIRECCION CENTRAL DEL SERVICIO NACIONAL DE SALUD | B45: Hospital Materno Infantil San Lorenzo de Los Minas | C45: HSLM-DAF-CD-2025-0031 | D45: TUBOS, TIPS, PORTA Y TRANSEFER | E45: No | F45: No | G45: Compras por Debajo del Umbral | H45: 146000 | I45: Adjudicado | J45: 41100000 | K45: Equipo de laboratorio y científico | L45: Bello-Lab, SRL | M45: Activo | N45: 1 | O45: 147451 | P45: Mipyme Mujer | Q45: 45670.418
A46: DIRECCION CENTRAL DEL SERVICIO NACIONAL DE SALUD | B46: Hospital Materno Infantil San Lorenzo de Los Minas | C46: HSLM-DAF-CD-2025-0032 | D46: MANZANA , UVA , REFRESCO | E46: No | F46: No | G46: Compras por Debajo del Umbral | H46: 15000 | I46: Adjudicado | J46: 50100000 | K46: Frutos secos | N46: 0 | P46: Grande | Q46: 45670.418
A47: DIRECCION CENTRAL DEL SERVICIO NACIONAL DE SALUD | B47: Hospital Materno Infantil San Lorenzo de Los Minas | C47: HSLM-DAF-CD-2025-0033 | D47: ADQUISICION DE SALBUTAMOL, NOR-CREZIN JARABE, MASCARILLAS, MICROGOTEROS. | E47: No | F47: No | G47: Compras por Debajo del Umbral | H47: 236850 | I47: Adjudicado | J47: 51160000 | K47: Medicamentos que afectan al sistema respiratorio | N47: 0 | P47: Grande | Q47: 45670.486
A48: DIRECCION CENTRAL DEL SERVICIO NACIONAL DE SALUD | B48: Hospital Materno Infantil San Lorenzo de Los Minas | C48: HSLM-DAF-CD-2025-0034 | D48: ADQUISICION DE NIFEDIPINA, METAMIZOL 1G AMP,HOJAS DE BISTURI,ENEMA PEDIATRICOS Y ESPECULOS VAGINALES M | E48: No | F48: No | G48: Compras por Debajo del Umbral | H48: 171150 | I48: Cancelado | J48: 51120000 | K48: Medicamentos cardiovasculares | N48: 0 | P48: Grande | Q48: 45670.576
A49: DIRECCION CENTRAL DEL SERVICIO NACIONAL DE SALUD | B49: Hospital Materno Infantil San Lorenzo de Los Minas | C49: HSLM-DAF-CD-2025-0035 | D49: ADQUISICION DE NIFEDIPINA, METAMIZOL 1G AMP,HOJAS DE BISTURI,ENEMA PEDIATRICOS Y ESPECULOS VAGINALES M | E49: No | F49: No | G49: Compras por Debajo del Umbral | H49: 241150 | I49: Adjudicado | J49: 51120000 | K49: Medicamentos cardiovasculares | L49: G & M Gelmat Comercial, SRL | M49: Activo | N49: 1 | O49: 253279 | P49: Grande | Q49: 45670.624
A50: DIRECCION CENTRAL DEL SERVICIO NACIONAL DE SALUD | B50: Hospital Materno Infantil San Lorenzo de Los Minas | C50: HSLM-DAF-CD-2025-0036 | D50: ADQUISICION DE ACIDO FOLICO 5MG Y BROMURO DE IPATROPIO 0.9 AMPOLLA | E50: No | F50: No | G50: Compras por Debajo del Umbral | H50: 220500 | I50: Adjudicado | J50: 51160000 | K50: Medicamentos que afectan al sistema respiratorio | L50: Smart Supply Medical Dominicana (SMARTMEDOM), SRL | M50: Activo | N50: 1 | O50: 220500 | P50: Grande | Q50: 45670.66
A51: DIRECCION CENTRAL DEL SERVICIO NACIONAL DE SALUD | B51: Hospital Materno Infantil San Lorenzo de Los Minas | C51: HSLM-DAF-CD-2025-0038 | D51: ADQUISICION DE GUANTES DE EXAMEN L | E51: No | F51: No | G51: Compras por Debajo del Umbral | H51: 197500 | I51: Adjudicado | J51: 42130000 | K51: Telas y vestidos médicos | L51: Ventas Diversas Farmaceuticas, SRL | M51: Activo | N51: 1 | O51: 233050 | P51: MiPyme | Q51: 45671.418
A52: DIRECCION CENTRAL DEL SERVICIO NACIONAL DE SALUD | B52: Hospital Materno Infantil San Lorenzo de Los Minas | C52: HSLM-DAF-CD-2025-0039 | D52: ADQUISICION DE MEDICAMENTO PARA USO DEL ALMACEN DE FARMACIA | E52: No | F52: No | G52: Compras por Debajo del Umbral | H52: 240000 | I52: Adjudicado | J52: 51140000 | K52: Medicamentos para el sistema nervioso central | L52: Socomedi Multisolutions, SRL | M52: Activo | N52: 1 | O52: 240000 | P52: Grande | Q52: 45671.418
A53: DIRECCION CENTRAL DEL SERVICIO NACIONAL DE SALUD | B53: Hospital Materno Infantil San Lorenzo de Los Minas | C53: HSLM-DAF-CD-2025-0040 | D53: ADQUISICION VASOS HUMIFICADORES Y ESFIGNOMANOMETRO DIGITAL | E53: No | F53: No | G53: Compras por Debajo del Umbral | H53: 244801 | I53: Adjudicado | J53: 42270000 | K53: Productos de resucitación, anestesia y respiratorio | L53: Cristina Rosario Rosario | M53: Activo | N53: 1 | O53: 272844 | P53: Grande | Q53: 45671.459
A54: DIRECCION CENTRAL DEL SERVICIO NACIONAL DE SALUD | B54: Hospital Materno Infantil San Lorenzo de Los Minas | C54: HSLM-DAF-CD-2025-0041 | D54: ADQUISICION DE GUANTES MEDIUM | E54: No | F54: No | G54: Compras por Debajo del Umbral | H54: 172500 | I54: Cancelado | J54: 42130000 | K54: Telas y vestidos médicos | N54: 0 | P54: Grande | Q54: 45671.459
A55: DIRECCION CENTRAL DEL SERVICIO NACIONAL DE SALUD | B55: Hospital Materno Infantil San Lorenzo de Los Minas | C55: HSLM-DAF-CD-2025-0042 | D55: ADQUISICION DE CATETER JELCO #20. | E55: No | F55: No | G55: Compras por Debajo del Umbral | H55: 141000 | I55: Adjudicado | J55: 42220000 | K55: Productos para administración intravenosa y arterial | N55: 0 | P55: Grande | Q55: 45671.483
A56: DIRECCION CENTRAL DEL SERVICIO NACIONAL DE SALUD | B56: Hospital Materno Infantil San Lorenzo de Los Minas | C56: HSLM-DAF-CD-2025-0043 | D56: ADQUISICION DE GUANTES MEDIUM | E56: No | F56: No | G56: Compras por Debajo del Umbral | H56: 172500 | I56: Adjudicado | J56: 42130000 | K56: Telas y vestidos médicos | L56: Dumas Pharmaceuticals, SRL | M56: Activo | N56: 1 | O56: 203550 | P56: Mipyme Mujer | Q56: 45671.502
A57: DIRECCION CENTRAL DEL SERVICIO NACIONAL DE SALUD | B57: Hospital Materno Infantil San Lorenzo de Los Minas | C57: HSLM-DAF-CD-2025-0044 | D57: MATERIALES IMPRESOS | E57: No | F57: No | G57: Compras por Debajo del Umbral | H57: 91200 | I57: Adjudicado | J57: 82120000 | K57: Servicios de reproducción | N57: 0 | P57: Grande | Q57: 45671.542
A58: DIRECCION CENTRAL DEL SERVICIO NACIONAL DE SALUD | B58: Hospital Materno Infantil San Lorenzo de Los Minas | C58: HSLM-DAF-CD-2025-0046 | D58: ADQUISICION DE AGUJAS RAQUIDEA # 23 Y 25, CATETER # 22 | E58: No | F58: No | G58: Compras por Debajo del Umbral | H58: 205000 | I58: Adjudicado | J58: 42220000 | K58: Productos para administración intravenosa y arterial | N58: 0 | P58: Grande | Q58: 45671.584
A59: DIRECCION CENTRAL DEL SERVICIO NACIONAL DE SALUD | B59: Hospital Materno Infantil San Lorenzo de Los Minas | C59: HSLM-DAF-CD-2025-0047 | D59: ADQUISICION DE GASA COMPRESA Y BAJA LENGUA DE MADERA | E59: No | F59: No | G59: Compras por Debajo del Umbral | H59: 181250 | I59: Adjudicado | J59: 42310000 | K59: Productos para el cuidado de heridas | L59: A&S Importadora Medicas, SRL | M59: Activo | N59: 1 | O59: 182375 | P59: Mipyme Mujer | Q59: 45671.619
A60: DIRECCION CENTRAL DEL SERVICIO NACIONAL DE SALUD | B60: Hospital Materno Infantil San Lorenzo de Los Minas | C60: HSLM-DAF-CD-2025-0045 | D60: REACTIVOS DEL GASOMETRO ABL 835 01-25 | E60: No | F60: No | G60: Compras por Debajo del Umbral | H60: 76000 | I60: Adjudicado | J60: 41110000 | K60: Instrumentos de medida, observación y ensayo | L60: Q&Q Medical RD, SRL | M60: Activo | N60: 1 | O60: 69561 | P60: Grande | Q60: 45671.625
A61: DIRECCION CENTRAL DEL SERVICIO NACIONAL DE SALUD | B61: Hospital Materno Infantil San Lorenzo de Los Minas | C61: HSLM-DAF-CD-2025-0048 | D61: ADQUISICION DE ALUCAL , PONTI OFTENO ,CATETER EPIDURAL | E61: No | F61: No | G61: Compras por Debajo del Umbral | H61: 200200 | I61: Cancelado | J61: 51140000 | K61: Medicamentos para el sistema nervioso central | N61: 0 | P61: Grande | Q61: 45672.46
A62: DIRECCION CENTRAL DEL SERVICIO NACIONAL DE SALUD | B62: Hospital Materno Infantil San Lorenzo de Los Minas | C62: HSLM-DAF-CD-2025-0050 | D62: ADQUISICION DE MANTAS TERMICAS | E62: No | F62: No | G62: Compras por Debajo del Umbral | H62: 210000 | I62: Adjudicado | J62: 42140000 | K62: Suministros, productos de tratamiento y cuidado del enfermo | L62: Jean Carlos Basulto Lopez | M62: Activo | N62: 1 | O62: 247998 | P62: Grande | Q62: 45672.514
A63: DIRECCION CENTRAL DEL SERVICIO NACIONAL DE SALUD | B63: Hospital Materno Infantil San Lorenzo de Los Minas | C63: HSLM-DAF-CD-2025-0049 | D63: ADQUISICION DE CATETER DE SUCCION CERRADO 8FR | E63: No | F63: No | G63: Compras por Debajo del Umbral | H63: 59250 | I63: Adjudicado | J63: 42140000 | K63: Suministros, productos de tratamiento y cuidado del enfermo | L63: Destreza Comercial, SRL | M63: Activo | N63: 1 | O63: 69915 | P63: Grande | Q63: 45672.521
A64: DIRECCION CENTRAL DEL SERVICIO NACIONAL DE SALUD | B64: Hospital Materno Infantil San Lorenzo de Los Minas | C64: HSLM-DAF-CD-2025-0052 | D64: ADQUISICION DE MATERIAL DE USO MEDICO | E64: No | F64: No | G64: Compras por Debajo del Umbral | H64: 59400 | I64: Adjudicado | J64: 42140000 | K64: Suministros, productos de tratamiento y cuidado del enfermo | L64: Ventas Diversas Farmaceuticas, SRL | M64: Activo | N64: 1 | O64: 70092 | P64: MiPyme | Q64: 45672.528
A65: DIRECCION CENTRAL DEL SERVICIO NACIONAL DE SALUD | B65: Hospital Materno Infantil San Lorenzo de Los Minas | C65: HSLM-DAF-CD-2025-0051 | D65: ADQUISICION DE ALUCAL , PONTI OFTENO ,CATETER EPIDURAL | E65: No | F65: No | G65: Compras por Debajo del Umbral | H65: 208850 | I65: Adjudicado | J65: 51140000 | K65: Medicamentos para el sistema nervioso central | L65: Dumas Pharmaceuticals, SRL | M65: Activo | N65: 1 | O65: 236948 | P65: Mipyme Mujer | Q65: 45672.542
A66: DIRECCION CENTRAL DEL SERVICIO NACIONAL DE SALUD | B66: Hospital Materno Infantil San Lorenzo de Los Minas | C66: HSLM-DAF-CD-2025-0054 | D66: ADQUISICION DE AGUA BIDESTILADA, ALGODÓN, SELLO BAJO AGUA Y LANCETAS | E66: No | F66: No | G66: Compras por Debajo del Umbral | H66: 185700 | I66: Adjudicado | J66: 51100000 | K66: Medicamentos antiinfecciosos | L66: Dumas Pharmaceuticals, SRL | M66: Activo | N66: 1 | O66: 209354 | P66: Mipyme Mujer | Q66: 45673.418
A67: DIRECCION CENTRAL DEL SERVICIO NACIONAL DE SALUD | B67: Hospital Materno Infantil San Lorenzo de Los Minas | C67: HSLM-DAF-CD-2025-0055 | D67: ADQUISICION DE GEL ANTIBACTERIAL | E67: No | F67: No | G67: Compras por Debajo del Umbral | H67: 110000 | I67: Adjudicado | J67: 51100000 | K67: Medicamentos antiinfecciosos | L67: Dumas Pharmaceuticals, SRL | M67: Activo | N67: 1 | O67: 110000 | P67: Mipyme Mujer | Q67: 45673.459
A68: DIRECCION CENTRAL DEL SERVICIO NACIONAL DE SALUD | B68: Hospital Materno Infantil San Lorenzo de Los Minas | C68: HSLM-DAF-CD-2025-0056 | D68: CLORURO DE SODIO 0.9% | E68: No | F68: No | G68: Compras por Debajo del Umbral | H68: 54720 | I68: Adjudicado | J68: 51190000 | K68: Agentes que afectan el agua y los electrolitos | L68: Farach, SA | M68: Activo | N68: 1 | O68: 54720 | P68: Grande | Q68: 45673.459
A69: DIRECCION CENTRAL DEL SERVICIO NACIONAL DE SALUD | B69: Hospital Materno Infantil San Lorenzo de Los Minas | C69: HSLM-DAF-CD-2025-0053 | D69: SOLUCION MIXTA 0.33% | E69: No | F69: No | G69: Compras por Debajo del Umbral | H69: 31250 | I69: Adjudicado | J69: 51190000 | K69: Agentes que afectan el agua y los electrolitos | L69: Farach, SA | M69: Activo | N69: 1 | O69: 31250 | P69: Grande | Q69: 45673.459
A70: DIRECCION CENTRAL DEL SERVICIO NACIONAL DE SALUD | B70: Hospital Materno Infantil San Lorenzo de Los Minas | C70: HSLM-DAF-CD-2025-0057 | D70: REACTIVOS MEDMAY | E70: No | F70: No | G70: Compras por Debajo del Umbral | H70: 150000 | I70: Adjudicado | J70: 41110000 | K70: Instrumentos de medida, observación y ensayo | L70: Bio Nova, SRL | M70: Activo | N70: 1 | O70: 150060 | P70: Grande | Q70: 45673.501
A71: DIRECCION CENTRAL DEL SERVICIO NACIONAL DE SALUD | B71: Hospital Materno Infantil San Lorenzo de Los Minas | C71: HSLM-DAF-CD-2025-0058 | D71: PRODUCTOS DE LIMPIEZA | E71: No | F71: No | G71: Compras por Debajo del Umbral | H71: 145500 | I71: Adjudicado | J71: 47130000 | K71: Suministros de aseo y limpieza | L71: Abrias Novo Group SRL | M71: Activo | N71: 1 | O71: 160215 | P71: Mipyme Mujer | Q71: 45673.521
A72: DIRECCION CENTRAL DEL SERVICIO NACIONAL DE SALUD | B72: Hospital Materno Infantil San Lorenzo de Los Minas | C72: HSLM-DAF-CM-2025-0011 | D72: SOFTWARE DETECTOR DIGITAL DE RAYOS X | E72: No | F72: No | G72: Compras Menores | H72: 1800000 | I72: Adjudicado | J72: 41110000 | K72: Instrumentos de medida, observación y ensayo | N72: 0 | P72: Grande | Q72: 45673.542
A73: DIRECCION CENTRAL DEL SERVICIO NACIONAL DE SALUD | B73: Hospital Materno Infantil San Lorenzo de Los Minas | C73: HSLM-DAF-CM-2025-0009 | D73: MODULO GENERADOR DE RAYOS X PROTATIL DIRIGIDO A MIPYMES. | E73: Sí | F73: No | G73: Compras Menores | H73: 1850000 | I73: Adjudicado | J73: 41110000 | K73: Instrumentos de medida, observación y ensayo | N73: 0 | P73: Grande | Q73: 45673.542
A74: DIRECCION CENTRAL DEL SERVICIO NACIONAL DE SALUD | B74: Hospital Materno Infantil San Lorenzo de Los Minas | C74: HSLM-DAF-CD-2025-0059 | D74: UTILES DE LIMPIEZA | E74: No | F74: No | G74: Compras por Debajo del Umbral | H74: 154230 | I74: Adjudicado | J74: 47130000 | K74: Suministros de aseo y limpieza | L74: Abrias Novo Group SRL | M74: Activo | N74: 1 | O74: 184344 | P74: Mipyme Mujer | Q74: 45673.627
A75: DIRECCION CENTRAL DEL SERVICIO NACIONAL DE SALUD | B75: Hospital Materno Infantil San Lorenzo de Los Minas | C75: HSLM-DAF-CD-2025-0060 | D75: ADQUISICION DE GAS LICUADO DE PETROLEO | E75: No | F75: No | G75: Compras por Debajo del Umbral | H75: 238680 | I75: Adjudicado | J75: 15110000 | K75: Combustibles gaseosos y aditivos | N75: 0 | P75: Grande | Q75: 45674.431
A76: DIRECCION CENTRAL DEL SERVICIO NACIONAL DE SALUD | B76: Hospital Materno Infantil San Lorenzo de Los Minas | C76: HSLM-DAF-CD-2025-0062 | D76: CIRCUITO DE VENTILACION -ADULTO | E76: No | F76: No | G76: Compras por Debajo del Umbral | H76: 53000 | I76: Adjudicado | J76: 42270000 | K76: Productos de resucitación, anestesia y respiratorio | L76: A&S Importadora Medicas, SRL | M76: Activo | N76: 1 | O76: 62540 | P76: Mipyme Mujer | Q76: 45674.46
A77: DIRECCION CENTRAL DEL SERVICIO NACIONAL DE SALUD | B77: Hospital Materno Infantil San Lorenzo de Los Minas | C77: HSLM-DAF-CD-2025-0061 | D77: Servicio de Transporte de medicamentos periodo enero-junio 2025 | E77: No | F77: No | G77: Compras por Debajo del Umbral | H77: 128000 | I77: Adjudicado | J77: 78110000 | K77: Transporte de pasajeros | N77: 0 | P77: Grande | Q77: 45674.469
A78: DIRECCION CENTRAL DEL SERVICIO NACIONAL DE SALUD | B78: Hospital Materno Infantil San Lorenzo de Los Minas | C78: HSLM-DAF-CD-2025-0063 | D78: COMPRA DE COMPUTADOR PARA USO DE ESTE HOSPITAL | E78: No | F78: No | G78: Compras por Debajo del Umbral | H78: 48500 | I78: Adjudicado | J78: 43210000 | K78: Equipo informático y accesorios | L78: Súper Laptop Browsing, SRL | M78: Activo | N78: 1 | O78: 57230 | P78: MiPyme | Q78: 45674.559
A79: DIRECCION CENTRAL DEL SERVICIO NACIONAL DE SALUD | B79: Hospital Materno Infantil San Lorenzo de Los Minas | C79: HSLM-DAF-CD-2025-0065 | D79: CLORURO DE SODIO 0.9% | E79: No | F79: No | G79: Compras por Debajo del Umbral | H79: 179280 | I79: Adjudicado | J79: 51190000 | K79: Agentes que afectan el agua y los electrolitos | L79: Farach, SA | M79: Activo | N79: 1 | O79: 179280 | P79: Grande | Q79: 45684.419
A80: DIRECCION CENTRAL DEL SERVICIO NACIONAL DE SALUD | B80: Hospital Materno Infantil San Lorenzo de Los Minas | C80: HSLM-DAF-CD-2025-0066 | D80: ADQUISICION DE INSUMOS DE FARMACIA | E80: Sí | F80: No | G80: Compras por Debajo del Umbral | H80: 112600 | I80: Adjudicado | J80: 51190000 | K80: Agentes que afectan el agua y los electrolitos | N80: 0 | P80: Grande | Q80: 45684.427
A81: DIRECCION CENTRAL DEL SERVICIO NACIONAL DE SALUD | B81: Hospital Materno Infantil San Lorenzo de Los Minas | C81: HSLM-DAF-CM-2025-0012 | D81: VEGETALES | E81: No | F81: No | G81: Compras Menores | H81: 355720 | I81: Adjudicado | J81: 50100000 | K81: Frutos secos | N81: 0 | P81: Grande | Q81: 45684.501
A82: DIRECCION CENTRAL DEL SERVICIO NACIONAL DE SALUD | B82: Hospital Materno Infantil San Lorenzo de Los Minas | C82: HSLM-DAF-CM-2025-0014 | D82: CARNES | E82: No | F82: No | G82: Compras Menores | H82: 848500 | I82: Adjudicado | J82: 50110000 | K82: Productos de carne y aves de corral | L82: AGROGLOBAL EXPORT E IMPORT, SRL | M82: Activo | N82: 1 | O82: 220000 | P82: MiPyme | Q82: 45684.501
A83: DIRECCION CENTRAL DEL SERVICIO NACIONAL DE SALUD | B83: Hospital Materno Infantil San Lorenzo de Los Minas | C83: HSLM-DAF-CM-2025-0013 | D83: SERVICIO DE MANTENIMIENTO REPARACION Y MODIFICACION DEL MONTACARGAS DEL ARA DE CIRUGIA Y SALA DE PARTOS. | E83: No | F83: No | G83: Compras Menores | H83: 600000 | I83: Adjudicado | J83: 72100000 | K83: Servicios de mantenimiento y reparaciones de construcciones e instalaciones | N83: 0 | P83: Grande | Q83: 45684.504
A84: DIRECCION CENTRAL DEL SERVICIO NACIONAL DE SALUD | B84: Hospital Materno Infantil San Lorenzo de Los Minas | C84: HSLM-DAF-CD-2025-0067 | D84: ADQUISICION DE PAPEL PARA ELECTROCARDIOGRAMA | E84: No | F84: No | G84: Compras por Debajo del Umbral | H84: 162800 | I84: Adjudicado | J84: 42180000 | K84: Productos de examen y control del paciente | L84: Osiris & Co, SA | M84: Activo | N84: 1 | O84: 192276 | P84: Grande | Q84: 45684.507
A85: DIRECCION CENTRAL DEL SERVICIO NACIONAL DE SALUD | B85: Hospital Materno Infantil San Lorenzo de Los Minas | C85: HSLM-DAF-CD-2025-0069 | D85: COMPRA DE MATERIALES PARA USO DEL ALMACEN DE FARMACIA | E85: No | F85: No | G85: Compras por Debajo del Umbral | H85: 192000 | I85: Adjudicado | J85: 42220000 | K85: Productos para administración intravenosa y arterial | L85: G & M Gelmat Comercial, SRL | M85: Activo | N85: 1 | O85: 226560 | P85: Grande | Q85: 45684.528
A86: DIRECCION CENTRAL DEL SERVICIO NACIONAL DE SALUD | B86: Hospital Materno Infantil San Lorenzo de Los Minas | C86: HSLM-DAF-CD-2025-0070 | D86: COMPRA DE GASA TIPO ALMOHADA | E86: Sí | F86: No | G86: Compras por Debajo del Umbral | H86: 220000 | I86: Adjudicado | J86: 42310000 | K86: Productos para el cuidado de heridas | L86: Oficclin Comercial, SRL | M86: Activo | N86: 1 | O86: 229800 | P86: MiPyme | Q86: 45684.542
A87: DIRECCION CENTRAL DEL SERVICIO NACIONAL DE SALUD | B87: Hospital Materno Infantil San Lorenzo de Los Minas | C87: HSLM-DAF-CD-2025-0068 | D87: EMBUTIDOS | E87: No | F87: No | G87: Compras por Debajo del Umbral | H87: 142020 | I87: Adjudicado | J87: 50130000 | K87: Productos lácteos y huevos | L87: Margayu, SRL | M87: Activo | N87: 1 | O87: 264630 | P87: Grande | Q87: 45684.544
A88: DIRECCION CENTRAL DEL SERVICIO NACIONAL DE SALUD | B88: Hospital Materno Infantil San Lorenzo de Los Minas | C88: HSLM-DAF-CD-2025-0064 | D88: SERVICIO DE LABPLUS 01-2025 | E88: No | F88: No | G88: Compras por Debajo del Umbral | H88: 150000 | I88: Adjudicado | J88: 81110000 | K88: Servicios informáticos | L88: Bio Nuclear, SA | M88: Modificado | N88: 1 | O88: 150000 | P88: Grande | Q88: 45684.556
A89: DIRECCION CENTRAL DEL SERVICIO NACIONAL DE SALUD | B89: Hospital Materno Infantil San Lorenzo de Los Minas | C89: HSLM-DAF-CD-2025-0072 | D89: SOLICITUD DE COMPRA DE CARROS DE CARGA | E89: Sí | F89: No | G89: Compras por Debajo del Umbral | H89: 91000 | I89: Adjudicado | J89: 24100000 | K89: Maquinaria y equipo para manejo de materiales | L89: Soluciones de Servicios y Técnicas Altadis, SRL | M89: Activo | N89: 1 | O89: 107609 | P89: MiPyme | Q89: 45684.667
A90: DIRECCION CENTRAL DEL SERVICIO NACIONAL DE SALUD | B90: Hospital Materno Infantil San Lorenzo de Los Minas | C90: HSLM-DAF-CM-2025-0015 | D90: ADQUISICION DE ULTRASONIDO | E90: No | F90: No | G90: Compras Menores | H90: 490000 | I90: Evaluación | J90: 42200000 | K90: Productos de hacer imágenes diagnósticas médicas y de medicina nuclear | N90: 0 | P90: Grande | Q90: 45685.501
A91: DIRECCION CENTRAL DEL SERVICIO NACIONAL DE SALUD | B91: Hospital Materno Infantil San Lorenzo de Los Minas | C91: HSLM-DAF-CD-2025-0073 | D91: ADQUISICION DE LAPTOS | E91: Sí | F91: No | G91: Compras por Debajo del Umbral | H91: 102000 | I91: Adjudicado | J91: 43210000 | K91: Equipo informático y accesorios | N91: 0 | P91: Grande | Q91: 45685.503
A92: DIRECCION CENTRAL DEL SERVICIO NACIONAL DE SALUD | B92: Hospital Materno Infantil San Lorenzo de Los Minas | C92: HSLM-DAF-CM-2025-0016 | D92: DESPENSA | E92: No | F92: No | G92: Compras Menores | H92: 687350 | I92: Evaluación | J92: 50190000 | K92: Alimentos preparados y conservados | N92: 0 | P92: Grande | Q92: 45685.542
A93: DIRECCION CENTRAL DEL SERVICIO NACIONAL DE SALUD | B93: Hospital Materno Infantil San Lorenzo de Los Minas | C93: HSLM-DAF-CD-2025-0074 | D93: MORFINA 0.1 MG | E93: No | F93: No | G93: Compras por Debajo del Umbral | H93: 92000 | I93: Adjudicado | J93: 51140000 | K93: Medicamentos para el sistema nervioso central | L93: Gerenfar, S.R.L. | M93: Activo | N93: 1 | O93: 92000 | P93: Grande | Q93: 45685.668
A94: DIRECCION CENTRAL DEL SERVICIO NACIONAL DE SALUD | B94: Hospital Materno Infantil San Lorenzo de Los Minas | C94: HSLM-DAF-CD-2025-0075 | D94: SOLUCION SALINO 0.9% 100ML | E94: No | F94: No | G94: Compras por Debajo del Umbral | H94: 180000 | I94: Adjudicado | J94: 51190000 | K94: Agentes que afectan el agua y los electrolitos | L94: Farach, SA | M94: Activo | N94: 1 | O94: 180000 | P94: Grande | Q94: 45686.479
A95: DIRECCION CENTRAL DEL SERVICIO NACIONAL DE SALUD | B95: Hospital Materno Infantil San Lorenzo de Los Minas | C95: HSLM-DAF-CM-2025-0018 | D95: SERV. DE MANT. Y REPARACION DE MUROS Y PASILLOS DEL AREA DE PARTO 2DO NIVEL | E95: No | F95: No | G95: Compras Menores | H95: 950010.65 | I95: Abierto | J95: 72100000 | K95: Servicios de mantenimiento y reparaciones de construcciones e instalaciones | N95: 0 | P95: Grande | Q95: 45686.585
A96: DIRECCION CENTRAL DEL SERVICIO NACIONAL DE SALUD | B96: Hospital Materno Infantil San Lorenzo de Los Minas | C96: HSLM-DAF-CM-2025-0017 | D96: SERV. DE MANT. Y REPARACION DE PISOS DEL AREA DE PARTO 2DO NIVEL | E96: No | F96: No | G96: Compras Menores | H96: 1599999.1 | I96: Abierto | J96: 72100000 | K96: Servicios de mantenimiento y reparaciones de construcciones e instalaciones | N96: 0 | P96: Grande | Q96: 45686.585
A97: DIRECCION CENTRAL DEL SERVICIO NACIONAL DE SALUD | B97: Hospital Materno Infantil San Lorenzo de Los Minas | C97: HSLM-DAF-CM-2025-0019 | D97: ADQUISICION DE PAN SEGÚN DESCIPCION. | E97: No | F97: No | G97: Compras Menores | H97: 614250 | I97: Evaluación | J97: 50180000 | K97: Productos de panadería | N97: 0 | P97: Grande | Q97: 45686.646
A98: DIRECCION CENTRAL DEL SERVICIO NACIONAL DE SALUD | B98: Hospital Materno Infantil San Lorenzo de Los Minas | C98: HSLM-DAF-CD-2025-0077 | D98: ADQUISICION DE MATERIALES DE USO MEDICO | E98: No | F98: No | G98: Compras por Debajo del Umbral | H98: 218000 | I98: Adjudicado | J98: 42270000 | K98: Productos de resucitación, anestesia y respiratorio | L98: Destreza Comercial, SRL | M98: Activo | N98: 1 | O98: 257240 | P98: Grande | Q98: 45686.649
A99: DIRECCION CENTRAL DEL SERVICIO NACIONAL DE SALUD | B99: Hospital Materno Infantil San Lorenzo de Los Minas | C99: HSLM-DAF-CD-2025-0079 | D99: ADQUISICION DE ENFAMIL NEURO PRO PREMATURE | E99: No | F99: No | G99: Compras por Debajo del Umbral | H99: 19200 | I99: Adjudicado | J99: 50130000 | K99: Productos lácteos y huevos | L99: Livao Farmacéutica, SRL | M99: Activo | N99: 1 | O99: 19520 | P99: MiPyme | Q99: 45686.668
A100: DIRECCION CENTRAL DEL SERVICIO NACIONAL DE SALUD | B100: Hospital Materno Infantil San Lorenzo de Los Minas | C100: HSLM-DAF-CD-2025-0078 | D100: GUANTES DESECHABLES M | E100: Sí | F100: No | G100: Compras por Debajo del Umbral | H100: 195000 | I100: Adjudicado | J100: 42130000 | K100: Telas y vestidos médicos | L100: Ventas Diversas Farmaceuticas, SRL | M100: Activo | N100: 1 | O100: 233050 | P100: MiPyme | Q100: 45686.681
A101: DIRECCION CENTRAL DEL SERVICIO NACIONAL DE SALUD | B101: Hospital Materno Infantil San Lorenzo de Los Minas | C101: HSLM-DAF-CD-2025-0080 | D101: ADQUISICION DE AVAGARD | E101: Sí | F101: No | G101: Compras por Debajo del Umbral | H101: 240000 | I101: Adjudicado | J101: 51100000 | K101: Medicamentos antiinfecciosos | L101: Dumas Pharmaceuticals, SRL | M101: Activo | N101: 1 | O101: 268000 | P101: Mipyme Mujer | Q101: 45687.438
...

Sheet Hoja1

Sheet CONS. FUENTES FINAN
A1: Form. No.6 SRS
A3: Servicio Nacional de Salud
A4: Dirección de Fizcalización
A5: Consolidado de Ingresos y Gastos por Fuente de Financiamiento
A6: HOSPITAL MATERNO INFANTIL SAN LORENZO DE LOS MINA
A7: ENERO 2025
C8: Ingresos Generales:
E9: 1.- Balance Inicial / Fuente:
E10: Anticipo Financiero | G10: 0 | H10: Otros Aportes | M10: Contraseña: 0001
E11: Transferencias Corrientes | G11: 0
E12: Venta de Servicios | G12: 2244994.1
E13: 2.- Ingresos por Fuente / Cuenta
E14: Anticipo Financiero | H14: Otros Aportes | J14: =+'INGRESOS SEGUN ORIGEN'!E8 -> 15763473 | M14: OBJETAL | N14: FR | O14: VS
E15: Transferencias Corrientes | H15: Aportes Nomina SNS | J15: =+'INGRESOS SEGUN ORIGEN'!E7 -> 84553322 | M15: 2.1 | N15: =G26 -> 65091180 | O15: =H26 -> 0
E16: Venta de Servicios | G16: =+'INGRESOS SEGUN ORIGEN'!E26+'INGRESOS SEGUN ORIGEN'!E31 -> 6032481.2 | M16: 2.2 | N16: =G87 -> 0 | O16: =H87 -> 2733844.3
H17: TOTAL INGRESOS RDS | J17: =+G10+G11+G12+J10+G14+G15+G16+J14+J15 -> 1.0859427e+08 | M17: 2.3 | N17: ='CONS. FUENTES FINAN'!G212 -> 4970601.2 | O17: ='CONS. FUENTES FINAN'!H212 -> 3062630.7
M18: 2.4 | N18: =G330 -> 0 | O18: =H330 -> 136966.7
M19: 2.6 | N19: =G336 -> 0 | O19: =H336 -> 887994.84
M20: 2.7 | N20: ='CONS. FUENTES FINAN'!G463 -> 0 | O20: ='CONS. FUENTES FINAN'!H463 -> 0
A21: 1 | F21: 2 | G21: 3 | J21: 4 | K21: 5
A22: Código Presupuestario | F22: Descripción Gasto por Cuenta | G22: Distribución del Gasto por Fuente de Financiamiento | J22: TOTAL | K22: %
A23: Tipo | B23: Objeto | C23: Cuenta | D23: Sub-Cuenta | E23: Auxiliar | G23: Fondo 100 | H23: Venta de Servicios/ Otros Aportes | I23: Aportes Nomina SNS
A25: 2 | F25: Gastos | G25: =+G26+G87+G212+G330+G336+G463 -> 70061781 | H25: =+H26+H87+H212+H330+H336+H463 -> 6821436.5 | I25: =+I26+I87+I212+I330+I336+I463 -> 0 | J25: =SUM(G25:I25) -> 76883218 | K25: =+K26+K87+K212+K330+K336+K463 -> 1
A26: 2 | B26: 1 | F26: Servicios Personales | G26: =+G27+G51+G64+G71+G78 -> 65091180 | H26: =+H27+H51+H64+H71+H78 -> 0 | I26: =+I27+I51+I64+I71+I78 -> 0 | J26: =SUM(G26:I26) -> 65091180 | K26: =J26/$J$25 -> 0.84662404
A27: 2 | B27: 1 | C27: 1 | F27: Remuneraciones | G27: =+G28+G35+G42+G44+G46 -> 53640339 | H27: =+H28+H35+H42+H44+H46 -> 0 | I27: =+I28+I35+I42+I44+I46 -> 0 | J27: =SUM(G27:I27) -> 53640339 | K27: =J27/$J$25 -> 0.69768592
A28: 2 | B28: 1 | C28: 1 | D28: 1 | F28: Remuneraciones al personal fijo | G28: =SUM(G29:G34) -> 52666808 | H28: =SUM(H29:H34) -> 0 | I28: =SUM(I29:I34) -> 0 | J28: =SUM(G28:I28) -> 52666808 | K28: =J28/$J$25 -> 0.68502346
A29: 2 | B29: 1 | C29: 1 | D29: 1 | E29: 01 | F29: Sueldos a empleados fijos | G29: ='CUENTA T FONDO 100'!A288 -> 52666808 | H29: ='CUENTA T VS'!A81 -> 0 | I29: ='CUENTA T NOMINA SNS'!A58 -> 0 | J29: =SUM(G29:I29) -> 52666808 | K29: =J29/$J$25 -> 0.68502346
A30: 2 | B30: 1 | C30: 1 | D30: 1 | E30: 02 | F30: Sueldos a médicos | G30: ='CUENTA T FONDO 100'!B288 -> 0 | H30: ='CUENTA T VS'!B81 -> 0 | I30: ='CUENTA T NOMINA SNS'!B58 -> 0 | J30: =SUM(G30:I30) -> 0 | K30: =J30/$J$25 -> 0
A31: 2 | B31: 1 | C31: 1 | D31: 1 | E31: 03 | F31: Ascensos a militares | G31: ='CUENTA T FONDO 100'!C288 -> 0 | H31: ='CUENTA T VS'!C81 -> 0 | I31: ='CUENTA T NOMINA SNS'!C58 -> 0 | J31: =SUM(G31:I31) -> 0 | K31: =J31/$J$25 -> 0
A32: 2 | B32: 1 | C32: 1 | D32: 1 | E32: 04 | F32: Nuevas plazas maestros | G32: ='CUENTA T FONDO 100'!D288 -> 0 | H32: ='CUENTA T VS'!D81 -> 0 | I32: ='CUENTA T NOMINA SNS'!D58 -> 0 | J32: =SUM(G32:I32) -> 0 | K32: =J32/$J$25 -> 0
A33: 2 | B33: 1 | C33: 1 | D33: 1 | E33: 05 | F33: Incentivos y escalafón | G33: ='CUENTA T FONDO 100'!E288 -> 0 | H33: ='CUENTA T VS'!E81 -> 0 | I33: ='CUENTA T NOMINA SNS'!E58 -> 0 | J33: =SUM(G33:I33) -> 0 | K33: =J33/$J$25 -> 0
A34: 2 | B34: 1 | C34: 1 | D34: 1 | E34: 06 | F34: Nuevas plazas a médicos | G34: ='CUENTA T FONDO 100'!F288 -> 0 | H34: ='CUENTA T VS'!F81 -> 0 | I34: ='CUENTA T NOMINA SNS'!F58 -> 0 | J34: =SUM(G34:I34) -> 0 | K34: =J34/$J$25 -> 0
A35: 2 | B35: 1 | C35: 1 | D35: 2 | F35: Remuneraciones al personal con carácter transitorio | G35: =SUM(G36:G41) -> 973531.03 | H35: =SUM(H36:H41) -> 0 | I35: =SUM(I36:I41) -> 0 | J35: =SUM(G35:I35) -> 973531.03
A36: 2 | B36: 1 | C36: 1 | D36: 2 | E36: 03 | F36: Suplencias | G36: ='CUENTA T FONDO 100'!G288 -> 0 | H36: ='CUENTA T VS'!G81 -> 0 | I36: ='CUENTA T NOMINA SNS'!G58 -> 0 | J36: =SUM(G36:I36) -> 0 | K36: =J36/$J$25 -> 0
A37: 2 | B37: 1 | C37: 1 | D37: 2 | E37: 05 | F37: Sueldo al personal nominal en período probatorio | G37: ='CUENTA T FONDO 100'!H288 -> 0 | H37: ='CUENTA T VS'!H81 -> 0 | I37: ='CUENTA T NOMINA SNS'!H58 -> 0 | J37: =SUM(G37:I37) -> 0 | K37: =J37/$J$25 -> 0
A38: 2 | B38: 1 | C38: 1 | D38: 2 | E38: 06 | F38: Jornales | G38: ='CUENTA T FONDO 100'!I288 -> 0 | H38: ='CUENTA T VS'!I81 -> 0 | I38: ='CUENTA T NOMINA SNS'!I58 -> 0 | J38: =SUM(G38:I38) -> 0 | K38: =J38/$J$25 -> 0
A39: 2 | B39: 1 | C39: 1 | D39: 2 | E39: 08 | F39: Empleados temporales | G39: ='CUENTA T FONDO 100'!J288 -> 973531.03 | H39: ='CUENTA T VS'!J81 -> 0 | I39: ='CUENTA T NOMINA SNS'!J58 -> 0 | J39: =SUM(G39:I39) -> 973531.03 | K39: =J39/$J$25 -> 0.012662465
A40: 2 | B40: 1 | C40: 1 | D40: 2 | E40: 09 | F40: Personal de carácter eventual | G40: ='CUENTA T FONDO 100'!K288 -> 0 | H40: ='CUENTA T VS'!K81 -> 0 | I40: ='CUENTA T NOMINA SNS'!K58 -> 0 | J40: =SUM(G40:I40) -> 0 | K40: =J40/$J$25 -> 0
A41: 2 | B41: 1 | C41: 1 | D41: 2 | E41: 11 | F41: Interinato | G41: ='CUENTA T FONDO 100'!L288 -> 0 | H41: ='CUENTA T VS'!L81 -> 0 | I41: ='CUENTA T NOMINA SNS'!L58 -> 0 | J41: =SUM(G41:I41) -> 0 | K41: =J41/$J$25 -> 0
A42: 2 | B42: 1 | C42: 1 | D42: 3 | F42: Sueldos al personal fijo en trámite de pensiones | G42: =SUM(G43) -> 0 | H42: =SUM(H43) -> 0 | I42: =SUM(I43) -> 0 | J42: =SUM(G42:I42) -> 0
A43: 2 | B43: 1 | C43: 1 | D43: 3 | E43: 01 | F43: Sueldos al personal fijo en trámite de pensiones | G43: ='CUENTA T FONDO 100'!M288 -> 0 | H43: ='CUENTA T VS'!M81 -> 0 | I43: ='CUENTA T NOMINA SNS'!M58 -> 0 | J43: =SUM(G43:I43) -> 0 | K43: =J43/$J$25 -> 0
A44: 2 | B44: 1 | C44: 1 | D44: 4 | F44: Sueldo anual no. 13 | G44: =SUM(G45) -> 0 | H44: =SUM(H45) -> 0 | I44: =SUM(I45) -> 0 | J44: =SUM(G44:I44) -> 0
A45: 2 | B45: 1 | C45: 1 | D45: 4 | E45: 01 | F45: Sueldo anual no. 13 | G45: ='CUENTA T FONDO 100'!N288 -> 0 | H45: ='CUENTA T VS'!N81 -> 0 | I45: ='CUENTA T NOMINA SNS'!N58 -> 0 | J45: =SUM(G45:I45) -> 0 | K45: =J45/$J$25 -> 0
A46: 2 | B46: 1 | C46: 1 | D46: 5 | F46: Prestaciones económinas | G46: =SUM(G47:G50) -> 0 | H46: =SUM(H47:H50) -> 0 | I46: =SUM(I47:I50) -> 0 | J46: =SUM(G46:I46) -> 0
A47: 2 | B47: 1 | C47: 1 | D47: 5 | E47: 01 | F47: Prestaciones económinas | G47: ='CUENTA T FONDO 100'!O288 -> 0 | H47: ='CUENTA T VS'!O81 -> 0 | I47: ='CUENTA T NOMINA SNS'!O58 -> 0 | J47: =SUM(G47:I47) -> 0 | K47: =J47/$J$25 -> 0
A48: 2 | B48: 1 | C48: 1 | D48: 5 | E48: 02 | F48: Pago de porcentaje por desvinculación de cargo | G48: ='CUENTA T FONDO 100'!P288 -> 0 | H48: ='CUENTA T VS'!P81 -> 0 | I48: ='CUENTA T NOMINA SNS'!P58 -> 0 | J48: =SUM(G48:I48) -> 0 | K48: =J48/$J$25 -> 0
A49: 2 | B49: 1 | C49: 1 | D49: 5 | E49: 03 | F49: Prestación laboral por desvinculación | G49: ='CUENTA T FONDO 100'!Q288 -> 0 | H49: ='CUENTA T VS'!Q81 -> 0 | I49: ='CUENTA T NOMINA SNS'!Q58 -> 0 | J49: =SUM(G49:I49) -> 0 | K49: =J49/$J$25 -> 0
A50: 2 | B50: 1 | C50: 1 | D50: 5 | E50: 04 | F50: Proporción de vacaciones no disfrutadas | G50: ='CUENTA T FONDO 100'!R288 -> 0 | H50: ='CUENTA T VS'!R81 -> 0 | I50: ='CUENTA T NOMINA SNS'!R58 -> 0 | J50: =SUM(G50:I50) -> 0 | K50: =J50/$J$25 -> 0
A51: 2 | B51: 1 | C51: 2 | F51: Sobresueldos | G51: =+G52+G54 -> 3196999.6 | H51: =+H52+H54 -> 0 | I51: =+I52+I54 -> 0 | J51: =SUM(G51:I51) -> 3196999.6
A52: 2 | B52: 1 | C52: 2 | D52: 1 | F52: Primas por antigüedad | G52: =SUM(G53) -> 2752136.5 | H52: =SUM(H53) -> 0 | I52: =SUM(I53) -> 0 | J52: =SUM(G52:I52) -> 2752136.5
A53: 2 | B53: 1 | C53: 2 | D53: 1 | E53: 01 | F53: Primas por antigüedad | G53: ='CUENTA T FONDO 100'!S288 -> 2752136.5 | H53: ='CUENTA T VS'!S81 -> 0 | I53: ='CUENTA T NOMINA SNS'!S58 -> 0 | J53: =SUM(G53:I53) -> 2752136.5 | K53: =J53/$J$25 -> 0.035796323
A54: 2 | B54: 1 | C54: 2 | D54: 2 | F54: Compensación | G54: =SUM(G55:G63) -> 444863.1 | H54: =SUM(H55:H63) -> 0 | I54: =SUM(I55:I63) -> 0 | J54: =SUM(G54:I54) -> 444863.1
A55: 2 | B55: 1 | C55: 2 | D55: 2 | E55: 01 | F55: Compensación por gastos de alimentación | G55: ='CUENTA T FONDO 100'!T288 -> 0 | H55: ='CUENTA T VS'!T81 -> 0 | I55: ='CUENTA T NOMINA SNS'!T58 -> 0 | J55: =SUM(G55:I55) -> 0 | K55: =J55/$J$25 -> 0
A56: 2 | B56: 1 | C56: 2 | D56: 2 | E56: 03 | F56: Pago de horas extraordinarias | G56: ='CUENTA T FONDO 100'!U288 -> 0 | H56: ='CUENTA T VS'!U81 -> 0 | I56: ='CUENTA T NOMINA SNS'!U58 -> 0 | J56: =SUM(G56:I56) -> 0 | K56: =J56/$J$25 -> 0
A57: 2 | B57: 1 | C57: 2 | D57: 2 | E57: 04 | F57: Prima de transporte | G57: ='CUENTA T FONDO 100'!V288 -> 0 | H57: ='CUENTA T VS'!V81 -> 0 | I57: ='CUENTA T NOMINA SNS'!V58 -> 0 | J57: =SUM(G57:I57) -> 0 | K57: =J57/$J$25 -> 0
A58: 2 | B58: 1 | C58: 2 | D58: 2 | E58: 05 | F58: Compensación servicios de Seguridad | G58: ='CUENTA T FONDO 100'!W288 -> 45000 | H58: ='CUENTA T VS'!W81 -> 0 | I58: ='CUENTA T NOMINA SNS'!W58 -> 0 | J58: =SUM(G58:I58) -> 45000 | K58: =J58/$J$25 -> 0.00058530329
A59: 2 | B59: 1 | C59: 2 | D59: 2 | E59: 06 | F59: Incentivo por Rendimieto Individual | G59: ='CUENTA T FONDO 100'!X288 -> 0 | H59: ='CUENTA T VS'!X81 -> 0 | I59: ='CUENTA T NOMINA SNS'!X58 -> 0 | J59: =SUM(G59:I59) -> 0 | K59: =J59/$J$25 -> 0
A60: 2 | B60: 1 | C60: 2 | D60: 2 | E60: 07 | F60: Compensación por distancia | G60: ='CUENTA T FONDO 100'!Y288 -> 0 | H60: ='CUENTA T VS'!Y81 -> 0 | I60: ='CUENTA T NOMINA SNS'!Y58 -> 0 | J60: =SUM(G60:I60) -> 0 | K60: =J60/$J$25 -> 0
A61: 2 | B61: 1 | C61: 2 | D61: 2 | E61: 08 | F61: Compensaciones especiales | G61: ='CUENTA T FONDO 100'!Z288 -> 330200 | H61: ='CUENTA T VS'!Z81 -> 0 | I61: ='CUENTA T NOMINA SNS'!Z58 -> 0 | J61: =SUM(G61:I61) -> 330200 | K61: =J61/$J$25 -> 0.0042948255
A62: 2 | B62: 1 | C62: 2 | D62: 2 | E62: 09 | F62: Bono por desempeño a servidores de carrera | G62: ='CUENTA T FONDO 100'!AA288 -> 0 | H62: ='CUENTA T VS'!AA81 -> 0 | I62: ='CUENTA T NOMINA SNS'!AA58 -> 0 | J62: =SUM(G62:I62) -> 0 | K62: =J62/$J$25 -> 0
A63: 2 | B63: 1 | C63: 2 | D63: 2 | E63: 10 | F63: Compensacion por cumplimiento de indicadores | G63: ='CUENTA T FONDO 100'!AB288 -> 69663.1 | H63: ='CUENTA T VS'!AB81 -> 0 | I63: ='CUENTA T NOMINA SNS'!AB58 -> 0 | J63: =SUM(G63:I63) -> 69663.1 | K63: =J63/$J$25 -> 0.00090608981
A64: 2 | B64: 1 | C64: 3 | F64: Dietas y Gastos de Representación | G64: =+G65+G68 -> 0 | H64: =+H65+H68 -> 0 | I64: =+I65+I68 -> 0 | J64: =SUM(G64:I64) -> 0
A65: 2 | B65: 1 | C65: 3 | D65: 1 | F65: Dietas | G65: =SUM(G66:G67) -> 0 | H65: =SUM(H66:H67) -> 0 | I65: =SUM(I66:I67) -> 0 | J65: =SUM(G65:I65) -> 0
A66: 2 | B66: 1 | C66: 3 | D66: 1 | E66: 01 | F66: Dietas en el país | G66: ='CUENTA T FONDO 100'!AC288 -> 0 | H66: ='CUENTA T VS'!AC81 -> 0 | I66: ='CUENTA T NOMINA SNS'!AC58 -> 0 | J66: =SUM(G66:I66) -> 0 | K66: =J66/$J$25 -> 0
A67: 2 | B67: 1 | C67: 3 | D67: 1 | E67: 02 | F67: Dietas en el exterior | G67: ='CUENTA T FONDO 100'!AD288 -> 0 | H67: ='CUENTA T VS'!AD81 -> 0 | I67: ='CUENTA T NOMINA SNS'!AD58 -> 0 | J67: =SUM(G67:I67) -> 0 | K67: =J67/$J$25 -> 0
A68: 2 | B68: 1 | C68: 3 | D68: 2 | F68: Gastos de representación | G68: =SUM(G69:G70) -> 0 | H68: =SUM(H69:H70) -> 0 | I68: =SUM(I69:I70) -> 0 | J68: =SUM(G68:I68) -> 0
A69: 2 | B69: 1 | C69: 3 | D69: 2 | E69: 01 | F69: Gastos de representación en el país | G69: ='CUENTA T FONDO 100'!AE288 -> 0 | H69: ='CUENTA T VS'!AE81 -> 0 | I69: ='CUENTA T NOMINA SNS'!AE58 -> 0 | J69: =SUM(G69:I69) -> 0 | K69: =J69/$J$25 -> 0
A70: 2 | B70: 1 | C70: 3 | D70: 2 | E70: 02 | F70: Gastos de representación en el exterior | G70: ='CUENTA T FONDO 100'!AF288 -> 0 | H70: ='CUENTA T VS'!AF81 -> 0 | I70: ='CUENTA T NOMINA SNS'!AF58 -> 0 | J70: =SUM(G70:I70) -> 0 | K70: =J70/$J$25 -> 0
A71: 2 | B71: 1 | C71: 4 | F71: Gratificaciones y Bonificaciones | G71: =+G72+G74 -> 0 | H71: =+H72+H74 -> 0 | I71: =+I72+I74 -> 0 | J71: =SUM(G71:I71) -> 0
A72: 2 | B72: 1 | C72: 4 | D72: 1 | F72: Bonificaciones | G72: =SUM(G73) -> 0 | H72: =SUM(H73) -> 0 | I72: =SUM(I73) -> 0 | J72: =SUM(G72:I72) -> 0
A73: 2 | B73: 1 | C73: 4 | D73: 1 | E73: 01 | F73: Bonificaciones | G73: ='CUENTA T FONDO 100'!AG288 -> 0 | H73: ='CUENTA T VS'!AG81 -> 0 | I73: ='CUENTA T NOMINA SNS'!AG58 -> 0 | J73: =SUM(G73:I73) -> 0 | K73: =J73/$J$25 -> 0
A74: 2 | B74: 1 | C74: 4 | D74: 2 | F74: Otras Gratificaciones y Bonificaciones | G74: =SUM(G75:G77) -> 0 | H74: =SUM(H75:H77) -> 0 | I74: =SUM(I75:I77) -> 0 | J74: =SUM(G74:I74) -> 0
A75: 2 | B75: 1 | C75: 4 | D75: 2 | E75: 01 | F75: Bono escolar | G75: ='CUENTA T FONDO 100'!AH288 -> 0 | H75: ='CUENTA T VS'!AH81 -> 0 | I75: ='CUENTA T NOMINA SNS'!AH58 -> 0 | J75: =SUM(G75:I75) -> 0 | K75: =J75/$J$25 -> 0
A76: 2 | B76: 1 | C76: 4 | D76: 2 | E76: 02 | F76: Gratificaciones por pasantías | G76: ='CUENTA T FONDO 100'!AI288 -> 0 | H76: ='CUENTA T VS'!AI81 -> 0 | I76: ='CUENTA T NOMINA SNS'!AI58 -> 0 | J76: =SUM(G76:I76) -> 0 | K76: =J76/$J$25 -> 0
A77: 2 | B77: 1 | C77: 4 | D77: 2 | E77: 03 | F77: Gratificaciones por aniversario de institución | G77: ='CUENTA T FONDO 100'!AJ288 -> 0 | H77: ='CUENTA T VS'!AJ81 -> 0 | I77: ='CUENTA T NOMINA SNS'!AJ58 -> 0 | J77: =SUM(G77:I77) -> 0 | K77: =J77/$J$25 -> 0
A78: 2 | B78: 1 | C78: 5 | F78: Contribuciones a la Seguridad Social y Riesgo Laboral | G78: =+G79+G81+G83+G85 -> 8253841.6 | H78: =+H79+H81+H83+H85 -> 0 | I78: =+I79+I81+I83+I85 -> 0 | J78: =SUM(G78:I78) -> 8253841.6
A79: 2 | B79: 1 | C79: 5 | D79: 1 | F79: Contribuciones al seguro de salud | G79: =SUM(G80) -> 3803102.3 | H79: =SUM(H80) -> 0 | I79: =SUM(I80) -> 0 | J79: =SUM(G79:I79) -> 3803102.3
A80: 2 | B80: 1 | C80: 5 | D80: 1 | E80: 01 | F80: Contribuciones al seguro de salud | G80: ='CUENTA T FONDO 100'!AK288 -> 3803102.3 | H80: ='CUENTA T VS'!AK81 -> 0 | I80: ='CUENTA T NOMINA SNS'!AK58 -> 0 | J80: =SUM(G80:I80) -> 3803102.3 | K80: =J80/$J$25 -> 0.049465962
A81: 2 | B81: 1 | C81: 5 | D81: 2 | F81: Contribuciones al seguro de pensiones | G81: =SUM(G82) -> 3808464.5 | H81: =SUM(H82) -> 0 | I81: =SUM(I82) -> 0 | J81: =SUM(G81:I81) -> 3808464.5
A82: 2 | B82: 1 | C82: 5 | D82: 2 | E82: 01 | F82: Contribuciones al seguro de pensiones | G82: ='CUENTA T FONDO 100'!AL288 -> 3808464.5 | H82: ='CUENTA T VS'!AL81 -> 0 | I82: ='CUENTA T NOMINA SNS'!AL58 -> 0 | J82: =SUM(G82:I82) -> 3808464.5 | K82: =J82/$J$25 -> 0.049535706
A83: 2 | B83: 1 | C83: 5 | D83: 3 | F83: Contribuciones al seguro de riesgo laboral | G83: =SUM(G84) -> 642274.82 | H83: =SUM(H84) -> 0 | I83: =SUM(I84) -> 0 | J83: =SUM(G83:I83) -> 642274.82
A84: 2 | B84: 1 | C84: 5 | D84: 3 | E84: 01 | F84: Contribuciones al seguro de riesgo laboral | G84: ='CUENTA T FONDO 100'!AM288 -> 642274.82 | H84: ='CUENTA T VS'!AM81 -> 0 | I84: ='CUENTA T NOMINA SNS'!AM58 -> 0 | J84: =SUM(G84:I84) -> 642274.82 | K84: =J84/$J$25 -> 0.0083539014
A85: 2 | B85: 1 | C85: 5 | D85: 4 | F85: Contribuciones al plan de retiro complementario | G85: =SUM(G86) -> 0 | H85: =SUM(H86) -> 0 | I85: =SUM(I86) -> 0 | J85: =SUM(G85:I85) -> 0
A86: 2 | B86: 1 | C86: 5 | D86: 4 | E86: 01 | F86: Contribuciones al plan de retiro complementario | G86: ='CUENTA T FONDO 100'!AN288 -> 0 | H86: ='CUENTA T VS'!AN81 -> 0 | I86: ='CUENTA T NOMINA SNS'!AN58 -> 0 | J86: =SUM(G86:I86) -> 0 | K86: =J86/$J$25 -> 0
A87: 2 | B87: 2 | F87: Servicios No Personales | G87: =G88+G106+G111+G116+G125+G148+G157+G179+G208 -> 0 | H87: =H88+H106+H111+H116+H125+H148+H157+H179+H208 -> 2733844.3 | I87: =I88+I106+I111+I116+I125+I148+I157+I179+I208 -> 0 | J87: =SUM(G87:I87) -> 2733844.3 | K87: =J87/$J$25 -> 0.035558401
A88: 2 | B88: 2 | C88: 1 | F88: Servicios Básicos | G88: =+G89+G91+G93+G95+G97+G99+G102+G104 -> 0 | H88: =+H89+H91+H93+H95+H97+H99+H102+H104 -> 351316.33 | I88: =+I89+I91+I93+I95+I97+I99+I102+I104 -> 0 | J88: =SUM(G88:I88) -> 351316.33
A89: 2 | B89: 2 | C89: 1 | D89: 1 | F89: Radiocomunicación | G89: =SUM(G90) -> 0 | H89: =SUM(H90) -> 0 | I89: =SUM(I90) -> 0 | J89: =SUM(G89:I89) -> 0
A90: 2 | B90: 2 | C90: 1 | D90: 1 | E90: 01 | F90: Radiocomunicación | G90: ='CUENTA T FONDO 100'!AO288 -> 0 | H90: ='CUENTA T VS'!AO81 -> 0 | J90: =SUM(G90:I90) -> 0 | K90: =J90/$J$25 -> 0
A91: 2 | B91: 2 | C91: 1 | D91: 2 | F91: Servicios telefónico de larga distancia | G91: =SUM(G92) -> 0 | H91: =SUM(H92) -> 0 | I91: =SUM(I92) -> 0 | J91: =SUM(G91:I91) -> 0
A92: 2 | B92: 2 | C92: 1 | D92: 2 | E92: 01 | F92: Servicios telefónico de larga distancia | G92: ='CUENTA T FONDO 100'!AP288 -> 0 | H92: ='CUENTA T VS'!AP81 -> 0 | J92: =SUM(G92:I92) -> 0 | K92: =J92/$J$25 -> 0
A93: 2 | B93: 2 | C93: 1 | D93: 3 | F93: Teléfono local | G93: =SUM(G94) -> 0 | H93: =SUM(H94) -> 301316.33 | I93: =SUM(I94) -> 0 | J93: =SUM(G93:I93) -> 301316.33
A94: 2 | B94: 2 | C94: 1 | D94: 3 | E94: 01 | F94: Teléfono local | G94: ='CUENTA T FONDO 100'!AQ288 -> 0 | H94: ='CUENTA T VS'!AQ81 -> 301316.33 | J94: =SUM(G94:I94) -> 301316.33 | K94: =J94/$J$25 -> 0.0039191431
A95: 2 | B95: 2 | C95: 1 | D95: 4 | F95: Telefax y correos | G95: =SUM(G96) -> 0 | H95: =SUM(H96) -> 0 | I95: =SUM(I96) -> 0 | J95: =SUM(G95:I95) -> 0
A96: 2 | B96: 2 | C96: 1 | D96: 4 | E96: 01 | F96: Telefax y correos | G96: ='CUENTA T FONDO 100'!AR288 -> 0 | H96: ='CUENTA T VS'!AR81 -> 0 | J96: =SUM(G96:I96) -> 0 | K96: =J96/$J$25 -> 0
A97: 2 | B97: 2 | C97: 1 | D97: 5 | F97: Servicio de Internet y televisión por cable | G97: =SUM(G98) -> 0 | H97: =SUM(H98) -> 0 | I97: =SUM(I98) -> 0 | J97: =SUM(G97:I97) -> 0
A98: 2 | B98: 2 | C98: 1 | D98: 5 | E98: 01 | F98: Servicio de Internet y televisión por cable | G98: ='CUENTA T FONDO 100'!AS288 -> 0 | H98: ='CUENTA T VS'!AS81 -> 0 | J98: =SUM(G98:I98) -> 0 | K98: =J98/$J$25 -> 0
A99: 2 | B99: 2 | C99: 1 | D99: 6 | F99: Electricidad | G99: =SUM(G100:G101) -> 0 | H99: =SUM(H100:H101) -> 0 | I99: =SUM(I100:I101) -> 0 | J99: =SUM(G99:I99) -> 0
A100: 2 | B100: 2 | C100: 1 | D100: 6 | E100: 01 | F100: Energía eléctrica | G100: ='CUENTA T FONDO 100'!AT288 -> 0 | H100: ='CUENTA T VS'!AT81 -> 0 | J100: =SUM(G100:I100) -> 0 | K100: =J100/$J$25 -> 0
A101: 2 | B101: 2 | C101: 1 | D101: 6 | E101: 02 | F101: Electricidad no cortable | G101: ='CUENTA T FONDO 100'!AU288 -> 0 | H101: ='CUENTA T VS'!AU81 -> 0 | J101: =SUM(G101:I101) -> 0 | K101: =J101/$J$25 -> 0
A102: 2 | B102: 2 | C102: 1 | D102: 7 | F102: Agua | G102: =SUM(G103) -> 0 | H102: =SUM(H103) -> 0 | I102: =SUM(I103) -> 0 | J102: =SUM(G102:I102) -> 0
...

Sheet CUENTA T FONDO 100
A1: D E S G L O S E D E L A S C U E N T A S
A2: 211101 | B2: 211102 | C2: 211103 | D2: 211104 | E2: 211105 | F2: 211106 | G2: 211203 | H2: 211205 | I2: 211206 | J2: 211208 | K2: 211209 | L2: 211211 | M2: 211301 | N2: 211401 | O2: 211501 | P2: 211502 | Q2: 211503 | R2: 211504 | S2: 212101 | T2: 212201 | U2: 212203 | V2: 212204 | W2: 212205 | X2: 212206 | Y2: 212207 | Z2: 212208 | AA2: 212209 | AB2: 212210 | AC2: 213101 | AD2: 213102 | AE2: 213201 | AF2: 213202 | AG2: 214101 | AH2: 214201 | AI2: 214202 | AJ2: 214203 | AK2: 215101 | AL2: 215201 | AM2: 215301 | AN2: 215401 | AO2: 221101 | AP2: 221201 | AQ2: 221301 | AR2: 221401 | AS2: 221501 | AT2: 221601 | AU2: 221602 | AV2: 221701 | AW2: 221801 | AX2: 222101 | AY2: 222201 | AZ2: 223101 | BA2: 223201 | BB2: 224101 | BC2: 224201 | BD2: 224301 | BE2: 224401 | BF2: 225101 | BG2: 225201 | BH2: 225301 | BI2: 225302 | BJ2: 225303 | BK2: 225304 | BL2: 225305 | BM2: 225401 | BN2: 225501 | BO2: 225601 | BP2: 225701 | BQ2: 225801 | BR2: 225901 | BS2: 226101 | BT2: 226201 | BU2: 226301 | BV2: 226401 | BW2: 227101 | BX2: 227102 | BY2: 227103 | BZ2: 227104 | CA2: 227105 | CB2: 227106 | CC2: 227107 | CD2: 227199 | CE2: 227201 | CF2: 227202 | CG2: 227203 | CH2: 227204 | CI2: 227205 | CJ2: 227206 | CK2: 227207 | CL2: 227208 | CM2: 227299 | CN2: 227301 | CO2: 228101 | CP2: 228201 | CQ2: 228301 | CR2: 228401 | CS2: 228501 | CT2: 228502 | CU2: 228503 | CV2: 228601 | CW2: 228602 | CX2: 228603 | CY2: 228604 | CZ2: 228701 | DA2: 228702 | DB2: 228703 | DC2: 228704 | DD2: 228705 | DE2: 228706 | DF2: 228801 | DG2: 228802 | DH2: 228803 | DI2: 229201 | DJ2: 229203 | DK2: 231101 | DL2: 231102 | DM2: 231201 | DN2: 231301 | DO2: 231302 | DP2: 231303 | DQ2: 231401 | DR2: 232101 | DS2: 232201 | DT2: 232301 | DU2: 233101 | DV2: 233201 | DW2: 233301 | DX2: 233401 | DY2: 233501 | DZ2: 233601 | EA2: 234101 | EB2: 234201 | EC2: 235101 | ED2: 235201 | EE2: 235301 | EF2: 235401 | EG2: 235501 | EH2: 236101 | EI2: 236102 | EJ2: 236103 | EK2: 236104 | EL2: 236105 | EM2: 236201 | EN2: 236202 | EO2: 236203 | EP2: 236304 | EQ2: 236305 | ER2: 236306 | ES2: 236401 | ET2: 236402 | EU2: 236403 | EV2: 236404 | EW2: 236405 | EX2: 236406 | EY2: 236407 | EZ2: 236901 | FA2: 237101 | FB2: 237102 | FC2: 237103 | FD2: 237104 | FE2: 237105 | FF2: 237106 | FG2: 237107 | FH2: 237201 | FI2: 237202 | FJ2: 237203 | FK2: 237204 | FL2: 237205 | FM2: 237206 | FN2: 237299 | FO2: 238101 | FP2: 238201 | FQ2: 239101 | FR2: 239102 | FS2: 239201 | FT2: 239301 | FU2: 239401 | FV2: 239501 | FW2: 239601 | FX2: 239701 | FY2: 239801 | FZ2: 239802 | GA2: 239901 | GB2: 239904 | GC2: 241201 | GD2: 241202 | GE2: 241203 | GF2: 241204 | GG2: 241205 | GH2: 261101 | GI2: 261201 | GJ2: 261301 | GK2: 261401 | GL2: 261901 | GM2: 262101 | GN2: 262201 | GO2: 262301 | GP2: 262401 | GQ2: 263101 | GR2: 263201 | GS2: 263301 | GT2: 263401 | GU2: 264101 | GV2: 264201 | GW2: 264301 | GX2: 264401 | GY2: 264501 | GZ2: 264601 | HA2: 264701 | HB2: 264801 | HC2: 265101 | HD2: 265201 | HE2: 265301 | HF2: 265401 | HG2: 265501 | HH2: 265601 | HI2: 265701 | HJ2: 265801 | HK2: 266101 | HL2: 266201 | HM2: 267101 | HN2: 267201 | HO2: 267301 | HP2: 267401 | HQ2: 267501 | HR2: 267601 | HS2: 267701 | HT2: 267801 | HU2: 267901 | HV2: 268101 | HW2: 268201 | HX2: 268301 | HY2: 268302 | HZ2: 268401 | IA2: 268501 | IB2: 268601 | IC2: 268701 | ID2: 268802 | IE2: 268803 | IF2: 268804 | IG2: 268901 | IH2: 269101 | II2: 269102 | IJ2: 269201 | IK2: 269202 | IL2: 269301 | IM2: 269401 | IN2: 269501 | IO2: 269502 | IP2: 269503 | IQ2: 2269901 | IR2: 271101 | IS2: 271201 | IT2: 271301 | IU2: 271401 | IV2: 272101 | IW2: 272201 | IX2: 272301 | IY2: 272401 | IZ2: 272501 | JA2: 272601 | JB2: 272701 | JC2: 272801 | JD2: 272901 | JE2: 273101 | JF2: 273201 | JG2: 274101 | JH2: 274201 | JI2: Totales | JJ2: LIBRAMIENTO | JK2: VALOR | JL2: RETENCION | JM2: AÑOS ANTERIORES | JN2: 2024 | JO2: Total | JP2: Proveedor Informal
JI3: =SUM(A3:JH3) -> 0 | JJ3: 5642 | JK3: =+JI3-JL3 -> 0
JI4: =SUM(A4:JH4) -> 0 | JJ4: 5646 | JK4: =+JI4-JL4 -> 0
JI5: =SUM(A5:JH5) -> 0 | JJ5: 5650 | JK5: =+JI5-JL5 -> 0
JI6: =SUM(A6:JH6) -> 0 | JJ6: 5654 | JK6: =+JI6-JL6 -> 0
JI7: =SUM(A7:JH7) -> 0 | JJ7: 5670 | JK7: =+JI7-JL7 -> 0
JI8: =SUM(A8:JH8) -> 0 | JJ8: 5671 | JK8: =+JI8-JL8 -> 0
JI9: =SUM(A9:JH9) -> 0 | JJ9: 5675 | JK9: =+JI9-JL9 -> 0
JI10: =SUM(A10:JH10) -> 0 | JJ10: 5680 | JK10: =+JI10-JL10 -> 0
JI11: =SUM(A11:JH11) -> 0 | JJ11: 5682 | JK11: =+JI11-JL11 -> 0
JI12: =SUM(A12:JH12) -> 0 | JJ12: 5683 | JK12: =+JI12-JL12 -> 0
JI13: =SUM(A13:JH13) -> 0 | JJ13: 5687 | JK13: =+JI13-JL13 -> 0
JI14: =SUM(A14:JH14) -> 0 | JJ14: 5691 | JK14: =+JI14-JL14 -> 0
... JI127: =SUM(A127:JH127) -> 0 | JJ127: 6312 | JK127: =+JI127-JL127 -> 0
JI128: =SUM(A128:JH128) -> 0 | JJ128: 6316 | JK128: =+JI128-JL128 -> 0 | JM128: =SUM(JM3:JM59) -> 0 | JN128: =SUM(JN3:JN59) -> 0 | JO128: =SUM(JO3:JO59) -> 0 | JP128: =SUM(JP3:JP59) -> 0
JI129: =SUM(A129:JH129) -> 0 | JJ129: 6322 | JK129: =+JI129-JL129 -> 0
JI130: =SUM(A130:JH130) -> 0 | JJ130: 6326 | JK130: =+JI130-JL130 -> 0
JI131: =SUM(A131:JH131) -> 0 | JJ131: 6330 | JK131: =+JI131-JL131 -> 0
JI132: =SUM(A132:JH132) -> 0 | JJ132: 6332 | JK132: =+JI132-JL132 -> 0
JI133: =SUM(A133:JH133) -> 0 | JJ133: 6344 | JK133: =+JI133-JL133 -> 0
JI134: =SUM(A134:JH134) -> 0 | JJ134: 6346 | JK134: =+JI134-JL134 -> 0
JI135: =SUM(A135:JH135) -> 0 | JJ135: 6355 | JK135: =+JI135-JL135 -> 0
JI136: =SUM(A136:JH136) -> 0 | JJ136: 6359 | JK136: =+JI136-JL136 -> 0
JI137: =SUM(A137:JH137) -> 0 | JJ137: 6361 | JK137: =+JI137-JL137 -> 0
JI138: =SUM(A138:JH138) -> 0 | JJ138: 6363 | JK138: =+JI138-JL138 -> 0
JI139: =SUM(A139:JH139) -> 0 | JJ139: 6369 | JK139: =+JI139-JL139 -> 0
JI140: =SUM(A140:JH140) -> 0 | JJ140: 6370 | JK140: =+JI140-JL140 -> 0
... JI165: =SUM(A165:JH165) -> 0 | JJ165: 6474 | JK165: =+JI165-JL165 -> 0
J166: 973531.03 | AK166: 69023.35 | AL166: 69120.7 | AM166: 11471.29 | JI166: =SUM(A166:JH166) -> 1123146.4 | JJ166: 6478 | JK166: =+JI166-JL166 -> 1123146.4
W167: 45000 | JI167: =SUM(A167:JH167) -> 45000 | JJ167: 6482 | JK167: =+JI167-JL167 -> 45000
A168: 52666808 | S168: 2752136.5 | W168: . | Z168: 330200 | AB168: =10717.4+58945.7 -> 69663.1 | AK168: 3734078.9 | AL168: 3739343.8 | AM168: 630803.53 | JI168: =SUM(A168:JH168) -> 63923034 | JJ168: 6486 | JK168: =+JI168-JL168 -> 63923034
EA169: 55550 | JI169: =SUM(A169:JH169) -> 55550 | JJ169: 6492 | JK169: =+JI169-JL169 -> 55550
EA170: 252000 | JI170: =SUM(A170:JH170) -> 252000 | JJ170: 6496 | JK170: =+JI170-JL170 -> 252000
FJ171: 467802 | JI171: =SUM(A171:JH171) -> 467802 | JJ171: 6500 | JK171: =+JI171-JL171 -> 467802
FJ172: 332252 | JI172: =SUM(A172:JH172) -> 332252 | JJ172: 6504 | JK172: =+JI172-JL172 -> 332252
EA173: 271350 | JI173: =SUM(A173:JH173) -> 271350 | JJ173: 6516 | JK173: =+JI173-JL173 -> 271350
FT174: 129664 | JI174: =SUM(A174:JH174) -> 129664 | JJ174: 6523 | JK174: =+JI174-JL174 -> 129664
FT175: 235971.68 | JI175: =SUM(A175:JH175) -> 235971.68 | JJ175: 6524 | JK175: =+JI175-JL175 -> 235971.68
EA176: 240000 | JI176: =SUM(A176:JH176) -> 240000 | JJ176: 6530 | JK176: =+JI176-JL176 -> 240000
FJ177: 703592.61 | JI177: =SUM(A177:JH177) -> 703592.61 | JJ177: 6533 | JK177: =+JI177-JL177 -> 703592.61
EA178: 85600 | JI178: =SUM(A178:JH178) -> 85600 | JJ178: 6537 | JK178: =+JI178-JL178 -> 85600
FT179: 157006.08 | JI179: =SUM(A179:JH179) -> 157006.08 | JJ179: 6544 | JK179: =+JI179-JL179 -> 157006.08
FT180: 206475.22 | JI180: =SUM(A180:JH180) -> 206475.22 | JJ180: 6545 | JK180: =+JI180-JL180 -> 206475.22
FJ181: 341016.8 | JI181: =SUM(A181:JH181) -> 341016.8 | JJ181: 6552 | JK181: =+JI181-JL181 -> 341016.8
FT182: 269040 | JI182: =SUM(A182:JH182) -> 269040 | JJ182: 6553 | JK182: =+JI182-JL182 -> 269040
EA183: 210960 | JI183: =SUM(A183:JH183) -> 210960 | JJ183: 6560 | JK183: =+JI183-JL183 -> 210960
EA184: 256800 | JI184: =SUM(A184:JH184) -> 256800 | JJ184: 6561 | JK184: =+JI184-JL184 -> 256800
FT185: 264900 | JI185: =SUM(A185:JH185) -> 264900 | JJ185: 6565 | JK185: =+JI185-JL185 -> 264900
EA186: 254620.8 | JI186: =SUM(A186:JH186) -> 254620.8 | JJ186: 6572 | JK186: =+JI186-JL186 -> 254620.8
EA187: 236000 | JI187: =SUM(A187:JH187) -> 236000 | JJ187: 6578 | JK187: =+JI187-JL187 -> 236000
JI188: =SUM(A188:JH188) -> 0 | JJ188: 6579 | JK188: =+JI188-JL188 -> 0
JI189: =SUM(A189:JH189) -> 0 | JJ189: 6583 | JK189: =+JI189-JL189 -> 0
JI190: =SUM(A190:JH190) -> 0 | JJ190: 6587 | JK190: =+JI190-JL190 -> 0
JI191: =SUM(A191:JH191) -> 0 | JJ191: 6591 | JK191: =+JI191-JL191 -> 0
JI192: =SUM(A192:JH192) -> 0 | JJ192: 6592 | JK192: =+JI192-JL192 -> 0
JI193: =SUM(A193:JH193) -> 0 | JJ193: 6595 | JK193: =+JI193-JL193 -> 0
JI194: =SUM(A194:JH194) -> 0 | JJ194: 6599 | JK194: =+JI194-JL194 -> 0
JI195: =SUM(A195:JH195) -> 0 | JJ195: 6603 | JK195: =+JI195-JL195 -> 0
JI196: =SUM(A196:JH196) -> 0 | JJ196: 6607 | JK196: =+JI196-JL196 -> 0
JI197: =SUM(A197:JH197) -> 0 | JJ197: 6611 | JK197: =+JI197-JL197 -> 0
JI198: =SUM(A198:JH198) -> 0 | JJ198: 6615 | JK198: =+JI198-JL198 -> 0
JI199: =SUM(A199:JH199) -> 0 | JJ199: 6619 | JK199: =+JI199-JL199 -> 0
... JI257: =SUM(A257:JH257) -> 0 | JJ257: 6966 | JK257: =+JI257-JL257 -> 0
JI258: =SUM(A258:JH258) -> 0 | JK258: =+JI258-JL258 -> 0
JI259: =SUM(A259:JH259) -> 0 | JK259: =+JI259-JL259 -> 0
JI260: =SUM(A260:JH260) -> 0 | JK260: =+JI260-JL260 -> 0
JI261: =SUM(A261:JH261) -> 0 | JK261: =+JI261-JL261 -> 0
JI262: =SUM(A262:JH262) -> 0 | JK262: =+JI262-JL262 -> 0
JI263: =SUM(A263:JH263) -> 0 | JK263: =+JI263-JL263 -> 0
JI264: =SUM(A264:JH264) -> 0 | JK264: =+JI264-JL264 -> 0
JI265: =SUM(A265:JH265) -> 0 | JK265: =+JI265-JL265 -> 0
JI266: =SUM(A266:JH266) -> 0 | JK266: =+JI266-JL266 -> 0
A271: =SUM(A3:A270) -> 52666808 | B271: =SUM(B3:B270) -> 0 | C271: =SUM(C3:C270) -> 0 | D271: =SUM(D3:D270) -> 0 | E271: =SUM(E3:E270) -> 0 | F271: =SUM(F3:F270) -> 0 | G271: =SUM(G3:G270) -> 0 | H271: =SUM(H3:H270) -> 0 | ... JI271: =SUM(JI3:JI270) -> 70061781 | JK271: =SUM(JK3:JK270) -> 70061781 | JL271: =SUM(JL3:JL270) -> 0
A272: 211101 | B272: 211102 | C272: 211103 | D272: 211104 | E272: 211105 | F272: 211106 | G272: 211203 | H272: 211205 | I272: 211206 | J272: 211208 | K272: 211209 | L272: 211211 | M272: 211301 | N272: 211401 | O272: 211501 | P272: 211502 | Q272: 211503 | R272: 211504 | S272: 212101 | T272: 212201 | U272: 212203 | V272: 212204 | W272: 212205 | X272: 212206 | Y272: 212207 | Z272: 212208 | AA272: 212209 | AB272: 212210 | AC272: 213101 | AD272: 213102 | AE272: 213201 | AF272: 213202 | AG272: 214101 | AH272: 214201 | AI272: 214202 | AJ272: 214203 | AK272: 215101 | AL272: 215201 | AM272: 215301 | AN272: 215401 | AO272: 221101 | AP272: 221201 | AQ272: 221301 | AR272: 221401 | AS272: 221501 | AT272: 221601 | AU272: 221602 | AV272: 221701 | AW272: 221801 | AX272: 222101 | AY272: 222201 | AZ272: 223101 | BA272: 223201 | BB272: 224101 | BC272: 224201 | BD272: 224301 | BE272: 224401 | BF272: 225101 | BG272: 225201 | BH272: 225301 | BI272: 225302 | BJ272: 225303 | BK272: 225304 | BL272: 225305 | BM272: 225401 | BN272: 225501 | BO272: 225601 | BP272: 225701 | BQ272: 225801 | BR272: 225901 | BS272: 226101 | BT272: 226201 | BU272: 226301 | BV272: 226401 | BW272: 227101 | BX272: 227102 | BY272: 227103 | BZ272: 227104 | CA272: 227105 | CB272: 227106 | CC272: 227107 | CD272: 227199 | CE272: 227201 | CF272: 227202 | CG272: 227203 | CH272: 227204 | CI272: 227205 | CJ272: 227206 | CK272: 227207 | CL272: 227208 | CM272: 227299 | CN272: 227301 | CO272: 228101 | CP272: 228201 | CQ272: 228301 | CR272: 228401 | CS272: 228501 | CT272: 228502 | CU272: 228503 | CV272: 228601 | CW272: 228602 | CX272: 228603 | CY272: 228604 | CZ272: 228701 | DA272: 228702 | DB272: 228703 | DC272: 228704 | DD272: 228705 | DE272: 228706 | DF272: 228801 | DG272: 228802 | DH272: 228803 | DI272: 229201 | DJ272: 229203 | DK272: 231101 | DL272: 231102 | DM272: 231201 | DN272: 231301 | DO272: 231302 | DP272: 231303 | DQ272: 231401 | DR272: 232101 | DS272: 232201 | DT272: 232301 | DU272: 233101 | DV272: 233201 | DW272: 233301 | DX272: 233401 | DY272: 233501 | DZ272: 233601 | EA272: 234101 | EB272: 234201 | EC272: 235101 | ED272: 235201 | EE272: 235301 | EF272: 235401 | EG272: 235501 | EH272: 236101 | EI272: 236102 | EJ272: 236103 | EK272: 236104 | EL272: 236105 | EM272: 236201 | EN272: 236202 | EO272: 236203 | EP272: 236304 | EQ272: 236305 | ER272: 236306 | ES272: 236401 | ET272: 236402 | EU272: 236403 | EV272: 236404 | EW272: 236405 | EX272: 236406 | EY272: 236407 | EZ272: 236901 | FA272: 237101 | FB272: 237102 | FC272: 237103 | FD272: 237104 | FE272: 237105 | FF272: 237106 | FG272: 237107 | FH272: 237201 | FI272: 237202 | FJ272: 237203 | FK272: 237204 | FL272: 237205 | FM272: 237206 | FN272: 237299 | FO272: 238101 | FP272: 238201 | FQ272: 239101 | FR272: 239102 | FS272: 239201 | FT272: 239301 | FU272: 239401 | FV272: 239501 | FW272: 239601 | FX272: 239701 | FY272: 239801 | FZ272: 239802 | GA272: 239901 | GB272: 239904 | GC272: 241201 | GD272: 241202 | GE272: 241203 | GF272: 241204 | GG272: 241205 | GH272: 261101 | GI272: 261201 | GJ272: 261301 | GK272: 261401 | GL272: 261901 | GM272: 262101 | GN272: 262201 | GO272: 262301 | GP272: 262401 | GQ272: 263101 | GR272: 263201 | GS272: 263301 | GT272: 263401 | GU272: 264101 | GV272: 264201 | GW272: 264301 | GX272: 264401 | GY272: 264501 | GZ272: 264601 | HA272: 264701 | HB272: 264801 | HC272: 265101 | HD272: 265201 | HE272: 265301 | HF272: 265401 | HG272: 265501 | HH272: 265601 | HI272: 265701 | HJ272: 265801 | HK272: 266101 | HL272: 266201 | HM272: 267101 | HN272: 267201 | HO272: 267301 | HP272: 267401 | HQ272: 267501 | HR272: 267601 | HS272: 267701 | HT272: 267801 | HU272: 267901 | HV272: 268101 | HW272: 268201 | HX272: 268301 | HY272: 268302 | HZ272: 268401 | IA272: 268501 | IB272: 268601 | IC272: 268701 | ID272: 268802 | IE272: 268803 | IF272: 268804 | IG272: 268901 | IH272: 269101 | II272: 269102 | IJ272: 269201 | IK272: 269202 | IL272: 269301 | IM272: 269401 | IN272: 269501 | IO272: 269502 | IP272: 269503 | IQ272: 2269901 | IR272: 271101 | IS272: 271201 | IT272: 271301 | IU272: 271401 | IV272: 272101 | IW272: 272201 | IX272: 272301 | IY272: 272401 | IZ272: 272501 | JA272: 272601 | JB272: 272701 | JC272: 272801 | JD272: 272901 | JE272: 273101 | JF272: 273201 | JG272: 274101 | JH272: 274201 | JI272: 2.0259826e+08
JI273: =+JI271-JI272 -> -1.3253648e+08
JI275: =SUM(A275:JH275) -> 0
JI276: =SUM(A276:JH276) -> 0
JI277: =SUM(A277:JH277) -> 0
JI278: =SUM(A278:JH278) -> 0
JI279: =SUM(A279:JH279) -> 0
JI280: =SUM(A280:JH280) -> 0
JI281: =SUM(A281:JH281) -> 0
JI282: =SUM(A282:JH282) -> 0
JI283: =SUM(A283:JH283) -> 0
JI284: =SUM(A284:JH284) -> 0
JI285: =SUM(A285:JH285) -> 0
JI286: =SUM(A286:JH286) -> 0
A287: =SUM(A273:A286) -> 0 | B287: =SUM(B273:B286) -> 0 | C287: =SUM(C273:C286) -> 0 | D287: =SUM(D273:D286) -> 0 | E287: =SUM(E273:E286) -> 0 | F287: =SUM(F273:F286) -> 0 | G287: =SUM(G273:G286) -> 0 | H287: =SUM(H273:H286) -> 0 | ... JH287: =SUM(JH273:JH286) -> 0 | JI287: =SUM(A287:JH287) -> 0
A288: =+A287+A271 -> 52666808 | B288: =+B287+B271 -> 0 | C288: =+C287+C271 -> 0 | D288: =+D287+D271 -> 0 | E288: =+E287+E271 -> 0 | F288: =+F287+F271 -> 0 | G288: =+G287+G271 -> 0 | H288: =+H287+H271 -> 0 | ... JI288: =+JI287+JI271 -> 70061781

Sheet CUENTA T VS
A1: D E S G L O S E D E L A S C U E N T A S
A2: 211101 | B2: 211102 | C2: 211103 | D2: 211104 | E2: 211105 | F2: 211106 | G2: 211203 | H2: 211205 | I2: 211206 | J2: 211208 | K2: 211209 | L2: 211211 | M2: 211301 | N2: 211401 | O2: 211501 | P2: 211502 | Q2: 211503 | R2: 211504 | S2: 212101 | T2: 212201 | U2: 212203 | V2: 212204 | W2: 212205 | X2: 212206 | Y2: 212207 | Z2: 212208 | AA2: 212209 | AB2: 212210 | AC2: 213101 | AD2: 213102 | AE2: 213201 | AF2: 213202 | AG2: 214101 | AH2: 214201 | AI2: 214202 | AJ2: 214203 | AK2: 215101 | AL2: 215201 | AM2: 215301 | AN2: 215401 | AO2: 221101 | AP2: 221201 | AQ2: 221301 | AR2: 221401 | AS2: 221501 | AT2: 221601 | AU2: 221602 | AV2: 221701 | AW2: 221801 | AX2: 222101 | AY2: 222201 | AZ2: 223101 | BA2: 223201 | BB2: 224101 | BC2: 224201 | BD2: 224301 | BE2: 224401 | BF2: 225101 | BG2: 225201 | BH2: 225301 | BI2: 225302 | BJ2: 225303 | BK2: 225304 | BL2: 225305 | BM2: 225401 | BN2: 225501 | BO2: 225601 | BP2: 225701 | BQ2: 225801 | BR2: 225901 | BS2: 226101 | BT2: 226201 | BU2: 226301 | BV2: 226401 | BW2: 227101 | BX2: 227102 | BY2: 227103 | BZ2: 227104 | CA2: 227105 | CB2: 227106 | CC2: 227107 | CD2: 227199 | CE2: 227201 | CF2: 227202 | CG2: 227203 | CH2: 227204 | CI2: 227205 | CJ2: 227206 | CK2: 227207 | CL2: 227208 | CM2: 227299 | CN2: 227301 | CO2: 228101 | CP2: 228201 | CQ2: 228301 | CR2: 228401 | CS2: 228501 | CT2: 228502 | CU2: 228503 | CV2: 228601 | CW2: 228602 | CX2: 228603 | CY2: 228604 | CZ2: 228701 | DA2: 228702 | DB2: 228703 | DC2: 228704 | DD2: 228705 | DE2: 228706 | DF2: 228801 | DG2: 228802 | DH2: 228803 | DI2: 229201 | DJ2: 229203 | DK2: 231101 | DL2: 231102 | DM2: 231201 | DN2: 231301 | DO2: 231302 | DP2: 231303 | DQ2: 231401 | DR2: 232101 | DS2: 232201 | DT2: 232301 | DU2: 233101 | DV2: 233201 | DW2: 233301 | DX2: 233401 | DY2: 233501 | DZ2: 233601 | EA2: 234101 | EB2: 234201 | EC2: 235101 | ED2: 235201 | EE2: 235301 | EF2: 235401 | EG2: 235501 | EH2: 236101 | EI2: 236102 | EJ2: 236103 | EK2: 236104 | EL2: 236105 | EM2: 236201 | EN2: 236202 | EO2: 236203 | EP2: 236304 | EQ2: 236305 | ER2: 236306 | ES2: 236401 | ET2: 236402 | EU2: 236403 | EV2: 236404 | EW2: 236405 | EX2: 236406 | EY2: 236407 | EZ2: 236901 | FA2: 237101 | FB2: 237102 | FC2: 237103 | FD2: 237104 | FE2: 237105 | FF2: 237106 | FG2: 237107 | FH2: 237201 | FI2: 237202 | FJ2: 237203 | FK2: 237204 | FL2: 237205 | FM2: 237206 | FN2: 237299 | FO2: 238101 | FP2: 238201 | FQ2: 239101 | FR2: 239102 | FS2: 239201 | FT2: 239301 | FU2: 239401 | FV2: 239501 | FW2: 239601 | FX2: 239701 | FY2: 239801 | FZ2: 239802 | GA2: 239901 | GB2: 239904 | GC2: 241201 | GD2: 241202 | GE2: 241203 | GF2: 241204 | GG2: 241205 | GH2: 261101 | GI2: 261201 | GJ2: 261301 | GK2: 261401 | GL2: 261901 | GM2: 262101 | GN2: 262201 | GO2: 262301 | GP2: 262401 | GQ2: 263101 | GR2: 263201 | GS2: 263301 | GT2: 263401 | GU2: 264101 | GV2: 264201 | GW2: 264301 | GX2: 264401 | GY2: 264501 | GZ2: 264601 | HA2: 264701 | HB2: 264801 | HC2: 265101 | HD2: 265201 | HE2: 265301 | HF2: 265401 | HG2: 265501 | HH2: 265601 | HI2: 265701 | HJ2: 265801 | HK2: 266101 | HL2: 266201 | HM2: 267101 | HN2: 267201 | HO2: 267301 | HP2: 267401 | HQ2: 267501 | HR2: 267601 | HS2: 267701 | HT2: 267801 | HU2: 267901 | HV2: 268101 | HW2: 268201 | HX2: 268301 | HY2: 268302 | HZ2: 268401 | IA2: 268501 | IB2: 268601 | IC2: 268701 | ID2: 268802 | IE2: 268803 | IF2: 268804 | IG2: 268901 | IH2: 269101 | II2: 269102 | IJ2: 269201 | IK2: 269202 | IL2: 269301 | IM2: 269401 | IN2: 269501 | IO2: 269502 | IP2: 269503 | IQ2: 2269901 | IR2: 271101 | IS2: 271201 | IT2: 271301 | IU2: 271401 | IV2: 272101 | IW2: 272201 | IX2: 272301 | IY2: 272401 | IZ2: 272501 | JA2: 272601 | JB2: 272701 | JC2: 272801 | JD2: 272901 | JE2: 273101 | JF2: 273201 | JG2: 274101 | JH2: 274201 | JI2: Totales | JJ2: TRANSF NO. | JK2: VALOR | JL2: RETENCION | JM2: AÑOS ANTERIORES | JN2: 2024 | JO2: Total | JP2: Proveedor Informal
FT3: 241900 | GQ3: 887994.84 | JI3: =SUM(A3:JH3) -> 1129894.8 | JJ3: TRANSF. 001 | JK3: 1082017.9 | JL3: =+JI3-JK3 -> 47876.9
EA4: 258000 | JI4: =SUM(A4:JH4) -> 258000 | JJ4: TRANSF. 002 | JK4: 245100 | JL4: =+JI4-JK4 -> 12900
GD5: 100000 | JI5: =SUM(A5:JH5) -> 100000 | JJ5: TRANSF. 003 | JK5: 100000 | JL5: =+JI5-JK5 -> 0
GD6: 30166.7 | JI6: =SUM(A6:JH6) -> 30166.7 | JJ6: TRANSF. 004 | JK6: 30166.7 | JL6: =+JI6-JK6 -> 0
DE7: 10100 | JI7: =SUM(A7:JH7) -> 10100 | JJ7: TRANSF. 005 | JK7: 9595 | JL7: =+JI7-JK7 -> 505
BI8: 266664.26 | JI8: =SUM(A8:JH8) -> 266664.26 | JJ8: TRANSF. 006 | JK8: 255364.93 | JL8: =+JI8-JK8 -> 11299.33
AW9: 50000 | JI9: =SUM(A9:JH9) -> 50000 | JJ9: TRANSF. 007 | JK9: 50000 | JL9: =+JI9-JK9 -> 0
DE10: 17740 | JI10: =SUM(A10:JH10) -> 17740 | JJ10: TRANSF. 008 | JK10: 16853 | JL10: =+JI10-JK10 -> 887
DK11: 37740 | JI11: =SUM(A11:JH11) -> 37740 | JJ11: TRANSF. 009 | JK11: 37740 | JL11: =+JI11-JK11 -> 0
FD12: 49512.84 | JI12: =SUM(A12:JH12) -> 49512.84 | JJ12: TRANSF. 010 | JK12: 49512.84 | JL12: =+JI12-JK12 -> 0
DK13: 98115 | JI13: =SUM(A13:JH13) -> 98115 | JJ13: TRANSF. 011 | JK13: 93209.25 | JL13: =+JI13-JK13 -> 4905.75
FJ14: 6900 | JI14: =SUM(A14:JH14) -> 6900 | JJ14: TRANSF. 012 | JK14: 6555 | JL14: =+JI14-JK14 -> 345
EA15: 50000 | JI15: =SUM(A15:JH15) -> 50000 | JJ15: TRANSF. 013 | JK15: 47500 | JL15: =+JI15-JK15 -> 2500
AQ16: 91518.64 | JI16: =SUM(A16:JH16) -> 91518.64 | JJ16: TRANSF. 014 | JK16: 91518.64 | JL16: =+JI16-JK16 -> 0
AQ17: 209797.69 | JI17: =SUM(A17:JH17) -> 209797.69 | JJ17: TRANSF. 015 | JK17: 209797.69 | JL17: =+JI17-JK17 -> 0
DW18: 29500 | JI18: =SUM(A18:JH18) -> 29500 | JJ18: TRANSF. 016 | JK18: 28250 | JL18: =+JI18-JK18 -> 1250
DW19: 56050 | JI19: =SUM(A19:JH19) -> 56050 | JJ19: TRANSF. 017 | JK19: 53675 | JL19: =+JI19-JK19 -> 2375
FT20: 684400 | JI20: =SUM(A20:JH20) -> 684400 | JJ20: TRANSF. 018 | JK20: 655400 | JL20: =+JI20-JK20 -> 29000
CU21: 10148 | JI21: =SUM(A21:JH21) -> 10148 | JJ21: TRANSF. 019 | JK21: 9718 | JL21: =+JI21-JK21 -> 430
FA22: 172000 | JI22: =SUM(A22:JH22) -> 172000 | JJ22: TRANSF. 020 | JK22: 170573.26 | JL22: =+JI22-JK22 -> 1426.74
CH23: 1888000 | JI23: =SUM(A23:JH23) -> 1888000 | JJ23: TRANSF. 021 | JK23: 1808000 | JL23: =+JI23-JK23 -> 80000
FT24: 192288.08 | JI24: =SUM(A24:JH24) -> 192288.08 | JJ24: TRANSF. 022 | JK24: 184140.28 | JL24: =+JI24-JK24 -> 8147.8
FT25: 69915 | JI25: =SUM(A25:JH25) -> 69915 | JJ25: TRANSF. 023 | JK25: 66952.5 | JL25: =+JI25-JK25 -> 2962.5
FT26: 269394 | JI26: =SUM(A26:JH26) -> 269394 | JJ26: TRANSF. 024 | JK26: 257979 | JL26: =+JI26-JK26 -> 11415
FT27: 269158 | JI27: =SUM(A27:JH27) -> 269158 | JJ27: TRANSF. 025 | JK27: 257753 | JL27: =+JI27-JK27 -> 11405
FT28: 25110 | JI28: =SUM(A28:JH28) -> 25110 | JJ28: TRANSF. 026 | JK28: 25110 | JL28: =+JI28-JK28 -> 0
DK29: 405410 | JI29: =SUM(A29:JH29) -> 405410 | JJ29: TRANSF. 027 | JK29: 385139.5 | JL29: =+JI29-JK29 -> 20270.5
FT30: 47176.05 | JI30: =SUM(A30:JH30) -> 47176.05 | JJ30: TRANSF. 028 | JK30: 45177.07 | JL30: =+JI30-JK30 -> 1998.98
GC31: 3400 | JI31: =SUM(A31:JH31) -> 3400 | JJ31: 37174 | JK31: 3400 | JL31: =+JI31-JK31 -> 0
GA32: 49134.32 | JI32: =SUM(A32:JH32) -> 49134.32 | JJ32: 37175 | JK32: 49134.32 | JL32: =+JI32-JK32 -> 0
CJ33: 23600 | JI33: =SUM(A33:JH33) -> 23600 | JJ33: 37176 | JK33: 19600 | JL33: =+JI33-JK33 -> 4000
BW34: 21673.46 | JI34: =SUM(A34:JH34) -> 21673.46 | JJ34: 37177 | JK34: 18000 | JL34: =+JI34-JK34 -> 3673.46
BX35: 18061.22 | JI35: =SUM(A35:JH35) -> 18061.22 | JJ35: 37178 | JK35: 15000 | JL35: =+JI35-JK35 -> 3061.22
JI36: =SUM(A36:JH36) -> 0 | JJ36: 37179 | JK36: 0 | JL36: =+JI36-JK36 -> 0
BX37: 42142.86 | JI37: =SUM(A37:JH37) -> 42142.86 | JJ37: 37180 | JK37: 35000 | JL37: =+JI37-JK37 -> 7142.86
GA38: 50927.38 | JI38: =SUM(A38:JH38) -> 50927.38 | JJ38: 37181 | JK38: 50927.38 | JL38: =+JI38-JK38 -> 0
BX39: 18061.22 | JI39: =SUM(A39:JH39) -> 18061.22 | JJ39: 37182 | JK39: 15000 | JL39: =+JI39-JK39 -> 3061.22
BX40: 21673.47 | JI40: =SUM(A40:JH40) -> 21673.47 | JJ40: 37183 | JK40: 18000 | JL40: =+JI40-JK40 -> 3673.47
BX41: 31306.12 | JI41: =SUM(A41:JH41) -> 31306.12 | JJ41: 37184 | JK41: 26000 | JL41: =+JI41-JK41 -> 5306.12
GC42: 3400 | JI42: =SUM(A42:JH42) -> 3400 | JJ42: 37185 | JK42: 3400 | JL42: =+JI42-JK42 -> 0
JI43: =SUM(A43:JH43) -> 0 | JL43: =+JI43-JK43 -> 0
JI44: =SUM(A44:JH44) -> 0 | JL44: =+JI44-JK44 -> 0
JI45: =SUM(A45:JH45) -> 0 | JL45: =+JI45-JK45 -> 0
JI46: =SUM(A46:JH46) -> 0 | JL46: =+JI46-JK46 -> 0
JI47: =SUM(A47:JH47) -> 0 | JL47: =+JI47-JK47 -> 0
JI48: =SUM(A48:JH48) -> 0 | JL48: =+JI48-JK48 -> 0
JI49: =SUM(A49:JH49) -> 0 | JL49: =+JI49-JK49 -> 0
JI50: =SUM(A50:JH50) -> 0 | JL50: =+JI50-JK50 -> 0
JI51: =SUM(A51:JH51) -> 0 | JL51: =+JI51-JK51 -> 0
JI52: =SUM(A52:JH52) -> 0 | JL52: =+JI52-JK52 -> 0
JI53: =SUM(A53:JH53) -> 0 | JL53: =+JI53-JK53 -> 0
JI54: =SUM(A54:JH54) -> 0 | JL54: =+JI54-JK54 -> 0
... JI71: =SUM(A71:JH71) -> 0 | JL71: =+JI71-JK71 -> 0
JI72: =SUM(A72:JH72) -> 0 | JL72: =+JI72-JK72 -> 0 | JP72: =+JI72-JL72 -> 0
JI73: =SUM(A73:JH73) -> 0 | JL73: =+JI73-JK73 -> 0 | JP73: =+JI73-JL73 -> 0
JI74: =SUM(A74:JH74) -> 0 | JL74: =+JI74-JK74 -> 0 | JP74: =+JI74-JL74 -> 0
JI75: =SUM(A75:JH75) -> 0 | JL75: =+JI75-JK75 -> 0 | JP75: =+JI75-JL75 -> 0
CP76: 13357.35 | JI76: =SUM(A76:JH76) -> 13357.35 | JL76: =+JI76-JK76 -> 13357.35 | JP76: =+JI76-JL76 -> 0
JI77: =SUM(A77:JH77) -> 0 | JL77: =+JI77-JK77 -> 0 | JP77: =+JI77-JL77 -> 0
JI78: =SUM(A78:JH78) -> 0 | JL78: =+JI78-JK78 -> 0 | JP78: =+JI78-JL78 -> 0
A81: =SUM(A3:A80) -> 0 | B81: =SUM(B3:B80) -> 0 | C81: =SUM(C3:C80) -> 0 | D81: =SUM(D3:D80) -> 0 | E81: =SUM(E3:E80) -> 0 | F81: =SUM(F3:F80) -> 0 | G81: =SUM(G3:G80) -> 0 | H81: =SUM(H3:H80) -> 0 | ... JI81: =SUM(JI3:JI80) -> 6821436.5 | JK81: =SUM(JK3:JK80) -> 6526260.3 | JL81: =SUM(JL3:JL80) -> 295176.2 | JM81: =SUM(JM3:JM80) -> 0 | JN81: =SUM(JN3:JN80) -> 0 | JO81: =SUM(JO3:JO80) -> 0 | JQ81: =SUM(JQ3:JQ80) -> 0 | JR81: =SUM(JR3:JR80) -> 0 | JS81: =SUM(JS3:JS80) -> 0 | JT81: =SUM(JT3:JT80) -> 0 | JU81: =SUM(JU3:JU80) -> 0 | JV81: =SUM(JV3:JV80) -> 0

Sheet CUENTA T NOMINA SNS
A1: D E S G L O S E D E L A S C U E N T A S
A2: 211101 | B2: 211102 | C2: 211103 | D2: 211104 | E2: 211105 | F2: 211106 | G2: 211203 | H2: 211205 | I2: 211206 | J2: 211208 | K2: 211209 | L2: 211211 | M2: 211301 | N2: 211401 | O2: 211501 | P2: 211502 | Q2: 211503 | R2: 211504 | S2: 212101 | T2: 212201 | U2: 212203 | V2: 212204 | W2: 212205 | X2: 212206 | Y2: 212207 | Z2: 212208 | AA2: 212209 | AB2: 212210 | AC2: 213101 | AD2: 213102 | AE2: 213201 | AF2: 213202 | AG2: 214101 | AH2: 214201 | AI2: 214202 | AJ2: 214203 | AK2: 215101 | AL2: 215201 | AM2: 215301 | AN2: 215401 | AO2: Totales
AO3: =SUM(A3:AN3) -> 0
AO4: =SUM(A4:AN4) -> 0
AO5: =SUM(A5:AN5) -> 0
AO6: =SUM(A6:AN6) -> 0
AO7: =SUM(A7:AN7) -> 0
AO8: =SUM(A8:AN8) -> 0
AO9: =SUM(A9:AN9) -> 0
AO10: =SUM(A10:AN10) -> 0
AO11: =SUM(A11:AN11) -> 0
AO12: =SUM(A12:AN12) -> 0
AO13: =SUM(A13:AN13) -> 0
AO14: =SUM(A14:AN14) -> 0
... AO57: =SUM(A57:AN57) -> 0
A58: =SUM(A3:A57) -> 0 | B58: =SUM(B3:B57) -> 0 | C58: =SUM(C3:C57) -> 0 | D58: =SUM(D3:D57) -> 0 | E58: =SUM(E3:E57) -> 0 | F58: =SUM(F3:F57) -> 0 | G58: =SUM(G3:G57) -> 0 | H58: =SUM(H3:H57) -> 0 | ... AO58: =SUM(AO3:AO57) -> 0 | AQ58: 0

Sheet GASTOS X ATENCION
A1: SERVICIO NACIONAL DE SALUD
A2: ='CONS. FUENTES FINAN'!A6 -> HOSPITAL MATERNO INFANTIL SAN LORENZO DE LOS MINA
A3: RESUMEN COMPARATIVO DE GASTOS ESPECIFICOS FONDO 100 Y VENTA DE SERVICIOS
A6: DETALLE | B6: REPONIBLE | C6: VENTA SERVICIOS | D6: TOTAL | E6: %
A8: Atención Directa
A9: Medicamentos e Insumos Médicos | B9: ='CONS. FUENTES FINAN'!G245+'CONS. FUENTES FINAN'!G315 -> 3125937.8 | C9: ='CONS. FUENTES FINAN'!H245+'CONS. FUENTES FINAN'!H315 -> 2107341.1 | D9: =SUM(B9:C9) -> 5233278.9 | E9: =+D9/D12 -> 0.73865849
A10: Oxigeno | B10: ='CONS. FUENTES FINAN'!G302 -> 0 | C10: ='CONS. FUENTES FINAN'!H302 -> 0 | D10: =SUM(B10:C10) -> 0 | E10: =+D10/D12 -> 0
A11: Reactivos e Insumos de Laboratorio | B11: ='CONS. FUENTES FINAN'!G296+'CONS. FUENTES FINAN'!G297+'CONS. FUENTES FINAN'!G298 -> 1844663.4 | C11: ='CONS. FUENTES FINAN'!H296+'CONS. FUENTES FINAN'!H297+'CONS. FUENTES FINAN'!H298 -> 6900 | D11: =SUM(B11:C11) -> 1851563.4 | E11: =+D11/D12 -> 0.26134151
A12: Total | B12: =SUM(B9:B11) -> 4970601.2 | C12: =SUM(C9:C11) -> 2114241.1 | D12: =SUM(D9:D11) -> 7084842.3 | E12: =+D12/D39 -> 0.0921507
A13: Mantenimiento de Equipos
A14: Reparación y Mantenimiento Maquinaria y Eq. | B14: ='CONS. FUENTES FINAN'!G157+'CONS. FUENTES FINAN'!G188+'CONS. FUENTES FINAN'!G223+'CONS. FUENTES FINAN'!G252+'CONS. FUENTES FINAN'!G254+'CONS. FUENTES FINAN'!G256+'CONS. FUENTES FINAN'!G258+'CONS. FUENTES FINAN'!G261+'CONS. FUENTES FINAN'!G292+'CONS. FUENTES FINAN'!G293+'CONS. FUENTES FINAN'!G299+'CONS. FUENTES FINAN'!G300+'CONS. FUENTES FINAN'!G301+'CONS. FUENTES FINAN'!G324 -> 0 | C14: ='CONS. FUENTES FINAN'!H157+'CONS. FUENTES FINAN'!H188+'CONS. FUENTES FINAN'!H223+'CONS. FUENTES FINAN'!H252+'CONS. FUENTES FINAN'!H254+'CONS. FUENTES FINAN'!H256+'CONS. FUENTES FINAN'!H258+'CONS. FUENTES FINAN'!H261+'CONS. FUENTES FINAN'!H292+'CONS. FUENTES FINAN'!H293+'CONS. FUENTES FINAN'!H299+'CONS. FUENTES FINAN'!H300+'CONS. FUENTES FINAN'!H301+'CONS. FUENTES FINAN'!H324 -> 2074666.4 | D14: =SUM(B14:C14) -> 2074666.4 | E14: =+D14/D16 -> 1
A15: Productos Eléctricos y Afines | B15: ='CONS. FUENTES FINAN'!G320 -> 0 | C15: ='CONS. FUENTES FINAN'!H320 -> 0 | D15: =SUM(B15:C15) -> 0 | E15: =+D15/D16 -> 0
A16: Total | B16: =SUM(B14:B15) -> 0 | C16: =SUM(C14:C15) -> 2074666.4 | D16: =SUM(D14:D15) -> 2074666.4 | E16: =+D16/D39 -> 0.026984645
A17: Gastos Administrativos
A18: Servicios Personales | B18: ='CONS. FUENTES FINAN'!G26 -> 65091180 | C18: ='CONS. FUENTES FINAN'!H26 -> 0 | D18: =SUM(B18:C18) -> 65091180 | E18: =+D18/D34 -> 0.97389817
A19: Servicio Telefónico | B19: ='CONS. FUENTES FINAN'!G91+'CONS. FUENTES FINAN'!G93+'CONS. FUENTES FINAN'!G95+'CONS. FUENTES FINAN'!G97 -> 0 | C19: ='CONS. FUENTES FINAN'!H91+'CONS. FUENTES FINAN'!H93+'CONS. FUENTES FINAN'!H95+'CONS. FUENTES FINAN'!H97 -> 301316.33 | D19: =SUM(B19:C19) -> 301316.33 | E19: =+D19/D34 -> 0.0045083132
A20: Servicios Basicos (electricidad, agua y residuos solidos) | B20: ='CONS. FUENTES FINAN'!G99+'CONS. FUENTES FINAN'!G102+'CONS. FUENTES FINAN'!G104 -> 0 | C20: ='CONS. FUENTES FINAN'!H99+'CONS. FUENTES FINAN'!H102+'CONS. FUENTES FINAN'!H104 -> 50000 | D20: =SUM(B20:C20) -> 50000 | E20: =+D20/D34 -> 0.00074810303
A21: Viáticos | B21: ='CONS. FUENTES FINAN'!G111 -> 0 | C21: ='CONS. FUENTES FINAN'!H111 -> 0 | D21: =SUM(B21:C21) -> 0 | E21: =+D21/D34 -> 0
A22: Transporte y almacenaje | B22: ='CONS. FUENTES FINAN'!G116 -> 0 | C22: ='CONS. FUENTES FINAN'!H116 -> 0 | D22: =SUM(B22:C22) -> 0 | E22: =+D22/D34 -> 0
A23: Alquileres | B23: ='CONS. FUENTES FINAN'!G125 -> 0 | C23: ='CONS. FUENTES FINAN'!H125 -> 266664.26 | D23: =SUM(B23:C23) -> 266664.26 | E23: =+D23/D34 -> 0.0039898468
A24: Comisiones y Gastos Bancarios | B24: ='CONS. FUENTES FINAN'!G182 -> 0 | C24: ='CONS. FUENTES FINAN'!H182 -> 13357.35 | D24: =SUM(B24:C24) -> 13357.35 | E24: =+D24/D34 -> 0.00019985348
A25: Materiales de Oficina, Impresión y Encuadernación | B25: ='CONS. FUENTES FINAN'!G109+'CONS. FUENTES FINAN'!G312 -> 0 | C25: ='CONS. FUENTES FINAN'!H109+'CONS. FUENTES FINAN'!H312 -> 0 | D25: =SUM(B25:C25) -> 0 | E25: =+D25/D34 -> 0
A26: Alimentos y Bebidas para Personas | B26: ='CONS. FUENTES FINAN'!G208+'CONS. FUENTES FINAN'!G214+'CONS. FUENTES FINAN'!G217+'CONS. FUENTES FINAN'!G219 -> 0 | C26: ='CONS. FUENTES FINAN'!H208+'CONS. FUENTES FINAN'!H214+'CONS. FUENTES FINAN'!H217+'CONS. FUENTES FINAN'!H219 -> 541265 | D26: =SUM(B26:C26) -> 541265 | E26: =+D26/D34 -> 0.0080984397
A27: Productos de papel, carton e impesos | B27: ='CONS. FUENTES FINAN'!G232 -> 0 | C27: ='CONS. FUENTES FINAN'!H232 -> 85550 | D27: =SUM(B27:C27) -> 85550 | E27: =+D27/D34 -> 0.0012800043
A28: Articulos de Plasticos | B28: ='CONS. FUENTES FINAN'!G259 -> 0 | C28: ='CONS. FUENTES FINAN'!H259 -> 0 | D28: =SUM(B28:C28) -> 0 | E28: =+D28/D34 -> 0
A29: Gasolina | B29: ='CONS. FUENTES FINAN'!G288 -> 0 | C29: ='CONS. FUENTES FINAN'!H288 -> 172000 | D29: =SUM(B29:C29) -> 172000 | E29: =+D29/D34 -> 0.0025734744
A30: Gasoil | B30: ='CONS. FUENTES FINAN'!G289+'CONS. FUENTES FINAN'!G290 -> 0 | C30: ='CONS. FUENTES FINAN'!H289+'CONS. FUENTES FINAN'!H290 -> 0 | D30: =SUM(B30:C30) -> 0 | E30: =+D30/D34 -> 0
A31: GLP | B31: ='CONS. FUENTES FINAN'!G291+'CONS. FUENTES FINAN'!G294 -> 0 | C31: ='CONS. FUENTES FINAN'!H291+'CONS. FUENTES FINAN'!H294 -> 49512.84 | D31: =SUM(B31:C31) -> 49512.84 | E31: =+D31/D34 -> 0.00074081411
A32: Materiales de Limpieza e Higiene | B32: ='CONS. FUENTES FINAN'!G309 -> 0 | C32: ='CONS. FUENTES FINAN'!H309 -> 0 | D32: =SUM(B32:C32) -> 0 | E32: =+D32/D34 -> 0
A33: Otros Egresos y Gastos | B33: ='CONS. FUENTES FINAN'!G89+'CONS. FUENTES FINAN'!G107+'CONS. FUENTES FINAN'!G148+'CONS. FUENTES FINAN'!G180+'CONS. FUENTES FINAN'!G184+'CONS. FUENTES FINAN'!G186+'CONS. FUENTES FINAN'!G192+'CONS. FUENTES FINAN'!G197+'CONS. FUENTES FINAN'!G204+'CONS. FUENTES FINAN'!G225+'CONS. FUENTES FINAN'!G303+'CONS. FUENTES FINAN'!G316+'CONS. FUENTES FINAN'!G318+'CONS. FUENTES FINAN'!G322+'CONS. FUENTES FINAN'!G327+'CONS. FUENTES FINAN'!G330 -> 0 | C33: ='CONS. FUENTES FINAN'!H89+'CONS. FUENTES FINAN'!H107+'CONS. FUENTES FINAN'!H148+'CONS. FUENTES FINAN'!H180+'CONS. FUENTES FINAN'!H184+'CONS. FUENTES FINAN'!H186+'CONS. FUENTES FINAN'!H192+'CONS. FUENTES FINAN'!H197+'CONS. FUENTES FINAN'!H204+'CONS. FUENTES FINAN'!H225+'CONS. FUENTES FINAN'!H303+'CONS. FUENTES FINAN'!H316+'CONS. FUENTES FINAN'!H318+'CONS. FUENTES FINAN'!H322+'CONS. FUENTES FINAN'!H327+'CONS. FUENTES FINAN'!H330 -> 264868.4 | D33: =SUM(B33:C33) -> 264868.4 | E33: =+D33/D34 -> 0.003962977
A34: Total | B34: =SUM(B17:B33) -> 65091180 | C34: =SUM(C17:C33) -> 1744534.2 | D34: =SUM(D17:D33) -> 66835714 | E34: =+D34/D39 -> 0.86931474
A35: Gastos Inversion y Capital
A36: Bienes Muebles, Inmuebles e Intangibles | B36: ='CONS. FUENTES FINAN'!G336 -> 0 | C36: ='CONS. FUENTES FINAN'!H336 -> 887994.84 | D36: =SUM(B36:C36) -> 887994.84 | E36: =+D36/D38 -> 1
A37: Obras | B37: ='CONS. FUENTES FINAN'!G463 -> 0 | C37: ='CONS. FUENTES FINAN'!H463 -> 0 | D37: =SUM(B37:C37) -> 0 | E37: =+D37/D38 -> 0
A38: Total | B38: =SUM(B36:B37) -> 0 | C38: =SUM(C36:C37) -> 887994.84 | D38: =SUM(D36:D37) -> 887994.84 | E38: =+D38/D39 -> 0.011549918
A39: Total General | B39: =+B12+B16+B34+B38 -> 70061781 | C39: =+C12+C16+C34+C38 -> 6821436.5 | D39: =+D12+D16+D34+D38 -> 76883218 | E39: =+E12+E16+E34+E38 -> 1
A40: Porciento | B40: =+B39/D39 -> 0.91127535 | C40: =+C39/D39 -> 0.088724649 | D40: =+B40+C40 -> 1

Sheet PLANTILLA PRESUPUESTO
A1: SERVICIO NACIONAL DE SALUD
A2: NOMBRE DEL ESTABLECIMIENTO
A3: CONSOLIDADO GASTOS EJECUCION FINANCIERA 2024
A4: En RD$
A6: Detalle | B6: FONDO GENERAL 100 | G6: VENTA SEVICIOS/OTROS APORTES | L6: TOTAL
A7: 2 - GASTOS | B7: 1ro | C7: 2do | D7: 3ro | E7: 4to | G7: 1ro | H7: 2do | I7: 3ro | J7: 4to | L7: 1ro | M7: 2do | N7: 3ro | O7: 4to
A8: 2.1 - REMUNERACIONES Y CONTRIBUCIONES | B8: =SUM(B9:B13) -> 65091180 | C8: =SUM(C9:C13) -> 0 | D8: =SUM(D9:D13) -> 0 | E8: =SUM(E9:E13) -> 0 | G8: =SUM(G9:G13) -> 0 | H8: =SUM(H9:H13) -> 0 | I8: =SUM(I9:I13) -> 0 | J8: =SUM(J9:J13) -> 0 | L8: =SUM(B8+G8) -> 65091180 | M8: =SUM(C8+H8) -> 0 | N8: =SUM(D8+I8) -> 0 | O8: =SUM(E8+J8) -> 0
A9: 2.1.1 - REMUNERACIONES | B9: =SUM('TRANSFERENCIA CORRIENTE'!C10:E10) -> 53640339 | C9: =SUM('TRANSFERENCIA CORRIENTE'!F10:H10) -> 0 | D9: =SUM('TRANSFERENCIA CORRIENTE'!I10:K10) -> 0 | E9: =SUM('TRANSFERENCIA CORRIENTE'!L10:N10) -> 0 | G9: =SUM(VS!C10:E10) -> 0 | H9: =SUM(VS!F10:H10) -> 0 | I9: =SUM(VS!I10:K10) -> 0 | J9: =SUM(VS!L10:N10) -> 0 | L9: =SUM(B9+G9) -> 53640339 | M9: =SUM(C9+H9) -> 0 | N9: =SUM(D9+I9) -> 0 | O9: =SUM(E9+J9) -> 0
A10: 2.1.2 - SOBRESUELDOS | B10: =SUM('TRANSFERENCIA CORRIENTE'!C11:E11) -> 3196999.6 | C10: =SUM('TRANSFERENCIA CORRIENTE'!F11:H11) -> 0 | D10: =SUM('TRANSFERENCIA CORRIENTE'!I11:K11) -> 0 | E10: =SUM('TRANSFERENCIA CORRIENTE'!L11:N11) -> 0 | G10: =SUM(VS!C11:E11) -> 0 | H10: =SUM(VS!F11:H11) -> 0 | I10: =SUM(VS!I11:K11) -> 0 | J10: =SUM(VS!L11:N11) -> 0 | L10: =SUM(B10+G10) -> 3196999.6 | M10: =SUM(C10+H10) -> 0 | N10: =SUM(D10+I10) -> 0 | O10: =SUM(E10+J10) -> 0
A11: 2.1.3 - DIETAS Y GASTOS DE REPRESENTACIÓN | B11: =SUM('TRANSFERENCIA CORRIENTE'!C12:E12) -> 0 | C11: =SUM('TRANSFERENCIA CORRIENTE'!F12:H12) -> 0 | D11: =SUM('TRANSFERENCIA CORRIENTE'!I12:K12) -> 0 | E11: =SUM('TRANSFERENCIA CORRIENTE'!L12:N12) -> 0 | G11: =SUM(VS!C12:E12) -> 0 | H11: =SUM(VS!F12:H12) -> 0 | I11: =SUM(VS!I12:K12) -> 0 | J11: =SUM(VS!L12:N12) -> 0 | L11: =SUM(B11+G11) -> 0 | M11: =SUM(C11+H11) -> 0 | N11: =SUM(D11+I11) -> 0 | O11: =SUM(E11+J11) -> 0
A12: 2.1.4 - GRATIFICACIONES Y BONIFICACIONES | B12: =SUM('TRANSFERENCIA CORRIENTE'!C13:E13) -> 0 | C12: =SUM('TRANSFERENCIA CORRIENTE'!F13:H13) -> 0 | D12: =SUM('TRANSFERENCIA CORRIENTE'!I13:K13) -> 0 | E12: =SUM('TRANSFERENCIA CORRIENTE'!L13:N13) -> 0 | G12: =SUM(VS!C13:E13) -> 0 | H12: =SUM(VS!F13:H13) -> 0 | I12: =SUM(VS!I13:K13) -> 0 | J12: =SUM(VS!L13:N13) -> 0 | L12: =SUM(B12+G12) -> 0 | M12: =SUM(C12+H12) -> 0 | N12: =SUM(D12+I12) -> 0 | O12: =SUM(E12+J12) -> 0
A13: 2.1.5 - CONTRIBUCIONES A LA SEGURIDAD SOCIAL | B13: =SUM('TRANSFERENCIA CORRIENTE'!C14:E14) -> 8253841.6 | C13: =SUM('TRANSFERENCIA CORRIENTE'!F14:H14) -> 0 | D13: =SUM('TRANSFERENCIA CORRIENTE'!I14:K14) -> 0 | E13: =SUM('TRANSFERENCIA CORRIENTE'!L14:N14) -> 0 | G13: =SUM(VS!C14:E14) -> 0 | H13: =SUM(VS!F14:H14) -> 0 | I13: =SUM(VS!I14:K14) -> 0 | J13: =SUM(VS!L14:N14) -> 0 | L13: =SUM(B13+G13) -> 8253841.6 | M13: =SUM(C13+H13) -> 0 | N13: =SUM(D13+I13) -> 0 | O13: =SUM(E13+J13) -> 0
A14: 2.2 - CONTRATACIÓN DE SERVICIOS | B14: =SUM(B15:B23) -> 0 | C14: =SUM(C15:C23) -> 0 | D14: =SUM(D15:D23) -> 0 | E14: =SUM(E15:E23) -> 0 | G14: =SUM(G15:G23) -> 2733844.3 | H14: =SUM(H15:H23) -> 0 | I14: =SUM(I15:I23) -> 0 | J14: =SUM(J15:J23) -> 0 | L14: =SUM(B14+G14) -> 2733844.3 | M14: =SUM(C14+H14) -> 0 | N14: =SUM(D14+I14) -> 0 | O14: =SUM(E14+J14) -> 0
A15: 2.2.1 - SERVICIOS BÁSICOS | B15: =SUM('TRANSFERENCIA CORRIENTE'!C16:E16) -> 0 | C15: =SUM('TRANSFERENCIA CORRIENTE'!F16:H16) -> 0 | D15: =SUM('TRANSFERENCIA CORRIENTE'!J16:L16) -> 0 | E15: =SUM('TRANSFERENCIA CORRIENTE'!L16:N16) -> 0 | G15: =SUM(VS!C16:E16) -> 351316.33 | H15: =SUM(VS!F16:H16) -> 0 | I15: =SUM(VS!I16:K16) -> 0 | J15: =SUM(VS!L16:N16) -> 0 | L15: =SUM(B15+G15) -> 351316.33 | M15: =SUM(C15+H15) -> 0 | N15: =SUM(D15+I15) -> 0 | O15: =SUM(E15+J15) -> 0
A16: 2.2.2 - PUBLICIDAD, IMPRESIÓN Y ENCUADERNACIÓN | B16: =SUM('TRANSFERENCIA CORRIENTE'!C17:E17) -> 0 | C16: =SUM('TRANSFERENCIA CORRIENTE'!F17:H17) -> 0 | D16: =SUM('TRANSFERENCIA CORRIENTE'!J17:L17) -> 0 | E16: =SUM('TRANSFERENCIA CORRIENTE'!L17:N17) -> 0 | G16: =SUM(VS!C17:E17) -> 0 | H16: =SUM(VS!F17:H17) -> 0 | I16: =SUM(VS!I17:K17) -> 0 | J16: =SUM(VS!L17:N17) -> 0 | L16: =SUM(B16+G16) -> 0 | M16: =SUM(C16+H16) -> 0 | N16: =SUM(D16+I16) -> 0 | O16: =SUM(E16+J16) -> 0
A17: 2.2.3 - VIÁTICOS | B17: =SUM('TRANSFERENCIA CORRIENTE'!C18:E18) -> 0 | C17: =SUM('TRANSFERENCIA CORRIENTE'!F18:H18) -> 0 | D17: =SUM('TRANSFERENCIA CORRIENTE'!J18:L18) -> 0 | E17: =SUM('TRANSFERENCIA CORRIENTE'!L18:N18) -> 0 | G17: =SUM(VS!C18:E18) -> 0 | H17: =SUM(VS!F18:H18) -> 0 | I17: =SUM(VS!I18:K18) -> 0 | J17: =SUM(VS!L18:N18) -> 0 | L17: =SUM(B17+G17) -> 0 | M17: =SUM(C17+H17) -> 0 | N17: =SUM(D17+I17) -> 0 | O17: =SUM(E17+J17) -> 0
A18: 2.2.4 - TRANSPORTE Y ALMACENAJE | B18: =SUM('TRANSFERENCIA CORRIENTE'!C19:E19) -> 0 | C18: =SUM('TRANSFERENCIA CORRIENTE'!F19:H19) -> 0 | D18: =SUM('TRANSFERENCIA CORRIENTE'!J19:L19) -> 0 | E18: =SUM('TRANSFERENCIA CORRIENTE'!L19:N19) -> 0 | G18: =SUM(VS!C19:E19) -> 0 | H18: =SUM(VS!F19:H19) -> 0 | I18: =SUM(VS!I19:K19) -> 0 | J18: =SUM(VS!L19:N19) -> 0 | L18: =SUM(B18+G18) -> 0 | M18: =SUM(C18+H18) -> 0 | N18: =SUM(D18+I18) -> 0 | O18: =SUM(E18+J18) -> 0
A19: 2.2.5 - ALQUILERES Y RENTAS | B19: =SUM('TRANSFERENCIA CORRIENTE'!C20:E20) -> 0 | C19: =SUM('TRANSFERENCIA CORRIENTE'!F20:H20) -> 0 | D19: =SUM('TRANSFERENCIA CORRIENTE'!J20:L20) -> 0 | E19: =SUM('TRANSFERENCIA CORRIENTE'!L20:N20) -> 0 | G19: =SUM(VS!C20:E20) -> 266664.26 | H19: =SUM(VS!F20:H20) -> 0 | I19: =SUM(VS!I20:K20) -> 0 | J19: =SUM(VS!L20:N20) -> 0 | L19: =SUM(B19+G19) -> 266664.26 | M19: =SUM(C19+H19) -> 0 | N19: =SUM(D19+I19) -> 0 | O19: =SUM(E19+J19) -> 0
A20: 2.2.6 - SEGUROS | B20: =SUM('TRANSFERENCIA CORRIENTE'!C21:E21) -> 0 | C20: =SUM('TRANSFERENCIA CORRIENTE'!F21:H21) -> 0 | D20: =SUM('TRANSFERENCIA CORRIENTE'!J21:L21) -> 0 | E20: =SUM('TRANSFERENCIA CORRIENTE'!L21:N21) -> 0 | G20: =SUM(VS!C21:E21) -> 0 | H20: =SUM(VS!F21:H21) -> 0 | I20: =SUM(VS!I21:K21) -> 0 | J20: =SUM(VS!L21:N21) -> 0 | L20: =SUM(B20+G20) -> 0 | M20: =SUM(C20+H20) -> 0 | N20: =SUM(D20+I20) -> 0 | O20: =SUM(E20+J20) -> 0
A21: 2.2.7 - SERVICIOS DE CONSERVACIÓN, REPARACIONES MENORES E INSTALACIONES TEMPORALES | B21: =SUM('TRANSFERENCIA CORRIENTE'!C22:E22) -> 0 | C21: =SUM('TRANSFERENCIA CORRIENTE'!F22:H22) -> 0 | D21: =SUM('TRANSFERENCIA CORRIENTE'!J22:L22) -> 0 | E21: =SUM('TRANSFERENCIA CORRIENTE'!L22:N22) -> 0 | G21: =SUM(VS!C22:E22) -> 2064518.4 | H21: =SUM(VS!F22:H22) -> 0 | I21: =SUM(VS!I22:K22) -> 0 | J21: =SUM(VS!L22:N22) -> 0 | L21: =SUM(B21+G21) -> 2064518.4 | M21: =SUM(C21+H21) -> 0 | N21: =SUM(D21+I21) -> 0 | O21: =SUM(E21+J21) -> 0
A22: 2.2.8 - OTROS SERVICIOS NO INCLUIDOS EN CONCEPTOS ANTERIORES | B22: =SUM('TRANSFERENCIA CORRIENTE'!C23:E23) -> 0 | C22: =SUM('TRANSFERENCIA CORRIENTE'!F23:H23) -> 0 | D22: =SUM('TRANSFERENCIA CORRIENTE'!J23:L23) -> 0 | E22: =SUM('TRANSFERENCIA CORRIENTE'!L23:N23) -> 0 | G22: =SUM(VS!C23:E23) -> 51345.35 | H22: =SUM(VS!F23:H23) -> 0 | I22: =SUM(VS!I23:K23) -> 0 | J22: =SUM(VS!L23:N23) -> 0 | L22: =SUM(B22+G22) -> 51345.35 | M22: =SUM(C22+H22) -> 0 | N22: =SUM(D22+I22) -> 0 | O22: =SUM(E22+J22) -> 0
A23: 2.2.9 - OTRAS CONTRATACIONES DE SERVICIOS | B23: =SUM('TRANSFERENCIA CORRIENTE'!C24:E24) -> 0 | C23: =SUM('TRANSFERENCIA CORRIENTE'!F24:H24) -> 0 | D23: =SUM('TRANSFERENCIA CORRIENTE'!J24:L24) -> 0 | E23: =SUM('TRANSFERENCIA CORRIENTE'!L24:N24) -> 0 | G23: =SUM(VS!C24:E24) -> 0 | H23: =SUM(VS!F24:H24) -> 0 | I23: =SUM(VS!I24:K24) -> 0 | J23: =SUM(VS!L24:N24) -> 0 | L23: =SUM(B23+G23) -> 0 | M23: =SUM(C23+H23) -> 0 | N23: =SUM(D23+I23) -> 0 | O23: =SUM(E23+J23) -> 0
A24: 2.3 - MATERIALES Y SUMINISTROS | B24: =SUM(B25:B33) -> 4970600.4 | C24: =SUM(C25:C33) -> 0 | D24: =SUM(D25:D33) -> 0 | E24: =SUM(E25:E33) -> 0 | G24: =SUM(G25:G33) -> 3062630.7 | H24: =SUM(H25:H33) -> 0 | I24: =SUM(I25:I33) -> 0 | J24: =SUM(J25:J33) -> 0 | L24: =SUM(B24+G24) -> 8033231.1 | M24: =SUM(C24+H24) -> 0 | N24: =SUM(D24+I24) -> 0 | O24: =SUM(E24+J24) -> 0
A25: 2.3.1 - ALIMENTOS Y PRODUCTOS AGROFORESTALES | B25: =SUM('TRANSFERENCIA CORRIENTE'!C26:E26) -> 0 | C25: =SUM('TRANSFERENCIA CORRIENTE'!F26:H26) -> 0 | D25: =SUM('TRANSFERENCIA CORRIENTE'!I23:K23) -> 0 | E25: =SUM('TRANSFERENCIA CORRIENTE'!L26:N26) -> 0 | G25: =SUM(VS!C26:E26) -> 541265 | H25: =SUM(VS!F26:H26) -> 0 | I25: =SUM(VS!I26:K26) -> 0 | J25: =SUM(VS!L26:N26) -> 0 | L25: =SUM(B25+G25) -> 541265 | M25: =SUM(C25+H25) -> 0 | N25: =SUM(D25+I25) -> 0 | O25: =SUM(E25+J25) -> 0
A26: 2.3.2 - TEXTILES Y VESTUARIOS | B26: =SUM('TRANSFERENCIA CORRIENTE'!C27:E27) -> 0 | C26: =SUM('TRANSFERENCIA CORRIENTE'!F27:H27) -> 0 | D26: =SUM('TRANSFERENCIA CORRIENTE'!I24:K24) -> 0 | E26: =SUM('TRANSFERENCIA CORRIENTE'!L27:N27) -> 0 | G26: =SUM(VS!C27:E27) -> 0 | H26: =SUM(VS!F27:H27) -> 0 | I26: =SUM(VS!I27:K27) -> 0 | J26: =SUM(VS!L27:N27) -> 0 | L26: =SUM(B26+G26) -> 0 | M26: =SUM(C26+H26) -> 0 | N26: =SUM(D26+I26) -> 0 | O26: =SUM(E26+J26) -> 0
A27: 2.3.3 - PRODUCTOS DE PAPEL, CARTÓN E IMPRESOS | B27: =SUM('TRANSFERENCIA CORRIENTE'!C28:E28) -> 0 | C27: =SUM('TRANSFERENCIA CORRIENTE'!F28:H28) -> 0 | D27: =SUM('TRANSFERENCIA CORRIENTE'!I25:K25) -> 0 | E27: =SUM('TRANSFERENCIA CORRIENTE'!L28:N28) -> 0 | G27: =SUM(VS!C28:E28) -> 85550 | H27: =SUM(VS!F28:H28) -> 0 | I27: =SUM(VS!I28:K28) -> 0 | J27: =SUM(VS!L28:N28) -> 0 | L27: =SUM(B27+G27) -> 85550 | M27: =SUM(C27+H27) -> 0 | N27: =SUM(D27+I27) -> 0 | O27: =SUM(E27+J27) -> 0
A28: 2.3.4 - PRODUCTOS FARMACÉUTICOS | B28: =SUM('TRANSFERENCIA CORRIENTE'!C29:E29) -> 1862880 | C28: =SUM('TRANSFERENCIA CORRIENTE'!F29:H29) -> 0 | D28: =SUM('TRANSFERENCIA CORRIENTE'!I26:K26) -> 0 | E28: =SUM('TRANSFERENCIA CORRIENTE'!L29:N29) -> 0 | G28: =SUM(VS!C29:E29) -> 308000 | H28: =SUM(VS!F29:H29) -> 0 | I28: =SUM(VS!I29:K29) -> 0 | J28: =SUM(VS!L29:N29) -> 0 | L28: =SUM(B28+G28) -> 2170880 | M28: =SUM(C28+H28) -> 0 | N28: =SUM(D28+I28) -> 0 | O28: =SUM(E28+J28) -> 0
A29: 2.3.5 - PRODUCTOS DE CUERO, CAUCHO Y PLÁSTICO | B29: =SUM('TRANSFERENCIA CORRIENTE'!C30:E30) -> 0 | C29: =SUM('TRANSFERENCIA CORRIENTE'!F30:H30) -> 0 | D29: =SUM('TRANSFERENCIA CORRIENTE'!I27:K27) -> 0 | E29: =SUM('TRANSFERENCIA CORRIENTE'!L30:N30) -> 0 | G29: =SUM(VS!C30:E30) -> 0 | H29: =SUM(VS!F30:H30) -> 0 | I29: =SUM(VS!I30:K30) -> 0 | J29: =SUM(VS!L30:N30) -> 0 | L29: =SUM(B29+G29) -> 0 | M29: =SUM(C29+H29) -> 0 | N29: =SUM(D29+I29) -> 0 | O29: =SUM(E29+J29) -> 0
A30: 2.3.6 - PRODUCTOS DE MINERALES, METÁLICOS Y NO METÁLICOS | B30: =SUM('TRANSFERENCIA CORRIENTE'!C31:E31) -> 0 | C30: =SUM('TRANSFERENCIA CORRIENTE'!F31:H31) -> 0 | D30: =SUM('TRANSFERENCIA CORRIENTE'!I28:K28) -> 0 | E30: =SUM('TRANSFERENCIA CORRIENTE'!L31:N31) -> 0 | G30: =SUM(VS!C31:E31) -> 0 | H30: =SUM(VS!F31:H31) -> 0 | I30: =SUM(VS!I31:K31) -> 0 | J30: =SUM(VS!L31:N31) -> 0 | L30: =SUM(B30+G30) -> 0 | M30: =SUM(C30+H30) -> 0 | N30: =SUM(D30+I30) -> 0 | O30: =SUM(E30+J30) -> 0
A31: 2.3.7 - COMBUSTIBLES, LUBRICANTES, PRODUCTOS QUÍMICOS Y CONEXOS | B31: =SUM('TRANSFERENCIA CORRIENTE'!C32:E32) -> 1844663.4 | C31: =SUM('TRANSFERENCIA CORRIENTE'!F32:H32) -> 0 | D31: =SUM('TRANSFERENCIA CORRIENTE'!I29:K29) -> 0 | E31: =SUM('TRANSFERENCIA CORRIENTE'!L32:N32) -> 0 | G31: =SUM(VS!C32:E32) -> 228412.84 | H31: =SUM(VS!F32:H32) -> 0 | I31: =SUM(VS!I32:K32) -> 0 | J31: =SUM(VS!L32:N32) -> 0 | L31: =SUM(B31+G31) -> 2073076.2 | M31: =SUM(C31+H31) -> 0 | N31: =SUM(D31+I31) -> 0 | O31: =SUM(E31+J31) -> 0
A32: 2.3.8 - GASTOS QUE SE ASIGNARÁN DURANTE EL EJERCICIO (ART. 32 Y 33 LEY 423-06) | B32: =SUM('TRANSFERENCIA CORRIENTE'!C33:E33) -> 0 | C32: =SUM('TRANSFERENCIA CORRIENTE'!F33:H33) -> 0 | D32: =SUM('TRANSFERENCIA CORRIENTE'!I30:K30) -> 0 | E32: =SUM('TRANSFERENCIA CORRIENTE'!L33:N33) -> 0 | G32: =SUM(VS!C33:E33) -> 0 | H32: =SUM(VS!F33:H33) -> 0 | I32: =SUM(VS!I33:K33) -> 0 | J32: =SUM(VS!L33:N33) -> 0 | L32: =SUM(B32+G32) -> 0 | M32: =SUM(C32+H32) -> 0 | N32: =SUM(D32+I32) -> 0 | O32: =SUM(E32+J32) -> 0
A33: 2.3.9 - PRODUCTOS Y ÚTILES VARIOS | B33: =SUM('TRANSFERENCIA CORRIENTE'!C34:E34) -> 1263057 | C33: =SUM('TRANSFERENCIA CORRIENTE'!F34:H34) -> 0 | D33: =SUM('TRANSFERENCIA CORRIENTE'!I31:K31) -> 0 | E33: =SUM('TRANSFERENCIA CORRIENTE'!L34:N34) -> 0 | G33: =SUM(VS!C34:E34) -> 1899402.8 | H33: =SUM(VS!F34:H34) -> 0 | I33: =SUM(VS!I34:K34) -> 0 | J33: =SUM(VS!L34:N34) -> 0 | L33: =SUM(B33+G33) -> 3162459.8 | M33: =SUM(C33+H33) -> 0 | N33: =SUM(D33+I33) -> 0 | O33: =SUM(E33+J33) -> 0
A34: 2.4 - TRANSFERENCIAS CORRIENTES | B34: =SUM(B35:B41) -> 0 | C34: =SUM(C35:C41) -> 0 | D34: =SUM(D35:D41) -> 0 | E34: =SUM(E35:E41) -> 0 | G34: =SUM(G35:G41) -> 136966.7 | H34: =SUM(H35:H41) -> 0 | I34: =SUM(I35:I41) -> 0 | J34: =SUM(J35:J41) -> 0 | L34: =SUM(B34+G34) -> 136966.7 | M34: =SUM(C34+H34) -> 0 | N34: =SUM(D34+I34) -> 0 | O34: =SUM(E34+J34) -> 0
A35: 2.4.1 - TRANSFERENCIAS CORRIENTES AL SECTOR PRIVADO | B35: =SUM('TRANSFERENCIA CORRIENTE'!C36:E36) -> 0 | C35: =SUM('TRANSFERENCIA CORRIENTE'!F36:H36) -> 0 | D35: =SUM('TRANSFERENCIA CORRIENTE'!I36:K36) -> 0 | E35: =SUM('TRANSFERENCIA CORRIENTE'!L36:N36) -> 0 | G35: =SUM(VS!C36:E36) -> 136966.7 | H35: =SUM(VS!F36:H36) -> 0 | I35: =SUM(VS!I36:K36) -> 0 | J35: =SUM(VS!L36:N36) -> 0 | L35: =SUM(B35+G35) -> 136966.7 | M35: =SUM(C35+H35) -> 0 | N35: =SUM(D35+I35) -> 0 | O35: =SUM(E35+J35) -> 0
A36: 2.4.2 - TRANSFERENCIAS CORRIENTES AL GOBIERNO GENERAL NACIONAL | B36: =SUM('TRANSFERENCIA CORRIENTE'!C37:E37) -> 0 | C36: =SUM('TRANSFERENCIA CORRIENTE'!F37:H37) -> 0 | D36: =SUM('TRANSFERENCIA CORRIENTE'!I37:K37) -> 0 | E36: =SUM('TRANSFERENCIA CORRIENTE'!L37:N37) -> 0 | G36: =SUM(VS!C37:E37) -> 0 | H36: =SUM(VS!F37:H37) -> 0 | I36: =SUM(VS!I37:K37) -> 0 | J36: =SUM(VS!L37:N37) -> 0 | L36: =SUM(B36+G36) -> 0 | M36: =SUM(C36+H36) -> 0 | N36: =SUM(D36+I36) -> 0 | O36: =SUM(E36+J36) -> 0
A37: 2.4.3 - TRANSFERENCIAS CORRIENTES A GOBIERNOS GENERALES LOCALES | B37: =SUM('TRANSFERENCIA CORRIENTE'!C38:E38) -> 0 | C37: =SUM('TRANSFERENCIA CORRIENTE'!F38:H38) -> 0 | D37: =SUM('TRANSFERENCIA CORRIENTE'!I38:K38) -> 0 | E37: =SUM('TRANSFERENCIA CORRIENTE'!L38:N38) -> 0 | G37: =SUM(VS!C38:E38) -> 0 | H37: =SUM(VS!F38:H38) -> 0 | I37: =SUM(VS!I38:K38) -> 0 | J37: =SUM(VS!L38:N38) -> 0 | L37: =SUM(B37+G37) -> 0 | M37: =SUM(C37+H37) -> 0 | N37: =SUM(D37+I37) -> 0 | O37: =SUM(E37+J37) -> 0
A38: 2.4.4 - TRANSFERENCIAS CORRIENTES A EMPRESAS PÚBLICAS NO FINANCIERAS | B38: =SUM('TRANSFERENCIA CORRIENTE'!C39:E39) -> 0 | C38: =SUM('TRANSFERENCIA CORRIENTE'!F39:H39) -> 0 | D38: =SUM('TRANSFERENCIA CORRIENTE'!I39:K39) -> 0 | E38: =SUM('TRANSFERENCIA CORRIENTE'!L39:N39) -> 0 | G38: =SUM(VS!C39:E39) -> 0 | H38: =SUM(VS!F39:H39) -> 0 | I38: =SUM(VS!I39:K39) -> 0 | J38: =SUM(VS!L39:N39) -> 0 | L38: =SUM(B38+G38) -> 0 | M38: =SUM(C38+H38) -> 0 | N38: =SUM(D38+I38) -> 0 | O38: =SUM(E38+J38) -> 0
A39: 2.4.5 - TRANSFERENCIAS CORRIENTES A INSTITUCIONES PÚBLICAS FINANCIERAS | B39: =SUM('TRANSFERENCIA CORRIENTE'!C40:E40) -> 0 | C39: =SUM('TRANSFERENCIA CORRIENTE'!F40:H40) -> 0 | D39: =SUM('TRANSFERENCIA CORRIENTE'!I40:K40) -> 0 | E39: =SUM('TRANSFERENCIA CORRIENTE'!L40:N40) -> 0 | G39: =SUM(VS!C40:E40) -> 0 | H39: =SUM(VS!F40:H40) -> 0 | I39: =SUM(VS!I40:K40) -> 0 | J39: =SUM(VS!L40:N40) -> 0 | L39: =SUM(B39+G39) -> 0 | M39: =SUM(C39+H39) -> 0 | N39: =SUM(D39+I39) -> 0 | O39: =SUM(E39+J39) -> 0
A40: 2.4.7 - TRANSFERENCIAS CORRIENTES AL SECTOR EXTERNO | B40: =SUM('TRANSFERENCIA CORRIENTE'!C41:E41) -> 0 | C40: =SUM('TRANSFERENCIA CORRIENTE'!F41:H41) -> 0 | D40: =SUM('TRANSFERENCIA CORRIENTE'!I41:K41) -> 0 | E40: =SUM('TRANSFERENCIA CORRIENTE'!L41:N41) -> 0 | G40: =SUM(VS!C41:E41) -> 0 | H40: =SUM(VS!F41:H41) -> 0 | I40: =SUM(VS!I41:K41) -> 0 | J40: =SUM(VS!L41:N41) -> 0 | L40: =SUM(B40+G40) -> 0 | M40: =SUM(C40+H40) -> 0 | N40: =SUM(D40+I40) -> 0 | O40: =SUM(E40+J40) -> 0
A41: 2.4.9 - TRANSFERENCIAS CORRIENTES A OTRAS INSTITUCIONES PÚBLICAS | B41: =SUM('TRANSFERENCIA CORRIENTE'!C42:E42) -> 0 | C41: =SUM('TRANSFERENCIA CORRIENTE'!F42:H42) -> 0 | D41: =SUM('TRANSFERENCIA CORRIENTE'!I42:K42) -> 0 | E41: =SUM('TRANSFERENCIA CORRIENTE'!L42:N42) -> 0 | G41: =SUM(VS!C42:E42) -> 0 | H41: =SUM(VS!F42:H42) -> 0 | I41: =SUM(VS!I42:K42) -> 0 | J41: =SUM(VS!L42:N42) -> 0 | L41: =SUM(B41+G41) -> 0 | M41: =SUM(C41+H41) -> 0 | N41: =SUM(D41+I41) -> 0 | O41: =SUM(E41+J41) -> 0
A42: 2.5 - TRANSFERENCIAS DE CAPITAL | B42: =SUM(B43:B49) -> 0 | C42: =SUM(C43:C49) -> 0 | D42: =SUM(D43:D49) -> 0 | E42: =SUM(E43:E49) -> 0 | G42: =SUM(G43:G49) -> 0 | H42: =SUM(H43:H49) -> 0 | I42: =SUM(I43:I49) -> 0 | J42: =SUM(J43:J49) -> 0 | L42: =SUM(B42+G42) -> 0 | M42: =SUM(C42+H42) -> 0 | N42: =SUM(D42+I42) -> 0 | O42: =SUM(E42+J42) -> 0
A43: 2.5.1 - TRANSFERENCIAS DE CAPITAL AL SECTOR PRIVADO | B43: =SUM('TRANSFERENCIA CORRIENTE'!C44:E44) -> 0 | C43: =SUM('TRANSFERENCIA CORRIENTE'!F44:H44) -> 0 | D43: =SUM('TRANSFERENCIA CORRIENTE'!I44:K44) -> 0 | E43: =SUM('TRANSFERENCIA CORRIENTE'!L44:N44) -> 0 | G43: =SUM(VS!C44:E44) -> 0 | H43: =SUM(VS!F44:H44) -> 0 | I43: =SUM(VS!I44:K44) -> 0 | J43: =SUM(VS!L44:N44) -> 0 | L43: =SUM(B43+G43) -> 0 | M43: =SUM(C43+H43) -> 0 | N43: =SUM(D43+I43) -> 0 | O43: =SUM(E43+J43) -> 0
A44: 2.5.2 - TRANSFERENCIAS DE CAPITAL AL GOBIERNO GENERAL NACIONAL | B44: =SUM('TRANSFERENCIA CORRIENTE'!C45:E45) -> 0 | C44: =SUM('TRANSFERENCIA CORRIENTE'!F45:H45) -> 0 | D44: =SUM('TRANSFERENCIA CORRIENTE'!I45:K45) -> 0 | E44: =SUM('TRANSFERENCIA CORRIENTE'!L45:N45) -> 0 | G44: =SUM(VS!C45:E45) -> 0 | H44: =SUM(VS!F45:H45) -> 0 | I44: =SUM(VS!I45:K45) -> 0 | J44: =SUM(VS!L45:N45) -> 0 | L44: =SUM(B44+G44) -> 0 | M44: =SUM(C44+H44) -> 0 | N44: =SUM(D44+I44) -> 0 | O44: =SUM(E44+J44) -> 0
A45: 2.5.3 - TRANSFERENCIAS DE CAPITAL A GOBIERNOS GENERALES LOCALES | B45: =SUM('TRANSFERENCIA CORRIENTE'!C46:E46) -> 0 | C45: =SUM('TRANSFERENCIA CORRIENTE'!F46:H46) -> 0 | D45: =SUM('TRANSFERENCIA CORRIENTE'!I46:K46) -> 0 | E45: =SUM('TRANSFERENCIA CORRIENTE'!L46:N46) -> 0 | G45: =SUM(VS!C46:E46) -> 0 | H45: =SUM(VS!F46:H46) -> 0 | I45: =SUM(VS!I46:K46) -> 0 | J45: =SUM(VS!L46:N46) -> 0 | L45: =SUM(B45+G45) -> 0 | M45: =SUM(C45+H45) -> 0 | N45: =SUM(D45+I45) -> 0 | O45: =SUM(E45+J45) -> 0
A46: 2.5.4 - TRANSFERENCIAS DE CAPITAL A EMPRESAS PÚBLICAS NO FINANCIERAS | B46: =SUM('TRANSFERENCIA CORRIENTE'!C47:E47) -> 0 | C46: =SUM('TRANSFERENCIA CORRIENTE'!F47:H47) -> 0 | D46: =SUM('TRANSFERENCIA CORRIENTE'!I47:K47) -> 0 | E46: =SUM('TRANSFERENCIA CORRIENTE'!L47:N47) -> 0 | G46: =SUM(VS!C47:E47) -> 0 | H46: =SUM(VS!F47:H47) -> 0 | I46: =SUM(VS!I47:K47) -> 0 | J46: =SUM(VS!L47:N47) -> 0 | L46: =SUM(B46+G46) -> 0 | M46: =SUM(C46+H46) -> 0 | N46: =SUM(D46+I46) -> 0 | O46: =SUM(E46+J46) -> 0
A47: 2.5.5 - TRANSFERENCIAS DE CAPITAL A INSTITUCIONES PÚBLICAS FINANCIERAS | B47: =SUM('TRANSFERENCIA CORRIENTE'!C48:E48) -> 0 | C47: =SUM('TRANSFERENCIA CORRIENTE'!F48:H48) -> 0 | D47: =SUM('TRANSFERENCIA CORRIENTE'!I48:K48) -> 0 | E47: =SUM('TRANSFERENCIA CORRIENTE'!L48:N48) -> 0 | G47: =SUM(VS!C48:E48) -> 0 | H47: =SUM(VS!F48:H48) -> 0 | I47: =SUM(VS!I48:K48) -> 0 | J47: =SUM(VS!L48:N48) -> 0 | L47: =SUM(B47+G47) -> 0 | M47: =SUM(C47+H47) -> 0 | N47: =SUM(D47+I47) -> 0 | O47: =SUM(E47+J47) -> 0
A48: 2.5.6 - TRANSFERENCIAS DE CAPITAL AL SECTOR EXTERNO | B48: =SUM('TRANSFERENCIA CORRIENTE'!C49:E49) -> 0 | C48: =SUM('TRANSFERENCIA CORRIENTE'!F49:H49) -> 0 | D48: =SUM('TRANSFERENCIA CORRIENTE'!I49:K49) -> 0 | E48: =SUM('TRANSFERENCIA CORRIENTE'!L49:N49) -> 0 | G48: =SUM(VS!C49:E49) -> 0 | H48: =SUM(VS!F49:H49) -> 0 | I48: =SUM(VS!I49:K49) -> 0 | J48: =SUM(VS!L49:N49) -> 0 | L48: =SUM(B48+G48) -> 0 | M48: =SUM(C48+H48) -> 0 | N48: =SUM(D48+I48) -> 0 | O48: =SUM(E48+J48) -> 0
A49: 2.5.9 - TRANSFERENCIAS DE CAPITAL A OTRAS INSTITUCIONES PÚBLICAS | B49: =SUM('TRANSFERENCIA CORRIENTE'!C50:E50) -> 0 | C49: =SUM('TRANSFERENCIA CORRIENTE'!F50:H50) -> 0 | D49: =SUM('TRANSFERENCIA CORRIENTE'!I50:K50) -> 0 | E49: =SUM('TRANSFERENCIA CORRIENTE'!L50:N50) -> 0 | G49: =SUM(VS!C50:E50) -> 0 | H49: =SUM(VS!F50:H50) -> 0 | I49: =SUM(VS!I50:K50) -> 0 | J49: =SUM(VS!L50:N50) -> 0 | L49: =SUM(B49+G49) -> 0 | M49: =SUM(C49+H49) -> 0 | N49: =SUM(D49+I49) -> 0 | O49: =SUM(E49+J49) -> 0
A50: 2.6 - BIENES MUEBLES, INMUEBLES E INTANGIBLES | B50: =SUM(B51:B59) -> 0 | C50: =SUM(C51:C59) -> 0 | D50: =SUM(D51:D59) -> 0 | E50: =SUM(E51:E59) -> 0 | G50: =SUM(G51:G59) -> 887994.84 | H50: =SUM(H51:H59) -> 0 | I50: =SUM(I51:I59) -> 0 | J50: =SUM(J51:J59) -> 0 | L50: =SUM(B50+G50) -> 887994.84 | M50: =SUM(C50+H50) -> 0 | N50: =SUM(D50+I50) -> 0 | O50: =SUM(E50+J50) -> 0
A51: 2.6.1 - MOBILIARIO Y EQUIPO | B51: =SUM('TRANSFERENCIA CORRIENTE'!C52:E52) -> 0 | C51: =SUM('TRANSFERENCIA CORRIENTE'!F52:H52) -> 0 | D51: =SUM('TRANSFERENCIA CORRIENTE'!I52:K52) -> 0 | E51: =SUM('TRANSFERENCIA CORRIENTE'!L52:N52) -> 0 | G51: =SUM(VS!C52:E52) -> 0 | H51: =SUM(VS!F52:H52) -> 0 | I51: =SUM(VS!I52:K52) -> 0 | J51: =SUM(VS!L52:N52) -> 0 | L51: =SUM(B51+G51) -> 0 | M51: =SUM(C51+H51) -> 0 | N51: =SUM(D51+I51) -> 0 | O51: =SUM(E51+J51) -> 0
A52: 2.6.2 - MOBILIARIO Y EQUIPO EDUCACIONAL Y RECREATIVO | B52: =SUM('TRANSFERENCIA CORRIENTE'!C53:E53) -> 0 | C52: =SUM('TRANSFERENCIA CORRIENTE'!F53:H53) -> 0 | D52: =SUM('TRANSFERENCIA CORRIENTE'!I53:K53) -> 0 | E52: =SUM('TRANSFERENCIA CORRIENTE'!L53:N53) -> 0 | G52: =SUM(VS!C53:E53) -> 0 | H52: =SUM(VS!F53:H53) -> 0 | I52: =SUM(VS!I53:K53) -> 0 | J52: =SUM(VS!L53:N53) -> 0 | L52: =SUM(B52+G52) -> 0 | M52: =SUM(C52+H52) -> 0 | N52: =SUM(D52+I52) -> 0 | O52: =SUM(E52+J52) -> 0
A53: 2.6.3 - EQUIPO E INSTRUMENTAL, CIENTÍFICO Y LABORATORIO | B53: =SUM('TRANSFERENCIA CORRIENTE'!C54:E54) -> 0 | C53: =SUM('TRANSFERENCIA CORRIENTE'!F54:H54) -> 0 | D53: =SUM('TRANSFERENCIA CORRIENTE'!I54:K54) -> 0 | E53: =SUM('TRANSFERENCIA CORRIENTE'!L54:N54) -> 0 | G53: =SUM(VS!C54:E54) -> 887994.84 | H53: =SUM(VS!F54:H54) -> 0 | I53: =SUM(VS!I54:K54) -> 0 | J53: =SUM(VS!L54:N54) -> 0 | L53: =SUM(B53+G53) -> 887994.84 | M53: =SUM(C53+H53) -> 0 | N53: =SUM(D53+I53) -> 0 | O53: =SUM(E53+J53) -> 0
A54: 2.6.4 - VEHÍCULOS Y EQUIPO DE TRANSPORTE, TRACCIÓN Y ELEVACIÓN | B54: =SUM('TRANSFERENCIA CORRIENTE'!C55:E55) -> 0 | C54: =SUM('TRANSFERENCIA CORRIENTE'!F55:H55) -> 0 | D54: =SUM('TRANSFERENCIA CORRIENTE'!I55:K55) -> 0 | E54: =SUM('TRANSFERENCIA CORRIENTE'!L55:N55) -> 0 | G54: =SUM(VS!C55:E55) -> 0 | H54: =SUM(VS!F55:H55) -> 0 | I54: =SUM(VS!I55:K55) -> 0 | J54: =SUM(VS!L55:N55) -> 0 | L54: =SUM(B54+G54) -> 0 | M54: =SUM(C54+H54) -> 0 | N54: =SUM(D54+I54) -> 0 | O54: =SUM(E54+J54) -> 0
A55: 2.6.5 - MAQUINARIA, OTROS EQUIPOS Y HERRAMIENTAS | B55: =SUM('TRANSFERENCIA CORRIENTE'!C56:E56) -> 0 | C55: =SUM('TRANSFERENCIA CORRIENTE'!F56:H56) -> 0 | D55: =SUM('TRANSFERENCIA CORRIENTE'!I56:K56) -> 0 | E55: =SUM('TRANSFERENCIA CORRIENTE'!L56:N56) -> 0 | G55: =SUM(VS!C56:E56) -> 0 | H55: =SUM(VS!F56:H56) -> 0 | I55: =SUM(VS!I56:K56) -> 0 | J55: =SUM(VS!L56:N56) -> 0 | L55: =SUM(B55+G55) -> 0 | M55: =SUM(C55+H55) -> 0 | N55: =SUM(D55+I55) -> 0 | O55: =SUM(E55+J55) -> 0
A56: 2.6.6 - EQUIPOS DE DEFENSA Y SEGURIDAD | B56: =SUM('TRANSFERENCIA CORRIENTE'!C57:E57) -> 0 | C56: =SUM('TRANSFERENCIA CORRIENTE'!F57:H57) -> 0 | D56: =SUM('TRANSFERENCIA CORRIENTE'!I57:K57) -> 0 | E56: =SUM('TRANSFERENCIA CORRIENTE'!L57:N57) -> 0 | G56: =SUM(VS!C57:E57) -> 0 | H56: =SUM(VS!F57:H57) -> 0 | I56: =SUM(VS!I57:K57) -> 0 | J56: =SUM(VS!L57:N57) -> 0 | L56: =SUM(B56+G56) -> 0 | M56: =SUM(C56+H56) -> 0 | N56: =SUM(D56+I56) -> 0 | O56: =SUM(E56+J56) -> 0
A57: 2.6.7 - ACTIVOS BIÓLOGICOS CULTIVABLES | B57: =SUM('TRANSFERENCIA CORRIENTE'!C58:E58) -> 0 | C57: =SUM('TRANSFERENCIA CORRIENTE'!F58:H58) -> 0 | D57: =SUM('TRANSFERENCIA CORRIENTE'!I58:K58) -> 0 | E57: =SUM('TRANSFERENCIA CORRIENTE'!L58:N58) -> 0 | G57: =SUM(VS!C58:E58) -> 0 | H57: =SUM(VS!F58:H58) -> 0 | I57: =SUM(VS!I58:K58) -> 0 | J57: =SUM(VS!L58:N58) -> 0 | L57: =SUM(B57+G57) -> 0 | M57: =SUM(C57+H57) -> 0 | N57: =SUM(D57+I57) -> 0 | O57: =SUM(E57+J57) -> 0
A58: 2.6.8 - BIENES INTANGIBLES | B58: =SUM('TRANSFERENCIA CORRIENTE'!C59:E59) -> 0 | C58: =SUM('TRANSFERENCIA CORRIENTE'!F59:H59) -> 0 | D58: =SUM('TRANSFERENCIA CORRIENTE'!I59:K59) -> 0 | E58: =SUM('TRANSFERENCIA CORRIENTE'!L59:N59) -> 0 | G58: =SUM(VS!C59:E59) -> 0 | H58: =SUM(VS!F59:H59) -> 0 | I58: =SUM(VS!I59:K59) -> 0 | J58: =SUM(VS!L59:N59) -> 0 | L58: =SUM(B58+G58) -> 0 | M58: =SUM(C58+H58) -> 0 | N58: =SUM(D58+I58) -> 0 | O58: =SUM(E58+J58) -> 0
A59: 2.6.9 - EDIFICIOS, ESTRUCTURAS, TIERRAS, TERRENOS Y OBJETOS DE VALOR | B59: =SUM('TRANSFERENCIA CORRIENTE'!C60:E60) -> 0 | C59: =SUM('TRANSFERENCIA CORRIENTE'!F60:H60) -> 0 | D59: =SUM('TRANSFERENCIA CORRIENTE'!I60:K60) -> 0 | E59: =SUM('TRANSFERENCIA CORRIENTE'!L60:N60) -> 0 | G59: =SUM(VS!C60:E60) -> 0 | H59: =SUM(VS!F60:H60) -> 0 | I59: =SUM(VS!I60:K60) -> 0 | J59: =SUM(VS!L60:N60) -> 0 | L59: =SUM(B59+G59) -> 0 | M59: =SUM(C59+H59) -> 0 | N59: =SUM(D59+I59) -> 0 | O59: =SUM(E59+J59) -> 0
A60: 2.7 - OBRAS | B60: =SUM(B61:B64) -> 0 | C60: =SUM(C61:C64) -> 0 | D60: =SUM(D61:D64) -> 0 | E60: =SUM(E61:E64) -> 0 | G60: =SUM(G61:G64) -> 0 | H60: =SUM(H61:H64) -> 0 | I60: =SUM(I61:I64) -> 0 | J60: =SUM(J61:J64) -> 0 | L60: =SUM(B60+G60) -> 0 | M60: =SUM(C60+H60) -> 0 | N60: =SUM(D60+I60) -> 0 | O60: =SUM(E60+J60) -> 0
A61: 2.7.1 - OBRAS EN EDIFICACIONES | B61: =SUM('TRANSFERENCIA CORRIENTE'!C62:E62) -> 0 | C61: =SUM('TRANSFERENCIA CORRIENTE'!F62:H62) -> 0 | D61: =SUM('TRANSFERENCIA CORRIENTE'!I62:K62) -> 0 | E61: =SUM('TRANSFERENCIA CORRIENTE'!L62:N62) -> 0 | G61: =SUM(VS!C62:E62) -> 0 | H61: =SUM(VS!F62:H62) -> 0 | I61: =SUM(VS!I62:K62) -> 0 | J61: =SUM(VS!L62:N62) -> 0 | L61: =SUM(B61+G61) -> 0 | M61: =SUM(C61+H61) -> 0 | N61: =SUM(D61+I61) -> 0 | O61: =SUM(E61+J61) -> 0
A62: 2.7.2 - INFRAESTRUCTURA | B62: =SUM('TRANSFERENCIA CORRIENTE'!C63:E63) -> 0 | C62: =SUM('TRANSFERENCIA CORRIENTE'!F63:H63) -> 0 | D62: =SUM('TRANSFERENCIA CORRIENTE'!I63:K63) -> 0 | E62: =SUM('TRANSFERENCIA CORRIENTE'!L63:N63) -> 0 | G62: =SUM(VS!C63:E63) -> 0 | H62: =SUM(VS!F63:H63) -> 0 | I62: =SUM(VS!I63:K63) -> 0 | J62: =SUM(VS!L63:N63) -> 0 | L62: =SUM(B62+G62) -> 0 | M62: =SUM(C62+H62) -> 0 | N62: =SUM(D62+I62) -> 0 | O62: =SUM(E62+J62) -> 0
A63: 2.7.3 - CONSTRUCCIONES EN BIENES CONCESIONADOS | B63: =SUM('TRANSFERENCIA CORRIENTE'!C64:E64) -> 0 | C63: =SUM('TRANSFERENCIA CORRIENTE'!F64:H64) -> 0 | D63: =SUM('TRANSFERENCIA CORRIENTE'!I64:K64) -> 0 | E63: =SUM('TRANSFERENCIA CORRIENTE'!L64:N64) -> 0 | G63: =SUM(VS!C64:E64) -> 0 | H63: =SUM(VS!F64:H64) -> 0 | I63: =SUM(VS!I64:K64) -> 0 | J63: =SUM(VS!L64:N64) -> 0 | L63: =SUM(B63+G63) -> 0 | M63: =SUM(C63+H63) -> 0 | N63: =SUM(D63+I63) -> 0 | O63: =SUM(E63+J63) -> 0
A64: 2.7.4 - GASTOS QUE SE ASIGNARÁN DURANTE EL EJERCICIO PARA INVERSIÓN (ART. 32 Y 33 LEY 423-06) | B64: =SUM('TRANSFERENCIA CORRIENTE'!C65:E65) -> 0 | C64: =SUM('TRANSFERENCIA CORRIENTE'!F65:H65) -> 0 | D64: =SUM('TRANSFERENCIA CORRIENTE'!I65:K65) -> 0 | E64: =SUM('TRANSFERENCIA CORRIENTE'!L65:N65) -> 0 | G64: =SUM(VS!C65:E65) -> 0 | H64: =SUM(VS!F65:H65) -> 0 | I64: =SUM(VS!I65:K65) -> 0 | J64: =SUM(VS!L65:N65) -> 0 | L64: =SUM(B64+G64) -> 0 | M64: =SUM(C64+H64) -> 0 | N64: =SUM(D64+I64) -> 0 | O64: =SUM(E64+J64) -> 0
A65: 2.8 - ADQUISICION DE ACTIVOS FINANCIEROS CON FINES DE POLÍTICA | B65: =SUM(B66:B67) -> 0 | C65: =SUM(C66:C67) -> 0 | D65: =SUM(D66:D67) -> 0 | E65: =SUM(E66:E67) -> 0 | G65: =SUM(G66:G67) -> 0 | H65: =SUM(H66:H67) -> 0 | I65: =SUM(I66:I67) -> 0 | J65: =SUM(J66:J67) -> 0 | L65: =SUM(B65+G65) -> 0 | M65: =SUM(C65+H65) -> 0 | N65: =SUM(D65+I65) -> 0 | O65: =SUM(E65+J65) -> 0
A66: 2.8.1 - CONCESIÓN DE PRESTAMOS | B66: =SUM('TRANSFERENCIA CORRIENTE'!C67:E67) -> 0 | C66: =SUM('TRANSFERENCIA CORRIENTE'!F67:H67) -> 0 | D66: =SUM('TRANSFERENCIA CORRIENTE'!I67:K67) -> 0 | E66: =SUM('TRANSFERENCIA CORRIENTE'!L67:N67) -> 0 | G66: =SUM(VS!C67:E67) -> 0 | H66: =SUM(VS!F67:H67) -> 0 | I66: =SUM(VS!I67:K67) -> 0 | J66: =SUM(VS!L67:N67) -> 0 | L66: =SUM(B66+G66) -> 0 | M66: =SUM(C66+H66) -> 0 | N66: =SUM(D66+I66) -> 0 | O66: =SUM(E66+J66) -> 0
A67: 2.8.2 - ADQUISICIÓN DE TÍTULOS VALORES REPRESENTATIVOS DE DEUDA | B67: =SUM('TRANSFERENCIA CORRIENTE'!C68:E68) -> 0 | C67: =SUM('TRANSFERENCIA CORRIENTE'!F68:H68) -> 0 | D67: =SUM('TRANSFERENCIA CORRIENTE'!I68:K68) -> 0 | E67: =SUM('TRANSFERENCIA CORRIENTE'!L68:N68) -> 0 | G67: =SUM(VS!C68:E68) -> 0 | H67: =SUM(VS!F68:H68) -> 0 | I67: =SUM(VS!I68:K68) -> 0 | J67: =SUM(VS!L68:N68) -> 0 | L67: =SUM(B67+G67) -> 0 | M67: =SUM(C67+H67) -> 0 | N67: =SUM(D67+I67) -> 0 | O67: =SUM(E67+J67) -> 0
A68: 2.9 - GASTOS FINANCIEROS | B68: =SUM(B69:B71) -> 0 | C68: =SUM(C69:C71) -> 0 | D68: =SUM(D69:D71) -> 0 | E68: =SUM(E69:E71) -> 0 | G68: =SUM(G69:G71) -> 0 | H68: =SUM(H69:H71) -> 0 | I68: =SUM(I69:I71) -> 0 | J68: =SUM(J69:J71) -> 0 | L68: =SUM(B68+G68) -> 0 | M68: =SUM(C68+H68) -> 0 | N68: =SUM(D68+I68) -> 0 | O68: =SUM(E68+J68) -> 0
A69: 2.9.1 - INTERESES DE LA DEUDA PÚBLICA INTERNA | B69: =SUM('TRANSFERENCIA CORRIENTE'!C70:E70) -> 0 | C69: =SUM('TRANSFERENCIA CORRIENTE'!F70:H70) -> 0 | D69: =SUM('TRANSFERENCIA CORRIENTE'!I70:K70) -> 0 | E69: =SUM('TRANSFERENCIA CORRIENTE'!L70:N70) -> 0 | G69: =SUM(VS!C70:E70) -> 0 | H69: =SUM(VS!F70:H70) -> 0 | I69: =SUM(VS!I70:K70) -> 0 | J69: =SUM(VS!L70:N70) -> 0 | L69: =SUM(B69+G69) -> 0 | M69: =SUM(C69+H69) -> 0 | N69: =SUM(D69+I69) -> 0 | O69: =SUM(E69+J69) -> 0
A70: 2.9.2 - INTERESES DE LA DEUDA PUBLICA EXTERNA | B70: =SUM('TRANSFERENCIA CORRIENTE'!C71:E71) -> 0 | C70: =SUM('TRANSFERENCIA CORRIENTE'!F71:H71) -> 0 | D70: =SUM('TRANSFERENCIA CORRIENTE'!I71:K71) -> 0 | E70: =SUM('TRANSFERENCIA CORRIENTE'!L71:N71) -> 0 | G70: =SUM(VS!C71:E71) -> 0 | H70: =SUM(VS!F71:H71) -> 0 | I70: =SUM(VS!I71:K71) -> 0 | J70: =SUM(VS!L71:N71) -> 0 | L70: =SUM(B70+G70) -> 0 | M70: =SUM(C70+H70) -> 0 | N70: =SUM(D70+I70) -> 0 | O70: =SUM(E70+J70) -> 0
A71: 2.9.4 - COMISIONES Y OTROS GASTOS BANCARIOS DE LA DEUDA PÚBLICA | B71: =SUM('TRANSFERENCIA CORRIENTE'!C72:E72) -> 0 | C71: =SUM('TRANSFERENCIA CORRIENTE'!F72:H72) -> 0 | D71: =SUM('TRANSFERENCIA CORRIENTE'!I72:K72) -> 0 | E71: =SUM('TRANSFERENCIA CORRIENTE'!L72:N72) -> 0 | H71: =SUM(VS!F72:H72) -> 0 | I71: =SUM(VS!I72:K72) -> 0 | J71: =SUM(VS!L72:N72) -> 0 | L71: =SUM(B71+G71) -> 0 | M71: =SUM(C71+H71) -> 0 | N71: =SUM(D71+I71) -> 0 | O71: =SUM(E71+J71) -> 0
A72: Total Gastos | B72: =+B8+B14+B24+B34+B42+B50+B60+B65+B68 -> 70061780 | C72: =+C8+C14+C24+C34+C42+C50+C60+C65+C68 -> 0 | D72: =+D8+D14+D24+D34+D42+D50+D60+D65+D68 -> 0 | E72: =+E8+E14+E24+E34+E42+E50+E60+E65+E68 -> 0 | G72: =+G8+G14+G24+G34+G42+G50+G60+G65+G68 -> 6821436.5 | H72: =+H8+H14+H24+H34+H42+H50+H60+H65+H68 -> 0 | I72: =+I8+I14+I24+I34+I42+I50+I60+I65+I68 -> 0 | J72: =+J8+J14+J24+J34+J42+J50+J60+J65+J68 -> 0 | L72: =SUM(B72+G72) -> 76883217 | M72: =SUM(C72+H72) -> 0 | N72: =SUM(D72+I72) -> 0 | O72: =SUM(E72+J72) -> 0
A73: 4 - APLICACIONES FINANCIERAS | B73: =SUM('TRANSFERENCIA CORRIENTE'!C74:E74) -> 0 | C73: =SUM('TRANSFERENCIA CORRIENTE'!F74:H74) -> 0 | D73: =SUM('TRANSFERENCIA CORRIENTE'!I74:K74) -> 0 | E73: =SUM('TRANSFERENCIA CORRIENTE'!L74:N74) -> 0 | G73: =SUM(VS!C74:E74) -> 0 | H73: =SUM(VS!F74:H74) -> 0 | I73: =SUM(VS!I74:K74) -> 0 | J73: =SUM(VS!L74:N74) -> 0 | L73: =SUM(B73+G73) -> 0 | M73: =SUM(C73+H73) -> 0 | N73: =SUM(D73+I73) -> 0 | O73: =SUM(E73+J73) -> 0
A74: 4.1 - INCREMENTO DE ACTIVOS FINANCIEROS | B74: =SUM('TRANSFERENCIA CORRIENTE'!C75:E75) -> 0 | C74: =SUM('TRANSFERENCIA CORRIENTE'!F75:H75) -> 0 | D74: =SUM('TRANSFERENCIA CORRIENTE'!I75:K75) -> 0 | E74: =SUM('TRANSFERENCIA CORRIENTE'!L75:N75) -> 0 | G74: =SUM(VS!C75:E75) -> 0 | H74: =SUM(VS!F75:H75) -> 0 | I74: =SUM(VS!I75:K75) -> 0 | J74: =SUM(VS!L75:N75) -> 0 | L74: =SUM(B74+G74) -> 0 | M74: =SUM(C74+H74) -> 0 | N74: =SUM(D74+I74) -> 0 | O74: =SUM(E74+J74) -> 0
A75: 4.1.1 - INCREMENTO DE ACTIVOS FINANCIEROS CORRIENTES | B75: =SUM('TRANSFERENCIA CORRIENTE'!C76:E76) -> 0 | C75: =SUM('TRANSFERENCIA CORRIENTE'!F76:H76) -> 0 | D75: =SUM('TRANSFERENCIA CORRIENTE'!I76:K76) -> 0 | E75: =SUM('TRANSFERENCIA CORRIENTE'!L76:N76) -> 0 | G75: =SUM(VS!C76:E76) -> 0 | H75: =SUM(VS!F76:H76) -> 0 | I75: =SUM(VS!I76:K76) -> 0 | J75: =SUM(VS!L76:N76) -> 0 | L75: =SUM(B75+G75) -> 0 | M75: =SUM(C75+H75) -> 0 | N75: =SUM(D75+I75) -> 0 | O75: =SUM(E75+J75) -> 0
A76: 4.1.2 - INCREMENTO DE ACTIVOS FINANCIEROS NO CORRIENTES | B76: =SUM('TRANSFERENCIA CORRIENTE'!C77:E77) -> 0 | C76: =SUM('TRANSFERENCIA CORRIENTE'!F77:H77) -> 0 | D76: =SUM('TRANSFERENCIA CORRIENTE'!I77:K77) -> 0 | E76: =SUM('TRANSFERENCIA CORRIENTE'!L77:N77) -> 0 | G76: =SUM(VS!C77:E77) -> 0 | H76: =SUM(VS!F77:H77) -> 0 | I76: =SUM(VS!I77:K77) -> 0 | J76: =SUM(VS!L77:N77) -> 0 | L76: =SUM(B76+G76) -> 0 | M76: =SUM(C76+H76) -> 0 | N76: =SUM(D76+I76) -> 0 | O76: =SUM(E76+J76) -> 0
A77: 4.2 - DISMINUCIÓN DE PASIVOS | B77: =SUM('TRANSFERENCIA CORRIENTE'!C78:E78) -> 0 | C77: =SUM('TRANSFERENCIA CORRIENTE'!F78:H78) -> 0 | D77: =SUM('TRANSFERENCIA CORRIENTE'!I78:K78) -> 0 | E77: =SUM('TRANSFERENCIA CORRIENTE'!L78:N78) -> 0 | G77: =SUM(VS!C78:E78) -> 0 | H77: =SUM(VS!F78:H78) -> 0 | I77: =SUM(VS!I78:K78) -> 0 | J77: =SUM(VS!L78:N78) -> 0 | L77: =SUM(B77+G77) -> 0 | M77: =SUM(C77+H77) -> 0 | N77: =SUM(D77+I77) -> 0 | O77: =SUM(E77+J77) -> 0
A78: 4.2.1 - DISMINUCIÓN DE PASIVOS CORRIENTES | B78: =SUM('TRANSFERENCIA CORRIENTE'!C79:E79) -> 0 | C78: =SUM('TRANSFERENCIA CORRIENTE'!F79:H79) -> 0 | D78: =SUM('TRANSFERENCIA CORRIENTE'!I79:K79) -> 0 | E78: =SUM('TRANSFERENCIA CORRIENTE'!L79:N79) -> 0 | G78: =SUM(VS!C79:E79) -> 0 | H78: =SUM(VS!F79:H79) -> 0 | I78: =SUM(VS!I79:K79) -> 0 | J78: =SUM(VS!L79:N79) -> 0 | L78: =SUM(B78+G78) -> 0 | M78: =SUM(C78+H78) -> 0 | N78: =SUM(D78+I78) -> 0 | O78: =SUM(E78+J78) -> 0
A79: 4.2.2 - DISMINUCIÓN DE PASIVOS NO CORRIENTES | B79: =SUM('TRANSFERENCIA CORRIENTE'!C80:E80) -> 0 | C79: =SUM('TRANSFERENCIA CORRIENTE'!F80:H80) -> 0 | D79: =SUM('TRANSFERENCIA CORRIENTE'!I80:K80) -> 0 | E79: =SUM('TRANSFERENCIA CORRIENTE'!L80:N80) -> 0 | G79: =SUM(VS!C80:E80) -> 0 | H79: =SUM(VS!F80:H80) -> 0 | I79: =SUM(VS!I80:K80) -> 0 | J79: =SUM(VS!L80:N80) -> 0 | L79: =SUM(B79+G79) -> 0 | M79: =SUM(C79+H79) -> 0 | N79: =SUM(D79+I79) -> 0 | O79: =SUM(E79+J79) -> 0
A80: 4.3 - DISMINUCIÓN DE FONDOS DE TERCEROS | B80: =SUM('TRANSFERENCIA CORRIENTE'!C81:E81) -> 0 | C80: =SUM('TRANSFERENCIA CORRIENTE'!F81:H81) -> 0 | D80: =SUM('TRANSFERENCIA CORRIENTE'!I81:K81) -> 0 | E80: =SUM('TRANSFERENCIA CORRIENTE'!L81:N81) -> 0 | G80: =SUM(VS!C81:E81) -> 0 | H80: =SUM(VS!F81:H81) -> 0 | I80: =SUM(VS!I81:K81) -> 0 | J80: =SUM(VS!L81:N81) -> 0 | L80: =SUM(B80+G80) -> 0 | M80: =SUM(C80+H80) -> 0 | N80: =SUM(D80+I80) -> 0 | O80: =SUM(E80+J80) -> 0
A81: 4.3.5 - DISMINUCIÓN DEPÓSITOS FONDOS DE TERCEROS | B81: =SUM('TRANSFERENCIA CORRIENTE'!C82:E82) -> 0 | C81: =SUM('TRANSFERENCIA CORRIENTE'!F82:H82) -> 0 | D81: =SUM('TRANSFERENCIA CORRIENTE'!I82:K82) -> 0 | E81: =SUM('TRANSFERENCIA CORRIENTE'!L82:N82) -> 0 | G81: =SUM(VS!C82:E82) -> 0 | H81: =SUM(VS!F82:H82) -> 0 | I81: =SUM(VS!I82:K82) -> 0 | J81: =SUM(VS!L82:N82) -> 0 | L81: =SUM(B81+G81) -> 0 | M81: =SUM(C81+H81) -> 0 | N81: =SUM(D81+I81) -> 0 | O81: =SUM(E81+J81) -> 0
A82: TOTAL APLICACIONES FINANCIERAS | B82: =SUM(B83) -> 70061780 | C82: =SUM(C83) -> 0 | D82: =SUM(D83) -> 0 | E82: =SUM(E83) -> 0 | G82: =SUM(G83) -> 6821436.5 | H82: =SUM(H83) -> 0 | I82: =SUM(I83) -> 0 | J82: =SUM(J83) -> 0 | L82: =SUM(B82+G82) -> 76883217 | M82: =SUM(C82+H82) -> 0 | N82: =SUM(D82+I82) -> 0 | O82: =SUM(E82+J82) -> 0
A83: TOTAL GASTOS Y APLICACIONES FINANCIERAS | B83: =SUM('TRANSFERENCIA CORRIENTE'!C85:E85) -> 70061780 | C83: =SUM('TRANSFERENCIA CORRIENTE'!F85:H85) -> 0 | D83: =SUM('TRANSFERENCIA CORRIENTE'!I85:K85) -> 0 | E83: =SUM('TRANSFERENCIA CORRIENTE'!L85:N85) -> 0 | G83: =SUM(VS!C85:E85) -> 6821436.5 | H83: =SUM(VS!F85:H85) -> 0 | I83: =SUM(VS!I85:K85) -> 0 | J83: =SUM(VS!L85:N85) -> 0 | L83: =SUM(B83+G83) -> 76883217 | M83: =SUM(C83+H83) -> 0 | N83: =SUM(D83+I83) -> 0 | O83: =SUM(E83+J83) -> 0

Sheet TRANSFERENCIA CORRIENTE
A1: SERVICIO NACIONAL DE SALUD
A2: HOSPITAL MATERNO INFANTIL SAN LORENZO DE LOS MINA
A3: REGION 0
A4: Ejecución de Gastos Fondo (100) 2024
A5: En RD$
A7: Detalle | B7: Total | C7: Enero | D7: Febrero | E7: Marzo | F7: Abril | G7: Mayo | H7: Junio | I7: Julio | J7: Agosto | K7: Septiembre | L7: Octubre | M7: Noviembre | N7: Diciembre
A8: 2 - GASTOS
A9: 2.1 - REMUNERACIONES Y CONTRIBUCIONES | B9: =SUM(C9:N9) -> 65091180 | C9: =SUM(C10:C14) -> 65091180 | D9: =SUM(D10:D14) -> 0 | E9: =SUM(E10:E14) -> 0 | F9: =SUM(F10:F14) -> 0 | G9: =SUM(G10:G14) -> 0 | H9: =SUM(H10:H14) -> 0 | I9: =SUM(I10:I14) -> 0 | J9: =SUM(J10:J14) -> 0 | ... N9: =SUM(N10:N14) -> 0
A10: 2.1.1 - REMUNERACIONES | B10: =SUM(C10:N10) -> 53640339 | C10: 53640339
A11: 2.1.2 - SOBRESUELDOS | B11: =SUM(C11:N11) -> 3196999.6 | C11: 3196999.6
A12: 2.1.3 - DIETAS Y GASTOS DE REPRESENTACIÓN | B12: =SUM(C12:N12) -> 0
A13: 2.1.4 - GRATIFICACIONES Y BONIFICACIONES | B13: =SUM(C13:N13) -> 0
A14: 2.1.5 - CONTRIBUCIONES A LA SEGURIDAD SOCIAL | B14: =SUM(C14:N14) -> 8253841.6 | C14: 8253841.6
A15: 2.2 - CONTRATACIÓN DE SERVICIOS | B15: =SUM(C15:N15) -> 0 | C15: =SUM(C16:C24) -> 0 | D15: =SUM(D16:D24) -> 0 | E15: =SUM(E16:E24) -> 0 | F15: =SUM(F16:F24) -> 0 | G15: =SUM(G16:G24) -> 0 | H15: =SUM(H16:H24) -> 0 | I15: =SUM(I16:I24) -> 0 | J15: =SUM(J16:J24) -> 0 | ... N15: =SUM(N16:N24) -> 0
A16: 2.2.1 - SERVICIOS BÁSICOS | B16: =SUM(C16:N16) -> 0
A17: 2.2.2 - PUBLICIDAD, IMPRESIÓN Y ENCUADERNACIÓN | B17: =SUM(C17:N17) -> 0
A18: 2.2.3 - VIÁTICOS | B18: =SUM(C18:N18) -> 0
A19: 2.2.4 - TRANSPORTE Y ALMACENAJE | B19: =SUM(C19:N19) -> 0
A20: 2.2.5 - ALQUILERES Y RENTAS | B20: =SUM(C20:N20) -> 0
A21: 2.2.6 - SEGUROS | B21: =SUM(C21:N21) -> 0
A22: 2.2.7 - SERVICIOS DE CONSERVACIÓN, REPARACIONES MENORES E INSTALACIONES TEMPORALES | B22: =SUM(C22:N22) -> 0
A23: 2.2.8 - OTROS SERVICIOS NO INCLUIDOS EN CONCEPTOS ANTERIORES | B23: =SUM(C23:N23) -> 0
A24: 2.2.9 - OTRAS CONTRATACIONES DE SERVICIOS | B24: =SUM(C24:N24) -> 0
A25: 2.3 - MATERIALES Y SUMINISTROS | B25: =SUM(C25:N25) -> 4970600.4 | C25: =SUM(C26:C34) -> 4970600.4 | D25: =SUM(D26:D34) -> 0 | E25: =SUM(E26:E34) -> 0 | F25: =SUM(F26:F34) -> 0 | G25: =SUM(G26:G34) -> 0 | H25: =SUM(H26:H34) -> 0 | I25: =SUM(I26:I34) -> 0 | J25: =SUM(J26:J34) -> 0 | ... N25: =SUM(N26:N34) -> 0
A26: 2.3.1 - ALIMENTOS Y PRODUCTOS AGROFORESTALES | B26: =SUM(C26:N26) -> 0
A27: 2.3.2 - TEXTILES Y VESTUARIOS | B27: =SUM(C27:N27) -> 0
A28: 2.3.3 - PRODUCTOS DE PAPEL, CARTÓN E IMPRESOS | B28: =SUM(C28:N28) -> 0
A29: 2.3.4 - PRODUCTOS FARMACÉUTICOS | B29: =SUM(C29:N29) -> 1862880 | C29: 1862880
A30: 2.3.5 - PRODUCTOS DE CUERO, CAUCHO Y PLÁSTICO | B30: =SUM(C30:N30) -> 0
A31: 2.3.6 - PRODUCTOS DE MINERALES, METÁLICOS Y NO METÁLICOS | B31: =SUM(C31:N31) -> 0
A32: 2.3.7 - COMBUSTIBLES, LUBRICANTES, PRODUCTOS QUÍMICOS Y CONEXOS | B32: =SUM(C32:N32) -> 1844663.4 | C32: 1844663.4
A33: 2.3.8 - GASTOS QUE SE ASIGNARÁN DURANTE EL EJERCICIO (ART. 32 Y 33 LEY 423-06) | B33: =SUM(C33:N33) -> 0
A34: 2.3.9 - PRODUCTOS Y ÚTILES VARIOS | B34: =SUM(C34:N34) -> 1263057 | C34: 1263057
A35: 2.4 - TRANSFERENCIAS CORRIENTES | B35: =SUM(C35:N35) -> 0 | C35: =SUM(C36:C42) -> 0 | D35: =SUM(D36:D42) -> 0 | E35: =SUM(E36:E42) -> 0 | F35: =SUM(F36:F42) -> 0 | G35: =SUM(G36:G42) -> 0 | H35: =SUM(H36:H42) -> 0 | I35: =SUM(I36:I42) -> 0 | J35: =SUM(J36:J42) -> 0 | ... N35: =SUM(N36:N42) -> 0
A36: 2.4.1 - TRANSFERENCIAS CORRIENTES AL SECTOR PRIVADO | B36: =SUM(C36:N36) -> 0
A37: 2.4.2 - TRANSFERENCIAS CORRIENTES AL GOBIERNO GENERAL NACIONAL | B37: =SUM(C37:N37) -> 0
A38: 2.4.3 - TRANSFERENCIAS CORRIENTES A GOBIERNOS GENERALES LOCALES | B38: =SUM(C38:N38) -> 0
A39: 2.4.4 - TRANSFERENCIAS CORRIENTES A EMPRESAS PÚBLICAS NO FINANCIERAS | B39: =SUM(C39:N39) -> 0
A40: 2.4.5 - TRANSFERENCIAS CORRIENTES A INSTITUCIONES PÚBLICAS FINANCIERAS | B40: =SUM(C40:N40) -> 0
A41: 2.4.7 - TRANSFERENCIAS CORRIENTES AL SECTOR EXTERNO | B41: =SUM(C41:N41) -> 0
A42: 2.4.9 - TRANSFERENCIAS CORRIENTES A OTRAS INSTITUCIONES PÚBLICAS | B42: =SUM(C42:N42) -> 0
A43: 2.5 - TRANSFERENCIAS DE CAPITAL | B43: =SUM(C43:N43) -> 0 | C43: =SUM(C44:C50) -> 0 | D43: =SUM(D44:D50) -> 0 | E43: =SUM(E44:E50) -> 0 | F43: =SUM(F44:F50) -> 0 | G43: =SUM(G44:G50) -> 0 | H43: =SUM(H44:H50) -> 0 | I43: =SUM(I44:I50) -> 0 | J43: =SUM(J44:J50) -> 0 | ... N43: =SUM(N44:N50) -> 0
A44: 2.5.1 - TRANSFERENCIAS DE CAPITAL AL SECTOR PRIVADO | B44: =SUM(C44:N44) -> 0
A45: 2.5.2 - TRANSFERENCIAS DE CAPITAL AL GOBIERNO GENERAL NACIONAL | B45: =SUM(C45:N45) -> 0
A46: 2.5.3 - TRANSFERENCIAS DE CAPITAL A GOBIERNOS GENERALES LOCALES | B46: =SUM(C46:N46) -> 0
A47: 2.5.4 - TRANSFERENCIAS DE CAPITAL A EMPRESAS PÚBLICAS NO FINANCIERAS | B47: =SUM(C47:N47) -> 0
A48: 2.5.5 - TRANSFERENCIAS DE CAPITAL A INSTITUCIONES PÚBLICAS FINANCIERAS | B48: =SUM(C48:N48) -> 0
A49: 2.5.6 - TRANSFERENCIAS DE CAPITAL AL SECTOR EXTERNO | B49: =SUM(C49:N49) -> 0
A50: 2.5.9 - TRANSFERENCIAS DE CAPITAL A OTRAS INSTITUCIONES PÚBLICAS | B50: =SUM(C50:N50) -> 0
A51: 2.6 - BIENES MUEBLES, INMUEBLES E INTANGIBLES | B51: =SUM(C51:N51) -> 0 | C51: =SUM(C52:C60) -> 0 | D51: =SUM(D52:D60) -> 0 | E51: =SUM(E52:E60) -> 0 | F51: =SUM(F52:F60) -> 0 | G51: =SUM(G52:G60) -> 0 | H51: =SUM(H52:H60) -> 0 | I51: =SUM(I52:I60) -> 0 | J51: =SUM(J52:J60) -> 0 | ... N51: =SUM(N52:N60) -> 0
A52: 2.6.1 - MOBILIARIO Y EQUIPO | B52: =SUM(C52:N52) -> 0
A53: 2.6.2 - MOBILIARIO Y EQUIPO EDUCACIONAL Y RECREATIVO | B53: =SUM(C53:N53) -> 0
A54: 2.6.3 - EQUIPO E INSTRUMENTAL, CIENTÍFICO Y LABORATORIO | B54: =SUM(C54:N54) -> 0
A55: 2.6.4 - VEHÍCULOS Y EQUIPO DE TRANSPORTE, TRACCIÓN Y ELEVACIÓN | B55: =SUM(C55:N55) -> 0
A56: 2.6.5 - MAQUINARIA, OTROS EQUIPOS Y HERRAMIENTAS | B56: =SUM(C56:N56) -> 0
A57: 2.6.6 - EQUIPOS DE DEFENSA Y SEGURIDAD | B57: =SUM(C57:N57) -> 0
A58: 2.6.7 - ACTIVOS BIÓLOGICOS CULTIVABLES | B58: =SUM(C58:N58) -> 0
A59: 2.6.8 - BIENES INTANGIBLES | B59: =SUM(C59:N59) -> 0
A60: 2.6.9 - EDIFICIOS, ESTRUCTURAS, TIERRAS, TERRENOS Y OBJETOS DE VALOR | B60: =SUM(C60:N60) -> 0
A61: 2.7 - OBRAS | B61: =SUM(C61:N61) -> 0 | C61: =SUM(C62:C65) -> 0 | D61: =SUM(D62:D65) -> 0 | E61: =SUM(E62:E65) -> 0 | F61: =SUM(F62:F65) -> 0 | G61: =SUM(G62:G65) -> 0 | H61: =SUM(H62:H65) -> 0 | I61: =SUM(I62:I65) -> 0 | J61: =SUM(J62:J65) -> 0 | ... N61: =SUM(N62:N65) -> 0
A62: 2.7.1 - OBRAS EN EDIFICACIONES | B62: =SUM(C62:N62) -> 0
A63: 2.7.2 - INFRAESTRUCTURA | B63: =SUM(C63:N63) -> 0
A64: 2.7.3 - CONSTRUCCIONES EN BIENES CONCESIONADOS | B64: =SUM(C64:N64) -> 0
A65: 2.7.4 - GASTOS QUE SE ASIGNARÁN DURANTE EL EJERCICIO PARA INVERSIÓN (ART. 32 Y 33 LEY 423-06) | B65: =SUM(C65:N65) -> 0
A66: 2.8 - ADQUISICION DE ACTIVOS FINANCIEROS CON FINES DE POLÍTICA | B66: =SUM(C66:N66) -> 0 | C66: =SUM(C67:C68) -> 0 | D66: =SUM(D67:D68) -> 0 | E66: =SUM(E67:E68) -> 0 | F66: =SUM(F67:F68) -> 0 | G66: =SUM(G67:G68) -> 0 | H66: =SUM(H67:H68) -> 0 | I66: =SUM(I67:I68) -> 0 | J66: =SUM(J67:J68) -> 0 | ... N66: =SUM(N67:N68) -> 0
A67: 2.8.1 - CONCESIÓN DE PRESTAMOS | B67: =SUM(C67:N67) -> 0
A68: 2.8.2 - ADQUISICIÓN DE TÍTULOS VALORES REPRESENTATIVOS DE DEUDA | B68: =SUM(C68:N68) -> 0
A69: 2.9 - GASTOS FINANCIEROS | B69: =SUM(C69:N69) -> 0 | C69: =SUM(C70:C72) -> 0 | D69: =SUM(D70:D72) -> 0 | E69: =SUM(E70:E72) -> 0 | F69: =SUM(F70:F72) -> 0 | G69: =SUM(G70:G72) -> 0 | H69: =SUM(H70:H72) -> 0 | I69: =SUM(I70:I72) -> 0 | J69: =SUM(J70:J72) -> 0 | ... N69: =SUM(N70:N72) -> 0
A70: 2.9.1 - INTERESES DE LA DEUDA PÚBLICA INTERNA | B70: =SUM(C70:N70) -> 0
A71: 2.9.2 - INTERESES DE LA DEUDA PUBLICA EXTERNA | B71: =SUM(C71:N71) -> 0
A72: 2.9.4 - COMISIONES Y OTROS GASTOS BANCARIOS DE LA DEUDA PÚBLICA | B72: =SUM(C72:N72) -> 0
A73: Total Gastos | B73: =B9+B15+B25+B35+B43+B51+B61+B66+B69 -> 70061780 | C73: =C9+C15+C25+C35+C43+C51+C61+C66+C69 -> 70061780 | D73: =D9+D15+D25+D35+D43+D51+D61+D66+D69 -> 0 | E73: =E9+E15+E25+E35+E43+E51+E61+E66+E69 -> 0 | F73: =F9+F15+F25+F35+F43+F51+F61+F66+F69 -> 0 | G73: =G9+G15+G25+G35+G43+G51+G61+G66+G69 -> 0 | H73: =H9+H15+H25+H35+H43+H51+H61+H66+H69 -> 0 | I73: =I9+I15+I25+I35+I43+I51+I61+I66+I69 -> 0 | ... N73: =N9+N15+N25+N35+N43+N51+N61+N66+N69 -> 0
A74: 4 - APLICACIONES FINANCIERAS
A75: 4.1 - INCREMENTO DE ACTIVOS FINANCIEROS
A76: 4.1.1 - INCREMENTO DE ACTIVOS FINANCIEROS CORRIENTES
A77: 4.1.2 - INCREMENTO DE ACTIVOS FINANCIEROS NO CORRIENTES
A78: 4.2 - DISMINUCIÓN DE PASIVOS
A79: 4.2.1 - DISMINUCIÓN DE PASIVOS CORRIENTES
A80: 4.2.2 - DISMINUCIÓN DE PASIVOS NO CORRIENTES
A81: 4.3 - DISMINUCIÓN DE FONDOS DE TERCEROS
A82: 4.3.5 - DISMINUCIÓN DEPÓSITOS FONDOS DE TERCEROS
A83: TOTAL APLICACIONES FINANCIERAS
A85: TOTAL GASTOS Y APLICACIONES FINANCIERAS | B85: =+B83+B73 -> 70061780 | C85: =+C83+C73 -> 70061780 | D85: =+D83+D73 -> 0 | E85: =+E83+E73 -> 0 | F85: =+F83+F73 -> 0 | G85: =+G83+G73 -> 0 | H85: =+H83+H73 -> 0 | I85: =+I83+I73 -> 0 | ... N85: =+N83+N73 -> 0
A86: Fuente: [SIGEF
A87: Fecha de registro: hasta el [01] de [01) del [2024]
A88: Fecha de imputación: hasta el 31 de [12] del [2024]

Sheet VS
A1: SERVICIO NACIONAL DE SALUD
A2: HOSPITAL MATERNO INFANTIL SAN LORENZO DE LOS MINA
A3: REGION 0
A4: Ejecución de Gastos Ventas de Servicios 2024
A5: En RD$
A7: Detalle | B7: Total | C7: Enero | D7: Febrero | E7: Marzo | F7: Abril | G7: Mayo | H7: Junio | I7: Julio | J7: Agosto | K7: Septiembre | L7: Octubre | M7: Noviembre | N7: Diciembre
A8: 2 - GASTOS
A9: 2.1 - REMUNERACIONES Y CONTRIBUCIONES | B9: =SUM(C9:N9) -> 0 | C9: =SUM(C10:C14) -> 0 | D9: =SUM(D10:D14) -> 0 | E9: =SUM(E10:E14) -> 0 | F9: =SUM(F10:F14) -> 0 | G9: =SUM(G10:G14) -> 0 | H9: =SUM(H10:H14) -> 0 | I9: =SUM(I10:I14) -> 0 | J9: =SUM(J10:J14) -> 0 | ... N9: =SUM(N10:N14) -> 0
A10: 2.1.1 - REMUNERACIONES | B10: =SUM(C10:N10) -> 0
A11: 2.1.2 - SOBRESUELDOS | B11: =SUM(C11:N11) -> 0
A12: 2.1.3 - DIETAS Y GASTOS DE REPRESENTACIÓN | B12: =SUM(C12:N12) -> 0
A13: 2.1.4 - GRATIFICACIONES Y BONIFICACIONES | B13: =SUM(C13:N13) -> 0
A14: 2.1.5 - CONTRIBUCIONES A LA SEGURIDAD SOCIAL | B14: =SUM(C14:N14) -> 0
A15: 2.2 - CONTRATACIÓN DE SERVICIOS | B15: =SUM(C15:N15) -> 2733844.3 | C15: =SUM(C16:C24) -> 2733844.3 | D15: =SUM(D16:D24) -> 0 | E15: =SUM(E16:E24) -> 0 | F15: =SUM(F16:F24) -> 0 | G15: =SUM(G16:G24) -> 0 | H15: =SUM(H16:H24) -> 0 | I15: =SUM(I16:I24) -> 0 | J15: =SUM(J16:J24) -> 0 | ... N15: =SUM(N16:N24) -> 0
A16: 2.2.1 - SERVICIOS BÁSICOS | B16: =SUM(C16:N16) -> 351316.33 | C16: 351316.33
A17: 2.2.2 - PUBLICIDAD, IMPRESIÓN Y ENCUADERNACIÓN | B17: =SUM(C17:N17) -> 0
A18: 2.2.3 - VIÁTICOS | B18: =SUM(C18:N18) -> 0
A19: 2.2.4 - TRANSPORTE Y ALMACENAJE | B19: =SUM(C19:N19) -> 0
A20: 2.2.5 - ALQUILERES Y RENTAS | B20: =SUM(C20:N20) -> 266664.26 | C20: 266664.26
A21: 2.2.6 - SEGUROS | B21: =SUM(C21:N21) -> 0
A22: 2.2.7 - SERVICIOS DE CONSERVACIÓN, REPARACIONES MENORES E INSTALACIONES TEMPORALES | B22: =SUM(C22:N22) -> 2064518.4 | C22: 2064518.4
A23: 2.2.8 - OTROS SERVICIOS NO INCLUIDOS EN CONCEPTOS ANTERIORES | B23: =SUM(C23:N23) -> 51345.35 | C23: =37988+13357.35 -> 51345.35
A24: 2.2.9 - OTRAS CONTRATACIONES DE SERVICIOS | B24: =SUM(C24:N24) -> 0
A25: 2.3 - MATERIALES Y SUMINISTROS | B25: =SUM(C25:N25) -> 3062630.7 | C25: =SUM(C26:C34) -> 3062630.7 | D25: =SUM(D26:D34) -> 0 | E25: =SUM(E26:E34) -> 0 | F25: =SUM(F26:F34) -> 0 | G25: =SUM(G26:G34) -> 0 | H25: =SUM(H26:H34) -> 0 | I25: =SUM(I26:I34) -> 0 | J25: =SUM(J26:J34) -> 0 | ... N25: =SUM(N26:N34) -> 0
A26: 2.3.1 - ALIMENTOS Y PRODUCTOS AGROFORESTALES | B26: =SUM(C26:N26) -> 541265 | C26: 541265
A27: 2.3.2 - TEXTILES Y VESTUARIOS | B27: =SUM(C27:N27) -> 0
A28: 2.3.3 - PRODUCTOS DE PAPEL, CARTÓN E IMPRESOS | B28: =SUM(C28:N28) -> 85550 | C28: 85550
A29: 2.3.4 - PRODUCTOS FARMACÉUTICOS | B29: =SUM(C29:N29) -> 308000 | C29: 308000
A30: 2.3.5 - PRODUCTOS DE CUERO, CAUCHO Y PLÁSTICO | B30: =SUM(C30:N30) -> 0
A31: 2.3.6 - PRODUCTOS DE MINERALES, METÁLICOS Y NO METÁLICOS | B31: =SUM(C31:N31) -> 0
A32: 2.3.7 - COMBUSTIBLES, LUBRICANTES, PRODUCTOS QUÍMICOS Y CONEXOS | B32: =SUM(C32:N32) -> 228412.84 | C32: 228412.84
A33: 2.3.8 - GASTOS QUE SE ASIGNARÁN DURANTE EL EJERCICIO (ART. 32 Y 33 LEY 423-06) | B33: =SUM(C33:N33) -> 0
A34: 2.3.9 - PRODUCTOS Y ÚTILES VARIOS | B34: =SUM(C34:N34) -> 1899402.8 | C34: 1899402.8
A35: 2.4 - TRANSFERENCIAS CORRIENTES | B35: =SUM(C35:N35) -> 136966.7 | C35: =SUM(C36:C42) -> 136966.7 | D35: =SUM(D36:D42) -> 0 | E35: =SUM(E36:E42) -> 0 | F35: =SUM(F36:F42) -> 0 | G35: =SUM(G36:G42) -> 0 | H35: =SUM(H36:H42) -> 0 | I35: =SUM(I36:I42) -> 0 | J35: =SUM(J36:J42) -> 0 | ... N35: =SUM(N36:N42) -> 0
A36: 2.4.1 - TRANSFERENCIAS CORRIENTES AL SECTOR PRIVADO | B36: =SUM(C36:N36) -> 136966.7 | C36: 136966.7
A37: 2.4.2 - TRANSFERENCIAS CORRIENTES AL GOBIERNO GENERAL NACIONAL | B37: =SUM(C37:N37) -> 0
A38: 2.4.3 - TRANSFERENCIAS CORRIENTES A GOBIERNOS GENERALES LOCALES | B38: =SUM(C38:N38) -> 0
A39: 2.4.4 - TRANSFERENCIAS CORRIENTES A EMPRESAS PÚBLICAS NO FINANCIERAS | B39: =SUM(C39:N39) -> 0
A40: 2.4.5 - TRANSFERENCIAS CORRIENTES A INSTITUCIONES PÚBLICAS FINANCIERAS | B40: =SUM(C40:N40) -> 0
A41: 2.4.7 - TRANSFERENCIAS CORRIENTES AL SECTOR EXTERNO | B41: =SUM(C41:N41) -> 0
A42: 2.4.9 - TRANSFERENCIAS CORRIENTES A OTRAS INSTITUCIONES PÚBLICAS | B42: =SUM(C42:N42) -> 0
A43: 2.5 - TRANSFERENCIAS DE CAPITAL | B43: =SUM(C43:N43) -> 0 | C43: =SUM(C44:C50) -> 0 | D43: =SUM(D44:D50) -> 0 | E43: =SUM(E44:E50) -> 0 | F43: =SUM(F44:F50) -> 0 | G43: =SUM(G44:G50) -> 0 | H43: =SUM(H44:H50) -> 0 | I43: =SUM(I44:I50) -> 0 | J43: =SUM(J44:J50) -> 0 | ... N43: =SUM(N44:N50) -> 0
A44: 2.5.1 - TRANSFERENCIAS DE CAPITAL AL SECTOR PRIVADO | B44: =SUM(C44:N44) -> 0
A45: 2.5.2 - TRANSFERENCIAS DE CAPITAL AL GOBIERNO GENERAL NACIONAL | B45: =SUM(C45:N45) -> 0
A46: 2.5.3 - TRANSFERENCIAS DE CAPITAL A GOBIERNOS GENERALES LOCALES | B46: =SUM(C46:N46) -> 0
A47: 2.5.4 - TRANSFERENCIAS DE CAPITAL A EMPRESAS PÚBLICAS NO FINANCIERAS | B47: =SUM(C47:N47) -> 0
A48: 2.5.5 - TRANSFERENCIAS DE CAPITAL A INSTITUCIONES PÚBLICAS FINANCIERAS | B48: =SUM(C48:N48) -> 0
A49: 2.5.6 - TRANSFERENCIAS DE CAPITAL AL SECTOR EXTERNO | B49: =SUM(C49:N49) -> 0
A50: 2.5.9 - TRANSFERENCIAS DE CAPITAL A OTRAS INSTITUCIONES PÚBLICAS | B50: =SUM(C50:N50) -> 0
A51: 2.6 - BIENES MUEBLES, INMUEBLES E INTANGIBLES | B51: =SUM(C51:N51) -> 887994.84 | C51: =SUM(C52:C60) -> 887994.84 | D51: =SUM(D52:D60) -> 0 | E51: =SUM(E52:E60) -> 0 | F51: =SUM(F52:F60) -> 0 | G51: =SUM(G52:G60) -> 0 | H51: =SUM(H52:H60) -> 0 | I51: =SUM(I52:I60) -> 0 | J51: =SUM(J52:J60) -> 0 | ... N51: =SUM(N52:N60) -> 0
A52: 2.6.1 - MOBILIARIO Y EQUIPO | B52: =SUM(C52:N52) -> 0
A53: 2.6.2 - MOBILIARIO Y EQUIPO EDUCACIONAL Y RECREATIVO | B53: =SUM(C53:N53) -> 0
A54: 2.6.3 - EQUIPO E INSTRUMENTAL, CIENTÍFICO Y LABORATORIO | B54: =SUM(C54:N54) -> 887994.84 | C54: 887994.84
A55: 2.6.4 - VEHÍCULOS Y EQUIPO DE TRANSPORTE, TRACCIÓN Y ELEVACIÓN | B55: =SUM(C55:N55) -> 0
A56: 2.6.5 - MAQUINARIA, OTROS EQUIPOS Y HERRAMIENTAS | B56: =SUM(C56:N56) -> 0
A57: 2.6.6 - EQUIPOS DE DEFENSA Y SEGURIDAD | B57: =SUM(C57:N57) -> 0
A58: 2.6.7 - ACTIVOS BIÓLOGICOS CULTIVABLES | B58: =SUM(C58:N58) -> 0
A59: 2.6.8 - BIENES INTANGIBLES | B59: =SUM(C59:N59) -> 0
A60: 2.6.9 - EDIFICIOS, ESTRUCTURAS, TIERRAS, TERRENOS Y OBJETOS DE VALOR | B60: =SUM(C60:N60) -> 0
A61: 2.7 - OBRAS | B61: =SUM(C61:N61) -> 0 | C61: =SUM(C62:C65) -> 0 | D61: =SUM(D62:D65) -> 0 | E61: =SUM(E62:E65) -> 0 | F61: =SUM(F62:F65) -> 0 | G61: =SUM(G62:G65) -> 0 | H61: =SUM(H62:H65) -> 0 | I61: =SUM(I62:I65) -> 0 | J61: =SUM(J62:J65) -> 0 | ... N61: =SUM(N62:N65) -> 0
A62: 2.7.1 - OBRAS EN EDIFICACIONES | B62: =SUM(C62:N62) -> 0
A63: 2.7.2 - INFRAESTRUCTURA | B63: =SUM(C63:N63) -> 0
A64: 2.7.3 - CONSTRUCCIONES EN BIENES CONCESIONADOS | B64: =SUM(C64:N64) -> 0
A65: 2.7.4 - GASTOS QUE SE ASIGNARÁN DURANTE EL EJERCICIO PARA INVERSIÓN (ART. 32 Y 33 LEY 423-06) | B65: =SUM(C65:N65) -> 0
A66: 2.8 - ADQUISICION DE ACTIVOS FINANCIEROS CON FINES DE POLÍTICA | B66: =SUM(C66:N66) -> 0 | C66: =SUM(C67:C68) -> 0 | D66: =SUM(D67:D68) -> 0 | E66: =SUM(E67:E68) -> 0 | F66: =SUM(F67:F68) -> 0 | G66: =SUM(G67:G68) -> 0 | H66: =SUM(H67:H68) -> 0 | I66: =SUM(I67:I68) -> 0 | J66: =SUM(J67:J68) -> 0 | ... N66: =SUM(N67:N68) -> 0
A67: 2.8.1 - CONCESIÓN DE PRESTAMOS | B67: =SUM(C67:N67) -> 0
A68: 2.8.2 - ADQUISICIÓN DE TÍTULOS VALORES REPRESENTATIVOS DE DEUDA | B68: =SUM(C68:N68) -> 0
A69: 2.9 - GASTOS FINANCIEROS | B69: =SUM(C69:N69) -> 0 | C69: =SUM(C70:C72) -> 0 | D69: =SUM(D70:D72) -> 0 | E69: =SUM(E70:E72) -> 0 | F69: =SUM(F70:F72) -> 0 | G69: =SUM(G70:G72) -> 0 | H69: =SUM(H70:H72) -> 0 | I69: =SUM(I70:I72) -> 0 | J69: =SUM(J70:J72) -> 0 | ... N69: =SUM(N70:N72) -> 0
A70: 2.9.1 - INTERESES DE LA DEUDA PÚBLICA INTERNA | B70: =SUM(C70:N70) -> 0
A71: 2.9.2 - INTERESES DE LA DEUDA PUBLICA EXTERNA | B71: =SUM(C71:N71) -> 0
A72: 2.9.4 - COMISIONES Y OTROS GASTOS BANCARIOS DE LA DEUDA PÚBLICA | B72: =SUM(C72:N72) -> 0
A73: Total Gastos | B73: =B9+B15+B25+B35+B43+B51+B61+B66+B69 -> 6821436.5 | C73: =C9+C15+C25+C35+C43+C51+C61+C66+C69 -> 6821436.5 | D73: =D9+D15+D25+D35+D43+D51+D61+D66+D69 -> 0 | E73: =E9+E15+E25+E35+E43+E51+E61+E66+E69 -> 0 | F73: =F9+F15+F25+F35+F43+F51+F61+F66+F69 -> 0 | G73: =G9+G15+G25+G35+G43+G51+G61+G66+G69 -> 0 | H73: =H9+H15+H25+H35+H43+H51+H61+H66+H69 -> 0 | I73: =I9+I15+I25+I35+I43+I51+I61+I66+I69 -> 0 | ... N73: =N9+N15+N25+N35+N43+N51+N61+N66+N69 -> 0
A74: 4 - APLICACIONES FINANCIERAS
A75: 4.1 - INCREMENTO DE ACTIVOS FINANCIEROS
A76: 4.1.1 - INCREMENTO DE ACTIVOS FINANCIEROS CORRIENTES
A77: 4.1.2 - INCREMENTO DE ACTIVOS FINANCIEROS NO CORRIENTES
A78: 4.2 - DISMINUCIÓN DE PASIVOS
A79: 4.2.1 - DISMINUCIÓN DE PASIVOS CORRIENTES
A80: 4.2.2 - DISMINUCIÓN DE PASIVOS NO CORRIENTES
A81: 4.3 - DISMINUCIÓN DE FONDOS DE TERCEROS
A82: 4.3.5 - DISMINUCIÓN DEPÓSITOS FONDOS DE TERCEROS
A83: TOTAL APLICACIONES FINANCIERAS
A85: TOTAL GASTOS Y APLICACIONES FINANCIERAS | B85: =+B83+B73 -> 6821436.5 | C85: =+C83+C73 -> 6821436.5 | D85: =+D83+D73 -> 0 | E85: =+E83+E73 -> 0 | F85: =+F83+F73 -> 0 | G85: =+G83+G73 -> 0 | H85: =+H83+H73 -> 0 | I85: =+I83+I73 -> 0 | ... N85: =+N83+N73 -> 0
A86: Fuente: [VENTA DE SERVICIOS)
A87: Fecha de registro: hasta el [01] de [01) del [2024]
A88: Fecha de imputación: hasta el [31] de [07] del [2024]

Sheet OBLIGACIONES PENDIENTES
B4: SERVICIO REGIONAL DE SALUD
B5: DIRECCIÓN DE FISCALIZACIÓN Y CONTROL
B6: DETALLE OBLIGACIONES CONTRAÍDAS PENDIENTES AL 31 DE ENERO 2025
B7: HOSPITAL MATERNO INFANTIL SAN LORENZO DE LOS MINA
B8: A | C8: B | E8: C | F8: D | G8: E | H8: F
B9: TIPO | C9: PERÍODO | F9: STATUS PRESTAMO
C10: DESDE | D10: HASTA | E10: MONTO | F10: MONTO ORIGEN | G10: MONTO AMORTIZADO | H10: BALANCE PENDIENTE
B11: PROMESE CAL
B12: RETENCIONES DE IMPUESTOS (DGII) | C12: 44470 | D12: 45688 | E12: =6455721.37+191917.63+545919.42+146780.59+231604.06+289366.65+335354.64+387110.47+660164.03+254405.37+295100.71+268154.84+476725.77+301006.83+418780.67+471731.75 -> 11729845
B13: APROVISIONAMIENTOS DE INCENTIVOS | C13: 45505 | D13: 45688 | E13: 4432093.6
B14: SEGURIDAD SOCIAL
B15: APROVISIONAMIENTO DE REGALIA PASCUAL
B16: PRESTACIONES LABORALES | C16: 45623 | D16: 45688 | E16: =894240.08+200792.95 -> 1095033
B17: VIATICOS
B18: PRÉSTAMOS Y/O ANTICIPOS FINANCIEROS OTORGADOS POR SENASA
B19: TOTAL | E19: =SUM(E12:E18)+E11 -> 17256971
B21: Nota. En el caso de las columnas D, E y F, solo aplican para llenado de los préstamos otogados por SENASA.
B25: Preparado por: | E25: Revisado por:

Sheet DEUDA
B1: Servicio Nacional de Salud
B2: Dirección de Control y Fiscalización
B3: Hospital Materno Infantil San Lorenzo de Los Mina
B4: Region Santo Domingo Este
B5: CUENTAS POR PAGAR 31 DE ENERO 2025
A8: NO | B8: NOMBRES PROVEEDOR | C8: MONTO | D8: FUENTE DE FINANCIAMIENTO | E8: Años ANTERIORES 2019 HACIA ATRÁS | F8: AL 31 DICIEMBRE 2020 | G8: AL 31 DICIEMBRE 2021 | H8: AL 31 DICIEMBRE 2022 | I8: Al 31 DICIEMBRE 2023 | J8: AÑO 2024 | K8: ENERO-2025 | L8: TOTAL
A9: 1 | B9: Copem Hospiclinic, SRL | C9: 14300 | D9: VS/FONDO GENERAL | H9: 14300 | L9: =SUM(E9:K9) -> 14300
A10: =+A9+1 -> 2 | B10: Ameriline Pharmaceutical, SRL | C10: 54000 | D10: VS/FONDO GENERAL | I10: 54000 | L10: =SUM(E10:K10) -> 54000
A11: =+A10+1 -> 3 | B11: Hospifar, SRL | C11: 11375 | D11: VS/FONDO GENERAL | I11: 11375 | L11: =SUM(E11:K11) -> 11375
A12: =+A11+1 -> 4 | B12: Hospifar, SRL | C12: 94965 | D12: VS/FONDO GENERAL | I12: 94965 | L12: =SUM(E12:K12) -> 94965
A13: =+A12+1 -> 5 | B13: Bio Win, SRL | C13: 1650 | D13: VS/FONDO GENERAL | I13: 1650 | L13: =SUM(E13:K13) -> 1650
A14: =+A13+1 -> 6 | B14: Bio Win, SRL | C14: 1650 | D14: VS/FONDO GENERAL | I14: 1650 | L14: =SUM(E14:K14) -> 1650
A15: =+A14+1 -> 7 | B15: BRONTILLO | C15: 88116 | D15: VS/FONDO GENERAL | I15: 88116 | L15: =SUM(E15:K15) -> 88116
A16: =+A15+1 -> 8 | B16: Global Multi-Pharma Dominicana THM, SRL | C16: 53395 | D16: VS/FONDO GENERAL | I16: 53395 | L16: =SUM(E16:K16) -> 53395
A17: =+A16+1 -> 9 | B17: Ventas Diversas Farmaceuticas, SRL (VENDIFAR) | C17: 224775 | D17: VS/FONDO GENERAL | I17: 224775 | L17: =SUM(E17:K17) -> 224775
A18: =+A17+1 -> 10 | B18: GA INTERPRISE IMPORT, SRL | C18: 287920 | D18: VS/FONDO GENERAL | I18: 287920 | L18: =SUM(E18:K18) -> 287920
A19: =+A18+1 -> 11 | B19: Mecala Importadora, SRL | C19: 25180 | D19: VS/FONDO GENERAL | I19: 25180 | L19: =SUM(E19:K19) -> 25180
A20: =+A19+1 -> 12 | B20: D, CORA INDUSTRIAL, S.R.L | C20: 220483.05 | D20: VS/FONDO GENERAL | I20: 220483.05 | L20: =SUM(E20:K20) -> 220483.05
A21: =+A20+1 -> 13 | B21: VARA, SRL. | C21: 58382.86 | D21: VS/FONDO GENERAL | I21: 58382.86 | L21: =SUM(E21:K21) -> 58382.86
... A27: =+A26+1 -> 19 | B27: ORTRO CHEMICAL, S. A. | C27: 252089.3 | D27: VS/FONDO GENERAL | I27: 252089.3 | L27: =SUM(E27:K27) -> 252089.3
A28: =+A27+1 -> 20 | B28: SLYKING GROUP, SRL | C28: 39361.26 | D28: VS/FONDO GENERAL | J28: 39361.26 | L28: =SUM(E28:K28) -> 39361.26
A29: =+A28+1 -> 21 | B29: FARMACIA RUTH | C29: 88100 | D29: VS/FONDO GENERAL | J29: 88100 | L29: =SUM(E29:K29) -> 88100
A30: =+A29+1 -> 22 | B30: Cristina Rosario Rosario | C30: 120006 | D30: VS/FONDO GENERAL | J30: 120006 | L30: =SUM(E30:K30) -> 120006
A31: =+A30+1 -> 23 | B31: Q&Q Medical RD, SRL | C31: 253810.92 | D31: VS/FONDO GENERAL | J31: 253810.92 | L31: =SUM(E31:K31) -> 253810.92
A32: =+A31+1 -> 24 | B32: Q&Q Medical RD, SRL | C32: 298492.8 | D32: VS/FONDO GENERAL | J32: 298492.8 | L32: =SUM(E32:K32) -> 298492.8
A33: =+A32+1 -> 25 | B33: Bio Nuclear, SA | C33: 5568 | D33: VS/FONDO GENERAL | J33: 5568 | L33: =SUM(E33:K33) -> 5568
A34: =+A33+1 -> 26 | B34: Macrotech Farmacéutica, SRL | C34: 215000 | D34: VS/FONDO GENERAL | J34: 215000 | L34: =SUM(E34:K34) -> 215000
A35: =+A34+1 -> 27 | B35: Air Liquide Dominicana, SAS | C35: 6369.3686 | D35: VS/FONDO GENERAL | J35: 6369.3686 | L35: =SUM(E35:K35) -> 6369.3686
A36: =+A35+1 -> 28 | B36: LE.F.P CONSULTORES SRL | C36: 48852 | D36: VS/FONDO GENERAL | J36: 48852 | L36: =SUM(E36:K36) -> 48852
A37: =+A36+1 -> 29 | B37: LE.F.P CONSULTORES SRL | C37: 48852 | D37: VS/FONDO GENERAL | J37: 48852 | L37: =SUM(E37:K37) -> 48852
A38: =+A37+1 -> 30 | B38: Air Liquide Dominicana, SAS | C38: 12832.5 | D38: VS/FONDO GENERAL | J38: 12832.5 | L38: =SUM(E38:K38) -> 12832.5
A39: =+A38+1 -> 31 | B39: ORTRO CHEMICAL, S. A. | C39: 42000 | D39: VS/FONDO GENERAL | J39: 42000 | L39: =SUM(E39:K39) -> 42000
... A173: =+A172+1 -> 165 | B173: Air Liquide Dominicana, SAS | C173: 673433.54 | D173: VS/FONDO GENERAL | J173: 673433.54 | L173: =SUM(E173:K173) -> 673433.54
A174: =+A173+1 -> 166 | B174: Air Liquide Dominicana, SAS | C174: 5459.46 | D174: VS/FONDO GENERAL | K174: 5459.46 | L174: =SUM(E174:K174) -> 5459.46
A175: =+A174+1 -> 167 | B175: IMD Medic Inter SRL | C175: 218400 | D175: VS/FONDO GENERAL | K175: 218400 | L175: =SUM(E175:K175) -> 218400
A176: =+A175+1 -> 168 | B176: Corporacion Medica A.G., SRL | C176: 264900 | D176: VS/FONDO GENERAL | K176: 264900 | L176: =SUM(E176:K176) -> 264900
A177: =+A176+1 -> 169 | B177: Corporacion Medica A.G., SRL | C177: 269892.4 | D177: VS/FONDO GENERAL | K177: 269892.4 | L177: =SUM(E177:K177) -> 269892.4
A178: =+A177+1 -> 170 | B178: Super Latop Browsing SRL | C178: 6490 | D178: VS/FONDO GENERAL | K178: 6490 | L178: =SUM(E178:K178) -> 6490
A179: =+A178+1 -> 171 | B179: Papelería E. Impresos Crishoan, SRL | C179: 226357.04 | D179: VS/FONDO GENERAL | K179: 226357.04 | L179: =SUM(E179:K179) -> 226357.04
A180: =+A179+1 -> 172 | B180: Express Service Conserg Exsercon, SRL | C180: 269040 | D180: VS/FONDO GENERAL | K180: 269040 | L180: =SUM(E180:K180) -> 269040
A181: =+A180+1 -> 173 | B181: Air Liquide Dominicana, SAS | C181: 8982.75 | D181: VS/FONDO GENERAL | K181: 8982.75 | L181: =SUM(E181:K181) -> 8982.75
A182: =+A181+1 -> 174 | B182: Air Liquide Dominicana, SAS | C182: 5459.46 | D182: VS/FONDO GENERAL | K182: 5459.46 | L182: =SUM(E182:K182) -> 5459.46
A183: =+A182+1 -> 175 | B183: Insocorp, S.R.L. | C183: 20060 | D183: VS/FONDO GENERAL | K183: 20060 | L183: =SUM(E183:K183) -> 20060
A184: =+A183+1 -> 176 | B184: Ameriline Pharmaceutical, SRL | C184: 86700 | D184: VS/FONDO GENERAL | K184: 86700 | L184: =SUM(E184:K184) -> 86700
A185: =+A184+1 -> 177 | B185: MEDINA N SOLUTIONS SRL | C185: 128506.72 | D185: VS/FONDO GENERAL | K185: 128506.72 | L185: =SUM(E185:K185) -> 128506.72
... A227: =+A226+1 -> 219 | B227: Super Latop Browsing SRL | C227: 120360 | D227: VS/FONDO GENERAL | K227: 120360 | L227: =SUM(E227:K227) -> 120360
B228: TOTAL GENERAL | C228: =SUM(C9:C227) -> 37206225 | D228: =SUM(D9:D227) -> 0 | E228: =SUM(E9:E227) -> 0 | F228: =SUM(F9:F227) -> 0 | G228: =SUM(G9:G227) -> 0 | H228: =SUM(H9:H227) -> 14300 | I228: =SUM(I9:I227) -> 2149204.8 | J228: =SUM(J9:J227) -> 21800399 | ... L228: =SUM(L9:L227) -> 37206225

Sheet INGRESOS POR A.R.S
A2: Servicio Nacional De Salud
A3: Dirección de Fiscalizacion y Control
A4: Ingresos Por Facturación ARS
E5: AÑO 2024
A6: Establecimiento: Hospital Materno Infantil San Lorenzo de Los Mina SRS: METROPOLITANO
A8: ARS | C8: ENERO | E8: FEBRERO | G8: MARZO | I8: ABRIL | K8: MAYO | M8: JUNIO | O8: JULIO | Q8: AGOSTO | S8: SEPTIEMBRE | U8: OCTUBRE | W8: NOVIEMBRE | Y8: DICIEMBRE | AA8: Total
C9: Facturado | D9: Recibido | E9: Facturado | F9: Recibido | G9: Facturado | H9: Recibido | I9: Facturado | J9: Recibido | K9: Facturado | L9: Recibido | M9: Facturado | N9: Recibido | O9: Facturado | P9: Recibido | Q9: Facturado | R9: Recibido | S9: Facturado | T9: Recibido | U9: Facturado | V9: Recibido | W9: Facturado | X9: Recibido | Y9: Facturado | Z9: Recibido | AA9: Facturado | AB9: Recibido
A10: 1 | B10: SENASA SUBSIDIADO | C10: =4014536.9+12720.43 -> 4027257.3 | D10: =4783111.5+50000 -> 4833111.5 | AA10: =+C10+E10+G10+I10+K10+M10+O10+Q10+S10+U10+W10+Y10 -> 4027257.3 | AB10: =+R10+D10+F10+H10+J10+L11+N10+P10+T10+V10+X10+Z10 -> 4833111.5
A11: 2 | B11: SENASA CONTRIBUTIVO | C11: 1094583.8 | AA11: =+C11+E11+G11+I11+K11+M11+O11+Q11+S11+U11+W11+Y11 -> 1094583.8 | AB11: =+R11+D11+F11+H11+J11+L12+N11+P11+T11+V11+X11+Z11 -> 0
B12: SENASA JUB. Y PENS. | AA12: =+Y12+W12+U12+S12+Q12+O12+M12+K12+I12+G12+E12+C12 -> 0
A13: Total SeNaSa | C13: =SUM(C10:C12) -> 5121841.1 | D13: =SUM(D10:D12) -> 4833111.5 | E13: =SUM(E10:E12) -> 0 | F13: =SUM(F10:F12) -> 0 | G13: =SUM(G10:G12) -> 0 | H13: =SUM(H10:H12) -> 0 | I13: =SUM(I10:I12) -> 0 | J13: =SUM(J10:J12) -> 0 | K13: =SUM(K10:K11) -> 0 | L13: =SUM(L10:L11) -> 0 | M13: 6698468.9 | N13: =SUM(N10:N12) -> 0 | O13: =SUM(O10:O12) -> 0 | P13: =SUM(P10:P12) -> 0 | Q13: =SUM(Q10:Q12) -> 0 | R13: =SUM(R10:R12) -> 0 | S13: =SUM(S10:S12) -> 0 | T13: =SUM(T10:T12) -> 0 | U13: =SUM(U10:U12) -> 0 | ... AB13: =SUM(AB10:AB12) -> 4833111.5
A14: 3 | B14: PALIC SALUD(MAPFRE) | C14: =39434.4+16378.75+155901.42 -> 211714.57 | D14: =143189.49+55488.8+8230.16 -> 206908.45 | AA14: =+Y14+W14+U14+S14+Q14+O14+M14+K14+I14+G14+E14+C14 -> 211714.57 | AB14: =+R14+D14+F14+H14+J14+L15+N14+P14+T14+V14+X14+Z14 -> 206908.45
A15: 4 | B15: ARL | AA15: =+Y15+W15+U15+S15+Q15+O15+M15+K15+I15+G15+E15+C15 -> 0 | AB15: =+R15+D15+F15+H15+J15+L16+N15+P15+T15+V15+X15+Z15 -> 0
A16: 5 | B16: RENACER | C16: 275352.44 | D16: 156983.55 | AA16: =+Y16+W16+U16+S16+Q16+O16+M16+K16+I16+G16+E16+C16 -> 275352.44 | AB16: =+R16+D16+F16+H16+J16+L17+N16+P16+T16+V16+X16+Z16 -> 156983.55
A17: 6 | B17: YUNEN | C17: 7848.94 | D17: 55135.74 | AA17: =+Y17+W17+U17+S17+Q17+O17+M17+K17+I17+G17+E17+C17 -> 7848.94 | AB17: =+R17+D17+F17+H17+J17+L18+N17+P17+T17+V17+X17+Z17 -> 55135.74
A18: 7 | B18: UNIVERSAL | AA18: =+Y18+W18+U18+S18+Q18+O18+M18+K18+I18+G18+E18+C18 -> 0 | AB18: =+R18+D18+F18+H18+J18+L19+N18+P18+T18+V18+X18+Z18 -> 0
A19: 8 | B19: ARS HUMANO | C19: 44770.98 | AA19: =+Y19+W19+U19+S19+Q19+O19+M19+K19+I19+G19+E19+C19 -> 44770.98 | AB19: =+R19+D19+F19+H19+J19+L20+N19+P19+T19+V19+X19+Z19 -> 0
A20: 9 | B20: ARS PLANSALUD BANCO CENTRAL | AA20: =+Y20+W20+U20+S20+Q20+O20+M20+K20+I20+G20+E20+C20 -> 0 | AB20: =+R20+D20+F20+H20+J20+L21+N20+P20+T20+V20+X20+Z20 -> 0
A21: 10 | B21: SEMMA | C21: 7193.05 | D21: 15993.02 | AA21: =+Y21+W21+U21+S21+Q21+O21+M21+K21+I21+G21+E21+C21 -> 7193.05 | AB21: =+R21+D21+F21+H21+J21+L22+N21+P21+T21+V21+X21+Z21 -> 15993.02
A22: 11 | B22: FUTURO | C22: 269639.73 | D22: 234503.89 | AA22: =+Y22+W22+U22+S22+Q22+O22+M22+K22+I22+G22+E22+C22 -> 269639.73 | AB22: =+R22+D22+F22+H22+J22+L23+N22+P22+T22+V22+X22+Z22 -> 234503.89
A23: 12 | B23: APS | C23: 69588.33 | AA23: =+Y23+W23+U23+S23+Q23+O23+M23+K23+I23+G23+E23+C23 -> 69588.33 | AB23: =+R23+D23+F23+H23+J23+L24+N23+P23+T23+V23+X23+Z23 -> 0
A24: 13 | B24: SALUD SEGURA | AA24: =+Y24+W24+U24+S24+Q24+O24+M24+K24+I24+G24+E24+C24 -> 0 | AB24: =+R24+D24+F24+H24+J24+L25+N24+P24+T24+V24+X24+Z24 -> 0
A25: 14 | B25: CONSTITUCION (ASISTANET) | AA25: =+Y25+W25+U25+S25+Q25+O25+M25+K25+I25+G25+E25+C25 -> 0 | AB25: =+R25+D25+F25+H25+J25+L26+N25+P25+T25+V25+X25+Z25 -> 0
A26: 15 | B26: META SALUD | C26: 1396 | AA26: =+Y26+W26+U26+S26+Q26+O26+M26+K26+I26+G26+E26+C26 -> 1396 | AB26: =+R26+D26+F26+H26+J26+L27+N26+P26+T26+V26+X26+Z26 -> 0
A27: 16 | B27: ASEMAP | C27: 4869.52 | D27: 6475.14 | AA27: =+Y27+W27+U27+S27+Q27+O27+M27+K27+I27+G27+E27+C27 -> 4869.52 | AB27: =+R27+D27+F27+H27+J27+L28+N27+P27+T27+V27+X27+Z27 -> 6475.14
A28: 17 | B28: GMA | C28: 76159.34 | AA28: =+Y28+W28+U28+S28+Q28+O28+M28+K28+I28+G28+E28+C28 -> 76159.34 | AB28: =+R28+D28+F28+H28+J28+L29+N28+P28+T28+V28+X28+Z28 -> 0
A29: 18 | B29: MONUMENTAL | C29: 75131.09 | D29: 71992.2 | AA29: =+Y29+W29+U29+S29+Q29+O29+M29+K29+I29+G29+E29+C29 -> 75131.09 | AB29: =+R29+D29+F29+H29+J29+L30+N29+P29+T29+V29+X29+Z29 -> 71992.2
A30: 19 | B30: CMD | C30: 273646.7 | D30: 273646.7 | AA30: =+Y30+W30+U30+S30+Q30+O30+M30+K30+I30+G30+E30+C30 -> 273646.7 | AB30: =+R30+D30+F30+H30+J30+L31+N30+P30+T30+V30+X30+Z30 -> 273646.7
A31: 20 | B31: RESERVAS | C31: 48081.02 | D31: 48081.02 | AA31: =+Y31+W31+U31+S31+Q31+O31+M31+K31+I31+G31+E31+C31 -> 48081.02 | AB31: =+R31+D31+F31+H31+J31+L32+N31+P31+T31+V31+X31+Z31 -> 48081.02
A32: 21 | B32: SIMAG | C32: 28637.51 | AA32: =+Y32+W32+U32+S32+Q32+O32+M32+K32+I32+G32+E32+C32 -> 28637.51 | AB32: =+R32+D32+F32+H32+J32+L33+N32+P32+T32+V32+X32+Z32 -> 0
A33: 22 | B33: SEMUNASED | AA33: =+Y33+W33+U33+S33+Q33+O33+M33+K33+I33+G33+E33+C33 -> 0 | AB33: =+R33+D33+F33+H33+J33+L34+N33+P33+T33+V33+X33+Z33 -> 0
A34: 23 | B34: PRIMERA ARS HUMANO | C34: 259154.57 | AA34: =+Y34+W34+U34+S34+Q34+O34+M34+K34+I34+G34+E34+C34 -> 259154.57 | AB34: =+R34+D34+F34+H34+J34+L35+N34+P34+T34+V34+X34+Z34 -> 0
A35: Total ARS PRIVADAS | C35: =SUM(C14:C34) -> 1653183.8 | D35: =SUM(D14:D34) -> 1069719.7 | E35: =SUM(E14:E34) -> 0 | F35: =SUM(F14:F34) -> 0 | G35: =SUM(G14:G34) -> 0 | H35: =SUM(H14:H34) -> 0 | I35: =SUM(I14:I34) -> 0 | J35: =SUM(J14:J34) -> 0 | ... AB35: =SUM(AB14:AB34) -> 1069719.7
A36: TOTAL | C36: =C13+C35 -> 6775024.9 | D36: =D13+D35 -> 5902831.2 | E36: =E13+E35 -> 0 | F36: =F13+F35 -> 0 | G36: =G13+G35 -> 0 | H36: =H13+H35 -> 0 | I36: =I13+I35 -> 0 | J36: =J13+J35 -> 0 | ... L36: =L13+L35 -> 0 | M36: =+M35+M13 -> 6698468.9 | N36: =+N35+N13 -> 0 | O36: =O13+O35 -> 0 | P36: =P13+P35 -> 0 | Q36: =Q13+Q35 -> 0 | R36: =R13+R35 -> 0 | S36: =S13+S35 -> 0 | T36: =T13+T35 -> 0 | U36: =U13+U35 -> 0 | V36: =V13+V35 -> 0 | ... AB36: =AB13+AB35 -> 5902831.2

Sheet INGRESOS SEGUN ORIGEN
A1: Servicio Nacional de Salud
A2: Dirección de Fiscalización y Control
A3: CORRESPONDIENTE AL MES DE ENERO 2025
A4: Comportamiento de Ingresos percibidos Segregados según Origen
A5: Establecimientos: HOSPITAL MATERNO INFANTIL SAN LORENZO DE LOS MINA
A6: origen | B6: ARS | C6: Fecha | D6: No. De Documento de referencia | E6: valor de Transferencia o Cheque
A7: Anticipos Financieros | B7: FONDO 100(PARA SERV. PERSONALES) | C7: 45658 | E7: =79621891.83+4931430 -> 84553322
B8: FONDO 100(PARA OBJECTALES 2.2,2.3,2.6,2.7.) | C8: 45659 | E8: =3169632.08+12593841.17 -> 15763473
B9: Fondos Asistencial | C9: 45660
B10: Sub-Total | E10: =(E7+E8) -> 1.003168e+08
A11: Venta de Servicio | B11: ARS SUBSIDIADO | C11: 45659 | E11: 4783111.5
B12: ARS SUBSIDIADO | C12: 45666 | E12: 50000
B13: ARS RENACER | C13: 45674 | E13: 156983.55
B14: ARS MAPHRE | C14: 45677 | E14: 143189.49
B15: ARS MAPHRE | C15: 45677 | E15: 55488.8
B16: ARS MAPHRE | C16: 45677 | E16: 8230.16
B17: ARS SEMMA | C17: 45677 | E17: 15993.02
B18: ARS ASEMAP | C18: 45680 | E18: 6475.14
B19: ARS MONUMENTAL | C19: 45680 | E19: 71992.2
B20: ARS CMD | C20: 45681 | E20: 273646.7
B21: ARS FUTURO | C21: 45686 | E21: 234503.89
B22: ARS RESERVAS | C22: 45687 | E22: 48081.02
B23: ARS YUNEN | C23: 45688 | E23: 55135.74
B26: Sub-Total | E26: =SUM(E11:E25) -> 5902831.2
A27: Otros aportes | B27: Ingresos por servicios pacientes privados y diferencias por seguros medicos | E27: 129650
B28: Aportes provenientes de convenios Institucionales
B30: Otros (CAFETERIA ) | E30: 0
B31: Sub-Total | E31: =SUM(E27:E30) -> 129650
B32: Total | E32: =E26+E31+E10 -> 1.0634928e+08
A34: Bajo las funciones que nos asisten certificamos que el valor de los ingresos percibidos al 31 DE ENERO 2025 fueronde(RD$106,349,276.29)
A40: Firma y sello Administrados | D40: Firma y sello Financiero
A43: **Nota: En Venta de Servicios agregar celda según pago segregado de ARS lo amerita.

Sheet GLOSA
A1: Servicio Nacional de Salud
A2: Hospital Materno Infantil San Lorenzo de Los Mina
A3: Dirección de Fiscalización y Control
A4: Glosa
A5: Establecimientos | B5: Facturado | C5: Recibido | D5: Glosado | E5: %
A6: ENERO | B6: 6672189.9 | C6: 5902831.2 | D6: 102835 | E6: =+D6/B6 -> 0.015412481
A7: FEBRERO | E7: =+D7/B7 -> #DIV/0!
A8: MARZO | E8: =+D8/B8 -> #DIV/0!
A9: ABRIL | E9: =+D9/B9 -> #DIV/0!
A10: MAYO | E10: =+D10/B10 -> #DIV/0!
A11: JUNIO | E11: =+D11/B11 -> #DIV/0!
A12: JULIO | E12: =+D12/B12 -> #DIV/0!
A13: AGOSTO | E13: 0
A14: SEPTIEMBRE | E14: 0
A15: OCTUBRE | E15: 0
A16: NOVIEMBRE | E16: 0
A17: DICIEMBRE | E17: 0
A18: Total | B18: =SUM(B6:B17) -> 6672189.9 | C18: =SUM(C6:C17) -> 5902831.2 | D18: =SUM(D6:D17) -> 102835 | E18: =+D18/B18 -> 0.015412481
A20: Preparado por:
A21: Licda.

Sheet CXC
A4: HOSPITAL MATERNO INFANTIL SAN LORENZO DE LOS MINA
A5: CUENTAS POR COBRAR ARS AÑO 2025
A7: Auxiliar Cuentas por Cobrar SeNaSa Subsidiado
J8: Balance Anterior | K8: 2710241.1
A9: ARS | B9: FECHA DE CORTE AUDITORIA | C9: CANTIDAD DE EXPEDIENTES | D9: MONTO GENERAL DE FACTURACION | E9: MONTO AUDITADO | F9: MONTO GLOSADO | G9: % | H9: Valor Facturado | I9: Referencia Documento de pago (CK-T) | J9: Monto pagado | K9: Balance CxC
A10: ARS SENASA SUBSIDIADO | B10: 45657 | D10: 4014536.9 | E10: 4014536.9 | F10: 85535 | G10: =+F10/E10 -> 0.021306318 | H10: 3929001.9 | K10: =+K8+H10-J10 -> 6639243
A11: ARS SENASA SUBSIDIADO | I11: 02/01/2025 | J11: 4783111.5 | K11: =+K10+H11-J11 -> 1856131.5
A12: ARS SENASA SUBSIDIADO | I12: 09/01/2025 | J12: 50000 | K12: =+K11+H12-J12 -> 1806131.5
A13: TOTALES | D13: =SUM(D10:D11) -> 4014536.9 | E13: =SUM(E10:E11) -> 4014536.9 | F13: =SUM(F10:F11) -> 85535 | H13: =SUM(H10:H11) -> 3929001.9 | I13: =SUM(I10:I11) -> 0 | J13: =SUM(J10:J11) -> 4783111.5 | K13: =+K12 -> 1806131.5
A16: Auxiliar Cuentas por Cobrar Ars Privadas
I17: BALANCE ANTERIOR | J17: 15638558
A18: ARS | B18: FECHA DE CORTE | C18: NCF | D18: CANTIDAD DE FACTURAS | E18: MONTO FACTURADO | F18: Referencia Documento de pago (CK-T) | G18: MONTO GLOSADO | H18: MONTO PAGADO | I18: DESMONTE POSTERIOR AL PAGO | J18: Balance CxC
A19: HUMANO | B19: 45667 | C19: B0100001070 | E19: 44770.98 | J19: =+J17+E19-H19 -> 15683329
A20: P. HUMANO | B20: 45667 | C20: B0100001071 | E20: 259154.57 | J20: =+J19+E20-G20-H20 -> 15942483
A21: MAPFRE AMB. | B21: 45667 | C21: B0100001072 | E21: 39434.4 | J21: =+J20+E21-G21-H21 -> 15981917
A22: MAPFRE EMERG. | B22: 45667 | C22: B0100001073 | E22: 16378.75 | J22: =+J21+E22-G22-H22 -> 15998296
A23: MAPFRE HOSP. | B23: 45667 | C23: B0100001074 | E23: 155901.42 | J23: =+J22+E23-G23-H23 -> 16154198
A24: RENACER | B24: 45667 | C24: B0100001075 | E24: 275352.44 | J24: =+J23+E24-G24-H24 -> 16429550
A25: YUNEN | B25: 45667 | C25: B0100001076 | E25: 7848.94 | J25: =+J24+E25-G25-H25 -> 16437399
A26: ASEMAP | B26: 45667 | C26: B0100001077 | E26: 4869.52 | J26: =+J25+E26-G26-H26 -> 16442269
A27: FUTURO | B27: 45667 | C27: B0100001078 | E27: 269639.73 | G27: 2300 | J27: =+J26+E27-G27-H27 -> 16709608
A28: MONUMENTAL | B28: 45667 | C28: B0100001079 | E28: 75131.09 | J28: =+J27+E28-G28-H28 -> 16784739
A29: RESERVAS | B29: 45667 | C29: B0100001080 | E29: 48081.02 | J29: =+J28+E29-G29-H29 -> 16832820
A30: CMD | B30: 45667 | C30: B0100001081 | E30: 273646.7 | J30: =+J29+E30-G30-H30 -> 17106467
A31: META SALUD | B31: 45667 | C31: B0100001082 | E31: 1396 | J31: =+J30+E31-G31-H31 -> 17107863
A32: SIMAG | B32: 45667 | C32: B0100001083 | E32: 28637.51 | J32: =+J31+E32-G32-H32 -> 17136501
A33: GMA | B33: 45667 | C33: B0100001084 | E33: 76159.34 | J33: =+J32+E33-G33-H33 -> 17212660
A34: APS | B34: 45667 | C34: B0100001085 | E34: 69588.33 | J34: =+J33+E34-G34-H34 -> 17282248
A35: RENACER | B35: 45674 | H35: 156983.55 | J35: =+J34+E35-G35-H35 -> 17125265
A36: MAPFRE AMB. | B36: 45677 | H36: 143189.49 | J36: =+J35+E36-G36-H36 -> 16982075
A37: MAPFRE EMERG. | B37: 45677 | H37: 55488.8 | J37: =+J36+E37-G37-H37 -> 16926586
A38: MAPFRE HOSP. | B38: 45677 | H38: 8230.16 | J38: =+J37+E38-G38-H38 -> 16918356
A39: ARS SEMMA | B39: 45677 | H39: 15993.02 | J39: =+J38+E39-G39-H39 -> 16902363
A40: ARS ASEMAP | B40: 45680 | H40: 6475.14 | J40: =+J39+E40-G40-H40 -> 16895888
A41: ARS MONUMENTAL | B41: 45680 | H41: 71992.2 | J41: =+J40+E41-G41-H41 -> 16823896
A42: ARS CMD | B42: 45681 | H42: 273646.7 | J42: =+J41+E42-G42-H42 -> 16550249
A43: ARS FUTURO | B43: 45686 | H43: 234503.89 | J43: =+J42+E43-G43-H43 -> 16315745
A44: ARS RESERVAS | B44: 45687 | H44: 48081.02 | J44: =+J43+E44-G44-H44 -> 16267664
A45: ARS YUNEN | B45: 45688 | H45: 55135.74 | J45: =+J44+E45-G45-H45 -> 16212529
A46: TOTAL GENERAL | E46: =SUM(E19:E45) -> 1645990.7 | F46: =SUM(F19:F45) -> 0 | G46: =SUM(G19:G45) -> 2300 | H46: =SUM(H35:H45) -> 1069719.7 | I46: =SUM(I19:I34) -> 0 | J46: =+J45 -> 16212529
A48: RESUMEN
A49: Total ARS Senasa Subsidiado | B49: =+K13 -> 1806131.5
A50: Total ARS Privada | B50: =+J46 -> 16212529
A51: TOTAL GENERAL | B51: =SUM(B49:B50) -> 18018660
H65: 3
