Workbook
Name CodigoActividad: #REF!
Name Insumos: #REF!
Name Insumos: Insumos!$A$540:$A$583
Name Ls_DepartamentosSRS: #REF!
Name Ls_LinesEstategica: #REF!
Name Ls_Medio_Verificacion: #REF!
Name ls_Regiones: #REF!
Name ls_TiposAcciones: #REF!
Name lsAcabadosTextiles: Insumos!$C$2:$C$3
Name lsAireAcondicionado: Insumos!$C$333:$C$334
Name lsAlimentosyBebidas: Insumos!$C$4:$C$23
Name lsArticulosdePlastico: Insumos!$C$24:$C$30
Name lsElectrodomesticos: Insumos!$C$31:$C$35
Name lsEquiposComputos: Insumos!$C$132:$C$136
Name lsEquiposMedicos: Insumos!$C$44:$C$131
Name lsEquiposSeguridad: Insumos!$C$137:$C$138
Name lsEquiposTransporte: Insumos!$C$518:$C$520
Name lsEventosGenerales: Insumos!$C$139:$C$141
Name lsFuentesFinanciamiento: #REF!
Name lsGasoil: Insumos!$C$142:$C$149
Name lsHerramientasMenores: Insumos!$C$150:$C$179
Name lsImpresionyEncuadernacion: Insumos!$C$180
Name lsInsumos: #REF!
Name lsInsumosEquipos: #REF!
Name lsLlantasyNeumaticos: Insumos!$C$181:$C$188
Name lsMantenimiento: Insumos!$C$189:$C$202
Name lsMaterialesdeLimpieza: Insumos!$C$203:$C$217
Name lsMueblesdeAlojamiento: Insumos!$C$218:$C$219
Name lsMueblesdeOficina: Insumos!$C$220:$C$243
Name lsObrasMenoresEdificaciones: Insumos!$C$244
Name lsOtrosEquipos: Insumos!$C$245:$C$248
Name lsPeaje: Insumos!$C$249
Name lsPinturas: Insumos!$C$250:$C$251
Name lsProductosArtesGraficas: Insumos!$C$252:$C$253
Name lsProductosdeCemento: Insumos!$C$254
Name lsProductosdeLoza: Insumos!$C$255:$C$257
Name lsProductosdePapel: Insumos!$C$258:$C$282
Name lsProductosdeVidrio: Insumos!$C$283:$C$287
Name lsProductosElectricos: Insumos!$C$288:$C$309
Name lsProductosMedicinalesH: Insumos!$C$310:$C$328
Name lsProductosMetalicos: Insumos!$C$329
Name lsProductosQuimicos: Insumos!$C$330
Name lsPublicidadyPropaganda: Insumos!$C$331
Name lsServiciosTecnicosProfesionales: Insumos!$C$332
Name lsTelecomunicaciones: Insumos!$C$36:$C$43
Name LsTipoEESS: #REF!
Name lsTipoIntervencion: #REF!
Name lsUtilesdeCocina: Insumos!$C$335:$C$346
Name lsUtilesdeOficina: Insumos!$C$347:$C$475
Name lsUtilesMenoresMQ: Insumos!$C$476:$C$513
Name lsViaticosDP: Insumos!$C$514:$C$517
Name Periodo_POA: #REF!
Name Productos: #REF!
Name Provincias: #REF!

Sheet PPNE1
B1: Plan Operativo Anual
B2: Servicio Nacional de Salud
B3: Dirección de Planificación y Desarrollo | K3: 2025 | L3: 2026 | M3: 2027 | N3: 2028
B4: Programación Insumos por Producto Nivel Especializado | K4: Cibao Norte | L4: Cibao Sur | M4: Cibao Nordeste | N4: Cibao Noroeste | O4: Valdesia | P4: El Valle | Q4: Enriquillo | R4: Yuma | S4: Higüamo | T4: Ozama
B5: Año | C5: 2026
A6: Servicio Regional de Salud: | B6: Cibao Norte
A7: CEAS
A8: Productos Terminales | B8: Unidad de Medida | C8: Meta Lograda Año 2024 | D8: Meta Proyectada a Lograr Año 2025 | E8: Meta Proyectada Año 2026 | F8: Programación Trimestral | K8: Meta Lograda actual periodo Año 2025
F9: 1er. Trimestre | G9: 2do. Trimestre | H9: 3er. Trimestre | I9: 4to. Trimestre
A10: Servicio de Consulta Externa | B10: Consultas | C10: =SUM(C11:C12) -> 184374 | D10: =SUM(D11:D12) -> 192150.86 | E10: =SUM(E11:E12) -> 201555.61 | F10: =SUM(F11:F12) -> 28217.785 | G10: =SUM(G11:G12) -> 46357.789 | H10: =SUM(H11:H12) -> 76591.13 | I10: =SUM(I11:I12) -> 50388.901 | K10: =SUM(K11:K12) -> 112088
A11: Primera Vez | C11: 61980 | D11: =(K11/7)*12 -> 57281.143 | E11: =IF(C11="",0,(D11/C11)*D11) -> 52938.518 | F11: =E11*14% -> 7411.3925 | G11: =E11*0.23 -> 12175.859 | H11: =E11*0.38 -> 20116.637 | I11: =E11*0.25 -> 13234.629 | K11: 33414
A12: Subsecuente | C12: 122394 | D12: =(K12/7)*12 -> 134869.71 | E12: =IF(C12="",0,(D12/C12)*D12) -> 148617.09 | F12: =E12*14% -> 20806.392 | G12: =E12*0.23 -> 34181.93 | H12: =E12*0.38 -> 56474.493 | I12: =E12*0.25 -> 37154.272 | K12: 78674
A13: Servicio de Emergencia | B13: Consultas | C13: =SUM(C14) -> 62767 | D13: =D14 -> 69276 | E13: =E14 -> 76459.99 | F13: =F14 -> 10704.399 | G13: =G14 -> 17585.798 | H13: =H14 -> 29054.796 | I13: =I14 -> 19114.997 | K13: =K14 -> 40411
A14: Emergencias | C14: 62767 | D14: =(K14/7)*12 -> 69276 | E14: =IF(C14="",0,(D14/C14)*D14) -> 76459.99 | F14: =E14*0.14 -> 10704.399 | G14: =E14*0.23 -> 17585.798 | H14: =E14*0.38 -> 29054.796 | I14: =E14*0.25 -> 19114.997 | K14: 40411
A15: Servicio Hospitalización | B15: Egresos | C15: =SUM(C16:C29) -> 13245 | D15: =SUM(D16:D29) -> 11885.143 | E15: =SUM(E16:E29) -> 11027.639 | F15: =SUM(F16:F29) -> 1543.8695 | G15: =SUM(G16:G29) -> 2536.3571 | H15: =SUM(H16:H29) -> 58638.069 | I15: =SUM(I16:I29) -> 7525.7261 | K15: =SUM(K16:K29) -> 6933
A16: Medicina General | C16: 50 | D16: =(K16/7)*12 -> 44.571429 | E16: =IF(C16="",0,(D16/C16)*D16) -> 39.732245 | F16: =E16*0.14 -> 5.5625143 | G16: =E16*0.23 -> 9.1384163 | H16: =E16*0.38 -> 15.098253 | I16: =I14*0.25 -> 4778.7494 | K16: 26
A17: Cirugia General | C17: 2 | D17: =(K17/7)*12 -> 0 | E17: =IF(C17="",0,(D17/C17)*D17) -> 0 | F17: =E17*0.14 -> 0 | G17: =E17*0.23 -> 0 | H17: =E17*0.38 -> 0 | I17: =E17*0.25 -> 0
A18: Ginecología | C18: 1544 | D18: =(K18/7)*12 -> 1719.4286 | E18: =IF(C18="",0,(D18/C18)*D18) -> 1914.7893 | F18: =E18*0.14 -> 268.0705 | G18: =E18*0.23 -> 440.40153 | H18: =E18*0.38 -> 727.61992 | I18: =E18*0.25 -> 478.69731 | K18: 1003
A19: Obstetricia | C19: 6944 | D19: =(K19/7)*12 -> 6078.8571 | E19: =IF(C19="",0,(D19/C19)*D19) -> 5321.5012 | F19: =E19*0.14 -> 745.01016 | G19: =E19*0.23 -> 1223.9453 | H19: =E19*0.38 -> 2022.1704 | I19: =E19*0.25 -> 1330.3753 | K19: 3546
A20: Pediatria | C20: 2761 | D20: =(K20/7)*12 -> 2218.2857 | E20: =IF(C20="",0,(D20/C20)*D20) -> 1782.2497 | F20: =E20*0.14 -> 249.51496 | G20: =E20*0.23 -> 409.91744 | H20: =E20*0.38 -> 677.2549 | I20: =E20*0.25 -> 445.56243 | K20: 1294
A21: Cardiologia | D21: =(K21/7)*12 -> 0 | E21: =IF(C21="",0,(D21/C21)*D21) -> 0 | F21: =E21*0.14 -> 0 | G21: =E21*0.23 -> 0 | H21: =E21*0.38 -> 0 | I21: =E21*0.25 -> 0
A22: Gastroenterologia | D22: =(K22/7)*12 -> 0 | E22: =IF(C22="",0,(D22/C22)*D22) -> 0 | F22: =E22*0.14 -> 0 | G22: =E22*0.23 -> 0 | H22: =E22*0.38 -> 0 | I22: =E22*0.25 -> 0
A23: Endocrinologia | D23: =(K23/7)*12 -> 252 | E23: =IF(C23="",0,(D23/C23)*D23) -> 0 | F23: =E23*0.14 -> 0 | G23: =E23*0.23 -> 0 | H23: =E23*0.38 -> 0 | I23: =E23*0.25 -> 0 | K23: 147
A24: Medicina Interna | D24: =(K24/7)*12 -> 0 | E24: =IF(C24="",0,(D24/C24)*D24) -> 0 | F24: =E24*0.14 -> 0 | G24: =E24*0.23 -> 0 | H24: =E24*0.38 -> 0 | I24: =E24*0.25 -> 0
A25: Ortopedia | D25: =(K25/7)*12 -> 0 | E25: =IF(C25="",0,(D25/C25)*D25) -> 0 | F25: =E25*0.14 -> 0 | G25: =E25*0.23 -> 0 | H25: =E25*0.38 -> 0 | I25: =E25*0.25 -> 0
A26: Neumología | D26: =(K26/7)*12 -> 10.285714 | E26: =IF(C26="",0,(D26/C26)*D26) -> 0 | F26: =E26*0.14 -> 0 | G26: =E26*0.23 -> 0 | H26: =E26*0.38 -> 0 | I26: =E26*0.25 -> 0 | K26: 6
A27: Cardiología | D27: =(K27/7)*12 -> 0 | E27: =IF(C27="",0,(D27/C27)*D27) -> 0 | F27: =E27*0.14 -> 0 | G27: =E27*0.23 -> 0 | H27: =E27*0.38 -> 0 | I27: =E27*0.25 -> 0
A28: Cuidados Intensivos | C28: 1672 | D28: =(K28/7)*12 -> 934.28571 | E28: =IF(C28="",0,(D28/C28)*D28) -> 522.06328 | F28: =E28*0.14 -> 73.088859 | G28: =E28*0.23 -> 120.07455 | H28: =E28*0.38 -> 198.38404 | I28: =E28*0.25 -> 130.51582 | K28: 545
A29: Otros | C29: 272 | D29: =(K29/7)*12 -> 627.42857 | E29: =IF(C29="",0,(D29/C29)*D29) -> 1447.3037 | F29: =E29*0.14 -> 202.62252 | G29: =E29*0.23 -> 332.87986 | H29: =E29*38 -> 54997.541 | I29: =E29*0.25 -> 361.82593 | K29: 366
A30: Servicios de Apoyo Diagnóstico | C30: =SUM(C31:C32) -> 535836 | D30: =SUM(D31:D32) -> 598673.14 | E30: =SUM(E31:E32) -> 669547.29 | F30: =SUM(F31:F32) -> 93736.62 | G30: =SUM(G31:G32) -> 153995.88 | H30: =SUM(H31:H32) -> 254427.97 | I30: =SUM(I31:I32) -> 167386.82 | K30: =SUM(K31:K32) -> 349226
A31: Análisis de Laboratorio | B31: Pruebas | C31: 506262 | D31: =(K31/7)*12 -> 561310.29 | E31: =IF(C31="",0,(D31/C31)*D31) -> 622344.23 | F31: =E31*0.14 -> 87128.193 | G31: =E31*0.23 -> 143139.17 | H31: =E31*0.38 -> 236490.81 | I31: =E31*0.25 -> 155586.06 | K31: 327431
A32: Servicio de Imágenes | B32: Imágenes | C32: 29574 | D32: =(K32/7)*12 -> 37362.857 | E32: =IF(C32="",0,(D32/C32)*D32) -> 47203.053 | F32: =E32*0.14 -> 6608.4274 | G32: =E32*0.23 -> 10856.702 | H32: =E32*0.38 -> 17937.16 | I32: =E32*0.25 -> 11800.763 | K32: 21795
A33: Indicadores de Producción
A34: Años | B34: Camas Disponibles | C34: Egresos Hospitalarios | D34: Día Cama Disponibles | E34: Dias Pacientes | F34: Promedio Días Estada | G34: Porcentaje Ocupacional | H34: Porcentaje nacimientos prematuros | I34: Porcentaje de cesárea
A35: 2022 | B35: 229 | C35: 17180 | D35: =+B35*365 -> 83585 | E35: 41979 | F35: =+E35/C35 -> 2.4434808 | G35: =+E35/D35*100 -> 50.223126
A36: 2023 | B36: 231 | C36: 12957 | D36: =+B36*365 -> 84315 | E36: 32659 | F36: =+E36/C36 -> 2.520568 | G36: =+E36/D36*100 -> 38.734508
A37: 2024 | B37: 259 | C37: 13245 | D37: =+B37*365 -> 94535 | F37: =+E37/C37 -> 0 | G37: =+E37/D37*100 -> 0

Sheet PPNE2
A1: =+PPNE1!$B$1 -> Plan Operativo Anual
A2: Servicio Nacional de Salud
A3: Dirección de Planificación y Desarrollo | K3: Anticipo Financiero
A4: Programación de actividades | K4: Nómina
A5: =PPNE1!$C$5 -> 2026 | K5: Venta Servicios
A6: Servicio Regional de Salud: | K6: Recursos Externos
A7: CEAS:
A8: Resultados Esperados | B8: Productos | C8: Código | D8: Actividades Programables Presupuestables | E8: Ene | F8: Feb | G8: Mar | H8: Abr | I8: May | J8: Jun | K8: Jul | L8: Ago | M8: Sep | N8: Oct | O8: Nov | P8: Dic | Q8: Total de Acciones | R8: Medio de Verificación 1 | S8: Medio de Verificación 2 | T8: Medio de Verificación 3 | U8: Observaciones/ Comentarios | V8: Área Responsable
A9: 1.1 Reducidos los niveles de morbilidad y mortalidad materna e infantil por causas prevenibles en la población materno-infantil del país, disminuyendo la mortalidad materna de 127.33 y la mortalidad infantil de 18.44 en 2023 a 89.13 y 16.56 en 2028 en todas las regiones del territorio nacional. | B9: 1.1.1 Niños, niñas y Adolescentes reciben atención médica y servicios de salud basado en protocolos nacionales e internacionales. | C9: 1.1.1.01 | D9: Fortalecimiento de los Programas Madre Canguro . | E9: 2 | F9: 2 | G9: 1 | H9: 1 | I9: 1 | J9: 2 | K9: 1 | L9: 1 | M9: 2 | N9: 1 | O9: 1 | P9: 2 | Q9: =SUM(E9:P9) -> 17 | T9: Autoevaluación (enero)/ Plan de mejora (febrero)/ Registro Módulo PMC (mensual)/ Avances Plan de mejora (junio, septiembre,diciembre) | U9: Maternidad Nuestra Señora de la Altagracia, Infantil Dr. Robert Reid Cabral, Materno Infantil San Lorenzo de Los Mina, Materno Dr.Reynaldo Almanzar, Materno Dra. Evangelina Rodríguez, Materno Infantil Dr. Marcelino Velez, Hospital Pediátrico Dr. José Manuel Rodriguez Jimenes, Juan Pablo Pina, Infantil Dr. Arturo Grullón, Maternidad Presidente Estrella Ureña, San Vicente de Paul, Jaime Mota, Dr. Antonio Musa, Materno Infantil Nuestra Señora de la Altagracia, Materno Infantil Dr. Francisco A. Gonzalvo, Taiwan 19 de marzo, Dr.Alejandro Cabral, Materno Infantil Dr. José Fco. Peña Gómez, Dr. Luis M. Morillo King | V9: Materno Infantil y Adolescentes
A10: 1.1 Reducidos los niveles de morbilidad y mortalidad materna e infantil por causas prevenibles en la población materno-infantil del país, disminuyendo la mortalidad materna de 127.33 y la mortalidad infantil de 18.44 en 2023 a 89.13 y 16.56 en 2028 en todas las regiones del territorio nacional. | B10: 1.1.1 Niños, niñas y Adolescentes reciben atención médica y servicios de salud basado en protocolos nacionales e internacionales. | C10: 1.1.1.02 | D10: Seguimiento a la Sala Situacional IA | E10: 1 | F10: 1 | G10: 1 | H10: 1 | I10: 1 | J10: 1 | K10: 1 | L10: 1 | M10: 1 | N10: 1 | O10: 1 | P10: 1 | Q10: =SUM(E10:P10) -> 12 | T10: Reporte digital Módulo Sala Situacional IA | U10: Infantil Dr. Arturo Grullón, Dr. Luis Morillo King, San Vicente de Paul, Materno Infantil Dr. José Francisco Peña Gómez, Juan Pablo Pina, Jaime Mota, Regional Dr. Alejandro Cabral, Taiwan 19 de marzo, Regional Dr. Antonio Musa, Materno Infantil Nuestra Señora de la Altagracia, Materno Infantil Dr. Francisco A. Gonzalvo, Infantil Dr. Robert Reid Cabral, Materno Infantil San Lorenzo de Los Mina, Materno Infantil Dr. Marcelino Vélez Santana, Pediátrico Dr. Hugo Mendoza, Infantil Dr. José Rodriguez Jimenes, Materno Infantil Dr. Julio Rodriguez Grullón, Materno Infantil de Villa Mella | V10: Materno Infantil y Adolescentes
A11: 1.1 Reducidos los niveles de morbilidad y mortalidad materna e infantil por causas prevenibles en la población materno-infantil del país, disminuyendo la mortalidad materna de 127.33 y la mortalidad infantil de 18.44 en 2023 a 89.13 y 16.56 en 2028 en todas las regiones del territorio nacional. | B11: 1.1.1 Niños, niñas y Adolescentes reciben atención médica y servicios de salud basado en protocolos nacionales e internacionales. | C11: 1.1.1.03 | D11: Reporte casos niños asistidos por violencia. | E11: 1 | F11: 1 | G11: 1 | H11: 1 | I11: 1 | J11: 1 | K11: 1 | L11: 1 | M11: 1 | N11: 1 | O11: 1 | P11: 1 | Q11: =SUM(E11:P11) -> 12 | T11: Registro Sala Situacional/ Formulario de reporte | U11: Infantil Dr. Arturo Grullón, Dr. Luis Morillo King, San Vicente de Paul, Materno Infantil Dr. José Francisco Peña Gómez, Juan Pablo Pina, Jaime Mota, Regional Dr. Alejandro Cabral, Taiwan 19 de marzo, Regional Dr. Antonio Musa, Materno Infantil Nuestra Señora de la Altagracia, Materno Infantil Dr. Francisco A. Gonzalvo, Infantil Dr. Robert Reid Cabral, Materno Infantil San Lorenzo de Los Mina, Materno Infantil Dr. Marcelino Vélez Santana, Pediátrico Dr. Hugo Mendoza, Infantil Dr. José Rodriguez Jimenes, Materno Infantil Dr. Julio Rodriguez Grullón, Materno Infantil de Villa Mella | V11: Materno Infantil y Adolescentes
A12: 1.1 Reducidos los niveles de morbilidad y mortalidad materna e infantil por causas prevenibles en la población materno-infantil del país, disminuyendo la mortalidad materna de 127.33 y la mortalidad infantil de 18.44 en 2023 a 89.13 y 16.56 en 2028 en todas las regiones del territorio nacional. | B12: 1.1.1 Niños, niñas y Adolescentes reciben atención médica y servicios de salud basado en protocolos nacionales e internacionales. | C12: 1.1.1.04 | D12: Elaboración e implementación del plan de mejora para fortalecimiento de las Unidades de Atención Integrales en Salud para personas Adolescentes | E12: 1 | H12: 1 | K12: 1 | N12: 1 | Q12: =SUM(E12:P12) -> 4 | T12: Plan (elaboración enero) Seguimiento (abril, julio, octubre) | U12: Pediátrico Dr. Hugo Mendoza, Pediátrico Dr. Robert Reid Cabral, Materno Infantil San Lorenzo de Los Mina, Municipal Materno Infantil Villa Mella, Infantil Dr. Arturo Grullón, Dr. Ricardo Limardo, Maternidad Infantil Nuestra Señora de la Altagracia (Higuey), Dr. Luis Manuel Morillo King, Juan Pablo Pina, Materno Infantil Dr.Francisco Gonzalvo, San Vicente de Paúl, Dr.Antonio Musa, Jaime Mota, Materno Infantil Dr. Marcelino Vélez, Centro Dr. Nelson Astacio | V12: Materno Infantil y Adolescentes
A13: 1.1 Reducidos los niveles de morbilidad y mortalidad materna e infantil por causas prevenibles en la población materno-infantil del país, disminuyendo la mortalidad materna de 127.33 y la mortalidad infantil de 18.44 en 2023 a 89.13 y 16.56 en 2028 en todas las regiones del territorio nacional. | B13: 1.1.1 Niños, niñas y Adolescentes reciben atención médica y servicios de salud basado en protocolos nacionales e internacionales. | C13: 1.1.1.05 | D13: Reporte de la Planificación familiar en Adolescentes | E13: 1 | F13: 1 | G13: 1 | H13: 1 | I13: 1 | J13: 1 | K13: 1 | L13: 1 | M13: 1 | N13: 1 | O13: 1 | P13: 1 | Q13: =SUM(E13:P13) -> 12 | T13: Reporte | U13: Hospitales que asisten Adolecentes | V13: Materno Infantil y Adolescentes
A14: 1.1 Reducidos los niveles de morbilidad y mortalidad materna e infantil por causas prevenibles en la población materno-infantil del país, disminuyendo la mortalidad materna de 127.33 y la mortalidad infantil de 18.44 en 2023 a 89.13 y 16.56 en 2028 en todas las regiones del territorio nacional. | B14: 1.1.2 Recién nacidos reciben atención medica y servicios de salud neonatal basados en protocolos y normas nacionales e internacionales | C14: 1.2.2.01 | D14: Vigilanica sanitaria del agua en las UCIN del SNS | J14: 1 | P14: 1 | Q14: =SUM(E14:P14) -> 2 | R14: Reporte | U14: Maternidad Nuestra Señora de la Altagracia , Materno Infantil San Lorenzo de los Mina, Materno Dr. Reynaldo Almánzar, Materno Infantil Dr. Marcelino Vélez, Maternidad Presidente Estrella Ureña, Materno Infantil Nuestra Señora de la Altagracia (Higuey), Juan Pablo Pina, San Vicente de Paul, Dr. Luis M. Morillo King, Infantil Dr.Robert Reid Cabral, Maternidad Dra.Evangelina Rodriguez, Materno Infantil Dr. José Fco.Peña Gomez, Jaime Mota, Dr. Antonio Musa, Infantil Dr. Arturo Grullon, Materno Infantil Dr. José Rodriguez Grullón (Ciudad Sanitaria), Pediatrico Dr.Hugo Mendoza, Taiwan 19 de marzo, Dr. Alejandro Cabral | V14: Materno Infantil y Adolescentes
A15: 1.1 Reducidos los niveles de morbilidad y mortalidad materna e infantil por causas prevenibles en la población materno-infantil del país, disminuyendo la mortalidad materna de 127.33 y la mortalidad infantil de 18.44 en 2023 a 89.13 y 16.56 en 2028 en todas las regiones del territorio nacional. | B15: 1.1.2 Recién nacidos reciben atención medica y servicios de salud neonatal basados en protocolos y normas nacionales e internacionales | C15: 1.2.2.02 | D15: Monitoreo del registro en línea del Certificado de Nacido Vivo | E15: 1 | F15: 1 | G15: 1 | H15: 1 | I15: 1 | J15: 1 | K15: 1 | L15: 1 | M15: 1 | N15: 1 | O15: 1 | P15: 1 | Q15: =SUM(E15:P15) -> 12 | R15: Reporte | U15: Todos los CEAS donde se producen nacimientos | V15: Materno Infantil y Adolescentes
A16: 1.2 Aumentado el cumplimiento normativo para reducir la incidencia de complicaciones neonatales y maternas, pasando de un promedio del 75.5% en el año 2023 al 88% en el año 2028 en todas las regiones de la Red Pública de Servicios de Salud. | B16: 1.2.1 Gestantes reciben atención médica y servicios de salud materna basados en protocolos y normas nacionales e internacionales. | C16: 1.2.1.01 | D16: Seguimiento de la Morbilidad Materna Extrema | F16: 1 | G16: 1 | H16: 1 | I16: 1 | J16: 1 | K16: 1 | L16: 1 | M16: 1 | N16: 1 | O16: 1 | Q16: =SUM(E16:P16) -> 10 | R16: Informe | U16: Todos los hospitales regionales, maternos, materno infantil, que ofrecen servicios maternos | V16: Materno Infantil y Adolescentes
A17: 1.2 Aumentado el cumplimiento normativo para reducir la incidencia de complicaciones neonatales y maternas, pasando de un promedio del 75.5% en el año 2023 al 88% en el año 2028 en todas las regiones de la Red Pública de Servicios de Salud. | B17: 1.2.1 Gestantes reciben atención médica y servicios de salud materna basados en protocolos y normas nacionales e internacionales. | C17: 1.2.1.02 | D17: Análisis de los indicadores Maternos Neonatales de la Sala Situacional | G17: 1 | J17: 1 | M17: 1 | P17: 1 | Q17: =SUM(E17:P17) -> 4 | R17: Informe | T17: Plantilla estandarizada | U17: Todos los CEAS regionales, especializados y de referencia que ofrezcan servicios maternos | V17: Materno Infantil y Adolescentes
A18: 1.2 Aumentado el cumplimiento normativo para reducir la incidencia de complicaciones neonatales y maternas, pasando de un promedio del 75.5% en el año 2023 al 88% en el año 2028 en todas las regiones de la Red Pública de Servicios de Salud. | B18: 1.2.1 Gestantes reciben atención médica y servicios de salud materna basados en protocolos y normas nacionales e internacionales. | C18: 1.2.1.03 | D18: Seguimiento a la implementacion de la Estrategia Código Rojo. | G18: 1 | J18: 1 | M18: 1 | P18: 1 | Q18: =SUM(E18:P18) -> 4 | R18: Informe | S18: Listado de participación | U18: Todos los hospitales regionales, maternos y materno infantil que ofrecen servicios maternos | V18: Materno Infantil y Adolescentes
A19: 1.2 Aumentado el cumplimiento normativo para reducir la incidencia de complicaciones neonatales y maternas, pasando de un promedio del 75.5% en el año 2023 al 88% en el año 2028 en todas las regiones de la Red Pública de Servicios de Salud. | B19: 1.2.1 Gestantes reciben atención médica y servicios de salud materna basados en protocolos y normas nacionales e internacionales. | C19: 1.2.1.04 | D19: Seguimiento al tamizaje de infecciones vaginales y urinarias en la embarazada | G19: 1 | J19: 1 | N19: 1 | Q19: =SUM(E19:P19) -> 3 | R19: Informe | U19: Materno Dr. Reynaldo Almanzar, Maternidad Nuestra Señora de la Altagracia, Materno Infantil San Lorenzo de los Mina, Maternidad Presidente Estrella Ureña | V19: Materno Infantil y Adolescentes
A20: 1.2 Aumentado el cumplimiento normativo para reducir la incidencia de complicaciones neonatales y maternas, pasando de un promedio del 75.5% en el año 2023 al 88% en el año 2028 en todas las regiones de la Red Pública de Servicios de Salud. | B20: 1.2.1 Gestantes reciben atención médica y servicios de salud materna basados en protocolos y normas nacionales e internacionales. | C20: 1.2.1.05 | D20: Elaboracion de los planes de mejora de la metodología de Observación de la Práctica Clínica (OPC) según los resultados del monitoreo de calidad de los servicios en los CEAS priorizados | I20: 1 | N20: 1 | Q20: =SUM(E20:P20) -> 2 | R20: Plan | S20: Listado de participación | U20: CEAS PRIORIZADOS SRS Ozama 1. Hospital Materno Dr. Reynaldo Almánzar 2. Hospital Maternidad Nuestra Señora de la Altagracia 3. Hospital Materno Infantil San Lorenzo de los Mina 4. Hospital Materno Dra. Evangelina Rodríguez 5. ⁠Hospital Materno Infantil Dr. Marcelino Vélez Santana 6. Hospital Materno Infantil Dr. Julio Rodriguez Grullón SRS Valdesia 7.Hospital Regional Juan Pablo Pina SRS Cibao Norte 8. Hospital Maternidad Presidente Estrella Ureña SRS Cibao Nordeste 9. Hospital Regional San Vicente de Paul SRS Enriquillo 10. Hospital Regional Jaime Mota SRS Higuamo 11. Hospital Materno Infantil Nuestra Señora de la Altagracia 12. Hospital Materno Infantil Dr. Francisco Gonzalvo. SRS Yuma 13. Hospital Regional Dr. Antonio Musa SRS El Valle 14. Hospital Regional Dr. Alejandro Cabral 15. Hospital Regional Taiwán 19 de marzo SRS Cibao Noroeste 16. Hospital Materno Infantil Dr.José Francisco Peña Gómez SRS Cibao Sur 17. Hospital Regional Dr. Luis Morillo King | V20: Materno Infantil y Adolescentes
A21: 1.2 Aumentado el cumplimiento normativo para reducir la incidencia de complicaciones neonatales y maternas, pasando de un promedio del 75.5% en el año 2023 al 88% en el año 2028 en todas las regiones de la Red Pública de Servicios de Salud. | B21: 1.2.1 Gestantes reciben atención médica y servicios de salud materna basados en protocolos y normas nacionales e internacionales. | C21: 1.2.1.06 | D21: Seguimiento a la Planificación Post Evento Obstétrico | H21: 1 | L21: 1 | O21: 1 | Q21: =SUM(E21:P21) -> 3 | R21: Informe | U21: CEAS PRIORIZADOS SRS Ozama 1. Hospital Materno Dr. Reynaldo Almánzar 2. Hospital Maternidad Nuestra Señora de la Altagracia 3. Hospital Materno Infantil San Lorenzo de los Mina 4. Hospital Materno Dra. Evangelina Rodríguez 5. ⁠Hospital Materno Infantil Dr. Marcelino Vélez Santana 6. Hospital Materno Infantil Dr. Julio Rodriguez Grullón SRS Valdesia 7.Hospital Regional Juan Pablo Pina SRS Cibao Norte 8. Hospital Maternidad Presidente Estrella Ureña SRS Cibao Nordeste 9. Hospital Regional San Vicente de Paul SRS Enriquillo 10. Hospital Regional Jaime Mota SRS Higuamo 11. Hospital Materno Infantil Nuestra Señora de la Altagracia 12. Hospital Materno Infantil Dr. Francisco Gonzalvo. SRS Yuma 13. Hospital Regional Dr. Antonio Musa SRS El Valle 14. Hospital Regional Dr. Alejandro Cabral 15. Hospital Regional Taiwán 19 de marzo SRS Cibao Noroeste 16. Hospital Materno Infantil Dr.José Francisco Peña Gómez SRS Cibao Sur 17. Hospital Regional Dr. Luis Morillo King | V21: Materno Infantil y Adolescentes
A22: 1.2 Aumentado el cumplimiento normativo para reducir la incidencia de complicaciones neonatales y maternas, pasando de un promedio del 75.5% en el año 2023 al 88% en el año 2028 en todas las regiones de la Red Pública de Servicios de Salud. | B22: 1.2.1 Gestantes reciben atención médica y servicios de salud materna basados en protocolos y normas nacionales e internacionales. | C22: 1.2.1.07 | D22: Monitoreo al apego a protocolo de atencion en consulta prenatal. | I22: 1 | N22: 1 | Q22: =SUM(E22:P22) -> 2 | R22: Informe | U22: CEAS PRIORIZADOS SRS Ozama 1. Hospital Materno Dr. Reynaldo Almánzar 2. Hospital Maternidad Nuestra Señora de la Altagracia 3. Hospital Materno Infantil San Lorenzo de los Mina 4. Hospital Materno Dra. Evangelina Rodríguez 5. ⁠Hospital Materno Infantil Dr. Marcelino Vélez Santana 6. Hospital Materno Infantil Dr. Julio Rodriguez Grullón SRS Valdesia 7.Hospital Regional Juan Pablo Pina SRS Cibao Norte 8. Hospital Maternidad Presidente Estrella Ureña SRS Cibao Nordeste 9. Hospital Regional San Vicente de Paul SRS Enriquillo 10. Hospital Regional Jaime Mota SRS Higuamo 11. Hospital Materno Infantil Nuestra Señora de la Altagracia 12. Hospital Materno Infantil Dr. Francisco Gonzalvo. SRS Yuma 13. Hospital Regional Dr. Antonio Musa SRS El Valle 14. Hospital Regional Dr. Alejandro Cabral 15. Hospital Regional Taiwán 19 de marzo SRS Cibao Noroeste 16. Hospital Materno Infantil Dr.José Francisco Peña Gómez SRS Cibao Sur 17. Hospital Regional Dr. Luis Morillo King | V22: Materno Infantil y Adolescentes
A23: 1.5 Reducida la morbilidad y mortalidad prematura por enfermedades no transmisibles en personas de 30 a 69 años, en un 20% al año 2028, mediante la implementación de intervenciones integrales de prevención, diagnóstico temprano y tratamiento oportuno en los establecimientos de la Red Pública. | B23: 1.5.1 La población con riesgo o diagnóstico de hipertensión y diabetes recibe servicios integrales de prevención, diagnóstico, manejo y seguimiento de enfermedades crónicas no transmisibles, fortalecidos mediante la implementación del enfoque HEARTS. | C23: 1.5.1.01 | Q23: =SUM(E23:P23) -> 0
A24: 1.5 Reducida la morbilidad y mortalidad prematura por enfermedades no transmisibles en personas de 30 a 69 años, en un 20% al año 2028, mediante la implementación de intervenciones integrales de prevención, diagnóstico temprano y tratamiento oportuno en los establecimientos de la Red Pública. | B24: 1.5.2 Las víctimas de violencia de género e intrafamiliar reciben atención integral, oportuna y segura en los servicios de salud. | C24: 1.5.2.01 | D24: Reporte de estadísticas de los casos de violencia de género e intrafamiliar. | E24: 1 | F24: 1 | G24: 1 | H24: 1 | I24: 1 | J24: 1 | K24: 1 | L24: 1 | M24: 1 | N24: 1 | O24: 1 | P24: 1 | Q24: =SUM(E24:P24) -> 12 | R24: Reporte | V24: Género
A25: 1.6 Incrementado el acceso oportuno a servicios de salud de calidad, aumentando el acceso a servicios preventivos de 2.23% de la población prioritaria en 2023 al 5.24% en 2028 en todas las regiones del país. | B25: 1.6.5 La población usuaria recibe servicios odontológicos fortalecidos y de calidad mediante la ejecución de planes de mejora de la atención dental. | C25: 1.6.5.01 | D25: Capacitaciones a RRHH de las areas de odontología de acuerdo a las necesidades. | G25: 1 | J25: 1 | M25: 1 | Q25: =SUM(E25:P25) -> 3 | R25: Listado de participación | S25: Plan | V25: Odontología
A26: 1.6 Incrementado el acceso oportuno a servicios de salud de calidad, aumentando el acceso a servicios preventivos de 2.23% de la población prioritaria en 2023 al 5.24% en 2028 en todas las regiones del país. | B26: 1.6.5 La población usuaria recibe servicios odontológicos fortalecidos y de calidad mediante la ejecución de planes de mejora de la atención dental. | C26: 1.6.5.02 | D26: Desarrollo de plan de acciones para el acondicionamiento de infraestructura, mantenimiento de equipos y equipamiento de las áreas de odontología EES | G26: 1 | J26: 1 | M26: 1 | O26: 1 | Q26: =SUM(E26:P26) -> 4 | R26: Informe | S26: Plan | V26: Odontología
A27: 1.6 Incrementado el acceso oportuno a servicios de salud de calidad, aumentando el acceso a servicios preventivos de 2.23% de la población prioritaria en 2023 al 5.24% en 2028 en todas las regiones del país. | B27: 1.6.5 La población usuaria recibe servicios odontológicos fortalecidos y de calidad mediante la ejecución de planes de mejora de la atención dental. | C27: 1.6.5.03 | D27: Desarrollo del Programa Fomento de la Salud bucal. | H27: 1 | L27: 1 | N27: 1 | Q27: =SUM(E27:P27) -> 3 | R27: Informe | V27: Odontología
A28: 1.6 Incrementado el acceso oportuno a servicios de salud de calidad, aumentando el acceso a servicios preventivos de 2.23% de la población prioritaria en 2023 al 5.24% en 2028 en todas las regiones del país. | B28: 1.6.5 La población usuaria recibe servicios odontológicos fortalecidos y de calidad mediante la ejecución de planes de mejora de la atención dental. | C28: 1.6.5.04 | D28: Desarrollo del Programa Hospitales libre de caries | H28: 1 | M28: 1 | Q28: =SUM(E28:P28) -> 2 | R28: Informe | V28: Odontología
A29: 1.7 Aumentada la disponibilidad de medicamentos esenciales en los establecimientos de la Red Pública de Servicios de Salud, incrementando el cumplimiento promedio de abastecimiento del 88% en 2023 al 93% en 2028 en todas las regiones del país. | B29: 1.7.1 Pacientes reciben medicamentos esenciales para el tratamiento adecuado y oportuno de sus condiciones de salud. | C29: 1.7.1.01 | D29: Reunión Comité Farmaco Terapeutico (CFT) Hospitalario y promoción del uso racional de los medicamentos. | E29: 1 | H29: 1 | K29: 1 | N29: 1 | Q29: =SUM(E29:P29) -> 4 | R29: Listado de participación | S29: Minuta | V29: Medicamentos
A30: 1.8 Superadas las deficiencias en la organización e implementación de las Redes Integradas de Servicios de Salud (RISS) beneficiando a toda la población que utiliza los servicios de salud de la Red Pública, aumentando del 38% en 2023 al 50% en 2028 en todo el territorio nacional. | B30: 1.8.2 La población recibe acceso equitativo a servicios de salud, incluidos los de emergencia, de calidad, seguros, integrales, continuos e inclusivos, mediante redes integradas que incorporan mejora continua de procesos y avances tecnológicos. | C30: 1.8.2.01 | D30: Implementación del Modelo hospitalario y flujos de Asistencia Emergencias y Urgencias | J30: 1 | Q30: =SUM(E30:P30) -> 1 | R30: Reporte | V30: Emergencia
A31: 1.8 Superadas las deficiencias en la organización e implementación de las Redes Integradas de Servicios de Salud (RISS) beneficiando a toda la población que utiliza los servicios de salud de la Red Pública, aumentando del 38% en 2023 al 50% en 2028 en todo el territorio nacional. | B31: 1.8.2 La población recibe acceso equitativo a servicios de salud, incluidos los de emergencia, de calidad, seguros, integrales, continuos e inclusivos, mediante redes integradas que incorporan mejora continua de procesos y avances tecnológicos. | C31: 1.8.2.02 | D31: Socializacion e implementación del RAC-Triaje en las Salas de Emergencias Centros Hospitalarios | J31: 1 | O31: 1 | Q31: =SUM(E31:P31) -> 2 | R31: Listado de participación | S31: Reporte | V31: Emergencia
A32: 1.8 Superadas las deficiencias en la organización e implementación de las Redes Integradas de Servicios de Salud (RISS) beneficiando a toda la población que utiliza los servicios de salud de la Red Pública, aumentando del 38% en 2023 al 50% en 2028 en todo el territorio nacional. | B32: 1.8.2 La población recibe acceso equitativo a servicios de salud, incluidos los de emergencia, de calidad, seguros, integrales, continuos e inclusivos, mediante redes integradas que incorporan mejora continua de procesos y avances tecnológicos. | C32: 1.8.2.03 | D32: Llenado de historia clinica de emergencias y registro de todos los pacientes del libro de emergencias | M32: 1 | Q32: =SUM(E32:P32) -> 1 | R32: Reporte | V32: Emergencia
A33: 1.8 Superadas las deficiencias en la organización e implementación de las Redes Integradas de Servicios de Salud (RISS) beneficiando a toda la población que utiliza los servicios de salud de la Red Pública, aumentando del 38% en 2023 al 50% en 2028 en todo el territorio nacional. | B33: 1.8.2 La población recibe acceso equitativo a servicios de salud, incluidos los de emergencia, de calidad, seguros, integrales, continuos e inclusivos, mediante redes integradas que incorporan mejora continua de procesos y avances tecnológicos. | C33: 1.8.2.04 | D33: Implementación del procedimiento para la entrega, recibo y reposicion de carro de paro | F33: 1 | I33: 1 | L33: 1 | O33: 1 | Q33: =SUM(E33:P33) -> 4 | T33: Formularios de verificacion de Carro de paro (Apertura, Stock y Verificacion de desfibrilador) | V33: Emergencia
A34: 1.8 Superadas las deficiencias en la organización e implementación de las Redes Integradas de Servicios de Salud (RISS) beneficiando a toda la población que utiliza los servicios de salud de la Red Pública, aumentando del 38% en 2023 al 50% en 2028 en todo el territorio nacional. | B34: 1.8.2 La población recibe acceso equitativo a servicios de salud, incluidos los de emergencia, de calidad, seguros, integrales, continuos e inclusivos, mediante redes integradas que incorporan mejora continua de procesos y avances tecnológicos. | C34: 1.8.2.05 | D34: Registros en el tablero de Indicadores de Gestión de las Salas de Emergencias de los Centros de Salud. | G34: 1 | J34: 1 | M34: 1 | P34: 1 | Q34: =SUM(E34:P34) -> 4 | R34: Reporte | V34: Emergencia
A35: 1.8 Superadas las deficiencias en la organización e implementación de las Redes Integradas de Servicios de Salud (RISS) beneficiando a toda la población que utiliza los servicios de salud de la Red Pública, aumentando del 38% en 2023 al 50% en 2028 en todo el territorio nacional. | B35: 1.8.2 La población recibe acceso equitativo a servicios de salud, incluidos los de emergencia, de calidad, seguros, integrales, continuos e inclusivos, mediante redes integradas que incorporan mejora continua de procesos y avances tecnológicos. | C35: 1.8.2.06 | D35: Socialización de los procedimientos de traslado de pacientes | I35: 1 | Q35: =SUM(E35:P35) -> 1 | R35: Listado de participación | S35: Agenda | V35: Emergencia
A36: 1.8 Superadas las deficiencias en la organización e implementación de las Redes Integradas de Servicios de Salud (RISS) beneficiando a toda la población que utiliza los servicios de salud de la Red Pública, aumentando del 38% en 2023 al 50% en 2028 en todo el territorio nacional. | B36: 1.8.2 La población recibe acceso equitativo a servicios de salud, incluidos los de emergencia, de calidad, seguros, integrales, continuos e inclusivos, mediante redes integradas que incorporan mejora continua de procesos y avances tecnológicos. | C36: 1.8.2.07 | D36: Elaboración y/o actualización de los Planes de Emergencias y Desastres Hospitalarios | G36: 1 | Q36: =SUM(E36:P36) -> 1 | R36: Plan | V36: Emergencia
A37: 1.8 Superadas las deficiencias en la organización e implementación de las Redes Integradas de Servicios de Salud (RISS) beneficiando a toda la población que utiliza los servicios de salud de la Red Pública, aumentando del 38% en 2023 al 50% en 2028 en todo el territorio nacional. | B37: 1.8.2 La población recibe acceso equitativo a servicios de salud, incluidos los de emergencia, de calidad, seguros, integrales, continuos e inclusivos, mediante redes integradas que incorporan mejora continua de procesos y avances tecnológicos. | C37: 1.8.2.08 | D37: Reunion del comité de emergencias para socializacion del plan Hospitalarios Emergencias de salud publica y desastres naturales con el personal del hospital. | G37: 1 | J37: 1 | M37: 1 | Q37: =SUM(E37:P37) -> 3 | R37: Listado de participación | S37: Minuta | V37: Emergencia
A38: 1.8 Superadas las deficiencias en la organización e implementación de las Redes Integradas de Servicios de Salud (RISS) beneficiando a toda la población que utiliza los servicios de salud de la Red Pública, aumentando del 38% en 2023 al 50% en 2028 en todo el territorio nacional. | B38: 1.8.2 La población recibe acceso equitativo a servicios de salud, incluidos los de emergencia, de calidad, seguros, integrales, continuos e inclusivos, mediante redes integradas que incorporan mejora continua de procesos y avances tecnológicos. | C38: 1.8.2.09 | D38: Simulacro para probar la funcionabilidad de los Planes de Emergencias y Desastres Hospitalarios. | N38: 1 | Q38: =SUM(E38:P38) -> 1 | R38: Listado de participación | S38: Reporte | V38: Emergencia
A39: 1.8 Superadas las deficiencias en la organización e implementación de las Redes Integradas de Servicios de Salud (RISS) beneficiando a toda la población que utiliza los servicios de salud de la Red Pública, aumentando del 38% en 2023 al 50% en 2028 en todo el territorio nacional. | B39: 1.8.2 La población recibe acceso equitativo a servicios de salud, incluidos los de emergencia, de calidad, seguros, integrales, continuos e inclusivos, mediante redes integradas que incorporan mejora continua de procesos y avances tecnológicos. | C39: 1.8.2.10 | D39: Reunión con el Comite Hospitalario de Emergencias y Desastres para preparar el Operativo de Navidad y Año Nuevo comité de emergencias | P39: 1 | Q39: =SUM(E39:P39) -> 1 | R39: Listado de participación | S39: Minuta | V39: Emergencia
A40: 1.8 Superadas las deficiencias en la organización e implementación de las Redes Integradas de Servicios de Salud (RISS) beneficiando a toda la población que utiliza los servicios de salud de la Red Pública, aumentando del 38% en 2023 al 50% en 2028 en todo el territorio nacional. | B40: 1.8.2 La población recibe acceso equitativo a servicios de salud, incluidos los de emergencia, de calidad, seguros, integrales, continuos e inclusivos, mediante redes integradas que incorporan mejora continua de procesos y avances tecnológicos. | C40: 1.8.2.11 | D40: Reunión con el Comite Hospitalario de Emergencias y Desastres para preparar el Operativo de Semana Santa comité de emergencias | G40: 1 | Q40: =SUM(E40:P40) -> 1 | R40: Listado de participación | S40: Minuta | V40: Emergencia
A41: 1.8 Superadas las deficiencias en la organización e implementación de las Redes Integradas de Servicios de Salud (RISS) beneficiando a toda la población que utiliza los servicios de salud de la Red Pública, aumentando del 38% en 2023 al 50% en 2028 en todo el territorio nacional. | B41: 1.8.2 La población recibe acceso equitativo a servicios de salud, incluidos los de emergencia, de calidad, seguros, integrales, continuos e inclusivos, mediante redes integradas que incorporan mejora continua de procesos y avances tecnológicos. | C41: 1.8.2.12 | D41: Reunión con el Comite Hospitalario de Emergencias y Desastres para respuesta a Temporada Ciclonica y Eventos Hidrometeorologicos comité de emergencias | E41: 1 | O41: 1 | Q41: =SUM(E41:P41) -> 2 | R41: Listado de participación | S41: Minuta | V41: Emergencia
A42: 1.8 Superadas las deficiencias en la organización e implementación de las Redes Integradas de Servicios de Salud (RISS) beneficiando a toda la población que utiliza los servicios de salud de la Red Pública, aumentando del 38% en 2023 al 50% en 2028 en todo el territorio nacional. | B42: 1.8.2 La población recibe acceso equitativo a servicios de salud, incluidos los de emergencia, de calidad, seguros, integrales, continuos e inclusivos, mediante redes integradas que incorporan mejora continua de procesos y avances tecnológicos. | C42: 1.8.2.13 | D42: Reunión con el Comite Hospitalario de Emergencias y Desastres para la respuesta alta demanda asistencial por siniestros siniestro viales, emergencias de salud, desastres naturales y cambio climaticos. | L42: 1 | Q42: =SUM(E42:P42) -> 1 | R42: Listado de participación | S42: Minuta | V42: Emergencia
A43: 1.8 Superadas las deficiencias en la organización e implementación de las Redes Integradas de Servicios de Salud (RISS) beneficiando a toda la población que utiliza los servicios de salud de la Red Pública, aumentando del 38% en 2023 al 50% en 2028 en todo el territorio nacional. | B43: 1.8.3 La población usuaria recibe servicios hospitalarios fortalecidos, integrales y de calidad mediante la mejora continua de procesos y servicios, la optimización de la gestión y el fortalecimiento de la infraestructura, el equipamiento y las capacidades del personal. | C43: 1.8.3.01 | D43: Supervision de indicadores de calidad en el programa de hemodialisis y diálisis peritoneal, para los centros que apliquen para el programa. | E43: 1 | F43: 1 | G43: 1 | H43: 1 | I43: 1 | J43: 1 | K43: 1 | L43: 1 | M43: 1 | N43: 1 | O43: 1 | P43: 1 | Q43: =SUM(E43:P43) -> 12 | R43: Informe | V43: Centros Hospitalarios
A44: 1.8 Superadas las deficiencias en la organización e implementación de las Redes Integradas de Servicios de Salud (RISS) beneficiando a toda la población que utiliza los servicios de salud de la Red Pública, aumentando del 38% en 2023 al 50% en 2028 en todo el territorio nacional. | B44: 1.8.3 La población usuaria recibe servicios hospitalarios fortalecidos, integrales y de calidad mediante la mejora continua de procesos y servicios, la optimización de la gestión y el fortalecimiento de la infraestructura, el equipamiento y las capacidades del personal. | C44: 1.8.3.02 | D44: Plan de mejora a partir de los resultados de la evaluacion de indicadores de calidad en el programa de hemodialisis y diálisis peritoneal, para los centros que apliquen para el programa. | G44: 1 | J44: 1 | M44: 1 | P44: 1 | Q44: =SUM(E44:P44) -> 4 | R44: Protocolo | V44: Centros Hospitalarios
A45: 1.8 Superadas las deficiencias en la organización e implementación de las Redes Integradas de Servicios de Salud (RISS) beneficiando a toda la población que utiliza los servicios de salud de la Red Pública, aumentando del 38% en 2023 al 50% en 2028 en todo el territorio nacional. | B45: 1.8.3 La población usuaria recibe servicios hospitalarios fortalecidos, integrales y de calidad mediante la mejora continua de procesos y servicios, la optimización de la gestión y el fortalecimiento de la infraestructura, el equipamiento y las capacidades del personal. | C45: 1.8.3.03 | D45: Seguimiento a los planes de mejora de la evaluacion de indicadores de calidad en el programa de hemodialisis y diálisis peritoneal, para los centros que apliquen para el programa. | H45: 1 | K45: 1 | N45: 1 | Q45: =SUM(E45:P45) -> 3 | R45: Informe | S45: Plan | V45: Centros Hospitalarios
A46: 1.8 Superadas las deficiencias en la organización e implementación de las Redes Integradas de Servicios de Salud (RISS) beneficiando a toda la población que utiliza los servicios de salud de la Red Pública, aumentando del 38% en 2023 al 50% en 2028 en todo el territorio nacional. | B46: 1.8.3 La población usuaria recibe servicios hospitalarios fortalecidos, integrales y de calidad mediante la mejora continua de procesos y servicios, la optimización de la gestión y el fortalecimiento de la infraestructura, el equipamiento y las capacidades del personal. | C46: 1.8.3.04 | D46: Seguimiento al plan de mejora de las evaluaciones de la calidad de los servicios de nutrición | G46: 1 | J46: 1 | M46: 1 | P46: 1 | Q46: =SUM(E46:P46) -> 4 | R46: Informe | S46: Plan | V46: Centros Hospitalarios
A47: 1.8 Superadas las deficiencias en la organización e implementación de las Redes Integradas de Servicios de Salud (RISS) beneficiando a toda la población que utiliza los servicios de salud de la Red Pública, aumentando del 38% en 2023 al 50% en 2028 en todo el territorio nacional. | B47: 1.8.3 La población usuaria recibe servicios hospitalarios fortalecidos, integrales y de calidad mediante la mejora continua de procesos y servicios, la optimización de la gestión y el fortalecimiento de la infraestructura, el equipamiento y las capacidades del personal. | C47: 1.8.3.05 | D47: Implementacion de los procesos de bioseguridad hospitalaria | G47: 1 | J47: 1 | M47: 1 | P47: 1 | Q47: =SUM(E47:P47) -> 4 | R47: Informe | V47: Centros Hospitalarios
A48: 1.8 Superadas las deficiencias en la organización e implementación de las Redes Integradas de Servicios de Salud (RISS) beneficiando a toda la población que utiliza los servicios de salud de la Red Pública, aumentando del 38% en 2023 al 50% en 2028 en todo el territorio nacional. | B48: 1.8.3 La población usuaria recibe servicios hospitalarios fortalecidos, integrales y de calidad mediante la mejora continua de procesos y servicios, la optimización de la gestión y el fortalecimiento de la infraestructura, el equipamiento y las capacidades del personal. | C48: 1.8.3.06 | D48: Elaboración de los planes de mejora a partir de los resultados de evaluacion de procesos de bioseguridad hospitalaria | G48: 1 | J48: 1 | M48: 1 | P48: 1 | Q48: =SUM(E48:P48) -> 4 | R48: Plan | V48: Centros Hospitalarios
A49: 1.8 Superadas las deficiencias en la organización e implementación de las Redes Integradas de Servicios de Salud (RISS) beneficiando a toda la población que utiliza los servicios de salud de la Red Pública, aumentando del 38% en 2023 al 50% en 2028 en todo el territorio nacional. | B49: 1.8.3 La población usuaria recibe servicios hospitalarios fortalecidos, integrales y de calidad mediante la mejora continua de procesos y servicios, la optimización de la gestión y el fortalecimiento de la infraestructura, el equipamiento y las capacidades del personal. | C49: 1.8.3.07 | D49: Seguimiento a los planes de mejora de evaluación de procesos de bioseguridad hospitalaria | G49: 1 | J49: 1 | M49: 1 | P49: 1 | Q49: =SUM(E49:P49) -> 4 | R49: Informe | S49: Plan | V49: Centros Hospitalarios
A50: 1.8 Superadas las deficiencias en la organización e implementación de las Redes Integradas de Servicios de Salud (RISS) beneficiando a toda la población que utiliza los servicios de salud de la Red Pública, aumentando del 38% en 2023 al 50% en 2028 en todo el territorio nacional. | B50: 1.8.3 La población usuaria recibe servicios hospitalarios fortalecidos, integrales y de calidad mediante la mejora continua de procesos y servicios, la optimización de la gestión y el fortalecimiento de la infraestructura, el equipamiento y las capacidades del personal. | C50: 1.8.3.08 | D50: Notificación oportuna de las enfermedades bajo vigilancia epidemiológica (Epi 1 y 2) | E50: 1 | F50: 1 | G50: 1 | H50: 1 | I50: 1 | J50: 1 | K50: 1 | L50: 1 | M50: 1 | N50: 1 | O50: 1 | P50: 1 | Q50: =SUM(E50:P50) -> 12 | R50: Reporte | V50: Centros Hospitalarios
A51: 1.8 Superadas las deficiencias en la organización e implementación de las Redes Integradas de Servicios de Salud (RISS) beneficiando a toda la población que utiliza los servicios de salud de la Red Pública, aumentando del 38% en 2023 al 50% en 2028 en todo el territorio nacional. | B51: 1.8.3 La población usuaria recibe servicios hospitalarios fortalecidos, integrales y de calidad mediante la mejora continua de procesos y servicios, la optimización de la gestión y el fortalecimiento de la infraestructura, el equipamiento y las capacidades del personal. | C51: 1.8.3.09 | D51: Implementación del procedimiento de hosteleria hospitalaria | J51: 1 | P51: 1 | Q51: =SUM(E51:P51) -> 2 | R51: Informe | V51: Centros Hospitalarios
A52: 1.8 Superadas las deficiencias en la organización e implementación de las Redes Integradas de Servicios de Salud (RISS) beneficiando a toda la población que utiliza los servicios de salud de la Red Pública, aumentando del 38% en 2023 al 50% en 2028 en todo el territorio nacional. | B52: 1.8.3 La población usuaria recibe servicios hospitalarios fortalecidos, integrales y de calidad mediante la mejora continua de procesos y servicios, la optimización de la gestión y el fortalecimiento de la infraestructura, el equipamiento y las capacidades del personal. | C52: 1.8.3.10 | D52: Diagnóstico situacional de la conformación de los comités hospitalarios | G52: 1 | J52: 1 | M52: 1 | P52: 1 | Q52: =SUM(E52:P52) -> 4 | R52: Informe | V52: Centros Hospitalarios
A53: 1.8 Superadas las deficiencias en la organización e implementación de las Redes Integradas de Servicios de Salud (RISS) beneficiando a toda la población que utiliza los servicios de salud de la Red Pública, aumentando del 38% en 2023 al 50% en 2028 en todo el territorio nacional. | B53: 1.8.3 La población usuaria recibe servicios hospitalarios fortalecidos, integrales y de calidad mediante la mejora continua de procesos y servicios, la optimización de la gestión y el fortalecimiento de la infraestructura, el equipamiento y las capacidades del personal. | C53: 1.8.3.11 | D53: Conformacion de los comité Hospitalarios | G53: 1 | J53: 1 | M53: 1 | P53: 1 | Q53: =SUM(E53:P53) -> 4 | R53: Reporte | T53: Matriz | V53: Centros Hospitalarios
A54: 1.8 Superadas las deficiencias en la organización e implementación de las Redes Integradas de Servicios de Salud (RISS) beneficiando a toda la población que utiliza los servicios de salud de la Red Pública, aumentando del 38% en 2023 al 50% en 2028 en todo el territorio nacional. | B54: 1.8.3 La población usuaria recibe servicios hospitalarios fortalecidos, integrales y de calidad mediante la mejora continua de procesos y servicios, la optimización de la gestión y el fortalecimiento de la infraestructura, el equipamiento y las capacidades del personal. | C54: 1.8.3.12 | D54: Evaluacion de la Metodologia de Gestion Productiva | G54: 1 | J54: 1 | M54: 1 | P54: 1 | Q54: =SUM(E54:P54) -> 4 | R54: Informe | V54: Centros Hospitalarios
A55: 1.8 Superadas las deficiencias en la organización e implementación de las Redes Integradas de Servicios de Salud (RISS) beneficiando a toda la población que utiliza los servicios de salud de la Red Pública, aumentando del 38% en 2023 al 50% en 2028 en todo el territorio nacional. | B55: 1.8.3 La población usuaria recibe servicios hospitalarios fortalecidos, integrales y de calidad mediante la mejora continua de procesos y servicios, la optimización de la gestión y el fortalecimiento de la infraestructura, el equipamiento y las capacidades del personal. | C55: 1.8.3.13 | D55: Plan de mejora a partir de los resultados de la evaluacion de la metodologia de gestion productiva | H55: 1 | K55: 1 | N55: 1 | P55: 1 | Q55: =SUM(E55:P55) -> 4 | R55: Plan | V55: Centros Hospitalarios
A56: 1.8 Superadas las deficiencias en la organización e implementación de las Redes Integradas de Servicios de Salud (RISS) beneficiando a toda la población que utiliza los servicios de salud de la Red Pública, aumentando del 38% en 2023 al 50% en 2028 en todo el territorio nacional. | B56: 1.8.3 La población usuaria recibe servicios hospitalarios fortalecidos, integrales y de calidad mediante la mejora continua de procesos y servicios, la optimización de la gestión y el fortalecimiento de la infraestructura, el equipamiento y las capacidades del personal. | C56: 1.8.3.14 | D56: Seguimiento a los planes de mejora de la MGP | I56: 1 | L56: 1 | P56: 1 | Q56: =SUM(E56:P56) -> 3 | R56: Informe | S56: Plan | V56: Centros Hospitalarios
A57: 1.8 Superadas las deficiencias en la organización e implementación de las Redes Integradas de Servicios de Salud (RISS) beneficiando a toda la población que utiliza los servicios de salud de la Red Pública, aumentando del 38% en 2023 al 50% en 2028 en todo el territorio nacional. | B57: 1.8.3 La población usuaria recibe servicios hospitalarios fortalecidos, integrales y de calidad mediante la mejora continua de procesos y servicios, la optimización de la gestión y el fortalecimiento de la infraestructura, el equipamiento y las capacidades del personal. | C57: 1.8.3.15 | D57: Supervisión de la calidad de los servicios de nutrición | E57: 1 | F57: 1 | G57: 1 | H57: 1 | I57: 1 | J57: 1 | K57: 1 | L57: 1 | M57: 1 | N57: 1 | O57: 1 | P57: 1 | Q57: =SUM(E57:P57) -> 12 | R57: Informe | V57: Centros Hospitalarios
A58: 1.8 Superadas las deficiencias en la organización e implementación de las Redes Integradas de Servicios de Salud (RISS) beneficiando a toda la población que utiliza los servicios de salud de la Red Pública, aumentando del 38% en 2023 al 50% en 2028 en todo el territorio nacional. | B58: 1.8.3 La población usuaria recibe servicios hospitalarios fortalecidos, integrales y de calidad mediante la mejora continua de procesos y servicios, la optimización de la gestión y el fortalecimiento de la infraestructura, el equipamiento y las capacidades del personal. | C58: 1.8.3.16 | D58: Desarrollo de los planes de mejora a partir de los resultados de las evaluaciones de la calidad de los servicios de nutrición | G58: 1 | J58: 1 | M58: 1 | P58: 1 | Q58: =SUM(E58:P58) -> 4 | R58: Plan | V58: Centros Hospitalarios
A59: 1.8 Superadas las deficiencias en la organización e implementación de las Redes Integradas de Servicios de Salud (RISS) beneficiando a toda la población que utiliza los servicios de salud de la Red Pública, aumentando del 38% en 2023 al 50% en 2028 en todo el territorio nacional. | B59: 1.8.3 La población usuaria recibe servicios hospitalarios fortalecidos, integrales y de calidad mediante la mejora continua de procesos y servicios, la optimización de la gestión y el fortalecimiento de la infraestructura, el equipamiento y las capacidades del personal. | C59: 1.8.3.17 | D59: Implementación del plan de mejora de las evaluaciones de la calidad de los servicios de nutrición | H59: 1 | K59: 1 | N59: 1 | Q59: =SUM(E59:P59) -> 3 | R59: Informe | V59: Centros Hospitalarios
A60: 1.8 Superadas las deficiencias en la organización e implementación de las Redes Integradas de Servicios de Salud (RISS) beneficiando a toda la población que utiliza los servicios de salud de la Red Pública, aumentando del 38% en 2023 al 50% en 2028 en todo el territorio nacional. | B60: 1.8.3 La población usuaria recibe servicios hospitalarios fortalecidos, integrales y de calidad mediante la mejora continua de procesos y servicios, la optimización de la gestión y el fortalecimiento de la infraestructura, el equipamiento y las capacidades del personal. | C60: 1.8.3.18 | D60: Análisis del comportamiento de las objeciones médicas y administrativas | E60: 1 | F60: 1 | G60: 1 | H60: 1 | I60: 1 | J60: 1 | K60: 1 | L60: 1 | M60: 1 | N60: 1 | O60: 1 | P60: 1 | Q60: =SUM(E60:P60) -> 12 | R60: Inventario | V60: Centros Hospitalarios
A61: 1.8 Superadas las deficiencias en la organización e implementación de las Redes Integradas de Servicios de Salud (RISS) beneficiando a toda la población que utiliza los servicios de salud de la Red Pública, aumentando del 38% en 2023 al 50% en 2028 en todo el territorio nacional. | B61: 1.8.3 La población usuaria recibe servicios hospitalarios fortalecidos, integrales y de calidad mediante la mejora continua de procesos y servicios, la optimización de la gestión y el fortalecimiento de la infraestructura, el equipamiento y las capacidades del personal. | C61: 1.8.3.19 | D61: Elaboracion de los planes de mejora para la disminucion de las objeciones médicas, administrativas y el incremento de la facturación de los CEAS, en coordinacion de los SRS los centros de salud. | G61: 1 | J61: 1 | M61: 1 | P61: 1 | Q61: =SUM(E61:P61) -> 4 | R61: Plan | V61: Centros Hospitalarios
A62: 1.8 Superadas las deficiencias en la organización e implementación de las Redes Integradas de Servicios de Salud (RISS) beneficiando a toda la población que utiliza los servicios de salud de la Red Pública, aumentando del 38% en 2023 al 50% en 2028 en todo el territorio nacional. | B62: 1.8.3 La población usuaria recibe servicios hospitalarios fortalecidos, integrales y de calidad mediante la mejora continua de procesos y servicios, la optimización de la gestión y el fortalecimiento de la infraestructura, el equipamiento y las capacidades del personal. | C62: 1.8.3.20 | D62: Seguimiento a la ejecución de planes de mejora para la disminucion de las objeciones médicas, administrativas y el incremento de la facturación de los CEAS. | G62: 1 | J62: 1 | M62: 1 | P62: 1 | Q62: =SUM(E62:P62) -> 4 | R62: Informe | S62: Plan | V62: Centros Hospitalarios
A63: 2.1 Reducida la escasez de recursos humanos de salud, aumentando un 12% en el 2028 la dotación de personal en establecimientos públicos del país. | B63: 2.1.1 El personal del SNS recibe desarrollo de competencias (técnicas y blandas), evaluación del desempeño y gestión de seguridad y salud en el trabajo, con procesos efectivos de relaciones laborales, para mejorar el desempeño, el bienestar y el cumplimiento normativo en toda la red. | C63: 2.1.1.01 | D63: Ejecución Plan de Capacitación 2026. | G63: 1 | J63: 1 | M63: 1 | P63: 1 | Q63: =SUM(E63:P63) -> 4 | R63: Informe | S63: Plan | U63: 1- El informe trimestral se realiza en el formulario estandarizado por el INAP. 2-Adicional presentar listados de asistencia y plan de capacitación 2026. | V63: Recursos Humanos
A64: 2.1 Reducida la escasez de recursos humanos de salud, aumentando un 12% en el 2028 la dotación de personal en establecimientos públicos del país. | B64: 2.1.1 El personal del SNS recibe desarrollo de competencias (técnicas y blandas), evaluación del desempeño y gestión de seguridad y salud en el trabajo, con procesos efectivos de relaciones laborales, para mejorar el desempeño, el bienestar y el cumplimiento normativo en toda la red. | C64: 2.1.1.02 | D64: Detección necesidades capacitación por departamento CEAS Plan 2027. | M64: 1 | Q64: =SUM(E64:P64) -> 1 | R64: Reporte | U64: Presentar anexo formulario por departamento, de acuerdo a la estructura organizativa de cada dependencia. | V64: Recursos Humanos
A65: 2.1 Reducida la escasez de recursos humanos de salud, aumentando un 12% en el 2028 la dotación de personal en establecimientos públicos del país. | B65: 2.1.1 El personal del SNS recibe desarrollo de competencias (técnicas y blandas), evaluación del desempeño y gestión de seguridad y salud en el trabajo, con procesos efectivos de relaciones laborales, para mejorar el desempeño, el bienestar y el cumplimiento normativo en toda la red. | C65: 2.1.1.03 | D65: Elaboración del Plan de Capacitación CEAS 2027. | N65: 1 | Q65: =SUM(E65:P65) -> 1 | R65: Plan | U65: Realizar plan de capacitación en formulario estándarizado por el INAP. | V65: Recursos Humanos
A66: 2.1 Reducida la escasez de recursos humanos de salud, aumentando un 12% en el 2028 la dotación de personal en establecimientos públicos del país. | B66: 2.1.1 El personal del SNS recibe desarrollo de competencias (técnicas y blandas), evaluación del desempeño y gestión de seguridad y salud en el trabajo, con procesos efectivos de relaciones laborales, para mejorar el desempeño, el bienestar y el cumplimiento normativo en toda la red. | C66: 2.1.1.04 | D66: Consolidado de resultados de evaluación del desempeño laboral 2025. | E66: 1 | Q66: =SUM(E66:P66) -> 1 | R66: Reporte | U66: Matriz para reportar resultados de evaluación del desempeño laboral 2025. | V66: Recursos Humanos
A67: 2.1 Reducida la escasez de recursos humanos de salud, aumentando un 12% en el 2028 la dotación de personal en establecimientos públicos del país. | B67: 2.1.1 El personal del SNS recibe desarrollo de competencias (técnicas y blandas), evaluación del desempeño y gestión de seguridad y salud en el trabajo, con procesos efectivos de relaciones laborales, para mejorar el desempeño, el bienestar y el cumplimiento normativo en toda la red. | C67: 2.1.1.05 | D67: Consolidado de resultados de acuerdos del desempeño laboral 2026. | E67: 1 | Q67: =SUM(E67:P67) -> 1 | R67: Reporte | U67: Matriz para reportar acuerdos del desempeño laboral 2026. | V67: Recursos Humanos
A68: 2.1 Reducida la escasez de recursos humanos de salud, aumentando un 12% en el 2028 la dotación de personal en establecimientos públicos del país. | B68: 2.1.1 El personal del SNS recibe desarrollo de competencias (técnicas y blandas), evaluación del desempeño y gestión de seguridad y salud en el trabajo, con procesos efectivos de relaciones laborales, para mejorar el desempeño, el bienestar y el cumplimiento normativo en toda la red. | C68: 2.1.1.06 | D68: Elaboración informe técnico resultados de evaluación del desempeño laboral 2025 CEAS y remisión al SRS. | G68: 1 | Q68: =SUM(E68:P68) -> 1 | R68: Informe | U68: Informe técnico de resultados evaluación del desempeño laboral 2025. | V68: Recursos Humanos
A69: 2.1 Reducida la escasez de recursos humanos de salud, aumentando un 12% en el 2028 la dotación de personal en establecimientos públicos del país. | B69: 2.1.1 El personal del SNS recibe desarrollo de competencias (técnicas y blandas), evaluación del desempeño y gestión de seguridad y salud en el trabajo, con procesos efectivos de relaciones laborales, para mejorar el desempeño, el bienestar y el cumplimiento normativo en toda la red. | C69: 2.1.1.07 | D69: Monitoreo por departamento de los acuerdos de desempeño laboral 2027 | H69: 1 | K69: 1 | N69: 1 | Q69: =SUM(E69:P69) -> 3 | R69: Minuta | U69: No se requiere listado de asistencia adicional, ya que la minuta estandarizada del MAP es firmada por los colaboradores que participan en la reunión de revisión. | V69: Recursos Humanos
A70: 2.1 Reducida la escasez de recursos humanos de salud, aumentando un 12% en el 2028 la dotación de personal en establecimientos públicos del país. | B70: 2.1.1 El personal del SNS recibe desarrollo de competencias (técnicas y blandas), evaluación del desempeño y gestión de seguridad y salud en el trabajo, con procesos efectivos de relaciones laborales, para mejorar el desempeño, el bienestar y el cumplimiento normativo en toda la red. | C70: 2.1.1.08 | D70: Remisión al SRS consolidado trimestral de acuerdos de desempeño personal nuevo ingreso CEAS | H70: 1 | K70: 1 | N70: 1 | Q70: =SUM(E70:P70) -> 3 | R70: Reporte | V70: Recursos Humanos
A71: 3.1 Fortalecida la capacidad institucional para aumentar el acceso a servicios públicos de calidad mediante la optimización de procesos, empoderamiento del talento humano, articulación efectiva, incorporación de tecnologías de la información y comunicación, modernización de la infraestructura física y equipamiento adecuado. | B71: 3.1.1 Los Centros de Atención y Servicios (CEAS) y las Oficinas Regionales de Salud (ORS) reciben el Formulario de Levantamiento de Necesidades de Cooperación No Reembolsable como instrumento estandarizado, | C71: 3.1.1.01 | D71: Llenado y envío del formulario de levantamiento de necesidades de cooperación no reembolsable a la ORS. | E71: 1 | Q71: =SUM(E71:P71) -> 1 | T71: 1. Formulario de levantamiento de necesidades de cooperación no reembolsable completo y firmado. 2. Remisión vía correo electrónico del formulario a la ORS. | V71: Planificación
A72: 3.1 Fortalecida la capacidad institucional para aumentar el acceso a servicios públicos de calidad mediante la optimización de procesos, empoderamiento del talento humano, articulación efectiva, incorporación de tecnologías de la información y comunicación, modernización de la infraestructura física y equipamiento adecuado. | B72: 3.1.1 Los Centros de Atención y Servicios (CEAS) y las Oficinas Regionales de Salud (ORS) reciben el Formulario de Levantamiento de Necesidades de Cooperación No Reembolsable como instrumento estandarizado, | C72: 3.1.1.02 | D72: Llenado y envío del Formulario de Reporte de Donaciones a la ORS. | K72: 1 | P72: 1 | Q72: =SUM(E72:P72) -> 2 | T72: 1. Formulario de Reporte de Donaciones sellado y firmado. 2. Remisión vía correo electrónico del formulario a la ORS. | V72: Planificación
A73: 3.1 Fortalecida la capacidad institucional para aumentar el acceso a servicios públicos de calidad mediante la optimización de procesos, empoderamiento del talento humano, articulación efectiva, incorporación de tecnologías de la información y comunicación, modernización de la infraestructura física y equipamiento adecuado. | B73: 3.1.5 Personal y usuarios del SNS reciben servicios tecnológicos confiables | C73: 3.1.5.01 | D73: Actualización de portales web | G73: 1 | J73: 1 | M73: 1 | P73: 1 | Q73: =SUM(E73:P73) -> 4 | R73: Reporte | V73: Tecnología
A74: 3.1 Fortalecida la capacidad institucional para aumentar el acceso a servicios públicos de calidad mediante la optimización de procesos, empoderamiento del talento humano, articulación efectiva, incorporación de tecnologías de la información y comunicación, modernización de la infraestructura física y equipamiento adecuado. | B74: 3.1.5 Personal y usuarios del SNS reciben servicios tecnológicos confiables | C74: 3.1.5.02 | D74: Soportes incidencias tecnológicas atendidas | G74: 1 | J74: 1 | M74: 1 | P74: 1 | Q74: =SUM(E74:P74) -> 4 | R74: Reporte | V74: Tecnología
A75: 3.1 Fortalecida la capacidad institucional para aumentar el acceso a servicios públicos de calidad mediante la optimización de procesos, empoderamiento del talento humano, articulación efectiva, incorporación de tecnologías de la información y comunicación, modernización de la infraestructura física y equipamiento adecuado. | B75: 3.1.5 Personal y usuarios del SNS reciben servicios tecnológicos confiables | C75: 3.1.5.03 | D75: Inventario de activos tecnológicos | G75: 1 | J75: 1 | M75: 1 | P75: 1 | Q75: =SUM(E75:P75) -> 4 | R75: Inventario | V75: Tecnología
A76: 3.1 Fortalecida la capacidad institucional para aumentar el acceso a servicios públicos de calidad mediante la optimización de procesos, empoderamiento del talento humano, articulación efectiva, incorporación de tecnologías de la información y comunicación, modernización de la infraestructura física y equipamiento adecuado. | B76: 3.1.6 La población usuaria recibe servicios seguros y de calidad mediante el fortalecimiento del modelo institucional de gestión y monitoreo de la calidad, con estándares, indicadores, auditorías y acciones de mejora continua en todas las unidades. | C76: 3.1.6.01 | D76: Elaboración de la memoria institucional 2026 | O76: 1 | Q76: =SUM(E76:P76) -> 1 | R76: Memoria | V76: Planificación
A77: 3.1 Fortalecida la capacidad institucional para aumentar el acceso a servicios públicos de calidad mediante la optimización de procesos, empoderamiento del talento humano, articulación efectiva, incorporación de tecnologías de la información y comunicación, modernización de la infraestructura física y equipamiento adecuado. | B77: 3.1.6 La población usuaria recibe servicios seguros y de calidad mediante el fortalecimiento del modelo institucional de gestión y monitoreo de la calidad, con estándares, indicadores, auditorías y acciones de mejora continua en todas las unidades. | C77: 3.1.6.02 | D77: Elaboración del Plan Operativo Anual 2027 | M77: 1 | Q77: =SUM(E77:P77) -> 1 | R77: Plan | V77: Planificación
A78: 3.1 Fortalecida la capacidad institucional para aumentar el acceso a servicios públicos de calidad mediante la optimización de procesos, empoderamiento del talento humano, articulación efectiva, incorporación de tecnologías de la información y comunicación, modernización de la infraestructura física y equipamiento adecuado. | B78: 3.1.6 La población usuaria recibe servicios seguros y de calidad mediante el fortalecimiento del modelo institucional de gestión y monitoreo de la calidad, con estándares, indicadores, auditorías y acciones de mejora continua en todas las unidades. | C78: 3.1.6.03 | D78: Autoevaluación POA 2026 | E78: 1 | H78: 1 | K78: 1 | N78: 1 | Q78: =SUM(E78:P78) -> 4 | T78: MEP | V78: Planificación
A79: 3.1 Fortalecida la capacidad institucional para aumentar el acceso a servicios públicos de calidad mediante la optimización de procesos, empoderamiento del talento humano, articulación efectiva, incorporación de tecnologías de la información y comunicación, modernización de la infraestructura física y equipamiento adecuado. | B79: 3.1.6 La población usuaria recibe servicios seguros y de calidad mediante el fortalecimiento del modelo institucional de gestión y monitoreo de la calidad, con estándares, indicadores, auditorías y acciones de mejora continua en todas las unidades. | C79: 3.1.6.04 | D79: Elaboración y seguimiento a la ejecución de los planes de mejora acorde a los hallazgos del MEP | F79: 1 | I79: 1 | L79: 1 | O79: 1 | Q79: =SUM(E79:P79) -> 4 | R79: Listado de participación | S79: Informe | T79: Plan | V79: Planificación
A80: 3.1 Fortalecida la capacidad institucional para aumentar el acceso a servicios públicos de calidad mediante la optimización de procesos, empoderamiento del talento humano, articulación efectiva, incorporación de tecnologías de la información y comunicación, modernización de la infraestructura física y equipamiento adecuado. | B80: 3.1.6 La población usuaria recibe servicios seguros y de calidad mediante el fortalecimiento del modelo institucional de gestión y monitoreo de la calidad, con estándares, indicadores, auditorías y acciones de mejora continua en todas las unidades. | C80: 3.1.6.05 | D80: Elaboración del informe de autodiagnóstico y sistema afinado de puntuación CAF | I80: 1 | Q80: =SUM(E80:P80) -> 1 | R80: Informe | V80: Planificación
A81: 3.1 Fortalecida la capacidad institucional para aumentar el acceso a servicios públicos de calidad mediante la optimización de procesos, empoderamiento del talento humano, articulación efectiva, incorporación de tecnologías de la información y comunicación, modernización de la infraestructura física y equipamiento adecuado. | B81: 3.1.6 La población usuaria recibe servicios seguros y de calidad mediante el fortalecimiento del modelo institucional de gestión y monitoreo de la calidad, con estándares, indicadores, auditorías y acciones de mejora continua en todas las unidades. | C81: 3.1.6.06 | D81: Informe de seguimiento a plan de mejora CAF año en curso | I81: 1 | Q81: =SUM(E81:P81) -> 1 | R81: Informe | V81: Planificación
A82: 3.1 Fortalecida la capacidad institucional para aumentar el acceso a servicios públicos de calidad mediante la optimización de procesos, empoderamiento del talento humano, articulación efectiva, incorporación de tecnologías de la información y comunicación, modernización de la infraestructura física y equipamiento adecuado. | B82: 3.1.6 La población usuaria recibe servicios seguros y de calidad mediante el fortalecimiento del modelo institucional de gestión y monitoreo de la calidad, con estándares, indicadores, auditorías y acciones de mejora continua en todas las unidades. | C82: 3.1.6.07 | D82: Elaboración plan de mejora CAF del próximo año | K82: 1 | Q82: =SUM(E82:P82) -> 1 | R82: Plan | V82: Planificación
A83: 3.1 Fortalecida la capacidad institucional para aumentar el acceso a servicios públicos de calidad mediante la optimización de procesos, empoderamiento del talento humano, articulación efectiva, incorporación de tecnologías de la información y comunicación, modernización de la infraestructura física y equipamiento adecuado. | B83: 3.1.6 La población usuaria recibe servicios seguros y de calidad mediante el fortalecimiento del modelo institucional de gestión y monitoreo de la calidad, con estándares, indicadores, auditorías y acciones de mejora continua en todas las unidades. | C83: 3.1.6.08 | D83: Implementación, renovación o actualización de CCC (Carta Compromiso al Ciudadano) según aplique | O83: 1 | Q83: =SUM(E83:P83) -> 1 | T83: Resolución aprobatoria | V83: Planificación
A84: 3.1 Fortalecida la capacidad institucional para aumentar el acceso a servicios públicos de calidad mediante la optimización de procesos, empoderamiento del talento humano, articulación efectiva, incorporación de tecnologías de la información y comunicación, modernización de la infraestructura física y equipamiento adecuado. | B84: 3.1.6 La población usuaria recibe servicios seguros y de calidad mediante el fortalecimiento del modelo institucional de gestión y monitoreo de la calidad, con estándares, indicadores, auditorías y acciones de mejora continua en todas las unidades. | C84: 3.1.6.09 | D84: Seguimiento al cumplimiento de la CCC (Carta Compromiso al Ciudadano) | G84: 1 | J84: 1 | M84: 1 | P84: 1 | Q84: =SUM(E84:P84) -> 4 | R84: Reporte | V84: Planificación
A85: 3.1 Fortalecida la capacidad institucional para aumentar el acceso a servicios públicos de calidad mediante la optimización de procesos, empoderamiento del talento humano, articulación efectiva, incorporación de tecnologías de la información y comunicación, modernización de la infraestructura física y equipamiento adecuado. | B85: 3.1.6 La población usuaria recibe servicios seguros y de calidad mediante el fortalecimiento del modelo institucional de gestión y monitoreo de la calidad, con estándares, indicadores, auditorías y acciones de mejora continua en todas las unidades. | C85: 3.1.6.10 | D85: Seguimiento a la implementación plan de mejora SISMAP Salud y Programa de Desempeño SNS | O85: 1 | Q85: =SUM(E85:P85) -> 1 | R85: Informe | V85: Planificación
A86: 3.1 Fortalecida la capacidad institucional para aumentar el acceso a servicios públicos de calidad mediante la optimización de procesos, empoderamiento del talento humano, articulación efectiva, incorporación de tecnologías de la información y comunicación, modernización de la infraestructura física y equipamiento adecuado. | B86: 3.1.6 La población usuaria recibe servicios seguros y de calidad mediante el fortalecimiento del modelo institucional de gestión y monitoreo de la calidad, con estándares, indicadores, auditorías y acciones de mejora continua en todas las unidades. | C86: 3.1.6.11 | D86: Ejecución de las sesiones del comité de calidad del CEAS | J86: 1 | Q86: =SUM(E86:P86) -> 1 | R86: Listado de participación | S86: Minuta | V86: Planificación
A87: 3.1 Fortalecida la capacidad institucional para aumentar el acceso a servicios públicos de calidad mediante la optimización de procesos, empoderamiento del talento humano, articulación efectiva, incorporación de tecnologías de la información y comunicación, modernización de la infraestructura física y equipamiento adecuado. | B87: 3.1.7 Los establecimientos de la red SNS disponen de bienes oportunos, custodiados y en condiciones óptimas mediante el fortalecimiento del Sistema de Administración de Bienes: registro e inventario, control y trazabilidad, mantenimiento, distribución y bajas, con enfoque de ciclo de vida y transparencia. | C87: 3.1.7.01 | D87: Actualizacion de Inventarios de la ORS | J87: 1 | P87: 1 | Q87: =SUM(E87:P87) -> 2 | R87: Informe | S87: Inventario | V87: Administrativo-Financiero
A88: 3.1 Fortalecida la capacidad institucional para aumentar el acceso a servicios públicos de calidad mediante la optimización de procesos, empoderamiento del talento humano, articulación efectiva, incorporación de tecnologías de la información y comunicación, modernización de la infraestructura física y equipamiento adecuado. | B88: 3.1.7 Los establecimientos de la red SNS disponen de bienes oportunos, custodiados y en condiciones óptimas mediante el fortalecimiento del Sistema de Administración de Bienes: registro e inventario, control y trazabilidad, mantenimiento, distribución y bajas, con enfoque de ciclo de vida y transparencia. | C88: 3.1.7.02 | D88: Registro de Activos en el Sistema de Administracion de Bienes (SIAB) | G88: 1 | J88: 1 | M88: 1 | P88: 1 | Q88: =SUM(E88:P88) -> 4 | R88: Reporte | V88: Administrativo-Financiero
A89: 3.2 Incrementada la satisfacción de usuarios y la calidad percibida de los servicios públicos | B89: 3.2.1 Los pacientes reciben cuidados seguros y de calidad mediante la continuidad en la implementación y aplicación de los siete estándares de calidad de los servicios de enfermería. | C89: 3.2.1.01 | D89: Supervisión y aplicación expediente clínico en el hospital | G89: 1 | J89: 1 | M89: 1 | O89: 1 | Q89: =SUM(E89:P89) -> 4 | R89: Informe | V89: Enfermería
A90: 3.2 Incrementada la satisfacción de usuarios y la calidad percibida de los servicios públicos | B90: 3.2.1 Los pacientes reciben cuidados seguros y de calidad mediante la continuidad en la implementación y aplicación de los siete estándares de calidad de los servicios de enfermería. | C90: 3.2.1.02 | D90: Capacitación y retroalimentación en dosificación y administración de medicamentos al personal de enfermería | F90: 1 | H90: 1 | J90: 1 | L90: 1 | N90: 1 | Q90: =SUM(E90:P90) -> 5 | R90: Listado de participación | S90: Agenda | V90: Enfermería
A91: 3.2 Incrementada la satisfacción de usuarios y la calidad percibida de los servicios públicos | B91: 3.2.1 Los pacientes reciben cuidados seguros y de calidad mediante la continuidad en la implementación y aplicación de los siete estándares de calidad de los servicios de enfermería. | C91: 3.2.1.03 | D91: Seguimiento a la aplicación de los 7 estándares de cuidados de enfermería | M91: 1 | Q91: =SUM(E91:P91) -> 1 | R91: Informe | V91: Enfermería
A92: 3.2 Incrementada la satisfacción de usuarios y la calidad percibida de los servicios públicos | B92: 3.2.2 La población usuaria y los clínicos reciben diagnósticos confiables y oportunos mediante el fortalecimiento de la red del SNS: monitoreo y evaluación continua de la calidad para guiar decisiones, habilitación/acreditación de establecimientos y cumplimiento de estándares de seguridad, asegurando acceso eficiente a servicios de calidad. | C92: 3.2.2.01 | D92: Autoevaluacion SLIPTA para cumplimiento de SISMAP SALUD | H92: 1 | J92: 1 | M92: 1 | Q92: =SUM(E92:P92) -> 3 | R92: Listado de participación | U92: Plan de Mejora | V92: Laboratorios e Imágenes
A93: 3.2 Incrementada la satisfacción de usuarios y la calidad percibida de los servicios públicos | B93: 3.2.2 La población usuaria y los clínicos reciben diagnósticos confiables y oportunos mediante el fortalecimiento de la red del SNS: monitoreo y evaluación continua de la calidad para guiar decisiones, habilitación/acreditación de establecimientos y cumplimiento de estándares de seguridad, asegurando acceso eficiente a servicios de calidad. | C93: 3.2.2.02 | D93: Garantizar la disponibilidad de pruebas de laboratorios y estudios de imágenes que se realizan a embarazadas y recien nacidos en hospitales maternos. | F93: 1 | H93: 1 | J93: 1 | L93: 1 | Q93: =SUM(E93:P93) -> 4 | R93: Informe | U93: Febrero EES que apliquen de : ozama, el valle, higuamo Abril EES que apliquen de: valdesia, cibao noroeste Junio EES que apliquen de: enriquillo, cibao norte, cibao sur Agosto EES que apliquen de: cibao nordeste,yuma | V93: Laboratorios e Imágenes
A94: 3.2 Incrementada la satisfacción de usuarios y la calidad percibida de los servicios públicos | B94: 3.2.2 La población usuaria y los clínicos reciben diagnósticos confiables y oportunos mediante el fortalecimiento de la red del SNS: monitoreo y evaluación continua de la calidad para guiar decisiones, habilitación/acreditación de establecimientos y cumplimiento de estándares de seguridad, asegurando acceso eficiente a servicios de calidad. | C94: 3.2.2.03 | D94: Automatización de los servicios/ mantenimiento a los equipos y calibracion de cabinas de los departamentos de microbiologia en los EES que cuentan con departamento de microbiologia clinica. | K94: 1 | Q94: =SUM(E94:P94) -> 1 | R94: Informe | V94: laboratorios e Imágenes
A95: 3.2 Incrementada la satisfacción de usuarios y la calidad percibida de los servicios públicos | B95: 3.2.2 La población usuaria y los clínicos reciben diagnósticos confiables y oportunos mediante el fortalecimiento de la red del SNS: monitoreo y evaluación continua de la calidad para guiar decisiones, habilitación/acreditación de establecimientos y cumplimiento de estándares de seguridad, asegurando acceso eficiente a servicios de calidad. | C95: 3.2.2.04 | D95: Cumplimiento la ruta de recolecion y/o envio y/o recepción de las muestras. | E95: 1 | H95: 1 | K95: 1 | M95: 1 | Q95: =SUM(E95:P95) -> 4 | T95: Cronograma de ruta/ formularios de envios y/o recepción de muestras. | U95: Enero EES que apliquen de : ozama, el valle, higuamo Abril EES de: valdesia, cibao noroeste Julio EES de: enriquillo, cibao norte, cibao sur Septiembre EES de : cibao nordeste,yuma | V95: Laboratorios e Imágenes
A96: 3.2 Incrementada la satisfacción de usuarios y la calidad percibida de los servicios públicos | B96: 3.2.2 La población usuaria y los clínicos reciben diagnósticos confiables y oportunos mediante el fortalecimiento de la red del SNS: monitoreo y evaluación continua de la calidad para guiar decisiones, habilitación/acreditación de establecimientos y cumplimiento de estándares de seguridad, asegurando acceso eficiente a servicios de calidad. | C96: 3.2.2.05 | D96: Autoevaluacion para cumplimiento de habilitacion en los EES que cuentan con servicios de hemoterapia. | E96: 1 | J96: 1 | Q96: =SUM(E96:P96) -> 2 | R96: Informe | V96: Laboratorios e Imágenes
A97: 3.2 Incrementada la satisfacción de usuarios y la calidad percibida de los servicios públicos | B97: 3.2.2 La población usuaria y los clínicos reciben diagnósticos confiables y oportunos mediante el fortalecimiento de la red del SNS: monitoreo y evaluación continua de la calidad para guiar decisiones, habilitación/acreditación de establecimientos y cumplimiento de estándares de seguridad, asegurando acceso eficiente a servicios de calidad. | C97: 3.2.2.06 | D97: Conformación y/o actualización de clubes de donantes de sangre en EES que cuentan con servicios de hemoterapia. | E97: 1 | J97: 1 | Q97: =SUM(E97:P97) -> 2 | T97: Acta de formación/ Listado actualizado del club de donantes. | V97: Laboratorios e Imágenes
A98: 3.2 Incrementada la satisfacción de usuarios y la calidad percibida de los servicios públicos | B98: 3.2.2 La población usuaria y los clínicos reciben diagnósticos confiables y oportunos mediante el fortalecimiento de la red del SNS: monitoreo y evaluación continua de la calidad para guiar decisiones, habilitación/acreditación de establecimientos y cumplimiento de estándares de seguridad, asegurando acceso eficiente a servicios de calidad. | C98: 3.2.2.07 | D98: Mantenimiento a los equipos y calibracion de cabinas. | G98: 1 | I98: 1 | L98: 1 | Q98: =SUM(E98:P98) -> 3 | R98: Reporte | T98: Reporte de los mantenimientos de equipos y calibración de cabinas. | U98: EES donde aplique, Marzo: enriquillo, cibao norte, cibao sur mayo: ozama, el valle, higuamo agosto: valdesia, cibao noroeste,Yuma y cibao nordeste | V98: Laboratorios e Imágenes
A99: 3.2 Incrementada la satisfacción de usuarios y la calidad percibida de los servicios públicos | B99: 3.2.2 La población usuaria y los clínicos reciben diagnósticos confiables y oportunos mediante el fortalecimiento de la red del SNS: monitoreo y evaluación continua de la calidad para guiar decisiones, habilitación/acreditación de establecimientos y cumplimiento de estándares de seguridad, asegurando acceso eficiente a servicios de calidad. | C99: 3.2.2.08 | D99: Compra de insumos para la toma de las muestras. | G99: 1 | M99: 1 | Q99: =SUM(E99:P99) -> 2 | T99: Listado de disponibilidad de insumos de toma de muestras. Evidencia de compra de insumos actualizada. | V99: Laboratorios e Imágenes
A100: 3.2 Incrementada la satisfacción de usuarios y la calidad percibida de los servicios públicos | B100: 3.2.2 La población usuaria y los clínicos reciben diagnósticos confiables y oportunos mediante el fortalecimiento de la red del SNS: monitoreo y evaluación continua de la calidad para guiar decisiones, habilitación/acreditación de establecimientos y cumplimiento de estándares de seguridad, asegurando acceso eficiente a servicios de calidad. | C100: 3.2.2.09 | D100: Envio mensual Infolab a SRS | E100: 1 | F100: 1 | G100: 1 | H100: 1 | I100: 1 | J100: 1 | K100: 1 | L100: 1 | M100: 1 | N100: 1 | O100: 1 | P100: 1 | Q100: =SUM(E100:P100) -> 12 | T100: Captura de envio a SRS | V100: Laboratorios e Imágenes
...

Sheet Sheet1
E2: Informe | F2: 1.1 Reducidos los niveles de morbilidad y mortalidad materna e infantil por causas prevenibles en la población materno-infantil del país, disminuyendo la mortalidad materna de 127.33 y la mortalidad infantil de 18.44 en 2023 a 89.13 y 16.56 en 2028 en todas las regiones del territorio nacional.
E3: Listado de participación | F3: 1.2 Aumentado el cumplimiento normativo para reducir la incidencia de complicaciones neonatales y maternas, pasando de un promedio del 75.5% en el año 2023 al 88% en el año 2028 en todas las regiones de la Red Pública de Servicios de Salud.
E4: Fotos | F4: 1.3 Reducido el embarazo en adolescentes atendidas en los establecimientos de la Red Pública en un 20% al año 2028, mediante el fortalecimiento del acceso a servicios integrales de salud sexual y reproductiva.
E5: Agenda | F5: 1.4 Disminuida la proporción de partos por cesárea en hospitales del sector público pasando de 48.83 en el 2023 a 34 en el 2028.
E6: Plan | F6: 1.5 Reducida la morbilidad y mortalidad prematura por enfermedades no transmisibles en personas de 30 a 69 años, en un 20% al año 2028, mediante la implementación de intervenciones integrales de prevención, diagnóstico temprano y tratamiento oportuno en los establecimientos de la Red Pública.
E7: Protocolo | F7: 1.6 Incrementado el acceso oportuno a servicios de salud de calidad, aumentando el acceso a servicios preventivos de 2.23% de la población prioritaria en 2023 al 5.24% en 2028 en todas las regiones del país.
E8: Manual | F8: 1.7 Aumentada la disponibilidad de medicamentos esenciales en los establecimientos de la Red Pública de Servicios de Salud, incrementando el cumplimiento promedio de abastecimiento del 88% en 2023 al 93% en 2028 en todas las regiones del país.
E9: Resolución | F9: 1.8 Superadas las deficiencias en la organización e implementación de las Redes Integradas de Servicios de Salud (RISS) beneficiando a toda la población que utiliza los servicios de salud de la Red Pública, aumentando del 38% en 2023 al 50% en 2028 en todo el territorio nacional.
E10: Boletin | F10: 1.9 Fortalecida la implementación del Modelo de Atención en Salud beneficiando a la población usuaria del primer nivel de atención, incrementando la adscripción del 7% en 2023 al 80% en 2028, en todas las regiones del país.
E11: Reporte | F11: 1.10 Mejorada la distribución y presencia del Primer Nivel de Atención respecto a la sectorización, incrementando la presencia del Primer Nivel del 70% en 2023 al 71% en 2028 en todas las regiones del territorio nacional.
E12: Minuta | F12: 1.11 Fortalecida la continuidad en la atención de las puérperas y recién nacidos, aumentando la captación oportuna del 30% en 2023 al 50% en 2028 en el Primer Nivel de Atención.
E13: Hoja de supervisión | F13: 1.12 Superadas las deficiencias en la organización e implementación de las Redes Integradas de Servicios de Salud (RISS) beneficiando a toda la población que utiliza los servicios de salud de la Red Pública, aumentando del 38% en 2023 al 50% en 2028 en todo el territorio nacional.
... E20: Otros | F20: 3.4 Alcanzado un cumplimiento mínimo del 90% de las metas de planificación y ejecución presupuestaria, optimizando la asignación y uso de recursos.
F21: 3.5 Atendidas las solicitudes de información recibidas en los plazos establecidos, con reportes de cumplimiento mensual y mecanismos de retroalimentación al usuario.
F22: 3.6 Registradas y procesadas en el Sistema Electrónico de Compras Públicas las adquisiciones y contrataciones institucionales y de la Red Pública.
F23: 3.7 Incrementando progresivamente el índice de uso de las TIC y Gobierno Digital en la Red Pública de Servicios de Salud.
F24: 3.8 Implementados y operativos los controles internos definidos por las NOBACI, con revisiones de cumplimiento semestrales y planes de mejora continua.
F25: 3.9 Instalaciones físicas remodeladas y equipadas conforme a estándares de centros de salud incrementando su capacidad resolutiva.
F26: 3.10 Implementado un sistema integral de medición y gestión de la satisfacción de usuarios, con reportes trimestrales y planes de mejora continua para elevar la calidad percibida de los servicios públicos.

Sheet PPNE2.1
O1: Venta Servicios
G2: Servicio Nacional de Salud | S2: Anticipo Financiero
G3: Dirección de Planificación y Desarrollo | S3: Venta de Servicios
G4: Programación de Insumos | S4: Donaciones
J5: =+PPNE1!C5 -> 2026
G6: CEAS | H6: =+PPNE1!B7 -> 0
B7: ID_Dependendencia | C7: POA | D7: SRS | E7: AREA | F7: TIPO | G7: Código_Actividad | H7: Insumos | I7: Unidad de Medida | J7: Cantidad de Insumos | K7: Precio Unitario | L7: Valor Total | M7: Código Presupuestario | N7: Fuente de Financiamiento
B8: =IF(Tabla1[[#This Row],[Código_Actividad]]="","",CONCATENATE(Tabla1[[#This Row],[POA]],".",Tabla1[[#This Row],[SRS]],".",Tabla1[[#This Row],[AREA]],".",Tabla1[[#This Row],[TIPO]])) -> ... | G8: 1.2.1.01 | H8: leche | I8: und | L8: =+Tabla1[[#This Row],[Precio Unitario]]*Tabla1[[#This Row],[Cantidad de Insumos]] -> 0
B9: =IF(Tabla1[[#This Row],[Código_Actividad]]="","",CONCATENATE(Tabla1[[#This Row],[POA]],".",Tabla1[[#This Row],[SRS]],".",Tabla1[[#This Row],[AREA]],".",Tabla1[[#This Row],[TIPO]])) | L9: =+Tabla1[[#This Row],[Precio Unitario]]*Tabla1[[#This Row],[Cantidad de Insumos]] -> 0
B10: =IF(Tabla1[[#This Row],[Código_Actividad]]="","",CONCATENATE(Tabla1[[#This Row],[POA]],".",Tabla1[[#This Row],[SRS]],".",Tabla1[[#This Row],[AREA]],".",Tabla1[[#This Row],[TIPO]])) | L10: =+Tabla1[[#This Row],[Precio Unitario]]*Tabla1[[#This Row],[Cantidad de Insumos]] -> 0
B11: =IF(Tabla1[[#This Row],[Código_Actividad]]="","",CONCATENATE(Tabla1[[#This Row],[POA]],".",Tabla1[[#This Row],[SRS]],".",Tabla1[[#This Row],[AREA]],".",Tabla1[[#This Row],[TIPO]])) | L11: =+Tabla1[[#This Row],[Precio Unitario]]*Tabla1[[#This Row],[Cantidad de Insumos]] -> 0
B12: =IF(Tabla1[[#This Row],[Código_Actividad]]="","",CONCATENATE(Tabla1[[#This Row],[POA]],".",Tabla1[[#This Row],[SRS]],".",Tabla1[[#This Row],[AREA]],".",Tabla1[[#This Row],[TIPO]])) | L12: =+Tabla1[[#This Row],[Precio Unitario]]*Tabla1[[#This Row],[Cantidad de Insumos]] -> 0
B13: =IF(Tabla1[[#This Row],[Código_Actividad]]="","",CONCATENATE(Tabla1[[#This Row],[POA]],".",Tabla1[[#This Row],[SRS]],".",Tabla1[[#This Row],[AREA]],".",Tabla1[[#This Row],[TIPO]])) | L13: =+Tabla1[[#This Row],[Precio Unitario]]*Tabla1[[#This Row],[Cantidad de Insumos]] -> 0
B14: =IF(Tabla1[[#This Row],[Código_Actividad]]="","",CONCATENATE(Tabla1[[#This Row],[POA]],".",Tabla1[[#This Row],[SRS]],".",Tabla1[[#This Row],[AREA]],".",Tabla1[[#This Row],[TIPO]])) | L14: =+Tabla1[[#This Row],[Precio Unitario]]*Tabla1[[#This Row],[Cantidad de Insumos]] -> 0
B15: =IF(Tabla1[[#This Row],[Código_Actividad]]="","",CONCATENATE(Tabla1[[#This Row],[POA]],".",Tabla1[[#This Row],[SRS]],".",Tabla1[[#This Row],[AREA]],".",Tabla1[[#This Row],[TIPO]])) | L15: =+Tabla1[[#This Row],[Precio Unitario]]*Tabla1[[#This Row],[Cantidad de Insumos]] -> 0
B16: =IF(Tabla1[[#This Row],[Código_Actividad]]="","",CONCATENATE(Tabla1[[#This Row],[POA]],".",Tabla1[[#This Row],[SRS]],".",Tabla1[[#This Row],[AREA]],".",Tabla1[[#This Row],[TIPO]])) | L16: =+Tabla1[[#This Row],[Precio Unitario]]*Tabla1[[#This Row],[Cantidad de Insumos]] -> 0
B17: =IF(Tabla1[[#This Row],[Código_Actividad]]="","",CONCATENATE(Tabla1[[#This Row],[POA]],".",Tabla1[[#This Row],[SRS]],".",Tabla1[[#This Row],[AREA]],".",Tabla1[[#This Row],[TIPO]])) | L17: =+Tabla1[[#This Row],[Precio Unitario]]*Tabla1[[#This Row],[Cantidad de Insumos]] -> 0
B18: =IF(Tabla1[[#This Row],[Código_Actividad]]="","",CONCATENATE(Tabla1[[#This Row],[POA]],".",Tabla1[[#This Row],[SRS]],".",Tabla1[[#This Row],[AREA]],".",Tabla1[[#This Row],[TIPO]])) | L18: =+Tabla1[[#This Row],[Precio Unitario]]*Tabla1[[#This Row],[Cantidad de Insumos]] -> 0
B19: =IF(Tabla1[[#This Row],[Código_Actividad]]="","",CONCATENATE(Tabla1[[#This Row],[POA]],".",Tabla1[[#This Row],[SRS]],".",Tabla1[[#This Row],[AREA]],".",Tabla1[[#This Row],[TIPO]])) | L19: =+Tabla1[[#This Row],[Precio Unitario]]*Tabla1[[#This Row],[Cantidad de Insumos]] -> 0
B20: =IF(Tabla1[[#This Row],[Código_Actividad]]="","",CONCATENATE(Tabla1[[#This Row],[POA]],".",Tabla1[[#This Row],[SRS]],".",Tabla1[[#This Row],[AREA]],".",Tabla1[[#This Row],[TIPO]])) | L20: =+Tabla1[[#This Row],[Precio Unitario]]*Tabla1[[#This Row],[Cantidad de Insumos]] -> 0
... B214: =IF(Tabla1[[#This Row],[Código_Actividad]]="","",CONCATENATE(Tabla1[[#This Row],[POA]],".",Tabla1[[#This Row],[SRS]],".",Tabla1[[#This Row],[AREA]],".",Tabla1[[#This Row],[TIPO]])) | L214: =+Tabla1[[#This Row],[Precio Unitario]]*Tabla1[[#This Row],[Cantidad de Insumos]] -> 0

Sheet PPNE3
A1: =+PPNE1!B1 -> Plan Operativo Anual
A2: =+PPNE1!B2 -> Servicio Nacional de Salud
A3: =+PPNE1!B3 -> Dirección de Planificación y Desarrollo
A4: Estimación de Ingresos
A5: =+PPNE1!C5 -> 2026
A6: Servicio Regional de Salud: | E6: =+PPNE1!B6 -> Cibao Norte
A7: CEAS: | E7: =+PPNE1!B7 -> 0
A8: Grupo | B8: Subgrupo | C8: Cuenta | D8: Auxiliar | E8: Descripción Ingresos por Cuenta | F8: Valor RD$ | G8: %
A9: 3 | E9: Donaciones | F9: =+F10 -> 0 | G9: =G10 -> 0
B10: 31 | E10: Donaciones Corrientes | F10: =SUM(F11:F11) -> 0 | G10: =G11 -> 0
C11: 312 | E11: Donaciones corrientes de organismos internacionales | F11: 0 | G11: =IFERROR(F11/$F$31*100,"0.00") -> 0
A12: 4 | E12: Transferencias | F12: =+F13+F19 -> 1650000000 | G12: =G13+G19 -> 94.657767
B13: 41 | E13: Transferencias Corrientes | F13: =SUM(F15:F18) -> 1650000000 | G13: =SUM(G15:G18) -> 94.657767
C14: 413 | E14: Transferencias Corrientes Recibidas de Instituciones Públicas Descentralizas y Autonomas No Financieras | F14: =SUM(F16:F19) -> 1650000000 | G14: =SUM(G16:G19) -> 94.657767
C15: 413 | D15: ´01 | E15: Aportes SNS Nomina | F15: 0 | G15: =IFERROR(F15/$F$31*100,"0.00") -> 0
C16: 413 | D16: ´02 | E16: Anticipos Financieros | F16: 0 | G16: =IFERROR(F16/$F$31*100,"0.00") -> 0
C17: 413 | D17: ´03 | E17: Aportes SNS Medicamentos | F17: 0 | G17: =IFERROR(F17/$F$31*100,"0.00") -> 0
C18: 414 | E18: Transferencias Corrientes Recibidas de Instituciones Públicas de la Seguridad Social | F18: 1650000000 | G18: =IFERROR(F18/$F$31*100,"0.00") -> 94.657767
B19: 42 | E19: Transferencia de Capital | F19: =SUM(F21:F22) -> 0 | G19: =G21+G22 -> 0
C20: 423 | E20: Tranferencia de Capital Recibidas de Instituciones Públicas Descentralizas y Autonomas No Financieras | F20: =+F21+F22 -> 0 | G20: =+G21+G22 -> 0
C21: 423 | D21: ´01 | E21: Aportes SNS Equipamiento | F21: 0 | G21: =IFERROR(F21/$F$31*100,"0.00") -> 0
C22: 423 | D22: ´02 | E22: Aportes para otros gastos de inversión del SNS | F22: 0 | G22: =IFERROR(F22/$F$31*100,"0.00") -> 0
A23: 5 | E23: Ingresos por Contraprestación | F23: =+F24 -> 93121627 | G23: =G24 -> 5.3422335
B24: 51 | E24: Venta de Bienes y Servicios | F24: =F25 -> 93121627 | G24: =G25 -> 5.3422335
C25: 512 | E25: Venta de Servicios del Estado | F25: =F26 -> 93121627 | G25: =G26 -> 5.3422335
C26: 512 | D26: ´99 | E26: Otras ventas de servicios | F26: =+F27+F28+F29+F30 -> 93121627 | G26: =+G27+G28+G29+G30 -> 5.3422335
C27: 513 | E27: Venta de Servicios a SENASA por afiliados regimen subsidiado | F27: 44698381 | G27: =IFERROR(F27/$F$31*100,"0.00") -> 2.5642721
C28: 512 | E28: Venta de Servicios a SENASA por afiliados regimen contributivo | F28: 20486758 | G28: =IFERROR(F28/$F$31*100,"0.00") -> 1.1752914
C29: 512 | E29: Venta de Servicios a otras ARS por atencion a Regimen contributivo | F29: 27936488 | G29: =IFERROR(F29/$F$31*100,"0.00") -> 1.60267
C30: 512 | E30: Venta de Servicios a ARL | F30: 0 | G30: =IFERROR(F30/$F$31*100,"0.00") -> 0
E31: Total Ingresos | F31: =+F23+F12+F9 -> 1.7431216e+09 | G31: =+G23+G12+G9 -> 100

Sheet PPNE4
A1: =+PPNE1!B1 -> Plan Operativo Anual
A2: Servicio Nacional de Salud
A3: Dirección de Planificación y Desarrollo
A4: Consolidado Presupuesto Estimado de Ingresos y Gastos Nivel Especializado por Actividad Especifica
A5: =+PPNE1!C5 -> 2026
A6: Servicio Regional de Salud: | F6: =+PPNE1!B6 -> Cibao Norte
A7: Establecimiento: | F7: =+PPNE1!B7 -> 0
A8: Estimación de Ingresos
A9: Anticipos Financieros | G9: =+PPNE3!F16 -> 0
A10: Venta de Servicios y Otros Ingresos | G10: =+PPNE3!F25 -> 93121627
A11: Aportes SNS Nómina | G11: =+PPNE3!F15 -> 0
A12: Otros Aportes | G12: =+PPNE3!F9+PPNE3!F17+PPNE3!F21+PPNE3!F22 -> 0
A13: Transferencias Corrientes | G13: =+PPNE3!F18 -> 1650000000
A14: Total Ingresos RD$ | G14: =SUM(G9:G13) -> 1.7431216e+09
A15: Estimación de Gastos
A16: Tipo | B16: Objeto | C16: Cuenta | D16: Sub-Cuenta | E16: Auxiliar | F16: Descripción Gasto por Cuenta | G16: Consultas Externa | H16: Emergencias | I16: Hospitalización | J16: Apoyo Diagnóstico | L16: Servicios de Apoyo | N16: Total RD$ | O16: %
J17: Servicios de Laboratorios y Banco de Sangre | K17: Servicios de Imágenes RX | L17: Gestión de Usuario y Educación para la Salud | M17: Gestión Técnica y Administrativa
A18: 2 | F18: Egresos | G18: =+G19+G67+G171+G255+G272+G325 -> 1.7043851e+08 | H18: =+H19+H67+H171+H255+H272+H325 -> 1.653273e+08 | I18: =+I19+I67+I171+I255+I272+I325 -> 6.316076e+08 | J18: =+J19+J67+J171+J255+J272+J325 -> 1.3001682e+08 | K18: =+K19+K67+K171+K255+K272+K325 -> 1.3697676e+08 | L18: =+L19+L67+L171+L255+L272+L325 -> 1.2368163e+08 | M18: =+M19+M67+M171+M255+M272+M325 -> 3.85073e+08 | N18: =+N19+N67+N171+N255+N272+N325 -> 1.7431216e+09 | O18: =IFERROR(N18/$N$18*100,"0.00")/100 -> 1
A19: 2 | B19: 1 | F19: Servicios Personales | G19: =+G20+G42+G54+G58 -> 1.6622686e+08 | H19: =+H20+H42+H54+H58 -> 1.3908833e+08 | I19: =+I20+I42+I54+I58 -> 3.9523521e+08 | J19: =+J20+J42+J54+J58 -> 96211128 | K19: =+K20+K42+K54+K58 -> 1.282815e+08 | L19: =+L20+L42+L54+L58 -> 1.2164178e+08 | M19: =+M20+M42+M54+M58 -> 2.0352553e+08 | N19: =+G19+H19+I19+J19+K19+L19+M19 -> 1.2502103e+09 | O19: =IFERROR(N19/$N$18*100,"0.00")/100 -> 0.71722496
A20: 2 | B20: 1 | C20: 1 | F20: Remuneraciones | G20: =+G21+G26+G33+G35+G37 -> 1.3150267e+08 | H20: =+H21+H26+H33+H35+H37 -> 1.0648276e+08 | I20: =+I21+I26+I33+I35+I37 -> 3.0683956e+08 | J20: =+J21+J26+J33+J35+J37 -> 78901601 | K20: =+K21+K26+K33+K35+K37 -> 1.0520213e+08 | L20: =+L21+L26+L33+L35+L37 -> 96435290 | M20: =+M21+M26+M33+M35+M37 -> 1.9290661e+08 | N20: =+G20+H20+I20+J20+K20+L20+M20 -> 1.0182706e+09 | O20: =IFERROR(N20/$N$18*100,"0.00")/100 -> 0.58416499
A21: 2 | B21: 1 | C21: 1 | D21: 1 | F21: Remuneraciones al personal fijo | G21: =SUM(G22:G25) -> 1.2190495e+08 | H21: =SUM(H22:H25) -> 1.0565095e+08 | I21: =SUM(I22:I25) -> 2.8444487e+08 | J21: =SUM(J22:J25) -> 73142968 | K21: =SUM(K22:K25) -> 97523957 | L21: =SUM(L22:L25) -> 89396960 | M21: =SUM(M22:M25) -> 40634982 | N21: =+G21+H21+I21+J21+K21+L21+M21 -> 8.1269964e+08 | O21: =IFERROR(N21/$N$18*100,"0.00")/100 -> 0.46623232
A22: 2 | B22: 1 | C22: 1 | D22: 1 | E22: `01 | F22: Sueldos fijos | G22: =812699639.34*0.15 -> 1.2190495e+08 | H22: =812699639.34*0.13 -> 1.0565095e+08 | I22: =812699639.34*0.35 -> 2.8444487e+08 | J22: =812699639.34*0.09 -> 73142968 | K22: =812699639.34*0.12 -> 97523957 | L22: =812699639.34*0.11 -> 89396960 | M22: 40634982 | N22: =+G22+H22+I22+J22+K22+L22+M22 -> 8.1269964e+08 | O22: =IFERROR(N22/$N$18*100,"0.00")/100 -> 0.46623232
A23: 2 | B23: 1 | C23: 1 | D23: 1 | E23: `02 | F23: Sueldos a medicos | N23: =+G23+H23+I23+J23+K23+L23+M23 -> 0 | O23: =IFERROR(N23/$N$18*100,"0.00")/100 -> 0
A24: 2 | B24: 1 | C24: 1 | D24: 1 | E24: `05 | F24: Incentivos y escalafón | N24: =+G24+H24+I24+J24+K24+L24+M24 -> 0 | O24: =IFERROR(N24/$N$18*100,"0.00")/100 -> 0
A25: 2 | B25: 1 | C25: 1 | D25: 1 | E25: `06 | F25: Nuevas plazas a medicos | N25: =+G25+H25+I25+J25+K25+L25+M25 -> 0 | O25: =IFERROR(N25/$N$18*100,"0.00")/100 -> 0
A26: 2 | B26: 1 | C26: 1 | D26: 2 | F26: Remuneraciones al personal con carácter transitorio | G26: =SUM(G27:G32) -> 0 | H26: =SUM(H27:H32) -> 0 | I26: =SUM(I27:I32) -> 0 | J26: =SUM(J27:J32) -> 0 | K26: =SUM(K27:K32) -> 0 | L26: =SUM(L27:L32) -> 0 | M26: =SUM(M27:M32) -> 1.4007194e+08 | N26: =+G26+H26+I26+J26+K26+L26+M26 -> 1.4007194e+08 | O26: =IFERROR(N26/$N$18*100,"0.00")/100 -> 0.08035695
A27: 2 | B27: 1 | C27: 1 | D27: 2 | E27: `03 | F27: Suplencias | N27: =+G27+H27+I27+J27+K27+L27+M27 -> 0 | O27: =IFERROR(N27/$N$18*100,"0.00")/100 -> 0
A28: 2 | B28: 1 | C28: 1 | D28: 2 | E28: `05 | F28: Sueldo al personal nominal en período probatorio | N28: =+G28+H28+I28+J28+K28+L28+M28 -> 0 | O28: =IFERROR(N28/$N$18*100,"0.00")/100 -> 0
A29: 2 | B29: 1 | C29: 1 | D29: 2 | E29: `06 | F29: Jornales | N29: =+G29+H29+I29+J29+K29+L29+M29 -> 0 | O29: =IFERROR(N29/$N$18*100,"0.00")/100 -> 0
A30: 2 | B30: 1 | C30: 1 | D30: 2 | E30: `08 | F30: Empleados temporales | M30: 1.4007194e+08 | N30: =+G30+H30+I30+J30+K30+L30+M30 -> 1.4007194e+08 | O30: =IFERROR(N30/$N$18*100,"0.00")/100 -> 0.08035695
A31: 2 | B31: 1 | C31: 1 | D31: 2 | E31: `09 | F31: Personal de carácter eventual | N31: =+G31+H31+I31+J31+K31+L31+M31 -> 0 | O31: =IFERROR(N31/$N$18*100,"0.00")/100 -> 0
A32: 2 | B32: 1 | C32: 1 | D32: 2 | E32: `11 | F32: Interinato | N32: =+G32+H32+I32+J32+K32+L32+M32 -> 0 | O32: =IFERROR(N32/$N$18*100,"0.00")/100 -> 0
A33: 2 | B33: 1 | C33: 1 | D33: 3 | F33: Sueldos al personal fijo en trámite de pensiones | G33: =G34 -> 0 | H33: =H34 -> 0 | I33: =I34 -> 0 | J33: =J34 -> 0 | K33: =K34 -> 0 | L33: =L34 -> 0 | M33: =M34 -> 0 | N33: =+G33+H33+I33+J33+K33+L33+M33 -> 0 | O33: =IFERROR(N33/$N$18*100,"0.00")/100 -> 0
A34: 2 | B34: 1 | C34: 1 | D34: 3 | E34: `01 | F34: Sueldos al personal fijo en trámite de pensiones | N34: =+G34+H34+I34+J34+K34+L34+M34 -> 0 | O34: =IFERROR(N34/$N$18*100,"0.00")/100 -> 0
A35: 2 | B35: 1 | C35: 1 | D35: 4 | F35: Sueldo anual No. 13 | G35: =G36 -> 9597721.9 | H35: =H36 -> 831802.62 | I35: =I36 -> 22394684 | J35: =J36 -> 5758633.1 | K35: =K36 -> 7678177.5 | L35: =L36 -> 7038329.4 | M35: =M36 -> 10685464 | N35: =+G35+H35+I35+J35+K35+L35+M35 -> 63984813 | O35: =IFERROR(N35/$N$18*100,"0.00")/100 -> 0.036707027
A36: 2 | B36: 1 | C36: 1 | D36: 4 | E36: `01 | F36: Sueldo anual No. 13 | G36: =63984812.73*0.15 -> 9597721.9 | H36: =6398481.73*0.13 -> 831802.62 | I36: =63984812.73*0.35 -> 22394684 | J36: =63984812.73*0.09 -> 5758633.1 | K36: =63984812.73*0.12 -> 7678177.5 | L36: =63984812.73*0.11 -> 7038329.4 | M36: 10685464 | N36: =+G36+H36+I36+J36+K36+L36+M36 -> 63984813 | O36: =IFERROR(N36/$N$18*100,"0.00")/100 -> 0.036707027
A37: 2 | B37: 1 | C37: 1 | D37: 5 | F37: Prestacianes economicas | G37: =SUM(G38:G41) -> 0 | H37: =SUM(H38:H41) -> 0 | I37: =SUM(I38:I41) -> 0 | J37: =SUM(J38:J41) -> 0 | K37: =SUM(K38:K41) -> 0 | L37: =SUM(L38:L41) -> 0 | M37: =SUM(M38:M41) -> 1514231.2 | N37: =+G37+H37+I37+J37+K37+L37+M37 -> 1514231.2 | O37: =IFERROR(N37/$N$18*100,"0.00")/100 -> 0.00086868937
A38: 2 | B38: 1 | C38: 1 | D38: 5 | E38: `01 | F38: Prestacianes economicas | N38: =+G38+H38+I38+J38+K38+L38+M38 -> 0 | O38: =IFERROR(N38/$N$18*100,"0.00")/100 -> 0
A39: 2 | B39: 1 | C39: 1 | D39: 5 | E39: `02 | F39: Pago de porcentaje por desvinculación de cargo | N39: =+G39+H39+I39+J39+K39+L39+M39 -> 0 | O39: =IFERROR(N39/$N$18*100,"0.00")/100 -> 0
A40: 2 | B40: 1 | C40: 1 | D40: 5 | E40: `03 | F40: Prestacion laboral por desvinculación | M40: 907400 | N40: =+G40+H40+I40+J40+K40+L40+M40 -> 907400 | O40: =IFERROR(N40/$N$18*100,"0.00")/100 -> 0.00052056035
A41: 2 | B41: 1 | C41: 1 | D41: 5 | E41: `04 | F41: Proporción de vacaciones no disfrutadas | M41: 606831.23 | N41: =+G41+H41+I41+J41+K41+L41+M41 -> 606831.23 | O41: =IFERROR(N41/$N$18*100,"0.00")/100 -> 0.00034812902
A42: 2 | B42: 1 | C42: 2 | F42: Sobresueldos | G42: =+G43+G45 -> 17700607 | H42: =+H43+H45 -> 17851794 | I42: =+I43+I45 -> 48673945 | J42: =+J43+J45 -> 7095374.5 | K42: =+K43+K45 -> 9460499.3 | L42: =+L43+L45 -> 12722523 | M42: =+M43+M45 -> 4944380.7 | N42: =+G42+H42+I42+J42+K42+L42+M42 -> 1.1844912e+08 | O42: =IFERROR(N42/$N$18*100,"0.00")/100 -> 0.0679523
A43: 2 | B43: 1 | C43: 2 | D43: 1 | F43: Primas por antigüedad | G43: =G44 -> 5874983.2 | H43: =H44 -> 7602919.5 | I43: =I44 -> 21080822 | J43: =J44 -> 0 | K43: =K44 -> 0 | L43: =L44 -> 0 | M43: =M44 -> 0 | N43: =+G43+H43+I43+J43+K43+L43+M43 -> 34558725 | O43: =IFERROR(N43/$N$18*100,"0.00")/100 -> 0.019825768
A44: 2 | B44: 1 | C44: 2 | D44: 1 | E44: `01 | F44: Primas por antigüedad | G44: =34558724.88*0.17 -> 5874983.2 | H44: =34558724.88*0.22 -> 7602919.5 | I44: 21080822 | N44: =+G44+H44+I44+J44+K44+L44+M44 -> 34558725 | O44: =IFERROR(N44/$N$18*100,"0.00")/100 -> 0.019825768
A45: 2 | B45: 1 | C45: 2 | D45: 2 | F45: Compensación | G45: =SUM(G46:G53) -> 11825624 | H45: =SUM(H46:H53) -> 10248874 | I45: =SUM(I46:I53) -> 27593123 | J45: =SUM(J46:J53) -> 7095374.5 | K45: =SUM(K46:K53) -> 9460499.3 | L45: =SUM(L46:L53) -> 12722523 | M45: =SUM(M46:M53) -> 4944380.7 | N45: =+G45+H45+I45+J45+K45+L45+M45 -> 83890399 | O45: =IFERROR(N45/$N$18*100,"0.00")/100 -> 0.048126532
A46: 2 | B46: 1 | C46: 2 | D46: 2 | E46: `03 | F46: Pago de horas extraordinarias, Horas extraordinarias fin de año (Reglamento 523-09) | N46: =+G46+H46+I46+J46+K46+L46+M46 -> 0 | O46: =IFERROR(N46/$N$18*100,"0.00")/100 -> 0
A47: 2 | B47: 1 | C47: 2 | D47: 2 | E47: `04 | F47: Prima de transporte | N47: =+G47+H47+I47+J47+K47+L47+M47 -> 0 | O47: =IFERROR(N47/$N$18*100,"0.00")/100 -> 0
A48: 2 | B48: 1 | C48: 2 | D48: 2 | E48: `05 | F48: Compensación servicios de Seguridad | M48: 540000 | N48: =+G48+H48+I48+J48+K48+L48+M48 -> 540000 | O48: =IFERROR(N48/$N$18*100,"0.00")/100 -> 0.00030978905
A49: 2 | B49: 1 | C49: 2 | D49: 2 | E49: `06 | F49: Incentivo por rendimiento individual | G49: =9283645*0.15 -> 1392546.8 | H49: =9283645*0.13 -> 1206873.9 | I49: =9283645*0.35 -> 3249275.8 | J49: =9283645*0.09 -> 835528.05 | K49: =9283645*0.12 -> 1114037.4 | L49: =9283645*0.11 -> 1021200.9 | M49: 464182.25 | N49: =+G49+H49+I49+J49+K49+L49+M49 -> 9283645 | O49: =IFERROR(N49/$N$18*100,"0.00")/100 -> 0.0053258733
A50: 2 | B50: 1 | C50: 2 | D50: 2 | E50: `07 | F50: Compensación por distancia | N50: =+G50+H50+I50+J50+K50+L50+M50 -> 0 | O50: =IFERROR(N50/$N$18*100,"0.00")/100 -> 0
A51: 2 | B51: 1 | C51: 2 | D51: 2 | E51: `08 | F51: Compensaciones especiales | L51: 4050399 | N51: =+G51+H51+I51+J51+K51+L51+M51 -> 4050399 | O51: =IFERROR(N51/$N$18*100,"0.00")/100 -> 0.0023236468
A52: 2 | B52: 1 | C52: 2 | D52: 2 | E52: `09 | F52: Bono por desempeño | M52: 462506 | N52: =+G52+H52+I52+J52+K52+L52+M52 -> 462506 | O52: =IFERROR(N52/$N$18*100,"0.00")/100 -> 0.00026533203
A53: 2 | B53: 1 | C53: 2 | D53: 2 | E53: `10 | F53: Compensación por cumplimiento de indicadores | G53: =69553848.94*0.15 -> 10433077 | H53: =69553848.94*0.13 -> 9042000.4 | I53: =69553848.94*0.35 -> 24343847 | J53: =69553848.94*0.09 -> 6259846.4 | K53: =69553848.94*0.12 -> 8346461.9 | L53: =69553848.94*0.11 -> 7650923.4 | M53: 3477692.5 | N53: =+G53+H53+I53+J53+K53+L53+M53 -> 69553849 | O53: =IFERROR(N53/$N$18*100,"0.00")/100 -> 0.039901891
A54: 2 | B54: 1 | C54: 3 | F54: Dietas y Gastos de Representación | G54: =+G55 -> 0 | H54: =+H55 -> 0 | I54: =+I55 -> 0 | J54: =+J55 -> 0 | K54: =+K55 -> 0 | L54: =+L55 -> 0 | M54: =+M55 -> 0 | N54: =+G54+H54+I54+J54+K54+L54+M54 -> 0 | O54: =IFERROR(N54/$N$18*100,"0.00")/100 -> 0
A55: 2 | B55: 1 | C55: 3 | D55: 2 | F55: Gastos de representación | G55: =SUM(G56:G57) -> 0 | H55: =SUM(H56:H57) -> 0 | I55: =SUM(I56:I57) -> 0 | J55: =SUM(J56:J57) -> 0 | K55: =SUM(K56:K57) -> 0 | L55: =SUM(L56:L57) -> 0 | M55: =SUM(M56:M57) -> 0 | N55: =+G55+H55+I55+J55+K55+L55+M55 -> 0 | O55: =IFERROR(N55/$N$18*100,"0.00")/100 -> 0
A56: 2 | B56: 1 | C56: 3 | D56: 2 | E56: `01 | F56: Gastos de representación en el país | N56: =+G56+H56+I56+J56+K56+L56+M56 -> 0 | O56: =IFERROR(N56/$N$18*100,"0.00")/100 -> 0
A57: 2 | B57: 1 | C57: 3 | D57: 2 | E57: `02 | F57: Gastos de representación en el exterior | N57: =+G57+H57+I57+J57+K57+L57+M57 -> 0 | O57: =IFERROR(N57/$N$18*100,"0.00")/100 -> 0
A58: 2 | B58: 1 | C58: 5 | F58: Contribuciones a la Seguridad Social y Riesgo Laboral | G58: =G59+G61+G63+G65 -> 17023589 | H58: =H59+H61+H63+H65 -> 14753777 | I58: =I59+I61+I63+I65 -> 39721707 | J58: =J59+J61+J63+J65 -> 10214153 | K58: =K59+K61+K63+K65 -> 13618871 | L58: =L59+L61+L63+L65 -> 12483965 | M58: =M59+M61+M63+M65 -> 5674529.6 | N58: =+G58+H58+I58+J58+K58+L58+M58 -> 1.1349059e+08 | O58: =IFERROR(N58/$N$18*100,"0.00")/100 -> 0.065107672
A59: 2 | B59: 1 | C59: 5 | D59: 1 | F59: Contribuciones al seguro de salud | G59: =G60 -> 7849108.6 | H59: =H60 -> 6802560.7 | I59: =I60 -> 18314587 | J59: =J60 -> 4709465.1 | K59: =K60 -> 6279286.8 | L59: =L60 -> 5756012.9 | M59: =M60 -> 2616369.5 | N59: =+G59+H59+I59+J59+K59+L59+M59 -> 52327390 | O59: =IFERROR(N59/$N$18*100,"0.00")/100 -> 0.030019357
A60: 2 | B60: 1 | C60: 5 | D60: 1 | E60: `01 | F60: Contribuciones al seguro de salud | G60: =52327390.36*0.15 -> 7849108.6 | H60: =52327390.36*0.13 -> 6802560.7 | I60: =52327390.36*0.35 -> 18314587 | J60: =52327390.36*0.09 -> 4709465.1 | K60: =52327390.36*0.12 -> 6279286.8 | L60: =52327390.36*0.11 -> 5756012.9 | M60: 2616369.5 | N60: =+G60+H60+I60+J60+K60+L60+M60 -> 52327390 | O60: =IFERROR(N60/$N$18*100,"0.00")/100 -> 0.030019357
A61: 2 | B61: 1 | C61: 5 | D61: 2 | F61: Contribuciones al seguro de pensiones | G61: =G62 -> 7849108.6 | H61: =H62 -> 6802560.7 | I61: =I62 -> 18314587 | J61: =J62 -> 4709465.1 | K61: =K62 -> 6279286.8 | L61: =L62 -> 5756012.9 | M61: =M62 -> 2616369.5 | N61: =+G61+H61+I61+J61+K61+L61+M61 -> 52327390 | O61: =IFERROR(N61/$N$18*100,"0.00")/100 -> 0.030019357
A62: 2 | B62: 1 | C62: 5 | D62: 2 | E62: `01 | F62: Contribuciones al seguro de pensiones | G62: =52327390.36*0.15 -> 7849108.6 | H62: =52327390.36*0.13 -> 6802560.7 | I62: =52327390.36*0.35 -> 18314587 | J62: =52327390.36*0.09 -> 4709465.1 | K62: =52327390.36*0.12 -> 6279286.8 | L62: =52327390.36*0.11 -> 5756012.9 | M62: 2616369.5 | N62: =+G62+H62+I62+J62+K62+L62+M62 -> 52327390 | O62: =IFERROR(N62/$N$18*100,"0.00")/100 -> 0.030019357
A63: 2 | B63: 1 | C63: 5 | D63: 3 | F63: Contribuciones al seguro de riesgo laboral | G63: =G64 -> 1325371.6 | H63: =H64 -> 1148655.4 | I63: =I64 -> 3092533.7 | J63: =J64 -> 795222.96 | K63: =K64 -> 1060297.3 | L63: =L64 -> 971939.18 | M63: =M64 -> 441790.53 | N63: =+G63+H63+I63+J63+K63+L63+M63 -> 8835810.7 | O63: =IFERROR(N63/$N$18*100,"0.00")/100 -> 0.0050689582
A64: 2 | B64: 1 | C64: 5 | D64: 3 | E64: `01 | F64: Contribuciones al seguro de riesgo laboral | G64: =8835810.69*0.15 -> 1325371.6 | H64: =8835810.69*0.13 -> 1148655.4 | I64: =8835810.69*0.35 -> 3092533.7 | J64: =8835810.69*0.09 -> 795222.96 | K64: =8835810.69*0.12 -> 1060297.3 | L64: =8835810.69*0.11 -> 971939.18 | M64: 441790.53 | N64: =+G64+H64+I64+J64+K64+L64+M64 -> 8835810.7 | O64: =IFERROR(N64/$N$18*100,"0.00")/100 -> 0.0050689582
A65: 2 | B65: 1 | C65: 5 | D65: 4 | F65: Contribuciones al plan de retiro complementario | G65: =G66 -> 0 | H65: =H66 -> 0 | I65: =I66 -> 0 | J65: =J66 -> 0 | K65: =K66 -> 0 | L65: =L66 -> 0 | M65: =M66 -> 0 | N65: =+G65+H65+I65+J65+K65+L65+M65 -> 0 | O65: =IFERROR(N65/$N$18*100,"0.00")/100 -> 0
A66: 2 | B66: 1 | C66: 5 | D66: 4 | E66: `01 | F66: Contribuciones al plan de retiro complementario | N66: =+G66+H66+I66+J66+K66+L66+M66 -> 0 | O66: =IFERROR(N66/$N$18*100,"0.00")/100 -> 0
A67: 2 | B67: 2 | F67: Contratacion de servicios | G67: =+G68+G82+G87+G92+G99+G116+G125+G143 -> 0 | H67: =+H68+H82+H87+H92+H99+H116+H125+H143 -> 0 | I67: =+I68+I82+I87+I92+I99+I116+I125+I143 -> 0 | J67: =+J68+J82+J87+J92+J99+J116+J125+J143 -> 0 | K67: =+K68+K82+K87+K92+K99+K116+K125+K143 -> 0 | L67: =+L68+L82+L87+L92+L99+L116+L125+L143 -> 0 | M67: =+M68+M82+M87+M92+M99+M116+M125+M143 -> 72682712 | N67: =+G67+H67+I67+J67+K67+L67+M67 -> 72682712 | O67: =IFERROR(N67/$N$18*100,"0.00")/100 -> 0.041696868
A68: 2 | B68: 2 | C68: 1 | F68: Servicios Básicos | G68: =+G69+G71+G73+G75+G78+G80 -> 0 | H68: =+H69+H71+H73+H75+H78+H80 -> 0 | I68: =+I69+I71+I73+I75+I78+I80 -> 0 | J68: =+J69+J71+J73+J75+J78+J80 -> 0 | K68: =+K69+K71+K73+K75+K78+K80 -> 0 | L68: =+L69+L71+L73+L75+L78+L80 -> 0 | M68: =+M71+M78+M80 -> 3804000 | N68: =+G68+H68+I68+J68+K68+L68+M68 -> 3804000 | O68: =IFERROR(N68/$N$18*100,"0.00")/100 -> 0.0021822918
A69: 2 | B69: 2 | C69: 1 | D69: 2 | F69: Servicios telefónico de larga distancia | G69: =G70 -> 0 | H69: =H70 -> 0 | I69: =I70 -> 0 | J69: =J70 -> 0 | K69: =K70 -> 0 | L69: =L70 -> 0 | M69: =M70 -> 0 | N69: =+G69+H69+I69+J69+K69+L69+M69 -> 0 | O69: =IFERROR(N69/$N$18*100,"0.00")/100 -> 0
A70: 2 | B70: 2 | C70: 1 | D70: 2 | E70: `01 | F70: Servicios telefónico de larga distancia | N70: =+G70+H70+I70+J70+K70+L70+M70 -> 0 | O70: =IFERROR(N70/$N$18*100,"0.00")/100 -> 0
A71: 2 | B71: 2 | C71: 1 | D71: 3 | F71: Teléfono local | G71: =G72 -> 0 | H71: =H72 -> 0 | I71: =I72 -> 0 | J71: =J72 -> 0 | K71: =K72 -> 0 | L71: =L72 -> 0 | M71: =M72 -> 2724000 | N71: =+G71+H71+I71+J71+K71+L71+M71 -> 2724000 | O71: =IFERROR(N71/$N$18*100,"0.00")/100 -> 0.0015627137
A72: 2 | B72: 2 | C72: 1 | D72: 3 | E72: `01 | F72: Teléfono local | M72: 2724000 | N72: =+G72+H72+I72+J72+K72+L72+M72 -> 2724000 | O72: =IFERROR(N72/$N$18*100,"0.00")/100 -> 0.0015627137
A73: 2 | B73: 2 | C73: 1 | D73: 5 | F73: Servicio de internet y televisión por cable | G73: =G74 -> 0 | H73: =H74 -> 0 | I73: =I74 -> 0 | J73: =J74 -> 0 | K73: =K74 -> 0 | L73: =L74 -> 0 | M73: =M74 -> 0 | N73: =+G73+H73+I73+J73+K73+L73+M73 -> 0 | O73: =IFERROR(N73/$N$18*100,"0.00")/100 -> 0
A74: 2 | B74: 2 | C74: 1 | D74: 5 | E74: `01 | F74: Servicio de internet y televisión por cable | N74: =+G74+H74+I74+J74+K74+L74+M74 -> 0 | O74: =IFERROR(N74/$N$18*100,"0.00")/100 -> 0
A75: 2 | B75: 2 | C75: 1 | D75: 6 | F75: Electricidad | G75: =G76+G77 -> 0 | H75: =H76+H77 -> 0 | I75: =I76+I77 -> 0 | J75: =J76+J77 -> 0 | K75: =K76+K77 -> 0 | L75: =L76+L77 -> 0 | M75: =M76+M77 -> 0 | N75: =+G75+H75+I75+J75+K75+L75+M75 -> 0 | O75: =IFERROR(N75/$N$18*100,"0.00")/100 -> 0
A76: 2 | B76: 2 | C76: 1 | D76: 6 | E76: `01 | F76: Energía eléctrica | N76: =+G76+H76+I76+J76+K76+L76+M76 -> 0 | O76: =IFERROR(N76/$N$18*100,"0.00")/100 -> 0
A77: 2 | B77: 2 | C77: 1 | D77: 6 | E77: `02 | F77: Electricidad no cortable | N77: =+G77+H77+I77+J77+K77+L77+M77 -> 0 | O77: =IFERROR(N77/$N$18*100,"0.00")/100 -> 0
A78: 2 | B78: 2 | C78: 1 | D78: 7 | F78: Agua | G78: =G79 -> 0 | H78: =H79 -> 0 | I78: =I79 -> 0 | J78: =J79 -> 0 | K78: =K79 -> 0 | L78: =L79 -> 0 | M78: =M79 -> 780000 | N78: =+G78+H78+I78+J78+K78+L78+M78 -> 780000 | O78: =IFERROR(N78/$N$18*100,"0.00")/100 -> 0.00044747308
A79: 2 | B79: 2 | C79: 1 | D79: 7 | E79: `01 | F79: Agua | M79: 780000 | N79: =+G79+H79+I79+J79+K79+L79+M79 -> 780000 | O79: =IFERROR(N79/$N$18*100,"0.00")/100 -> 0.00044747308
A80: 2 | B80: 2 | C80: 1 | D80: 8 | F80: Recolección de residuos sólidos | G80: =G81 -> 0 | H80: =H81 -> 0 | I80: =I81 -> 0 | J80: =J81 -> 0 | K80: =K81 -> 0 | L80: =L81 -> 0 | M80: =M81 -> 300000 | N80: =+G80+H80+I80+J80+K80+L80+M80 -> 300000 | O80: =IFERROR(N80/$N$18*100,"0.00")/100 -> 0.00017210503
A81: 2 | B81: 2 | C81: 1 | D81: 8 | E81: `01 | F81: Recolección de residuos sólidos | M81: 300000 | N81: =+G81+H81+I81+J81+K81+L81+M81 -> 300000 | O81: =IFERROR(N81/$N$18*100,"0.00")/100 -> 0.00017210503
A82: 2 | B82: 2 | C82: 2 | F82: Publicidad Impresión y Encuadernación | G82: =+G83+G85 -> 0 | H82: =+H83+H85 -> 0 | I82: =+I83+I85 -> 0 | J82: =+J83+J85 -> 0 | K82: =+K83+K85 -> 0 | L82: =+L83+L85 -> 0 | M82: =+M83+M85 -> 0 | N82: =+G82+H82+I82+J82+K82+L82+M82 -> 0 | O82: =IFERROR(N82/$N$18*100,"0.00")/100 -> 0
A83: 2 | B83: 2 | C83: 2 | D83: 1 | F83: Publicidad y propaganda | G83: =G84 -> 0 | H83: =H84 -> 0 | I83: =I84 -> 0 | J83: =J84 -> 0 | K83: =K84 -> 0 | L83: =L84 -> 0 | M83: =M84 -> 0 | N83: =+G83+H83+I83+J83+K83+L83+M83 -> 0 | O83: =IFERROR(N83/$N$18*100,"0.00")/100 -> 0
A84: 2 | B84: 2 | C84: 2 | D84: 1 | E84: `01 | F84: Publicidad y propaganda | N84: =+G84+H84+I84+J84+K84+L84+M84 -> 0 | O84: =IFERROR(N84/$N$18*100,"0.00")/100 -> 0
A85: 2 | B85: 2 | C85: 2 | D85: 2 | F85: Impresión y encuadernación | G85: =G86 -> 0 | H85: =H86 -> 0 | I85: =I86 -> 0 | J85: =J86 -> 0 | K85: =K86 -> 0 | L85: =L86 -> 0 | M85: =M86 -> 0 | N85: =+G85+H85+I85+J85+K85+L85+M85 -> 0 | O85: =IFERROR(N85/$N$18*100,"0.00")/100 -> 0
A86: 2 | B86: 2 | C86: 2 | D86: 2 | E86: `01 | F86: Impresión y encuadernación | N86: =+G86+H86+I86+J86+K86+L86+M86 -> 0 | O86: =IFERROR(N86/$N$18*100,"0.00")/100 -> 0
A87: 2 | B87: 2 | C87: 3 | F87: Viáticos | G87: =+G88+G90 -> 0 | H87: =+H88+H90 -> 0 | I87: =+I88+I90 -> 0 | J87: =+J88+J90 -> 0 | K87: =+K88+K90 -> 0 | L87: =+L88+L90 -> 0 | M87: =+M88+M90 -> 0 | N87: =+G87+H87+I87+J87+K87+L87+M87 -> 0 | O87: =IFERROR(N87/$N$18*100,"0.00")/100 -> 0
A88: 2 | B88: 2 | C88: 3 | D88: 1 | F88: Viáticos dentro del país | G88: =G89 -> 0 | H88: =H89 -> 0 | I88: =I89 -> 0 | J88: =J89 -> 0 | K88: =K89 -> 0 | L88: =L89 -> 0 | M88: =M89 -> 0 | N88: =+G88+H88+I88+J88+K88+L88+M88 -> 0 | O88: =IFERROR(N88/$N$18*100,"0.00")/100 -> 0
A89: 2 | B89: 2 | C89: 3 | D89: 1 | E89: `01 | F89: Viáticos dentro del país | N89: =+G89+H89+I89+J89+K89+L89+M89 -> 0 | O89: =IFERROR(N89/$N$18*100,"0.00")/100 -> 0
A90: 2 | B90: 2 | C90: 3 | D90: 2 | F90: Viáticos fuera del país | G90: =G91 -> 0 | H90: =H91 -> 0 | I90: =I91 -> 0 | J90: =J91 -> 0 | K90: =K91 -> 0 | L90: =L91 -> 0 | M90: =M91 -> 0 | N90: =+G90+H90+I90+J90+K90+L90+M90 -> 0 | O90: =IFERROR(N90/$N$18*100,"0.00")/100 -> 0
A91: 2 | B91: 2 | C91: 3 | D91: 2 | E91: `01 | F91: Viáticos fuera del país | N91: =+G91+H91+I91+J91+K91+L91+M91 -> 0 | O91: =IFERROR(N91/$N$18*100,"0.00")/100 -> 0
A92: 2 | B92: 2 | C92: 4 | F92: Transporte y Alamcenaje | G92: =+G93+G95+G97 -> 0 | H92: =+H93+H95+H97 -> 0 | I92: =+I93+I95+I97 -> 0 | J92: =+J93+J95+J97 -> 0 | K92: =+K93+K95+K97 -> 0 | L92: =+L93+L95+L97 -> 0 | M92: =+M93+M95+M97 -> 708803.54 | N92: =+G92+H92+I92+J92+K92+L92+M92 -> 708803.54 | O92: =IFERROR(N92/$N$18*100,"0.00")/100 -> 0.00040662885
A93: 2 | B93: 2 | C93: 4 | D93: 1 | F93: Pasajes y gastos de transporte | G93: =G94 -> 0 | H93: =H94 -> 0 | I93: =I94 -> 0 | J93: =J94 -> 0 | K93: =K94 -> 0 | L93: =L94 -> 0 | M93: =M94 -> 0 | N93: =+G93+H93+I93+J93+K93+L93+M93 -> 0 | O93: =IFERROR(N93/$N$18*100,"0.00")/100 -> 0
A94: 2 | B94: 2 | C94: 4 | D94: 1 | E94: `01 | F94: Pasajes y gastos de transporte | N94: =+G94+H94+I94+J94+K94+L94+M94 -> 0 | O94: =IFERROR(N94/$N$18*100,"0.00")/100 -> 0
A95: 2 | B95: 2 | C95: 4 | D95: 2 | F95: Fletes | G95: =G96 -> 0 | H95: =H96 -> 0 | I95: =I96 -> 0 | J95: =J96 -> 0 | K95: =K96 -> 0 | L95: =L96 -> 0 | M95: =M96 -> 708803.54 | N95: =+G95+H95+I95+J95+K95+L95+M95 -> 708803.54 | O95: =IFERROR(N95/$N$18*100,"0.00")/100 -> 0.00040662885
A96: 2 | B96: 2 | C96: 4 | D96: 2 | E96: `01 | F96: Fletes | M96: 708803.54 | N96: =+G96+H96+I96+J96+K96+L96+M96 -> 708803.54 | O96: =IFERROR(N96/$N$18*100,"0.00")/100 -> 0.00040662885
A97: 2 | B97: 2 | C97: 4 | D97: 4 | F97: Peaje | G97: =G98 -> 0 | H97: =H98 -> 0 | I97: =I98 -> 0 | J97: =J98 -> 0 | K97: =K98 -> 0 | L97: =L98 -> 0 | M97: =M98 -> 0 | N97: =+G97+H97+I97+J97+K97+L97+M97 -> 0 | O97: =IFERROR(N97/$N$18*100,"0.00")/100 -> 0
A98: 2 | B98: 2 | C98: 4 | D98: 4 | E98: `01 | F98: Peaje | N98: =+G98+H98+I98+J98+K98+L98+M98 -> 0 | O98: =IFERROR(N98/$N$18*100,"0.00")/100 -> 0
A99: 2 | B99: 2 | C99: 5 | F99: Alquileres y Rentas | G99: =+G100+G102+G104+G110+G112+G114 -> 0 | H99: =+H100+H102+H104+H110+H112+H114 -> 0 | I99: =+I100+I102+I104+I110+I112+I114 -> 0 | J99: =+J100+J102+J104+J110+J112+J114 -> 0 | K99: =+K100+K102+K104+K110+K112+K114 -> 0 | L99: =+L100+L102+L104+L110+L112+L114 -> 0 | M99: =+M100+M102+M104+M110+M112+M114 -> 4200000 | N99: =+G99+H99+I99+J99+K99+L99+M99 -> 4200000 | O99: =IFERROR(N99/$N$18*100,"0.00")/100 -> 0.0024094704
A100: 2 | B100: 2 | C100: 5 | D100: 1 | F100: Alquilleres y rentas de edificios y locales | G100: =G101 -> 0 | H100: =H101 -> 0 | I100: =I101 -> 0 | J100: =J101 -> 0 | K100: =K101 -> 0 | L100: =L101 -> 0 | M100: =M101 -> 0 | N100: =+G100+H100+I100+J100+K100+L100+M100 -> 0 | O100: =IFERROR(N100/$N$18*100,"0.00")/100 -> 0
...

Sheet PPNE5
A1: =+PPNE1!B1 -> Plan Operativo Anual
A2: Servicio Nacional de Salud
A3: Dirección de Planificación y Desarrollo
A4: Consolidado Presupuesto Estimado de Ingresos y Gastos Nivel Especializado por Fuente de Financiamiento
A5: =+PPNE1!C5 -> 2026
A6: Servicio Regional de Salud: | F6: =+PPNE1!B6 -> Cibao Norte
A7: Establecimiento: | F7: =+PPNE1!B7 -> 0
A8: Estimación de Ingresos
A9: Anticipos Financieros | G9: =+PPNE3!F16 -> 0
A10: Venta de Servicios y Otros Ingresos | G10: =+PPNE3!F25 -> 93121627
A11: Aportes SNS Nómina | G11: =+PPNE3!F15 -> 0
A12: Otros Aportes | G12: =+PPNE3!F9+PPNE3!F17+PPNE3!F21+PPNE3!F22 -> 0
A13: Transferencias Corrientes | G13: =+PPNE3!F18 -> 1650000000
A14: Total Ingresos RD$ | G14: =SUM(G9:G13) -> 1.7431216e+09
A15: Estimación de Gastos
A16: Tipo | B16: Objeto | C16: Cuenta | D16: Sub-Cuenta | E16: Auxiliar | F16: Descripción Gasto por Cuenta | G16: Anticipos Financieros / Transferencias | H16: Venta de Servicios | I16: Nómina | J16: Total RD$ | K16: %
A18: 2 | F18: Egresos | G18: =+G19+G67+G170+G254+G270 -> 1.65e+09 | H18: =+H19+H67+H170+H254+H270+H323 -> 93121627 | I18: =+I19+I67+I170+I254+I270+I323 -> 0 | J18: =+J19+J67+J170+J254+J270 -> 1.7431216e+09 | K18: =IFERROR(J18/$J$18*100,"0.00")/100 -> 1
A19: 2 | B19: 1 | F19: Servicios Personales | G19: =+G20+G42+G54+G58 -> 1.2502103e+09 | H19: =+H20+H42+H54+H58 -> 0 | I19: =+I20+I47+I63+I70+I78 -> 0 | J19: =+G19+H19 -> 1.2502103e+09 | K19: =IFERROR(J19/$J$18*100,"0.00")/100 -> 0.71722496
A20: 2 | B20: 1 | C20: 1 | F20: Remuneraciones | G20: =+G21+G26+G33+G35+G37 -> 1.0182706e+09 | H20: =+H21+H28+H36+H38+H40+H45 -> 0 | I20: =+I21+I28+I36+I38+I40+I45 -> 0 | J20: =+G20+H20 -> 1.0182706e+09 | K20: =IFERROR(J20/$J$18*100,"0.00")/100 -> 0.58416499
A21: 2 | B21: 1 | C21: 1 | D21: 1 | F21: Remuneraciones al personal fijo | G21: =SUM(G22:G25) -> 8.1269964e+08 | H21: =SUM(H22:H27) -> 0 | I21: =SUM(I22:I27) -> 0 | J21: =+G21+H21 -> 8.1269964e+08 | K21: =IFERROR(J21/$J$18*100,"0.00")/100 -> 0.46623232
A22: 2 | B22: 1 | C22: 1 | D22: 1 | E22: `01 | F22: Sueldos fijos | G22: 8.1269964e+08 | J22: =+G22+H22 -> 8.1269964e+08 | K22: =IFERROR(J22/$J$18*100,"0.00")/100 -> 0.46623232
A23: 2 | B23: 1 | C23: 1 | D23: 1 | E23: `02 | F23: Sueldos a medicos | J23: =+G23+H23 -> 0 | K23: =IFERROR(J23/$J$18*100,"0.00")/100 -> 0
A24: 2 | B24: 1 | C24: 1 | D24: 1 | E24: `05 | F24: Incentivos y escalafón | J24: =+G24+H24 -> 0 | K24: =IFERROR(J24/$J$18*100,"0.00")/100 -> 0
A25: 2 | B25: 1 | C25: 1 | D25: 1 | E25: `06 | F25: Nuevas plazas a medicos | J25: =+G25+H25 -> 0 | K25: =IFERROR(J25/$J$18*100,"0.00")/100 -> 0
A26: 2 | B26: 1 | C26: 1 | D26: 2 | F26: Remuneraciones al personal con carácter transitorio | G26: =SUM(G27:G32) -> 1.4007194e+08 | H26: =SUM(H27:H32) -> 0 | I26: =SUM(I27:I32) -> 0 | J26: =+G26+H26 -> 1.4007194e+08 | K26: =IFERROR(J26/$J$18*100,"0.00")/100 -> 0.08035695
A27: 2 | B27: 1 | C27: 1 | D27: 2 | E27: `03 | F27: Suplencias | J27: =+G27+H27 -> 0 | K27: =IFERROR(J27/$J$18*100,"0.00")/100 -> 0
A28: 2 | B28: 1 | C28: 1 | D28: 2 | E28: `05 | F28: Sueldo al personal nominal en período probatorio | J28: =+G28+H28 -> 0 | K28: =IFERROR(J28/$J$18*100,"0.00")/100 -> 0
A29: 2 | B29: 1 | C29: 1 | D29: 2 | E29: `06 | F29: Jornales | J29: =+G29+H29 -> 0 | K29: =IFERROR(J29/$J$18*100,"0.00")/100 -> 0
A30: 2 | B30: 1 | C30: 1 | D30: 2 | E30: `08 | F30: Empleados temporales | G30: 1.4007194e+08 | J30: =+G30+H30 -> 1.4007194e+08 | K30: =IFERROR(J30/$J$18*100,"0.00")/100 -> 0.08035695
A31: 2 | B31: 1 | C31: 1 | D31: 2 | E31: `09 | F31: Personal de carácter eventual | J31: =+G31+H31 -> 0 | K31: =IFERROR(J31/$J$18*100,"0.00")/100 -> 0
A32: 2 | B32: 1 | C32: 1 | D32: 2 | E32: `11 | F32: Interinato | J32: =+G32+H32 -> 0 | K32: =IFERROR(J32/$J$18*100,"0.00")/100 -> 0
A33: 2 | B33: 1 | C33: 1 | D33: 3 | F33: Sueldos al personal fijo en trámite de pensiones | G33: =G34 -> 0 | H33: =H34 -> 0 | I33: =I34 -> 0 | J33: =+G33+H33 -> 0 | K33: =IFERROR(J33/$J$18*100,"0.00")/100 -> 0
A34: 2 | B34: 1 | C34: 1 | D34: 3 | E34: `01 | F34: Sueldos al personal fijo en trámite de pensiones | J34: =+G34+H34 -> 0 | K34: =IFERROR(J34/$J$18*100,"0.00")/100 -> 0
A35: 2 | B35: 1 | C35: 1 | D35: 4 | F35: Sueldo anual No. 13 | G35: =G36 -> 63984813 | H35: =H36 -> 0 | I35: =I36 -> 0 | J35: =+G35+H35 -> 63984813 | K35: =IFERROR(J35/$J$18*100,"0.00")/100 -> 0.036707027
A36: 2 | B36: 1 | C36: 1 | D36: 4 | E36: `01 | F36: Sueldo anual No. 13 | G36: 63984813 | J36: =+G36+H36 -> 63984813 | K36: =IFERROR(J36/$J$18*100,"0.00")/100 -> 0.036707027
A37: 2 | B37: 1 | C37: 1 | D37: 5 | F37: Prestacianes economicas | G37: =SUM(G38:G41) -> 1514231.2 | H37: =SUM(H38:H41) -> 0 | I37: =SUM(I38:I41) -> 0 | J37: =+G37+H37 -> 1514231.2 | K37: =IFERROR(J37/$J$18*100,"0.00")/100 -> 0.00086868937
A38: 2 | B38: 1 | C38: 1 | D38: 5 | E38: `01 | F38: Prestacianes economicas | J38: =+G38+H38 -> 0 | K38: =IFERROR(J38/$J$18*100,"0.00")/100 -> 0
A39: 2 | B39: 1 | C39: 1 | D39: 5 | E39: `02 | F39: Pago de porcentaje por desvinculación de cargo | J39: =+G39+H39 -> 0 | K39: =IFERROR(J39/$J$18*100,"0.00")/100 -> 0
A40: 2 | B40: 1 | C40: 1 | D40: 5 | E40: `03 | F40: Prestacion laboral por desvinculación | G40: 907400 | J40: =+G40+H40 -> 907400 | K40: =IFERROR(J40/$J$18*100,"0.00")/100 -> 0.00052056035
A41: 2 | B41: 1 | C41: 1 | D41: 5 | E41: `04 | F41: Proporción de vacaciones no disfrutadas | G41: 606831.23 | J41: =+G41+H41 -> 606831.23 | K41: =IFERROR(J41/$J$18*100,"0.00")/100 -> 0.00034812902
A42: 2 | B42: 1 | C42: 2 | F42: Sobresueldos | G42: =+G43+G45 -> 1.1844912e+08 | H42: =+H43+H45 -> 0 | I42: =+I43+I45 -> 0 | J42: =+G42+H42 -> 1.1844912e+08 | K42: =IFERROR(J42/$J$18*100,"0.00")/100 -> 0.0679523
A43: 2 | B43: 1 | C43: 2 | D43: 1 | F43: Primas por antigüedad | G43: =G44 -> 34558725 | H43: =H44 -> 0 | I43: =I44 -> 0 | J43: =+G43+H43 -> 34558725 | K43: =IFERROR(J43/$J$18*100,"0.00")/100 -> 0.019825768
A44: 2 | B44: 1 | C44: 2 | D44: 1 | E44: `01 | F44: Primas por antigüedad | G44: 34558725 | J44: =+G44+H44 -> 34558725 | K44: =IFERROR(J44/$J$18*100,"0.00")/100 -> 0.019825768
A45: 2 | B45: 1 | C45: 2 | D45: 2 | F45: Compensación | G45: =SUM(G46:G53) -> 83890399 | H45: =SUM(H46:H53) -> 0 | I45: =SUM(I46:I53) -> 0 | J45: =+G45+H45 -> 83890399 | K45: =IFERROR(J45/$J$18*100,"0.00")/100 -> 0.048126532
A46: 2 | B46: 1 | C46: 2 | D46: 2 | E46: `03 | F46: Pago de horas extraordinarias, Horas extraordinarias fin de año (Reglamento 523-09) | J46: =+G46+H46 -> 0 | K46: =IFERROR(J46/$J$18*100,"0.00")/100 -> 0
A47: 2 | B47: 1 | C47: 2 | D47: 2 | E47: `04 | F47: Prima de transporte | J47: =+G47+H47 -> 0 | K47: =IFERROR(J47/$J$18*100,"0.00")/100 -> 0
A48: 2 | B48: 1 | C48: 2 | D48: 2 | E48: `05 | F48: Compensación servicios de Seguridad | G48: 540000 | J48: =+G48+H48 -> 540000 | K48: =IFERROR(J48/$J$18*100,"0.00")/100 -> 0.00030978905
A49: 2 | B49: 1 | C49: 2 | D49: 2 | E49: `06 | F49: Incentivo por rendimiento individual | G49: 9283645 | J49: =+G49+H49 -> 9283645 | K49: =IFERROR(J49/$J$18*100,"0.00")/100 -> 0.0053258733
A50: 2 | B50: 1 | C50: 2 | D50: 2 | E50: `07 | F50: Compensación por distancia | J50: =+G50+H50 -> 0 | K50: =IFERROR(J50/$J$18*100,"0.00")/100 -> 0
A51: 2 | B51: 1 | C51: 2 | D51: 2 | E51: `08 | F51: Compensaciones especiales | G51: 4050399 | J51: =+G51+H51 -> 4050399 | K51: =IFERROR(J51/$J$18*100,"0.00")/100 -> 0.0023236468
A52: 2 | B52: 1 | C52: 2 | D52: 2 | E52: `09 | F52: Bono por desempeño | G52: 462506 | J52: =+G52+H52 -> 462506 | K52: =IFERROR(J52/$J$18*100,"0.00")/100 -> 0.00026533203
A53: 2 | B53: 1 | C53: 2 | D53: 2 | E53: `10 | F53: Compensación por cumplimiento de indicadores | G53: 69553849 | J53: =+G53+H53 -> 69553849 | K53: =IFERROR(J53/$J$18*100,"0.00")/100 -> 0.039901891
A54: 2 | B54: 1 | C54: 3 | F54: Dietas y Gastos de Representación | G54: =+G55 -> 0 | H54: =+H55 -> 0 | I54: =+I55 -> 0 | J54: =+G54+H54 -> 0 | K54: =IFERROR(J54/$J$18*100,"0.00")/100 -> 0
A55: 2 | B55: 1 | C55: 3 | D55: 2 | F55: Gastos de representación | G55: =SUM(G56:G57) -> 0 | H55: =SUM(H56:H57) -> 0 | I55: =SUM(I56:I57) -> 0 | J55: =+G55+H55 -> 0 | K55: =IFERROR(J55/$J$18*100,"0.00")/100 -> 0
A56: 2 | B56: 1 | C56: 3 | D56: 2 | E56: `01 | F56: Gastos de representación en el país | J56: =+G56+H56 -> 0 | K56: =IFERROR(J56/$J$18*100,"0.00")/100 -> 0
A57: 2 | B57: 1 | C57: 3 | D57: 2 | E57: `02 | F57: Gastos de representación en el exterior | J57: =+G57+H57 -> 0 | K57: =IFERROR(J57/$J$18*100,"0.00")/100 -> 0
A58: 2 | B58: 1 | C58: 5 | F58: Contribuciones a la Seguridad Social y Riesgo Laboral | G58: =G59+G61+G63+G65 -> 1.1349059e+08 | H58: =H59+H61+H63+H65 -> 0 | I58: =I59+I61+I63+I65 -> 0 | J58: =+G58+H58 -> 1.1349059e+08 | K58: =IFERROR(J58/$J$18*100,"0.00")/100 -> 0.065107672
A59: 2 | B59: 1 | C59: 5 | D59: 1 | F59: Contribuciones al seguro de salud | G59: =G60 -> 52327390 | H59: =H60 -> 0 | I59: =I60 -> 0 | J59: =+G59+H59 -> 52327390 | K59: =IFERROR(J59/$J$18*100,"0.00")/100 -> 0.030019357
A60: 2 | B60: 1 | C60: 5 | D60: 1 | E60: `01 | F60: Contribuciones al seguro de salud | G60: 52327390 | J60: =+G60+H60 -> 52327390 | K60: =IFERROR(J60/$J$18*100,"0.00")/100 -> 0.030019357
A61: 2 | B61: 1 | C61: 5 | D61: 2 | F61: Contribuciones al seguro de pensiones | G61: =G62 -> 52327390 | H61: =H62 -> 0 | I61: =I62 -> 0 | J61: =+G61+H61 -> 52327390 | K61: =IFERROR(J61/$J$18*100,"0.00")/100 -> 0.030019357
A62: 2 | B62: 1 | C62: 5 | D62: 2 | E62: `01 | F62: Contribuciones al seguro de pensiones | G62: 52327390 | J62: =+G62+H62 -> 52327390 | K62: =IFERROR(J62/$J$18*100,"0.00")/100 -> 0.030019357
A63: 2 | B63: 1 | C63: 5 | D63: 3 | F63: Contribuciones al seguro de riesgo laboral | G63: =G64 -> 8835810.7 | H63: =H64 -> 0 | I63: =I64 -> 0 | J63: =+G63+H63 -> 8835810.7 | K63: =IFERROR(J63/$J$18*100,"0.00")/100 -> 0.0050689582
A64: 2 | B64: 1 | C64: 5 | D64: 3 | E64: `01 | F64: Contribuciones al seguro de riesgo laboral | G64: 8835810.7 | J64: =+G64+H64 -> 8835810.7 | K64: =IFERROR(J64/$J$18*100,"0.00")/100 -> 0.0050689582
A65: 2 | B65: 1 | C65: 5 | D65: 4 | F65: Contribuciones al plan de retiro complementario | G65: =G66 -> 0 | H65: =H66 -> 0 | I65: =I66 -> 0 | J65: =+G65+H65 -> 0 | K65: =IFERROR(J65/$J$18*100,"0.00")/100 -> 0
A66: 2 | B66: 1 | C66: 5 | D66: 4 | E66: `01 | F66: Contribuciones al plan de retiro complementario | J66: =+G66+H66 -> 0 | K66: =IFERROR(J66/$J$18*100,"0.00")/100 -> 0
A67: 2 | B67: 2 | F67: Contratacion de servicios | G67: =+G68+G82+G87+G92+G99+G116+G125+G143 -> 47730529 | H67: =+H68+H82+H87+H92+H99+H116+H125+H143+H167 -> 24952182 | I67: =+I68+I82+I87+I92+I99+I116+I125+I143 -> 0 | J67: =+G67+H67 -> 72682712 | K67: =IFERROR(J67/$J$18*100,"0.00")/100 -> 0.041696868
A68: 2 | B68: 2 | C68: 1 | F68: Servicios Básicos | G68: =+G69+G71+G73+G75+G78+G80 -> 0 | H68: =+H69+H71+H73+H75+H78+H80 -> 3804000 | I68: =+I69+I71+I73+I75+I78+I80 -> 0 | J68: =+G68+H68 -> 3804000 | K68: =IFERROR(J68/$J$18*100,"0.00")/100 -> 0.0021822918
A69: 2 | B69: 2 | C69: 1 | D69: 2 | F69: Servicios telefónico de larga distancia | G69: =G70 -> 0 | H69: =H70 -> 0 | I69: =I70 -> 0 | J69: =+G69+H69 -> 0 | K69: =IFERROR(J69/$J$18*100,"0.00")/100 -> 0
A70: 2 | B70: 2 | C70: 1 | D70: 2 | E70: `01 | F70: Servicios telefónico de larga distancia | J70: =+G70+H70 -> 0 | K70: =IFERROR(J70/$J$18*100,"0.00")/100 -> 0
A71: 2 | B71: 2 | C71: 1 | D71: 3 | F71: Teléfono local | G71: =G72 -> 0 | H71: =H72 -> 2724000 | I71: =I72 -> 0 | J71: =+G71+H71 -> 2724000 | K71: =IFERROR(J71/$J$18*100,"0.00")/100 -> 0.0015627137
A72: 2 | B72: 2 | C72: 1 | D72: 3 | E72: `01 | F72: Teléfono local | H72: 2724000 | J72: =+G72+H72 -> 2724000 | K72: =IFERROR(J72/$J$18*100,"0.00")/100 -> 0.0015627137
A73: 2 | B73: 2 | C73: 1 | D73: 5 | F73: Servicio de internet y televisión por cable | G73: =G74 -> 0 | H73: =H74 -> 0 | I73: =I74 -> 0 | J73: =+G73+H73 -> 0 | K73: =IFERROR(J73/$J$18*100,"0.00")/100 -> 0
A74: 2 | B74: 2 | C74: 1 | D74: 5 | E74: `01 | F74: Servicio de internet y televisión por cable | J74: =+G74+H74 -> 0 | K74: =IFERROR(J74/$J$18*100,"0.00")/100 -> 0
A75: 2 | B75: 2 | C75: 1 | D75: 6 | F75: Electricidad | G75: =G76+G77 -> 0 | H75: =H76+H77 -> 0 | I75: =I76+I77 -> 0 | J75: =+G75+H75 -> 0 | K75: =IFERROR(J75/$J$18*100,"0.00")/100 -> 0
A76: 2 | B76: 2 | C76: 1 | D76: 6 | E76: `01 | F76: Energía eléctrica | J76: =+G76+H76 -> 0 | K76: =IFERROR(J76/$J$18*100,"0.00")/100 -> 0
A77: 2 | B77: 2 | C77: 1 | D77: 6 | E77: `02 | F77: Electricidad no cortable | J77: =+G77+H77 -> 0 | K77: =IFERROR(J77/$J$18*100,"0.00")/100 -> 0
A78: 2 | B78: 2 | C78: 1 | D78: 7 | F78: Agua | G78: =G79 -> 0 | H78: =H79 -> 780000 | I78: =I79 -> 0 | J78: =+G78+H78 -> 780000 | K78: =IFERROR(J78/$J$18*100,"0.00")/100 -> 0.00044747308
A79: 2 | B79: 2 | C79: 1 | D79: 7 | E79: `01 | F79: Agua | H79: 780000 | J79: =+G79+H79 -> 780000 | K79: =IFERROR(J79/$J$18*100,"0.00")/100 -> 0.00044747308
A80: 2 | B80: 2 | C80: 1 | D80: 8 | F80: Recolección de residuos sólidos | G80: =G81 -> 0 | H80: =H81 -> 300000 | I80: =I81 -> 0 | J80: =+G80+H80 -> 300000 | K80: =IFERROR(J80/$J$18*100,"0.00")/100 -> 0.00017210503
A81: 2 | B81: 2 | C81: 1 | D81: 8 | E81: `01 | F81: Recolección de residuos sólidos | H81: 300000 | J81: =+G81+H81 -> 300000 | K81: =IFERROR(J81/$J$18*100,"0.00")/100 -> 0.00017210503
A82: 2 | B82: 2 | C82: 2 | F82: Publicidad Impresión y Encuadernación | G82: =+G83+G85 -> 0 | H82: =+H83+H85 -> 0 | I82: =+I83+I85 -> 0 | J82: =+G82+H82 -> 0 | K82: =IFERROR(J82/$J$18*100,"0.00")/100 -> 0
A83: 2 | B83: 2 | C83: 2 | D83: 1 | F83: Publicidad y propaganda | G83: =G84 -> 0 | H83: =H84 -> 0 | I83: =I84 -> 0 | J83: =+G83+H83 -> 0 | K83: =IFERROR(J83/$J$18*100,"0.00")/100 -> 0
A84: 2 | B84: 2 | C84: 2 | D84: 1 | E84: `01 | F84: Publicidad y propaganda | J84: =+G84+H84 -> 0 | K84: =IFERROR(J84/$J$18*100,"0.00")/100 -> 0
A85: 2 | B85: 2 | C85: 2 | D85: 2 | F85: Impresión y encuadernación | G85: =G86 -> 0 | H85: =H86 -> 0 | I85: =I86 -> 0 | J85: =+G85+H85 -> 0 | K85: =IFERROR(J85/$J$18*100,"0.00")/100 -> 0
A86: 2 | B86: 2 | C86: 2 | D86: 2 | E86: `01 | F86: Impresión y encuadernación | J86: =+G86+H86 -> 0 | K86: =IFERROR(J86/$J$18*100,"0.00")/100 -> 0
A87: 2 | B87: 2 | C87: 3 | F87: Viáticos | G87: =+G88+G90 -> 0 | H87: =+H88+H90 -> 0 | I87: =+I88+I90 -> 0 | J87: =+G87+H87 -> 0 | K87: =IFERROR(J87/$J$18*100,"0.00")/100 -> 0
A88: 2 | B88: 2 | C88: 3 | D88: 1 | F88: Viáticos dentro del país | G88: =G89 -> 0 | H88: =H89 -> 0 | I88: =I89 -> 0 | J88: =+G88+H88 -> 0 | K88: =IFERROR(J88/$J$18*100,"0.00")/100 -> 0
A89: 2 | B89: 2 | C89: 3 | D89: 1 | E89: `01 | F89: Viáticos dentro del país | J89: =+G89+H89 -> 0 | K89: =IFERROR(J89/$J$18*100,"0.00")/100 -> 0
A90: 2 | B90: 2 | C90: 3 | D90: 2 | F90: Viáticos fuera del país | G90: =G91 -> 0 | H90: =H91 -> 0 | I90: =I91 -> 0 | J90: =+G90+H90 -> 0 | K90: =IFERROR(J90/$J$18*100,"0.00")/100 -> 0
A91: 2 | B91: 2 | C91: 3 | D91: 2 | E91: `01 | F91: Viáticos fuera del país | J91: =+G91+H91 -> 0 | K91: =IFERROR(J91/$J$18*100,"0.00")/100 -> 0
A92: 2 | B92: 2 | C92: 4 | F92: Transporte y Alamcenaje | G92: =+G93+G95+G97 -> 0 | H92: =+H93+H95+H97 -> 708803.54 | I92: =+I93+I95+I97 -> 0 | J92: =+G92+H92 -> 708803.54 | K92: =IFERROR(J92/$J$18*100,"0.00")/100 -> 0.00040662885
A93: 2 | B93: 2 | C93: 4 | D93: 1 | F93: Pasajes y gastos de transporte | G93: =G94 -> 0 | H93: =H94 -> 0 | I93: =I94 -> 0 | J93: =+G93+H93 -> 0 | K93: =IFERROR(J93/$J$18*100,"0.00")/100 -> 0
A94: 2 | B94: 2 | C94: 4 | D94: 1 | E94: `01 | F94: Pasajes y gastos de transporte | J94: =+G94+H94 -> 0 | K94: =IFERROR(J94/$J$18*100,"0.00")/100 -> 0
A95: 2 | B95: 2 | C95: 4 | D95: 2 | F95: Fletes | G95: =G96 -> 0 | H95: =H96 -> 708803.54 | I95: =I96 -> 0 | J95: =+G95+H95 -> 708803.54 | K95: =IFERROR(J95/$J$18*100,"0.00")/100 -> 0.00040662885
A96: 2 | B96: 2 | C96: 4 | D96: 2 | E96: `01 | F96: Fletes | H96: 708803.54 | J96: =+G96+H96 -> 708803.54 | K96: =IFERROR(J96/$J$18*100,"0.00")/100 -> 0.00040662885
A97: 2 | B97: 2 | C97: 4 | D97: 4 | F97: Peaje | G97: =G98 -> 0 | H97: =H98 -> 0 | I97: =I98 -> 0 | J97: =+G97+H97 -> 0 | K97: =IFERROR(J97/$J$18*100,"0.00")/100 -> 0
A98: 2 | B98: 2 | C98: 4 | D98: 4 | E98: `01 | F98: Peaje | J98: =+G98+H98 -> 0 | K98: =IFERROR(J98/$J$18*100,"0.00")/100 -> 0
A99: 2 | B99: 2 | C99: 5 | F99: Alquileres y Rentas | G99: =+G100+G102+G104+G110+G112 -> 0 | H99: =+H100+H102+H104+H110+H112 -> 4200000 | I99: =+I100+I102+I104+I110+I112 -> 0 | J99: =+G99+H99 -> 4200000 | K99: =IFERROR(J99/$J$18*100,"0.00")/100 -> 0.0024094704
A100: 2 | B100: 2 | C100: 5 | D100: 1 | F100: Alquilleres y rentas de edificios y locales | G100: =G101 -> 0 | H100: =H101 -> 0 | I100: =I101 -> 0 | J100: =+G100+H100 -> 0 | K100: =IFERROR(J100/$J$18*100,"0.00")/100 -> 0
A101: 2 | B101: 2 | C101: 5 | D101: 1 | E101: `01 | F101: Alquilleres y rentas de edificios y locales | J101: =+G101+H101 -> 0 | K101: =IFERROR(J101/$J$18*100,"0.00")/100 -> 0
...

Sheet Insumos
A1: Insumo | B1: InsumoAbrev | C1: Descripción | D1: Unidad de Medida | E1: Precio Unitario | F1: CODIGO PRESUPUESTARIO
A2: Acabados textiles | B2: lsAcabadosTextiles | C2: Manteles en encajes para bandejas grandes (rectangulares) | D2: unidad | E2: 944 | F2: 2.3.2.2.01
A3: Acabados textiles | B3: lsAcabadosTextiles | C3: Manteles en encajes para bandejas pequeñas (rectangulares) | D3: unidad | E3: 590 | F3: 2.3.2.2.01
A4: Alimentos y bebidas para personas | B4: lsAlimentosyBebidas | C4: Almuerzo tipo Buffet para 10 personas (Cristaleria, Cuberteria, Servilletas, Jugo) | D4: unidad | E4: 5000.5 | F4: 2.3.1.1.01
A5: Alimentos y bebidas para personas | B5: lsAlimentosyBebidas | C5: Almuerzo tipo Buffet para 20 personas (Cristalería, Cubertería, Servilletas, Jugo, Café) | D5: unidad | E5: 10133.5 | F5: 2.3.1.1.01
A6: Alimentos y bebidas para personas | B6: lsAlimentosyBebidas | C6: Almuerzo tipo Buffet para 30 personas (Cristaleria, Cuberteria, Servilletas, Jugo) | D6: unidad | E6: 25488 | F6: 2.3.1.1.01
A7: Alimentos y bebidas para personas | B7: lsAlimentosyBebidas | C7: Almuerzo tipo Buffet para 40 personas (Cristalería, Cuberteria, Mesas, Sillas, Manteles, Servilletas) | D7: unidad | E7: 61419 | F7: 2.3.1.1.01
A8: Alimentos y bebidas para personas | B8: lsAlimentosyBebidas | C8: Refrigerio Dulce tipo Buffet p/65 Personas (Arreglo Flores, Alquiler Cristalería, Sillas, Servilletas, Mesa, Bambalina, Tope) | D8: unidad | E8: 33435.3 | F8: 2.3.1.1.01
A9: Alimentos y bebidas para personas | B9: lsAlimentosyBebidas | C9: Refrigerio tipo Buffet p/12 personas (4 Variedades, Desechables Transparentes, Jugo Natural, Servilletas, Hielo) | D9: unidad | E9: 9410.5 | F9: 2.3.1.1.01
A10: Alimentos y bebidas para personas | B10: lsAlimentosyBebidas | C10: Refrigerio tipo Buffet p/15 personas (3 Variedades, Desechables Transparentes, Jugo Natural, Servilletas, Hielo) | D10: unidad | E10: 5929.5 | F10: 2.3.1.1.01
A11: Alimentos y bebidas para personas | B11: lsAlimentosyBebidas | C11: Refrigerio tipo Buffet p/150 personas (Diferentes Variedades, Bambalinas, Manteles, Desechables, Hielo, Servilletas) | D11: unidad | E11: 65844 | F11: 2.3.1.1.01
A12: Alimentos y bebidas para personas | B12: lsAlimentosyBebidas | C12: Refrigerio tipo Buffet p/40 personas (5 Variedades, Cristaleria, Mantel, Tope, Bambalina, Servilletas, Hielo) | D12: unidad | E12: 29393.8 | F12: 2.3.1.1.01
A13: Alimentos y bebidas para personas | B13: lsAlimentosyBebidas | C13: Refrigerio tipo Buffet p/45 personas (5 Variedades, Desechable Transparentes, Servilletas, Hielo) | D13: unidad | E13: 27193.1 | F13: 2.3.1.1.01
... A36: Equipo de comunicación, telecomunicaciones y señalamiento | B36: lsTelecomunicaciones | C36: Mapas de Evacuación | D36: unidad | E36: 2330.5 | F36: 2.6.5.5.01
A37: Equipo de comunicación, telecomunicaciones y señalamiento | B37: lsTelecomunicaciones | C37: Otros Señales | E37: 1150 | F37: 2.6.5.5.01
A38: Equipo de comunicación, telecomunicaciones y señalamiento | B38: lsTelecomunicaciones | C38: Punto de Reunion 2x2 pies, Metla colocado en pared | D38: unidad | E38: 2330.5 | F38: 2.6.5.5.01
A39: Equipo de comunicación, telecomunicaciones y señalamiento | B39: lsTelecomunicaciones | C39: Señal de Ruta de Evacuacion Area, Doble Cara 6x12, para techo con cables de acero Fotoluminiscente | D39: unidad | E39: 3009 | F39: 2.6.5.5.01
A40: Equipo de comunicación, telecomunicaciones y señalamiento | B40: lsTelecomunicaciones | C40: Señales de Ruta de Evacuacion Flecha Derecha 5x8 en vinil fotoluminiscente sobre PVC de 4mm | D40: unidad | E40: 1150.5 | F40: 2.6.5.5.01
A41: Equipo de comunicación, telecomunicaciones y señalamiento | B41: lsTelecomunicaciones | C41: Señales de Ruta de Evacuacion Flecha Izquierda 5x8 en vinil fotoluminiscente sobre PVC de 4mm | D41: unidad | E41: 1150.5 | F41: 2.6.5.5.01
A42: Equipo de comunicación, telecomunicaciones y señalamiento | B42: lsTelecomunicaciones | C42: Señales de Salida 12x25¨ en vinil fotoluminiscente sobre PVC de 4mm | D42: unidad | E42: 1947 | F42: 2.6.5.5.01
A43: Equipo de comunicación, telecomunicaciones y señalamiento | B43: lsTelecomunicaciones | C43: Señalizaciones de Extintores y Modo de uso | D43: unidad | E43: 2212.5 | F43: 2.6.5.5.01
A44: Equipo médico y de laboratorio | B44: lsEquiposMedicos | C44: Agitador rotador VDRL. | D44: unidad | E44: 11210 | F44: 2.6.3.1.01
A45: Equipo médico y de laboratorio | B45: lsEquiposMedicos | C45: Aspirador de secreciones eléctrico rodable | D45: unidad | E45: 15692.82 | F45: 2.6.3.1.01
A46: Equipo médico y de laboratorio | B46: lsEquiposMedicos | C46: Bandeja de Urología | D46: unidad | E46: 342200 | F46: 2.6.3.1.01
A47: Equipo médico y de laboratorio | B47: lsEquiposMedicos | C47: Contador de células hematológicas. | D47: unidad | E47: 6254 | F47: 2.6.3.1.01
A48: Equipo médico y de laboratorio | B48: lsEquiposMedicos | C48: Incubadora neonatal para UCI | D48: unidad | E48: 531000 | F48: 2.6.3.1.01
A49: Equipo médico y de laboratorio | B49: lsEquiposMedicos | C49: Vitrina de acero inoxidable para material estéril 0.68x0.45x1.70m. | D49: unidad | E49: 49794.525 | F49: 2.6.3.1.01
... A243: Muebles de oficina y estantería | B243: lsMueblesdeOficina | C243: Taburete metalico giratorio con espaldar para anestesiologo | D243: unidad | E243: 6755.736 | F243: 2.6.1.1.02
A244: Obras menores en edificaciones | B244: lsObrasMenoresEdificaciones | C244: Adecuación Local | D244: unidad | F244: 2.7.1.1.01
A245: Otros equipos | B245: lsOtrosEquipos | C245: Bomba de agua de 1.5 hp, doble impele | D245: unidad | E245: 36028.94 | F245: 2.6.5.8.01
A246: Otros equipos | B246: lsOtrosEquipos | C246: Bomba de Agua de 3HP - 110-220V | D246: unidad | E246: 30591.5 | F246: 2.6.5.8.01
A247: Otros equipos | B247: lsOtrosEquipos | C247: Gato Hidráulico 2 TOM. TW | D247: unidad | E247: 626.58 | F247: 2.6.5.8.01
A248: Otros equipos | B248: lsOtrosEquipos | C248: Tanque de hidroneumatico de 120 galones - alta presion | D248: unidad | E248: 62031.42 | F248: 2.6.5.8.01
A249: Peaje | B249: lsPeaje | C249: Peaje (por vehiculo) | D249: unidad | E249: 60 | F249: 2.2.4.4.01
A250: Pinturas, barnices, lacas, diluyentes y absorbentes para pintura | B250: lsPinturas | C250: Cemento de pvc de 16oz | D250: unidad | E250: 487.34 | F250: 2.3.7.2.06
A251: Pinturas, barnices, lacas, diluyentes y absorbentes para pintura | B251: lsPinturas | C251: Pastas de cloro de cisternas 200GRS | D251: unidad | E251: 88.5 | F251: 2.3.7.2.06
A252: Productos de artes gráficas | B252: lsProductosArtesGraficas | C252: Calcomanias | D252: unidad | E252: 177 | F252: 2.3.3.3.01
A253: Productos de artes gráficas | B253: lsProductosArtesGraficas | C253: Letrero en Acrílico rotulado en Vinil adhesivo, Tornillos Decorativo (0.71mt x 1.06mt) con instalación | D253: unidad | E253: 5959 | F253: 2.3.3.3.01
A254: Productos de cemento | B254: lsProductosdeCemento | C254: Cemento blanco | D254: libra | E254: 18.88 | F254: 2.3.6.1.01
A255: Productos de loza | B255: lsProductosdeLoza | C255: Inodoros color blanco | D255: unidad | E255: 4124.1 | F255: 2.3.6.2.02
A256: Productos de loza | B256: lsProductosdeLoza | C256: Lavamanos con pedestal color blanco | D256: unidad | E256: 4737.7 | F256: 2.3.6.2.02
... A520: Otros equipos de transporte | B520: lsEquiposTransporte | C520: Otros equipos de transporte | D520: Unidad | E520: 0 | F520: 2.6.4.8.01
A539: Insumos
A540: Acabados textiles | B540: lsAcabadosTextiles
A541: Alimentos y bebidas para personas | B541: lsAlimentosyBebidas
A542: Artículos de plástico | B542: lsArticulosdePlastico
A543: Automóviles y camiones | B543: lsEquiposTransporte
A544: Carrocerías y remolques | B544: lsEquiposTransporte
A545: Electrodomésticos | B545: lsElectrodomesticos
A546: Equipo de comunicación, telecomunicaciones y señalamiento | B546: lsTelecomunicaciones
A547: Equipo médico y de laboratorio | B547: lsEquiposMedicos
A548: Equipos de cómputo | B548: lsEquiposComputos
A549: Equipos de seguridad | B549: lsEquiposSeguridad
A550: Eventos generales | B550: lsEventosGenerales
A551: Gasoil | B551: lsGasoil
... A583: Viáticos dentro del país | B583: lsViaticosDP
