Workbook

Sheet ABRIL 
A1: Form. No.6 SRS
A3: Servicio Nacional de Salud
A4: Dirección de Fizcalización
A5: Consolidado de Ingresos y Gastos por Fuente de Financiamiento
A6: HOSPITAL MATERNO INFANTIL SAN LORENZO DE LOS MINA
A7: ABRIL 2025
C8: Ingresos Generales:
E9: 1.- Balance Inicial / Fuente:
E10: Anticipo Financiero | H10: Otros Aportes
E11: Transferencias Corrientes
E12: Venta de Servicios | G12: 4614.79
E13: 2.- Ingresos por Fuente / Cuenta
E14: Anticipo Financiero | H14: Otros Aportes | I14: =+'[1]INGR SEGUN ORIGEN'!E39 -> 214750
E15: Transferencias Corrientes | G15: =+'[1]INGR SEGUN ORIGEN'!E12 -> 1.007793e+08 | H15: Aportes Nomina SNS | I15: 0
E16: Venta de Servicios | G16: =+'[1]INGR SEGUN ORIGEN'!E32 -> 6892064.8
H17: TOTAL INGRESOS RDS | I17: =+G10+G11+G12+I10+G14+G15+G16+I14+I15 -> 1.0789073e+08
A21: 1 | F21: 2 | G21: 3 | I21: 4 | J21: 5
A22: Código Presupuestario | F22: Descripción Gasto por Cuenta | G22: Distribución del Gasto por Fuente de Financiamiento | I22: TOTAL | J22: %
A23: Tipo | B23: Objeto | C23: Cuenta | D23: Sub-Cuenta | E23: Auxiliar | G23: Fondo 100 | H23: Venta de Servicios/ Otros Aportes
A25: 2 | F25: Gastos | G25: =+G26+G87+G212+G330+G336+G463 -> 91800340 | H25: =+H26+H87+H212+H330+H336+H463 -> 4881550.3 | I25: =SUM(G25:H25) -> 96681890 | J25: =+J26+J87+J212+J330+J336+J463 -> 1
A26: 2 | B26: 1 | F26: Servicios Personales | G26: =+G27+G51+G64+G71+G78 -> 66556156 | H26: =+H27+H51+H64+H71+H78 -> 0 | I26: =SUM(G26:H26) -> 66556156 | J26: =I26/$I$25 -> 0.68840355
A27: 2 | B27: 1 | C27: 1 | F27: Remuneraciones | G27: =+G28+G35+G42+G44+G46 -> 54771097 | H27: =+H28+H35+H42+H44+H46 -> 0 | I27: =SUM(G27:H27) -> 54771097 | J27: =I27/$I$25 -> 0.56650834
A28: 2 | B28: 1 | C28: 1 | D28: 1 | F28: Remuneraciones al personal fijo | G28: =SUM(G29:G34) -> 53482455 | H28: =SUM(H29:H34) -> 0 | I28: =SUM(G28:H28) -> 53482455 | J28: =I28/$I$25 -> 0.55317966
A29: 2 | B29: 1 | C29: 1 | D29: 1 | E29: 01 | F29: Sueldos a empleados fijos | G29: ='[1]CUENTA T FONDO 100'!A127 -> 53482455 | H29: ='[1]CUENTA T VS'!A89 -> 0 | I29: =SUM(G29:H29) -> 53482455 | J29: =I29/$I$25 -> 0.55317966
A30: 2 | B30: 1 | C30: 1 | D30: 1 | E30: 02 | F30: Sueldos a médicos | G30: ='[1]CUENTA T FONDO 100'!B127 -> 0 | H30: ='[1]CUENTA T VS'!B89 -> 0 | I30: =SUM(G30:H30) -> 0 | J30: =I30/$I$25 -> 0
A31: 2 | B31: 1 | C31: 1 | D31: 1 | E31: 03 | F31: Ascensos a militares | G31: ='[1]CUENTA T FONDO 100'!C127 -> 0 | H31: ='[1]CUENTA T VS'!C89 -> 0 | I31: =SUM(G31:H31) -> 0 | J31: =I31/$I$25 -> 0
A32: 2 | B32: 1 | C32: 1 | D32: 1 | E32: 04 | F32: Nuevas plazas maestros | G32: ='[1]CUENTA T FONDO 100'!D127 -> 0 | H32: ='[1]CUENTA T VS'!D89 -> 0 | I32: =SUM(G32:H32) -> 0 | J32: =I32/$I$25 -> 0
A33: 2 | B33: 1 | C33: 1 | D33: 1 | E33: 05 | F33: Incentivos y escalafón | G33: ='[1]CUENTA T FONDO 100'!E127 -> 0 | H33: ='[1]CUENTA T VS'!E89 -> 0 | I33: =SUM(G33:H33) -> 0 | J33: =I33/$I$25 -> 0
A34: 2 | B34: 1 | C34: 1 | D34: 1 | E34: 06 | F34: Nuevas plazas a médicos | G34: ='[1]CUENTA T FONDO 100'!F127 -> 0 | H34: ='[1]CUENTA T VS'!F89 -> 0 | I34: =SUM(G34:H34) -> 0 | J34: =I34/$I$25 -> 0
A35: 2 | B35: 1 | C35: 1 | D35: 2 | F35: Remuneraciones al personal con carácter transitorio | G35: =SUM(G36:G41) -> 1107531 | H35: =SUM(H36:H41) -> 0 | I35: =SUM(G35:H35) -> 1107531
A36: 2 | B36: 1 | C36: 1 | D36: 2 | E36: 03 | F36: Suplencias | G36: ='[1]CUENTA T FONDO 100'!G127 -> 0 | H36: ='[1]CUENTA T VS'!G89 -> 0 | I36: =SUM(G36:H36) -> 0 | J36: =I36/$I$25 -> 0
A37: 2 | B37: 1 | C37: 1 | D37: 2 | E37: 05 | F37: Sueldo al personal nominal en período probatorio | G37: ='[1]CUENTA T FONDO 100'!H127 -> 0 | H37: ='[1]CUENTA T VS'!H89 -> 0 | I37: =SUM(G37:H37) -> 0 | J37: =I37/$I$25 -> 0
A38: 2 | B38: 1 | C38: 1 | D38: 2 | E38: 06 | F38: Jornales | G38: ='[1]CUENTA T FONDO 100'!I127 -> 0 | H38: ='[1]CUENTA T VS'!I89 -> 0 | I38: =SUM(G38:H38) -> 0 | J38: =I38/$I$25 -> 0
A39: 2 | B39: 1 | C39: 1 | D39: 2 | E39: 08 | F39: Empleados temporales | G39: ='[1]CUENTA T FONDO 100'!J127 -> 1107531 | H39: ='[1]CUENTA T VS'!J89 -> 0 | I39: =SUM(G39:H39) -> 1107531 | J39: =I39/$I$25 -> 0.011455414
A40: 2 | B40: 1 | C40: 1 | D40: 2 | E40: 09 | F40: Personal de carácter eventual | G40: ='[1]CUENTA T FONDO 100'!K127 -> 0 | H40: ='[1]CUENTA T VS'!K89 -> 0 | I40: =SUM(G40:H40) -> 0 | J40: =I40/$I$25 -> 0
A41: 2 | B41: 1 | C41: 1 | D41: 2 | E41: 11 | F41: Interinato | G41: ='[1]CUENTA T FONDO 100'!L127 -> 0 | H41: ='[1]CUENTA T VS'!L89 -> 0 | I41: =SUM(G41:H41) -> 0 | J41: =I41/$I$25 -> 0
A42: 2 | B42: 1 | C42: 1 | D42: 3 | F42: Sueldos al personal fijo en trámite de pensiones | G42: =SUM(G43) -> 0 | H42: =SUM(H43) -> 0 | I42: =SUM(G42:H42) -> 0
A43: 2 | B43: 1 | C43: 1 | D43: 3 | E43: 01 | F43: Sueldos al personal fijo en trámite de pensiones | G43: ='[1]CUENTA T FONDO 100'!M127 -> 0 | H43: ='[1]CUENTA T VS'!M89 -> 0 | I43: =SUM(G43:H43) -> 0 | J43: =I43/$I$25 -> 0
A44: 2 | B44: 1 | C44: 1 | D44: 4 | F44: Sueldo anual no. 13 | G44: =SUM(G45) -> 0 | H44: =SUM(H45) -> 0 | I44: =SUM(G44:H44) -> 0
A45: 2 | B45: 1 | C45: 1 | D45: 4 | E45: 01 | F45: Sueldo anual no. 13 | G45: ='[1]CUENTA T FONDO 100'!N127 -> 0 | H45: ='[1]CUENTA T VS'!N89 -> 0 | I45: =SUM(G45:H45) -> 0 | J45: =I45/$I$25 -> 0
A46: 2 | B46: 1 | C46: 1 | D46: 5 | F46: Prestaciones económinas | G46: =SUM(G47:G50) -> 181111.08 | H46: =SUM(H47:H50) -> 0 | I46: =SUM(G46:H46) -> 181111.08
A47: 2 | B47: 1 | C47: 1 | D47: 5 | E47: 01 | F47: Prestaciones económinas | G47: ='[1]CUENTA T FONDO 100'!O127 -> 0 | H47: ='[1]CUENTA T VS'!O89 -> 0 | I47: =SUM(G47:H47) -> 0 | J47: =I47/$I$25 -> 0
A48: 2 | B48: 1 | C48: 1 | D48: 5 | E48: 02 | F48: Pago de porcentaje por desvinculación de cargo | G48: ='[1]CUENTA T FONDO 100'!P127 -> 0 | H48: ='[1]CUENTA T VS'!P89 -> 0 | I48: =SUM(G48:H48) -> 0 | J48: =I48/$I$25 -> 0
A49: 2 | B49: 1 | C49: 1 | D49: 5 | E49: 03 | F49: Prestación laboral por desvinculación | G49: ='[1]CUENTA T FONDO 100'!Q127 -> 92400 | H49: ='[1]CUENTA T VS'!Q89 -> 0 | I49: =SUM(G49:H49) -> 92400 | J49: =I49/$I$25 -> 0.00095571156
A50: 2 | B50: 1 | C50: 1 | D50: 5 | E50: 04 | F50: Proporción de vacaciones no disfrutadas | G50: ='[1]CUENTA T FONDO 100'!R127 -> 88711.08 | H50: ='[1]CUENTA T VS'!R89 -> 0 | I50: =SUM(G50:H50) -> 88711.08 | J50: =I50/$I$25 -> 0.00091755633
A51: 2 | B51: 1 | C51: 2 | F51: Sobresueldos | G51: =+G52+G54 -> 3384964.5 | H51: =+H52+H54 -> 0 | I51: =SUM(G51:H51) -> 3384964.5
A52: 2 | B52: 1 | C52: 2 | D52: 1 | F52: Primas por antigüedad | G52: =SUM(G53) -> 2739824.5 | H52: =SUM(H53) -> 0 | I52: =SUM(G52:H52) -> 2739824.5
A53: 2 | B53: 1 | C53: 2 | D53: 1 | E53: 01 | F53: Primas por antigüedad | G53: ='[1]CUENTA T FONDO 100'!S127 -> 2739824.5 | H53: ='[1]CUENTA T VS'!S89 -> 0 | I53: =SUM(G53:H53) -> 2739824.5 | J53: =I53/$I$25 -> 0.02833855
A54: 2 | B54: 1 | C54: 2 | D54: 2 | F54: Compensación | G54: =SUM(G55:G63) -> 645139.96 | H54: =SUM(H55:H63) -> 0 | I54: =SUM(G54:H54) -> 645139.96
A55: 2 | B55: 1 | C55: 2 | D55: 2 | E55: 01 | F55: Compensación por gastos de alimentación | G55: ='[1]CUENTA T FONDO 100'!T127 -> 0 | H55: ='[1]CUENTA T VS'!T89 -> 0 | I55: =SUM(G55:H55) -> 0 | J55: =I55/$I$25 -> 0
A56: 2 | B56: 1 | C56: 2 | D56: 2 | E56: 03 | F56: Pago de horas extraordinarias | G56: ='[1]CUENTA T FONDO 100'!U127 -> 0 | H56: ='[1]CUENTA T VS'!U89 -> 0 | I56: =SUM(G56:H56) -> 0 | J56: =I56/$I$25 -> 0
A57: 2 | B57: 1 | C57: 2 | D57: 2 | E57: 04 | F57: Prima de transporte | G57: ='[1]CUENTA T FONDO 100'!V127 -> 0 | H57: ='[1]CUENTA T VS'!V89 -> 0 | I57: =SUM(G57:H57) -> 0 | J57: =I57/$I$25 -> 0
A58: 2 | B58: 1 | C58: 2 | D58: 2 | E58: 05 | F58: Compensación servicios de Seguridad | G58: ='[1]CUENTA T FONDO 100'!W127 -> 45000 | H58: ='[1]CUENTA T VS'!W89 -> 0 | I58: =SUM(G58:H58) -> 45000 | J58: =I58/$I$25 -> 0.00046544394
A59: 2 | B59: 1 | C59: 2 | D59: 2 | E59: 06 | F59: Incentivo por Rendimieto Individual | G59: ='[1]CUENTA T FONDO 100'!X127 -> 0 | H59: ='[1]CUENTA T VS'!X89 -> 0 | I59: =SUM(G59:H59) -> 0 | J59: =I59/$I$25 -> 0
A60: 2 | B60: 1 | C60: 2 | D60: 2 | E60: 07 | F60: Compensación por distancia | G60: ='[1]CUENTA T FONDO 100'!Y127 -> 0 | H60: ='[1]CUENTA T VS'!Y89 -> 0 | I60: =SUM(G60:H60) -> 0 | J60: =I60/$I$25 -> 0
A61: 2 | B61: 1 | C61: 2 | D61: 2 | E61: 08 | F61: Compensaciones especiales | G61: ='[1]CUENTA T FONDO 100'!Z127 -> 339600 | H61: ='[1]CUENTA T VS'!Z89 -> 0 | I61: =SUM(G61:H61) -> 339600 | J61: =I61/$I$25 -> 0.0035125503
A62: 2 | B62: 1 | C62: 2 | D62: 2 | E62: 09 | F62: Bono por desempeño a servidores de carrera | G62: ='[1]CUENTA T FONDO 100'!AA127 -> 0 | H62: ='[1]CUENTA T VS'!AA89 -> 0 | I62: =SUM(G62:H62) -> 0 | J62: =I62/$I$25 -> 0
A63: 2 | B63: 1 | C63: 2 | D63: 2 | E63: 10 | F63: Compensacion por cumplimiento de indicadores | G63: ='[1]CUENTA T FONDO 100'!AB127 -> 260539.96 | H63: ='[1]CUENTA T VS'!AB89 -> 0 | I63: =SUM(G63:H63) -> 260539.96 | J63: =I63/$I$25 -> 0.0026948166
A64: 2 | B64: 1 | C64: 3 | F64: Dietas y Gastos de Representación | G64: =+G65+G68 -> 0 | H64: =+H65+H68 -> 0 | I64: =SUM(G64:H64) -> 0
A65: 2 | B65: 1 | C65: 3 | D65: 1 | F65: Dietas | G65: =SUM(G66:G67) -> 0 | H65: =SUM(H66:H67) -> 0 | I65: =SUM(G65:H65) -> 0
A66: 2 | B66: 1 | C66: 3 | D66: 1 | E66: 01 | F66: Dietas en el país | G66: ='[1]CUENTA T FONDO 100'!AC127 -> 0 | H66: ='[1]CUENTA T VS'!AC89 -> 0 | I66: =SUM(G66:H66) -> 0 | J66: =I66/$I$25 -> 0
A67: 2 | B67: 1 | C67: 3 | D67: 1 | E67: 02 | F67: Dietas en el exterior | G67: ='[1]CUENTA T FONDO 100'!AD127 -> 0 | H67: ='[1]CUENTA T VS'!AD89 -> 0 | I67: =SUM(G67:H67) -> 0 | J67: =I67/$I$25 -> 0
A68: 2 | B68: 1 | C68: 3 | D68: 2 | F68: Gastos de representación | G68: =SUM(G69:G70) -> 0 | H68: =SUM(H69:H70) -> 0 | I68: =SUM(G68:H68) -> 0
A69: 2 | B69: 1 | C69: 3 | D69: 2 | E69: 01 | F69: Gastos de representación en el país | G69: ='[1]CUENTA T FONDO 100'!AE127 -> 0 | H69: ='[1]CUENTA T VS'!AE89 -> 0 | I69: =SUM(G69:H69) -> 0 | J69: =I69/$I$25 -> 0
A70: 2 | B70: 1 | C70: 3 | D70: 2 | E70: 02 | F70: Gastos de representación en el exterior | G70: ='[1]CUENTA T FONDO 100'!AF127 -> 0 | H70: ='[1]CUENTA T VS'!AF89 -> 0 | I70: =SUM(G70:H70) -> 0 | J70: =I70/$I$25 -> 0
A71: 2 | B71: 1 | C71: 4 | F71: Gratificaciones y Bonificaciones | G71: =+G72+G74 -> 0 | H71: =+H72+H74 -> 0 | I71: =SUM(G71:H71) -> 0
A72: 2 | B72: 1 | C72: 4 | D72: 1 | F72: Bonificaciones | G72: =SUM(G73) -> 0 | H72: =SUM(H73) -> 0 | I72: =SUM(G72:H72) -> 0
A73: 2 | B73: 1 | C73: 4 | D73: 1 | E73: 01 | F73: Bonificaciones | G73: ='[1]CUENTA T FONDO 100'!AG127 -> 0 | H73: ='[1]CUENTA T VS'!AG89 -> 0 | I73: =SUM(G73:H73) -> 0 | J73: =I73/$I$25 -> 0
A74: 2 | B74: 1 | C74: 4 | D74: 2 | F74: Otras Gratificaciones y Bonificaciones | G74: =SUM(G75:G77) -> 0 | H74: =SUM(H75:H77) -> 0 | I74: =SUM(G74:H74) -> 0
A75: 2 | B75: 1 | C75: 4 | D75: 2 | E75: 01 | F75: Bono escolar | G75: ='[1]CUENTA T FONDO 100'!AH127 -> 0 | H75: ='[1]CUENTA T VS'!AH89 -> 0 | I75: =SUM(G75:H75) -> 0 | J75: =I75/$I$25 -> 0
A76: 2 | B76: 1 | C76: 4 | D76: 2 | E76: 02 | F76: Gratificaciones por pasantías | G76: ='[1]CUENTA T FONDO 100'!AI127 -> 0 | H76: ='[1]CUENTA T VS'!AI89 -> 0 | I76: =SUM(G76:H76) -> 0 | J76: =I76/$I$25 -> 0
A77: 2 | B77: 1 | C77: 4 | D77: 2 | E77: 03 | F77: Gratificaciones por aniversario de institución | G77: ='[1]CUENTA T FONDO 100'!AJ127 -> 0 | H77: ='[1]CUENTA T VS'!AJ89 -> 0 | I77: =SUM(G77:H77) -> 0 | J77: =I77/$I$25 -> 0
A78: 2 | B78: 1 | C78: 5 | F78: Contribuciones a la Seguridad Social y Riesgo Laboral | G78: =+G79+G81+G83+G85 -> 8400093.9 | H78: =+H79+H81+H83+H85 -> 0 | I78: =SUM(G78:H78) -> 8400093.9
A79: 2 | B79: 1 | C79: 5 | D79: 1 | F79: Contribuciones al seguro de salud | G79: =SUM(G80) -> 3870432.3 | H79: =SUM(H80) -> 0 | I79: =SUM(G79:H79) -> 3870432.3
A80: 2 | B80: 1 | C80: 5 | D80: 1 | E80: 01 | F80: Contribuciones al seguro de salud | G80: ='[1]CUENTA T FONDO 100'!AK127 -> 3870432.3 | H80: ='[1]CUENTA T VS'!AK89 -> 0 | I80: =SUM(G80:H80) -> 3870432.3 | J80: =I80/$I$25 -> 0.040032651
A81: 2 | B81: 1 | C81: 5 | D81: 2 | F81: Contribuciones al seguro de pensiones | G81: =SUM(G82) -> 3875889.5 | H81: =SUM(H82) -> 0 | I81: =SUM(G81:H81) -> 3875889.5
A82: 2 | B82: 1 | C82: 5 | D82: 2 | E82: 01 | F82: Contribuciones al seguro de pensiones | G82: ='[1]CUENTA T FONDO 100'!AL127 -> 3875889.5 | H82: ='[1]CUENTA T VS'!AL89 -> 0 | I82: =SUM(G82:H82) -> 3875889.5 | J82: =I82/$I$25 -> 0.040089095
A83: 2 | B83: 1 | C83: 5 | D83: 3 | F83: Contribuciones al seguro de riesgo laboral | G83: =SUM(G84) -> 653772.07 | H83: =SUM(H84) -> 0 | I83: =SUM(G83:H83) -> 653772.07
A84: 2 | B84: 1 | C84: 5 | D84: 3 | E84: 01 | F84: Contribuciones al seguro de riesgo laboral | G84: ='[1]CUENTA T FONDO 100'!AM127 -> 653772.07 | H84: ='[1]CUENTA T VS'!AM89 -> 0 | I84: =SUM(G84:H84) -> 653772.07 | J84: =I84/$I$25 -> 0.0067620944
A85: 2 | B85: 1 | C85: 5 | D85: 4 | F85: Contribuciones al plan de retiro complementario | G85: =SUM(G86) -> 0 | H85: =SUM(H86) -> 0 | I85: =SUM(G85:H85) -> 0
A86: 2 | B86: 1 | C86: 5 | D86: 4 | E86: 01 | F86: Contribuciones al plan de retiro complementario | G86: ='[1]CUENTA T FONDO 100'!AN127 -> 0 | H86: ='[1]CUENTA T VS'!AN89 -> 0 | I86: =SUM(G86:H86) -> 0 | J86: =I86/$I$25 -> 0
A87: 2 | B87: 2 | F87: Servicios No Personales | G87: =G88+G106+G111+G116+G125+G148+G157+G179+G208 -> 210535 | H87: =H88+H106+H111+H116+H125+H148+H157+H179+H208 -> 1256712.1 | I87: =SUM(G87:H87) -> 1467247.1 | J87: =I87/$I$25 -> 0.015176028
A88: 2 | B88: 2 | C88: 1 | F88: Servicios Básicos | G88: =+G89+G91+G93+G95+G97+G99+G102+G104 -> 60535 | H88: =+H89+H91+H93+H95+H97+H99+H102+H104 -> 285608.3 | I88: =SUM(G88:H88) -> 346143.3
A89: 2 | B89: 2 | C89: 1 | D89: 1 | F89: Radiocomunicación | G89: =SUM(G90) -> 0 | H89: =SUM(H90) -> 0 | I89: =SUM(G89:H89) -> 0
A90: 2 | B90: 2 | C90: 1 | D90: 1 | E90: 01 | F90: Radiocomunicación | G90: ='[1]CUENTA T FONDO 100'!AO127 -> 0 | H90: ='[1]CUENTA T VS'!AO89 -> 0 | I90: =SUM(G90:H90) -> 0 | J90: =I90/$I$25 -> 0
A91: 2 | B91: 2 | C91: 1 | D91: 2 | F91: Servicios telefónico de larga distancia | G91: =SUM(G92) -> 0 | H91: =SUM(H92) -> 0 | I91: =SUM(G91:H91) -> 0
A92: 2 | B92: 2 | C92: 1 | D92: 2 | E92: 01 | F92: Servicios telefónico de larga distancia | G92: ='[1]CUENTA T FONDO 100'!AP127 -> 0 | H92: ='[1]CUENTA T VS'!AP89 -> 0 | I92: =SUM(G92:H92) -> 0 | J92: =I92/$I$25 -> 0
A93: 2 | B93: 2 | C93: 1 | D93: 3 | F93: Teléfono local | G93: =SUM(G94) -> 0 | H93: =SUM(H94) -> 104569.42 | I93: =SUM(G93:H93) -> 104569.42
A94: 2 | B94: 2 | C94: 1 | D94: 3 | E94: 01 | F94: Teléfono local | G94: ='[1]CUENTA T FONDO 100'!AQ127 -> 0 | H94: ='[1]CUENTA T VS'!AQ89 -> 104569.42 | I94: =SUM(G94:H94) -> 104569.42 | J94: =I94/$I$25 -> 0.0010815823
A95: 2 | B95: 2 | C95: 1 | D95: 4 | F95: Telefax y correos | G95: =SUM(G96) -> 0 | H95: =SUM(H96) -> 0 | I95: =SUM(G95:H95) -> 0
A96: 2 | B96: 2 | C96: 1 | D96: 4 | E96: 01 | F96: Telefax y correos | G96: ='[1]CUENTA T FONDO 100'!AR127 -> 0 | H96: ='[1]CUENTA T VS'!AR89 -> 0 | I96: =SUM(G96:H96) -> 0 | J96: =I96/$I$25 -> 0
A97: 2 | B97: 2 | C97: 1 | D97: 5 | F97: Servicio de Internet y televisión por cable | G97: =SUM(G98) -> 0 | H97: =SUM(H98) -> 106038.88 | I97: =SUM(G97:H97) -> 106038.88
A98: 2 | B98: 2 | C98: 1 | D98: 5 | E98: 01 | F98: Servicio de Internet y televisión por cable | G98: ='[1]CUENTA T FONDO 100'!AS127 -> 0 | H98: ='[1]CUENTA T VS'!AS89 -> 106038.88 | I98: =SUM(G98:H98) -> 106038.88 | J98: =I98/$I$25 -> 0.0010967812
A99: 2 | B99: 2 | C99: 1 | D99: 6 | F99: Electricidad | G99: =SUM(G100:G101) -> 0 | H99: =SUM(H100:H101) -> 0 | I99: =SUM(G99:H99) -> 0
A100: 2 | B100: 2 | C100: 1 | D100: 6 | E100: 01 | F100: Energía eléctrica | G100: ='[1]CUENTA T FONDO 100'!AT127 -> 0 | H100: ='[1]CUENTA T VS'!AT89 -> 0 | I100: =SUM(G100:H100) -> 0 | J100: =I100/$I$25 -> 0
A101: 2 | B101: 2 | C101: 1 | D101: 6 | E101: 02 | F101: Electricidad no cortable | G101: ='[1]CUENTA T FONDO 100'!AU127 -> 0 | H101: ='[1]CUENTA T VS'!AU89 -> 0 | I101: =SUM(G101:H101) -> 0 | J101: =I101/$I$25 -> 0
A102: 2 | B102: 2 | C102: 1 | D102: 7 | F102: Agua | G102: =SUM(G103) -> 60535 | H102: =SUM(H103) -> 0 | I102: =SUM(G102:H102) -> 60535
A103: 2 | B103: 2 | C103: 1 | D103: 7 | E103: 01 | F103: Agua | G103: ='[1]CUENTA T FONDO 100'!AV127 -> 60535 | H103: ='[1]CUENTA T VS'!AV89 -> 0 | I103: =SUM(G103:H103) -> 60535 | J103: =I103/$I$25 -> 0.00062612554
A104: 2 | B104: 2 | C104: 1 | D104: 8 | F104: Recolección de residuos sólidos | G104: =SUM(G105) -> 0 | H104: =SUM(H105) -> 75000 | I104: =SUM(G104:H104) -> 75000
A105: 2 | B105: 2 | C105: 1 | D105: 8 | E105: 01 | F105: Recolección de residuos sólidos | G105: ='[1]CUENTA T FONDO 100'!AW127 -> 0 | H105: ='[1]CUENTA T VS'!AW89 -> 75000 | I105: =SUM(G105:H105) -> 75000 | J105: =I105/$I$25 -> 0.0007757399
...

Sheet mayo 2025
A1: Form. No.6 SRS
A3: Servicio Nacional de Salud
A4: Dirección de Fizcalización
A5: Consolidado de Ingresos y Gastos por Fuente de Financiamiento
A6: HOSPITAL MATERNO INFANTIL SAN LORENZO DE LOS MINA
A7: MAYO 2025
C8: Ingresos Generales:
E9: 1.- Balance Inicial / Fuente:
E10: Anticipo Financiero | H10: Otros Aportes
E11: Transferencias Corrientes
E12: Venta de Servicios | G12: 1731116.6
E13: 2.- Ingresos por Fuente / Cuenta
E14: Anticipo Financiero | G14: 0 | H14: Otros Aportes | I14: =+'[2]INGR SEGUN ORIGEN'!E37 -> 574300
E15: Transferencias Corrientes | G15: =+'[2]INGR SEGUN ORIGEN'!E12 -> 1.003168e+08 | H15: Aportes Nomina SNS | I15: 0
E16: Venta de Servicios | G16: =+'[2]INGR SEGUN ORIGEN'!E29 -> 7518709.1
H17: TOTAL INGRESOS RDS | I17: =+G10+G11+G12+I10+G14+G15+G16+I14+I15 -> 1.1014092e+08
A21: 1 | F21: 2 | G21: 3 | I21: 4 | J21: 5
A22: Código Presupuestario | F22: Descripción Gasto por Cuenta | G22: Distribución del Gasto por Fuente de Financiamiento | I22: TOTAL | J22: %
A23: Tipo | B23: Objeto | C23: Cuenta | D23: Sub-Cuenta | E23: Auxiliar | G23: Fondo 100 | H23: Venta de Servicios/ Otros Aportes
A25: 2 | F25: Gastos | G25: =+G26+G87+G212+G330+G336+G463 -> 91500562 | H25: =+H26+H87+H212+H330+H336+H463 -> 9009314.4 | I25: =SUM(G25:H25) -> 1.0050988e+08 | J25: =+J26+J87+J212+J330+J336+J463 -> 1
A26: 2 | B26: 1 | F26: Servicios Personales | G26: =+G27+G51+G64+G71+G78 -> 66630551 | H26: =+H27+H51+H64+H71+H78 -> 0 | I26: =SUM(G26:H26) -> 66630551 | J26: =I26/$I$25 -> 0.66292541
A27: 2 | B27: 1 | C27: 1 | F27: Remuneraciones | G27: =+G28+G35+G42+G44+G46 -> 54445140 | H27: =+H28+H35+H42+H44+H46 -> 0 | I27: =SUM(G27:H27) -> 54445140 | J27: =I27/$I$25 -> 0.54168946
A28: 2 | B28: 1 | C28: 1 | D28: 1 | F28: Remuneraciones al personal fijo | G28: =SUM(G29:G34) -> 53314609 | H28: =SUM(H29:H34) -> 0 | I28: =SUM(G28:H28) -> 53314609 | J28: =I28/$I$25 -> 0.5304415
A29: 2 | B29: 1 | C29: 1 | D29: 1 | E29: 01 | F29: Sueldos a empleados fijos | G29: ='[2]CUENTA T FONDO 100'!A126 -> 53314609 | H29: ='[2]CUENTA T VS'!A106 -> 0 | I29: =SUM(G29:H29) -> 53314609 | J29: =I29/$I$25 -> 0.5304415
A30: 2 | B30: 1 | C30: 1 | D30: 1 | E30: 02 | F30: Sueldos a médicos | G30: ='[2]CUENTA T FONDO 100'!B126 -> 0 | H30: ='[2]CUENTA T VS'!B106 -> 0 | I30: =SUM(G30:H30) -> 0 | J30: =I30/$I$25 -> 0
A31: 2 | B31: 1 | C31: 1 | D31: 1 | E31: 03 | F31: Ascensos a militares | G31: ='[2]CUENTA T FONDO 100'!C126 -> 0 | H31: ='[2]CUENTA T VS'!C106 -> 0 | I31: =SUM(G31:H31) -> 0 | J31: =I31/$I$25 -> 0
A32: 2 | B32: 1 | C32: 1 | D32: 1 | E32: 04 | F32: Nuevas plazas maestros | G32: ='[2]CUENTA T FONDO 100'!D126 -> 0 | H32: ='[2]CUENTA T VS'!D106 -> 0 | I32: =SUM(G32:H32) -> 0 | J32: =I32/$I$25 -> 0
A33: 2 | B33: 1 | C33: 1 | D33: 1 | E33: 05 | F33: Incentivos y escalafón | G33: ='[2]CUENTA T FONDO 100'!E126 -> 0 | H33: ='[2]CUENTA T VS'!E106 -> 0 | I33: =SUM(G33:H33) -> 0 | J33: =I33/$I$25 -> 0
A34: 2 | B34: 1 | C34: 1 | D34: 1 | E34: 06 | F34: Nuevas plazas a médicos | G34: ='[2]CUENTA T FONDO 100'!F126 -> 0 | H34: ='[2]CUENTA T VS'!F106 -> 0 | I34: =SUM(G34:H34) -> 0 | J34: =I34/$I$25 -> 0
A35: 2 | B35: 1 | C35: 1 | D35: 2 | F35: Remuneraciones al personal con carácter transitorio | G35: =SUM(G36:G41) -> 1130531 | H35: =SUM(H36:H41) -> 0 | I35: =SUM(G35:H35) -> 1130531
A36: 2 | B36: 1 | C36: 1 | D36: 2 | E36: 03 | F36: Suplencias | G36: ='[2]CUENTA T FONDO 100'!G126 -> 0 | H36: ='[2]CUENTA T VS'!G106 -> 0 | I36: =SUM(G36:H36) -> 0 | J36: =I36/$I$25 -> 0
A37: 2 | B37: 1 | C37: 1 | D37: 2 | E37: 05 | F37: Sueldo al personal nominal en período probatorio | G37: ='[2]CUENTA T FONDO 100'!H126 -> 0 | H37: ='[2]CUENTA T VS'!H106 -> 0 | I37: =SUM(G37:H37) -> 0 | J37: =I37/$I$25 -> 0
A38: 2 | B38: 1 | C38: 1 | D38: 2 | E38: 06 | F38: Jornales | G38: ='[2]CUENTA T FONDO 100'!I126 -> 0 | H38: ='[2]CUENTA T VS'!I106 -> 0 | I38: =SUM(G38:H38) -> 0 | J38: =I38/$I$25 -> 0
A39: 2 | B39: 1 | C39: 1 | D39: 2 | E39: 08 | F39: Empleados temporales | G39: ='[2]CUENTA T FONDO 100'!J126 -> 1130531 | H39: ='[2]CUENTA T VS'!J106 -> 0 | I39: =SUM(G39:H39) -> 1130531 | J39: =I39/$I$25 -> 0.01124796
A40: 2 | B40: 1 | C40: 1 | D40: 2 | E40: 09 | F40: Personal de carácter eventual | G40: ='[2]CUENTA T FONDO 100'!K126 -> 0 | H40: ='[2]CUENTA T VS'!K106 -> 0 | I40: =SUM(G40:H40) -> 0 | J40: =I40/$I$25 -> 0
A41: 2 | B41: 1 | C41: 1 | D41: 2 | E41: 11 | F41: Interinato | G41: ='[2]CUENTA T FONDO 100'!L126 -> 0 | H41: ='[2]CUENTA T VS'!L106 -> 0 | I41: =SUM(G41:H41) -> 0 | J41: =I41/$I$25 -> 0
A42: 2 | B42: 1 | C42: 1 | D42: 3 | F42: Sueldos al personal fijo en trámite de pensiones | G42: =SUM(G43) -> 0 | H42: =SUM(H43) -> 0 | I42: =SUM(G42:H42) -> 0
A43: 2 | B43: 1 | C43: 1 | D43: 3 | E43: 01 | F43: Sueldos al personal fijo en trámite de pensiones | G43: ='[2]CUENTA T FONDO 100'!M126 -> 0 | H43: ='[2]CUENTA T VS'!M106 -> 0 | I43: =SUM(G43:H43) -> 0 | J43: =I43/$I$25 -> 0
A44: 2 | B44: 1 | C44: 1 | D44: 4 | F44: Sueldo anual no. 13 | G44: =SUM(G45) -> 0 | H44: =SUM(H45) -> 0 | I44: =SUM(G44:H44) -> 0
A45: 2 | B45: 1 | C45: 1 | D45: 4 | E45: 01 | F45: Sueldo anual no. 13 | G45: ='[2]CUENTA T FONDO 100'!N126 -> 0 | H45: ='[2]CUENTA T VS'!N106 -> 0 | I45: =SUM(G45:H45) -> 0 | J45: =I45/$I$25 -> 0
A46: 2 | B46: 1 | C46: 1 | D46: 5 | F46: Prestaciones económinas | G46: =SUM(G47:G50) -> 0 | H46: =SUM(H47:H50) -> 0 | I46: =SUM(G46:H46) -> 0
A47: 2 | B47: 1 | C47: 1 | D47: 5 | E47: 01 | F47: Prestaciones económinas | G47: ='[2]CUENTA T FONDO 100'!O126 -> 0 | H47: ='[2]CUENTA T VS'!O106 -> 0 | I47: =SUM(G47:H47) -> 0 | J47: =I47/$I$25 -> 0
A48: 2 | B48: 1 | C48: 1 | D48: 5 | E48: 02 | F48: Pago de porcentaje por desvinculación de cargo | G48: ='[2]CUENTA T FONDO 100'!P126 -> 0 | H48: ='[2]CUENTA T VS'!P106 -> 0 | I48: =SUM(G48:H48) -> 0 | J48: =I48/$I$25 -> 0
A49: 2 | B49: 1 | C49: 1 | D49: 5 | E49: 03 | F49: Prestación laboral por desvinculación | G49: ='[2]CUENTA T FONDO 100'!Q126 -> 0 | H49: ='[2]CUENTA T VS'!Q106 -> 0 | I49: =SUM(G49:H49) -> 0 | J49: =I49/$I$25 -> 0
A50: 2 | B50: 1 | C50: 1 | D50: 5 | E50: 04 | F50: Proporción de vacaciones no disfrutadas | G50: ='[2]CUENTA T FONDO 100'!R126 -> 0 | H50: ='[2]CUENTA T VS'!R106 -> 0 | I50: =SUM(G50:H50) -> 0 | J50: =I50/$I$25 -> 0
A51: 2 | B51: 1 | C51: 2 | F51: Sobresueldos | G51: =+G52+G54 -> 3807608.3 | H51: =+H52+H54 -> 0 | I51: =SUM(G51:H51) -> 3807608.3
A52: 2 | B52: 1 | C52: 2 | D52: 1 | F52: Primas por antigüedad | G52: =SUM(G53) -> 2723298.2 | H52: =SUM(H53) -> 0 | I52: =SUM(G52:H52) -> 2723298.2
A53: 2 | B53: 1 | C53: 2 | D53: 1 | E53: 01 | F53: Primas por antigüedad | G53: ='[2]CUENTA T FONDO 100'!S126 -> 2723298.2 | H53: ='[2]CUENTA T VS'!S106 -> 0 | I53: =SUM(G53:H53) -> 2723298.2 | J53: =I53/$I$25 -> 0.027094832
A54: 2 | B54: 1 | C54: 2 | D54: 2 | F54: Compensación | G54: =SUM(G55:G63) -> 1084310.1 | H54: =SUM(H55:H63) -> 0 | I54: =SUM(G54:H54) -> 1084310.1
A55: 2 | B55: 1 | C55: 2 | D55: 2 | E55: 01 | F55: Compensación por gastos de alimentación | G55: ='[2]CUENTA T FONDO 100'!T126 -> 0 | H55: ='[2]CUENTA T VS'!T106 -> 0 | I55: =SUM(G55:H55) -> 0 | J55: =I55/$I$25 -> 0
A56: 2 | B56: 1 | C56: 2 | D56: 2 | E56: 03 | F56: Pago de horas extraordinarias | G56: ='[2]CUENTA T FONDO 100'!U126 -> 0 | H56: ='[2]CUENTA T VS'!U106 -> 0 | I56: =SUM(G56:H56) -> 0 | J56: =I56/$I$25 -> 0
A57: 2 | B57: 1 | C57: 2 | D57: 2 | E57: 04 | F57: Prima de transporte | G57: ='[2]CUENTA T FONDO 100'!V126 -> 0 | H57: ='[2]CUENTA T VS'!V106 -> 0 | I57: =SUM(G57:H57) -> 0 | J57: =I57/$I$25 -> 0
A58: 2 | B58: 1 | C58: 2 | D58: 2 | E58: 05 | F58: Compensación servicios de Seguridad | G58: ='[2]CUENTA T FONDO 100'!W126 -> 45000 | H58: ='[2]CUENTA T VS'!W106 -> 0 | I58: =SUM(G58:H58) -> 45000 | J58: =I58/$I$25 -> 0.00044771719
A59: 2 | B59: 1 | C59: 2 | D59: 2 | E59: 06 | F59: Incentivo por Rendimieto Individual | G59: ='[2]CUENTA T FONDO 100'!X126 -> 0 | H59: ='[2]CUENTA T VS'!X106 -> 0 | I59: =SUM(G59:H59) -> 0 | J59: =I59/$I$25 -> 0
A60: 2 | B60: 1 | C60: 2 | D60: 2 | E60: 07 | F60: Compensación por distancia | G60: ='[2]CUENTA T FONDO 100'!Y126 -> 0 | H60: ='[2]CUENTA T VS'!Y106 -> 0 | I60: =SUM(G60:H60) -> 0 | J60: =I60/$I$25 -> 0
A61: 2 | B61: 1 | C61: 2 | D61: 2 | E61: 08 | F61: Compensaciones especiales | G61: ='[2]CUENTA T FONDO 100'!Z126 -> 334800 | H61: ='[2]CUENTA T VS'!Z106 -> 0 | I61: =SUM(G61:H61) -> 334800 | J61: =I61/$I$25 -> 0.0033310159
A62: 2 | B62: 1 | C62: 2 | D62: 2 | E62: 09 | F62: Bono por desempeño a servidores de carrera | G62: ='[2]CUENTA T FONDO 100'!AA126 -> 443970.11 | H62: ='[2]CUENTA T VS'!AA106 -> 0 | I62: =SUM(G62:H62) -> 443970.11 | J62: =I62/$I$25 -> 0.0044171789
A63: 2 | B63: 1 | C63: 2 | D63: 2 | E63: 10 | F63: Compensacion por cumplimiento de indicadores | G63: ='[2]CUENTA T FONDO 100'!AB126 -> 260539.96 | H63: ='[2]CUENTA T VS'!AB106 -> 0 | I63: =SUM(G63:H63) -> 260539.96 | J63: =I63/$I$25 -> 0.0025921827
A64: 2 | B64: 1 | C64: 3 | F64: Dietas y Gastos de Representación | G64: =+G65+G68 -> 0 | H64: =+H65+H68 -> 0 | I64: =SUM(G64:H64) -> 0
A65: 2 | B65: 1 | C65: 3 | D65: 1 | F65: Dietas | G65: =SUM(G66:G67) -> 0 | H65: =SUM(H66:H67) -> 0 | I65: =SUM(G65:H65) -> 0
A66: 2 | B66: 1 | C66: 3 | D66: 1 | E66: 01 | F66: Dietas en el país | G66: ='[2]CUENTA T FONDO 100'!AC126 -> 0 | H66: ='[2]CUENTA T VS'!AC106 -> 0 | I66: =SUM(G66:H66) -> 0 | J66: =I66/$I$25 -> 0
A67: 2 | B67: 1 | C67: 3 | D67: 1 | E67: 02 | F67: Dietas en el exterior | G67: ='[2]CUENTA T FONDO 100'!AD126 -> 0 | H67: ='[2]CUENTA T VS'!AD106 -> 0 | I67: =SUM(G67:H67) -> 0 | J67: =I67/$I$25 -> 0
A68: 2 | B68: 1 | C68: 3 | D68: 2 | F68: Gastos de representación | G68: =SUM(G69:G70) -> 0 | H68: =SUM(H69:H70) -> 0 | I68: =SUM(G68:H68) -> 0
A69: 2 | B69: 1 | C69: 3 | D69: 2 | E69: 01 | F69: Gastos de representación en el país | G69: ='[2]CUENTA T FONDO 100'!AE126 -> 0 | H69: ='[2]CUENTA T VS'!AE106 -> 0 | I69: =SUM(G69:H69) -> 0 | J69: =I69/$I$25 -> 0
A70: 2 | B70: 1 | C70: 3 | D70: 2 | E70: 02 | F70: Gastos de representación en el exterior | G70: ='[2]CUENTA T FONDO 100'!AF126 -> 0 | H70: ='[2]CUENTA T VS'!AF106 -> 0 | I70: =SUM(G70:H70) -> 0 | J70: =I70/$I$25 -> 0
A71: 2 | B71: 1 | C71: 4 | F71: Gratificaciones y Bonificaciones | G71: =+G72+G74 -> 0 | H71: =+H72+H74 -> 0 | I71: =SUM(G71:H71) -> 0
A72: 2 | B72: 1 | C72: 4 | D72: 1 | F72: Bonificaciones | G72: =SUM(G73) -> 0 | H72: =SUM(H73) -> 0 | I72: =SUM(G72:H72) -> 0
A73: 2 | B73: 1 | C73: 4 | D73: 1 | E73: 01 | F73: Bonificaciones | G73: ='[2]CUENTA T FONDO 100'!AG126 -> 0 | H73: ='[2]CUENTA T VS'!AG106 -> 0 | I73: =SUM(G73:H73) -> 0 | J73: =I73/$I$25 -> 0
A74: 2 | B74: 1 | C74: 4 | D74: 2 | F74: Otras Gratificaciones y Bonificaciones | G74: =SUM(G75:G77) -> 0 | H74: =SUM(H75:H77) -> 0 | I74: =SUM(G74:H74) -> 0
A75: 2 | B75: 1 | C75: 4 | D75: 2 | E75: 01 | F75: Bono escolar | G75: ='[2]CUENTA T FONDO 100'!AH126 -> 0 | H75: ='[2]CUENTA T VS'!AH106 -> 0 | I75: =SUM(G75:H75) -> 0 | J75: =I75/$I$25 -> 0
A76: 2 | B76: 1 | C76: 4 | D76: 2 | E76: 02 | F76: Gratificaciones por pasantías | G76: ='[2]CUENTA T FONDO 100'!AI126 -> 0 | H76: ='[2]CUENTA T VS'!AI106 -> 0 | I76: =SUM(G76:H76) -> 0 | J76: =I76/$I$25 -> 0
A77: 2 | B77: 1 | C77: 4 | D77: 2 | E77: 03 | F77: Gratificaciones por aniversario de institución | G77: ='[2]CUENTA T FONDO 100'!AJ126 -> 0 | H77: ='[2]CUENTA T VS'!AJ106 -> 0 | I77: =SUM(G77:H77) -> 0 | J77: =I77/$I$25 -> 0
A78: 2 | B78: 1 | C78: 5 | F78: Contribuciones a la Seguridad Social y Riesgo Laboral | G78: =+G79+G81+G83+G85 -> 8377802.1 | H78: =+H79+H81+H83+H85 -> 0 | I78: =SUM(G78:H78) -> 8377802.1
A79: 2 | B79: 1 | C79: 5 | D79: 1 | F79: Contribuciones al seguro de salud | G79: =SUM(G80) -> 3860162.8 | H79: =SUM(H80) -> 0 | I79: =SUM(G79:H79) -> 3860162.8
A80: 2 | B80: 1 | C80: 5 | D80: 1 | E80: 01 | F80: Contribuciones al seguro de salud | G80: ='[2]CUENTA T FONDO 100'!AK126 -> 3860162.8 | H80: ='[2]CUENTA T VS'!AK106 -> 0 | I80: =SUM(G80:H80) -> 3860162.8 | J80: =I80/$I$25 -> 0.038405805
A81: 2 | B81: 1 | C81: 5 | D81: 2 | F81: Contribuciones al seguro de pensiones | G81: =SUM(G82) -> 3865605.4 | H81: =SUM(H82) -> 0 | I81: =SUM(G81:H81) -> 3865605.4
A82: 2 | B82: 1 | C82: 5 | D82: 2 | E82: 01 | F82: Contribuciones al seguro de pensiones | G82: ='[2]CUENTA T FONDO 100'!AL126 -> 3865605.4 | H82: ='[2]CUENTA T VS'!AL106 -> 0 | I82: =SUM(G82:H82) -> 3865605.4 | J82: =I82/$I$25 -> 0.038459956
A83: 2 | B83: 1 | C83: 5 | D83: 3 | F83: Contribuciones al seguro de riesgo laboral | G83: =SUM(G84) -> 652033.92 | H83: =SUM(H84) -> 0 | I83: =SUM(G83:H83) -> 652033.92
A84: 2 | B84: 1 | C84: 5 | D84: 3 | E84: 01 | F84: Contribuciones al seguro de riesgo laboral | G84: ='[2]CUENTA T FONDO 100'!AM126 -> 652033.92 | H84: ='[2]CUENTA T VS'!AM106 -> 0 | I84: =SUM(G84:H84) -> 652033.92 | J84: =I84/$I$25 -> 0.0064872622
A85: 2 | B85: 1 | C85: 5 | D85: 4 | F85: Contribuciones al plan de retiro complementario | G85: =SUM(G86) -> 0 | H85: =SUM(H86) -> 0 | I85: =SUM(G85:H85) -> 0
A86: 2 | B86: 1 | C86: 5 | D86: 4 | E86: 01 | F86: Contribuciones al plan de retiro complementario | G86: ='[2]CUENTA T FONDO 100'!AN126 -> 0 | H86: ='[2]CUENTA T VS'!AN106 -> 0 | I86: =SUM(G86:H86) -> 0 | J86: =I86/$I$25 -> 0
A87: 2 | B87: 2 | F87: Servicios No Personales | G87: =G88+G106+G111+G116+G125+G148+G157+G179+G208 -> 1680824.8 | H87: =H88+H106+H111+H116+H125+H148+H157+H179+H208 -> 2044062.6 | I87: =SUM(G87:H87) -> 3724887.4 | J87: =I87/$I$25 -> 0.037059914
A88: 2 | B88: 2 | C88: 1 | F88: Servicios Básicos | G88: =+G89+G91+G93+G95+G97+G99+G102+G104 -> 60535 | H88: =+H89+H91+H93+H95+H97+H99+H102+H104 -> 1098463.4 | I88: =SUM(G88:H88) -> 1158998.4
A89: 2 | B89: 2 | C89: 1 | D89: 1 | F89: Radiocomunicación | G89: =SUM(G90) -> 0 | H89: =SUM(H90) -> 0 | I89: =SUM(G89:H89) -> 0
A90: 2 | B90: 2 | C90: 1 | D90: 1 | E90: 01 | F90: Radiocomunicación | G90: ='[2]CUENTA T FONDO 100'!AO126 -> 0 | H90: ='[2]CUENTA T VS'!AO106 -> 0 | I90: =SUM(G90:H90) -> 0 | J90: =I90/$I$25 -> 0
A91: 2 | B91: 2 | C91: 1 | D91: 2 | F91: Servicios telefónico de larga distancia | G91: =SUM(G92) -> 0 | H91: =SUM(H92) -> 0 | I91: =SUM(G91:H91) -> 0
A92: 2 | B92: 2 | C92: 1 | D92: 2 | E92: 01 | F92: Servicios telefónico de larga distancia | G92: ='[2]CUENTA T FONDO 100'!AP126 -> 0 | H92: ='[2]CUENTA T VS'!AP106 -> 0 | I92: =SUM(G92:H92) -> 0 | J92: =I92/$I$25 -> 0
A93: 2 | B93: 2 | C93: 1 | D93: 3 | F93: Teléfono local | G93: =SUM(G94) -> 0 | H93: =SUM(H94) -> 209036.41 | I93: =SUM(G93:H93) -> 209036.41
A94: 2 | B94: 2 | C94: 1 | D94: 3 | E94: 01 | F94: Teléfono local | G94: ='[2]CUENTA T FONDO 100'!AQ126 -> 0 | H94: ='[2]CUENTA T VS'!AQ106 -> 209036.41 | I94: =SUM(G94:H94) -> 209036.41 | J94: =I94/$I$25 -> 0.0020797599
A95: 2 | B95: 2 | C95: 1 | D95: 4 | F95: Telefax y correos | G95: =SUM(G96) -> 0 | H95: =SUM(H96) -> 0 | I95: =SUM(G95:H95) -> 0
A96: 2 | B96: 2 | C96: 1 | D96: 4 | E96: 01 | F96: Telefax y correos | G96: ='[2]CUENTA T FONDO 100'!AR126 -> 0 | H96: ='[2]CUENTA T VS'!AR106 -> 0 | I96: =SUM(G96:H96) -> 0 | J96: =I96/$I$25 -> 0
A97: 2 | B97: 2 | C97: 1 | D97: 5 | F97: Servicio de Internet y televisión por cable | G97: =SUM(G98) -> 0 | H97: =SUM(H98) -> 104427.01 | I97: =SUM(G97:H97) -> 104427.01
A98: 2 | B98: 2 | C98: 1 | D98: 5 | E98: 01 | F98: Servicio de Internet y televisión por cable | G98: ='[2]CUENTA T FONDO 100'!AS126 -> 0 | H98: ='[2]CUENTA T VS'!AS106 -> 104427.01 | I98: =SUM(G98:H98) -> 104427.01 | J98: =I98/$I$25 -> 0.0010389726
A99: 2 | B99: 2 | C99: 1 | D99: 6 | F99: Electricidad | G99: =SUM(G100:G101) -> 0 | H99: =SUM(H100:H101) -> 0 | I99: =SUM(G99:H99) -> 0
A100: 2 | B100: 2 | C100: 1 | D100: 6 | E100: 01 | F100: Energía eléctrica | G100: ='[2]CUENTA T FONDO 100'!AT126 -> 0 | H100: ='[2]CUENTA T VS'!AT106 -> 0 | I100: =SUM(G100:H100) -> 0 | J100: =I100/$I$25 -> 0
A101: 2 | B101: 2 | C101: 1 | D101: 6 | E101: 02 | F101: Electricidad no cortable | G101: ='[2]CUENTA T FONDO 100'!AU126 -> 0 | H101: ='[2]CUENTA T VS'!AU106 -> 0 | I101: =SUM(G101:H101) -> 0 | J101: =I101/$I$25 -> 0
A102: 2 | B102: 2 | C102: 1 | D102: 7 | F102: Agua | G102: =SUM(G103) -> 60535 | H102: =SUM(H103) -> 0 | I102: =SUM(G102:H102) -> 60535
A103: 2 | B103: 2 | C103: 1 | D103: 7 | E103: 01 | F103: Agua | G103: ='[2]CUENTA T FONDO 100'!AV126 -> 60535 | H103: ='[2]CUENTA T VS'!AV106 -> 0 | I103: =SUM(G103:H103) -> 60535 | J103: =I103/$I$25 -> 0.00060227912
A104: 2 | B104: 2 | C104: 1 | D104: 8 | F104: Recolección de residuos sólidos | G104: =SUM(G105) -> 0 | H104: =SUM(H105) -> 785000 | I104: =SUM(G104:H104) -> 785000
A105: 2 | B105: 2 | C105: 1 | D105: 8 | E105: 01 | F105: Recolección de residuos sólidos | G105: ='[2]CUENTA T FONDO 100'!AW126 -> 0 | H105: ='[2]CUENTA T VS'!AW106 -> 785000 | I105: =SUM(G105:H105) -> 785000 | J105: =I105/$I$25 -> 0.0078101777
...

Sheet junioo 
A1: Form. No.6 SRS
A3: Servicio Nacional de Salud
A4: Dirección de Fizcalización
A5: Consolidado de Ingresos y Gastos por Fuente de Financiamiento
A6: HOSPITAL MATERNO INFANTIL SAN LORENZO DE LOS MINA
A7: JUNIO 2025
C8: Ingresos Generales:
E9: 1.- Balance Inicial / Fuente:
E10: Anticipo Financiero | H10: Otros Aportes
E11: Transferencias Corrientes
E12: Venta de Servicios | G12: 1377881.2
E13: 2.- Ingresos por Fuente / Cuenta
E14: Anticipo Financiero | G14: 0 | H14: Otros Aportes | I14: =+'[3]INGR SEGUN ORIGEN'!E31 -> 1026168.7
E15: Transferencias Corrientes | G15: =+'[3]INGR SEGUN ORIGEN'!E12 -> 1.003168e+08 | H15: Aportes Nomina SNS | I15: 0
E16: Venta de Servicios | G16: =+'[3]INGR SEGUN ORIGEN'!E23 -> 3631511.4
H17: TOTAL INGRESOS RDS | I17: =+G10+G11+G12+I10+G14+G15+G16+I14+I15 -> 1.0635236e+08
A21: 1 | F21: 2 | G21: 3 | I21: 4 | J21: 5
A22: Código Presupuestario | F22: Descripción Gasto por Cuenta | G22: Distribución del Gasto por Fuente de Financiamiento | I22: TOTAL | J22: %
A23: Tipo | B23: Objeto | C23: Cuenta | D23: Sub-Cuenta | E23: Auxiliar | G23: Fondo 100 | H23: Venta de Servicios/ Otros Aportes
A25: 2 | F25: Gastos | G25: =+G26+G87+G212+G330+G336+G463 -> 93930744 | H25: =+H26+H87+H212+H330+H336+H463 -> 6513141.9 | I25: =SUM(G25:H25) -> 1.0044389e+08 | J25: =+J26+J87+J212+J330+J336+J463 -> 1
A26: 2 | B26: 1 | F26: Servicios Personales | G26: =+G27+G51+G64+G71+G78 -> 66583615 | H26: =+H27+H51+H64+H71+H78 -> 0 | I26: =SUM(G26:H26) -> 66583615 | J26: =I26/$I$25 -> 0.66289366
A27: 2 | B27: 1 | C27: 1 | F27: Remuneraciones | G27: =+G28+G35+G42+G44+G46 -> 54868543 | H27: =+H28+H35+H42+H44+H46 -> 0 | I27: =SUM(G27:H27) -> 54868543 | J27: =I27/$I$25 -> 0.54626065
A28: 2 | B28: 1 | C28: 1 | D28: 1 | F28: Remuneraciones al personal fijo | G28: =SUM(G29:G34) -> 53275909 | H28: =SUM(H29:H34) -> 0 | I28: =SUM(G28:H28) -> 53275909 | J28: =I28/$I$25 -> 0.5304047
A29: 2 | B29: 1 | C29: 1 | D29: 1 | E29: 01 | F29: Sueldos a empleados fijos | G29: ='[3]CUENTA T FONDO 100'!A126 -> 53275909 | H29: ='[3]CUENTA T VS'!A106 -> 0 | I29: =SUM(G29:H29) -> 53275909 | J29: =I29/$I$25 -> 0.5304047
A30: 2 | B30: 1 | C30: 1 | D30: 1 | E30: 02 | F30: Sueldos a médicos | G30: ='[3]CUENTA T FONDO 100'!B126 -> 0 | H30: ='[3]CUENTA T VS'!B106 -> 0 | I30: =SUM(G30:H30) -> 0 | J30: =I30/$I$25 -> 0
A31: 2 | B31: 1 | C31: 1 | D31: 1 | E31: 03 | F31: Ascensos a militares | G31: ='[3]CUENTA T FONDO 100'!C126 -> 0 | H31: ='[3]CUENTA T VS'!C106 -> 0 | I31: =SUM(G31:H31) -> 0 | J31: =I31/$I$25 -> 0
A32: 2 | B32: 1 | C32: 1 | D32: 1 | E32: 04 | F32: Nuevas plazas maestros | G32: ='[3]CUENTA T FONDO 100'!D126 -> 0 | H32: ='[3]CUENTA T VS'!D106 -> 0 | I32: =SUM(G32:H32) -> 0 | J32: =I32/$I$25 -> 0
A33: 2 | B33: 1 | C33: 1 | D33: 1 | E33: 05 | F33: Incentivos y escalafón | G33: ='[3]CUENTA T FONDO 100'!E126 -> 0 | H33: ='[3]CUENTA T VS'!E106 -> 0 | I33: =SUM(G33:H33) -> 0 | J33: =I33/$I$25 -> 0
A34: 2 | B34: 1 | C34: 1 | D34: 1 | E34: 06 | F34: Nuevas plazas a médicos | G34: ='[3]CUENTA T FONDO 100'!F126 -> 0 | H34: ='[3]CUENTA T VS'!F106 -> 0 | I34: =SUM(G34:H34) -> 0 | J34: =I34/$I$25 -> 0
A35: 2 | B35: 1 | C35: 1 | D35: 2 | F35: Remuneraciones al personal con carácter transitorio | G35: =SUM(G36:G41) -> 1130531 | H35: =SUM(H36:H41) -> 0 | I35: =SUM(G35:H35) -> 1130531
A36: 2 | B36: 1 | C36: 1 | D36: 2 | E36: 03 | F36: Suplencias | G36: ='[3]CUENTA T FONDO 100'!G126 -> 0 | H36: ='[3]CUENTA T VS'!G106 -> 0 | I36: =SUM(G36:H36) -> 0 | J36: =I36/$I$25 -> 0
A37: 2 | B37: 1 | C37: 1 | D37: 2 | E37: 05 | F37: Sueldo al personal nominal en período probatorio | G37: ='[3]CUENTA T FONDO 100'!H126 -> 0 | H37: ='[3]CUENTA T VS'!H106 -> 0 | I37: =SUM(G37:H37) -> 0 | J37: =I37/$I$25 -> 0
A38: 2 | B38: 1 | C38: 1 | D38: 2 | E38: 06 | F38: Jornales | G38: ='[3]CUENTA T FONDO 100'!I126 -> 0 | H38: ='[3]CUENTA T VS'!I106 -> 0 | I38: =SUM(G38:H38) -> 0 | J38: =I38/$I$25 -> 0
A39: 2 | B39: 1 | C39: 1 | D39: 2 | E39: 08 | F39: Empleados temporales | G39: ='[3]CUENTA T FONDO 100'!J126 -> 1130531 | H39: ='[3]CUENTA T VS'!J106 -> 0 | I39: =SUM(G39:H39) -> 1130531 | J39: =I39/$I$25 -> 0.011255349
A40: 2 | B40: 1 | C40: 1 | D40: 2 | E40: 09 | F40: Personal de carácter eventual | G40: ='[3]CUENTA T FONDO 100'!K126 -> 0 | H40: ='[3]CUENTA T VS'!K106 -> 0 | I40: =SUM(G40:H40) -> 0 | J40: =I40/$I$25 -> 0
A41: 2 | B41: 1 | C41: 1 | D41: 2 | E41: 11 | F41: Interinato | G41: ='[3]CUENTA T FONDO 100'!L126 -> 0 | H41: ='[3]CUENTA T VS'!L106 -> 0 | I41: =SUM(G41:H41) -> 0 | J41: =I41/$I$25 -> 0
A42: 2 | B42: 1 | C42: 1 | D42: 3 | F42: Sueldos al personal fijo en trámite de pensiones | G42: =SUM(G43) -> 0 | H42: =SUM(H43) -> 0 | I42: =SUM(G42:H42) -> 0
A43: 2 | B43: 1 | C43: 1 | D43: 3 | E43: 01 | F43: Sueldos al personal fijo en trámite de pensiones | G43: ='[3]CUENTA T FONDO 100'!M126 -> 0 | H43: ='[3]CUENTA T VS'!M106 -> 0 | I43: =SUM(G43:H43) -> 0 | J43: =I43/$I$25 -> 0
A44: 2 | B44: 1 | C44: 1 | D44: 4 | F44: Sueldo anual no. 13 | G44: =SUM(G45) -> 0 | H44: =SUM(H45) -> 0 | I44: =SUM(G44:H44) -> 0
A45: 2 | B45: 1 | C45: 1 | D45: 4 | E45: 01 | F45: Sueldo anual no. 13 | G45: ='[3]CUENTA T FONDO 100'!N126 -> 0 | H45: ='[3]CUENTA T VS'!N106 -> 0 | I45: =SUM(G45:H45) -> 0 | J45: =I45/$I$25 -> 0
A46: 2 | B46: 1 | C46: 1 | D46: 5 | F46: Prestaciones económinas | G46: =SUM(G47:G50) -> 462102.51 | H46: =SUM(H47:H50) -> 0 | I46: =SUM(G46:H46) -> 462102.51
A47: 2 | B47: 1 | C47: 1 | D47: 5 | E47: 01 | F47: Prestaciones económinas | G47: ='[3]CUENTA T FONDO 100'!O126 -> 0 | H47: ='[3]CUENTA T VS'!O106 -> 0 | I47: =SUM(G47:H47) -> 0 | J47: =I47/$I$25 -> 0
A48: 2 | B48: 1 | C48: 1 | D48: 5 | E48: 02 | F48: Pago de porcentaje por desvinculación de cargo | G48: ='[3]CUENTA T FONDO 100'!P126 -> 0 | H48: ='[3]CUENTA T VS'!P106 -> 0 | I48: =SUM(G48:H48) -> 0 | J48: =I48/$I$25 -> 0
A49: 2 | B49: 1 | C49: 1 | D49: 5 | E49: 03 | F49: Prestación laboral por desvinculación | G49: ='[3]CUENTA T FONDO 100'!Q126 -> 211733.33 | H49: ='[3]CUENTA T VS'!Q106 -> 0 | I49: =SUM(G49:H49) -> 211733.33 | J49: =I49/$I$25 -> 0.0021079763
A50: 2 | B50: 1 | C50: 1 | D50: 5 | E50: 04 | F50: Proporción de vacaciones no disfrutadas | G50: ='[3]CUENTA T FONDO 100'!R126 -> 250369.18 | H50: ='[3]CUENTA T VS'!R106 -> 0 | I50: =SUM(G50:H50) -> 250369.18 | J50: =I50/$I$25 -> 0.0024926274
A51: 2 | B51: 1 | C51: 2 | F51: Sobresueldos | G51: =+G52+G54 -> 3343226.2 | H51: =+H52+H54 -> 0 | I51: =SUM(G51:H51) -> 3343226.2
A52: 2 | B52: 1 | C52: 2 | D52: 1 | F52: Primas por antigüedad | G52: =SUM(G53) -> 2707086.2 | H52: =SUM(H53) -> 0 | I52: =SUM(G52:H52) -> 2707086.2
A53: 2 | B53: 1 | C53: 2 | D53: 1 | E53: 01 | F53: Primas por antigüedad | G53: ='[3]CUENTA T FONDO 100'!S126 -> 2707086.2 | H53: ='[3]CUENTA T VS'!S106 -> 0 | I53: =SUM(G53:H53) -> 2707086.2 | J53: =I53/$I$25 -> 0.026951229
A54: 2 | B54: 1 | C54: 2 | D54: 2 | F54: Compensación | G54: =SUM(G55:G63) -> 636139.96 | H54: =SUM(H55:H63) -> 0 | I54: =SUM(G54:H54) -> 636139.96
A55: 2 | B55: 1 | C55: 2 | D55: 2 | E55: 01 | F55: Compensación por gastos de alimentación | G55: ='[3]CUENTA T FONDO 100'!T126 -> 0 | H55: ='[3]CUENTA T VS'!T106 -> 0 | I55: =SUM(G55:H55) -> 0 | J55: =I55/$I$25 -> 0
A56: 2 | B56: 1 | C56: 2 | D56: 2 | E56: 03 | F56: Pago de horas extraordinarias | G56: ='[3]CUENTA T FONDO 100'!U126 -> 0 | H56: ='[3]CUENTA T VS'!U106 -> 0 | I56: =SUM(G56:H56) -> 0 | J56: =I56/$I$25 -> 0
A57: 2 | B57: 1 | C57: 2 | D57: 2 | E57: 04 | F57: Prima de transporte | G57: ='[3]CUENTA T FONDO 100'!V126 -> 0 | H57: ='[3]CUENTA T VS'!V106 -> 0 | I57: =SUM(G57:H57) -> 0 | J57: =I57/$I$25 -> 0
A58: 2 | B58: 1 | C58: 2 | D58: 2 | E58: 05 | F58: Compensación servicios de Seguridad | G58: ='[3]CUENTA T FONDO 100'!W126 -> 45000 | H58: ='[3]CUENTA T VS'!W106 -> 0 | I58: =SUM(G58:H58) -> 45000 | J58: =I58/$I$25 -> 0.00044801134
A59: 2 | B59: 1 | C59: 2 | D59: 2 | E59: 06 | F59: Incentivo por Rendimieto Individual | G59: ='[3]CUENTA T FONDO 100'!X126 -> 0 | H59: ='[3]CUENTA T VS'!X106 -> 0 | I59: =SUM(G59:H59) -> 0 | J59: =I59/$I$25 -> 0
A60: 2 | B60: 1 | C60: 2 | D60: 2 | E60: 07 | F60: Compensación por distancia | G60: ='[3]CUENTA T FONDO 100'!Y126 -> 0 | H60: ='[3]CUENTA T VS'!Y106 -> 0 | I60: =SUM(G60:H60) -> 0 | J60: =I60/$I$25 -> 0
A61: 2 | B61: 1 | C61: 2 | D61: 2 | E61: 08 | F61: Compensaciones especiales | G61: ='[3]CUENTA T FONDO 100'!Z126 -> 330600 | H61: ='[3]CUENTA T VS'!Z106 -> 0 | I61: =SUM(G61:H61) -> 330600 | J61: =I61/$I$25 -> 0.00329139
A62: 2 | B62: 1 | C62: 2 | D62: 2 | E62: 09 | F62: Bono por desempeño a servidores de carrera | G62: ='[3]CUENTA T FONDO 100'!AA126 -> 0 | H62: ='[3]CUENTA T VS'!AA106 -> 0 | I62: =SUM(G62:H62) -> 0 | J62: =I62/$I$25 -> 0
A63: 2 | B63: 1 | C63: 2 | D63: 2 | E63: 10 | F63: Compensacion por cumplimiento de indicadores | G63: ='[3]CUENTA T FONDO 100'!AB126 -> 260539.96 | H63: ='[3]CUENTA T VS'!AB106 -> 0 | I63: =SUM(G63:H63) -> 260539.96 | J63: =I63/$I$25 -> 0.0025938857
A64: 2 | B64: 1 | C64: 3 | F64: Dietas y Gastos de Representación | G64: =+G65+G68 -> 0 | H64: =+H65+H68 -> 0 | I64: =SUM(G64:H64) -> 0
A65: 2 | B65: 1 | C65: 3 | D65: 1 | F65: Dietas | G65: =SUM(G66:G67) -> 0 | H65: =SUM(H66:H67) -> 0 | I65: =SUM(G65:H65) -> 0
A66: 2 | B66: 1 | C66: 3 | D66: 1 | E66: 01 | F66: Dietas en el país | G66: ='[3]CUENTA T FONDO 100'!AC126 -> 0 | H66: ='[3]CUENTA T VS'!AC106 -> 0 | I66: =SUM(G66:H66) -> 0 | J66: =I66/$I$25 -> 0
A67: 2 | B67: 1 | C67: 3 | D67: 1 | E67: 02 | F67: Dietas en el exterior | G67: ='[3]CUENTA T FONDO 100'!AD126 -> 0 | H67: ='[3]CUENTA T VS'!AD106 -> 0 | I67: =SUM(G67:H67) -> 0 | J67: =I67/$I$25 -> 0
A68: 2 | B68: 1 | C68: 3 | D68: 2 | F68: Gastos de representación | G68: =SUM(G69:G70) -> 0 | H68: =SUM(H69:H70) -> 0 | I68: =SUM(G68:H68) -> 0
A69: 2 | B69: 1 | C69: 3 | D69: 2 | E69: 01 | F69: Gastos de representación en el país | G69: ='[3]CUENTA T FONDO 100'!AE126 -> 0 | H69: ='[3]CUENTA T VS'!AE106 -> 0 | I69: =SUM(G69:H69) -> 0 | J69: =I69/$I$25 -> 0
A70: 2 | B70: 1 | C70: 3 | D70: 2 | E70: 02 | F70: Gastos de representación en el exterior | G70: ='[3]CUENTA T FONDO 100'!AF126 -> 0 | H70: ='[3]CUENTA T VS'!AF106 -> 0 | I70: =SUM(G70:H70) -> 0 | J70: =I70/$I$25 -> 0
A71: 2 | B71: 1 | C71: 4 | F71: Gratificaciones y Bonificaciones | G71: =+G72+G74 -> 0 | H71: =+H72+H74 -> 0 | I71: =SUM(G71:H71) -> 0
A72: 2 | B72: 1 | C72: 4 | D72: 1 | F72: Bonificaciones | G72: =SUM(G73) -> 0 | H72: =SUM(H73) -> 0 | I72: =SUM(G72:H72) -> 0
A73: 2 | B73: 1 | C73: 4 | D73: 1 | E73: 01 | F73: Bonificaciones | G73: ='[3]CUENTA T FONDO 100'!AG126 -> 0 | H73: ='[3]CUENTA T VS'!AG106 -> 0 | I73: =SUM(G73:H73) -> 0 | J73: =I73/$I$25 -> 0
A74: 2 | B74: 1 | C74: 4 | D74: 2 | F74: Otras Gratificaciones y Bonificaciones | G74: =SUM(G75:G77) -> 0 | H74: =SUM(H75:H77) -> 0 | I74: =SUM(G74:H74) -> 0
A75: 2 | B75: 1 | C75: 4 | D75: 2 | E75: 01 | F75: Bono escolar | G75: ='[3]CUENTA T FONDO 100'!AH126 -> 0 | H75: ='[3]CUENTA T VS'!AH106 -> 0 | I75: =SUM(G75:H75) -> 0 | J75: =I75/$I$25 -> 0
A76: 2 | B76: 1 | C76: 4 | D76: 2 | E76: 02 | F76: Gratificaciones por pasantías | G76: ='[3]CUENTA T FONDO 100'!AI126 -> 0 | H76: ='[3]CUENTA T VS'!AI106 -> 0 | I76: =SUM(G76:H76) -> 0 | J76: =I76/$I$25 -> 0
A77: 2 | B77: 1 | C77: 4 | D77: 2 | E77: 03 | F77: Gratificaciones por aniversario de institución | G77: ='[3]CUENTA T FONDO 100'!AJ126 -> 0 | H77: ='[3]CUENTA T VS'!AJ106 -> 0 | I77: =SUM(G77:H77) -> 0 | J77: =I77/$I$25 -> 0
A78: 2 | B78: 1 | C78: 5 | F78: Contribuciones a la Seguridad Social y Riesgo Laboral | G78: =+G79+G81+G83+G85 -> 8371846.2 | H78: =+H79+H81+H83+H85 -> 0 | I78: =SUM(G78:H78) -> 8371846.2
A79: 2 | B79: 1 | C79: 5 | D79: 1 | F79: Contribuciones al seguro de salud | G79: =SUM(G80) -> 3857418.9 | H79: =SUM(H80) -> 0 | I79: =SUM(G79:H79) -> 3857418.9
A80: 2 | B80: 1 | C80: 5 | D80: 1 | E80: 01 | F80: Contribuciones al seguro de salud | G80: ='[3]CUENTA T FONDO 100'!AK126 -> 3857418.9 | H80: ='[3]CUENTA T VS'!AK106 -> 0 | I80: =SUM(G80:H80) -> 3857418.9 | J80: =I80/$I$25 -> 0.038403721
A81: 2 | B81: 1 | C81: 5 | D81: 2 | F81: Contribuciones al seguro de pensiones | G81: =SUM(G82) -> 3862857.7 | H81: =SUM(H82) -> 0 | I81: =SUM(G81:H81) -> 3862857.7
A82: 2 | B82: 1 | C82: 5 | D82: 2 | E82: 01 | F82: Contribuciones al seguro de pensiones | G82: ='[3]CUENTA T FONDO 100'!AL126 -> 3862857.7 | H82: ='[3]CUENTA T VS'!AL106 -> 0 | I82: =SUM(G82:H82) -> 3862857.7 | J82: =I82/$I$25 -> 0.038457868
A83: 2 | B83: 1 | C83: 5 | D83: 3 | F83: Contribuciones al seguro de riesgo laboral | G83: =SUM(G84) -> 651569.52 | H83: =SUM(H84) -> 0 | I83: =SUM(G83:H83) -> 651569.52
A84: 2 | B84: 1 | C84: 5 | D84: 3 | E84: 01 | F84: Contribuciones al seguro de riesgo laboral | G84: ='[3]CUENTA T FONDO 100'!AM126 -> 651569.52 | H84: ='[3]CUENTA T VS'!AM106 -> 0 | I84: =SUM(G84:H84) -> 651569.52 | J84: =I84/$I$25 -> 0.0064869007
A85: 2 | B85: 1 | C85: 5 | D85: 4 | F85: Contribuciones al plan de retiro complementario | G85: =SUM(G86) -> 0 | H85: =SUM(H86) -> 0 | I85: =SUM(G85:H85) -> 0
A86: 2 | B86: 1 | C86: 5 | D86: 4 | E86: 01 | F86: Contribuciones al plan de retiro complementario | G86: ='[3]CUENTA T FONDO 100'!AN126 -> 0 | H86: ='[3]CUENTA T VS'!AN106 -> 0 | I86: =SUM(G86:H86) -> 0 | J86: =I86/$I$25 -> 0
A87: 2 | B87: 2 | F87: Servicios No Personales | G87: =G88+G106+G111+G116+G125+G148+G157+G179+G208 -> 8240458.4 | H87: =H88+H106+H111+H116+H125+H148+H157+H179+H208 -> 3938639.1 | I87: =SUM(G87:H87) -> 12179097 | J87: =I87/$I$25 -> 0.12125275
A88: 2 | B88: 2 | C88: 1 | F88: Servicios Básicos | G88: =+G89+G91+G93+G95+G97+G99+G102+G104 -> 60535 | H88: =+H89+H91+H93+H95+H97+H99+H102+H104 -> 964509 | I88: =SUM(G88:H88) -> 1025044
A89: 2 | B89: 2 | C89: 1 | D89: 1 | F89: Radiocomunicación | G89: =SUM(G90) -> 0 | H89: =SUM(H90) -> 0 | I89: =SUM(G89:H89) -> 0
A90: 2 | B90: 2 | C90: 1 | D90: 1 | E90: 01 | F90: Radiocomunicación | G90: ='[3]CUENTA T FONDO 100'!AO126 -> 0 | H90: ='[3]CUENTA T VS'!AO106 -> 0 | I90: =SUM(G90:H90) -> 0 | J90: =I90/$I$25 -> 0
A91: 2 | B91: 2 | C91: 1 | D91: 2 | F91: Servicios telefónico de larga distancia | G91: =SUM(G92) -> 0 | H91: =SUM(H92) -> 0 | I91: =SUM(G91:H91) -> 0
A92: 2 | B92: 2 | C92: 1 | D92: 2 | E92: 01 | F92: Servicios telefónico de larga distancia | G92: ='[3]CUENTA T FONDO 100'!AP126 -> 0 | H92: ='[3]CUENTA T VS'!AP106 -> 0 | I92: =SUM(G92:H92) -> 0 | J92: =I92/$I$25 -> 0
A93: 2 | B93: 2 | C93: 1 | D93: 3 | F93: Teléfono local | G93: =SUM(G94) -> 0 | H93: =SUM(H94) -> 204509 | I93: =SUM(G93:H93) -> 204509
A94: 2 | B94: 2 | C94: 1 | D94: 3 | E94: 01 | F94: Teléfono local | G94: ='[3]CUENTA T FONDO 100'!AQ126 -> 0 | H94: ='[3]CUENTA T VS'!AQ106 -> 204509 | I94: =SUM(G94:H94) -> 204509 | J94: =I94/$I$25 -> 0.0020360522
A95: 2 | B95: 2 | C95: 1 | D95: 4 | F95: Telefax y correos | G95: =SUM(G96) -> 0 | H95: =SUM(H96) -> 0 | I95: =SUM(G95:H95) -> 0
A96: 2 | B96: 2 | C96: 1 | D96: 4 | E96: 01 | F96: Telefax y correos | G96: ='[3]CUENTA T FONDO 100'!AR126 -> 0 | H96: ='[3]CUENTA T VS'!AR106 -> 0 | I96: =SUM(G96:H96) -> 0 | J96: =I96/$I$25 -> 0
A97: 2 | B97: 2 | C97: 1 | D97: 5 | F97: Servicio de Internet y televisión por cable | G97: =SUM(G98) -> 0 | H97: =SUM(H98) -> 0 | I97: =SUM(G97:H97) -> 0
A98: 2 | B98: 2 | C98: 1 | D98: 5 | E98: 01 | F98: Servicio de Internet y televisión por cable | G98: ='[3]CUENTA T FONDO 100'!AS126 -> 0 | H98: ='[3]CUENTA T VS'!AS106 -> 0 | I98: =SUM(G98:H98) -> 0 | J98: =I98/$I$25 -> 0
A99: 2 | B99: 2 | C99: 1 | D99: 6 | F99: Electricidad | G99: =SUM(G100:G101) -> 0 | H99: =SUM(H100:H101) -> 0 | I99: =SUM(G99:H99) -> 0
A100: 2 | B100: 2 | C100: 1 | D100: 6 | E100: 01 | F100: Energía eléctrica | G100: ='[3]CUENTA T FONDO 100'!AT126 -> 0 | H100: ='[3]CUENTA T VS'!AT106 -> 0 | I100: =SUM(G100:H100) -> 0 | J100: =I100/$I$25 -> 0
A101: 2 | B101: 2 | C101: 1 | D101: 6 | E101: 02 | F101: Electricidad no cortable | G101: ='[3]CUENTA T FONDO 100'!AU126 -> 0 | H101: ='[3]CUENTA T VS'!AU106 -> 0 | I101: =SUM(G101:H101) -> 0 | J101: =I101/$I$25 -> 0
A102: 2 | B102: 2 | C102: 1 | D102: 7 | F102: Agua | G102: =SUM(G103) -> 60535 | H102: =SUM(H103) -> 0 | I102: =SUM(G102:H102) -> 60535
A103: 2 | B103: 2 | C103: 1 | D103: 7 | E103: 01 | F103: Agua | G103: ='[3]CUENTA T FONDO 100'!AV126 -> 60535 | H103: ='[3]CUENTA T VS'!AV106 -> 0 | I103: =SUM(G103:H103) -> 60535 | J103: =I103/$I$25 -> 0.00060267481
A104: 2 | B104: 2 | C104: 1 | D104: 8 | F104: Recolección de residuos sólidos | G104: =SUM(G105) -> 0 | H104: =SUM(H105) -> 760000 | I104: =SUM(G104:H104) -> 760000
A105: 2 | B105: 2 | C105: 1 | D105: 8 | E105: 01 | F105: Recolección de residuos sólidos | G105: ='[3]CUENTA T FONDO 100'!AW126 -> 0 | H105: ='[3]CUENTA T VS'!AW106 -> 760000 | I105: =SUM(G105:H105) -> 760000 | J105: =I105/$I$25 -> 0.0075664137
...

Sheet abril-junio 2025
A1: Form. No.6 SRS
A3: Servicio Nacional de Salud
A4: Dirección de Fizcalización
A5: Consolidado de Ingresos y Gastos por Fuente de Financiamiento
A6: HOSPITAL MATERNO INFANTIL SAN LORENZO DE LOS MINA
A7: EJECUCION DE INGRESOS E INGRESOS ABRIL- JUNIO 2025 3.1.1.2.05
C8: Ingresos Generales:
E9: 1.- Balance Inicial / Fuente:
E10: Anticipo Financiero | H10: Otros Aportes
E11: Transferencias Corrientes
E12: Venta de Servicios | G12: 0
E13: 2.- Ingresos por Fuente / Cuenta
E14: Anticipo Financiero | G14: 0 | H14: Otros Aportes | I14: =+'ABRIL '!I14+'mayo 2025'!I14+'junioo '!I14 -> 1815218.7
E15: Transferencias Corrientes | G15: =+'ABRIL '!G15+'mayo 2025'!G15+'junioo '!G15 -> 3.0141289e+08 | H15: Aportes Nomina SNS | I15: 0
E16: Venta de Servicios | G16: =+'ABRIL '!G16+'mayo 2025'!G16+'junioo '!G16 -> 18042285
H17: TOTAL INGRESOS RDS | I17: =+G10+G11+G12+I10+G14+G15+G16+I14+I15 -> 3.212704e+08
A21: 1 | F21: 2 | G21: 3 | I21: 4 | J21: 5
A22: Código Presupuestario | F22: Descripción Gasto por Cuenta | G22: Distribución del Gasto por Fuente de Financiamiento | I22: TOTAL | J22: %
A23: Tipo | B23: Objeto | C23: Cuenta | D23: Sub-Cuenta | E23: Auxiliar | G23: Fondo 100 | H23: Venta de Servicios/ Otros Aportes
A25: 2 | F25: Gastos | G25: =+'ABRIL '!G25+'mayo 2025'!G25+'junioo '!G25 -> 2.7723165e+08 | H25: =+'ABRIL '!H25+'mayo 2025'!H25+'junioo '!H25 -> 20404007 | I25: =SUM(G25:H25) -> 2.9763565e+08 | J25: =+J26+J87+J212+J330+J336+J463 -> 1
A26: 2 | B26: 1 | F26: Servicios Personales | G26: =+'ABRIL '!G26+'mayo 2025'!G26+'junioo '!G26 -> 1.9977032e+08 | H26: =+'ABRIL '!H26+'mayo 2025'!H26+'junioo '!H26 -> 0 | I26: =SUM(G26:H26) -> 1.9977032e+08 | J26: =I26/$I$25 -> 0.67119083
A27: 2 | B27: 1 | C27: 1 | F27: Remuneraciones | G27: =+'ABRIL '!G27+'mayo 2025'!G27+'junioo '!G27 -> 1.6408478e+08 | H27: =+'ABRIL '!H27+'mayo 2025'!H27+'junioo '!H27 -> 0 | I27: =SUM(G27:H27) -> 1.6408478e+08 | J27: =I27/$I$25 -> 0.5512941
A28: 2 | B28: 1 | C28: 1 | D28: 1 | F28: Remuneraciones al personal fijo | G28: =+'ABRIL '!G28+'mayo 2025'!G28+'junioo '!G28 -> 1.6007297e+08 | H28: =+'ABRIL '!H28+'mayo 2025'!H28+'junioo '!H28 -> 0 | I28: =SUM(G28:H28) -> 1.6007297e+08 | J28: =I28/$I$25 -> 0.53781519
A29: 2 | B29: 1 | C29: 1 | D29: 1 | E29: 01 | F29: Sueldos a empleados fijos | G29: =+'ABRIL '!G29+'mayo 2025'!G29+'junioo '!G29 -> 1.6007297e+08 | H29: =+'ABRIL '!H29+'mayo 2025'!H29+'junioo '!H29 -> 0 | I29: =SUM(G29:H29) -> 1.6007297e+08 | J29: =I29/$I$25 -> 0.53781519
A30: 2 | B30: 1 | C30: 1 | D30: 1 | E30: 02 | F30: Sueldos a médicos | G30: =+'ABRIL '!G30+'mayo 2025'!G30+'junioo '!G30 -> 0 | H30: =+'ABRIL '!H30+'mayo 2025'!H30+'junioo '!H30 -> 0 | I30: =SUM(G30:H30) -> 0 | J30: =I30/$I$25 -> 0
A31: 2 | B31: 1 | C31: 1 | D31: 1 | E31: 03 | F31: Ascensos a militares | G31: =+'ABRIL '!G31+'mayo 2025'!G31+'junioo '!G31 -> 0 | H31: =+'ABRIL '!H31+'mayo 2025'!H31+'junioo '!H31 -> 0 | I31: =SUM(G31:H31) -> 0 | J31: =I31/$I$25 -> 0
A32: 2 | B32: 1 | C32: 1 | D32: 1 | E32: 04 | F32: Nuevas plazas maestros | G32: =+'ABRIL '!G32+'mayo 2025'!G32+'junioo '!G32 -> 0 | H32: =+'ABRIL '!H32+'mayo 2025'!H32+'junioo '!H32 -> 0 | I32: =SUM(G32:H32) -> 0 | J32: =I32/$I$25 -> 0
A33: 2 | B33: 1 | C33: 1 | D33: 1 | E33: 05 | F33: Incentivos y escalafón | G33: =+'ABRIL '!G33+'mayo 2025'!G33+'junioo '!G33 -> 0 | H33: =+'ABRIL '!H33+'mayo 2025'!H33+'junioo '!H33 -> 0 | I33: =SUM(G33:H33) -> 0 | J33: =I33/$I$25 -> 0
A34: 2 | B34: 1 | C34: 1 | D34: 1 | E34: 06 | F34: Nuevas plazas a médicos | G34: =+'ABRIL '!G34+'mayo 2025'!G34+'junioo '!G34 -> 0 | H34: =+'ABRIL '!H34+'mayo 2025'!H34+'junioo '!H34 -> 0 | I34: =SUM(G34:H34) -> 0 | J34: =I34/$I$25 -> 0
A35: 2 | B35: 1 | C35: 1 | D35: 2 | F35: Remuneraciones al personal con carácter transitorio | G35: =+'ABRIL '!G35+'mayo 2025'!G35+'junioo '!G35 -> 3368593.1 | H35: =+'ABRIL '!H35+'mayo 2025'!H35+'junioo '!H35 -> 0 | I35: =SUM(G35:H35) -> 3368593.1
A36: 2 | B36: 1 | C36: 1 | D36: 2 | E36: 03 | F36: Suplencias | G36: =+'ABRIL '!G36+'mayo 2025'!G36+'junioo '!G36 -> 0 | H36: =+'ABRIL '!H36+'mayo 2025'!H36+'junioo '!H36 -> 0 | I36: =SUM(G36:H36) -> 0 | J36: =I36/$I$25 -> 0
A37: 2 | B37: 1 | C37: 1 | D37: 2 | E37: 05 | F37: Sueldo al personal nominal en período probatorio | G37: =+'ABRIL '!G37+'mayo 2025'!G37+'junioo '!G37 -> 0 | H37: =+'ABRIL '!H37+'mayo 2025'!H37+'junioo '!H37 -> 0 | I37: =SUM(G37:H37) -> 0 | J37: =I37/$I$25 -> 0
A38: 2 | B38: 1 | C38: 1 | D38: 2 | E38: 06 | F38: Jornales | G38: =+'ABRIL '!G38+'mayo 2025'!G38+'junioo '!G38 -> 0 | H38: =+'ABRIL '!H38+'mayo 2025'!H38+'junioo '!H38 -> 0 | I38: =SUM(G38:H38) -> 0 | J38: =I38/$I$25 -> 0
A39: 2 | B39: 1 | C39: 1 | D39: 2 | E39: 08 | F39: Empleados temporales | G39: =+'ABRIL '!G39+'mayo 2025'!G39+'junioo '!G39 -> 3368593.1 | H39: =+'ABRIL '!H39+'mayo 2025'!H39+'junioo '!H39 -> 0 | I39: =SUM(G39:H39) -> 3368593.1 | J39: =I39/$I$25 -> 0.011317841
A40: 2 | B40: 1 | C40: 1 | D40: 2 | E40: 09 | F40: Personal de carácter eventual | G40: =+'ABRIL '!G40+'mayo 2025'!G40+'junioo '!G40 -> 0 | H40: =+'ABRIL '!H40+'mayo 2025'!H40+'junioo '!H40 -> 0 | I40: =SUM(G40:H40) -> 0 | J40: =I40/$I$25 -> 0
A41: 2 | B41: 1 | C41: 1 | D41: 2 | E41: 11 | F41: Interinato | G41: =+'ABRIL '!G41+'mayo 2025'!G41+'junioo '!G41 -> 0 | H41: =+'ABRIL '!H41+'mayo 2025'!H41+'junioo '!H41 -> 0 | I41: =SUM(G41:H41) -> 0 | J41: =I41/$I$25 -> 0
A42: 2 | B42: 1 | C42: 1 | D42: 3 | F42: Sueldos al personal fijo en trámite de pensiones | G42: =+'ABRIL '!G42+'mayo 2025'!G42+'junioo '!G42 -> 0 | H42: =+'ABRIL '!H42+'mayo 2025'!H42+'junioo '!H42 -> 0 | I42: =SUM(G42:H42) -> 0
A43: 2 | B43: 1 | C43: 1 | D43: 3 | E43: 01 | F43: Sueldos al personal fijo en trámite de pensiones | G43: =+'ABRIL '!G43+'mayo 2025'!G43+'junioo '!G43 -> 0 | H43: =+'ABRIL '!H43+'mayo 2025'!H43+'junioo '!H43 -> 0 | I43: =SUM(G43:H43) -> 0 | J43: =I43/$I$25 -> 0
A44: 2 | B44: 1 | C44: 1 | D44: 4 | F44: Sueldo anual no. 13 | G44: =+'ABRIL '!G44+'mayo 2025'!G44+'junioo '!G44 -> 0 | H44: =+'ABRIL '!H44+'mayo 2025'!H44+'junioo '!H44 -> 0 | I44: =SUM(G44:H44) -> 0
A45: 2 | B45: 1 | C45: 1 | D45: 4 | E45: 01 | F45: Sueldo anual no. 13 | G45: =+'ABRIL '!G45+'mayo 2025'!G45+'junioo '!G45 -> 0 | H45: =+'ABRIL '!H45+'mayo 2025'!H45+'junioo '!H45 -> 0 | I45: =SUM(G45:H45) -> 0 | J45: =I45/$I$25 -> 0
A46: 2 | B46: 1 | C46: 1 | D46: 5 | F46: Prestaciones económinas | G46: =+'ABRIL '!G46+'mayo 2025'!G46+'junioo '!G46 -> 643213.59 | H46: =+'ABRIL '!H46+'mayo 2025'!H46+'junioo '!H46 -> 0 | I46: =SUM(G46:H46) -> 643213.59
A47: 2 | B47: 1 | C47: 1 | D47: 5 | E47: 01 | F47: Prestaciones económinas | G47: =+'ABRIL '!G47+'mayo 2025'!G47+'junioo '!G47 -> 0 | H47: =+'ABRIL '!H47+'mayo 2025'!H47+'junioo '!H47 -> 0 | I47: =SUM(G47:H47) -> 0 | J47: =I47/$I$25 -> 0
A48: 2 | B48: 1 | C48: 1 | D48: 5 | E48: 02 | F48: Pago de porcentaje por desvinculación de cargo | G48: =+'ABRIL '!G48+'mayo 2025'!G48+'junioo '!G48 -> 0 | H48: =+'ABRIL '!H48+'mayo 2025'!H48+'junioo '!H48 -> 0 | I48: =SUM(G48:H48) -> 0 | J48: =I48/$I$25 -> 0
A49: 2 | B49: 1 | C49: 1 | D49: 5 | E49: 03 | F49: Prestación laboral por desvinculación | G49: =+'ABRIL '!G49+'mayo 2025'!G49+'junioo '!G49 -> 304133.33 | H49: =+'ABRIL '!H49+'mayo 2025'!H49+'junioo '!H49 -> 0 | I49: =SUM(G49:H49) -> 304133.33 | J49: =I49/$I$25 -> 0.001021831
A50: 2 | B50: 1 | C50: 1 | D50: 5 | E50: 04 | F50: Proporción de vacaciones no disfrutadas | G50: =+'ABRIL '!G50+'mayo 2025'!G50+'junioo '!G50 -> 339080.26 | H50: =+'ABRIL '!H50+'mayo 2025'!H50+'junioo '!H50 -> 0 | I50: =SUM(G50:H50) -> 339080.26 | J50: =I50/$I$25 -> 0.0011392461
A51: 2 | B51: 1 | C51: 2 | F51: Sobresueldos | G51: =+'ABRIL '!G51+'mayo 2025'!G51+'junioo '!G51 -> 10535799 | H51: =+'ABRIL '!H51+'mayo 2025'!H51+'junioo '!H51 -> 0 | I51: =SUM(G51:H51) -> 10535799
A52: 2 | B52: 1 | C52: 2 | D52: 1 | F52: Primas por antigüedad | G52: =+'ABRIL '!G52+'mayo 2025'!G52+'junioo '!G52 -> 8170209 | H52: =+'ABRIL '!H52+'mayo 2025'!H52+'junioo '!H52 -> 0 | I52: =SUM(G52:H52) -> 8170209
A53: 2 | B53: 1 | C53: 2 | D53: 1 | E53: 01 | F53: Primas por antigüedad | G53: =+'ABRIL '!G53+'mayo 2025'!G53+'junioo '!G53 -> 8170209 | H53: =+'ABRIL '!H53+'mayo 2025'!H53+'junioo '!H53 -> 0 | I53: =SUM(G53:H53) -> 8170209 | J53: =I53/$I$25 -> 0.027450371
A54: 2 | B54: 1 | C54: 2 | D54: 2 | F54: Compensación | G54: =+'ABRIL '!G54+'mayo 2025'!G54+'junioo '!G54 -> 2365590 | H54: =+'ABRIL '!H54+'mayo 2025'!H54+'junioo '!H54 -> 0 | I54: =SUM(G54:H54) -> 2365590
A55: 2 | B55: 1 | C55: 2 | D55: 2 | E55: 01 | F55: Compensación por gastos de alimentación | G55: =+'ABRIL '!G55+'mayo 2025'!G55+'junioo '!G55 -> 0 | H55: =+'ABRIL '!H55+'mayo 2025'!H55+'junioo '!H55 -> 0 | I55: =SUM(G55:H55) -> 0 | J55: =I55/$I$25 -> 0
A56: 2 | B56: 1 | C56: 2 | D56: 2 | E56: 03 | F56: Pago de horas extraordinarias | G56: =+'ABRIL '!G56+'mayo 2025'!G56+'junioo '!G56 -> 0 | H56: =+'ABRIL '!H56+'mayo 2025'!H56+'junioo '!H56 -> 0 | I56: =SUM(G56:H56) -> 0 | J56: =I56/$I$25 -> 0
A57: 2 | B57: 1 | C57: 2 | D57: 2 | E57: 04 | F57: Prima de transporte | G57: =+'ABRIL '!G57+'mayo 2025'!G57+'junioo '!G57 -> 0 | H57: =+'ABRIL '!H57+'mayo 2025'!H57+'junioo '!H57 -> 0 | I57: =SUM(G57:H57) -> 0 | J57: =I57/$I$25 -> 0
A58: 2 | B58: 1 | C58: 2 | D58: 2 | E58: 05 | F58: Compensación servicios de Seguridad | G58: =+'ABRIL '!G58+'mayo 2025'!G58+'junioo '!G58 -> 135000 | H58: =+'ABRIL '!H58+'mayo 2025'!H58+'junioo '!H58 -> 0 | I58: =SUM(G58:H58) -> 135000 | J58: =I58/$I$25 -> 0.00045357469
A59: 2 | B59: 1 | C59: 2 | D59: 2 | E59: 06 | F59: Incentivo por Rendimieto Individual | G59: =+'ABRIL '!G59+'mayo 2025'!G59+'junioo '!G59 -> 0 | H59: =+'ABRIL '!H59+'mayo 2025'!H59+'junioo '!H59 -> 0 | I59: =SUM(G59:H59) -> 0 | J59: =I59/$I$25 -> 0
A60: 2 | B60: 1 | C60: 2 | D60: 2 | E60: 07 | F60: Compensación por distancia | G60: =+'ABRIL '!G60+'mayo 2025'!G60+'junioo '!G60 -> 0 | H60: =+'ABRIL '!H60+'mayo 2025'!H60+'junioo '!H60 -> 0 | I60: =SUM(G60:H60) -> 0 | J60: =I60/$I$25 -> 0
A61: 2 | B61: 1 | C61: 2 | D61: 2 | E61: 08 | F61: Compensaciones especiales | G61: =+'ABRIL '!G61+'mayo 2025'!G61+'junioo '!G61 -> 1005000 | H61: =+'ABRIL '!H61+'mayo 2025'!H61+'junioo '!H61 -> 0 | I61: =SUM(G61:H61) -> 1005000 | J61: =I61/$I$25 -> 0.0033766116
A62: 2 | B62: 1 | C62: 2 | D62: 2 | E62: 09 | F62: Bono por desempeño a servidores de carrera | G62: =+'ABRIL '!G62+'mayo 2025'!G62+'junioo '!G62 -> 443970.11 | H62: =+'ABRIL '!H62+'mayo 2025'!H62+'junioo '!H62 -> 0 | I62: =SUM(G62:H62) -> 443970.11 | J62: =I62/$I$25 -> 0.0014916563
A63: 2 | B63: 1 | C63: 2 | D63: 2 | E63: 10 | F63: Compensacion por cumplimiento de indicadores | G63: =+'ABRIL '!G63+'mayo 2025'!G63+'junioo '!G63 -> 781619.88 | H63: =+'ABRIL '!H63+'mayo 2025'!H63+'junioo '!H63 -> 0 | I63: =SUM(G63:H63) -> 781619.88 | J63: =I63/$I$25 -> 0.0026260963
A64: 2 | B64: 1 | C64: 3 | F64: Dietas y Gastos de Representación | G64: =+'ABRIL '!G64+'mayo 2025'!G64+'junioo '!G64 -> 0 | H64: =+'ABRIL '!H64+'mayo 2025'!H64+'junioo '!H64 -> 0 | I64: =SUM(G64:H64) -> 0
A65: 2 | B65: 1 | C65: 3 | D65: 1 | F65: Dietas | G65: =+'ABRIL '!G65+'mayo 2025'!G65+'junioo '!G65 -> 0 | H65: =+'ABRIL '!H65+'mayo 2025'!H65+'junioo '!H65 -> 0 | I65: =SUM(G65:H65) -> 0
A66: 2 | B66: 1 | C66: 3 | D66: 1 | E66: 01 | F66: Dietas en el país | G66: =+'ABRIL '!G66+'mayo 2025'!G66+'junioo '!G66 -> 0 | H66: =+'ABRIL '!H66+'mayo 2025'!H66+'junioo '!H66 -> 0 | I66: =SUM(G66:H66) -> 0 | J66: =I66/$I$25 -> 0
A67: 2 | B67: 1 | C67: 3 | D67: 1 | E67: 02 | F67: Dietas en el exterior | G67: =+'ABRIL '!G67+'mayo 2025'!G67+'junioo '!G67 -> 0 | H67: =+'ABRIL '!H67+'mayo 2025'!H67+'junioo '!H67 -> 0 | I67: =SUM(G67:H67) -> 0 | J67: =I67/$I$25 -> 0
A68: 2 | B68: 1 | C68: 3 | D68: 2 | F68: Gastos de representación | G68: =+'ABRIL '!G68+'mayo 2025'!G68+'junioo '!G68 -> 0 | H68: =+'ABRIL '!H68+'mayo 2025'!H68+'junioo '!H68 -> 0 | I68: =SUM(G68:H68) -> 0
A69: 2 | B69: 1 | C69: 3 | D69: 2 | E69: 01 | F69: Gastos de representación en el país | G69: =+'ABRIL '!G69+'mayo 2025'!G69+'junioo '!G69 -> 0 | H69: =+'ABRIL '!H69+'mayo 2025'!H69+'junioo '!H69 -> 0 | I69: =SUM(G69:H69) -> 0 | J69: =I69/$I$25 -> 0
A70: 2 | B70: 1 | C70: 3 | D70: 2 | E70: 02 | F70: Gastos de representación en el exterior | G70: =+'ABRIL '!G70+'mayo 2025'!G70+'junioo '!G70 -> 0 | H70: =+'ABRIL '!H70+'mayo 2025'!H70+'junioo '!H70 -> 0 | I70: =SUM(G70:H70) -> 0 | J70: =I70/$I$25 -> 0
A71: 2 | B71: 1 | C71: 4 | F71: Gratificaciones y Bonificaciones | G71: =+'ABRIL '!G71+'mayo 2025'!G71+'junioo '!G71 -> 0 | H71: =+'ABRIL '!H71+'mayo 2025'!H71+'junioo '!H71 -> 0 | I71: =SUM(G71:H71) -> 0
A72: 2 | B72: 1 | C72: 4 | D72: 1 | F72: Bonificaciones | G72: =+'ABRIL '!G72+'mayo 2025'!G72+'junioo '!G72 -> 0 | H72: =+'ABRIL '!H72+'mayo 2025'!H72+'junioo '!H72 -> 0 | I72: =SUM(G72:H72) -> 0
A73: 2 | B73: 1 | C73: 4 | D73: 1 | E73: 01 | F73: Bonificaciones | G73: =+'ABRIL '!G73+'mayo 2025'!G73+'junioo '!G73 -> 0 | H73: =+'ABRIL '!H73+'mayo 2025'!H73+'junioo '!H73 -> 0 | I73: =SUM(G73:H73) -> 0 | J73: =I73/$I$25 -> 0
A74: 2 | B74: 1 | C74: 4 | D74: 2 | F74: Otras Gratificaciones y Bonificaciones | G74: =+'ABRIL '!G74+'mayo 2025'!G74+'junioo '!G74 -> 0 | H74: =+'ABRIL '!H74+'mayo 2025'!H74+'junioo '!H74 -> 0 | I74: =SUM(G74:H74) -> 0
A75: 2 | B75: 1 | C75: 4 | D75: 2 | E75: 01 | F75: Bono escolar | G75: =+'ABRIL '!G75+'mayo 2025'!G75+'junioo '!G75 -> 0 | H75: =+'ABRIL '!H75+'mayo 2025'!H75+'junioo '!H75 -> 0 | I75: =SUM(G75:H75) -> 0 | J75: =I75/$I$25 -> 0
A76: 2 | B76: 1 | C76: 4 | D76: 2 | E76: 02 | F76: Gratificaciones por pasantías | G76: =+'ABRIL '!G76+'mayo 2025'!G76+'junioo '!G76 -> 0 | H76: =+'ABRIL '!H76+'mayo 2025'!H76+'junioo '!H76 -> 0 | I76: =SUM(G76:H76) -> 0 | J76: =I76/$I$25 -> 0
A77: 2 | B77: 1 | C77: 4 | D77: 2 | E77: 03 | F77: Gratificaciones por aniversario de institución | G77: =+'ABRIL '!G77+'mayo 2025'!G77+'junioo '!G77 -> 0 | H77: =+'ABRIL '!H77+'mayo 2025'!H77+'junioo '!H77 -> 0 | I77: =SUM(G77:H77) -> 0 | J77: =I77/$I$25 -> 0
A78: 2 | B78: 1 | C78: 5 | F78: Contribuciones a la Seguridad Social y Riesgo Laboral | G78: =+'ABRIL '!G78+'mayo 2025'!G78+'junioo '!G78 -> 25149742 | H78: =+'ABRIL '!H78+'mayo 2025'!H78+'junioo '!H78 -> 0 | I78: =SUM(G78:H78) -> 25149742
A79: 2 | B79: 1 | C79: 5 | D79: 1 | F79: Contribuciones al seguro de salud | G79: =+'ABRIL '!G79+'mayo 2025'!G79+'junioo '!G79 -> 11588014 | H79: =+'ABRIL '!H79+'mayo 2025'!H79+'junioo '!H79 -> 0 | I79: =SUM(G79:H79) -> 11588014
A80: 2 | B80: 1 | C80: 5 | D80: 1 | E80: 01 | F80: Contribuciones al seguro de salud | G80: =+'ABRIL '!G80+'mayo 2025'!G80+'junioo '!G80 -> 11588014 | H80: =+'ABRIL '!H80+'mayo 2025'!H80+'junioo '!H80 -> 0 | I80: =SUM(G80:H80) -> 11588014 | J80: =I80/$I$25 -> 0.038933555
A81: 2 | B81: 1 | C81: 5 | D81: 2 | F81: Contribuciones al seguro de pensiones | G81: =+'ABRIL '!G81+'mayo 2025'!G81+'junioo '!G81 -> 11604353 | H81: =+'ABRIL '!H81+'mayo 2025'!H81+'junioo '!H81 -> 0 | I81: =SUM(G81:H81) -> 11604353
A82: 2 | B82: 1 | C82: 5 | D82: 2 | E82: 01 | F82: Contribuciones al seguro de pensiones | G82: =+'ABRIL '!G82+'mayo 2025'!G82+'junioo '!G82 -> 11604353 | H82: =+'ABRIL '!H82+'mayo 2025'!H82+'junioo '!H82 -> 0 | I82: =SUM(G82:H82) -> 11604353 | J82: =I82/$I$25 -> 0.038988449
A83: 2 | B83: 1 | C83: 5 | D83: 3 | F83: Contribuciones al seguro de riesgo laboral | G83: =+'ABRIL '!G83+'mayo 2025'!G83+'junioo '!G83 -> 1957375.5 | H83: =+'ABRIL '!H83+'mayo 2025'!H83+'junioo '!H83 -> 0 | I83: =SUM(G83:H83) -> 1957375.5
A84: 2 | B84: 1 | C84: 5 | D84: 3 | E84: 01 | F84: Contribuciones al seguro de riesgo laboral | G84: =+'ABRIL '!G84+'mayo 2025'!G84+'junioo '!G84 -> 1957375.5 | H84: =+'ABRIL '!H84+'mayo 2025'!H84+'junioo '!H84 -> 0 | I84: =SUM(G84:H84) -> 1957375.5 | J84: =I84/$I$25 -> 0.0065764148
A85: 2 | B85: 1 | C85: 5 | D85: 4 | F85: Contribuciones al plan de retiro complementario | G85: =+'ABRIL '!G85+'mayo 2025'!G85+'junioo '!G85 -> 0 | H85: =+'ABRIL '!H85+'mayo 2025'!H85+'junioo '!H85 -> 0 | I85: =SUM(G85:H85) -> 0
A86: 2 | B86: 1 | C86: 5 | D86: 4 | E86: 01 | F86: Contribuciones al plan de retiro complementario | G86: =+'ABRIL '!G86+'mayo 2025'!G86+'junioo '!G86 -> 0 | H86: =+'ABRIL '!H86+'mayo 2025'!H86+'junioo '!H86 -> 0 | I86: =SUM(G86:H86) -> 0 | J86: =I86/$I$25 -> 0
A87: 2 | B87: 2 | F87: Servicios No Personales | G87: =+'ABRIL '!G87+'mayo 2025'!G87+'junioo '!G87 -> 10131818 | H87: =+'ABRIL '!H87+'mayo 2025'!H87+'junioo '!H87 -> 7239413.8 | I87: =SUM(G87:H87) -> 17371232 | J87: =I87/$I$25 -> 0.058364083
A88: 2 | B88: 2 | C88: 1 | F88: Servicios Básicos | G88: =+'ABRIL '!G88+'mayo 2025'!G88+'junioo '!G88 -> 181605 | H88: =+'ABRIL '!H88+'mayo 2025'!H88+'junioo '!H88 -> 2348580.7 | I88: =SUM(G88:H88) -> 2530185.7
A89: 2 | B89: 2 | C89: 1 | D89: 1 | F89: Radiocomunicación | G89: =+'ABRIL '!G89+'mayo 2025'!G89+'junioo '!G89 -> 0 | H89: =+'ABRIL '!H89+'mayo 2025'!H89+'junioo '!H89 -> 0 | I89: =SUM(G89:H89) -> 0
A90: 2 | B90: 2 | C90: 1 | D90: 1 | E90: 01 | F90: Radiocomunicación | G90: =+'ABRIL '!G90+'mayo 2025'!G90+'junioo '!G90 -> 0 | H90: =+'ABRIL '!H90+'mayo 2025'!H90+'junioo '!H90 -> 0 | I90: =SUM(G90:H90) -> 0 | J90: =I90/$I$25 -> 0
A91: 2 | B91: 2 | C91: 1 | D91: 2 | F91: Servicios telefónico de larga distancia | G91: =+'ABRIL '!G91+'mayo 2025'!G91+'junioo '!G91 -> 0 | H91: =+'ABRIL '!H91+'mayo 2025'!H91+'junioo '!H91 -> 0 | I91: =SUM(G91:H91) -> 0
A92: 2 | B92: 2 | C92: 1 | D92: 2 | E92: 01 | F92: Servicios telefónico de larga distancia | G92: =+'ABRIL '!G92+'mayo 2025'!G92+'junioo '!G92 -> 0 | H92: =+'ABRIL '!H92+'mayo 2025'!H92+'junioo '!H92 -> 0 | I92: =SUM(G92:H92) -> 0 | J92: =I92/$I$25 -> 0
A93: 2 | B93: 2 | C93: 1 | D93: 3 | F93: Teléfono local | G93: =+'ABRIL '!G93+'mayo 2025'!G93+'junioo '!G93 -> 0 | H93: =+'ABRIL '!H93+'mayo 2025'!H93+'junioo '!H93 -> 518114.83 | I93: =SUM(G93:H93) -> 518114.83
A94: 2 | B94: 2 | C94: 1 | D94: 3 | E94: 01 | F94: Teléfono local | G94: =+'ABRIL '!G94+'mayo 2025'!G94+'junioo '!G94 -> 0 | H94: =+'ABRIL '!H94+'mayo 2025'!H94+'junioo '!H94 -> 518114.83 | I94: =SUM(G94:H94) -> 518114.83 | J94: =I94/$I$25 -> 0.0017407687
A95: 2 | B95: 2 | C95: 1 | D95: 4 | F95: Telefax y correos | G95: =+'ABRIL '!G95+'mayo 2025'!G95+'junioo '!G95 -> 0 | H95: =+'ABRIL '!H95+'mayo 2025'!H95+'junioo '!H95 -> 0 | I95: =SUM(G95:H95) -> 0
A96: 2 | B96: 2 | C96: 1 | D96: 4 | E96: 01 | F96: Telefax y correos | G96: =+'ABRIL '!G96+'mayo 2025'!G96+'junioo '!G96 -> 0 | H96: =+'ABRIL '!H96+'mayo 2025'!H96+'junioo '!H96 -> 0 | I96: =SUM(G96:H96) -> 0 | J96: =I96/$I$25 -> 0
A97: 2 | B97: 2 | C97: 1 | D97: 5 | F97: Servicio de Internet y televisión por cable | G97: =+'ABRIL '!G97+'mayo 2025'!G97+'junioo '!G97 -> 0 | H97: =+'ABRIL '!H97+'mayo 2025'!H97+'junioo '!H97 -> 210465.89 | I97: =SUM(G97:H97) -> 210465.89
A98: 2 | B98: 2 | C98: 1 | D98: 5 | E98: 01 | F98: Servicio de Internet y televisión por cable | G98: =+'ABRIL '!G98+'mayo 2025'!G98+'junioo '!G98 -> 0 | H98: =+'ABRIL '!H98+'mayo 2025'!H98+'junioo '!H98 -> 210465.89 | I98: =SUM(G98:H98) -> 210465.89 | J98: =I98/$I$25 -> 0.00070712594
A99: 2 | B99: 2 | C99: 1 | D99: 6 | F99: Electricidad | G99: =+'ABRIL '!G99+'mayo 2025'!G99+'junioo '!G99 -> 0 | H99: =+'ABRIL '!H99+'mayo 2025'!H99+'junioo '!H99 -> 0 | I99: =SUM(G99:H99) -> 0
A100: 2 | B100: 2 | C100: 1 | D100: 6 | E100: 01 | F100: Energía eléctrica | G100: =+'ABRIL '!G100+'mayo 2025'!G100+'junioo '!G100 -> 0 | H100: =+'ABRIL '!H100+'mayo 2025'!H100+'junioo '!H100 -> 0 | I100: =SUM(G100:H100) -> 0 | J100: =I100/$I$25 -> 0
A101: 2 | B101: 2 | C101: 1 | D101: 6 | E101: 02 | F101: Electricidad no cortable | G101: =+'ABRIL '!G101+'mayo 2025'!G101+'junioo '!G101 -> 0 | H101: =+'ABRIL '!H101+'mayo 2025'!H101+'junioo '!H101 -> 0 | I101: =SUM(G101:H101) -> 0 | J101: =I101/$I$25 -> 0
A102: 2 | B102: 2 | C102: 1 | D102: 7 | F102: Agua | G102: =+'ABRIL '!G102+'mayo 2025'!G102+'junioo '!G102 -> 181605 | H102: =+'ABRIL '!H102+'mayo 2025'!H102+'junioo '!H102 -> 0 | I102: =SUM(G102:H102) -> 181605
A103: 2 | B103: 2 | C103: 1 | D103: 7 | E103: 01 | F103: Agua | G103: =+'ABRIL '!G103+'mayo 2025'!G103+'junioo '!G103 -> 181605 | H103: =+'ABRIL '!H103+'mayo 2025'!H103+'junioo '!H103 -> 0 | I103: =SUM(G103:H103) -> 181605 | J103: =I103/$I$25 -> 0.00061015876
A104: 2 | B104: 2 | C104: 1 | D104: 8 | F104: Recolección de residuos sólidos | G104: =+'ABRIL '!G104+'mayo 2025'!G104+'junioo '!G104 -> 0 | H104: =+'ABRIL '!H104+'mayo 2025'!H104+'junioo '!H104 -> 1620000 | I104: =SUM(G104:H104) -> 1620000
A105: 2 | B105: 2 | C105: 1 | D105: 8 | E105: 01 | F105: Recolección de residuos sólidos | G105: =+'ABRIL '!G105+'mayo 2025'!G105+'junioo '!G105 -> 0 | H105: =+'ABRIL '!H105+'mayo 2025'!H105+'junioo '!H105 -> 1620000 | I105: =SUM(G105:H105) -> 1620000 | J105: =I105/$I$25 -> 0.0054428963
...
